{
  "type": "Feature",
  "properties": {
    "iso:country":"US",
    "sg:address":"510 S Main St",
    "sg:city":"Albia",
    "sg:classifiers":[
        {
            "category":"Building & Trades",
            "subcategory":"Cleaning & Sanitation",
            "type":"Services"
        }
    ],
    "sg:phone":"+1 641 932 7454",
    "sg:postcode":"52531",
    "sg:province":"IA",
    "sg:tags":[
        "maintenance"
    ],
    "wof:name":"Clean Shine Carwsh R W",
    "wof:placetype":"venue"
},
  "geometry": {"coordinates":[-92.80700400000001,41.02193],"type":"Point"}
}