{
  "type": "Feature",
  "properties": {
    "addr:full":"1419 Lincoln Ave Harlan IA 51537",
    "addr:housenumber":"1419",
    "addr:postcode":"51537",
    "addr:street":"Lincoln Ave",
    "iso:country":"US",
    "sg:address":"1419 Lincoln Ave",
    "sg:city":"Harlan",
    "sg:classifiers":[
        {
            "category":"Organizations",
            "subcategory":"Religious Organization",
            "type":"Services"
        }
    ],
    "sg:phone":"+1 712 755 2022",
    "sg:postcode":"51537",
    "sg:province":"IA",
    "sg:tags":[
        "church"
    ],
    "wof:name":"Seventh Day Adventist Church",
    "wof:placetype":"venue"
},
  "geometry": {"coordinates":[-95.330201,41.648336],"type":"Point"}
}