{
  "type": "Feature",
  "properties": {
    "iso:country":"US",
    "sg:address":"3000 Scott Ave",
    "sg:city":"Des Moines",
    "sg:classifiers":[
        {
            "category":"Wholesale",
            "subcategory":"Machinery & Supplies",
            "type":"Manufacturing & Wholesale Goods"
        }
    ],
    "sg:phone":"+1 515 265 6694",
    "sg:postcode":"50317",
    "sg:province":"IA",
    "sg:tags":[
        "truck"
    ],
    "wof:name":"Accurate Lift Truck Svc",
    "wof:placetype":"venue"
},
  "geometry": {"coordinates":[-93.55299599999999,41.58399],"type":"Point"}
}