{
  "type": "Feature",
  "properties": {
    "iso:country":"US",
    "sg:address":"1440 Field of Dreams Way",
    "sg:city":"Dyersville",
    "sg:classifiers":[
        {
            "category":"Professional",
            "type":"Services"
        }
    ],
    "sg:phone":"+1 563 875 2288",
    "sg:postcode":"52040",
    "sg:province":"IA",
    "sg:tags":[
        "establishment"
    ],
    "wof:name":"Tek Supply",
    "wof:placetype":"venue"
},
  "geometry": {"coordinates":[-91.055009,42.49772],"type":"Point"}
}