{
  "type": "Feature",
  "properties": {
    "iso:country":"US",
    "sg:address":"2460 10th St",
    "sg:city":"Coralville",
    "sg:classifiers":[
        {
            "category":"Building & Trades",
            "subcategory":"Construction",
            "type":"Services"
        }
    ],
    "sg:phone":"+1 319 354 4071",
    "sg:postcode":"52241",
    "sg:province":"IA",
    "sg:tags":[
        "painter"
    ],
    "wof:name":"J R Painting & Decorating Inc",
    "wof:placetype":"venue"
},
  "geometry": {"coordinates":[-91.599503,41.688185],"type":"Point"}
}