{
  "type": "Feature",
  "properties": {
    "iso:country":"US",
    "sg:address":"120 E Ramsey St",
    "sg:city":"Bancroft",
    "sg:classifiers":[
        {
            "category":"Professional",
            "subcategory":"Accounting & Tax Preparation",
            "type":"Services"
        }
    ],
    "sg:phone":"+1 515 885 2723",
    "sg:postcode":"50517",
    "sg:province":"IA",
    "sg:tags":[
        "accountant"
    ],
    "wof:name":"Jim Cage Co",
    "wof:placetype":"venue"
},
  "geometry": {"coordinates":[-94.216801,43.292918],"type":"Point"}
}