{
  "type": "Feature",
  "properties": {
    "iso:country":"US",
    "sg:address":"315 N Crawford St",
    "sg:city":"Carroll",
    "sg:classifiers":[
        {
            "category":"Retail",
            "subcategory":"Repair Shop",
            "type":"Services"
        }
    ],
    "sg:phone":"+1 712 792 4926",
    "sg:postcode":"51401",
    "sg:province":"IA",
    "sg:tags":[
        "machine",
        "sewing"
    ],
    "wof:name":"Carroll Sewing Ctr",
    "wof:placetype":"venue"
},
  "geometry": {"coordinates":[-94.87397799999999,42.065039],"type":"Point"}
}