{
  "type": "Feature",
  "properties": {
    "addr:full":"111 Commercial St Raymond IA 50667",
    "addr:housenumber":"111",
    "addr:postcode":"50667",
    "addr:street":"Commercial St",
    "iso:country":"US",
    "sg:address":"111 Commercial St",
    "sg:city":"Raymond",
    "sg:classifiers":[
        {
            "category":"Government",
            "subcategory":"Post Office",
            "type":"Public Place"
        }
    ],
    "sg:phone":"+1 319 232 6244",
    "sg:postcode":"50667",
    "sg:province":"IA",
    "wof:name":"US Post Office",
    "wof:placetype":"venue"
},
  "geometry": {"coordinates":[-92.219317,42.466297],"type":"Point"}
}