{
  "type": "Feature",
  "properties": {
    "iso:country":"US",
    "sg:address":"714 N Adams Ave",
    "sg:city":"Mason City",
    "sg:classifiers":[
        {
            "category":"Organizations",
            "subcategory":"Religious Organization",
            "type":"Services"
        }
    ],
    "sg:phone":"+1 641 423 7301",
    "sg:postcode":"50401",
    "sg:province":"IA",
    "sg:tags":[
        "church"
    ],
    "wof:name":"Holy Family Catholic Church",
    "wof:placetype":"venue"
},
  "geometry": {"coordinates":[-93.20432599999999,43.159854],"type":"Point"}
}