{
  "type": "Feature",
  "properties": {
    "addr:full":"1259 200th St Linden IA 50146",
    "addr:housenumber":"1259",
    "addr:postcode":"50146",
    "addr:street":"200Th St",
    "iso:country":"US",
    "sg:address":"1259 200th St",
    "sg:city":"Linden",
    "sg:classifiers":[
        {
            "category":"Real Estate",
            "subcategory":"Real Estate Operator",
            "type":"Services"
        }
    ],
    "sg:phone":"+1 515 428 8290",
    "sg:postcode":"50146",
    "sg:province":"IA",
    "sg:tags":[
        "property",
        "lessor"
    ],
    "wof:name":"Herring Farm The",
    "wof:placetype":"venue"
},
  "geometry": {"coordinates":[-94.25103300000001,41.746215],"type":"Point"}
}