{
  "type": "Feature",
  "properties": {
    "addr:full":"812 W 9th St Pella IA 50219",
    "addr:housenumber":"812",
    "addr:postcode":"50219",
    "addr:street":"W 9Th St",
    "iso:country":"US",
    "sg:address":"812 W 9th St",
    "sg:city":"Pella",
    "sg:classifiers":[
        {
            "category":"Retail",
            "subcategory":"Auto Repair",
            "type":"Services"
        }
    ],
    "sg:phone":"+1 641 628 1413",
    "sg:postcode":"50219",
    "sg:province":"IA",
    "sg:tags":[
        "body",
        "automobile",
        "painting"
    ],
    "wof:name":"Dow's Auto Body",
    "wof:placetype":"venue"
},
  "geometry": {"coordinates":[-92.935306,41.409236],"type":"Point"}
}