{
  "type": "Feature",
  "properties": {
    "addr:full":"915 SE 14th Ct Des Moines IA 50309",
    "addr:housenumber":"915",
    "addr:postcode":"50309",
    "addr:street":"Se 14Th Ct",
    "iso:country":"US",
    "sg:address":"915 SE 14th Ct",
    "sg:city":"Des Moines",
    "sg:classifiers":[
        {
            "category":"Retail",
            "subcategory":"Auto Repair",
            "type":"Services"
        }
    ],
    "sg:phone":"+1 515 244 6342",
    "sg:postcode":"50309",
    "sg:province":"IA",
    "sg:tags":[
        "repairing",
        "automobile"
    ],
    "wof:name":"CNC Automotive Specialties",
    "wof:placetype":"venue"
},
  "geometry": {"coordinates":[-93.59560999999999,41.581219],"type":"Point"}
}