{
  "type": "Feature",
  "properties": {
    "iso:country":"US",
    "sg:address":"212 Park Ave",
    "sg:city":"Story City",
    "sg:classifiers":[
        {
            "category":"Manufacturing",
            "subcategory":"Tools & Machinery",
            "type":"Manufacturing & Wholesale Goods"
        }
    ],
    "sg:phone":"+1 515 733 4523",
    "sg:postcode":"50248",
    "sg:province":"IA",
    "sg:tags":[
        "machine",
        "shop"
    ],
    "wof:name":"Custom Products",
    "wof:placetype":"venue"
},
  "geometry": {"coordinates":[-93.597713,42.182935],"type":"Point"}
}