{
  "type": "Feature",
  "properties": {
    "iso:country":"US",
    "sg:address":"1611 1st Ave N",
    "sg:city":"Fort Dodge",
    "sg:classifiers":[
        {
            "category":"Banks & Credit Unions",
            "subcategory":"Bank",
            "type":"Services"
        }
    ],
    "sg:phone":"+1 515 576 2121",
    "sg:postcode":"50501",
    "sg:province":"IA",
    "sg:tags":[
        "loan",
        "real estate"
    ],
    "wof:name":"Bradford Mortgage",
    "wof:placetype":"venue"
},
  "geometry": {"coordinates":[-94.175821,42.507236],"type":"Point"}
}