{
  "type": "Feature",
  "properties": {
    "addr:full":"206 3rd St Defiance IA 51527",
    "addr:housenumber":"206",
    "addr:postcode":"51527",
    "addr:street":"3Rd St",
    "iso:country":"US",
    "sg:address":"206 3rd St",
    "sg:city":"Defiance",
    "sg:classifiers":[
        {
            "category":"Building & Trades",
            "subcategory":"Plumbing",
            "type":"Services"
        }
    ],
    "sg:phone":"+1 712 748 3961",
    "sg:postcode":"51527",
    "sg:province":"IA",
    "sg:tags":[
        "septic"
    ],
    "wof:name":"John Kloewer Cesspool Svc",
    "wof:placetype":"venue"
},
  "geometry": {"coordinates":[-95.341482,41.823271],"type":"Point"}
}