{
  "type": "Feature",
  "properties": {
    "iso:country":"US",
    "sg:address":"1116 Old Lincoln Hwy",
    "sg:city":"Crescent",
    "sg:classifiers":[
        {
            "category":"Wholesale",
            "subcategory":"Plants",
            "type":"Manufacturing & Wholesale Goods"
        }
    ],
    "sg:phone":"+1 712 545 3265",
    "sg:postcode":"51526",
    "sg:province":"IA",
    "sg:tags":[
        "nursery",
        "tree"
    ],
    "wof:name":"Brewer's Crescent Nurseries",
    "wof:placetype":"venue"
},
  "geometry": {"coordinates":[-95.85840399999999,41.367641],"type":"Point"}
}