{
  "type": "Feature",
  "properties": {
    "iso:country":"US",
    "sg:address":"3327 Cheyenne Blvd",
    "sg:city":"Sioux City",
    "sg:classifiers":[
        {
            "category":"Wholesale",
            "subcategory":"Electrical",
            "type":"Manufacturing & Wholesale Goods"
        }
    ],
    "sg:phone":"+1 712 277 3632",
    "sg:postcode":"51104",
    "sg:province":"IA",
    "sg:tags":[
        "sound",
        "equipment",
        "system"
    ],
    "wof:name":"Moeller Electronics",
    "wof:placetype":"venue"
},
  "geometry": {"coordinates":[-96.39422,42.529629],"type":"Point"}
}