{
  "type": "Feature",
  "properties": {
    "iso:country":"US",
    "sg:address":"121 2nd St N",
    "sg:city":"Rockwell",
    "sg:classifiers":[
        {
            "category":"Organizations",
            "subcategory":"Religious Organization",
            "type":"Services"
        }
    ],
    "sg:phone":"+1 641 822 4919",
    "sg:postcode":"50469",
    "sg:province":"IA",
    "sg:tags":[
        "church"
    ],
    "wof:name":"First Baptist Church",
    "wof:placetype":"venue"
},
  "geometry": {"coordinates":[-93.19079600000001,42.986081],"type":"Point"}
}