{
  "type": "Feature",
  "properties": {
    "iso:country":"US",
    "sg:address":"4800 Mills Civic Pkwy",
    "sg:city":"West Des Moines",
    "sg:classifiers":[
        {
            "category":"Restaurant",
            "type":"Food & Drink"
        }
    ],
    "sg:menulink":"http://www.allmenus.com/ia/walnut/124498-quiznos-sub/menu/",
    "sg:phone":"+1 515 222 1213",
    "sg:postcode":"50265",
    "sg:province":"IA",
    "sg:tags":[
        "wrap",
        "american",
        "sandwich"
    ],
    "wof:name":"Quiznos Sub",
    "wof:placetype":"venue"
},
  "geometry": {"coordinates":[-93.76956,41.557971],"type":"Point"}
}