{
  "type": "Feature",
  "properties": {
    "addr:full":"217 Main St Ida Grove IA 51445",
    "addr:housenumber":"217",
    "addr:postcode":"51445",
    "addr:street":"Main St",
    "iso:country":"US",
    "sg:address":"217 Main St",
    "sg:city":"Ida Grove",
    "sg:classifiers":[
        {
            "category":"Real Estate",
            "subcategory":"Real Estate Services",
            "type":"Services"
        }
    ],
    "sg:phone":"+1 712 364 2287",
    "sg:postcode":"51445",
    "sg:province":"IA",
    "sg:website":"www.christierealestate.com",
    "wof:name":"Ida County Abstract Co",
    "wof:placetype":"venue"
},
  "geometry": {"coordinates":[-95.471216,42.344876],"type":"Point"}
}