{
  "type": "Feature",
  "properties": {
    "iso:country":"US",
    "sg:address":"5422 Blairs Forest Way NE",
    "sg:city":"Cedar Rapids",
    "sg:classifiers":[
        {
            "category":"Professional",
            "subcategory":"Accounting & Tax Preparation",
            "type":"Services"
        }
    ],
    "sg:phone":"+1 319 393 1300",
    "sg:postcode":"52402",
    "sg:province":"IA",
    "sg:tags":[
        "return",
        "filing"
    ],
    "wof:name":"Jackson Hewitt Tax Svc",
    "wof:placetype":"venue"
},
  "geometry": {"coordinates":[-91.681595,42.029966],"type":"Point"}
}