{
  "type": "Feature",
  "properties": {
    "iso:country":"US",
    "sg:address":"1205 330th St",
    "sg:city":"Forest City",
    "sg:phone":"+1 641 565 3220",
    "sg:postcode":"50436",
    "sg:province":"IA",
    "sg:tags":[
        "farm",
        "grain",
        "cash"
    ],
    "wof:name":"Roger Schimmelpfen Farm",
    "wof:placetype":"venue"
},
  "geometry": {"coordinates":[-93.74891700000001,43.241572],"type":"Point"}
}