{
  "type": "Feature",
  "properties": {
    "addr:full":"325 N Calhoun St West Liberty IA 52776",
    "addr:housenumber":"325",
    "addr:postcode":"52776",
    "addr:street":"N Calhoun St",
    "iso:country":"US",
    "sg:address":"325 N Calhoun St",
    "sg:city":"West Liberty",
    "sg:classifiers":[
        {
            "category":"Education",
            "subcategory":"Dance Studio",
            "type":"Public Place"
        }
    ],
    "sg:phone":"+1 319 627 2000",
    "sg:postcode":"52776",
    "sg:province":"IA",
    "sg:tags":[
        "instruction",
        "dancing"
    ],
    "wof:name":"Liberty Dance Center",
    "wof:placetype":"venue"
},
  "geometry": {"coordinates":[-91.263492,41.571053],"type":"Point"}
}