{
  "type": "Feature",
  "properties": {
    "addr:full":"1925 150th St Boone IA 50036",
    "addr:housenumber":"1925",
    "addr:postcode":"50036",
    "addr:street":"150Th St",
    "iso:country":"US",
    "sg:address":"1925 150th St",
    "sg:city":"Boone",
    "sg:classifiers":[
        {
            "category":"Real Estate",
            "subcategory":"Real Estate Agent",
            "type":"Services"
        }
    ],
    "sg:phone":"+1 515 432 8690",
    "sg:postcode":"50036",
    "sg:province":"IA",
    "wof:name":"Mac Rentals",
    "wof:placetype":"venue"
},
  "geometry": {"coordinates":[-93.790989,42.137584],"type":"Point"}
}