{
  "type": "Feature",
  "properties": {
    "iso:country":"US",
    "sg:address":"101 S 1st St",
    "sg:city":"Guthrie Center",
    "sg:classifiers":[
        {
            "category":"Home & Garden",
            "subcategory":"Garden Supply",
            "type":"Retail Goods"
        }
    ],
    "sg:phone":"+1 641 747 2266",
    "sg:postcode":"50115",
    "sg:province":"IA",
    "sg:tags":[
        "lawn",
        "mower"
    ],
    "wof:name":"Guthrie Automotive Inc",
    "wof:placetype":"venue"
},
  "geometry": {"coordinates":[-94.50684,41.677124],"type":"Point"}
}