{
  "type": "Feature",
  "properties": {
    "iso:country":"US",
    "sg:address":"1207 Park Dr",
    "sg:city":"Rock Rapids",
    "sg:classifiers":[
        {
            "category":"Retail",
            "subcategory":"Funeral Services",
            "type":"Services"
        }
    ],
    "sg:phone":"+1 712 472 2523",
    "sg:postcode":"51246",
    "sg:province":"IA",
    "sg:tags":[
        "director"
    ],
    "wof:name":"Roste Funeral Home",
    "wof:placetype":"venue"
},
  "geometry": {"coordinates":[-96.18112000000001,43.430457],"type":"Point"}
}