{
  "type": "Feature",
  "properties": {
    "iso:country":"US",
    "sg:address":"4020 State Hwy 136",
    "sg:city":"Clinton",
    "sg:classifiers":[
        {
            "category":"Retail",
            "subcategory":"Repair Shop",
            "type":"Services"
        }
    ],
    "sg:phone":"+1 563 682 7462",
    "sg:postcode":"52732",
    "sg:province":"IA",
    "sg:tags":[
        "welding"
    ],
    "wof:name":"Buech Welding",
    "wof:placetype":"venue"
},
  "geometry": {"coordinates":[-90.309352,41.927935],"type":"Point"}
}