{
  "type": "Feature",
  "properties": {
    "iso:country":"US",
    "sg:address":"701 Read St",
    "sg:city":"Wesley",
    "sg:classifiers":[
        {
            "category":"Government",
            "subcategory":"Office",
            "type":"Public Place"
        }
    ],
    "sg:phone":"+1 515 679 4173",
    "sg:postcode":"50483",
    "sg:province":"IA",
    "wof:name":"Wesley Kossuth County Shop",
    "wof:placetype":"venue"
},
  "geometry": {"coordinates":[-93.99962600000001,43.086698],"type":"Point"}
}