{
  "type": "Feature",
  "properties": {
    "iso:country":"US",
    "sg:address":"107 S Marion Ave",
    "sg:city":"Washington",
    "sg:classifiers":[
        {
            "category":"Real Estate",
            "subcategory":"Real Estate Agent",
            "type":"Services"
        }
    ],
    "sg:phone":"+1 319 653 6612",
    "sg:postcode":"52353",
    "sg:province":"IA",
    "wof:name":"Washington Real Estate",
    "wof:placetype":"venue"
},
  "geometry": {"coordinates":[-91.693048,41.2994],"type":"Point"}
}