{
  "type": "Feature",
  "properties": {
    "iso:country":"US",
    "sg:address":"2501 Des Moines St",
    "sg:city":"Webster City",
    "sg:classifiers":[
        {
            "category":"Personal",
            "subcategory":"Beauty Salon",
            "type":"Services"
        }
    ],
    "sg:phone":"+1 515 832 3405",
    "sg:postcode":"50595",
    "sg:province":"IA",
    "sg:tags":[
        "shop"
    ],
    "wof:name":"Crest Cut & Curl",
    "wof:placetype":"venue"
},
  "geometry": {"coordinates":[-93.82082800000001,42.449777],"type":"Point"}
}