{
  "type": "Feature",
  "properties": {
    "iso:country":"US",
    "sg:address":"812 7th Ave",
    "sg:city":"De Witt",
    "sg:classifiers":[
        {
            "category":"Professional",
            "subcategory":"Accounting & Tax Preparation",
            "type":"Services"
        }
    ],
    "sg:phone":"+1 563 659 2247",
    "sg:postcode":"52742",
    "sg:province":"IA",
    "sg:tags":[
        "accountant"
    ],
    "wof:name":"Shelly Accounting & Tax Svc",
    "wof:placetype":"venue"
},
  "geometry": {"coordinates":[-90.540412,41.82409],"type":"Point"}
}