{
  "type": "Feature",
  "properties": {
    "addr:full":"320 11th Ave SE Cedar Rapids IA 52401",
    "addr:housenumber":"320",
    "addr:postcode":"52401",
    "addr:street":"11Th Ave Se",
    "iso:country":"US",
    "sg:address":"320 11th Ave SE",
    "sg:city":"Cedar Rapids",
    "sg:classifiers":[
        {
            "category":"Wholesale",
            "subcategory":"Non-durable Goods",
            "type":"Manufacturing & Wholesale Goods"
        }
    ],
    "sg:phone":"+1 319 365 4350",
    "sg:postcode":"52401",
    "sg:province":"IA",
    "sg:tags":[
        "poster"
    ],
    "sg:website":"www.inspirationart.com",
    "wof:name":"Inspirationart Scripture Inc",
    "wof:placetype":"venue"
},
  "geometry": {"coordinates":[-91.658142,41.971549],"type":"Point"}
}