{
  "type": "Feature",
  "properties": {
    "addr:full":"3380 155th St Cumming IA 50061",
    "addr:housenumber":"3380",
    "addr:postcode":"50061",
    "addr:street":"155Th St",
    "iso:country":"US",
    "sg:address":"3380 155th St",
    "sg:city":"Cumming",
    "sg:classifiers":[
        {
            "category":"Professional",
            "subcategory":"Business Services",
            "type":"Services"
        }
    ],
    "sg:phone":"+1 515 981 0246",
    "sg:postcode":"50061",
    "sg:province":"IA",
    "wof:name":"Connor Partnership",
    "wof:placetype":"venue"
},
  "geometry": {"coordinates":[-93.83153799999999,41.428974],"type":"Point"}
}