{
  "type": "Feature",
  "properties": {
    "iso:country":"US",
    "sg:address":"2155 Iowa Ave",
    "sg:city":"Humboldt",
    "sg:phone":"+1 515 332 3587",
    "sg:postcode":"50548",
    "sg:province":"IA",
    "sg:tags":[
        "farm",
        "corn",
        "soybean"
    ],
    "wof:name":"Richard M Moench",
    "wof:placetype":"venue"
},
  "geometry": {"coordinates":[-94.286929,42.746239],"type":"Point"}
}