{
  "type": "Feature",
  "properties": {
    "iso:country":"US",
    "sg:address":"729 Main St",
    "sg:city":"Janesville",
    "sg:classifiers":[
        {
            "category":"Autos & Motor Vehicles",
            "subcategory":"Auto Supplies",
            "type":"Retail Goods"
        }
    ],
    "sg:phone":"+1 319 987 2608",
    "sg:postcode":"50647",
    "sg:province":"IA",
    "sg:tags":[
        "tire"
    ],
    "wof:name":"County Line Tire",
    "wof:placetype":"venue"
},
  "geometry": {"coordinates":[-92.463035,42.643104],"type":"Point"}
}