{
  "type": "Feature",
  "properties": {
    "addr:full":"1517 Mall Dr Iowa City IA 52240",
    "addr:housenumber":"1517",
    "addr:postcode":"52240",
    "addr:street":"Mall Dr",
    "iso:country":"US",
    "sg:address":"1517 Mall Dr",
    "sg:city":"Iowa City",
    "sg:classifiers":[
        {
            "category":"Health Services",
            "subcategory":"Doctor",
            "type":"Services"
        }
    ],
    "sg:phone":"+1 319 337 5752",
    "sg:postcode":"52240",
    "sg:province":"IA",
    "sg:tags":[
        "dentist"
    ],
    "wof:name":"Ann Romanowski DDS",
    "wof:placetype":"venue"
},
  "geometry": {"coordinates":[-91.507929,41.643439],"type":"Point"}
}