{
  "type": "Feature",
  "properties": {
    "addr:full":"1911 Franklin St Cedar Falls IA 50613",
    "addr:housenumber":"1911",
    "addr:postcode":"50613",
    "addr:street":"Franklin St",
    "iso:country":"US",
    "sg:address":"1911 Franklin St",
    "sg:city":"Cedar Falls",
    "sg:classifiers":[
        {
            "category":"Professional",
            "subcategory":"Lawyer & Legal Services",
            "type":"Services"
        }
    ],
    "sg:phone":"+1 319 277 6028",
    "sg:postcode":"50613",
    "sg:province":"IA",
    "sg:tags":[
        "attorney"
    ],
    "wof:name":"Theodore R Stone",
    "wof:placetype":"venue"
},
  "geometry": {"coordinates":[-92.44954799999999,42.521111],"type":"Point"}
}