{
  "type": "Feature",
  "properties": {
    "addr:full":"580 US Hwy 18 E Clear Lake IA 50428",
    "addr:housenumber":"580",
    "addr:postcode":"50428",
    "addr:street":"Us Hwy 18 E",
    "iso:country":"US",
    "sg:address":"580 US Hwy 18 E",
    "sg:city":"Clear Lake",
    "sg:classifiers":[
        {
            "category":"Home & Garden",
            "subcategory":"Hardware",
            "type":"Retail Goods"
        }
    ],
    "sg:phone":"+1 641 357 7080",
    "sg:postcode":"50428",
    "sg:province":"IA",
    "wof:name":"Kramer Hardware",
    "wof:placetype":"venue"
},
  "geometry": {"coordinates":[-93.382998,43.143471],"type":"Point"}
}