{
  "type": "Feature",
  "properties": {
    "iso:country":"US",
    "sg:address":"2721 Violet Dr",
    "sg:city":"Waterloo",
    "sg:classifiers":[
        {
            "category":"Arts & Performance",
            "subcategory":"Theater",
            "type":"Entertainment"
        }
    ],
    "sg:phone":"+1 319 296 9105",
    "sg:postcode":"50701",
    "sg:province":"IA",
    "sg:tags":[
        "live",
        "music"
    ],
    "wof:name":"Dr DJ",
    "wof:placetype":"venue"
},
  "geometry": {"coordinates":[-92.301238,42.429308],"type":"Point"}
}