{
  "type": "Feature",
  "properties": {
    "iso:country":"US",
    "sg:address":"504 11th Ave NE",
    "sg:city":"Sibley",
    "sg:classifiers":[
        {
            "category":"Manufacturing",
            "subcategory":"Food",
            "type":"Manufacturing & Wholesale Goods"
        }
    ],
    "sg:phone":"+1 712 754 2945",
    "sg:postcode":"51249",
    "sg:province":"IA",
    "sg:tags":[
        "product"
    ],
    "wof:name":"Curtis Vankley",
    "wof:placetype":"venue"
},
  "geometry": {"coordinates":[-95.73764799999999,43.409202],"type":"Point"}
}