{
  "type": "Feature",
  "properties": {
    "addr:full":"202 Isabella St Radcliffe IA 50230",
    "addr:housenumber":"202",
    "addr:postcode":"50230",
    "addr:street":"Isabella St",
    "iso:country":"US",
    "sg:address":"202 Isabella St",
    "sg:city":"Radcliffe",
    "sg:classifiers":[
        {
            "category":"Utilities",
            "subcategory":"Cable",
            "type":"Services"
        }
    ],
    "sg:phone":"+1 515 899 2199",
    "sg:postcode":"50230",
    "sg:province":"IA",
    "sg:tags":[
        "television"
    ],
    "wof:name":"Radcliffe Cablevision",
    "wof:placetype":"venue"
},
  "geometry": {"coordinates":[-93.43415400000001,42.314063],"type":"Point"}
}