{
  "type": "Feature",
  "properties": {
    "iso:country":"US",
    "sg:address":"29509 Quail Ave",
    "sg:city":"Parkersburg",
    "sg:classifiers":[
        {
            "category":"Shopping",
            "subcategory":"Gifts & Souvenirs",
            "type":"Retail Goods"
        }
    ],
    "sg:phone":"+1 319 346 1278",
    "sg:postcode":"50665",
    "sg:province":"IA",
    "wof:name":"Toadily For You Gifts",
    "wof:placetype":"venue"
},
  "geometry": {"coordinates":[-92.712188,42.625494],"type":"Point"}
}