{
  "type": "Feature",
  "properties": {
    "addr:full":"722 Broad St Granville IA 51022",
    "addr:housenumber":"722",
    "addr:postcode":"51022",
    "addr:street":"Broad St",
    "iso:country":"US",
    "sg:address":"722 Broad St",
    "sg:city":"Granville",
    "sg:classifiers":[
        {
            "category":"Building & Trades",
            "subcategory":"Landscaping Services",
            "type":"Services"
        }
    ],
    "sg:phone":"+1 712 727 3800",
    "sg:postcode":"51022",
    "sg:province":"IA",
    "sg:tags":[
        "landscape",
        "contractor"
    ],
    "wof:name":"MLS Landscape & Design Inc",
    "wof:placetype":"venue"
},
  "geometry": {"coordinates":[-95.874346,42.98506],"type":"Point"}
}