{
  "type": "Feature",
  "properties": {
    "iso:country":"US",
    "sg:address":"1210 Southtown Dr",
    "sg:city":"Waterloo",
    "sg:classifiers":[
        {
            "category":"Retail",
            "subcategory":"Veterinary Services",
            "type":"Services"
        },
        {
            "category":"Retail",
            "subcategory":"Animal Services",
            "type":"Services"
        }
    ],
    "sg:phone":"+1 319 232 3674",
    "sg:postcode":"50702",
    "sg:province":"IA",
    "sg:tags":[
        "veterinarian"
    ],
    "wof:name":"Klima Small Animal Clinic",
    "wof:placetype":"venue"
},
  "geometry": {"coordinates":[-92.331417,42.455529],"type":"Point"}
}