{
  "type": "Feature",
  "properties": {
    "iso:country":"US",
    "sg:address":"2736 Hubbell Ave",
    "sg:city":"Des Moines",
    "sg:classifiers":[
        {
            "category":"Organizations",
            "subcategory":"Religious Organization",
            "type":"Services"
        }
    ],
    "sg:phone":"+1 515 262 7620",
    "sg:postcode":"50317",
    "sg:province":"IA",
    "wof:name":"Grandview Church Of Christ",
    "wof:placetype":"venue"
},
  "geometry": {"coordinates":[-93.56449600000001,41.617642],"type":"Point"}
}