{
  "type": "Feature",
  "properties": {
    "addr:full":"100 5th Ave De Witt IA 52742",
    "addr:housenumber":"100",
    "addr:postcode":"52742",
    "addr:street":"5Th Ave De",
    "iso:country":"US",
    "sg:address":"100 5th Ave",
    "sg:city":"De Witt",
    "sg:classifiers":[
        {
            "category":"Retail",
            "subcategory":"Auto Repair",
            "type":"Services"
        }
    ],
    "sg:phone":"+1 563 659 2609",
    "sg:postcode":"52742",
    "sg:province":"IA",
    "sg:tags":[
        "body",
        "automobile",
        "painting"
    ],
    "wof:name":"Bruce's Auto Body Repair Ctr",
    "wof:placetype":"venue"
},
  "geometry": {"coordinates":[-90.53742099999999,41.815366],"type":"Point"}
}