{
  "type": "Feature",
  "properties": {
    "addr:full":"1224 10th Ave N Clinton IA 52732",
    "addr:housenumber":"1224",
    "addr:postcode":"52732",
    "addr:street":"10Th Ave N",
    "iso:country":"US",
    "sg:address":"1224 10th Ave N",
    "sg:city":"Clinton",
    "sg:classifiers":[
        {
            "category":"Manufacturing",
            "subcategory":"Toys & Sporting Goods",
            "type":"Manufacturing & Wholesale Goods"
        }
    ],
    "sg:phone":"+1 563 242 1246",
    "sg:postcode":"52732",
    "sg:province":"IA",
    "sg:tags":[
        "mfg"
    ],
    "wof:name":"L A Sugar Bakers",
    "wof:placetype":"venue"
},
  "geometry": {"coordinates":[-90.216065,41.854313],"type":"Point"}
}