{
  "type": "Feature",
  "properties": {
    "iso:country":"US",
    "sg:address":"107 N Federal Ave",
    "sg:city":"Mason City",
    "sg:classifiers":[
        {
            "category":"Home & Garden",
            "subcategory":"Furniture",
            "type":"Retail Goods"
        }
    ],
    "sg:phone":"+1 641 424 1473",
    "sg:postcode":"50401",
    "sg:province":"IA",
    "sg:website":"www.brickfurniture.com",
    "wof:name":"Brick Furniture Store",
    "wof:placetype":"venue"
},
  "geometry": {"coordinates":[-93.200973,43.153568],"type":"Point"}
}