{
  "type": "Feature",
  "properties": {
    "addr:full":"1734 Miami Dr NE Cedar Rapids IA 52402",
    "addr:housenumber":"1734",
    "addr:postcode":"52402",
    "addr:street":"Miami Dr Ne",
    "iso:country":"US",
    "sg:address":"1734 Miami Dr NE",
    "sg:city":"Cedar Rapids",
    "sg:classifiers":[
        {
            "category":"Insurance",
            "subcategory":"Insurance Agent",
            "type":"Services"
        }
    ],
    "sg:phone":"+1 319 378 8213",
    "sg:postcode":"52402",
    "sg:province":"IA",
    "wof:name":"AFLAC",
    "wof:placetype":"venue"
},
  "geometry": {"coordinates":[-91.662415,42.018489],"type":"Point"}
}