{
  "type": "Feature",
  "properties": {
    "iso:country":"US",
    "sg:address":"216 E Milwaukee St",
    "sg:city":"Spencer",
    "sg:phone":"+1 712 262 2921",
    "sg:postcode":"51301",
    "sg:province":"IA",
    "sg:tags":[
        "oil"
    ],
    "wof:name":"Dyno Oil Co",
    "wof:placetype":"venue"
},
  "geometry": {"coordinates":[-95.141964,43.144702],"type":"Point"}
}