{
  "type": "Feature",
  "properties": {
    "iso:country":"US",
    "sg:address":"2542 Putnam St NE",
    "sg:city":"Iowa City",
    "sg:classifiers":[
        {
            "category":"Organizations",
            "subcategory":"Community Association",
            "type":"Services"
        }
    ],
    "sg:phone":"+1 319 643 2283",
    "sg:postcode":"52240",
    "sg:province":"IA",
    "sg:tags":[
        "club"
    ],
    "wof:name":"Morse Community Club",
    "wof:placetype":"venue"
},
  "geometry": {"coordinates":[-91.430378,41.744579],"type":"Point"}
}