{
  "type": "Feature",
  "properties": {
    "iso:country":"US",
    "sg:address":"10394 Yale Ave",
    "sg:city":"Nashua",
    "sg:classifiers":[
        {
            "category":"Farming",
            "subcategory":"Livestock Farm",
            "type":"Manufacturing & Wholesale Goods"
        }
    ],
    "sg:phone":"+1 641 435 4769",
    "sg:postcode":"50619",
    "sg:province":"IA",
    "sg:tags":[
        "feedlot",
        "corn",
        "soybean",
        "beef",
        "cattle"
    ],
    "wof:name":"Bernard Horn",
    "wof:placetype":"venue"
},
  "geometry": {"coordinates":[-92.57402500000001,42.892573],"type":"Point"}
}