{
  "type": "Feature",
  "properties": {
    "iso:country":"US",
    "sg:address":"20010 Higginsport Rd",
    "sg:city":"Bernard",
    "sg:classifiers":[
        {
            "category":"Building & Trades",
            "subcategory":"Construction",
            "type":"Services"
        }
    ],
    "sg:phone":"+1 563 879 3515",
    "sg:postcode":"52032",
    "sg:province":"IA",
    "sg:tags":[
        "house"
    ],
    "wof:name":"Chad L Curoe",
    "wof:placetype":"venue"
},
  "geometry": {"coordinates":[-90.88296200000001,42.309218],"type":"Point"}
}