{
  "type": "Feature",
  "properties": {
    "addr:full":"12778 Hwy 61 Burlington IA 52601",
    "addr:housenumber":"12778",
    "addr:postcode":"52601",
    "addr:street":"Hwy 61",
    "iso:country":"US",
    "sg:address":"12778 Hwy 61",
    "sg:city":"Burlington",
    "sg:classifiers":[
        {
            "category":"Building & Trades",
            "subcategory":"Landscaping Services",
            "type":"Services"
        }
    ],
    "sg:phone":"+1 319 752 4279",
    "sg:postcode":"52601",
    "sg:province":"IA",
    "sg:tags":[
        "tree"
    ],
    "wof:name":"Foster Tree Svc",
    "wof:placetype":"venue"
},
  "geometry": {"coordinates":[-91.162127,40.869637],"type":"Point"}
}