{
  "type": "Feature",
  "properties": {
    "iso:country":"US",
    "sg:address":"1842 State Hwy 4",
    "sg:city":"Estherville",
    "sg:classifiers":[
        {
            "category":"Manufacturing",
            "subcategory":"Pet Food",
            "type":"Manufacturing & Wholesale Goods"
        }
    ],
    "sg:phone":"+1 712 362 3551",
    "sg:postcode":"51334",
    "sg:province":"IA",
    "sg:tags":[
        "feed"
    ],
    "wof:name":"Golden Sun Feeds",
    "wof:placetype":"venue"
},
  "geometry": {"coordinates":[-94.821754,43.379163],"type":"Point"}
}