{
  "type": "Feature",
  "properties": {
    "iso:country":"US",
    "sg:address":"1504 Park Ave",
    "sg:city":"Muscatine",
    "sg:classifiers":[
        {
            "category":"Shopping",
            "subcategory":"Tobacco",
            "type":"Retail Goods"
        }
    ],
    "sg:phone":"+1 563 262 5400",
    "sg:postcode":"52761",
    "sg:province":"IA",
    "sg:tags":[
        "cigarette",
        "cigar",
        "dealer"
    ],
    "wof:name":"Cigarette Outlet",
    "wof:placetype":"venue"
},
  "geometry": {"coordinates":[-91.03071,41.438547],"type":"Point"}
}