{
  "type": "Feature",
  "properties": {
    "iso:country":"US",
    "sg:address":"109 2nd St SW",
    "sg:city":"Waukon",
    "sg:classifiers":[
        {
            "category":"Organizations",
            "subcategory":"Religious Organization",
            "type":"Services"
        }
    ],
    "sg:phone":"+1 563 568 3671",
    "sg:postcode":"52172",
    "sg:province":"IA",
    "sg:tags":[
        "church"
    ],
    "wof:name":"St Patrick Catholic Church",
    "wof:placetype":"venue"
},
  "geometry": {"coordinates":[-91.478807,43.268326],"type":"Point"}
}