{
  "type": "Feature",
  "properties": {
    "iso:country":"US",
    "sg:address":"206 S Clark St",
    "sg:city":"Winfield",
    "sg:classifiers":[
        {
            "category":"Education",
            "subcategory":"School",
            "type":"Public Place"
        }
    ],
    "sg:phone":"+1 319 257 7723",
    "sg:postcode":"52659",
    "sg:province":"IA",
    "wof:name":"Little Friends Day Care",
    "wof:placetype":"venue"
},
  "geometry": {"coordinates":[-91.440744,41.127541],"type":"Point"}
}