{
  "type": "Feature",
  "properties": {
    "iso:country":"US",
    "sg:address":"301 W Broadway",
    "sg:city":"Council Bluffs",
    "sg:classifiers":[
        {
            "category":"Health Services",
            "subcategory":"Health Practitioner",
            "type":"Services"
        }
    ],
    "sg:phone":"+1 712 322 9688",
    "sg:postcode":"51503",
    "sg:province":"IA",
    "sg:tags":[
        "therapist",
        "physical"
    ],
    "wof:name":"Excel Physical Therapy",
    "wof:placetype":"venue"
},
  "geometry": {"coordinates":[-95.84873399999999,41.260836],"type":"Point"}
}