{
  "type": "Feature",
  "properties": {
    "iso:country":"US",
    "sg:address":"5070 Lindale Dr NE",
    "sg:city":"Cedar Rapids",
    "sg:classifiers":[
        {
            "category":"Autos & Motor Vehicles",
            "subcategory":"Auto Supplies",
            "type":"Retail Goods"
        }
    ],
    "sg:phone":"+1 319 447 4640",
    "sg:postcode":"52402",
    "sg:province":"IA",
    "sg:tags":[
        "battery"
    ],
    "wof:name":"Batteries Plus",
    "wof:placetype":"venue"
},
  "geometry": {"coordinates":[-91.626807,42.027912],"type":"Point"}
}