{
  "type": "Feature",
  "properties": {
    "addr:full":"304 N Sherman St Knoxville IA 50138",
    "addr:housenumber":"304",
    "addr:postcode":"50138",
    "addr:street":"N Sherman St",
    "iso:country":"US",
    "sg:address":"304 N Sherman St",
    "sg:city":"Knoxville",
    "sg:classifiers":[
        {
            "category":"Banks & Credit Unions",
            "subcategory":"Bank",
            "type":"Services"
        }
    ],
    "sg:phone":"+1 641 842 2580",
    "sg:postcode":"50138",
    "sg:province":"IA",
    "sg:tags":[
        "loan"
    ],
    "wof:name":"Cash N Go",
    "wof:placetype":"venue"
},
  "geometry": {"coordinates":[-93.10652399999999,41.320786],"type":"Point"}
}