{
  "type": "Feature",
  "properties": {
    "iso:country":"US",
    "sg:address":"311 W 5th St",
    "sg:city":"Spencer",
    "sg:classifiers":[
        {
            "category":"Building & Trades",
            "subcategory":"Plumbing",
            "type":"Services"
        }
    ],
    "sg:phone":"+1 712 262 2384",
    "sg:postcode":"51301",
    "sg:province":"IA",
    "sg:tags":[
        "plumbing",
        "contractor"
    ],
    "wof:name":"Roto-Rooter Plumbing & Drain",
    "wof:placetype":"venue"
},
  "geometry": {"coordinates":[-95.148943,43.142298],"type":"Point"}
}