{
  "type": "Feature",
  "properties": {
    "iso:country":"US",
    "sg:address":"1191 Sorrel Ave",
    "sg:city":"Ocheyedan",
    "sg:phone":"+1 712 758 3387",
    "sg:postcode":"51354",
    "sg:province":"IA",
    "sg:tags":[
        "beef",
        "farm",
        "corn",
        "soybean",
        "cattle",
        "feedlot"
    ],
    "wof:name":"Van Heuvelen Rick",
    "wof:placetype":"venue"
},
  "geometry": {"coordinates":[-95.60434600000001,43.47727],"type":"Point"}
}