{
  "type": "Feature",
  "properties": {
    "addr:full":"111 E Robinson St Knoxville IA 50138",
    "addr:housenumber":"111",
    "addr:postcode":"50138",
    "addr:street":"E Robinson St",
    "iso:country":"US",
    "sg:address":"111 E Robinson St",
    "sg:city":"Knoxville",
    "sg:classifiers":[
        {
            "category":"Wholesale",
            "subcategory":"Meat",
            "type":"Manufacturing & Wholesale Goods"
        }
    ],
    "sg:phone":"+1 641 842 5622",
    "sg:postcode":"50138",
    "sg:province":"IA",
    "sg:tags":[
        "prod",
        "prepared"
    ],
    "wof:name":"Hometown Meats",
    "wof:placetype":"venue"
},
  "geometry": {"coordinates":[-93.097714,41.318102],"type":"Point"}
}