{
  "type": "Feature",
  "properties": {
    "iso:country":"US",
    "sg:address":"2227 225th St",
    "sg:city":"Williamsburg",
    "sg:classifiers":[
        {
            "category":"Social Services",
            "subcategory":"Adult Care",
            "type":"Services"
        }
    ],
    "sg:phone":"+1 319 668 1659",
    "sg:postcode":"52361",
    "sg:province":"IA",
    "sg:tags":[
        "home",
        "residential"
    ],
    "wof:name":"Hillside Estate Inc",
    "wof:placetype":"venue"
},
  "geometry": {"coordinates":[-92.06314500000001,41.680631],"type":"Point"}
}