{
  "type": "Feature",
  "properties": {
    "iso:country":"US",
    "sg:address":"600 E Oak St",
    "sg:city":"Mt Pleasant",
    "sg:classifiers":[
        {
            "category":"Wholesale",
            "subcategory":"Hardware",
            "type":"Manufacturing & Wholesale Goods"
        }
    ],
    "sg:phone":"+1 319 385 3800",
    "sg:postcode":"52641",
    "sg:province":"IA",
    "sg:tags":[
        "machine",
        "making",
        "ice",
        "equipment"
    ],
    "wof:name":"J & S Ice",
    "wof:placetype":"venue"
},
  "geometry": {"coordinates":[-91.544522,40.970711],"type":"Point"}
}