{
  "type": "Feature",
  "properties": {
    "iso:country":"US",
    "sg:address":"1 E Margaret St",
    "sg:city":"Earlville",
    "sg:classifiers":[
        {
            "category":"Shopping",
            "subcategory":"Computers & Home Electronics",
            "type":"Retail Goods"
        }
    ],
    "sg:phone":"+1 563 923 7204",
    "sg:postcode":"52041",
    "sg:province":"IA",
    "sg:tags":[
        "equipment",
        "satellite",
        "system"
    ],
    "wof:name":"Unlimited Security & Satellite",
    "wof:placetype":"venue"
},
  "geometry": {"coordinates":[-91.272426,42.485347],"type":"Point"}
}