{
  "type": "Feature",
  "properties": {
    "iso:country":"US",
    "sg:address":"3970 Center Point Rd NE",
    "sg:city":"Cedar Rapids",
    "sg:classifiers":[
        {
            "category":"Bars & Pubs",
            "subcategory":"Nightclub",
            "type":"Food & Drink"
        }
    ],
    "sg:phone":"+1 319 393 9858",
    "sg:postcode":"52402",
    "sg:province":"IA",
    "sg:tags":[
        "nightlife"
    ],
    "wof:name":"Red Lion Lounge",
    "wof:placetype":"venue"
},
  "geometry": {"coordinates":[-91.66480300000001,42.019501],"type":"Point"}
}