{
  "type": "Feature",
  "properties": {
    "iso:country":"US",
    "sg:address":"1055 Hwy 67",
    "sg:city":"Sabula",
    "sg:classifiers":[
        {
            "category":"Farming",
            "subcategory":"Farm",
            "type":"Manufacturing & Wholesale Goods"
        }
    ],
    "sg:phone":"+1 563 687 2508",
    "sg:postcode":"52070",
    "sg:province":"IA",
    "sg:tags":[
        "crop",
        "general"
    ],
    "wof:name":"Edward Kuhl Farm",
    "wof:placetype":"venue"
},
  "geometry": {"coordinates":[-90.191784,42.042974],"type":"Point"}
}