{
  "type": "Feature",
  "properties": {
    "addr:full":"1624 S Garfield Pl Mason City IA 50401",
    "addr:housenumber":"1624",
    "addr:postcode":"50401",
    "addr:street":"S Garfield Pl",
    "iso:country":"US",
    "sg:address":"1624 S Garfield Pl",
    "sg:city":"Mason City",
    "sg:classifiers":[
        {
            "category":"Retail",
            "subcategory":"Auto Repair",
            "type":"Services"
        }
    ],
    "sg:phone":"+1 641 424 9336",
    "sg:postcode":"50401",
    "sg:province":"IA",
    "sg:tags":[
        "repairing",
        "automobile"
    ],
    "wof:name":"Wick's Repair",
    "wof:placetype":"venue"
},
  "geometry": {"coordinates":[-93.226372,43.13665],"type":"Point"}
}