{
  "type": "Feature",
  "properties": {
    "iso:country":"US",
    "sg:address":"310 27th St NE",
    "sg:city":"Cedar Rapids",
    "sg:classifiers":[
        {
            "category":"Social Services",
            "subcategory":"Child Care",
            "type":"Services"
        }
    ],
    "sg:phone":"+1 319 558 2550",
    "sg:postcode":"52402",
    "sg:province":"IA",
    "sg:tags":[
        "day"
    ],
    "wof:name":"Five Seasons Learning Centers",
    "wof:placetype":"venue"
},
  "geometry": {"coordinates":[-91.63780199999999,42.003601],"type":"Point"}
}