{
  "type": "Feature",
  "properties": {
    "addr:full":"1702 Harding St Tama IA 52339",
    "addr:housenumber":"1702",
    "addr:postcode":"52339",
    "addr:street":"Harding St",
    "iso:country":"US",
    "sg:address":"1702 Harding St",
    "sg:city":"Tama",
    "sg:classifiers":[
        {
            "category":"Education",
            "subcategory":"School",
            "type":"Public Place"
        }
    ],
    "sg:phone":"+1 641 484 4811",
    "sg:postcode":"52339",
    "sg:province":"IA",
    "wof:name":"South Tama County Comm School",
    "wof:placetype":"venue"
},
  "geometry": {"coordinates":[-92.581605,41.9782],"type":"Point"}
}