{
  "type": "Feature",
  "properties": {
    "iso:country":"US",
    "sg:address":"500 State Hwy 175",
    "sg:city":"Ida Grove",
    "sg:classifiers":[
        {
            "category":"Restaurant",
            "type":"Food & Drink"
        }
    ],
    "sg:phone":"+1 712 364 2799",
    "sg:postcode":"51445",
    "sg:province":"IA",
    "wof:name":"Subway Sandwiches & Salads",
    "wof:placetype":"venue"
},
  "geometry": {"coordinates":[-95.469573,42.351136],"type":"Point"}
}