{
  "type": "Feature",
  "properties": {
    "iso:country":"US",
    "sg:address":"109 Main St",
    "sg:city":"Sanborn",
    "sg:classifiers":[
        {
            "category":"Personal",
            "subcategory":"Barber",
            "type":"Services"
        }
    ],
    "sg:phone":"+1 712 930 5045",
    "sg:postcode":"51248",
    "sg:province":"IA",
    "wof:name":"Barber Shop",
    "wof:placetype":"venue"
},
  "geometry": {"coordinates":[-95.655817,43.181478],"type":"Point"}
}