{
  "type": "Feature",
  "properties": {
    "addr:full":"2012 Sabbath Dr Muscatine IA 52761",
    "addr:housenumber":"2012",
    "addr:postcode":"52761",
    "addr:street":"Sabbath Dr",
    "iso:country":"US",
    "sg:address":"2012 Sabbath Dr",
    "sg:city":"Muscatine",
    "sg:classifiers":[
        {
            "category":"Professional",
            "type":"Services"
        }
    ],
    "sg:phone":"+1 563 264 5948",
    "sg:postcode":"52761",
    "sg:province":"IA",
    "sg:tags":[
        "establishment"
    ],
    "wof:name":"QSP Inc",
    "wof:placetype":"venue"
},
  "geometry": {"coordinates":[-90.97911999999999,41.445883],"type":"Point"}
}