{
  "type": "Feature",
  "properties": {
    "iso:country":"US",
    "sg:address":"1607 Grandview Ave",
    "sg:city":"Muscatine",
    "sg:classifiers":[
        {
            "category":"Wholesale",
            "subcategory":"Farm Supplies",
            "type":"Manufacturing & Wholesale Goods"
        }
    ],
    "sg:phone":"+1 563 263 0543",
    "sg:postcode":"52761",
    "sg:province":"IA",
    "wof:name":"Orscheln Farm & Home",
    "wof:placetype":"venue"
},
  "geometry": {"coordinates":[-91.072428,41.401433],"type":"Point"}
}