{
  "type": "Feature",
  "properties": {
    "iso:country":"US",
    "sg:address":"537 3rd St NE",
    "sg:city":"Mason City",
    "sg:classifiers":[
        {
            "category":"Manufacturing",
            "subcategory":"Printing",
            "type":"Manufacturing & Wholesale Goods"
        }
    ],
    "sg:phone":"+1 641 423 1877",
    "sg:postcode":"50401",
    "sg:province":"IA",
    "sg:tags":[
        "lithographic",
        "commercial"
    ],
    "wof:name":"C&R Printing",
    "wof:placetype":"venue"
},
  "geometry": {"coordinates":[-93.190882,43.154543],"type":"Point"}
}