{
  "type": "Feature",
  "properties": {
    "iso:country":"US",
    "sg:address":"204 Cass St",
    "sg:city":"Keosauqua",
    "sg:classifiers":[
        {
            "category":"Food & Beverages",
            "subcategory":"Groceries & Convenience Stores",
            "type":"Retail Goods"
        }
    ],
    "sg:phone":"+1 319 293 3336",
    "sg:postcode":"52565",
    "sg:province":"IA",
    "sg:tags":[
        "grocer"
    ],
    "wof:name":"Archie's Food Market",
    "wof:placetype":"venue"
},
  "geometry": {"coordinates":[-91.962592,40.731469],"type":"Point"}
}