{
  "type": "Feature",
  "properties": {
    "addr:full":"2272 Dayton Pkwy Ames IA 50010",
    "addr:housenumber":"2272",
    "addr:postcode":"50010",
    "addr:street":"Dayton Pkwy",
    "iso:country":"US",
    "sg:address":"2272 Dayton Pkwy",
    "sg:city":"Ames",
    "sg:classifiers":[
        {
            "category":"Professional",
            "subcategory":"Research",
            "type":"Services"
        }
    ],
    "sg:phone":"+1 515 232 4957",
    "sg:postcode":"50010",
    "sg:province":"IA",
    "sg:tags":[
        "environmental",
        "ecological"
    ],
    "wof:name":"Miner Environmental Conslnts",
    "wof:placetype":"venue"
},
  "geometry": {"coordinates":[-93.583286,42.077363],"type":"Point"}
}