{
  "type": "Feature",
  "properties": {
    "addr:full":"1805 5th Ave Council Bluffs IA 51501",
    "addr:housenumber":"1805",
    "addr:postcode":"51501",
    "addr:street":"5Th Ave",
    "iso:country":"US",
    "sg:address":"1805 5th Ave",
    "sg:city":"Council Bluffs",
    "sg:classifiers":[
        {
            "category":"Freight",
            "type":"Transportation"
        }
    ],
    "sg:phone":"+1 712 322 3138",
    "sg:postcode":"51501",
    "sg:province":"IA",
    "sg:tags":[
        "delivery"
    ],
    "wof:name":"Brogan Enterprises Inc",
    "wof:placetype":"venue"
},
  "geometry": {"coordinates":[-95.87211600000001,41.257057],"type":"Point"}
}