{
  "type": "Feature",
  "properties": {
    "addr:full":"300 E Park St Spencer IA 51301",
    "addr:housenumber":"300",
    "addr:postcode":"51301",
    "addr:street":"E Park St",
    "iso:country":"US",
    "sg:address":"300 E Park St",
    "sg:city":"Spencer",
    "sg:classifiers":[
        {
            "category":"Government",
            "subcategory":"Office",
            "type":"Public Place"
        }
    ],
    "sg:phone":"+1 712 262 4425",
    "sg:postcode":"51301",
    "sg:province":"IA",
    "wof:name":"Clay County Maintenance Garage",
    "wof:placetype":"venue"
},
  "geometry": {"coordinates":[-95.139583,43.137851],"type":"Point"}
}