{
  "type": "Feature",
  "properties": {
    "iso:country":"US",
    "sg:address":"8 Timberlane Dr",
    "sg:city":"Sioux City",
    "sg:classifiers":[
        {
            "category":"Professional",
            "subcategory":"Management & Consulting",
            "type":"Services"
        }
    ],
    "sg:phone":"+1 712 258 8732",
    "sg:postcode":"51108",
    "sg:province":"IA",
    "wof:name":"International Marketing Entp",
    "wof:placetype":"venue"
},
  "geometry": {"coordinates":[-96.451053,42.582863],"type":"Point"}
}