{
  "type": "Feature",
  "properties": {
    "iso:country":"US",
    "sg:address":"2516 160th St",
    "sg:city":"Marshalltown",
    "sg:phone":"+1 641 753 8057",
    "sg:postcode":"50158",
    "sg:province":"IA",
    "sg:tags":[
        "farm",
        "crop"
    ],
    "wof:name":"Asher Valley Farms Inc",
    "wof:placetype":"venue"
},
  "geometry": {"coordinates":[-92.939571,42.123041],"type":"Point"}
}