{
  "type": "Feature",
  "properties": {
    "addr:full":"1204 15th St West Des Moines IA 50265",
    "addr:housenumber":"1204",
    "addr:postcode":"50265",
    "addr:street":"15Th St",
    "iso:country":"US",
    "sg:address":"1204 15th St",
    "sg:city":"West Des Moines",
    "sg:classifiers":[
        {
            "category":"Building & Trades",
            "subcategory":"Cleaning & Sanitation",
            "type":"Services"
        }
    ],
    "sg:phone":"+1 515 224 6383",
    "sg:postcode":"50265",
    "sg:province":"IA",
    "sg:tags":[
        "janitor"
    ],
    "wof:name":"AAA Allied Building Svc",
    "wof:placetype":"venue"
},
  "geometry": {"coordinates":[-93.723883,41.591134],"type":"Point"}
}