{
  "type": "Feature",
  "properties": {
    "iso:country":"US",
    "sg:address":"124 S 1st St",
    "sg:city":"Oskaloosa",
    "sg:classifiers":[
        {
            "category":"Banks & Credit Unions",
            "subcategory":"Bank",
            "type":"Services"
        }
    ],
    "sg:phone":"+1 641 673 8303",
    "sg:postcode":"52577",
    "sg:province":"IA",
    "wof:name":"Midwest One Bank & Trust",
    "wof:placetype":"venue"
},
  "geometry": {"coordinates":[-92.64377,41.295123],"type":"Point"}
}