{
  "type": "Feature",
  "properties": {
    "iso:country":"US",
    "sg:address":"18954 Hickory Grove Rd",
    "sg:city":"Anamosa",
    "sg:classifiers":[
        {
            "category":"Farming",
            "subcategory":"Livestock Farm",
            "type":"Manufacturing & Wholesale Goods"
        }
    ],
    "sg:phone":"+1 319 465 4001",
    "sg:postcode":"52205",
    "sg:province":"IA",
    "sg:tags":[
        "corn",
        "beef",
        "feedlot",
        "cattle"
    ],
    "wof:name":"Stimpson John",
    "wof:placetype":"venue"
},
  "geometry": {"coordinates":[-91.28684,42.20895],"type":"Point"}
}