{
  "type": "Feature",
  "properties": {
    "iso:country":"US",
    "sg:address":"205 S 8th St",
    "sg:city":"Fort Dodge",
    "sg:classifiers":[
        {
            "category":"Building & Trades",
            "subcategory":"Construction",
            "type":"Services"
        }
    ],
    "sg:phone":"+1 515 576 1730",
    "sg:postcode":"50501",
    "sg:province":"IA",
    "sg:tags":[
        "general",
        "contractor"
    ],
    "wof:name":"L B & B Assoc",
    "wof:placetype":"venue"
},
  "geometry": {"coordinates":[-94.186853,42.503093],"type":"Point"}
}