{
  "type": "Feature",
  "properties": {
    "iso:country":"US",
    "sg:address":"10550 New York Ave",
    "sg:city":"Urbandale",
    "sg:classifiers":[
        {
            "category":"Professional",
            "subcategory":"Accounting & Tax Preparation",
            "type":"Services"
        }
    ],
    "sg:phone":"+1 515 270 8080",
    "sg:postcode":"50322",
    "sg:province":"IA",
    "sg:tags":[
        "accountant"
    ],
    "sg:website":"www.tkjcpa.com",
    "wof:name":"Timmins Kroll & Jacobsen LLP",
    "wof:placetype":"venue"
},
  "geometry": {"coordinates":[-93.761804,41.618849],"type":"Point"}
}