{
  "type": "Feature",
  "properties": {
    "iso:country":"US",
    "sg:address":"1012 N 10th St",
    "sg:city":"Winterset",
    "sg:classifiers":[
        {
            "category":"Retail",
            "subcategory":"Auto Repair",
            "type":"Services"
        }
    ],
    "sg:phone":"+1 515 462 1035",
    "sg:postcode":"50273",
    "sg:province":"IA",
    "sg:tags":[
        "repairing",
        "automobile"
    ],
    "wof:name":"Quality Car Care",
    "wof:placetype":"venue"
},
  "geometry": {"coordinates":[-94.00317,41.343168],"type":"Point"}
}