{
  "type": "Feature",
  "properties": {
    "iso:country":"US",
    "sg:address":"941 Kennedy St",
    "sg:city":"Granville",
    "sg:classifiers":[
        {
            "category":"Farming",
            "subcategory":"Livestock Farm",
            "type":"Manufacturing & Wholesale Goods"
        }
    ],
    "sg:phone":"+1 712 727 3398",
    "sg:postcode":"51022",
    "sg:province":"IA",
    "sg:tags":[
        "beef",
        "feedlot",
        "cattle"
    ],
    "wof:name":"Dean Bunkers",
    "wof:placetype":"venue"
},
  "geometry": {"coordinates":[-95.874815,42.987081],"type":"Point"}
}