{
  "type": "Feature",
  "properties": {
    "iso:country":"US",
    "sg:address":"207 E Church St",
    "sg:city":"Marshalltown",
    "sg:classifiers":[
        {
            "category":"Health Services",
            "subcategory":"Chiropractor",
            "type":"Services"
        }
    ],
    "sg:phone":"+1 641 752 9700",
    "sg:postcode":"50158",
    "sg:province":"IA",
    "wof:name":"Chiropractic Healthcare",
    "wof:placetype":"venue"
},
  "geometry": {"coordinates":[-92.90956300000001,42.047846],"type":"Point"}
}