{
  "type": "Feature",
  "properties": {
    "iso:country":"US",
    "sg:address":"2160 E Douglas Ave",
    "sg:city":"Des Moines",
    "sg:classifiers":[
        {
            "category":"Organizations",
            "subcategory":"Labor Organization",
            "type":"Services"
        }
    ],
    "sg:phone":"+1 515 265 3467",
    "sg:postcode":"50313",
    "sg:province":"IA",
    "wof:name":"Carpenters",
    "wof:placetype":"venue"
},
  "geometry": {"coordinates":[-93.57843699999999,41.629654],"type":"Point"}
}