{
  "type": "Feature",
  "properties": {
    "iso:country":"US",
    "sg:address":"1521 220th St",
    "sg:city":"Ionia",
    "sg:classifiers":[
        {
            "category":"Freight",
            "type":"Transportation"
        }
    ],
    "sg:phone":"+1 641 394 4384",
    "sg:postcode":"50645",
    "sg:province":"IA",
    "sg:tags":[
        "trucking"
    ],
    "wof:name":"Rausch Brothers Trucking",
    "wof:placetype":"venue"
},
  "geometry": {"coordinates":[-92.44893500000001,43.034183],"type":"Point"}
}