{
  "type": "Feature",
  "properties": {
    "addr:full":"1170 Twixt Town Rd NE Cedar Rapids IA 52402",
    "addr:housenumber":"1170",
    "addr:postcode":"52402",
    "addr:street":"Twixt Town Rd Ne",
    "iso:country":"US",
    "sg:address":"1170 Twixt Town Rd NE",
    "sg:city":"Cedar Rapids",
    "sg:classifiers":[
        {
            "category":"Home & Garden",
            "subcategory":"Furniture",
            "type":"Retail Goods"
        }
    ],
    "sg:phone":"+1 319 377 6364",
    "sg:postcode":"52402",
    "sg:province":"IA",
    "wof:name":"Ethan Allen Galleries Inc",
    "wof:placetype":"venue"
},
  "geometry": {"coordinates":[-91.61885100000001,42.02781],"type":"Point"}
}