{
  "type": "Feature",
  "properties": {
    "iso:country":"US",
    "sg:address":"2924 Elderberry Ave",
    "sg:city":"Macksburg",
    "sg:classifiers":[
        {
            "category":"Farming",
            "subcategory":"Farm",
            "type":"Manufacturing & Wholesale Goods"
        }
    ],
    "sg:phone":"+1 641 768 2336",
    "sg:postcode":"50155",
    "sg:province":"IA",
    "sg:tags":[
        "crop",
        "general"
    ],
    "wof:name":"Hazel Pinckney Farm",
    "wof:placetype":"venue"
},
  "geometry": {"coordinates":[-94.15146,41.225116],"type":"Point"}
}