{
  "type": "Feature",
  "properties": {
    "iso:country":"US",
    "sg:address":"2600 Blvd of Champions",
    "sg:city":"Sioux City",
    "sg:classifiers":[
        {
            "category":"Wholesale",
            "subcategory":"Scrap",
            "type":"Manufacturing & Wholesale Goods"
        }
    ],
    "sg:phone":"+1 712 277 4100",
    "sg:postcode":"51111",
    "sg:province":"IA",
    "sg:tags":[
        "metal"
    ],
    "sg:website":"www.compressedsteel.com",
    "wof:name":"Compressed Steel Co",
    "wof:placetype":"venue"
},
  "geometry": {"coordinates":[-96.37329,42.421758],"type":"Point"}
}