{
  "type": "Feature",
  "properties": {
    "iso:country":"US",
    "sg:address":"172 290th St",
    "sg:city":"West Branch",
    "sg:classifiers":[
        {
            "category":"Building & Trades",
            "subcategory":"Plumbing",
            "type":"Services"
        }
    ],
    "sg:phone":"+1 319 643 5522",
    "sg:postcode":"52358",
    "sg:province":"IA",
    "sg:tags":[
        "conditioning",
        "air",
        "system",
        "contractor"
    ],
    "wof:name":"West Branch Heating & Air Cond",
    "wof:placetype":"venue"
},
  "geometry": {"coordinates":[-91.328901,41.671187],"type":"Point"}
}