{
  "type": "Feature",
  "properties": {
    "iso:country":"US",
    "sg:address":"318 E 4th St",
    "sg:city":"Waterloo",
    "sg:classifiers":[
        {
            "category":"Professional",
            "subcategory":"Lawyer & Legal Services",
            "type":"Services"
        }
    ],
    "sg:phone":"+1 319 233 1979",
    "sg:postcode":"50703",
    "sg:province":"IA",
    "sg:tags":[
        "attorney"
    ],
    "wof:name":"Bandy Law Office",
    "wof:placetype":"venue"
},
  "geometry": {"coordinates":[-92.33410000000001,42.499625],"type":"Point"}
}