{
  "type": "Feature",
  "properties": {
    "iso:country":"US",
    "sg:address":"201 N 15th St",
    "sg:city":"Fort Dodge",
    "sg:classifiers":[
        {
            "category":"Ice Cream",
            "type":"Food & Drink"
        }
    ],
    "sg:menulink":"http://www.allmenus.com/ia/fort-dodge/172680-dairy-queen/menu/",
    "sg:phone":"+1 515 955 6125",
    "sg:postcode":"50501",
    "sg:province":"IA",
    "sg:tags":[
        "burger",
        "american"
    ],
    "wof:name":"Dairy Queen",
    "wof:placetype":"venue"
},
  "geometry": {"coordinates":[-94.177708,42.508413],"type":"Point"}
}