{
  "type": "Feature",
  "properties": {
    "iso:country":"US",
    "sg:address":"216 Sycamore St",
    "sg:city":"Muscatine",
    "sg:classifiers":[
        {
            "category":"Organizations",
            "subcategory":"Religious Organization",
            "type":"Services"
        }
    ],
    "sg:phone":"+1 563 264 6836",
    "sg:postcode":"52761",
    "sg:province":"IA",
    "wof:name":"United Methodist Distrct Offce",
    "wof:placetype":"venue"
},
  "geometry": {"coordinates":[-91.04488600000001,41.422055],"type":"Point"}
}