{
  "type": "Feature",
  "properties": {
    "iso:country":"US",
    "sg:address":"1814 Central Ave",
    "sg:city":"Fort Dodge",
    "sg:classifiers":[
        {
            "category":"Professional",
            "type":"Services"
        }
    ],
    "sg:phone":"+1 515 955 8344",
    "sg:postcode":"50501",
    "sg:province":"IA",
    "sg:tags":[
        "establishment"
    ],
    "wof:name":"Mid-Iowa Regional Housing",
    "wof:placetype":"venue"
},
  "geometry": {"coordinates":[-94.17233400000001,42.506308],"type":"Point"}
}