{
  "type": "Feature",
  "properties": {
    "iso:country":"US",
    "sg:address":"606 E Hwy 30",
    "sg:city":"Jefferson",
    "sg:classifiers":[
        {
            "category":"Food & Beverages",
            "subcategory":"Groceries & Convenience Stores",
            "type":"Retail Goods"
        }
    ],
    "sg:phone":"+1 515 386 4913",
    "sg:postcode":"50129",
    "sg:province":"IA",
    "wof:name":"Sparky's One Stop",
    "wof:placetype":"venue"
},
  "geometry": {"coordinates":[-94.363461,42.034735],"type":"Point"}
}