{
  "type": "Feature",
  "properties": {
    "iso:country":"US",
    "sg:address":"3726 Santa Fe Trl",
    "sg:city":"Davenport",
    "sg:classifiers":[
        {
            "category":"Building & Trades",
            "subcategory":"Landscaping Services",
            "type":"Services"
        }
    ],
    "sg:phone":"+1 563 514 0701",
    "sg:postcode":"52804",
    "sg:province":"IA",
    "sg:tags":[
        "tree"
    ],
    "wof:name":"Stick Mans Tree Service",
    "wof:placetype":"venue"
},
  "geometry": {"coordinates":[-90.631739,41.517773],"type":"Point"}
}