{
  "type": "Feature",
  "properties": {
    "iso:country":"US",
    "sg:address":"214 1st Ave",
    "sg:city":"Coralville",
    "sg:classifiers":[
        {
            "category":"Professional",
            "subcategory":"Accounting & Tax Preparation",
            "type":"Services"
        }
    ],
    "sg:phone":"+1 319 351 2411",
    "sg:postcode":"52241",
    "sg:province":"IA",
    "sg:tags":[
        "return",
        "filing"
    ],
    "sg:website":"www.hrblock.com",
    "wof:name":"H & R Block Tax Svc",
    "wof:placetype":"venue"
},
  "geometry": {"coordinates":[-91.565664,41.66937],"type":"Point"}
}