{
  "type": "Feature",
  "properties": {
    "iso:country":"US",
    "sg:address":"12998 338th St",
    "sg:city":"Strawberry Point",
    "sg:classifiers":[
        {
            "category":"Organizations",
            "subcategory":"Religious Organization",
            "type":"Services"
        }
    ],
    "sg:phone":"+1 563 933 6127",
    "sg:postcode":"52076",
    "sg:province":"IA",
    "sg:tags":[
        "clergy"
    ],
    "wof:name":"St Sebald's Lutheran Parsonage",
    "wof:placetype":"venue"
},
  "geometry": {"coordinates":[-91.54675899999999,42.740491],"type":"Point"}
}