{
  "type": "Feature",
  "properties": {
    "iso:country":"US",
    "sg:address":"3553 8th St SW",
    "sg:city":"Altoona",
    "sg:classifiers":[
        {
            "category":"Restaurant",
            "type":"Food & Drink"
        }
    ],
    "sg:menulink":"http://www.allmenus.com/ia/delaware/158437-arbys/menu/",
    "sg:phone":"+1 515 957 9556",
    "sg:postcode":"50009",
    "sg:province":"IA",
    "sg:tags":[
        "burger",
        "american"
    ],
    "wof:name":"Arby's",
    "wof:placetype":"venue"
},
  "geometry": {"coordinates":[-93.505616,41.644738],"type":"Point"}
}