{
  "type": "Feature",
  "properties": {
    "iso:country":"US",
    "sg:address":"702 W 9th St",
    "sg:city":"Vinton",
    "sg:classifiers":[
        {
            "category":"Retail",
            "subcategory":"Auto Repair",
            "type":"Services"
        }
    ],
    "sg:phone":"+1 319 472 2287",
    "sg:postcode":"52349",
    "sg:province":"IA",
    "sg:tags":[
        "good",
        "general",
        "lead",
        "mfg"
    ],
    "wof:name":"Ceramic Craze",
    "wof:placetype":"venue"
},
  "geometry": {"coordinates":[-92.032708,42.162952],"type":"Point"}
}