{
  "type": "Feature",
  "properties": {
    "iso:country":"US",
    "sg:address":"225 33rd St",
    "sg:city":"Bettendorf",
    "sg:classifiers":[
        {
            "category":"Manufacturing",
            "subcategory":"Metals",
            "type":"Manufacturing & Wholesale Goods"
        }
    ],
    "sg:phone":"+1 563 355 1811",
    "sg:postcode":"52722",
    "sg:province":"IA",
    "sg:tags":[
        "foundry"
    ],
    "sg:website":"www.sivyersteel.com",
    "wof:name":"Sivyer Steel Corp",
    "wof:placetype":"venue"
},
  "geometry": {"coordinates":[-90.486133,41.522079],"type":"Point"}
}