{
  "type": "Feature",
  "properties": {
    "iso:country":"US",
    "sg:address":"900 Grand Ave",
    "sg:city":"West Des Moines",
    "sg:classifiers":[
        {
            "category":"Retail",
            "subcategory":"Laundry & Dry Cleaning",
            "type":"Services"
        }
    ],
    "sg:phone":"+1 515 226 9805",
    "sg:postcode":"50265",
    "sg:province":"IA",
    "sg:tags":[
        "cleaners"
    ],
    "wof:name":"Victoria Cleaners",
    "wof:placetype":"venue"
},
  "geometry": {"coordinates":[-93.71580299999999,41.582459],"type":"Point"}
}