{
  "type": "Feature",
  "properties": {
    "addr:full":"200 9th St Corning IA 50841",
    "addr:housenumber":"200",
    "addr:postcode":"50841",
    "addr:street":"9Th St",
    "iso:country":"US",
    "sg:address":"200 9th St",
    "sg:city":"Corning",
    "sg:classifiers":[
        {
            "category":"Restaurant",
            "type":"Food & Drink"
        }
    ],
    "sg:menulink":"http://www.allmenus.com/ia/quincy/67039-pizza-hut/menu/",
    "sg:phone":"+1 641 322 4212",
    "sg:postcode":"50841",
    "sg:province":"IA",
    "sg:tags":[
        "american",
        "pizza"
    ],
    "wof:name":"Pizza Hut",
    "wof:placetype":"venue"
},
  "geometry": {"coordinates":[-94.730591,40.990902],"type":"Point"}
}