{
  "type": "Feature",
  "properties": {
    "addr:full":"703 Douglas St Sioux City IA 51101",
    "addr:housenumber":"703",
    "addr:postcode":"51101",
    "addr:street":"Douglas St",
    "iso:country":"US",
    "sg:address":"703 Douglas St",
    "sg:city":"Sioux City",
    "sg:classifiers":[
        {
            "category":"Personal",
            "subcategory":"Beauty Salon",
            "type":"Services"
        }
    ],
    "sg:phone":"+1 712 252 2112",
    "sg:postcode":"51101",
    "sg:province":"IA",
    "wof:name":"Sir Richards & Dick's Barber",
    "wof:placetype":"venue"
},
  "geometry": {"coordinates":[-96.40655,42.498475],"type":"Point"}
}