{
  "type": "Feature",
  "properties": {
    "iso:country":"US",
    "sg:address":"56395 US Hwy 275",
    "sg:city":"Glenwood",
    "sg:classifiers":[
        {
            "category":"Building & Trades",
            "subcategory":"Construction",
            "type":"Services"
        }
    ],
    "sg:phone":"+1 712 527 4265",
    "sg:postcode":"51534",
    "sg:province":"IA",
    "sg:tags":[
        "builder",
        "general",
        "operative",
        "contractor"
    ],
    "wof:name":"Caddy Homes",
    "wof:placetype":"venue"
},
  "geometry": {"coordinates":[-95.757614,41.067676],"type":"Point"}
}