{
  "type": "Feature",
  "properties": {
    "addr:full":"116 N Chestnut Ave New Hampton IA 50659",
    "addr:housenumber":"116",
    "addr:postcode":"50659",
    "addr:street":"N Chestnut Ave",
    "iso:country":"US",
    "sg:address":"116 N Chestnut Ave",
    "sg:city":"New Hampton",
    "sg:classifiers":[
        {
            "category":"Government",
            "subcategory":"Police Station",
            "type":"Public Place"
        }
    ],
    "sg:phone":"+1 641 394 3121",
    "sg:postcode":"50659",
    "sg:province":"IA",
    "sg:tags":[
        "sheriff"
    ],
    "wof:name":"Chickasaw County Sheriff",
    "wof:placetype":"venue"
},
  "geometry": {"coordinates":[-92.31540800000001,43.06038],"type":"Point"}
}