{
  "type": "Feature",
  "properties": {
    "addr:full":"114 E 5th St Storm Lake IA 50588",
    "addr:housenumber":"114",
    "addr:postcode":"50588",
    "addr:street":"E 5Th St",
    "iso:country":"US",
    "sg:address":"114 E 5th St",
    "sg:city":"Storm Lake",
    "sg:classifiers":[
        {
            "category":"Banks & Credit Unions",
            "subcategory":"Investment Brokerage",
            "type":"Services"
        }
    ],
    "sg:phone":"+1 712 732 9984",
    "sg:postcode":"50588",
    "sg:province":"IA",
    "sg:tags":[
        "security"
    ],
    "sg:website":"www.edwardjones.com",
    "wof:name":"Edward Jones Co",
    "wof:placetype":"venue"
},
  "geometry": {"coordinates":[-95.20075,42.644357],"type":"Point"}
}