{
  "type": "Feature",
  "properties": {
    "iso:country":"US",
    "sg:address":"375 S McCormack Ave",
    "sg:city":"Primghar",
    "sg:classifiers":[
        {
            "category":"Personal",
            "subcategory":"Beauty Salon",
            "type":"Services"
        }
    ],
    "sg:phone":"+1 712 957 1185",
    "sg:postcode":"51245",
    "sg:province":"IA",
    "wof:name":"Hair Corner",
    "wof:placetype":"venue"
},
  "geometry": {"coordinates":[-95.629447,43.084731],"type":"Point"}
}