{
  "type": "Feature",
  "properties": {
    "iso:country":"US",
    "sg:address":"2322 E Kimberly Rd",
    "sg:city":"Davenport",
    "sg:classifiers":[
        {
            "category":"Professional",
            "subcategory":"Lawyer & Legal Services",
            "type":"Services"
        }
    ],
    "sg:phone":"+1 563 359 3591",
    "sg:postcode":"52807",
    "sg:province":"IA",
    "sg:tags":[
        "attorney"
    ],
    "sg:website":"http://www.gomezmaylaw.com",
    "wof:name":"gomez may schutte yeggy bieber & wells",
    "wof:placetype":"venue"
},
  "geometry": {"coordinates":[-90.542952,41.556933],"type":"Point"}
}