{
  "type": "Feature",
  "properties": {
    "iso:country":"US",
    "sg:address":"24 1st St NW",
    "sg:city":"Hampton",
    "sg:classifiers":[
        {
            "category":"Restaurant",
            "type":"Food & Drink"
        }
    ],
    "sg:menulink":"http://www.allmenus.com/ia/hampton/69020-breadeaux-pizza/menu/",
    "sg:phone":"+1 641 456 5608",
    "sg:postcode":"50441",
    "sg:province":"IA",
    "sg:tags":[
        "american",
        "pizza"
    ],
    "wof:name":"Breadeaux Pizza",
    "wof:placetype":"venue"
},
  "geometry": {"coordinates":[-93.208814,42.742023],"type":"Point"}
}