{
  "type": "Feature",
  "properties": {
    "addr:full":"221 N 2nd Ave W Newton IA 50208",
    "addr:housenumber":"221",
    "addr:postcode":"50208",
    "addr:street":"N 2Nd Ave W",
    "iso:country":"US",
    "sg:address":"221 N 2nd Ave W",
    "sg:city":"Newton",
    "sg:classifiers":[
        {
            "category":"Manufacturing",
            "subcategory":"Tools & Machinery",
            "type":"Manufacturing & Wholesale Goods"
        }
    ],
    "sg:phone":"+1 641 792 7836",
    "sg:postcode":"50208",
    "sg:province":"IA",
    "sg:tags":[
        "engine",
        "internal",
        "combustion"
    ],
    "wof:name":"Parker Machine & Specialties",
    "wof:placetype":"venue"
},
  "geometry": {"coordinates":[-93.055099,41.700399],"type":"Point"}
}