{
  "type": "Feature",
  "properties": {
    "iso:country":"US",
    "sg:address":"701 Melrose Ave",
    "sg:city":"Iowa City",
    "sg:classifiers":[
        {
            "category":"Social Services",
            "subcategory":"Child Care",
            "type":"Services"
        }
    ],
    "sg:phone":"+1 319 338 1805",
    "sg:postcode":"52246",
    "sg:province":"IA",
    "sg:tags":[
        "kindergarten",
        "academic",
        "school"
    ],
    "wof:name":"Melrose Day Care Ctr",
    "wof:placetype":"venue"
},
  "geometry": {"coordinates":[-91.548773,41.656778],"type":"Point"}
}