{
  "type": "Feature",
  "properties": {
    "iso:country":"US",
    "sg:address":"10457 US Hwy 52",
    "sg:city":"Dubuque",
    "sg:classifiers":[
        {
            "category":"Home & Garden",
            "subcategory":"Furniture",
            "type":"Retail Goods"
        }
    ],
    "sg:phone":"+1 563 556 6064",
    "sg:postcode":"52001",
    "sg:province":"IA",
    "wof:name":"Minnesota Furniture",
    "wof:placetype":"venue"
},
  "geometry": {"coordinates":[-90.688292,42.534689],"type":"Point"}
}