{
  "type": "Feature",
  "properties": {
    "addr:full":"304 Main St Renwick IA 50577",
    "addr:housenumber":"304",
    "addr:postcode":"50577",
    "addr:street":"Main St",
    "iso:country":"US",
    "sg:address":"304 Main St",
    "sg:city":"Renwick",
    "sg:classifiers":[
        {
            "category":"Bars & Pubs",
            "type":"Food & Drink"
        }
    ],
    "sg:phone":"+1 515 824 3448",
    "sg:postcode":"50577",
    "sg:province":"IA",
    "wof:name":"Charlie's Bar",
    "wof:placetype":"venue"
},
  "geometry": {"coordinates":[-93.977205,42.82798],"type":"Point"}
}