{
  "type": "Feature",
  "properties": {
    "addr:full":"913 Giddings St Kelley IA 50134",
    "addr:housenumber":"913",
    "addr:postcode":"50134",
    "addr:street":"Giddings St",
    "iso:country":"US",
    "sg:address":"913 Giddings St",
    "sg:city":"Kelley",
    "sg:classifiers":[
        {
            "category":"Building & Trades",
            "subcategory":"Construction",
            "type":"Services"
        }
    ],
    "sg:phone":"+1 515 769 2212",
    "sg:postcode":"50134",
    "sg:province":"IA",
    "sg:tags":[
        "woodworker"
    ],
    "wof:name":"Falls Millwork",
    "wof:placetype":"venue"
},
  "geometry": {"coordinates":[-93.66394099999999,41.950494],"type":"Point"}
}