{
  "type": "Feature",
  "properties": {
    "addr:full":"1005 N 18th St Centerville IA 52544",
    "addr:housenumber":"1005",
    "addr:postcode":"52544",
    "addr:street":"N 18Th St",
    "iso:country":"US",
    "sg:address":"1005 N 18th St",
    "sg:city":"Centerville",
    "sg:classifiers":[
        {
            "category":"Restaurant",
            "type":"Food & Drink"
        }
    ],
    "sg:menulink":"http://www.allmenus.com/ia/centerville/73806-pizza-ranch/menu/",
    "sg:phone":"+1 641 856 3430",
    "sg:postcode":"52544",
    "sg:province":"IA",
    "sg:tags":[
        "american",
        "pizza"
    ],
    "wof:name":"Pizza Ranch",
    "wof:placetype":"venue"
},
  "geometry": {"coordinates":[-92.867976,40.740922],"type":"Point"}
}