{
  "type": "Feature",
  "properties": {
    "iso:country":"US",
    "sg:address":"2388 Oak Brook",
    "sg:city":"Denison",
    "sg:classifiers":[
        {
            "category":"Retail",
            "subcategory":"Portrait Studio",
            "type":"Services"
        }
    ],
    "sg:phone":"+1 712 263 4321",
    "sg:postcode":"51442",
    "sg:province":"IA",
    "sg:tags":[
        "photographer"
    ],
    "wof:name":"Brass Shutter Photography",
    "wof:placetype":"venue"
},
  "geometry": {"coordinates":[-95.31948199999999,42.012436],"type":"Point"}
}