{
  "type": "Feature",
  "properties": {
    "iso:country":"US",
    "sg:address":"27983 Garber Rd",
    "sg:city":"Garber",
    "sg:classifiers":[
        {
            "category":"Freight",
            "type":"Transportation"
        }
    ],
    "sg:phone":"+1 563 255 2721",
    "sg:postcode":"52048",
    "sg:province":"IA",
    "sg:tags":[
        "operator",
        "local",
        "trucking"
    ],
    "wof:name":"Bruce E Rodenberg",
    "wof:placetype":"venue"
},
  "geometry": {"coordinates":[-91.24726,42.755157],"type":"Point"}
}