{
  "type": "Feature",
  "properties": {
    "iso:country":"US",
    "sg:address":"2476 112th St",
    "sg:city":"Moscow",
    "sg:classifiers":[
        {
            "category":"Government",
            "subcategory":"Post Office",
            "type":"Public Place"
        }
    ],
    "sg:phone":"+1 563 724 3510",
    "sg:postcode":"52760",
    "sg:province":"IA",
    "wof:name":"US Post Office",
    "wof:placetype":"venue"
},
  "geometry": {"coordinates":[-91.067398,41.574],"type":"Point"}
}