{
  "type": "Feature",
  "properties": {
    "iso:country":"US",
    "sg:address":"1214 9th Ave",
    "sg:city":"Belle Plaine",
    "sg:classifiers":[
        {
            "category":"Education",
            "subcategory":"College",
            "type":"Public Place"
        }
    ],
    "sg:phone":"+1 319 444 2549",
    "sg:postcode":"52208",
    "sg:province":"IA",
    "sg:tags":[
        "academic",
        "school"
    ],
    "wof:name":"Kirkwood Community College",
    "wof:placetype":"venue"
},
  "geometry": {"coordinates":[-92.275023,41.896986],"type":"Point"}
}