{
  "type": "Feature",
  "properties": {
    "addr:full":"547 2nd St Webster City IA 50595",
    "addr:housenumber":"547",
    "addr:postcode":"50595",
    "addr:street":"2Nd St",
    "iso:country":"US",
    "sg:address":"547 2nd St",
    "sg:city":"Webster City",
    "sg:classifiers":[
        {
            "category":"Shopping",
            "subcategory":"Florist",
            "type":"Retail Goods"
        }
    ],
    "sg:phone":"+1 515 832 8800",
    "sg:postcode":"50595",
    "sg:province":"IA",
    "wof:name":"Wild Rose",
    "wof:placetype":"venue"
},
  "geometry": {"coordinates":[-93.818431,42.469497],"type":"Point"}
}