{
  "type": "Feature",
  "properties": {
    "iso:country":"US",
    "sg:address":"1016 S Gilbert Ct",
    "sg:city":"Iowa City",
    "sg:classifiers":[
        {
            "category":"Personal",
            "subcategory":"Beauty Salon",
            "type":"Services"
        }
    ],
    "sg:phone":"+1 319 351 9690",
    "sg:postcode":"52240",
    "sg:province":"IA",
    "sg:tags":[
        "shop"
    ],
    "wof:name":"Patty Bridgeforth",
    "wof:placetype":"venue"
},
  "geometry": {"coordinates":[-91.529736,41.648109],"type":"Point"}
}