{
  "type": "Feature",
  "properties": {
    "iso:country":"US",
    "sg:address":"1737 Cornwall Ave",
    "sg:city":"Waterloo",
    "sg:classifiers":[
        {
            "category":"Social Services",
            "subcategory":"Child Care",
            "type":"Services"
        }
    ],
    "sg:phone":"+1 319 833 0053",
    "sg:postcode":"50702",
    "sg:province":"IA",
    "wof:name":"Building Bright Beginnings",
    "wof:placetype":"venue"
},
  "geometry": {"coordinates":[-92.32827899999999,42.474882],"type":"Point"}
}