{
  "type": "Feature",
  "properties": {
    "addr:full":"901 2nd St Coralville IA 52241",
    "addr:housenumber":"901",
    "addr:postcode":"52241",
    "addr:street":"2Nd St",
    "iso:country":"US",
    "sg:address":"901 2nd St",
    "sg:city":"Coralville",
    "sg:classifiers":[
        {
            "category":"Organizations",
            "subcategory":"Community Association",
            "type":"Services"
        }
    ],
    "sg:phone":"+1 319 351 9937",
    "sg:postcode":"52241",
    "sg:province":"IA",
    "sg:tags":[
        "military"
    ],
    "wof:name":"American Legion",
    "wof:placetype":"venue"
},
  "geometry": {"coordinates":[-91.57497100000001,41.671813],"type":"Point"}
}