{
  "type": "Feature",
  "properties": {
    "iso:country":"US",
    "sg:address":"85 Jones St",
    "sg:city":"Dubuque",
    "sg:classifiers":[
        {
            "category":"Railroad",
            "type":"Transportation"
        }
    ],
    "sg:phone":"+1 563 582 5643",
    "sg:postcode":"52001",
    "sg:province":"IA",
    "wof:name":"Canadian National Railroad",
    "wof:placetype":"venue"
},
  "geometry": {"coordinates":[-90.658862,42.492867],"type":"Point"}
}