{
  "type": "Feature",
  "properties": {
    "iso:country":"US",
    "sg:address":"1603 110th Ave",
    "sg:city":"Algona",
    "sg:phone":"+1 515 295 7508",
    "sg:postcode":"50511",
    "sg:province":"IA",
    "sg:tags":[
        "hog",
        "farm",
        "corn",
        "soybean",
        "or",
        "feedlot"
    ],
    "wof:name":"Chuck Frideres",
    "wof:placetype":"venue"
},
  "geometry": {"coordinates":[-94.251791,42.996498],"type":"Point"}
}