{
  "type": "Feature",
  "properties": {
    "iso:country":"US",
    "sg:address":"1701 Indiana Ave",
    "sg:city":"Independence",
    "sg:classifiers":[
        {
            "category":"Freight",
            "type":"Transportation"
        }
    ],
    "sg:phone":"+1 319 334 3350",
    "sg:postcode":"50644",
    "sg:province":"IA",
    "sg:tags":[
        "trucking"
    ],
    "wof:name":"K & E Co Inc",
    "wof:placetype":"venue"
},
  "geometry": {"coordinates":[-91.92435399999999,42.540814],"type":"Point"}
}