{
  "type": "Feature",
  "properties": {
    "iso:country":"US",
    "sg:address":"307 W Pleasant St",
    "sg:city":"Maquoketa",
    "sg:classifiers":[
        {
            "category":"Insurance",
            "subcategory":"Insurance Agent",
            "type":"Services"
        }
    ],
    "sg:phone":"+1 563 652 2187",
    "sg:postcode":"52060",
    "sg:province":"IA",
    "sg:tags":[
        "merchandise"
    ],
    "wof:name":"Maquoketa Monuments",
    "wof:placetype":"venue"
},
  "geometry": {"coordinates":[-90.667947,42.067641],"type":"Point"}
}