{
  "type": "Feature",
  "properties": {
    "iso:country":"US",
    "sg:address":"209 S Locust St",
    "sg:city":"Monticello",
    "sg:classifiers":[
        {
            "category":"Professional",
            "type":"Services"
        }
    ],
    "sg:phone":"+1 319 437 3132",
    "sg:postcode":"52310",
    "sg:province":"IA",
    "wof:name":"Paula L Taylor",
    "wof:placetype":"venue"
},
  "geometry": {"coordinates":[-91.18309600000001,42.236592],"type":"Point"}
}