{
  "type": "Feature",
  "properties": {
    "iso:country":"US",
    "sg:address":"1340 W Airline Hwy",
    "sg:city":"Waterloo",
    "sg:classifiers":[
        {
            "category":"Professional",
            "subcategory":"Business Services",
            "type":"Services"
        }
    ],
    "sg:phone":"+1 319 235 1004",
    "sg:postcode":"50703",
    "sg:province":"IA",
    "sg:tags":[
        "paging",
        "answering"
    ],
    "wof:name":"MIDWEST Answering Svc",
    "wof:placetype":"venue"
},
  "geometry": {"coordinates":[-92.360668,42.542138],"type":"Point"}
}