{
  "type": "Feature",
  "properties": {
    "iso:country":"US",
    "sg:address":"103 Golf Course Dr",
    "sg:city":"Armstrong",
    "sg:classifiers":[
        {
            "category":"Transit Center",
            "subcategory":"Freight",
            "type":"Transportation"
        },
        {
            "category":"Freight",
            "type":"Transportation"
        }
    ],
    "sg:phone":"+1 712 868 3273",
    "sg:postcode":"50514",
    "sg:province":"IA",
    "sg:tags":[
        "local",
        "trucking-motor",
        "trucking"
    ],
    "wof:name":"D L M Trucking",
    "wof:placetype":"venue"
},
  "geometry": {"coordinates":[-94.477445,43.391375],"type":"Point"}
}