{
  "type": "Feature",
  "properties": {
    "iso:country":"US",
    "sg:address":"7209 Airline Ave",
    "sg:city":"Urbandale",
    "sg:classifiers":[
        {
            "category":"Personal",
            "type":"Services"
        }
    ],
    "sg:phone":"+1 515 251 8888",
    "sg:postcode":"50322",
    "sg:province":"IA",
    "sg:tags":[
        "program",
        "physical",
        "exercise",
        "fitness"
    ],
    "wof:name":"Jazzercise",
    "wof:placetype":"venue"
},
  "geometry": {"coordinates":[-93.718445,41.633048],"type":"Point"}
}