{
  "type": "Feature",
  "properties": {
    "addr:full":"2560 320th St Rockwell City IA 50579",
    "addr:housenumber":"2560",
    "addr:postcode":"50579",
    "addr:street":"320Th St",
    "iso:country":"US",
    "sg:address":"2560 320th St",
    "sg:city":"Rockwell City",
    "sg:phone":"+1 712 297 5085",
    "sg:postcode":"50579",
    "sg:province":"IA",
    "sg:tags":[
        "farm",
        "corn",
        "soybean"
    ],
    "wof:name":"Daniel Reynolds Farm",
    "wof:placetype":"venue"
},
  "geometry": {"coordinates":[-94.618706,42.32497],"type":"Point"}
}