{
  "type": "Feature",
  "properties": {
    "iso:country":"US",
    "sg:address":"6301 University Ave",
    "sg:city":"Cedar Falls",
    "sg:classifiers":[
        {
            "category":"Restaurant",
            "type":"Food & Drink"
        }
    ],
    "sg:phone":"+1 319 266 3200",
    "sg:postcode":"50613",
    "sg:province":"IA",
    "wof:name":"Texas Roadhouse",
    "wof:placetype":"venue"
},
  "geometry": {"coordinates":[-92.435509,42.512603],"type":"Point"}
}