{
  "type": "Feature",
  "properties": {
    "addr:full":"25291 Jade Ave Bloomfield IA 52537",
    "addr:housenumber":"25291",
    "addr:postcode":"52537",
    "addr:street":"Jade Ave",
    "iso:country":"US",
    "sg:address":"25291 Jade Ave",
    "sg:city":"Bloomfield",
    "sg:classifiers":[
        {
            "category":"Farming",
            "subcategory":"Farm",
            "type":"Manufacturing & Wholesale Goods"
        }
    ],
    "sg:phone":"+1 641 929 3249",
    "sg:postcode":"52537",
    "sg:province":"IA",
    "wof:name":"Dixon Farm",
    "wof:placetype":"venue"
},
  "geometry": {"coordinates":[-92.46579300000001,40.674501],"type":"Point"}
}