{
  "type": "Feature",
  "properties": {
    "iso:country":"US",
    "sg:address":"4071 555th Ave",
    "sg:city":"Whittemore",
    "sg:phone":"+1 515 884 2552",
    "sg:postcode":"50598",
    "sg:province":"IA",
    "sg:tags":[
        "farm",
        "corn",
        "soybean"
    ],
    "wof:name":"Robert Fuerstenau",
    "wof:placetype":"venue"
},
  "geometry": {"coordinates":[-94.49162,43.057062],"type":"Point"}
}