{
  "type": "Feature",
  "properties": {
    "iso:country":"US",
    "sg:address":"3083 Orchard Ave",
    "sg:city":"Ida Grove",
    "sg:phone":"+1 712 675 4203",
    "sg:postcode":"51445",
    "sg:province":"IA",
    "sg:tags":[
        "farm",
        "corn",
        "soybean"
    ],
    "wof:name":"Charles Rohlf",
    "wof:placetype":"venue"
},
  "geometry": {"coordinates":[-95.381518,42.256772],"type":"Point"}
}