{
  "type": "Feature",
  "properties": {
    "iso:country":"US",
    "sg:address":"1403 Kimberly Rd",
    "sg:city":"Bettendorf",
    "sg:classifiers":[
        {
            "category":"Shopping",
            "subcategory":"Clothing, Apparel, & Fashions",
            "type":"Retail Goods"
        }
    ],
    "sg:phone":"+1 563 359 5005",
    "sg:postcode":"52722",
    "sg:province":"IA",
    "sg:website":"www.maxineparrish.com",
    "wof:name":"MAXX Models & Talent",
    "wof:placetype":"venue"
},
  "geometry": {"coordinates":[-90.519558,41.533803],"type":"Point"}
}