{
  "type": "Feature",
  "properties": {
    "iso:country":"US",
    "sg:address":"112 S 2nd Ave",
    "sg:city":"Anthon",
    "sg:classifiers":[
        {
            "category":"Retail",
            "subcategory":"Veterinary Services",
            "type":"Services"
        }
    ],
    "sg:phone":"+1 712 373 5215",
    "sg:postcode":"51004",
    "sg:province":"IA",
    "sg:tags":[
        "veterinarian"
    ],
    "wof:name":"Four Rivers Veterinary Svc",
    "wof:placetype":"venue"
},
  "geometry": {"coordinates":[-95.86635,42.388152],"type":"Point"}
}