{
  "type": "Feature",
  "properties": {
    "iso:country":"US",
    "sg:address":"323 E 4th St",
    "sg:city":"Villisca",
    "sg:classifiers":[
        {
            "category":"Museum",
            "type":"Entertainment"
        }
    ],
    "sg:phone":"+1 712 826 2756",
    "sg:postcode":"50864",
    "sg:province":"IA",
    "sg:tags":[
        "gallery"
    ],
    "wof:name":"D & M Partners",
    "wof:placetype":"venue"
},
  "geometry": {"coordinates":[-94.976962,40.928586],"type":"Point"}
}