{
  "type": "Feature",
  "properties": {
    "iso:country":"US",
    "sg:address":"607 1st Ave",
    "sg:city":"Clarence",
    "sg:classifiers":[
        {
            "category":"Building & Trades",
            "subcategory":"Construction",
            "type":"Services"
        }
    ],
    "sg:phone":"+1 563 452 3633",
    "sg:postcode":"52216",
    "sg:province":"IA",
    "sg:tags":[
        "excavating",
        "contractor"
    ],
    "wof:name":"Wynkoop Equipment",
    "wof:placetype":"venue"
},
  "geometry": {"coordinates":[-91.06439,41.88294],"type":"Point"}
}