{
  "type": "Feature",
  "properties": {
    "addr:full":"331 11th St SW Spencer IA 51301",
    "addr:housenumber":"331",
    "addr:postcode":"51301",
    "addr:street":"11Th St Sw",
    "iso:country":"US",
    "sg:address":"331 11th St SW",
    "sg:city":"Spencer",
    "sg:classifiers":[
        {
            "category":"Restaurant",
            "type":"Food & Drink"
        }
    ],
    "sg:phone":"+1 712 262 7690",
    "sg:postcode":"51301",
    "sg:province":"IA",
    "wof:name":"Cindy's Steak House",
    "wof:placetype":"venue"
},
  "geometry": {"coordinates":[-95.148624,43.126744],"type":"Point"}
}