{
  "type": "Feature",
  "properties": {
    "iso:country":"US",
    "sg:address":"121 W Washington St",
    "sg:city":"Washington",
    "sg:classifiers":[
        {
            "category":"Shopping",
            "subcategory":"Used Merchandise",
            "type":"Retail Goods"
        }
    ],
    "sg:phone":"+1 319 653 2928",
    "sg:postcode":"52353",
    "sg:province":"IA",
    "sg:tags":[
        "clothing"
    ],
    "wof:name":"Once More Store",
    "wof:placetype":"venue"
},
  "geometry": {"coordinates":[-91.69273099999999,41.298301],"type":"Point"}
}