{
  "type": "Feature",
  "properties": {
    "iso:country":"US",
    "sg:address":"1401 SE 60th St",
    "sg:city":"Des Moines",
    "sg:classifiers":[
        {
            "category":"Building & Trades",
            "subcategory":"Construction",
            "type":"Services"
        }
    ],
    "sg:phone":"+1 515 266 7407",
    "sg:postcode":"50327",
    "sg:province":"IA",
    "sg:tags":[
        "house"
    ],
    "wof:name":"Bills Custom Homes",
    "wof:placetype":"venue"
},
  "geometry": {"coordinates":[-93.49136300000001,41.579356],"type":"Point"}
}