{
  "type": "Feature",
  "properties": {
    "iso:country":"US",
    "sg:address":"1814 Foster St",
    "sg:city":"Muscatine",
    "sg:classifiers":[
        {
            "category":"Building & Trades",
            "subcategory":"Electrical",
            "type":"Services"
        }
    ],
    "sg:phone":"+1 563 263 4095",
    "sg:postcode":"52761",
    "sg:province":"IA",
    "sg:tags":[
        "electric",
        "contractor"
    ],
    "wof:name":"Ash Electric",
    "wof:placetype":"venue"
},
  "geometry": {"coordinates":[-91.061665,41.431879],"type":"Point"}
}