{
  "type": "Feature",
  "properties": {
    "iso:country":"US",
    "sg:address":"103 W Hwy 30",
    "sg:city":"Toledo",
    "sg:classifiers":[
        {
            "category":"Autos & Motor Vehicles",
            "subcategory":"Automobile Sales",
            "type":"Retail Goods"
        }
    ],
    "sg:phone":"+1 641 484 5432",
    "sg:postcode":"52342",
    "sg:province":"IA",
    "sg:tags":[
        "used"
    ],
    "wof:name":"Brown & Son Auto",
    "wof:placetype":"venue"
},
  "geometry": {"coordinates":[-92.579911,41.986118],"type":"Point"}
}