{
  "type": "Feature",
  "properties": {
    "iso:country":"US",
    "sg:address":"2509 Correctionville Rd",
    "sg:city":"Sioux City",
    "sg:classifiers":[
        {
            "category":"Personal",
            "subcategory":"Barber",
            "type":"Services"
        }
    ],
    "sg:phone":"+1 712 277 3179",
    "sg:postcode":"51106",
    "sg:province":"SD",
    "sg:tags":[
        "shop"
    ],
    "wof:name":"Dale's Barber Shop",
    "wof:placetype":"venue"
},
  "geometry": {"coordinates":[-96.375997,42.490313],"type":"Point"}
}