{
  "type": "Feature",
  "properties": {
    "addr:full":"2000 E Euclid Ave Des Moines IA 50317",
    "addr:housenumber":"2000",
    "addr:postcode":"50317",
    "addr:street":"E Euclid Ave",
    "iso:country":"US",
    "sg:address":"2000 E Euclid Ave",
    "sg:city":"Des Moines",
    "sg:classifiers":[
        {
            "category":"Retail",
            "subcategory":"Auto Rental",
            "type":"Services"
        }
    ],
    "sg:phone":"+1 515 245 2626",
    "sg:postcode":"50317",
    "sg:province":"IA",
    "sg:tags":[
        "renting",
        "truck",
        "leasing"
    ],
    "wof:name":"Ruan Leasing Co",
    "wof:placetype":"venue"
},
  "geometry": {"coordinates":[-93.58140899999999,41.627756],"type":"Point"}
}