{
  "type": "Feature",
  "properties": {
    "iso:country":"US",
    "sg:address":"1416 W 16th St",
    "sg:city":"Davenport",
    "sg:classifiers":[
        {
            "category":"Freight",
            "type":"Transportation"
        }
    ],
    "sg:phone":"+1 563 323 0857",
    "sg:postcode":"52804",
    "sg:province":"IA",
    "sg:tags":[
        "trucking"
    ],
    "wof:name":"Hill & Hill Trucking",
    "wof:placetype":"venue"
},
  "geometry": {"coordinates":[-90.59595400000001,41.535903],"type":"Point"}
}