{
  "type": "Feature",
  "properties": {
    "iso:country":"US",
    "sg:address":"494 180th Ave",
    "sg:city":"Carlisle",
    "sg:classifiers":[
        {
            "category":"Building & Trades",
            "subcategory":"Construction",
            "type":"Services"
        }
    ],
    "sg:phone":"+1 515 989 5248",
    "sg:postcode":"50047",
    "sg:province":"IA",
    "sg:tags":[
        "contractor"
    ],
    "wof:name":"ABC Plastering",
    "wof:placetype":"venue"
},
  "geometry": {"coordinates":[-93.46226,41.449897],"type":"Point"}
}