{
  "type": "Feature",
  "properties": {
    "iso:country":"US",
    "sg:address":"822 Harrison Ave",
    "sg:city":"Burlington",
    "sg:classifiers":[
        {
            "category":"Insurance",
            "subcategory":"Insurance Agent",
            "type":"Services"
        }
    ],
    "sg:phone":"+1 319 752 7470",
    "sg:postcode":"52601",
    "sg:province":"IA",
    "wof:name":"Mutual Of Omaha Insurance Co",
    "wof:placetype":"venue"
},
  "geometry": {"coordinates":[-91.10718799999999,40.789227],"type":"Point"}
}