{
  "type": "Feature",
  "properties": {
    "iso:country":"US",
    "sg:address":"5818 Nordic Dr",
    "sg:city":"Cedar Falls",
    "sg:classifiers":[
        {
            "category":"Travel",
            "subcategory":"Hotels & Motels",
            "type":"Entertainment"
        }
    ],
    "sg:phone":"+1 319 277 6166",
    "sg:postcode":"50613",
    "sg:province":"IA",
    "wof:name":"Americinn Lodge & Suites",
    "wof:placetype":"venue"
},
  "geometry": {"coordinates":[-92.448716,42.487462],"type":"Point"}
}