{
  "type": "Feature",
  "properties": {
    "addr:full":"1310 Locust St Des Moines IA 50309",
    "addr:housenumber":"1310",
    "addr:postcode":"50309",
    "addr:street":"Locust St",
    "iso:country":"US",
    "sg:address":"1310 Locust St",
    "sg:city":"Des Moines",
    "sg:classifiers":[
        {
            "category":"Manufacturing",
            "subcategory":"Retail Goods",
            "type":"Manufacturing & Wholesale Goods"
        }
    ],
    "sg:phone":"+1 515 286 4633",
    "sg:postcode":"50309",
    "sg:province":"IA",
    "sg:tags":[
        "manufacturer"
    ],
    "wof:name":"Metro Glass & Mfg",
    "wof:placetype":"venue"
},
  "geometry": {"coordinates":[-93.634882,41.584649],"type":"Point"}
}