{
  "type": "Feature",
  "properties": {
    "addr:full":"4 Madison St Rock Falls IA 50467",
    "addr:housenumber":"4",
    "addr:postcode":"50467",
    "addr:street":"Madison St",
    "iso:country":"US",
    "sg:address":"4 Madison St",
    "sg:city":"Rock Falls",
    "sg:classifiers":[
        {
            "category":"Retail",
            "subcategory":"Auto Repair",
            "type":"Services"
        }
    ],
    "sg:phone":"+1 641 696 5663",
    "sg:postcode":"50467",
    "sg:province":"IA",
    "sg:tags":[
        "transmission"
    ],
    "wof:name":"Brosz Transmissions",
    "wof:placetype":"venue"
},
  "geometry": {"coordinates":[-93.083938,43.208261],"type":"Point"}
}