{
  "type": "Feature",
  "properties": {
    "addr:full":"148 Watson Rd Monona IA 52159",
    "addr:housenumber":"148",
    "addr:postcode":"52159",
    "addr:street":"Watson Rd",
    "iso:country":"US",
    "sg:address":"148 Watson Rd",
    "sg:city":"Monona",
    "sg:classifiers":[
        {
            "category":"Farming",
            "subcategory":"Farm",
            "type":"Manufacturing & Wholesale Goods"
        }
    ],
    "sg:phone":"+1 563 539 4723",
    "sg:postcode":"52159",
    "sg:province":"IA",
    "sg:tags":[
        "crop",
        "general"
    ],
    "wof:name":"J Ruff",
    "wof:placetype":"venue"
},
  "geometry": {"coordinates":[-91.325417,43.092988],"type":"Point"}
}