{
  "type": "Feature",
  "properties": {
    "iso:country":"US",
    "sg:address":"115 E Delaware St",
    "sg:city":"Manchester",
    "sg:classifiers":[
        {
            "category":"Insurance",
            "subcategory":"Insurance Agent",
            "type":"Services"
        }
    ],
    "sg:phone":"+1 563 927 3816",
    "sg:postcode":"52057",
    "sg:province":"IA",
    "wof:name":"Farm Bureau Insurance",
    "wof:placetype":"venue"
},
  "geometry": {"coordinates":[-91.45775399999999,42.482985],"type":"Point"}
}