{
  "type": "Feature",
  "properties": {
    "iso:country":"US",
    "sg:address":"3120 Cedar Cross Ct",
    "sg:city":"Dubuque",
    "sg:classifiers":[
        {
            "category":"Home & Garden",
            "subcategory":"Carpets & Floor Coverings",
            "type":"Retail Goods"
        }
    ],
    "sg:phone":"+1 563 582 5777",
    "sg:postcode":"52003",
    "sg:province":"IA",
    "sg:tags":[
        "dealer",
        "rug"
    ],
    "wof:name":"Mel's Carpet Outlet",
    "wof:placetype":"venue"
},
  "geometry": {"coordinates":[-90.71168299999999,42.481415],"type":"Point"}
}