{
  "type": "Feature",
  "properties": {
    "iso:country":"US",
    "sg:address":"225 N 8th Ave",
    "sg:city":"Sheldon",
    "sg:phone":"+1 712 324 4057",
    "sg:postcode":"51201",
    "sg:province":"IA",
    "sg:tags":[
        "farm",
        "corn"
    ],
    "wof:name":"Harold Sterk",
    "wof:placetype":"venue"
},
  "geometry": {"coordinates":[-95.846084,43.188375],"type":"Point"}
}