{
  "type": "Feature",
  "properties": {
    "addr:full":"134 W Main St Fredericksburg IA 50630",
    "addr:housenumber":"134",
    "addr:postcode":"50630",
    "addr:street":"W Main St",
    "iso:country":"US",
    "sg:address":"134 W Main St",
    "sg:city":"Fredericksburg",
    "sg:classifiers":[
        {
            "category":"Insurance",
            "subcategory":"Insurance Agent",
            "type":"Services"
        }
    ],
    "sg:phone":"+1 563 237 5349",
    "sg:postcode":"50630",
    "sg:province":"IA",
    "wof:name":"Insurance Center",
    "wof:placetype":"venue"
},
  "geometry": {"coordinates":[-92.199597,42.965069],"type":"Point"}
}