{
  "type": "Feature",
  "properties": {
    "iso:country":"US",
    "sg:address":"1600 Court Ave",
    "sg:city":"Chariton",
    "sg:classifiers":[
        {
            "category":"Ice Cream",
            "type":"Food & Drink"
        }
    ],
    "sg:menulink":"http://www.allmenus.com/ia/chariton/172730-dairy-queen/menu/",
    "sg:phone":"+1 641 774 5221",
    "sg:postcode":"50049",
    "sg:province":"IA",
    "sg:tags":[
        "burger",
        "american"
    ],
    "wof:name":"Dairy Queen",
    "wof:placetype":"venue"
},
  "geometry": {"coordinates":[-93.319329,41.014526],"type":"Point"}
}