{
  "type": "Feature",
  "properties": {
    "addr:full":"1115 235th St Wheatland IA 52777",
    "addr:housenumber":"1115",
    "addr:postcode":"52777",
    "addr:street":"235Th St",
    "iso:country":"US",
    "sg:address":"1115 235th St",
    "sg:city":"Wheatland",
    "sg:phone":"+1 563 374 1883",
    "sg:postcode":"52777",
    "sg:province":"IA",
    "sg:tags":[
        "farm",
        "soybean"
    ],
    "wof:name":"Ronald Wenndt",
    "wof:placetype":"venue"
},
  "geometry": {"coordinates":[-90.876564,41.84418],"type":"Point"}
}