{
  "type": "Feature",
  "properties": {
    "iso:country":"US",
    "sg:address":"14050 70th St",
    "sg:city":"Wapello",
    "sg:classifiers":[
        {
            "category":"Manufacturing",
            "subcategory":"Retail Goods",
            "type":"Manufacturing & Wholesale Goods"
        }
    ],
    "sg:phone":"+1 319 523 8191",
    "sg:postcode":"52653",
    "sg:province":"IA",
    "sg:tags":[
        "manufacturer"
    ],
    "wof:name":"S & J Tube Mfg",
    "wof:placetype":"venue"
},
  "geometry": {"coordinates":[-91.19783099999999,41.169488],"type":"Point"}
}