{
  "type": "Feature",
  "properties": {
    "iso:country":"US",
    "sg:address":"4043 120th St",
    "sg:city":"Urbandale",
    "sg:classifiers":[
        {
            "category":"Manufacturing",
            "subcategory":"Furniture",
            "type":"Manufacturing & Wholesale Goods"
        }
    ],
    "sg:phone":"+1 515 276 9900",
    "sg:postcode":"50323",
    "sg:province":"IA",
    "wof:name":"OSE Office Furniture",
    "wof:placetype":"venue"
},
  "geometry": {"coordinates":[-93.779067,41.634799],"type":"Point"}
}