{
  "type": "Feature",
  "properties": {
    "addr:full":"104 Elm Ave NW Mitchellville IA 50169",
    "addr:housenumber":"104",
    "addr:postcode":"50169",
    "addr:street":"Elm Ave Nw Mitchellville",
    "iso:country":"US",
    "sg:address":"104 Elm Ave NW",
    "sg:city":"Mitchellville",
    "sg:classifiers":[
        {
            "category":"Building & Trades",
            "subcategory":"Construction",
            "type":"Services"
        }
    ],
    "sg:phone":"+1 515 957 0944",
    "sg:postcode":"50169",
    "sg:province":"IA",
    "sg:tags":[
        "house"
    ],
    "wof:name":"Underwood Construction",
    "wof:placetype":"venue"
},
  "geometry": {"coordinates":[-93.362781,41.667474],"type":"Point"}
}