{
  "type": "Feature",
  "properties": {
    "addr:full":"105 E Walnut St Ogden IA 50212",
    "addr:housenumber":"105",
    "addr:postcode":"50212",
    "addr:street":"E Walnut St",
    "iso:country":"US",
    "sg:address":"105 E Walnut St",
    "sg:city":"Ogden",
    "sg:classifiers":[
        {
            "category":"Retail",
            "subcategory":"Auto Repair",
            "type":"Services"
        }
    ],
    "sg:phone":"+1 515 275 2961",
    "sg:postcode":"50212",
    "sg:province":"IA",
    "sg:tags":[
        "repairing",
        "automobile"
    ],
    "wof:name":"Ahren's Service",
    "wof:placetype":"venue"
},
  "geometry": {"coordinates":[-94.02720600000001,42.039129],"type":"Point"}
}