{
  "type": "Feature",
  "properties": {
    "iso:country":"US",
    "sg:address":"401 Moorehead St",
    "sg:city":"Ida Grove",
    "sg:classifiers":[
        {
            "category":"Government",
            "subcategory":"Office",
            "type":"Public Place"
        }
    ],
    "sg:phone":"+1 712 364 4176",
    "sg:postcode":"51445",
    "sg:province":"IA",
    "sg:tags":[
        "county",
        "affairs",
        "admin"
    ],
    "wof:name":"Ida County Veterans Affairs",
    "wof:placetype":"venue"
},
  "geometry": {"coordinates":[-95.468487,42.342624],"type":"Point"}
}