{
  "type": "Feature",
  "properties": {
    "addr:full":"43 W Main St Waukon IA 52172",
    "addr:housenumber":"43",
    "addr:postcode":"52172",
    "addr:street":"W Main St",
    "iso:country":"US",
    "sg:address":"43 W Main St",
    "sg:city":"Waukon",
    "sg:classifiers":[
        {
            "category":"Home & Garden",
            "subcategory":"Hardware",
            "type":"Retail Goods"
        }
    ],
    "sg:phone":"+1 563 568 4553",
    "sg:postcode":"52172",
    "sg:province":"IA",
    "wof:name":"Cunningham Hardware/Rental",
    "wof:placetype":"venue"
},
  "geometry": {"coordinates":[-91.475442,43.269359],"type":"Point"}
}