{
  "type": "Feature",
  "properties": {
    "iso:country":"US",
    "sg:address":"315 N Main St",
    "sg:city":"Sigourney",
    "sg:classifiers":[
        {
            "category":"Shopping",
            "subcategory":"Department Store",
            "type":"Retail Goods"
        }
    ],
    "sg:phone":"+1 641 622 2454",
    "sg:postcode":"52591",
    "sg:province":"IA",
    "sg:tags":[
        "shop"
    ],
    "wof:name":"Dollar General",
    "wof:placetype":"venue"
},
  "geometry": {"coordinates":[-92.205116,41.336274],"type":"Point"}
}