{
  "type": "Feature",
  "properties": {
    "iso:country":"US",
    "sg:address":"2514 175th St",
    "sg:city":"Calmar",
    "sg:classifiers":[
        {
            "category":"Farming",
            "subcategory":"Livestock Farm",
            "type":"Manufacturing & Wholesale Goods"
        }
    ],
    "sg:phone":"+1 563 562 3768",
    "sg:postcode":"52132",
    "sg:province":"IA",
    "sg:tags":[
        "beef",
        "feedlot",
        "cattle"
    ],
    "wof:name":"Ruth Boe",
    "wof:placetype":"venue"
},
  "geometry": {"coordinates":[-91.883017,43.190556],"type":"Point"}
}