{
  "type": "Feature",
  "properties": {
    "iso:country":"US",
    "sg:address":"127 N Main St",
    "sg:city":"Elkader",
    "sg:classifiers":[
        {
            "category":"Restaurant",
            "type":"Food & Drink"
        }
    ],
    "sg:phone":"+1 563 245 2414",
    "sg:postcode":"52043",
    "sg:province":"IA",
    "wof:name":"Pizza Well",
    "wof:placetype":"venue"
},
  "geometry": {"coordinates":[-91.405078,42.855036],"type":"Point"}
}