{
  "type": "Feature",
  "properties": {
    "addr:full":"2211 College St Cedar Falls IA 50613",
    "addr:housenumber":"2211",
    "addr:postcode":"50613",
    "addr:street":"College St",
    "iso:country":"US",
    "sg:address":"2211 College St",
    "sg:city":"Cedar Falls",
    "sg:classifiers":[
        {
            "category":"Personal",
            "subcategory":"Beauty Salon",
            "type":"Services"
        }
    ],
    "sg:phone":"+1 319 268 1682",
    "sg:postcode":"50613",
    "sg:province":"IA",
    "wof:name":"Razor's Edge Hairstyling",
    "wof:placetype":"venue"
},
  "geometry": {"coordinates":[-92.45582,42.51692],"type":"Point"}
}