{
  "type": "Feature",
  "properties": {
    "addr:full":"418 W Main St La Porte City IA 50651",
    "addr:housenumber":"418",
    "addr:postcode":"50651",
    "addr:street":"W Main St",
    "iso:country":"US",
    "sg:address":"418 W Main St",
    "sg:city":"La Porte City",
    "sg:phone":"+1 319 342 2790",
    "sg:postcode":"50651",
    "sg:province":"IA",
    "sg:tags":[
        "farm",
        "grain",
        "chicken",
        "egg",
        "cash"
    ],
    "wof:name":"Generation Acres",
    "wof:placetype":"venue"
},
  "geometry": {"coordinates":[-92.20079800000001,42.321809],"type":"Point"}
}