{
  "type": "Feature",
  "properties": {
    "addr:full":"210 N Egbert St Monona IA 52159",
    "addr:housenumber":"210",
    "addr:postcode":"52159",
    "addr:street":"N Egbert St",
    "iso:country":"US",
    "sg:address":"210 N Egbert St",
    "sg:city":"Monona",
    "sg:classifiers":[
        {
            "category":"Museum",
            "type":"Entertainment"
        }
    ],
    "sg:phone":"+1 563 539 8083",
    "sg:postcode":"52159",
    "sg:province":"IA",
    "wof:name":"Monona Historical Society",
    "wof:placetype":"venue"
},
  "geometry": {"coordinates":[-91.388662,43.056616],"type":"Point"}
}