{
  "type": "Feature",
  "properties": {
    "addr:full":"301 5th St N Springville IA 52336",
    "addr:housenumber":"301",
    "addr:postcode":"52336",
    "addr:street":"5Th St N",
    "iso:country":"US",
    "sg:address":"301 5th St N",
    "sg:city":"Springville",
    "sg:classifiers":[
        {
            "category":"Manufacturing",
            "subcategory":"Glass & Minerals",
            "type":"Manufacturing & Wholesale Goods"
        }
    ],
    "sg:phone":"+1 319 854 7415",
    "sg:postcode":"52336",
    "sg:province":"IA",
    "sg:tags":[
        "ready"
    ],
    "wof:name":"Springville Ready Mix Co",
    "wof:placetype":"venue"
},
  "geometry": {"coordinates":[-91.445849,42.060947],"type":"Point"}
}