{
  "type": "Feature",
  "properties": {
    "iso:country":"US",
    "sg:address":"106 N 4th St",
    "sg:city":"Fairfield",
    "sg:classifiers":[
        {
            "category":"Retail",
            "subcategory":"Auto Repair",
            "type":"Services"
        }
    ],
    "sg:phone":"+1 641 472 9811",
    "sg:postcode":"52556",
    "sg:province":"IA",
    "sg:tags":[
        "muffler",
        "exhaust",
        "system"
    ],
    "wof:name":"Palmer Muffler",
    "wof:placetype":"venue"
},
  "geometry": {"coordinates":[-91.96804299999999,41.008081],"type":"Point"}
}