{
  "type": "Feature",
  "properties": {
    "iso:country":"US",
    "sg:address":"745 Pepper Dr",
    "sg:city":"Iowa City",
    "sg:classifiers":[
        {
            "category":"Social Services",
            "type":"Services"
        }
    ],
    "sg:phone":"+1 319 341 9849",
    "sg:postcode":"52240",
    "sg:province":"IA",
    "sg:tags":[
        "organization",
        "welfare"
    ],
    "wof:name":"Hillcrest Birch House",
    "wof:placetype":"venue"
},
  "geometry": {"coordinates":[-91.52565,41.635994],"type":"Point"}
}