{
  "type": "Feature",
  "properties": {
    "iso:country":"US",
    "sg:address":"800 N 8th St",
    "sg:city":"Clear Lake",
    "sg:classifiers":[
        {
            "category":"Insurance",
            "subcategory":"Insurance Agent",
            "type":"Services"
        }
    ],
    "sg:phone":"+1 641 357 4420",
    "sg:postcode":"50428",
    "sg:province":"IA",
    "wof:name":"Dennis M Stephens & Assoc",
    "wof:placetype":"venue"
},
  "geometry": {"coordinates":[-93.378816,43.142776],"type":"Point"}
}