{
  "type": "Feature",
  "properties": {
    "iso:country":"US",
    "sg:address":"15053 Rosewood Dr",
    "sg:city":"Clive",
    "sg:classifiers":[
        {
            "category":"Professional",
            "subcategory":"Business Services",
            "type":"Services"
        }
    ],
    "sg:phone":"+1 515 778 0292",
    "sg:postcode":"50325",
    "sg:province":"IA",
    "wof:name":"Financially Speaking Inc",
    "wof:placetype":"venue"
},
  "geometry": {"coordinates":[-93.829323,41.611068],"type":"Point"}
}