{
  "type": "Feature",
  "properties": {
    "addr:full":"1009 2nd St Coralville IA 52241",
    "addr:housenumber":"1009",
    "addr:postcode":"52241",
    "addr:street":"2Nd St",
    "iso:country":"US",
    "sg:address":"1009 2nd St",
    "sg:city":"Coralville",
    "sg:classifiers":[
        {
            "category":"Banks & Credit Unions",
            "subcategory":"Bank",
            "type":"Services"
        }
    ],
    "sg:phone":"+1 319 351 8000",
    "sg:postcode":"52241",
    "sg:province":"IA",
    "sg:website":"www.hillsbank.com",
    "wof:name":"Hills Bank & Trust Co",
    "wof:placetype":"venue"
},
  "geometry": {"coordinates":[-91.58157199999999,41.674486],"type":"Point"}
}