{
  "type": "Feature",
  "properties": {
    "iso:country":"US",
    "sg:address":"1420 W 1st St",
    "sg:city":"Cedar Falls",
    "sg:classifiers":[
        {
            "category":"Shopping",
            "subcategory":"Music",
            "type":"Retail Goods"
        }
    ],
    "sg:phone":"+1 319 277 7222",
    "sg:postcode":"50613",
    "sg:province":"IA",
    "sg:tags":[
        "compact",
        "record",
        "disc",
        "tape"
    ],
    "wof:name":"Music Station",
    "wof:placetype":"venue"
},
  "geometry": {"coordinates":[-92.462969,42.537775],"type":"Point"}
}