{
  "type": "Feature",
  "properties": {
    "iso:country":"US",
    "sg:address":"4903 Asbury Rd",
    "sg:city":"Dubuque",
    "sg:classifiers":[
        {
            "category":"Building & Trades",
            "subcategory":"Construction",
            "type":"Services"
        }
    ],
    "sg:phone":"+1 563 556 6121",
    "sg:postcode":"52002",
    "sg:province":"IA",
    "sg:tags":[
        "house"
    ],
    "wof:name":"First Choice Construction",
    "wof:placetype":"venue"
},
  "geometry": {"coordinates":[-90.75015399999999,42.514592],"type":"Point"}
}