{
  "type": "Feature",
  "properties": {
    "iso:country":"US",
    "sg:address":"4900 Council St NE",
    "sg:city":"Cedar Rapids",
    "sg:classifiers":[
        {
            "category":"Government",
            "subcategory":"Office",
            "type":"Public Place"
        }
    ],
    "sg:phone":"+1 319 286 5762",
    "sg:postcode":"52402",
    "sg:province":"IA",
    "sg:tags":[
        "conservation"
    ],
    "wof:name":"Parks Dept Noelridge Pk Grnhse",
    "wof:placetype":"venue"
},
  "geometry": {"coordinates":[-91.65828399999999,42.028577],"type":"Point"}
}