{
  "type": "Feature",
  "properties": {
    "iso:country":"US",
    "sg:address":"2100 5th Ave S",
    "sg:city":"Fort Dodge",
    "sg:classifiers":[
        {
            "category":"Autos & Motor Vehicles",
            "subcategory":"Automobile Sales",
            "type":"Retail Goods"
        }
    ],
    "sg:phone":"+1 515 955 1476",
    "sg:postcode":"50501",
    "sg:province":"IA",
    "sg:tags":[
        "car",
        "dealer"
    ],
    "wof:name":"Crimmins Corp",
    "wof:placetype":"venue"
},
  "geometry": {"coordinates":[-94.16934999999999,42.501163],"type":"Point"}
}