{
  "type": "Feature",
  "properties": {
    "iso:country":"US",
    "sg:address":"2163 N Fork Dr",
    "sg:city":"Fort Madison",
    "sg:classifiers":[
        {
            "category":"Building & Trades",
            "subcategory":"Construction",
            "type":"Services"
        }
    ],
    "sg:phone":"+1 319 372 6929",
    "sg:postcode":"52627",
    "sg:province":"IA",
    "sg:tags":[
        "painter"
    ],
    "wof:name":"Rung & Hundt Painting & Dcrtng",
    "wof:placetype":"venue"
},
  "geometry": {"coordinates":[-91.286891,40.64455],"type":"Point"}
}