{
  "type": "Feature",
  "properties": {
    "iso:country":"US",
    "sg:address":"507 17th St",
    "sg:city":"Belle Plaine",
    "sg:classifiers":[
        {
            "category":"Freight",
            "type":"Transportation"
        }
    ],
    "sg:phone":"+1 319 434 6460",
    "sg:postcode":"52208",
    "sg:province":"IA",
    "sg:tags":[
        "hauling",
        "trucking"
    ],
    "wof:name":"TKL Trucking",
    "wof:placetype":"venue"
},
  "geometry": {"coordinates":[-92.278628,41.901963],"type":"Point"}
}