{
  "type": "Feature",
  "properties": {
    "iso:country":"US",
    "sg:address":"1880 Kountry Ln",
    "sg:city":"Fort Dodge",
    "sg:classifiers":[
        {
            "category":"Retail",
            "subcategory":"Auto Repair",
            "type":"Services"
        }
    ],
    "sg:phone":"+1 515 955 4437",
    "sg:postcode":"50501",
    "sg:province":"IA",
    "sg:tags":[
        "truck"
    ],
    "wof:name":"Bennett Truck Svc",
    "wof:placetype":"venue"
},
  "geometry": {"coordinates":[-94.226766,42.516523],"type":"Point"}
}