{
  "type": "Feature",
  "properties": {
    "iso:country":"US",
    "sg:address":"217 N 14th St",
    "sg:city":"Denison",
    "sg:phone":"+1 712 263 5569",
    "sg:postcode":"51442",
    "sg:province":"IA",
    "sg:tags":[
        "farm",
        "corn",
        "soybean"
    ],
    "wof:name":"Ken Schurke",
    "wof:placetype":"venue"
},
  "geometry": {"coordinates":[-95.35285399999999,42.019194],"type":"Point"}
}