{
  "type": "Feature",
  "properties": {
    "iso:country":"US",
    "sg:address":"6603 NW 6th Dr",
    "sg:city":"Des Moines",
    "sg:classifiers":[
        {
            "category":"Retail",
            "subcategory":"Auto Repair",
            "type":"Services"
        }
    ],
    "sg:phone":"+1 515 289 1841",
    "sg:postcode":"50313",
    "sg:province":"IA",
    "sg:tags":[
        "repairing",
        "automobile"
    ],
    "wof:name":"L & S Auto Repair",
    "wof:placetype":"venue"
},
  "geometry": {"coordinates":[-93.62955599999999,41.680362],"type":"Point"}
}