{
  "type": "Feature",
  "properties": {
    "iso:country":"US",
    "sg:address":"104 W Paton St",
    "sg:city":"Paton",
    "sg:classifiers":[
        {
            "category":"Manufacturing",
            "subcategory":"Tools & Machinery",
            "type":"Manufacturing & Wholesale Goods"
        }
    ],
    "sg:phone":"+1 515 968 4180",
    "sg:postcode":"50217",
    "sg:province":"IA",
    "sg:tags":[
        "equipment",
        "handling",
        "grain"
    ],
    "wof:name":"Quad County Ag Svc",
    "wof:placetype":"venue"
},
  "geometry": {"coordinates":[-94.25423000000001,42.166277],"type":"Point"}
}