{
  "type": "Feature",
  "properties": {
    "iso:country":"US",
    "sg:address":"1904 280th St",
    "sg:city":"Bedford",
    "sg:classifiers":[
        {
            "category":"Farming",
            "subcategory":"Farm",
            "type":"Manufacturing & Wholesale Goods"
        }
    ],
    "sg:phone":"+1 712 523 2026",
    "sg:postcode":"50833",
    "sg:province":"IA",
    "sg:tags":[
        "crop",
        "general"
    ],
    "wof:name":"Max A Park",
    "wof:placetype":"venue"
},
  "geometry": {"coordinates":[-94.76338800000001,40.649693],"type":"Point"}
}