{
  "type": "Feature",
  "properties": {
    "iso:country":"US",
    "sg:address":"3050 English Glen Ct",
    "sg:city":"Marion",
    "sg:classifiers":[
        {
            "category":"Building & Trades",
            "subcategory":"Construction",
            "type":"Services"
        }
    ],
    "sg:phone":"+1 319 373 0238",
    "sg:postcode":"52302",
    "sg:province":"IA",
    "sg:tags":[
        "builder",
        "patio",
        "deck"
    ],
    "wof:name":"Deck Hands Inc",
    "wof:placetype":"venue"
},
  "geometry": {"coordinates":[-91.57458,42.051695],"type":"Point"}
}