{
  "type": "Feature",
  "properties": {
    "addr:full":"317 8th St SW Altoona IA 50009",
    "addr:housenumber":"317",
    "addr:postcode":"50009",
    "addr:street":"8Th St Sw",
    "iso:country":"US",
    "sg:address":"317 8th St SW",
    "sg:city":"Altoona",
    "sg:classifiers":[
        {
            "category":"Professional",
            "subcategory":"Accounting & Tax Preparation",
            "type":"Services"
        }
    ],
    "sg:phone":"+1 515 967 5995",
    "sg:postcode":"50009",
    "sg:province":"IA",
    "sg:tags":[
        "return",
        "filing"
    ],
    "wof:name":"Altoona Tax Svc",
    "wof:placetype":"venue"
},
  "geometry": {"coordinates":[-93.467167,41.644163],"type":"Point"}
}