{
  "type": "Feature",
  "properties": {
    "addr:full":"1121 E Main St Manchester IA 52057",
    "addr:housenumber":"1121",
    "addr:postcode":"52057",
    "addr:street":"E Main St",
    "iso:country":"US",
    "sg:address":"1121 E Main St",
    "sg:city":"Manchester",
    "sg:classifiers":[
        {
            "category":"Wholesale",
            "subcategory":"Farm Supplies",
            "type":"Manufacturing & Wholesale Goods"
        }
    ],
    "sg:phone":"+1 563 927 4151",
    "sg:postcode":"52057",
    "sg:province":"IA",
    "wof:name":"Norby Farm Fleet",
    "wof:placetype":"venue"
},
  "geometry": {"coordinates":[-91.438959,42.483981],"type":"Point"}
}