{
  "type": "Feature",
  "properties": {
    "iso:country":"US",
    "sg:address":"1106 S 8th St",
    "sg:city":"Clinton",
    "sg:classifiers":[
        {
            "category":"Bars & Pubs",
            "type":"Food & Drink"
        }
    ],
    "sg:phone":"+1 563 244 4747",
    "sg:postcode":"52732",
    "sg:province":"IA",
    "wof:name":"Paul's Tavern",
    "wof:placetype":"venue"
},
  "geometry": {"coordinates":[-90.204111,41.834133],"type":"Point"}
}