{
  "type": "Feature",
  "properties": {
    "iso:country":"US",
    "sg:address":"6012 Silver Sioux Rd",
    "sg:city":"Quimby",
    "sg:classifiers":[
        {
            "category":"Farming",
            "subcategory":"Farm & Veterinary Services",
            "type":"Manufacturing & Wholesale Goods"
        }
    ],
    "sg:phone":"+1 712 445 2247",
    "sg:postcode":"51049",
    "sg:province":"IA",
    "sg:tags":[
        "breeder",
        "livestock"
    ],
    "wof:name":"Lau Cattle Co",
    "wof:placetype":"venue"
},
  "geometry": {"coordinates":[-95.611189,42.646504],"type":"Point"}
}