{
  "type": "Feature",
  "properties": {
    "iso:country":"US",
    "sg:address":"902 Seneca St",
    "sg:city":"Webster City",
    "sg:classifiers":[
        {
            "category":"Shopping",
            "subcategory":"Gifts & Souvenirs",
            "type":"Retail Goods"
        }
    ],
    "sg:phone":"+1 515 832 4480",
    "sg:postcode":"50595",
    "sg:province":"IA",
    "sg:tags":[
        "shop"
    ],
    "wof:name":"House Of Bargains",
    "wof:placetype":"venue"
},
  "geometry": {"coordinates":[-93.817049,42.467494],"type":"Point"}
}