{
  "type": "Feature",
  "properties": {
    "addr:full":"13057 118th St Blakesburg IA 52536",
    "addr:housenumber":"13057",
    "addr:postcode":"52536",
    "addr:street":"118Th St",
    "iso:country":"US",
    "sg:address":"13057 118th St",
    "sg:city":"Blakesburg",
    "sg:classifiers":[
        {
            "category":"Farming",
            "subcategory":"Livestock Farm",
            "type":"Manufacturing & Wholesale Goods"
        }
    ],
    "sg:phone":"+1 641 938 2710",
    "sg:postcode":"52536",
    "sg:province":"IA",
    "sg:tags":[
        "feedlot",
        "cattle",
        "crop",
        "beef",
        "general"
    ],
    "wof:name":"Mike Glosser Farm",
    "wof:placetype":"venue"
},
  "geometry": {"coordinates":[-92.58079499999999,40.888751],"type":"Point"}
}