{
  "type": "Feature",
  "properties": {
    "iso:country":"US",
    "sg:address":"625 31st Ave SW",
    "sg:city":"Cedar Rapids",
    "sg:classifiers":[
        {
            "category":"Freight",
            "type":"Transportation"
        },
        {
            "category":"Government",
            "subcategory":"Office",
            "type":"Public Place"
        }
    ],
    "sg:phone":"+1 319 892 5170",
    "sg:postcode":"52404",
    "sg:province":"IA",
    "sg:tags":[
        "trucking"
    ],
    "wof:name":"Linn County Lifts",
    "wof:placetype":"venue"
},
  "geometry": {"coordinates":[-91.681197,41.947006],"type":"Point"}
}