{
  "type": "Feature",
  "properties": {
    "addr:full":"320 W Kimberly Rd Davenport IA 52806",
    "addr:housenumber":"320",
    "addr:postcode":"52806",
    "addr:street":"W Kimberly Rd",
    "iso:country":"US",
    "sg:address":"320 W Kimberly Rd",
    "sg:city":"Davenport",
    "sg:classifiers":[
        {
            "category":"Shopping",
            "subcategory":"Clothing, Apparel, & Fashions",
            "type":"Retail Goods"
        }
    ],
    "sg:phone":"+1 563 386 9696",
    "sg:postcode":"52806",
    "sg:province":"IA",
    "sg:tags":[
        "clothing",
        "store"
    ],
    "sg:website":"http://www.pacsun.com",
    "wof:name":"Pac Sun",
    "wof:placetype":"venue"
},
  "geometry": {"coordinates":[-90.569016,41.56039],"type":"Point"}
}