{
  "type": "Feature",
  "properties": {
    "iso:country":"US",
    "sg:address":"1200 John St",
    "sg:city":"Corning",
    "sg:classifiers":[
        {
            "category":"Sports & Exercise",
            "subcategory":"Race Track",
            "type":"Entertainment"
        }
    ],
    "sg:phone":"+1 641 322 4184",
    "sg:postcode":"50841",
    "sg:province":"IA",
    "wof:name":"Adams County Speedway",
    "wof:placetype":"venue"
},
  "geometry": {"coordinates":[-94.73050000000001,40.994488],"type":"Point"}
}