{
  "type": "Feature",
  "properties": {
    "iso:country":"US",
    "sg:address":"6414 250th St",
    "sg:city":"Hartley",
    "sg:classifiers":[
        {
            "category":"Farming",
            "subcategory":"Farm & Veterinary Services",
            "type":"Manufacturing & Wholesale Goods"
        }
    ],
    "sg:phone":"+1 712 736 2500",
    "sg:postcode":"51346",
    "sg:province":"IA",
    "wof:name":"Gary Schiernbeck Combining",
    "wof:placetype":"venue"
},
  "geometry": {"coordinates":[-95.52292799999999,43.2854],"type":"Point"}
}