{
  "type": "Feature",
  "properties": {
    "addr:full":"2406 Main St Keokuk IA 52632",
    "addr:housenumber":"2406",
    "addr:postcode":"52632",
    "addr:street":"Main St",
    "iso:country":"US",
    "sg:address":"2406 Main St",
    "sg:city":"Keokuk",
    "sg:classifiers":[
        {
            "category":"Professional",
            "subcategory":"Accounting & Tax Preparation",
            "type":"Services"
        }
    ],
    "sg:phone":"+1 319 524 7278",
    "sg:postcode":"52632",
    "sg:province":"IA",
    "sg:tags":[
        "return",
        "filing"
    ],
    "wof:name":"Taxes Plus",
    "wof:placetype":"venue"
},
  "geometry": {"coordinates":[-91.3991,40.410841],"type":"Point"}
}