{
  "type": "Feature",
  "properties": {
    "iso:country":"US",
    "sg:address":"130 5th St",
    "sg:city":"West Des Moines",
    "sg:classifiers":[
        {
            "category":"Health Services",
            "subcategory":"Health Practitioner",
            "type":"Services"
        }
    ],
    "sg:phone":"+1 515 279 0302",
    "sg:postcode":"50265",
    "sg:province":"IA",
    "wof:name":"Joan Lmt Martell",
    "wof:placetype":"venue"
},
  "geometry": {"coordinates":[-93.70896500000001,41.569629],"type":"Point"}
}