{
  "type": "Feature",
  "properties": {
    "iso:country":"US",
    "sg:address":"104 W Fountain St",
    "sg:city":"Brighton",
    "sg:classifiers":[
        {
            "category":"Shopping",
            "subcategory":"Gifts & Souvenirs",
            "type":"Retail Goods"
        }
    ],
    "sg:phone":"+1 319 694 2080",
    "sg:postcode":"52540",
    "sg:province":"IA",
    "sg:tags":[
        "shop"
    ],
    "wof:name":"A Darling Touch",
    "wof:placetype":"venue"
},
  "geometry": {"coordinates":[-91.82252,41.175986],"type":"Point"}
}