{
  "type": "Feature",
  "properties": {
    "iso:country":"US",
    "sg:address":"810 8th St",
    "sg:city":"Kalona",
    "sg:classifiers":[
        {
            "category":"Personal",
            "type":"Services"
        }
    ],
    "sg:phone":"+1 319 656 2767",
    "sg:postcode":"52247",
    "sg:province":"IA",
    "wof:name":"Nordic Massage Inc",
    "wof:placetype":"venue"
},
  "geometry": {"coordinates":[-91.701795,41.490251],"type":"Point"}
}