{
  "type": "Feature",
  "properties": {
    "iso:country":"US",
    "sg:address":"438 16th St",
    "sg:city":"Bettendorf",
    "sg:classifiers":[
        {
            "category":"Education",
            "subcategory":"School",
            "type":"Public Place"
        }
    ],
    "sg:phone":"+1 563 355 8352",
    "sg:postcode":"52722",
    "sg:province":"IA",
    "sg:tags":[
        "academic",
        "special"
    ],
    "wof:name":"Valley Shelter School",
    "wof:placetype":"venue"
},
  "geometry": {"coordinates":[-90.510119,41.526369],"type":"Point"}
}