{
  "type": "Feature",
  "properties": {
    "addr:full":"3764 Needham Ave Wall Lake IA 51466",
    "addr:housenumber":"3764",
    "addr:postcode":"51466",
    "addr:street":"Needham Ave Wall",
    "iso:country":"US",
    "sg:address":"3764 Needham Ave",
    "sg:city":"Wall Lake",
    "sg:phone":"+1 712 664 2802",
    "sg:postcode":"51466",
    "sg:province":"IA",
    "sg:tags":[
        "farm",
        "corn",
        "soybean"
    ],
    "wof:name":"Geake John",
    "wof:placetype":"venue"
},
  "geometry": {"coordinates":[-95.090695,42.246511],"type":"Point"}
}