{
  "type": "Feature",
  "properties": {
    "iso:country":"US",
    "sg:address":"113 5th St",
    "sg:city":"Whittemore",
    "sg:classifiers":[
        {
            "category":"Recreation",
            "type":"Entertainment"
        }
    ],
    "sg:phone":"+1 515 884 2633",
    "sg:postcode":"50598",
    "sg:province":"IA",
    "sg:tags":[
        "pool",
        "swimming"
    ],
    "wof:name":"Whittemore Municipal Swim Pool",
    "wof:placetype":"venue"
},
  "geometry": {"coordinates":[-94.423063,43.066638],"type":"Point"}
}