{
  "type": "Feature",
  "properties": {
    "iso:country":"US",
    "sg:address":"21176 Greenview Rd",
    "sg:city":"Council Bluffs",
    "sg:classifiers":[
        {
            "category":"Professional",
            "subcategory":"Business Services",
            "type":"Services"
        }
    ],
    "sg:phone":"+1 712 323 7202",
    "sg:postcode":"51503",
    "sg:province":"IA",
    "wof:name":"Advantage Home Inspection Svc",
    "wof:placetype":"venue"
},
  "geometry": {"coordinates":[-95.77012999999999,41.239765],"type":"Point"}
}