{
  "type": "Feature",
  "properties": {
    "addr:full":"119 Columbus Ave Des Moines IA 50315",
    "addr:housenumber":"119",
    "addr:postcode":"50315",
    "addr:street":"Columbus Ave",
    "iso:country":"US",
    "sg:address":"119 Columbus Ave",
    "sg:city":"Des Moines",
    "sg:classifiers":[
        {
            "category":"Professional",
            "subcategory":"Business Services",
            "type":"Services"
        }
    ],
    "sg:phone":"+1 515 283 2709",
    "sg:postcode":"50315",
    "sg:province":"IA",
    "sg:tags":[
        "auctioneer"
    ],
    "wof:name":"Auction Outlet",
    "wof:placetype":"venue"
},
  "geometry": {"coordinates":[-93.61856299999999,41.573364],"type":"Point"}
}