{
  "type": "Feature",
  "properties": {
    "addr:full":"1518 Mulberry Ave Muscatine IA 52761",
    "addr:housenumber":"1518",
    "addr:postcode":"52761",
    "addr:street":"Mulberry Ave",
    "iso:country":"US",
    "sg:address":"1518 Mulberry Ave",
    "sg:city":"Muscatine",
    "sg:classifiers":[
        {
            "category":"Health Services",
            "subcategory":"Doctor",
            "type":"Services"
        }
    ],
    "sg:phone":"+1 563 262 4115",
    "sg:postcode":"52761",
    "sg:province":"IA",
    "sg:tags":[
        "physician",
        "surgeon"
    ],
    "wof:name":"Kessler Jason MD",
    "wof:placetype":"venue"
},
  "geometry": {"coordinates":[-91.05237,41.433926],"type":"Point"}
}