{
  "type": "Feature",
  "properties": {
    "addr:full":"704 Central Ave Hawarden IA 51023",
    "addr:housenumber":"704",
    "addr:postcode":"51023",
    "addr:street":"Central Ave",
    "iso:country":"US",
    "sg:address":"704 Central Ave",
    "sg:city":"Hawarden",
    "sg:classifiers":[
        {
            "category":"Home & Garden",
            "subcategory":"Furniture",
            "type":"Retail Goods"
        }
    ],
    "sg:phone":"+1 712 551 2756",
    "sg:postcode":"51023",
    "sg:province":"IA",
    "wof:name":"Mc Kenny Furniture",
    "wof:placetype":"venue"
},
  "geometry": {"coordinates":[-96.485147,42.994367],"type":"Point"}
}