{
  "type": "Feature",
  "properties": {
    "addr:full":"4932 Ave O Fort Madison IA 52627",
    "addr:housenumber":"4932",
    "addr:postcode":"52627",
    "addr:street":"Ave O",
    "iso:country":"US",
    "sg:address":"4932 Ave O",
    "sg:city":"Fort Madison",
    "sg:classifiers":[
        {
            "category":"Home & Garden",
            "subcategory":"Carpets & Floor Coverings",
            "type":"Retail Goods"
        }
    ],
    "sg:phone":"+1 319 372 4048",
    "sg:postcode":"52627",
    "sg:province":"IA",
    "sg:tags":[
        "dealer",
        "rug"
    ],
    "wof:name":"Interiors By Philip",
    "wof:placetype":"venue"
},
  "geometry": {"coordinates":[-91.37463700000001,40.623936],"type":"Point"}
}