{
  "type": "Feature",
  "properties": {
    "iso:country":"US",
    "sg:address":"808 6th St Ste 1",
    "sg:city":"Marion",
    "sg:classifiers":[
        {
            "category":"Communications",
            "subcategory":"Newspaper",
            "type":"Services"
        }
    ],
    "sg:phone":"+1 319 377 7037",
    "sg:postcode":"52302",
    "sg:province":"IA",
    "sg:tags":[
        "print",
        "medium"
    ],
    "wof:name":"Marion Times the",
    "wof:placetype":"venue"
},
  "geometry": {"coordinates":[-91.60410299999999,42.0341],"type":"Point"}
}