{
  "type": "Feature",
  "properties": {
    "addr:full":"249 9th St Sibley IA 51249",
    "addr:housenumber":"249",
    "addr:postcode":"51249",
    "addr:street":"9Th St",
    "iso:country":"US",
    "sg:address":"249 9th St",
    "sg:city":"Sibley",
    "sg:classifiers":[
        {
            "category":"Insurance",
            "subcategory":"Insurance Agent",
            "type":"Services"
        }
    ],
    "sg:phone":"+1 712 754 2626",
    "sg:postcode":"51249",
    "sg:province":"IA",
    "sg:tags":[
        "real estate"
    ],
    "sg:website":"http://www.ellerbroekagency.com",
    "wof:name":"Ellerbroek Assoc",
    "wof:placetype":"venue"
},
  "geometry": {"coordinates":[-95.751147,43.399337],"type":"Point"}
}