{
  "type": "Feature",
  "properties": {
    "iso:country":"US",
    "sg:address":"103 N Front St",
    "sg:city":"Mapleton",
    "sg:classifiers":[
        {
            "category":"Government",
            "subcategory":"Office",
            "type":"Public Place"
        }
    ],
    "sg:phone":"+1 712 881 1411",
    "sg:postcode":"51034",
    "sg:province":"IA",
    "sg:tags":[
        "village"
    ],
    "wof:name":"Mapleton Light Plant",
    "wof:placetype":"venue"
},
  "geometry": {"coordinates":[-95.79465,42.16689],"type":"Point"}
}