{
  "type": "Feature",
  "properties": {
    "iso:country":"US",
    "sg:address":"107 1st Ave",
    "sg:city":"Royal",
    "sg:classifiers":[
        {
            "category":"Freight",
            "type":"Transportation"
        }
    ],
    "sg:phone":"+1 712 933 2231",
    "sg:postcode":"51357",
    "sg:province":"IA",
    "sg:tags":[
        "cartage",
        "trucking"
    ],
    "wof:name":"C H Trucking",
    "wof:placetype":"venue"
},
  "geometry": {"coordinates":[-95.280261,43.06438],"type":"Point"}
}