{
  "type": "Feature",
  "properties": {
    "iso:country":"US",
    "sg:address":"425 W Us Highway 30",
    "sg:city":"Carroll",
    "sg:classifiers":[
        {
            "category":"Restaurant",
            "type":"Food & Drink"
        }
    ],
    "sg:menulink":"http://www.allmenus.com/ia/carroll/120788-subway/menu/",
    "sg:phone":"+1 712 792 6422",
    "sg:postcode":"51401",
    "sg:province":"IA",
    "sg:tags":[
        "american",
        "sandwich"
    ],
    "wof:name":"Subway",
    "wof:placetype":"venue"
},
  "geometry": {"coordinates":[-94.873142,42.067406],"type":"Point"}
}