{
  "type": "Feature",
  "properties": {
    "addr:full":"7600 University Ave Clive IA 50325",
    "addr:housenumber":"7600",
    "addr:postcode":"50325",
    "addr:street":"University Ave",
    "iso:country":"US",
    "sg:address":"7600 University Ave",
    "sg:city":"Clive",
    "sg:classifiers":[
        {
            "category":"Home & Garden",
            "subcategory":"Garden Supply",
            "type":"Retail Goods"
        }
    ],
    "sg:phone":"+1 515 279 2296",
    "sg:postcode":"50325",
    "sg:province":"IA",
    "sg:tags":[
        "engine"
    ],
    "sg:website":"www.clivepowerequipment.com",
    "wof:name":"Clive Power Equipment",
    "wof:placetype":"venue"
},
  "geometry": {"coordinates":[-93.72253000000001,41.60031],"type":"Point"}
}