{
  "type": "Feature",
  "properties": {
    "addr:full":"134 Greenfield Pkwy Des Moines IA 50320",
    "addr:housenumber":"134",
    "addr:postcode":"50320",
    "addr:street":"Greenfield Pkwy",
    "iso:country":"US",
    "sg:address":"134 Greenfield Pkwy",
    "sg:city":"Des Moines",
    "sg:classifiers":[
        {
            "category":"Building & Trades",
            "subcategory":"Construction",
            "type":"Services"
        }
    ],
    "sg:phone":"+1 515 285 6576",
    "sg:postcode":"50320",
    "sg:province":"IA",
    "sg:tags":[
        "hanging",
        "contractor"
    ],
    "wof:name":"Everett Painting Co",
    "wof:placetype":"venue"
},
  "geometry": {"coordinates":[-93.613316,41.505297],"type":"Point"}
}