{
  "type": "Feature",
  "properties": {
    "iso:country":"US",
    "sg:address":"501 Locust St",
    "sg:city":"Des Moines",
    "sg:classifiers":[
        {
            "category":"Restaurant",
            "type":"Food & Drink"
        }
    ],
    "sg:phone":"+1 515 280 3353",
    "sg:postcode":"50309",
    "sg:province":"IA",
    "wof:name":"Pablo's California Taqueria",
    "wof:placetype":"venue"
},
  "geometry": {"coordinates":[-93.62496899999999,41.586833],"type":"Point"}
}