{
  "type": "Feature",
  "properties": {
    "iso:country":"US",
    "sg:address":"502 S Locust St",
    "sg:city":"Edgewood",
    "sg:classifiers":[
        {
            "category":"Professional",
            "type":"Services"
        }
    ],
    "sg:phone":"+1 563 928 6844",
    "sg:postcode":"52042",
    "sg:province":"IA",
    "sg:tags":[
        "establishment"
    ],
    "wof:name":"Susie's Keepsakes",
    "wof:placetype":"venue"
},
  "geometry": {"coordinates":[-91.398664,42.640749],"type":"Point"}
}