{
  "type": "Feature",
  "properties": {
    "iso:country":"US",
    "sg:address":"1435 Mount Pleasant St",
    "sg:city":"Dubuque",
    "sg:classifiers":[
        {
            "category":"Manufacturing",
            "subcategory":"Printing",
            "type":"Manufacturing & Wholesale Goods"
        }
    ],
    "sg:phone":"+1 563 690 7438",
    "sg:postcode":"52001",
    "sg:province":"IA",
    "sg:tags":[
        "publishing",
        "desktop"
    ],
    "wof:name":"S Squared Advertising",
    "wof:placetype":"venue"
},
  "geometry": {"coordinates":[-90.685703,42.501805],"type":"Point"}
}