{
  "type": "Feature",
  "properties": {
    "iso:country":"US",
    "sg:address":"304 S Seneca St",
    "sg:city":"Pomeroy",
    "sg:classifiers":[
        {
            "category":"Organizations",
            "subcategory":"Religious Organization",
            "type":"Services"
        }
    ],
    "sg:phone":"+1 712 468 2341",
    "sg:postcode":"50575",
    "sg:province":"IA",
    "sg:tags":[
        "clergy"
    ],
    "wof:name":"Kevin Schnakenberg",
    "wof:placetype":"venue"
},
  "geometry": {"coordinates":[-94.68811100000001,42.548919],"type":"Point"}
}