{
  "type": "Feature",
  "properties": {
    "iso:country":"US",
    "sg:address":"27325 240th Ave",
    "sg:city":"Princeton",
    "sg:classifiers":[
        {
            "category":"Freight",
            "type":"Transportation"
        }
    ],
    "sg:phone":"+1 563 225 2880",
    "sg:postcode":"52768",
    "sg:province":"IA",
    "sg:tags":[
        "operator",
        "local",
        "trucking"
    ],
    "wof:name":"J E M Trucking Inc",
    "wof:placetype":"venue"
},
  "geometry": {"coordinates":[-90.432395,41.701211],"type":"Point"}
}