{
  "type": "Feature",
  "properties": {
    "addr:full":"1129 Cerro Gordo St Sheffield IA 50475",
    "addr:housenumber":"1129",
    "addr:postcode":"50475",
    "addr:street":"Cerro Gordo St",
    "iso:country":"US",
    "sg:address":"1129 Cerro Gordo St",
    "sg:city":"Sheffield",
    "sg:classifiers":[
        {
            "category":"Retail",
            "subcategory":"Animal Services",
            "type":"Services"
        }
    ],
    "sg:phone":"+1 641 892 4488",
    "sg:postcode":"50475",
    "sg:province":"IA",
    "sg:tags":[
        "breeder",
        "horse"
    ],
    "wof:name":"Sheriff Stock Farm",
    "wof:placetype":"venue"
},
  "geometry": {"coordinates":[-93.296295,42.907697],"type":"Point"}
}