{
  "type": "Feature",
  "properties": {
    "addr:full":"101 Main St Elberon IA 52225",
    "addr:housenumber":"101",
    "addr:postcode":"52225",
    "addr:street":"Main St",
    "iso:country":"US",
    "sg:address":"101 Main St",
    "sg:city":"Elberon",
    "sg:classifiers":[
        {
            "category":"Building & Trades",
            "subcategory":"Plumbing",
            "type":"Services"
        }
    ],
    "sg:phone":"+1 319 439 5354",
    "sg:postcode":"52225",
    "sg:province":"IA",
    "sg:tags":[
        "heating",
        "contractor"
    ],
    "wof:name":"Elberon Hardware",
    "wof:placetype":"venue"
},
  "geometry": {"coordinates":[-92.316789,42.00601],"type":"Point"}
}