{
  "type": "Feature",
  "properties": {
    "iso:country":"US",
    "sg:address":"301 E Salem Ave",
    "sg:city":"Indianola",
    "sg:classifiers":[
        {
            "category":"Retail",
            "subcategory":"Auto Repair",
            "type":"Services"
        }
    ],
    "sg:phone":"+1 515 961 9077",
    "sg:postcode":"50125",
    "sg:province":"IA",
    "sg:tags":[
        "wrecker"
    ],
    "wof:name":"Craig's Automotive",
    "wof:placetype":"venue"
},
  "geometry": {"coordinates":[-93.55695900000001,41.360265],"type":"Point"}
}