{
  "type": "Feature",
  "properties": {
    "iso:country":"US",
    "sg:address":"10 E Southridge Rd",
    "sg:city":"Marshalltown",
    "sg:classifiers":[
        {
            "category":"Retail",
            "subcategory":"Auto Repair",
            "type":"Services"
        }
    ],
    "sg:phone":"+1 641 753 8952",
    "sg:postcode":"50158",
    "sg:province":"IA",
    "sg:tags":[
        "repairing",
        "automobile"
    ],
    "wof:name":"Latino Auto",
    "wof:placetype":"venue"
},
  "geometry": {"coordinates":[-92.91206699999999,42.018028],"type":"Point"}
}