{
  "type": "Feature",
  "properties": {
    "iso:country":"US",
    "sg:address":"401 Main St",
    "sg:city":"Cedar Falls",
    "sg:classifiers":[
        {
            "category":"Utilities",
            "subcategory":"Mobile Phone",
            "type":"Services"
        }
    ],
    "sg:phone":"+1 319 266 5070",
    "sg:postcode":"50613",
    "sg:province":"IA",
    "sg:tags":[
        "telephone",
        "cellular"
    ],
    "wof:name":"Next Generation Wireless",
    "wof:placetype":"venue"
},
  "geometry": {"coordinates":[-92.445482,42.53413],"type":"Point"}
}