{
  "type": "Feature",
  "properties": {
    "addr:full":"20 E Main St Waukon IA 52172",
    "addr:housenumber":"20",
    "addr:postcode":"52172",
    "addr:street":"E Main St",
    "iso:country":"US",
    "sg:address":"20 E Main St",
    "sg:city":"Waukon",
    "sg:classifiers":[
        {
            "category":"Building & Trades",
            "subcategory":"Plumbing",
            "type":"Services"
        }
    ],
    "sg:phone":"+1 563 568 2784",
    "sg:postcode":"52172",
    "sg:province":"IA",
    "sg:tags":[
        "heating",
        "contractor"
    ],
    "wof:name":"De Buhr & Casper Plumbing",
    "wof:placetype":"venue"
},
  "geometry": {"coordinates":[-91.475111,43.269331],"type":"Point"}
}