{
  "type": "Feature",
  "properties": {
    "addr:full":"7105 Reite Ave Des Moines IA 50311",
    "addr:postcode":"7105;50311",
    "addr:street":"Reite Ave",
    "iso:country":"US",
    "sg:address":"7105 Reite Ave",
    "sg:city":"Des Moines",
    "sg:classifiers":[
        {
            "category":"Real Estate",
            "subcategory":"Real Estate Agent",
            "type":"Services"
        }
    ],
    "sg:phone":"+1 515 279 1072",
    "sg:postcode":"50311",
    "sg:province":"IA",
    "sg:tags":[
        "appraiser"
    ],
    "wof:name":"Gusland-Castek Appraisal Co",
    "wof:placetype":"venue"
},
  "geometry": {"coordinates":[-93.716579,41.606354],"type":"Point"}
}