{
  "type": "Feature",
  "properties": {
    "iso:country":"US",
    "sg:address":"1501 E Washington St",
    "sg:city":"Mt Pleasant",
    "sg:classifiers":[
        {
            "category":"Professional",
            "subcategory":"Computer Services",
            "type":"Services"
        }
    ],
    "sg:phone":"+1 319 986 5131",
    "sg:postcode":"52641",
    "sg:province":"IA",
    "sg:tags":[
        "consultant",
        "designer",
        "datum",
        "system"
    ],
    "wof:name":"Health Software Inc",
    "wof:placetype":"venue"
},
  "geometry": {"coordinates":[-91.531334,40.963102],"type":"Point"}
}