{
  "type": "Feature",
  "properties": {
    "iso:country":"US",
    "sg:address":"515 N Jefferson Way",
    "sg:city":"Indianola",
    "sg:classifiers":[
        {
            "category":"Social Services",
            "type":"Services"
        }
    ],
    "sg:phone":"+1 515 961 5161",
    "sg:postcode":"50125",
    "sg:province":"IA",
    "sg:tags":[
        "organization",
        "welfare"
    ],
    "wof:name":"Mica Fadss Program",
    "wof:placetype":"venue"
},
  "geometry": {"coordinates":[-93.558429,41.364598],"type":"Point"}
}