{
  "type": "Feature",
  "properties": {
    "iso:country":"US",
    "sg:address":"4049 120th St",
    "sg:city":"Urbandale",
    "sg:classifiers":[
        {
            "category":"Manufacturing",
            "subcategory":"Printing",
            "type":"Manufacturing & Wholesale Goods"
        }
    ],
    "sg:phone":"+1 515 254 0080",
    "sg:postcode":"50323",
    "sg:province":"IA",
    "sg:tags":[
        "printer"
    ],
    "sg:website":"www.advertisersduplicating.com",
    "wof:name":"Advertisers Duplicating Inc",
    "wof:placetype":"venue"
},
  "geometry": {"coordinates":[-93.779067,41.634723],"type":"Point"}
}