{
  "type": "Feature",
  "properties": {
    "iso:country":"US",
    "sg:address":"705 Barry Ave",
    "sg:city":"Muscatine",
    "sg:classifiers":[
        {
            "category":"Education",
            "subcategory":"School",
            "type":"Public Place"
        }
    ],
    "sg:phone":"+1 563 263 7005",
    "sg:postcode":"52761",
    "sg:province":"IA",
    "wof:name":"Grant Elementary School",
    "wof:placetype":"venue"
},
  "geometry": {"coordinates":[-91.051823,41.439752],"type":"Point"}
}