{
  "type": "Feature",
  "properties": {
    "addr:full":"2908 Morgan St Sioux City IA 51104",
    "addr:housenumber":"2908",
    "addr:postcode":"51104",
    "addr:street":"Morgan St",
    "iso:country":"US",
    "sg:address":"2908 Morgan St",
    "sg:city":"Sioux City",
    "sg:classifiers":[
        {
            "category":"Building & Trades",
            "subcategory":"Construction",
            "type":"Services"
        }
    ],
    "sg:phone":"+1 712 255 1357",
    "sg:postcode":"51104",
    "sg:province":"IA",
    "sg:tags":[
        "house",
        "contractor",
        "concrete"
    ],
    "wof:name":"Bob Merchant & Son Const",
    "wof:placetype":"venue"
},
  "geometry": {"coordinates":[-96.38736,42.521024],"type":"Point"}
}