{
  "type": "Feature",
  "properties": {
    "iso:country":"US",
    "sg:address":"2030 2nd Ave S",
    "sg:city":"Clinton",
    "sg:classifiers":[
        {
            "category":"Building & Trades",
            "subcategory":"Construction",
            "type":"Services"
        }
    ],
    "sg:phone":"+1 563 242 2922",
    "sg:postcode":"52732",
    "sg:province":"IA",
    "sg:tags":[
        "contractor"
    ],
    "wof:name":"Adees Drywall & Painting",
    "wof:placetype":"venue"
},
  "geometry": {"coordinates":[-90.232702,41.844618],"type":"Point"}
}