{
  "type": "Feature",
  "properties": {
    "addr:full":"1705 Angle Rd SW Kalona IA 52247",
    "addr:housenumber":"1705",
    "addr:postcode":"52247",
    "addr:street":"Angle Rd Sw",
    "iso:country":"US",
    "sg:address":"1705 Angle Rd SW",
    "sg:city":"Kalona",
    "sg:classifiers":[
        {
            "category":"Building & Trades",
            "subcategory":"Electrical",
            "type":"Services"
        }
    ],
    "sg:phone":"+1 319 683 2547",
    "sg:postcode":"52247",
    "sg:province":"IA",
    "sg:tags":[
        "electric",
        "contractor"
    ],
    "wof:name":"Yoder-Short Electric",
    "wof:placetype":"venue"
},
  "geometry": {"coordinates":[-91.770787,41.546732],"type":"Point"}
}