{
  "type": "Feature",
  "properties": {
    "iso:country":"US",
    "sg:address":"2300 N 4th St",
    "sg:city":"Red Oak",
    "sg:classifiers":[
        {
            "category":"Education",
            "subcategory":"College",
            "type":"Public Place"
        }
    ],
    "sg:phone":"+1 712 623 2541",
    "sg:postcode":"51566",
    "sg:province":"IA",
    "sg:tags":[
        "academic",
        "school"
    ],
    "wof:name":"Southwestern Community College",
    "wof:placetype":"venue"
},
  "geometry": {"coordinates":[-95.227998,41.025219],"type":"Point"}
}