{
  "type": "Feature",
  "properties": {
    "iso:country":"US",
    "sg:address":"1564 245th St",
    "sg:city":"Mt Pleasant",
    "sg:classifiers":[
        {
            "category":"Retail",
            "subcategory":"Auto Repair",
            "type":"Services"
        }
    ],
    "sg:phone":"+1 319 986 5193",
    "sg:postcode":"52641",
    "sg:province":"IA",
    "sg:tags":[
        "repairing",
        "automobile"
    ],
    "wof:name":"Holtkamp Automotive Inc",
    "wof:placetype":"venue"
},
  "geometry": {"coordinates":[-91.604719,40.947992],"type":"Point"}
}