{
  "type": "Feature",
  "properties": {
    "addr:full":"603 E Main St Panora IA 50216",
    "addr:housenumber":"603",
    "addr:postcode":"50216",
    "addr:street":"E Main St",
    "iso:country":"US",
    "sg:address":"603 E Main St",
    "sg:city":"Panora",
    "sg:classifiers":[
        {
            "category":"Health Services",
            "subcategory":"Doctor",
            "type":"Services"
        }
    ],
    "sg:phone":"+1 641 755 4000",
    "sg:postcode":"50216",
    "sg:province":"IA",
    "sg:tags":[
        "physician",
        "surgeon"
    ],
    "wof:name":"GCH Family Medicine",
    "wof:placetype":"venue"
},
  "geometry": {"coordinates":[-94.35608000000001,41.69186],"type":"Point"}
}