{
  "type": "Feature",
  "properties": {
    "iso:country":"US",
    "sg:address":"903 E Pleasant View Dr",
    "sg:city":"Des Moines",
    "sg:classifiers":[
        {
            "category":"Utilities",
            "subcategory":"Water",
            "type":"Services"
        }
    ],
    "sg:phone":"+1 515 471 8649",
    "sg:postcode":"50315",
    "sg:province":"IA",
    "sg:tags":[
        "company",
        "sewage"
    ],
    "wof:name":"Des Moines Water Works",
    "wof:placetype":"venue"
},
  "geometry": {"coordinates":[-93.601145,41.556558],"type":"Point"}
}