{
  "type": "Feature",
  "properties": {
    "iso:country":"US",
    "sg:address":"528 Pierce St",
    "sg:city":"Sioux City",
    "sg:classifiers":[
        {
            "category":"Arts & Performance",
            "subcategory":"Theater",
            "type":"Entertainment"
        }
    ],
    "sg:phone":"+1 712 279 4850",
    "sg:postcode":"51101",
    "sg:province":"IA",
    "sg:tags":[
        "bureau",
        "concert"
    ],
    "wof:name":"Orpheum Theatre",
    "wof:placetype":"venue"
},
  "geometry": {"coordinates":[-96.40487400000001,42.496029],"type":"Point"}
}