{
  "type": "Feature",
  "properties": {
    "addr:full":"411 Peterson St Iowa City IA 52245",
    "addr:housenumber":"411",
    "addr:postcode":"52245",
    "addr:street":"Peterson St",
    "iso:country":"US",
    "sg:address":"411 Peterson St",
    "sg:city":"Iowa City",
    "sg:classifiers":[
        {
            "category":"Freight",
            "type":"Transportation"
        }
    ],
    "sg:phone":"+1 319 337 2860",
    "sg:postcode":"52245",
    "sg:province":"IA",
    "sg:tags":[
        "delivery"
    ],
    "wof:name":"Whateva We Can Deliva",
    "wof:placetype":"venue"
},
  "geometry": {"coordinates":[-91.483043,41.655534],"type":"Point"}
}