{
  "type": "Feature",
  "properties": {
    "iso:country":"US",
    "sg:address":"201 Forest Glen Dr",
    "sg:city":"Council Bluffs",
    "sg:classifiers":[
        {
            "category":"Professional",
            "type":"Services"
        }
    ],
    "sg:phone":"+1 712 325 1772",
    "sg:postcode":"51503",
    "sg:province":"IA",
    "wof:name":"Hr Central Inc",
    "wof:placetype":"venue"
},
  "geometry": {"coordinates":[-95.79561699999999,41.244686],"type":"Point"}
}