{
  "type": "Feature",
  "properties": {
    "addr:full":"1432 Q Ave Oelwein IA 50662",
    "addr:housenumber":"1432",
    "addr:postcode":"50662",
    "addr:street":"Q Ave",
    "iso:country":"US",
    "sg:address":"1432 Q Ave",
    "sg:city":"Oelwein",
    "sg:classifiers":[
        {
            "category":"Sports & Exercise",
            "subcategory":"Golf",
            "type":"Entertainment"
        }
    ],
    "sg:phone":"+1 319 283 3258",
    "sg:postcode":"50662",
    "sg:province":"IA",
    "sg:tags":[
        "course"
    ],
    "wof:name":"Edgewater Golf Course",
    "wof:placetype":"venue"
},
  "geometry": {"coordinates":[-91.923444,42.642807],"type":"Point"}
}