{
  "type": "Feature",
  "properties": {
    "addr:full":"902 Flindt Dr Storm Lake IA 50588",
    "addr:housenumber":"902",
    "addr:postcode":"50588",
    "addr:street":"Flindt Dr",
    "iso:country":"US",
    "sg:address":"902 Flindt Dr",
    "sg:city":"Storm Lake",
    "sg:classifiers":[
        {
            "category":"Insurance",
            "subcategory":"Insurance Agent",
            "type":"Services"
        }
    ],
    "sg:phone":"+1 712 732 1908",
    "sg:postcode":"50588",
    "sg:province":"IA",
    "sg:website":"www.danaphipps.com",
    "wof:name":"Phipps Crop Insurance",
    "wof:placetype":"venue"
},
  "geometry": {"coordinates":[-95.193586,42.647238],"type":"Point"}
}