{
  "type": "Feature",
  "properties": {
    "iso:country":"US",
    "sg:address":"2730 State St",
    "sg:city":"Bettendorf",
    "sg:classifiers":[
        {
            "category":"Home & Garden",
            "subcategory":"Home Furnishings",
            "type":"Retail Goods"
        },
        {
            "category":"Home & Garden",
            "subcategory":"Building Materials",
            "type":"Retail Goods"
        },
        {
            "category":"Manufacturing",
            "subcategory":"Glass & Minerals",
            "type":"Manufacturing & Wholesale Goods"
        },
        {
            "category":"Manufacturing",
            "subcategory":"Building Materials",
            "type":"Manufacturing & Wholesale Goods"
        }
    ],
    "sg:phone":"+1 563 359 3531",
    "sg:postcode":"52722",
    "sg:province":"IA",
    "sg:tags":[
        "repair",
        "bathroom",
        "glass-auto",
        "baths-equipment",
        "plate",
        "supply",
        "replacement",
        "glazier",
        "window",
        "cabinet",
        "glass-wholesale",
        "shape",
        "mirror",
        "fixtures",
        "accessory",
        "circle",
        "special",
        "manufacturer"
    ],
    "wof:name":"Steve's Mirror And Glass Ltd",
    "wof:placetype":"venue"
},
  "geometry": {"coordinates":[-90.494733,41.526032],"type":"Point"}
}