{
  "type": "Feature",
  "properties": {
    "iso:country":"US",
    "sg:address":"130 S 1st St",
    "sg:city":"Carlisle",
    "sg:classifiers":[
        {
            "category":"Restaurant",
            "type":"Food & Drink"
        }
    ],
    "sg:phone":"+1 515 989 0222",
    "sg:postcode":"50047",
    "sg:province":"IA",
    "sg:tags":[
        "pizza"
    ],
    "wof:name":"Johnny & Mike's Pizza",
    "wof:placetype":"venue"
},
  "geometry": {"coordinates":[-93.48647200000001,41.498241],"type":"Point"}
}