{
  "type": "Feature",
  "properties": {
    "addr:full":"1111 Jersey Ridge Rd Davenport IA 52803",
    "addr:housenumber":"1111",
    "addr:postcode":"52803",
    "addr:street":"Jersey Ridge Rd",
    "iso:country":"US",
    "sg:address":"1111 Jersey Ridge Rd",
    "sg:city":"Davenport",
    "sg:classifiers":[
        {
            "category":"Shopping",
            "subcategory":"Gifts & Souvenirs",
            "type":"Retail Goods"
        }
    ],
    "sg:phone":"+1 563 323 5544",
    "sg:postcode":"52803",
    "sg:province":"IA",
    "sg:tags":[
        "shop"
    ],
    "wof:name":"Village Rooster",
    "wof:placetype":"venue"
},
  "geometry": {"coordinates":[-90.543654,41.531471],"type":"Point"}
}