{
  "type": "Feature",
  "properties": {
    "iso:country":"US",
    "sg:address":"1004 N Vine St",
    "sg:city":"Creston",
    "sg:classifiers":[
        {
            "category":"Organizations",
            "subcategory":"Religious Organization",
            "type":"Services"
        }
    ],
    "sg:phone":"+1 641 782 7553",
    "sg:postcode":"50801",
    "sg:province":"IA",
    "wof:name":"First United Methdst Parsonage",
    "wof:placetype":"venue"
},
  "geometry": {"coordinates":[-94.357984,41.06875],"type":"Point"}
}