{
  "type": "Feature",
  "properties": {
    "addr:full":"507 1st Ave Perry IA 50220",
    "addr:housenumber":"507",
    "addr:postcode":"50220",
    "addr:street":"1St Ave",
    "iso:country":"US",
    "sg:address":"507 1st Ave",
    "sg:city":"Perry",
    "sg:classifiers":[
        {
            "category":"Building & Trades",
            "subcategory":"Equipment Rental",
            "type":"Services"
        }
    ],
    "sg:phone":"+1 515 465 8958",
    "sg:postcode":"50220",
    "sg:province":"IA",
    "sg:tags":[
        "leasing",
        "furniture"
    ],
    "wof:name":"Rentall",
    "wof:placetype":"venue"
},
  "geometry": {"coordinates":[-94.106606,41.83208],"type":"Point"}
}