{
  "type": "Feature",
  "properties": {
    "iso:country":"US",
    "sg:address":"310 S 1st St",
    "sg:city":"Terril",
    "sg:classifiers":[
        {
            "category":"Building & Trades",
            "subcategory":"Construction",
            "type":"Services"
        }
    ],
    "sg:phone":"+1 712 853 6130",
    "sg:postcode":"51364",
    "sg:province":"IA",
    "sg:tags":[
        "repairing",
        "remodeling",
        "contractor"
    ],
    "wof:name":"Loring Construction",
    "wof:placetype":"venue"
},
  "geometry": {"coordinates":[-94.972497,43.303763],"type":"Point"}
}