{
  "type": "Feature",
  "properties": {
    "iso:country":"US",
    "sg:address":"2120 11th St",
    "sg:city":"Emmetsburg",
    "sg:classifiers":[
        {
            "category":"Restaurant",
            "type":"Food & Drink"
        }
    ],
    "sg:menulink":"http://www.allmenus.com/ia/freedom/32072-pizza-ranch/menu/",
    "sg:phone":"+1 712 852 2222",
    "sg:postcode":"50536",
    "sg:province":"IA",
    "sg:tags":[
        "american",
        "pizza"
    ],
    "wof:name":"Pizza Ranch",
    "wof:placetype":"venue"
},
  "geometry": {"coordinates":[-94.67785600000001,43.110171],"type":"Point"}
}