{
  "type": "Feature",
  "properties": {
    "addr:full":"12844 Lincoln Ave Des Moines IA 50325",
    "addr:housenumber":"12844",
    "addr:postcode":"50325",
    "addr:street":"Lincoln Ave",
    "iso:country":"US",
    "sg:address":"12844 Lincoln Ave",
    "sg:city":"Des Moines",
    "sg:classifiers":[
        {
            "category":"Shopping",
            "subcategory":"Computers & Home Electronics",
            "type":"Retail Goods"
        }
    ],
    "sg:phone":"+1 515 225 2262",
    "sg:postcode":"50325",
    "sg:province":"IA",
    "sg:tags":[
        "software"
    ],
    "sg:website":"www.precisdev.com",
    "wof:name":"Precision Development Inc",
    "wof:placetype":"venue"
},
  "geometry": {"coordinates":[-93.794799,41.607193],"type":"Point"}
}