{
  "type": "Feature",
  "properties": {
    "iso:country":"US",
    "sg:address":"2550 Rockdale Rd",
    "sg:city":"Dubuque",
    "sg:classifiers":[
        {
            "category":"Wholesale",
            "subcategory":"Machinery & Supplies",
            "type":"Manufacturing & Wholesale Goods"
        }
    ],
    "sg:phone":"+1 563 557 1184",
    "sg:postcode":"52003",
    "sg:province":"IA",
    "sg:tags":[
        "farm",
        "equipment"
    ],
    "sg:website":"www.roederimplement.com",
    "wof:name":"Roeder Implement",
    "wof:placetype":"venue"
},
  "geometry": {"coordinates":[-90.67340900000001,42.468441],"type":"Point"}
}