{
  "type": "Feature",
  "properties": {
    "addr:full":"513 Sycamore St Muscatine IA 52761",
    "addr:housenumber":"513",
    "addr:postcode":"52761",
    "addr:street":"Sycamore St",
    "iso:country":"US",
    "sg:address":"513 Sycamore St",
    "sg:city":"Muscatine",
    "sg:classifiers":[
        {
            "category":"Organizations",
            "subcategory":"Religious Organization",
            "type":"Services"
        }
    ],
    "sg:phone":"+1 563 263 5074",
    "sg:postcode":"52761",
    "sg:province":"IA",
    "sg:tags":[
        "church"
    ],
    "wof:name":"Zion Lutheran Church",
    "wof:placetype":"venue"
},
  "geometry": {"coordinates":[-91.047133,41.424563],"type":"Point"}
}