{
  "type": "Feature",
  "properties": {
    "iso:country":"US",
    "sg:address":"607 Black Forest Rd",
    "sg:city":"Hull",
    "sg:classifiers":[
        {
            "category":"Building & Trades",
            "subcategory":"Construction",
            "type":"Services"
        }
    ],
    "sg:phone":"+1 712 439 2065",
    "sg:postcode":"51239",
    "sg:province":"IA",
    "sg:tags":[
        "concrete",
        "contractor"
    ],
    "wof:name":"Vanvoorst Concrete",
    "wof:placetype":"venue"
},
  "geometry": {"coordinates":[-96.14246900000001,43.185772],"type":"Point"}
}