{
  "type": "Feature",
  "properties": {
    "iso:country":"US",
    "sg:address":"204 12th St",
    "sg:city":"Des Moines",
    "sg:classifiers":[
        {
            "category":"Banks & Credit Unions",
            "subcategory":"Bank",
            "type":"Services"
        }
    ],
    "sg:phone":"+1 515 557 8994",
    "sg:postcode":"50309",
    "sg:province":"IA",
    "sg:tags":[
        "commercial"
    ],
    "wof:name":"Wells Fargo",
    "wof:placetype":"venue"
},
  "geometry": {"coordinates":[-93.63203799999999,41.584284],"type":"Point"}
}