{
  "type": "Feature",
  "properties": {
    "addr:full":"1211 Rushridge Rd Jefferson IA 50129",
    "addr:housenumber":"1211",
    "addr:postcode":"50129",
    "addr:street":"Rushridge Rd",
    "iso:country":"US",
    "sg:address":"1211 Rushridge Rd",
    "sg:city":"Jefferson",
    "sg:classifiers":[
        {
            "category":"Real Estate",
            "subcategory":"Real Estate Operator",
            "type":"Services"
        }
    ],
    "sg:phone":"+1 515 386 4288",
    "sg:postcode":"50129",
    "sg:province":"IA",
    "sg:tags":[
        "property",
        "lessor"
    ],
    "wof:name":"Piepel John",
    "wof:placetype":"venue"
},
  "geometry": {"coordinates":[-94.392533,42.011039],"type":"Point"}
}