{
  "type": "Feature",
  "properties": {
    "iso:country":"US",
    "sg:address":"8302 Streeter Rd",
    "sg:city":"Cedar Falls",
    "sg:classifiers":[
        {
            "category":"Wholesale",
            "subcategory":"Machinery & Supplies",
            "type":"Manufacturing & Wholesale Goods"
        }
    ],
    "sg:phone":"+1 319 987 2543",
    "sg:postcode":"50613",
    "sg:province":"IA",
    "sg:tags":[
        "equipment",
        "industrial",
        "truck"
    ],
    "wof:name":"L-T Authority",
    "wof:placetype":"venue"
},
  "geometry": {"coordinates":[-92.396621,42.621368],"type":"Point"}
}