{
  "type": "Feature",
  "properties": {
    "iso:country":"US",
    "sg:address":"101 E Hill St",
    "sg:city":"St Olaf",
    "sg:classifiers":[
        {
            "category":"Wholesale",
            "subcategory":"Farm Supplies",
            "type":"Manufacturing & Wholesale Goods"
        }
    ],
    "sg:phone":"+1 563 783 2626",
    "sg:postcode":"52072",
    "sg:province":"IA",
    "sg:tags":[
        "feed"
    ],
    "wof:name":"St Olaf Ag Sales & Svc",
    "wof:placetype":"venue"
},
  "geometry": {"coordinates":[-91.38613599999999,42.928387],"type":"Point"}
}