{
  "type": "Feature",
  "properties": {
    "addr:full":"824 Orchard St Iowa City IA 52246",
    "addr:housenumber":"824",
    "addr:postcode":"52246",
    "addr:street":"Orchard St",
    "iso:country":"US",
    "sg:address":"824 Orchard St",
    "sg:city":"Iowa City",
    "sg:classifiers":[
        {
            "category":"Retail",
            "subcategory":"Auto Rental",
            "type":"Services"
        }
    ],
    "sg:phone":"+1 319 351 4529",
    "sg:postcode":"52246",
    "sg:province":"IA",
    "sg:tags":[
        "renting",
        "automobile"
    ],
    "wof:name":"Budget Rent A Car",
    "wof:placetype":"venue"
},
  "geometry": {"coordinates":[-91.54140200000001,41.649425],"type":"Point"}
}