{
  "type": "Feature",
  "properties": {
    "iso:country":"US",
    "sg:address":"4643 Butterfield Rd",
    "sg:city":"Cedar Falls",
    "sg:phone":"+1 319 988 4126",
    "sg:postcode":"50613",
    "sg:province":"IA",
    "sg:tags":[
        "farm",
        "field",
        "crop"
    ],
    "wof:name":"Walter Mochal",
    "wof:placetype":"venue"
},
  "geometry": {"coordinates":[-92.44149299999999,42.445399],"type":"Point"}
}