{
  "type": "Feature",
  "properties": {
    "iso:country":"US",
    "sg:address":"1730 110th St",
    "sg:city":"Goodell",
    "sg:classifiers":[
        {
            "category":"Home & Garden",
            "subcategory":"Garden Supply",
            "type":"Retail Goods"
        }
    ],
    "sg:phone":"+1 641 495 6258",
    "sg:postcode":"50439",
    "sg:province":"IA",
    "sg:tags":[
        "bulb",
        "seed"
    ],
    "wof:name":"Thomas Burk-Pioneer Seed",
    "wof:placetype":"venue"
},
  "geometry": {"coordinates":[-93.650355,42.923112],"type":"Point"}
}