{
  "type": "Feature",
  "properties": {
    "iso:country":"US",
    "sg:address":"3710 56th St",
    "sg:city":"Des Moines",
    "sg:classifiers":[
        {
            "category":"Real Estate",
            "subcategory":"Real Estate Operator",
            "type":"Services"
        }
    ],
    "sg:phone":"+1 515 278 5823",
    "sg:postcode":"50310",
    "sg:province":"IA",
    "sg:tags":[
        "building",
        "apartment"
    ],
    "wof:name":"Rawecienda Apartments",
    "wof:placetype":"venue"
},
  "geometry": {"coordinates":[-93.69446499999999,41.625746],"type":"Point"}
}