{
  "type": "Feature",
  "properties": {
    "iso:country":"US",
    "sg:address":"916 Pleasant Ave",
    "sg:city":"Decorah",
    "sg:classifiers":[
        {
            "category":"Building & Trades",
            "subcategory":"Equipment Rental",
            "type":"Services"
        }
    ],
    "sg:phone":"+1 563 382 2105",
    "sg:postcode":"52101",
    "sg:province":"IA",
    "wof:name":"Taylor Rentals",
    "wof:placetype":"venue"
},
  "geometry": {"coordinates":[-91.782927,43.289834],"type":"Point"}
}