{
  "type": "Feature",
  "properties": {
    "iso:country":"US",
    "sg:address":"916 Oak St",
    "sg:city":"Burlington",
    "sg:classifiers":[
        {
            "category":"Freight",
            "type":"Transportation"
        }
    ],
    "sg:phone":"+1 319 752 8377",
    "sg:postcode":"52601",
    "sg:province":"IA",
    "sg:tags":[
        "operator",
        "local",
        "trucking"
    ],
    "wof:name":"Strickland Trucking",
    "wof:placetype":"venue"
},
  "geometry": {"coordinates":[-91.108313,40.823526],"type":"Point"}
}