{
  "type": "Feature",
  "properties": {
    "addr:full":"13609 110th Ave Davenport IA 52804",
    "addr:housenumber":"13609",
    "addr:postcode":"52804",
    "addr:street":"110Th Ave",
    "iso:country":"US",
    "sg:address":"13609 110th Ave",
    "sg:city":"Davenport",
    "sg:classifiers":[
        {
            "category":"Building & Trades",
            "subcategory":"Construction",
            "type":"Services"
        }
    ],
    "sg:phone":"+1 563 381 3525",
    "sg:postcode":"52804",
    "sg:province":"IA",
    "sg:tags":[
        "fabricator",
        "metal"
    ],
    "wof:name":"Grisham Industries Inc",
    "wof:placetype":"venue"
},
  "geometry": {"coordinates":[-90.68824600000001,41.502711],"type":"Point"}
}