{
  "type": "Feature",
  "properties": {
    "addr:full":"3215 Lafayette St Waterloo IA 50707",
    "addr:housenumber":"3215",
    "addr:postcode":"50707",
    "addr:street":"Lafayette St",
    "iso:country":"US",
    "sg:address":"3215 Lafayette St",
    "sg:city":"Waterloo",
    "sg:classifiers":[
        {
            "category":"Home & Garden",
            "subcategory":"Building Materials",
            "type":"Retail Goods"
        }
    ],
    "sg:phone":"+1 319 234 1763",
    "sg:postcode":"50707",
    "sg:province":"IA",
    "sg:tags":[
        "door"
    ],
    "sg:website":"www.windorinc.com",
    "wof:name":"Windor Inc",
    "wof:placetype":"venue"
},
  "geometry": {"coordinates":[-92.294619,42.47997],"type":"Point"}
}