{
  "type": "Feature",
  "properties": {
    "iso:country":"US",
    "sg:address":"1220 Tuttle St",
    "sg:city":"Des Moines",
    "sg:classifiers":[
        {
            "category":"Freight",
            "type":"Transportation"
        }
    ],
    "sg:phone":"+1 515 270 9122",
    "sg:postcode":"50309",
    "sg:province":"IA",
    "sg:tags":[
        "trucking"
    ],
    "wof:name":"Seibert Trucking",
    "wof:placetype":"venue"
},
  "geometry": {"coordinates":[-93.631731,41.578648],"type":"Point"}
}