{
  "type": "Feature",
  "properties": {
    "iso:country":"US",
    "sg:address":"3945 6th Ave",
    "sg:city":"Des Moines",
    "sg:classifiers":[
        {
            "category":"Retail",
            "subcategory":"Auto Repair",
            "type":"Services"
        }
    ],
    "sg:phone":"+1 515 243 2343",
    "sg:postcode":"50313",
    "sg:province":"IA",
    "sg:tags":[
        "repairing",
        "automobile"
    ],
    "wof:name":"Classic Automotive",
    "wof:placetype":"venue"
},
  "geometry": {"coordinates":[-93.62470500000001,41.632328],"type":"Point"}
}