{
  "type": "Feature",
  "properties": {
    "addr:full":"829 2nd Ave SE Cedar Rapids IA 52403",
    "addr:housenumber":"829",
    "addr:postcode":"52403",
    "addr:street":"2Nd Ave Se",
    "iso:country":"US",
    "sg:address":"829 2nd Ave SE",
    "sg:city":"Cedar Rapids",
    "sg:classifiers":[
        {
            "category":"Shopping",
            "subcategory":"Antiques",
            "type":"Retail Goods"
        }
    ],
    "sg:phone":"+1 319 362 4324",
    "sg:postcode":"52403",
    "sg:province":"IA",
    "wof:name":"Furniture On Consignment",
    "wof:placetype":"venue"
},
  "geometry": {"coordinates":[-91.66070999999999,41.981713],"type":"Point"}
}