{
  "type": "Feature",
  "properties": {
    "iso:country":"US",
    "sg:address":"490 S Grandview Ave",
    "sg:city":"Dubuque",
    "sg:classifiers":[
        {
            "category":"Real Estate",
            "subcategory":"Real Estate Operator",
            "type":"Services"
        }
    ],
    "sg:phone":"+1 563 583 1041",
    "sg:postcode":"52003",
    "sg:province":"IA",
    "sg:tags":[
        "property",
        "lessor"
    ],
    "wof:name":"Knepper Farm Property",
    "wof:placetype":"venue"
},
  "geometry": {"coordinates":[-90.6806,42.486862],"type":"Point"}
}