{
  "type": "Feature",
  "properties": {
    "iso:country":"US",
    "sg:address":"1140 15th St",
    "sg:city":"De Witt",
    "sg:classifiers":[
        {
            "category":"Education",
            "subcategory":"School",
            "type":"Public Place"
        }
    ],
    "sg:phone":"+1 563 659 0750",
    "sg:postcode":"52742",
    "sg:province":"IA",
    "wof:name":"Ekstrand Elementary",
    "wof:placetype":"venue"
},
  "geometry": {"coordinates":[-90.546921,41.83043],"type":"Point"}
}