{
  "type": "Feature",
  "properties": {
    "iso:country":"US",
    "sg:address":"17744 410th St",
    "sg:city":"Leland",
    "sg:classifiers":[
        {
            "category":"Farming",
            "subcategory":"Farm",
            "type":"Manufacturing & Wholesale Goods"
        }
    ],
    "sg:phone":"+1 641 567 3662",
    "sg:postcode":"50453",
    "sg:province":"IA",
    "sg:tags":[
        "crop",
        "general"
    ],
    "wof:name":"Harold Knutson",
    "wof:placetype":"venue"
},
  "geometry": {"coordinates":[-93.642591,43.356856],"type":"Point"}
}