{
  "type": "Feature",
  "properties": {
    "addr:full":"118 N Leebrick St Burlington IA 52601",
    "addr:housenumber":"118",
    "addr:postcode":"52601",
    "addr:street":"N Leebrick St",
    "iso:country":"US",
    "sg:address":"118 N Leebrick St",
    "sg:city":"Burlington",
    "sg:classifiers":[
        {
            "category":"Shopping",
            "subcategory":"Beauty & Cosmetics",
            "type":"Retail Goods"
        },
        {
            "category":"Shopping",
            "subcategory":"Catalog Store",
            "type":"Retail Goods"
        }
    ],
    "sg:phone":"+1 319 753 0155",
    "sg:postcode":"52601",
    "sg:province":"IA",
    "sg:tags":[
        "supply",
        "perfume",
        "salons-equipment",
        "online",
        "mail",
        "order"
    ],
    "sg:website":"http://www.avon.com",
    "wof:name":"Avon",
    "wof:placetype":"venue"
},
  "geometry": {"coordinates":[-91.120355,40.809963],"type":"Point"}
}