{
  "type": "Feature",
  "properties": {
    "addr:full":"120 W Jackson St Lime Springs IA 52155",
    "addr:housenumber":"120",
    "addr:postcode":"52155",
    "addr:street":"W Jackson St",
    "iso:country":"US",
    "sg:address":"120 W Jackson St",
    "sg:city":"Lime Springs",
    "sg:classifiers":[
        {
            "category":"Education",
            "subcategory":"School",
            "type":"Public Place"
        }
    ],
    "sg:phone":"+1 563 566 2221",
    "sg:postcode":"52155",
    "sg:province":"IA",
    "wof:name":"Lime Chester Elementary",
    "wof:placetype":"venue"
},
  "geometry": {"coordinates":[-92.280378,43.450635],"type":"Point"}
}