{
  "type": "Feature",
  "properties": {
    "iso:country":"US",
    "sg:address":"1879 State Hwy 44",
    "sg:city":"Hamlin",
    "sg:classifiers":[
        {
            "category":"Farming",
            "subcategory":"Livestock Farm",
            "type":"Manufacturing & Wholesale Goods"
        }
    ],
    "sg:phone":"+1 712 764 5262",
    "sg:postcode":"50117",
    "sg:province":"IA",
    "sg:tags":[
        "horse",
        "other",
        "equine"
    ],
    "wof:name":"Wiges Quarter Horses",
    "wof:placetype":"venue"
},
  "geometry": {"coordinates":[-94.92351600000001,41.666895],"type":"Point"}
}