{
  "type": "Feature",
  "properties": {
    "iso:country":"US",
    "sg:address":"759 W 28th St S",
    "sg:city":"Newton",
    "sg:classifiers":[
        {
            "category":"Manufacturing",
            "subcategory":"Motor Vehicles & Parts",
            "type":"Manufacturing & Wholesale Goods"
        }
    ],
    "sg:phone":"+1 641 792 7616",
    "sg:postcode":"50208",
    "sg:province":"IA",
    "sg:tags":[
        "mfg"
    ],
    "wof:name":"Jado Corp",
    "wof:placetype":"venue"
},
  "geometry": {"coordinates":[-93.08705,41.692561],"type":"Point"}
}