{
  "type": "Feature",
  "properties": {
    "iso:country":"US",
    "sg:address":"201 N Hickory St",
    "sg:city":"Smithland",
    "sg:classifiers":[
        {
            "category":"Personal",
            "subcategory":"Beauty Salon",
            "type":"Services"
        }
    ],
    "sg:phone":"+1 712 889 2310",
    "sg:postcode":"51056",
    "sg:province":"IA",
    "wof:name":"Ellen's Beauty Shop",
    "wof:placetype":"venue"
},
  "geometry": {"coordinates":[-95.93067600000001,42.230731],"type":"Point"}
}