{
  "type": "Feature",
  "properties": {
    "addr:full":"47929 277th St Canton IA 57013",
    "addr:housenumber":"47929",
    "addr:postcode":"57013",
    "addr:street":"277Th St",
    "iso:country":"US",
    "sg:address":"47929 277th St",
    "sg:city":"Canton",
    "sg:phone":"+1 605 987 5279",
    "sg:postcode":"57013",
    "sg:province":"IA",
    "sg:tags":[
        "farm",
        "corn",
        "soybean"
    ],
    "wof:name":"Vandentop Gerrit",
    "wof:placetype":"venue"
},
  "geometry": {"coordinates":[-96.62267199999999,43.373452],"type":"Point"}
}