{
  "type": "Feature",
  "properties": {
    "iso:country":"US",
    "sg:address":"4310 220th Trl",
    "sg:city":"Amana",
    "sg:classifiers":[
        {
            "category":"Professional",
            "type":"Services"
        }
    ],
    "sg:phone":"+1 319 622 6446",
    "sg:postcode":"52203",
    "sg:province":"IA",
    "sg:tags":[
        "establishment"
    ],
    "wof:name":"Communal Studies Assoc",
    "wof:placetype":"venue"
},
  "geometry": {"coordinates":[-91.872409,41.800289],"type":"Point"}
}