{
  "type": "Feature",
  "properties": {
    "addr:full":"2214 Forest Ave Des Moines IA 50311",
    "addr:housenumber":"2214",
    "addr:postcode":"50311",
    "addr:street":"Forest Ave",
    "iso:country":"US",
    "sg:address":"2214 Forest Ave",
    "sg:city":"Des Moines",
    "sg:classifiers":[
        {
            "category":"Health Services",
            "subcategory":"Doctor",
            "type":"Services"
        }
    ],
    "sg:phone":"+1 515 273 5263",
    "sg:postcode":"50311",
    "sg:province":"IA",
    "sg:tags":[
        "dentist"
    ],
    "wof:name":"Forest Avenue Dentists",
    "wof:placetype":"venue"
},
  "geometry": {"coordinates":[-93.648061,41.603982],"type":"Point"}
}