{
  "type": "Feature",
  "properties": {
    "addr:full":"2201 N 15th St Fort Dodge IA 50501",
    "addr:housenumber":"2201",
    "addr:postcode":"50501",
    "addr:street":"N 15Th St",
    "iso:country":"US",
    "sg:address":"2201 N 15th St",
    "sg:city":"Fort Dodge",
    "sg:classifiers":[
        {
            "category":"Real Estate",
            "subcategory":"Developer",
            "type":"Services"
        }
    ],
    "sg:phone":"+1 515 573 2671",
    "sg:postcode":"50501",
    "sg:province":"IA",
    "sg:tags":[
        "cemetery"
    ],
    "wof:name":"North Lawn Cemetery",
    "wof:placetype":"venue"
},
  "geometry": {"coordinates":[-94.177938,42.52859],"type":"Point"}
}