{
  "type": "Feature",
  "properties": {
    "addr:full":"901 N Cedar St Monticello IA 52310",
    "addr:housenumber":"901",
    "addr:postcode":"52310",
    "addr:street":"N Cedar St",
    "iso:country":"US",
    "sg:address":"901 N Cedar St",
    "sg:city":"Monticello",
    "sg:classifiers":[
        {
            "category":"Retail",
            "subcategory":"Auto Repair",
            "type":"Services"
        }
    ],
    "sg:phone":"+1 319 465 3151",
    "sg:postcode":"52310",
    "sg:province":"IA",
    "sg:tags":[
        "repairing",
        "automobile"
    ],
    "wof:name":"Monticello Auto Ctr Inc",
    "wof:placetype":"venue"
},
  "geometry": {"coordinates":[-91.192312,42.250685],"type":"Point"}
}