{
  "type": "Feature",
  "properties": {
    "iso:country":"US",
    "sg:address":"500 N 5th St",
    "sg:city":"Indianola",
    "sg:classifiers":[
        {
            "category":"Recreation",
            "type":"Entertainment"
        }
    ],
    "sg:phone":"+1 515 961 2159",
    "sg:postcode":"50125",
    "sg:province":"IA",
    "sg:tags":[
        "club",
        "membership"
    ],
    "wof:name":"Iowa Donkey & Mule Society",
    "wof:placetype":"venue"
},
  "geometry": {"coordinates":[-93.55490899999999,41.36398],"type":"Point"}
}