{
  "type": "Feature",
  "properties": {
    "iso:country":"US",
    "sg:address":"419 41st St NE",
    "sg:city":"Cedar Rapids",
    "sg:classifiers":[
        {
            "category":"Building & Trades",
            "subcategory":"Construction",
            "type":"Services"
        }
    ],
    "sg:phone":"+1 319 310 3926",
    "sg:postcode":"52402",
    "sg:province":"IA",
    "sg:tags":[
        "handyman"
    ],
    "wof:name":"Cedar Rapids Handyman",
    "wof:placetype":"venue"
},
  "geometry": {"coordinates":[-91.640759,42.020333],"type":"Point"}
}