{
  "type": "Feature",
  "properties": {
    "addr:full":"505 W Main St Ottumwa IA 52501",
    "addr:housenumber":"505",
    "addr:postcode":"52501",
    "addr:street":"W Main St",
    "iso:country":"US",
    "sg:address":"505 W Main St",
    "sg:city":"Ottumwa",
    "sg:classifiers":[
        {
            "category":"Social Services",
            "type":"Services"
        }
    ],
    "sg:phone":"+1 641 682 3606",
    "sg:postcode":"52501",
    "sg:province":"IA",
    "sg:tags":[
        "organization",
        "welfare"
    ],
    "wof:name":"Salvation Army Thrift Store",
    "wof:placetype":"venue"
},
  "geometry": {"coordinates":[-92.418683,41.02237],"type":"Point"}
}