{
  "type": "Feature",
  "properties": {
    "addr:full":"121 5th Ave SW Le Mars IA 51031",
    "addr:housenumber":"121",
    "addr:postcode":"51031",
    "addr:street":"5Th Ave Sw",
    "iso:country":"US",
    "sg:address":"121 5th Ave SW",
    "sg:city":"Le Mars",
    "sg:classifiers":[
        {
            "category":"Utilities",
            "subcategory":"Mobile Phone",
            "type":"Services"
        }
    ],
    "sg:phone":"+1 712 548 5494",
    "sg:postcode":"51031",
    "sg:province":"IA",
    "sg:tags":[
        "telephone",
        "cellular"
    ],
    "wof:name":"U S Cellular",
    "wof:placetype":"venue"
},
  "geometry": {"coordinates":[-96.173849,42.791584],"type":"Point"}
}