{
  "type": "Feature",
  "properties": {
    "addr:full":"701 27th St NW Cedar Rapids IA 52405",
    "addr:housenumber":"701",
    "addr:postcode":"52405",
    "addr:street":"27Th St Nw",
    "iso:country":"US",
    "sg:address":"701 27th St NW",
    "sg:city":"Cedar Rapids",
    "sg:classifiers":[
        {
            "category":"Home & Garden",
            "subcategory":"Home Furnishings",
            "type":"Retail Goods"
        }
    ],
    "sg:phone":"+1 319 396 4807",
    "sg:postcode":"52405",
    "sg:province":"IA",
    "sg:tags":[
        "curtain",
        "made",
        "drapery"
    ],
    "wof:name":"Stegman Custom Draperies",
    "wof:placetype":"venue"
},
  "geometry": {"coordinates":[-91.708136,41.979879],"type":"Point"}
}