{
  "type": "Feature",
  "properties": {
    "iso:country":"US",
    "sg:address":"222 5th St",
    "sg:city":"West Des Moines",
    "sg:classifiers":[
        {
            "category":"Shopping",
            "subcategory":"Florist",
            "type":"Retail Goods"
        }
    ],
    "sg:phone":"+1 515 277 2535",
    "sg:postcode":"50265",
    "sg:province":"IA",
    "wof:name":"Petal Perfect Custom Florals",
    "wof:placetype":"venue"
},
  "geometry": {"coordinates":[-93.70896399999999,41.572187],"type":"Point"}
}