{
  "type": "Feature",
  "properties": {
    "addr:full":"375 C St SW Dallas IA 50062",
    "addr:housenumber":"375",
    "addr:postcode":"50062",
    "addr:street":"C St Sw",
    "iso:country":"US",
    "sg:address":"375 C St SW",
    "sg:city":"Dallas",
    "sg:classifiers":[
        {
            "category":"Manufacturing",
            "subcategory":"Lumber",
            "type":"Manufacturing & Wholesale Goods"
        }
    ],
    "sg:phone":"+1 641 947 3015",
    "sg:postcode":"50062",
    "sg:province":"IA",
    "sg:tags":[
        "mill"
    ],
    "wof:name":"Lankford Logging and Lumber",
    "wof:placetype":"venue"
},
  "geometry": {"coordinates":[-93.244614,41.220043],"type":"Point"}
}