{
  "type": "Feature",
  "properties": {
    "addr:full":"1224 13th St NW Cedar Rapids IA 52405",
    "addr:housenumber":"1224",
    "addr:postcode":"52405",
    "addr:street":"13Th St Nw",
    "iso:country":"US",
    "sg:address":"1224 13th St NW",
    "sg:city":"Cedar Rapids",
    "sg:classifiers":[
        {
            "category":"Health Services",
            "subcategory":"Nursing And Care Facility",
            "type":"Services"
        }
    ],
    "sg:phone":"+1 319 365 9171",
    "sg:postcode":"52405",
    "sg:province":"IA",
    "sg:tags":[
        "home",
        "retirement",
        "community"
    ],
    "wof:name":"Greenwood Terrace",
    "wof:placetype":"venue"
},
  "geometry": {"coordinates":[-91.689549,41.984078],"type":"Point"}
}