{
  "type": "Feature",
  "properties": {
    "iso:country":"US",
    "sg:address":"115 N Howard St",
    "sg:city":"Indianola",
    "sg:classifiers":[
        {
            "category":"Government",
            "subcategory":"Police Station",
            "type":"Public Place"
        }
    ],
    "sg:phone":"+1 515 961 1122",
    "sg:postcode":"50125",
    "sg:province":"IA",
    "sg:tags":[
        "department"
    ],
    "wof:name":"Martindale Police Dept",
    "wof:placetype":"venue"
},
  "geometry": {"coordinates":[-93.561036,41.360451],"type":"Point"}
}