{
  "type": "Feature",
  "properties": {
    "iso:country":"US",
    "sg:address":"414 N 3rd St",
    "sg:city":"Marshalltown",
    "sg:classifiers":[
        {
            "category":"Building & Trades",
            "subcategory":"Landscaping Services",
            "type":"Services"
        }
    ],
    "sg:phone":"+1 641 753 3738",
    "sg:postcode":"50158",
    "sg:province":"IA",
    "sg:tags":[
        "landscape",
        "contractor"
    ],
    "wof:name":"Child Garden",
    "wof:placetype":"venue"
},
  "geometry": {"coordinates":[-92.917933,42.054315],"type":"Point"}
}