{
  "type": "Feature",
  "properties": {
    "iso:country":"US",
    "sg:address":"406 B St",
    "sg:city":"Sergeant Bluff",
    "sg:classifiers":[
        {
            "category":"Shopping",
            "subcategory":"Florist",
            "type":"Retail Goods"
        }
    ],
    "sg:phone":"+1 712 943 5340",
    "sg:postcode":"51054",
    "sg:province":"IA",
    "wof:name":"Barbara's Florals",
    "wof:placetype":"venue"
},
  "geometry": {"coordinates":[-96.364164,42.403785],"type":"Point"}
}