{
  "type": "Feature",
  "properties": {
    "addr:full":"1333 Buckeye Ave Ames IA 50010",
    "addr:housenumber":"1333",
    "addr:postcode":"50010",
    "addr:street":"Buckeye Ave",
    "iso:country":"US",
    "sg:address":"1333 Buckeye Ave",
    "sg:city":"Ames",
    "sg:classifiers":[
        {
            "category":"Shopping",
            "subcategory":"Stationery & Office Supplies",
            "type":"Retail Goods"
        }
    ],
    "sg:phone":"+1 515 663 0597",
    "sg:postcode":"50010",
    "sg:province":"IA",
    "wof:name":"Staples The Office Superstore",
    "wof:placetype":"venue"
},
  "geometry": {"coordinates":[-93.611617,42.01015],"type":"Point"}
}