{
  "type": "Feature",
  "properties": {
    "addr:full":"1010 E 9th St Muscatine IA 52761",
    "addr:housenumber":"1010",
    "addr:postcode":"52761",
    "addr:street":"E 9Th St",
    "iso:country":"US",
    "sg:address":"1010 E 9th St",
    "sg:city":"Muscatine",
    "sg:classifiers":[
        {
            "category":"Building & Trades",
            "subcategory":"Plumbing",
            "type":"Services"
        }
    ],
    "sg:phone":"+1 563 264 8934",
    "sg:postcode":"52761",
    "sg:province":"IA",
    "sg:tags":[
        "plumbing",
        "contractor"
    ],
    "wof:name":"Boche Plumbing & Heating Inc",
    "wof:placetype":"venue"
},
  "geometry": {"coordinates":[-91.040667,41.432667],"type":"Point"}
}