{
  "type": "Feature",
  "properties": {
    "addr:full":"2938 N Harrison St Davenport IA 52803",
    "addr:housenumber":"2938",
    "addr:postcode":"52803",
    "addr:street":"N Harrison St",
    "iso:country":"US",
    "sg:address":"2938 N Harrison St",
    "sg:city":"Davenport",
    "sg:classifiers":[
        {
            "category":"Shopping",
            "subcategory":"Clothing, Apparel, & Fashions",
            "type":"Retail Goods"
        }
    ],
    "sg:phone":"+1 563 386 0209",
    "sg:postcode":"52803",
    "sg:province":"IA",
    "sg:tags":[
        "hair",
        "salon",
        "gallery"
    ],
    "wof:name":"Suitcase Boutique",
    "wof:placetype":"venue"
},
  "geometry": {"coordinates":[-90.576711,41.550915],"type":"Point"}
}