{
  "type": "Feature",
  "properties": {
    "iso:country":"US",
    "sg:address":"310 S 4th Ave",
    "sg:city":"Marshalltown",
    "sg:classifiers":[
        {
            "category":"Freight",
            "type":"Transportation"
        }
    ],
    "sg:phone":"+1 641 752 4848",
    "sg:postcode":"50158",
    "sg:province":"IA",
    "sg:tags":[
        "commercial",
        "storage"
    ],
    "wof:name":"L S Storage Rental",
    "wof:placetype":"venue"
},
  "geometry": {"coordinates":[-92.90631399999999,42.045342],"type":"Point"}
}