{
  "type": "Feature",
  "properties": {
    "iso:country":"US",
    "sg:address":"199 25th Pl",
    "sg:city":"Runnells",
    "sg:classifiers":[
        {
            "category":"Farming",
            "subcategory":"Farm",
            "type":"Manufacturing & Wholesale Goods"
        }
    ],
    "sg:phone":"+1 515 966 2022",
    "sg:postcode":"50237",
    "sg:province":"IA",
    "sg:tags":[
        "crop",
        "general"
    ],
    "wof:name":"Donald Kain",
    "wof:placetype":"venue"
},
  "geometry": {"coordinates":[-93.302717,41.507984],"type":"Point"}
}