{
  "type": "Feature",
  "properties": {
    "addr:full":"693 31st St Des Moines IA 50312",
    "addr:housenumber":"693",
    "addr:postcode":"50312",
    "addr:street":"31St St",
    "iso:country":"US",
    "sg:address":"693 31st St",
    "sg:city":"Des Moines",
    "sg:classifiers":[
        {
            "category":"Building & Trades",
            "subcategory":"Construction",
            "type":"Services"
        }
    ],
    "sg:phone":"+1 515 279 1284",
    "sg:postcode":"50312",
    "sg:province":"IA",
    "sg:tags":[
        "contractor"
    ],
    "wof:name":"De Marchi Masonry",
    "wof:placetype":"venue"
},
  "geometry": {"coordinates":[-93.65924200000001,41.588264],"type":"Point"}
}