{
  "type": "Feature",
  "properties": {
    "addr:full":"2820 Rockingham Rd Davenport IA 52802",
    "addr:housenumber":"2820",
    "addr:postcode":"52802",
    "addr:street":"Rockingham Rd",
    "iso:country":"US",
    "sg:address":"2820 Rockingham Rd",
    "sg:city":"Davenport",
    "sg:classifiers":[
        {
            "category":"Bars & Pubs",
            "type":"Food & Drink"
        }
    ],
    "sg:phone":"+1 563 326 0202",
    "sg:postcode":"52802",
    "sg:province":"IA",
    "wof:name":"Frankie's Pub",
    "wof:placetype":"venue"
},
  "geometry": {"coordinates":[-90.61881,41.5117],"type":"Point"}
}