{
  "type": "Feature",
  "properties": {
    "iso:country":"US",
    "sg:address":"17015 294th St",
    "sg:city":"Long Grove",
    "sg:classifiers":[
        {
            "category":"Professional",
            "type":"Services"
        }
    ],
    "sg:phone":"+1 563 285 9461",
    "sg:postcode":"52756",
    "sg:province":"IA",
    "wof:name":"Rural Transcription Service",
    "wof:placetype":"venue"
},
  "geometry": {"coordinates":[-90.56600400000001,41.734391],"type":"Point"}
}