{
  "type": "Feature",
  "properties": {
    "iso:country":"US",
    "sg:address":"37220 Colesburg Rd",
    "sg:city":"Garber",
    "sg:classifiers":[
        {
            "category":"Farming",
            "subcategory":"Farm",
            "type":"Manufacturing & Wholesale Goods"
        }
    ],
    "sg:phone":"+1 563 856 5985",
    "sg:postcode":"52048",
    "sg:province":"IA",
    "sg:tags":[
        "crop",
        "general"
    ],
    "wof:name":"Lueken Farms Inc",
    "wof:placetype":"venue"
},
  "geometry": {"coordinates":[-91.245902,42.68289],"type":"Point"}
}