{
  "type": "Feature",
  "properties": {
    "iso:country":"US",
    "sg:address":"10 W 4th St",
    "sg:city":"Spencer",
    "sg:classifiers":[
        {
            "category":"Shopping",
            "subcategory":"Hobbies, Toys, & Games",
            "type":"Retail Goods"
        }
    ],
    "sg:phone":"+1 712 262 9462",
    "sg:postcode":"51301",
    "sg:province":"IA",
    "sg:tags":[
        "doll"
    ],
    "wof:name":"Plaster Shop",
    "wof:placetype":"venue"
},
  "geometry": {"coordinates":[-95.14476999999999,43.141257],"type":"Point"}
}