{
  "type": "Feature",
  "properties": {
    "addr:full":"4119 Rollins Ave Des Moines IA 50312",
    "addr:housenumber":"4119",
    "addr:postcode":"50312",
    "addr:street":"Rollins Ave",
    "iso:country":"US",
    "sg:address":"4119 Rollins Ave",
    "sg:city":"Des Moines",
    "sg:classifiers":[
        {
            "category":"Health Services",
            "subcategory":"Chiropractor",
            "type":"Services"
        }
    ],
    "sg:phone":"+1 515 274 6104",
    "sg:postcode":"50312",
    "sg:province":"IA",
    "wof:name":"Des Moines Chiropractic Ctr",
    "wof:placetype":"venue"
},
  "geometry": {"coordinates":[-93.674205,41.593082],"type":"Point"}
}