{
  "type": "Feature",
  "properties": {
    "iso:country":"US",
    "sg:address":"3017 Inkpaduta Ave",
    "sg:city":"Webster City",
    "sg:classifiers":[
        {
            "category":"Farming",
            "subcategory":"Farm",
            "type":"Manufacturing & Wholesale Goods"
        }
    ],
    "sg:phone":"+1 515 826 3357",
    "sg:postcode":"50595",
    "sg:province":"IA",
    "sg:tags":[
        "crop",
        "general"
    ],
    "wof:name":"Point Ranch The",
    "wof:placetype":"venue"
},
  "geometry": {"coordinates":[-93.815783,42.349382],"type":"Point"}
}