{
  "type": "Feature",
  "properties": {
    "iso:country":"US",
    "sg:address":"100 6th St",
    "sg:city":"Ames",
    "sg:classifiers":[
        {
            "category":"Real Estate",
            "subcategory":"Real Estate Agent",
            "type":"Services"
        }
    ],
    "sg:phone":"+1 515 232 6175",
    "sg:postcode":"50010",
    "sg:province":"IA",
    "sg:website":"www.greatiowahomes.com",
    "wof:name":"Freidrich Realty",
    "wof:placetype":"venue"
},
  "geometry": {"coordinates":[-93.612117,42.026948],"type":"Point"}
}