{
  "type": "Feature",
  "properties": {
    "iso:country":"US",
    "sg:address":"2651 Crosspark Rd",
    "sg:city":"Coralville",
    "sg:classifiers":[
        {
            "category":"Shopping",
            "subcategory":"Computers & Home Electronics",
            "type":"Retail Goods"
        }
    ],
    "sg:phone":"+1 319 626 6700",
    "sg:postcode":"52241",
    "sg:province":"IA",
    "sg:tags":[
        "software"
    ],
    "wof:name":"LMS Cadsi",
    "wof:placetype":"venue"
},
  "geometry": {"coordinates":[-91.605358,41.709901],"type":"Point"}
}