{
  "type": "Feature",
  "properties": {
    "iso:country":"US",
    "sg:address":"57006 241st St",
    "sg:city":"Ames",
    "sg:classifiers":[
        {
            "category":"Recreation",
            "type":"Entertainment"
        }
    ],
    "sg:phone":"+1 515 232 2880",
    "sg:postcode":"50010",
    "sg:province":"IA",
    "sg:tags":[
        "range",
        "baseball",
        "batting"
    ],
    "wof:name":"All Star Sports Academy",
    "wof:placetype":"venue"
},
  "geometry": {"coordinates":[-93.564575,42.007564],"type":"Point"}
}