{
  "type": "Feature",
  "properties": {
    "addr:full":"1790 14th St Marion IA 52302",
    "addr:housenumber":"1790",
    "addr:postcode":"52302",
    "addr:street":"14Th St",
    "iso:country":"US",
    "sg:address":"1790 14th St",
    "sg:city":"Marion",
    "sg:classifiers":[
        {
            "category":"Organizations",
            "subcategory":"Religious Organization",
            "type":"Services"
        }
    ],
    "sg:phone":"+1 319 377 4869",
    "sg:postcode":"52302",
    "sg:province":"IA",
    "sg:tags":[
        "church"
    ],
    "sg:website":"www.stjoesmarion.org",
    "wof:name":"St Joseph's Church",
    "wof:placetype":"venue"
},
  "geometry": {"coordinates":[-91.594855,42.041517],"type":"Point"}
}