{
  "type": "Feature",
  "properties": {
    "addr:full":"2110 12th St Harlan IA 51537",
    "addr:housenumber":"2110",
    "addr:postcode":"51537",
    "addr:street":"12Th St",
    "iso:country":"US",
    "sg:address":"2110 12th St",
    "sg:city":"Harlan",
    "sg:classifiers":[
        {
            "category":"Health Services",
            "subcategory":"Optometrist",
            "type":"Services"
        }
    ],
    "sg:phone":"+1 712 755 2150",
    "sg:postcode":"51537",
    "sg:province":"IA",
    "wof:name":"Professional Vision Care",
    "wof:placetype":"venue"
},
  "geometry": {"coordinates":[-95.325427,41.648324],"type":"Point"}
}