{
  "type": "Feature",
  "properties": {
    "iso:country":"US",
    "sg:address":"114 N Main St",
    "sg:city":"Charles City",
    "sg:classifiers":[
        {
            "category":"Health Services",
            "subcategory":"Doctor",
            "type":"Services"
        }
    ],
    "sg:phone":"+1 641 228 1803",
    "sg:postcode":"50616",
    "sg:province":"IA",
    "sg:tags":[
        "dentist"
    ],
    "wof:name":"Stephen P Earney DDS",
    "wof:placetype":"venue"
},
  "geometry": {"coordinates":[-92.678832,43.067202],"type":"Point"}
}