{
  "type": "Feature",
  "properties": {
    "iso:country":"US",
    "sg:address":"503 US Hwy 30",
    "sg:city":"Westside",
    "sg:classifiers":[
        {
            "category":"Shopping",
            "subcategory":"Used Merchandise",
            "type":"Retail Goods"
        }
    ],
    "sg:phone":"+1 712 663 4436",
    "sg:postcode":"51467",
    "sg:province":"IA",
    "sg:tags":[
        "antique"
    ],
    "wof:name":"Westside Antiques",
    "wof:placetype":"venue"
},
  "geometry": {"coordinates":[-95.100683,42.076072],"type":"Point"}
}