{
  "type": "Feature",
  "properties": {
    "addr:full":"1709 360th St Stanhope IA 50246",
    "addr:housenumber":"1709",
    "addr:postcode":"50246",
    "addr:street":"360Th St",
    "iso:country":"US",
    "sg:address":"1709 360th St",
    "sg:city":"Stanhope",
    "sg:phone":"+1 515 826 3654",
    "sg:postcode":"50246",
    "sg:province":"IA",
    "sg:tags":[
        "farm",
        "corn",
        "soybean"
    ],
    "wof:name":"Sealine Orien",
    "wof:placetype":"venue"
},
  "geometry": {"coordinates":[-93.834086,42.26752],"type":"Point"}
}