{
  "type": "Feature",
  "properties": {
    "iso:country":"US",
    "sg:address":"1600 1st Ave NE",
    "sg:city":"Cedar Rapids",
    "sg:classifiers":[
        {
            "category":"Shopping",
            "subcategory":"Gifts & Souvenirs",
            "type":"Retail Goods"
        }
    ],
    "sg:phone":"+1 319 395 6361",
    "sg:postcode":"52402",
    "sg:province":"IA",
    "sg:tags":[
        "shop",
        "novelty"
    ],
    "wof:name":"Things Remembered",
    "wof:placetype":"venue"
},
  "geometry": {"coordinates":[-91.649529,41.989711],"type":"Point"}
}