{
  "type": "Feature",
  "properties": {
    "iso:country":"US",
    "sg:address":"809 Iowa Ave",
    "sg:city":"Onawa",
    "sg:classifiers":[
        {
            "category":"Shopping",
            "subcategory":"Florist",
            "type":"Retail Goods"
        }
    ],
    "sg:phone":"+1 712 423 1371",
    "sg:postcode":"51040",
    "sg:province":"IA",
    "wof:name":"Onawa Florists Inc",
    "wof:placetype":"venue"
},
  "geometry": {"coordinates":[-96.095814,42.026626],"type":"Point"}
}