{
  "type": "Feature",
  "properties": {
    "iso:country":"US",
    "sg:address":"102 E Bremer Ave",
    "sg:city":"Waverly",
    "sg:classifiers":[
        {
            "category":"Home & Garden",
            "subcategory":"Furniture",
            "type":"Retail Goods"
        }
    ],
    "sg:phone":"+1 319 352 4480",
    "sg:postcode":"50677",
    "sg:province":"IA",
    "sg:tags":[
        "cabinet"
    ],
    "wof:name":"Cabinets Galore",
    "wof:placetype":"venue"
},
  "geometry": {"coordinates":[-92.468118,42.725723],"type":"Point"}
}