{
  "type": "Feature",
  "properties": {
    "iso:country":"US",
    "sg:address":"309 Main Ave",
    "sg:city":"Clear Lake",
    "sg:classifiers":[
        {
            "category":"Shopping",
            "subcategory":"Used Merchandise",
            "type":"Retail Goods"
        }
    ],
    "sg:phone":"+1 641 357 3077",
    "sg:postcode":"50428",
    "sg:province":"IA",
    "sg:tags":[
        "antique"
    ],
    "wof:name":"Antiques On Main",
    "wof:placetype":"venue"
},
  "geometry": {"coordinates":[-93.38102499999999,43.136409],"type":"Point"}
}