{
  "type": "Feature",
  "properties": {
    "iso:country":"US",
    "sg:address":"401 4th Ave",
    "sg:city":"De Witt",
    "sg:classifiers":[
        {
            "category":"Utilities",
            "subcategory":"Fuel Oil & Lpg",
            "type":"Services"
        }
    ],
    "sg:phone":"+1 563 659 3017",
    "sg:postcode":"52742",
    "sg:province":"IA",
    "sg:tags":[
        "dealer"
    ],
    "wof:name":"Griffith Oil",
    "wof:placetype":"venue"
},
  "geometry": {"coordinates":[-90.535951,41.820298],"type":"Point"}
}