{
  "type": "Feature",
  "properties": {
    "addr:full":"307 1st Ave E Rock Rapids IA 51246",
    "addr:housenumber":"307",
    "addr:postcode":"51246",
    "addr:street":"1St Ave E Rock",
    "iso:country":"US",
    "sg:address":"307 1st Ave E",
    "sg:city":"Rock Rapids",
    "sg:classifiers":[
        {
            "category":"Building & Trades",
            "subcategory":"Plumbing",
            "type":"Services"
        }
    ],
    "sg:phone":"+1 712 472 2400",
    "sg:postcode":"51246",
    "sg:province":"IA",
    "sg:tags":[
        "conditioning",
        "air",
        "system",
        "contractor"
    ],
    "wof:name":"Air Conditioning & Heating Inc",
    "wof:placetype":"venue"
},
  "geometry": {"coordinates":[-96.160584,43.432059],"type":"Point"}
}