{
  "type": "Feature",
  "properties": {
    "iso:country":"US",
    "sg:address":"3258 230th St",
    "sg:city":"Rose Hill",
    "sg:classifiers":[
        {
            "category":"Farming",
            "subcategory":"Farm",
            "type":"Manufacturing & Wholesale Goods"
        }
    ],
    "sg:phone":"+1 641 632 8313",
    "sg:postcode":"52586",
    "sg:province":"IA",
    "sg:tags":[
        "crop",
        "general"
    ],
    "wof:name":"Blanche Jacobs",
    "wof:placetype":"venue"
},
  "geometry": {"coordinates":[-92.437016,41.321942],"type":"Point"}
}