{
  "type": "Feature",
  "properties": {
    "iso:country":"US",
    "sg:address":"2223 202nd St",
    "sg:city":"Clarinda",
    "sg:classifiers":[
        {
            "category":"Farming",
            "subcategory":"Farm",
            "type":"Manufacturing & Wholesale Goods"
        }
    ],
    "sg:phone":"+1 712 542 4031",
    "sg:postcode":"51632",
    "sg:province":"IA",
    "sg:tags":[
        "crop",
        "general"
    ],
    "wof:name":"Lyle Nothwehr",
    "wof:placetype":"venue"
},
  "geometry": {"coordinates":[-95.15520100000001,40.753465],"type":"Point"}
}