{
  "type": "Feature",
  "properties": {
    "iso:country":"US",
    "sg:address":"611 Cedar St",
    "sg:city":"Stockport",
    "sg:classifiers":[
        {
            "category":"Shopping",
            "type":"Retail Goods"
        }
    ],
    "sg:phone":"+1 319 796 4417",
    "sg:postcode":"52651",
    "sg:province":"IA",
    "sg:tags":[
        "product",
        "wood"
    ],
    "wof:name":"Mad Scottsman Wood Shop",
    "wof:placetype":"venue"
},
  "geometry": {"coordinates":[-91.941338,40.878821],"type":"Point"}
}