{
  "type": "Feature",
  "properties": {
    "iso:country":"US",
    "sg:address":"2141 State Hwy 148",
    "sg:city":"Bedford",
    "sg:classifiers":[
        {
            "category":"Building & Trades",
            "subcategory":"Cleaning & Sanitation",
            "type":"Services"
        }
    ],
    "sg:phone":"+1 712 537 2261",
    "sg:postcode":"50833",
    "sg:province":"IA",
    "sg:tags":[
        "ventilating",
        "system"
    ],
    "wof:name":"Nortech Air Duct Cleaning",
    "wof:placetype":"venue"
},
  "geometry": {"coordinates":[-94.725469,40.678234],"type":"Point"}
}