{
  "type": "Feature",
  "properties": {
    "addr:full":"118 S 12th St Fort Dodge IA 50501",
    "addr:housenumber":"118",
    "addr:postcode":"50501",
    "addr:street":"S 12Th St",
    "iso:country":"US",
    "sg:address":"118 S 12th St",
    "sg:city":"Fort Dodge",
    "sg:classifiers":[
        {
            "category":"Professional",
            "subcategory":"Accounting & Tax Preparation",
            "type":"Services"
        }
    ],
    "sg:phone":"+1 515 955 4614",
    "sg:postcode":"50501",
    "sg:province":"IA",
    "sg:tags":[
        "accountant"
    ],
    "wof:name":"Jon Schuman CPA",
    "wof:placetype":"venue"
},
  "geometry": {"coordinates":[-94.182784,42.504888],"type":"Point"}
}