{
  "type": "Feature",
  "properties": {
    "addr:full":"326 3rd Ave S Clinton IA 52732",
    "addr:housenumber":"326",
    "addr:postcode":"52732",
    "addr:street":"3Rd Ave S",
    "iso:country":"US",
    "sg:address":"326 3rd Ave S",
    "sg:city":"Clinton",
    "sg:classifiers":[
        {
            "category":"Health Services",
            "subcategory":"Chiropractor",
            "type":"Services"
        }
    ],
    "sg:phone":"+1 563 241 4295",
    "sg:postcode":"52732",
    "sg:province":"IA",
    "wof:name":"Chiropractic Solutions",
    "wof:placetype":"venue"
},
  "geometry": {"coordinates":[-90.191388,41.843477],"type":"Point"}
}