{
  "type": "Feature",
  "properties": {
    "addr:full":"819 Country Lane Rd Keosauqua IA 52565",
    "addr:housenumber":"819",
    "addr:postcode":"52565",
    "addr:street":"Country Lane Rd",
    "iso:country":"US",
    "sg:address":"819 Country Lane Rd",
    "sg:city":"Keosauqua",
    "sg:classifiers":[
        {
            "category":"Professional",
            "type":"Services"
        }
    ],
    "sg:phone":"+1 319 293 6379",
    "sg:postcode":"52565",
    "sg:province":"IA",
    "sg:tags":[
        "establishment"
    ],
    "wof:name":"Good Samaritan Activity Ctr",
    "wof:placetype":"venue"
},
  "geometry": {"coordinates":[-91.968277,40.736477],"type":"Point"}
}