{
  "type": "Feature",
  "properties": {
    "addr:full":"5936 S Winwood Dr Johnston IA 50131",
    "addr:housenumber":"5936",
    "addr:postcode":"50131",
    "addr:street":"S Winwood Dr",
    "iso:country":"US",
    "sg:address":"5936 S Winwood Dr",
    "sg:city":"Johnston",
    "sg:classifiers":[
        {
            "category":"Building & Trades",
            "subcategory":"Construction",
            "type":"Services"
        }
    ],
    "sg:phone":"+1 515 276 8125",
    "sg:postcode":"50131",
    "sg:province":"IA",
    "sg:tags":[
        "house"
    ],
    "wof:name":"Ventura Home Builders",
    "wof:placetype":"venue"
},
  "geometry": {"coordinates":[-93.70331299999999,41.668811],"type":"Point"}
}