{
  "type": "Feature",
  "properties": {
    "iso:country":"US",
    "sg:address":"3124 E Court Ave",
    "sg:city":"Des Moines",
    "sg:classifiers":[
        {
            "category":"Manufacturing",
            "subcategory":"Chemicals & Compounds",
            "type":"Manufacturing & Wholesale Goods"
        }
    ],
    "sg:phone":"+1 515 266 3221",
    "sg:postcode":"50317",
    "sg:province":"IA",
    "sg:website":"www.gustafson.com",
    "wof:name":"Gustafson LLC",
    "wof:placetype":"venue"
},
  "geometry": {"coordinates":[-93.552758,41.589475],"type":"Point"}
}