{
  "type": "Feature",
  "properties": {
    "iso:country":"US",
    "sg:address":"15 1st St NE",
    "sg:city":"Mason City",
    "sg:classifiers":[
        {
            "category":"Insurance",
            "subcategory":"Health Insurance",
            "type":"Services"
        }
    ],
    "sg:phone":"+1 641 423 5964",
    "sg:postcode":"50401",
    "sg:province":"IA",
    "sg:tags":[
        "carrier"
    ],
    "wof:name":"Principal Life Insurance Co",
    "wof:placetype":"venue"
},
  "geometry": {"coordinates":[-93.200847,43.152638],"type":"Point"}
}