{
  "type": "Feature",
  "properties": {
    "iso:country":"US",
    "sg:address":"9708 Madison Ave",
    "sg:city":"Urbandale",
    "sg:classifiers":[
        {
            "category":"Organizations",
            "subcategory":"Community Association",
            "type":"Services"
        }
    ],
    "sg:phone":"+1 515 276 9202",
    "sg:postcode":"50322",
    "sg:province":"IA",
    "sg:tags":[
        "club"
    ],
    "wof:name":"Urbandale Soccer Club",
    "wof:placetype":"venue"
},
  "geometry": {"coordinates":[-93.75274,41.629937],"type":"Point"}
}