{
  "type": "Feature",
  "properties": {
    "iso:country":"US",
    "sg:address":"316 N River Park Dr",
    "sg:city":"Guttenberg",
    "sg:classifiers":[
        {
            "category":"Insurance",
            "subcategory":"Insurance Agent",
            "type":"Services"
        }
    ],
    "sg:phone":"+1 563 252 3754",
    "sg:postcode":"52052",
    "sg:province":"IA",
    "wof:name":"Farm Bureau Insurance",
    "wof:placetype":"venue"
},
  "geometry": {"coordinates":[-91.099358,42.789649],"type":"Point"}
}