{
  "type": "Feature",
  "properties": {
    "iso:country":"US",
    "sg:address":"35085 Jolly Ridge Rd",
    "sg:city":"Guttenberg",
    "sg:classifiers":[
        {
            "category":"Farming",
            "subcategory":"Livestock Farm",
            "type":"Manufacturing & Wholesale Goods"
        }
    ],
    "sg:phone":"+1 563 252 2185",
    "sg:postcode":"52052",
    "sg:province":"IA",
    "sg:tags":[
        "animal",
        "general"
    ],
    "wof:name":"Richard Hinzman",
    "wof:placetype":"venue"
},
  "geometry": {"coordinates":[-91.112148,42.749754],"type":"Point"}
}