{
  "type": "Feature",
  "properties": {
    "iso:country":"US",
    "sg:address":"5849 S Winwood Dr",
    "sg:city":"Johnston",
    "sg:classifiers":[
        {
            "category":"Professional",
            "subcategory":"Business Services",
            "type":"Services"
        }
    ],
    "sg:phone":"+1 515 251 8448",
    "sg:postcode":"50131",
    "sg:province":"IA",
    "wof:name":"Romig Enterprises",
    "wof:placetype":"venue"
},
  "geometry": {"coordinates":[-93.70346000000001,41.668226],"type":"Point"}
}