{
  "type": "Feature",
  "properties": {
    "iso:country":"US",
    "sg:address":"702 7th St NE",
    "sg:city":"Sioux Center",
    "sg:classifiers":[
        {
            "category":"Government",
            "subcategory":"Office",
            "type":"Public Place"
        }
    ],
    "sg:phone":"+1 712 722 4386",
    "sg:postcode":"51250",
    "sg:province":"IA",
    "sg:tags":[
        "village"
    ],
    "wof:name":"Sioux Center All Seasons Ctr",
    "wof:placetype":"venue"
},
  "geometry": {"coordinates":[-96.166157,43.084443],"type":"Point"}
}