{
  "type": "Feature",
  "properties": {
    "iso:country":"US",
    "sg:address":"205 1st Ave SW",
    "sg:city":"Le Mars",
    "sg:classifiers":[
        {
            "category":"Freight",
            "type":"Transportation"
        }
    ],
    "sg:phone":"+1 712 546 4133",
    "sg:postcode":"51031",
    "sg:province":"IA",
    "sg:tags":[
        "grain",
        "elevator"
    ],
    "wof:name":"Lamars Agri Ctr",
    "wof:placetype":"venue"
},
  "geometry": {"coordinates":[-96.167889,42.790566],"type":"Point"}
}