{
  "type": "Feature",
  "properties": {
    "addr:full":"416 Walnut St Cedar Falls IA 50613",
    "addr:housenumber":"416",
    "addr:postcode":"50613",
    "addr:street":"Walnut St",
    "iso:country":"US",
    "sg:address":"416 Walnut St",
    "sg:city":"Cedar Falls",
    "sg:classifiers":[
        {
            "category":"Building & Trades",
            "subcategory":"Landscaping Services",
            "type":"Services"
        }
    ],
    "sg:phone":"+1 319 277 8651",
    "sg:postcode":"50613",
    "sg:province":"IA",
    "wof:name":"A True Cut Turf Care",
    "wof:placetype":"venue"
},
  "geometry": {"coordinates":[-92.453283,42.534287],"type":"Point"}
}