{
  "type": "Feature",
  "properties": {
    "iso:country":"US",
    "sg:address":"417 1st Ave S",
    "sg:city":"Mt Vernon",
    "sg:classifiers":[
        {
            "category":"Health Services",
            "subcategory":"Doctor",
            "type":"Services"
        }
    ],
    "sg:phone":"+1 319 895 8451",
    "sg:postcode":"52314",
    "sg:province":"IA",
    "sg:tags":[
        "dentist"
    ],
    "wof:name":"Douglas C Easker DDS",
    "wof:placetype":"venue"
},
  "geometry": {"coordinates":[-91.41935100000001,41.919854],"type":"Point"}
}