{
  "type": "Feature",
  "properties": {
    "addr:full":"20611 State Hwy 1 Keosauqua IA 52565",
    "addr:housenumber":"20611",
    "addr:postcode":"52565",
    "addr:street":"State Hwy 1",
    "iso:country":"US",
    "sg:address":"20611 State Hwy 1",
    "sg:city":"Keosauqua",
    "sg:classifiers":[
        {
            "category":"Sports & Exercise",
            "subcategory":"Bowling",
            "type":"Entertainment"
        }
    ],
    "sg:phone":"+1 319 293 3075",
    "sg:postcode":"52565",
    "sg:province":"IA",
    "sg:tags":[
        "center"
    ],
    "wof:name":"Van Buren Bowl",
    "wof:placetype":"venue"
},
  "geometry": {"coordinates":[-91.9581,40.743768],"type":"Point"}
}