{
  "type": "Feature",
  "properties": {
    "iso:country":"US",
    "sg:address":"305 1st St",
    "sg:city":"Sully",
    "sg:classifiers":[
        {
            "category":"Autos & Motor Vehicles",
            "subcategory":"Boat Sales",
            "type":"Retail Goods"
        }
    ],
    "sg:phone":"+1 641 594 4462",
    "sg:postcode":"50251",
    "sg:province":"IA",
    "sg:tags":[
        "dealer",
        "sales"
    ],
    "wof:name":"Fast Trax Sports",
    "wof:placetype":"venue"
},
  "geometry": {"coordinates":[-92.851225,41.581135],"type":"Point"}
}