{
  "type": "Feature",
  "properties": {
    "iso:country":"US",
    "sg:address":"202 E Grant St",
    "sg:city":"Monroe",
    "sg:classifiers":[
        {
            "category":"Retail",
            "subcategory":"Auto Repair",
            "type":"Services"
        }
    ],
    "sg:phone":"+1 641 259 2344",
    "sg:postcode":"50170",
    "sg:province":"IA",
    "sg:tags":[
        "body",
        "automobile",
        "painting"
    ],
    "wof:name":"C D Body Shop",
    "wof:placetype":"venue"
},
  "geometry": {"coordinates":[-93.100607,41.527538],"type":"Point"}
}