{
  "type": "Feature",
  "properties": {
    "iso:country":"US",
    "sg:address":"1850 Curoe Rd",
    "sg:city":"Bernard",
    "sg:phone":"+1 563 879 3462",
    "sg:postcode":"52032",
    "sg:province":"IA",
    "sg:tags":[
        "farm",
        "corn",
        "soybean"
    ],
    "wof:name":"Jim Krapfl",
    "wof:placetype":"venue"
},
  "geometry": {"coordinates":[-90.88889399999999,42.318863],"type":"Point"}
}