{
  "type": "Feature",
  "properties": {
    "iso:country":"US",
    "sg:address":"20359 State Hwy 77",
    "sg:city":"Keota",
    "sg:classifiers":[
        {
            "category":"Wholesale",
            "subcategory":"Meat",
            "type":"Manufacturing & Wholesale Goods"
        }
    ],
    "sg:phone":"+1 641 636 2314",
    "sg:postcode":"52248",
    "sg:province":"IA",
    "sg:tags":[
        "product"
    ],
    "wof:name":"Swift & Co",
    "wof:placetype":"venue"
},
  "geometry": {"coordinates":[-91.966145,41.365661],"type":"Point"}
}