{
  "type": "Feature",
  "properties": {
    "addr:full":"14044 110th Ave Davenport IA 52804",
    "addr:housenumber":"14044",
    "addr:postcode":"52804",
    "addr:street":"110Th Ave",
    "iso:country":"US",
    "sg:address":"14044 110th Ave",
    "sg:city":"Davenport",
    "sg:classifiers":[
        {
            "category":"Freight",
            "type":"Transportation"
        }
    ],
    "sg:phone":"+1 563 381 8888",
    "sg:postcode":"52804",
    "sg:province":"IA",
    "sg:tags":[
        "recreational",
        "vehicle"
    ],
    "wof:name":"T & T Storage",
    "wof:placetype":"venue"
},
  "geometry": {"coordinates":[-90.688393,41.509843],"type":"Point"}
}