{
  "type": "Feature",
  "properties": {
    "addr:full":"4547 Kirkwood Ave Osage IA 50476",
    "addr:housenumber":"4547",
    "addr:postcode":"50476",
    "addr:street":"Kirkwood Ave",
    "iso:country":"US",
    "sg:address":"4547 Kirkwood Ave",
    "sg:city":"Osage",
    "sg:classifiers":[
        {
            "category":"Professional",
            "type":"Services"
        }
    ],
    "sg:phone":"+1 641 737 2154",
    "sg:postcode":"50476",
    "sg:province":"IA",
    "wof:name":"Tf Ltd",
    "wof:placetype":"venue"
},
  "geometry": {"coordinates":[-92.83052600000001,43.400126],"type":"Point"}
}