{
  "type": "Feature",
  "properties": {
    "addr:full":"1776 US Hwy 59 Sibley IA 51249",
    "addr:housenumber":"1776",
    "addr:postcode":"51249",
    "addr:street":"Us Hwy 59",
    "iso:country":"US",
    "sg:address":"1776 US Hwy 59",
    "sg:city":"Sibley",
    "sg:classifiers":[
        {
            "category":"Professional",
            "type":"Services"
        }
    ],
    "sg:phone":"+1 712 754 3569",
    "sg:postcode":"51249",
    "sg:province":"IA",
    "sg:tags":[
        "establishment"
    ],
    "wof:name":"K & B Pork Inc",
    "wof:placetype":"venue"
},
  "geometry": {"coordinates":[-95.64285099999999,43.392567],"type":"Point"}
}