{
  "type": "Feature",
  "properties": {
    "iso:country":"US",
    "sg:address":"127 W Washington St",
    "sg:city":"Osceola",
    "sg:classifiers":[
        {
            "category":"Health Services",
            "subcategory":"Doctor",
            "type":"Services"
        }
    ],
    "sg:phone":"+1 641 342 6568",
    "sg:postcode":"50213",
    "sg:province":"IA",
    "sg:tags":[
        "physician",
        "surgeon"
    ],
    "wof:name":"Thomas J Lower DO",
    "wof:placetype":"venue"
},
  "geometry": {"coordinates":[-93.766678,41.03497],"type":"Point"}
}