{
  "type": "Feature",
  "properties": {
    "addr:full":"208 S Grimmell Rd Jefferson IA 50129",
    "addr:housenumber":"208",
    "addr:postcode":"50129",
    "addr:street":"S Grimmell Rd",
    "iso:country":"US",
    "sg:address":"208 S Grimmell Rd",
    "sg:city":"Jefferson",
    "sg:classifiers":[
        {
            "category":"Wholesale",
            "subcategory":"Non-durable Goods",
            "type":"Manufacturing & Wholesale Goods"
        }
    ],
    "sg:phone":"+1 515 386 5254",
    "sg:postcode":"50129",
    "sg:province":"IA",
    "sg:tags":[
        "advertising"
    ],
    "wof:name":"Ink Spot",
    "wof:placetype":"venue"
},
  "geometry": {"coordinates":[-94.38717200000001,42.014172],"type":"Point"}
}