{
  "type": "Feature",
  "properties": {
    "iso:country":"US",
    "sg:address":"1116 W 3rd St",
    "sg:city":"Davenport",
    "sg:classifiers":[
        {
            "category":"Bars & Pubs",
            "type":"Food & Drink"
        }
    ],
    "sg:phone":"+1 563 328 2921",
    "sg:postcode":"52802",
    "sg:province":"IA",
    "wof:name":"A Knights Of Pythias",
    "wof:placetype":"venue"
},
  "geometry": {"coordinates":[-90.590689,41.522431],"type":"Point"}
}