{
  "type": "Feature",
  "properties": {
    "addr:full":"109 Ferry Rd Miles IA 52064",
    "addr:housenumber":"109",
    "addr:postcode":"52064",
    "addr:street":"Ferry Rd",
    "iso:country":"US",
    "sg:address":"109 Ferry Rd",
    "sg:city":"Miles",
    "sg:classifiers":[
        {
            "category":"Wholesale",
            "subcategory":"Farm Supplies",
            "type":"Manufacturing & Wholesale Goods"
        }
    ],
    "sg:phone":"+1 563 682 7776",
    "sg:postcode":"52064",
    "sg:province":"IA",
    "sg:tags":[
        "feed"
    ],
    "wof:name":"Pmc Agri-Svc",
    "wof:placetype":"venue"
},
  "geometry": {"coordinates":[-90.315669,42.041965],"type":"Point"}
}