{
  "type": "Feature",
  "properties": {
    "addr:full":"5024 Willow Dr Des Moines IA 50327",
    "addr:housenumber":"5024",
    "addr:postcode":"50327",
    "addr:street":"Willow Dr",
    "iso:country":"US",
    "sg:address":"5024 Willow Dr",
    "sg:city":"Des Moines",
    "sg:classifiers":[
        {
            "category":"Real Estate",
            "subcategory":"Real Estate Agent",
            "type":"Services"
        }
    ],
    "sg:phone":"+1 515 264 8400",
    "sg:postcode":"50327",
    "sg:province":"IA",
    "wof:name":"McRoberts & Associates",
    "wof:placetype":"venue"
},
  "geometry": {"coordinates":[-93.515293,41.595782],"type":"Point"}
}