{
  "type": "Feature",
  "properties": {
    "addr:full":"800 S 12th Ave Rock Rapids IA 51246",
    "addr:housenumber":"800",
    "addr:postcode":"51246",
    "addr:street":"S 12Th Ave",
    "iso:country":"US",
    "sg:address":"800 S 12th Ave",
    "sg:city":"Rock Rapids",
    "sg:classifiers":[
        {
            "category":"Organizations",
            "subcategory":"Religious Organization",
            "type":"Services"
        }
    ],
    "sg:phone":"+1 712 472 2218",
    "sg:postcode":"51246",
    "sg:province":"IA",
    "wof:name":"Faith Baptist Church",
    "wof:placetype":"venue"
},
  "geometry": {"coordinates":[-96.18583700000001,43.419039],"type":"Point"}
}