{
  "type": "Feature",
  "properties": {
    "addr:full":"839 Broadway St Pella IA 50219",
    "addr:housenumber":"839",
    "addr:postcode":"50219",
    "addr:street":"Broadway St",
    "iso:country":"US",
    "sg:address":"839 Broadway St",
    "sg:city":"Pella",
    "sg:classifiers":[
        {
            "category":"Health Services",
            "subcategory":"Doctor",
            "type":"Services"
        }
    ],
    "sg:phone":"+1 641 628 1121",
    "sg:postcode":"50219",
    "sg:province":"IA",
    "sg:tags":[
        "dentist"
    ],
    "wof:name":"Jeffery Allen DDS",
    "wof:placetype":"venue"
},
  "geometry": {"coordinates":[-92.918387,41.407545],"type":"Point"}
}