{
  "type": "Feature",
  "properties": {
    "addr:full":"1700 4th St SE Mason City IA 50401",
    "addr:housenumber":"1700",
    "addr:postcode":"50401",
    "addr:street":"4Th St Se",
    "iso:country":"US",
    "sg:address":"1700 4th St SE",
    "sg:city":"Mason City",
    "sg:classifiers":[
        {
            "category":"Education",
            "subcategory":"School",
            "type":"Public Place"
        }
    ],
    "sg:phone":"+1 641 421 4432",
    "sg:postcode":"50401",
    "sg:province":"IA",
    "sg:website":"www.masoncityschools.org",
    "wof:name":"Mason City Public Schools",
    "wof:placetype":"venue"
},
  "geometry": {"coordinates":[-93.164306,43.148179],"type":"Point"}
}