{
  "type": "Feature",
  "properties": {
    "iso:country":"US",
    "sg:address":"19986 200th Ave",
    "sg:city":"Centerville",
    "sg:classifiers":[
        {
            "category":"Building & Trades",
            "subcategory":"Construction",
            "type":"Services"
        }
    ],
    "sg:phone":"+1 641 437 4494",
    "sg:postcode":"52544",
    "sg:province":"IA",
    "sg:tags":[
        "culvert"
    ],
    "wof:name":"Quality Culverts & Fabrication",
    "wof:placetype":"venue"
},
  "geometry": {"coordinates":[-92.90598900000001,40.754429],"type":"Point"}
}