{
  "type": "Feature",
  "properties": {
    "iso:country":"US",
    "sg:address":"606 Oswego St",
    "sg:city":"Tama",
    "sg:classifiers":[
        {
            "category":"Organizations",
            "subcategory":"Community Association",
            "type":"Services"
        }
    ],
    "sg:phone":"+1 641 484 3132",
    "sg:postcode":"52339",
    "sg:province":"IA",
    "wof:name":"Knights of Columbus 7504",
    "wof:placetype":"venue"
},
  "geometry": {"coordinates":[-92.57311,41.96556],"type":"Point"}
}