{
  "type": "Feature",
  "properties": {
    "iso:country":"US",
    "sg:address":"1313 E Davenport St",
    "sg:city":"Iowa City",
    "sg:classifiers":[
        {
            "category":"Retail",
            "subcategory":"Animal Services",
            "type":"Services"
        }
    ],
    "sg:phone":"+1 319 400 0186",
    "sg:postcode":"52245",
    "sg:province":"IA",
    "sg:tags":[
        "pet",
        "boarding",
        "sitting"
    ],
    "wof:name":"Above & Beyond Pet Care",
    "wof:placetype":"venue"
},
  "geometry": {"coordinates":[-91.51373,41.665661],"type":"Point"}
}