{
  "type": "Feature",
  "properties": {
    "addr:full":"107 Pioneer Valley Dr Sergeant Bluff IA 51054",
    "addr:housenumber":"107",
    "addr:postcode":"51054",
    "addr:street":"Pioneer Valley Dr",
    "iso:country":"US",
    "sg:address":"107 Pioneer Valley Dr",
    "sg:city":"Sergeant Bluff",
    "sg:classifiers":[
        {
            "category":"Manufacturing",
            "subcategory":"Apparel",
            "type":"Manufacturing & Wholesale Goods"
        }
    ],
    "sg:phone":"+1 712 943 4204",
    "sg:postcode":"51054",
    "sg:province":"IA",
    "sg:tags":[
        "household",
        "furnishing",
        "mfg"
    ],
    "wof:name":"Missouri River Quilting C",
    "wof:placetype":"venue"
},
  "geometry": {"coordinates":[-96.340963,42.393487],"type":"Point"}
}