{
  "type": "Feature",
  "properties": {
    "iso:country":"US",
    "sg:address":"100 Oakdale Blvd",
    "sg:city":"Coralville",
    "sg:classifiers":[
        {
            "category":"Food & Beverages",
            "subcategory":"Bakery",
            "type":"Retail Goods"
        }
    ],
    "sg:phone":"+1 319 337 0478",
    "sg:postcode":"52241",
    "sg:province":"IA",
    "sg:tags":[
        "baker"
    ],
    "wof:name":"Taste Of Home Bakery & Gifts",
    "wof:placetype":"venue"
},
  "geometry": {"coordinates":[-91.57211700000001,41.705036],"type":"Point"}
}