{
  "type": "Feature",
  "properties": {
    "iso:country":"US",
    "sg:address":"2677 Hales Mill Rd",
    "sg:city":"Dubuque",
    "sg:classifiers":[
        {
            "category":"Building & Trades",
            "subcategory":"Landscaping Services",
            "type":"Services"
        }
    ],
    "sg:phone":"+1 563 583 9261",
    "sg:postcode":"52002",
    "sg:province":"IA",
    "sg:tags":[
        "landscape",
        "contractor"
    ],
    "wof:name":"Wagner Nursery",
    "wof:placetype":"venue"
},
  "geometry": {"coordinates":[-90.752825,42.515296],"type":"Point"}
}