{
  "type": "Feature",
  "properties": {
    "iso:country":"US",
    "sg:address":"1775 7th Ave",
    "sg:city":"Marion",
    "sg:classifiers":[
        {
            "category":"Shopping",
            "subcategory":"Computers & Home Electronics",
            "type":"Retail Goods"
        }
    ],
    "sg:phone":"+1 319 377 7550",
    "sg:postcode":"52302",
    "sg:province":"IA",
    "sg:tags":[
        "equipment"
    ],
    "wof:name":"Rahm Inc",
    "wof:placetype":"venue"
},
  "geometry": {"coordinates":[-91.59169799999999,42.033298],"type":"Point"}
}