{
  "type": "Feature",
  "properties": {
    "addr:full":"6550 SE Bloomfield Rd Des Moines IA 50320",
    "addr:housenumber":"6550",
    "addr:postcode":"50320",
    "addr:street":"Se Bloomfield Rd Des",
    "iso:country":"US",
    "sg:address":"6550 SE Bloomfield Rd",
    "sg:city":"Des Moines",
    "sg:classifiers":[
        {
            "category":"Recreation",
            "type":"Entertainment"
        }
    ],
    "sg:phone":"+1 515 285 9700",
    "sg:postcode":"50320",
    "sg:province":"IA",
    "sg:tags":[
        "parlor",
        "billiard"
    ],
    "wof:name":"Loco Joe's Nickel Arcade",
    "wof:placetype":"venue"
},
  "geometry": {"coordinates":[-93.59669,41.524644],"type":"Point"}
}