{
  "type": "Feature",
  "properties": {
    "iso:country":"US",
    "sg:address":"1021 Wright Rd",
    "sg:city":"Council Bluffs",
    "sg:classifiers":[
        {
            "category":"Wholesale",
            "subcategory":"Metals & Minerals",
            "type":"Manufacturing & Wholesale Goods"
        }
    ],
    "sg:phone":"+1 712 322 2858",
    "sg:postcode":"51501",
    "sg:province":"IA",
    "sg:tags":[
        "steel",
        "warehouse"
    ],
    "wof:name":"JNJ Steel",
    "wof:placetype":"venue"
},
  "geometry": {"coordinates":[-95.851676,41.218128],"type":"Point"}
}