{
  "type": "Feature",
  "properties": {
    "iso:country":"US",
    "sg:address":"2701 S Lakeport St",
    "sg:city":"Sioux City",
    "sg:classifiers":[
        {
            "category":"Government",
            "subcategory":"Office",
            "type":"Public Place"
        }
    ],
    "sg:phone":"+1 712 279 6269",
    "sg:postcode":"51106",
    "sg:province":"IA",
    "sg:tags":[
        "village"
    ],
    "wof:name":"Graceland Cemetery",
    "wof:placetype":"venue"
},
  "geometry": {"coordinates":[-96.346391,42.460515],"type":"Point"}
}