{
  "type": "Feature",
  "properties": {
    "iso:country":"US",
    "sg:address":"1053 Duck Creek Dr",
    "sg:city":"Iowa City",
    "sg:classifiers":[
        {
            "category":"Professional",
            "subcategory":"Business Services",
            "type":"Services"
        }
    ],
    "sg:phone":"+1 319 338 2587",
    "sg:postcode":"52246",
    "sg:province":"IA",
    "wof:name":"S&S Enterprises LLC",
    "wof:placetype":"venue"
},
  "geometry": {"coordinates":[-91.59080299999999,41.648759],"type":"Point"}
}