{
  "type": "Feature",
  "properties": {
    "addr:full":"1 Benton Ave E Albia IA 52531",
    "addr:housenumber":"1",
    "addr:postcode":"52531",
    "addr:street":"Benton Ave E Albia",
    "iso:country":"US",
    "sg:address":"1 Benton Ave E",
    "sg:city":"Albia",
    "sg:classifiers":[
        {
            "category":"Personal",
            "type":"Services"
        }
    ],
    "sg:phone":"+1 641 932 3339",
    "sg:postcode":"52531",
    "sg:province":"IA",
    "sg:tags":[
        "therapist",
        "massage"
    ],
    "wof:name":"Body Kneads Therapeutic Mssg",
    "wof:placetype":"venue"
},
  "geometry": {"coordinates":[-92.80837099999999,41.027111],"type":"Point"}
}