{
  "type": "Feature",
  "properties": {
    "iso:country":"US",
    "sg:address":"1006 SE Chaparal Dr",
    "sg:city":"Ankeny",
    "sg:classifiers":[
        {
            "category":"Health Services",
            "subcategory":"Health Practitioner",
            "type":"Services"
        }
    ],
    "sg:phone":"+1 515 965 8322",
    "sg:postcode":"50021",
    "sg:province":"IA",
    "sg:tags":[
        "nutrition",
        "consultant"
    ],
    "wof:name":"Best 4U Inc",
    "wof:placetype":"venue"
},
  "geometry": {"coordinates":[-93.582049,41.716313],"type":"Point"}
}