{
  "type": "Feature",
  "properties": {
    "addr:full":"1075 180th St State Center IA 50247",
    "addr:housenumber":"1075",
    "addr:postcode":"50247",
    "addr:street":"180Th St",
    "iso:country":"US",
    "sg:address":"1075 180th St",
    "sg:city":"State Center",
    "sg:phone":"+1 641 477 8394",
    "sg:postcode":"50247",
    "sg:province":"IA",
    "sg:tags":[
        "farm",
        "corn",
        "soybean"
    ],
    "wof:name":"Whitaker Ora",
    "wof:placetype":"venue"
},
  "geometry": {"coordinates":[-93.223879,42.092301],"type":"Point"}
}