{
  "type": "Feature",
  "properties": {
    "iso:country":"US",
    "sg:address":"405 Maxwell St",
    "sg:city":"Waterloo",
    "sg:classifiers":[
        {
            "category":"Farming",
            "subcategory":"Nursery",
            "type":"Manufacturing & Wholesale Goods"
        }
    ],
    "sg:phone":"+1 319 987 3130",
    "sg:postcode":"50701",
    "sg:province":"IA",
    "sg:tags":[
        "ornamental"
    ],
    "wof:name":"Flower Farm",
    "wof:placetype":"venue"
},
  "geometry": {"coordinates":[-92.381658,42.505746],"type":"Point"}
}