{
  "type": "Feature",
  "properties": {
    "iso:country":"US",
    "sg:address":"101 2nd St SE",
    "sg:city":"Cedar Rapids",
    "sg:classifiers":[
        {
            "category":"Professional",
            "subcategory":"Lawyer & Legal Services",
            "type":"Services"
        }
    ],
    "sg:phone":"+1 319 364 1535",
    "sg:postcode":"52401",
    "sg:province":"IA",
    "sg:tags":[
        "attorney"
    ],
    "wof:name":"Gray Stefani & Mitvalsky",
    "wof:placetype":"venue"
},
  "geometry": {"coordinates":[-91.66782499999999,41.97788],"type":"Point"}
}