{
  "type": "Feature",
  "properties": {
    "addr:full":"719 River St Iowa Falls IA 50126",
    "addr:housenumber":"719",
    "addr:postcode":"50126",
    "addr:street":"River St",
    "iso:country":"US",
    "sg:address":"719 River St",
    "sg:city":"Iowa Falls",
    "sg:classifiers":[
        {
            "category":"Education",
            "subcategory":"School",
            "type":"Public Place"
        }
    ],
    "sg:phone":"+1 641 648 2157",
    "sg:postcode":"50126",
    "sg:province":"IA",
    "wof:name":"Edgewood",
    "wof:placetype":"venue"
},
  "geometry": {"coordinates":[-93.26792399999999,42.523966],"type":"Point"}
}