{
  "type": "Feature",
  "properties": {
    "addr:full":"1010 N Clark St Davenport IA 52804",
    "addr:housenumber":"1010",
    "addr:postcode":"52804",
    "addr:street":"N Clark St",
    "iso:country":"US",
    "sg:address":"1010 N Clark St",
    "sg:city":"Davenport",
    "sg:classifiers":[
        {
            "category":"Organizations",
            "subcategory":"Religious Organization",
            "type":"Services"
        }
    ],
    "sg:phone":"+1 563 386 4688",
    "sg:postcode":"52804",
    "sg:province":"IA",
    "sg:tags":[
        "church"
    ],
    "wof:name":"First Church Of The Nazarene",
    "wof:placetype":"venue"
},
  "geometry": {"coordinates":[-90.624523,41.529548],"type":"Point"}
}