{
  "type": "Feature",
  "properties": {
    "iso:country":"US",
    "sg:address":"326 1st Ave SE",
    "sg:city":"Sioux Center",
    "sg:classifiers":[
        {
            "category":"Personal",
            "subcategory":"Beauty Salon",
            "type":"Services"
        }
    ],
    "sg:phone":"+1 712 722 1726",
    "sg:postcode":"51250",
    "sg:province":"IA",
    "sg:tags":[
        "shop"
    ],
    "wof:name":"Sandy Draayer Beauty Salon",
    "wof:placetype":"venue"
},
  "geometry": {"coordinates":[-96.173956,43.074962],"type":"Point"}
}