{
  "type": "Feature",
  "properties": {
    "iso:country":"US",
    "sg:address":"4027 Glass Rd NE",
    "sg:city":"Cedar Rapids",
    "sg:classifiers":[
        {
            "category":"Health Services",
            "subcategory":"Clinic",
            "type":"Services"
        }
    ],
    "sg:phone":"+1 319 294 3527",
    "sg:postcode":"52402",
    "sg:province":"IA",
    "sg:tags":[
        "home"
    ],
    "wof:name":"Comfort Care Inc",
    "wof:placetype":"venue"
},
  "geometry": {"coordinates":[-91.69905900000001,42.017306],"type":"Point"}
}