{
  "type": "Feature",
  "properties": {
    "iso:country":"US",
    "sg:address":"412 Angle St",
    "sg:city":"Cedar Rapids",
    "sg:classifiers":[
        {
            "category":"Organizations",
            "subcategory":"Non-profit Organization",
            "type":"Services"
        }
    ],
    "sg:phone":"+1 319 363 0887",
    "sg:postcode":"52403",
    "sg:province":"IA",
    "wof:name":"Conner Center",
    "wof:placetype":"venue"
},
  "geometry": {"coordinates":[-91.536727,41.950646],"type":"Point"}
}