{
  "type": "Feature",
  "properties": {
    "iso:country":"US",
    "sg:address":"1057 210th Pl",
    "sg:city":"Pella",
    "sg:classifiers":[
        {
            "category":"Professional",
            "type":"Services"
        }
    ],
    "sg:phone":"+1 641 628 9678",
    "sg:postcode":"50219",
    "sg:province":"IA",
    "wof:name":"J & K Marine",
    "wof:placetype":"venue"
},
  "geometry": {"coordinates":[-92.948104,41.372225],"type":"Point"}
}