{
  "type": "Feature",
  "properties": {
    "addr:full":"701 G Ave W Oskaloosa IA 52577",
    "addr:housenumber":"701",
    "addr:postcode":"52577",
    "addr:street":"G Ave W Oskaloosa",
    "iso:country":"US",
    "sg:address":"701 G Ave W",
    "sg:city":"Oskaloosa",
    "sg:classifiers":[
        {
            "category":"Railroad",
            "type":"Transportation"
        }
    ],
    "sg:phone":"+1 641 672 2191",
    "sg:postcode":"52577",
    "sg:province":"IA",
    "wof:name":"Chicago Northwestern Trnsprtn",
    "wof:placetype":"venue"
},
  "geometry": {"coordinates":[-92.65218,41.301142],"type":"Point"}
}