{
  "type": "Feature",
  "properties": {
    "iso:country":"US",
    "sg:address":"3893 Quail Ave",
    "sg:city":"Manly",
    "sg:phone":"+1 641 454 3044",
    "sg:postcode":"50456",
    "sg:province":"IA",
    "sg:tags":[
        "farm",
        "grain",
        "cash"
    ],
    "wof:name":"Brad Dietrich",
    "wof:placetype":"venue"
},
  "geometry": {"coordinates":[-93.181003,43.327339],"type":"Point"}
}