{
  "type": "Feature",
  "properties": {
    "iso:country":"US",
    "sg:address":"1121 Prairie du Chien Rd",
    "sg:city":"Iowa City",
    "sg:classifiers":[
        {
            "category":"Shopping",
            "subcategory":"Bicycles & Sporting Goods",
            "type":"Retail Goods"
        }
    ],
    "sg:phone":"+1 319 466 1307",
    "sg:postcode":"52245",
    "sg:province":"IA",
    "sg:tags":[
        "repair"
    ],
    "wof:name":"D & D Arms",
    "wof:placetype":"venue"
},
  "geometry": {"coordinates":[-91.521306,41.678676],"type":"Point"}
}