{
  "type": "Feature",
  "properties": {
    "iso:country":"US",
    "sg:address":"221 3rd St SE",
    "sg:city":"Cedar Rapids",
    "sg:classifiers":[
        {
            "category":"Shopping",
            "subcategory":"Hobbies, Toys, & Games",
            "type":"Retail Goods"
        }
    ],
    "sg:phone":"+1 319 364 0506",
    "sg:postcode":"52401",
    "sg:province":"IA",
    "sg:tags":[
        "craft",
        "supply"
    ],
    "wof:name":"Art Cellar",
    "wof:placetype":"venue"
},
  "geometry": {"coordinates":[-91.666014,41.977786],"type":"Point"}
}