{
  "type": "Feature",
  "properties": {
    "addr:full":"608 S Gertrude St Burlington IA 52601",
    "addr:housenumber":"608",
    "addr:postcode":"52601",
    "addr:street":"S Gertrude St",
    "iso:country":"US",
    "sg:address":"608 S Gertrude St",
    "sg:city":"Burlington",
    "sg:classifiers":[
        {
            "category":"Retail",
            "subcategory":"Auto Repair",
            "type":"Services"
        }
    ],
    "sg:phone":"+1 319 754 4950",
    "sg:postcode":"52601",
    "sg:province":"IA",
    "sg:tags":[
        "automotive"
    ],
    "wof:name":"River City Customs & ACC",
    "wof:placetype":"venue"
},
  "geometry": {"coordinates":[-91.123608,40.803118],"type":"Point"}
}