{
  "type": "Feature",
  "properties": {
    "addr:full":"214 5th St SE Cresco IA 52136",
    "addr:housenumber":"214",
    "addr:postcode":"52136",
    "addr:street":"5Th St Se",
    "iso:country":"US",
    "sg:address":"214 5th St SE",
    "sg:city":"Cresco",
    "sg:classifiers":[
        {
            "category":"Retail",
            "subcategory":"Auto Repair",
            "type":"Services"
        }
    ],
    "sg:phone":"+1 563 547 4363",
    "sg:postcode":"52136",
    "sg:province":"IA",
    "sg:tags":[
        "truck"
    ],
    "wof:name":"East Side Truck & Tractor Rpr",
    "wof:placetype":"venue"
},
  "geometry": {"coordinates":[-92.11031699999999,43.370935],"type":"Point"}
}