{
  "type": "Feature",
  "properties": {
    "addr:full":"1481 140th St Sioux City SD 51106",
    "addr:housenumber":"1481",
    "addr:postcode":"51106",
    "addr:street":"140Th St",
    "iso:country":"US",
    "sg:address":"1481 140th St",
    "sg:city":"Sioux City",
    "sg:classifiers":[
        {
            "category":"Organizations",
            "subcategory":"Labor Organization",
            "type":"Services"
        }
    ],
    "sg:phone":"+1 712 258 0145",
    "sg:postcode":"51106",
    "sg:province":"SD",
    "wof:name":"Asbestos Workers Local Union",
    "wof:placetype":"venue"
},
  "geometry": {"coordinates":[-96.310107,42.504326],"type":"Point"}
}