{
  "type": "Feature",
  "properties": {
    "iso:country":"US",
    "sg:address":"1401 S Main St",
    "sg:city":"Fairfield",
    "sg:classifiers":[
        {
            "category":"Home & Garden",
            "subcategory":"Hardware",
            "type":"Retail Goods"
        }
    ],
    "sg:phone":"+1 641 472 2847",
    "sg:postcode":"52556",
    "sg:province":"IA",
    "wof:name":"Pedrick & Thorne Ace Hardware",
    "wof:placetype":"venue"
},
  "geometry": {"coordinates":[-91.963126,40.994868],"type":"Point"}
}