{
  "type": "Feature",
  "properties": {
    "iso:country":"US",
    "sg:address":"3627 Center Point Rd NE",
    "sg:city":"Cedar Rapids",
    "sg:classifiers":[
        {
            "category":"Professional",
            "subcategory":"Accounting & Tax Preparation",
            "type":"Services"
        }
    ],
    "sg:phone":"+1 319 393 8200",
    "sg:postcode":"52402",
    "sg:province":"IA",
    "sg:tags":[
        "bookkeeping",
        "general"
    ],
    "wof:name":"Accurate Bookkeeping Svc",
    "wof:placetype":"venue"
},
  "geometry": {"coordinates":[-91.664272,42.016774],"type":"Point"}
}