{
  "type": "Feature",
  "properties": {
    "iso:country":"US",
    "sg:address":"11716 125th St",
    "sg:city":"Lime Springs",
    "sg:classifiers":[
        {
            "category":"Insurance",
            "subcategory":"Insurance Agent",
            "type":"Services"
        }
    ],
    "sg:phone":"+1 563 547 3773",
    "sg:postcode":"52155",
    "sg:province":"IA",
    "wof:name":"Wacha Insurance",
    "wof:placetype":"venue"
},
  "geometry": {"coordinates":[-92.336917,43.33485],"type":"Point"}
}