{
  "type": "Feature",
  "properties": {
    "addr:full":"1127 W 9th St S Newton IA 50208",
    "addr:housenumber":"1127",
    "addr:postcode":"50208",
    "addr:street":"W 9Th St S",
    "iso:country":"US",
    "sg:address":"1127 W 9th St S",
    "sg:city":"Newton",
    "sg:classifiers":[
        {
            "category":"Professional",
            "type":"Services"
        }
    ],
    "sg:phone":"+1 641 792 5192",
    "sg:postcode":"50208",
    "sg:province":"IA",
    "sg:tags":[
        "establishment"
    ],
    "wof:name":"Hesse & Co",
    "wof:placetype":"venue"
},
  "geometry": {"coordinates":[-93.06283000000001,41.689964],"type":"Point"}
}