{
  "type": "Feature",
  "properties": {
    "iso:country":"US",
    "sg:address":"606 Main St",
    "sg:city":"Lowden",
    "sg:classifiers":[
        {
            "category":"Organizations",
            "subcategory":"Community Association",
            "type":"Services"
        }
    ],
    "sg:phone":"+1 563 941 5548",
    "sg:postcode":"52255",
    "sg:province":"IA",
    "sg:tags":[
        "military"
    ],
    "wof:name":"Legion",
    "wof:placetype":"venue"
},
  "geometry": {"coordinates":[-90.92974100000001,41.857709],"type":"Point"}
}