{
  "type": "Feature",
  "properties": {
    "iso:country":"US",
    "sg:address":"1258 200th St",
    "sg:city":"Barnum",
    "sg:phone":"+1 515 542 3332",
    "sg:postcode":"50518",
    "sg:province":"IA",
    "sg:tags":[
        "farm",
        "corn",
        "soybean"
    ],
    "wof:name":"Eugene Francois",
    "wof:placetype":"venue"
},
  "geometry": {"coordinates":[-94.391796,42.502404],"type":"Point"}
}