{
  "type": "Feature",
  "properties": {
    "addr:full":"109 1st Ave W Cascade IA 52033",
    "addr:housenumber":"109",
    "addr:postcode":"52033",
    "addr:street":"1St Ave W Cascade",
    "iso:country":"US",
    "sg:address":"109 1st Ave W",
    "sg:city":"Cascade",
    "sg:classifiers":[
        {
            "category":"Social Services",
            "subcategory":"Adult Care",
            "type":"Services"
        }
    ],
    "sg:phone":"+1 563 852 3047",
    "sg:postcode":"52033",
    "sg:province":"IA",
    "sg:tags":[
        "organization",
        "senior",
        "citizen"
    ],
    "wof:name":"Cascade Senior Citizens",
    "wof:placetype":"venue"
},
  "geometry": {"coordinates":[-91.01370300000001,42.298857],"type":"Point"}
}