{
  "type": "Feature",
  "properties": {
    "addr:full":"201 E Salem Ave Indianola IA 50125",
    "addr:housenumber":"201",
    "addr:postcode":"50125",
    "addr:street":"E Salem Ave",
    "iso:country":"US",
    "sg:address":"201 E Salem Ave",
    "sg:city":"Indianola",
    "sg:classifiers":[
        {
            "category":"Health Services",
            "subcategory":"Doctor",
            "type":"Services"
        }
    ],
    "sg:phone":"+1 515 961 8673",
    "sg:postcode":"50125",
    "sg:province":"IA",
    "sg:tags":[
        "dentist"
    ],
    "wof:name":"Family Dentistry",
    "wof:placetype":"venue"
},
  "geometry": {"coordinates":[-93.558308,41.360277],"type":"Point"}
}