{
  "type": "Feature",
  "properties": {
    "addr:full":"804 Kenyon Rd Fort Dodge IA 50501",
    "addr:housenumber":"804",
    "addr:postcode":"50501",
    "addr:street":"Kenyon Rd",
    "iso:country":"US",
    "sg:address":"804 Kenyon Rd",
    "sg:city":"Fort Dodge",
    "sg:classifiers":[
        {
            "category":"Health Services",
            "subcategory":"Health Practitioner",
            "type":"Services"
        }
    ],
    "sg:phone":"+1 515 574 6850",
    "sg:postcode":"50501",
    "sg:province":"IA",
    "sg:tags":[
        "physician",
        "assistant"
    ],
    "wof:name":"Diane Simons",
    "wof:placetype":"venue"
},
  "geometry": {"coordinates":[-94.189029,42.494243],"type":"Point"}
}