{
  "type": "Feature",
  "properties": {
    "iso:country":"US",
    "sg:address":"2001 Lower Muscatine Rd",
    "sg:city":"Iowa City",
    "sg:classifiers":[
        {
            "category":"Government",
            "subcategory":"Fire Station",
            "type":"Public Place"
        }
    ],
    "sg:phone":"+1 319 356 5265",
    "sg:postcode":"52240",
    "sg:province":"IA",
    "sg:tags":[
        "department"
    ],
    "wof:name":"Iowa City Fire Dept",
    "wof:placetype":"venue"
},
  "geometry": {"coordinates":[-91.502629,41.639081],"type":"Point"}
}