{
  "type": "Feature",
  "properties": {
    "iso:country":"US",
    "sg:address":"1001 S 6th St",
    "sg:city":"Council Bluffs",
    "sg:classifiers":[
        {
            "category":"Wholesale",
            "subcategory":"Toys & Hobbies",
            "type":"Manufacturing & Wholesale Goods"
        }
    ],
    "sg:phone":"+1 712 328 8417",
    "sg:postcode":"51501",
    "sg:province":"IA",
    "sg:tags":[
        "wholesaler"
    ],
    "wof:name":"Heartland Hobby Wholesale",
    "wof:placetype":"venue"
},
  "geometry": {"coordinates":[-95.853055,41.25156],"type":"Point"}
}