{
  "type": "Feature",
  "properties": {
    "iso:country":"US",
    "sg:address":"148 W Jefferson St",
    "sg:city":"Osceola",
    "sg:classifiers":[
        {
            "category":"Health Services",
            "subcategory":"Doctor",
            "type":"Services"
        }
    ],
    "sg:phone":"+1 641 342 6541",
    "sg:postcode":"50213",
    "sg:province":"IA",
    "sg:tags":[
        "dentist"
    ],
    "wof:name":"Bruce A Harris DDS",
    "wof:placetype":"venue"
},
  "geometry": {"coordinates":[-93.765672,41.033477],"type":"Point"}
}