{
  "type": "Feature",
  "properties": {
    "addr:full":"1201 S Main St Burlington IA 52601",
    "addr:housenumber":"1201",
    "addr:postcode":"52601",
    "addr:street":"S Main St",
    "iso:country":"US",
    "sg:address":"1201 S Main St",
    "sg:city":"Burlington",
    "sg:classifiers":[
        {
            "category":"Autos & Motor Vehicles",
            "subcategory":"Fuel & Gas Station",
            "type":"Retail Goods"
        }
    ],
    "sg:phone":"+1 319 754 7806",
    "sg:postcode":"52601",
    "sg:province":"IA",
    "sg:tags":[
        "oil"
    ],
    "wof:name":"Daco Service Co",
    "wof:placetype":"venue"
},
  "geometry": {"coordinates":[-91.09986499999999,40.798235],"type":"Point"}
}