{
  "type": "Feature",
  "properties": {
    "addr:full":"2000 Walker St Des Moines IA 50317",
    "addr:housenumber":"2000",
    "addr:postcode":"50317",
    "addr:street":"Walker St",
    "iso:country":"US",
    "sg:address":"2000 Walker St",
    "sg:city":"Des Moines",
    "sg:classifiers":[
        {
            "category":"Organizations",
            "subcategory":"Labor Organization",
            "type":"Services"
        }
    ],
    "sg:phone":"+1 515 262 9571",
    "sg:postcode":"50317",
    "sg:province":"IA",
    "wof:name":"Iowa Federation Of Labor",
    "wof:placetype":"venue"
},
  "geometry": {"coordinates":[-93.580733,41.599556],"type":"Point"}
}