{
  "type": "Feature",
  "properties": {
    "iso:country":"US",
    "sg:address":"1401 N 2nd St",
    "sg:city":"Clinton",
    "sg:classifiers":[
        {
            "category":"Banks & Credit Unions",
            "subcategory":"Bank",
            "type":"Services"
        }
    ],
    "sg:phone":"+1 563 244 8000",
    "sg:postcode":"52732",
    "sg:province":"IA",
    "sg:tags":[
        "cashing",
        "check"
    ],
    "wof:name":"Payday Loan",
    "wof:placetype":"venue"
},
  "geometry": {"coordinates":[-90.18401799999999,41.861101],"type":"Point"}
}