{
  "type": "Feature",
  "properties": {
    "iso:country":"US",
    "sg:address":"914 W Sheridan Ave",
    "sg:city":"Shenandoah",
    "sg:classifiers":[
        {
            "category":"Home & Garden",
            "subcategory":"Carpets & Floor Coverings",
            "type":"Retail Goods"
        }
    ],
    "sg:phone":"+1 712 246 4762",
    "sg:postcode":"51601",
    "sg:province":"IA",
    "sg:tags":[
        "dealer",
        "rug"
    ],
    "wof:name":"Bopp's Carpet",
    "wof:placetype":"venue"
},
  "geometry": {"coordinates":[-95.37822,40.765866],"type":"Point"}
}