{
  "type": "Feature",
  "properties": {
    "iso:country":"US",
    "sg:address":"1305 W 53rd St",
    "sg:city":"Davenport",
    "sg:classifiers":[
        {
            "category":"Professional",
            "subcategory":"Accounting & Tax Preparation",
            "type":"Services"
        }
    ],
    "sg:phone":"+1 563 323 9224",
    "sg:postcode":"52806",
    "sg:province":"IA",
    "sg:tags":[
        "bookkeeping",
        "return",
        "billing",
        "preparation-business"
    ],
    "wof:name":"Resource Accounting And Tax Service Inc",
    "wof:placetype":"venue"
},
  "geometry": {"coordinates":[-90.591038,41.57382],"type":"Point"}
}