{
  "type": "Feature",
  "properties": {
    "addr:full":"5909 Grand Ave Des Moines IA 50312",
    "addr:housenumber":"5909",
    "addr:postcode":"50312",
    "addr:street":"Grand Ave",
    "iso:country":"US",
    "sg:address":"5909 Grand Ave",
    "sg:city":"Des Moines",
    "sg:classifiers":[
        {
            "category":"Building & Trades",
            "subcategory":"Construction",
            "type":"Services"
        }
    ],
    "sg:phone":"+1 515 255 1557",
    "sg:postcode":"50312",
    "sg:province":"IA",
    "sg:tags":[
        "home",
        "builder"
    ],
    "wof:name":"Madden Construction",
    "wof:placetype":"venue"
},
  "geometry": {"coordinates":[-93.69806,41.582699],"type":"Point"}
}