{
  "type": "Feature",
  "properties": {
    "addr:full":"512 Main St Lorimor IA 50149",
    "addr:housenumber":"512",
    "addr:postcode":"50149",
    "addr:street":"Main St",
    "iso:country":"US",
    "sg:address":"512 Main St",
    "sg:city":"Lorimor",
    "sg:classifiers":[
        {
            "category":"Government",
            "subcategory":"Post Office",
            "type":"Public Place"
        }
    ],
    "sg:phone":"+1 641 763 2119",
    "sg:postcode":"50149",
    "sg:province":"IA",
    "wof:name":"US Post Office",
    "wof:placetype":"venue"
},
  "geometry": {"coordinates":[-94.056523,41.126962],"type":"Point"}
}