{
  "type": "Feature",
  "properties": {
    "addr:full":"20851 270th St Grundy Center IA 50638",
    "addr:housenumber":"20851",
    "addr:postcode":"50638",
    "addr:street":"270Th St",
    "iso:country":"US",
    "sg:address":"20851 270th St",
    "sg:city":"Grundy Center",
    "sg:classifiers":[
        {
            "category":"Home & Garden",
            "subcategory":"Building Materials",
            "type":"Retail Goods"
        }
    ],
    "sg:phone":"+1 319 824 3550",
    "sg:postcode":"50638",
    "sg:province":"IA",
    "sg:tags":[
        "glass",
        "leaded"
    ],
    "wof:name":"Shari's Glass",
    "wof:placetype":"venue"
},
  "geometry": {"coordinates":[-92.811702,42.311054],"type":"Point"}
}