{
  "type": "Feature",
  "properties": {
    "iso:country":"US",
    "sg:address":"268 Jess St",
    "sg:city":"Bernard",
    "sg:classifiers":[
        {
            "category":"Bars & Pubs",
            "type":"Food & Drink"
        }
    ],
    "sg:phone":"+1 563 879 3686",
    "sg:postcode":"52032",
    "sg:province":"IA",
    "wof:name":"Old Mcdonald's Bar & Grill",
    "wof:placetype":"venue"
},
  "geometry": {"coordinates":[-90.831513,42.313984],"type":"Point"}
}