{
  "type": "Feature",
  "properties": {
    "iso:country":"US",
    "sg:address":"412 S Van Buren St",
    "sg:city":"Iowa City",
    "sg:classifiers":[
        {
            "category":"Retail",
            "subcategory":"Auto Repair",
            "type":"Services"
        }
    ],
    "sg:phone":"+1 319 351 7671",
    "sg:postcode":"52240",
    "sg:province":"IA",
    "sg:tags":[
        "body",
        "automobile",
        "painting"
    ],
    "wof:name":"Nick's Body Shop",
    "wof:placetype":"venue"
},
  "geometry": {"coordinates":[-91.52869200000001,41.655514],"type":"Point"}
}