{
  "type": "Feature",
  "properties": {
    "iso:country":"US",
    "sg:address":"6250 Crow Valley Dr",
    "sg:city":"Bettendorf",
    "sg:classifiers":[
        {
            "category":"Professional",
            "type":"Services"
        }
    ],
    "sg:phone":"+1 563 355 5257",
    "sg:postcode":"52722",
    "sg:province":"IA",
    "sg:tags":[
        "establishment"
    ],
    "wof:name":"Kellenberger & Kellenberger",
    "wof:placetype":"venue"
},
  "geometry": {"coordinates":[-90.498845,41.585153],"type":"Point"}
}