{
  "type": "Feature",
  "properties": {
    "iso:country":"US",
    "sg:address":"1661 S Monroe Ave",
    "sg:city":"Mason City",
    "sg:classifiers":[
        {
            "category":"Building & Trades",
            "subcategory":"Cleaning & Sanitation",
            "type":"Services"
        }
    ],
    "sg:phone":"+1 641 424 6509",
    "sg:postcode":"50401",
    "sg:province":"IA",
    "sg:tags":[
        "window"
    ],
    "wof:name":"Shineway Window Cleaning",
    "wof:placetype":"venue"
},
  "geometry": {"coordinates":[-93.210977,43.136301],"type":"Point"}
}