{
  "type": "Feature",
  "properties": {
    "addr:full":"1400 2nd Ave SE Apt 101 Cedar Rapids IA 52403",
    "addr:housenumber":"1400;101",
    "addr:postcode":"52403",
    "addr:street":"2Nd Ave Se Apt",
    "iso:country":"US",
    "sg:address":"1400 2nd Ave SE Apt 101",
    "sg:city":"Cedar Rapids",
    "sg:classifiers":[
        {
            "category":"Real Estate",
            "subcategory":"Real Estate Operator",
            "type":"Services"
        }
    ],
    "sg:phone":"+1 319 364 4121",
    "sg:postcode":"52403",
    "sg:province":"IA",
    "sg:tags":[
        "apartment"
    ],
    "wof:name":"Commonwealth Apartments",
    "wof:placetype":"venue"
},
  "geometry": {"coordinates":[-91.652901,41.986401],"type":"Point"}
}