{
  "type": "Feature",
  "properties": {
    "iso:country":"US",
    "sg:address":"1264 425th Ave",
    "sg:city":"Clinton",
    "sg:phone":"+1 563 682 7447",
    "sg:postcode":"52732",
    "sg:province":"IA",
    "sg:tags":[
        "farm",
        "corn",
        "soybean"
    ],
    "wof:name":"Wilcke Bauernhof Corp",
    "wof:placetype":"venue"
},
  "geometry": {"coordinates":[-90.26737,41.995092],"type":"Point"}
}