{
  "type": "Feature",
  "properties": {
    "iso:country":"US",
    "sg:address":"6 S 5th St",
    "sg:city":"Estherville",
    "sg:classifiers":[
        {
            "category":"Personal",
            "subcategory":"Beauty Salon",
            "type":"Services"
        }
    ],
    "sg:phone":"+1 712 362 2317",
    "sg:postcode":"51334",
    "sg:province":"IA",
    "wof:name":"Fifth Street Salon",
    "wof:placetype":"venue"
},
  "geometry": {"coordinates":[-94.837902,43.401915],"type":"Point"}
}