{
  "type": "Feature",
  "properties": {
    "iso:country":"US",
    "sg:address":"3626 Jackson Ave",
    "sg:city":"Boyden",
    "sg:phone":"+1 712 722 2198",
    "sg:postcode":"51234",
    "sg:province":"IA",
    "sg:tags":[
        "farm",
        "corn"
    ],
    "wof:name":"Robert Westra",
    "wof:placetype":"venue"
},
  "geometry": {"coordinates":[-96.058155,43.124161],"type":"Point"}
}