{
  "type": "Feature",
  "properties": {
    "iso:country":"US",
    "sg:address":"2986 Barrows Ave",
    "sg:city":"Bussey",
    "sg:classifiers":[
        {
            "category":"Farming",
            "subcategory":"Farm",
            "type":"Manufacturing & Wholesale Goods"
        }
    ],
    "sg:phone":"+1 641 944 5804",
    "sg:postcode":"50044",
    "sg:province":"IA",
    "sg:tags":[
        "crop",
        "general"
    ],
    "wof:name":"Keith Bailey",
    "wof:placetype":"venue"
},
  "geometry": {"coordinates":[-92.851055,41.220642],"type":"Point"}
}