{
  "type": "Feature",
  "properties": {
    "iso:country":"US",
    "sg:address":"816 1st Ave S",
    "sg:city":"Fort Dodge",
    "sg:classifiers":[
        {
            "category":"Bars & Pubs",
            "type":"Food & Drink"
        }
    ],
    "sg:phone":"+1 515 573 2187",
    "sg:postcode":"50501",
    "sg:province":"IA",
    "sg:tags":[
        "club",
        "night"
    ],
    "wof:name":"Pee Wee's Pub",
    "wof:placetype":"venue"
},
  "geometry": {"coordinates":[-94.186031,42.504339],"type":"Point"}
}