{
  "type": "Feature",
  "properties": {
    "iso:country":"US",
    "sg:address":"824 Flindt Dr",
    "sg:city":"Storm Lake",
    "sg:classifiers":[
        {
            "category":"Government",
            "subcategory":"Office",
            "type":"Public Place"
        }
    ],
    "sg:phone":"+1 712 732 5056",
    "sg:postcode":"50588",
    "sg:province":"IA",
    "wof:name":"Buena Vista Cnty Extension Svc",
    "wof:placetype":"venue"
},
  "geometry": {"coordinates":[-95.191422,42.646696],"type":"Point"}
}