{
  "type": "Feature",
  "properties": {
    "iso:country":"US",
    "sg:address":"31661 Hwy 52",
    "sg:city":"Bellevue",
    "sg:classifiers":[
        {
            "category":"Freight",
            "type":"Transportation"
        }
    ],
    "sg:phone":"+1 563 872 3897",
    "sg:postcode":"52031",
    "sg:province":"IA",
    "sg:tags":[
        "operator",
        "local",
        "trucking"
    ],
    "wof:name":"Randy Feller Trucking",
    "wof:placetype":"venue"
},
  "geometry": {"coordinates":[-90.45635900000001,42.304678],"type":"Point"}
}