{
  "type": "Feature",
  "properties": {
    "iso:country":"US",
    "sg:address":"1205 Springbrook Ln",
    "sg:city":"De Witt",
    "sg:classifiers":[
        {
            "category":"Recreation",
            "type":"Entertainment"
        }
    ],
    "sg:phone":"+1 563 659 1432",
    "sg:postcode":"52742",
    "sg:province":"IA",
    "wof:name":"Mississippi Vlly Gymnstcs Acdm",
    "wof:placetype":"venue"
},
  "geometry": {"coordinates":[-90.54777,41.834369],"type":"Point"}
}