{
  "type": "Feature",
  "properties": {
    "addr:full":"728 SE Creekview Dr Ankeny IA 50021",
    "addr:housenumber":"728",
    "addr:postcode":"50021",
    "addr:street":"Se Creekview Dr",
    "iso:country":"US",
    "sg:address":"728 SE Creekview Dr",
    "sg:city":"Ankeny",
    "sg:classifiers":[
        {
            "category":"Manufacturing",
            "subcategory":"Chemicals & Compounds",
            "type":"Manufacturing & Wholesale Goods"
        }
    ],
    "sg:phone":"+1 515 965 5667",
    "sg:postcode":"50021",
    "sg:province":"IA",
    "sg:tags":[
        "pesticide",
        "ag"
    ],
    "sg:website":"www.helenachemical.com",
    "wof:name":"Helena Chemical Co",
    "wof:placetype":"venue"
},
  "geometry": {"coordinates":[-93.573538,41.724943],"type":"Point"}
}