{
  "type": "Feature",
  "properties": {
    "iso:country":"US",
    "sg:address":"2717 Martin Luther King Jr Pkwy",
    "sg:city":"Des Moines",
    "sg:classifiers":[
        {
            "category":"Food & Beverages",
            "subcategory":"Groceries & Convenience Stores",
            "type":"Retail Goods"
        }
    ],
    "sg:phone":"+1 515 271 9157",
    "sg:postcode":"50310",
    "sg:province":"IA",
    "sg:tags":[
        "grocer"
    ],
    "wof:name":"Institutional Wholesale",
    "wof:placetype":"venue"
},
  "geometry": {"coordinates":[-93.646586,41.615498],"type":"Point"}
}