{
  "type": "Feature",
  "properties": {
    "iso:country":"US",
    "sg:address":"212 N Madison St",
    "sg:city":"Iowa City",
    "sg:classifiers":[
        {
            "category":"Education",
            "subcategory":"College",
            "type":"Public Place"
        }
    ],
    "sg:phone":"+1 319 335 8064",
    "sg:postcode":"52242",
    "sg:province":"IA",
    "sg:tags":[
        "school"
    ],
    "wof:name":"Univ Of Ia College Of Medicine",
    "wof:placetype":"venue"
},
  "geometry": {"coordinates":[-91.537515,41.664491],"type":"Point"}
}