{
  "type": "Feature",
  "properties": {
    "addr:full":"102 E Washington St Sigourney IA 52591",
    "addr:housenumber":"102",
    "addr:postcode":"52591",
    "addr:street":"E Washington St",
    "iso:country":"US",
    "sg:address":"102 E Washington St",
    "sg:city":"Sigourney",
    "sg:classifiers":[
        {
            "category":"Government",
            "subcategory":"Office",
            "type":"Public Place"
        }
    ],
    "sg:phone":"+1 641 622 2680",
    "sg:postcode":"52591",
    "sg:province":"IA",
    "wof:name":"Keokuk County Extension Svc",
    "wof:placetype":"venue"
},
  "geometry": {"coordinates":[-92.20509,41.333739],"type":"Point"}
}