{
  "type": "Feature",
  "properties": {
    "iso:country":"US",
    "sg:address":"2111 Old Hwy 163",
    "sg:city":"Pella",
    "sg:classifiers":[
        {
            "category":"Shopping",
            "type":"Retail Goods"
        }
    ],
    "sg:phone":"+1 641 628 1344",
    "sg:postcode":"50219",
    "sg:province":"IA",
    "sg:tags":[
        "monument"
    ],
    "wof:name":"Mc Call Monument Works",
    "wof:placetype":"venue"
},
  "geometry": {"coordinates":[-92.952443,41.415704],"type":"Point"}
}