{
  "type": "Feature",
  "properties": {
    "addr:full":"203 E Main St Riceville IA 50466",
    "addr:housenumber":"203",
    "addr:postcode":"50466",
    "addr:street":"E Main St",
    "iso:country":"US",
    "sg:address":"203 E Main St",
    "sg:city":"Riceville",
    "sg:classifiers":[
        {
            "category":"Food & Beverages",
            "subcategory":"Groceries & Convenience Stores",
            "type":"Retail Goods"
        }
    ],
    "sg:phone":"+1 641 985 2800",
    "sg:postcode":"50466",
    "sg:province":"IA",
    "wof:name":"Andy's Mini Mart",
    "wof:placetype":"venue"
},
  "geometry": {"coordinates":[-92.552791,43.363787],"type":"Point"}
}