{
  "type": "Feature",
  "properties": {
    "iso:country":"US",
    "sg:address":"4016 Morningside Ave",
    "sg:city":"Sioux City",
    "sg:classifiers":[
        {
            "category":"Health Services",
            "subcategory":"Doctor",
            "type":"Services"
        }
    ],
    "sg:phone":"+1 712 276 2206",
    "sg:postcode":"51106",
    "sg:province":"SD",
    "sg:tags":[
        "dentist"
    ],
    "wof:name":"Morningside Dental Clinic",
    "wof:placetype":"venue"
},
  "geometry": {"coordinates":[-96.354957,42.47063],"type":"Point"}
}