{
  "type": "Feature",
  "properties": {
    "iso:country":"US",
    "sg:address":"3302 Ave L",
    "sg:city":"Fort Madison",
    "sg:classifiers":[
        {
            "category":"Shopping",
            "subcategory":"Bicycles & Sporting Goods",
            "type":"Retail Goods"
        }
    ],
    "sg:phone":"+1 319 376 0096",
    "sg:postcode":"52627",
    "sg:province":"IA",
    "sg:tags":[
        "equipment",
        "skateboard"
    ],
    "wof:name":"Boardwalk",
    "wof:placetype":"venue"
},
  "geometry": {"coordinates":[-91.354135,40.626605],"type":"Point"}
}