{
  "type": "Feature",
  "properties": {
    "iso:country":"US",
    "sg:address":"13683 590th Ave",
    "sg:city":"Roland",
    "sg:classifiers":[
        {
            "category":"Real Estate",
            "subcategory":"Real Estate Operator",
            "type":"Services"
        }
    ],
    "sg:phone":"+1 515 388 4810",
    "sg:postcode":"50236",
    "sg:province":"IA",
    "sg:tags":[
        "property",
        "lessor"
    ],
    "wof:name":"Esther R Frandsen",
    "wof:placetype":"venue"
},
  "geometry": {"coordinates":[-93.521344,42.15636],"type":"Point"}
}