{
  "type": "Feature",
  "properties": {
    "addr:full":"308 S 1st St Guttenberg IA 52052",
    "addr:housenumber":"308",
    "addr:postcode":"52052",
    "addr:street":"S 1St St",
    "iso:country":"US",
    "sg:address":"308 S 1st St",
    "sg:city":"Guttenberg",
    "sg:classifiers":[
        {
            "category":"Building & Trades",
            "subcategory":"Plumbing",
            "type":"Services"
        }
    ],
    "sg:phone":"+1 563 252 3159",
    "sg:postcode":"52052",
    "sg:province":"IA",
    "sg:tags":[
        "conditioning",
        "air",
        "system",
        "contractor"
    ],
    "wof:name":"Meyer Mechanical Contracting",
    "wof:placetype":"venue"
},
  "geometry": {"coordinates":[-91.097244,42.783509],"type":"Point"}
}