{
  "type": "Feature",
  "properties": {
    "iso:country":"US",
    "sg:address":"4444 Douglas Ave",
    "sg:city":"Des Moines",
    "sg:classifiers":[
        {
            "category":"Restaurant",
            "type":"Food & Drink"
        }
    ],
    "sg:phone":"+1 515 270 6058",
    "sg:postcode":"50310",
    "sg:province":"IA",
    "wof:name":"Porky's Diner",
    "wof:placetype":"venue"
},
  "geometry": {"coordinates":[-93.68006800000001,41.629412],"type":"Point"}
}