{
  "type": "Feature",
  "properties": {
    "addr:full":"724 10th Ave Coralville IA 52241",
    "addr:housenumber":"724",
    "addr:postcode":"52241",
    "addr:street":"10Th Ave",
    "iso:country":"US",
    "sg:address":"724 10th Ave",
    "sg:city":"Coralville",
    "sg:classifiers":[
        {
            "category":"Personal",
            "subcategory":"Beauty Salon",
            "type":"Services"
        }
    ],
    "sg:phone":"+1 319 341 9399",
    "sg:postcode":"52241",
    "sg:province":"IA",
    "wof:name":"Greenman Hair & Body Studio",
    "wof:placetype":"venue"
},
  "geometry": {"coordinates":[-91.57814500000001,41.679778],"type":"Point"}
}