{
  "type": "Feature",
  "properties": {
    "iso:country":"US",
    "sg:address":"210 2nd Ave",
    "sg:city":"Des Moines",
    "sg:classifiers":[
        {
            "category":"Parking",
            "type":"Transportation"
        }
    ],
    "sg:phone":"+1 515 243 8442",
    "sg:postcode":"50309",
    "sg:province":"IA",
    "sg:tags":[
        "garage"
    ],
    "wof:name":"AMPCO System Parking",
    "wof:placetype":"venue"
},
  "geometry": {"coordinates":[-93.61947000000001,41.586028],"type":"Point"}
}