{
  "type": "Feature",
  "properties": {
    "iso:country":"US",
    "sg:address":"1110 N Grand Ave",
    "sg:city":"Charles City",
    "sg:classifiers":[
        {
            "category":"Home & Garden",
            "subcategory":"Household Appliances",
            "type":"Retail Goods"
        }
    ],
    "sg:phone":"+1 641 228 4418",
    "sg:postcode":"50616",
    "sg:province":"IA",
    "sg:tags":[
        "cleaners",
        "vacuum"
    ],
    "wof:name":"Vac Shack & Sewing Ctr",
    "wof:placetype":"venue"
},
  "geometry": {"coordinates":[-92.672451,43.073026],"type":"Point"}
}