{
  "type": "Feature",
  "properties": {
    "iso:country":"US",
    "sg:address":"126 N Ford St",
    "sg:city":"Anamosa",
    "sg:classifiers":[
        {
            "category":"Social Services",
            "subcategory":"Adult Care",
            "type":"Services"
        }
    ],
    "sg:phone":"+1 319 462 4947",
    "sg:postcode":"52205",
    "sg:province":"IA",
    "sg:tags":[
        "residential"
    ],
    "wof:name":"Evelyn Merrill",
    "wof:placetype":"venue"
},
  "geometry": {"coordinates":[-91.285555,42.109217],"type":"Point"}
}