{
  "type": "Feature",
  "properties": {
    "iso:country":"US",
    "sg:address":"606 E Colorado St",
    "sg:city":"Davenport",
    "sg:classifiers":[
        {
            "category":"Building & Trades",
            "subcategory":"Cleaning & Sanitation",
            "type":"Services"
        }
    ],
    "sg:phone":"+1 563 370 6417",
    "sg:postcode":"52803",
    "sg:province":"IA",
    "sg:tags":[
        "snow",
        "removal"
    ],
    "wof:name":"Eric's Snow Removal",
    "wof:placetype":"venue"
},
  "geometry": {"coordinates":[-90.564768,41.545241],"type":"Point"}
}