{
  "type": "Feature",
  "properties": {
    "iso:country":"US",
    "sg:address":"5111 59th Ave W",
    "sg:city":"Muscatine",
    "sg:classifiers":[
        {
            "category":"Utilities",
            "subcategory":"Refuse",
            "type":"Services"
        }
    ],
    "sg:phone":"+1 563 263 5474",
    "sg:postcode":"52761",
    "sg:province":"IA",
    "sg:tags":[
        "garbage",
        "collection"
    ],
    "wof:name":"L & M Waste Systems",
    "wof:placetype":"venue"
},
  "geometry": {"coordinates":[-91.118905,41.368962],"type":"Point"}
}