{
  "type": "Feature",
  "properties": {
    "iso:country":"US",
    "sg:address":"511 W Benton St",
    "sg:city":"Winterset",
    "sg:classifiers":[
        {
            "category":"Professional",
            "subcategory":"Advertising",
            "type":"Services"
        }
    ],
    "sg:phone":"+1 515 462 3479",
    "sg:postcode":"50273",
    "sg:province":"IA",
    "sg:tags":[
        "agency"
    ],
    "wof:name":"Married In Madison County",
    "wof:placetype":"venue"
},
  "geometry": {"coordinates":[-94.019256,41.340246],"type":"Point"}
}