{
  "type": "Feature",
  "properties": {
    "addr:full":"404 Heivly St Decorah IA 52101",
    "addr:housenumber":"404",
    "addr:postcode":"52101",
    "addr:street":"Heivly St",
    "iso:country":"US",
    "sg:address":"404 Heivly St",
    "sg:city":"Decorah",
    "sg:classifiers":[
        {
            "category":"Government",
            "subcategory":"Office",
            "type":"Public Place"
        }
    ],
    "sg:phone":"+1 563 382 9684",
    "sg:postcode":"52101",
    "sg:province":"IA",
    "sg:tags":[
        "federal",
        "security"
    ],
    "wof:name":"US Army Reserve",
    "wof:placetype":"venue"
},
  "geometry": {"coordinates":[-91.789376,43.305197],"type":"Point"}
}