{
  "type": "Feature",
  "properties": {
    "addr:full":"1321 Sunset St Iowa City IA 52246",
    "addr:housenumber":"1321",
    "addr:postcode":"52246",
    "addr:street":"Sunset St",
    "iso:country":"US",
    "sg:address":"1321 Sunset St",
    "sg:city":"Iowa City",
    "sg:classifiers":[
        {
            "category":"Health Services",
            "subcategory":"Doctor",
            "type":"Services"
        }
    ],
    "sg:phone":"+1 319 354 7616",
    "sg:postcode":"52246",
    "sg:province":"IA",
    "sg:tags":[
        "dentist"
    ],
    "wof:name":"Lanny V Kampfe DDS",
    "wof:placetype":"venue"
},
  "geometry": {"coordinates":[-91.56011599999999,41.643144],"type":"Point"}
}