{
  "type": "Feature",
  "properties": {
    "iso:country":"US",
    "sg:address":"1996 220th Ave",
    "sg:city":"Bussey",
    "sg:classifiers":[
        {
            "category":"Professional",
            "subcategory":"Business Services",
            "type":"Services"
        }
    ],
    "sg:phone":"+1 641 944 5577",
    "sg:postcode":"50044",
    "sg:province":"IA",
    "wof:name":"Thats A Wrap",
    "wof:placetype":"venue"
},
  "geometry": {"coordinates":[-92.927583,41.23194],"type":"Point"}
}