{
  "type": "Feature",
  "properties": {
    "iso:country":"US",
    "sg:address":"3643 450th Ave",
    "sg:city":"Emmetsburg",
    "sg:classifiers":[
        {
            "category":"Manufacturing",
            "subcategory":"Chemicals & Compounds",
            "type":"Manufacturing & Wholesale Goods"
        }
    ],
    "sg:phone":"+1 712 852 4151",
    "sg:postcode":"50536",
    "sg:province":"IA",
    "wof:name":"Osmonics/Autotrol",
    "wof:placetype":"venue"
},
  "geometry": {"coordinates":[-94.698747,43.119203],"type":"Point"}
}