{
  "type": "Feature",
  "properties": {
    "iso:country":"US",
    "sg:address":"666 Walnut St",
    "sg:city":"Des Moines",
    "sg:classifiers":[
        {
            "category":"Professional",
            "subcategory":"Lawyer & Legal Services",
            "type":"Services"
        }
    ],
    "sg:phone":"+1 515 283 4646",
    "sg:postcode":"50309",
    "sg:province":"IA",
    "sg:tags":[
        "attorney"
    ],
    "wof:name":"Norwegian Consul",
    "wof:placetype":"venue"
},
  "geometry": {"coordinates":[-93.62521,41.58575],"type":"Point"}
}