{
  "type": "Feature",
  "properties": {
    "iso:country":"US",
    "sg:address":"3145 170th St",
    "sg:city":"Goldfield",
    "sg:classifiers":[
        {
            "category":"Farming",
            "subcategory":"Farm",
            "type":"Manufacturing & Wholesale Goods"
        }
    ],
    "sg:phone":"+1 515 824 3581",
    "sg:postcode":"50542",
    "sg:province":"IA",
    "sg:tags":[
        "crop",
        "general"
    ],
    "wof:name":"Haverly Farms Inc",
    "wof:placetype":"venue"
},
  "geometry": {"coordinates":[-94.029934,42.804133],"type":"Point"}
}