{
  "type": "Feature",
  "properties": {
    "addr:full":"1420 Tri View Ave Sioux City IA 51103",
    "addr:housenumber":"1420",
    "addr:postcode":"51103",
    "addr:street":"Tri View Ave",
    "iso:country":"US",
    "sg:address":"1420 Tri View Ave",
    "sg:city":"Sioux City",
    "sg:classifiers":[
        {
            "category":"Banks & Credit Unions",
            "subcategory":"Bank",
            "type":"Services"
        }
    ],
    "sg:phone":"+1 712 252 4368",
    "sg:postcode":"51103",
    "sg:province":"IA",
    "sg:website":"www.telcotriad.org",
    "wof:name":"Telco Triad Community CU",
    "wof:placetype":"venue"
},
  "geometry": {"coordinates":[-96.42475,42.494356],"type":"Point"}
}