{
  "type": "Feature",
  "properties": {
    "iso:country":"US",
    "sg:address":"613 W 4th St",
    "sg:city":"Waterloo",
    "sg:classifiers":[
        {
            "category":"Organizations",
            "subcategory":"Religious Organization",
            "type":"Services"
        }
    ],
    "sg:phone":"+1 319 232 4773",
    "sg:postcode":"50702",
    "sg:province":"IA",
    "sg:tags":[
        "church"
    ],
    "wof:name":"St Demetrios' Greek Orthodox",
    "wof:placetype":"venue"
},
  "geometry": {"coordinates":[-92.34425299999999,42.491274],"type":"Point"}
}