{
  "type": "Feature",
  "properties": {
    "iso:country":"US",
    "sg:address":"332 N 2nd St",
    "sg:city":"Wapello",
    "sg:classifiers":[
        {
            "category":"Personal",
            "subcategory":"Beauty Salon",
            "type":"Services"
        }
    ],
    "sg:phone":"+1 319 527 3010",
    "sg:postcode":"52653",
    "sg:province":"IA",
    "wof:name":"Shades Hair & Tanning Salon",
    "wof:placetype":"venue"
},
  "geometry": {"coordinates":[-91.185643,41.18248],"type":"Point"}
}