{
  "type": "Feature",
  "properties": {
    "addr:full":"1675 2nd Ave Marion IA 52302",
    "addr:housenumber":"1675",
    "addr:postcode":"52302",
    "addr:street":"2Nd Ave",
    "iso:country":"US",
    "sg:address":"1675 2nd Ave",
    "sg:city":"Marion",
    "sg:classifiers":[
        {
            "category":"Building & Trades",
            "subcategory":"Construction",
            "type":"Services"
        }
    ],
    "sg:phone":"+1 319 377 0898",
    "sg:postcode":"52302",
    "sg:province":"IA",
    "sg:tags":[
        "concrete",
        "contractor"
    ],
    "wof:name":"Heim Bobcat & Concrete Constr",
    "wof:placetype":"venue"
},
  "geometry": {"coordinates":[-91.59204200000001,42.02917],"type":"Point"}
}