{
  "type": "Feature",
  "properties": {
    "iso:country":"US",
    "sg:address":"1100 Oregon St",
    "sg:city":"Muscatine",
    "sg:classifiers":[
        {
            "category":"Government",
            "subcategory":"Fire Station",
            "type":"Public Place"
        }
    ],
    "sg:phone":"+1 563 263 9232",
    "sg:postcode":"52761",
    "sg:province":"IA",
    "sg:tags":[
        "department"
    ],
    "wof:name":"Muscatine Fire Dept",
    "wof:placetype":"venue"
},
  "geometry": {"coordinates":[-91.063238,41.404776],"type":"Point"}
}