{
  "type": "Feature",
  "properties": {
    "iso:country":"US",
    "sg:address":"608 1st St",
    "sg:city":"Keosauqua",
    "sg:classifiers":[
        {
            "category":"Education",
            "subcategory":"Library",
            "type":"Public Place"
        }
    ],
    "sg:phone":"+1 319 293 3766",
    "sg:postcode":"52565",
    "sg:province":"IA",
    "wof:name":"Keosauqua Public Library",
    "wof:placetype":"venue"
},
  "geometry": {"coordinates":[-91.962148,40.73012],"type":"Point"}
}