{
  "type": "Feature",
  "properties": {
    "addr:full":"2408 US Hwy 18 Wesley IA 50483",
    "addr:housenumber":"2408",
    "addr:postcode":"50483",
    "addr:street":"Us Hwy 18",
    "iso:country":"US",
    "sg:address":"2408 US Hwy 18",
    "sg:city":"Wesley",
    "sg:classifiers":[
        {
            "category":"Shopping",
            "type":"Retail Goods"
        }
    ],
    "sg:phone":"+1 515 679 4338",
    "sg:postcode":"50483",
    "sg:province":"IA",
    "sg:tags":[
        "merchandise"
    ],
    "wof:name":"Highway Farm Supply",
    "wof:placetype":"venue"
},
  "geometry": {"coordinates":[-93.988772,43.097041],"type":"Point"}
}