{
  "type": "Feature",
  "properties": {
    "addr:full":"212 N 1st St Rockwell City IA 50579",
    "addr:housenumber":"212",
    "addr:postcode":"50579",
    "addr:street":"N 1St St",
    "iso:country":"US",
    "sg:address":"212 N 1st St",
    "sg:city":"Rockwell City",
    "sg:classifiers":[
        {
            "category":"Freight",
            "type":"Transportation"
        }
    ],
    "sg:phone":"+1 712 297 7168",
    "sg:postcode":"50579",
    "sg:province":"IA",
    "sg:tags":[
        "operator",
        "local",
        "trucking"
    ],
    "wof:name":"Weston Trucking",
    "wof:placetype":"venue"
},
  "geometry": {"coordinates":[-94.630194,42.401661],"type":"Point"}
}