{
  "type": "Feature",
  "properties": {
    "addr:full":"1219 Ave H Fort Madison IA 52627",
    "addr:housenumber":"1219",
    "addr:postcode":"52627",
    "addr:street":"Ave H",
    "iso:country":"US",
    "sg:address":"1219 Ave H",
    "sg:city":"Fort Madison",
    "sg:classifiers":[
        {
            "category":"Health Services",
            "subcategory":"Chiropractor",
            "type":"Services"
        }
    ],
    "sg:phone":"+1 319 372 2435",
    "sg:postcode":"52627",
    "sg:province":"IA",
    "wof:name":"Courtney Family Chiropractic",
    "wof:placetype":"venue"
},
  "geometry": {"coordinates":[-91.32063100000001,40.630195],"type":"Point"}
}