{
  "type": "Feature",
  "properties": {
    "addr:full":"107 S Chestnut St Jefferson IA 50129",
    "addr:housenumber":"107",
    "addr:postcode":"50129",
    "addr:street":"S Chestnut St",
    "iso:country":"US",
    "sg:address":"107 S Chestnut St",
    "sg:city":"Jefferson",
    "sg:classifiers":[
        {
            "category":"Home & Garden",
            "subcategory":"Building Materials",
            "type":"Retail Goods"
        }
    ],
    "sg:phone":"+1 515 386 3319",
    "sg:postcode":"50129",
    "sg:province":"IA",
    "sg:tags":[
        "paint"
    ],
    "wof:name":"Hemping Paint & Glass",
    "wof:placetype":"venue"
},
  "geometry": {"coordinates":[-94.37334799999999,42.015223],"type":"Point"}
}