{
  "type": "Feature",
  "properties": {
    "iso:country":"US",
    "sg:address":"620 1st Ave SE",
    "sg:city":"Le Mars",
    "sg:classifiers":[
        {
            "category":"Farming",
            "subcategory":"Farm",
            "type":"Manufacturing & Wholesale Goods"
        }
    ],
    "sg:phone":"+1 712 546 4793",
    "sg:postcode":"51031",
    "sg:province":"IA",
    "sg:tags":[
        "crop",
        "general"
    ],
    "wof:name":"Jean M & Daryl J Steinkamp",
    "wof:placetype":"venue"
},
  "geometry": {"coordinates":[-96.165065,42.785642],"type":"Point"}
}