{
  "type": "Feature",
  "properties": {
    "iso:country":"US",
    "sg:address":"2401 E University Ave",
    "sg:city":"Des Moines",
    "sg:classifiers":[
        {
            "category":"Autos & Motor Vehicles",
            "subcategory":"Automobile Sales",
            "type":"Retail Goods"
        }
    ],
    "sg:phone":"+1 515 263 8117",
    "sg:postcode":"50317",
    "sg:province":"IA",
    "sg:tags":[
        "car",
        "dealer"
    ],
    "wof:name":"Premier Auto Sales",
    "wof:placetype":"venue"
},
  "geometry": {"coordinates":[-93.571637,41.600491],"type":"Point"}
}