{
  "type": "Feature",
  "properties": {
    "addr:full":"4628 490th Ave Mallard IA 50562",
    "addr:housenumber":"4628",
    "addr:postcode":"50562",
    "addr:street":"490Th Ave",
    "iso:country":"US",
    "sg:address":"4628 490th Ave",
    "sg:city":"Mallard",
    "sg:phone":"+1 712 425 3588",
    "sg:postcode":"50562",
    "sg:province":"IA",
    "sg:tags":[
        "farm",
        "corn"
    ],
    "wof:name":"Larry Smith",
    "wof:placetype":"venue"
},
  "geometry": {"coordinates":[-94.619643,42.977112],"type":"Point"}
}