{
  "type": "Feature",
  "properties": {
    "iso:country":"US",
    "sg:address":"124 SE 18th St",
    "sg:city":"Des Moines",
    "sg:classifiers":[
        {
            "category":"Freight",
            "type":"Transportation"
        }
    ],
    "sg:phone":"+1 515 262 2522",
    "sg:postcode":"50317",
    "sg:province":"IA",
    "sg:tags":[
        "grain",
        "elevator"
    ],
    "wof:name":"Heartland Co-Op",
    "wof:placetype":"venue"
},
  "geometry": {"coordinates":[-93.587262,41.587455],"type":"Point"}
}