{
  "type": "Feature",
  "properties": {
    "iso:country":"US",
    "sg:address":"60326 280th St",
    "sg:city":"Cambridge",
    "sg:classifiers":[
        {
            "category":"Travel",
            "subcategory":"Hotels & Motels",
            "type":"Entertainment"
        }
    ],
    "sg:phone":"+1 515 382 4471",
    "sg:postcode":"50046",
    "sg:province":"IA",
    "sg:tags":[
        "membership",
        "lodging"
    ],
    "wof:name":"Ancient Free & Accepted Masons",
    "wof:placetype":"venue"
},
  "geometry": {"coordinates":[-93.492559,41.950356],"type":"Point"}
}