{
  "type": "Feature",
  "properties": {
    "addr:full":"4530 Oakwood Ln West Des Moines IA 50265",
    "addr:housenumber":"4530",
    "addr:postcode":"50265",
    "addr:street":"Oakwood Ln",
    "iso:country":"US",
    "sg:address":"4530 Oakwood Ln",
    "sg:city":"West Des Moines",
    "sg:classifiers":[
        {
            "category":"Retail",
            "subcategory":"Portrait Studio",
            "type":"Services"
        }
    ],
    "sg:phone":"+1 515 225 4325",
    "sg:postcode":"50265",
    "sg:province":"IA",
    "sg:tags":[
        "photo"
    ],
    "wof:name":"Wayne Belling Photography",
    "wof:placetype":"venue"
},
  "geometry": {"coordinates":[-93.765958,41.54944],"type":"Point"}
}