{
  "type": "Feature",
  "properties": {
    "iso:country":"US",
    "sg:address":"221 1st St SE",
    "sg:city":"Le Mars",
    "sg:classifiers":[
        {
            "category":"Building & Trades",
            "subcategory":"Landscaping Services",
            "type":"Services"
        }
    ],
    "sg:phone":"+1 712 546 8910",
    "sg:postcode":"51031",
    "sg:province":"IA",
    "wof:name":"Randys Mowing & Repair",
    "wof:placetype":"venue"
},
  "geometry": {"coordinates":[-96.162441,42.791911],"type":"Point"}
}