{
  "type": "Feature",
  "properties": {
    "iso:country":"US",
    "sg:address":"1990 Mission Ave",
    "sg:city":"New Hampton",
    "sg:classifiers":[
        {
            "category":"Government",
            "subcategory":"Office",
            "type":"Public Place"
        }
    ],
    "sg:phone":"+1 641 394 4413",
    "sg:postcode":"50659",
    "sg:province":"IA",
    "wof:name":"Maintenance Garage",
    "wof:placetype":"venue"
},
  "geometry": {"coordinates":[-92.308567,43.071208],"type":"Point"}
}