{
  "type": "Feature",
  "properties": {
    "addr:full":"3410 12th Ave SW Cedar Rapids IA 52404",
    "addr:housenumber":"3410",
    "addr:postcode":"52404",
    "addr:street":"12Th Ave Sw",
    "iso:country":"US",
    "sg:address":"3410 12th Ave SW",
    "sg:city":"Cedar Rapids",
    "sg:classifiers":[
        {
            "category":"Real Estate",
            "subcategory":"Real Estate Operator",
            "type":"Services"
        }
    ],
    "sg:phone":"+1 319 396 3692",
    "sg:postcode":"52404",
    "sg:province":"IA",
    "sg:tags":[
        "apartment"
    ],
    "sg:website":"www.evergreenestates.biz",
    "wof:name":"Evergreen Estates",
    "wof:placetype":"venue"
},
  "geometry": {"coordinates":[-91.716499,41.965599],"type":"Point"}
}