{
  "type": "Feature",
  "properties": {
    "iso:country":"US",
    "sg:address":"202 E Detroit Ave",
    "sg:city":"Indianola",
    "sg:classifiers":[
        {
            "category":"Personal",
            "subcategory":"Barber",
            "type":"Services"
        }
    ],
    "sg:phone":"+1 515 961 3055",
    "sg:postcode":"50125",
    "sg:province":"IA",
    "wof:name":"Gary's Barber Shop",
    "wof:placetype":"venue"
},
  "geometry": {"coordinates":[-93.55837200000001,41.364497],"type":"Point"}
}