{
  "type": "Feature",
  "properties": {
    "addr:full":"303 1st Ave Vinton IA 52349",
    "addr:housenumber":"303",
    "addr:postcode":"52349",
    "addr:street":"1St Ave",
    "iso:country":"US",
    "sg:address":"303 1st Ave",
    "sg:city":"Vinton",
    "sg:classifiers":[
        {
            "category":"Local Transit",
            "type":"Transportation"
        }
    ],
    "sg:phone":"+1 319 472 2413",
    "sg:postcode":"52349",
    "sg:province":"IA",
    "sg:tags":[
        "bus",
        "line"
    ],
    "wof:name":"East Central Iowa Transit",
    "wof:placetype":"venue"
},
  "geometry": {"coordinates":[-92.02436899999999,42.168658],"type":"Point"}
}