{
  "type": "Feature",
  "properties": {
    "iso:country":"US",
    "sg:address":"3641 1st Ave SE",
    "sg:city":"Cedar Rapids",
    "sg:classifiers":[
        {
            "category":"Sports & Exercise",
            "subcategory":"Gym",
            "type":"Entertainment"
        }
    ],
    "sg:phone":"+1 319 368 8031",
    "sg:postcode":"52402",
    "sg:province":"IA",
    "sg:tags":[
        "club",
        "health",
        "studio",
        "gymnasium"
    ],
    "wof:name":"Curves For Women",
    "wof:placetype":"venue"
},
  "geometry": {"coordinates":[-91.634929,42.015493],"type":"Point"}
}