{
  "type": "Feature",
  "properties": {
    "addr:full":"5235 Jasper Ave SW Riverside IA 52327",
    "addr:housenumber":"5235",
    "addr:postcode":"52327",
    "addr:street":"Jasper Ave Sw",
    "iso:country":"US",
    "sg:address":"5235 Jasper Ave SW",
    "sg:city":"Riverside",
    "sg:classifiers":[
        {
            "category":"Freight",
            "type":"Transportation"
        }
    ],
    "sg:phone":"+1 319 683 3730",
    "sg:postcode":"52327",
    "sg:province":"IA",
    "sg:tags":[
        "operator",
        "local",
        "trucking"
    ],
    "wof:name":"Schrock Trucking Inc",
    "wof:placetype":"venue"
},
  "geometry": {"coordinates":[-91.64666099999999,41.551865],"type":"Point"}
}