{
  "type": "Feature",
  "properties": {
    "iso:country":"US",
    "sg:address":"9068 N Ave",
    "sg:city":"Maynard",
    "sg:classifiers":[
        {
            "category":"Farming",
            "subcategory":"Farm",
            "type":"Manufacturing & Wholesale Goods"
        }
    ],
    "sg:phone":"+1 563 637 2249",
    "sg:postcode":"50655",
    "sg:province":"IA",
    "sg:tags":[
        "crop",
        "general"
    ],
    "wof:name":"Lowry Farms Inc",
    "wof:placetype":"venue"
},
  "geometry": {"coordinates":[-91.86318799999999,42.7536],"type":"Point"}
}