{
  "type": "Feature",
  "properties": {
    "iso:country":"US",
    "sg:address":"1445 Ansborough Ave",
    "sg:city":"Waterloo",
    "sg:classifiers":[
        {
            "category":"Health Services",
            "subcategory":"Chiropractor",
            "type":"Services"
        }
    ],
    "sg:phone":"+1 319 232 9436",
    "sg:postcode":"50701",
    "sg:province":"IA",
    "wof:name":"Ebert Chiropractic Clinic",
    "wof:placetype":"venue"
},
  "geometry": {"coordinates":[-92.376848,42.49427],"type":"Point"}
}