{
  "type": "Feature",
  "properties": {
    "iso:country":"US",
    "sg:address":"1719 Hull Ave",
    "sg:city":"Des Moines",
    "sg:classifiers":[
        {
            "category":"Building & Trades",
            "subcategory":"Construction",
            "type":"Services"
        }
    ],
    "sg:phone":"+1 515 266 5146",
    "sg:postcode":"50313",
    "sg:province":"IA",
    "sg:tags":[
        "general",
        "contractor"
    ],
    "wof:name":"Bergstrom Construction Inc",
    "wof:placetype":"venue"
},
  "geometry": {"coordinates":[-93.58915,41.622207],"type":"Point"}
}