{
  "type": "Feature",
  "properties": {
    "iso:country":"US",
    "sg:address":"545 5th St",
    "sg:city":"West Des Moines",
    "sg:classifiers":[
        {
            "category":"Home & Garden",
            "subcategory":"Home Furnishings",
            "type":"Retail Goods"
        }
    ],
    "sg:phone":"+1 515 255 1550",
    "sg:postcode":"50265",
    "sg:province":"IA",
    "sg:tags":[
        "mirror"
    ],
    "wof:name":"Mc Gough Glass & Mirror",
    "wof:placetype":"venue"
},
  "geometry": {"coordinates":[-93.708815,41.576476],"type":"Point"}
}