{
  "type": "Feature",
  "properties": {
    "iso:country":"US",
    "sg:address":"3556 L Ln",
    "sg:city":"Adel",
    "sg:classifiers":[
        {
            "category":"Building & Trades",
            "subcategory":"Landscaping Services",
            "type":"Services"
        }
    ],
    "sg:phone":"+1 515 202 9200",
    "sg:postcode":"50003",
    "sg:province":"IA",
    "sg:tags":[
        "landscape",
        "contractor"
    ],
    "wof:name":"Knight & Sons",
    "wof:placetype":"venue"
},
  "geometry": {"coordinates":[-94.065506,41.527002],"type":"Point"}
}