{
  "type": "Feature",
  "properties": {
    "addr:full":"3102 S Center St Marshalltown IA 50158",
    "addr:housenumber":"3102",
    "addr:postcode":"50158",
    "addr:street":"S Center St",
    "iso:country":"US",
    "sg:address":"3102 S Center St",
    "sg:city":"Marshalltown",
    "sg:classifiers":[
        {
            "category":"Bakery",
            "type":"Food & Drink"
        }
    ],
    "sg:menulink":"http://www.allmenus.com/ia/timber-creek/102023-perkins-restaurant--bakery/menu/",
    "sg:phone":"+1 641 753 4038",
    "sg:postcode":"50158",
    "sg:province":"IA",
    "sg:tags":[
        "sandwich",
        "salad",
        "soup",
        "american",
        "pastry",
        "wrap"
    ],
    "wof:name":"Perkins Restaurant & Bakery",
    "wof:placetype":"venue"
},
  "geometry": {"coordinates":[-92.91240500000001,42.010085],"type":"Point"}
}