{
  "type": "Feature",
  "properties": {
    "iso:country":"US",
    "sg:address":"512 8th St SE",
    "sg:city":"Orange City",
    "sg:classifiers":[
        {
            "category":"Shopping",
            "subcategory":"Department Store",
            "type":"Retail Goods"
        }
    ],
    "sg:phone":"+1 712 737 8086",
    "sg:postcode":"51041",
    "sg:province":"IA",
    "sg:tags":[
        "shop"
    ],
    "sg:website":"www.pamida.com",
    "wof:name":"Pamida",
    "wof:placetype":"venue"
},
  "geometry": {"coordinates":[-96.05262399999999,42.997435],"type":"Point"}
}