{
  "type": "Feature",
  "properties": {
    "iso:country":"US",
    "sg:address":"1230 E Rusholme St",
    "sg:city":"Davenport",
    "sg:classifiers":[
        {
            "category":"Health Services",
            "subcategory":"Doctor",
            "type":"Services"
        }
    ],
    "sg:phone":"+1 563 326 8181",
    "sg:postcode":"52803",
    "sg:province":"IA",
    "sg:tags":[
        "physician",
        "surgeon"
    ],
    "wof:name":"Quad City Retina Consultants",
    "wof:placetype":"venue"
},
  "geometry": {"coordinates":[-90.556757,41.542923],"type":"Point"}
}