{
  "type": "Feature",
  "properties": {
    "iso:country":"US",
    "sg:address":"2940 Stevens Trl",
    "sg:city":"Lawler",
    "sg:classifiers":[
        {
            "category":"Organizations",
            "subcategory":"Religious Organization",
            "type":"Services"
        }
    ],
    "sg:phone":"+1 563 569 8602",
    "sg:postcode":"52154",
    "sg:province":"IA",
    "wof:name":"Saude Evang Luthern Church",
    "wof:placetype":"venue"
},
  "geometry": {"coordinates":[-92.165915,43.204536],"type":"Point"}
}