{
  "type": "Feature",
  "properties": {
    "iso:country":"US",
    "sg:address":"2024 Vanilla Ave",
    "sg:city":"Creston",
    "sg:classifiers":[
        {
            "category":"Real Estate",
            "subcategory":"Real Estate Operator",
            "type":"Services"
        }
    ],
    "sg:phone":"+1 641 782 8650",
    "sg:postcode":"50801",
    "sg:province":"IA",
    "sg:tags":[
        "property",
        "lessor"
    ],
    "wof:name":"Frank Tallmon",
    "wof:placetype":"venue"
},
  "geometry": {"coordinates":[-94.509163,41.0113],"type":"Point"}
}