{
  "type": "Feature",
  "properties": {
    "iso:country":"US",
    "sg:address":"1525 Florida Ave",
    "sg:city":"Ames",
    "sg:classifiers":[
        {
            "category":"Freight",
            "type":"Transportation"
        }
    ],
    "sg:phone":"+1 515 290 9331",
    "sg:postcode":"50014",
    "sg:province":"IA",
    "sg:tags":[
        "commercial",
        "storage"
    ],
    "wof:name":"Ames Westside Storage",
    "wof:placetype":"venue"
},
  "geometry": {"coordinates":[-93.681578,42.036483],"type":"Point"}
}