{
  "type": "Feature",
  "properties": {
    "addr:full":"321 E Michigan St Missouri Valley IA 51555",
    "addr:housenumber":"321",
    "addr:postcode":"51555",
    "addr:street":"E Michigan St",
    "iso:country":"US",
    "sg:address":"321 E Michigan St",
    "sg:city":"Missouri Valley",
    "sg:classifiers":[
        {
            "category":"Professional",
            "type":"Services"
        }
    ],
    "sg:phone":"+1 712 642 4413",
    "sg:postcode":"51555",
    "sg:province":"IA",
    "wof:name":"Bierce Inc",
    "wof:placetype":"venue"
},
  "geometry": {"coordinates":[-95.891657,41.559504],"type":"Point"}
}