{
  "type": "Feature",
  "properties": {
    "iso:country":"US",
    "sg:address":"511 N Bluff St",
    "sg:city":"Guttenberg",
    "sg:classifiers":[
        {
            "category":"Health Services",
            "subcategory":"Doctor",
            "type":"Services"
        }
    ],
    "sg:phone":"+1 563 252 2150",
    "sg:postcode":"52052",
    "sg:province":"IA",
    "sg:tags":[
        "dentist"
    ],
    "wof:name":"John D Barron DDS",
    "wof:placetype":"venue"
},
  "geometry": {"coordinates":[-91.105859,42.791408],"type":"Point"}
}