{
  "type": "Feature",
  "properties": {
    "iso:country":"US",
    "sg:address":"229 S 7th St",
    "sg:city":"Cherokee",
    "sg:classifiers":[
        {
            "category":"Building & Trades",
            "subcategory":"Landscaping Services",
            "type":"Services"
        }
    ],
    "sg:phone":"+1 712 225 2650",
    "sg:postcode":"51012",
    "sg:province":"IA",
    "sg:tags":[
        "landscape",
        "contractor"
    ],
    "wof:name":"Chris' Lawn Svc",
    "wof:placetype":"venue"
},
  "geometry": {"coordinates":[-95.559119,42.746843],"type":"Point"}
}