{
  "type": "Feature",
  "properties": {
    "addr:full":"1327 N Federal Ave Mason City IA 50401",
    "addr:housenumber":"1327",
    "addr:postcode":"50401",
    "addr:street":"N Federal Ave",
    "iso:country":"US",
    "sg:address":"1327 N Federal Ave",
    "sg:city":"Mason City",
    "sg:classifiers":[
        {
            "category":"Restaurant",
            "type":"Food & Drink"
        }
    ],
    "sg:phone":"+1 641 424 5929",
    "sg:postcode":"50401",
    "sg:province":"IA",
    "wof:name":"Champions Bar & Grill",
    "wof:placetype":"venue"
},
  "geometry": {"coordinates":[-93.200997,43.163942],"type":"Point"}
}