{
  "type": "Feature",
  "properties": {
    "addr:full":"2500 S Center St Marshalltown IA 50158",
    "addr:housenumber":"2500",
    "addr:postcode":"50158",
    "addr:street":"S Center St",
    "iso:country":"US",
    "sg:address":"2500 S Center St",
    "sg:city":"Marshalltown",
    "sg:classifiers":[
        {
            "category":"Shopping",
            "subcategory":"Clothing, Apparel, & Fashions",
            "type":"Retail Goods"
        }
    ],
    "sg:phone":"+1 641 753 0631",
    "sg:postcode":"50158",
    "sg:province":"IA",
    "wof:name":"Christopher & Banks",
    "wof:placetype":"venue"
},
  "geometry": {"coordinates":[-92.91215,42.016777],"type":"Point"}
}