{
  "type": "Feature",
  "properties": {
    "iso:country":"US",
    "sg:address":"600 Reber Ave",
    "sg:city":"Waterloo",
    "sg:classifiers":[
        {
            "category":"Autos & Motor Vehicles",
            "subcategory":"Auto Supplies",
            "type":"Retail Goods"
        }
    ],
    "sg:phone":"+1 319 232 6702",
    "sg:postcode":"50701",
    "sg:province":"IA",
    "sg:tags":[
        "automobile",
        "parts"
    ],
    "wof:name":"Dave's Auto Parts",
    "wof:placetype":"venue"
},
  "geometry": {"coordinates":[-92.365302,42.487551],"type":"Point"}
}