{
  "type": "Feature",
  "properties": {
    "iso:country":"US",
    "sg:address":"4925 West Ave",
    "sg:city":"Burlington",
    "sg:classifiers":[
        {
            "category":"Health Services",
            "subcategory":"Nursing And Care Facility",
            "type":"Services"
        }
    ],
    "sg:phone":"+1 319 752 1200",
    "sg:postcode":"52601",
    "sg:province":"IA",
    "sg:tags":[
        "home",
        "convalescent"
    ],
    "wof:name":"Rose Bush Gardens Assisted",
    "wof:placetype":"venue"
},
  "geometry": {"coordinates":[-91.157798,40.799374],"type":"Point"}
}