{
  "type": "Feature",
  "properties": {
    "addr:full":"109 W Main Springbrook IA 52031",
    "addr:housenumber":"109",
    "addr:postcode":"52031",
    "addr:street":"W Main",
    "iso:country":"US",
    "sg:address":"109 W Main",
    "sg:city":"Springbrook",
    "sg:classifiers":[
        {
            "category":"Manufacturing",
            "subcategory":"Chemicals & Compounds",
            "type":"Manufacturing & Wholesale Goods"
        }
    ],
    "sg:phone":"+1 563 872 4692",
    "sg:postcode":"52031",
    "sg:province":"IA",
    "sg:tags":[
        "fertilizer",
        "mixing",
        "only"
    ],
    "wof:name":"Cloos & Sons Garage Inc",
    "wof:placetype":"venue"
},
  "geometry": {"coordinates":[-90.48156,42.163839],"type":"Point"}
}