{
  "type": "Feature",
  "properties": {
    "iso:country":"US",
    "sg:address":"301 Main St",
    "sg:city":"Sanborn",
    "sg:classifiers":[
        {
            "category":"Insurance",
            "subcategory":"Insurance Agent",
            "type":"Services"
        }
    ],
    "sg:phone":"+1 712 729 3252",
    "sg:postcode":"51248",
    "sg:province":"IA",
    "sg:website":"www.prinsins.com",
    "wof:name":"Prins Insurance Inc",
    "wof:placetype":"venue"
},
  "geometry": {"coordinates":[-95.655789,43.183582],"type":"Point"}
}