{
  "type": "Feature",
  "properties": {
    "iso:country":"US",
    "sg:address":"210 2nd St SE",
    "sg:city":"Cedar Rapids",
    "sg:classifiers":[
        {
            "category":"Professional",
            "subcategory":"Lawyer & Legal Services",
            "type":"Services"
        }
    ],
    "sg:phone":"+1 319 364 1530",
    "sg:postcode":"52401",
    "sg:province":"IA",
    "wof:name":"O'brien Daniel",
    "wof:placetype":"venue"
},
  "geometry": {"coordinates":[-91.667571,41.977834],"type":"Point"}
}