{
  "type": "Feature",
  "properties": {
    "addr:full":"717 N 18th St Centerville IA 52544",
    "addr:housenumber":"717",
    "addr:postcode":"52544",
    "addr:street":"N 18Th St",
    "iso:country":"US",
    "sg:address":"717 N 18th St",
    "sg:city":"Centerville",
    "sg:classifiers":[
        {
            "category":"Personal",
            "subcategory":"Barber",
            "type":"Services"
        }
    ],
    "sg:phone":"+1 641 856 3581",
    "sg:postcode":"52544",
    "sg:province":"IA",
    "sg:tags":[
        "shop"
    ],
    "wof:name":"Razor's Edge",
    "wof:placetype":"venue"
},
  "geometry": {"coordinates":[-92.867914,40.740673],"type":"Point"}
}