{
  "type": "Feature",
  "properties": {
    "iso:country":"US",
    "sg:address":"101 N Lake St",
    "sg:city":"Lake Mills",
    "sg:classifiers":[
        {
            "category":"Building & Trades",
            "subcategory":"Electrical",
            "type":"Services"
        }
    ],
    "sg:phone":"+1 641 592 9922",
    "sg:postcode":"50450",
    "sg:province":"IA",
    "sg:tags":[
        "booth",
        "equipment",
        "telephone",
        "pay"
    ],
    "wof:name":"Pay Phone Concepts Inc",
    "wof:placetype":"venue"
},
  "geometry": {"coordinates":[-93.532476,43.420201],"type":"Point"}
}