{
  "type": "Feature",
  "properties": {
    "iso:country":"US",
    "sg:address":"210 S 9th Ave",
    "sg:city":"Eldridge",
    "sg:classifiers":[
        {
            "category":"Real Estate",
            "subcategory":"Real Estate Agent",
            "type":"Services"
        }
    ],
    "sg:phone":"+1 563 285 6200",
    "sg:postcode":"52748",
    "sg:province":"IA",
    "sg:website":"www.melfosterco.com",
    "wof:name":"Mel Foster Co",
    "wof:placetype":"venue"
},
  "geometry": {"coordinates":[-90.57178399999999,41.653727],"type":"Point"}
}