{
  "type": "Feature",
  "properties": {
    "addr:full":"302 3rd Ave SE Ste 414 Cedar Rapids IA 52401",
    "addr:housenumber":"302",
    "addr:postcode":"52401",
    "addr:street":"3Rd Ave Se Ste 414",
    "iso:country":"US",
    "sg:address":"302 3rd Ave SE Ste 414",
    "sg:city":"Cedar Rapids",
    "sg:classifiers":[
        {
            "category":"Personal",
            "subcategory":"Massage",
            "type":"Services"
        }
    ],
    "sg:phone":"+1 319 202 0717",
    "sg:postcode":"52401",
    "sg:province":"IA",
    "sg:website":"www.lehmassagetherapy.com",
    "wof:name":"Leh Massage Therapy",
    "wof:placetype":"venue"
},
  "geometry": {"coordinates":[-91.665753,41.977636],"type":"Point"}
}