{
  "type": "Feature",
  "properties": {
    "addr:full":"1801 Maury St Des Moines IA 50317",
    "addr:housenumber":"1801",
    "addr:postcode":"50317",
    "addr:street":"Maury St",
    "iso:country":"US",
    "sg:address":"1801 Maury St",
    "sg:city":"Des Moines",
    "sg:classifiers":[
        {
            "category":"Freight",
            "type":"Transportation"
        }
    ],
    "sg:phone":"+1 515 564 1006",
    "sg:postcode":"50317",
    "sg:province":"IA",
    "sg:tags":[
        "packing",
        "crating"
    ],
    "wof:name":"Packing Co",
    "wof:placetype":"venue"
},
  "geometry": {"coordinates":[-93.583974,41.581291],"type":"Point"}
}