{
  "type": "Feature",
  "properties": {
    "iso:country":"US",
    "sg:address":"300 W Jefferson St",
    "sg:city":"Afton",
    "sg:classifiers":[
        {
            "category":"Home & Garden",
            "subcategory":"Building Materials",
            "type":"Retail Goods"
        }
    ],
    "sg:phone":"+1 641 347 8489",
    "sg:postcode":"50830",
    "sg:province":"IA",
    "sg:tags":[
        "mixed",
        "concrete"
    ],
    "wof:name":"American Concrete Products",
    "wof:placetype":"venue"
},
  "geometry": {"coordinates":[-94.199956,41.032838],"type":"Point"}
}