{
  "type": "Feature",
  "properties": {
    "iso:country":"US",
    "sg:address":"633 Market Ave",
    "sg:city":"Story City",
    "sg:classifiers":[
        {
            "category":"Home & Garden",
            "subcategory":"Garden Supply",
            "type":"Retail Goods"
        }
    ],
    "sg:phone":"+1 515 733 4358",
    "sg:postcode":"50248",
    "sg:province":"IA",
    "sg:tags":[
        "fertilizer"
    ],
    "sg:website":"www.hoic.com",
    "wof:name":"Heart Of Iowa Coop",
    "wof:placetype":"venue"
},
  "geometry": {"coordinates":[-93.600185,42.187902],"type":"Point"}
}