{
  "type": "Feature",
  "properties": {
    "addr:full":"1161 130th St Charles City IA 50616",
    "addr:housenumber":"1161",
    "addr:postcode":"50616",
    "addr:street":"130Th St",
    "iso:country":"US",
    "sg:address":"1161 130th St",
    "sg:city":"Charles City",
    "sg:classifiers":[
        {
            "category":"Farming",
            "subcategory":"Farm",
            "type":"Manufacturing & Wholesale Goods"
        }
    ],
    "sg:phone":"+1 641 364 7371",
    "sg:postcode":"50616",
    "sg:province":"IA",
    "sg:tags":[
        "crop",
        "general"
    ],
    "wof:name":"Geerts James E & Linda Farm",
    "wof:placetype":"venue"
},
  "geometry": {"coordinates":[-92.519835,43.169433],"type":"Point"}
}