{
  "type": "Feature",
  "properties": {
    "iso:country":"US",
    "sg:address":"210 W Park St",
    "sg:city":"Sheldon",
    "sg:classifiers":[
        {
            "category":"Autos & Motor Vehicles",
            "subcategory":"Auto Supplies",
            "type":"Retail Goods"
        },
        {
            "category":"Retail",
            "subcategory":"Auto Repair",
            "type":"Services"
        }
    ],
    "sg:phone":"+1 712 324 3600",
    "sg:postcode":"51201",
    "sg:province":"IA",
    "sg:tags":[
        "automobile",
        "part",
        "truck"
    ],
    "sg:website":"http://clickserve.dartsearch.net/link/click?lid=43000000313870538&ds_s_kwgid=58000000006820725&ds_e_matchtype={MatchType}&ds_e_kwdid={OrderItemId}&ds_e_adid={AdId}&ds_url_v=2",
    "wof:name":"Morgan Collision and Tire Center",
    "wof:placetype":"venue"
},
  "geometry": {"coordinates":[-95.85651900000001,43.185865],"type":"Point"}
}