{
  "type": "Feature",
  "properties": {
    "iso:country":"US",
    "sg:address":"100 E Main St",
    "sg:city":"New London",
    "sg:classifiers":[
        {
            "category":"Bars & Pubs",
            "type":"Food & Drink"
        }
    ],
    "sg:phone":"+1 319 367 5884",
    "sg:postcode":"52645",
    "sg:province":"IA",
    "wof:name":"Woobie's",
    "wof:placetype":"venue"
},
  "geometry": {"coordinates":[-91.401691,40.925751],"type":"Point"}
}