{
  "type": "Feature",
  "properties": {
    "iso:country":"US",
    "sg:address":"860 2nd Ave SE",
    "sg:city":"Cedar Rapids",
    "sg:classifiers":[
        {
            "category":"Health Services",
            "subcategory":"Optometrist",
            "type":"Services"
        }
    ],
    "sg:phone":"+1 319 365 8621",
    "sg:postcode":"52403",
    "sg:province":"IA",
    "wof:name":"Teig Gary A Optometrist",
    "wof:placetype":"venue"
},
  "geometry": {"coordinates":[-91.660301,41.982101],"type":"Point"}
}