{
  "type": "Feature",
  "properties": {
    "iso:country":"US",
    "sg:address":"317 SW Walnut St",
    "sg:city":"Ankeny",
    "sg:classifiers":[
        {
            "category":"Shopping",
            "subcategory":"Clothing, Apparel, & Fashions",
            "type":"Retail Goods"
        }
    ],
    "sg:phone":"+1 515 963 1849",
    "sg:postcode":"50023",
    "sg:province":"IA",
    "sg:tags":[
        "dancing",
        "supply"
    ],
    "wof:name":"Dance Boutique",
    "wof:placetype":"venue"
},
  "geometry": {"coordinates":[-93.605874,41.728831],"type":"Point"}
}