{
  "type": "Feature",
  "properties": {
    "iso:country":"US",
    "sg:address":"1101 6th St",
    "sg:city":"West Des Moines",
    "sg:classifiers":[
        {
            "category":"Building & Trades",
            "subcategory":"Pest Control",
            "type":"Services"
        }
    ],
    "sg:phone":"+1 515 996 9000",
    "sg:postcode":"50265",
    "sg:province":"IA",
    "wof:name":"Ridd X Inc",
    "wof:placetype":"venue"
},
  "geometry": {"coordinates":[-93.709909,41.586947],"type":"Point"}
}