{
  "type": "Feature",
  "properties": {
    "iso:country":"US",
    "sg:address":"117 N Clark St",
    "sg:city":"Forest City",
    "sg:classifiers":[
        {
            "category":"Retail",
            "subcategory":"Repair Shop",
            "type":"Services"
        }
    ],
    "sg:phone":"+1 641 585 4600",
    "sg:postcode":"50436",
    "sg:province":"IA",
    "sg:tags":[
        "equipment",
        "electronic",
        "supply"
    ],
    "wof:name":"C B & Sound",
    "wof:placetype":"venue"
},
  "geometry": {"coordinates":[-93.63822399999999,43.26383],"type":"Point"}
}