{
  "type": "Feature",
  "properties": {
    "addr:full":"15256 Ash St Clear Lake IA 50428",
    "addr:housenumber":"15256",
    "addr:postcode":"50428",
    "addr:street":"Ash St",
    "iso:country":"US",
    "sg:address":"15256 Ash St",
    "sg:city":"Clear Lake",
    "sg:classifiers":[
        {
            "category":"Travel",
            "subcategory":"Hotels & Motels",
            "type":"Entertainment"
        }
    ],
    "sg:phone":"+1 641 357 3336",
    "sg:postcode":"50428",
    "sg:province":"IA",
    "sg:tags":[
        "breakfast",
        "accommodation",
        "bed"
    ],
    "sg:website":"www.oakwoodhouse.com",
    "wof:name":"Oakwood House",
    "wof:placetype":"venue"
},
  "geometry": {"coordinates":[-93.412615,43.115669],"type":"Point"}
}