{
  "type": "Feature",
  "properties": {
    "addr:full":"430 W 35th St Davenport IA 52806",
    "addr:housenumber":"430",
    "addr:postcode":"52806",
    "addr:street":"W 35Th St",
    "iso:country":"US",
    "sg:address":"430 W 35th St",
    "sg:city":"Davenport",
    "sg:classifiers":[
        {
            "category":"Health Services",
            "subcategory":"Doctor",
            "type":"Services"
        }
    ],
    "sg:phone":"+1 563 445 0999",
    "sg:postcode":"52806",
    "sg:province":"IA",
    "sg:tags":[
        "physician",
        "surgeon"
    ],
    "wof:name":"Family Care Assoc Do",
    "wof:placetype":"venue"
},
  "geometry": {"coordinates":[-90.577343,41.555785],"type":"Point"}
}