{
  "type": "Feature",
  "properties": {
    "iso:country":"US",
    "sg:address":"2155 Tolbert Ave",
    "sg:city":"Clarinda",
    "sg:classifiers":[
        {
            "category":"Building & Trades",
            "subcategory":"Pest Control",
            "type":"Services"
        }
    ],
    "sg:phone":"+1 712 542 0416",
    "sg:postcode":"51632",
    "sg:province":"IA",
    "wof:name":"Gray Pest Control",
    "wof:placetype":"venue"
},
  "geometry": {"coordinates":[-94.992237,40.744476],"type":"Point"}
}