{
  "type": "Feature",
  "properties": {
    "addr:full":"1002 N Wilson St Jefferson IA 50129",
    "addr:housenumber":"1002",
    "addr:postcode":"50129",
    "addr:street":"N Wilson St",
    "iso:country":"US",
    "sg:address":"1002 N Wilson St",
    "sg:city":"Jefferson",
    "sg:classifiers":[
        {
            "category":"Building & Trades",
            "subcategory":"Electrical",
            "type":"Services"
        }
    ],
    "sg:phone":"+1 515 386 2905",
    "sg:postcode":"50129",
    "sg:province":"IA",
    "sg:tags":[
        "electric",
        "contractor"
    ],
    "wof:name":"Taylor Electric & Constr",
    "wof:placetype":"venue"
},
  "geometry": {"coordinates":[-94.374875,42.02523],"type":"Point"}
}