{
  "type": "Feature",
  "properties": {
    "iso:country":"US",
    "sg:address":"1109 SW 63rd St",
    "sg:city":"Des Moines",
    "sg:classifiers":[
        {
            "category":"Autos & Motor Vehicles",
            "subcategory":"Automobile Sales",
            "type":"Retail Goods"
        }
    ],
    "sg:phone":"+1 515 277 5501",
    "sg:postcode":"50321",
    "sg:province":"IA",
    "sg:tags":[
        "car",
        "dealer"
    ],
    "wof:name":"Acheson Auto Sales",
    "wof:placetype":"venue"
},
  "geometry": {"coordinates":[-93.703587,41.564935],"type":"Point"}
}