{
  "type": "Feature",
  "properties": {
    "addr:full":"901 W 2nd St Davenport IA 52802",
    "addr:housenumber":"901",
    "addr:postcode":"52802",
    "addr:street":"W 2Nd St",
    "iso:country":"US",
    "sg:address":"901 W 2nd St",
    "sg:city":"Davenport",
    "sg:classifiers":[
        {
            "category":"Autos & Motor Vehicles",
            "subcategory":"Fuel & Gas Station",
            "type":"Retail Goods"
        }
    ],
    "sg:phone":"+1 563 326 2451",
    "sg:postcode":"52802",
    "sg:province":"IA",
    "sg:tags":[
        "oil"
    ],
    "wof:name":"Guenther's Conoco Svc",
    "wof:placetype":"venue"
},
  "geometry": {"coordinates":[-90.58693100000001,41.521297],"type":"Point"}
}