{
  "type": "Feature",
  "properties": {
    "iso:country":"US",
    "sg:address":"806 W Main St",
    "sg:city":"Le Grand",
    "sg:classifiers":[
        {
            "category":"Food & Beverages",
            "subcategory":"Groceries & Convenience Stores",
            "type":"Retail Goods"
        }
    ],
    "sg:phone":"+1 641 479 2242",
    "sg:postcode":"50142",
    "sg:province":"IA",
    "wof:name":"Cissy's III Food Mart",
    "wof:placetype":"venue"
},
  "geometry": {"coordinates":[-92.784266,42.006733],"type":"Point"}
}