{
  "type": "Feature",
  "properties": {
    "addr:full":"710 Hilltop Ave Stanton IA 51573",
    "addr:housenumber":"710",
    "addr:postcode":"51573",
    "addr:street":"Hilltop Ave",
    "iso:country":"US",
    "sg:address":"710 Hilltop Ave",
    "sg:city":"Stanton",
    "sg:classifiers":[
        {
            "category":"Arts & Performance",
            "subcategory":"Theater",
            "type":"Entertainment"
        }
    ],
    "sg:phone":"+1 712 829 2388",
    "sg:postcode":"51573",
    "sg:province":"IA",
    "sg:tags":[
        "group"
    ],
    "wof:name":"Wilson Sound",
    "wof:placetype":"venue"
},
  "geometry": {"coordinates":[-95.101874,40.988183],"type":"Point"}
}