{
  "type": "Feature",
  "properties": {
    "addr:full":"1726 N 16th St Council Bluffs IA 51501",
    "addr:housenumber":"1726",
    "addr:postcode":"51501",
    "addr:street":"N 16Th St",
    "iso:country":"US",
    "sg:address":"1726 N 16th St",
    "sg:city":"Council Bluffs",
    "sg:classifiers":[
        {
            "category":"Banks & Credit Unions",
            "subcategory":"Bank",
            "type":"Services"
        }
    ],
    "sg:phone":"+1 712 322 3314",
    "sg:postcode":"51501",
    "sg:province":"IA",
    "sg:tags":[
        "cashing",
        "check"
    ],
    "wof:name":"Check Into Cash",
    "wof:placetype":"venue"
},
  "geometry": {"coordinates":[-95.867559,41.276843],"type":"Point"}
}