{
  "type": "Feature",
  "properties": {
    "addr:full":"12 N 1st Ave Marshalltown IA 50158",
    "addr:housenumber":"12",
    "addr:postcode":"50158",
    "addr:street":"N 1St Ave",
    "iso:country":"US",
    "sg:address":"12 N 1st Ave",
    "sg:city":"Marshalltown",
    "sg:classifiers":[
        {
            "category":"Shopping",
            "subcategory":"Musical Instruments",
            "type":"Retail Goods"
        }
    ],
    "sg:phone":"+1 641 753 7854",
    "sg:postcode":"50158",
    "sg:province":"IA",
    "wof:name":"Marshall Music & Drum Shop",
    "wof:placetype":"venue"
},
  "geometry": {"coordinates":[-92.911372,42.05026],"type":"Point"}
}