{
  "type": "Feature",
  "properties": {
    "addr:full":"3200 Ross Rd Ames IA 50014",
    "addr:housenumber":"3200",
    "addr:postcode":"50014",
    "addr:street":"Ross Rd",
    "iso:country":"US",
    "sg:address":"3200 Ross Rd",
    "sg:city":"Ames",
    "sg:classifiers":[
        {
            "category":"Organizations",
            "subcategory":"Membership Organization",
            "type":"Services"
        }
    ],
    "sg:phone":"+1 515 292 3044",
    "sg:postcode":"50014",
    "sg:province":"IA",
    "wof:name":"Chinese Cultural Center",
    "wof:placetype":"venue"
},
  "geometry": {"coordinates":[-93.66203899999999,42.032575],"type":"Point"}
}