{
  "type": "Feature",
  "properties": {
    "iso:country":"US",
    "sg:address":"421 4th Ave SE",
    "sg:city":"Cedar Rapids",
    "sg:classifiers":[
        {
            "category":"Real Estate",
            "subcategory":"Real Estate Services",
            "type":"Services"
        }
    ],
    "sg:phone":"+1 319 294 6634",
    "sg:postcode":"52401",
    "sg:province":"IA",
    "wof:name":"Truenorth Real Estate",
    "wof:placetype":"venue"
},
  "geometry": {"coordinates":[-91.663597,41.977699],"type":"Point"}
}