{
  "type": "Feature",
  "properties": {
    "addr:full":"4119 400th St Hospers IA 51238",
    "addr:housenumber":"4119",
    "addr:postcode":"51238",
    "addr:street":"400Th St",
    "iso:country":"US",
    "sg:address":"4119 400th St",
    "sg:city":"Hospers",
    "sg:phone":"+1 712 752 8034",
    "sg:postcode":"51238",
    "sg:province":"IA",
    "sg:tags":[
        "farm"
    ],
    "wof:name":"Berwyn Aberson",
    "wof:placetype":"venue"
},
  "geometry": {"coordinates":[-95.97483200000001,43.069944],"type":"Point"}
}