{
  "type": "Feature",
  "properties": {
    "iso:country":"US",
    "sg:address":"26 5th St S",
    "sg:city":"Dakota City",
    "sg:classifiers":[
        {
            "category":"Government",
            "subcategory":"Office",
            "type":"Public Place"
        }
    ],
    "sg:phone":"+1 515 332 3083",
    "sg:postcode":"50529",
    "sg:province":"IA",
    "sg:tags":[
        "city"
    ],
    "wof:name":"Dakota City City Hall",
    "wof:placetype":"venue"
},
  "geometry": {"coordinates":[-94.20123599999999,42.721124],"type":"Point"}
}