{
  "type": "Feature",
  "properties": {
    "addr:full":"1003 21st Ave Rock Valley IA 51247",
    "addr:housenumber":"1003",
    "addr:postcode":"51247",
    "addr:street":"21St Ave",
    "iso:country":"US",
    "sg:address":"1003 21st Ave",
    "sg:city":"Rock Valley",
    "sg:classifiers":[
        {
            "category":"Manufacturing",
            "subcategory":"Tools & Machinery",
            "type":"Manufacturing & Wholesale Goods"
        }
    ],
    "sg:phone":"+1 712 476 5585",
    "sg:postcode":"51247",
    "sg:province":"IA",
    "sg:tags":[
        "alternator",
        "starter"
    ],
    "wof:name":"Rozy's Auto Electric Inc",
    "wof:placetype":"venue"
},
  "geometry": {"coordinates":[-96.285141,43.200323],"type":"Point"}
}