{
  "type": "Feature",
  "properties": {
    "iso:country":"US",
    "sg:address":"2673 Wisconsin Ave",
    "sg:city":"Des Moines",
    "sg:classifiers":[
        {
            "category":"Shopping",
            "subcategory":"Hobbies, Toys, & Games",
            "type":"Retail Goods"
        }
    ],
    "sg:phone":"+1 515 265 4939",
    "sg:postcode":"50317",
    "sg:province":"IA",
    "wof:name":"Saw Dust Mfg",
    "wof:placetype":"venue"
},
  "geometry": {"coordinates":[-93.56388699999999,41.615654],"type":"Point"}
}