{
  "type": "Feature",
  "properties": {
    "addr:full":"1800 Hill Ave Spirit Lake IA 51360",
    "addr:housenumber":"1800",
    "addr:postcode":"51360",
    "addr:street":"Hill Ave",
    "iso:country":"US",
    "sg:address":"1800 Hill Ave",
    "sg:city":"Spirit Lake",
    "sg:classifiers":[
        {
            "category":"Government",
            "subcategory":"Office",
            "type":"Public Place"
        }
    ],
    "sg:phone":"+1 712 336 2525",
    "sg:postcode":"51360",
    "sg:province":"IA",
    "wof:name":"Dickinson Emergency Comm Ctr",
    "wof:placetype":"venue"
},
  "geometry": {"coordinates":[-95.102279,43.422632],"type":"Point"}
}