{
  "type": "Feature",
  "properties": {
    "iso:country":"US",
    "sg:address":"507 W Boston Ave",
    "sg:city":"Indianola",
    "sg:classifiers":[
        {
            "category":"Shopping",
            "subcategory":"Hobbies, Toys, & Games",
            "type":"Retail Goods"
        }
    ],
    "sg:phone":"+1 515 962 9448",
    "sg:postcode":"50125",
    "sg:province":"IA",
    "wof:name":"Little Candle Shop",
    "wof:placetype":"venue"
},
  "geometry": {"coordinates":[-93.566467,41.362316],"type":"Point"}
}