{
  "type": "Feature",
  "properties": {
    "iso:country":"US",
    "sg:address":"702 E 3rd St S",
    "sg:city":"Newton",
    "sg:classifiers":[
        {
            "category":"Social Services",
            "subcategory":"Adult Care",
            "type":"Services"
        }
    ],
    "sg:phone":"+1 641 792 6354",
    "sg:postcode":"50208",
    "sg:province":"IA",
    "sg:tags":[
        "organization",
        "senior",
        "citizen"
    ],
    "wof:name":"Jasper County Senior Citizens",
    "wof:placetype":"venue"
},
  "geometry": {"coordinates":[-93.051227,41.692985],"type":"Point"}
}