{
  "type": "Feature",
  "properties": {
    "iso:country":"US",
    "sg:address":"2176 Buffalo Rd",
    "sg:city":"Denison",
    "sg:classifiers":[
        {
            "category":"Government",
            "subcategory":"Office",
            "type":"Public Place"
        }
    ],
    "sg:phone":"+1 712 263 8454",
    "sg:postcode":"51442",
    "sg:province":"IA",
    "sg:tags":[
        "county",
        "program"
    ],
    "wof:name":"Sanitary Landfill Scalehouse",
    "wof:placetype":"venue"
},
  "geometry": {"coordinates":[-95.367379,42.040849],"type":"Point"}
}