{
  "type": "Feature",
  "properties": {
    "addr:full":"1100 N Hickory Blvd Pleasant Hill IA 50327",
    "addr:housenumber":"1100",
    "addr:postcode":"50327",
    "addr:street":"N Hickory Blvd",
    "iso:country":"US",
    "sg:address":"1100 N Hickory Blvd",
    "sg:city":"Pleasant Hill",
    "sg:classifiers":[
        {
            "category":"Restaurant",
            "type":"Food & Drink"
        }
    ],
    "sg:phone":"+1 515 265 2465",
    "sg:postcode":"50327",
    "sg:province":"IA",
    "wof:name":"Azteca Mexican Restaurants",
    "wof:placetype":"venue"
},
  "geometry": {"coordinates":[-93.516666,41.600587],"type":"Point"}
}