{
  "type": "Feature",
  "properties": {
    "addr:full":"600 7th St SE Cedar Rapids IA 52401",
    "addr:housenumber":"600",
    "addr:postcode":"52401",
    "addr:street":"7Th St Se",
    "iso:country":"US",
    "sg:address":"600 7th St SE",
    "sg:city":"Cedar Rapids",
    "sg:classifiers":[
        {
            "category":"Health Services",
            "subcategory":"Health Practitioner",
            "type":"Services"
        }
    ],
    "sg:phone":"+1 319 398 1568",
    "sg:postcode":"52401",
    "sg:province":"IA",
    "sg:tags":[
        "therapist",
        "physical"
    ],
    "wof:name":"Sports Medicine Clinic",
    "wof:placetype":"venue"
},
  "geometry": {"coordinates":[-91.65767099999999,41.976583],"type":"Point"}
}