{
  "type": "Feature",
  "properties": {
    "iso:country":"US",
    "sg:address":"2349 Jamestown Ave",
    "sg:city":"Independence",
    "sg:classifiers":[
        {
            "category":"Professional",
            "subcategory":"Employment Agencies",
            "type":"Services"
        }
    ],
    "sg:phone":"+1 319 334 2653",
    "sg:postcode":"50644",
    "sg:province":"IA",
    "sg:tags":[
        "opportunity"
    ],
    "wof:name":"Iowa Workforce Development Ctr",
    "wof:placetype":"venue"
},
  "geometry": {"coordinates":[-91.890193,42.446031],"type":"Point"}
}