{
  "type": "Feature",
  "properties": {
    "iso:country":"US",
    "sg:address":"2659 State Hwy 148",
    "sg:city":"Corning",
    "sg:classifiers":[
        {
            "category":"Building & Trades",
            "subcategory":"Construction",
            "type":"Services"
        }
    ],
    "sg:phone":"+1 641 322 4019",
    "sg:postcode":"50841",
    "sg:province":"IA",
    "sg:tags":[
        "nonresidential"
    ],
    "wof:name":"Modern Construction Svcs",
    "wof:placetype":"venue"
},
  "geometry": {"coordinates":[-94.738214,40.920218],"type":"Point"}
}