{
  "type": "Feature",
  "properties": {
    "iso:country":"US",
    "sg:address":"5540 Saratoga Rd",
    "sg:city":"Dubuque",
    "sg:classifiers":[
        {
            "category":"Retail",
            "subcategory":"Portrait Studio",
            "type":"Services"
        }
    ],
    "sg:phone":"+1 563 556 1265",
    "sg:postcode":"52002",
    "sg:province":"IA",
    "sg:tags":[
        "photographer"
    ],
    "sg:website":"www.weberphotography.com",
    "wof:name":"Weber Portrait Design",
    "wof:placetype":"venue"
},
  "geometry": {"coordinates":[-90.75823099999999,42.50835],"type":"Point"}
}