{
  "type": "Feature",
  "properties": {
    "iso:country":"US",
    "sg:address":"613 W Central Ave",
    "sg:city":"Estherville",
    "sg:classifiers":[
        {
            "category":"Education",
            "subcategory":"Library",
            "type":"Public Place"
        }
    ],
    "sg:phone":"+1 712 362 7731",
    "sg:postcode":"51334",
    "sg:province":"IA",
    "wof:name":"Estherville Public Library",
    "wof:placetype":"venue"
},
  "geometry": {"coordinates":[-94.836575,43.40206],"type":"Point"}
}