{
  "type": "Feature",
  "properties": {
    "iso:country":"US",
    "sg:address":"14 S 5th St",
    "sg:city":"Keokuk",
    "sg:classifiers":[
        {
            "category":"Government",
            "subcategory":"Jail",
            "type":"Public Place"
        }
    ],
    "sg:phone":"+1 319 524 6122",
    "sg:postcode":"52632",
    "sg:province":"IA",
    "sg:tags":[
        "govt",
        "state",
        "institution"
    ],
    "wof:name":"Juvenile Court Svc",
    "wof:placetype":"venue"
},
  "geometry": {"coordinates":[-91.38344600000001,40.395747],"type":"Point"}
}