{
  "type": "Feature",
  "properties": {
    "addr:full":"1017 570th St Cherokee IA 51012",
    "addr:housenumber":"1017",
    "addr:postcode":"51012",
    "addr:street":"570Th St",
    "iso:country":"US",
    "sg:address":"1017 570th St",
    "sg:city":"Cherokee",
    "sg:phone":"+1 712 225 5213",
    "sg:postcode":"51012",
    "sg:province":"IA",
    "sg:tags":[
        "hog",
        "farm",
        "corn",
        "soybean",
        "or",
        "feedlot"
    ],
    "wof:name":"Kevin Tapper",
    "wof:placetype":"venue"
},
  "geometry": {"coordinates":[-95.678214,42.691828],"type":"Point"}
}