{
  "type": "Feature",
  "properties": {
    "addr:full":"324 W 3rd St Cedar Falls IA 50613",
    "addr:housenumber":"324",
    "addr:postcode":"50613",
    "addr:street":"W 3Rd St",
    "iso:country":"US",
    "sg:address":"324 W 3rd St",
    "sg:city":"Cedar Falls",
    "sg:classifiers":[
        {
            "category":"Social Services",
            "type":"Services"
        }
    ],
    "sg:phone":"+1 319 277 4383",
    "sg:postcode":"50613",
    "sg:province":"IA",
    "sg:tags":[
        "counselor",
        "marriage",
        "family"
    ],
    "wof:name":"Cedar Falls Counseling Assoc",
    "wof:placetype":"venue"
},
  "geometry": {"coordinates":[-92.449214,42.53589],"type":"Point"}
}