{
  "type": "Feature",
  "properties": {
    "addr:full":"3735 Hubbell Ave Des Moines IA 50317",
    "addr:housenumber":"3735",
    "addr:postcode":"50317",
    "addr:street":"Hubbell Ave",
    "iso:country":"US",
    "sg:address":"3735 Hubbell Ave",
    "sg:city":"Des Moines",
    "sg:classifiers":[
        {
            "category":"Food & Beverages",
            "subcategory":"Groceries & Convenience Stores",
            "type":"Retail Goods"
        }
    ],
    "sg:phone":"+1 515 265 1840",
    "sg:postcode":"50317",
    "sg:province":"IA",
    "wof:name":"Git N Go",
    "wof:placetype":"venue"
},
  "geometry": {"coordinates":[-93.54193100000001,41.630421],"type":"Point"}
}