{
  "type": "Feature",
  "properties": {
    "addr:full":"707 Yellow River Dr Postville IA 52162",
    "addr:housenumber":"707",
    "addr:postcode":"52162",
    "addr:street":"Yellow River Dr Postville",
    "iso:country":"US",
    "sg:address":"707 Yellow River Dr",
    "sg:city":"Postville",
    "sg:classifiers":[
        {
            "category":"Building & Trades",
            "subcategory":"Plumbing",
            "type":"Services"
        }
    ],
    "sg:phone":"+1 563 568 3080",
    "sg:postcode":"52162",
    "sg:province":"IA",
    "sg:tags":[
        "contractor"
    ],
    "wof:name":"Marting Electrical Plbg & Htg",
    "wof:placetype":"venue"
},
  "geometry": {"coordinates":[-91.48835699999999,43.156091],"type":"Point"}
}