{
  "type": "Feature",
  "properties": {
    "iso:country":"US",
    "sg:address":"2327 135th St",
    "sg:city":"New Sharon",
    "sg:classifiers":[
        {
            "category":"Professional",
            "type":"Services"
        }
    ],
    "sg:phone":"+1 641 637 4522",
    "sg:postcode":"50207",
    "sg:province":"IA",
    "wof:name":"3f Inc",
    "wof:placetype":"venue"
},
  "geometry": {"coordinates":[-92.61723600000001,41.458866],"type":"Point"}
}