{
  "type": "Feature",
  "properties": {
    "iso:country":"US",
    "sg:address":"905 Silver Ln",
    "sg:city":"Carter Lake",
    "sg:classifiers":[
        {
            "category":"Retail",
            "subcategory":"Auto Repair",
            "type":"Services"
        }
    ],
    "sg:phone":"+1 712 347 5527",
    "sg:postcode":"51510",
    "sg:province":"IA",
    "sg:tags":[
        "general"
    ],
    "wof:name":"Jones Motorsports",
    "wof:placetype":"venue"
},
  "geometry": {"coordinates":[-95.915689,41.293604],"type":"Point"}
}