{
  "type": "Feature",
  "properties": {
    "addr:full":"1643 Eagle Ave Audubon IA 50025",
    "addr:housenumber":"1643",
    "addr:postcode":"50025",
    "addr:street":"Eagle Ave",
    "iso:country":"US",
    "sg:address":"1643 Eagle Ave",
    "sg:city":"Audubon",
    "sg:phone":"+1 712 563 3690",
    "sg:postcode":"50025",
    "sg:province":"IA",
    "sg:tags":[
        "hog",
        "farm",
        "corn",
        "soybean",
        "or",
        "feedlot"
    ],
    "wof:name":"Robert Weber",
    "wof:placetype":"venue"
},
  "geometry": {"coordinates":[-95.015372,41.769324],"type":"Point"}
}