{
  "type": "Feature",
  "properties": {
    "iso:country":"US",
    "sg:address":"1321 3rd St",
    "sg:city":"Webster City",
    "sg:classifiers":[
        {
            "category":"Manufacturing",
            "subcategory":"Signs",
            "type":"Manufacturing & Wholesale Goods"
        }
    ],
    "sg:phone":"+1 515 832 1484",
    "sg:postcode":"50595",
    "sg:province":"IA",
    "sg:tags":[
        "printing",
        "commercial",
        "specialty",
        "mfg"
    ],
    "wof:name":"Kinnetz Signs",
    "wof:placetype":"venue"
},
  "geometry": {"coordinates":[-93.836343,42.470581],"type":"Point"}
}