{
  "type": "Feature",
  "properties": {
    "addr:full":"110 S Jordan Creek Pkwy West Des Moines IA 50266",
    "addr:housenumber":"110",
    "addr:postcode":"50266",
    "addr:street":"S Jordan Creek Pkwy",
    "iso:country":"US",
    "sg:address":"110 S Jordan Creek Pkwy",
    "sg:city":"West Des Moines",
    "sg:classifiers":[
        {
            "category":"Restaurant",
            "type":"Food & Drink"
        }
    ],
    "sg:menulink":"http://www.allmenus.com/ia/boone/6750-pf-changs/menu/",
    "sg:phone":"+1 515 457 7772",
    "sg:postcode":"50266",
    "sg:province":"IA",
    "sg:tags":[
        "japanese",
        "chinese",
        "asian"
    ],
    "wof:name":"P.F. Chang's",
    "wof:placetype":"venue"
},
  "geometry": {"coordinates":[-93.809304,41.567017],"type":"Point"}
}