{
  "type": "Feature",
  "properties": {
    "iso:country":"US",
    "sg:address":"6231 24th Ave",
    "sg:city":"Vinton",
    "sg:classifiers":[
        {
            "category":"Home & Garden",
            "subcategory":"Garden Supply",
            "type":"Retail Goods"
        }
    ],
    "sg:phone":"+1 319 472 5417",
    "sg:postcode":"52349",
    "sg:province":"IA",
    "sg:tags":[
        "nurseryman"
    ],
    "wof:name":"Weiss Country Bloomers",
    "wof:placetype":"venue"
},
  "geometry": {"coordinates":[-92.028632,42.118704],"type":"Point"}
}