{
  "type": "Feature",
  "properties": {
    "iso:country":"US",
    "sg:address":"403 1st Ave",
    "sg:city":"Perry",
    "sg:classifiers":[
        {
            "category":"Health Services",
            "subcategory":"Chiropractor",
            "type":"Services"
        }
    ],
    "sg:phone":"+1 515 465 3585",
    "sg:postcode":"50220",
    "sg:province":"IA",
    "wof:name":"Perry Family Chiropractic Ctr",
    "wof:placetype":"venue"
},
  "geometry": {"coordinates":[-94.10661899999999,41.833087],"type":"Point"}
}