{
  "type": "Feature",
  "properties": {
    "iso:country":"US",
    "sg:address":"225 State St S",
    "sg:city":"Crystal Lake",
    "sg:classifiers":[
        {
            "category":"Social Services",
            "subcategory":"Adult Care",
            "type":"Services"
        }
    ],
    "sg:phone":"+1 641 565 3535",
    "sg:postcode":"50432",
    "sg:province":"IA",
    "sg:tags":[
        "organization",
        "senior",
        "citizen"
    ],
    "wof:name":"Senior Citizen's Ctr",
    "wof:placetype":"venue"
},
  "geometry": {"coordinates":[-93.790043,43.222963],"type":"Point"}
}