{
  "type": "Feature",
  "properties": {
    "addr:full":"2016 2nd Ave E Spencer IA 51301",
    "addr:housenumber":"2016",
    "addr:postcode":"51301",
    "addr:street":"2Nd Ave E",
    "iso:country":"US",
    "sg:address":"2016 2nd Ave E",
    "sg:city":"Spencer",
    "sg:classifiers":[
        {
            "category":"Health Services",
            "subcategory":"Chiropractor",
            "type":"Services"
        }
    ],
    "sg:phone":"+1 712 264 8829",
    "sg:postcode":"51301",
    "sg:province":"IA",
    "wof:name":"Schwartz Chiropractic Clinic",
    "wof:placetype":"venue"
},
  "geometry": {"coordinates":[-95.14212499999999,43.158823],"type":"Point"}
}