{
  "type": "Feature",
  "properties": {
    "iso:country":"US",
    "sg:address":"506 6th St",
    "sg:city":"Sioux City",
    "sg:classifiers":[
        {
            "category":"Organizations",
            "subcategory":"Non-profit Organization",
            "type":"Services"
        }
    ],
    "sg:phone":"+1 712 255 1065",
    "sg:postcode":"51101",
    "sg:province":"IA",
    "sg:tags":[
        "disability"
    ],
    "wof:name":"Three Rivers Independent Lvng",
    "wof:placetype":"venue"
},
  "geometry": {"coordinates":[-96.404286,42.49627],"type":"Point"}
}