{
  "type": "Feature",
  "properties": {
    "iso:country":"US",
    "sg:address":"1008 7th St",
    "sg:city":"Grundy Center",
    "sg:classifiers":[
        {
            "category":"Social Services",
            "subcategory":"Child Care",
            "type":"Services"
        }
    ],
    "sg:phone":"+1 319 825 5529",
    "sg:postcode":"50638",
    "sg:province":"IA",
    "wof:name":"Cribs To Crayons Day Care",
    "wof:placetype":"venue"
},
  "geometry": {"coordinates":[-92.772543,42.358553],"type":"Point"}
}