{
  "type": "Feature",
  "properties": {
    "addr:full":"16073 Keystone Ave Greene IA 50636",
    "addr:housenumber":"16073",
    "addr:postcode":"50636",
    "addr:street":"Keystone Ave",
    "iso:country":"US",
    "sg:address":"16073 Keystone Ave",
    "sg:city":"Greene",
    "sg:classifiers":[
        {
            "category":"Organizations",
            "subcategory":"Religious Organization",
            "type":"Services"
        }
    ],
    "sg:phone":"+1 641 775 3390",
    "sg:postcode":"50636",
    "sg:province":"IA",
    "sg:tags":[
        "church"
    ],
    "wof:name":"St John's Lutheran Church",
    "wof:placetype":"venue"
},
  "geometry": {"coordinates":[-92.829897,42.815637],"type":"Point"}
}