{
  "type": "Feature",
  "properties": {
    "addr:full":"340 Union St West Union IA 52175",
    "addr:housenumber":"340",
    "addr:postcode":"52175",
    "addr:street":"Union St",
    "iso:country":"US",
    "sg:address":"340 Union St",
    "sg:city":"West Union",
    "sg:classifiers":[
        {
            "category":"Wholesale",
            "subcategory":"Machinery & Supplies",
            "type":"Manufacturing & Wholesale Goods"
        }
    ],
    "sg:phone":"+1 563 422 6148",
    "sg:postcode":"52175",
    "sg:province":"IA",
    "sg:tags":[
        "equipment",
        "steam",
        "cleaning"
    ],
    "wof:name":"Alkota Cleaning Systems",
    "wof:placetype":"venue"
},
  "geometry": {"coordinates":[-91.810534,42.958541],"type":"Point"}
}