{
  "type": "Feature",
  "properties": {
    "iso:country":"US",
    "sg:address":"5259 Jersey Ridge Rd",
    "sg:city":"Davenport",
    "sg:classifiers":[
        {
            "category":"Shopping",
            "subcategory":"Computers & Home Electronics",
            "type":"Retail Goods"
        }
    ],
    "sg:phone":"+1 563 823 1090",
    "sg:postcode":"52807",
    "sg:province":"IA",
    "sg:tags":[
        "software"
    ],
    "wof:name":"Gamerz Arena",
    "wof:placetype":"venue"
},
  "geometry": {"coordinates":[-90.541532,41.574484],"type":"Point"}
}