{
  "type": "Feature",
  "properties": {
    "iso:country":"US",
    "sg:address":"2309 Union Rd",
    "sg:city":"Cedar Falls",
    "sg:phone":"+1 319 266 6859",
    "sg:postcode":"50613",
    "sg:province":"IA",
    "sg:tags":[
        "farm",
        "corn",
        "soybean"
    ],
    "wof:name":"Roger Heise",
    "wof:placetype":"venue"
},
  "geometry": {"coordinates":[-92.49504,42.523912],"type":"Point"}
}