{
  "type": "Feature",
  "properties": {
    "iso:country":"US",
    "sg:address":"107 Sergeant Sq",
    "sg:city":"Sergeant Bluff",
    "sg:classifiers":[
        {
            "category":"Restaurant",
            "type":"Food & Drink"
        }
    ],
    "sg:phone":"+1 712 943 8888",
    "sg:postcode":"51054",
    "sg:province":"IA",
    "wof:name":"Aggie's",
    "wof:placetype":"venue"
},
  "geometry": {"coordinates":[-96.364904,42.399167],"type":"Point"}
}