{
  "type": "Feature",
  "properties": {
    "iso:country":"US",
    "sg:address":"2999 290th St",
    "sg:city":"Gilman",
    "sg:classifiers":[
        {
            "category":"Manufacturing",
            "subcategory":"Glass & Minerals",
            "type":"Manufacturing & Wholesale Goods"
        }
    ],
    "sg:phone":"+1 641 478 3357",
    "sg:postcode":"50158",
    "sg:province":"IA",
    "sg:tags":[
        "stone",
        "cut",
        "product"
    ],
    "sg:website":"www.martinmarietta.com",
    "wof:name":"Martin Marietta Aggregates",
    "wof:placetype":"venue"
},
  "geometry": {"coordinates":[-92.843907,41.935418],"type":"Point"}
}