{
  "type": "Feature",
  "properties": {
    "iso:country":"US",
    "sg:address":"3260 Getty Ter",
    "sg:city":"Dubuque",
    "sg:classifiers":[
        {
            "category":"Real Estate",
            "subcategory":"Real Estate Operator",
            "type":"Services"
        }
    ],
    "sg:phone":"+1 608 833 8788",
    "sg:postcode":"52001",
    "sg:province":"IA",
    "sg:tags":[
        "apartment"
    ],
    "wof:name":"Sheridan Village",
    "wof:placetype":"venue"
},
  "geometry": {"coordinates":[-90.673753,42.53129],"type":"Point"}
}