{
  "type": "Feature",
  "properties": {
    "iso:country":"US",
    "sg:address":"1490 Daleview Dr",
    "sg:city":"Marion",
    "sg:classifiers":[
        {
            "category":"Organizations",
            "subcategory":"Non-profit Organization",
            "type":"Services"
        }
    ],
    "sg:phone":"+1 319 377 0895",
    "sg:postcode":"52302",
    "sg:province":"IA",
    "sg:tags":[
        "human"
    ],
    "wof:name":"REM Iowa Inc",
    "wof:placetype":"venue"
},
  "geometry": {"coordinates":[-91.593823,42.017814],"type":"Point"}
}