{
  "type": "Feature",
  "properties": {
    "addr:full":"120 Hudson Rd Cedar Falls IA 50613",
    "addr:housenumber":"120",
    "addr:postcode":"50613",
    "addr:street":"Hudson Rd",
    "iso:country":"US",
    "sg:address":"120 Hudson Rd",
    "sg:city":"Cedar Falls",
    "sg:classifiers":[
        {
            "category":"Professional",
            "subcategory":"Lawyer & Legal Services",
            "type":"Services"
        }
    ],
    "sg:phone":"+1 319 268 1654",
    "sg:postcode":"50613",
    "sg:province":"IA",
    "sg:tags":[
        "attorney"
    ],
    "wof:name":"Reed Merner & Sabbath",
    "wof:placetype":"venue"
},
  "geometry": {"coordinates":[-92.465214,42.537102],"type":"Point"}
}