{
  "type": "Feature",
  "properties": {
    "iso:country":"US",
    "sg:address":"3079 170th St",
    "sg:city":"Fort Madison",
    "sg:classifiers":[
        {
            "category":"Shopping",
            "subcategory":"Clothing, Apparel, & Fashions",
            "type":"Retail Goods"
        }
    ],
    "sg:phone":"+1 319 528 4513",
    "sg:postcode":"52627",
    "sg:province":"IA",
    "sg:tags":[
        "riding",
        "wear",
        "western",
        "supply"
    ],
    "wof:name":"B-Bar-B Western Store",
    "wof:placetype":"venue"
},
  "geometry": {"coordinates":[-91.32466599999999,40.710908],"type":"Point"}
}