{
  "type": "Feature",
  "properties": {
    "iso:country":"US",
    "sg:address":"2720 W Locust St",
    "sg:city":"Davenport",
    "sg:classifiers":[
        {
            "category":"Shopping",
            "subcategory":"Department Store",
            "type":"Retail Goods"
        }
    ],
    "sg:phone":"+1 563 386 1109",
    "sg:postcode":"52804",
    "sg:province":"IA",
    "wof:name":"Super $1 Store",
    "wof:placetype":"venue"
},
  "geometry": {"coordinates":[-90.617141,41.538268],"type":"Point"}
}