{
  "type": "Feature",
  "properties": {
    "iso:country":"US",
    "sg:address":"318 S Main St",
    "sg:city":"Harris",
    "sg:phone":"+1 712 349 2404",
    "sg:postcode":"51345",
    "sg:province":"IA",
    "sg:tags":[
        "farm",
        "corn",
        "soybean"
    ],
    "wof:name":"Keith Klaassen",
    "wof:placetype":"venue"
},
  "geometry": {"coordinates":[-95.43377099999999,43.443131],"type":"Point"}
}