{
  "type": "Feature",
  "properties": {
    "iso:country":"US",
    "sg:address":"2431 120th St",
    "sg:city":"New Sharon",
    "sg:classifiers":[
        {
            "category":"Farming",
            "subcategory":"Farm",
            "type":"Manufacturing & Wholesale Goods"
        }
    ],
    "sg:phone":"+1 641 637 2770",
    "sg:postcode":"50207",
    "sg:province":"IA",
    "sg:tags":[
        "crop",
        "general"
    ],
    "wof:name":"Grant & Jayne Ferguson",
    "wof:placetype":"venue"
},
  "geometry": {"coordinates":[-92.59980400000001,41.480588],"type":"Point"}
}