{
  "type": "Feature",
  "properties": {
    "iso:country":"US",
    "sg:address":"10009 Hawks Haven Rd",
    "sg:city":"Cedar Rapids",
    "sg:classifiers":[
        {
            "category":"Professional",
            "subcategory":"Business Services",
            "type":"Services"
        }
    ],
    "sg:phone":"+1 319 393 7841",
    "sg:postcode":"52411",
    "sg:province":"IA",
    "wof:name":"Lancaster Enterprises",
    "wof:placetype":"venue"
},
  "geometry": {"coordinates":[-91.730451,42.07615],"type":"Point"}
}