{
  "type": "Feature",
  "properties": {
    "addr:full":"207 W Pearl St Decorah IA 52101",
    "addr:housenumber":"207",
    "addr:postcode":"52101",
    "addr:street":"W Pearl St",
    "iso:country":"US",
    "sg:address":"207 W Pearl St",
    "sg:city":"Decorah",
    "sg:classifiers":[
        {
            "category":"Building & Trades",
            "subcategory":"Electrical",
            "type":"Services"
        }
    ],
    "sg:phone":"+1 563 382 4244",
    "sg:postcode":"52101",
    "sg:province":"IA",
    "wof:name":"Onmedia Cable Advertising",
    "wof:placetype":"venue"
},
  "geometry": {"coordinates":[-91.78878,43.298367],"type":"Point"}
}