{
  "type": "Feature",
  "properties": {
    "iso:country":"US",
    "sg:address":"3596 Timber Ave",
    "sg:city":"Osage",
    "sg:classifiers":[
        {
            "category":"Building & Trades",
            "subcategory":"Construction",
            "type":"Services"
        }
    ],
    "sg:phone":"+1 641 982 4254",
    "sg:postcode":"50461",
    "sg:province":"IA",
    "sg:tags":[
        "drainage",
        "contractor"
    ],
    "wof:name":"Johanns Tiling & Excavating",
    "wof:placetype":"venue"
},
  "geometry": {"coordinates":[-92.65339299999999,43.278168],"type":"Point"}
}