{
  "type": "Feature",
  "properties": {
    "iso:country":"US",
    "sg:address":"301 N 4th St",
    "sg:city":"Eldridge",
    "sg:classifiers":[
        {
            "category":"Health Services",
            "subcategory":"Doctor",
            "type":"Services"
        }
    ],
    "sg:phone":"+1 563 285 7232",
    "sg:postcode":"52748",
    "sg:province":"IA",
    "sg:tags":[
        "physician",
        "surgeon"
    ],
    "wof:name":"Genesis Health Group",
    "wof:placetype":"venue"
},
  "geometry": {"coordinates":[-90.587059,41.657311],"type":"Point"}
}