{
  "type": "Feature",
  "properties": {
    "addr:full":"606 Topaz Dr Sergeant Bluff IA 51054",
    "addr:housenumber":"606",
    "addr:postcode":"51054",
    "addr:street":"Topaz Dr",
    "iso:country":"US",
    "sg:address":"606 Topaz Dr",
    "sg:city":"Sergeant Bluff",
    "sg:classifiers":[
        {
            "category":"Retail",
            "subcategory":"Repair Shop",
            "type":"Services"
        }
    ],
    "sg:phone":"+1 712 943 3311",
    "sg:postcode":"51054",
    "sg:province":"IA",
    "sg:tags":[
        "bathtub",
        "sink",
        "refinishing"
    ],
    "wof:name":"Surface Doctor",
    "wof:placetype":"venue"
},
  "geometry": {"coordinates":[-96.356793,42.395967],"type":"Point"}
}