{
  "type": "Feature",
  "properties": {
    "iso:country":"US",
    "sg:address":"223 E 2nd St",
    "sg:city":"Muscatine",
    "sg:classifiers":[
        {
            "category":"Shopping",
            "subcategory":"Clothing, Apparel, & Fashions",
            "type":"Retail Goods"
        }
    ],
    "sg:phone":"+1 563 263 4901",
    "sg:postcode":"52761",
    "sg:province":"IA",
    "sg:tags":[
        "furnishing"
    ],
    "wof:name":"K & D Clothiers",
    "wof:placetype":"venue"
},
  "geometry": {"coordinates":[-91.043781,41.42243],"type":"Point"}
}