{
  "type": "Feature",
  "properties": {
    "iso:country":"US",
    "sg:address":"205 N Maple St",
    "sg:city":"Graettinger",
    "sg:classifiers":[
        {
            "category":"Shopping",
            "subcategory":"Gifts & Souvenirs",
            "type":"Retail Goods"
        }
    ],
    "sg:phone":"+1 712 859 3609",
    "sg:postcode":"51342",
    "sg:province":"IA",
    "wof:name":"Unique Country Gifts",
    "wof:placetype":"venue"
},
  "geometry": {"coordinates":[-94.745975,43.239584],"type":"Point"}
}