{
  "type": "Feature",
  "properties": {
    "iso:country":"US",
    "sg:address":"508 N 4th Ave",
    "sg:city":"Logan",
    "sg:classifiers":[
        {
            "category":"Building & Trades",
            "subcategory":"Landscaping Services",
            "type":"Services"
        }
    ],
    "sg:phone":"+1 712 644 3374",
    "sg:postcode":"51546",
    "sg:province":"IA",
    "wof:name":"Meekers Logging",
    "wof:placetype":"venue"
},
  "geometry": {"coordinates":[-95.78635,41.648158],"type":"Point"}
}