{
  "type": "Feature",
  "properties": {
    "addr:full":"803 W Adams Ave Fairfield IA 52556",
    "addr:housenumber":"803",
    "addr:postcode":"52556",
    "addr:street":"W Adams Ave",
    "iso:country":"US",
    "sg:address":"803 W Adams Ave",
    "sg:city":"Fairfield",
    "sg:classifiers":[
        {
            "category":"Government",
            "subcategory":"Office",
            "type":"Public Place"
        }
    ],
    "sg:phone":"+1 641 472 5367",
    "sg:postcode":"52556",
    "sg:province":"IA",
    "sg:tags":[
        "state",
        "program"
    ],
    "wof:name":"Transportation Dept Mntnc",
    "wof:placetype":"venue"
},
  "geometry": {"coordinates":[-91.973536,41.004807],"type":"Point"}
}