{
  "type": "Feature",
  "properties": {
    "addr:full":"205 1st Ave Wellman IA 52356",
    "addr:housenumber":"205",
    "addr:postcode":"52356",
    "addr:street":"1St Ave",
    "iso:country":"US",
    "sg:address":"205 1st Ave",
    "sg:city":"Wellman",
    "sg:classifiers":[
        {
            "category":"Government",
            "subcategory":"Office",
            "type":"Public Place"
        }
    ],
    "sg:phone":"+1 319 646 2544",
    "sg:postcode":"52356",
    "sg:province":"IA",
    "sg:tags":[
        "govt",
        "city"
    ],
    "wof:name":"Wellman Waste Water Treatment",
    "wof:placetype":"venue"
},
  "geometry": {"coordinates":[-91.829345,41.463316],"type":"Point"}
}