{
  "type": "Feature",
  "properties": {
    "iso:country":"US",
    "sg:address":"1506 Forest Ave",
    "sg:city":"Red Oak",
    "sg:classifiers":[
        {
            "category":"Farming",
            "subcategory":"Livestock Farm",
            "type":"Manufacturing & Wholesale Goods"
        }
    ],
    "sg:phone":"+1 712 623 2360",
    "sg:postcode":"51566",
    "sg:province":"IA",
    "sg:tags":[
        "beef",
        "feedlot",
        "cattle"
    ],
    "wof:name":"Mark Palmquist",
    "wof:placetype":"venue"
},
  "geometry": {"coordinates":[-95.21278100000001,41.012693],"type":"Point"}
}