{
  "type": "Feature",
  "properties": {
    "iso:country":"US",
    "sg:address":"795 Julien Dubuque Dr",
    "sg:city":"Dubuque",
    "sg:classifiers":[
        {
            "category":"Government",
            "subcategory":"Office",
            "type":"Public Place"
        }
    ],
    "sg:phone":"+1 563 589 4176",
    "sg:postcode":"52003",
    "sg:province":"IA",
    "sg:tags":[
        "govt",
        "city"
    ],
    "sg:website":"www.cityofdubuque.org",
    "wof:name":"Waste Water Treatment Plant",
    "wof:placetype":"venue"
},
  "geometry": {"coordinates":[-90.650684,42.47118],"type":"Point"}
}