{
  "type": "Feature",
  "properties": {
    "addr:full":"2040 Edgewood Rd SW Ste 300 Cedar Rapids IA 52404",
    "addr:housenumber":"2040",
    "addr:postcode":"52404",
    "addr:street":"Edgewood Rd Sw Ste 300",
    "iso:country":"US",
    "sg:address":"2040 Edgewood Rd SW Ste 300",
    "sg:city":"Cedar Rapids",
    "sg:classifiers":[
        {
            "category":"Personal",
            "subcategory":"Nail Salon",
            "type":"Services"
        }
    ],
    "sg:phone":"+1 319 396 5110",
    "sg:postcode":"52404",
    "sg:province":"IA",
    "wof:name":"Nail World",
    "wof:placetype":"venue"
},
  "geometry": {"coordinates":[-91.71632099999999,41.960444],"type":"Point"}
}