{
  "type": "Feature",
  "properties": {
    "iso:country":"US",
    "sg:address":"303 Chestnut St",
    "sg:city":"Atlantic",
    "sg:classifiers":[
        {
            "category":"Personal",
            "subcategory":"Beauty Salon",
            "type":"Services"
        }
    ],
    "sg:phone":"+1 712 243 1181",
    "sg:postcode":"50022",
    "sg:province":"IA",
    "wof:name":"Hair Clips Salon",
    "wof:placetype":"venue"
},
  "geometry": {"coordinates":[-95.013065,41.407969],"type":"Point"}
}