{
  "type": "Feature",
  "properties": {
    "addr:full":"907 Chatburn Ave Harlan IA 51537",
    "addr:housenumber":"907",
    "addr:postcode":"51537",
    "addr:street":"Chatburn Ave",
    "iso:country":"US",
    "sg:address":"907 Chatburn Ave",
    "sg:city":"Harlan",
    "sg:classifiers":[
        {
            "category":"Building & Trades",
            "subcategory":"Construction",
            "type":"Services"
        }
    ],
    "sg:phone":"+1 712 755 3546",
    "sg:postcode":"51537",
    "sg:province":"IA",
    "sg:tags":[
        "general",
        "contractor"
    ],
    "wof:name":"Ahrenholtz Construction",
    "wof:placetype":"venue"
},
  "geometry": {"coordinates":[-95.321195,41.64528],"type":"Point"}
}