{
  "type": "Feature",
  "properties": {
    "iso:country":"US",
    "sg:address":"109 Alt St",
    "sg:city":"Alta Vista",
    "sg:classifiers":[
        {
            "category":"Freight",
            "type":"Transportation"
        }
    ],
    "sg:phone":"+1 641 364 2009",
    "sg:postcode":"50603",
    "sg:province":"IA",
    "sg:tags":[
        "grain",
        "elevator"
    ],
    "wof:name":"Howard County Equity Co-Op",
    "wof:placetype":"venue"
},
  "geometry": {"coordinates":[-92.416144,43.196641],"type":"Point"}
}