{
  "type": "Feature",
  "properties": {
    "iso:country":"US",
    "sg:address":"316 S Iowa Ave",
    "sg:city":"Ottumwa",
    "sg:classifiers":[
        {
            "category":"Home & Garden",
            "subcategory":"Building Materials",
            "type":"Retail Goods"
        }
    ],
    "sg:phone":"+1 641 684 2071",
    "sg:postcode":"52501",
    "sg:province":"IA",
    "sg:tags":[
        "mixed",
        "concrete"
    ],
    "wof:name":"Skyline Ready Mix",
    "wof:placetype":"venue"
},
  "geometry": {"coordinates":[-92.39554200000001,41.007939],"type":"Point"}
}