{
  "type": "Feature",
  "properties": {
    "iso:country":"US",
    "sg:address":"118 N Main St",
    "sg:city":"Wheatland",
    "sg:classifiers":[
        {
            "category":"Freight",
            "type":"Transportation"
        }
    ],
    "sg:phone":"+1 563 374 1379",
    "sg:postcode":"52777",
    "sg:province":"IA",
    "sg:tags":[
        "trucking"
    ],
    "wof:name":"Ricky R Kay & Sons Inc",
    "wof:placetype":"venue"
},
  "geometry": {"coordinates":[-90.838595,41.834354],"type":"Point"}
}