{
  "type": "Feature",
  "properties": {
    "iso:country":"US",
    "sg:address":"952 N Main Ave",
    "sg:city":"Sioux Center",
    "sg:classifiers":[
        {
            "category":"Banks & Credit Unions",
            "subcategory":"Investment Brokerage",
            "type":"Services"
        }
    ],
    "sg:phone":"+1 712 722 4902",
    "sg:postcode":"51250",
    "sg:province":"IA",
    "sg:tags":[
        "advisory",
        "financial"
    ],
    "wof:name":"Water Valley Investment Adv",
    "wof:placetype":"venue"
},
  "geometry": {"coordinates":[-96.175652,43.086397],"type":"Point"}
}