{
  "type": "Feature",
  "properties": {
    "addr:full":"806 W Taylor Ave Fairfield IA 52556",
    "addr:housenumber":"806",
    "addr:postcode":"52556",
    "addr:street":"W Taylor Ave",
    "iso:country":"US",
    "sg:address":"806 W Taylor Ave",
    "sg:city":"Fairfield",
    "sg:classifiers":[
        {
            "category":"Shopping",
            "subcategory":"Gifts & Souvenirs",
            "type":"Retail Goods"
        }
    ],
    "sg:phone":"+1 641 472 6423",
    "sg:postcode":"52556",
    "sg:province":"IA",
    "wof:name":"Cookies From Heart",
    "wof:placetype":"venue"
},
  "geometry": {"coordinates":[-91.974925,40.99627],"type":"Point"}
}