{
  "type": "Feature",
  "properties": {
    "addr:full":"612 Cyclone Ave Harlan IA 51537",
    "addr:housenumber":"612",
    "addr:postcode":"51537",
    "addr:street":"Cyclone Ave",
    "iso:country":"US",
    "sg:address":"612 Cyclone Ave",
    "sg:city":"Harlan",
    "sg:classifiers":[
        {
            "category":"Shopping",
            "type":"Retail Goods"
        }
    ],
    "sg:phone":"+1 712 755 5773",
    "sg:postcode":"51537",
    "sg:province":"IA",
    "sg:tags":[
        "armature",
        "merchandise",
        "rewinding"
    ],
    "wof:name":"Petersen Electric Motors",
    "wof:placetype":"venue"
},
  "geometry": {"coordinates":[-95.317882,41.660378],"type":"Point"}
}