{
  "type": "Feature",
  "properties": {
    "addr:full":"318 S Maple St Carroll IA 51401",
    "addr:housenumber":"318",
    "addr:postcode":"51401",
    "addr:street":"S Maple St",
    "iso:country":"US",
    "sg:address":"318 S Maple St",
    "sg:city":"Carroll",
    "sg:classifiers":[
        {
            "category":"Health Services",
            "subcategory":"Clinic",
            "type":"Services"
        }
    ],
    "sg:phone":"+1 712 792 8279",
    "sg:postcode":"51401",
    "sg:province":"IA",
    "sg:tags":[
        "home"
    ],
    "wof:name":"St Anthony Home Health",
    "wof:placetype":"venue"
},
  "geometry": {"coordinates":[-94.864239,42.056617],"type":"Point"}
}