{
  "type": "Feature",
  "properties": {
    "addr:full":"1570 S 1st Ave Iowa City IA 52240",
    "addr:housenumber":"1570",
    "addr:postcode":"52240",
    "addr:street":"S 1St Ave",
    "iso:country":"US",
    "sg:address":"1570 S 1st Ave",
    "sg:city":"Iowa City",
    "sg:classifiers":[
        {
            "category":"Real Estate",
            "subcategory":"Real Estate Agent",
            "type":"Services"
        }
    ],
    "sg:phone":"+1 319 358 0161",
    "sg:postcode":"52240",
    "sg:province":"IA",
    "wof:name":"Realty Executives",
    "wof:placetype":"venue"
},
  "geometry": {"coordinates":[-91.506193,41.642006],"type":"Point"}
}