{
  "type": "Feature",
  "properties": {
    "iso:country":"US",
    "sg:address":"111 Lynn Ave",
    "sg:city":"Ames",
    "sg:classifiers":[
        {
            "category":"Professional",
            "subcategory":"Business Services",
            "type":"Services"
        }
    ],
    "sg:phone":"+1 515 292 0710",
    "sg:postcode":"50014",
    "sg:province":"IA",
    "wof:name":"Jls Enterprises USA Inc",
    "wof:placetype":"venue"
},
  "geometry": {"coordinates":[-93.646478,42.021942],"type":"Point"}
}