{
  "type": "Feature",
  "properties": {
    "addr:full":"1405 Center St Cedar Falls IA 50613",
    "addr:housenumber":"1405",
    "addr:postcode":"50613",
    "addr:street":"Center St",
    "iso:country":"US",
    "sg:address":"1405 Center St",
    "sg:city":"Cedar Falls",
    "sg:classifiers":[
        {
            "category":"Shopping",
            "type":"Retail Goods"
        }
    ],
    "sg:phone":"+1 319 273 9021",
    "sg:postcode":"50613",
    "sg:province":"IA",
    "sg:tags":[
        "monument"
    ],
    "wof:name":"Granite By Design",
    "wof:placetype":"venue"
},
  "geometry": {"coordinates":[-92.454961,42.552554],"type":"Point"}
}