{
  "type": "Feature",
  "properties": {
    "iso:country":"US",
    "sg:address":"1302 N 2nd Ave",
    "sg:city":"Washington",
    "sg:classifiers":[
        {
            "category":"Retail",
            "subcategory":"Auto Repair",
            "type":"Services"
        }
    ],
    "sg:phone":"+1 319 653 6919",
    "sg:postcode":"52353",
    "sg:province":"IA",
    "sg:tags":[
        "body",
        "automobile",
        "painting"
    ],
    "wof:name":"Randall's Body & Paint",
    "wof:placetype":"venue"
},
  "geometry": {"coordinates":[-91.690219,41.311801],"type":"Point"}
}