{
  "type": "Feature",
  "properties": {
    "iso:country":"US",
    "sg:address":"1108 Bruce Ln",
    "sg:city":"Pella",
    "sg:classifiers":[
        {
            "category":"Organizations",
            "subcategory":"Labor Organization",
            "type":"Services"
        }
    ],
    "sg:phone":"+1 641 628 3302",
    "sg:postcode":"50219",
    "sg:province":"IA",
    "wof:name":"Fifield Development Lc",
    "wof:placetype":"venue"
},
  "geometry": {"coordinates":[-92.925589,41.41907],"type":"Point"}
}