{
  "type": "Feature",
  "properties": {
    "iso:country":"US",
    "sg:address":"1507 237th St",
    "sg:city":"Ventura",
    "sg:classifiers":[
        {
            "category":"Retail",
            "subcategory":"Repair Shop",
            "type":"Services"
        }
    ],
    "sg:phone":"+1 641 829 4409",
    "sg:postcode":"50482",
    "sg:province":"IA",
    "wof:name":"Big Marsh Taxidermy",
    "wof:placetype":"venue"
},
  "geometry": {"coordinates":[-93.487978,43.108409],"type":"Point"}
}