{
  "type": "Feature",
  "properties": {
    "addr:full":"204 N Main St Fairfield IA 52556",
    "addr:housenumber":"204",
    "addr:postcode":"52556",
    "addr:street":"N Main St",
    "iso:country":"US",
    "sg:address":"204 N Main St",
    "sg:city":"Fairfield",
    "sg:classifiers":[
        {
            "category":"Health Services",
            "subcategory":"Chiropractor",
            "type":"Services"
        }
    ],
    "sg:phone":"+1 641 472 6202",
    "sg:postcode":"52556",
    "sg:province":"IA",
    "wof:name":"Main Chiropractic",
    "wof:placetype":"venue"
},
  "geometry": {"coordinates":[-91.963819,41.009489],"type":"Point"}
}