{
  "type": "Feature",
  "properties": {
    "iso:country":"US",
    "sg:address":"4396 NW 6th Dr",
    "sg:city":"Des Moines",
    "sg:classifiers":[
        {
            "category":"Building & Trades",
            "subcategory":"Landscaping Services",
            "type":"Services"
        }
    ],
    "sg:phone":"+1 515 282 0203",
    "sg:postcode":"50313",
    "sg:province":"IA",
    "sg:tags":[
        "landscape",
        "contractor"
    ],
    "wof:name":"Brown's Dirt Work",
    "wof:placetype":"venue"
},
  "geometry": {"coordinates":[-93.625472,41.638591],"type":"Point"}
}