{
  "type": "Feature",
  "properties": {
    "iso:country":"US",
    "sg:address":"1001 Ave H",
    "sg:city":"Carter Lake",
    "sg:classifiers":[
        {
            "category":"Organizations",
            "subcategory":"Non-profit Organization",
            "type":"Services"
        }
    ],
    "sg:phone":"+1 712 347 6781",
    "sg:postcode":"51510",
    "sg:province":"IA",
    "wof:name":"Ponca Tribe Of Nebraska",
    "wof:placetype":"venue"
},
  "geometry": {"coordinates":[-95.913546,41.281245],"type":"Point"}
}