{
  "type": "Feature",
  "properties": {
    "iso:country":"US",
    "sg:address":"607 W Grimes Ave",
    "sg:city":"Fairfield",
    "sg:classifiers":[
        {
            "category":"Building & Trades",
            "subcategory":"Construction",
            "type":"Services"
        }
    ],
    "sg:phone":"+1 641 469 3432",
    "sg:postcode":"52556",
    "sg:province":"IA",
    "sg:tags":[
        "spray",
        "painting",
        "finishing"
    ],
    "wof:name":"Paint-Line",
    "wof:placetype":"venue"
},
  "geometry": {"coordinates":[-91.97111599999999,41.010133],"type":"Point"}
}