{
  "type": "Feature",
  "properties": {
    "iso:country":"US",
    "sg:address":"802 E 1st St",
    "sg:city":"Pella",
    "sg:classifiers":[
        {
            "category":"Health Services",
            "subcategory":"Doctor",
            "type":"Services"
        }
    ],
    "sg:phone":"+1 641 628 1587",
    "sg:postcode":"50219",
    "sg:province":"IA",
    "sg:tags":[
        "dentist"
    ],
    "wof:name":"American Orthodontists",
    "wof:placetype":"venue"
},
  "geometry": {"coordinates":[-92.914625,41.408041],"type":"Point"}
}