{
  "type": "Feature",
  "properties": {
    "iso:country":"US",
    "sg:address":"3571 260th St",
    "sg:city":"Lytton",
    "sg:classifiers":[
        {
            "category":"Building & Trades",
            "subcategory":"Construction",
            "type":"Services"
        }
    ],
    "sg:phone":"+1 712 466 2784",
    "sg:postcode":"50561",
    "sg:province":"IA",
    "sg:tags":[
        "house"
    ],
    "wof:name":"Graeve Const Co",
    "wof:placetype":"venue"
},
  "geometry": {"coordinates":[-94.893452,42.414127],"type":"Point"}
}