{
  "type": "Feature",
  "properties": {
    "addr:full":"4473 Texas St Waterloo IA 50702",
    "addr:housenumber":"4473",
    "addr:postcode":"50702",
    "addr:street":"Texas St",
    "iso:country":"US",
    "sg:address":"4473 Texas St",
    "sg:city":"Waterloo",
    "sg:classifiers":[
        {
            "category":"Manufacturing",
            "subcategory":"Tools & Machinery",
            "type":"Manufacturing & Wholesale Goods"
        }
    ],
    "sg:phone":"+1 319 296 2335",
    "sg:postcode":"50702",
    "sg:province":"IA",
    "sg:tags":[
        "water",
        "equipment",
        "works",
        "supply"
    ],
    "wof:name":"Utility Equipment Co",
    "wof:placetype":"venue"
},
  "geometry": {"coordinates":[-92.304661,42.451172],"type":"Point"}
}