{
  "type": "Feature",
  "properties": {
    "addr:full":"700 Baker St Minburn IA 50167",
    "addr:housenumber":"700",
    "addr:postcode":"50167",
    "addr:street":"Baker St",
    "iso:country":"US",
    "sg:address":"700 Baker St",
    "sg:city":"Minburn",
    "sg:classifiers":[
        {
            "category":"Manufacturing",
            "subcategory":"Tools & Machinery",
            "type":"Manufacturing & Wholesale Goods"
        }
    ],
    "sg:phone":"+1 515 677 2700",
    "sg:postcode":"50167",
    "sg:province":"IA",
    "wof:name":"Di-Mold Machine & Tool",
    "wof:placetype":"venue"
},
  "geometry": {"coordinates":[-94.03132100000001,41.757428],"type":"Point"}
}