{
  "type": "Feature",
  "properties": {
    "addr:full":"129 Derbyshire Rd Waterloo IA 50701",
    "addr:housenumber":"129",
    "addr:postcode":"50701",
    "addr:street":"Derbyshire Rd",
    "iso:country":"US",
    "sg:address":"129 Derbyshire Rd",
    "sg:city":"Waterloo",
    "sg:classifiers":[
        {
            "category":"Wholesale",
            "subcategory":"Vending Machines",
            "type":"Manufacturing & Wholesale Goods"
        }
    ],
    "sg:phone":"+1 319 226 3000",
    "sg:postcode":"50701",
    "sg:province":"IA",
    "wof:name":"Vending Connection",
    "wof:placetype":"venue"
},
  "geometry": {"coordinates":[-92.360817,42.477334],"type":"Point"}
}