{
  "type": "Feature",
  "properties": {
    "addr:full":"102 W Quarry St Maquoketa IA 52060",
    "addr:housenumber":"102",
    "addr:postcode":"52060",
    "addr:street":"W Quarry St",
    "iso:country":"US",
    "sg:address":"102 W Quarry St",
    "sg:city":"Maquoketa",
    "sg:classifiers":[
        {
            "category":"Professional",
            "subcategory":"Advertising",
            "type":"Services"
        }
    ],
    "sg:phone":"+1 563 652 2441",
    "sg:postcode":"52060",
    "sg:province":"IA",
    "sg:website":"www.maquoketasentinelpress.com",
    "wof:name":"Maquoketa Sentinel Press",
    "wof:placetype":"venue"
},
  "geometry": {"coordinates":[-90.66669899999999,42.070998],"type":"Point"}
}