{
  "type": "Feature",
  "properties": {
    "iso:country":"US",
    "sg:address":"506 Holmes St",
    "sg:city":"Bettendorf",
    "sg:classifiers":[
        {
            "category":"Bakery",
            "type":"Food & Drink"
        }
    ],
    "sg:phone":"+1 563 344 7947",
    "sg:postcode":"52722",
    "sg:province":"IA",
    "sg:tags":[
        "cake",
        "pastry",
        "wedding"
    ],
    "wof:name":"Cakes By Ronda",
    "wof:placetype":"venue"
},
  "geometry": {"coordinates":[-90.52521400000001,41.528614],"type":"Point"}
}