{
  "type": "Feature",
  "properties": {
    "addr:full":"1101 Avenue H Carter Lake IA 51510",
    "addr:housenumber":"1101",
    "addr:postcode":"51510",
    "addr:street":"Avenue H Carter",
    "iso:country":"US",
    "sg:address":"1101 Avenue H",
    "sg:city":"Carter Lake",
    "sg:classifiers":[
        {
            "category":"Wholesale",
            "subcategory":"Fruits & Vegetables",
            "type":"Manufacturing & Wholesale Goods"
        }
    ],
    "sg:phone":"+1 712 347 6787",
    "sg:postcode":"51510",
    "sg:province":"IA",
    "sg:tags":[
        "veggie"
    ],
    "wof:name":"Loffredo Fresh Produce Inc",
    "wof:placetype":"venue"
},
  "geometry": {"coordinates":[-95.915497,41.2813],"type":"Point"}
}