{
  "type": "Feature",
  "properties": {
    "addr:full":"12 N 4th St Clear Lake IA 50428",
    "addr:housenumber":"12",
    "addr:postcode":"50428",
    "addr:street":"N 4Th St",
    "iso:country":"US",
    "sg:address":"12 N 4th St",
    "sg:city":"Clear Lake",
    "sg:classifiers":[
        {
            "category":"Manufacturing",
            "subcategory":"Printing",
            "type":"Manufacturing & Wholesale Goods"
        }
    ],
    "sg:phone":"+1 641 357 2131",
    "sg:postcode":"50428",
    "sg:province":"IA",
    "sg:tags":[
        "newspaper"
    ],
    "sg:website":"www.clreporter.com",
    "wof:name":"Clear Lake Mirror-Reporter",
    "wof:placetype":"venue"
},
  "geometry": {"coordinates":[-93.381687,43.13724],"type":"Point"}
}