{
  "type": "Feature",
  "properties": {
    "iso:country":"US",
    "sg:address":"303 3rd St NE",
    "sg:city":"Dyersville",
    "sg:classifiers":[
        {
            "category":"Wholesale",
            "subcategory":"Farm Supplies",
            "type":"Manufacturing & Wholesale Goods"
        }
    ],
    "sg:phone":"+1 563 875 7953",
    "sg:postcode":"52040",
    "sg:province":"IA",
    "sg:tags":[
        "feed"
    ],
    "wof:name":"Farmers Shipping Assoc",
    "wof:placetype":"venue"
},
  "geometry": {"coordinates":[-91.121499,42.487319],"type":"Point"}
}