{
  "type": "Feature",
  "properties": {
    "iso:country":"US",
    "sg:address":"1035 Shore St",
    "sg:city":"Murray",
    "sg:classifiers":[
        {
            "category":"Farming",
            "subcategory":"Farm",
            "type":"Manufacturing & Wholesale Goods"
        }
    ],
    "sg:phone":"+1 641 763 2338",
    "sg:postcode":"50174",
    "sg:province":"IA",
    "sg:tags":[
        "crop",
        "general"
    ],
    "wof:name":"Gibbons Farms",
    "wof:placetype":"venue"
},
  "geometry": {"coordinates":[-94.00873,41.145225],"type":"Point"}
}