{
  "type": "Feature",
  "properties": {
    "iso:country":"US",
    "sg:address":"1240 NW 75th St",
    "sg:city":"Clive",
    "sg:classifiers":[
        {
            "category":"Retail",
            "subcategory":"Auto Repair",
            "type":"Services"
        }
    ],
    "sg:phone":"+1 515 255 4041",
    "sg:postcode":"50325",
    "sg:province":"IA",
    "sg:tags":[
        "repairing",
        "automobile"
    ],
    "wof:name":"Terry's Auto Svc",
    "wof:placetype":"venue"
},
  "geometry": {"coordinates":[-93.722414,41.606395],"type":"Point"}
}