{
  "type": "Feature",
  "properties": {
    "iso:country":"US",
    "sg:address":"711 Main St",
    "sg:city":"Bernardsville",
    "sg:classifiers":[
        {
            "category":"Building & Trades",
            "subcategory":"Pest Control",
            "type":"Services"
        }
    ],
    "sg:phone":"+1 908 766 0411",
    "sg:postcode":"52141",
    "sg:province":"IA",
    "wof:name":"Viking Termite & Pest Control",
    "wof:placetype":"venue"
},
  "geometry": {"coordinates":[-91.638204,42.956489],"type":"Point"}
}