{
  "type": "Feature",
  "properties": {
    "iso:country":"US",
    "sg:address":"827 12th St",
    "sg:city":"Belle Plaine",
    "sg:classifiers":[
        {
            "category":"Home & Garden",
            "subcategory":"Hardware",
            "type":"Retail Goods"
        }
    ],
    "sg:phone":"+1 319 444 2541",
    "sg:postcode":"52208",
    "sg:province":"IA",
    "wof:name":"True Value Hardware",
    "wof:placetype":"venue"
},
  "geometry": {"coordinates":[-92.275268,41.896229],"type":"Point"}
}