{
  "type": "Feature",
  "properties": {
    "iso:country":"US",
    "sg:address":"18536 296th Ave",
    "sg:city":"Udell",
    "sg:classifiers":[
        {
            "category":"Farming",
            "subcategory":"Livestock Farm",
            "type":"Manufacturing & Wholesale Goods"
        }
    ],
    "sg:phone":"+1 641 452 6448",
    "sg:postcode":"52593",
    "sg:province":"IA",
    "sg:tags":[
        "feedlot",
        "corn",
        "soybean",
        "beef",
        "cattle"
    ],
    "wof:name":"Terry Piatt",
    "wof:placetype":"venue"
},
  "geometry": {"coordinates":[-92.724346,40.775593],"type":"Point"}
}