{
  "type": "Feature",
  "properties": {
    "addr:full":"912 Gilman St Sheffield IA 50475",
    "addr:housenumber":"912",
    "addr:postcode":"50475",
    "addr:street":"Gilman St",
    "iso:country":"US",
    "sg:address":"912 Gilman St",
    "sg:city":"Sheffield",
    "sg:classifiers":[
        {
            "category":"Professional",
            "subcategory":"Business Services",
            "type":"Services"
        }
    ],
    "sg:phone":"+1 641 892 4669",
    "sg:postcode":"50475",
    "sg:province":"IA",
    "wof:name":"Moehle Salvage",
    "wof:placetype":"venue"
},
  "geometry": {"coordinates":[-93.223592,42.893452],"type":"Point"}
}