{
  "type": "Feature",
  "properties": {
    "addr:full":"1044 Mobile St Waterloo IA 50703",
    "addr:housenumber":"1044",
    "addr:postcode":"50703",
    "addr:street":"Mobile St",
    "iso:country":"US",
    "sg:address":"1044 Mobile St",
    "sg:city":"Waterloo",
    "sg:classifiers":[
        {
            "category":"Organizations",
            "subcategory":"Religious Organization",
            "type":"Services"
        }
    ],
    "sg:phone":"+1 319 233 8189",
    "sg:postcode":"50703",
    "sg:province":"IA",
    "sg:tags":[
        "church"
    ],
    "wof:name":"Payne Memorial AME Church",
    "wof:placetype":"venue"
},
  "geometry": {"coordinates":[-92.32273499999999,42.505658],"type":"Point"}
}