{
  "type": "Feature",
  "properties": {
    "addr:full":"610 Iowa Ave Onawa IA 51040",
    "addr:housenumber":"610",
    "addr:postcode":"51040",
    "addr:street":"Iowa Ave",
    "iso:country":"US",
    "sg:address":"610 Iowa Ave",
    "sg:city":"Onawa",
    "sg:classifiers":[
        {
            "category":"Government",
            "subcategory":"Office",
            "type":"Public Place"
        }
    ],
    "sg:phone":"+1 712 423 1921",
    "sg:postcode":"51040",
    "sg:province":"IA",
    "sg:tags":[
        "county",
        "resource"
    ],
    "wof:name":"Monona County Human Svc",
    "wof:placetype":"venue"
},
  "geometry": {"coordinates":[-96.092994,42.026756],"type":"Point"}
}