{
  "type": "Feature",
  "properties": {
    "addr:full":"531 Commanche St Council Bluffs IA 51501",
    "addr:housenumber":"531",
    "addr:postcode":"51501",
    "addr:street":"Commanche St",
    "iso:country":"US",
    "sg:address":"531 Commanche St",
    "sg:city":"Council Bluffs",
    "sg:classifiers":[
        {
            "category":"Sports & Exercise",
            "subcategory":"Sports Center",
            "type":"Entertainment"
        },
        {
            "category":"Arena",
            "subcategory":"Sports Club",
            "type":"Entertainment"
        }
    ],
    "sg:phone":"+1 712 366 9930",
    "sg:postcode":"51501",
    "sg:province":"IA",
    "sg:tags":[
        "professional",
        "amateur",
        "team"
    ],
    "wof:name":"Fish & Game Club",
    "wof:placetype":"venue"
},
  "geometry": {"coordinates":[-95.854401,41.214401],"type":"Point"}
}