{
  "type": "Feature",
  "properties": {
    "iso:country":"US",
    "sg:address":"3000 Ave B",
    "sg:city":"Council Bluffs",
    "sg:classifiers":[
        {
            "category":"Shopping",
            "subcategory":"Florist",
            "type":"Retail Goods"
        }
    ],
    "sg:phone":"+1 712 322 4445",
    "sg:postcode":"51501",
    "sg:province":"IA",
    "wof:name":"Perla's Flower Shop",
    "wof:placetype":"venue"
},
  "geometry": {"coordinates":[-95.894127,41.263697],"type":"Point"}
}