{
  "type": "Feature",
  "properties": {
    "addr:full":"830 2nd St NE Hartley IA 51346",
    "addr:housenumber":"830",
    "addr:postcode":"51346",
    "addr:street":"2Nd St Ne",
    "iso:country":"US",
    "sg:address":"830 2nd St NE",
    "sg:city":"Hartley",
    "sg:classifiers":[
        {
            "category":"Retail",
            "subcategory":"Funeral Services",
            "type":"Services"
        }
    ],
    "sg:phone":"+1 712 928 4238",
    "sg:postcode":"51346",
    "sg:province":"IA",
    "sg:tags":[
        "director"
    ],
    "wof:name":"Hartley Funeral Home",
    "wof:placetype":"venue"
},
  "geometry": {"coordinates":[-95.467697,43.183756],"type":"Point"}
}