{
  "type": "Feature",
  "properties": {
    "iso:country":"US",
    "sg:address":"800 2nd St",
    "sg:city":"Coralville",
    "sg:classifiers":[
        {
            "category":"Utilities",
            "subcategory":"Mobile Phone",
            "type":"Services"
        }
    ],
    "sg:phone":"+1 319 354 7440",
    "sg:postcode":"52241",
    "sg:province":"IA",
    "sg:tags":[
        "telephone",
        "cellular"
    ],
    "wof:name":"That Cellular Place",
    "wof:placetype":"venue"
},
  "geometry": {"coordinates":[-91.576092,41.671974],"type":"Point"}
}