{
  "type": "Feature",
  "properties": {
    "addr:full":"4556 390th Ave Curlew IA 50527",
    "addr:housenumber":"4556",
    "addr:postcode":"50527",
    "addr:street":"390Th Ave",
    "iso:country":"US",
    "sg:address":"4556 390th Ave",
    "sg:city":"Curlew",
    "sg:phone":"+1 712 426 4162",
    "sg:postcode":"50527",
    "sg:province":"IA",
    "sg:tags":[
        "farm",
        "corn",
        "soybean"
    ],
    "wof:name":"Emmett Degnan",
    "wof:placetype":"venue"
},
  "geometry": {"coordinates":[-94.816564,42.987885],"type":"Point"}
}