{
  "type": "Feature",
  "properties": {
    "addr:full":"2000 E Grand Ave Des Moines IA 50317",
    "addr:housenumber":"2000",
    "addr:postcode":"50317",
    "addr:street":"E Grand Ave",
    "iso:country":"US",
    "sg:address":"2000 E Grand Ave",
    "sg:city":"Des Moines",
    "sg:classifiers":[
        {
            "category":"Home & Garden",
            "subcategory":"Building Materials",
            "type":"Retail Goods"
        }
    ],
    "sg:phone":"+1 515 262 5662",
    "sg:postcode":"50317",
    "sg:province":"IA",
    "sg:tags":[
        "glass",
        "window",
        "plate"
    ],
    "sg:website":"www.clarkglass.com",
    "wof:name":"Clark Glass Inc",
    "wof:placetype":"venue"
},
  "geometry": {"coordinates":[-93.57998000000001,41.595411],"type":"Point"}
}