{
  "type": "Feature",
  "properties": {
    "iso:country":"US",
    "sg:address":"728 3rd Ave SE",
    "sg:city":"Cedar Rapids",
    "sg:classifiers":[
        {
            "category":"Professional",
            "subcategory":"Business Services",
            "type":"Services"
        }
    ],
    "sg:phone":"+1 319 363 9634",
    "sg:postcode":"52401",
    "sg:province":"IA",
    "sg:tags":[
        "interior",
        "consultant",
        "design",
        "decorator"
    ],
    "sg:website":"www.phelansinteriors.com",
    "wof:name":"Phelan's Interiors",
    "wof:placetype":"venue"
},
  "geometry": {"coordinates":[-91.66089599999999,41.980301],"type":"Point"}
}