{
  "type": "Feature",
  "properties": {
    "iso:country":"US",
    "sg:address":"312 S 1st St",
    "sg:city":"Manchester",
    "sg:classifiers":[
        {
            "category":"Bars & Pubs",
            "type":"Food & Drink"
        }
    ],
    "sg:phone":"+1 563 927 3864",
    "sg:postcode":"52057",
    "sg:province":"IA",
    "wof:name":"Barn",
    "wof:placetype":"venue"
},
  "geometry": {"coordinates":[-91.459377,42.482064],"type":"Point"}
}