{
  "type": "Feature",
  "properties": {
    "iso:country":"US",
    "sg:address":"111 S Main St",
    "sg:city":"Preston",
    "sg:classifiers":[
        {
            "category":"Retail",
            "subcategory":"Funeral Services",
            "type":"Services"
        }
    ],
    "sg:phone":"+1 563 689 5326",
    "sg:postcode":"52069",
    "sg:province":"IA",
    "sg:tags":[
        "director"
    ],
    "wof:name":"Miller-Law-Jones Funeral Home",
    "wof:placetype":"venue"
},
  "geometry": {"coordinates":[-90.39402699999999,42.048856],"type":"Point"}
}