{
  "type": "Feature",
  "properties": {
    "iso:country":"US",
    "sg:address":"217 S Duff Ave",
    "sg:city":"Ames",
    "sg:classifiers":[
        {
            "category":"Banks & Credit Unions",
            "subcategory":"Investment Brokerage",
            "type":"Services"
        }
    ],
    "sg:phone":"+1 515 232 3371",
    "sg:postcode":"50010",
    "sg:province":"IA",
    "sg:tags":[
        "stock",
        "bond"
    ],
    "wof:name":"Edward Jones Co",
    "wof:placetype":"venue"
},
  "geometry": {"coordinates":[-93.61039,42.020976],"type":"Point"}
}