{
  "type": "Feature",
  "properties": {
    "iso:country":"US",
    "sg:address":"5090 State Hwy 3",
    "sg:city":"Cherokee",
    "sg:classifiers":[
        {
            "category":"Manufacturing",
            "subcategory":"Tools & Machinery",
            "type":"Manufacturing & Wholesale Goods"
        }
    ],
    "sg:phone":"+1 712 225 3107",
    "sg:postcode":"51012",
    "sg:province":"IA",
    "sg:tags":[
        "machine",
        "shop"
    ],
    "wof:name":"Johnson Machine Shop",
    "wof:placetype":"venue"
},
  "geometry": {"coordinates":[-95.56139899999999,42.779326],"type":"Point"}
}