{
  "type": "Feature",
  "properties": {
    "addr:full":"14854 385th St Carson IA 51525",
    "addr:housenumber":"14854",
    "addr:postcode":"51525",
    "addr:street":"385Th St",
    "iso:country":"US",
    "sg:address":"14854 385th St",
    "sg:city":"Carson",
    "sg:phone":"+1 712 484 3484",
    "sg:postcode":"51525",
    "sg:province":"IA",
    "sg:tags":[
        "farm",
        "corn"
    ],
    "wof:name":"Jeffrey Martens",
    "wof:placetype":"venue"
},
  "geometry": {"coordinates":[-95.452063,41.230098],"type":"Point"}
}