{
  "type": "Feature",
  "properties": {
    "addr:full":"2748 300th St Rock Valley IA 51247",
    "addr:housenumber":"2748",
    "addr:postcode":"51247",
    "addr:street":"300Th St",
    "iso:country":"US",
    "sg:address":"2748 300th St",
    "sg:city":"Rock Valley",
    "sg:classifiers":[
        {
            "category":"Wholesale",
            "subcategory":"Vending Machines",
            "type":"Manufacturing & Wholesale Goods"
        }
    ],
    "sg:phone":"+1 712 476 2941",
    "sg:postcode":"51247",
    "sg:province":"IA",
    "sg:tags":[
        "candy"
    ],
    "wof:name":"Consumer Advantage",
    "wof:placetype":"venue"
},
  "geometry": {"coordinates":[-96.24620400000001,43.214894],"type":"Point"}
}