{
  "type": "Feature",
  "properties": {
    "iso:country":"US",
    "sg:address":"205 S 27th St",
    "sg:city":"Council Bluffs",
    "sg:classifiers":[
        {
            "category":"Social Services",
            "subcategory":"Child Care",
            "type":"Services"
        },
        {
            "category":"Education",
            "subcategory":"Preschool",
            "type":"Public Place"
        },
        {
            "category":"Education",
            "subcategory":"School",
            "type":"Public Place"
        }
    ],
    "sg:phone":"+1 712 325 5530",
    "sg:postcode":"51501",
    "sg:province":"IA",
    "sg:tags":[
        "elementary",
        "day"
    ],
    "sg:website":"www.lhwp.com",
    "wof:name":"Little Hands At Work & Play",
    "wof:placetype":"venue"
},
  "geometry": {"coordinates":[-95.886588,41.259752],"type":"Point"}
}