{
  "type": "Feature",
  "properties": {
    "iso:country":"US",
    "sg:address":"2626 Grandview Ave",
    "sg:city":"Des Moines",
    "sg:classifiers":[
        {
            "category":"Building & Trades",
            "subcategory":"Construction",
            "type":"Services"
        }
    ],
    "sg:phone":"+1 515 202 0290",
    "sg:postcode":"50317",
    "sg:province":"IA",
    "sg:tags":[
        "repairing",
        "remodeling",
        "contractor"
    ],
    "wof:name":"A 1 Construction Plus LLC",
    "wof:placetype":"venue"
},
  "geometry": {"coordinates":[-93.567081,41.620531],"type":"Point"}
}