{
  "type": "Feature",
  "properties": {
    "addr:full":"309 S 7th Ave Villisca IA 50864",
    "addr:housenumber":"309",
    "addr:postcode":"50864",
    "addr:street":"S 7Th Ave",
    "iso:country":"US",
    "sg:address":"309 S 7th Ave",
    "sg:city":"Villisca",
    "sg:classifiers":[
        {
            "category":"Building & Trades",
            "subcategory":"Landscaping Services",
            "type":"Services"
        }
    ],
    "sg:phone":"+1 712 826 3995",
    "sg:postcode":"50864",
    "sg:province":"IA",
    "wof:name":"Means Lawn Scape",
    "wof:placetype":"venue"
},
  "geometry": {"coordinates":[-94.971546,40.929479],"type":"Point"}
}