{
  "type": "Feature",
  "properties": {
    "addr:full":"3210 O Ave NW Cedar Rapids IA 52405",
    "addr:housenumber":"3210",
    "addr:postcode":"52405",
    "addr:street":"O Ave Nw",
    "iso:country":"US",
    "sg:address":"3210 O Ave NW",
    "sg:city":"Cedar Rapids",
    "sg:classifiers":[
        {
            "category":"Building & Trades",
            "subcategory":"Construction",
            "type":"Services"
        }
    ],
    "sg:phone":"+1 319 521 2872",
    "sg:postcode":"52405",
    "sg:province":"IA",
    "sg:tags":[
        "house"
    ],
    "wof:name":"All Star Home Improvement Inc",
    "wof:placetype":"venue"
},
  "geometry": {"coordinates":[-91.71524700000001,41.989331],"type":"Point"}
}