{
  "type": "Feature",
  "properties": {
    "iso:country":"US",
    "sg:address":"320 W Kimberly Rd",
    "sg:city":"Davenport",
    "sg:classifiers":[
        {
            "category":"Personal",
            "subcategory":"Beauty Salon",
            "type":"Services"
        }
    ],
    "sg:phone":"+1 563 386 2160",
    "sg:postcode":"52806",
    "sg:province":"IA",
    "wof:name":"Inn Case Of Needs",
    "wof:placetype":"venue"
},
  "geometry": {"coordinates":[-90.58105500000001,41.56026],"type":"Point"}
}