{
  "type": "Feature",
  "properties": {
    "addr:full":"2505 Utility Ave Harlan IA 51537",
    "addr:housenumber":"2505",
    "addr:postcode":"51537",
    "addr:street":"Utility Ave",
    "iso:country":"US",
    "sg:address":"2505 Utility Ave",
    "sg:city":"Harlan",
    "sg:classifiers":[
        {
            "category":"Recreation",
            "type":"Entertainment"
        }
    ],
    "sg:phone":"+1 712 755 3705",
    "sg:postcode":"51537",
    "sg:province":"IA",
    "sg:tags":[
        "parks"
    ],
    "wof:name":"Harlan Park Dept",
    "wof:placetype":"venue"
},
  "geometry": {"coordinates":[-95.317082,41.644689],"type":"Point"}
}