{
  "type": "Feature",
  "properties": {
    "addr:full":"5625 Carey Ave Davenport IA 52807",
    "addr:housenumber":"5625",
    "addr:postcode":"52807",
    "addr:street":"Carey Ave",
    "iso:country":"US",
    "sg:address":"5625 Carey Ave",
    "sg:city":"Davenport",
    "sg:classifiers":[
        {
            "category":"Wholesale",
            "subcategory":"Home Furnishings",
            "type":"Manufacturing & Wholesale Goods"
        },
        {
            "category":"Manufacturing",
            "subcategory":"Rubber & Plastics",
            "type":"Manufacturing & Wholesale Goods"
        }
    ],
    "sg:phone":"+1 563 386 3194",
    "sg:postcode":"52807",
    "sg:province":"IA",
    "sg:tags":[
        "product",
        "accessory",
        "closet",
        "mfg"
    ],
    "wof:name":"California Closet Co",
    "wof:placetype":"venue"
},
  "geometry": {"coordinates":[-90.558154,41.578918],"type":"Point"}
}