{
  "type": "Feature",
  "properties": {
    "iso:country":"US",
    "sg:address":"616 1st Ave S",
    "sg:city":"Estherville",
    "sg:classifiers":[
        {
            "category":"Autos & Motor Vehicles",
            "subcategory":"Auto Supplies",
            "type":"Retail Goods"
        }
    ],
    "sg:phone":"+1 712 362 3547",
    "sg:postcode":"51334",
    "sg:province":"IA",
    "sg:tags":[
        "automobile",
        "parts"
    ],
    "wof:name":"Motor Supply Co",
    "wof:placetype":"venue"
},
  "geometry": {"coordinates":[-94.835477,43.400947],"type":"Point"}
}