{
  "type": "Feature",
  "properties": {
    "addr:full":"29383 Olde Farley Rd Farley IA 52046",
    "addr:housenumber":"29383",
    "addr:postcode":"52046",
    "addr:street":"Olde Farley Rd",
    "iso:country":"US",
    "sg:address":"29383 Olde Farley Rd",
    "sg:city":"Farley",
    "sg:classifiers":[
        {
            "category":"Farming",
            "subcategory":"Livestock Farm",
            "type":"Manufacturing & Wholesale Goods"
        }
    ],
    "sg:phone":"+1 563 875 7343",
    "sg:postcode":"52046",
    "sg:province":"IA",
    "sg:tags":[
        "feedlot",
        "hog",
        "or",
        "beef",
        "cattle"
    ],
    "wof:name":"Edwin Burlege",
    "wof:placetype":"venue"
},
  "geometry": {"coordinates":[-91.065915,42.429906],"type":"Point"}
}