{
  "type": "Feature",
  "properties": {
    "iso:country":"US",
    "sg:address":"311 370th St",
    "sg:city":"Fenton",
    "sg:classifiers":[
        {
            "category":"Government",
            "subcategory":"Office",
            "type":"Public Place"
        }
    ],
    "sg:phone":"+1 515 925 3308",
    "sg:postcode":"50539",
    "sg:province":"IA",
    "wof:name":"Kossuth County Shed",
    "wof:placetype":"venue"
},
  "geometry": {"coordinates":[-94.39258700000001,43.298447],"type":"Point"}
}