{
  "type": "Feature",
  "properties": {
    "addr:full":"2309 Arlington Ave Davenport IA 52803",
    "addr:housenumber":"2309",
    "addr:postcode":"52803",
    "addr:street":"Arlington Ave",
    "iso:country":"US",
    "sg:address":"2309 Arlington Ave",
    "sg:city":"Davenport",
    "sg:classifiers":[
        {
            "category":"Organizations",
            "subcategory":"Non-profit Organization",
            "type":"Services"
        }
    ],
    "sg:phone":"+1 563 324 5655",
    "sg:postcode":"52803",
    "sg:province":"IA",
    "sg:tags":[
        "information",
        "alcoholism",
        "treatment"
    ],
    "wof:name":"Alcoholics Anonymous",
    "wof:placetype":"venue"
},
  "geometry": {"coordinates":[-90.562206,41.543219],"type":"Point"}
}