{
  "type": "Feature",
  "properties": {
    "addr:full":"2112 Stuart Rd Greenfield IA 50849",
    "addr:housenumber":"2112",
    "addr:postcode":"50849",
    "addr:street":"Stuart Rd",
    "iso:country":"US",
    "sg:address":"2112 Stuart Rd",
    "sg:city":"Greenfield",
    "sg:classifiers":[
        {
            "category":"Farming",
            "subcategory":"Livestock Farm",
            "type":"Manufacturing & Wholesale Goods"
        }
    ],
    "sg:phone":"+1 641 743 2628",
    "sg:postcode":"50849",
    "sg:province":"IA",
    "sg:tags":[
        "feedlot",
        "hog",
        "or",
        "beef",
        "cattle"
    ],
    "wof:name":"Larry Vandewater",
    "wof:placetype":"venue"
},
  "geometry": {"coordinates":[-94.317993,41.343056],"type":"Point"}
}