{
  "type": "Feature",
  "properties": {
    "iso:country":"US",
    "sg:address":"31973 State Hwy 2",
    "sg:city":"Pulaski",
    "sg:phone":"+1 641 675 3409",
    "sg:postcode":"52584",
    "sg:province":"IA",
    "sg:tags":[
        "farm",
        "corn",
        "soybean"
    ],
    "wof:name":"William Baughman",
    "wof:placetype":"venue"
},
  "geometry": {"coordinates":[-92.213419,40.683335],"type":"Point"}
}