{
  "type": "Feature",
  "properties": {
    "iso:country":"US",
    "sg:address":"1541 Jennings Ave",
    "sg:city":"Council Bluffs",
    "sg:classifiers":[
        {
            "category":"Building & Trades",
            "subcategory":"Cleaning & Sanitation",
            "type":"Services"
        }
    ],
    "sg:phone":"+1 712 325 8636",
    "sg:postcode":"51503",
    "sg:province":"IA",
    "sg:tags":[
        "property",
        "maintenance"
    ],
    "wof:name":"Professional Building Mntnc",
    "wof:placetype":"venue"
},
  "geometry": {"coordinates":[-95.79956300000001,41.296099],"type":"Point"}
}