{
  "type": "Feature",
  "properties": {
    "addr:full":"333 SW 9th St Des Moines IA 50309",
    "addr:housenumber":"333",
    "addr:postcode":"50309",
    "addr:street":"Sw 9Th St",
    "iso:country":"US",
    "sg:address":"333 SW 9th St",
    "sg:city":"Des Moines",
    "sg:classifiers":[
        {
            "category":"Professional",
            "subcategory":"Engineering",
            "type":"Services"
        }
    ],
    "sg:phone":"+1 515 282 8818",
    "sg:postcode":"50309",
    "sg:province":"IA",
    "sg:tags":[
        "engineer"
    ],
    "sg:website":"www.teamsvcs.com",
    "wof:name":"Team Services",
    "wof:placetype":"venue"
},
  "geometry": {"coordinates":[-93.62615099999999,41.579328],"type":"Point"}
}