{
  "type": "Feature",
  "properties": {
    "iso:country":"US",
    "sg:address":"1531 N 2nd St",
    "sg:city":"Clinton",
    "sg:classifiers":[
        {
            "category":"Personal",
            "subcategory":"Beauty Salon",
            "type":"Services"
        }
    ],
    "sg:phone":"+1 563 242 9398",
    "sg:postcode":"52732",
    "sg:province":"IA",
    "sg:tags":[
        "hair",
        "stylist"
    ],
    "wof:name":"Beyond Hail",
    "wof:placetype":"venue"
},
  "geometry": {"coordinates":[-90.183858,41.861469],"type":"Point"}
}