{
  "type": "Feature",
  "properties": {
    "addr:full":"2889 Hart Ave Melbourne IA 50162",
    "addr:housenumber":"2889",
    "addr:postcode":"50162",
    "addr:street":"Hart Ave",
    "iso:country":"US",
    "sg:address":"2889 Hart Ave",
    "sg:city":"Melbourne",
    "sg:classifiers":[
        {
            "category":"Wholesale",
            "subcategory":"Farm Supplies",
            "type":"Manufacturing & Wholesale Goods"
        }
    ],
    "sg:phone":"+1 641 482 3477",
    "sg:postcode":"50162",
    "sg:province":"IA",
    "sg:tags":[
        "grain"
    ],
    "wof:name":"Leon's Farm Ctr Co",
    "wof:placetype":"venue"
},
  "geometry": {"coordinates":[-93.096582,41.937392],"type":"Point"}
}