{
  "type": "Feature",
  "properties": {
    "iso:country":"US",
    "sg:address":"1710 N 13th Ave E",
    "sg:city":"Newton",
    "sg:classifiers":[
        {
            "category":"Manufacturing",
            "subcategory":"Printing",
            "type":"Manufacturing & Wholesale Goods"
        }
    ],
    "sg:phone":"+1 641 791 2291",
    "sg:postcode":"50208",
    "sg:province":"IA",
    "sg:tags":[
        "commercial"
    ],
    "wof:name":"Jacob North Printing Co",
    "wof:placetype":"venue"
},
  "geometry": {"coordinates":[-93.03175899999999,41.711653],"type":"Point"}
}