{
  "type": "Feature",
  "properties": {
    "iso:country":"US",
    "sg:address":"3339 Agency St",
    "sg:city":"Burlington",
    "sg:classifiers":[
        {
            "category":"Personal",
            "subcategory":"Beauty Salon",
            "type":"Services"
        }
    ],
    "sg:phone":"+1 319 754 9099",
    "sg:postcode":"52601",
    "sg:province":"IA",
    "sg:tags":[
        "shop"
    ],
    "wof:name":"Star Nail",
    "wof:placetype":"venue"
},
  "geometry": {"coordinates":[-91.144588,40.814768],"type":"Point"}
}