{
  "type": "Feature",
  "properties": {
    "iso:country":"US",
    "sg:address":"5206 Seger Ave",
    "sg:city":"Sioux City",
    "sg:classifiers":[
        {
            "category":"Real Estate",
            "subcategory":"Real Estate Agent",
            "type":"Services"
        }
    ],
    "sg:phone":"+1 712 276 7007",
    "sg:postcode":"51106",
    "sg:province":"SD",
    "sg:tags":[
        "appraiser"
    ],
    "wof:name":"Schlueter Appraisal Svc Inc",
    "wof:placetype":"venue"
},
  "geometry": {"coordinates":[-96.338965,42.460415],"type":"Point"}
}