{
  "type": "Feature",
  "properties": {
    "iso:country":"US",
    "sg:address":"216 15th St SE",
    "sg:city":"Cedar Rapids",
    "sg:classifiers":[
        {
            "category":"Arts & Performance",
            "subcategory":"Theater",
            "type":"Entertainment"
        }
    ],
    "sg:phone":"+1 319 363 1109",
    "sg:postcode":"52403",
    "sg:province":"IA",
    "sg:tags":[
        "group"
    ],
    "wof:name":"Prairie Ghost Karaoke",
    "wof:placetype":"venue"
},
  "geometry": {"coordinates":[-91.650555,41.986552],"type":"Point"}
}