{
  "type": "Feature",
  "properties": {
    "addr:full":"92 2nd St Calamus IA 52729",
    "addr:housenumber":"92",
    "addr:postcode":"52729",
    "addr:street":"2Nd St",
    "iso:country":"US",
    "sg:address":"92 2nd St",
    "sg:city":"Calamus",
    "sg:classifiers":[
        {
            "category":"Organizations",
            "subcategory":"Non-profit Organization",
            "type":"Services"
        }
    ],
    "sg:phone":"+1 563 246 2886",
    "sg:postcode":"52729",
    "sg:province":"IA",
    "sg:tags":[
        "fund",
        "counselor",
        "raising"
    ],
    "wof:name":"Jon Knabel Business",
    "wof:placetype":"venue"
},
  "geometry": {"coordinates":[-90.758765,41.823342],"type":"Point"}
}