{
  "type": "Feature",
  "properties": {
    "iso:country":"US",
    "sg:address":"1726 175th St",
    "sg:city":"New Sharon",
    "sg:phone":"+1 641 637 4385",
    "sg:postcode":"50207",
    "sg:province":"IA",
    "sg:tags":[
        "farm",
        "corn",
        "soybean"
    ],
    "wof:name":"Degoey Farm",
    "wof:placetype":"venue"
},
  "geometry": {"coordinates":[-92.732679,41.404488],"type":"Point"}
}