{
  "type": "Feature",
  "properties": {
    "addr:full":"326 2nd Ave Templeton IA 51463",
    "addr:housenumber":"326",
    "addr:postcode":"51463",
    "addr:street":"2Nd Ave",
    "iso:country":"US",
    "sg:address":"326 2nd Ave",
    "sg:city":"Templeton",
    "sg:phone":"+1 712 669 3535",
    "sg:postcode":"51463",
    "sg:province":"IA",
    "sg:tags":[
        "farm",
        "grain",
        "cash"
    ],
    "wof:name":"Schoeppner Digging",
    "wof:placetype":"venue"
},
  "geometry": {"coordinates":[-94.94035,41.916475],"type":"Point"}
}