{
  "type": "Feature",
  "properties": {
    "iso:country":"US",
    "sg:address":"205 Harrison St",
    "sg:city":"Remsen",
    "sg:classifiers":[
        {
            "category":"Personal",
            "subcategory":"Tanning Parlor",
            "type":"Services"
        }
    ],
    "sg:phone":"+1 712 786 3277",
    "sg:postcode":"51050",
    "sg:province":"IA",
    "sg:tags":[
        "salon"
    ],
    "wof:name":"Peggy's Tanning",
    "wof:placetype":"venue"
},
  "geometry": {"coordinates":[-95.970553,42.814366],"type":"Point"}
}