{
  "type": "Feature",
  "properties": {
    "iso:country":"US",
    "sg:address":"506 Harrison St",
    "sg:city":"Victor",
    "sg:classifiers":[
        {
            "category":"Building & Trades",
            "subcategory":"Construction",
            "type":"Services"
        }
    ],
    "sg:phone":"+1 319 647 3287",
    "sg:postcode":"52347",
    "sg:province":"IA",
    "sg:tags":[
        "house"
    ],
    "wof:name":"Bayer Construction",
    "wof:placetype":"venue"
},
  "geometry": {"coordinates":[-92.29505399999999,41.728716],"type":"Point"}
}