{
  "type": "Feature",
  "properties": {
    "iso:country":"US",
    "sg:address":"3089 230th St",
    "sg:city":"Saint Charles",
    "sg:classifiers":[
        {
            "category":"Building & Trades",
            "subcategory":"Construction",
            "type":"Services"
        }
    ],
    "sg:phone":"+1 515 462 4874",
    "sg:postcode":"50240",
    "sg:province":"IA",
    "sg:tags":[
        "residential"
    ],
    "wof:name":"Jim D Tracy",
    "wof:placetype":"venue"
},
  "geometry": {"coordinates":[-93.858977,41.317752],"type":"Point"}
}