{
  "type": "Feature",
  "properties": {
    "addr:full":"400 Public Sq Greenfield IA 50849",
    "addr:housenumber":"400",
    "addr:postcode":"50849",
    "addr:street":"Public Sq",
    "iso:country":"US",
    "sg:address":"400 Public Sq",
    "sg:city":"Greenfield",
    "sg:classifiers":[
        {
            "category":"Government",
            "subcategory":"Office",
            "type":"Public Place"
        }
    ],
    "sg:phone":"+1 641 743 2546",
    "sg:postcode":"50849",
    "sg:province":"IA",
    "wof:name":"Election Information",
    "wof:placetype":"venue"
},
  "geometry": {"coordinates":[-94.461423,41.304789],"type":"Point"}
}