{
  "type": "Feature",
  "properties": {
    "iso:country":"US",
    "sg:address":"24738 130th Ave",
    "sg:city":"Eldridge",
    "sg:classifiers":[
        {
            "category":"Retail",
            "subcategory":"Repair Shop",
            "type":"Services"
        }
    ],
    "sg:phone":"+1 563 285 4123",
    "sg:postcode":"52748",
    "sg:province":"IA",
    "wof:name":"Lloyd Keppy",
    "wof:placetype":"venue"
},
  "geometry": {"coordinates":[-90.64626800000001,41.665488],"type":"Point"}
}