{
  "type": "Feature",
  "properties": {
    "addr:full":"2003 S Center St Marshalltown IA 50158",
    "addr:housenumber":"2003",
    "addr:postcode":"50158",
    "addr:street":"S Center St",
    "iso:country":"US",
    "sg:address":"2003 S Center St",
    "sg:city":"Marshalltown",
    "sg:classifiers":[
        {
            "category":"Real Estate",
            "subcategory":"Real Estate Agent",
            "type":"Services"
        }
    ],
    "sg:phone":"+1 641 752 1680",
    "sg:postcode":"50158",
    "sg:province":"IA",
    "sg:tags":[
        "agency"
    ],
    "wof:name":"ERA",
    "wof:placetype":"venue"
},
  "geometry": {"coordinates":[-92.912451,42.023198],"type":"Point"}
}