{
  "type": "Feature",
  "properties": {
    "addr:full":"319 Lake St Lake View IA 51450",
    "addr:housenumber":"319",
    "addr:postcode":"51450",
    "addr:street":"Lake St",
    "iso:country":"US",
    "sg:address":"319 Lake St",
    "sg:city":"Lake View",
    "sg:classifiers":[
        {
            "category":"Bars & Pubs",
            "type":"Food & Drink"
        }
    ],
    "sg:phone":"+1 712 657 2008",
    "sg:postcode":"51450",
    "sg:province":"IA",
    "wof:name":"Laney's Corrall",
    "wof:placetype":"venue"
},
  "geometry": {"coordinates":[-95.047467,42.30666],"type":"Point"}
}