{
  "type": "Feature",
  "properties": {
    "iso:country":"US",
    "sg:address":"301 Ashworth Rd",
    "sg:city":"West Des Moines",
    "sg:classifiers":[
        {
            "category":"Education",
            "subcategory":"Dance Studio",
            "type":"Public Place"
        }
    ],
    "sg:phone":"+1 515 223 6152",
    "sg:postcode":"50265",
    "sg:province":"IA",
    "sg:tags":[
        "instruction",
        "dancing"
    ],
    "wof:name":"Val Air Ballroom",
    "wof:placetype":"venue"
},
  "geometry": {"coordinates":[-93.705878,41.584648],"type":"Point"}
}