{
  "type": "Feature",
  "properties": {
    "iso:country":"US",
    "sg:address":"1265 E 9th St",
    "sg:city":"Des Moines",
    "sg:classifiers":[
        {
            "category":"Education",
            "subcategory":"School",
            "type":"Public Place"
        }
    ],
    "sg:phone":"+1 515 262 8025",
    "sg:postcode":"50316",
    "sg:province":"IA",
    "sg:website":"www.hfsdm.org",
    "wof:name":"Holy Family Schools",
    "wof:placetype":"venue"
},
  "geometry": {"coordinates":[-93.606481,41.60106],"type":"Point"}
}