{
  "type": "Feature",
  "properties": {
    "addr:full":"3558 Vine Ave Hartley IA 51346",
    "addr:housenumber":"3558",
    "addr:postcode":"51346",
    "addr:street":"Vine Ave",
    "iso:country":"US",
    "sg:address":"3558 Vine Ave",
    "sg:city":"Hartley",
    "sg:classifiers":[
        {
            "category":"Sports & Exercise",
            "subcategory":"Golf",
            "type":"Entertainment"
        }
    ],
    "sg:phone":"+1 712 728 2060",
    "sg:postcode":"51346",
    "sg:province":"IA",
    "sg:tags":[
        "course"
    ],
    "wof:name":"Meadowbrook Golf & Country Clb",
    "wof:placetype":"venue"
},
  "geometry": {"coordinates":[-95.486682,43.134105],"type":"Point"}
}