{
  "type": "Feature",
  "properties": {
    "iso:country":"US",
    "sg:address":"21423 Granite Ave",
    "sg:city":"Carroll",
    "sg:classifiers":[
        {
            "category":"Building & Trades",
            "subcategory":"Construction",
            "type":"Services"
        }
    ],
    "sg:phone":"+1 712 792 1104",
    "sg:postcode":"51444",
    "sg:province":"IA",
    "sg:tags":[
        "house"
    ],
    "wof:name":"Tim Rohe Const",
    "wof:placetype":"venue"
},
  "geometry": {"coordinates":[-94.97622699999999,42.008302],"type":"Point"}
}