{
  "type": "Feature",
  "properties": {
    "iso:country":"US",
    "sg:address":"1611 E 2nd St",
    "sg:city":"Webster City",
    "sg:classifiers":[
        {
            "category":"Wholesale",
            "subcategory":"Meat",
            "type":"Manufacturing & Wholesale Goods"
        }
    ],
    "sg:phone":"+1 515 832 1130",
    "sg:postcode":"50595",
    "sg:province":"IA",
    "sg:website":"www.webstercitycustommeats.com",
    "wof:name":"Webster City Custom Meats Inc",
    "wof:placetype":"venue"
},
  "geometry": {"coordinates":[-93.78505199999999,42.471136],"type":"Point"}
}