{
  "type": "Feature",
  "properties": {
    "iso:country":"US",
    "sg:address":"1504 N Lincoln St",
    "sg:city":"Knoxville",
    "sg:classifiers":[
        {
            "category":"Restaurant",
            "type":"Food & Drink"
        }
    ],
    "sg:phone":"+1 641 828 8866",
    "sg:postcode":"50138",
    "sg:province":"IA",
    "sg:tags":[
        "pizza"
    ],
    "wof:name":"Godfather's Pizza",
    "wof:placetype":"venue"
},
  "geometry": {"coordinates":[-93.10959099999999,41.331292],"type":"Point"}
}