{
  "type": "Feature",
  "properties": {
    "addr:full":"6306 Hillcrest Rd Cedar Rapids IA 52404",
    "addr:housenumber":"6306",
    "addr:postcode":"52404",
    "addr:street":"Hillcrest Rd",
    "iso:country":"US",
    "sg:address":"6306 Hillcrest Rd",
    "sg:city":"Cedar Rapids",
    "sg:classifiers":[
        {
            "category":"Building & Trades",
            "subcategory":"Construction",
            "type":"Services"
        }
    ],
    "sg:phone":"+1 319 396 4890",
    "sg:postcode":"52404",
    "sg:province":"IA",
    "sg:tags":[
        "contractor"
    ],
    "wof:name":"D W Snyder Construction",
    "wof:placetype":"venue"
},
  "geometry": {"coordinates":[-91.752402,41.930254],"type":"Point"}
}