{
  "type": "Feature",
  "properties": {
    "iso:country":"US",
    "sg:address":"610 9th Ave SW",
    "sg:city":"Independence",
    "sg:classifiers":[
        {
            "category":"Manufacturing",
            "subcategory":"Retail Goods",
            "type":"Manufacturing & Wholesale Goods"
        }
    ],
    "sg:phone":"+1 319 334 6338",
    "sg:postcode":"50644",
    "sg:province":"IA",
    "sg:tags":[
        "product",
        "mfg"
    ],
    "wof:name":"Cartoon Mans Logo Country",
    "wof:placetype":"venue"
},
  "geometry": {"coordinates":[-91.90370299999999,42.464315],"type":"Point"}
}