{
  "type": "Feature",
  "properties": {
    "iso:country":"US",
    "sg:address":"406 4th St SW",
    "sg:city":"Le Mars",
    "sg:classifiers":[
        {
            "category":"Government",
            "subcategory":"Office",
            "type":"Public Place"
        }
    ],
    "sg:phone":"+1 712 546 4192",
    "sg:postcode":"51031",
    "sg:province":"IA",
    "sg:tags":[
        "county",
        "program"
    ],
    "wof:name":"Western Hills Area Education",
    "wof:placetype":"venue"
},
  "geometry": {"coordinates":[-96.173695,42.788101],"type":"Point"}
}