{
  "type": "Feature",
  "properties": {
    "addr:full":"207 N Main St Leon IA 50144",
    "addr:housenumber":"207",
    "addr:postcode":"50144",
    "addr:street":"N Main St",
    "iso:country":"US",
    "sg:address":"207 N Main St",
    "sg:city":"Leon",
    "sg:classifiers":[
        {
            "category":"Government",
            "subcategory":"Police Station",
            "type":"Public Place"
        }
    ],
    "sg:phone":"+1 641 446 4111",
    "sg:postcode":"50144",
    "sg:province":"IA",
    "sg:tags":[
        "sheriff"
    ],
    "wof:name":"Decatur County Sheriff",
    "wof:placetype":"venue"
},
  "geometry": {"coordinates":[-93.746876,40.74035],"type":"Point"}
}