{
  "type": "Feature",
  "properties": {
    "iso:country":"US",
    "sg:address":"921 8th St",
    "sg:city":"Eddyville",
    "sg:classifiers":[
        {
            "category":"Shopping",
            "subcategory":"Hobbies, Toys, & Games",
            "type":"Retail Goods"
        }
    ],
    "sg:phone":"+1 641 969 4422",
    "sg:postcode":"52553",
    "sg:province":"IA",
    "sg:tags":[
        "craft",
        "supply"
    ],
    "wof:name":"Calico Country Crafts",
    "wof:placetype":"venue"
},
  "geometry": {"coordinates":[-92.63353499999999,41.163116],"type":"Point"}
}