{
  "type": "Feature",
  "properties": {
    "iso:country":"US",
    "sg:address":"815 15th Ave E",
    "sg:city":"Oskaloosa",
    "sg:classifiers":[
        {
            "category":"Real Estate",
            "subcategory":"Real Estate Operator",
            "type":"Services"
        }
    ],
    "sg:phone":"+1 641 673 5796",
    "sg:postcode":"52577",
    "sg:province":"IA",
    "sg:tags":[
        "apartment"
    ],
    "wof:name":"Mahaska Village",
    "wof:placetype":"venue"
},
  "geometry": {"coordinates":[-92.636521,41.281794],"type":"Point"}
}