{
  "type": "Feature",
  "properties": {
    "addr:full":"302 1st St NW Hampton IA 50441",
    "addr:housenumber":"302",
    "addr:postcode":"50441",
    "addr:street":"1St St Nw",
    "iso:country":"US",
    "sg:address":"302 1st St NW",
    "sg:city":"Hampton",
    "sg:classifiers":[
        {
            "category":"Shopping",
            "subcategory":"Gifts & Souvenirs",
            "type":"Retail Goods"
        }
    ],
    "sg:phone":"+1 641 456 2178",
    "sg:postcode":"50441",
    "sg:province":"IA",
    "wof:name":"Lighthouse Candles",
    "wof:placetype":"venue"
},
  "geometry": {"coordinates":[-93.20876699999999,42.745367],"type":"Point"}
}