{
  "type": "Feature",
  "properties": {
    "iso:country":"US",
    "sg:address":"428 Main St",
    "sg:city":"Keokuk",
    "sg:classifiers":[
        {
            "category":"Shopping",
            "subcategory":"Clothing, Apparel, & Fashions",
            "type":"Retail Goods"
        }
    ],
    "sg:phone":"+1 319 524 2505",
    "sg:postcode":"52632",
    "sg:province":"IA",
    "sg:tags":[
        "furnishing"
    ],
    "wof:name":"Johnson-Schmidt Men's Wear",
    "wof:placetype":"venue"
},
  "geometry": {"coordinates":[-91.38314,40.3955],"type":"Point"}
}