{
  "type": "Feature",
  "properties": {
    "addr:full":"1211 Vine St West Des Moines IA 50265",
    "addr:housenumber":"1211",
    "addr:postcode":"50265",
    "addr:street":"Vine St",
    "iso:country":"US",
    "sg:address":"1211 Vine St",
    "sg:city":"West Des Moines",
    "sg:classifiers":[
        {
            "category":"Organizations",
            "subcategory":"Religious Organization",
            "type":"Services"
        }
    ],
    "sg:phone":"+1 515 252 1418",
    "sg:postcode":"50265",
    "sg:province":"IA",
    "sg:tags":[
        "church"
    ],
    "wof:name":"Heartland Church-Open Bible",
    "wof:placetype":"venue"
},
  "geometry": {"coordinates":[-93.72092600000001,41.577414],"type":"Point"}
}