{
  "type": "Feature",
  "properties": {
    "addr:full":"510 Smith St Grand Mound IA 52751",
    "addr:housenumber":"510",
    "addr:postcode":"52751",
    "addr:street":"Smith St",
    "iso:country":"US",
    "sg:address":"510 Smith St",
    "sg:city":"Grand Mound",
    "sg:classifiers":[
        {
            "category":"Recreation",
            "type":"Entertainment"
        }
    ],
    "sg:phone":"+1 563 847 1300",
    "sg:postcode":"52751",
    "sg:province":"IA",
    "sg:tags":[
        "hall",
        "auditorium"
    ],
    "wof:name":"Community Center",
    "wof:placetype":"venue"
},
  "geometry": {"coordinates":[-90.647777,41.824006],"type":"Point"}
}