{
  "type": "Feature",
  "properties": {
    "iso:country":"US",
    "sg:address":"814 E River Dr",
    "sg:city":"Davenport",
    "sg:classifiers":[
        {
            "category":"Real Estate",
            "subcategory":"Surveying",
            "type":"Services"
        }
    ],
    "sg:phone":"+1 563 336 3256",
    "sg:postcode":"52803",
    "sg:province":"IA",
    "sg:tags":[
        "surveyor"
    ],
    "wof:name":"Crapnell Land Surveying Co",
    "wof:placetype":"venue"
},
  "geometry": {"coordinates":[-90.561521,41.525111],"type":"Point"}
}