{
  "type": "Feature",
  "properties": {
    "addr:full":"2196 White St Dubuque IA 52001",
    "addr:housenumber":"2196",
    "addr:postcode":"52001",
    "addr:street":"White St",
    "iso:country":"US",
    "sg:address":"2196 White St",
    "sg:city":"Dubuque",
    "sg:classifiers":[
        {
            "category":"Banks & Credit Unions",
            "subcategory":"Bank",
            "type":"Services"
        }
    ],
    "sg:phone":"+1 563 557 3268",
    "sg:postcode":"52001",
    "sg:province":"IA",
    "wof:name":"US Bank",
    "wof:placetype":"venue"
},
  "geometry": {"coordinates":[-90.669895,42.51248],"type":"Point"}
}