{
  "type": "Feature",
  "properties": {
    "iso:country":"US",
    "sg:address":"301 Church St",
    "sg:city":"Audubon",
    "sg:classifiers":[
        {
            "category":"Organizations",
            "subcategory":"Religious Organization",
            "type":"Services"
        }
    ],
    "sg:phone":"+1 712 563 3475",
    "sg:postcode":"50025",
    "sg:province":"IA",
    "sg:tags":[
        "church"
    ],
    "wof:name":"First Presbyterian Church",
    "wof:placetype":"venue"
},
  "geometry": {"coordinates":[-94.92895300000001,41.722237],"type":"Point"}
}