{
  "type": "Feature",
  "properties": {
    "iso:country":"US",
    "sg:address":"10500 NW 54th Ave",
    "sg:city":"Grimes",
    "sg:classifiers":[
        {
            "category":"Travel",
            "subcategory":"Campground",
            "type":"Entertainment"
        }
    ],
    "sg:phone":"+1 515 986 3929",
    "sg:postcode":"50111",
    "sg:province":"IA",
    "wof:name":"Cutty's Resorts",
    "wof:placetype":"venue"
},
  "geometry": {"coordinates":[-93.764139,41.658477],"type":"Point"}
}