{
  "type": "Feature",
  "properties": {
    "iso:country":"US",
    "sg:address":"608 N 2nd St",
    "sg:city":"Red Oak",
    "sg:classifiers":[
        {
            "category":"Banks & Credit Unions",
            "subcategory":"Investment Brokerage",
            "type":"Services"
        }
    ],
    "sg:phone":"+1 712 623 4807",
    "sg:postcode":"51566",
    "sg:province":"IA",
    "sg:tags":[
        "security"
    ],
    "wof:name":"BDF Investments",
    "wof:placetype":"venue"
},
  "geometry": {"coordinates":[-95.230273,41.010065],"type":"Point"}
}