{
  "type": "Feature",
  "properties": {
    "iso:country":"US",
    "sg:address":"1247 41st St",
    "sg:city":"Des Moines",
    "sg:classifiers":[
        {
            "category":"Professional",
            "type":"Services"
        }
    ],
    "sg:phone":"+1 515 255 4576",
    "sg:postcode":"50311",
    "sg:province":"IA",
    "sg:tags":[
        "establishment"
    ],
    "wof:name":"Postma Co",
    "wof:placetype":"venue"
},
  "geometry": {"coordinates":[-93.67286199999999,41.603152],"type":"Point"}
}