{
  "type": "Feature",
  "properties": {
    "iso:country":"US",
    "sg:address":"13527 Kober Rd",
    "sg:city":"La Porte City",
    "sg:classifiers":[
        {
            "category":"Retail",
            "subcategory":"Repair Shop",
            "type":"Services"
        }
    ],
    "sg:phone":"+1 319 342 2504",
    "sg:postcode":"50651",
    "sg:province":"IA",
    "wof:name":"Bronner Repair",
    "wof:placetype":"venue"
},
  "geometry": {"coordinates":[-92.22044200000001,42.325478],"type":"Point"}
}