{
  "type": "Feature",
  "properties": {
    "iso:country":"US",
    "sg:address":"337 11th St SW",
    "sg:city":"Spencer",
    "sg:classifiers":[
        {
            "category":"Building & Trades",
            "subcategory":"Construction",
            "type":"Services"
        }
    ],
    "sg:phone":"+1 712 262 1003",
    "sg:postcode":"51301",
    "sg:province":"IA",
    "sg:tags":[
        "roofing",
        "contractor"
    ],
    "wof:name":"Henningsen Const Inc",
    "wof:placetype":"venue"
},
  "geometry": {"coordinates":[-95.148537,43.126739],"type":"Point"}
}