{
  "type": "Feature",
  "properties": {
    "iso:country":"US",
    "sg:address":"974 73rd St",
    "sg:city":"Windsor Heights",
    "sg:classifiers":[
        {
            "category":"Health Services",
            "subcategory":"Doctor",
            "type":"Services"
        }
    ],
    "sg:phone":"+1 515 223 4146",
    "sg:postcode":"50312",
    "sg:province":"IA",
    "sg:tags":[
        "physician",
        "surgeon"
    ],
    "wof:name":"West Des Moines Children's",
    "wof:placetype":"venue"
},
  "geometry": {"coordinates":[-93.717991,41.595263],"type":"Point"}
}