{
  "type": "Feature",
  "properties": {
    "iso:country":"US",
    "sg:address":"2757 Michel Ave",
    "sg:city":"Rowley",
    "sg:classifiers":[
        {
            "category":"Freight",
            "type":"Transportation"
        }
    ],
    "sg:phone":"+1 319 938 0004",
    "sg:postcode":"52329",
    "sg:province":"IA",
    "sg:tags":[
        "trucking"
    ],
    "wof:name":"Rowley Transport Inc",
    "wof:placetype":"venue"
},
  "geometry": {"coordinates":[-91.830873,42.392746],"type":"Point"}
}