{
  "type": "Feature",
  "properties": {
    "iso:country":"US",
    "sg:address":"109 15th St SE",
    "sg:city":"Mason City",
    "sg:classifiers":[
        {
            "category":"Building & Trades",
            "subcategory":"Construction",
            "type":"Services"
        }
    ],
    "sg:phone":"+1 641 423 7775",
    "sg:postcode":"50401",
    "sg:province":"IA",
    "sg:tags":[
        "woodworker"
    ],
    "wof:name":"Wood By Wood",
    "wof:placetype":"venue"
},
  "geometry": {"coordinates":[-93.199696,43.137181],"type":"Point"}
}