{
  "type": "Feature",
  "properties": {
    "addr:full":"1808 Mulberry Ave Muscatine IA 52761",
    "addr:housenumber":"1808",
    "addr:postcode":"52761",
    "addr:street":"Mulberry Ave",
    "iso:country":"US",
    "sg:address":"1808 Mulberry Ave",
    "sg:city":"Muscatine",
    "sg:classifiers":[
        {
            "category":"Social Services",
            "type":"Services"
        }
    ],
    "sg:phone":"+1 563 264 8995",
    "sg:postcode":"52761",
    "sg:province":"IA",
    "sg:tags":[
        "care",
        "center",
        "day"
    ],
    "wof:name":"Senior Circle Adult Day Care",
    "wof:placetype":"venue"
},
  "geometry": {"coordinates":[-91.05599100000001,41.436999],"type":"Point"}
}