{
  "type": "Feature",
  "properties": {
    "iso:country":"US",
    "sg:address":"19126 230th St",
    "sg:city":"Hawkeye",
    "sg:phone":"+1 563 427 3483",
    "sg:postcode":"52147",
    "sg:province":"IA",
    "sg:tags":[
        "farm",
        "grain",
        "cash"
    ],
    "wof:name":"Ervin Senner",
    "wof:placetype":"venue"
},
  "geometry": {"coordinates":[-91.96463,42.964899],"type":"Point"}
}