{
  "type": "Feature",
  "properties": {
    "iso:country":"US",
    "sg:address":"111 Greene St",
    "sg:city":"Riverside",
    "sg:classifiers":[
        {
            "category":"Retail",
            "subcategory":"Funeral Services",
            "type":"Services"
        }
    ],
    "sg:phone":"+1 319 648 4111",
    "sg:postcode":"52327",
    "sg:province":"IA",
    "sg:tags":[
        "director"
    ],
    "wof:name":"Sorden-Lewis Funeral Home",
    "wof:placetype":"venue"
},
  "geometry": {"coordinates":[-91.57993500000001,41.48128],"type":"Point"}
}