{
  "type": "Feature",
  "properties": {
    "addr:full":"208 W State St Jefferson IA 50129",
    "addr:housenumber":"208",
    "addr:postcode":"50129",
    "addr:street":"W State St",
    "iso:country":"US",
    "sg:address":"208 W State St",
    "sg:city":"Jefferson",
    "sg:classifiers":[
        {
            "category":"Organizations",
            "subcategory":"Religious Organization",
            "type":"Services"
        }
    ],
    "sg:phone":"+1 515 386 2514",
    "sg:postcode":"50129",
    "sg:province":"IA",
    "sg:tags":[
        "church"
    ],
    "sg:website":"www.fpcjefferson.org",
    "wof:name":"Presbyterian Church",
    "wof:placetype":"venue"
},
  "geometry": {"coordinates":[-94.376177,42.016338],"type":"Point"}
}