{
  "type": "Feature",
  "properties": {
    "addr:full":"3601 29th Ave SW Cedar Rapids IA 52404",
    "addr:housenumber":"3601",
    "addr:postcode":"52404",
    "addr:street":"29Th Ave Sw",
    "iso:country":"US",
    "sg:address":"3601 29th Ave SW",
    "sg:city":"Cedar Rapids",
    "sg:classifiers":[
        {
            "category":"Restaurant",
            "type":"Food & Drink"
        }
    ],
    "sg:phone":"+1 319 396 5416",
    "sg:postcode":"52404",
    "sg:province":"IA",
    "wof:name":"Subway Sandwiches & Salads",
    "wof:placetype":"venue"
},
  "geometry": {"coordinates":[-91.720037,41.949147],"type":"Point"}
}