{
  "type": "Feature",
  "properties": {
    "iso:country":"US",
    "sg:address":"309 Main St",
    "sg:city":"Colo",
    "sg:classifiers":[
        {
            "category":"Social Services",
            "type":"Services"
        }
    ],
    "sg:phone":"+1 641 377 2233",
    "sg:postcode":"50056",
    "sg:province":"IA",
    "sg:tags":[
        "senior",
        "citizen"
    ],
    "wof:name":"Heartland Senior Svc",
    "wof:placetype":"venue"
},
  "geometry": {"coordinates":[-93.313393,42.01846],"type":"Point"}
}