{
  "type": "Feature",
  "properties": {
    "iso:country":"US",
    "sg:address":"502 W High St",
    "sg:city":"Avoca",
    "sg:classifiers":[
        {
            "category":"Wholesale",
            "subcategory":"Machinery & Supplies",
            "type":"Manufacturing & Wholesale Goods"
        }
    ],
    "sg:phone":"+1 712 343 6351",
    "sg:postcode":"51521",
    "sg:province":"IA",
    "sg:tags":[
        "farm",
        "equipment"
    ],
    "sg:website":"www.avocaimplement.com",
    "wof:name":"Avoca Implement Co",
    "wof:placetype":"venue"
},
  "geometry": {"coordinates":[-95.342332,41.476721],"type":"Point"}
}