{
  "type": "Feature",
  "properties": {
    "addr:full":"23 3rd St NW Mason City IA 50401",
    "addr:housenumber":"23",
    "addr:postcode":"50401",
    "addr:street":"3Rd St Nw",
    "iso:country":"US",
    "sg:address":"23 3rd St NW",
    "sg:city":"Mason City",
    "sg:classifiers":[
        {
            "category":"Social Services",
            "subcategory":"Job Training",
            "type":"Services"
        }
    ],
    "sg:phone":"+1 641 494 2540",
    "sg:postcode":"50401",
    "sg:province":"IA",
    "sg:tags":[
        "rehabilitation"
    ],
    "wof:name":"Adults Inc",
    "wof:placetype":"venue"
},
  "geometry": {"coordinates":[-93.201553,43.154449],"type":"Point"}
}