{
  "type": "Feature",
  "properties": {
    "addr:full":"1515 S 21st St Clinton IA 52732",
    "addr:housenumber":"1515",
    "addr:postcode":"52732",
    "addr:street":"S 21St St",
    "iso:country":"US",
    "sg:address":"1515 S 21st St",
    "sg:city":"Clinton",
    "sg:classifiers":[
        {
            "category":"Shopping",
            "subcategory":"Catalog Store",
            "type":"Retail Goods"
        }
    ],
    "sg:phone":"+1 563 243 0269",
    "sg:postcode":"52732",
    "sg:province":"IA",
    "sg:tags":[
        "mail",
        "order"
    ],
    "wof:name":"D M Svc Inc",
    "wof:placetype":"venue"
},
  "geometry": {"coordinates":[-90.235186,41.829579],"type":"Point"}
}