{
  "type": "Feature",
  "properties": {
    "iso:country":"US",
    "sg:address":"5163 320th St",
    "sg:city":"Danbury",
    "sg:classifiers":[
        {
            "category":"Retail",
            "subcategory":"Repair Shop",
            "type":"Services"
        }
    ],
    "sg:phone":"+1 712 365 4462",
    "sg:postcode":"51019",
    "sg:province":"IA",
    "sg:tags":[
        "farm",
        "equipment",
        "parts"
    ],
    "wof:name":"Brent Bower Shop",
    "wof:placetype":"venue"
},
  "geometry": {"coordinates":[-95.60132299999999,42.239999],"type":"Point"}
}