{
  "type": "Feature",
  "properties": {
    "iso:country":"US",
    "sg:address":"911 10th St",
    "sg:city":"Hawarden",
    "sg:classifiers":[
        {
            "category":"Autos & Motor Vehicles",
            "subcategory":"Automobile Sales",
            "type":"Retail Goods"
        }
    ],
    "sg:phone":"+1 712 551 4730",
    "sg:postcode":"51023",
    "sg:province":"SD",
    "sg:tags":[
        "car",
        "dealer"
    ],
    "wof:name":"Hawarden Motors LLC",
    "wof:placetype":"venue"
},
  "geometry": {"coordinates":[-96.482231,42.996832],"type":"Point"}
}