{
  "type": "Feature",
  "properties": {
    "addr:full":"2504 12th St Harlan IA 51537",
    "addr:housenumber":"2504",
    "addr:postcode":"51537",
    "addr:street":"12Th St",
    "iso:country":"US",
    "sg:address":"2504 12th St",
    "sg:city":"Harlan",
    "sg:classifiers":[
        {
            "category":"Restaurant",
            "type":"Food & Drink"
        },
        {
            "category":"Ice Cream",
            "type":"Food & Drink"
        }
    ],
    "sg:menulink":"http://www.allmenus.com/ia/harlan/172696-dairy-queen/menu/",
    "sg:phone":"+1 712 755 3224",
    "sg:postcode":"51537",
    "sg:province":"IA",
    "sg:tags":[
        "burger",
        "american",
        "ice",
        "cream"
    ],
    "wof:name":"Dairy Queen",
    "wof:placetype":"venue"
},
  "geometry": {"coordinates":[-95.325552,41.645832],"type":"Point"}
}