{
  "type": "Feature",
  "properties": {
    "addr:full":"1280 Hopkins Ave Union IA 50258",
    "addr:housenumber":"1280",
    "addr:postcode":"50258",
    "addr:street":"Hopkins Ave",
    "iso:country":"US",
    "sg:address":"1280 Hopkins Ave",
    "sg:city":"Union",
    "sg:phone":"+1 641 486 2282",
    "sg:postcode":"50258",
    "sg:province":"IA",
    "sg:tags":[
        "farm",
        "corn"
    ],
    "wof:name":"William Macy",
    "wof:placetype":"venue"
},
  "geometry": {"coordinates":[-93.088644,42.168943],"type":"Point"}
}