{
  "type": "Feature",
  "properties": {
    "addr:full":"1685 Independence Ave Waterloo IA 50707",
    "addr:housenumber":"1685",
    "addr:postcode":"50707",
    "addr:street":"Independence Ave",
    "iso:country":"US",
    "sg:address":"1685 Independence Ave",
    "sg:city":"Waterloo",
    "sg:classifiers":[
        {
            "category":"Home & Garden",
            "subcategory":"Garden Supply",
            "type":"Retail Goods"
        }
    ],
    "sg:phone":"+1 319 232 3954",
    "sg:postcode":"50707",
    "sg:province":"IA",
    "sg:tags":[
        "nurseryman"
    ],
    "sg:website":"www.meyersnursery.com",
    "wof:name":"Meyers Nursery",
    "wof:placetype":"venue"
},
  "geometry": {"coordinates":[-92.30632900000001,42.498466],"type":"Point"}
}