{
  "type": "Feature",
  "properties": {
    "iso:country":"US",
    "sg:address":"1040 492nd St",
    "sg:city":"Peterson",
    "sg:classifiers":[
        {
            "category":"Shopping",
            "type":"Retail Goods"
        }
    ],
    "sg:phone":"+1 712 295 6047",
    "sg:postcode":"51047",
    "sg:province":"IA",
    "sg:tags":[
        "product",
        "wood"
    ],
    "wof:name":"Donna's Woodshop",
    "wof:placetype":"venue"
},
  "geometry": {"coordinates":[-95.380787,42.937644],"type":"Point"}
}