{
  "type": "Feature",
  "properties": {
    "iso:country":"US",
    "sg:address":"101 E Main St",
    "sg:city":"Clarinda",
    "sg:classifiers":[
        {
            "category":"Professional",
            "subcategory":"Lawyer & Legal Services",
            "type":"Services"
        }
    ],
    "sg:phone":"+1 712 542 2141",
    "sg:postcode":"51632",
    "sg:province":"IA",
    "sg:tags":[
        "attorney"
    ],
    "wof:name":"Millhone & Anderson",
    "wof:placetype":"venue"
},
  "geometry": {"coordinates":[-95.03785000000001,40.738259],"type":"Point"}
}