{
  "type": "Feature",
  "properties": {
    "iso:country":"US",
    "sg:address":"1405 Mitchell Dr",
    "sg:city":"Hiawatha",
    "sg:classifiers":[
        {
            "category":"Building & Trades",
            "subcategory":"Construction",
            "type":"Services"
        }
    ],
    "sg:phone":"+1 319 393 1610",
    "sg:postcode":"52233",
    "sg:province":"IA",
    "sg:tags":[
        "millwright"
    ],
    "sg:website":"www.newellmachinery.com",
    "wof:name":"Newell Machinery Co Inc",
    "wof:placetype":"venue"
},
  "geometry": {"coordinates":[-91.692137,42.051302],"type":"Point"}
}