{
  "type": "Feature",
  "properties": {
    "iso:country":"US",
    "sg:address":"207 S 3rd St",
    "sg:city":"Burlington",
    "sg:classifiers":[
        {
            "category":"Wholesale",
            "subcategory":"Auto Parts",
            "type":"Manufacturing & Wholesale Goods"
        }
    ],
    "sg:phone":"+1 319 753 6323",
    "sg:postcode":"52601",
    "sg:province":"IA",
    "sg:tags":[
        "body",
        "automobile",
        "shop"
    ],
    "wof:name":"Automotive Finishes",
    "wof:placetype":"venue"
},
  "geometry": {"coordinates":[-91.103695,40.807055],"type":"Point"}
}