{
  "type": "Feature",
  "properties": {
    "iso:country":"US",
    "sg:address":"1037 Milstead Dr",
    "sg:city":"Hiawatha",
    "sg:classifiers":[
        {
            "category":"Real Estate",
            "subcategory":"Real Estate Agent",
            "type":"Services"
        }
    ],
    "sg:phone":"+1 319 395 7786",
    "sg:postcode":"52233",
    "sg:province":"IA",
    "sg:tags":[
        "appraiser"
    ],
    "wof:name":"Caldwell Appraisal & Conslntg",
    "wof:placetype":"venue"
},
  "geometry": {"coordinates":[-91.687467,42.04163],"type":"Point"}
}