{
  "type": "Feature",
  "properties": {
    "addr:full":"305 Broadway St Springville IA 52336",
    "addr:housenumber":"305",
    "addr:postcode":"52336",
    "addr:street":"Broadway St",
    "iso:country":"US",
    "sg:address":"305 Broadway St",
    "sg:city":"Springville",
    "sg:classifiers":[
        {
            "category":"Retail",
            "subcategory":"Auto Repair",
            "type":"Services"
        }
    ],
    "sg:phone":"+1 319 854 7112",
    "sg:postcode":"52336",
    "sg:province":"IA",
    "sg:tags":[
        "repairing",
        "automobile"
    ],
    "wof:name":"Carnahan Auto Supply & Svc",
    "wof:placetype":"venue"
},
  "geometry": {"coordinates":[-91.44353599999999,42.060077],"type":"Point"}
}