{
  "type": "Feature",
  "properties": {
    "iso:country":"US",
    "sg:address":"2279 Burt Rd",
    "sg:city":"West Point",
    "sg:classifiers":[
        {
            "category":"Building & Trades",
            "subcategory":"Construction",
            "type":"Services"
        }
    ],
    "sg:phone":"+1 319 837 6214",
    "sg:postcode":"52656",
    "sg:province":"IA",
    "sg:tags":[
        "concrete",
        "contractor"
    ],
    "wof:name":"Larry Gregory Cement Contr",
    "wof:placetype":"venue"
},
  "geometry": {"coordinates":[-91.463159,40.689519],"type":"Point"}
}