{
  "type": "Feature",
  "properties": {
    "iso:country":"US",
    "sg:address":"243 8th Ave N",
    "sg:city":"Fort Dodge",
    "sg:classifiers":[
        {
            "category":"Retail",
            "subcategory":"Repair Shop",
            "type":"Services"
        }
    ],
    "sg:phone":"+1 515 576 6511",
    "sg:postcode":"50501",
    "sg:province":"IA",
    "sg:tags":[
        "communication",
        "mfg"
    ],
    "wof:name":"Radio Center",
    "wof:placetype":"venue"
},
  "geometry": {"coordinates":[-94.197301,42.512665],"type":"Point"}
}