{
  "type": "Feature",
  "properties": {
    "iso:country":"US",
    "sg:address":"1000 4th St SW",
    "sg:city":"Mason City",
    "sg:classifiers":[
        {
            "category":"Health Services",
            "subcategory":"Doctor",
            "type":"Services"
        }
    ],
    "sg:phone":"+1 641 422 7487",
    "sg:postcode":"50401",
    "sg:province":"IA",
    "sg:tags":[
        "medical"
    ],
    "wof:name":"Mercy Center North Iowa",
    "wof:placetype":"venue"
},
  "geometry": {"coordinates":[-93.21732299999999,43.148416],"type":"Point"}
}