{
  "type": "Feature",
  "properties": {
    "addr:full":"1350 NW 138th St Clive IA 50325",
    "addr:housenumber":"1350",
    "addr:postcode":"50325",
    "addr:street":"Nw 138Th St",
    "iso:country":"US",
    "sg:address":"1350 NW 138th St",
    "sg:city":"Clive",
    "sg:classifiers":[
        {
            "category":"Professional",
            "subcategory":"Lawyer & Legal Services",
            "type":"Services"
        }
    ],
    "sg:phone":"+1 515 440 6302",
    "sg:postcode":"50325",
    "sg:province":"IA",
    "sg:tags":[
        "attorney"
    ],
    "wof:name":"Davis Brown Koehn Shors",
    "wof:placetype":"venue"
},
  "geometry": {"coordinates":[-93.805148,41.602796],"type":"Point"}
}