{
  "type": "Feature",
  "properties": {
    "iso:country":"US",
    "sg:address":"3020 Wayland Rd",
    "sg:city":"Washington",
    "sg:classifiers":[
        {
            "category":"Farming",
            "subcategory":"Farm",
            "type":"Manufacturing & Wholesale Goods"
        }
    ],
    "sg:phone":"+1 319 653 2300",
    "sg:postcode":"52353",
    "sg:province":"IA",
    "sg:tags":[
        "crop",
        "general"
    ],
    "wof:name":"Farmers Insurance",
    "wof:placetype":"venue"
},
  "geometry": {"coordinates":[-91.66999,41.220644],"type":"Point"}
}