{
  "type": "Feature",
  "properties": {
    "addr:full":"1010 S Grand Ave Charles City IA 50616",
    "addr:housenumber":"1010",
    "addr:postcode":"50616",
    "addr:street":"S Grand Ave",
    "iso:country":"US",
    "sg:address":"1010 S Grand Ave",
    "sg:city":"Charles City",
    "sg:classifiers":[
        {
            "category":"Health Services",
            "subcategory":"Doctor",
            "type":"Services"
        }
    ],
    "sg:phone":"+1 641 228 5555",
    "sg:postcode":"50616",
    "sg:province":"IA",
    "sg:tags":[
        "physician",
        "surgeon"
    ],
    "wof:name":"KIMM Family Practice",
    "wof:placetype":"venue"
},
  "geometry": {"coordinates":[-92.67249200000001,43.057851],"type":"Point"}
}