{
  "type": "Feature",
  "properties": {
    "addr:full":"319 9th Pl NW Hampton IA 50441",
    "addr:housenumber":"319",
    "addr:postcode":"50441",
    "addr:street":"9Th Pl Nw",
    "iso:country":"US",
    "sg:address":"319 9th Pl NW",
    "sg:city":"Hampton",
    "sg:classifiers":[
        {
            "category":"Real Estate",
            "subcategory":"Real Estate Operator",
            "type":"Services"
        }
    ],
    "sg:phone":"+1 641 456 4119",
    "sg:postcode":"50441",
    "sg:province":"IA",
    "sg:tags":[
        "property",
        "lessor"
    ],
    "wof:name":"Galen Viet",
    "wof:placetype":"venue"
},
  "geometry": {"coordinates":[-93.21106899999999,42.750567],"type":"Point"}
}