{
  "type": "Feature",
  "properties": {
    "iso:country":"US",
    "sg:address":"3108 W Central Park Ave",
    "sg:city":"Davenport",
    "sg:classifiers":[
        {
            "category":"Food & Beverages",
            "subcategory":"Groceries & Convenience Stores",
            "type":"Retail Goods"
        }
    ],
    "sg:phone":"+1 563 386 8491",
    "sg:postcode":"52804",
    "sg:province":"IA",
    "wof:name":"Sood & Inc",
    "wof:placetype":"venue"
},
  "geometry": {"coordinates":[-90.61826499999999,41.545442],"type":"Point"}
}