{
  "type": "Feature",
  "properties": {
    "addr:full":"1775 260th St Tipton IA 52772",
    "addr:housenumber":"1775",
    "addr:postcode":"52772",
    "addr:street":"260Th St",
    "iso:country":"US",
    "sg:address":"1775 260th St",
    "sg:city":"Tipton",
    "sg:classifiers":[
        {
            "category":"Real Estate",
            "subcategory":"Real Estate Operator",
            "type":"Services"
        }
    ],
    "sg:phone":"+1 563 893 2588",
    "sg:postcode":"52772",
    "sg:province":"IA",
    "sg:tags":[
        "property",
        "lessor"
    ],
    "wof:name":"Leonard Schwitzer Farm",
    "wof:placetype":"venue"
},
  "geometry": {"coordinates":[-91.01691599999999,41.713653],"type":"Point"}
}