{
  "type": "Feature",
  "properties": {
    "iso:country":"US",
    "sg:address":"3430 Dodge St",
    "sg:city":"Dubuque",
    "sg:classifiers":[
        {
            "category":"Health Services",
            "subcategory":"Doctor",
            "type":"Services"
        }
    ],
    "sg:phone":"+1 563 556 8388",
    "sg:postcode":"52003",
    "sg:province":"IA",
    "sg:tags":[
        "dentist"
    ],
    "wof:name":"Abbadent Ctr-Cosmetic Dntstry",
    "wof:placetype":"venue"
},
  "geometry": {"coordinates":[-90.720741,42.491907],"type":"Point"}
}