{
  "type": "Feature",
  "properties": {
    "addr:full":"3098 220th St Lockridge IA 52635",
    "addr:housenumber":"3098",
    "addr:postcode":"52635",
    "addr:street":"220Th St",
    "iso:country":"US",
    "sg:address":"3098 220th St",
    "sg:city":"Lockridge",
    "sg:classifiers":[
        {
            "category":"Wholesale",
            "subcategory":"Machinery & Supplies",
            "type":"Manufacturing & Wholesale Goods"
        }
    ],
    "sg:phone":"+1 319 696 2821",
    "sg:postcode":"52635",
    "sg:province":"IA",
    "sg:tags":[
        "farm",
        "equipment"
    ],
    "wof:name":"Graber Services LTD",
    "wof:placetype":"venue"
},
  "geometry": {"coordinates":[-91.776659,40.98771],"type":"Point"}
}