{
  "type": "Feature",
  "properties": {
    "addr:full":"828 E Washington St Iowa City IA 52240",
    "addr:housenumber":"828",
    "addr:postcode":"52240",
    "addr:street":"E Washington St",
    "iso:country":"US",
    "sg:address":"828 E Washington St",
    "sg:city":"Iowa City",
    "sg:classifiers":[
        {
            "category":"Organizations",
            "subcategory":"Community Association",
            "type":"Services"
        }
    ],
    "sg:phone":"+1 319 338 9261",
    "sg:postcode":"52240",
    "sg:province":"IA",
    "sg:tags":[
        "sorority"
    ],
    "sg:website":"www.uiowa.edu",
    "wof:name":"Alpha Chi Omega Sorority",
    "wof:placetype":"venue"
},
  "geometry": {"coordinates":[-91.523191,41.66012],"type":"Point"}
}