{
  "type": "Feature",
  "properties": {
    "iso:country":"US",
    "sg:address":"317 7th Ave NE",
    "sg:city":"Clarion",
    "sg:classifiers":[
        {
            "category":"Personal",
            "subcategory":"Beauty Salon",
            "type":"Services"
        }
    ],
    "sg:phone":"+1 515 532 2454",
    "sg:postcode":"50525",
    "sg:province":"IA",
    "sg:tags":[
        "shop"
    ],
    "wof:name":"Beauty Corral Inc",
    "wof:placetype":"venue"
},
  "geometry": {"coordinates":[-93.728538,42.738306],"type":"Point"}
}