{
  "type": "Feature",
  "properties": {
    "iso:country":"US",
    "sg:address":"545 Locust St",
    "sg:city":"Wapello",
    "sg:classifiers":[
        {
            "category":"Real Estate",
            "subcategory":"Real Estate Agent",
            "type":"Services"
        }
    ],
    "sg:phone":"+1 319 523 3001",
    "sg:postcode":"52653",
    "sg:province":"IA",
    "sg:website":"www.smallauctionandrealestate.com",
    "wof:name":"Small Auction & Real Estate",
    "wof:placetype":"venue"
},
  "geometry": {"coordinates":[-91.19063199999999,41.171148],"type":"Point"}
}