{
  "type": "Feature",
  "properties": {
    "iso:country":"US",
    "sg:address":"3275 120th St",
    "sg:city":"Brighton",
    "sg:phone":"+1 319 694 4016",
    "sg:postcode":"52540",
    "sg:province":"IA",
    "sg:tags":[
        "farm",
        "corn",
        "soybean"
    ],
    "wof:name":"Curtis Pacha",
    "wof:placetype":"venue"
},
  "geometry": {"coordinates":[-91.75510199999999,41.133215],"type":"Point"}
}