{
  "type": "Feature",
  "properties": {
    "addr:full":"18 Plymouth St SE Le Mars IA 51031",
    "addr:housenumber":"18",
    "addr:postcode":"51031",
    "addr:street":"Plymouth St Se",
    "iso:country":"US",
    "sg:address":"18 Plymouth St SE",
    "sg:city":"Le Mars",
    "sg:classifiers":[
        {
            "category":"Retail",
            "subcategory":"Laundry & Dry Cleaning",
            "type":"Services"
        }
    ],
    "sg:phone":"+1 712 546 6600",
    "sg:postcode":"51031",
    "sg:province":"IA",
    "sg:tags":[
        "cleaners"
    ],
    "wof:name":"Ideal Cleaners",
    "wof:placetype":"venue"
},
  "geometry": {"coordinates":[-96.166301,42.792989],"type":"Point"}
}