{
  "type": "Feature",
  "properties": {
    "iso:country":"US",
    "sg:address":"1706 N John Wayne Dr",
    "sg:city":"Winterset",
    "sg:classifiers":[
        {
            "category":"Wholesale",
            "subcategory":"Machinery & Supplies",
            "type":"Manufacturing & Wholesale Goods"
        }
    ],
    "sg:phone":"+1 515 462 3115",
    "sg:postcode":"50273",
    "sg:province":"IA",
    "sg:tags":[
        "farm",
        "equipment"
    ],
    "sg:website":"www.ebarkers.com",
    "wof:name":"Barke Implement & Motor Co",
    "wof:placetype":"venue"
},
  "geometry": {"coordinates":[-94.01355,41.350133],"type":"Point"}
}