{
  "type": "Feature",
  "properties": {
    "addr:full":"323 Dieckman St Titonka IA 50480",
    "addr:housenumber":"323",
    "addr:postcode":"50480",
    "addr:street":"Dieckman St",
    "iso:country":"US",
    "sg:address":"323 Dieckman St",
    "sg:city":"Titonka",
    "sg:classifiers":[
        {
            "category":"Organizations",
            "subcategory":"Religious Organization",
            "type":"Services"
        }
    ],
    "sg:phone":"+1 515 928 2282",
    "sg:postcode":"50480",
    "sg:province":"IA",
    "sg:tags":[
        "church"
    ],
    "wof:name":"Good Hope Lutheran Church",
    "wof:placetype":"venue"
},
  "geometry": {"coordinates":[-94.040142,43.238525],"type":"Point"}
}