{
  "type": "Feature",
  "properties": {
    "addr:full":"64 Broadway St Arnolds Park IA 51331",
    "addr:housenumber":"64",
    "addr:postcode":"51331",
    "addr:street":"Broadway St",
    "iso:country":"US",
    "sg:address":"64 Broadway St",
    "sg:city":"Arnolds Park",
    "sg:classifiers":[
        {
            "category":"Personal",
            "subcategory":"Beauty Salon",
            "type":"Services"
        }
    ],
    "sg:phone":"+1 712 332 7270",
    "sg:postcode":"51331",
    "sg:province":"IA",
    "wof:name":"Salon One Inc",
    "wof:placetype":"venue"
},
  "geometry": {"coordinates":[-95.12948,43.367874],"type":"Point"}
}