{
  "type": "Feature",
  "properties": {
    "iso:country":"US",
    "sg:address":"850 Pierce St",
    "sg:city":"Indianola",
    "sg:classifiers":[
        {
            "category":"Retail",
            "subcategory":"Repair Shop",
            "type":"Services"
        }
    ],
    "sg:phone":"+1 515 961 7274",
    "sg:postcode":"50125",
    "sg:province":"IA",
    "wof:name":"Horseshoe Morgan & Supply",
    "wof:placetype":"venue"
},
  "geometry": {"coordinates":[-93.648009,41.27062],"type":"Point"}
}