{
  "type": "Feature",
  "properties": {
    "iso:country":"US",
    "sg:address":"3684 Crescent Rdg",
    "sg:city":"Dubuque",
    "sg:classifiers":[
        {
            "category":"Professional",
            "subcategory":"Engineering",
            "type":"Services"
        },
        {
            "category":"Wholesale",
            "subcategory":"Computers",
            "type":"Manufacturing & Wholesale Goods"
        },
        {
            "category":"Professional",
            "subcategory":"Computer Services",
            "type":"Services"
        }
    ],
    "sg:phone":"+1 563 590 2984",
    "sg:postcode":"52003",
    "sg:province":"IA",
    "sg:tags":[
        "repair",
        "designer",
        "consultant",
        "integration",
        "system",
        "equipment",
        "equipment-service",
        "engineer"
    ],
    "sg:website":"http://www.pctechneer.com",
    "wof:name":"A+ PC Techneer",
    "wof:placetype":"venue"
},
  "geometry": {"coordinates":[-90.731903,42.489891],"type":"Point"}
}