{
  "type": "Feature",
  "properties": {
    "addr:full":"514 S River Park Dr Guttenberg IA 52052",
    "addr:housenumber":"514",
    "addr:postcode":"52052",
    "addr:street":"S River Park Dr",
    "iso:country":"US",
    "sg:address":"514 S River Park Dr",
    "sg:city":"Guttenberg",
    "sg:classifiers":[
        {
            "category":"Shopping",
            "subcategory":"Gifts & Souvenirs",
            "type":"Retail Goods"
        }
    ],
    "sg:phone":"+1 563 252 3450",
    "sg:postcode":"52052",
    "sg:province":"IA",
    "sg:tags":[
        "shop"
    ],
    "wof:name":"Town House Accents",
    "wof:placetype":"venue"
},
  "geometry": {"coordinates":[-91.09525499999999,42.781497],"type":"Point"}
}