{
  "type": "Feature",
  "properties": {
    "iso:country":"US",
    "sg:address":"2129 Hamilton Blvd",
    "sg:city":"Sioux City",
    "sg:classifiers":[
        {
            "category":"Restaurant",
            "type":"Food & Drink"
        },
        {
            "category":"Ice Cream",
            "type":"Food & Drink"
        }
    ],
    "sg:menulink":"http://www.allmenus.com/ia/sioux-city/209049-tcby/menu/",
    "sg:phone":"+1 712 252 2730",
    "sg:postcode":"51104",
    "sg:province":"IA",
    "sg:tags":[
        "smoothy",
        "juice",
        "american",
        "ice",
        "cream"
    ],
    "wof:name":"TCBY",
    "wof:placetype":"venue"
},
  "geometry": {"coordinates":[-96.416864,42.512661],"type":"Point"}
}