{
  "type": "Feature",
  "properties": {
    "addr:full":"105 Ave A W Lake Park IA 51347",
    "addr:housenumber":"105",
    "addr:postcode":"51347",
    "addr:street":"Ave A W",
    "iso:country":"US",
    "sg:address":"105 Ave A W",
    "sg:city":"Lake Park",
    "sg:classifiers":[
        {
            "category":"Education",
            "subcategory":"School",
            "type":"Public Place"
        }
    ],
    "sg:phone":"+1 712 832 3640",
    "sg:postcode":"51347",
    "sg:province":"IA",
    "wof:name":"Lake Park Schl Superintendent",
    "wof:placetype":"venue"
},
  "geometry": {"coordinates":[-95.32316,43.455351],"type":"Point"}
}