{
  "type": "Feature",
  "properties": {
    "iso:country":"US",
    "sg:address":"2705 N Court St",
    "sg:city":"Ottumwa",
    "sg:classifiers":[
        {
            "category":"Organizations",
            "subcategory":"Religious Organization",
            "type":"Services"
        }
    ],
    "sg:phone":"+1 641 684 8811",
    "sg:postcode":"52501",
    "sg:province":"IA",
    "sg:tags":[
        "church"
    ],
    "wof:name":"Northgate Alliance Church",
    "wof:placetype":"venue"
},
  "geometry": {"coordinates":[-92.408041,41.049779],"type":"Point"}
}