{
  "type": "Feature",
  "properties": {
    "iso:country":"US",
    "sg:address":"402 E 4th St",
    "sg:city":"Waterloo",
    "sg:classifiers":[
        {
            "category":"Railroad",
            "type":"Transportation"
        }
    ],
    "sg:phone":"+1 319 236 9200",
    "sg:postcode":"50703",
    "sg:province":"IA",
    "wof:name":"Chicago Central & Pacific Rr",
    "wof:placetype":"venue"
},
  "geometry": {"coordinates":[-92.333054,42.500534],"type":"Point"}
}