{
  "type": "Feature",
  "properties": {
    "iso:country":"US",
    "sg:address":"705 Douglas St",
    "sg:city":"Sioux City",
    "sg:classifiers":[
        {
            "category":"Professional",
            "subcategory":"Management & Consulting",
            "type":"Services"
        }
    ],
    "sg:phone":"+1 712 224 3302",
    "sg:postcode":"51101",
    "sg:province":"IA",
    "sg:tags":[
        "business"
    ],
    "wof:name":"Employers Advantage Inc",
    "wof:placetype":"venue"
},
  "geometry": {"coordinates":[-96.40655,42.498453],"type":"Point"}
}