{
  "type": "Feature",
  "properties": {
    "addr:full":"3720 SW 32nd St Des Moines IA 50321",
    "addr:housenumber":"3720",
    "addr:postcode":"50321",
    "addr:street":"Sw 32Nd St",
    "iso:country":"US",
    "sg:address":"3720 SW 32nd St",
    "sg:city":"Des Moines",
    "sg:classifiers":[
        {
            "category":"Building & Trades",
            "subcategory":"Construction",
            "type":"Services"
        }
    ],
    "sg:phone":"+1 515 250 2305",
    "sg:postcode":"50321",
    "sg:province":"IA",
    "sg:tags":[
        "concrete",
        "contractor"
    ],
    "wof:name":"Cal Concrete Construction",
    "wof:placetype":"venue"
},
  "geometry": {"coordinates":[-93.660743,41.549039],"type":"Point"}
}