{
  "type": "Feature",
  "properties": {
    "addr:full":"1030 N Hancock St Lake City IA 51449",
    "addr:housenumber":"1030",
    "addr:postcode":"51449",
    "addr:street":"N Hancock St",
    "iso:country":"US",
    "sg:address":"1030 N Hancock St",
    "sg:city":"Lake City",
    "sg:classifiers":[
        {
            "category":"Building & Trades",
            "subcategory":"Construction",
            "type":"Services"
        }
    ],
    "sg:phone":"+1 712 464 7626",
    "sg:postcode":"51449",
    "sg:province":"IA",
    "sg:tags":[
        "excavating",
        "contractor"
    ],
    "wof:name":"Ben Hart Drainage",
    "wof:placetype":"venue"
},
  "geometry": {"coordinates":[-94.72633999999999,42.276965],"type":"Point"}
}