{
  "type": "Feature",
  "properties": {
    "iso:country":"US",
    "sg:address":"2751 Dove Ave",
    "sg:city":"Elk Horn",
    "sg:classifiers":[
        {
            "category":"Professional",
            "subcategory":"Advertising",
            "type":"Services"
        }
    ],
    "sg:phone":"+1 712 764 5123",
    "sg:postcode":"51531",
    "sg:province":"IA",
    "sg:tags":[
        "distribution"
    ],
    "wof:name":"Nikken Independent Distr",
    "wof:placetype":"venue"
},
  "geometry": {"coordinates":[-95.03398199999999,41.609086],"type":"Point"}
}