{
  "type": "Feature",
  "properties": {
    "iso:country":"US",
    "sg:address":"3288 Halter Ave",
    "sg:city":"Newton",
    "sg:classifiers":[
        {
            "category":"Retail",
            "subcategory":"Animal Services",
            "type":"Services"
        }
    ],
    "sg:phone":"+1 641 792 5355",
    "sg:postcode":"50208",
    "sg:province":"IA",
    "wof:name":"Skiles Sales Inc",
    "wof:placetype":"venue"
},
  "geometry": {"coordinates":[-93.01258900000001,41.700009],"type":"Point"}
}