{
  "type": "Feature",
  "properties": {
    "iso:country":"US",
    "sg:address":"201 N 12th St",
    "sg:city":"Centerville",
    "sg:classifiers":[
        {
            "category":"Government",
            "subcategory":"Court House",
            "type":"Public Place"
        }
    ],
    "sg:phone":"+1 641 856 6101",
    "sg:postcode":"52544",
    "sg:province":"IA",
    "sg:tags":[
        "county"
    ],
    "wof:name":"District Court Clerk",
    "wof:placetype":"venue"
},
  "geometry": {"coordinates":[-92.875035,40.734232],"type":"Point"}
}