{
  "type": "Feature",
  "properties": {
    "addr:full":"1727 Des Moines St Keokuk IA 52632",
    "addr:housenumber":"1727",
    "addr:postcode":"52632",
    "addr:street":"Des Moines St",
    "iso:country":"US",
    "sg:address":"1727 Des Moines St",
    "sg:city":"Keokuk",
    "sg:classifiers":[
        {
            "category":"Building & Trades",
            "subcategory":"Landscaping Services",
            "type":"Services"
        }
    ],
    "sg:phone":"+1 319 524 0157",
    "sg:postcode":"52632",
    "sg:province":"IA",
    "wof:name":"King Arthurs Landscape & Tree",
    "wof:placetype":"venue"
},
  "geometry": {"coordinates":[-91.398915,40.40268],"type":"Point"}
}