{
  "type": "Feature",
  "properties": {
    "iso:country":"US",
    "sg:address":"2929 Sweet Briar Ave",
    "sg:city":"Iowa City",
    "sg:classifiers":[
        {
            "category":"Farming",
            "subcategory":"Farm & Veterinary Services",
            "type":"Manufacturing & Wholesale Goods"
        }
    ],
    "sg:phone":"+1 319 351 1066",
    "sg:postcode":"52245",
    "sg:province":"IA",
    "sg:tags":[
        "management"
    ],
    "wof:name":"Farmers National Co",
    "wof:placetype":"venue"
},
  "geometry": {"coordinates":[-91.48863299999999,41.660076],"type":"Point"}
}