{
  "type": "Feature",
  "properties": {
    "iso:country":"US",
    "sg:address":"4316 Grand Ave",
    "sg:city":"Des Moines",
    "sg:classifiers":[
        {
            "category":"Organizations",
            "subcategory":"Professional Association",
            "type":"Services"
        }
    ],
    "sg:phone":"+1 515 274 9310",
    "sg:postcode":"50312",
    "sg:province":"IA",
    "wof:name":"Fortythree Sixteen Grand Ave",
    "wof:placetype":"venue"
},
  "geometry": {"coordinates":[-93.67721,41.584456],"type":"Point"}
}