{
  "type": "Feature",
  "properties": {
    "iso:country":"US",
    "sg:address":"1210 3rd Ave N",
    "sg:city":"Humboldt",
    "sg:classifiers":[
        {
            "category":"Shopping",
            "subcategory":"Computers & Home Electronics",
            "type":"Retail Goods"
        }
    ],
    "sg:phone":"+1 515 332 5050",
    "sg:postcode":"50548",
    "sg:province":"IA",
    "sg:tags":[
        "equipment",
        "dealer"
    ],
    "wof:name":"Quality Computer Technicians",
    "wof:placetype":"venue"
},
  "geometry": {"coordinates":[-94.225601,42.72419],"type":"Point"}
}