{
  "type": "Feature",
  "properties": {
    "iso:country":"US",
    "sg:address":"2750 University Ave",
    "sg:city":"Waterloo",
    "sg:classifiers":[
        {
            "category":"Professional",
            "subcategory":"Accounting & Tax Preparation",
            "type":"Services"
        }
    ],
    "sg:phone":"+1 319 233 1989",
    "sg:postcode":"50701",
    "sg:province":"IA",
    "sg:tags":[
        "return",
        "filing"
    ],
    "wof:name":"H & R Block Tax Svc",
    "wof:placetype":"venue"
},
  "geometry": {"coordinates":[-92.376904,42.496114],"type":"Point"}
}