{
  "type": "Feature",
  "properties": {
    "addr:full":"123 N Center St Lake City IA 51449",
    "addr:housenumber":"123",
    "addr:postcode":"51449",
    "addr:street":"N Center St",
    "iso:country":"US",
    "sg:address":"123 N Center St",
    "sg:city":"Lake City",
    "sg:classifiers":[
        {
            "category":"Restaurant",
            "type":"Food & Drink"
        }
    ],
    "sg:phone":"+1 712 464 7908",
    "sg:postcode":"51449",
    "sg:province":"IA",
    "wof:name":"Excuses",
    "wof:placetype":"venue"
},
  "geometry": {"coordinates":[-94.73388799999999,42.268083],"type":"Point"}
}