{
  "type": "Feature",
  "properties": {
    "addr:full":"3028 E Court St Iowa City IA 52245",
    "addr:housenumber":"3028",
    "addr:postcode":"52245",
    "addr:street":"E Court St",
    "iso:country":"US",
    "sg:address":"3028 E Court St",
    "sg:city":"Iowa City",
    "sg:classifiers":[
        {
            "category":"Home & Garden",
            "subcategory":"Building Materials",
            "type":"Retail Goods"
        }
    ],
    "sg:phone":"+1 319 338 6686",
    "sg:postcode":"52245",
    "sg:province":"IA",
    "wof:name":"Stained Glass By Jim Voss",
    "wof:placetype":"venue"
},
  "geometry": {"coordinates":[-91.49026000000001,41.656978],"type":"Point"}
}