{
  "type": "Feature",
  "properties": {
    "iso:country":"US",
    "sg:address":"306 Walnut St",
    "sg:city":"Atlantic",
    "sg:classifiers":[
        {
            "category":"Insurance",
            "subcategory":"Insurance Agent",
            "type":"Services"
        }
    ],
    "sg:phone":"+1 712 243 5451",
    "sg:postcode":"50022",
    "sg:province":"IA",
    "wof:name":"Total Concept Marketing",
    "wof:placetype":"venue"
},
  "geometry": {"coordinates":[-95.011492,41.407915],"type":"Point"}
}