{
  "type": "Feature",
  "properties": {
    "addr:full":"2446 W 62 St Davenport IA 52806",
    "addr:housenumber":"2446",
    "addr:postcode":"52806",
    "addr:street":"W 62 St",
    "iso:country":"US",
    "sg:address":"2446 W 62 St",
    "sg:city":"Davenport",
    "sg:classifiers":[
        {
            "category":"Building & Trades",
            "subcategory":"Landscaping Services",
            "type":"Services"
        }
    ],
    "sg:phone":"+1 563 391 1807",
    "sg:postcode":"52806",
    "sg:province":"IA",
    "sg:tags":[
        "landscape",
        "contractor"
    ],
    "wof:name":"KWIK Kerb Of The Quad Cities",
    "wof:placetype":"venue"
},
  "geometry": {"coordinates":[-90.61409999999999,41.584489],"type":"Point"}
}