{
  "type": "Feature",
  "properties": {
    "addr:full":"808 E 3rd St Pella IA 50219",
    "addr:housenumber":"808",
    "addr:postcode":"50219",
    "addr:street":"E 3Rd St",
    "iso:country":"US",
    "sg:address":"808 E 3rd St",
    "sg:city":"Pella",
    "sg:classifiers":[
        {
            "category":"Organizations",
            "subcategory":"Religious Organization",
            "type":"Services"
        }
    ],
    "sg:phone":"+1 641 628 9467",
    "sg:postcode":"50219",
    "sg:province":"IA",
    "wof:name":"Lower Grove Community Church",
    "wof:placetype":"venue"
},
  "geometry": {"coordinates":[-92.91119399999999,41.407948],"type":"Point"}
}