{
  "type": "Feature",
  "properties": {
    "iso:country":"US",
    "sg:address":"311 West St",
    "sg:city":"Dysart",
    "sg:classifiers":[
        {
            "category":"Building & Trades",
            "subcategory":"Landscaping Services",
            "type":"Services"
        }
    ],
    "sg:phone":"+1 319 476 3088",
    "sg:postcode":"52224",
    "sg:province":"IA",
    "sg:tags":[
        "lawn",
        "maintenance",
        "grounds"
    ],
    "wof:name":"Tri-County Lawn Svc",
    "wof:placetype":"venue"
},
  "geometry": {"coordinates":[-92.31427600000001,42.171855],"type":"Point"}
}