{
  "type": "Feature",
  "properties": {
    "iso:country":"US",
    "sg:address":"1378 60th Ave",
    "sg:city":"Blue Grass",
    "sg:classifiers":[
        {
            "category":"Wholesale",
            "subcategory":"Construction Materials",
            "type":"Manufacturing & Wholesale Goods"
        }
    ],
    "sg:phone":"+1 563 381 5277",
    "sg:postcode":"52726",
    "sg:province":"IA",
    "sg:tags":[
        "terrazzo"
    ],
    "wof:name":"Martin Flooring",
    "wof:placetype":"venue"
},
  "geometry": {"coordinates":[-90.784678,41.539989],"type":"Point"}
}