{
  "type": "Feature",
  "properties": {
    "addr:full":"605 N Main St Davenport IA 52803",
    "addr:housenumber":"605",
    "addr:postcode":"52803",
    "addr:street":"N Main St",
    "iso:country":"US",
    "sg:address":"605 N Main St",
    "sg:city":"Davenport",
    "sg:classifiers":[
        {
            "category":"Social Services",
            "type":"Services"
        }
    ],
    "sg:phone":"+1 563 324 1654",
    "sg:postcode":"52803",
    "sg:province":"IA",
    "sg:tags":[
        "probation"
    ],
    "wof:name":"Iowa State-Parole & Probation",
    "wof:placetype":"venue"
},
  "geometry": {"coordinates":[-90.575489,41.526776],"type":"Point"}
}