{
  "type": "Feature",
  "properties": {
    "addr:full":"208 Bank St Keokuk IA 52632",
    "addr:housenumber":"208",
    "addr:postcode":"52632",
    "addr:street":"Bank St",
    "iso:country":"US",
    "sg:address":"208 Bank St",
    "sg:city":"Keokuk",
    "sg:classifiers":[
        {
            "category":"Social Services",
            "type":"Services"
        }
    ],
    "sg:phone":"+1 319 524 3873",
    "sg:postcode":"52632",
    "sg:province":"IA",
    "sg:tags":[
        "organization",
        "welfare"
    ],
    "wof:name":"Bridgeway Inc",
    "wof:placetype":"venue"
},
  "geometry": {"coordinates":[-91.384798,40.392168],"type":"Point"}
}