{
  "type": "Feature",
  "properties": {
    "addr:full":"10201 University Ave Clive IA 50325",
    "addr:housenumber":"10201",
    "addr:postcode":"50325",
    "addr:street":"University Ave",
    "iso:country":"US",
    "sg:address":"10201 University Ave",
    "sg:city":"Clive",
    "sg:classifiers":[
        {
            "category":"Shopping",
            "subcategory":"Used Merchandise",
            "type":"Retail Goods"
        }
    ],
    "sg:phone":"+1 515 222 0774",
    "sg:postcode":"50325",
    "sg:province":"IA",
    "sg:tags":[
        "infant",
        "wear"
    ],
    "wof:name":"Once Upon A Child",
    "wof:placetype":"venue"
},
  "geometry": {"coordinates":[-93.758954,41.600505],"type":"Point"}
}