{
  "type": "Feature",
  "properties": {
    "addr:full":"203 1st St W Mt Vernon IA 52314",
    "addr:housenumber":"203",
    "addr:postcode":"52314",
    "addr:street":"1St St W",
    "iso:country":"US",
    "sg:address":"203 1st St W",
    "sg:city":"Mt Vernon",
    "sg:classifiers":[
        {
            "category":"Real Estate",
            "subcategory":"Real Estate Agent",
            "type":"Services"
        }
    ],
    "sg:phone":"+1 319 895 8634",
    "sg:postcode":"52314",
    "sg:province":"IA",
    "wof:name":"Walden Real Estate",
    "wof:placetype":"venue"
},
  "geometry": {"coordinates":[-91.418998,41.923418],"type":"Point"}
}