{
  "type": "Feature",
  "properties": {
    "addr:full":"407 Oak St Moorhead IA 51558",
    "addr:housenumber":"407",
    "addr:postcode":"51558",
    "addr:street":"Oak St",
    "iso:country":"US",
    "sg:address":"407 Oak St",
    "sg:city":"Moorhead",
    "sg:classifiers":[
        {
            "category":"Organizations",
            "subcategory":"Religious Organization",
            "type":"Services"
        }
    ],
    "sg:phone":"+1 712 886 5532",
    "sg:postcode":"51558",
    "sg:province":"IA",
    "wof:name":"Christian Church",
    "wof:placetype":"venue"
},
  "geometry": {"coordinates":[-95.851342,41.924981],"type":"Point"}
}