{
  "type": "Feature",
  "properties": {
    "addr:full":"365 Western Ave Marengo IA 52301",
    "addr:housenumber":"365",
    "addr:postcode":"52301",
    "addr:street":"Western Ave",
    "iso:country":"US",
    "sg:address":"365 Western Ave",
    "sg:city":"Marengo",
    "sg:classifiers":[
        {
            "category":"Home & Garden",
            "subcategory":"Hardware",
            "type":"Retail Goods"
        }
    ],
    "sg:phone":"+1 319 642 5584",
    "sg:postcode":"52301",
    "sg:province":"IA",
    "wof:name":"Marengo Farm & Home",
    "wof:placetype":"venue"
},
  "geometry": {"coordinates":[-92.07425499999999,41.795256],"type":"Point"}
}