{
  "type": "Feature",
  "properties": {
    "iso:country":"US",
    "sg:address":"100 Polk St",
    "sg:city":"Burlington",
    "sg:classifiers":[
        {
            "category":"Professional",
            "type":"Services"
        }
    ],
    "sg:phone":"+1 319 752 2533",
    "sg:postcode":"52601",
    "sg:province":"IA",
    "wof:name":"Annvitas Inc",
    "wof:placetype":"venue"
},
  "geometry": {"coordinates":[-91.096879,40.796409],"type":"Point"}
}