{
  "type": "Feature",
  "properties": {
    "iso:country":"US",
    "sg:address":"609 S 9th St",
    "sg:city":"Clear Lake",
    "sg:classifiers":[
        {
            "category":"Building & Trades",
            "subcategory":"Construction",
            "type":"Services"
        }
    ],
    "sg:phone":"+1 641 357 7726",
    "sg:postcode":"50428",
    "sg:province":"IA",
    "sg:tags":[
        "contractor"
    ],
    "wof:name":"Dr Drywall",
    "wof:placetype":"venue"
},
  "geometry": {"coordinates":[-93.377011,43.13162],"type":"Point"}
}