{
  "type": "Feature",
  "properties": {
    "addr:full":"1620 Pattee St Perry IA 50220",
    "addr:housenumber":"1620",
    "addr:postcode":"50220",
    "addr:street":"Pattee St",
    "iso:country":"US",
    "sg:address":"1620 Pattee St",
    "sg:city":"Perry",
    "sg:classifiers":[
        {
            "category":"Shopping",
            "subcategory":"Florist",
            "type":"Retail Goods"
        }
    ],
    "sg:phone":"+1 515 465 3539",
    "sg:postcode":"50220",
    "sg:province":"IA",
    "wof:name":"Hartman Floral & Greenhouses",
    "wof:placetype":"venue"
},
  "geometry": {"coordinates":[-94.099514,41.841633],"type":"Point"}
}