{
  "type": "Feature",
  "properties": {
    "iso:country":"US",
    "sg:address":"402 Villa Ave",
    "sg:city":"Alexander",
    "sg:classifiers":[
        {
            "category":"Shopping",
            "subcategory":"Gifts & Souvenirs",
            "type":"Retail Goods"
        }
    ],
    "sg:phone":"+1 641 692 3586",
    "sg:postcode":"50420",
    "sg:province":"IA",
    "sg:tags":[
        "shop"
    ],
    "wof:name":"Country Creations & Ceramics",
    "wof:placetype":"venue"
},
  "geometry": {"coordinates":[-93.467517,42.803736],"type":"Point"}
}