{
  "type": "Feature",
  "properties": {
    "iso:country":"US",
    "sg:address":"212 Mitchell Ave SW",
    "sg:city":"Mitchellville",
    "sg:classifiers":[
        {
            "category":"Professional",
            "subcategory":"Business Services",
            "type":"Services"
        }
    ],
    "sg:phone":"+1 515 967 7114",
    "sg:postcode":"50169",
    "sg:province":"IA",
    "wof:name":"Gw Enterprises LLC",
    "wof:placetype":"venue"
},
  "geometry": {"coordinates":[-93.35939999999999,41.665808],"type":"Point"}
}