{
  "type": "Feature",
  "properties": {
    "iso:country":"US",
    "sg:address":"1465 Walnut Ave",
    "sg:city":"Brighton",
    "sg:classifiers":[
        {
            "category":"Organizations",
            "subcategory":"Religious Organization",
            "type":"Services"
        }
    ],
    "sg:phone":"+1 319 694 3771",
    "sg:postcode":"52540",
    "sg:province":"IA",
    "wof:name":"Hope Lutheran Church",
    "wof:placetype":"venue"
},
  "geometry": {"coordinates":[-91.75546,41.079583],"type":"Point"}
}