{
  "type": "Feature",
  "properties": {
    "addr:full":"304 9th St NE Independence IA 50644",
    "addr:housenumber":"304",
    "addr:postcode":"50644",
    "addr:street":"9Th St Ne",
    "iso:country":"US",
    "sg:address":"304 9th St NE",
    "sg:city":"Independence",
    "sg:classifiers":[
        {
            "category":"Travel",
            "subcategory":"Travel Agent",
            "type":"Entertainment"
        }
    ],
    "sg:phone":"+1 319 334 3178",
    "sg:postcode":"50644",
    "sg:province":"IA",
    "sg:tags":[
        "operator",
        "tour",
        "agency",
        "bureau"
    ],
    "wof:name":"Hoover's Travel & Tour",
    "wof:placetype":"venue"
},
  "geometry": {"coordinates":[-91.89180899999999,42.476686],"type":"Point"}
}