{
  "type": "Feature",
  "properties": {
    "iso:country":"US",
    "sg:address":"301 N 3rd St",
    "sg:city":"Doon",
    "sg:classifiers":[
        {
            "category":"Personal",
            "subcategory":"Beauty Salon",
            "type":"Services"
        }
    ],
    "sg:phone":"+1 712 726 3038",
    "sg:postcode":"51235",
    "sg:province":"IA",
    "sg:tags":[
        "shop"
    ],
    "wof:name":"Creative Designs By Jill",
    "wof:placetype":"venue"
},
  "geometry": {"coordinates":[-96.23110200000001,43.282714],"type":"Point"}
}