{
  "type": "Feature",
  "properties": {
    "iso:country":"US",
    "sg:address":"4310 Ryan Ct",
    "sg:city":"Davenport",
    "sg:classifiers":[
        {
            "category":"Professional",
            "subcategory":"Business Services",
            "type":"Services"
        }
    ],
    "sg:phone":"+1 563 344 6880",
    "sg:postcode":"52807",
    "sg:province":"IA",
    "wof:name":"Fraud Resource Group LLC",
    "wof:placetype":"venue"
},
  "geometry": {"coordinates":[-90.52915299999999,41.563514],"type":"Point"}
}