{
  "type": "Feature",
  "properties": {
    "iso:country":"US",
    "sg:address":"19655 U Ave",
    "sg:city":"Reinbeck",
    "sg:classifiers":[
        {
            "category":"Farming",
            "subcategory":"Farm",
            "type":"Manufacturing & Wholesale Goods"
        }
    ],
    "sg:phone":"+1 319 989 2756",
    "sg:postcode":"50669",
    "sg:province":"IA",
    "sg:tags":[
        "crop",
        "general"
    ],
    "wof:name":"Larry Depping",
    "wof:placetype":"venue"
},
  "geometry": {"coordinates":[-92.631388,42.419033],"type":"Point"}
}