{
  "type": "Feature",
  "properties": {
    "iso:country":"US",
    "sg:address":"131 N 8th St",
    "sg:city":"Fort Dodge",
    "sg:classifiers":[
        {
            "category":"Real Estate",
            "subcategory":"Real Estate Operator",
            "type":"Services"
        }
    ],
    "sg:phone":"+1 515 576 8090",
    "sg:postcode":"50501",
    "sg:province":"IA",
    "sg:tags":[
        "apartment"
    ],
    "wof:name":"Court Apartments",
    "wof:placetype":"venue"
},
  "geometry": {"coordinates":[-94.187983,42.507438],"type":"Point"}
}