{
  "type": "Feature",
  "properties": {
    "addr:full":"2173 170th St West Point IA 52656",
    "addr:housenumber":"2173",
    "addr:postcode":"52656",
    "addr:street":"170Th St",
    "iso:country":"US",
    "sg:address":"2173 170th St",
    "sg:city":"West Point",
    "sg:phone":"+1 319 837 6420",
    "sg:postcode":"52656",
    "sg:province":"IA",
    "sg:tags":[
        "farm",
        "corn",
        "soybean"
    ],
    "wof:name":"Larry Fedler",
    "wof:placetype":"venue"
},
  "geometry": {"coordinates":[-91.49308000000001,40.70431],"type":"Point"}
}