{
  "type": "Feature",
  "properties": {
    "addr:full":"610 Bush St Lamont IA 50650",
    "addr:housenumber":"610",
    "addr:postcode":"50650",
    "addr:street":"Bush St",
    "iso:country":"US",
    "sg:address":"610 Bush St",
    "sg:city":"Lamont",
    "sg:classifiers":[
        {
            "category":"Restaurant",
            "type":"Food & Drink"
        }
    ],
    "sg:phone":"+1 563 924 2222",
    "sg:postcode":"50650",
    "sg:province":"IA",
    "sg:tags":[
        "caterer"
    ],
    "wof:name":"Coach House",
    "wof:placetype":"venue"
},
  "geometry": {"coordinates":[-91.64174800000001,42.599864],"type":"Point"}
}