{
  "type": "Feature",
  "properties": {
    "iso:country":"US",
    "sg:address":"8650 Northwest Blvd",
    "sg:city":"Davenport",
    "sg:classifiers":[
        {
            "category":"Wholesale",
            "subcategory":"Electrical",
            "type":"Manufacturing & Wholesale Goods"
        }
    ],
    "sg:phone":"+1 563 391 2622",
    "sg:postcode":"52806",
    "sg:province":"IA",
    "sg:tags":[
        "supply",
        "sign"
    ],
    "sg:website":"www.wensco.com",
    "wof:name":"Wensco Sign Supplies",
    "wof:placetype":"venue"
},
  "geometry": {"coordinates":[-90.62999000000001,41.607244],"type":"Point"}
}