{
  "type": "Feature",
  "properties": {
    "iso:country":"US",
    "sg:address":"15295 215th St",
    "sg:city":"Bloomfield",
    "sg:classifiers":[
        {
            "category":"Home & Garden",
            "subcategory":"Furniture",
            "type":"Retail Goods"
        }
    ],
    "sg:phone":"+1 641 664 2541",
    "sg:postcode":"52537",
    "sg:province":"IA",
    "sg:tags":[
        "store"
    ],
    "wof:name":"Millers Furniture",
    "wof:placetype":"venue"
},
  "geometry": {"coordinates":[-92.534046,40.74656],"type":"Point"}
}