{
  "type": "Feature",
  "properties": {
    "addr:full":"107 E Franklin St Bloomfield IA 52537",
    "addr:housenumber":"107",
    "addr:postcode":"52537",
    "addr:street":"E Franklin St",
    "iso:country":"US",
    "sg:address":"107 E Franklin St",
    "sg:city":"Bloomfield",
    "sg:classifiers":[
        {
            "category":"Cinema",
            "subcategory":"Movie Rental",
            "type":"Entertainment"
        }
    ],
    "sg:phone":"+1 641 664 3138",
    "sg:postcode":"52537",
    "sg:province":"IA",
    "sg:tags":[
        "leasing",
        "video",
        "disc",
        "tape"
    ],
    "wof:name":"Videoland",
    "wof:placetype":"venue"
},
  "geometry": {"coordinates":[-92.414978,40.750589],"type":"Point"}
}