{
  "type": "Feature",
  "properties": {
    "iso:country":"US",
    "sg:address":"315 5th St",
    "sg:city":"West Des Moines",
    "sg:classifiers":[
        {
            "category":"Professional",
            "subcategory":"Business Services",
            "type":"Services"
        }
    ],
    "sg:phone":"+1 515 271 5005",
    "sg:postcode":"50265",
    "sg:province":"IA",
    "sg:tags":[
        "interior",
        "consultant",
        "design",
        "decorator"
    ],
    "wof:name":"S A Kenny Interiors",
    "wof:placetype":"venue"
},
  "geometry": {"coordinates":[-93.708814,41.573714],"type":"Point"}
}