{
  "type": "Feature",
  "properties": {
    "iso:country":"US",
    "sg:address":"719 2nd St E",
    "sg:city":"Cresco",
    "sg:classifiers":[
        {
            "category":"Manufacturing",
            "subcategory":"Food",
            "type":"Manufacturing & Wholesale Goods"
        },
        {
            "category":"Farming",
            "subcategory":"Farm",
            "type":"Manufacturing & Wholesale Goods"
        }
    ],
    "sg:phone":"+1 563 547 2656",
    "sg:postcode":"52136",
    "sg:province":"IA",
    "sg:tags":[
        "corn",
        "product"
    ],
    "wof:name":"Merlin Reicks",
    "wof:placetype":"venue"
},
  "geometry": {"coordinates":[-92.11302000000001,43.379485],"type":"Point"}
}