{
  "type": "Feature",
  "properties": {
    "iso:country":"US",
    "sg:address":"106 Sunset Ln",
    "sg:city":"Mount Ayr",
    "sg:classifiers":[
        {
            "category":"Farming",
            "subcategory":"Livestock Farm",
            "type":"Manufacturing & Wholesale Goods"
        }
    ],
    "sg:phone":"+1 641 464 2453",
    "sg:postcode":"50854",
    "sg:province":"IA",
    "sg:tags":[
        "feedlot",
        "corn",
        "soybean",
        "beef",
        "cattle"
    ],
    "wof:name":"Jeff Sickels",
    "wof:placetype":"venue"
},
  "geometry": {"coordinates":[-94.246391,40.714846],"type":"Point"}
}