{
  "type": "Feature",
  "properties": {
    "addr:full":"616 N 8th St Osage IA 50461",
    "addr:housenumber":"616",
    "addr:postcode":"50461",
    "addr:street":"N 8Th St",
    "iso:country":"US",
    "sg:address":"616 N 8th St",
    "sg:city":"Osage",
    "sg:classifiers":[
        {
            "category":"Shopping",
            "subcategory":"Pharmacy",
            "type":"Retail Goods"
        }
    ],
    "sg:phone":"+1 641 732 6161",
    "sg:postcode":"50461",
    "sg:province":"IA",
    "wof:name":"Prescription Center",
    "wof:placetype":"venue"
},
  "geometry": {"coordinates":[-92.80941,43.289761],"type":"Point"}
}