{
  "type": "Feature",
  "properties": {
    "addr:full":"828 Des Moines Ave Ellsworth IA 50075",
    "addr:housenumber":"828",
    "addr:postcode":"50075",
    "addr:street":"Des Moines Ave",
    "iso:country":"US",
    "sg:address":"828 Des Moines Ave",
    "sg:city":"Ellsworth",
    "sg:classifiers":[
        {
            "category":"Building & Trades",
            "subcategory":"Construction",
            "type":"Services"
        }
    ],
    "sg:phone":"+1 515 836 4559",
    "sg:postcode":"50075",
    "sg:province":"IA",
    "sg:tags":[
        "general",
        "contractor"
    ],
    "wof:name":"Thompson Construction & Sharp",
    "wof:placetype":"venue"
},
  "geometry": {"coordinates":[-93.576078,42.312822],"type":"Point"}
}