{
  "type": "Feature",
  "properties": {
    "addr:full":"120 Lost Grove Rd Princeton IA 52768",
    "addr:housenumber":"120",
    "addr:postcode":"52768",
    "addr:street":"Lost Grove Rd",
    "iso:country":"US",
    "sg:address":"120 Lost Grove Rd",
    "sg:city":"Princeton",
    "sg:classifiers":[
        {
            "category":"Manufacturing",
            "subcategory":"Tools & Machinery",
            "type":"Manufacturing & Wholesale Goods"
        }
    ],
    "sg:phone":"+1 563 289 5808",
    "sg:postcode":"52768",
    "sg:province":"IA",
    "sg:tags":[
        "machine",
        "shop"
    ],
    "wof:name":"Schult Engine & Pattern Co",
    "wof:placetype":"venue"
},
  "geometry": {"coordinates":[-90.34057,41.677204],"type":"Point"}
}