{
  "type": "Feature",
  "properties": {
    "addr:full":"713 N 12th St Guthrie Center IA 50115",
    "addr:housenumber":"713",
    "addr:postcode":"50115",
    "addr:street":"N 12Th St",
    "iso:country":"US",
    "sg:address":"713 N 12th St",
    "sg:city":"Guthrie Center",
    "sg:classifiers":[
        {
            "category":"Organizations",
            "subcategory":"Religious Organization",
            "type":"Services"
        }
    ],
    "sg:phone":"+1 641 747 3918",
    "sg:postcode":"50115",
    "sg:province":"IA",
    "wof:name":"Immanuel Lutheran Church",
    "wof:placetype":"venue"
},
  "geometry": {"coordinates":[-94.494469,41.683605],"type":"Point"}
}