{
  "type": "Feature",
  "properties": {
    "addr:full":"305 6th St Victor IA 52347",
    "addr:housenumber":"305",
    "addr:postcode":"ia 52347",
    "addr:street":"6Th St",
    "iso:country":"US",
    "sg:address":"305 6th St",
    "sg:city":"Victor",
    "sg:classifiers":[
        {
            "category":"Wholesale",
            "subcategory":"Home Furnishings",
            "type":"Manufacturing & Wholesale Goods"
        }
    ],
    "sg:phone":"+1 319 647 3782",
    "sg:postcode":"52347",
    "sg:province":"IA",
    "wof:name":"Willow Creek LTD",
    "wof:placetype":"venue"
},
  "geometry": {"coordinates":[-92.291837,41.728791],"type":"Point"}
}