{
  "type": "Feature",
  "properties": {
    "iso:country":"US",
    "sg:address":"1204 13th St N",
    "sg:city":"Humboldt",
    "sg:classifiers":[
        {
            "category":"Retail",
            "subcategory":"Repair Shop",
            "type":"Services"
        }
    ],
    "sg:phone":"+1 515 332 3576",
    "sg:postcode":"50548",
    "sg:province":"IA",
    "sg:tags":[
        "outboard",
        "motor"
    ],
    "wof:name":"Johnson Marine",
    "wof:placetype":"venue"
},
  "geometry": {"coordinates":[-94.227225,42.735182],"type":"Point"}
}