{
  "type": "Feature",
  "properties": {
    "addr:full":"5326 330th St Battle Creek IA 51006",
    "addr:housenumber":"5326",
    "addr:postcode":"51006",
    "addr:street":"330Th St",
    "iso:country":"US",
    "sg:address":"5326 330th St",
    "sg:city":"Battle Creek",
    "sg:phone":"+1 712 365 4712",
    "sg:postcode":"51006",
    "sg:province":"IA",
    "sg:tags":[
        "farm",
        "field",
        "corn",
        "crop"
    ],
    "wof:name":"Robert Bumann",
    "wof:placetype":"venue"
},
  "geometry": {"coordinates":[-95.56993,42.225418],"type":"Point"}
}