{
  "type": "Feature",
  "properties": {
    "addr:full":"39 4th Ave SE Oelwein IA 50662",
    "addr:housenumber":"39",
    "addr:postcode":"50662",
    "addr:street":"4Th Ave Se",
    "iso:country":"US",
    "sg:address":"39 4th Ave SE",
    "sg:city":"Oelwein",
    "sg:classifiers":[
        {
            "category":"Personal",
            "subcategory":"Beauty Salon",
            "type":"Services"
        }
    ],
    "sg:phone":"+1 319 283 1841",
    "sg:postcode":"50662",
    "sg:province":"IA",
    "sg:tags":[
        "shop"
    ],
    "wof:name":"Lindas Beauty Shop",
    "wof:placetype":"venue"
},
  "geometry": {"coordinates":[-91.90773900000001,42.677999],"type":"Point"}
}