{
  "type": "Feature",
  "properties": {
    "addr:full":"851 630th St Washta IA 51049",
    "addr:housenumber":"851",
    "addr:postcode":"51049",
    "addr:street":"630Th St",
    "iso:country":"US",
    "sg:address":"851 630th St",
    "sg:city":"Washta",
    "sg:classifiers":[
        {
            "category":"Farming",
            "subcategory":"Livestock Farm",
            "type":"Manufacturing & Wholesale Goods"
        }
    ],
    "sg:phone":"+1 712 447 6369",
    "sg:postcode":"51049",
    "sg:province":"IA",
    "sg:tags":[
        "beef",
        "feedlot",
        "cattle"
    ],
    "wof:name":"Joshua Ebert",
    "wof:placetype":"venue"
},
  "geometry": {"coordinates":[-95.707323,42.604311],"type":"Point"}
}