{
  "type": "Feature",
  "properties": {
    "addr:full":"209 E San Marnan Dr Waterloo IA 50702",
    "addr:housenumber":"209",
    "addr:postcode":"50702",
    "addr:street":"E;Dr",
    "iso:country":"US",
    "sg:address":"209 E San Marnan Dr",
    "sg:city":"Waterloo",
    "sg:classifiers":[
        {
            "category":"Government",
            "subcategory":"Office",
            "type":"Public Place"
        }
    ],
    "sg:phone":"+1 319 233 2903",
    "sg:postcode":"50702",
    "sg:province":"IA",
    "sg:tags":[
        "sector",
        "regulation",
        "commercial"
    ],
    "wof:name":"Wage and Hour Div Field Off",
    "wof:placetype":"venue"
},
  "geometry": {"coordinates":[-92.35299999999999,42.457559],"type":"Point"}
}