{
  "type": "Feature",
  "properties": {
    "iso:country":"US",
    "sg:address":"301 Colony St",
    "sg:city":"Westphalia",
    "sg:classifiers":[
        {
            "category":"Retail",
            "subcategory":"Laundry & Dry Cleaning",
            "type":"Services"
        }
    ],
    "sg:phone":"+1 712 627 4625",
    "sg:postcode":"51530",
    "sg:province":"IA",
    "sg:tags":[
        "cleaners",
        "rug",
        "carpet"
    ],
    "wof:name":"Frank's Karpet Kleaning",
    "wof:placetype":"venue"
},
  "geometry": {"coordinates":[-95.396309,41.719651],"type":"Point"}
}