{
  "type": "Feature",
  "properties": {
    "iso:country":"US",
    "sg:address":"738 Division St",
    "sg:city":"Webster City",
    "sg:classifiers":[
        {
            "category":"Organizations",
            "subcategory":"Religious Organization",
            "type":"Services"
        }
    ],
    "sg:phone":"+1 515 832 5367",
    "sg:postcode":"50595",
    "sg:province":"IA",
    "wof:name":"Church of Christ of Webst",
    "wof:placetype":"venue"
},
  "geometry": {"coordinates":[-93.822954,42.467503],"type":"Point"}
}