{
  "type": "Feature",
  "properties": {
    "addr:full":"727 Birmingham Ave Waterloo IA 50702",
    "addr:housenumber":"727",
    "addr:postcode":"50702",
    "addr:street":"Birmingham Ave",
    "iso:country":"US",
    "sg:address":"727 Birmingham Ave",
    "sg:city":"Waterloo",
    "sg:classifiers":[
        {
            "category":"Autos & Motor Vehicles",
            "subcategory":"Automobile Sales",
            "type":"Retail Goods"
        }
    ],
    "sg:phone":"+1 319 233 9491",
    "sg:postcode":"50702",
    "sg:province":"IA",
    "sg:tags":[
        "car",
        "dealer"
    ],
    "wof:name":"Dave's Follies",
    "wof:placetype":"venue"
},
  "geometry": {"coordinates":[-92.321696,42.479675],"type":"Point"}
}