{
  "type": "Feature",
  "properties": {
    "iso:country":"US",
    "sg:address":"738 Alta Vista Dr",
    "sg:city":"Carroll",
    "sg:phone":"+1 712 792 4842",
    "sg:postcode":"51401",
    "sg:province":"IA",
    "sg:tags":[
        "farm",
        "corn",
        "soybean"
    ],
    "wof:name":"John Semprimi",
    "wof:placetype":"venue"
},
  "geometry": {"coordinates":[-94.856514,42.072661],"type":"Point"}
}