{
  "type": "Feature",
  "properties": {
    "iso:country":"US",
    "sg:address":"1201 Garfield Ave",
    "sg:city":"Dubuque",
    "sg:classifiers":[
        {
            "category":"Building & Trades",
            "subcategory":"Construction",
            "type":"Services"
        }
    ],
    "sg:phone":"+1 563 582 3824",
    "sg:postcode":"52001",
    "sg:province":"IA",
    "wof:name":"Choice Cable Contractors",
    "wof:placetype":"venue"
},
  "geometry": {"coordinates":[-90.658468,42.519844],"type":"Point"}
}