{
  "type": "Feature",
  "properties": {
    "addr:full":"101 3rd Ave SW Cedar Rapids IA 52404",
    "addr:housenumber":"101",
    "addr:postcode":"52404",
    "addr:street":"3Rd Ave Sw",
    "iso:country":"US",
    "sg:address":"101 3rd Ave SW",
    "sg:city":"Cedar Rapids",
    "sg:classifiers":[
        {
            "category":"Travel",
            "subcategory":"Hotels & Motels",
            "type":"Entertainment"
        }
    ],
    "sg:phone":"+1 319 363 8613",
    "sg:postcode":"52404",
    "sg:province":"IA",
    "sg:tags":[
        "management"
    ],
    "sg:website":"www.grandkeyresort.net",
    "wof:name":"Heartland Hotel Corp",
    "wof:placetype":"venue"
},
  "geometry": {"coordinates":[-91.67321200000001,41.974205],"type":"Point"}
}