{
  "type": "Feature",
  "properties": {
    "addr:full":"3371 290th St Manilla IA 51454",
    "addr:housenumber":"3371",
    "addr:postcode":"51454",
    "addr:street":"290Th St",
    "iso:country":"US",
    "sg:address":"3371 290th St",
    "sg:city":"Manilla",
    "sg:classifiers":[
        {
            "category":"Wholesale",
            "subcategory":"Farm Supplies",
            "type":"Manufacturing & Wholesale Goods"
        }
    ],
    "sg:phone":"+1 712 654 8148",
    "sg:postcode":"51454",
    "sg:province":"IA",
    "sg:tags":[
        "livestock"
    ],
    "wof:name":"D & D Feeder Pigs",
    "wof:placetype":"venue"
},
  "geometry": {"coordinates":[-95.305566,41.868243],"type":"Point"}
}