{
  "type": "Feature",
  "properties": {
    "iso:country":"US",
    "sg:address":"132 Shaul Ave",
    "sg:city":"Ottumwa",
    "sg:classifiers":[
        {
            "category":"Professional",
            "type":"Services"
        }
    ],
    "sg:phone":"+1 641 682 3585",
    "sg:postcode":"52501",
    "sg:province":"IA",
    "wof:name":"Wapello Web Services",
    "wof:placetype":"venue"
},
  "geometry": {"coordinates":[-92.44416699999999,41.001306],"type":"Point"}
}