{
  "type": "Feature",
  "properties": {
    "iso:country":"US",
    "sg:address":"621 N 3rd St",
    "sg:city":"Red Oak",
    "sg:classifiers":[
        {
            "category":"Professional",
            "subcategory":"Business Services",
            "type":"Services"
        }
    ],
    "sg:phone":"+1 712 623 3100",
    "sg:postcode":"51566",
    "sg:province":"IA",
    "sg:tags":[
        "embroidery"
    ],
    "wof:name":"Gregory's Embroidery",
    "wof:placetype":"venue"
},
  "geometry": {"coordinates":[-95.229208,41.009938],"type":"Point"}
}