{
  "type": "Feature",
  "properties": {
    "iso:country":"US",
    "sg:address":"1530 NE 53rd Ave",
    "sg:city":"Des Moines",
    "sg:classifiers":[
        {
            "category":"Government",
            "subcategory":"Office",
            "type":"Public Place"
        }
    ],
    "sg:phone":"+1 515 262 5692",
    "sg:postcode":"50313",
    "sg:province":"IA",
    "sg:tags":[
        "state"
    ],
    "wof:name":"Residency Construction Office",
    "wof:placetype":"venue"
},
  "geometry": {"coordinates":[-93.597201,41.656562],"type":"Point"}
}