{
  "type": "Feature",
  "properties": {
    "addr:full":"1010 N Broadway St Red Oak IA 51566",
    "addr:housenumber":"1010",
    "addr:postcode":"51566",
    "addr:street":"N Broadway St",
    "iso:country":"US",
    "sg:address":"1010 N Broadway St",
    "sg:city":"Red Oak",
    "sg:classifiers":[
        {
            "category":"Banks & Credit Unions",
            "subcategory":"Investment Brokerage",
            "type":"Services"
        }
    ],
    "sg:phone":"+1 712 623 4802",
    "sg:postcode":"51566",
    "sg:province":"IA",
    "sg:tags":[
        "advisory",
        "financial"
    ],
    "wof:name":"ASI Financial Inc",
    "wof:placetype":"venue"
},
  "geometry": {"coordinates":[-95.232624,41.013362],"type":"Point"}
}