{
  "type": "Feature",
  "properties": {
    "iso:country":"US",
    "sg:address":"501 2nd Ave SW",
    "sg:city":"Sioux Center",
    "sg:classifiers":[
        {
            "category":"Organizations",
            "subcategory":"Religious Organization",
            "type":"Services"
        }
    ],
    "sg:phone":"+1 712 476 2060",
    "sg:postcode":"51250",
    "sg:province":"IA",
    "sg:tags":[
        "church"
    ],
    "wof:name":"Christ The King Catholic Cmnty",
    "wof:placetype":"venue"
},
  "geometry": {"coordinates":[-96.178236,43.073358],"type":"Point"}
}