{
  "type": "Feature",
  "properties": {
    "iso:country":"US",
    "sg:address":"210 E 9th St",
    "sg:city":"Coralville",
    "sg:classifiers":[
        {
            "category":"Retail",
            "subcategory":"Auto Repair",
            "type":"Services"
        }
    ],
    "sg:phone":"+1 319 351 3231",
    "sg:postcode":"52241",
    "sg:province":"IA",
    "sg:tags":[
        "body",
        "automobile",
        "painting"
    ],
    "wof:name":"Clear Co Auto Body",
    "wof:placetype":"venue"
},
  "geometry": {"coordinates":[-91.560154,41.681348],"type":"Point"}
}