{
  "type": "Feature",
  "properties": {
    "addr:full":"3115 260th St Ainsworth IA 52201",
    "addr:housenumber":"3115",
    "addr:postcode":"52201",
    "addr:street":"260Th St",
    "iso:country":"US",
    "sg:address":"3115 260th St",
    "sg:city":"Ainsworth",
    "sg:classifiers":[
        {
            "category":"Farming",
            "subcategory":"Livestock Farm",
            "type":"Manufacturing & Wholesale Goods"
        }
    ],
    "sg:phone":"+1 319 657 2732",
    "sg:postcode":"52201",
    "sg:province":"IA",
    "sg:tags":[
        "hog",
        "or",
        "feedlot"
    ],
    "wof:name":"Jay Greene",
    "wof:placetype":"venue"
},
  "geometry": {"coordinates":[-91.544662,41.279008],"type":"Point"}
}