{
  "type": "Feature",
  "properties": {
    "iso:country":"US",
    "sg:address":"1400 6th St SW",
    "sg:city":"Cedar Rapids",
    "sg:classifiers":[
        {
            "category":"Food & Beverages",
            "subcategory":"Groceries & Convenience Stores",
            "type":"Retail Goods"
        }
    ],
    "sg:phone":"+1 319 365 7594",
    "sg:postcode":"52404",
    "sg:province":"IA",
    "wof:name":"Nordstrom Oil Co",
    "wof:placetype":"venue"
},
  "geometry": {"coordinates":[-91.677299,41.963501],"type":"Point"}
}