{
  "type": "Feature",
  "properties": {
    "addr:full":"1708 G Ave Grundy Center IA 50638",
    "addr:housenumber":"1708",
    "addr:postcode":"50638",
    "addr:street":"G Ave",
    "iso:country":"US",
    "sg:address":"1708 G Ave",
    "sg:city":"Grundy Center",
    "sg:classifiers":[
        {
            "category":"Restaurant",
            "type":"Food & Drink"
        }
    ],
    "sg:menulink":"http://www.allmenus.com/ia/palermo/225928-caseys-general-store/menu/",
    "sg:phone":"+1 319 824 3137",
    "sg:postcode":"50638",
    "sg:province":"IA",
    "sg:tags":[
        "american",
        "pizza"
    ],
    "wof:name":"Casey's General Store",
    "wof:placetype":"venue"
},
  "geometry": {"coordinates":[-92.78650500000001,42.361602],"type":"Point"}
}