{
  "type": "Feature",
  "properties": {
    "iso:country":"US",
    "sg:address":"309 Ballard St",
    "sg:city":"West Burlington",
    "sg:classifiers":[
        {
            "category":"Professional",
            "type":"Services"
        }
    ],
    "sg:phone":"+1 319 752 3438",
    "sg:postcode":"52655",
    "sg:province":"IA",
    "wof:name":"Iowa Soc Fire Svc Instructors",
    "wof:placetype":"venue"
},
  "geometry": {"coordinates":[-91.154205,40.823919],"type":"Point"}
}