{
  "type": "Feature",
  "properties": {
    "addr:full":"306 N River Park Dr Guttenberg IA 52052",
    "addr:housenumber":"306",
    "addr:postcode":"52052",
    "addr:street":"N River Park Dr",
    "iso:country":"US",
    "sg:address":"306 N River Park Dr",
    "sg:city":"Guttenberg",
    "sg:classifiers":[
        {
            "category":"Insurance",
            "subcategory":"Insurance Agent",
            "type":"Services"
        }
    ],
    "sg:phone":"+1 563 252 2018",
    "sg:postcode":"52052",
    "sg:province":"IA",
    "wof:name":"Degnan-Green Insurance & Rlty",
    "wof:placetype":"venue"
},
  "geometry": {"coordinates":[-91.09940400000001,42.789768],"type":"Point"}
}