{
  "type": "Feature",
  "properties": {
    "iso:country":"US",
    "sg:address":"223 S Delaware St",
    "sg:city":"Osceola",
    "sg:classifiers":[
        {
            "category":"Professional",
            "type":"Services"
        }
    ],
    "sg:phone":"+1 641 342 6106",
    "sg:postcode":"50213",
    "sg:province":"IA",
    "sg:tags":[
        "establishment"
    ],
    "wof:name":"Grubbs & Grubbs",
    "wof:placetype":"venue"
},
  "geometry": {"coordinates":[-93.77343500000001,41.032549],"type":"Point"}
}