{
  "type": "Feature",
  "properties": {
    "iso:country":"US",
    "sg:address":"612 Locust St",
    "sg:city":"Des Moines",
    "sg:classifiers":[
        {
            "category":"Health Services",
            "subcategory":"Doctor",
            "type":"Services"
        }
    ],
    "sg:phone":"+1 515 280 3030",
    "sg:postcode":"50309",
    "sg:province":"IA",
    "sg:tags":[
        "dentist"
    ],
    "wof:name":"Skywalk Dental Office",
    "wof:placetype":"venue"
},
  "geometry": {"coordinates":[-93.626052,41.586534],"type":"Point"}
}