{
  "type": "Feature",
  "properties": {
    "addr:full":"1104 State St Bettendorf IA 52722",
    "addr:housenumber":"1104",
    "addr:postcode":"52722",
    "addr:street":"State St",
    "iso:country":"US",
    "sg:address":"1104 State St",
    "sg:city":"Bettendorf",
    "sg:classifiers":[
        {
            "category":"Wholesale",
            "subcategory":"Machinery & Supplies",
            "type":"Manufacturing & Wholesale Goods"
        }
    ],
    "sg:phone":"+1 563 355 3737",
    "sg:postcode":"52722",
    "sg:province":"IA",
    "sg:tags":[
        "salon",
        "beauty"
    ],
    "wof:name":"State Beauty Supply",
    "wof:placetype":"venue"
},
  "geometry": {"coordinates":[-90.51703500000001,41.525142],"type":"Point"}
}