{
  "type": "Feature",
  "properties": {
    "addr:full":"1715 Whitters Way NW Cedar Rapids IA 52405",
    "addr:housenumber":"1715",
    "addr:postcode":"52405",
    "addr:street":"Whitters Way Nw",
    "iso:country":"US",
    "sg:address":"1715 Whitters Way NW",
    "sg:city":"Cedar Rapids",
    "sg:classifiers":[
        {
            "category":"Retail",
            "subcategory":"Portrait Studio",
            "type":"Services"
        }
    ],
    "sg:phone":"+1 319 399 1948",
    "sg:postcode":"52405",
    "sg:province":"IA",
    "sg:tags":[
        "photo"
    ],
    "wof:name":"Quiet Places Photography",
    "wof:placetype":"venue"
},
  "geometry": {"coordinates":[-91.69372300000001,41.99368],"type":"Point"}
}