{
  "type": "Feature",
  "properties": {
    "addr:full":"203 Adair St Griswold IA 51535",
    "addr:housenumber":"203",
    "addr:postcode":"51535",
    "addr:street":"Adair St",
    "iso:country":"US",
    "sg:address":"203 Adair St",
    "sg:city":"Griswold",
    "sg:classifiers":[
        {
            "category":"Organizations",
            "subcategory":"Religious Organization",
            "type":"Services"
        }
    ],
    "sg:phone":"+1 712 778 4540",
    "sg:postcode":"51535",
    "sg:province":"IA",
    "sg:tags":[
        "church"
    ],
    "wof:name":"Our Lady Of Grace Catholic Chr",
    "wof:placetype":"venue"
},
  "geometry": {"coordinates":[-95.137097,41.235651],"type":"Point"}
}