{
  "type": "Feature",
  "properties": {
    "addr:full":"1812 Lucas Ave Burlington IA 52601",
    "addr:housenumber":"1812",
    "addr:postcode":"52601",
    "addr:street":"Lucas Ave",
    "iso:country":"US",
    "sg:address":"1812 Lucas Ave",
    "sg:city":"Burlington",
    "sg:classifiers":[
        {
            "category":"Building & Trades",
            "subcategory":"Construction",
            "type":"Services"
        }
    ],
    "sg:phone":"+1 319 753 2683",
    "sg:postcode":"52601",
    "sg:province":"IA",
    "sg:tags":[
        "house"
    ],
    "wof:name":"Ruberg Construction",
    "wof:placetype":"venue"
},
  "geometry": {"coordinates":[-91.125387,40.818583],"type":"Point"}
}