{
  "type": "Feature",
  "properties": {
    "addr:full":"1583 120th St Sioux City IA 51108",
    "addr:housenumber":"1583",
    "addr:postcode":"51108",
    "addr:street":"120Th St",
    "iso:country":"US",
    "sg:address":"1583 120th St",
    "sg:city":"Sioux City",
    "sg:classifiers":[
        {
            "category":"Building & Trades",
            "subcategory":"Plumbing",
            "type":"Services"
        }
    ],
    "sg:phone":"+1 712 239 3100",
    "sg:postcode":"51108",
    "sg:province":"IA",
    "sg:tags":[
        "plumbing",
        "contractor"
    ],
    "wof:name":"Beane Plumbing-Heating Co",
    "wof:placetype":"venue"
},
  "geometry": {"coordinates":[-96.28155099999999,42.533092],"type":"Point"}
}