{
  "type": "Feature",
  "properties": {
    "iso:country":"US",
    "sg:address":"501 Locust St",
    "sg:city":"Des Moines",
    "sg:classifiers":[
        {
            "category":"Social Services",
            "subcategory":"Child Care",
            "type":"Services"
        }
    ],
    "sg:phone":"+1 515 284 5848",
    "sg:postcode":"50309",
    "sg:province":"IA",
    "sg:tags":[
        "center",
        "daycare"
    ],
    "wof:name":"Bright Horizons Childrens Ctrs",
    "wof:placetype":"venue"
},
  "geometry": {"coordinates":[-93.62496899999999,41.586833],"type":"Point"}
}