{
  "type": "Feature",
  "properties": {
    "addr:full":"600 W Main St Anamosa IA 52205",
    "addr:housenumber":"600",
    "addr:postcode":"52205",
    "addr:street":"W Main St",
    "iso:country":"US",
    "sg:address":"600 W Main St",
    "sg:city":"Anamosa",
    "sg:classifiers":[
        {
            "category":"Retail",
            "subcategory":"Auto Repair",
            "type":"Services"
        }
    ],
    "sg:phone":"+1 319 462 2627",
    "sg:postcode":"52205",
    "sg:province":"IA",
    "sg:tags":[
        "wrecker"
    ],
    "wof:name":"Red's Towing",
    "wof:placetype":"venue"
},
  "geometry": {"coordinates":[-91.291265,42.108294],"type":"Point"}
}