{
  "type": "Feature",
  "properties": {
    "iso:country":"US",
    "sg:address":"810 Hwy 175",
    "sg:city":"Stratford",
    "sg:classifiers":[
        {
            "category":"Food & Beverages",
            "subcategory":"Groceries & Convenience Stores",
            "type":"Retail Goods"
        }
    ],
    "sg:phone":"+1 515 838 2800",
    "sg:postcode":"50249",
    "sg:province":"IA",
    "wof:name":"Ampride",
    "wof:placetype":"venue"
},
  "geometry": {"coordinates":[-93.928158,42.26774],"type":"Point"}
}