{
  "type": "Feature",
  "properties": {
    "iso:country":"US",
    "sg:address":"2290 Evergreen Dr",
    "sg:city":"Dubuque",
    "sg:classifiers":[
        {
            "category":"Professional",
            "subcategory":"Management & Consulting",
            "type":"Services"
        },
        {
            "category":"Education",
            "subcategory":"Special Training",
            "type":"Public Place"
        }
    ],
    "sg:phone":"+1 563 556 0985",
    "sg:postcode":"52001",
    "sg:province":"IA",
    "wof:name":"Dan Block & Assoc LLC",
    "wof:placetype":"venue"
},
  "geometry": {"coordinates":[-90.715992,42.510485],"type":"Point"}
}