{
  "type": "Feature",
  "properties": {
    "addr:full":"1013 N Federal Ave Mason City IA 50401",
    "addr:housenumber":"1013",
    "addr:postcode":"50401",
    "addr:street":"N Federal Ave",
    "iso:country":"US",
    "sg:address":"1013 N Federal Ave",
    "sg:city":"Mason City",
    "sg:classifiers":[
        {
            "category":"Autos & Motor Vehicles",
            "subcategory":"Automobile Sales",
            "type":"Retail Goods"
        }
    ],
    "sg:phone":"+1 641 424 6642",
    "sg:postcode":"50401",
    "sg:province":"IA",
    "sg:tags":[
        "car",
        "dealer"
    ],
    "wof:name":"Smitty's Auto Sales",
    "wof:placetype":"venue"
},
  "geometry": {"coordinates":[-93.20098900000001,43.160263],"type":"Point"}
}