{
  "type": "Feature",
  "properties": {
    "iso:country":"US",
    "sg:address":"2003 E Bremer Ave",
    "sg:city":"Waverly",
    "sg:classifiers":[
        {
            "category":"Autos & Motor Vehicles",
            "subcategory":"Auto Supplies",
            "type":"Retail Goods"
        }
    ],
    "sg:phone":"+1 319 352 5552",
    "sg:postcode":"50677",
    "sg:province":"IA",
    "sg:tags":[
        "tire"
    ],
    "wof:name":"Garry's Tire Svc",
    "wof:placetype":"venue"
},
  "geometry": {"coordinates":[-92.447315,42.720527],"type":"Point"}
}