{
  "type": "Feature",
  "properties": {
    "iso:country":"US",
    "sg:address":"28429 E Ave",
    "sg:city":"Conrad",
    "sg:classifiers":[
        {
            "category":"Organizations",
            "subcategory":"Labor Organization",
            "type":"Services"
        }
    ],
    "sg:phone":"+1 641 366 2515",
    "sg:postcode":"50621",
    "sg:province":"IA",
    "wof:name":"Diversity Ventures LLC",
    "wof:placetype":"venue"
},
  "geometry": {"coordinates":[-92.943851,42.290177],"type":"Point"}
}