{
  "type": "Feature",
  "properties": {
    "iso:country":"US",
    "sg:address":"2481 Alderman Rd",
    "sg:city":"Springville",
    "sg:classifiers":[
        {
            "category":"Real Estate",
            "subcategory":"Real Estate Operator",
            "type":"Services"
        }
    ],
    "sg:phone":"+1 319 854 6692",
    "sg:postcode":"52336",
    "sg:province":"IA",
    "sg:tags":[
        "property",
        "lessor"
    ],
    "wof:name":"Stanley Pedersen",
    "wof:placetype":"venue"
},
  "geometry": {"coordinates":[-91.423518,42.03586],"type":"Point"}
}