{
  "type": "Feature",
  "properties": {
    "addr:full":"3305 Asbury Rd Dubuque IA 52002",
    "addr:housenumber":"3305",
    "addr:postcode":"52002",
    "addr:street":"Asbury Rd",
    "iso:country":"US",
    "sg:address":"3305 Asbury Rd",
    "sg:city":"Dubuque",
    "sg:classifiers":[
        {
            "category":"Professional",
            "subcategory":"Accounting & Tax Preparation",
            "type":"Services"
        }
    ],
    "sg:phone":"+1 563 556 6061",
    "sg:postcode":"52002",
    "sg:province":"IA",
    "sg:tags":[
        "return",
        "filing"
    ],
    "wof:name":"Liberty Tax Svc",
    "wof:placetype":"venue"
},
  "geometry": {"coordinates":[-90.72507299999999,42.514263],"type":"Point"}
}