{
  "type": "Feature",
  "properties": {
    "iso:country":"US",
    "sg:address":"510 Lake Ave",
    "sg:city":"Storm Lake",
    "sg:classifiers":[
        {
            "category":"Shopping",
            "type":"Retail Goods"
        }
    ],
    "sg:phone":"+1 712 732 5763",
    "sg:postcode":"50588",
    "sg:province":"IA",
    "sg:tags":[
        "art",
        "gallery",
        "dealer"
    ],
    "wof:name":"Frame'n Art Shoppe",
    "wof:placetype":"venue"
},
  "geometry": {"coordinates":[-95.200952,42.644325],"type":"Point"}
}