{
  "type": "Feature",
  "properties": {
    "iso:country":"US",
    "sg:address":"27 S 14th St",
    "sg:city":"Keokuk",
    "sg:classifiers":[
        {
            "category":"Building & Trades",
            "subcategory":"Construction",
            "type":"Services"
        }
    ],
    "sg:phone":"+1 319 524 5887",
    "sg:postcode":"52632",
    "sg:province":"IA",
    "sg:tags":[
        "general",
        "contractor"
    ],
    "wof:name":"Pro-Maps Inc",
    "wof:placetype":"venue"
},
  "geometry": {"coordinates":[-91.39093800000001,40.402629],"type":"Point"}
}