{
  "type": "Feature",
  "properties": {
    "iso:country":"US",
    "sg:address":"1055 Linden Dr",
    "sg:city":"Marion",
    "sg:classifiers":[
        {
            "category":"Cinema",
            "subcategory":"Movie Rental",
            "type":"Entertainment"
        }
    ],
    "sg:phone":"+1 319 373 6951",
    "sg:postcode":"52302",
    "sg:province":"IA",
    "sg:tags":[
        "leasing",
        "video",
        "disc",
        "tape"
    ],
    "wof:name":"Family Video",
    "wof:placetype":"venue"
},
  "geometry": {"coordinates":[-91.575517,42.036659],"type":"Point"}
}