{
  "type": "Feature",
  "properties": {
    "addr:full":"1611 US Hwy 65 Hampton IA 50441",
    "addr:housenumber":"1611",
    "addr:postcode":"50441",
    "addr:street":"Us Hwy 65",
    "iso:country":"US",
    "sg:address":"1611 US Hwy 65",
    "sg:city":"Hampton",
    "sg:classifiers":[
        {
            "category":"Wholesale",
            "subcategory":"Machinery & Supplies",
            "type":"Manufacturing & Wholesale Goods"
        }
    ],
    "sg:phone":"+1 641 456 2534",
    "sg:postcode":"50441",
    "sg:province":"IA",
    "sg:tags":[
        "tractor"
    ],
    "wof:name":"Phelps Implement",
    "wof:placetype":"venue"
},
  "geometry": {"coordinates":[-93.202161,42.776186],"type":"Point"}
}