{
  "type": "Feature",
  "properties": {
    "iso:country":"US",
    "sg:address":"502 5th St NW",
    "sg:city":"Dyersville",
    "sg:classifiers":[
        {
            "category":"Manufacturing",
            "subcategory":"Rubber & Plastics",
            "type":"Manufacturing & Wholesale Goods"
        }
    ],
    "sg:phone":"+1 563 875 8548",
    "sg:postcode":"52040",
    "sg:province":"IA",
    "sg:tags":[
        "product"
    ],
    "wof:name":"Scale Models",
    "wof:placetype":"venue"
},
  "geometry": {"coordinates":[-91.130087,42.487785],"type":"Point"}
}