{
  "type": "Feature",
  "properties": {
    "iso:country":"US",
    "sg:address":"1575 SE Olson Dr",
    "sg:city":"Waukee",
    "sg:classifiers":[
        {
            "category":"Professional",
            "type":"Services"
        }
    ],
    "sg:phone":"+1 515 987 8991",
    "sg:postcode":"50263",
    "sg:province":"IA",
    "sg:tags":[
        "establishment"
    ],
    "wof:name":"Dyvig & Dyvig",
    "wof:placetype":"venue"
},
  "geometry": {"coordinates":[-93.84231800000001,41.603465],"type":"Point"}
}