{
  "type": "Feature",
  "properties": {
    "iso:country":"US",
    "sg:address":"1571 Joplin Ave",
    "sg:city":"Waverly",
    "sg:classifiers":[
        {
            "category":"Retail",
            "subcategory":"Repair Shop",
            "type":"Services"
        }
    ],
    "sg:phone":"+1 319 276 3302",
    "sg:postcode":"50677",
    "sg:province":"IA",
    "wof:name":"Brandt AG Repair",
    "wof:placetype":"venue"
},
  "geometry": {"coordinates":[-92.376777,42.82259],"type":"Point"}
}