{
  "type": "Feature",
  "properties": {
    "addr:full":"1555 S 1st Ave Iowa City IA 52240",
    "addr:housenumber":"1555",
    "addr:postcode":"52240",
    "addr:street":"S 1St Ave",
    "iso:country":"US",
    "sg:address":"1555 S 1st Ave",
    "sg:city":"Iowa City",
    "sg:classifiers":[
        {
            "category":"Personal",
            "subcategory":"Tanning Parlor",
            "type":"Services"
        }
    ],
    "sg:phone":"+1 319 351 2673",
    "sg:postcode":"52240",
    "sg:province":"IA",
    "sg:tags":[
        "salon"
    ],
    "sg:website":"www.corefitness1.com",
    "wof:name":"Pacific Tan",
    "wof:placetype":"venue"
},
  "geometry": {"coordinates":[-91.506489,41.64199],"type":"Point"}
}