{
  "type": "Feature",
  "properties": {
    "addr:full":"1141 11th St Sheldon IA 51201",
    "addr:housenumber":"1141",
    "addr:postcode":"51201",
    "addr:street":"11Th St",
    "iso:country":"US",
    "sg:address":"1141 11th St",
    "sg:city":"Sheldon",
    "sg:classifiers":[
        {
            "category":"Freight",
            "type":"Transportation"
        }
    ],
    "sg:phone":"+1 712 324 2496",
    "sg:postcode":"51201",
    "sg:province":"IA",
    "sg:tags":[
        "operator",
        "local",
        "trucking"
    ],
    "wof:name":"F & B Transportation",
    "wof:placetype":"venue"
},
  "geometry": {"coordinates":[-95.843037,43.175838],"type":"Point"}
}