{
  "type": "Feature",
  "properties": {
    "iso:country":"US",
    "sg:address":"11374 Maple Grove Ct",
    "sg:city":"Dubuque",
    "sg:classifiers":[
        {
            "category":"Shopping",
            "type":"Retail Goods"
        }
    ],
    "sg:phone":"+1 563 583 9501",
    "sg:postcode":"52003",
    "sg:province":"IA",
    "sg:tags":[
        "spa",
        "hot",
        "tub"
    ],
    "wof:name":"Spa Connections",
    "wof:placetype":"venue"
},
  "geometry": {"coordinates":[-90.760633,42.459913],"type":"Point"}
}