{
  "type": "Feature",
  "properties": {
    "iso:country":"US",
    "sg:address":"3983 Thrush Ave",
    "sg:city":"Kensett",
    "sg:phone":"+1 641 748 2374",
    "sg:postcode":"50448",
    "sg:province":"IA",
    "sg:tags":[
        "farm",
        "corn",
        "soybean"
    ],
    "wof:name":"Dale Schultz",
    "wof:placetype":"venue"
},
  "geometry": {"coordinates":[-93.123604,43.340688],"type":"Point"}
}