{
  "type": "Feature",
  "properties": {
    "iso:country":"US",
    "sg:address":"1201 US Hwy 18",
    "sg:city":"Britt",
    "sg:classifiers":[
        {
            "category":"Farming",
            "subcategory":"Farm",
            "type":"Manufacturing & Wholesale Goods"
        }
    ],
    "sg:phone":"+1 641 843 4516",
    "sg:postcode":"50423",
    "sg:province":"IA",
    "sg:tags":[
        "feedlot",
        "hog",
        "or",
        "crop",
        "general"
    ],
    "wof:name":"Eagle Estate Inc",
    "wof:placetype":"venue"
},
  "geometry": {"coordinates":[-93.754283,43.103936],"type":"Point"}
}