{
  "type": "Feature",
  "properties": {
    "addr:full":"4210 Floyd Blvd Sioux City IA 51108",
    "addr:housenumber":"4210",
    "addr:postcode":"51108",
    "addr:street":"Floyd Blvd",
    "iso:country":"US",
    "sg:address":"4210 Floyd Blvd",
    "sg:city":"Sioux City",
    "sg:classifiers":[
        {
            "category":"Retail",
            "subcategory":"Auto Repair",
            "type":"Services"
        }
    ],
    "sg:phone":"+1 712 239 2744",
    "sg:postcode":"51108",
    "sg:province":"IA",
    "sg:tags":[
        "repairing",
        "automobile"
    ],
    "wof:name":"Don's Auto Ctr",
    "wof:placetype":"venue"
},
  "geometry": {"coordinates":[-96.356289,42.543317],"type":"Point"}
}