{
  "type": "Feature",
  "properties": {
    "addr:full":"1511 E San Marnan Dr Waterloo IA 50702",
    "addr:housenumber":"1511",
    "addr:postcode":"50702",
    "addr:street":"E;Dr",
    "iso:country":"US",
    "sg:address":"1511 E San Marnan Dr",
    "sg:city":"Waterloo",
    "sg:classifiers":[
        {
            "category":"Shopping",
            "subcategory":"Hobbies, Toys, & Games",
            "type":"Retail Goods"
        }
    ],
    "sg:phone":"+1 319 833 8134",
    "sg:postcode":"50702",
    "sg:province":"IA",
    "sg:tags":[
        "supply"
    ],
    "wof:name":"Game Crazy",
    "wof:placetype":"venue"
},
  "geometry": {"coordinates":[-92.32364699999999,42.465621],"type":"Point"}
}