{
  "type": "Feature",
  "properties": {
    "iso:country":"US",
    "sg:address":"711 W 76th St",
    "sg:city":"Davenport",
    "sg:classifiers":[
        {
            "category":"Autos & Motor Vehicles",
            "subcategory":"Recreational Vehicle Sales",
            "type":"Retail Goods"
        }
    ],
    "sg:phone":"+1 563 386 4213",
    "sg:postcode":"52806",
    "sg:province":"IA",
    "sg:tags":[
        "canopy",
        "shell",
        "truck",
        "cap"
    ],
    "sg:website":"www.sadlerpowertrain.com",
    "wof:name":"Sadler Power Train Inc",
    "wof:placetype":"venue"
},
  "geometry": {"coordinates":[-90.583865,41.596103],"type":"Point"}
}