{
  "type": "Feature",
  "properties": {
    "addr:full":"1201 Grandview Ave Des Moines IA 50316",
    "addr:housenumber":"1201",
    "addr:postcode":"50316",
    "addr:street":"Grandview Ave",
    "iso:country":"US",
    "sg:address":"1201 Grandview Ave",
    "sg:city":"Des Moines",
    "sg:classifiers":[
        {
            "category":"Organizations",
            "subcategory":"Religious Organization",
            "type":"Services"
        }
    ],
    "sg:phone":"+1 515 262 1392",
    "sg:postcode":"50316",
    "sg:province":"IA",
    "sg:tags":[
        "church"
    ],
    "wof:name":"Luther Memorial Church",
    "wof:placetype":"venue"
},
  "geometry": {"coordinates":[-93.605209,41.620361],"type":"Point"}
}