{
  "type": "Feature",
  "properties": {
    "iso:country":"US",
    "sg:address":"1312 18th St SW",
    "sg:city":"Cedar Rapids",
    "sg:classifiers":[
        {
            "category":"Social Services",
            "subcategory":"Child Care",
            "type":"Services"
        }
    ],
    "sg:phone":"+1 319 366 1825",
    "sg:postcode":"52404",
    "sg:province":"IA",
    "sg:tags":[
        "day"
    ],
    "wof:name":"Culps Cuties",
    "wof:placetype":"venue"
},
  "geometry": {"coordinates":[-91.696147,41.962433],"type":"Point"}
}