{
  "type": "Feature",
  "properties": {
    "addr:full":"112 W Briggs Ave Fairfield IA 52556",
    "addr:housenumber":"112",
    "addr:postcode":"52556",
    "addr:street":"W Briggs Ave",
    "iso:country":"US",
    "sg:address":"112 W Briggs Ave",
    "sg:city":"Fairfield",
    "sg:classifiers":[
        {
            "category":"Insurance",
            "subcategory":"Insurance Agent",
            "type":"Services"
        }
    ],
    "sg:phone":"+1 641 472 2141",
    "sg:postcode":"52556",
    "sg:province":"IA",
    "wof:name":"Gamrath-Doyle & Assoc Inc",
    "wof:placetype":"venue"
},
  "geometry": {"coordinates":[-91.9644,41.008535],"type":"Point"}
}