{
  "type": "Feature",
  "properties": {
    "addr:full":"1760 Radford Rd Dubuque IA 52002",
    "addr:housenumber":"1760",
    "addr:postcode":"52002",
    "addr:street":"Radford Rd",
    "iso:country":"US",
    "sg:address":"1760 Radford Rd",
    "sg:city":"Dubuque",
    "sg:classifiers":[
        {
            "category":"Manufacturing",
            "subcategory":"Tools & Machinery",
            "type":"Manufacturing & Wholesale Goods"
        }
    ],
    "sg:phone":"+1 563 588 2122",
    "sg:postcode":"52002",
    "sg:province":"IA",
    "sg:tags":[
        "pattern",
        "maker"
    ],
    "wof:name":"Ja-Mar Pattern Inc",
    "wof:placetype":"venue"
},
  "geometry": {"coordinates":[-90.74985100000001,42.501581],"type":"Point"}
}