{
  "type": "Feature",
  "properties": {
    "addr:full":"5520 Miehe Dr Grimes IA 50111",
    "addr:housenumber":"5520",
    "addr:postcode":"50111",
    "addr:street":"Miehe Dr",
    "iso:country":"US",
    "sg:address":"5520 Miehe Dr",
    "sg:city":"Grimes",
    "sg:classifiers":[
        {
            "category":"Building & Trades",
            "subcategory":"Construction",
            "type":"Services"
        }
    ],
    "sg:phone":"+1 515 986 1161",
    "sg:postcode":"50111",
    "sg:province":"IA",
    "sg:tags":[
        "concrete",
        "contractor"
    ],
    "wof:name":"Warren Concrete Svc",
    "wof:placetype":"venue"
},
  "geometry": {"coordinates":[-93.76684,41.658486],"type":"Point"}
}