{
  "type": "Feature",
  "properties": {
    "addr:full":"304 Main St Chester IA 52134",
    "addr:housenumber":"304",
    "addr:postcode":"52134",
    "addr:street":"Main St",
    "iso:country":"US",
    "sg:address":"304 Main St",
    "sg:city":"Chester",
    "sg:classifiers":[
        {
            "category":"Food & Beverages",
            "subcategory":"Groceries & Convenience Stores",
            "type":"Retail Goods"
        }
    ],
    "sg:phone":"+1 563 565 2631",
    "sg:postcode":"52134",
    "sg:province":"IA",
    "wof:name":"R & S Fuel",
    "wof:placetype":"venue"
},
  "geometry": {"coordinates":[-92.358712,43.49011],"type":"Point"}
}