{
  "type": "Feature",
  "properties": {
    "iso:country":"US",
    "sg:address":"2611 Ingersoll Ave",
    "sg:city":"Des Moines",
    "sg:classifiers":[
        {
            "category":"Insurance",
            "subcategory":"Insurance Agent",
            "type":"Services"
        }
    ],
    "sg:phone":"+1 515 243 1223",
    "sg:postcode":"50312",
    "sg:province":"IA",
    "sg:website":"www.insnetw.com",
    "wof:name":"INSURANCE Networking Systems",
    "wof:placetype":"venue"
},
  "geometry": {"coordinates":[-93.6544,41.585769],"type":"Point"}
}