{
  "type": "Feature",
  "properties": {
    "iso:country":"US",
    "sg:address":"1307 SW 7th St",
    "sg:city":"Atlantic",
    "sg:classifiers":[
        {
            "category":"Building & Trades",
            "subcategory":"Construction",
            "type":"Services"
        }
    ],
    "sg:phone":"+1 712 243 2981",
    "sg:postcode":"50022",
    "sg:province":"IA",
    "sg:tags":[
        "roofing",
        "contractor"
    ],
    "sg:website":"www.mcdermottroofing.com",
    "wof:name":"Mc Dermott & Son",
    "wof:placetype":"venue"
},
  "geometry": {"coordinates":[-95.031947,41.397896],"type":"Point"}
}