{
  "type": "Feature",
  "properties": {
    "iso:country":"US",
    "sg:address":"107 N Main St",
    "sg:city":"Rake",
    "sg:classifiers":[
        {
            "category":"Building & Trades",
            "subcategory":"Construction",
            "type":"Services"
        }
    ],
    "sg:phone":"+1 641 566 3582",
    "sg:postcode":"50482",
    "sg:province":"IA",
    "sg:tags":[
        "water",
        "well",
        "drilling"
    ],
    "wof:name":"Arnie's Pump Svc & Well",
    "wof:placetype":"venue"
},
  "geometry": {"coordinates":[-93.477626,43.128246],"type":"Point"}
}