{
  "type": "Feature",
  "properties": {
    "iso:country":"US",
    "sg:address":"214 E Market St",
    "sg:city":"Iowa City",
    "sg:classifiers":[
        {
            "category":"Restaurant",
            "type":"Food & Drink"
        }
    ],
    "sg:menulink":"http://www.allmenus.com/ia/iowa-city/17638-pizza-pit/menu/",
    "sg:phone":"+1 319 354 1111",
    "sg:postcode":"52245",
    "sg:province":"IA",
    "sg:tags":[
        "american",
        "pizza"
    ],
    "wof:name":"Pizza Pit",
    "wof:placetype":"venue"
},
  "geometry": {"coordinates":[-91.532841,41.663559],"type":"Point"}
}