{
  "type": "Feature",
  "properties": {
    "iso:country":"US",
    "sg:address":"1809 Landmark Ave",
    "sg:city":"Ida Grove",
    "sg:classifiers":[
        {
            "category":"Real Estate",
            "subcategory":"Real Estate Operator",
            "type":"Services"
        }
    ],
    "sg:phone":"+1 712 364 2713",
    "sg:postcode":"51445",
    "sg:province":"IA",
    "sg:tags":[
        "property",
        "lessor"
    ],
    "wof:name":"Charles Phelps",
    "wof:placetype":"venue"
},
  "geometry": {"coordinates":[-95.438749,42.44098],"type":"Point"}
}