{
  "type": "Feature",
  "properties": {
    "iso:country":"US",
    "sg:address":"20568 190th St",
    "sg:city":"Akron",
    "sg:phone":"+1 712 568 2709",
    "sg:postcode":"51001",
    "sg:province":"IA",
    "sg:tags":[
        "beef",
        "farm",
        "corn",
        "soybean",
        "cattle",
        "feedlot"
    ],
    "wof:name":"Alan Lucken",
    "wof:placetype":"venue"
},
  "geometry": {"coordinates":[-96.418891,42.778856],"type":"Point"}
}