{
  "type": "Feature",
  "properties": {
    "iso:country":"US",
    "sg:address":"1230 25th St",
    "sg:city":"Bettendorf",
    "sg:classifiers":[
        {
            "category":"Retail",
            "subcategory":"Repair Shop",
            "type":"Services"
        }
    ],
    "sg:phone":"+1 563 355 7513",
    "sg:postcode":"52722",
    "sg:province":"IA",
    "sg:tags":[
        "appliance"
    ],
    "wof:name":"Dennis' Appliance Repair",
    "wof:placetype":"venue"
},
  "geometry": {"coordinates":[-90.498762,41.533331],"type":"Point"}
}