{
  "type": "Feature",
  "properties": {
    "iso:country":"US",
    "sg:address":"3339 Hickory Ave",
    "sg:city":"Adair",
    "sg:classifiers":[
        {
            "category":"Manufacturing",
            "subcategory":"Retail Goods",
            "type":"Manufacturing & Wholesale Goods"
        }
    ],
    "sg:phone":"+1 641 742 3059",
    "sg:postcode":"50002",
    "sg:province":"IA",
    "sg:tags":[
        "product",
        "mfg"
    ],
    "wof:name":"Hillside Novelty Candles",
    "wof:placetype":"venue"
},
  "geometry": {"coordinates":[-94.60518999999999,41.528415],"type":"Point"}
}