{
  "type": "Feature",
  "properties": {
    "iso:country":"US",
    "sg:address":"827 Cedar Rd",
    "sg:city":"Portsmouth",
    "sg:phone":"+1 712 743 3450",
    "sg:postcode":"51565",
    "sg:province":"IA",
    "sg:tags":[
        "farm",
        "corn",
        "soybean"
    ],
    "wof:name":"Kaufman Farm",
    "wof:placetype":"venue"
},
  "geometry": {"coordinates":[-95.518686,41.619364],"type":"Point"}
}