{
  "type": "Feature",
  "properties": {
    "iso:country":"US",
    "sg:address":"117 W Center St",
    "sg:city":"Monona",
    "sg:classifiers":[
        {
            "category":"Insurance",
            "subcategory":"Insurance Agent",
            "type":"Services"
        }
    ],
    "sg:phone":"+1 563 539 2185",
    "sg:postcode":"52159",
    "sg:province":"IA",
    "wof:name":"Bruns & James Insurance",
    "wof:placetype":"venue"
},
  "geometry": {"coordinates":[-91.39000799999999,43.052864],"type":"Point"}
}