{
  "type": "Feature",
  "properties": {
    "iso:country":"US",
    "sg:address":"4685 NE 14th St",
    "sg:city":"Des Moines",
    "sg:classifiers":[
        {
            "category":"Travel",
            "subcategory":"Hotels & Motels",
            "type":"Entertainment"
        }
    ],
    "sg:phone":"+1 515 265 5671",
    "sg:postcode":"50313",
    "sg:province":"IA",
    "sg:website":"www.ramada.com",
    "wof:name":"14th St Inn",
    "wof:placetype":"venue"
},
  "geometry": {"coordinates":[-93.600448,41.64483],"type":"Point"}
}