{
  "type": "Feature",
  "properties": {
    "iso:country":"US",
    "sg:address":"2609 2nd Ave",
    "sg:city":"Muscatine",
    "sg:classifiers":[
        {
            "category":"Cinema",
            "subcategory":"Movie Rental",
            "type":"Entertainment"
        }
    ],
    "sg:phone":"+1 563 263 5095",
    "sg:postcode":"52761",
    "sg:province":"IA",
    "sg:tags":[
        "video",
        "tape"
    ],
    "wof:name":"Blockbuster",
    "wof:placetype":"venue"
},
  "geometry": {"coordinates":[-91.03521499999999,41.450726],"type":"Point"}
}