{
  "type": "Feature",
  "properties": {
    "iso:country":"US",
    "sg:address":"1826 Jefferson St",
    "sg:city":"Waterloo",
    "sg:classifiers":[
        {
            "category":"Retail",
            "subcategory":"Auto Repair",
            "type":"Services"
        }
    ],
    "sg:phone":"+1 319 235 9106",
    "sg:postcode":"50702",
    "sg:province":"IA",
    "sg:tags":[
        "body",
        "automobile",
        "painting"
    ],
    "wof:name":"John's Auto Body",
    "wof:placetype":"venue"
},
  "geometry": {"coordinates":[-92.32723799999999,42.485452],"type":"Point"}
}