{
  "type": "Feature",
  "properties": {
    "iso:country":"US",
    "sg:address":"821 N High St",
    "sg:city":"Elkader",
    "sg:classifiers":[
        {
            "category":"Sports & Exercise",
            "subcategory":"Bowling",
            "type":"Entertainment"
        }
    ],
    "sg:phone":"+1 563 245 2460",
    "sg:postcode":"52043",
    "sg:province":"IA",
    "sg:tags":[
        "center"
    ],
    "wof:name":"C J Lanes LTD",
    "wof:placetype":"venue"
},
  "geometry": {"coordinates":[-91.40164799999999,42.862146],"type":"Point"}
}