{
  "type": "Feature",
  "properties": {
    "iso:country":"US",
    "sg:address":"3000 McKinley Ave",
    "sg:city":"Des Moines",
    "sg:classifiers":[
        {
            "category":"Government",
            "subcategory":"Office",
            "type":"Public Place"
        }
    ],
    "sg:phone":"+1 515 287 4620",
    "sg:postcode":"50321",
    "sg:province":"IA",
    "sg:tags":[
        "federal"
    ],
    "wof:name":"US Air Traffic Control",
    "wof:placetype":"venue"
},
  "geometry": {"coordinates":[-93.653128,41.540906],"type":"Point"}
}