{
  "type": "Feature",
  "properties": {
    "addr:full":"400 Main St Ames IA 50010",
    "addr:housenumber":"400",
    "addr:postcode":"50010",
    "addr:street":"Main St",
    "iso:country":"US",
    "sg:address":"400 Main St",
    "sg:city":"Ames",
    "sg:classifiers":[
        {
            "category":"Restaurant",
            "type":"Food & Drink"
        }
    ],
    "sg:menulink":"http://www.allmenus.com/ia/ames/270630-lucullans-restaraunt/menu/",
    "sg:phone":"+1 515 232 8484",
    "sg:postcode":"50010",
    "sg:province":"IA",
    "sg:tags":[
        "italian"
    ],
    "wof:name":"Lucullans Restaraunt",
    "wof:placetype":"venue"
},
  "geometry": {"coordinates":[-93.615521,42.02497],"type":"Point"}
}