{
  "type": "Feature",
  "properties": {
    "iso:country":"US",
    "sg:address":"17674 Kestrel Ave",
    "sg:city":"Le Mars",
    "sg:phone":"+1 712 533 6178",
    "sg:postcode":"51031",
    "sg:province":"IA",
    "sg:tags":[
        "farm",
        "corn",
        "soybean"
    ],
    "wof:name":"Hanno Hilltop Farm Inc",
    "wof:placetype":"venue"
},
  "geometry": {"coordinates":[-96.233053,42.797721],"type":"Point"}
}