{
  "type": "Feature",
  "properties": {
    "iso:country":"US",
    "sg:address":"10437 Hickman Rd",
    "sg:city":"Des Moines",
    "sg:classifiers":[
        {
            "category":"Shopping",
            "subcategory":"Gifts & Souvenirs",
            "type":"Retail Goods"
        }
    ],
    "sg:phone":"+1 515 252 0006",
    "sg:postcode":"50322",
    "sg:province":"IA",
    "sg:tags":[
        "shop"
    ],
    "wof:name":"Gathering Place",
    "wof:placetype":"venue"
},
  "geometry": {"coordinates":[-93.763857,41.615015],"type":"Point"}
}