{
  "type": "Feature",
  "properties": {
    "iso:country":"US",
    "sg:address":"231 5th Ave N",
    "sg:city":"Fort Dodge",
    "sg:classifiers":[
        {
            "category":"Food & Beverages",
            "subcategory":"Groceries & Convenience Stores",
            "type":"Retail Goods"
        }
    ],
    "sg:phone":"+1 515 576 7026",
    "sg:postcode":"50501",
    "sg:province":"IA",
    "wof:name":"Dale's Corner Store",
    "wof:placetype":"venue"
},
  "geometry": {"coordinates":[-94.19678,42.509722],"type":"Point"}
}