{
  "type": "Feature",
  "properties": {
    "iso:country":"US",
    "sg:address":"315 E 5th St",
    "sg:city":"Des Moines",
    "sg:classifiers":[
        {
            "category":"Manufacturing",
            "subcategory":"Printing",
            "type":"Manufacturing & Wholesale Goods"
        }
    ],
    "sg:phone":"+1 515 243 0138",
    "sg:postcode":"50309",
    "sg:province":"IA",
    "sg:tags":[
        "newspaper"
    ],
    "wof:name":"Lee Enterprises News Bureau",
    "wof:placetype":"venue"
},
  "geometry": {"coordinates":[-93.611119,41.589529],"type":"Point"}
}