{
  "type": "Feature",
  "properties": {
    "iso:country":"US",
    "sg:address":"21765 196th",
    "sg:city":"Sigourney",
    "sg:classifiers":[
        {
            "category":"Farming",
            "subcategory":"Fish & Marine Products",
            "type":"Manufacturing & Wholesale Goods"
        }
    ],
    "sg:phone":"+1 641 622 3318",
    "sg:postcode":"52591",
    "sg:province":"IA",
    "sg:tags":[
        "preserves",
        "fishing",
        "hunting"
    ],
    "wof:name":"Oakwood Sporting Resort",
    "wof:placetype":"venue"
},
  "geometry": {"coordinates":[-92.194861,41.369571],"type":"Point"}
}