{
  "type": "Feature",
  "properties": {
    "iso:country":"US",
    "sg:address":"5678 NE 14th St",
    "sg:city":"Des Moines",
    "sg:classifiers":[
        {
            "category":"Autos & Motor Vehicles",
            "subcategory":"Recreational Vehicle Sales",
            "type":"Retail Goods"
        }
    ],
    "sg:phone":"+1 515 265 9901",
    "sg:postcode":"50313",
    "sg:province":"IA",
    "sg:tags":[
        "canopy",
        "shell",
        "truck",
        "cap"
    ],
    "sg:website":"www.inlandtruck.com",
    "wof:name":"Inland Truck Parts & Svc",
    "wof:placetype":"venue"
},
  "geometry": {"coordinates":[-93.600858,41.668542],"type":"Point"}
}