{
  "type": "Feature",
  "properties": {
    "addr:full":"405 N Hazel St Glenwood IA 51534",
    "addr:housenumber":"405",
    "addr:postcode":"51534",
    "addr:street":"N Hazel St",
    "iso:country":"US",
    "sg:address":"405 N Hazel St",
    "sg:city":"Glenwood",
    "sg:classifiers":[
        {
            "category":"Personal",
            "subcategory":"Beauty Salon",
            "type":"Services"
        }
    ],
    "sg:phone":"+1 712 527 2186",
    "sg:postcode":"51534",
    "sg:province":"IA",
    "sg:tags":[
        "shop"
    ],
    "wof:name":"Doni's Home Styling",
    "wof:placetype":"venue"
},
  "geometry": {"coordinates":[-95.74636,41.05159],"type":"Point"}
}