{
  "type": "Feature",
  "properties": {
    "iso:country":"US",
    "sg:address":"2551 Holiday Rd",
    "sg:city":"Coralville",
    "sg:classifiers":[
        {
            "category":"Real Estate",
            "subcategory":"Real Estate Operator",
            "type":"Services"
        }
    ],
    "sg:phone":"+1 319 339 1509",
    "sg:postcode":"52241",
    "sg:province":"IA",
    "sg:tags":[
        "apartment"
    ],
    "sg:website":"www.barkerapartments.com",
    "wof:name":"Knollridge Garden Apartments",
    "wof:placetype":"venue"
},
  "geometry": {"coordinates":[-91.60629,41.700422],"type":"Point"}
}