{
  "type": "Feature",
  "properties": {
    "iso:country":"US",
    "sg:address":"10418 Jubilee Rd",
    "sg:city":"La Porte City",
    "sg:classifiers":[
        {
            "category":"Farming",
            "subcategory":"Farm & Veterinary Services",
            "type":"Manufacturing & Wholesale Goods"
        }
    ],
    "sg:phone":"+1 319 342 3716",
    "sg:postcode":"50651",
    "sg:province":"IA",
    "sg:tags":[
        "breeder",
        "livestock"
    ],
    "wof:name":"Roco Farms",
    "wof:placetype":"venue"
},
  "geometry": {"coordinates":[-92.136483,42.384484],"type":"Point"}
}