{
  "type": "Feature",
  "properties": {
    "iso:country":"US",
    "sg:address":"36 W Skillet Ave",
    "sg:city":"Dayton",
    "sg:classifiers":[
        {
            "category":"Education",
            "subcategory":"Library",
            "type":"Public Place"
        }
    ],
    "sg:phone":"+1 515 547 2700",
    "sg:postcode":"50530",
    "sg:province":"IA",
    "wof:name":"Dayton City Library",
    "wof:placetype":"venue"
},
  "geometry": {"coordinates":[-94.068855,42.261442],"type":"Point"}
}