{
  "type": "Feature",
  "properties": {
    "iso:country":"US",
    "sg:address":"415 10th St",
    "sg:city":"Sioux City",
    "sg:classifiers":[
        {
            "category":"Personal",
            "subcategory":"Barber",
            "type":"Services"
        }
    ],
    "sg:phone":"+1 712 277 4541",
    "sg:postcode":"51105",
    "sg:province":"IA",
    "sg:tags":[
        "shop"
    ],
    "wof:name":"Sydney Apartment Barber Shop",
    "wof:placetype":"venue"
},
  "geometry": {"coordinates":[-96.40590400000001,42.500752],"type":"Point"}
}