{
  "type": "Feature",
  "properties": {
    "iso:country":"US",
    "sg:address":"3933 Marquette St",
    "sg:city":"Davenport",
    "sg:classifiers":[
        {
            "category":"Real Estate",
            "subcategory":"Architect",
            "type":"Services"
        }
    ],
    "sg:phone":"+1 563 386 9161",
    "sg:postcode":"52806",
    "sg:province":"IA",
    "sg:tags":[
        "architects'",
        "specification",
        "builders'",
        "construction",
        "architectural",
        "engineer"
    ],
    "wof:name":"Larrison & Assoc Architects Pc",
    "wof:placetype":"venue"
},
  "geometry": {"coordinates":[-90.591014,41.561078],"type":"Point"}
}