{
  "type": "Feature",
  "properties": {
    "addr:full":"751 Jewell Dr Knoxville IA 50138",
    "addr:housenumber":"751",
    "addr:postcode":"50138",
    "addr:street":"Jewell Dr",
    "iso:country":"US",
    "sg:address":"751 Jewell Dr",
    "sg:city":"Knoxville",
    "sg:classifiers":[
        {
            "category":"Farming",
            "subcategory":"Livestock Farm",
            "type":"Manufacturing & Wholesale Goods"
        }
    ],
    "sg:phone":"+1 641 842 2560",
    "sg:postcode":"50138",
    "sg:province":"IA",
    "sg:tags":[
        "feedlot",
        "corn",
        "soybean",
        "beef",
        "cattle"
    ],
    "wof:name":"Bill Hughs Farm",
    "wof:placetype":"venue"
},
  "geometry": {"coordinates":[-93.191306,41.356659],"type":"Point"}
}