{
  "type": "Feature",
  "properties": {
    "iso:country":"US",
    "sg:address":"3234 Center Point Rd NE",
    "sg:city":"Cedar Rapids",
    "sg:classifiers":[
        {
            "category":"Restaurant",
            "type":"Food & Drink"
        }
    ],
    "sg:phone":"+1 319 364 4313",
    "sg:postcode":"52402",
    "sg:province":"IA",
    "sg:tags":[
        "pizza"
    ],
    "wof:name":"Tomaso's Pizza",
    "wof:placetype":"venue"
},
  "geometry": {"coordinates":[-91.66390199999999,42.012299],"type":"Point"}
}