{
  "type": "Feature",
  "properties": {
    "iso:country":"US",
    "sg:address":"1432 220th St",
    "sg:city":"Creston",
    "sg:phone":"+1 641 782 5318",
    "sg:postcode":"50801",
    "sg:province":"IA",
    "sg:tags":[
        "farm",
        "grain",
        "cash"
    ],
    "wof:name":"Stephen Weese Farm",
    "wof:placetype":"venue"
},
  "geometry": {"coordinates":[-94.378491,40.985033],"type":"Point"}
}