{
  "type": "Feature",
  "properties": {
    "iso:country":"US",
    "sg:address":"329 Washington St",
    "sg:city":"Audubon",
    "sg:classifiers":[
        {
            "category":"Restaurant",
            "type":"Food & Drink"
        }
    ],
    "sg:phone":"+1 712 563 3319",
    "sg:postcode":"50025",
    "sg:province":"IA",
    "sg:tags":[
        "caterer"
    ],
    "wof:name":"Simply Sweet Catering",
    "wof:placetype":"venue"
},
  "geometry": {"coordinates":[-94.932739,41.720505],"type":"Point"}
}