{
  "type": "Feature",
  "properties": {
    "addr:full":"1 S 3rd Ave Marshalltown IA 50158",
    "addr:housenumber":"1",
    "addr:postcode":"50158",
    "addr:street":"S 3Rd Ave",
    "iso:country":"US",
    "sg:address":"1 S 3rd Ave",
    "sg:city":"Marshalltown",
    "sg:classifiers":[
        {
            "category":"Manufacturing",
            "subcategory":"Glass & Minerals",
            "type":"Manufacturing & Wholesale Goods"
        }
    ],
    "sg:phone":"+1 641 752 1597",
    "sg:postcode":"50158",
    "sg:province":"IA",
    "sg:tags":[
        "concrete",
        "brick",
        "prod",
        "block"
    ],
    "wof:name":"Marquart Block Co",
    "wof:placetype":"venue"
},
  "geometry": {"coordinates":[-92.908024,42.049164],"type":"Point"}
}