{
  "type": "Feature",
  "properties": {
    "addr:full":"101 N Downey St West Branch IA 52358",
    "addr:housenumber":"101",
    "addr:postcode":"52358",
    "addr:street":"N Downey St",
    "iso:country":"US",
    "sg:address":"101 N Downey St",
    "sg:city":"West Branch",
    "sg:classifiers":[
        {
            "category":"Insurance",
            "subcategory":"Insurance Agent",
            "type":"Services"
        }
    ],
    "sg:phone":"+1 319 643 5525",
    "sg:postcode":"52358",
    "sg:province":"IA",
    "wof:name":"Springdale Agency",
    "wof:placetype":"venue"
},
  "geometry": {"coordinates":[-91.346615,41.672523],"type":"Point"}
}