{
  "type": "Feature",
  "properties": {
    "addr:full":"1203 Noble Hills Pl Boone IA 50036",
    "addr:housenumber":"1203",
    "addr:postcode":"50036",
    "addr:street":"Noble Hills Pl",
    "iso:country":"US",
    "sg:address":"1203 Noble Hills Pl",
    "sg:city":"Boone",
    "sg:classifiers":[
        {
            "category":"Recreation",
            "type":"Entertainment"
        }
    ],
    "sg:phone":"+1 515 432 7772",
    "sg:postcode":"50036",
    "sg:province":"IA",
    "sg:tags":[
        "club",
        "membership"
    ],
    "wof:name":"Boone County Sportsmens Club",
    "wof:placetype":"venue"
},
  "geometry": {"coordinates":[-93.900459,42.033949],"type":"Point"}
}