{
  "type": "Feature",
  "properties": {
    "addr:full":"8 E 2nd St Kingsley IA 51028",
    "addr:housenumber":"8",
    "addr:postcode":"51028",
    "addr:street":"E 2Nd St",
    "iso:country":"US",
    "sg:address":"8 E 2nd St",
    "sg:city":"Kingsley",
    "sg:classifiers":[
        {
            "category":"Shopping",
            "subcategory":"Clothing, Apparel, & Fashions",
            "type":"Retail Goods"
        }
    ],
    "sg:phone":"+1 712 378 2788",
    "sg:postcode":"51028",
    "sg:province":"IA",
    "wof:name":"Fashion Shoppe",
    "wof:placetype":"venue"
},
  "geometry": {"coordinates":[-95.967254,42.588115],"type":"Point"}
}