{
  "type": "Feature",
  "properties": {
    "iso:country":"US",
    "sg:address":"3601 Douglas Ave",
    "sg:city":"Des Moines",
    "sg:classifiers":[
        {
            "category":"Health Services",
            "subcategory":"Health Practitioner",
            "type":"Services"
        }
    ],
    "sg:phone":"+1 515 277 2126",
    "sg:postcode":"50310",
    "sg:province":"IA",
    "wof:name":"College of Mssage Healing Arts",
    "wof:placetype":"venue"
},
  "geometry": {"coordinates":[-93.66720599999999,41.629532],"type":"Point"}
}