{
  "type": "Feature",
  "properties": {
    "iso:country":"US",
    "sg:address":"1027 Cress Pkwy",
    "sg:city":"Hiawatha",
    "sg:classifiers":[
        {
            "category":"Shopping",
            "type":"Retail Goods"
        }
    ],
    "sg:phone":"+1 319 395 7296",
    "sg:postcode":"52233",
    "sg:province":"IA",
    "sg:tags":[
        "merchandise"
    ],
    "wof:name":"Lee Electronics",
    "wof:placetype":"venue"
},
  "geometry": {"coordinates":[-91.68632100000001,42.03978],"type":"Point"}
}