{
  "type": "Feature",
  "properties": {
    "iso:country":"US",
    "sg:address":"411 Oak Dr",
    "sg:city":"Postville",
    "sg:classifiers":[
        {
            "category":"Government",
            "subcategory":"Police Station",
            "type":"Public Place"
        }
    ],
    "sg:phone":"+1 563 864 3234",
    "sg:postcode":"52162",
    "sg:province":"IA",
    "sg:tags":[
        "department"
    ],
    "wof:name":"Postville Police Dept Office",
    "wof:placetype":"venue"
},
  "geometry": {"coordinates":[-91.56146200000001,43.082524],"type":"Point"}
}