{
  "type": "Feature",
  "properties": {
    "iso:country":"US",
    "sg:address":"2126 Hickory Ln",
    "sg:city":"Cedar Falls",
    "sg:classifiers":[
        {
            "category":"Professional",
            "subcategory":"Accounting & Tax Preparation",
            "type":"Services"
        }
    ],
    "sg:phone":"+1 319 268 1473",
    "sg:postcode":"50613",
    "sg:province":"IA",
    "sg:tags":[
        "return"
    ],
    "wof:name":"Hickory Tax Service Inc",
    "wof:placetype":"venue"
},
  "geometry": {"coordinates":[-92.420023,42.518399],"type":"Point"}
}