{
  "type": "Feature",
  "properties": {
    "iso:country":"US",
    "sg:address":"100 W 2nd St",
    "sg:city":"Atlantic",
    "sg:classifiers":[
        {
            "category":"Autos & Motor Vehicles",
            "subcategory":"Auto Supplies",
            "type":"Retail Goods"
        }
    ],
    "sg:phone":"+1 712 243 4413",
    "sg:postcode":"50022",
    "sg:province":"IA",
    "sg:tags":[
        "tire"
    ],
    "wof:name":"Mc Atee Tire & Muffler",
    "wof:placetype":"venue"
},
  "geometry": {"coordinates":[-95.015016,41.409017],"type":"Point"}
}