{
  "type": "Feature",
  "properties": {
    "iso:country":"US",
    "sg:address":"702 13th Ave",
    "sg:city":"Camanche",
    "sg:classifiers":[
        {
            "category":"Education",
            "subcategory":"School",
            "type":"Public Place"
        }
    ],
    "sg:phone":"+1 563 259 3000",
    "sg:postcode":"52730",
    "sg:province":"IA",
    "wof:name":"Camanche Superintendents Ofc",
    "wof:placetype":"venue"
},
  "geometry": {"coordinates":[-90.259045,41.785851],"type":"Point"}
}