{
  "type": "Feature",
  "properties": {
    "iso:country":"US",
    "sg:address":"320 6th Ave",
    "sg:city":"Grinnell",
    "sg:classifiers":[
        {
            "category":"Shopping",
            "subcategory":"Pharmacy",
            "type":"Retail Goods"
        }
    ],
    "sg:phone":"+1 641 236 3663",
    "sg:postcode":"50112",
    "sg:province":"IA",
    "wof:name":"Medicap Pharmacy",
    "wof:placetype":"venue"
},
  "geometry": {"coordinates":[-92.73299,41.746074],"type":"Point"}
}