{
  "type": "Feature",
  "properties": {
    "addr:full":"429 Main St Keokuk IA 52632",
    "addr:housenumber":"429",
    "addr:postcode":"52632",
    "addr:street":"Main St",
    "iso:country":"US",
    "sg:address":"429 Main St",
    "sg:city":"Keokuk",
    "sg:classifiers":[
        {
            "category":"Insurance",
            "subcategory":"Insurance Agent",
            "type":"Services"
        }
    ],
    "sg:phone":"+1 319 524 2421",
    "sg:postcode":"52632",
    "sg:province":"IA",
    "wof:name":"Lofton Stebbings & Sohl Inc",
    "wof:placetype":"venue"
},
  "geometry": {"coordinates":[-91.383022,40.395593],"type":"Point"}
}