{
  "type": "Feature",
  "properties": {
    "iso:country":"US",
    "sg:address":"611 Locust Rd",
    "sg:city":"Decorah",
    "sg:classifiers":[
        {
            "category":"Personal",
            "subcategory":"Beauty Salon",
            "type":"Services"
        }
    ],
    "sg:phone":"+1 563 387 0855",
    "sg:postcode":"52101",
    "sg:province":"IA",
    "sg:tags":[
        "shop"
    ],
    "wof:name":"Exclusively Yours Salon",
    "wof:placetype":"venue"
},
  "geometry": {"coordinates":[-91.79431599999999,43.311141],"type":"Point"}
}