{
  "type": "Feature",
  "properties": {
    "iso:country":"US",
    "sg:address":"2321 Laredo Trl",
    "sg:city":"Adel",
    "sg:classifiers":[
        {
            "category":"Professional",
            "type":"Services"
        }
    ],
    "sg:phone":"+1 515 677 2411",
    "sg:postcode":"50003",
    "sg:province":"IA",
    "sg:tags":[
        "establishment"
    ],
    "wof:name":"Wright Farm Shop",
    "wof:placetype":"venue"
},
  "geometry": {"coordinates":[-94.057343,41.699912],"type":"Point"}
}