{
  "type": "Feature",
  "properties": {
    "iso:country":"US",
    "sg:address":"2729 W South Omaha Brg Rd",
    "sg:city":"Council Bluffs",
    "sg:classifiers":[
        {
            "category":"Travel",
            "subcategory":"Hotels & Motels",
            "type":"Entertainment"
        }
    ],
    "sg:phone":"+1 712 366 0547",
    "sg:postcode":"51501",
    "sg:province":"IA",
    "wof:name":"Bart's Motel",
    "wof:placetype":"venue"
},
  "geometry": {"coordinates":[-95.886002,41.216202],"type":"Point"}
}