{
  "type": "Feature",
  "properties": {
    "iso:country":"US",
    "sg:address":"708 5th St",
    "sg:city":"Sully",
    "sg:classifiers":[
        {
            "category":"Building & Trades",
            "subcategory":"Construction",
            "type":"Services"
        }
    ],
    "sg:phone":"+1 641 594 4340",
    "sg:postcode":"50251",
    "sg:province":"IA",
    "sg:tags":[
        "general",
        "contractor"
    ],
    "wof:name":"Sully Construction Inc",
    "wof:placetype":"venue"
},
  "geometry": {"coordinates":[-92.846009,41.577196],"type":"Point"}
}