{
  "type": "Feature",
  "properties": {
    "addr:full":"814 6th Ave De Witt IA 52742",
    "addr:housenumber":"814",
    "addr:postcode":"52742",
    "addr:street":"6Th Ave De",
    "iso:country":"US",
    "sg:address":"814 6th Ave",
    "sg:city":"De Witt",
    "sg:classifiers":[
        {
            "category":"Retail",
            "subcategory":"Portrait Studio",
            "type":"Services"
        }
    ],
    "sg:phone":"+1 563 659 5221",
    "sg:postcode":"52742",
    "sg:province":"IA",
    "sg:tags":[
        "photographer"
    ],
    "wof:name":"William Luse Photography",
    "wof:placetype":"venue"
},
  "geometry": {"coordinates":[-90.53889599999999,41.824094],"type":"Point"}
}