{
  "type": "Feature",
  "properties": {
    "iso:country":"US",
    "sg:address":"7046 310th St",
    "sg:city":"Hartley",
    "sg:phone":"+1 712 728 2495",
    "sg:postcode":"51346",
    "sg:province":"IA",
    "sg:tags":[
        "farm",
        "corn",
        "soybean"
    ],
    "wof:name":"Alan Jatho",
    "wof:placetype":"venue"
},
  "geometry": {"coordinates":[-95.399461,43.198733],"type":"Point"}
}