{
  "type": "Feature",
  "properties": {
    "iso:country":"US",
    "sg:address":"1202 Broadway",
    "sg:city":"Denison",
    "sg:classifiers":[
        {
            "category":"Government",
            "subcategory":"Office",
            "type":"Public Place"
        }
    ],
    "sg:phone":"+1 712 263 3340",
    "sg:postcode":"51442",
    "sg:province":"IA",
    "sg:tags":[
        "county"
    ],
    "wof:name":"Crawford County Supervisors",
    "wof:placetype":"venue"
},
  "geometry": {"coordinates":[-95.35677800000001,42.016821],"type":"Point"}
}