{
  "type": "Feature",
  "properties": {
    "iso:country":"US",
    "sg:address":"532 N Dodge St",
    "sg:city":"Iowa City",
    "sg:classifiers":[
        {
            "category":"Shopping",
            "type":"Retail Goods"
        }
    ],
    "sg:phone":"+1 319 337 6893",
    "sg:postcode":"52245",
    "sg:province":"IA",
    "sg:tags":[
        "religious"
    ],
    "wof:name":"Mustardseed Catholic Books",
    "wof:placetype":"venue"
},
  "geometry": {"coordinates":[-91.525615,41.667574],"type":"Point"}
}