{
  "type": "Feature",
  "properties": {
    "addr:full":"2076 220th St Independence IA 50644",
    "addr:housenumber":"2076",
    "addr:postcode":"50644",
    "addr:street":"220Th St",
    "iso:country":"US",
    "sg:address":"2076 220th St",
    "sg:city":"Independence",
    "sg:classifiers":[
        {
            "category":"Mining & Drilling",
            "type":"Manufacturing & Wholesale Goods"
        }
    ],
    "sg:phone":"+1 319 334 4292",
    "sg:postcode":"50644",
    "sg:province":"IA",
    "sg:tags":[
        "limestone"
    ],
    "wof:name":"Bruening Rock Products Inc",
    "wof:placetype":"venue"
},
  "geometry": {"coordinates":[-91.86159000000001,42.468686],"type":"Point"}
}