{
  "type": "Feature",
  "properties": {
    "iso:country":"US",
    "sg:address":"21831 Falcon Ave",
    "sg:city":"Wellsburg",
    "sg:phone":"+1 641 869 3375",
    "sg:postcode":"50680",
    "sg:province":"IA",
    "sg:tags":[
        "farm",
        "corn",
        "soybean"
    ],
    "wof:name":"Kenneth L Bunger",
    "wof:placetype":"venue"
},
  "geometry": {"coordinates":[-92.915266,42.387042],"type":"Point"}
}