{
  "type": "Feature",
  "properties": {
    "iso:country":"US",
    "sg:address":"3119 SW 30th St",
    "sg:city":"Des Moines",
    "sg:classifiers":[
        {
            "category":"Organizations",
            "subcategory":"Religious Organization",
            "type":"Services"
        }
    ],
    "sg:phone":"+1 515 244 5674",
    "sg:postcode":"50321",
    "sg:province":"IA",
    "sg:tags":[
        "church"
    ],
    "wof:name":"Des Moines First Friends Ch",
    "wof:placetype":"venue"
},
  "geometry": {"coordinates":[-93.657721,41.556566],"type":"Point"}
}