{
  "type": "Feature",
  "properties": {
    "iso:country":"US",
    "sg:address":"525 Hwy 1 S",
    "sg:city":"Washington",
    "sg:classifiers":[
        {
            "category":"Wholesale",
            "subcategory":"Farm Supplies",
            "type":"Manufacturing & Wholesale Goods"
        }
    ],
    "sg:phone":"+1 319 653 3928",
    "sg:postcode":"52353",
    "sg:province":"IA",
    "sg:tags":[
        "buyer",
        "livestock"
    ],
    "wof:name":"Jimmy Dean Foods",
    "wof:placetype":"venue"
},
  "geometry": {"coordinates":[-91.708055,41.296089],"type":"Point"}
}