{
  "type": "Feature",
  "properties": {
    "iso:country":"US",
    "sg:address":"2415 Westdale Dr SW",
    "sg:city":"Cedar Rapids",
    "sg:classifiers":[
        {
            "category":"Autos & Motor Vehicles",
            "subcategory":"Motorcycle Sales",
            "type":"Retail Goods"
        }
    ],
    "sg:phone":"+1 319 362 9496",
    "sg:postcode":"52404",
    "sg:province":"IA",
    "wof:name":"Metro Suzuki Harley Davidson",
    "wof:placetype":"venue"
},
  "geometry": {"coordinates":[-91.721802,41.954498],"type":"Point"}
}