{
  "type": "Feature",
  "properties": {
    "iso:country":"US",
    "sg:address":"815 N Compton Dr",
    "sg:city":"Hiawatha",
    "sg:classifiers":[
        {
            "category":"Retail",
            "subcategory":"Photofinishing",
            "type":"Services"
        }
    ],
    "sg:phone":"+1 319 393 1561",
    "sg:postcode":"52233",
    "sg:province":"IA",
    "sg:tags":[
        "photo",
        "finishing"
    ],
    "wof:name":"Color Pro Digital",
    "wof:placetype":"venue"
},
  "geometry": {"coordinates":[-91.691445,42.045481],"type":"Point"}
}