{
  "type": "Feature",
  "properties": {
    "iso:country":"US",
    "sg:address":"2120 S 11th St",
    "sg:city":"Fort Dodge",
    "sg:classifiers":[
        {
            "category":"Wholesale",
            "subcategory":"Scrap",
            "type":"Manufacturing & Wholesale Goods"
        }
    ],
    "sg:phone":"+1 515 573 5904",
    "sg:postcode":"50501",
    "sg:province":"IA",
    "sg:tags":[
        "metal",
        "iron"
    ],
    "wof:name":"D & L Metal Recycling",
    "wof:placetype":"venue"
},
  "geometry": {"coordinates":[-94.18243,42.476822],"type":"Point"}
}