{
  "type": "Feature",
  "properties": {
    "addr:full":"5722 22nd Ave Trl Vinton IA 52349",
    "addr:housenumber":"5722",
    "addr:postcode":"52349",
    "addr:street":"22Nd Ave Trl",
    "iso:country":"US",
    "sg:address":"5722 22nd Ave Trl",
    "sg:city":"Vinton",
    "sg:classifiers":[
        {
            "category":"Building & Trades",
            "subcategory":"Construction",
            "type":"Services"
        }
    ],
    "sg:phone":"+1 319 472 2045",
    "sg:postcode":"52349",
    "sg:province":"IA",
    "sg:tags":[
        "concrete",
        "contractor"
    ],
    "wof:name":"KARR Mobile Concrete",
    "wof:placetype":"venue"
},
  "geometry": {"coordinates":[-92.050916,42.1928],"type":"Point"}
}