{
  "type": "Feature",
  "properties": {
    "addr:full":"616 State Hwy 9 Forest City IA 50436",
    "addr:housenumber":"616",
    "addr:postcode":"50436",
    "addr:street":"State Hwy 9",
    "iso:country":"US",
    "sg:address":"616 State Hwy 9",
    "sg:city":"Forest City",
    "sg:classifiers":[
        {
            "category":"Shopping",
            "subcategory":"Pharmacy",
            "type":"Retail Goods"
        }
    ],
    "sg:phone":"+1 641 582 2780",
    "sg:postcode":"50436",
    "sg:province":"IA",
    "wof:name":"Pamida Pharmacy",
    "wof:placetype":"venue"
},
  "geometry": {"coordinates":[-93.62681499999999,43.270326],"type":"Point"}
}