{
  "type": "Feature",
  "properties": {
    "addr:full":"428 Franklin St Waterloo IA 50703",
    "addr:housenumber":"428",
    "addr:postcode":"50703",
    "addr:street":"Franklin St",
    "iso:country":"US",
    "sg:address":"428 Franklin St",
    "sg:city":"Waterloo",
    "sg:classifiers":[
        {
            "category":"Restaurant",
            "type":"Food & Drink"
        }
    ],
    "sg:phone":"+1 319 233 4164",
    "sg:postcode":"50703",
    "sg:province":"IA",
    "sg:tags":[
        "parlor",
        "ice",
        "cream"
    ],
    "wof:name":"4 Queens Dairy Cream",
    "wof:placetype":"venue"
},
  "geometry": {"coordinates":[-92.334445,42.501456],"type":"Point"}
}