{
  "type": "Feature",
  "properties": {
    "iso:country":"US",
    "sg:address":"1619 2nd St",
    "sg:city":"Coralville",
    "sg:classifiers":[
        {
            "category":"Home & Garden",
            "subcategory":"Furniture",
            "type":"Retail Goods"
        }
    ],
    "sg:phone":"+1 319 351 1717",
    "sg:postcode":"52241",
    "sg:province":"IA",
    "wof:name":"Town & Country Home Furnishing",
    "wof:placetype":"venue"
},
  "geometry": {"coordinates":[-91.587157,41.677058],"type":"Point"}
}