{
  "type": "Feature",
  "properties": {
    "iso:country":"US",
    "sg:address":"600 W 6th St",
    "sg:city":"Wall Lake",
    "sg:classifiers":[
        {
            "category":"Health Services",
            "subcategory":"Nursing And Care Facility",
            "type":"Services"
        }
    ],
    "sg:phone":"+1 712 664 2488",
    "sg:postcode":"51466",
    "sg:province":"IA",
    "sg:tags":[
        "home",
        "convalescent"
    ],
    "wof:name":"Twilight Acres Homes",
    "wof:placetype":"venue"
},
  "geometry": {"coordinates":[-95.096586,42.27557],"type":"Point"}
}