{
  "type": "Feature",
  "properties": {
    "addr:full":"3264 270th St Marshalltown IA 50158",
    "addr:housenumber":"3264",
    "addr:postcode":"50158",
    "addr:street":"270Th St",
    "iso:country":"US",
    "sg:address":"3264 270th St",
    "sg:city":"Marshalltown",
    "sg:phone":"+1 641 479 2824",
    "sg:postcode":"50158",
    "sg:province":"IA",
    "sg:tags":[
        "farm",
        "corn",
        "soybean"
    ],
    "wof:name":"Hoover Farm",
    "wof:placetype":"venue"
},
  "geometry": {"coordinates":[-92.79311199999999,41.963516],"type":"Point"}
}