{
  "type": "Feature",
  "properties": {
    "iso:country":"US",
    "sg:address":"220 N Dodge St",
    "sg:city":"Algona",
    "sg:classifiers":[
        {
            "category":"Health Services",
            "subcategory":"Optometrist",
            "type":"Services"
        }
    ],
    "sg:phone":"+1 515 295 3743",
    "sg:postcode":"50511",
    "sg:province":"IA",
    "wof:name":"Algona Eye Clinic",
    "wof:placetype":"venue"
},
  "geometry": {"coordinates":[-94.23661800000001,43.070157],"type":"Point"}
}