{
  "type": "Feature",
  "properties": {
    "iso:country":"US",
    "sg:address":"609 Myatt Dr",
    "sg:city":"Maquoketa",
    "sg:classifiers":[
        {
            "category":"Building & Trades",
            "subcategory":"Construction",
            "type":"Services"
        }
    ],
    "sg:phone":"+1 563 652 3443",
    "sg:postcode":"52060",
    "sg:province":"IA",
    "sg:tags":[
        "general",
        "contractor"
    ],
    "wof:name":"Ken Moore Construction Inc",
    "wof:placetype":"venue"
},
  "geometry": {"coordinates":[-90.684674,42.060537],"type":"Point"}
}