{
  "type": "Feature",
  "properties": {
    "iso:country":"US",
    "sg:address":"409 N Fulton St",
    "sg:city":"Keota",
    "sg:classifiers":[
        {
            "category":"Freight",
            "type":"Transportation"
        }
    ],
    "sg:phone":"+1 641 636 3184",
    "sg:postcode":"52248",
    "sg:province":"IA",
    "sg:tags":[
        "livestock",
        "hauling"
    ],
    "wof:name":"Dill Trucking Inc",
    "wof:placetype":"venue"
},
  "geometry": {"coordinates":[-91.952084,41.366701],"type":"Point"}
}