{
  "type": "Feature",
  "properties": {
    "addr:full":"610 Kelling St Renwick IA 50577",
    "addr:housenumber":"610",
    "addr:postcode":"50577",
    "addr:street":"Kelling St",
    "iso:country":"US",
    "sg:address":"610 Kelling St",
    "sg:city":"Renwick",
    "sg:classifiers":[
        {
            "category":"Organizations",
            "subcategory":"Religious Organization",
            "type":"Services"
        }
    ],
    "sg:phone":"+1 515 824 3359",
    "sg:postcode":"50577",
    "sg:province":"IA",
    "sg:tags":[
        "church"
    ],
    "wof:name":"United Methodist Church",
    "wof:placetype":"venue"
},
  "geometry": {"coordinates":[-93.98130399999999,42.8289],"type":"Point"}
}