{
  "type": "Feature",
  "properties": {
    "addr:full":"327 Kirkwood Ave Iowa City IA 52240",
    "addr:housenumber":"327",
    "addr:postcode":"52240",
    "addr:street":"Kirkwood Ave",
    "iso:country":"US",
    "sg:address":"327 Kirkwood Ave",
    "sg:city":"Iowa City",
    "sg:classifiers":[
        {
            "category":"Professional",
            "subcategory":"Computer Services",
            "type":"Services"
        }
    ],
    "sg:phone":"+1 319 351 7549",
    "sg:postcode":"52240",
    "sg:province":"IA",
    "sg:website":"www.comp-sol.com",
    "wof:name":"Computer Solutions LTD",
    "wof:placetype":"venue"
},
  "geometry": {"coordinates":[-91.53107300000001,41.649372],"type":"Point"}
}