{
  "type": "Feature",
  "properties": {
    "addr:full":"808 5th Ave Des Moines IA 50309",
    "addr:housenumber":"808",
    "addr:postcode":"50309",
    "addr:street":"5Th Ave",
    "iso:country":"US",
    "sg:address":"808 5th Ave",
    "sg:city":"Des Moines",
    "sg:classifiers":[
        {
            "category":"Social Services",
            "type":"Services"
        }
    ],
    "sg:phone":"+1 515 244 2267",
    "sg:postcode":"50309",
    "sg:province":"IA",
    "sg:tags":[
        "guidance",
        "child"
    ],
    "wof:name":"Child Guidence Ctr",
    "wof:placetype":"venue"
},
  "geometry": {"coordinates":[-93.62451299999999,41.592734],"type":"Point"}
}