{
  "type": "Feature",
  "properties": {
    "addr:full":"78 South St Akron IA 51001",
    "addr:housenumber":"78",
    "addr:postcode":"51001",
    "addr:street":"South St",
    "iso:country":"US",
    "sg:address":"78 South St",
    "sg:city":"Akron",
    "sg:classifiers":[
        {
            "category":"Government",
            "subcategory":"Office",
            "type":"Public Place"
        }
    ],
    "sg:phone":"+1 712 568 2071",
    "sg:postcode":"51001",
    "sg:province":"IA",
    "sg:tags":[
        "state",
        "program"
    ],
    "wof:name":"Transportation Dept",
    "wof:placetype":"venue"
},
  "geometry": {"coordinates":[-96.561564,42.823029],"type":"Point"}
}