{
  "type": "Feature",
  "properties": {
    "addr:full":"806 River St Decorah IA 52101",
    "addr:housenumber":"806",
    "addr:postcode":"52101",
    "addr:street":"River St",
    "iso:country":"US",
    "sg:address":"806 River St",
    "sg:city":"Decorah",
    "sg:classifiers":[
        {
            "category":"Social Services",
            "type":"Services"
        }
    ],
    "sg:phone":"+1 563 382 9557",
    "sg:postcode":"52101",
    "sg:province":"IA",
    "sg:tags":[
        "senior",
        "citizen"
    ],
    "wof:name":"Decorah Senior Ctr",
    "wof:placetype":"venue"
},
  "geometry": {"coordinates":[-91.789732,43.296928],"type":"Point"}
}