{
  "type": "Feature",
  "properties": {
    "iso:country":"US",
    "sg:address":"1022 3rd Ave",
    "sg:city":"Alton",
    "sg:classifiers":[
        {
            "category":"Retail",
            "subcategory":"Repair Shop",
            "type":"Services"
        }
    ],
    "sg:phone":"+1 712 756 8996",
    "sg:postcode":"51003",
    "sg:province":"IA",
    "sg:tags":[
        "taxidermist"
    ],
    "wof:name":"J B's Taxidermy",
    "wof:placetype":"venue"
},
  "geometry": {"coordinates":[-96.010319,42.987438],"type":"Point"}
}