{
  "type": "Feature",
  "properties": {
    "iso:country":"US",
    "sg:address":"2428 H Ave",
    "sg:city":"Williamsburg",
    "sg:phone":"+1 319 623 8291",
    "sg:postcode":"52361",
    "sg:province":"IA",
    "sg:tags":[
        "farm",
        "corn",
        "beef",
        "feedlot",
        "cattle"
    ],
    "wof:name":"Allen Pope",
    "wof:placetype":"venue"
},
  "geometry": {"coordinates":[-92.163099,41.654419],"type":"Point"}
}