{
  "type": "Feature",
  "properties": {
    "iso:country":"US",
    "sg:address":"10881 220th St",
    "sg:city":"Milton",
    "sg:classifiers":[
        {
            "category":"Autos & Motor Vehicles",
            "subcategory":"Automobile Sales",
            "type":"Retail Goods"
        }
    ],
    "sg:phone":"+1 641 656 4231",
    "sg:postcode":"52570",
    "sg:province":"IA",
    "sg:tags":[
        "car",
        "dealer"
    ],
    "wof:name":"Klodt Mustangs",
    "wof:placetype":"venue"
},
  "geometry": {"coordinates":[-92.162817,40.726604],"type":"Point"}
}