{
  "type": "Feature",
  "properties": {
    "iso:country":"US",
    "sg:address":"255 Classic Car Ct SW",
    "sg:city":"Cedar Rapids",
    "sg:classifiers":[
        {
            "category":"Retail",
            "subcategory":"Auto Repair",
            "type":"Services"
        }
    ],
    "sg:phone":"+1 319 366 8370",
    "sg:postcode":"52404",
    "sg:province":"IA",
    "sg:tags":[
        "body",
        "automobile",
        "painting"
    ],
    "wof:name":"Prime Auto Collision Ctr",
    "wof:placetype":"venue"
},
  "geometry": {"coordinates":[-91.667621,41.942517],"type":"Point"}
}