{
  "type": "Feature",
  "properties": {
    "addr:full":"705 Clinton St Grand Mound IA 52751",
    "addr:housenumber":"705",
    "addr:postcode":"52751",
    "addr:street":"Clinton St",
    "iso:country":"US",
    "sg:address":"705 Clinton St",
    "sg:city":"Grand Mound",
    "sg:classifiers":[
        {
            "category":"Utilities",
            "subcategory":"Telephone",
            "type":"Services"
        }
    ],
    "sg:phone":"+1 563 847 3000",
    "sg:postcode":"52751",
    "sg:province":"IA",
    "sg:tags":[
        "company"
    ],
    "wof:name":"Grand Mound Communications Co",
    "wof:placetype":"venue"
},
  "geometry": {"coordinates":[-90.64764599999999,41.824035],"type":"Point"}
}