{
  "type": "Feature",
  "properties": {
    "iso:country":"US",
    "sg:address":"520 Charles St",
    "sg:city":"Waterloo",
    "sg:classifiers":[
        {
            "category":"Building & Trades",
            "subcategory":"Construction",
            "type":"Services"
        }
    ],
    "sg:phone":"+1 319 233 2782",
    "sg:postcode":"50703",
    "sg:province":"IA",
    "sg:tags":[
        "excavating",
        "contractor"
    ],
    "wof:name":"Ernster & Co",
    "wof:placetype":"venue"
},
  "geometry": {"coordinates":[-92.3261,42.517207],"type":"Point"}
}