{
  "type": "Feature",
  "properties": {
    "iso:country":"US",
    "sg:address":"3320 Yew Ave",
    "sg:city":"Hartley",
    "sg:classifiers":[
        {
            "category":"Farming",
            "subcategory":"Farm",
            "type":"Manufacturing & Wholesale Goods"
        }
    ],
    "sg:phone":"+1 712 728 2158",
    "sg:postcode":"51346",
    "sg:province":"IA",
    "sg:tags":[
        "crop",
        "general"
    ],
    "wof:name":"A & R Builders",
    "wof:placetype":"venue"
},
  "geometry": {"coordinates":[-95.40757600000001,43.166745],"type":"Point"}
}