{
  "type": "Feature",
  "properties": {
    "iso:country":"US",
    "sg:address":"3525 Center Point Rd NE",
    "sg:city":"Cedar Rapids",
    "sg:classifiers":[
        {
            "category":"Banks & Credit Unions",
            "subcategory":"Investment Brokerage",
            "type":"Services"
        }
    ],
    "sg:phone":"+1 319 395 0723",
    "sg:postcode":"52402",
    "sg:province":"IA",
    "sg:tags":[
        "advisory",
        "financial"
    ],
    "wof:name":"Hawkeye Financial Group",
    "wof:placetype":"venue"
},
  "geometry": {"coordinates":[-91.664253,42.015056],"type":"Point"}
}