{
  "type": "Feature",
  "properties": {
    "addr:full":"101 W Church St Marshalltown IA 50158",
    "addr:housenumber":"101",
    "addr:postcode":"50158",
    "addr:street":"W Church St",
    "iso:country":"US",
    "sg:address":"101 W Church St",
    "sg:city":"Marshalltown",
    "sg:classifiers":[
        {
            "category":"Organizations",
            "subcategory":"Community Association",
            "type":"Services"
        }
    ],
    "sg:phone":"+1 641 752 4151",
    "sg:postcode":"50158",
    "sg:province":"IA",
    "sg:tags":[
        "fraternal"
    ],
    "wof:name":"Elks Lodge",
    "wof:placetype":"venue"
},
  "geometry": {"coordinates":[-92.916218,42.047913],"type":"Point"}
}