{
  "type": "Feature",
  "properties": {
    "iso:country":"US",
    "sg:address":"301 E Boiler Ave",
    "sg:city":"George",
    "sg:classifiers":[
        {
            "category":"Shopping",
            "type":"Retail Goods"
        }
    ],
    "sg:phone":"+1 712 475 3888",
    "sg:postcode":"51237",
    "sg:province":"IA",
    "sg:tags":[
        "product",
        "wood"
    ],
    "wof:name":"Devries Wood Boats",
    "wof:placetype":"venue"
},
  "geometry": {"coordinates":[-96.00023299999999,43.341449],"type":"Point"}
}