{
  "type": "Feature",
  "properties": {
    "iso:country":"US",
    "sg:address":"1708 Commercial St",
    "sg:city":"Waterloo",
    "sg:classifiers":[
        {
            "category":"Building & Trades",
            "subcategory":"Construction",
            "type":"Services"
        }
    ],
    "sg:phone":"+1 319 232 0770",
    "sg:postcode":"50702",
    "sg:province":"IA",
    "sg:tags":[
        "paving",
        "contractor"
    ],
    "wof:name":"Rooff & Co Blacktop Paving",
    "wof:placetype":"venue"
},
  "geometry": {"coordinates":[-92.327173,42.486782],"type":"Point"}
}