{
  "type": "Feature",
  "properties": {
    "addr:full":"114 Main St La Porte City IA 50651",
    "addr:housenumber":"114",
    "addr:postcode":"50651",
    "addr:street":"Main St",
    "iso:country":"US",
    "sg:address":"114 Main St",
    "sg:city":"La Porte City",
    "sg:classifiers":[
        {
            "category":"Government",
            "subcategory":"Fire Station",
            "type":"Public Place"
        }
    ],
    "sg:phone":"+1 319 342 2521",
    "sg:postcode":"50651",
    "sg:province":"IA",
    "sg:tags":[
        "department"
    ],
    "wof:name":"LA Porte Fire Station",
    "wof:placetype":"venue"
},
  "geometry": {"coordinates":[-92.193493,42.315611],"type":"Point"}
}