{
  "type": "Feature",
  "properties": {
    "iso:country":"US",
    "sg:address":"32315 Plum Ave",
    "sg:city":"Moorhead",
    "sg:classifiers":[
        {
            "category":"Farming",
            "subcategory":"Farm",
            "type":"Manufacturing & Wholesale Goods"
        }
    ],
    "sg:phone":"+1 712 886 5562",
    "sg:postcode":"51558",
    "sg:province":"IA",
    "sg:tags":[
        "crop",
        "general"
    ],
    "wof:name":"Maynard Holverson",
    "wof:placetype":"venue"
},
  "geometry": {"coordinates":[-95.847182,41.893266],"type":"Point"}
}