{
  "type": "Feature",
  "properties": {
    "iso:country":"US",
    "sg:address":"202 S 1st St",
    "sg:city":"Long Grove",
    "sg:classifiers":[
        {
            "category":"Organizations",
            "subcategory":"Religious Organization",
            "type":"Services"
        }
    ],
    "sg:phone":"+1 563 285 8246",
    "sg:postcode":"52756",
    "sg:province":"IA",
    "sg:tags":[
        "church"
    ],
    "wof:name":"Long Grove Christian Church",
    "wof:placetype":"venue"
},
  "geometry": {"coordinates":[-90.58297,41.69601],"type":"Point"}
}