{
  "type": "Feature",
  "properties": {
    "iso:country":"US",
    "sg:address":"2716 144th St",
    "sg:city":"Urbandale",
    "sg:classifiers":[
        {
            "category":"Professional",
            "subcategory":"Management & Consulting",
            "type":"Services"
        }
    ],
    "sg:phone":"+1 515 987 8363",
    "sg:postcode":"50323",
    "sg:province":"IA",
    "sg:tags":[
        "counselor",
        "public",
        "relations"
    ],
    "wof:name":"J S Day & Assoc",
    "wof:placetype":"venue"
},
  "geometry": {"coordinates":[-93.81760300000001,41.621176],"type":"Point"}
}