{
  "type": "Feature",
  "properties": {
    "iso:country":"US",
    "sg:address":"3004 Hwy 9",
    "sg:city":"Spirit Lake",
    "sg:classifiers":[
        {
            "category":"Home & Garden",
            "subcategory":"Household Appliances",
            "type":"Retail Goods"
        }
    ],
    "sg:phone":"+1 712 336 6500",
    "sg:postcode":"51360",
    "sg:province":"IA",
    "sg:website":"www.homeresourcecenter.net",
    "wof:name":"Home Resource Ctr LLC",
    "wof:placetype":"venue"
},
  "geometry": {"coordinates":[-94.993252,43.43041],"type":"Point"}
}