{
  "type": "Feature",
  "properties": {
    "iso:country":"US",
    "sg:address":"2973 Teller Ave",
    "sg:city":"Cedar",
    "sg:classifiers":[
        {
            "category":"Wholesale",
            "subcategory":"Drugs",
            "type":"Manufacturing & Wholesale Goods"
        }
    ],
    "sg:phone":"+1 641 933 4570",
    "sg:postcode":"52543",
    "sg:province":"IA",
    "sg:tags":[
        "cosmetic"
    ],
    "wof:name":"Mary Kay Cosmetics",
    "wof:placetype":"venue"
},
  "geometry": {"coordinates":[-92.50649199999999,41.222841],"type":"Point"}
}