{
  "type": "Feature",
  "properties": {
    "iso:country":"US",
    "sg:address":"1004 Hillcrest Dr",
    "sg:city":"Fairfield",
    "sg:classifiers":[
        {
            "category":"Farming",
            "subcategory":"Farm",
            "type":"Manufacturing & Wholesale Goods"
        }
    ],
    "sg:phone":"+1 641 472 6931",
    "sg:postcode":"52556",
    "sg:province":"IA",
    "sg:tags":[
        "crop",
        "general"
    ],
    "wof:name":"Rice Century Farm LLC",
    "wof:placetype":"venue"
},
  "geometry": {"coordinates":[-91.94898000000001,41.000058],"type":"Point"}
}