{
  "type": "Feature",
  "properties": {
    "addr:full":"111 N Front St Mapleton IA 51034",
    "addr:housenumber":"111",
    "addr:postcode":"51034",
    "addr:street":"N Front St",
    "iso:country":"US",
    "sg:address":"111 N Front St",
    "sg:city":"Mapleton",
    "sg:classifiers":[
        {
            "category":"Wholesale",
            "subcategory":"Farm Supplies",
            "type":"Manufacturing & Wholesale Goods"
        }
    ],
    "sg:phone":"+1 712 882 2733",
    "sg:postcode":"51034",
    "sg:province":"IA",
    "sg:tags":[
        "grain"
    ],
    "wof:name":"Mapleton Grain Co",
    "wof:placetype":"venue"
},
  "geometry": {"coordinates":[-95.794724,42.166808],"type":"Point"}
}