{
  "type": "Feature",
  "properties": {
    "addr:full":"809 Main St Plainfield IA 50666",
    "addr:housenumber":"809",
    "addr:postcode":"50666",
    "addr:street":"Main St",
    "iso:country":"US",
    "sg:address":"809 Main St",
    "sg:city":"Plainfield",
    "sg:classifiers":[
        {
            "category":"Organizations",
            "subcategory":"Religious Organization",
            "type":"Services"
        }
    ],
    "sg:phone":"+1 319 276 3330",
    "sg:postcode":"50666",
    "sg:province":"IA",
    "sg:tags":[
        "church"
    ],
    "sg:website":"www.fbc-plainfield.org",
    "wof:name":"First Baptist Church",
    "wof:placetype":"venue"
},
  "geometry": {"coordinates":[-92.53754499999999,42.849105],"type":"Point"}
}