{
  "type": "Feature",
  "properties": {
    "addr:full":"102 N Main St Centerville IA 52544",
    "addr:housenumber":"102",
    "addr:postcode":"52544",
    "addr:street":"N Main St",
    "iso:country":"US",
    "sg:address":"102 N Main St",
    "sg:city":"Centerville",
    "sg:classifiers":[
        {
            "category":"Place Of Worship",
            "subcategory":"Church",
            "type":"Public Place"
        },
        {
            "category":"Place Of Worship",
            "type":"Public Place"
        }
    ],
    "sg:phone":"+1 641 856 3565",
    "sg:postcode":"52544",
    "sg:province":"IA",
    "sg:tags":[
        "churches-presbyterian-arp",
        "churches-presbyterian"
    ],
    "sg:website":"http://www.fpcjackson.org",
    "wof:name":"First Presbyterian Church, Inc",
    "wof:placetype":"venue"
},
  "geometry": {"coordinates":[-92.87418,40.735926],"type":"Point"}
}