{
  "type": "Feature",
  "properties": {
    "addr:full":"306 2nd St Rolfe IA 50581",
    "addr:housenumber":"306",
    "addr:postcode":"50581",
    "addr:street":"2Nd St",
    "iso:country":"US",
    "sg:address":"306 2nd St",
    "sg:city":"Rolfe",
    "sg:classifiers":[
        {
            "category":"Professional",
            "subcategory":"Computer Services",
            "type":"Services"
        }
    ],
    "sg:phone":"+1 712 848 3844",
    "sg:postcode":"50581",
    "sg:province":"IA",
    "wof:name":"Fishnet Computing",
    "wof:placetype":"venue"
},
  "geometry": {"coordinates":[-94.53623399999999,42.813631],"type":"Point"}
}