{
  "type": "Feature",
  "properties": {
    "iso:country":"US",
    "sg:address":"5725 Dry Creek Ln NE",
    "sg:city":"Cedar Rapids",
    "sg:classifiers":[
        {
            "category":"Restaurant",
            "type":"Food & Drink"
        }
    ],
    "sg:menulink":"http://www.allmenus.com/ia/cedar-rapids/202646-mcdonalds/menu/",
    "sg:postcode":"52402",
    "sg:province":"IA",
    "sg:tags":[
        "burger",
        "american"
    ],
    "wof:name":"McDonald's",
    "wof:placetype":"venue"
},
  "geometry": {"coordinates":[-91.65532899999999,42.03629],"type":"Point"}
}