{
  "type": "Feature",
  "properties": {
    "addr:full":"1921 51st St NE Cedar Rapids IA 52402",
    "addr:housenumber":"1921",
    "addr:postcode":"52402",
    "addr:street":"51St St Ne",
    "iso:country":"US",
    "sg:address":"1921 51st St NE",
    "sg:city":"Cedar Rapids",
    "sg:classifiers":[
        {
            "category":"Professional",
            "subcategory":"Lawyer & Legal Services",
            "type":"Services"
        }
    ],
    "sg:phone":"+1 319 378 7416",
    "sg:postcode":"52402",
    "sg:province":"IA",
    "wof:name":"Scheetz Raphael",
    "wof:placetype":"venue"
},
  "geometry": {"coordinates":[-91.66800499999999,42.029859],"type":"Point"}
}