{
  "type": "Feature",
  "properties": {
    "iso:country":"US",
    "sg:address":"1506 8th St",
    "sg:city":"Coralville",
    "sg:classifiers":[
        {
            "category":"Recreation",
            "type":"Entertainment"
        }
    ],
    "sg:phone":"+1 319 248 1750",
    "sg:postcode":"52241",
    "sg:province":"IA",
    "sg:tags":[
        "center"
    ],
    "sg:website":"www.coralville.org",
    "wof:name":"Coralville Park & Recreation",
    "wof:placetype":"venue"
},
  "geometry": {"coordinates":[-91.586459,41.681748],"type":"Point"}
}