{
  "type": "Feature",
  "properties": {
    "iso:country":"US",
    "sg:address":"131 31st Ave",
    "sg:city":"Rock Island",
    "sg:classifiers":[
        {
            "category":"Building & Trades",
            "subcategory":"Plumbing",
            "type":"Services"
        }
    ],
    "sg:phone":"+1 309 788 9022",
    "sg:postcode":"61201",
    "sg:province":"IL",
    "sg:tags":[
        "conditioning",
        "air",
        "system",
        "contractor"
    ],
    "sg:website":"www.hannaheating.com",
    "wof:name":"Hanna Heating & Air Cond Inc",
    "wof:placetype":"venue"
},
  "geometry": {"coordinates":[-90.59191199999999,41.479684],"type":"Point"}
}