{
  "type": "Feature",
  "properties": {
    "iso:country":"US",
    "sg:address":"23942 US Hwy 52",
    "sg:city":"Garnavillo",
    "sg:classifiers":[
        {
            "category":"Wholesale",
            "subcategory":"Farm Supplies",
            "type":"Manufacturing & Wholesale Goods"
        }
    ],
    "sg:phone":"+1 563 964 2885",
    "sg:postcode":"52049",
    "sg:province":"IA",
    "sg:tags":[
        "livestock"
    ],
    "wof:name":"Mc Andrews Livestock Co",
    "wof:placetype":"venue"
},
  "geometry": {"coordinates":[-91.24152599999999,42.877831],"type":"Point"}
}