{
  "type": "Feature",
  "properties": {
    "addr:full":"1022 Waterfront Dr Ankeny IA 50023",
    "addr:housenumber":"1022",
    "addr:postcode":"50023",
    "addr:street":"Waterfront Dr",
    "iso:country":"US",
    "sg:address":"1022 Waterfront Dr",
    "sg:city":"Ankeny",
    "sg:classifiers":[
        {
            "category":"Retail",
            "subcategory":"Laundry & Dry Cleaning",
            "type":"Services"
        },
        {
            "category":"Building & Trades",
            "subcategory":"Cleaning & Sanitation",
            "type":"Services"
        }
    ],
    "sg:phone":"+1 515 964 3745",
    "sg:postcode":"50023",
    "sg:province":"IA",
    "sg:tags":[
        "cleaner",
        "fabric",
        "rug",
        "protection",
        "furniture",
        "carpet"
    ],
    "wof:name":"Skinner's",
    "wof:placetype":"venue"
},
  "geometry": {"coordinates":[-93.64120800000001,41.740141],"type":"Point"}
}