{
  "type": "Feature",
  "properties": {
    "iso:country":"US",
    "sg:address":"215 6th Ave SW",
    "sg:city":"Clarion",
    "sg:classifiers":[
        {
            "category":"Professional",
            "subcategory":"Engineering",
            "type":"Services"
        }
    ],
    "sg:phone":"+1 515 532 9874",
    "sg:postcode":"50525",
    "sg:province":"IA",
    "sg:tags":[
        "engineer"
    ],
    "wof:name":"Wright County Engineers",
    "wof:placetype":"venue"
},
  "geometry": {"coordinates":[-93.73523299999999,42.726961],"type":"Point"}
}