{
  "type": "Feature",
  "properties": {
    "iso:country":"US",
    "sg:address":"26 Blue Grass Ct",
    "sg:city":"Davenport",
    "sg:classifiers":[
        {
            "category":"Retail",
            "subcategory":"Repair Shop",
            "type":"Services"
        }
    ],
    "sg:phone":"+1 563 326 5453",
    "sg:postcode":"52802",
    "sg:province":"IA",
    "sg:tags":[
        "trade",
        "welding",
        "contractor"
    ],
    "wof:name":"R & JC Contracting",
    "wof:placetype":"venue"
},
  "geometry": {"coordinates":[-90.652331,41.507891],"type":"Point"}
}