{
  "type": "Feature",
  "properties": {
    "iso:country":"US",
    "sg:address":"2113 57th St Trl",
    "sg:city":"Vinton",
    "sg:classifiers":[
        {
            "category":"Recreation",
            "type":"Entertainment"
        }
    ],
    "sg:phone":"+1 319 472 4942",
    "sg:postcode":"52349",
    "sg:province":"IA",
    "sg:tags":[
        "parks"
    ],
    "wof:name":"Rodgers Park",
    "wof:placetype":"venue"
},
  "geometry": {"coordinates":[-92.078062,42.195284],"type":"Point"}
}