{
  "type": "Feature",
  "properties": {
    "addr:full":"24493 State Hwy 128 Elkader IA 52043",
    "addr:housenumber":"24493",
    "addr:postcode":"52043",
    "addr:street":"State Hwy 128",
    "iso:country":"US",
    "sg:address":"24493 State Hwy 128",
    "sg:city":"Elkader",
    "sg:classifiers":[
        {
            "category":"Communications",
            "subcategory":"Radio Station",
            "type":"Services"
        }
    ],
    "sg:phone":"+1 563 245 1400",
    "sg:postcode":"52043",
    "sg:province":"IA",
    "sg:tags":[
        "company",
        "broadcasting"
    ],
    "wof:name":"KADR",
    "wof:placetype":"venue"
},
  "geometry": {"coordinates":[-91.32226300000001,42.884763],"type":"Point"}
}