{
  "type": "Feature",
  "properties": {
    "iso:country":"US",
    "sg:address":"211 W Washington St",
    "sg:city":"Monticello",
    "sg:phone":"+1 319 465 5014",
    "sg:postcode":"52310",
    "sg:province":"IA",
    "sg:tags":[
        "farm",
        "field",
        "crop",
        "soybean"
    ],
    "wof:name":"Rose Dunkel",
    "wof:placetype":"venue"
},
  "geometry": {"coordinates":[-91.19131299999999,42.236003],"type":"Point"}
}