{
  "type": "Feature",
  "properties": {
    "iso:country":"US",
    "sg:address":"1511 1st St E",
    "sg:city":"Independence",
    "sg:classifiers":[
        {
            "category":"Building & Trades",
            "subcategory":"Construction",
            "type":"Services"
        }
    ],
    "sg:phone":"+1 319 334 6031",
    "sg:postcode":"50644",
    "sg:province":"IA",
    "sg:tags":[
        "grading",
        "contractor"
    ],
    "wof:name":"Buchanan County Highway Dept",
    "wof:placetype":"venue"
},
  "geometry": {"coordinates":[-91.875951,42.468723],"type":"Point"}
}