{
  "type": "Feature",
  "properties": {
    "addr:full":"318 Main St Janesville IA 50647",
    "addr:housenumber":"318",
    "addr:postcode":"50647",
    "addr:street":"Main St",
    "iso:country":"US",
    "sg:address":"318 Main St",
    "sg:city":"Janesville",
    "sg:classifiers":[
        {
            "category":"Health Services",
            "subcategory":"Clinic",
            "type":"Services"
        }
    ],
    "sg:phone":"+1 319 987 2081",
    "sg:postcode":"50647",
    "sg:province":"IA",
    "sg:tags":[
        "holistic",
        "practitioner"
    ],
    "wof:name":"Terrie Harlan",
    "wof:placetype":"venue"
},
  "geometry": {"coordinates":[-92.463106,42.647068],"type":"Point"}
}