{
  "type": "Feature",
  "properties": {
    "iso:country":"US",
    "sg:address":"3100 N US Hwy 75",
    "sg:city":"Sioux City",
    "sg:classifiers":[
        {
            "category":"Home & Garden",
            "subcategory":"Furniture",
            "type":"Retail Goods"
        }
    ],
    "sg:phone":"+1 712 255 3575",
    "sg:postcode":"51105",
    "sg:province":"IA",
    "wof:name":"Miller Brothers Furniture",
    "wof:placetype":"venue"
},
  "geometry": {"coordinates":[-96.36506799999999,42.524044],"type":"Point"}
}