{
  "type": "Feature",
  "properties": {
    "addr:full":"301 W Bremer Ave Waverly IA 50677",
    "addr:housenumber":"301",
    "addr:postcode":"50677",
    "addr:street":"W Bremer Ave",
    "iso:country":"US",
    "sg:address":"301 W Bremer Ave",
    "sg:city":"Waverly",
    "sg:classifiers":[
        {
            "category":"Insurance",
            "subcategory":"Insurance Agent",
            "type":"Services"
        }
    ],
    "sg:phone":"+1 319 352 3395",
    "sg:postcode":"50677",
    "sg:province":"IA",
    "wof:name":"State Farm Insurance",
    "wof:placetype":"venue"
},
  "geometry": {"coordinates":[-92.47566999999999,42.725732],"type":"Point"}
}