{
  "type": "Feature",
  "properties": {
    "iso:country":"US",
    "sg:address":"608 1st Ave W",
    "sg:city":"Swea City",
    "sg:classifiers":[
        {
            "category":"Organizations",
            "subcategory":"Religious Organization",
            "type":"Services"
        }
    ],
    "sg:phone":"+1 515 272 4327",
    "sg:postcode":"50590",
    "sg:province":"IA",
    "wof:name":"Swea Cy Frst Untd Mthdst Chrch",
    "wof:placetype":"venue"
},
  "geometry": {"coordinates":[-94.313772,43.382214],"type":"Point"}
}