{
  "type": "Feature",
  "properties": {
    "iso:country":"US",
    "sg:address":"2009 SW 1st St",
    "sg:city":"Des Moines",
    "sg:classifiers":[
        {
            "category":"Organizations",
            "subcategory":"Religious Organization",
            "type":"Services"
        }
    ],
    "sg:phone":"+1 515 288 6183",
    "sg:postcode":"50315",
    "sg:province":"IA",
    "sg:tags":[
        "church"
    ],
    "wof:name":"Bethany Open Bible Church",
    "wof:placetype":"venue"
},
  "geometry": {"coordinates":[-93.616997,41.569143],"type":"Point"}
}