{
  "type": "Feature",
  "properties": {
    "addr:full":"901 E Euclid Ave Des Moines IA 50316",
    "addr:housenumber":"901",
    "addr:postcode":"50316",
    "addr:street":"E Euclid Ave",
    "iso:country":"US",
    "sg:address":"901 E Euclid Ave",
    "sg:city":"Des Moines",
    "sg:classifiers":[
        {
            "category":"Restaurant",
            "type":"Food & Drink"
        }
    ],
    "sg:phone":"+1 515 263 2666",
    "sg:postcode":"50316",
    "sg:province":"IA",
    "wof:name":"Vientiane Restaurant Inc",
    "wof:placetype":"venue"
},
  "geometry": {"coordinates":[-93.60583,41.627711],"type":"Point"}
}