{
  "type": "Feature",
  "properties": {
    "addr:full":"28825 476th Ave Canton IA 57013",
    "addr:housenumber":"28825",
    "addr:postcode":"57013",
    "addr:street":"476Th Ave",
    "iso:country":"US",
    "sg:address":"28825 476th Ave",
    "sg:city":"Canton",
    "sg:classifiers":[
        {
            "category":"Farming",
            "subcategory":"Farm",
            "type":"Manufacturing & Wholesale Goods"
        }
    ],
    "sg:phone":"+1 605 987 2152",
    "sg:postcode":"57013",
    "sg:province":"IA",
    "sg:tags":[
        "crop",
        "general"
    ],
    "wof:name":"David Myers",
    "wof:placetype":"venue"
},
  "geometry": {"coordinates":[-96.687484,43.210412],"type":"Point"}
}