{
  "type": "Feature",
  "properties": {
    "iso:country":"US",
    "sg:address":"303 E Main St",
    "sg:city":"Knoxville",
    "sg:classifiers":[
        {
            "category":"Insurance",
            "subcategory":"Insurance Agent",
            "type":"Services"
        }
    ],
    "sg:phone":"+1 641 842 2519",
    "sg:postcode":"50138",
    "sg:province":"IA",
    "wof:name":"Marion County Mutual Insurance",
    "wof:placetype":"venue"
},
  "geometry": {"coordinates":[-93.09528,41.319021],"type":"Point"}
}