{
  "type": "Feature",
  "properties": {
    "iso:country":"US",
    "sg:address":"1100 Old Marion Rd NE",
    "sg:city":"Cedar Rapids",
    "sg:classifiers":[
        {
            "category":"Building & Trades",
            "subcategory":"Construction",
            "type":"Services"
        }
    ],
    "sg:phone":"+1 319 395 9300",
    "sg:postcode":"52402",
    "sg:province":"IA",
    "sg:tags":[
        "general",
        "contractor"
    ],
    "wof:name":"Regency Commercial Svc",
    "wof:placetype":"venue"
},
  "geometry": {"coordinates":[-91.65316799999999,42.020125],"type":"Point"}
}