{
  "type": "Feature",
  "properties": {
    "iso:country":"US",
    "sg:address":"240 7th Ave SE",
    "sg:city":"Sioux Center",
    "sg:classifiers":[
        {
            "category":"Health Services",
            "subcategory":"Clinic",
            "type":"Services"
        }
    ],
    "sg:phone":"+1 712 722 0047",
    "sg:postcode":"51250",
    "sg:province":"IA",
    "sg:tags":[
        "specialty",
        "outpatient"
    ],
    "wof:name":"Hope Hven Psychtric Rhbltation",
    "wof:placetype":"venue"
},
  "geometry": {"coordinates":[-96.164958,43.075632],"type":"Point"}
}