{
  "type": "Feature",
  "properties": {
    "iso:country":"US",
    "sg:address":"25159 280th Ave",
    "sg:city":"Sigourney",
    "sg:classifiers":[
        {
            "category":"Retail",
            "subcategory":"Repair Shop",
            "type":"Services"
        }
    ],
    "sg:phone":"+1 641 635 2294",
    "sg:postcode":"52591",
    "sg:province":"IA",
    "wof:name":"Hammes Vermeer LLC",
    "wof:placetype":"venue"
},
  "geometry": {"coordinates":[-92.064009,41.289887],"type":"Point"}
}