{
  "type": "Feature",
  "properties": {
    "iso:country":"US",
    "sg:address":"1200 Grand Ave",
    "sg:city":"Des Moines",
    "sg:classifiers":[
        {
            "category":"Organizations",
            "subcategory":"Political Organization",
            "type":"Services"
        }
    ],
    "sg:phone":"+1 515 282 4811",
    "sg:postcode":"50309",
    "sg:province":"IA",
    "wof:name":"Ganske For Congress Campaign",
    "wof:placetype":"venue"
},
  "geometry": {"coordinates":[-93.633866,41.585926],"type":"Point"}
}