{
  "type": "Feature",
  "properties": {
    "addr:full":"2410 Grande Ave SE Cedar Rapids IA 52403",
    "addr:housenumber":"2410",
    "addr:postcode":"52403",
    "addr:street":"Grande Ave Se",
    "iso:country":"US",
    "sg:address":"2410 Grande Ave SE",
    "sg:city":"Cedar Rapids",
    "sg:classifiers":[
        {
            "category":"Professional",
            "subcategory":"Management & Consulting",
            "type":"Services"
        }
    ],
    "sg:phone":"+1 319 365 2080",
    "sg:postcode":"52403",
    "sg:province":"IA",
    "sg:tags":[
        "business"
    ],
    "wof:name":"Benwood Consulting Group",
    "wof:placetype":"venue"
},
  "geometry": {"coordinates":[-91.63195,41.986641],"type":"Point"}
}