{
  "type": "Feature",
  "properties": {
    "iso:country":"US",
    "sg:address":"314 S Collins St",
    "sg:city":"Sioux City",
    "sg:classifiers":[
        {
            "category":"Building & Trades",
            "subcategory":"Construction",
            "type":"Services"
        }
    ],
    "sg:phone":"+1 712 234 0212",
    "sg:postcode":"51103",
    "sg:province":"IA",
    "sg:tags":[
        "roofing",
        "contractor"
    ],
    "wof:name":"Dryco Roofing",
    "wof:placetype":"venue"
},
  "geometry": {"coordinates":[-96.4366,42.494027],"type":"Point"}
}