{
  "type": "Feature",
  "properties": {
    "iso:country":"US",
    "sg:address":"126 W Main Ave",
    "sg:city":"Rockford",
    "sg:classifiers":[
        {
            "category":"Personal",
            "subcategory":"Beauty Salon",
            "type":"Services"
        }
    ],
    "sg:phone":"+1 641 756 2482",
    "sg:postcode":"50468",
    "sg:province":"IA",
    "wof:name":"Sherry's Style Shoppe",
    "wof:placetype":"venue"
},
  "geometry": {"coordinates":[-92.948166,43.052384],"type":"Point"}
}