{
  "type": "Feature",
  "properties": {
    "addr:full":"723 Platt St Sac City IA 50583",
    "addr:housenumber":"723",
    "addr:postcode":"50583",
    "addr:street":"Platt St",
    "iso:country":"US",
    "sg:address":"723 Platt St",
    "sg:city":"Sac City",
    "sg:classifiers":[
        {
            "category":"Personal",
            "subcategory":"Beauty Salon",
            "type":"Services"
        }
    ],
    "sg:phone":"+1 712 662 4106",
    "sg:postcode":"50583",
    "sg:province":"IA",
    "sg:tags":[
        "shop"
    ],
    "wof:name":"Susan's Beauty Salon",
    "wof:placetype":"venue"
},
  "geometry": {"coordinates":[-94.99438600000001,42.418459],"type":"Point"}
}