{
  "type": "Feature",
  "properties": {
    "addr:full":"303 N 4th St Bellevue IA 52031",
    "addr:housenumber":"303",
    "addr:postcode":"52031",
    "addr:street":"N 4Th St",
    "iso:country":"US",
    "sg:address":"303 N 4th St",
    "sg:city":"Bellevue",
    "sg:classifiers":[
        {
            "category":"Building & Trades",
            "subcategory":"Construction",
            "type":"Services"
        }
    ],
    "sg:phone":"+1 563 872 3603",
    "sg:postcode":"52031",
    "sg:province":"IA",
    "sg:tags":[
        "general",
        "contractor"
    ],
    "wof:name":"Carl Hoffmann Construction",
    "wof:placetype":"venue"
},
  "geometry": {"coordinates":[-90.42757,42.260423],"type":"Point"}
}