{
  "type": "Feature",
  "properties": {
    "iso:country":"US",
    "sg:address":"6674 25th Ave",
    "sg:city":"Van Horne",
    "sg:classifiers":[
        {
            "category":"Farming",
            "subcategory":"Farm",
            "type":"Manufacturing & Wholesale Goods"
        }
    ],
    "sg:phone":"+1 319 223 5619",
    "sg:postcode":"52346",
    "sg:province":"IA",
    "sg:tags":[
        "crop",
        "general"
    ],
    "wof:name":"Virgil Schminke",
    "wof:placetype":"venue"
},
  "geometry": {"coordinates":[-92.009794,42.054482],"type":"Point"}
}