{
  "type": "Feature",
  "properties": {
    "iso:country":"US",
    "sg:address":"110 E State St",
    "sg:city":"Jefferson",
    "sg:classifiers":[
        {
            "category":"Social Services",
            "subcategory":"Job Training",
            "type":"Services"
        }
    ],
    "sg:phone":"+1 515 386 8558",
    "sg:postcode":"50129",
    "sg:province":"IA",
    "sg:tags":[
        "rehab",
        "government"
    ],
    "wof:name":"US Job Training Partnership",
    "wof:placetype":"venue"
},
  "geometry": {"coordinates":[-94.37464199999999,42.016339],"type":"Point"}
}