{
  "type": "Feature",
  "properties": {
    "iso:country":"US",
    "sg:address":"525 Belmont Rd",
    "sg:city":"Riverdale",
    "sg:classifiers":[
        {
            "category":"Education",
            "subcategory":"School",
            "type":"Public Place"
        }
    ],
    "sg:phone":"+1 563 332 5550",
    "sg:postcode":"52722",
    "sg:province":"IA",
    "sg:website":"http://www.pleasval.k12.ia.us",
    "wof:name":"Pleasant Valley Community Schools",
    "wof:placetype":"venue"
},
  "geometry": {"coordinates":[-90.466301,41.551899],"type":"Point"}
}