{
  "type": "Feature",
  "properties": {
    "iso:country":"US",
    "sg:address":"1115 N Court St",
    "sg:city":"Carroll",
    "sg:classifiers":[
        {
            "category":"Retail",
            "subcategory":"Repair Shop",
            "type":"Services"
        }
    ],
    "sg:phone":"+1 712 792 4829",
    "sg:postcode":"51401",
    "sg:province":"IA",
    "wof:name":"Rods Key Service",
    "wof:placetype":"venue"
},
  "geometry": {"coordinates":[-94.86292,42.07152],"type":"Point"}
}