{
  "type": "Feature",
  "properties": {
    "iso:country":"US",
    "sg:address":"334 S 2nd St",
    "sg:city":"Manchester",
    "sg:classifiers":[
        {
            "category":"Government",
            "subcategory":"Office",
            "type":"Public Place"
        }
    ],
    "sg:phone":"+1 563 927 4011",
    "sg:postcode":"52057",
    "sg:province":"IA",
    "sg:tags":[
        "village"
    ],
    "wof:name":"Manchester City Shop",
    "wof:placetype":"venue"
},
  "geometry": {"coordinates":[-91.460835,42.48196],"type":"Point"}
}