{
  "type": "Feature",
  "properties": {
    "iso:country":"US",
    "sg:address":"320 W 27th St",
    "sg:city":"Sioux City",
    "sg:classifiers":[
        {
            "category":"Restaurant",
            "type":"Food & Drink"
        }
    ],
    "sg:menulink":"http://www.allmenus.com/ia/sioux-city/124377-quiznos-sub/menu/",
    "sg:phone":"+1 712 258 7827",
    "sg:postcode":"51104",
    "sg:province":"IA",
    "sg:tags":[
        "wrap",
        "american",
        "sandwich"
    ],
    "wof:name":"Quiznos Sub",
    "wof:placetype":"venue"
},
  "geometry": {"coordinates":[-96.41786500000001,42.517997],"type":"Point"}
}