{
  "type": "Feature",
  "properties": {
    "iso:country":"US",
    "sg:address":"205 W 10th Ave N",
    "sg:city":"Clear Lake",
    "sg:classifiers":[
        {
            "category":"Organizations",
            "subcategory":"Religious Organization",
            "type":"Services"
        }
    ],
    "sg:phone":"+1 641 357 2818",
    "sg:postcode":"50428",
    "sg:province":"IA",
    "sg:tags":[
        "church"
    ],
    "sg:website":"www.congregationalcl.com",
    "wof:name":"First Congregational Church",
    "wof:placetype":"venue"
},
  "geometry": {"coordinates":[-93.390423,43.14452],"type":"Point"}
}