{
  "type": "Feature",
  "properties": {
    "addr:full":"2105 440th Ave Estherville IA 51334",
    "addr:housenumber":"2105",
    "addr:postcode":"51334",
    "addr:street":"440Th Ave",
    "iso:country":"US",
    "sg:address":"2105 440th Ave",
    "sg:city":"Estherville",
    "sg:classifiers":[
        {
            "category":"Organizations",
            "subcategory":"Religious Organization",
            "type":"Services"
        }
    ],
    "sg:phone":"+1 712 362 2072",
    "sg:postcode":"51334",
    "sg:province":"IA",
    "sg:tags":[
        "church"
    ],
    "wof:name":"Immanuel Evangelical Lutheran",
    "wof:placetype":"venue"
},
  "geometry": {"coordinates":[-94.71826799999999,43.341196],"type":"Point"}
}