{
  "type": "Feature",
  "properties": {
    "iso:country":"US",
    "sg:address":"914 2nd St SW",
    "sg:city":"Clarion",
    "sg:phone":"+1 515 532 3866",
    "sg:postcode":"50525",
    "sg:province":"IA",
    "sg:tags":[
        "farm",
        "corn",
        "soybean"
    ],
    "wof:name":"George Boyington",
    "wof:placetype":"venue"
},
  "geometry": {"coordinates":[-93.73543100000001,42.724962],"type":"Point"}
}