{
  "type": "Feature",
  "properties": {
    "iso:country":"US",
    "sg:address":"205 Robins Rd",
    "sg:city":"Hiawatha",
    "sg:classifiers":[
        {
            "category":"Retail",
            "subcategory":"Auto Repair",
            "type":"Services"
        },
        {
            "category":"Manufacturing",
            "subcategory":"Motor Vehicles & Parts",
            "type":"Manufacturing & Wholesale Goods"
        }
    ],
    "sg:phone":"+1 319 294 8600",
    "sg:postcode":"52233",
    "sg:province":"IA",
    "sg:tags":[
        "equipment",
        "recreational",
        "transportation",
        "mfg"
    ],
    "wof:name":"All American Rv Inc",
    "wof:placetype":"venue"
},
  "geometry": {"coordinates":[-91.672907,42.041093],"type":"Point"}
}