{
  "type": "Feature",
  "properties": {
    "iso:country":"US",
    "sg:address":"4343 Grant Ave",
    "sg:city":"Sioux Center",
    "sg:classifiers":[
        {
            "category":"Farming",
            "subcategory":"Farm",
            "type":"Manufacturing & Wholesale Goods"
        }
    ],
    "sg:phone":"+1 712 722 3639",
    "sg:postcode":"51250",
    "sg:province":"IA",
    "wof:name":"F & R Farm",
    "wof:placetype":"venue"
},
  "geometry": {"coordinates":[-96.19506,43.020004],"type":"Point"}
}