{
  "type": "Feature",
  "properties": {
    "addr:full":"1305 W Jefferson St Winterset IA 50273",
    "addr:housenumber":"1305",
    "addr:postcode":"50273",
    "addr:street":"W Jefferson St",
    "iso:country":"US",
    "sg:address":"1305 W Jefferson St",
    "sg:city":"Winterset",
    "sg:classifiers":[
        {
            "category":"Organizations",
            "subcategory":"Religious Organization",
            "type":"Services"
        }
    ],
    "sg:phone":"+1 515 462 1050",
    "sg:postcode":"50273",
    "sg:province":"IA",
    "sg:tags":[
        "church"
    ],
    "sg:website":"www.fbcwin.org",
    "wof:name":"First Baptist Church",
    "wof:placetype":"venue"
},
  "geometry": {"coordinates":[-94.02852300000001,41.335522],"type":"Point"}
}