{
  "type": "Feature",
  "properties": {
    "addr:full":"207 E Harrison St Jefferson IA 50129",
    "addr:housenumber":"207",
    "addr:postcode":"50129",
    "addr:street":"E Harrison St",
    "iso:country":"US",
    "sg:address":"207 E Harrison St",
    "sg:city":"Jefferson",
    "sg:phone":"+1 515 386 4694",
    "sg:postcode":"50129",
    "sg:province":"IA",
    "sg:tags":[
        "farm",
        "corn"
    ],
    "wof:name":"David Ausberger",
    "wof:placetype":"venue"
},
  "geometry": {"coordinates":[-94.373366,42.014217],"type":"Point"}
}