{
  "type": "Feature",
  "properties": {
    "iso:country":"US",
    "sg:address":"110 N Cody Rd",
    "sg:city":"Le Claire",
    "sg:classifiers":[
        {
            "category":"Freight",
            "type":"Transportation"
        }
    ],
    "sg:phone":"+1 563 289 3715",
    "sg:postcode":"52753",
    "sg:province":"IA",
    "sg:tags":[
        "commercial",
        "storage"
    ],
    "wof:name":"Le Clair Storage",
    "wof:placetype":"venue"
},
  "geometry": {"coordinates":[-90.343671,41.598485],"type":"Point"}
}