{
  "type": "Feature",
  "properties": {
    "iso:country":"US",
    "sg:address":"1903 Main St",
    "sg:city":"Granger",
    "sg:classifiers":[
        {
            "category":"Home & Garden",
            "subcategory":"Furniture",
            "type":"Retail Goods"
        }
    ],
    "sg:phone":"+1 515 999 2500",
    "sg:postcode":"50109",
    "sg:province":"IA",
    "sg:tags":[
        "top",
        "counter"
    ],
    "wof:name":"Iowa Countertops",
    "wof:placetype":"venue"
},
  "geometry": {"coordinates":[-93.82039,41.760809],"type":"Point"}
}