{
  "type": "Feature",
  "properties": {
    "iso:country":"US",
    "sg:address":"1436 Penrose St",
    "sg:city":"Grinnell",
    "sg:classifiers":[
        {
            "category":"Social Services",
            "subcategory":"Child Care",
            "type":"Services"
        }
    ],
    "sg:phone":"+1 641 236 7214",
    "sg:postcode":"50112",
    "sg:province":"IA",
    "wof:name":"Grinnell Community Day Care",
    "wof:placetype":"venue"
},
  "geometry": {"coordinates":[-92.70789000000001,41.751402],"type":"Point"}
}