{
  "type": "Feature",
  "properties": {
    "iso:country":"US",
    "sg:address":"204 N Cherry Ave",
    "sg:city":"Woodward",
    "sg:classifiers":[
        {
            "category":"Personal",
            "subcategory":"Beauty Salon",
            "type":"Services"
        }
    ],
    "sg:phone":"+1 515 438 2900",
    "sg:postcode":"50276",
    "sg:province":"IA",
    "wof:name":"Jody's House Of Styling",
    "wof:placetype":"venue"
},
  "geometry": {"coordinates":[-93.926046,41.860614],"type":"Point"}
}