{
  "type": "Feature",
  "properties": {
    "iso:country":"US",
    "sg:address":"1980 280th St",
    "sg:city":"Spencer",
    "sg:classifiers":[
        {
            "category":"Professional",
            "subcategory":"Computer Services",
            "type":"Services"
        }
    ],
    "sg:phone":"+1 712 262 9039",
    "sg:postcode":"51301",
    "sg:province":"IA",
    "sg:tags":[
        "consultant",
        "designer"
    ],
    "sg:website":"www.boji.com",
    "wof:name":"Boji Information Systems",
    "wof:placetype":"venue"
},
  "geometry": {"coordinates":[-95.195797,43.242405],"type":"Point"}
}