{
  "type": "Feature",
  "properties": {
    "iso:country":"US",
    "sg:address":"709 S Oak St",
    "sg:city":"Iowa Falls",
    "sg:classifiers":[
        {
            "category":"Professional",
            "subcategory":"Business Services",
            "type":"Services"
        }
    ],
    "sg:phone":"+1 641 648 4393",
    "sg:postcode":"50126",
    "sg:province":"IA",
    "sg:tags":[
        "license"
    ],
    "wof:name":"County Of Hardin",
    "wof:placetype":"venue"
},
  "geometry": {"coordinates":[-93.262455,42.50634],"type":"Point"}
}