{
  "type": "Feature",
  "properties": {
    "addr:full":"208 Main St Williams IA 50271",
    "addr:housenumber":"208",
    "addr:postcode":"50271",
    "addr:street":"Main St",
    "iso:country":"US",
    "sg:address":"208 Main St",
    "sg:city":"Williams",
    "sg:classifiers":[
        {
            "category":"Government",
            "subcategory":"Post Office",
            "type":"Public Place"
        }
    ],
    "sg:phone":"+1 515 854 2252",
    "sg:postcode":"50271",
    "sg:province":"IA",
    "wof:name":"US Post Office",
    "wof:placetype":"venue"
},
  "geometry": {"coordinates":[-93.544532,42.488048],"type":"Point"}
}