{
  "type": "Feature",
  "properties": {
    "addr:full":"1554 Bittersweet Rd Woodward IA 50276",
    "addr:housenumber":"1554",
    "addr:postcode":"50276",
    "addr:street":"Bittersweet Rd",
    "iso:country":"US",
    "sg:address":"1554 Bittersweet Rd",
    "sg:city":"Woodward",
    "sg:classifiers":[
        {
            "category":"Professional",
            "subcategory":"Management & Consulting",
            "type":"Services"
        }
    ],
    "sg:phone":"+1 515 438 2347",
    "sg:postcode":"50276",
    "sg:province":"IA",
    "wof:name":"Comprhensive Envmtl Hlth Servi",
    "wof:placetype":"venue"
},
  "geometry": {"coordinates":[-93.85677099999999,41.811735],"type":"Point"}
}