{
  "type": "Feature",
  "properties": {
    "iso:country":"US",
    "sg:address":"1003 Chase St",
    "sg:city":"Osage",
    "sg:phone":"+1 641 732 4922",
    "sg:postcode":"50461",
    "sg:province":"IA",
    "sg:tags":[
        "farm",
        "corn",
        "soybean"
    ],
    "wof:name":"Steve Penney",
    "wof:placetype":"venue"
},
  "geometry": {"coordinates":[-92.805931,43.285211],"type":"Point"}
}