{
  "type": "Feature",
  "properties": {
    "iso:country":"US",
    "sg:address":"513 Locust St",
    "sg:city":"Minburn",
    "sg:classifiers":[
        {
            "category":"Building & Trades",
            "subcategory":"Plumbing",
            "type":"Services"
        }
    ],
    "sg:phone":"+1 515 677 2171",
    "sg:postcode":"50063",
    "sg:province":"IA",
    "sg:tags":[
        "plumbing",
        "contractor"
    ],
    "wof:name":"Huss Plumbing",
    "wof:placetype":"venue"
},
  "geometry": {"coordinates":[-94.03030200000001,41.754453],"type":"Point"}
}