{
  "type": "Feature",
  "properties": {
    "iso:country":"US",
    "sg:address":"1210 13th St N",
    "sg:city":"Humboldt",
    "sg:classifiers":[
        {
            "category":"Utilities",
            "subcategory":"Electric",
            "type":"Services"
        }
    ],
    "sg:phone":"+1 515 332 1616",
    "sg:postcode":"50548",
    "sg:province":"IA",
    "sg:tags":[
        "company"
    ],
    "sg:website":"www.humboldtrec.com",
    "wof:name":"Humboldt County Rural Electric",
    "wof:placetype":"venue"
},
  "geometry": {"coordinates":[-94.227226,42.735112],"type":"Point"}
}