{
  "type": "Feature",
  "properties": {
    "addr:full":"1201 Washington St Hamburg IA 51640",
    "addr:housenumber":"1201",
    "addr:postcode":"51640",
    "addr:street":"Washington St",
    "iso:country":"US",
    "sg:address":"1201 Washington St",
    "sg:city":"Hamburg",
    "sg:phone":"+1 712 382 1040",
    "sg:postcode":"51640",
    "sg:province":"IA",
    "sg:tags":[
        "oil"
    ],
    "wof:name":"Hamburg Oil Co",
    "wof:placetype":"venue"
},
  "geometry": {"coordinates":[-95.65466000000001,40.60507],"type":"Point"}
}