{
  "type": "Feature",
  "properties": {
    "iso:country":"US",
    "sg:address":"14077 Lakeview Dr",
    "sg:city":"Clive",
    "sg:classifiers":[
        {
            "category":"Professional",
            "subcategory":"Computer Services",
            "type":"Services"
        }
    ],
    "sg:phone":"+1 515 225 3570",
    "sg:postcode":"50325",
    "sg:province":"IA",
    "sg:tags":[
        "datum"
    ],
    "wof:name":"Paula Levay",
    "wof:placetype":"venue"
},
  "geometry": {"coordinates":[-93.811626,41.609296],"type":"Point"}
}