{
  "type": "Feature",
  "properties": {
    "iso:country":"US",
    "sg:address":"3305 Redwood Ave",
    "sg:city":"Wayland",
    "sg:classifiers":[
        {
            "category":"Farming",
            "subcategory":"Poultry Farm",
            "type":"Manufacturing & Wholesale Goods"
        }
    ],
    "sg:phone":"+1 319 256 8731",
    "sg:postcode":"52654",
    "sg:province":"IA",
    "sg:tags":[
        "egg"
    ],
    "wof:name":"Keith Nebel",
    "wof:placetype":"venue"
},
  "geometry": {"coordinates":[-91.62038800000001,41.177259],"type":"Point"}
}