{
  "type": "Feature",
  "properties": {
    "iso:country":"US",
    "sg:address":"1248 42nd St NE",
    "sg:city":"Cedar Rapids",
    "sg:classifiers":[
        {
            "category":"Recreation",
            "type":"Entertainment"
        }
    ],
    "sg:phone":"+1 319 286 5795",
    "sg:postcode":"52402",
    "sg:province":"IA",
    "sg:tags":[
        "pool",
        "swimming"
    ],
    "wof:name":"Noelridge Pool",
    "wof:placetype":"venue"
},
  "geometry": {"coordinates":[-91.654385,42.021303],"type":"Point"}
}