{
  "type": "Feature",
  "properties": {
    "addr:full":"436 Main St Dysart IA 52224",
    "addr:housenumber":"436",
    "addr:postcode":"52224",
    "addr:street":"Main St",
    "iso:country":"US",
    "sg:address":"436 Main St",
    "sg:city":"Dysart",
    "sg:classifiers":[
        {
            "category":"Government",
            "subcategory":"Fire Station",
            "type":"Public Place"
        }
    ],
    "sg:phone":"+1 319 476 4390",
    "sg:postcode":"52224",
    "sg:province":"IA",
    "sg:tags":[
        "department"
    ],
    "wof:name":"Dysart Fire Dept",
    "wof:placetype":"venue"
},
  "geometry": {"coordinates":[-92.306281,42.17013],"type":"Point"}
}