{
  "type": "Feature",
  "properties": {
    "addr:full":"217 W Salem Ave Indianola IA 50125",
    "addr:housenumber":"217",
    "addr:postcode":"50125",
    "addr:street":"W Salem Ave",
    "iso:country":"US",
    "sg:address":"217 W Salem Ave",
    "sg:city":"Indianola",
    "sg:classifiers":[
        {
            "category":"Personal",
            "subcategory":"Beauty Salon",
            "type":"Services"
        }
    ],
    "sg:phone":"+1 515 961 7240",
    "sg:postcode":"50125",
    "sg:province":"IA",
    "sg:tags":[
        "manicuring"
    ],
    "wof:name":"Indulge Nails",
    "wof:placetype":"venue"
},
  "geometry": {"coordinates":[-93.56246899999999,41.360255],"type":"Point"}
}