{
  "type": "Feature",
  "properties": {
    "iso:country":"US",
    "sg:address":"6460 Williams Blvd",
    "sg:city":"Cedar Rapids",
    "sg:phone":"+1 319 396 7037",
    "sg:postcode":"52404",
    "sg:province":"IA",
    "sg:tags":[
        "farm",
        "corn"
    ],
    "wof:name":"Roemig John",
    "wof:placetype":"venue"
},
  "geometry": {"coordinates":[-91.753427,41.940355],"type":"Point"}
}