{
  "type": "Feature",
  "properties": {
    "iso:country":"US",
    "sg:address":"1261 Linn Ridge Rd",
    "sg:city":"Mount Vernon",
    "sg:classifiers":[
        {
            "category":"Manufacturing",
            "subcategory":"Tools & Machinery",
            "type":"Manufacturing & Wholesale Goods"
        }
    ],
    "sg:phone":"+1 319 362 8555",
    "sg:postcode":"52314",
    "sg:province":"IA",
    "sg:tags":[
        "farm",
        "mfg"
    ],
    "wof:name":"Thomas Conner",
    "wof:placetype":"venue"
},
  "geometry": {"coordinates":[-91.49883199999999,41.992292],"type":"Point"}
}