{
  "type": "Feature",
  "properties": {
    "iso:country":"US",
    "sg:address":"12655 University Ave",
    "sg:city":"Clive",
    "sg:classifiers":[
        {
            "category":"Coffee & Tea",
            "type":"Food & Drink"
        }
    ],
    "sg:menulink":"http://www.allmenus.com/ia/walnut/221084-caribou-coffee/menu/",
    "sg:phone":"+1 515 457 3078",
    "sg:postcode":"50325",
    "sg:province":"IA",
    "sg:tags":[
        "american",
        "diner"
    ],
    "wof:name":"Caribou Coffee",
    "wof:placetype":"venue"
},
  "geometry": {"coordinates":[-93.792883,41.600477],"type":"Point"}
}