{
  "type": "Feature",
  "properties": {
    "iso:country":"US",
    "sg:address":"125 Plymouth St NE",
    "sg:city":"Le Mars",
    "sg:classifiers":[
        {
            "category":"Restaurant",
            "type":"Food & Drink"
        }
    ],
    "sg:phone":"+1 712 546 4406",
    "sg:postcode":"51031",
    "sg:province":"IA",
    "wof:name":"East Side Restaurant",
    "wof:placetype":"venue"
},
  "geometry": {"coordinates":[-96.16500000000001,42.793065],"type":"Point"}
}