{
  "type": "Feature",
  "properties": {
    "iso:country":"US",
    "sg:address":"503 3rd St",
    "sg:city":"Armstrong",
    "sg:classifiers":[
        {
            "category":"Shopping",
            "subcategory":"Gifts & Souvenirs",
            "type":"Retail Goods"
        }
    ],
    "sg:phone":"+1 712 868 3143",
    "sg:postcode":"50514",
    "sg:province":"IA",
    "sg:tags":[
        "shop"
    ],
    "wof:name":"Tiques To Treasures",
    "wof:placetype":"venue"
},
  "geometry": {"coordinates":[-94.484475,43.39833],"type":"Point"}
}