{
  "type": "Feature",
  "properties": {
    "iso:country":"US",
    "sg:address":"6887 NE 22nd St",
    "sg:city":"Ankeny",
    "sg:classifiers":[
        {
            "category":"Building & Trades",
            "subcategory":"Electrical",
            "type":"Services"
        }
    ],
    "sg:phone":"+1 515 289 2496",
    "sg:postcode":"50021",
    "sg:province":"IA",
    "sg:tags":[
        "electric",
        "contractor"
    ],
    "wof:name":"Rogers Electric & Plumbing",
    "wof:placetype":"venue"
},
  "geometry": {"coordinates":[-93.581273,41.68054],"type":"Point"}
}