{
  "type": "Feature",
  "properties": {
    "addr:full":"309 High Ave E Oskaloosa IA 52577",
    "addr:housenumber":"309",
    "addr:postcode":"52577",
    "addr:street":"High Ave E Oskaloosa",
    "iso:country":"US",
    "sg:address":"309 High Ave E",
    "sg:city":"Oskaloosa",
    "sg:classifiers":[
        {
            "category":"Insurance",
            "subcategory":"Insurance Agent",
            "type":"Services"
        }
    ],
    "sg:phone":"+1 641 673 8603",
    "sg:postcode":"52577",
    "sg:province":"IA",
    "wof:name":"Butler-Brown Insurance Svc",
    "wof:placetype":"venue"
},
  "geometry": {"coordinates":[-92.64256399999999,41.295435],"type":"Point"}
}