{
  "type": "Feature",
  "properties": {
    "addr:full":"507 N Dubuque St Albion IA 50005",
    "addr:housenumber":"507",
    "addr:postcode":"50005",
    "addr:street":"N Dubuque St",
    "iso:country":"US",
    "sg:address":"507 N Dubuque St",
    "sg:city":"Albion",
    "sg:classifiers":[
        {
            "category":"Shopping",
            "subcategory":"Hobbies, Toys, & Games",
            "type":"Retail Goods"
        },
        {
            "category":"Shopping",
            "subcategory":"Luggage & Leather Goods",
            "type":"Retail Goods"
        }
    ],
    "sg:phone":"+1 641 488 2250",
    "sg:postcode":"50005",
    "sg:province":"IA",
    "wof:name":"Sharon's Leathers",
    "wof:placetype":"venue"
},
  "geometry": {"coordinates":[-92.99094599999999,42.117305],"type":"Point"}
}