{
  "type": "Feature",
  "properties": {
    "iso:country":"US",
    "sg:address":"1014 Pleasant Dr",
    "sg:city":"Parkersburg",
    "sg:classifiers":[
        {
            "category":"Building & Trades",
            "subcategory":"Electrical",
            "type":"Services"
        }
    ],
    "sg:phone":"+1 319 346 1379",
    "sg:postcode":"50665",
    "sg:province":"IA",
    "sg:tags":[
        "electrical",
        "contractor"
    ],
    "wof:name":"Oelmann Electric",
    "wof:placetype":"venue"
},
  "geometry": {"coordinates":[-92.779535,42.56811],"type":"Point"}
}