{
  "type": "Feature",
  "properties": {
    "iso:country":"US",
    "sg:address":"648 13th Ave SW",
    "sg:city":"Sioux Center",
    "sg:classifiers":[
        {
            "category":"Building & Trades",
            "subcategory":"Cleaning & Sanitation",
            "type":"Services"
        }
    ],
    "sg:phone":"+1 712 722 3422",
    "sg:postcode":"51250",
    "sg:province":"IA",
    "wof:name":"Service Master Of Nw Iowa",
    "wof:placetype":"venue"
},
  "geometry": {"coordinates":[-96.19511900000001,43.071502],"type":"Point"}
}