{
  "type": "Feature",
  "properties": {
    "iso:country":"US",
    "sg:address":"208 W Main St",
    "sg:city":"Anamosa",
    "sg:classifiers":[
        {
            "category":"Professional",
            "subcategory":"Advertising",
            "type":"Services"
        }
    ],
    "sg:phone":"+1 319 462 2744",
    "sg:postcode":"52205",
    "sg:province":"IA",
    "wof:name":"Town Crier",
    "wof:placetype":"venue"
},
  "geometry": {"coordinates":[-91.287959,42.108308],"type":"Point"}
}