{
  "type": "Feature",
  "properties": {
    "addr:full":"1610 20th St Rock Valley IA 51247",
    "addr:housenumber":"1610",
    "addr:postcode":"51247",
    "addr:street":"20Th St",
    "iso:country":"US",
    "sg:address":"1610 20th St",
    "sg:city":"Rock Valley",
    "sg:classifiers":[
        {
            "category":"Real Estate",
            "subcategory":"Real Estate Operator",
            "type":"Services"
        }
    ],
    "sg:phone":"+1 712 476 5952",
    "sg:postcode":"51247",
    "sg:province":"IA",
    "sg:tags":[
        "apartment"
    ],
    "wof:name":"Riverview Apartments",
    "wof:placetype":"venue"
},
  "geometry": {"coordinates":[-96.294854,43.210782],"type":"Point"}
}