{
  "type": "Feature",
  "properties": {
    "iso:country":"US",
    "sg:address":"1610 20th St",
    "sg:city":"Rock Valley",
    "sg:classifiers":[
        {
            "category":"Real Estate",
            "subcategory":"Real Estate Operator",
            "type":"Services"
        }
    ],
    "sg:phone":"+1 712 476 5952",
    "sg:postcode":"51247",
    "sg:province":"IA",
    "sg:tags":[
        "apartment"
    ],
    "wof:name":"Riverview Apartments",
    "wof:placetype":"venue"
},
  "geometry": {"coordinates":[-96.294854,43.210782],"type":"Point"}
}