{
  "type": "Feature",
  "properties": {
    "addr:full":"1012 1st Ave SW Oelwein IA 50662",
    "addr:housenumber":"1012",
    "addr:postcode":"50662",
    "addr:street":"1St Ave Sw",
    "iso:country":"US",
    "sg:address":"1012 1st Ave SW",
    "sg:city":"Oelwein",
    "sg:classifiers":[
        {
            "category":"Professional",
            "subcategory":"Business Services",
            "type":"Services"
        }
    ],
    "sg:phone":"+1 319 283 2061",
    "sg:postcode":"50662",
    "sg:province":"IA",
    "sg:tags":[
        "sharpening",
        "tool"
    ],
    "wof:name":"Carls Saw Sharpening",
    "wof:placetype":"venue"
},
  "geometry": {"coordinates":[-91.91500499999999,42.663723],"type":"Point"}
}