{
  "type": "Feature",
  "properties": {
    "iso:country":"US",
    "sg:address":"629 S Linn St",
    "sg:city":"Sioux City",
    "sg:classifiers":[
        {
            "category":"Building & Trades",
            "subcategory":"Construction",
            "type":"Services"
        }
    ],
    "sg:phone":"+1 712 276 7654",
    "sg:postcode":"51106",
    "sg:province":"IA",
    "sg:tags":[
        "painter"
    ],
    "wof:name":"Timothy Jacobs Contracting",
    "wof:placetype":"venue"
},
  "geometry": {"coordinates":[-96.375963,42.485295],"type":"Point"}
}