{
  "type": "Feature",
  "properties": {
    "addr:full":"509 Ave D West Point IA 52656",
    "addr:housenumber":"509",
    "addr:postcode":"52656",
    "addr:street":"Ave D",
    "iso:country":"US",
    "sg:address":"509 Ave D",
    "sg:city":"West Point",
    "sg:classifiers":[
        {
            "category":"Banks & Credit Unions",
            "subcategory":"Bank",
            "type":"Services"
        }
    ],
    "sg:phone":"+1 319 837 6121",
    "sg:postcode":"52656",
    "sg:province":"IA",
    "wof:name":"Pilot Grove Savings Bank",
    "wof:placetype":"venue"
},
  "geometry": {"coordinates":[-91.45235599999999,40.716576],"type":"Point"}
}