{
  "type": "Feature",
  "properties": {
    "iso:country":"US",
    "sg:address":"601 5th Ave",
    "sg:city":"Prescott",
    "sg:classifiers":[
        {
            "category":"Building & Trades",
            "subcategory":"Landscaping Services",
            "type":"Services"
        }
    ],
    "sg:phone":"+1 641 335 2255",
    "sg:postcode":"50859",
    "sg:province":"IA",
    "wof:name":"Bloom Where You Stand",
    "wof:placetype":"venue"
},
  "geometry": {"coordinates":[-94.616866,41.021694],"type":"Point"}
}