{
  "type": "Feature",
  "properties": {
    "addr:full":"290 Okoboji Grove Rd Arnolds Park IA 51331",
    "addr:housenumber":"290",
    "addr:postcode":"51331",
    "addr:street":"Okoboji Grove Rd",
    "iso:country":"US",
    "sg:address":"290 Okoboji Grove Rd",
    "sg:city":"Arnolds Park",
    "sg:classifiers":[
        {
            "category":"Bars & Pubs",
            "type":"Food & Drink"
        }
    ],
    "sg:phone":"+1 712 332 9416",
    "sg:postcode":"51331",
    "sg:province":"IA",
    "sg:tags":[
        "lounge",
        "cocktail"
    ],
    "wof:name":"Regal Beagle",
    "wof:placetype":"venue"
},
  "geometry": {"coordinates":[-95.13785799999999,43.364347],"type":"Point"}
}