{
  "type": "Feature",
  "properties": {
    "iso:country":"US",
    "sg:address":"524 Center St",
    "sg:city":"Sioux City",
    "sg:classifiers":[
        {
            "category":"Organizations",
            "subcategory":"Religious Organization",
            "type":"Services"
        }
    ],
    "sg:phone":"+1 712 255 5162",
    "sg:postcode":"51103",
    "sg:province":"IA",
    "sg:tags":[
        "church"
    ],
    "wof:name":"St Paul Episcopal Church",
    "wof:placetype":"venue"
},
  "geometry": {"coordinates":[-96.42092700000001,42.502827],"type":"Point"}
}