{
  "type": "Feature",
  "properties": {
    "iso:country":"US",
    "sg:address":"924 Jones St",
    "sg:city":"Sioux City",
    "sg:classifiers":[
        {
            "category":"Organizations",
            "subcategory":"Religious Organization",
            "type":"Services"
        }
    ],
    "sg:phone":"+1 712 255 4808",
    "sg:postcode":"51105",
    "sg:province":"IA",
    "wof:name":"Siouxland Mltcultural Ministry",
    "wof:placetype":"venue"
},
  "geometry": {"coordinates":[-96.4008,42.499927],"type":"Point"}
}