{
  "type": "Feature",
  "properties": {
    "iso:country":"US",
    "sg:address":"5648 US Hwy 59",
    "sg:city":"Cherokee",
    "sg:classifiers":[
        {
            "category":"Manufacturing",
            "subcategory":"Wood Products",
            "type":"Manufacturing & Wholesale Goods"
        }
    ],
    "sg:phone":"+1 712 225 5115",
    "sg:postcode":"51012",
    "sg:province":"IA",
    "sg:website":"www.pilotrock.com",
    "wof:name":"R J Thomas Mfg Co Inc",
    "wof:placetype":"venue"
},
  "geometry": {"coordinates":[-95.554624,42.695279],"type":"Point"}
}