{
  "type": "Feature",
  "properties": {
    "iso:country":"US",
    "sg:address":"509 US Hwy 61",
    "sg:city":"Wapello",
    "sg:classifiers":[
        {
            "category":"Retail",
            "subcategory":"Auto Repair",
            "type":"Services"
        }
    ],
    "sg:phone":"+1 319 523 4074",
    "sg:postcode":"52653",
    "sg:province":"IA",
    "sg:tags":[
        "repairing",
        "automobile"
    ],
    "wof:name":"Snyder's Auto Repair",
    "wof:placetype":"venue"
},
  "geometry": {"coordinates":[-91.195903,41.183871],"type":"Point"}
}