{
  "type": "Feature",
  "properties": {
    "addr:full":"709 S 5th St Wapello IA 52653",
    "addr:housenumber":"709",
    "addr:postcode":"52653",
    "addr:street":"S 5Th St",
    "iso:country":"US",
    "sg:address":"709 S 5th St",
    "sg:city":"Wapello",
    "sg:classifiers":[
        {
            "category":"Shopping",
            "subcategory":"Clothing, Apparel, & Fashions",
            "type":"Retail Goods"
        }
    ],
    "sg:phone":"+1 319 523 6603",
    "sg:postcode":"52653",
    "sg:province":"IA",
    "wof:name":"Shirts By Lou Ann",
    "wof:placetype":"venue"
},
  "geometry": {"coordinates":[-91.18661299999999,41.173134],"type":"Point"}
}