{
  "type": "Feature",
  "properties": {
    "iso:country":"US",
    "sg:address":"943 Cottonwood Ave",
    "sg:city":"Iowa City",
    "sg:classifiers":[
        {
            "category":"Professional",
            "type":"Services"
        }
    ],
    "sg:phone":"+1 319 338 6768",
    "sg:postcode":"52240",
    "sg:province":"IA",
    "wof:name":"Carberry Enviro Svc",
    "wof:placetype":"venue"
},
  "geometry": {"coordinates":[-91.521683,41.645025],"type":"Point"}
}