{
  "type": "Feature",
  "properties": {
    "iso:country":"US",
    "sg:address":"902 Sycamore St",
    "sg:city":"Dallas Center",
    "sg:classifiers":[
        {
            "category":"Building & Trades",
            "subcategory":"Construction",
            "type":"Services"
        }
    ],
    "sg:phone":"+1 515 202 7383",
    "sg:postcode":"50063",
    "sg:province":"IA",
    "sg:tags":[
        "shed",
        "utility"
    ],
    "wof:name":"Backyard Sheds",
    "wof:placetype":"venue"
},
  "geometry": {"coordinates":[-93.95590300000001,41.683241],"type":"Point"}
}