{
  "type": "Feature",
  "properties": {
    "iso:country":"US",
    "sg:address":"1518 Smith St",
    "sg:city":"Burlington",
    "sg:classifiers":[
        {
            "category":"Arts & Performance",
            "subcategory":"Theater",
            "type":"Entertainment"
        }
    ],
    "sg:phone":"+1 319 753 6974",
    "sg:postcode":"52601",
    "sg:province":"IA",
    "sg:tags":[
        "live",
        "music"
    ],
    "wof:name":"Premium Sound Productions",
    "wof:placetype":"venue"
},
  "geometry": {"coordinates":[-91.117653,40.808719],"type":"Point"}
}