{
  "type": "Feature",
  "properties": {
    "iso:country":"US",
    "sg:address":"114 E Monroe St",
    "sg:city":"Mt Pleasant",
    "sg:classifiers":[
        {
            "category":"Education",
            "subcategory":"School",
            "type":"Public Place"
        }
    ],
    "sg:phone":"+1 319 385 9005",
    "sg:postcode":"52641",
    "sg:province":"IA",
    "wof:name":"Area Education Agency",
    "wof:placetype":"venue"
},
  "geometry": {"coordinates":[-91.55304599999999,40.966472],"type":"Point"}
}