{
  "type": "Feature",
  "properties": {
    "addr:full":"114 NW 5th St Ankeny IA 50023",
    "addr:housenumber":"114",
    "addr:postcode":"50023",
    "addr:street":"Nw 5Th St",
    "iso:country":"US",
    "sg:address":"114 NW 5th St",
    "sg:city":"Ankeny",
    "sg:classifiers":[
        {
            "category":"Professional",
            "subcategory":"Lawyer & Legal Services",
            "type":"Services"
        }
    ],
    "sg:phone":"+1 515 964 9469",
    "sg:postcode":"50023",
    "sg:province":"IA",
    "wof:name":"Smeader Gerry W",
    "wof:placetype":"venue"
},
  "geometry": {"coordinates":[-93.602388,41.735511],"type":"Point"}
}