{
  "type": "Feature",
  "properties": {
    "iso:country":"US",
    "sg:address":"1965 SE Delaware Ave",
    "sg:city":"Ankeny",
    "sg:classifiers":[
        {
            "category":"Shopping",
            "subcategory":"Department Store",
            "type":"Retail Goods"
        }
    ],
    "sg:phone":"+1 515 963 9119",
    "sg:postcode":"50021",
    "sg:province":"IA",
    "sg:tags":[
        "shop"
    ],
    "wof:name":"Pier 1 Imports",
    "wof:placetype":"venue"
},
  "geometry": {"coordinates":[-93.58112199999999,41.712089],"type":"Point"}
}