{
  "type": "Feature",
  "properties": {
    "iso:country":"US",
    "sg:address":"402 Queen St",
    "sg:city":"Fonda",
    "sg:classifiers":[
        {
            "category":"Farming",
            "subcategory":"Farm",
            "type":"Manufacturing & Wholesale Goods"
        }
    ],
    "sg:phone":"+1 712 288 6610",
    "sg:postcode":"50540",
    "sg:province":"IA",
    "sg:tags":[
        "crop",
        "general"
    ],
    "wof:name":"Fred Kraft",
    "wof:placetype":"venue"
},
  "geometry": {"coordinates":[-94.842085,42.584434],"type":"Point"}
}