{
  "type": "Feature",
  "properties": {
    "iso:country":"US",
    "sg:address":"2425 W 20th St",
    "sg:city":"Sioux City",
    "sg:classifiers":[
        {
            "category":"Freight",
            "type":"Transportation"
        }
    ],
    "sg:phone":"+1 712 258 0332",
    "sg:postcode":"51103",
    "sg:province":"IA",
    "sg:tags":[
        "commercial",
        "storage"
    ],
    "wof:name":"Brothers LLC",
    "wof:placetype":"venue"
},
  "geometry": {"coordinates":[-96.44096500000001,42.510857],"type":"Point"}
}