{
  "type": "Feature",
  "properties": {
    "addr:full":"1189 200th St State Center IA 50247",
    "addr:housenumber":"1189",
    "addr:postcode":"50247",
    "addr:street":"200Th St",
    "iso:country":"US",
    "sg:address":"1189 200th St",
    "sg:city":"State Center",
    "sg:classifiers":[
        {
            "category":"Farming",
            "subcategory":"Livestock Farm",
            "type":"Manufacturing & Wholesale Goods"
        }
    ],
    "sg:phone":"+1 641 483 2291",
    "sg:postcode":"50247",
    "sg:province":"IA",
    "wof:name":"Jeff Sandage",
    "wof:placetype":"venue"
},
  "geometry": {"coordinates":[-93.19722,42.063197],"type":"Point"}
}