{
  "type": "Feature",
  "properties": {
    "iso:country":"US",
    "sg:address":"933 E 53rd St",
    "sg:city":"Davenport",
    "sg:classifiers":[
        {
            "category":"Wholesale",
            "subcategory":"Office Equipment",
            "type":"Manufacturing & Wholesale Goods"
        }
    ],
    "sg:phone":"+1 563 391 7696",
    "sg:postcode":"52807",
    "sg:province":"IA",
    "sg:tags":[
        "machine",
        "duplicating",
        "copying"
    ],
    "sg:website":"www.commandbusiness.com",
    "wof:name":"Command Business Systems Inc",
    "wof:placetype":"venue"
},
  "geometry": {"coordinates":[-90.56254800000001,41.574538],"type":"Point"}
}