{
  "type": "Feature",
  "properties": {
    "addr:full":"1794 Washington Ave Belmond IA 50421",
    "addr:housenumber":"1794",
    "addr:postcode":"50421",
    "addr:street":"Washington Ave",
    "iso:country":"US",
    "sg:address":"1794 Washington Ave",
    "sg:city":"Belmond",
    "sg:classifiers":[
        {
            "category":"Farming",
            "subcategory":"Livestock Farm",
            "type":"Manufacturing & Wholesale Goods"
        }
    ],
    "sg:phone":"+1 641 444 4636",
    "sg:postcode":"50421",
    "sg:province":"IA",
    "sg:tags":[
        "hog"
    ],
    "wof:name":"Sunsix Pork LLC",
    "wof:placetype":"venue"
},
  "geometry": {"coordinates":[-93.53833899999999,42.789881],"type":"Point"}
}