{
  "type": "Feature",
  "properties": {
    "iso:country":"US",
    "sg:address":"1027 Rainbow Dr",
    "sg:city":"Cedar Falls",
    "sg:classifiers":[
        {
            "category":"Real Estate",
            "subcategory":"Real Estate Agent",
            "type":"Services"
        }
    ],
    "sg:phone":"+1 319 273 9114",
    "sg:postcode":"50613",
    "sg:province":"IA",
    "wof:name":"Stone Appraisals Service",
    "wof:placetype":"venue"
},
  "geometry": {"coordinates":[-92.43321299999999,42.521068],"type":"Point"}
}