{
  "type": "Feature",
  "properties": {
    "iso:country":"US",
    "sg:address":"3100 Cedar Crest Rdg # 4",
    "sg:city":"Dubuque",
    "sg:classifiers":[
        {
            "category":"Health Services",
            "subcategory":"Health Practitioner",
            "type":"Services"
        },
        {
            "category":"Health Services",
            "subcategory":"Chiropractor",
            "type":"Services"
        }
    ],
    "sg:phone":"+1 563 557 3040",
    "sg:postcode":"52003",
    "sg:province":"IA",
    "sg:tags":[
        "acupuncture",
        "alternative",
        "medicine",
        "chiropractic"
    ],
    "wof:name":"Dolezal Chiropractic Acup",
    "wof:placetype":"venue"
},
  "geometry": {"coordinates":[-90.709457,42.476501],"type":"Point"}
}