{
  "type": "Feature",
  "properties": {
    "iso:country":"US",
    "sg:address":"1501 Grandview Ave",
    "sg:city":"Waterloo",
    "sg:classifiers":[
        {
            "category":"Wholesale",
            "subcategory":"Auto Parts",
            "type":"Manufacturing & Wholesale Goods"
        }
    ],
    "sg:phone":"+1 319 234 5207",
    "sg:postcode":"50703",
    "sg:province":"IA",
    "sg:tags":[
        "automobile",
        "rebuilt"
    ],
    "sg:website":"www.waterlooautoparts.com",
    "wof:name":"Waterloo Auto Parts Inc",
    "wof:placetype":"venue"
},
  "geometry": {"coordinates":[-92.350037,42.522327],"type":"Point"}
}