{
  "type": "Feature",
  "properties": {
    "iso:country":"US",
    "sg:address":"802 Cypress St",
    "sg:city":"Muscatine",
    "sg:classifiers":[
        {
            "category":"Food & Beverages",
            "subcategory":"Groceries & Convenience Stores",
            "type":"Retail Goods"
        }
    ],
    "sg:phone":"+1 563 264 0980",
    "sg:postcode":"52761",
    "sg:province":"IA",
    "wof:name":"Mac's",
    "wof:placetype":"venue"
},
  "geometry": {"coordinates":[-91.041735,41.432132],"type":"Point"}
}