{
  "type": "Feature",
  "properties": {
    "iso:country":"US",
    "sg:address":"328 Washington St",
    "sg:city":"Decorah",
    "sg:classifiers":[
        {
            "category":"Insurance",
            "subcategory":"Hazard Insurance",
            "type":"Services"
        }
    ],
    "sg:phone":"+1 563 382 4008",
    "sg:postcode":"52101",
    "sg:province":"IA",
    "sg:tags":[
        "commercial",
        "business"
    ],
    "sg:website":"http://www.principal.com",
    "wof:name":"Principal Financial Group",
    "wof:placetype":"venue"
},
  "geometry": {"coordinates":[-91.785873,43.301949],"type":"Point"}
}