{
  "type": "Feature",
  "properties": {
    "iso:country":"US",
    "sg:address":"3848 6th Ave",
    "sg:city":"Des Moines",
    "sg:classifiers":[
        {
            "category":"Autos & Motor Vehicles",
            "subcategory":"Fuel & Gas Station",
            "type":"Retail Goods"
        }
    ],
    "sg:phone":"+1 515 288 2057",
    "sg:postcode":"50313",
    "sg:province":"IA",
    "sg:tags":[
        "oil"
    ],
    "wof:name":"Oak Park Svc",
    "wof:placetype":"venue"
},
  "geometry": {"coordinates":[-93.62485700000001,41.630437],"type":"Point"}
}