{
  "type": "Feature",
  "properties": {
    "iso:country":"US",
    "sg:address":"1212 Lucinda St",
    "sg:city":"Perry",
    "sg:classifiers":[
        {
            "category":"Utilities",
            "subcategory":"Refuse",
            "type":"Services"
        }
    ],
    "sg:phone":"+1 515 465 3919",
    "sg:postcode":"50220",
    "sg:province":"IA",
    "sg:tags":[
        "sanitation"
    ],
    "wof:name":"DCS Sanitation Management",
    "wof:placetype":"venue"
},
  "geometry": {"coordinates":[-94.10504,41.840637],"type":"Point"}
}