{
  "type": "Feature",
  "properties": {
    "iso:country":"US",
    "sg:address":"4440 Hwy 71",
    "sg:city":"Sioux Rapids",
    "sg:classifiers":[
        {
            "category":"Education",
            "subcategory":"School",
            "type":"Public Place"
        }
    ],
    "sg:phone":"+1 712 283 2312",
    "sg:postcode":"50585",
    "sg:province":"IA",
    "wof:name":"Headstart Sioux Rapids",
    "wof:placetype":"venue"
},
  "geometry": {"coordinates":[-95.161399,43.004267],"type":"Point"}
}