{
  "type": "Feature",
  "properties": {
    "addr:full":"702 Lincoln Ave SE Orange City IA 51041",
    "addr:housenumber":"702",
    "addr:postcode":"51041",
    "addr:street":"Lincoln Ave Se",
    "iso:country":"US",
    "sg:address":"702 Lincoln Ave SE",
    "sg:city":"Orange City",
    "sg:classifiers":[
        {
            "category":"Wholesale",
            "subcategory":"Non-durable Goods",
            "type":"Manufacturing & Wholesale Goods"
        }
    ],
    "sg:phone":"+1 712 737 3807",
    "sg:postcode":"51041",
    "sg:province":"IA",
    "wof:name":"Van Wechel Shirley",
    "wof:placetype":"venue"
},
  "geometry": {"coordinates":[-96.046345,42.999507],"type":"Point"}
}