{
  "type": "Feature",
  "properties": {
    "iso:country":"US",
    "sg:address":"1907 200th St",
    "sg:city":"Garner",
    "sg:classifiers":[
        {
            "category":"Organizations",
            "subcategory":"Religious Organization",
            "type":"Services"
        }
    ],
    "sg:phone":"+1 641 923 3060",
    "sg:postcode":"50438",
    "sg:province":"IA",
    "sg:tags":[
        "church"
    ],
    "wof:name":"Peace Reformed Church In Us",
    "wof:placetype":"venue"
},
  "geometry": {"coordinates":[-93.606818,43.053284],"type":"Point"}
}