{
  "type": "Feature",
  "properties": {
    "addr:full":"500 Jefferson St Waterloo IA 50701",
    "addr:housenumber":"500",
    "addr:postcode":"50701",
    "addr:street":"Jefferson St",
    "iso:country":"US",
    "sg:address":"500 Jefferson St",
    "sg:city":"Waterloo",
    "sg:classifiers":[
        {
            "category":"Wholesale",
            "subcategory":"Construction Materials",
            "type":"Manufacturing & Wholesale Goods"
        }
    ],
    "sg:phone":"+1 319 235 1779",
    "sg:postcode":"50701",
    "sg:province":"IA",
    "sg:tags":[
        "fence"
    ],
    "wof:name":"Country Estate Fence",
    "wof:placetype":"venue"
},
  "geometry": {"coordinates":[-92.34062299999999,42.494341],"type":"Point"}
}