{
  "type": "Feature",
  "properties": {
    "iso:country":"US",
    "sg:address":"3305 E Bremer Ave",
    "sg:city":"Waverly",
    "sg:classifiers":[
        {
            "category":"Bars & Pubs",
            "type":"Food & Drink"
        }
    ],
    "sg:phone":"+1 319 352 4257",
    "sg:postcode":"50677",
    "sg:province":"IA",
    "sg:tags":[
        "lounge",
        "cocktail"
    ],
    "wof:name":"Risky Business Lounge",
    "wof:placetype":"venue"
},
  "geometry": {"coordinates":[-92.430948,42.714906],"type":"Point"}
}