{
  "type": "Feature",
  "properties": {
    "iso:country":"US",
    "sg:address":"116 2nd St SE",
    "sg:city":"Oelwein",
    "sg:classifiers":[
        {
            "category":"Manufacturing",
            "subcategory":"Metals",
            "type":"Manufacturing & Wholesale Goods"
        }
    ],
    "sg:phone":"+1 319 283 2225",
    "sg:postcode":"50662",
    "sg:province":"IA",
    "sg:tags":[
        "fitting",
        "fluid",
        "power"
    ],
    "sg:website":"www.rawsoncontrol.com",
    "wof:name":"Rawson Control Systems",
    "wof:placetype":"venue"
},
  "geometry": {"coordinates":[-91.911832,42.675399],"type":"Point"}
}