{
  "type": "Feature",
  "properties": {
    "addr:full":"403 W Elm St Eldon IA 52554",
    "addr:housenumber":"403",
    "addr:postcode":"52554",
    "addr:street":"W Elm St",
    "iso:country":"US",
    "sg:address":"403 W Elm St",
    "sg:city":"Eldon",
    "sg:classifiers":[
        {
            "category":"Banks & Credit Unions",
            "subcategory":"Bank",
            "type":"Services"
        }
    ],
    "sg:phone":"+1 641 652 7838",
    "sg:postcode":"52554",
    "sg:province":"IA",
    "wof:name":"Libertyville Savings Bank",
    "wof:placetype":"venue"
},
  "geometry": {"coordinates":[-92.223052,40.918467],"type":"Point"}
}