{
  "type": "Feature",
  "properties": {
    "iso:country":"US",
    "sg:address":"123 Anton Dr",
    "sg:city":"La Porte City",
    "sg:classifiers":[
        {
            "category":"Real Estate",
            "subcategory":"Real Estate Agent",
            "type":"Services"
        }
    ],
    "sg:phone":"+1 319 342 3436",
    "sg:postcode":"50651",
    "sg:province":"IA",
    "wof:name":"Winther & Assoc",
    "wof:placetype":"venue"
},
  "geometry": {"coordinates":[-92.205353,42.324563],"type":"Point"}
}