{
  "type": "Feature",
  "properties": {
    "iso:country":"US",
    "sg:address":"4815 Euclid Ave",
    "sg:city":"Des Moines",
    "sg:classifiers":[
        {
            "category":"Manufacturing",
            "subcategory":"Metals",
            "type":"Manufacturing & Wholesale Goods"
        }
    ],
    "sg:phone":"+1 515 250 6757",
    "sg:postcode":"50310",
    "sg:province":"IA",
    "sg:tags":[
        "manufacture",
        "metalwork",
        "architectural"
    ],
    "wof:name":"Railcraft Iowa LLC",
    "wof:placetype":"venue"
},
  "geometry": {"coordinates":[-93.683943,41.627199],"type":"Point"}
}