{
  "type": "Feature",
  "properties": {
    "iso:country":"US",
    "sg:address":"311 18th St",
    "sg:city":"Spirit Lake",
    "sg:classifiers":[
        {
            "category":"Social Services",
            "type":"Services"
        }
    ],
    "sg:phone":"+1 712 336 4464",
    "sg:postcode":"51360",
    "sg:province":"IA",
    "sg:tags":[
        "counselor",
        "marriage",
        "family"
    ],
    "wof:name":"Seasons Center-Community Mntl",
    "wof:placetype":"venue"
},
  "geometry": {"coordinates":[-95.094122,43.422537],"type":"Point"}
}