{
  "type": "Feature",
  "properties": {
    "iso:country":"US",
    "sg:address":"916 Decathlon Dr",
    "sg:city":"Waterloo",
    "sg:classifiers":[
        {
            "category":"Building & Trades",
            "subcategory":"Cleaning & Sanitation",
            "type":"Services"
        }
    ],
    "sg:phone":"+1 319 287 6280",
    "sg:postcode":"50701",
    "sg:province":"IA",
    "sg:tags":[
        "house"
    ],
    "wof:name":"Maidpro",
    "wof:placetype":"venue"
},
  "geometry": {"coordinates":[-92.377033,42.492695],"type":"Point"}
}