{
  "type": "Feature",
  "properties": {
    "addr:full":"409 Main St Bedford IA 50833",
    "addr:housenumber":"409",
    "addr:postcode":"50833",
    "addr:street":"Main St",
    "iso:country":"US",
    "sg:address":"409 Main St",
    "sg:city":"Bedford",
    "sg:classifiers":[
        {
            "category":"Insurance",
            "subcategory":"Insurance Agent",
            "type":"Services"
        }
    ],
    "sg:phone":"+1 712 523 3601",
    "sg:postcode":"50833",
    "sg:province":"IA",
    "wof:name":"Ewart Insurance",
    "wof:placetype":"venue"
},
  "geometry": {"coordinates":[-94.720113,40.667085],"type":"Point"}
}