{
  "type": "Feature",
  "properties": {
    "iso:country":"US",
    "sg:address":"1115 6th St",
    "sg:city":"Nevada",
    "sg:classifiers":[
        {
            "category":"Restaurant",
            "type":"Food & Drink"
        }
    ],
    "sg:phone":"+1 515 382 2444",
    "sg:postcode":"50201",
    "sg:province":"IA",
    "wof:name":"Mi Casita Mexican Restaurant",
    "wof:placetype":"venue"
},
  "geometry": {"coordinates":[-93.45217100000001,42.022575],"type":"Point"}
}