{
  "type": "Feature",
  "properties": {
    "addr:full":"416 Water St Sioux City IA 51103",
    "addr:housenumber":"416",
    "addr:postcode":"51103",
    "addr:street":"Water St",
    "iso:country":"US",
    "sg:address":"416 Water St",
    "sg:city":"Sioux City",
    "sg:classifiers":[
        {
            "category":"Manufacturing",
            "subcategory":"Signs",
            "type":"Manufacturing & Wholesale Goods"
        }
    ],
    "sg:phone":"+1 712 252 4595",
    "sg:postcode":"51103",
    "sg:province":"IA",
    "wof:name":"Avery Brothers Sign Co",
    "wof:placetype":"venue"
},
  "geometry": {"coordinates":[-96.40929,42.495038],"type":"Point"}
}