{
  "type": "Feature",
  "properties": {
    "iso:country":"US",
    "sg:address":"1031 Fayette Ave",
    "sg:city":"Kingsley",
    "sg:classifiers":[
        {
            "category":"Real Estate",
            "subcategory":"Real Estate Operator",
            "type":"Services"
        }
    ],
    "sg:phone":"+1 712 944 5349",
    "sg:postcode":"51028",
    "sg:province":"IA",
    "sg:tags":[
        "property",
        "lessor"
    ],
    "wof:name":"Harold Karrer",
    "wof:placetype":"venue"
},
  "geometry": {"coordinates":[-96.154844,42.559779],"type":"Point"}
}