{
  "type": "Feature",
  "properties": {
    "iso:country":"US",
    "sg:address":"502 N 9th Ave",
    "sg:city":"Vinton",
    "sg:classifiers":[
        {
            "category":"Health Services",
            "subcategory":"Doctor",
            "type":"Services"
        }
    ],
    "sg:phone":"+1 319 472 6270",
    "sg:postcode":"52349",
    "sg:province":"IA",
    "sg:tags":[
        "physician",
        "surgeon"
    ],
    "wof:name":"University Of Iowa Health Care",
    "wof:placetype":"venue"
},
  "geometry": {"coordinates":[-92.013335,42.175414],"type":"Point"}
}