{
  "type": "Feature",
  "properties": {
    "iso:country":"US",
    "sg:address":"27123 Yale Ave",
    "sg:city":"Shell Rock",
    "sg:classifiers":[
        {
            "category":"Building & Trades",
            "subcategory":"Construction",
            "type":"Services"
        }
    ],
    "sg:phone":"+1 319 885 6187",
    "sg:postcode":"50670",
    "sg:province":"IA",
    "sg:tags":[
        "contractor"
    ],
    "wof:name":"C & K Drywall",
    "wof:placetype":"venue"
},
  "geometry": {"coordinates":[-92.57418699999999,42.643609],"type":"Point"}
}