{
  "type": "Feature",
  "properties": {
    "iso:country":"US",
    "sg:address":"322 A Ave",
    "sg:city":"Atkins",
    "sg:classifiers":[
        {
            "category":"Food & Beverages",
            "subcategory":"Specialty",
            "type":"Retail Goods"
        }
    ],
    "sg:phone":"+1 319 446 7540",
    "sg:postcode":"52206",
    "sg:province":"IA",
    "wof:name":"Padley Eleanor Shaklee Distr",
    "wof:placetype":"venue"
},
  "geometry": {"coordinates":[-91.859173,41.993823],"type":"Point"}
}