{
  "type": "Feature",
  "properties": {
    "iso:country":"US",
    "sg:address":"27189 Horseshoe Rd",
    "sg:city":"Greeley",
    "sg:classifiers":[
        {
            "category":"Utilities",
            "subcategory":"Telephone",
            "type":"Services"
        }
    ],
    "sg:phone":"+1 563 856 3113",
    "sg:postcode":"52050",
    "sg:province":"IA",
    "sg:tags":[
        "communications"
    ],
    "wof:name":"Judy Craft",
    "wof:placetype":"venue"
},
  "geometry": {"coordinates":[-91.266935,42.661119],"type":"Point"}
}