{
  "type": "Feature",
  "properties": {
    "addr:full":"4211 High Ridge Rd Cedar Rapids IA 52403",
    "addr:housenumber":"4211",
    "addr:postcode":"52403",
    "addr:street":"High Ridge Rd",
    "iso:country":"US",
    "sg:address":"4211 High Ridge Rd",
    "sg:city":"Cedar Rapids",
    "sg:classifiers":[
        {
            "category":"Education",
            "subcategory":"School",
            "type":"Public Place"
        }
    ],
    "sg:phone":"+1 319 365 4184",
    "sg:postcode":"52403",
    "sg:province":"IA",
    "wof:name":"Iowa High Schl Baseball",
    "wof:placetype":"venue"
},
  "geometry": {"coordinates":[-91.606843,41.981848],"type":"Point"}
}