{
  "type": "Feature",
  "properties": {
    "iso:country":"US",
    "sg:address":"409 N Lincoln St",
    "sg:city":"Knoxville",
    "sg:classifiers":[
        {
            "category":"Retail",
            "subcategory":"Auto Repair",
            "type":"Services"
        }
    ],
    "sg:phone":"+1 641 842 4079",
    "sg:postcode":"50138",
    "sg:province":"IA",
    "sg:tags":[
        "repairing",
        "automobile"
    ],
    "wof:name":"Robuck's Fast Lube",
    "wof:placetype":"venue"
},
  "geometry": {"coordinates":[-93.109426,41.321773],"type":"Point"}
}