{
  "type": "Feature",
  "properties": {
    "addr:full":"14 Quarry Rd Mason City IA 50401",
    "addr:housenumber":"14",
    "addr:postcode":"50401",
    "addr:street":"Quarry Rd",
    "iso:country":"US",
    "sg:address":"14 Quarry Rd",
    "sg:city":"Mason City",
    "sg:classifiers":[
        {
            "category":"Banks & Credit Unions",
            "subcategory":"Bank",
            "type":"Services"
        }
    ],
    "sg:phone":"+1 641 423 2701",
    "sg:postcode":"50401",
    "sg:province":"IA",
    "sg:tags":[
        "broker",
        "mortgage"
    ],
    "wof:name":"Priority Mortgage",
    "wof:placetype":"venue"
},
  "geometry": {"coordinates":[-93.167565,43.157448],"type":"Point"}
}