{
  "type": "Feature",
  "properties": {
    "addr:full":"807 Oak St Guthrie Center IA 50115",
    "addr:housenumber":"807",
    "addr:postcode":"50115",
    "addr:street":"Oak St",
    "iso:country":"US",
    "sg:address":"807 Oak St",
    "sg:city":"Guthrie Center",
    "sg:classifiers":[
        {
            "category":"Professional",
            "subcategory":"Lawyer & Legal Services",
            "type":"Services"
        }
    ],
    "sg:phone":"+1 641 747 2228",
    "sg:postcode":"50115",
    "sg:province":"IA",
    "sg:tags":[
        "attorney"
    ],
    "wof:name":"Robert Feilmeyer Attorney",
    "wof:placetype":"venue"
},
  "geometry": {"coordinates":[-94.498829,41.684631],"type":"Point"}
}