{
  "type": "Feature",
  "properties": {
    "iso:country":"US",
    "sg:address":"3300 1/2 1st Ave NE",
    "sg:city":"Cedar Rapids",
    "sg:classifiers":[
        {
            "category":"Personal",
            "subcategory":"Barber",
            "type":"Services"
        }
    ],
    "sg:phone":"+1 319 365 5240",
    "sg:postcode":"52402",
    "sg:province":"IA",
    "wof:name":"Kenwood Barber Shop",
    "wof:placetype":"venue"
},
  "geometry": {"coordinates":[-91.63500000000001,42.011209],"type":"Point"}
}