{
  "type": "Feature",
  "properties": {
    "iso:country":"US",
    "sg:address":"6697 345th Ave",
    "sg:city":"Cresco",
    "sg:classifiers":[
        {
            "category":"Farming",
            "subcategory":"Livestock Farm",
            "type":"Manufacturing & Wholesale Goods"
        }
    ],
    "sg:phone":"+1 563 547 2932",
    "sg:postcode":"52136",
    "sg:province":"IA",
    "sg:tags":[
        "beef",
        "feedlot",
        "cattle"
    ],
    "wof:name":"Everett Schacht",
    "wof:placetype":"venue"
},
  "geometry": {"coordinates":[-92.08000800000001,43.428847],"type":"Point"}
}