{
  "type": "Feature",
  "properties": {
    "addr:full":"101 Jordan Creek Pkwy West Des Moines IA 50266",
    "addr:housenumber":"101",
    "addr:postcode":"50266",
    "addr:street":"Jordan Creek Pkwy",
    "iso:country":"US",
    "sg:address":"101 Jordan Creek Pkwy",
    "sg:city":"West Des Moines",
    "sg:classifiers":[
        {
            "category":"Bakery",
            "type":"Food & Drink"
        }
    ],
    "sg:menulink":"http://www.allmenus.com/ia/boone/223869-cinnabon/menu/",
    "sg:phone":"+1 515 327 9283",
    "sg:postcode":"50266",
    "sg:province":"IA",
    "sg:tags":[
        "american",
        "pastry"
    ],
    "wof:name":"Cinnabon",
    "wof:placetype":"venue"
},
  "geometry": {"coordinates":[-93.809308,41.567632],"type":"Point"}
}