{
  "type": "Feature",
  "properties": {
    "addr:full":"570 N Pennsylvania Ave Mason City IA 50401",
    "addr:housenumber":"570",
    "addr:postcode":"50401",
    "addr:street":"N Pennsylvania Ave",
    "iso:country":"US",
    "sg:address":"570 N Pennsylvania Ave",
    "sg:city":"Mason City",
    "sg:classifiers":[
        {
            "category":"Organizations",
            "subcategory":"Labor Organization",
            "type":"Services"
        }
    ],
    "sg:phone":"+1 319 233 8050",
    "sg:postcode":"50401",
    "sg:province":"IA",
    "wof:name":"IBEW",
    "wof:placetype":"venue"
},
  "geometry": {"coordinates":[-93.197929,43.156621],"type":"Point"}
}