{
  "type": "Feature",
  "properties": {
    "iso:country":"US",
    "sg:address":"300 15th St NE",
    "sg:city":"Mason City",
    "sg:classifiers":[
        {
            "category":"Social Services",
            "subcategory":"Child Care",
            "type":"Services"
        }
    ],
    "sg:phone":"+1 641 424 5599",
    "sg:postcode":"50401",
    "sg:province":"IA",
    "wof:name":"Head Start",
    "wof:placetype":"venue"
},
  "geometry": {"coordinates":[-93.197946,43.166433],"type":"Point"}
}