{
  "type": "Feature",
  "properties": {
    "iso:country":"US",
    "sg:address":"6207 10th St",
    "sg:city":"Marion",
    "sg:classifiers":[
        {
            "category":"Real Estate",
            "subcategory":"Real Estate Operator",
            "type":"Services"
        }
    ],
    "sg:phone":"+1 319 377 6542",
    "sg:postcode":"52302",
    "sg:province":"IA",
    "sg:tags":[
        "property",
        "lessor"
    ],
    "wof:name":"Sarah Fishel",
    "wof:placetype":"venue"
},
  "geometry": {"coordinates":[-91.599338,42.082922],"type":"Point"}
}