{
  "type": "Feature",
  "properties": {
    "addr:full":"20242 Hanna Ave Pacific Junction IA 51561",
    "addr:housenumber":"20242",
    "addr:postcode":"51561",
    "addr:street":"Hanna Ave",
    "iso:country":"US",
    "sg:address":"20242 Hanna Ave",
    "sg:city":"Pacific Junction",
    "sg:classifiers":[
        {
            "category":"Travel",
            "subcategory":"Hotels & Motels",
            "type":"Entertainment"
        }
    ],
    "sg:phone":"+1 712 527 9491",
    "sg:postcode":"51561",
    "sg:province":"IA",
    "sg:tags":[
        "operation"
    ],
    "wof:name":"Hidden Hill Cabin",
    "wof:placetype":"venue"
},
  "geometry": {"coordinates":[-95.79951,41.050521],"type":"Point"}
}