{
  "type": "Feature",
  "properties": {
    "iso:country":"US",
    "sg:address":"2836 Quarry Rd",
    "sg:city":"Marshalltown",
    "sg:classifiers":[
        {
            "category":"Wholesale",
            "subcategory":"Farm Supplies",
            "type":"Manufacturing & Wholesale Goods"
        }
    ],
    "sg:phone":"+1 641 752 7016",
    "sg:postcode":"50158",
    "sg:province":"IA",
    "sg:tags":[
        "buyer",
        "livestock"
    ],
    "sg:website":"www.lynchlivestock.com",
    "wof:name":"Lynch Livestock Inc",
    "wof:placetype":"venue"
},
  "geometry": {"coordinates":[-92.85659,42.042132],"type":"Point"}
}