{
  "type": "Feature",
  "properties": {
    "iso:country":"US",
    "sg:address":"202 Sadie St",
    "sg:city":"Laurens",
    "sg:classifiers":[
        {
            "category":"Home & Garden",
            "subcategory":"Garden Supply",
            "type":"Retail Goods"
        }
    ],
    "sg:phone":"+1 712 841 4477",
    "sg:postcode":"50554",
    "sg:province":"IA",
    "sg:tags":[
        "lawn",
        "mower"
    ],
    "wof:name":"Ger-Fers Sales & Svc",
    "wof:placetype":"venue"
},
  "geometry": {"coordinates":[-94.843952,42.845468],"type":"Point"}
}