{
  "type": "Feature",
  "properties": {
    "iso:country":"US",
    "sg:address":"304 S Mill St",
    "sg:city":"Lake Mills",
    "sg:classifiers":[
        {
            "category":"Government",
            "subcategory":"Police Station",
            "type":"Public Place"
        }
    ],
    "sg:phone":"+1 641 592 2188",
    "sg:postcode":"50450",
    "sg:province":"IA",
    "sg:tags":[
        "department"
    ],
    "wof:name":"Lake Mills Police Dept",
    "wof:placetype":"venue"
},
  "geometry": {"coordinates":[-93.53522599999999,43.41644],"type":"Point"}
}