{
  "type": "Feature",
  "properties": {
    "iso:country":"US",
    "sg:address":"3220 110th St",
    "sg:city":"Dunlap",
    "sg:phone":"+1 712 643 5171",
    "sg:postcode":"51529",
    "sg:province":"IA",
    "sg:tags":[
        "farm",
        "corn"
    ],
    "wof:name":"Frank Roberts",
    "wof:placetype":"venue"
},
  "geometry": {"coordinates":[-95.653751,41.890933],"type":"Point"}
}