{
  "type": "Feature",
  "properties": {
    "addr:full":"2291 L Ave Toledo IA 52342",
    "addr:housenumber":"2291",
    "addr:postcode":"52342",
    "addr:street":"L Ave",
    "iso:country":"US",
    "sg:address":"2291 L Ave",
    "sg:city":"Toledo",
    "sg:classifiers":[
        {
            "category":"Real Estate",
            "subcategory":"Real Estate Operator",
            "type":"Services"
        }
    ],
    "sg:phone":"+1 641 484 2973",
    "sg:postcode":"52342",
    "sg:province":"IA",
    "sg:tags":[
        "property",
        "lessor"
    ],
    "wof:name":"Farm Land Lease",
    "wof:placetype":"venue"
},
  "geometry": {"coordinates":[-92.55230400000001,42.108344],"type":"Point"}
}