{
  "type": "Feature",
  "properties": {
    "iso:country":"US",
    "sg:address":"1606 J Ave",
    "sg:city":"Jefferson",
    "sg:classifiers":[
        {
            "category":"Farming",
            "subcategory":"Farm",
            "type":"Manufacturing & Wholesale Goods"
        }
    ],
    "sg:phone":"+1 515 386 2481",
    "sg:postcode":"50129",
    "sg:province":"IA",
    "sg:tags":[
        "crop",
        "general"
    ],
    "wof:name":"Jon Morlan",
    "wof:placetype":"venue"
},
  "geometry": {"coordinates":[-94.454888,41.992842],"type":"Point"}
}