{
  "type": "Feature",
  "properties": {
    "iso:country":"US",
    "sg:address":"616 4th Ave E",
    "sg:city":"Spencer",
    "sg:classifiers":[
        {
            "category":"Building & Trades",
            "subcategory":"Construction",
            "type":"Services"
        }
    ],
    "sg:phone":"+1 712 262 4118",
    "sg:postcode":"51301",
    "sg:province":"IA",
    "sg:tags":[
        "excavating",
        "contractor"
    ],
    "wof:name":"Bill Stevenson Construction Co",
    "wof:placetype":"venue"
},
  "geometry": {"coordinates":[-95.139376,43.14582],"type":"Point"}
}