{
  "type": "Feature",
  "properties": {
    "addr:full":"626 E 5th St N Newton IA 50208",
    "addr:housenumber":"626",
    "addr:postcode":"50208",
    "addr:street":"E 5Th St N",
    "iso:country":"US",
    "sg:address":"626 E 5th St N",
    "sg:city":"Newton",
    "sg:classifiers":[
        {
            "category":"Professional",
            "subcategory":"Business Services",
            "type":"Services"
        }
    ],
    "sg:phone":"+1 641 792 4485",
    "sg:postcode":"50208",
    "sg:province":"IA",
    "wof:name":"Patterson James & Cuba",
    "wof:placetype":"venue"
},
  "geometry": {"coordinates":[-93.04825099999999,41.704477],"type":"Point"}
}