{
  "type": "Feature",
  "properties": {
    "addr:full":"4685 270th St Stockton IA 52769",
    "addr:housenumber":"4685",
    "addr:postcode":"52769",
    "addr:street":"270Th St",
    "iso:country":"US",
    "sg:address":"4685 270th St",
    "sg:city":"Stockton",
    "sg:classifiers":[
        {
            "category":"Personal",
            "subcategory":"Beauty Salon",
            "type":"Services"
        }
    ],
    "sg:phone":"+1 563 843 3544",
    "sg:postcode":"52769",
    "sg:province":"IA",
    "wof:name":"Dawn's Hair Designs",
    "wof:placetype":"venue"
},
  "geometry": {"coordinates":[-90.80817399999999,41.698329],"type":"Point"}
}