{
  "type": "Feature",
  "properties": {
    "iso:country":"US",
    "sg:address":"325 S 25th St",
    "sg:city":"Fort Dodge",
    "sg:classifiers":[
        {
            "category":"Restaurant",
            "type":"Food & Drink"
        }
    ],
    "sg:phone":"+1 515 576 4511",
    "sg:postcode":"50501",
    "sg:province":"IA",
    "wof:name":"Ja-Mar Drive In Restaurant",
    "wof:placetype":"venue"
},
  "geometry": {"coordinates":[-94.16304599999999,42.502993],"type":"Point"}
}