{
  "type": "Feature",
  "properties": {
    "iso:country":"US",
    "sg:address":"3275 Nolton Ave",
    "sg:city":"New London",
    "sg:phone":"+1 319 367 5585",
    "sg:postcode":"52645",
    "sg:province":"IA",
    "sg:tags":[
        "beef",
        "farm",
        "corn",
        "crop",
        "field",
        "cattle",
        "feedlot"
    ],
    "wof:name":"Larry Francy Farms",
    "wof:placetype":"venue"
},
  "geometry": {"coordinates":[-91.461747,40.83027],"type":"Point"}
}