{
  "type": "Feature",
  "properties": {
    "addr:full":"1039 5th Ave Des Moines IA 50314",
    "addr:housenumber":"1039",
    "addr:postcode":"50314",
    "addr:street":"5Th Ave",
    "iso:country":"US",
    "sg:address":"1039 5th Ave",
    "sg:city":"Des Moines",
    "sg:classifiers":[
        {
            "category":"Health Services",
            "subcategory":"Doctor",
            "type":"Services"
        }
    ],
    "sg:phone":"+1 515 244 2422",
    "sg:postcode":"50314",
    "sg:province":"IA",
    "sg:tags":[
        "physician",
        "surgeon"
    ],
    "wof:name":"Bruce J Murphy DO",
    "wof:placetype":"venue"
},
  "geometry": {"coordinates":[-93.624392,41.597169],"type":"Point"}
}