{
  "type": "Feature",
  "properties": {
    "iso:country":"US",
    "sg:address":"10851 E 100 St N",
    "sg:city":"Laurel",
    "sg:classifiers":[
        {
            "category":"Professional",
            "type":"Services"
        }
    ],
    "sg:phone":"+1 641 476 3255",
    "sg:postcode":"50141",
    "sg:province":"IA",
    "sg:tags":[
        "establishment"
    ],
    "wof:name":"Das Enterprises",
    "wof:placetype":"venue"
},
  "geometry": {"coordinates":[-92.902731,41.848925],"type":"Point"}
}