{
  "type": "Feature",
  "properties": {
    "addr:full":"801 1st Ave Rock Rapids IA 51246",
    "addr:housenumber":"801",
    "addr:postcode":"51246",
    "addr:street":"1St Ave",
    "iso:country":"US",
    "sg:address":"801 1st Ave",
    "sg:city":"Rock Rapids",
    "sg:classifiers":[
        {
            "category":"Home & Garden",
            "subcategory":"Building Materials",
            "type":"Retail Goods"
        }
    ],
    "sg:phone":"+1 712 472 2370",
    "sg:postcode":"51246",
    "sg:province":"IA",
    "wof:name":"H & S Home Building",
    "wof:placetype":"venue"
},
  "geometry": {"coordinates":[-96.17691000000001,43.431912],"type":"Point"}
}