{
  "type": "Feature",
  "properties": {
    "iso:country":"US",
    "sg:address":"22616 Grenoble Ave",
    "sg:city":"Sioux City",
    "sg:classifiers":[
        {
            "category":"Insurance",
            "subcategory":"Insurance Agent",
            "type":"Services"
        }
    ],
    "sg:phone":"+1 712 239 1907",
    "sg:postcode":"51108",
    "sg:province":"IA",
    "wof:name":"Jensens Financial Services",
    "wof:placetype":"venue"
},
  "geometry": {"coordinates":[-96.377808,42.571329],"type":"Point"}
}