{
  "type": "Feature",
  "properties": {
    "iso:country":"US",
    "sg:address":"120 E Main St",
    "sg:city":"Marshalltown",
    "sg:classifiers":[
        {
            "category":"Home & Garden",
            "subcategory":"Furniture",
            "type":"Retail Goods"
        }
    ],
    "sg:phone":"+1 641 752 6215",
    "sg:postcode":"50158",
    "sg:province":"IA",
    "wof:name":"Sit 'n Sleep Furniture Outlet",
    "wof:placetype":"venue"
},
  "geometry": {"coordinates":[-92.910988,42.049236],"type":"Point"}
}