{
  "type": "Feature",
  "properties": {
    "addr:full":"18829 200th St St Olaf IA 52072",
    "addr:housenumber":"18829",
    "addr:postcode":"52072",
    "addr:street":"200Th St",
    "iso:country":"US",
    "sg:address":"18829 200th St",
    "sg:city":"St Olaf",
    "sg:classifiers":[
        {
            "category":"Organizations",
            "subcategory":"Religious Organization",
            "type":"Services"
        }
    ],
    "sg:phone":"+1 563 783 7714",
    "sg:postcode":"52072",
    "sg:province":"IA",
    "sg:tags":[
        "church"
    ],
    "wof:name":"Norway Lutheran Church",
    "wof:placetype":"venue"
},
  "geometry": {"coordinates":[-91.439278,42.935454],"type":"Point"}
}