{
  "type": "Feature",
  "properties": {
    "iso:country":"US",
    "sg:address":"206 N Lawrence St",
    "sg:city":"Stacyville",
    "sg:classifiers":[
        {
            "category":"Food & Beverages",
            "subcategory":"Dairy",
            "type":"Retail Goods"
        }
    ],
    "sg:phone":"+1 641 710 2101",
    "sg:postcode":"50476",
    "sg:province":"IA",
    "sg:tags":[
        "product"
    ],
    "wof:name":"Stacyville Co-Op Creamery",
    "wof:placetype":"venue"
},
  "geometry": {"coordinates":[-92.780987,43.437344],"type":"Point"}
}