{
  "type": "Feature",
  "properties": {
    "iso:country":"US",
    "sg:address":"1056 Highland Ave",
    "sg:city":"Corning",
    "sg:classifiers":[
        {
            "category":"Farming",
            "subcategory":"Livestock Farm",
            "type":"Manufacturing & Wholesale Goods"
        }
    ],
    "sg:phone":"+1 641 322 5192",
    "sg:postcode":"50841",
    "sg:province":"IA",
    "sg:tags":[
        "beef",
        "feedlot",
        "cattle"
    ],
    "wof:name":"Claude Hayes",
    "wof:placetype":"venue"
},
  "geometry": {"coordinates":[-94.79520599999999,40.89554],"type":"Point"}
}