{
  "type": "Feature",
  "properties": {
    "addr:full":"415 Main St Griswold IA 51535",
    "addr:housenumber":"415",
    "addr:postcode":"51535",
    "addr:street":"Main St",
    "iso:country":"US",
    "sg:address":"415 Main St",
    "sg:city":"Griswold",
    "sg:classifiers":[
        {
            "category":"Shopping",
            "subcategory":"Crafts & Fabrics",
            "type":"Retail Goods"
        }
    ],
    "sg:phone":"+1 712 778 4221",
    "sg:postcode":"51535",
    "sg:province":"IA",
    "sg:tags":[
        "shop"
    ],
    "wof:name":"Reflections In Fabric",
    "wof:placetype":"venue"
},
  "geometry": {"coordinates":[-95.14397,41.234791],"type":"Point"}
}