{
  "type": "Feature",
  "properties": {
    "addr:full":"315 5th St NE Orange City IA 51041",
    "addr:housenumber":"315",
    "addr:postcode":"51041",
    "addr:street":"5Th St Ne",
    "iso:country":"US",
    "sg:address":"315 5th St NE",
    "sg:city":"Orange City",
    "sg:classifiers":[
        {
            "category":"Shopping",
            "subcategory":"Photographic Equipment",
            "type":"Retail Goods"
        }
    ],
    "sg:phone":"+1 712 737 3680",
    "sg:postcode":"51041",
    "sg:province":"IA",
    "sg:tags":[
        "supply"
    ],
    "wof:name":"Creative Memories Director",
    "wof:placetype":"venue"
},
  "geometry": {"coordinates":[-96.05408799999999,43.010563],"type":"Point"}
}