{
  "type": "Feature",
  "properties": {
    "iso:country":"US",
    "sg:address":"219 W 6th St",
    "sg:city":"Storm Lake",
    "sg:classifiers":[
        {
            "category":"Insurance",
            "subcategory":"Insurance Agent",
            "type":"Services"
        }
    ],
    "sg:phone":"+1 712 732 3578",
    "sg:postcode":"50588",
    "sg:province":"IA",
    "wof:name":"American Family Insurance",
    "wof:placetype":"venue"
},
  "geometry": {"coordinates":[-95.20315600000001,42.645564],"type":"Point"}
}