{
  "type": "Feature",
  "properties": {
    "iso:country":"US",
    "sg:address":"2303 19th Ave N",
    "sg:city":"Fort Dodge",
    "sg:classifiers":[
        {
            "category":"Wholesale",
            "subcategory":"Non-durable Goods",
            "type":"Manufacturing & Wholesale Goods"
        }
    ],
    "sg:phone":"+1 515 576 3297",
    "sg:postcode":"50501",
    "sg:province":"IA",
    "sg:tags":[
        "product",
        "mfg",
        "sp",
        "novelty",
        "advertising",
        "representative"
    ],
    "wof:name":"Johnston Co",
    "wof:placetype":"venue"
},
  "geometry": {"coordinates":[-94.165817,42.523717],"type":"Point"}
}