{
  "type": "Feature",
  "properties": {
    "addr:full":"11912 Hwy 99 Burlington IA 52601",
    "addr:housenumber":"11912",
    "addr:postcode":"52601",
    "addr:street":"Hwy 99",
    "iso:country":"US",
    "sg:address":"11912 Hwy 99",
    "sg:city":"Burlington",
    "sg:classifiers":[
        {
            "category":"Professional",
            "subcategory":"Business Services",
            "type":"Services"
        }
    ],
    "sg:phone":"+1 319 758 0358",
    "sg:postcode":"52601",
    "sg:province":"IA",
    "wof:name":"Maddox Distributing",
    "wof:placetype":"venue"
},
  "geometry": {"coordinates":[-91.10909599999999,40.854277],"type":"Point"}
}