{
  "type": "Feature",
  "properties": {
    "iso:country":"US",
    "sg:address":"114 S Harrison St",
    "sg:city":"Missouri Valley",
    "sg:classifiers":[
        {
            "category":"Marine",
            "type":"Transportation"
        }
    ],
    "sg:phone":"+1 712 642 2411",
    "sg:postcode":"51555",
    "sg:province":"IA",
    "wof:name":"Eds Towing & Repair",
    "wof:placetype":"venue"
},
  "geometry": {"coordinates":[-95.897626,41.55618],"type":"Point"}
}