{
  "type": "Feature",
  "properties": {
    "iso:country":"US",
    "sg:address":"722 South St",
    "sg:city":"Rockwell City",
    "sg:classifiers":[
        {
            "category":"Building & Trades",
            "subcategory":"Construction",
            "type":"Services"
        }
    ],
    "sg:phone":"+1 712 297 5128",
    "sg:postcode":"50579",
    "sg:province":"IA",
    "sg:tags":[
        "contractor"
    ],
    "wof:name":"John Johnson Construction",
    "wof:placetype":"venue"
},
  "geometry": {"coordinates":[-94.639498,42.392591],"type":"Point"}
}