{
  "type": "Feature",
  "properties": {
    "iso:country":"US",
    "sg:address":"325 S Main St",
    "sg:city":"Osceola",
    "sg:classifiers":[
        {
            "category":"Travel",
            "subcategory":"Hotels & Motels",
            "type":"Entertainment"
        }
    ],
    "sg:phone":"+1 641 342 2115",
    "sg:postcode":"50213",
    "sg:province":"IA",
    "wof:name":"Blue Haven Motel",
    "wof:placetype":"venue"
},
  "geometry": {"coordinates":[-93.765584,41.031644],"type":"Point"}
}