{
  "type": "Feature",
  "properties": {
    "iso:country":"US",
    "sg:address":"1103 Nebraska St",
    "sg:city":"Sioux City",
    "sg:classifiers":[
        {
            "category":"Real Estate",
            "subcategory":"Real Estate Operator",
            "type":"Services"
        }
    ],
    "sg:phone":"+1 712 255 9002",
    "sg:postcode":"51105",
    "sg:province":"IA",
    "sg:tags":[
        "apartment"
    ],
    "wof:name":"Argonaut",
    "wof:placetype":"venue"
},
  "geometry": {"coordinates":[-96.403634,42.502905],"type":"Point"}
}