{
  "type": "Feature",
  "properties": {
    "iso:country":"US",
    "sg:address":"720 NE 52nd Ave",
    "sg:city":"Des Moines",
    "sg:classifiers":[
        {
            "category":"Social Services",
            "subcategory":"Child Care",
            "type":"Services"
        }
    ],
    "sg:phone":"+1 515 265 0508",
    "sg:postcode":"50313",
    "sg:province":"IA",
    "sg:tags":[
        "kindergarten",
        "academic",
        "school"
    ],
    "wof:name":"Bethany Reformed Church",
    "wof:placetype":"venue"
},
  "geometry": {"coordinates":[-93.603002,41.654689],"type":"Point"}
}