{
  "type": "Feature",
  "properties": {
    "addr:full":"1217 Army Post Rd Des Moines IA 50315",
    "addr:housenumber":"1217",
    "addr:postcode":"50315",
    "addr:street":"Army Post Rd Des",
    "iso:country":"US",
    "sg:address":"1217 Army Post Rd",
    "sg:city":"Des Moines",
    "sg:classifiers":[
        {
            "category":"Professional",
            "subcategory":"Lawyer & Legal Services",
            "type":"Services"
        }
    ],
    "sg:phone":"+1 515 287 1454",
    "sg:postcode":"50315",
    "sg:province":"IA",
    "sg:tags":[
        "attorney"
    ],
    "wof:name":"Harding Harding Griffin Hobbs",
    "wof:placetype":"venue"
},
  "geometry": {"coordinates":[-93.63260200000001,41.526513],"type":"Point"}
}