{
  "type": "Feature",
  "properties": {
    "iso:country":"US",
    "sg:address":"3220 Beaver Ave",
    "sg:city":"Des Moines",
    "sg:classifiers":[
        {
            "category":"Retail",
            "subcategory":"Repair Shop",
            "type":"Services"
        }
    ],
    "sg:phone":"+1 515 279 8457",
    "sg:postcode":"50310",
    "sg:province":"IA",
    "sg:tags":[
        "lock",
        "locksmith"
    ],
    "wof:name":"Hollie Smith Glass & Door",
    "wof:placetype":"venue"
},
  "geometry": {"coordinates":[-93.67578399999999,41.625121],"type":"Point"}
}