{
  "type": "Feature",
  "properties": {
    "addr:full":"168 S 25th St Fort Dodge IA 50501",
    "addr:housenumber":"168",
    "addr:postcode":"50501",
    "addr:street":"S 25Th St",
    "iso:country":"US",
    "sg:address":"168 S 25th St",
    "sg:city":"Fort Dodge",
    "sg:classifiers":[
        {
            "category":"Shopping",
            "subcategory":"Jewelry",
            "type":"Retail Goods"
        }
    ],
    "sg:phone":"+1 515 955 6975",
    "sg:postcode":"50501",
    "sg:province":"IA",
    "sg:tags":[
        "jeweler"
    ],
    "wof:name":"Gordon's Jewelers",
    "wof:placetype":"venue"
},
  "geometry": {"coordinates":[-94.163229,42.50458],"type":"Point"}
}