{
  "type": "Feature",
  "properties": {
    "iso:country":"US",
    "sg:address":"353 9th St SW",
    "sg:city":"Sioux Center",
    "sg:classifiers":[
        {
            "category":"Wholesale",
            "subcategory":"Farm Supplies",
            "type":"Manufacturing & Wholesale Goods"
        }
    ],
    "sg:phone":"+1 712 722 3835",
    "sg:postcode":"51250",
    "sg:province":"IA",
    "sg:tags":[
        "livestock"
    ],
    "wof:name":"Northwest Order Buyers",
    "wof:placetype":"venue"
},
  "geometry": {"coordinates":[-96.181104,43.069638],"type":"Point"}
}