{
  "type": "Feature",
  "properties": {
    "iso:country":"US",
    "sg:address":"24245 White Tail Rd",
    "sg:city":"Waucoma",
    "sg:phone":"+1 563 776 7272",
    "sg:postcode":"52171",
    "sg:province":"IA",
    "sg:tags":[
        "farm",
        "corn"
    ],
    "wof:name":"Luke Schmitt",
    "wof:placetype":"venue"
},
  "geometry": {"coordinates":[-92.06661099999999,43.057535],"type":"Point"}
}