{
  "type": "Feature",
  "properties": {
    "iso:country":"US",
    "sg:address":"2315 630th St",
    "sg:city":"Newell",
    "sg:phone":"+1 712 272 3511",
    "sg:postcode":"50568",
    "sg:province":"IA",
    "sg:tags":[
        "farm",
        "corn",
        "soybean"
    ],
    "wof:name":"Joseph Wolff",
    "wof:placetype":"venue"
},
  "geometry": {"coordinates":[-94.952175,42.604094],"type":"Point"}
}