{
  "type": "Feature",
  "properties": {
    "addr:full":"3615 Jefferson Ave Boyden IA 51234",
    "addr:housenumber":"3615",
    "addr:postcode":"51234",
    "addr:street":"Jefferson Ave",
    "iso:country":"US",
    "sg:address":"3615 Jefferson Ave",
    "sg:city":"Boyden",
    "sg:classifiers":[
        {
            "category":"Farming",
            "subcategory":"Livestock Farm",
            "type":"Manufacturing & Wholesale Goods"
        }
    ],
    "sg:phone":"+1 712 752 8995",
    "sg:postcode":"51234",
    "sg:province":"IA",
    "sg:tags":[
        "hog",
        "or",
        "feedlot"
    ],
    "wof:name":"Kevin Moss",
    "wof:placetype":"venue"
},
  "geometry": {"coordinates":[-96.018843,43.125918],"type":"Point"}
}