{
  "type": "Feature",
  "properties": {
    "iso:country":"US",
    "sg:address":"2018 Three Elms Park Rd",
    "sg:city":"Independence",
    "sg:classifiers":[
        {
            "category":"Government",
            "subcategory":"Office",
            "type":"Public Place"
        }
    ],
    "sg:phone":"+1 319 334 3750",
    "sg:postcode":"50644",
    "sg:province":"IA",
    "sg:tags":[
        "village"
    ],
    "wof:name":"Independence Waste Water Plant",
    "wof:placetype":"venue"
},
  "geometry": {"coordinates":[-91.887367,42.456573],"type":"Point"}
}