{
  "type": "Feature",
  "properties": {
    "iso:country":"US",
    "sg:address":"1008 19th St",
    "sg:city":"Spirit Lake",
    "sg:classifiers":[
        {
            "category":"Social Services",
            "type":"Services"
        }
    ],
    "sg:phone":"+1 712 336 5725",
    "sg:postcode":"51360",
    "sg:province":"IA",
    "sg:tags":[
        "organization",
        "welfare"
    ],
    "wof:name":"ECHO Plus Inc",
    "wof:placetype":"venue"
},
  "geometry": {"coordinates":[-95.106185,43.421782],"type":"Point"}
}