{
  "type": "Feature",
  "properties": {
    "addr:full":"717 Seneca St Webster City IA 50595",
    "addr:housenumber":"717",
    "addr:postcode":"50595",
    "addr:street":"Seneca St",
    "iso:country":"US",
    "sg:address":"717 Seneca St",
    "sg:city":"Webster City",
    "sg:classifiers":[
        {
            "category":"Shopping",
            "type":"Retail Goods"
        }
    ],
    "sg:phone":"+1 515 832 4849",
    "sg:postcode":"50595",
    "sg:province":"IA",
    "sg:tags":[
        "equipment",
        "care",
        "health",
        "home"
    ],
    "wof:name":"My Med Mart Inc",
    "wof:placetype":"venue"
},
  "geometry": {"coordinates":[-93.817123,42.468917],"type":"Point"}
}