{
  "type": "Feature",
  "properties": {
    "iso:country":"US",
    "sg:address":"1322 Red Bridge Rd",
    "sg:city":"Central City",
    "sg:phone":"+1 319 438 6321",
    "sg:postcode":"52214",
    "sg:province":"IA",
    "sg:tags":[
        "feed",
        "beef",
        "farm",
        "corn",
        "crop",
        "field",
        "soybean",
        "cattle"
    ],
    "wof:name":"Harold Rehrauer",
    "wof:placetype":"venue"
},
  "geometry": {"coordinates":[-91.488164,42.252929],"type":"Point"}
}