{
  "type": "Feature",
  "properties": {
    "iso:country":"US",
    "sg:address":"6110 NW 86th St",
    "sg:city":"Johnston",
    "sg:classifiers":[
        {
            "category":"Building & Trades",
            "subcategory":"Landscaping Services",
            "type":"Services"
        }
    ],
    "sg:phone":"+1 515 334 3444",
    "sg:postcode":"50131",
    "sg:province":"IA",
    "sg:tags":[
        "tree"
    ],
    "wof:name":"Sage Tree Inc",
    "wof:placetype":"venue"
},
  "geometry": {"coordinates":[-93.736547,41.672429],"type":"Point"}
}