{
  "type": "Feature",
  "properties": {
    "iso:country":"US",
    "sg:address":"14 Walbrier Ct",
    "sg:city":"Le Claire",
    "sg:classifiers":[
        {
            "category":"Professional",
            "subcategory":"Advertising",
            "type":"Services"
        }
    ],
    "sg:phone":"+1 563 449 9958",
    "sg:postcode":"52753",
    "sg:province":"IA",
    "sg:tags":[
        "counselor"
    ],
    "wof:name":"Adesign Inc",
    "wof:placetype":"venue"
},
  "geometry": {"coordinates":[-90.382755,41.582411],"type":"Point"}
}