{
  "type": "Feature",
  "properties": {
    "iso:country":"US",
    "sg:address":"325 2nd Ave SW",
    "sg:city":"Cresco",
    "sg:classifiers":[
        {
            "category":"Arts & Performance",
            "subcategory":"Theater",
            "type":"Entertainment"
        }
    ],
    "sg:phone":"+1 563 547 4292",
    "sg:postcode":"52136",
    "sg:province":"IA",
    "wof:name":"Cresco Theatre",
    "wof:placetype":"venue"
},
  "geometry": {"coordinates":[-92.120553,43.371133],"type":"Point"}
}