{
  "type": "Feature",
  "properties": {
    "iso:country":"US",
    "sg:address":"135 3rd Ave SW",
    "sg:city":"Le Mars",
    "sg:classifiers":[
        {
            "category":"Personal",
            "subcategory":"Beauty Salon",
            "type":"Services"
        }
    ],
    "sg:phone":"+1 712 546 7210",
    "sg:postcode":"51031",
    "sg:province":"IA",
    "wof:name":"Bev's Hair Fashions",
    "wof:placetype":"venue"
},
  "geometry": {"coordinates":[-96.17088,42.791404],"type":"Point"}
}