{
  "type": "Feature",
  "properties": {
    "iso:country":"US",
    "sg:address":"1419 Washington St",
    "sg:city":"Pella",
    "sg:classifiers":[
        {
            "category":"Manufacturing",
            "subcategory":"Tools & Machinery",
            "type":"Manufacturing & Wholesale Goods"
        }
    ],
    "sg:phone":"+1 641 628 8034",
    "sg:postcode":"50219",
    "sg:province":"IA",
    "sg:tags":[
        "machine",
        "shop"
    ],
    "wof:name":"Pella Machine Inc",
    "wof:placetype":"venue"
},
  "geometry": {"coordinates":[-92.92862100000001,41.408763],"type":"Point"}
}