{
  "type": "Feature",
  "properties": {
    "iso:country":"US",
    "sg:address":"1629 Main Ave",
    "sg:city":"Clinton",
    "sg:classifiers":[
        {
            "category":"Personal",
            "type":"Services"
        },
        {
            "category":"Retail",
            "subcategory":"Auto Repair",
            "type":"Services"
        },
        {
            "category":"Utilities",
            "type":"Services"
        }
    ],
    "sg:phone":"+1 563 243 8869",
    "sg:postcode":"52732",
    "sg:province":"IA",
    "sg:tags":[
        "body",
        "automobile",
        "removal",
        "equipment",
        "towing",
        "dent",
        "painting",
        "repairing"
    ],
    "sg:website":"http://gripstowing.com/",
    "wof:name":"Grips Towing and Auto Body",
    "wof:placetype":"venue"
},
  "geometry": {"coordinates":[-90.218395,41.873847],"type":"Point"}
}