{
  "type": "Feature",
  "properties": {
    "iso:country":"US",
    "sg:address":"1515 Columbia Dr",
    "sg:city":"Cedar Falls",
    "sg:classifiers":[
        {
            "category":"Health Services",
            "subcategory":"Health Practitioner",
            "type":"Services"
        }
    ],
    "sg:phone":"+1 319 266 6242",
    "sg:postcode":"50613",
    "sg:province":"IA",
    "sg:tags":[
        "psychologist"
    ],
    "wof:name":"Ralph Scott",
    "wof:placetype":"venue"
},
  "geometry": {"coordinates":[-92.45814799999999,42.524161],"type":"Point"}
}