{
  "type": "Feature",
  "properties": {
    "iso:country":"US",
    "sg:address":"109 S Phillips St",
    "sg:city":"Algona",
    "sg:classifiers":[
        {
            "category":"Utilities",
            "subcategory":"Mobile Phone",
            "type":"Services"
        }
    ],
    "sg:phone":"+1 515 295 9202",
    "sg:postcode":"50511",
    "sg:province":"IA",
    "sg:tags":[
        "telephone",
        "cellular"
    ],
    "wof:name":"Midwest Wireless",
    "wof:placetype":"venue"
},
  "geometry": {"coordinates":[-94.226744,43.068833],"type":"Point"}
}