{
  "type": "Feature",
  "properties": {
    "iso:country":"US",
    "sg:address":"1104 4th St SW",
    "sg:city":"Altoona",
    "sg:classifiers":[
        {
            "category":"Real Estate",
            "subcategory":"Real Estate Operator",
            "type":"Services"
        }
    ],
    "sg:phone":"+1 515 967 4116",
    "sg:postcode":"50009",
    "sg:province":"IA",
    "sg:tags":[
        "apartment"
    ],
    "wof:name":"Altoona Terrace Apartments",
    "wof:placetype":"venue"
},
  "geometry": {"coordinates":[-93.47706700000001,41.648442],"type":"Point"}
}