{
  "type": "Feature",
  "properties": {
    "iso:country":"US",
    "sg:address":"718 W Sheridan Ave",
    "sg:city":"Shenandoah",
    "sg:classifiers":[
        {
            "category":"Shopping",
            "subcategory":"Musical Instruments",
            "type":"Retail Goods"
        }
    ],
    "sg:phone":"+1 712 246 2100",
    "sg:postcode":"51601",
    "sg:province":"IA",
    "wof:name":"Generation Music",
    "wof:placetype":"venue"
},
  "geometry": {"coordinates":[-95.374956,40.765863],"type":"Point"}
}