{
  "type": "Feature",
  "properties": {
    "iso:country":"US",
    "sg:address":"2501 Floyd Blvd",
    "sg:city":"Sioux City",
    "sg:classifiers":[
        {
            "category":"Food & Beverages",
            "subcategory":"Groceries & Convenience Stores",
            "type":"Retail Goods"
        }
    ],
    "sg:phone":"+1 712 258 0031",
    "sg:postcode":"51104",
    "sg:province":"IA",
    "wof:name":"Hoc Floyd",
    "wof:placetype":"venue"
},
  "geometry": {"coordinates":[-96.38494799999999,42.516129],"type":"Point"}
}