{
  "type": "Feature",
  "properties": {
    "iso:country":"US",
    "sg:address":"5505 Cody Dr",
    "sg:city":"West Des Moines",
    "sg:classifiers":[
        {
            "category":"Professional",
            "subcategory":"Business Services",
            "type":"Services"
        }
    ],
    "sg:phone":"+1 515 267 0866",
    "sg:postcode":"50266",
    "sg:province":"IA",
    "wof:name":"Patnic Enterprises Inc",
    "wof:placetype":"venue"
},
  "geometry": {"coordinates":[-93.78431,41.577569],"type":"Point"}
}