{
  "type": "Feature",
  "properties": {
    "addr:full":"19548 225th St Onawa IA 51040",
    "addr:housenumber":"19548",
    "addr:postcode":"51040",
    "addr:street":"225Th St",
    "iso:country":"US",
    "sg:address":"19548 225th St",
    "sg:city":"Onawa",
    "sg:classifiers":[
        {
            "category":"Banks & Credit Unions",
            "subcategory":"Investment Brokerage",
            "type":"Services"
        }
    ],
    "sg:phone":"+1 712 423 1601",
    "sg:postcode":"51040",
    "sg:province":"IA",
    "sg:tags":[
        "security"
    ],
    "wof:name":"Thrivent Financial",
    "wof:placetype":"venue"
},
  "geometry": {"coordinates":[-96.17476499999999,42.033895],"type":"Point"}
}