{
  "type": "Feature",
  "properties": {
    "iso:country":"US",
    "sg:address":"4300 Center Point Rd NE",
    "sg:city":"Cedar Rapids",
    "sg:classifiers":[
        {
            "category":"Personal",
            "subcategory":"Barber",
            "type":"Services"
        }
    ],
    "sg:phone":"+1 319 366 5544",
    "sg:postcode":"52402",
    "sg:province":"IA",
    "wof:name":"Shear Happenings",
    "wof:placetype":"venue"
},
  "geometry": {"coordinates":[-91.665814,42.022352],"type":"Point"}
}