{
  "type": "Feature",
  "properties": {
    "iso:country":"US",
    "sg:address":"933 Ave H",
    "sg:city":"Fort Madison",
    "sg:classifiers":[
        {
            "category":"Organizations",
            "subcategory":"Non-profit Organization",
            "type":"Services"
        }
    ],
    "sg:phone":"+1 319 524 2522",
    "sg:postcode":"52627",
    "sg:province":"IA",
    "sg:tags":[
        "information",
        "abuse",
        "treatment",
        "child"
    ],
    "wof:name":"Child Abuse",
    "wof:placetype":"venue"
},
  "geometry": {"coordinates":[-91.314007,40.630122],"type":"Point"}
}