{
  "type": "Feature",
  "properties": {
    "addr:full":"2021 Wright Ave Rowan IA 50470",
    "addr:housenumber":"2021",
    "addr:postcode":"50470",
    "addr:street":"Wright Ave",
    "iso:country":"US",
    "sg:address":"2021 Wright Ave",
    "sg:city":"Rowan",
    "sg:classifiers":[
        {
            "category":"Farming",
            "subcategory":"Farm",
            "type":"Manufacturing & Wholesale Goods"
        }
    ],
    "sg:phone":"+1 641 853 2252",
    "sg:postcode":"50470",
    "sg:province":"IA",
    "wof:name":"JBR Farms",
    "wof:placetype":"venue"
},
  "geometry": {"coordinates":[-93.498755,42.757005],"type":"Point"}
}