{
  "type": "Feature",
  "properties": {
    "iso:country":"US",
    "sg:address":"1008 Summit St",
    "sg:city":"Marshalltown",
    "sg:classifiers":[
        {
            "category":"Shopping",
            "subcategory":"Musical Instruments",
            "type":"Retail Goods"
        }
    ],
    "sg:phone":"+1 641 752 8876",
    "sg:postcode":"50158",
    "sg:province":"IA",
    "wof:name":"Randall's Guitar School",
    "wof:placetype":"venue"
},
  "geometry": {"coordinates":[-92.930595,42.052682],"type":"Point"}
}