{
  "type": "Feature",
  "properties": {
    "iso:country":"US",
    "sg:address":"1526 NE 44th Ave",
    "sg:city":"Des Moines",
    "sg:classifiers":[
        {
            "category":"Retail",
            "subcategory":"Auto Repair",
            "type":"Services"
        }
    ],
    "sg:phone":"+1 515 265 4300",
    "sg:postcode":"50313",
    "sg:province":"IA",
    "sg:tags":[
        "truck"
    ],
    "wof:name":"Newell Truck Repair",
    "wof:placetype":"venue"
},
  "geometry": {"coordinates":[-93.60781299999999,41.640412],"type":"Point"}
}