{
  "type": "Feature",
  "properties": {
    "iso:country":"US",
    "sg:address":"5137 NW 2nd St",
    "sg:city":"Des Moines",
    "sg:classifiers":[
        {
            "category":"Building & Trades",
            "subcategory":"Equipment Rental",
            "type":"Services"
        }
    ],
    "sg:phone":"+1 515 246 8843",
    "sg:postcode":"50313",
    "sg:province":"IA",
    "sg:tags":[
        "yard"
    ],
    "wof:name":"Sunbet Rentals",
    "wof:placetype":"venue"
},
  "geometry": {"coordinates":[-93.619839,41.652761],"type":"Point"}
}