{
  "type": "Feature",
  "properties": {
    "addr:full":"116 N 2nd Ave Logan IA 51546",
    "addr:housenumber":"116",
    "addr:postcode":"51546",
    "addr:street":"N 2Nd Ave",
    "iso:country":"US",
    "sg:address":"116 N 2nd Ave",
    "sg:city":"Logan",
    "sg:classifiers":[
        {
            "category":"Organizations",
            "subcategory":"Community Association",
            "type":"Services"
        }
    ],
    "sg:phone":"+1 712 644 3329",
    "sg:postcode":"51546",
    "sg:province":"IA",
    "sg:tags":[
        "military"
    ],
    "wof:name":"Veterans Affairs",
    "wof:placetype":"venue"
},
  "geometry": {"coordinates":[-95.789086,41.643204],"type":"Point"}
}