{
  "type": "Feature",
  "properties": {
    "iso:country":"US",
    "sg:address":"3300 101st St",
    "sg:city":"Des Moines",
    "sg:classifiers":[
        {
            "category":"Manufacturing",
            "subcategory":"Signs",
            "type":"Manufacturing & Wholesale Goods"
        }
    ],
    "sg:phone":"+1 515 253 9622",
    "sg:postcode":"50322",
    "sg:province":"IA",
    "wof:name":"Porters-Bowers Sign Co",
    "wof:placetype":"venue"
},
  "geometry": {"coordinates":[-93.75719599999999,41.62566],"type":"Point"}
}