{
  "type": "Feature",
  "properties": {
    "addr:full":"1305 E Walnut St Des Moines IA 50309",
    "addr:housenumber":"1305",
    "addr:postcode":"50309",
    "addr:street":"E Walnut St",
    "iso:country":"US",
    "sg:address":"1305 E Walnut St",
    "sg:city":"Des Moines",
    "sg:classifiers":[
        {
            "category":"Government",
            "subcategory":"Office",
            "type":"Public Place"
        }
    ],
    "sg:phone":"+1 515 281 5428",
    "sg:postcode":"50309",
    "sg:province":"IA",
    "wof:name":"Prosecuting Attorneys Council",
    "wof:placetype":"venue"
},
  "geometry": {"coordinates":[-93.59834600000001,41.590961],"type":"Point"}
}