{
  "type": "Feature",
  "properties": {
    "addr:full":"210 6th St SW Mason City IA 50401",
    "addr:housenumber":"210",
    "addr:postcode":"50401",
    "addr:street":"6Th St Sw",
    "iso:country":"US",
    "sg:address":"210 6th St SW",
    "sg:city":"Mason City",
    "sg:classifiers":[
        {
            "category":"Retail",
            "subcategory":"Car Wash",
            "type":"Services"
        }
    ],
    "sg:phone":"+1 641 423 6669",
    "sg:postcode":"50401",
    "sg:province":"IA",
    "sg:tags":[
        "polishing",
        "washing"
    ],
    "wof:name":"Super Wash",
    "wof:placetype":"venue"
},
  "geometry": {"coordinates":[-93.205861,43.146357],"type":"Point"}
}