{
  "type": "Feature",
  "properties": {
    "iso:country":"US",
    "sg:address":"1926 480th St",
    "sg:city":"Saint Ansgar",
    "sg:classifiers":[
        {
            "category":"Retail",
            "subcategory":"Auto Repair",
            "type":"Services"
        }
    ],
    "sg:phone":"+1 641 326 4746",
    "sg:postcode":"50472",
    "sg:province":"IA",
    "sg:tags":[
        "general"
    ],
    "wof:name":"Pattersons Repair",
    "wof:placetype":"venue"
},
  "geometry": {"coordinates":[-92.845586,43.458049],"type":"Point"}
}