{
  "type": "Feature",
  "properties": {
    "addr:full":"2431 120th St New Sharon IA 50207",
    "addr:housenumber":"2431",
    "addr:postcode":"50207",
    "addr:street":"120Th St",
    "iso:country":"US",
    "sg:address":"2431 120th St",
    "sg:city":"New Sharon",
    "sg:classifiers":[
        {
            "category":"Banks & Credit Unions",
            "subcategory":"Investment Brokerage",
            "type":"Services"
        }
    ],
    "sg:phone":"+1 641 637 1018",
    "sg:postcode":"50207",
    "sg:province":"IA",
    "sg:tags":[
        "advisory",
        "financial"
    ],
    "wof:name":"First Financial Health",
    "wof:placetype":"venue"
},
  "geometry": {"coordinates":[-92.59980400000001,41.480588],"type":"Point"}
}