{
  "type": "Feature",
  "properties": {
    "addr:full":"1064 Crane Ave Manning IA 51455",
    "addr:housenumber":"1064",
    "addr:postcode":"51455",
    "addr:street":"Crane Ave",
    "iso:country":"US",
    "sg:address":"1064 Crane Ave",
    "sg:city":"Manning",
    "sg:classifiers":[
        {
            "category":"Professional",
            "subcategory":"Business Services",
            "type":"Services"
        }
    ],
    "sg:phone":"+1 712 653 2000",
    "sg:postcode":"51455",
    "sg:province":"IA",
    "sg:tags":[
        "auctioneer"
    ],
    "wof:name":"Meryl Kerkhoff Auctioneer",
    "wof:placetype":"venue"
},
  "geometry": {"coordinates":[-95.05353100000001,41.861973],"type":"Point"}
}