{
  "type": "Feature",
  "properties": {
    "addr:full":"312 17th St Bettendorf IA 52722",
    "addr:housenumber":"312",
    "addr:postcode":"52722",
    "addr:street":"17Th St",
    "iso:country":"US",
    "sg:address":"312 17th St",
    "sg:city":"Bettendorf",
    "sg:classifiers":[
        {
            "category":"Autos & Motor Vehicles",
            "subcategory":"Auto Supplies",
            "type":"Retail Goods"
        }
    ],
    "sg:phone":"+1 563 359 4413",
    "sg:postcode":"52722",
    "sg:province":"IA",
    "sg:tags":[
        "automobile",
        "part"
    ],
    "sg:website":"http://ad.doubleclick.net/clk;221862232;45455595;j?http://www.carquest.com/carquest/store_locator.html",
    "wof:name":"CARQUEST Auto Parts",
    "wof:placetype":"venue"
},
  "geometry": {"coordinates":[-90.508594,41.525375],"type":"Point"}
}