{
  "type": "Feature",
  "properties": {
    "iso:country":"US",
    "sg:address":"3421 W 9th St",
    "sg:city":"Waterloo",
    "sg:classifiers":[
        {
            "category":"Health Services",
            "subcategory":"Health Practitioner",
            "type":"Services"
        }
    ],
    "sg:phone":"+1 319 272 2600",
    "sg:postcode":"50702",
    "sg:province":"IA",
    "sg:tags":[
        "nurse",
        "registry"
    ],
    "wof:name":"Ask A Nurse",
    "wof:placetype":"venue"
},
  "geometry": {"coordinates":[-92.344556,42.464772],"type":"Point"}
}