{
  "type": "Feature",
  "properties": {
    "iso:country":"US",
    "sg:address":"539 Cayuga St",
    "sg:city":"Storm Lake",
    "sg:classifiers":[
        {
            "category":"Health Services",
            "subcategory":"Medical Lab",
            "type":"Services"
        }
    ],
    "sg:phone":"+1 712 732 2060",
    "sg:postcode":"50588",
    "sg:province":"IA",
    "sg:tags":[
        "laboratory"
    ],
    "wof:name":"Hill Dental Laboratory",
    "wof:placetype":"venue"
},
  "geometry": {"coordinates":[-95.198294,42.643706],"type":"Point"}
}