{
  "type": "Feature",
  "properties": {
    "iso:country":"US",
    "sg:address":"205 E Erie St",
    "sg:city":"Missouri Valley",
    "sg:classifiers":[
        {
            "category":"Banks & Credit Unions",
            "subcategory":"Bank",
            "type":"Services"
        }
    ],
    "sg:phone":"+1 712 642 4151",
    "sg:postcode":"51555",
    "sg:province":"IA",
    "sg:tags":[
        "savings",
        "loan",
        "association"
    ],
    "wof:name":"Tier One Bank",
    "wof:placetype":"venue"
},
  "geometry": {"coordinates":[-95.891915,41.55646],"type":"Point"}
}