{
  "type": "Feature",
  "properties": {
    "iso:country":"US",
    "sg:address":"1301 5th Ave",
    "sg:city":"Marion",
    "sg:classifiers":[
        {
            "category":"Education",
            "subcategory":"School",
            "type":"Public Place"
        }
    ],
    "sg:phone":"+1 319 377 4079",
    "sg:postcode":"52302",
    "sg:province":"IA",
    "sg:tags":[
        "high",
        "middle",
        "elementary"
    ],
    "wof:name":"Marion Ind School Dist-Vernon Middle School",
    "wof:placetype":"venue"
},
  "geometry": {"coordinates":[-91.595398,42.031399],"type":"Point"}
}