{
  "type": "Feature",
  "properties": {
    "iso:country":"US",
    "sg:address":"1096 210th St",
    "sg:city":"Victor",
    "sg:classifiers":[
        {
            "category":"Freight",
            "type":"Transportation"
        }
    ],
    "sg:phone":"+1 319 647 3623",
    "sg:postcode":"52347",
    "sg:province":"IA",
    "sg:tags":[
        "trucking"
    ],
    "wof:name":"David Miller & Sons Inc",
    "wof:placetype":"venue"
},
  "geometry": {"coordinates":[-92.287802,41.703122],"type":"Point"}
}