{
  "type": "Feature",
  "properties": {
    "iso:country":"US",
    "sg:address":"1724 S 12th St",
    "sg:city":"Burlington",
    "sg:classifiers":[
        {
            "category":"Personal",
            "subcategory":"Beauty Salon",
            "type":"Services"
        }
    ],
    "sg:phone":"+1 319 753 6188",
    "sg:postcode":"52601",
    "sg:province":"IA",
    "wof:name":"Personality Shop",
    "wof:placetype":"venue"
},
  "geometry": {"coordinates":[-91.110855,40.79072],"type":"Point"}
}