{
  "type": "Feature",
  "properties": {
    "iso:country":"US",
    "sg:address":"485 E Main St",
    "sg:city":"Letts",
    "sg:classifiers":[
        {
            "category":"Retail",
            "subcategory":"Auto Repair",
            "type":"Services"
        }
    ],
    "sg:phone":"+1 319 726 5026",
    "sg:postcode":"52754",
    "sg:province":"IA",
    "sg:tags":[
        "body",
        "automobile",
        "painting"
    ],
    "wof:name":"Kirks Collision",
    "wof:placetype":"venue"
},
  "geometry": {"coordinates":[-91.232647,41.328191],"type":"Point"}
}