{
  "type": "Feature",
  "properties": {
    "iso:country":"US",
    "sg:address":"10 Benton Ave E",
    "sg:city":"Albia",
    "sg:classifiers":[
        {
            "category":"Government",
            "subcategory":"Office",
            "type":"Public Place"
        }
    ],
    "sg:phone":"+1 641 932 5212",
    "sg:postcode":"52531",
    "sg:province":"IA",
    "sg:tags":[
        "county"
    ],
    "wof:name":"Monroe County Clerk Of Court",
    "wof:placetype":"venue"
},
  "geometry": {"coordinates":[-92.80829199999999,41.027036],"type":"Point"}
}