{
  "type": "Feature",
  "properties": {
    "addr:full":"430 S River Park Dr Guttenberg IA 52052",
    "addr:housenumber":"430",
    "addr:postcode":"52052",
    "addr:street":"S River Park Dr",
    "iso:country":"US",
    "sg:address":"430 S River Park Dr",
    "sg:city":"Guttenberg",
    "sg:classifiers":[
        {
            "category":"Home & Garden",
            "subcategory":"Hardware",
            "type":"Retail Goods"
        }
    ],
    "sg:phone":"+1 563 252 1824",
    "sg:postcode":"52052",
    "sg:province":"IA",
    "wof:name":"Kuempel's True Value Hardware",
    "wof:placetype":"venue"
},
  "geometry": {"coordinates":[-91.095635,42.782538],"type":"Point"}
}