{
  "type": "Feature",
  "properties": {
    "iso:country":"US",
    "sg:address":"1403 8th St",
    "sg:city":"Boone",
    "sg:classifiers":[
        {
            "category":"Freight",
            "type":"Transportation"
        }
    ],
    "sg:phone":"+1 515 432 1610",
    "sg:postcode":"50036",
    "sg:province":"IA",
    "sg:tags":[
        "trucking"
    ],
    "wof:name":"Guenther Transport",
    "wof:placetype":"venue"
},
  "geometry": {"coordinates":[-93.870006,42.063713],"type":"Point"}
}