{
  "type": "Feature",
  "properties": {
    "iso:country":"US",
    "sg:address":"2801 Westover Blvd",
    "sg:city":"Des Moines",
    "sg:classifiers":[
        {
            "category":"Retail",
            "subcategory":"Animal Services",
            "type":"Services"
        }
    ],
    "sg:phone":"+1 515 278 2336",
    "sg:postcode":"50322",
    "sg:province":"IA",
    "sg:tags":[
        "pet",
        "boarding",
        "sitting"
    ],
    "wof:name":"WIL-A-Lo Boarding Kennels",
    "wof:placetype":"venue"
},
  "geometry": {"coordinates":[-93.706129,41.621395],"type":"Point"}
}