{
  "type": "Feature",
  "properties": {
    "addr:full":"112 1st St NE Waverly IA 50677",
    "addr:housenumber":"112",
    "addr:postcode":"50677",
    "addr:street":"1St St Ne",
    "iso:country":"US",
    "sg:address":"112 1st St NE",
    "sg:city":"Waverly",
    "sg:classifiers":[
        {
            "category":"Shopping",
            "subcategory":"Computers & Home Electronics",
            "type":"Retail Goods"
        }
    ],
    "sg:phone":"+1 319 352 2743",
    "sg:postcode":"50677",
    "sg:province":"IA",
    "sg:tags":[
        "equipment",
        "satellite",
        "system"
    ],
    "wof:name":"Fish Electronics TV",
    "wof:placetype":"venue"
},
  "geometry": {"coordinates":[-92.46927100000001,42.726671],"type":"Point"}
}