{
  "type": "Feature",
  "properties": {
    "addr:full":"4973 160th St Sibley IA 51249",
    "addr:housenumber":"4973",
    "addr:postcode":"51249",
    "addr:street":"160Th St",
    "iso:country":"US",
    "sg:address":"4973 160th St",
    "sg:city":"Sibley",
    "sg:classifiers":[
        {
            "category":"Professional",
            "subcategory":"Business Services",
            "type":"Services"
        }
    ],
    "sg:phone":"+1 712 754 2005",
    "sg:postcode":"51249",
    "sg:province":"IA",
    "sg:tags":[
        "auctioneer"
    ],
    "wof:name":"Norman D Klaassen Auct",
    "wof:placetype":"venue"
},
  "geometry": {"coordinates":[-95.806714,43.418316],"type":"Point"}
}