{
  "type": "Feature",
  "properties": {
    "iso:country":"US",
    "sg:address":"902 6th Ave",
    "sg:city":"De Witt",
    "sg:classifiers":[
        {
            "category":"Shopping",
            "subcategory":"Tobacco",
            "type":"Retail Goods"
        }
    ],
    "sg:phone":"+1 563 659 8348",
    "sg:postcode":"52742",
    "sg:province":"IA",
    "sg:tags":[
        "cigarette",
        "cigar",
        "dealer"
    ],
    "wof:name":"M J's Discount Smokes",
    "wof:placetype":"venue"
},
  "geometry": {"coordinates":[-90.538904,41.825188],"type":"Point"}
}