{
  "type": "Feature",
  "properties": {
    "addr:full":"306 S 8th St Clear Lake IA 50428",
    "addr:housenumber":"306",
    "addr:postcode":"50428",
    "addr:street":"S 8Th St",
    "iso:country":"US",
    "sg:address":"306 S 8th St",
    "sg:city":"Clear Lake",
    "sg:classifiers":[
        {
            "category":"Education",
            "subcategory":"School",
            "type":"Public Place"
        }
    ],
    "sg:phone":"+1 641 357 2174",
    "sg:postcode":"50428",
    "sg:province":"IA",
    "wof:name":"Lincoln Elementary School",
    "wof:placetype":"venue"
},
  "geometry": {"coordinates":[-93.378668,43.134567],"type":"Point"}
}