{
  "type": "Feature",
  "properties": {
    "iso:country":"US",
    "sg:address":"1505 Little Blue Stem Ct",
    "sg:city":"Ames",
    "sg:classifiers":[
        {
            "category":"Building & Trades",
            "subcategory":"Construction",
            "type":"Services"
        }
    ],
    "sg:phone":"+1 515 291 3530",
    "sg:postcode":"50014",
    "sg:province":"IA",
    "sg:tags":[
        "concrete",
        "contractor"
    ],
    "wof:name":"Rhoads Concrete",
    "wof:placetype":"venue"
},
  "geometry": {"coordinates":[-93.64566600000001,42.009433],"type":"Point"}
}