{
  "type": "Feature",
  "properties": {
    "iso:country":"US",
    "sg:address":"519 10th Ave S",
    "sg:city":"Clinton",
    "sg:classifiers":[
        {
            "category":"Building & Trades",
            "subcategory":"Landscaping Services",
            "type":"Services"
        }
    ],
    "sg:phone":"+1 563 243 9143",
    "sg:postcode":"52732",
    "sg:province":"IA",
    "sg:tags":[
        "lawn",
        "maintenance",
        "grounds"
    ],
    "wof:name":"Jim's Lawn Care Maintenance",
    "wof:placetype":"venue"
},
  "geometry": {"coordinates":[-90.196141,41.835234],"type":"Point"}
}