{
  "type": "Feature",
  "properties": {
    "iso:country":"US",
    "sg:address":"1512 US Hwy 169",
    "sg:city":"Algona",
    "sg:classifiers":[
        {
            "category":"Restaurant",
            "type":"Food & Drink"
        }
    ],
    "sg:phone":"+1 515 295 2432",
    "sg:postcode":"50511",
    "sg:province":"IA",
    "wof:name":"Subway Sandwiches & Salads",
    "wof:placetype":"venue"
},
  "geometry": {"coordinates":[-94.235705,43.079024],"type":"Point"}
}