{
  "type": "Feature",
  "properties": {
    "iso:country":"US",
    "sg:address":"617 45th Ave",
    "sg:city":"Amana",
    "sg:classifiers":[
        {
            "category":"Home & Garden",
            "subcategory":"Home Furnishings",
            "type":"Retail Goods"
        }
    ],
    "sg:phone":"+1 319 622 3097",
    "sg:postcode":"52203",
    "sg:province":"IA",
    "sg:tags":[
        "curtain",
        "made",
        "drapery"
    ],
    "wof:name":"Olde World Lace Shoppe",
    "wof:placetype":"venue"
},
  "geometry": {"coordinates":[-91.870442,41.801341],"type":"Point"}
}