{
  "type": "Feature",
  "properties": {
    "iso:country":"US",
    "sg:address":"306 E Linn St",
    "sg:city":"Quasqueton",
    "sg:classifiers":[
        {
            "category":"Retail",
            "subcategory":"Auto Repair",
            "type":"Services"
        }
    ],
    "sg:phone":"+1 319 934 3210",
    "sg:postcode":"52326",
    "sg:province":"IA",
    "sg:tags":[
        "repairing",
        "automobile"
    ],
    "wof:name":"Kimball Garage",
    "wof:placetype":"venue"
},
  "geometry": {"coordinates":[-91.752602,42.392683],"type":"Point"}
}