{
  "type": "Feature",
  "properties": {
    "iso:country":"US",
    "sg:address":"620 Mulberry St",
    "sg:city":"Waterloo",
    "sg:classifiers":[
        {
            "category":"Real Estate",
            "subcategory":"Real Estate Agent",
            "type":"Services"
        }
    ],
    "sg:phone":"+1 319 233 0201",
    "sg:postcode":"50703",
    "sg:province":"IA",
    "sg:tags":[
        "finding",
        "apartment",
        "rental"
    ],
    "wof:name":"Waterloo Housing Authority",
    "wof:placetype":"venue"
},
  "geometry": {"coordinates":[-92.333191,42.499213],"type":"Point"}
}