{
  "type": "Feature",
  "properties": {
    "addr:full":"1232 100th St Sully IA 50251",
    "addr:housenumber":"1232",
    "addr:postcode":"50251",
    "addr:street":"100Th St",
    "iso:country":"US",
    "sg:address":"1232 100th St",
    "sg:city":"Sully",
    "sg:classifiers":[
        {
            "category":"Manufacturing",
            "subcategory":"Tools & Machinery",
            "type":"Manufacturing & Wholesale Goods"
        }
    ],
    "sg:phone":"+1 641 594 2953",
    "sg:postcode":"50251",
    "sg:province":"IA",
    "sg:tags":[
        "farm",
        "equipment"
    ],
    "sg:website":"www.colinemfg.com",
    "wof:name":"Co-Line Welding Inc",
    "wof:placetype":"venue"
},
  "geometry": {"coordinates":[-92.827894,41.508593],"type":"Point"}
}