{
  "type": "Feature",
  "properties": {
    "iso:country":"US",
    "sg:address":"24215 580th Ave",
    "sg:city":"Ames",
    "sg:classifiers":[
        {
            "category":"Farming",
            "subcategory":"Farm",
            "type":"Manufacturing & Wholesale Goods"
        }
    ],
    "sg:phone":"+1 515 233 2080",
    "sg:postcode":"50010",
    "sg:province":"IA",
    "sg:tags":[
        "crop",
        "general"
    ],
    "wof:name":"Lowell Kingsbury",
    "wof:placetype":"venue"
},
  "geometry": {"coordinates":[-93.540925,42.008626],"type":"Point"}
}