{
  "type": "Feature",
  "properties": {
    "addr:full":"2385 Kerper Blvd Dubuque IA 52001",
    "addr:housenumber":"2385",
    "addr:postcode":"52001",
    "addr:street":"Kerper Blvd",
    "iso:country":"US",
    "sg:address":"2385 Kerper Blvd",
    "sg:city":"Dubuque",
    "sg:classifiers":[
        {
            "category":"Autos & Motor Vehicles",
            "subcategory":"Boat Sales",
            "type":"Retail Goods"
        }
    ],
    "sg:phone":"+1 563 557 0313",
    "sg:postcode":"52001",
    "sg:province":"IA",
    "sg:tags":[
        "dealer",
        "sales"
    ],
    "wof:name":"Hawkeye Boat Sales",
    "wof:placetype":"venue"
},
  "geometry": {"coordinates":[-90.65604999999999,42.518896],"type":"Point"}
}