{
  "type": "Feature",
  "properties": {
    "iso:country":"US",
    "sg:address":"521 6th Ave",
    "sg:city":"De Witt",
    "sg:classifiers":[
        {
            "category":"Professional",
            "type":"Services"
        }
    ],
    "sg:phone":"+1 563 659 9265",
    "sg:postcode":"52742",
    "sg:province":"IA",
    "sg:tags":[
        "establishment"
    ],
    "wof:name":"Beatrice-Hunt-Wesson",
    "wof:placetype":"venue"
},
  "geometry": {"coordinates":[-90.539025,41.821056],"type":"Point"}
}