{
  "type": "Feature",
  "properties": {
    "iso:country":"US",
    "sg:address":"410 W Front St",
    "sg:city":"Lake Mills",
    "sg:classifiers":[
        {
            "category":"Building & Trades",
            "subcategory":"Construction",
            "type":"Services"
        }
    ],
    "sg:phone":"+1 641 592 8265",
    "sg:postcode":"50450",
    "sg:province":"IA",
    "sg:tags":[
        "foundation"
    ],
    "wof:name":"Tank Foundations Inc",
    "wof:placetype":"venue"
},
  "geometry": {"coordinates":[-93.543094,43.423152],"type":"Point"}
}