{
  "type": "Feature",
  "properties": {
    "iso:country":"US",
    "sg:address":"4005 E 53rd St",
    "sg:city":"Davenport",
    "sg:classifiers":[
        {
            "category":"Restaurant",
            "type":"Food & Drink"
        }
    ],
    "sg:menulink":"http://www.allmenus.com/ia/davenport/10385-texas-roadhouse/menu/",
    "sg:phone":"+1 563 355 2373",
    "sg:postcode":"52807",
    "sg:province":"IA",
    "sg:tags":[
        "american",
        "steakhouse"
    ],
    "wof:name":"Texas Roadhouse",
    "wof:placetype":"venue"
},
  "geometry": {"coordinates":[-90.51567,41.574832],"type":"Point"}
}