{
  "type": "Feature",
  "properties": {
    "addr:full":"501 Gordon Dr Sioux City IA 51101",
    "addr:housenumber":"501",
    "addr:postcode":"51101",
    "addr:street":"Gordon Dr",
    "iso:country":"US",
    "sg:address":"501 Gordon Dr",
    "sg:city":"Sioux City",
    "sg:classifiers":[
        {
            "category":"Bakery",
            "type":"Food & Drink"
        }
    ],
    "sg:menulink":"http://www.allmenus.com/ia/sioux-city/102025-perkins-restaurant--bakery/menu/",
    "sg:phone":"+1 712 277 4765",
    "sg:postcode":"51101",
    "sg:province":"IA",
    "sg:tags":[
        "sandwich",
        "salad",
        "soup",
        "american",
        "pastry",
        "wrap"
    ],
    "wof:name":"Perkins Restaurant & Bakery",
    "wof:placetype":"venue"
},
  "geometry": {"coordinates":[-96.404921,42.489792],"type":"Point"}
}