{
  "type": "Feature",
  "properties": {
    "iso:country":"US",
    "sg:address":"404 Arnold Ave",
    "sg:city":"Council Bluffs",
    "sg:classifiers":[
        {
            "category":"Professional",
            "subcategory":"Management & Consulting",
            "type":"Services"
        }
    ],
    "sg:phone":"+1 712 325 1307",
    "sg:postcode":"51503",
    "sg:province":"IA",
    "sg:tags":[
        "party",
        "planning"
    ],
    "wof:name":"Creative Celebrations",
    "wof:placetype":"venue"
},
  "geometry": {"coordinates":[-95.81321,41.256781],"type":"Point"}
}