{
  "type": "Feature",
  "properties": {
    "iso:country":"US",
    "sg:address":"416 2nd Ave E",
    "sg:city":"Oskaloosa",
    "sg:classifiers":[
        {
            "category":"Organizations",
            "subcategory":"Religious Organization",
            "type":"Services"
        }
    ],
    "sg:phone":"+1 641 673 4277",
    "sg:postcode":"52577",
    "sg:province":"IA",
    "wof:name":"First Pentecostal Church",
    "wof:placetype":"venue"
},
  "geometry": {"coordinates":[-92.641284,41.293463],"type":"Point"}
}