{
  "type": "Feature",
  "properties": {
    "iso:country":"US",
    "sg:address":"3097 325th St",
    "sg:city":"Cresco",
    "sg:classifiers":[
        {
            "category":"Farming",
            "subcategory":"Livestock Farm",
            "type":"Manufacturing & Wholesale Goods"
        }
    ],
    "sg:phone":"+1 563 547 4319",
    "sg:postcode":"52136",
    "sg:province":"IA",
    "sg:tags":[
        "hog",
        "or",
        "feedlot"
    ],
    "wof:name":"Eugene Bronner",
    "wof:placetype":"venue"
},
  "geometry": {"coordinates":[-92.016527,43.406944],"type":"Point"}
}