{
  "type": "Feature",
  "properties": {
    "iso:country":"US",
    "sg:address":"1975 Orange Ave",
    "sg:city":"Washington",
    "sg:classifiers":[
        {
            "category":"Farming",
            "subcategory":"Farm",
            "type":"Manufacturing & Wholesale Goods"
        }
    ],
    "sg:phone":"+1 319 653 3816",
    "sg:postcode":"52353",
    "sg:province":"IA",
    "sg:tags":[
        "crop",
        "general"
    ],
    "wof:name":"Francis Litwiller",
    "wof:placetype":"venue"
},
  "geometry": {"coordinates":[-91.676919,41.370243],"type":"Point"}
}