{
  "type": "Feature",
  "properties": {
    "iso:country":"US",
    "sg:address":"213 SE 2nd St",
    "sg:city":"Ankeny",
    "sg:classifiers":[
        {
            "category":"Professional",
            "subcategory":"Business Services",
            "type":"Services"
        }
    ],
    "sg:phone":"+1 515 965 0930",
    "sg:postcode":"50021",
    "sg:province":"IA",
    "wof:name":"Referral Enterprises LLC",
    "wof:placetype":"venue"
},
  "geometry": {"coordinates":[-93.59563799999999,41.730357],"type":"Point"}
}