{
  "type": "Feature",
  "properties": {
    "iso:country":"US",
    "sg:address":"200 E Grand Ave",
    "sg:city":"Des Moines",
    "sg:classifiers":[
        {
            "category":"Organizations",
            "subcategory":"Non-profit Organization",
            "type":"Services"
        }
    ],
    "sg:phone":"+1 515 281 6514",
    "sg:postcode":"50309",
    "sg:province":"IA",
    "sg:website":"www.iacudiv.state.ia.us",
    "wof:name":"Iowa Credit Union Div",
    "wof:placetype":"venue"
},
  "geometry": {"coordinates":[-93.61301899999999,41.590342],"type":"Point"}
}