{
  "type": "Feature",
  "properties": {
    "iso:country":"US",
    "sg:address":"6110 Hillandale Rd",
    "sg:city":"Davenport",
    "sg:classifiers":[
        {
            "category":"Personal",
            "type":"Services"
        },
        {
            "category":"Communications",
            "subcategory":"Film & Video Production",
            "type":"Services"
        }
    ],
    "sg:phone":"+1 563 323 3042",
    "sg:postcode":"52806",
    "sg:province":"IA",
    "sg:tags":[
        "photography",
        "videography",
        "wedding"
    ],
    "wof:name":"Midwest Whitetail Madness Inc",
    "wof:placetype":"venue"
},
  "geometry": {"coordinates":[-90.617177,41.583649],"type":"Point"}
}