{
  "type": "Feature",
  "properties": {
    "iso:country":"US",
    "sg:address":"901 W Sheridan Ave",
    "sg:city":"Shenandoah",
    "sg:classifiers":[
        {
            "category":"Insurance",
            "subcategory":"Insurance Agent",
            "type":"Services"
        }
    ],
    "sg:phone":"+1 712 246 3199",
    "sg:postcode":"51601",
    "sg:province":"IA",
    "wof:name":"State Farm Insurance",
    "wof:placetype":"venue"
},
  "geometry": {"coordinates":[-95.378361,40.765938],"type":"Point"}
}