{
  "type": "Feature",
  "properties": {
    "addr:full":"710 S 3rd Ave Marshalltown IA 50158",
    "addr:housenumber":"710",
    "addr:postcode":"50158",
    "addr:street":"S 3Rd Ave",
    "iso:country":"US",
    "sg:address":"710 S 3rd Ave",
    "sg:city":"Marshalltown",
    "sg:classifiers":[
        {
            "category":"Autos & Motor Vehicles",
            "subcategory":"Auto Supplies",
            "type":"Retail Goods"
        }
    ],
    "sg:phone":"+1 641 754 0586",
    "sg:postcode":"50158",
    "sg:province":"IA",
    "sg:tags":[
        "automobile",
        "parts"
    ],
    "wof:name":"O'Reilly Auto Parts",
    "wof:placetype":"venue"
},
  "geometry": {"coordinates":[-92.907844,42.040472],"type":"Point"}
}