{
  "type": "Feature",
  "properties": {
    "iso:country":"US",
    "sg:address":"416 4th St",
    "sg:city":"Rockwell City",
    "sg:classifiers":[
        {
            "category":"Government",
            "subcategory":"Office",
            "type":"Public Place"
        }
    ],
    "sg:phone":"+1 712 297 7123",
    "sg:postcode":"50579",
    "sg:province":"IA",
    "wof:name":"Judges Chambers",
    "wof:placetype":"venue"
},
  "geometry": {"coordinates":[-94.633548,42.395588],"type":"Point"}
}