{
  "type": "Feature",
  "properties": {
    "iso:country":"US",
    "sg:address":"1616 NE Broadway Ave",
    "sg:city":"Des Moines",
    "sg:classifiers":[
        {
            "category":"Retail",
            "subcategory":"Auto Repair",
            "type":"Services"
        }
    ],
    "sg:phone":"+1 515 262 7312",
    "sg:postcode":"50313",
    "sg:province":"IA",
    "sg:tags":[
        "repairing",
        "automobile",
        "radiator"
    ],
    "wof:name":"Midwest Radiator Co",
    "wof:placetype":"venue"
},
  "geometry": {"coordinates":[-93.59358,41.644165],"type":"Point"}
}