{
  "type": "Feature",
  "properties": {
    "iso:country":"US",
    "sg:address":"406 US Hwy 18 Bus",
    "sg:city":"Luana",
    "sg:classifiers":[
        {
            "category":"Retail",
            "subcategory":"Auto Repair",
            "type":"Services"
        }
    ],
    "sg:phone":"+1 563 539 8030",
    "sg:postcode":"52141",
    "sg:province":"IA",
    "sg:tags":[
        "general"
    ],
    "wof:name":"Buerger Repair",
    "wof:placetype":"venue"
},
  "geometry": {"coordinates":[-91.17855900000001,43.021952],"type":"Point"}
}