{
  "type": "Feature",
  "properties": {
    "addr:full":"2220 Iowa Ave N Onawa IA 51040",
    "addr:housenumber":"2220",
    "addr:postcode":"51040",
    "addr:street":"Iowa Ave N",
    "iso:country":"US",
    "sg:address":"2220 Iowa Ave N",
    "sg:city":"Onawa",
    "sg:classifiers":[
        {
            "category":"Shopping",
            "subcategory":"Department Store",
            "type":"Retail Goods"
        }
    ],
    "sg:phone":"+1 712 423 3683",
    "sg:postcode":"51040",
    "sg:province":"IA",
    "sg:tags":[
        "shop"
    ],
    "sg:website":"www.pamida.com",
    "wof:name":"Pamida",
    "wof:placetype":"venue"
},
  "geometry": {"coordinates":[-96.112565,42.027194],"type":"Point"}
}