{
  "type": "Feature",
  "properties": {
    "addr:full":"101 E Union St Edgewood IA 52042",
    "addr:housenumber":"101",
    "addr:postcode":"52042",
    "addr:street":"E Union St",
    "iso:country":"US",
    "sg:address":"101 E Union St",
    "sg:city":"Edgewood",
    "sg:classifiers":[
        {
            "category":"Banks & Credit Unions",
            "subcategory":"Financial Services",
            "type":"Services"
        }
    ],
    "sg:phone":"+1 563 928 6428",
    "sg:postcode":"52042",
    "sg:province":"IA",
    "sg:tags":[
        "company",
        "holding"
    ],
    "sg:website":"www.csbiowa.com",
    "wof:name":"Community Financial Corp",
    "wof:placetype":"venue"
},
  "geometry": {"coordinates":[-91.401185,42.644444],"type":"Point"}
}