{
  "type": "Feature",
  "properties": {
    "iso:country":"US",
    "sg:address":"410 Pacific St",
    "sg:city":"Walnut",
    "sg:classifiers":[
        {
            "category":"Building & Trades",
            "subcategory":"Electrical",
            "type":"Services"
        }
    ],
    "sg:phone":"+1 712 784 3460",
    "sg:postcode":"51577",
    "sg:province":"IA",
    "sg:tags":[
        "electric",
        "contractor"
    ],
    "wof:name":"Erwin J Arndt",
    "wof:placetype":"venue"
},
  "geometry": {"coordinates":[-95.225083,41.479087],"type":"Point"}
}