{
  "type": "Feature",
  "properties": {
    "iso:country":"US",
    "sg:address":"2859 Pierce Ave",
    "sg:city":"Sanborn",
    "sg:classifiers":[
        {
            "category":"Food & Beverages",
            "subcategory":"Fruits & Vegetables",
            "type":"Retail Goods"
        }
    ],
    "sg:phone":"+1 712 729 3776",
    "sg:postcode":"51248",
    "sg:province":"IA",
    "sg:tags":[
        "produce"
    ],
    "wof:name":"Getting's Garden",
    "wof:placetype":"venue"
},
  "geometry": {"coordinates":[-95.723479,43.235941],"type":"Point"}
}