{
  "type": "Feature",
  "properties": {
    "addr:full":"414 Front St Kellogg IA 50135",
    "addr:housenumber":"414",
    "addr:postcode":"50135",
    "addr:street":"Front St",
    "iso:country":"US",
    "sg:address":"414 Front St",
    "sg:city":"Kellogg",
    "sg:classifiers":[
        {
            "category":"Government",
            "subcategory":"Fire Station",
            "type":"Public Place"
        }
    ],
    "sg:phone":"+1 641 526 3051",
    "sg:postcode":"50135",
    "sg:province":"IA",
    "sg:tags":[
        "department"
    ],
    "wof:name":"Kellogg Fire Dept",
    "wof:placetype":"venue"
},
  "geometry": {"coordinates":[-92.907445,41.71616],"type":"Point"}
}