{
  "type": "Feature",
  "properties": {
    "addr:full":"1205 Pacquette Ave Sioux City IA 51109",
    "addr:housenumber":"1205",
    "addr:postcode":"51109",
    "addr:street":"Pacquette Ave",
    "iso:country":"US",
    "sg:address":"1205 Pacquette Ave",
    "sg:city":"Sioux City",
    "sg:classifiers":[
        {
            "category":"Building & Trades",
            "subcategory":"Construction",
            "type":"Services"
        }
    ],
    "sg:phone":"+1 712 252 5299",
    "sg:postcode":"51109",
    "sg:province":"IA",
    "sg:tags":[
        "painter"
    ],
    "wof:name":"Protective Coatings & Snblstng",
    "wof:placetype":"venue"
},
  "geometry": {"coordinates":[-96.483441,42.519711],"type":"Point"}
}