{
  "type": "Feature",
  "properties": {
    "addr:full":"1030 5th Ave SE Cedar Rapids IA 52403",
    "addr:housenumber":"1030",
    "addr:postcode":"52403",
    "addr:street":"5Th Ave Se",
    "iso:country":"US",
    "sg:address":"1030 5th Ave SE",
    "sg:city":"Cedar Rapids",
    "sg:classifiers":[
        {
            "category":"Organizations",
            "subcategory":"Non-profit Organization",
            "type":"Services"
        }
    ],
    "sg:phone":"+1 319 866 6144",
    "sg:postcode":"52403",
    "sg:province":"IA",
    "sg:tags":[
        "human"
    ],
    "wof:name":"Goodwill Industries",
    "wof:placetype":"venue"
},
  "geometry": {"coordinates":[-91.65499,41.981229],"type":"Point"}
}