{
  "type": "Feature",
  "properties": {
    "iso:country":"US",
    "sg:address":"1200 215th Ave",
    "sg:city":"Spirit Lake",
    "sg:phone":"+1 712 336 5807",
    "sg:postcode":"51360",
    "sg:province":"IA",
    "sg:tags":[
        "farm",
        "corn",
        "soybean"
    ],
    "wof:name":"Boettcher John",
    "wof:placetype":"venue"
},
  "geometry": {"coordinates":[-95.160878,43.47386],"type":"Point"}
}