{
  "type": "Feature",
  "properties": {
    "iso:country":"US",
    "sg:address":"411 3rd St S",
    "sg:city":"Quasqueton",
    "sg:phone":"+1 319 934 3768",
    "sg:postcode":"52326",
    "sg:province":"IA",
    "sg:tags":[
        "farm",
        "soybean"
    ],
    "wof:name":"David Daubenberger",
    "wof:placetype":"venue"
},
  "geometry": {"coordinates":[-91.75841699999999,42.390989],"type":"Point"}
}