{
  "type": "Feature",
  "properties": {
    "iso:country":"US",
    "sg:address":"1501 Walnut St",
    "sg:city":"Dallas Center",
    "sg:classifiers":[
        {
            "category":"Home & Garden",
            "subcategory":"Hardware",
            "type":"Retail Goods"
        }
    ],
    "sg:phone":"+1 515 992 3957",
    "sg:postcode":"50063",
    "sg:province":"IA",
    "wof:name":"Four H Hardware",
    "wof:placetype":"venue"
},
  "geometry": {"coordinates":[-93.96374400000001,41.68436],"type":"Point"}
}