{
  "type": "Feature",
  "properties": {
    "addr:full":"1421 S Bell Ave Ames IA 50010",
    "addr:housenumber":"1421",
    "addr:postcode":"50010",
    "addr:street":"S Bell Ave",
    "iso:country":"US",
    "sg:address":"1421 S Bell Ave",
    "sg:city":"Ames",
    "sg:classifiers":[
        {
            "category":"Professional",
            "subcategory":"Engineering",
            "type":"Services"
        }
    ],
    "sg:phone":"+1 515 232 0950",
    "sg:postcode":"50010",
    "sg:province":"IA",
    "sg:tags":[
        "engineer"
    ],
    "wof:name":"Terracon",
    "wof:placetype":"venue"
},
  "geometry": {"coordinates":[-93.57531299999999,42.009913],"type":"Point"}
}