{
  "type": "Feature",
  "properties": {
    "iso:country":"US",
    "sg:address":"21795 Fantail Rd",
    "sg:city":"Edgewood",
    "sg:classifiers":[
        {
            "category":"Farming",
            "subcategory":"Dairy Farm",
            "type":"Manufacturing & Wholesale Goods"
        }
    ],
    "sg:phone":"+1 563 245 1345",
    "sg:postcode":"52042",
    "sg:province":"IA",
    "wof:name":"Fred Schaffer",
    "wof:placetype":"venue"
},
  "geometry": {"coordinates":[-91.368706,42.725613],"type":"Point"}
}