{
  "type": "Feature",
  "properties": {
    "addr:full":"3800 Merle Hay Rd Des Moines IA 50310",
    "addr:housenumber":"3800",
    "addr:postcode":"50310",
    "addr:street":"Merle Hay Rd Des",
    "iso:country":"US",
    "sg:address":"3800 Merle Hay Rd",
    "sg:city":"Des Moines",
    "sg:classifiers":[
        {
            "category":"Shopping",
            "subcategory":"Gifts & Souvenirs",
            "type":"Retail Goods"
        }
    ],
    "sg:phone":"+1 515 278 2248",
    "sg:postcode":"50310",
    "sg:province":"IA",
    "sg:tags":[
        "engraving",
        "custom"
    ],
    "wof:name":"Things Remembered",
    "wof:placetype":"venue"
},
  "geometry": {"coordinates":[-93.697867,41.629403],"type":"Point"}
}