{
  "type": "Feature",
  "properties": {
    "iso:country":"US",
    "sg:address":"1125 485th St",
    "sg:city":"Saint Ansgar",
    "sg:classifiers":[
        {
            "category":"Farming",
            "subcategory":"Livestock Farm",
            "type":"Manufacturing & Wholesale Goods"
        }
    ],
    "sg:phone":"+1 641 326 4654",
    "sg:postcode":"50472",
    "sg:province":"IA",
    "sg:tags":[
        "hog",
        "or",
        "feedlot"
    ],
    "wof:name":"Dennis Koch",
    "wof:placetype":"venue"
},
  "geometry": {"coordinates":[-93.00528199999999,43.46575],"type":"Point"}
}