{
  "type": "Feature",
  "properties": {
    "iso:country":"US",
    "sg:address":"734 W Prairie St",
    "sg:city":"West Liberty",
    "sg:phone":"+1 319 627 4215",
    "sg:postcode":"52776",
    "sg:province":"IA",
    "sg:tags":[
        "farm",
        "corn",
        "beef",
        "feedlot",
        "cattle"
    ],
    "wof:name":"Richard Neipert",
    "wof:placetype":"venue"
},
  "geometry": {"coordinates":[-91.27050699999999,41.568509],"type":"Point"}
}