{
  "type": "Feature",
  "properties": {
    "addr:full":"5900 Pioneer Pkwy Johnston IA 50131",
    "addr:housenumber":"5900",
    "addr:postcode":"50131",
    "addr:street":"Pioneer Pkwy",
    "iso:country":"US",
    "sg:address":"5900 Pioneer Pkwy",
    "sg:city":"Johnston",
    "sg:classifiers":[
        {
            "category":"Health Services",
            "subcategory":"Nursing And Care Facility",
            "type":"Services"
        }
    ],
    "sg:phone":"+1 515 270 2205",
    "sg:postcode":"50131",
    "sg:province":"IA",
    "wof:name":"Childserve Habilitation Ctr",
    "wof:placetype":"venue"
},
  "geometry": {"coordinates":[-93.69991899999999,41.661844],"type":"Point"}
}