{
  "type": "Feature",
  "properties": {
    "iso:country":"US",
    "sg:address":"2916 Hwy 71",
    "sg:city":"Spirit Lake",
    "sg:classifiers":[
        {
            "category":"Real Estate",
            "subcategory":"Real Estate Agent",
            "type":"Services"
        }
    ],
    "sg:phone":"+1 712 336 1240",
    "sg:postcode":"51360",
    "sg:province":"IA",
    "sg:website":"www.dowdenhinnrealtors.com",
    "wof:name":"Dowden-Hinn Realtors",
    "wof:placetype":"venue"
},
  "geometry": {"coordinates":[-95.126582,43.41296],"type":"Point"}
}