{
  "type": "Feature",
  "properties": {
    "iso:country":"US",
    "sg:address":"2107 Delaware Ave",
    "sg:city":"Des Moines",
    "sg:classifiers":[
        {
            "category":"Manufacturing",
            "subcategory":"Tools & Machinery",
            "type":"Manufacturing & Wholesale Goods"
        }
    ],
    "sg:phone":"+1 515 262 3900",
    "sg:postcode":"50317",
    "sg:province":"IA",
    "sg:tags":[
        "ink"
    ],
    "sg:website":"www.hostmann-steinberg.com",
    "wof:name":"Hostmann Steinberg Corp",
    "wof:placetype":"venue"
},
  "geometry": {"coordinates":[-93.581187,41.609512],"type":"Point"}
}