{
  "type": "Feature",
  "properties": {
    "addr:full":"702 W Prairie St Creston IA 50801",
    "addr:housenumber":"702",
    "addr:postcode":"50801",
    "addr:street":"W Prairie St",
    "iso:country":"US",
    "sg:address":"702 W Prairie St",
    "sg:city":"Creston",
    "sg:classifiers":[
        {
            "category":"Organizations",
            "subcategory":"Religious Organization",
            "type":"Services"
        }
    ],
    "sg:phone":"+1 641 782 5938",
    "sg:postcode":"50801",
    "sg:province":"IA",
    "sg:tags":[
        "church"
    ],
    "sg:website":"www.fpciowa.com",
    "wof:name":"Presbyterian Church",
    "wof:placetype":"venue"
},
  "geometry": {"coordinates":[-94.371673,41.067964],"type":"Point"}
}