{
  "type": "Feature",
  "properties": {
    "iso:country":"US",
    "sg:address":"1111 9th St",
    "sg:city":"Des Moines",
    "sg:classifiers":[
        {
            "category":"Organizations",
            "subcategory":"Non-profit Organization",
            "type":"Services"
        }
    ],
    "sg:phone":"+1 515 282 3561",
    "sg:postcode":"50314",
    "sg:province":"IA",
    "sg:tags":[
        "human"
    ],
    "wof:name":"Making Connections",
    "wof:placetype":"venue"
},
  "geometry": {"coordinates":[-93.629306,41.600274],"type":"Point"}
}