{
  "type": "Feature",
  "properties": {
    "iso:country":"US",
    "sg:address":"600 Quincy St",
    "sg:city":"Corning",
    "sg:classifiers":[
        {
            "category":"Restaurant",
            "type":"Food & Drink"
        },
        {
            "category":"Food & Beverages",
            "subcategory":"Groceries & Convenience Stores",
            "type":"Retail Goods"
        }
    ],
    "sg:menulink":"http://www.allmenus.com/ia/quincy/225840-caseys-general-store/menu/",
    "sg:phone":"+1 641 322 3031",
    "sg:postcode":"50841",
    "sg:province":"IA",
    "sg:tags":[
        "american",
        "pizza"
    ],
    "wof:name":"Casey's General Store",
    "wof:placetype":"venue"
},
  "geometry": {"coordinates":[-94.731883,40.988086],"type":"Point"}
}