{
  "type": "Feature",
  "properties": {
    "addr:full":"527 Park Ln Waterloo IA 50702",
    "addr:housenumber":"527",
    "addr:postcode":"50702",
    "addr:street":"Park Ln",
    "iso:country":"US",
    "sg:address":"527 Park Ln",
    "sg:city":"Waterloo",
    "sg:classifiers":[
        {
            "category":"Shopping",
            "type":"Retail Goods"
        }
    ],
    "sg:phone":"+1 319 234 7942",
    "sg:postcode":"50702",
    "sg:province":"IA",
    "sg:tags":[
        "limb",
        "artificial"
    ],
    "sg:website":"www.oandp1.com",
    "wof:name":"O & P1",
    "wof:placetype":"venue"
},
  "geometry": {"coordinates":[-92.351011,42.463756],"type":"Point"}
}