{
  "type": "Feature",
  "properties": {
    "iso:country":"US",
    "sg:address":"7605 Aurora Ave",
    "sg:city":"Urbandale",
    "sg:classifiers":[
        {
            "category":"Social Services",
            "subcategory":"Child Care",
            "type":"Services"
        }
    ],
    "sg:phone":"+1 515 278 1034",
    "sg:postcode":"50322",
    "sg:province":"IA",
    "sg:tags":[
        "kindergarten",
        "academic",
        "school"
    ],
    "wof:name":"Patricia Park Pre-School",
    "wof:placetype":"venue"
},
  "geometry": {"coordinates":[-93.726281,41.636668],"type":"Point"}
}