{
  "type": "Feature",
  "properties": {
    "addr:full":"2274 US Hwy 34 Fairfield IA 52556",
    "addr:housenumber":"2274",
    "addr:postcode":"52556",
    "addr:street":"Us Hwy 34",
    "iso:country":"US",
    "sg:address":"2274 US Hwy 34",
    "sg:city":"Fairfield",
    "sg:classifiers":[
        {
            "category":"Wholesale",
            "subcategory":"Construction Materials",
            "type":"Manufacturing & Wholesale Goods"
        }
    ],
    "sg:phone":"+1 641 472 4555",
    "sg:postcode":"52556",
    "sg:province":"IA",
    "sg:tags":[
        "pallet",
        "skid"
    ],
    "wof:name":"Allsup Pallet Recycling Inc",
    "wof:placetype":"venue"
},
  "geometry": {"coordinates":[-91.931563,41.002714],"type":"Point"}
}