{
  "type": "Feature",
  "properties": {
    "iso:country":"US",
    "sg:address":"52 Main Ave N",
    "sg:city":"Britt",
    "sg:classifiers":[
        {
            "category":"Shopping",
            "subcategory":"Pharmacy",
            "type":"Retail Goods"
        }
    ],
    "sg:phone":"+1 641 843 3885",
    "sg:postcode":"50423",
    "sg:province":"IA",
    "wof:name":"Fedders Health Mart Pharmacy",
    "wof:placetype":"venue"
},
  "geometry": {"coordinates":[-93.801925,43.097364],"type":"Point"}
}