{
  "type": "Feature",
  "properties": {
    "iso:country":"US",
    "sg:address":"1740 Grace St",
    "sg:city":"Dubuque",
    "sg:classifiers":[
        {
            "category":"Building & Trades",
            "subcategory":"Construction",
            "type":"Services"
        }
    ],
    "sg:phone":"+1 563 588 0147",
    "sg:postcode":"52001",
    "sg:province":"IA",
    "sg:tags":[
        "contractor"
    ],
    "wof:name":"Arrow Construction",
    "wof:placetype":"venue"
},
  "geometry": {"coordinates":[-90.689666,42.496749],"type":"Point"}
}