{
  "type": "Feature",
  "properties": {
    "iso:country":"US",
    "sg:address":"1400 2nd Ave SE",
    "sg:city":"Cedar Rapids",
    "sg:classifiers":[
        {
            "category":"Real Estate",
            "subcategory":"Real Estate Agent",
            "type":"Services"
        }
    ],
    "sg:phone":"+1 319 363 2820",
    "sg:postcode":"52403",
    "sg:province":"IA",
    "sg:tags":[
        "appraiser"
    ],
    "wof:name":"Frese Appraisals",
    "wof:placetype":"venue"
},
  "geometry": {"coordinates":[-91.65138399999999,41.987252],"type":"Point"}
}