{
  "type": "Feature",
  "properties": {
    "iso:country":"US",
    "sg:address":"602 5th St",
    "sg:city":"Lohrville",
    "sg:classifiers":[
        {
            "category":"Autos & Motor Vehicles",
            "subcategory":"Fuel & Gas Station",
            "type":"Retail Goods"
        },
        {
            "category":"Retail",
            "subcategory":"Auto Repair",
            "type":"Services"
        }
    ],
    "sg:phone":"+1 712 465 3255",
    "sg:postcode":"51453",
    "sg:province":"IA",
    "sg:tags":[
        "repairing",
        "automobile",
        "station",
        "gasoline"
    ],
    "wof:name":"Terry's Service",
    "wof:placetype":"venue"
},
  "geometry": {"coordinates":[-94.547702,42.267071],"type":"Point"}
}