{
  "type": "Feature",
  "properties": {
    "iso:country":"US",
    "sg:address":"836 300th St",
    "sg:city":"Ogden",
    "sg:classifiers":[
        {
            "category":"Retail",
            "subcategory":"Repair Shop",
            "type":"Services"
        }
    ],
    "sg:phone":"+1 515 438 2645",
    "sg:postcode":"50212",
    "sg:province":"IA",
    "sg:tags":[
        "fix"
    ],
    "wof:name":"Lewiston Brothers Shop",
    "wof:placetype":"venue"
},
  "geometry": {"coordinates":[-94.00187099999999,41.921386],"type":"Point"}
}