{
  "type": "Feature",
  "properties": {
    "addr:full":"214 3rd St Keystone IA 52249",
    "addr:housenumber":"214",
    "addr:postcode":"52249",
    "addr:street":"3Rd St",
    "iso:country":"US",
    "sg:address":"214 3rd St",
    "sg:city":"Keystone",
    "sg:classifiers":[
        {
            "category":"Health Services",
            "subcategory":"Doctor",
            "type":"Services"
        }
    ],
    "sg:phone":"+1 319 442 3215",
    "sg:postcode":"52249",
    "sg:province":"IA",
    "sg:tags":[
        "clinic"
    ],
    "wof:name":"St Luke's Physicians Clncs",
    "wof:placetype":"venue"
},
  "geometry": {"coordinates":[-92.198584,42.001511],"type":"Point"}
}