{
  "type": "Feature",
  "properties": {
    "addr:full":"423 N Main St Goldfield IA 50542",
    "addr:housenumber":"423",
    "addr:postcode":"50542",
    "addr:street":"N Main St",
    "iso:country":"US",
    "sg:address":"423 N Main St",
    "sg:city":"Goldfield",
    "sg:classifiers":[
        {
            "category":"Government",
            "subcategory":"Office",
            "type":"Public Place"
        }
    ],
    "sg:phone":"+1 515 825 3613",
    "sg:postcode":"50542",
    "sg:province":"IA",
    "sg:tags":[
        "village"
    ],
    "wof:name":"Goldfield Council Room",
    "wof:placetype":"venue"
},
  "geometry": {"coordinates":[-93.92041999999999,42.735121],"type":"Point"}
}