{
  "type": "Feature",
  "properties": {
    "iso:country":"US",
    "sg:address":"410 1st St SW",
    "sg:city":"Le Mars",
    "sg:classifiers":[
        {
            "category":"Organizations",
            "subcategory":"Religious Organization",
            "type":"Services"
        }
    ],
    "sg:phone":"+1 712 546 4535",
    "sg:postcode":"51031",
    "sg:province":"IA",
    "wof:name":"Assembly of God Church",
    "wof:placetype":"venue"
},
  "geometry": {"coordinates":[-96.173663,42.791759],"type":"Point"}
}