{
  "type": "Feature",
  "properties": {
    "addr:full":"6921 Chaffee Rd Des Moines IA 50315",
    "addr:housenumber":"6921",
    "addr:postcode":"50315",
    "addr:street":"Chaffee Rd Des",
    "iso:country":"US",
    "sg:address":"6921 Chaffee Rd",
    "sg:city":"Des Moines",
    "sg:classifiers":[
        {
            "category":"Government",
            "subcategory":"Office",
            "type":"Public Place"
        }
    ],
    "sg:phone":"+1 515 287 3186",
    "sg:postcode":"50315",
    "sg:province":"IA",
    "wof:name":"US Fleet Management",
    "wof:placetype":"venue"
},
  "geometry": {"coordinates":[-93.61598499999999,41.521622],"type":"Point"}
}