{
  "type": "Feature",
  "properties": {
    "iso:country":"US",
    "sg:address":"708 Simon Ave",
    "sg:city":"Carroll",
    "sg:classifiers":[
        {
            "category":"Restaurant",
            "type":"Food & Drink"
        }
    ],
    "sg:phone":"+1 712 792 5587",
    "sg:postcode":"51401",
    "sg:province":"IA",
    "wof:name":"Hunan Chinese Restaurant",
    "wof:placetype":"venue"
},
  "geometry": {"coordinates":[-94.873366,42.069514],"type":"Point"}
}