{
  "type": "Feature",
  "properties": {
    "addr:full":"5411 Forest Dr Johnston IA 50131",
    "addr:housenumber":"5411",
    "addr:postcode":"50131",
    "addr:street":"Forest Dr",
    "iso:country":"US",
    "sg:address":"5411 Forest Dr",
    "sg:city":"Johnston",
    "sg:classifiers":[
        {
            "category":"Professional",
            "subcategory":"Engineering",
            "type":"Services"
        }
    ],
    "sg:phone":"+1 515 331 7753",
    "sg:postcode":"50131",
    "sg:province":"IA",
    "sg:tags":[
        "engineer"
    ],
    "wof:name":"Aartec Engineering",
    "wof:placetype":"venue"
},
  "geometry": {"coordinates":[-93.691422,41.687801],"type":"Point"}
}