{
  "type": "Feature",
  "properties": {
    "addr:full":"331 E Fayette St Osceola IA 50213",
    "addr:housenumber":"331",
    "addr:postcode":"50213",
    "addr:street":"E Fayette St",
    "iso:country":"US",
    "sg:address":"331 E Fayette St",
    "sg:city":"Osceola",
    "sg:classifiers":[
        {
            "category":"Manufacturing",
            "subcategory":"Apparel",
            "type":"Manufacturing & Wholesale Goods"
        }
    ],
    "sg:phone":"+1 641 342 4141",
    "sg:postcode":"50213",
    "sg:province":"IA",
    "sg:tags":[
        "household",
        "sewing",
        "furnishing",
        "mfg"
    ],
    "wof:name":"Designs By Belva White",
    "wof:placetype":"venue"
},
  "geometry": {"coordinates":[-93.76142900000001,41.026635],"type":"Point"}
}