{
  "type": "Feature",
  "properties": {
    "iso:country":"US",
    "sg:address":"500 Mulberry St",
    "sg:city":"Des Moines",
    "sg:classifiers":[
        {
            "category":"Government",
            "subcategory":"Office",
            "type":"Public Place"
        }
    ],
    "sg:phone":"+1 515 286 2187",
    "sg:postcode":"50309",
    "sg:province":"IA",
    "wof:name":"Honorable Gregory Brandt",
    "wof:placetype":"venue"
},
  "geometry": {"coordinates":[-93.624281,41.584979],"type":"Point"}
}