{
  "type": "Feature",
  "properties": {
    "iso:country":"US",
    "sg:address":"2600 72nd St",
    "sg:city":"Urbandale",
    "sg:classifiers":[
        {
            "category":"Professional",
            "type":"Services"
        }
    ],
    "sg:phone":"+1 515 276 0255",
    "sg:postcode":"50322",
    "sg:province":"IA",
    "sg:tags":[
        "establishment"
    ],
    "wof:name":"Infrastructure Solutions Inc",
    "wof:placetype":"venue"
},
  "geometry": {"coordinates":[-93.717156,41.619601],"type":"Point"}
}