{
  "type": "Feature",
  "properties": {
    "iso:country":"US",
    "sg:address":"3300 Iowa Ave SE",
    "sg:city":"Cedar Rapids",
    "sg:classifiers":[
        {
            "category":"Building & Trades",
            "subcategory":"Construction",
            "type":"Services"
        }
    ],
    "sg:phone":"+1 319 363 8900",
    "sg:postcode":"52403",
    "sg:province":"IA",
    "sg:tags":[
        "home",
        "builder",
        "contractor"
    ],
    "wof:name":"Doyle Homes & Development",
    "wof:placetype":"venue"
},
  "geometry": {"coordinates":[-91.620102,41.982101],"type":"Point"}
}