{
  "type": "Feature",
  "properties": {
    "iso:country":"US",
    "sg:address":"1410 E Harrison St",
    "sg:city":"Washington",
    "sg:phone":"+1 319 653 5125",
    "sg:postcode":"52353",
    "sg:province":"IA",
    "sg:tags":[
        "farm",
        "corn",
        "soybean"
    ],
    "wof:name":"Leo Vittetoe",
    "wof:placetype":"venue"
},
  "geometry": {"coordinates":[-91.674498,41.2919],"type":"Point"}
}