{
  "type": "Feature",
  "properties": {
    "iso:country":"US",
    "sg:address":"882 Balsam Ave",
    "sg:city":"Dows",
    "sg:classifiers":[
        {
            "category":"Building & Trades",
            "subcategory":"Landscaping Services",
            "type":"Services"
        }
    ],
    "sg:phone":"+1 515 852 4543",
    "sg:postcode":"50071",
    "sg:province":"IA",
    "wof:name":"Francis Lawn & Garden Service",
    "wof:placetype":"venue"
},
  "geometry": {"coordinates":[-93.478562,42.673351],"type":"Point"}
}