{
  "type": "Feature",
  "properties": {
    "addr:full":"1010 Scott Park Dr Iowa City IA 52245",
    "addr:housenumber":"1010",
    "addr:postcode":"52245",
    "addr:street":"Scott Park Dr",
    "iso:country":"US",
    "sg:address":"1010 Scott Park Dr",
    "sg:city":"Iowa City",
    "sg:classifiers":[
        {
            "category":"Health Services",
            "subcategory":"Health Practitioner",
            "type":"Services"
        }
    ],
    "sg:phone":"+1 319 351 4370",
    "sg:postcode":"52245",
    "sg:province":"IA",
    "sg:tags":[
        "nurse"
    ],
    "wof:name":"Dodge NP Co",
    "wof:placetype":"venue"
},
  "geometry": {"coordinates":[-91.48031400000001,41.659957],"type":"Point"}
}