{
  "type": "Feature",
  "properties": {
    "addr:full":"1949 Benton Iowa Rd Blairstown IA 52209",
    "addr:housenumber":"1949",
    "addr:postcode":"52209",
    "addr:street":"Benton Iowa Rd",
    "iso:country":"US",
    "sg:address":"1949 Benton Iowa Rd",
    "sg:city":"Blairstown",
    "sg:classifiers":[
        {
            "category":"Travel",
            "subcategory":"Campground",
            "type":"Entertainment"
        }
    ],
    "sg:phone":"+1 319 454 6382",
    "sg:postcode":"52209",
    "sg:province":"IA",
    "sg:tags":[
        "trailer"
    ],
    "wof:name":"Hannens Park",
    "wof:placetype":"venue"
},
  "geometry": {"coordinates":[-92.11322199999999,41.86275],"type":"Point"}
}