{
  "type": "Feature",
  "properties": {
    "iso:country":"US",
    "sg:address":"101 N Oak St",
    "sg:city":"Winfield",
    "sg:phone":"+1 319 257 3379",
    "sg:postcode":"52659",
    "sg:province":"IA",
    "sg:tags":[
        "farm",
        "field",
        "crop",
        "supply"
    ],
    "wof:name":"Ponda Rossa",
    "wof:placetype":"venue"
},
  "geometry": {"coordinates":[-91.432379,41.12968],"type":"Point"}
}