{
  "type": "Feature",
  "properties": {
    "addr:full":"216 N Main St Charles City IA 50616",
    "addr:housenumber":"216",
    "addr:postcode":"50616",
    "addr:street":"N Main St",
    "iso:country":"US",
    "sg:address":"216 N Main St",
    "sg:city":"Charles City",
    "sg:classifiers":[
        {
            "category":"Insurance",
            "subcategory":"Insurance Agent",
            "type":"Services"
        }
    ],
    "sg:phone":"+1 641 228 4321",
    "sg:postcode":"50616",
    "sg:province":"IA",
    "wof:name":"People's Insurance",
    "wof:placetype":"venue"
},
  "geometry": {"coordinates":[-92.678112,43.067982],"type":"Point"}
}