{
  "type": "Feature",
  "properties": {
    "addr:full":"558 Sunset View St Harpers Ferry IA 52146",
    "addr:housenumber":"558",
    "addr:postcode":"52146",
    "addr:street":"Sunset View St",
    "iso:country":"US",
    "sg:address":"558 Sunset View St",
    "sg:city":"Harpers Ferry",
    "sg:classifiers":[
        {
            "category":"Professional",
            "type":"Services"
        }
    ],
    "sg:phone":"+1 563 586 2941",
    "sg:postcode":"52146",
    "sg:province":"IA",
    "sg:tags":[
        "establishment"
    ],
    "wof:name":"Mc Kenna Professional Imaging",
    "wof:placetype":"venue"
},
  "geometry": {"coordinates":[-91.145627,43.205872],"type":"Point"}
}