{
  "type": "Feature",
  "properties": {
    "iso:country":"US",
    "sg:address":"2650 105th St",
    "sg:city":"Riverside",
    "sg:classifiers":[
        {
            "category":"Farming",
            "subcategory":"Farm",
            "type":"Manufacturing & Wholesale Goods"
        }
    ],
    "sg:phone":"+1 319 648 5102",
    "sg:postcode":"52327",
    "sg:province":"IA",
    "wof:name":"Metz Urban Farm",
    "wof:placetype":"venue"
},
  "geometry": {"coordinates":[-91.620755,41.504496],"type":"Point"}
}