{
  "type": "Feature",
  "properties": {
    "addr:full":"309 W Adams St Creston IA 50801",
    "addr:housenumber":"309",
    "addr:postcode":"50801",
    "addr:street":"W Adams St",
    "iso:country":"US",
    "sg:address":"309 W Adams St",
    "sg:city":"Creston",
    "sg:classifiers":[
        {
            "category":"Cinema",
            "subcategory":"Movie Theater",
            "type":"Entertainment"
        }
    ],
    "sg:phone":"+1 641 782 7224",
    "sg:postcode":"50801",
    "sg:province":"IA",
    "wof:name":"Strand Theatre",
    "wof:placetype":"venue"
},
  "geometry": {"coordinates":[-94.364988,41.057406],"type":"Point"}
}