{
  "type": "Feature",
  "properties": {
    "addr:full":"1929 Freedom St Osceola IA 50213",
    "addr:housenumber":"1929",
    "addr:postcode":"50213",
    "addr:street":"Freedom St",
    "iso:country":"US",
    "sg:address":"1929 Freedom St",
    "sg:city":"Osceola",
    "sg:classifiers":[
        {
            "category":"Farming",
            "subcategory":"Farm",
            "type":"Manufacturing & Wholesale Goods"
        }
    ],
    "sg:phone":"+1 641 342 3458",
    "sg:postcode":"50213",
    "sg:province":"IA",
    "sg:tags":[
        "hog",
        "beef",
        "crop",
        "general",
        "cattle",
        "or",
        "feedlot"
    ],
    "wof:name":"Mc Cann Tana",
    "wof:placetype":"venue"
},
  "geometry": {"coordinates":[-93.840878,40.970603],"type":"Point"}
}