{
  "type": "Feature",
  "properties": {
    "iso:country":"US",
    "sg:address":"12795 S 12th Ave E",
    "sg:city":"Kellogg",
    "sg:phone":"+1 641 526 8286",
    "sg:postcode":"50135",
    "sg:province":"IA",
    "sg:tags":[
        "farm",
        "corn",
        "soybean"
    ],
    "wof:name":"Roger Zylstra Farm",
    "wof:placetype":"venue"
},
  "geometry": {"coordinates":[-92.83295699999999,41.68803],"type":"Point"}
}