{
  "type": "Feature",
  "properties": {
    "iso:country":"US",
    "sg:address":"1811 Westfield Ave",
    "sg:city":"Waterloo",
    "sg:classifiers":[
        {
            "category":"Autos & Motor Vehicles",
            "subcategory":"Auto Supplies",
            "type":"Retail Goods"
        }
    ],
    "sg:phone":"+1 319 233 2354",
    "sg:postcode":"50701",
    "sg:province":"IA",
    "sg:tags":[
        "automobile",
        "parts"
    ],
    "wof:name":"IWI Motor Parts",
    "wof:placetype":"venue"
},
  "geometry": {"coordinates":[-92.365263,42.503382],"type":"Point"}
}