{
  "type": "Feature",
  "properties": {
    "iso:country":"US",
    "sg:address":"801 Bison Dr",
    "sg:city":"Nora Springs",
    "sg:classifiers":[
        {
            "category":"Health Services",
            "subcategory":"Health Practitioner",
            "type":"Services"
        }
    ],
    "sg:phone":"+1 641 749 2626",
    "sg:postcode":"50458",
    "sg:province":"IA",
    "sg:tags":[
        "nutritionist"
    ],
    "wof:name":"Nutrition Dynamics",
    "wof:placetype":"venue"
},
  "geometry": {"coordinates":[-92.995082,43.143],"type":"Point"}
}