{
  "type": "Feature",
  "properties": {
    "iso:country":"US",
    "sg:address":"217 4th Ave W",
    "sg:city":"Grinnell",
    "sg:classifiers":[
        {
            "category":"Health Services",
            "subcategory":"Doctor",
            "type":"Services"
        }
    ],
    "sg:phone":"+1 641 236 7524",
    "sg:postcode":"50112",
    "sg:province":"IA",
    "sg:tags":[
        "physician",
        "surgeon"
    ],
    "wof:name":"Grinnell Family Care",
    "wof:placetype":"venue"
},
  "geometry": {"coordinates":[-92.737649,41.743324],"type":"Point"}
}