{
  "type": "Feature",
  "properties": {
    "iso:country":"US",
    "sg:address":"23951 W Ave",
    "sg:city":"Reinbeck",
    "sg:classifiers":[
        {
            "category":"Farming",
            "subcategory":"Livestock Farm",
            "type":"Manufacturing & Wholesale Goods"
        }
    ],
    "sg:phone":"+1 319 345 2137",
    "sg:postcode":"50669",
    "sg:province":"IA",
    "sg:tags":[
        "hog",
        "or",
        "feedlot"
    ],
    "wof:name":"Albert Bovy",
    "wof:placetype":"venue"
},
  "geometry": {"coordinates":[-92.592359,42.355278],"type":"Point"}
}