{
  "type": "Feature",
  "properties": {
    "addr:full":"22 N Linn Ave New Hampton IA 50659",
    "addr:housenumber":"22",
    "addr:postcode":"50659",
    "addr:street":"N Linn Ave",
    "iso:country":"US",
    "sg:address":"22 N Linn Ave",
    "sg:city":"New Hampton",
    "sg:classifiers":[
        {
            "category":"Shopping",
            "subcategory":"Music",
            "type":"Retail Goods"
        }
    ],
    "sg:phone":"+1 641 394 5033",
    "sg:postcode":"50659",
    "sg:province":"IA",
    "sg:tags":[
        "video",
        "disc",
        "tape",
        "cassette"
    ],
    "wof:name":"M & M Movies",
    "wof:placetype":"venue"
},
  "geometry": {"coordinates":[-92.317905,43.060007],"type":"Point"}
}