{
  "type": "Feature",
  "properties": {
    "iso:country":"US",
    "sg:address":"100 N Taylor St",
    "sg:city":"Mt Ayr",
    "sg:classifiers":[
        {
            "category":"Insurance",
            "subcategory":"Insurance Agent",
            "type":"Services"
        }
    ],
    "sg:phone":"+1 641 464 3212",
    "sg:postcode":"50854",
    "sg:province":"IA",
    "wof:name":"William H French Agency",
    "wof:placetype":"venue"
},
  "geometry": {"coordinates":[-94.23752399999999,40.715267],"type":"Point"}
}