{
  "type": "Feature",
  "properties": {
    "addr:full":"444 1st St SW Britt IA 50423",
    "addr:housenumber":"444",
    "addr:postcode":"50423",
    "addr:street":"1St St Sw",
    "iso:country":"US",
    "sg:address":"444 1st St SW",
    "sg:city":"Britt",
    "sg:phone":"+1 641 843 4075",
    "sg:postcode":"50423",
    "sg:province":"IA",
    "sg:tags":[
        "farm",
        "corn"
    ],
    "wof:name":"Donald Dallman",
    "wof:placetype":"venue"
},
  "geometry": {"coordinates":[-93.80739,43.096105],"type":"Point"}
}