{
  "type": "Feature",
  "properties": {
    "iso:country":"US",
    "sg:address":"802 Kenyon Rd",
    "sg:city":"Fort Dodge",
    "sg:classifiers":[
        {
            "category":"Professional",
            "type":"Services"
        }
    ],
    "sg:phone":"+1 515 574 6100",
    "sg:postcode":"50501",
    "sg:province":"IA",
    "sg:tags":[
        "establishment"
    ],
    "wof:name":"Health Partners",
    "wof:placetype":"venue"
},
  "geometry": {"coordinates":[-94.189027,42.494249],"type":"Point"}
}