{
  "type": "Feature",
  "properties": {
    "iso:country":"US",
    "sg:address":"34897 Crystal Rd",
    "sg:city":"Strawberry Point",
    "sg:classifiers":[
        {
            "category":"Shopping",
            "type":"Retail Goods"
        }
    ],
    "sg:phone":"+1 563 933 6504",
    "sg:postcode":"52076",
    "sg:province":"IA",
    "sg:tags":[
        "wood",
        "carving"
    ],
    "wof:name":"Johnson Wood Products",
    "wof:placetype":"venue"
},
  "geometry": {"coordinates":[-91.476457,42.7185],"type":"Point"}
}