{
  "type": "Feature",
  "properties": {
    "iso:country":"US",
    "sg:address":"104 E Water St",
    "sg:city":"Decorah",
    "sg:classifiers":[
        {
            "category":"Travel",
            "subcategory":"Hotels & Motels",
            "type":"Entertainment"
        }
    ],
    "sg:phone":"+1 563 382 4164",
    "sg:postcode":"52101",
    "sg:province":"IA",
    "sg:website":"www.hotelwinn.com",
    "wof:name":"Hotel Winneshiek",
    "wof:placetype":"venue"
},
  "geometry": {"coordinates":[-91.785848,43.30421],"type":"Point"}
}