{
  "type": "Feature",
  "properties": {
    "iso:country":"US",
    "sg:address":"119 N Court St",
    "sg:city":"Fairfield",
    "sg:classifiers":[
        {
            "category":"Professional",
            "subcategory":"Lawyer & Legal Services",
            "type":"Services"
        }
    ],
    "sg:phone":"+1 641 472 5049",
    "sg:postcode":"52556",
    "sg:province":"IA",
    "sg:tags":[
        "attorney"
    ],
    "wof:name":"David P Miller Law Office",
    "wof:placetype":"venue"
},
  "geometry": {"coordinates":[-91.962394,41.00792],"type":"Point"}
}