{
  "type": "Feature",
  "properties": {
    "iso:country":"US",
    "sg:address":"17354 175th St",
    "sg:city":"Keosauqua",
    "sg:classifiers":[
        {
            "category":"Manufacturing",
            "subcategory":"Food",
            "type":"Manufacturing & Wholesale Goods"
        }
    ],
    "sg:phone":"+1 319 498 4364",
    "sg:postcode":"52565",
    "sg:province":"IA",
    "sg:tags":[
        "preparation"
    ],
    "wof:name":"Millards Turtle Meat Inc",
    "wof:placetype":"venue"
},
  "geometry": {"coordinates":[-92.039959,40.787136],"type":"Point"}
}