{
  "type": "Feature",
  "properties": {
    "addr:full":"3332 Ashworth Rd Waukee IA 50263",
    "addr:housenumber":"3332",
    "addr:postcode":"50263",
    "addr:street":"Ashworth Rd",
    "iso:country":"US",
    "sg:address":"3332 Ashworth Rd",
    "sg:city":"Waukee",
    "sg:classifiers":[
        {
            "category":"Organizations",
            "subcategory":"Religious Organization",
            "type":"Services"
        }
    ],
    "sg:phone":"+1 515 334 3525",
    "sg:postcode":"50263",
    "sg:province":"IA",
    "sg:tags":[
        "church"
    ],
    "wof:name":"Sunday Church",
    "wof:placetype":"venue"
},
  "geometry": {"coordinates":[-93.839725,41.580043],"type":"Point"}
}