{
  "type": "Feature",
  "properties": {
    "addr:full":"17554 Jonquil Ave Clear Lake IA 50428",
    "addr:housenumber":"17554",
    "addr:postcode":"50428",
    "addr:street":"Jonquil Ave",
    "iso:country":"US",
    "sg:address":"17554 Jonquil Ave",
    "sg:city":"Clear Lake",
    "sg:classifiers":[
        {
            "category":"Farming",
            "subcategory":"Poultry Farm",
            "type":"Manufacturing & Wholesale Goods"
        }
    ],
    "sg:phone":"+1 641 357 4747",
    "sg:postcode":"50428",
    "sg:province":"IA",
    "wof:name":"Nicholas Turkey Farms & Htchry",
    "wof:placetype":"venue"
},
  "geometry": {"coordinates":[-93.320134,43.148281],"type":"Point"}
}