{
  "type": "Feature",
  "properties": {
    "iso:country":"US",
    "sg:address":"315 9th Ave",
    "sg:city":"Wellman",
    "sg:classifiers":[
        {
            "category":"Health Services",
            "subcategory":"Chiropractor",
            "type":"Services"
        }
    ],
    "sg:phone":"+1 319 646 6533",
    "sg:postcode":"52356",
    "sg:province":"IA",
    "wof:name":"Chiropractice",
    "wof:placetype":"venue"
},
  "geometry": {"coordinates":[-91.839124,41.466441],"type":"Point"}
}