{
  "type": "Feature",
  "properties": {
    "addr:full":"4101 E 14th St Des Moines IA 50313",
    "addr:housenumber":"4101",
    "addr:postcode":"50313",
    "addr:street":"E 14Th St",
    "iso:country":"US",
    "sg:address":"4101 E 14th St",
    "sg:city":"Des Moines",
    "sg:classifiers":[
        {
            "category":"Retail",
            "subcategory":"Auto Rental",
            "type":"Services"
        }
    ],
    "sg:phone":"+1 515 265 6016",
    "sg:postcode":"50313",
    "sg:province":"IA",
    "sg:tags":[
        "renting",
        "truck",
        "leasing"
    ],
    "sg:website":"www.penske.com",
    "wof:name":"Penske Truck Leasing",
    "wof:placetype":"venue"
},
  "geometry": {"coordinates":[-93.600526,41.636668],"type":"Point"}
}