{
  "type": "Feature",
  "properties": {
    "iso:country":"US",
    "sg:address":"122 3rd Ave SE",
    "sg:city":"Cedar Rapids",
    "sg:classifiers":[
        {
            "category":"Real Estate",
            "subcategory":"Real Estate Services",
            "type":"Services"
        }
    ],
    "sg:phone":"+1 319 247 5000",
    "sg:postcode":"52401",
    "sg:province":"IA",
    "wof:name":"Stagg Tim Rl Est",
    "wof:placetype":"venue"
},
  "geometry": {"coordinates":[-91.667198,41.976601],"type":"Point"}
}