{
  "type": "Feature",
  "properties": {
    "addr:full":"2627 Hickory Grove Rd Davenport IA 52804",
    "addr:housenumber":"2627",
    "addr:postcode":"52804",
    "addr:street":"Hickory Grove Rd",
    "iso:country":"US",
    "sg:address":"2627 Hickory Grove Rd",
    "sg:city":"Davenport",
    "sg:classifiers":[
        {
            "category":"Organizations",
            "subcategory":"Religious Organization",
            "type":"Services"
        }
    ],
    "sg:phone":"+1 563 386 9772",
    "sg:postcode":"52804",
    "sg:province":"IA",
    "sg:tags":[
        "church"
    ],
    "wof:name":"Good News Ctr",
    "wof:placetype":"venue"
},
  "geometry": {"coordinates":[-90.611946,41.546581],"type":"Point"}
}