{
  "type": "Feature",
  "properties": {
    "addr:full":"1330 1st Ave NE Cedar Rapids IA 52402",
    "addr:housenumber":"1330",
    "addr:postcode":"52402",
    "addr:street":"1St Ave Ne",
    "iso:country":"US",
    "sg:address":"1330 1st Ave NE",
    "sg:city":"Cedar Rapids",
    "sg:classifiers":[
        {
            "category":"Wholesale",
            "subcategory":"Medical Equipment & Supplies",
            "type":"Manufacturing & Wholesale Goods"
        }
    ],
    "sg:phone":"+1 319 364 8118",
    "sg:postcode":"52402",
    "sg:province":"IA",
    "sg:tags":[
        "hospital"
    ],
    "wof:name":"American Home Patient Inc",
    "wof:placetype":"venue"
},
  "geometry": {"coordinates":[-91.654343,41.986944],"type":"Point"}
}