{
  "type": "Feature",
  "properties": {
    "iso:country":"US",
    "sg:address":"4880 Texas St",
    "sg:city":"Waterloo",
    "sg:classifiers":[
        {
            "category":"Communications",
            "subcategory":"Radio Station",
            "type":"Services"
        }
    ],
    "sg:phone":"+1 319 296 1975",
    "sg:postcode":"50702",
    "sg:province":"IA",
    "sg:tags":[
        "company",
        "broadcasting"
    ],
    "sg:website":"www.knws.org",
    "wof:name":"KNWS",
    "wof:placetype":"venue"
},
  "geometry": {"coordinates":[-92.299305,42.445252],"type":"Point"}
}