{
  "type": "Feature",
  "properties": {
    "iso:country":"US",
    "sg:address":"109 E Delaware St",
    "sg:city":"Manchester",
    "sg:classifiers":[
        {
            "category":"Manufacturing",
            "subcategory":"Printing",
            "type":"Manufacturing & Wholesale Goods"
        }
    ],
    "sg:phone":"+1 563 927 2020",
    "sg:postcode":"52057",
    "sg:province":"IA",
    "sg:tags":[
        "newspaper"
    ],
    "wof:name":"Manchester Press",
    "wof:placetype":"venue"
},
  "geometry": {"coordinates":[-91.45780999999999,42.482984],"type":"Point"}
}