{
  "type": "Feature",
  "properties": {
    "iso:country":"US",
    "sg:address":"4001 Jackson St",
    "sg:city":"Sioux City",
    "sg:classifiers":[
        {
            "category":"Professional",
            "subcategory":"Business Services",
            "type":"Services"
        }
    ],
    "sg:phone":"+1 712 277 4612",
    "sg:postcode":"51104",
    "sg:province":"IA",
    "wof:name":"Mhm Enterprises Inc",
    "wof:placetype":"venue"
},
  "geometry": {"coordinates":[-96.403329,42.537912],"type":"Point"}
}