{
  "type": "Feature",
  "properties": {
    "iso:country":"US",
    "sg:address":"1037 N Ave",
    "sg:city":"Jefferson",
    "sg:classifiers":[
        {
            "category":"Farming",
            "subcategory":"Farm",
            "type":"Manufacturing & Wholesale Goods"
        }
    ],
    "sg:phone":"+1 515 386 4455",
    "sg:postcode":"50129",
    "sg:province":"IA",
    "wof:name":"Haupert Grain & Livestock LTD",
    "wof:placetype":"venue"
},
  "geometry": {"coordinates":[-94.37841,42.072761],"type":"Point"}
}