{
  "type": "Feature",
  "properties": {
    "addr:full":"4044 E Garden Ave Des Moines IA 50317",
    "addr:housenumber":"4044",
    "addr:postcode":"50317",
    "addr:street":"E Garden Ave",
    "iso:country":"US",
    "sg:address":"4044 E Garden Ave",
    "sg:city":"Des Moines",
    "sg:classifiers":[
        {
            "category":"Arts & Performance",
            "subcategory":"Theater",
            "type":"Entertainment"
        }
    ],
    "sg:phone":"+1 515 262 7685",
    "sg:postcode":"50317",
    "sg:province":"IA",
    "sg:tags":[
        "group"
    ],
    "wof:name":"Mc Unlimited",
    "wof:placetype":"venue"
},
  "geometry": {"coordinates":[-93.532825,41.630567],"type":"Point"}
}