{
  "type": "Feature",
  "properties": {
    "iso:country":"US",
    "sg:address":"1921 500th St",
    "sg:city":"Hawarden",
    "sg:classifiers":[
        {
            "category":"Retail",
            "subcategory":"Auto Repair",
            "type":"Services"
        }
    ],
    "sg:phone":"+1 712 552 1271",
    "sg:postcode":"51023",
    "sg:province":"SD",
    "sg:tags":[
        "repairing",
        "automobile"
    ],
    "wof:name":"Jim's Repair Inc",
    "wof:placetype":"venue"
},
  "geometry": {"coordinates":[-96.400603,42.923816],"type":"Point"}
}