{
  "type": "Feature",
  "properties": {
    "iso:country":"US",
    "sg:address":"5705 Old Lakeport Rd",
    "sg:city":"Sioux City",
    "sg:classifiers":[
        {
            "category":"Banks & Credit Unions",
            "subcategory":"Financial Services",
            "type":"Services"
        }
    ],
    "sg:phone":"+1 712 943 4455",
    "sg:postcode":"51106",
    "sg:province":"SD",
    "sg:tags":[
        "investor"
    ],
    "wof:name":"Olaf Inc",
    "wof:placetype":"venue"
},
  "geometry": {"coordinates":[-96.34209799999999,42.430485],"type":"Point"}
}