{
  "type": "Feature",
  "properties": {
    "iso:country":"US",
    "sg:address":"101 NW 7th St",
    "sg:city":"Pocahontas",
    "sg:classifiers":[
        {
            "category":"Shopping",
            "subcategory":"Used Merchandise",
            "type":"Retail Goods"
        },
        {
            "category":"Shopping",
            "subcategory":"Gifts & Souvenirs",
            "type":"Retail Goods"
        }
    ],
    "sg:phone":"+1 712 335 4929",
    "sg:postcode":"50574",
    "sg:province":"IA",
    "sg:tags":[
        "antique"
    ],
    "wof:name":"Rhythm & Blooms Ltd",
    "wof:placetype":"venue"
},
  "geometry": {"coordinates":[-94.678906,42.733182],"type":"Point"}
}