{
  "type": "Feature",
  "properties": {
    "iso:country":"US",
    "sg:address":"213 Duff Ave",
    "sg:city":"Ames",
    "sg:classifiers":[
        {
            "category":"Recreation",
            "type":"Entertainment"
        }
    ],
    "sg:phone":"+1 515 233 1655",
    "sg:postcode":"50010",
    "sg:province":"IA",
    "sg:tags":[
        "amusement"
    ],
    "wof:name":"Advanced Fitness & Performance",
    "wof:placetype":"venue"
},
  "geometry": {"coordinates":[-93.61048599999999,42.024394],"type":"Point"}
}