{
  "type": "Feature",
  "properties": {
    "iso:country":"US",
    "sg:address":"107 SE 6th St",
    "sg:city":"Des Moines",
    "sg:classifiers":[
        {
            "category":"Retail",
            "subcategory":"Auto Repair",
            "type":"Services"
        }
    ],
    "sg:phone":"+1 515 244 3780",
    "sg:postcode":"50309",
    "sg:province":"IA",
    "sg:tags":[
        "repairing",
        "automobile"
    ],
    "wof:name":"Don's Tire & Auto Repair",
    "wof:placetype":"venue"
},
  "geometry": {"coordinates":[-93.608344,41.586128],"type":"Point"}
}