{
  "type": "Feature",
  "properties": {
    "iso:country":"US",
    "sg:address":"702 Nile Kinnick Dr S",
    "sg:city":"Adel",
    "sg:classifiers":[
        {
            "category":"Organizations",
            "subcategory":"Religious Organization",
            "type":"Services"
        }
    ],
    "sg:phone":"+1 515 993 3418",
    "sg:postcode":"50003",
    "sg:province":"IA",
    "sg:tags":[
        "church"
    ],
    "wof:name":"First Southern Baptist Church",
    "wof:placetype":"venue"
},
  "geometry": {"coordinates":[-94.01737799999999,41.611215],"type":"Point"}
}