{
  "type": "Feature",
  "properties": {
    "iso:country":"US",
    "sg:address":"408 W Boone St",
    "sg:city":"Marshalltown",
    "sg:classifiers":[
        {
            "category":"Freight",
            "type":"Transportation"
        }
    ],
    "sg:phone":"+1 641 753 1028",
    "sg:postcode":"50158",
    "sg:province":"IA",
    "sg:tags":[
        "automobile",
        "storage"
    ],
    "wof:name":"Mid Iowa Mini Storage",
    "wof:placetype":"venue"
},
  "geometry": {"coordinates":[-92.920834,42.045407],"type":"Point"}
}