{
  "type": "Feature",
  "properties": {
    "iso:country":"US",
    "sg:address":"912 S 14th Ave",
    "sg:city":"Marshalltown",
    "sg:classifiers":[
        {
            "category":"Building & Trades",
            "subcategory":"Construction",
            "type":"Services"
        }
    ],
    "sg:phone":"+1 641 752 5771",
    "sg:postcode":"50158",
    "sg:province":"IA",
    "sg:tags":[
        "house"
    ],
    "wof:name":"Campbell Tom Contractors",
    "wof:placetype":"venue"
},
  "geometry": {"coordinates":[-92.88968199999999,42.038119],"type":"Point"}
}