{
  "type": "Feature",
  "properties": {
    "addr:full":"1125 130th St Renwick IA 50577",
    "addr:housenumber":"1125",
    "addr:postcode":"50577",
    "addr:street":"130Th St",
    "iso:country":"US",
    "sg:address":"1125 130th St",
    "sg:city":"Renwick",
    "sg:phone":"+1 515 824 3519",
    "sg:postcode":"50577",
    "sg:province":"IA",
    "sg:tags":[
        "hog",
        "farm",
        "corn",
        "soybean",
        "or",
        "feedlot"
    ],
    "wof:name":"Mark Wigans",
    "wof:placetype":"venue"
},
  "geometry": {"coordinates":[-93.945988,42.861771],"type":"Point"}
}