{
  "type": "Feature",
  "properties": {
    "addr:full":"2636 Marilyn Rd Ottumwa IA 52501",
    "addr:housenumber":"2636",
    "addr:postcode":"52501",
    "addr:street":"Marilyn Rd",
    "iso:country":"US",
    "sg:address":"2636 Marilyn Rd",
    "sg:city":"Ottumwa",
    "sg:classifiers":[
        {
            "category":"Banks & Credit Unions",
            "subcategory":"Investment Brokerage",
            "type":"Services"
        }
    ],
    "sg:phone":"+1 641 684 7825",
    "sg:postcode":"52501",
    "sg:province":"IA",
    "sg:tags":[
        "management"
    ],
    "wof:name":"Perkins Investment Management",
    "wof:placetype":"venue"
},
  "geometry": {"coordinates":[-92.412486,41.05465],"type":"Point"}
}