{
  "type": "Feature",
  "properties": {
    "iso:country":"US",
    "sg:address":"805 N Compton Dr",
    "sg:city":"Hiawatha",
    "sg:classifiers":[
        {
            "category":"Manufacturing",
            "subcategory":"Retail Goods",
            "type":"Manufacturing & Wholesale Goods"
        }
    ],
    "sg:phone":"+1 319 294 6753",
    "sg:postcode":"52233",
    "sg:province":"IA",
    "sg:tags":[
        "hair"
    ],
    "sg:website":"www.evanscric.com",
    "wof:name":"Evans Enterprises",
    "wof:placetype":"venue"
},
  "geometry": {"coordinates":[-91.691445,42.045549],"type":"Point"}
}