{
  "type": "Feature",
  "properties": {
    "addr:full":"427 Nash St Aplington IA 50604",
    "addr:housenumber":"427",
    "addr:postcode":"50604",
    "addr:street":"Nash St",
    "iso:country":"US",
    "sg:address":"427 Nash St",
    "sg:city":"Aplington",
    "sg:classifiers":[
        {
            "category":"Social Services",
            "subcategory":"Child Care",
            "type":"Services"
        }
    ],
    "sg:phone":"+1 319 347 6366",
    "sg:postcode":"50604",
    "sg:province":"IA",
    "wof:name":"Kidquest",
    "wof:placetype":"venue"
},
  "geometry": {"coordinates":[-92.87635299999999,42.582954],"type":"Point"}
}