{
  "type": "Feature",
  "properties": {
    "addr:full":"2158 179th St Fort Dodge IA 50501",
    "addr:housenumber":"2158",
    "addr:postcode":"50501",
    "addr:street":"179Th St",
    "iso:country":"US",
    "sg:address":"2158 179th St",
    "sg:city":"Fort Dodge",
    "sg:classifiers":[
        {
            "category":"Shopping",
            "subcategory":"Catalog Store",
            "type":"Retail Goods"
        }
    ],
    "sg:phone":"+1 515 573 4440",
    "sg:postcode":"50501",
    "sg:province":"IA",
    "sg:tags":[
        "house",
        "mail"
    ],
    "wof:name":"Avon",
    "wof:placetype":"venue"
},
  "geometry": {"coordinates":[-94.21596099999999,42.530876],"type":"Point"}
}