{
  "type": "Feature",
  "properties": {
    "addr:full":"2601 E Euclid Ave Des Moines IA 50317",
    "addr:housenumber":"2601",
    "addr:postcode":"50317",
    "addr:street":"E Euclid Ave",
    "iso:country":"US",
    "sg:address":"2601 E Euclid Ave",
    "sg:city":"Des Moines",
    "sg:classifiers":[
        {
            "category":"Restaurant",
            "type":"Food & Drink"
        }
    ],
    "sg:menulink":"http://www.allmenus.com/ia/lee/80668-papa-johns-pizza/menu/",
    "sg:phone":"+1 515 261 7272",
    "sg:postcode":"50317",
    "sg:province":"IA",
    "sg:tags":[
        "american",
        "pizza"
    ],
    "wof:name":"Papa John's Pizza",
    "wof:placetype":"venue"
},
  "geometry": {"coordinates":[-93.56623399999999,41.627351],"type":"Point"}
}