{
  "type": "Feature",
  "properties": {
    "iso:country":"US",
    "sg:address":"19259 231st St",
    "sg:city":"Manchester",
    "sg:classifiers":[
        {
            "category":"Real Estate",
            "subcategory":"Real Estate Operator",
            "type":"Services"
        }
    ],
    "sg:phone":"+1 563 927 2169",
    "sg:postcode":"52057",
    "sg:province":"IA",
    "sg:tags":[
        "property",
        "lessor"
    ],
    "wof:name":"Freeman Smith",
    "wof:placetype":"venue"
},
  "geometry": {"coordinates":[-91.414706,42.452654],"type":"Point"}
}