{
  "type": "Feature",
  "properties": {
    "iso:country":"US",
    "sg:address":"12964 244th Ave",
    "sg:city":"Moravia",
    "sg:classifiers":[
        {
            "category":"Building & Trades",
            "subcategory":"Cleaning & Sanitation",
            "type":"Services"
        }
    ],
    "sg:phone":"+1 641 724 3654",
    "sg:postcode":"52571",
    "sg:province":"IA",
    "sg:tags":[
        "janitorial"
    ],
    "wof:name":"Linda Ware",
    "wof:placetype":"venue"
},
  "geometry": {"coordinates":[-92.82079899999999,40.856616],"type":"Point"}
}