{
  "type": "Feature",
  "properties": {
    "iso:country":"US",
    "sg:address":"201 S Station St",
    "sg:city":"Mingo",
    "sg:classifiers":[
        {
            "category":"Professional",
            "subcategory":"Lawyer & Legal Services",
            "type":"Services"
        }
    ],
    "sg:phone":"+1 641 363 4365",
    "sg:postcode":"50168",
    "sg:province":"IA",
    "sg:tags":[
        "attorney"
    ],
    "wof:name":"Phelps Law Office",
    "wof:placetype":"venue"
},
  "geometry": {"coordinates":[-93.283568,41.765256],"type":"Point"}
}