{
  "type": "Feature",
  "properties": {
    "iso:country":"US",
    "sg:address":"507 Vernon St",
    "sg:city":"West Burlington",
    "sg:classifiers":[
        {
            "category":"Real Estate",
            "subcategory":"Real Estate Operator",
            "type":"Services"
        }
    ],
    "sg:phone":"+1 319 752 4797",
    "sg:postcode":"52655",
    "sg:province":"IA",
    "sg:tags":[
        "apartment"
    ],
    "wof:name":"Westland Apartments",
    "wof:placetype":"venue"
},
  "geometry": {"coordinates":[-91.164176,40.821523],"type":"Point"}
}