{
  "type": "Feature",
  "properties": {
    "iso:country":"US",
    "sg:address":"1115 Johnson St",
    "sg:city":"Keokuk",
    "sg:classifiers":[
        {
            "category":"Building & Trades",
            "subcategory":"Plumbing",
            "type":"Services"
        }
    ],
    "sg:phone":"+1 319 524 1631",
    "sg:postcode":"52632",
    "sg:province":"IA",
    "sg:tags":[
        "conditioning",
        "air",
        "system",
        "contractor"
    ],
    "wof:name":"All Season Heating & Cooling",
    "wof:placetype":"venue"
},
  "geometry": {"coordinates":[-91.389971,40.400575],"type":"Point"}
}