{
  "type": "Feature",
  "properties": {
    "addr:full":"5415 Douglas Ave Des Moines IA 50310",
    "addr:housenumber":"5415",
    "addr:postcode":"50310",
    "addr:street":"Douglas Ave",
    "iso:country":"US",
    "sg:address":"5415 Douglas Ave",
    "sg:city":"Des Moines",
    "sg:classifiers":[
        {
            "category":"Restaurant",
            "type":"Food & Drink"
        },
        {
            "category":"Ice Cream",
            "type":"Food & Drink"
        }
    ],
    "sg:menulink":"http://www.allmenus.com/ia/des-moines/172687-dairy-queen/menu/",
    "sg:phone":"+1 515 278 1847",
    "sg:postcode":"50310",
    "sg:province":"IA",
    "sg:tags":[
        "burger",
        "american",
        "ice",
        "cream"
    ],
    "wof:name":"Dairy Queen",
    "wof:placetype":"venue"
},
  "geometry": {"coordinates":[-93.693499,41.629702],"type":"Point"}
}