{
  "type": "Feature",
  "properties": {
    "iso:country":"US",
    "sg:address":"412 Iowa Ave",
    "sg:city":"Nora Springs",
    "sg:classifiers":[
        {
            "category":"Building & Trades",
            "subcategory":"Plumbing",
            "type":"Services"
        }
    ],
    "sg:phone":"+1 641 749 5387",
    "sg:postcode":"50458",
    "sg:province":"IA",
    "sg:tags":[
        "contractor"
    ],
    "wof:name":"Kevs Drain Cleaning",
    "wof:placetype":"venue"
},
  "geometry": {"coordinates":[-93.004457,43.147114],"type":"Point"}
}