{
  "type": "Feature",
  "properties": {
    "addr:full":"1609 5th St Perry IA 50220",
    "addr:housenumber":"1609",
    "addr:postcode":"50220",
    "addr:street":"5Th St",
    "iso:country":"US",
    "sg:address":"1609 5th St",
    "sg:city":"Perry",
    "sg:classifiers":[
        {
            "category":"Real Estate",
            "subcategory":"Real Estate Operator",
            "type":"Services"
        }
    ],
    "sg:phone":"+1 515 465 2287",
    "sg:postcode":"50220",
    "sg:province":"IA",
    "sg:tags":[
        "property",
        "lessor"
    ],
    "wof:name":"Marjorie Fish",
    "wof:placetype":"venue"
},
  "geometry": {"coordinates":[-94.101167,41.844532],"type":"Point"}
}