{
  "type": "Feature",
  "properties": {
    "iso:country":"US",
    "sg:address":"1281 Lake Ave",
    "sg:city":"Storm Lake",
    "sg:classifiers":[
        {
            "category":"Restaurant",
            "type":"Food & Drink"
        }
    ],
    "sg:menulink":"http://www.allmenus.com/ia/storm-lake/202742-mcdonalds/menu/",
    "sg:postcode":"50588",
    "sg:province":"IA",
    "sg:tags":[
        "burger",
        "american"
    ],
    "wof:name":"McDonald's",
    "wof:placetype":"venue"
},
  "geometry": {"coordinates":[-95.200602,42.647092],"type":"Point"}
}