{
  "type": "Feature",
  "properties": {
    "addr:full":"101 E Locust St Des Moines IA 50309",
    "addr:housenumber":"101",
    "addr:postcode":"50309",
    "addr:street":"E Locust St",
    "iso:country":"US",
    "sg:address":"101 E Locust St",
    "sg:city":"Des Moines",
    "sg:classifiers":[
        {
            "category":"Restaurant",
            "type":"Food & Drink"
        }
    ],
    "sg:phone":"+1 515 244 1700",
    "sg:postcode":"50309",
    "sg:province":"IA",
    "sg:tags":[
        "eating"
    ],
    "wof:name":"Doozies",
    "wof:placetype":"venue"
},
  "geometry": {"coordinates":[-93.61618799999999,41.588567],"type":"Point"}
}