{
  "type": "Feature",
  "properties": {
    "addr:full":"5517 118th Ave Ottumwa IA 52501",
    "addr:housenumber":"5517",
    "addr:postcode":"52501",
    "addr:street":"118Th Ave",
    "iso:country":"US",
    "sg:address":"5517 118th Ave",
    "sg:city":"Ottumwa",
    "sg:classifiers":[
        {
            "category":"Professional",
            "subcategory":"Management & Consulting",
            "type":"Services"
        }
    ],
    "sg:phone":"+1 641 682 2326",
    "sg:postcode":"52501",
    "sg:province":"IA",
    "wof:name":"Equine Leaders Network Inc",
    "wof:placetype":"venue"
},
  "geometry": {"coordinates":[-92.382248,40.965852],"type":"Point"}
}