{
  "type": "Feature",
  "properties": {
    "addr:full":"5316 210th Ave Albert City IA 50510",
    "addr:housenumber":"5316",
    "addr:postcode":"50510",
    "addr:street":"210Th Ave Albert",
    "iso:country":"US",
    "sg:address":"5316 210th Ave",
    "sg:city":"Albert City",
    "sg:phone":"+1 712 843 5393",
    "sg:postcode":"50510",
    "sg:province":"IA",
    "sg:tags":[
        "farm",
        "corn"
    ],
    "wof:name":"Elwood Loving",
    "wof:placetype":"venue"
},
  "geometry": {"coordinates":[-94.99248,42.746517],"type":"Point"}
}