{
  "type": "Feature",
  "properties": {
    "iso:country":"US",
    "sg:address":"1701 Mount Pleasant St",
    "sg:city":"Burlington",
    "sg:classifiers":[
        {
            "category":"Retail",
            "subcategory":"Auto Repair",
            "type":"Services"
        }
    ],
    "sg:phone":"+1 319 752 4361",
    "sg:postcode":"52601",
    "sg:province":"IA",
    "sg:tags":[
        "repairing",
        "automobile"
    ],
    "wof:name":"Precision Repair",
    "wof:placetype":"venue"
},
  "geometry": {"coordinates":[-91.12230599999999,40.820004],"type":"Point"}
}