{
  "type": "Feature",
  "properties": {
    "iso:country":"US",
    "sg:address":"2735 Mount Pleasant St",
    "sg:city":"Burlington",
    "sg:classifiers":[
        {
            "category":"Building & Trades",
            "subcategory":"Landscaping Services",
            "type":"Services"
        }
    ],
    "sg:phone":"+1 319 752 2135",
    "sg:postcode":"52601",
    "sg:province":"IA",
    "wof:name":"Grupe Nursery",
    "wof:placetype":"venue"
},
  "geometry": {"coordinates":[-91.140237,40.825749],"type":"Point"}
}