{
  "type": "Feature",
  "properties": {
    "addr:full":"5216 230th Ave Albert City IA 50510",
    "addr:housenumber":"5216",
    "addr:postcode":"50510",
    "addr:street":"230Th Ave Albert",
    "iso:country":"US",
    "sg:address":"5216 230th Ave",
    "sg:city":"Albert City",
    "sg:classifiers":[
        {
            "category":"Organizations",
            "subcategory":"Religious Organization",
            "type":"Services"
        }
    ],
    "sg:phone":"+1 712 843 5362",
    "sg:postcode":"50510",
    "sg:province":"IA",
    "wof:name":"St Johns Lutheran Church",
    "wof:placetype":"venue"
},
  "geometry": {"coordinates":[-94.953138,42.760919],"type":"Point"}
}