{
  "type": "Feature",
  "properties": {
    "iso:country":"US",
    "sg:address":"1700 22nd St",
    "sg:city":"West Des Moines",
    "sg:classifiers":[
        {
            "category":"Restaurant",
            "type":"Food & Drink"
        }
    ],
    "sg:menulink":"http://www.allmenus.com/ia/walnut/158447-arbys/menu/",
    "sg:phone":"+1 515 440 3599",
    "sg:postcode":"50266",
    "sg:province":"IA",
    "sg:tags":[
        "burger",
        "american"
    ],
    "wof:name":"Arby's",
    "wof:placetype":"venue"
},
  "geometry": {"coordinates":[-93.73693,41.597971],"type":"Point"}
}