{
  "type": "Feature",
  "properties": {
    "iso:country":"US",
    "sg:address":"2780 Tower Dr",
    "sg:city":"Cedar Rapids",
    "sg:classifiers":[
        {
            "category":"Building & Trades",
            "subcategory":"Construction",
            "type":"Services"
        }
    ],
    "sg:phone":"+1 319 378 8945",
    "sg:postcode":"52411",
    "sg:province":"IA",
    "sg:tags":[
        "carpentry",
        "contractor"
    ],
    "wof:name":"Wood Working Etc",
    "wof:placetype":"venue"
},
  "geometry": {"coordinates":[-91.71475,42.064914],"type":"Point"}
}