{
  "type": "Feature",
  "properties": {
    "addr:full":"711 Morgan St Keokuk IA 52632",
    "addr:housenumber":"711",
    "addr:postcode":"52632",
    "addr:street":"Morgan St",
    "iso:country":"US",
    "sg:address":"711 Morgan St",
    "sg:city":"Keokuk",
    "sg:classifiers":[
        {
            "category":"Education",
            "subcategory":"Dance Studio",
            "type":"Public Place"
        }
    ],
    "sg:phone":"+1 319 524 5867",
    "sg:postcode":"52632",
    "sg:province":"IA",
    "wof:name":"Unlimited Dance & Tumbling",
    "wof:placetype":"venue"
},
  "geometry": {"coordinates":[-91.381488,40.400632],"type":"Point"}
}