{
  "type": "Feature",
  "properties": {
    "iso:country":"US",
    "sg:address":"699 Walnut St",
    "sg:city":"Des Moines",
    "sg:classifiers":[
        {
            "category":"Professional",
            "subcategory":"Lawyer & Legal Services",
            "type":"Services"
        }
    ],
    "sg:phone":"+1 515 246 4506",
    "sg:postcode":"50309",
    "sg:province":"IA",
    "sg:tags":[
        "attorney"
    ],
    "wof:name":"David S Steward",
    "wof:placetype":"venue"
},
  "geometry": {"coordinates":[-93.62462499999999,41.585906],"type":"Point"}
}