{
  "type": "Feature",
  "properties": {
    "iso:country":"US",
    "sg:address":"2392 16th St NW",
    "sg:city":"Clinton",
    "sg:classifiers":[
        {
            "category":"Building & Trades",
            "subcategory":"Electrical",
            "type":"Services"
        }
    ],
    "sg:phone":"+1 563 242 8604",
    "sg:postcode":"52732",
    "sg:province":"IA",
    "sg:tags":[
        "electric",
        "contractor"
    ],
    "wof:name":"Preferred Electric",
    "wof:placetype":"venue"
},
  "geometry": {"coordinates":[-90.223592,41.864561],"type":"Point"}
}