{
  "type": "Feature",
  "properties": {
    "iso:country":"US",
    "sg:address":"3145 Harrison Ave",
    "sg:city":"Hull",
    "sg:classifiers":[
        {
            "category":"Farming",
            "subcategory":"Livestock Farm",
            "type":"Manufacturing & Wholesale Goods"
        }
    ],
    "sg:phone":"+1 712 439 1605",
    "sg:postcode":"51239",
    "sg:province":"IA",
    "sg:tags":[
        "beef",
        "feedlot",
        "cattle"
    ],
    "wof:name":"Vernon Hoekstra",
    "wof:placetype":"venue"
},
  "geometry": {"coordinates":[-96.15760400000001,43.193759],"type":"Point"}
}