{
  "type": "Feature",
  "properties": {
    "addr:full":"105 W Ellsworth St Dows IA 50071",
    "addr:housenumber":"105",
    "addr:postcode":"50071",
    "addr:street":"W Ellsworth St",
    "iso:country":"US",
    "sg:address":"105 W Ellsworth St",
    "sg:city":"Dows",
    "sg:classifiers":[
        {
            "category":"Government",
            "subcategory":"Post Office",
            "type":"Public Place"
        }
    ],
    "sg:phone":"+1 515 852 4243",
    "sg:postcode":"50071",
    "sg:province":"IA",
    "wof:name":"US Post Office",
    "wof:placetype":"venue"
},
  "geometry": {"coordinates":[-93.502979,42.656497],"type":"Point"}
}