{
  "type": "Feature",
  "properties": {
    "iso:country":"US",
    "sg:address":"300 Main St",
    "sg:city":"Ames",
    "sg:classifiers":[
        {
            "category":"Professional",
            "subcategory":"Business Services",
            "type":"Services"
        }
    ],
    "sg:phone":"+1 515 598 5809",
    "sg:postcode":"50010",
    "sg:province":"IA",
    "sg:tags":[
        "lecture",
        "bureau",
        "seminar"
    ],
    "wof:name":"Move The Mountain Leadership",
    "wof:placetype":"venue"
},
  "geometry": {"coordinates":[-93.61539399999999,42.025087],"type":"Point"}
}