{
  "type": "Feature",
  "properties": {
    "iso:country":"US",
    "sg:address":"1965 G Ave",
    "sg:city":"Red Oak",
    "sg:classifiers":[
        {
            "category":"Wholesale",
            "subcategory":"Motor Vehicles",
            "type":"Manufacturing & Wholesale Goods"
        }
    ],
    "sg:phone":"+1 712 623 2607",
    "sg:postcode":"51566",
    "sg:province":"IA",
    "sg:tags":[
        "trailer"
    ],
    "wof:name":"Larry's Welding",
    "wof:placetype":"venue"
},
  "geometry": {"coordinates":[-95.251741,41.021262],"type":"Point"}
}