{
  "type": "Feature",
  "properties": {
    "iso:country":"US",
    "sg:address":"2328 Gnahn St",
    "sg:city":"Burlington",
    "sg:classifiers":[
        {
            "category":"Professional",
            "subcategory":"Business Services",
            "type":"Services"
        }
    ],
    "sg:phone":"+1 319 752 2342",
    "sg:postcode":"52601",
    "sg:province":"IA",
    "wof:name":"Southstern Prperty Inspections",
    "wof:placetype":"venue"
},
  "geometry": {"coordinates":[-91.114159,40.833787],"type":"Point"}
}