{
  "type": "Feature",
  "properties": {
    "iso:country":"US",
    "sg:address":"1405 W 19th St S",
    "sg:city":"Newton",
    "sg:classifiers":[
        {
            "category":"Travel",
            "subcategory":"Hotels & Motels",
            "type":"Entertainment"
        }
    ],
    "sg:phone":"+1 641 792 8100",
    "sg:postcode":"50208",
    "sg:province":"IA",
    "wof:name":"Ramada Inn",
    "wof:placetype":"venue"
},
  "geometry": {"coordinates":[-93.078271,41.68826],"type":"Point"}
}