{
  "type": "Feature",
  "properties": {
    "iso:country":"US",
    "sg:address":"3535 N Main St",
    "sg:city":"Davenport",
    "sg:classifiers":[
        {
            "category":"Real Estate",
            "subcategory":"Real Estate Operator",
            "type":"Services"
        }
    ],
    "sg:phone":"+1 563 388 7623",
    "sg:postcode":"52806",
    "sg:province":"IA",
    "sg:tags":[
        "apartment"
    ],
    "wof:name":"Georgetown Apartments",
    "wof:placetype":"venue"
},
  "geometry": {"coordinates":[-90.57485,41.555823],"type":"Point"}
}