{
  "type": "Feature",
  "properties": {
    "addr:full":"1711 Crestline Dr Red Oak IA 51566",
    "addr:housenumber":"1711",
    "addr:postcode":"51566",
    "addr:street":"Crestline Dr",
    "iso:country":"US",
    "sg:address":"1711 Crestline Dr",
    "sg:city":"Red Oak",
    "sg:classifiers":[
        {
            "category":"Freight",
            "type":"Transportation"
        }
    ],
    "sg:phone":"+1 712 623 3583",
    "sg:postcode":"51566",
    "sg:province":"IA",
    "sg:tags":[
        "hauling",
        "trucking"
    ],
    "wof:name":"Red Oak Carriers",
    "wof:placetype":"venue"
},
  "geometry": {"coordinates":[-95.215142,41.02106],"type":"Point"}
}