{
  "type": "Feature",
  "properties": {
    "iso:country":"US",
    "sg:address":"102 W Wood St",
    "sg:city":"Urbana",
    "sg:classifiers":[
        {
            "category":"Government",
            "subcategory":"Office",
            "type":"Public Place"
        }
    ],
    "sg:phone":"+1 319 443 2763",
    "sg:postcode":"52345",
    "sg:province":"IA",
    "sg:tags":[
        "village"
    ],
    "wof:name":"Polk Township Trustees",
    "wof:placetype":"venue"
},
  "geometry": {"coordinates":[-91.873482,42.224045],"type":"Point"}
}