{
  "type": "Feature",
  "properties": {
    "iso:country":"US",
    "sg:address":"210 Nixon St",
    "sg:city":"Pleasantville",
    "sg:phone":"+1 641 947 2016",
    "sg:postcode":"50225",
    "sg:province":"IA",
    "sg:tags":[
        "farm",
        "corn",
        "soybean"
    ],
    "wof:name":"David Vanrheenen",
    "wof:placetype":"venue"
},
  "geometry": {"coordinates":[-93.30055400000001,41.291604],"type":"Point"}
}