{
  "type": "Feature",
  "properties": {
    "iso:country":"US",
    "sg:address":"2310 Main Ave",
    "sg:city":"Clear Lake",
    "sg:classifiers":[
        {
            "category":"Organizations",
            "subcategory":"Religious Organization",
            "type":"Services"
        }
    ],
    "sg:phone":"+1 641 357 4227",
    "sg:postcode":"50428",
    "sg:province":"IA",
    "wof:name":"Garden Angel Roadside Chapel",
    "wof:placetype":"venue"
},
  "geometry": {"coordinates":[-93.360243,43.137444],"type":"Point"}
}