{
  "type": "Feature",
  "properties": {
    "iso:country":"US",
    "sg:address":"359 Park Ter SE",
    "sg:city":"Cedar Rapids",
    "sg:classifiers":[
        {
            "category":"Retail",
            "subcategory":"Car Wash",
            "type":"Services"
        }
    ],
    "sg:phone":"+1 319 462 6080",
    "sg:postcode":"52403",
    "sg:province":"IA",
    "sg:tags":[
        "carwash"
    ],
    "wof:name":"Midwest Group",
    "wof:placetype":"venue"
},
  "geometry": {"coordinates":[-91.629908,41.98556],"type":"Point"}
}