{
  "type": "Feature",
  "properties": {
    "iso:country":"US",
    "sg:address":"107 E Main St",
    "sg:city":"Belmond",
    "sg:classifiers":[
        {
            "category":"Autos & Motor Vehicles",
            "subcategory":"Fuel & Gas Station",
            "type":"Retail Goods"
        }
    ],
    "sg:phone":"+1 641 444 3264",
    "sg:postcode":"50421",
    "sg:province":"IA",
    "sg:tags":[
        "oil"
    ],
    "wof:name":"Joe's 66 Svc",
    "wof:placetype":"venue"
},
  "geometry": {"coordinates":[-93.616737,42.845979],"type":"Point"}
}