{
  "type": "Feature",
  "properties": {
    "iso:country":"US",
    "sg:address":"827 West St",
    "sg:city":"Grinnell",
    "sg:classifiers":[
        {
            "category":"Restaurant",
            "type":"Food & Drink"
        }
    ],
    "sg:phone":"+1 641 236 4542",
    "sg:postcode":"50112",
    "sg:province":"IA",
    "wof:name":"John & Gary's Gametime",
    "wof:placetype":"venue"
},
  "geometry": {"coordinates":[-92.727405,41.742064],"type":"Point"}
}