{
  "type": "Feature",
  "properties": {
    "iso:country":"US",
    "sg:address":"5625 Franklin Ave",
    "sg:city":"Des Moines",
    "sg:classifiers":[
        {
            "category":"Organizations",
            "subcategory":"Religious Organization",
            "type":"Services"
        }
    ],
    "sg:phone":"+1 515 277 8349",
    "sg:postcode":"50310",
    "sg:province":"IA",
    "sg:tags":[
        "church"
    ],
    "sg:website":"www.mtolive-lutheran.org",
    "wof:name":"Mt Olive Lutheran Church",
    "wof:placetype":"venue"
},
  "geometry": {"coordinates":[-93.695674,41.611337],"type":"Point"}
}