{
  "type": "Feature",
  "properties": {
    "iso:country":"US",
    "sg:address":"2002 10th Ave",
    "sg:city":"Whittemore",
    "sg:classifiers":[
        {
            "category":"Farming",
            "subcategory":"Livestock Farm",
            "type":"Manufacturing & Wholesale Goods"
        }
    ],
    "sg:phone":"+1 515 884 2315",
    "sg:postcode":"50563",
    "sg:province":"IA",
    "sg:tags":[
        "equine"
    ],
    "wof:name":"Phil Kollasch",
    "wof:placetype":"venue"
},
  "geometry": {"coordinates":[-94.522617,42.529109],"type":"Point"}
}