{
  "type": "Feature",
  "properties": {
    "iso:country":"US",
    "sg:address":"1652 Oakland Mills Rd",
    "sg:city":"Mt Pleasant",
    "sg:classifiers":[
        {
            "category":"Building & Trades",
            "subcategory":"Construction",
            "type":"Services"
        }
    ],
    "sg:phone":"+1 319 986 6038",
    "sg:postcode":"52641",
    "sg:province":"IA",
    "sg:tags":[
        "general",
        "contractor"
    ],
    "wof:name":"John H Liechty General Constr",
    "wof:placetype":"venue"
},
  "geometry": {"coordinates":[-91.57997899999999,40.939589],"type":"Point"}
}