{
  "type": "Feature",
  "properties": {
    "iso:country":"US",
    "sg:address":"2605 Northridge Pkwy",
    "sg:city":"Ames",
    "sg:classifiers":[
        {
            "category":"Shopping",
            "subcategory":"Computers & Home Electronics",
            "type":"Retail Goods"
        }
    ],
    "sg:phone":"+1 515 290 4039",
    "sg:postcode":"50010",
    "sg:province":"IA",
    "sg:tags":[
        "audio"
    ],
    "wof:name":"Stegman Audio & Video",
    "wof:placetype":"venue"
},
  "geometry": {"coordinates":[-93.64276599999999,42.049011],"type":"Point"}
}