{
  "type": "Feature",
  "properties": {
    "iso:country":"US",
    "sg:address":"1114 220th St",
    "sg:city":"Jesup",
    "sg:classifiers":[
        {
            "category":"Personal",
            "subcategory":"Beauty Salon",
            "type":"Services"
        }
    ],
    "sg:phone":"+1 319 827 2171",
    "sg:postcode":"50648",
    "sg:province":"IA",
    "wof:name":"D J's Design Depo",
    "wof:placetype":"venue"
},
  "geometry": {"coordinates":[-92.05441399999999,42.468182],"type":"Point"}
}