{
  "type": "Feature",
  "properties": {
    "iso:country":"US",
    "sg:address":"328 N Jefferson St",
    "sg:city":"Hudson",
    "sg:classifiers":[
        {
            "category":"Professional",
            "type":"Services"
        }
    ],
    "sg:phone":"+1 319 988 9387",
    "sg:postcode":"50643",
    "sg:province":"IA",
    "wof:name":"Double Down Services LLC",
    "wof:placetype":"venue"
},
  "geometry": {"coordinates":[-92.45546899999999,42.405237],"type":"Point"}
}