{
  "type": "Feature",
  "properties": {
    "addr:full":"395 US Hwy 6 Waukee IA 50263",
    "addr:housenumber":"395",
    "addr:postcode":"50263",
    "addr:street":"Us Hwy 6",
    "iso:country":"US",
    "sg:address":"395 US Hwy 6",
    "sg:city":"Waukee",
    "sg:phone":"+1 515 987 1689",
    "sg:postcode":"50263",
    "sg:province":"IA",
    "sg:tags":[
        "farm",
        "corn"
    ],
    "wof:name":"Tim Broderick Farm",
    "wof:placetype":"venue"
},
  "geometry": {"coordinates":[-93.880793,41.615034],"type":"Point"}
}