{
  "type": "Feature",
  "properties": {
    "iso:country":"US",
    "sg:address":"554 290th St",
    "sg:city":"West Branch",
    "sg:classifiers":[
        {
            "category":"Organizations",
            "subcategory":"Religious Organization",
            "type":"Services"
        }
    ],
    "sg:phone":"+1 319 643 2390",
    "sg:postcode":"52358",
    "sg:province":"IA",
    "sg:tags":[
        "church"
    ],
    "wof:name":"Springdale Methodist Church",
    "wof:placetype":"venue"
},
  "geometry": {"coordinates":[-91.258633,41.670526],"type":"Point"}
}