{
  "type": "Feature",
  "properties": {
    "iso:country":"US",
    "sg:address":"1801 Hamilton Blvd",
    "sg:city":"Sioux City",
    "sg:classifiers":[
        {
            "category":"Manufacturing",
            "subcategory":"Printing",
            "type":"Manufacturing & Wholesale Goods"
        }
    ],
    "sg:phone":"+1 712 252 2700",
    "sg:postcode":"51103",
    "sg:province":"IA",
    "sg:tags":[
        "printer"
    ],
    "sg:website":"www.kinkos.com",
    "wof:name":"Fed Ex Kinko's Ofc & Print Ctr",
    "wof:placetype":"venue"
},
  "geometry": {"coordinates":[-96.416765,42.509999],"type":"Point"}
}