{
  "type": "Feature",
  "properties": {
    "iso:country":"US",
    "sg:address":"3978 Center Point Rd NE",
    "sg:city":"Cedar Rapids",
    "sg:classifiers":[
        {
            "category":"Personal",
            "subcategory":"Beauty Salon",
            "type":"Services"
        }
    ],
    "sg:phone":"+1 319 378 7475",
    "sg:postcode":"52402",
    "sg:province":"IA",
    "sg:tags":[
        "shop"
    ],
    "wof:name":"Stacey Cousins",
    "wof:placetype":"venue"
},
  "geometry": {"coordinates":[-91.665311,42.021391],"type":"Point"}
}