{
  "type": "Feature",
  "properties": {
    "addr:full":"7 W 2nd St Kingsley IA 51028",
    "addr:housenumber":"7",
    "addr:postcode":"51028",
    "addr:street":"W 2Nd St",
    "iso:country":"US",
    "sg:address":"7 W 2nd St",
    "sg:city":"Kingsley",
    "sg:classifiers":[
        {
            "category":"Shopping",
            "subcategory":"Pharmacy",
            "type":"Retail Goods"
        }
    ],
    "sg:phone":"+1 712 378 2700",
    "sg:postcode":"51028",
    "sg:province":"IA",
    "wof:name":"Kingsley Pharmacy",
    "wof:placetype":"venue"
},
  "geometry": {"coordinates":[-95.96877000000001,42.588287],"type":"Point"}
}