{
  "type": "Feature",
  "properties": {
    "addr:full":"1109 3rd St Lake View IA 51450",
    "addr:housenumber":"1109",
    "addr:postcode":"51450",
    "addr:street":"3Rd St",
    "iso:country":"US",
    "sg:address":"1109 3rd St",
    "sg:city":"Lake View",
    "sg:classifiers":[
        {
            "category":"Travel",
            "subcategory":"Campground",
            "type":"Entertainment"
        }
    ],
    "sg:phone":"+1 712 657 2189",
    "sg:postcode":"51450",
    "sg:province":"IA",
    "wof:name":"Lake View City Camp Crescent",
    "wof:placetype":"venue"
},
  "geometry": {"coordinates":[-95.023213,42.248702],"type":"Point"}
}