{
  "type": "Feature",
  "properties": {
    "addr:full":"3761 E University Ave Des Moines IA 50317",
    "addr:housenumber":"3761",
    "addr:postcode":"50317",
    "addr:street":"E University Ave",
    "iso:country":"US",
    "sg:address":"3761 E University Ave",
    "sg:city":"Des Moines",
    "sg:classifiers":[
        {
            "category":"Autos & Motor Vehicles",
            "subcategory":"Fuel & Gas Station",
            "type":"Retail Goods"
        }
    ],
    "sg:phone":"+1 515 266 3918",
    "sg:postcode":"50317",
    "sg:province":"IA",
    "sg:tags":[
        "oil"
    ],
    "wof:name":"Citgo Quik Mart",
    "wof:placetype":"venue"
},
  "geometry": {"coordinates":[-93.541411,41.600571],"type":"Point"}
}