{
  "type": "Feature",
  "properties": {
    "addr:full":"1430 2nd Ave SE Cedar Rapids IA 52403",
    "addr:housenumber":"1430",
    "addr:postcode":"52403",
    "addr:street":"2Nd Ave Se",
    "iso:country":"US",
    "sg:address":"1430 2nd Ave SE",
    "sg:city":"Cedar Rapids",
    "sg:classifiers":[
        {
            "category":"Social Services",
            "type":"Services"
        }
    ],
    "sg:phone":"+1 319 364 7121",
    "sg:postcode":"52403",
    "sg:province":"IA",
    "sg:tags":[
        "counselor",
        "marriage",
        "family"
    ],
    "wof:name":"Catholic Charities",
    "wof:placetype":"venue"
},
  "geometry": {"coordinates":[-91.65180700000001,41.987023],"type":"Point"}
}