{
  "type": "Feature",
  "properties": {
    "iso:country":"US",
    "sg:address":"4857 Harrison Ave",
    "sg:city":"Maurice",
    "sg:classifiers":[
        {
            "category":"Farming",
            "subcategory":"Livestock Farm",
            "type":"Manufacturing & Wholesale Goods"
        }
    ],
    "sg:phone":"+1 712 567 4335",
    "sg:postcode":"51036",
    "sg:province":"IA",
    "sg:tags":[
        "hog",
        "or",
        "feedlot"
    ],
    "wof:name":"Dennis Vanroekel",
    "wof:placetype":"venue"
},
  "geometry": {"coordinates":[-96.155288,42.94461],"type":"Point"}
}