{
  "type": "Feature",
  "properties": {
    "addr:full":"603 S Grand Ave Spencer IA 51301",
    "addr:housenumber":"603",
    "addr:postcode":"51301",
    "addr:street":"S Grand Ave",
    "iso:country":"US",
    "sg:address":"603 S Grand Ave",
    "sg:city":"Spencer",
    "sg:classifiers":[
        {
            "category":"Restaurant",
            "type":"Food & Drink"
        }
    ],
    "sg:phone":"+1 712 262 6549",
    "sg:postcode":"51301",
    "sg:province":"IA",
    "wof:name":"Subway Sandwiches & Salads",
    "wof:placetype":"venue"
},
  "geometry": {"coordinates":[-95.144156,43.132476],"type":"Point"}
}