{
  "type": "Feature",
  "properties": {
    "addr:full":"201 W State St Marshalltown IA 50158",
    "addr:housenumber":"201",
    "addr:postcode":"50158",
    "addr:street":"W State St",
    "iso:country":"US",
    "sg:address":"201 W State St",
    "sg:city":"Marshalltown",
    "sg:classifiers":[
        {
            "category":"Wholesale",
            "subcategory":"Electrical",
            "type":"Manufacturing & Wholesale Goods"
        }
    ],
    "sg:phone":"+1 641 752 5820",
    "sg:postcode":"50158",
    "sg:province":"IA",
    "sg:tags":[
        "communication",
        "radio",
        "system"
    ],
    "sg:website":"www.racom.net",
    "wof:name":"Racom Corp",
    "wof:placetype":"venue"
},
  "geometry": {"coordinates":[-92.917868,42.050382],"type":"Point"}
}