{
  "type": "Feature",
  "properties": {
    "iso:country":"US",
    "sg:address":"1379 Huron Dr",
    "sg:city":"Marion",
    "sg:classifiers":[
        {
            "category":"Social Services",
            "subcategory":"Child Care",
            "type":"Services"
        }
    ],
    "sg:phone":"+1 319 447 0231",
    "sg:postcode":"52302",
    "sg:province":"IA",
    "sg:tags":[
        "day"
    ],
    "wof:name":"Webbers Day Care",
    "wof:placetype":"venue"
},
  "geometry": {"coordinates":[-91.55434,42.04102],"type":"Point"}
}