{
  "type": "Feature",
  "properties": {
    "iso:country":"US",
    "sg:address":"312 SW 8th St",
    "sg:city":"Des Moines",
    "sg:classifiers":[
        {
            "category":"Real Estate",
            "subcategory":"Architect",
            "type":"Services"
        }
    ],
    "sg:phone":"+1 515 288 2270",
    "sg:postcode":"50309",
    "sg:province":"IA",
    "sg:tags":[
        "architectural"
    ],
    "wof:name":"John K Gardner",
    "wof:placetype":"venue"
},
  "geometry": {"coordinates":[-93.625028,41.57963],"type":"Point"}
}