{
  "type": "Feature",
  "properties": {
    "addr:full":"1120 N 8th Ave Washington IA 52353",
    "addr:housenumber":"1120",
    "addr:postcode":"52353",
    "addr:street":"N 8Th Ave",
    "iso:country":"US",
    "sg:address":"1120 N 8th Ave",
    "sg:city":"Washington",
    "sg:classifiers":[
        {
            "category":"Local Transit",
            "type":"Transportation"
        }
    ],
    "sg:phone":"+1 319 653 2047",
    "sg:postcode":"52353",
    "sg:province":"IA",
    "sg:tags":[
        "ambulance"
    ],
    "wof:name":"Washington County Ambulnce Svc",
    "wof:placetype":"venue"
},
  "geometry": {"coordinates":[-91.683256,41.309721],"type":"Point"}
}