{
  "type": "Feature",
  "properties": {
    "addr:full":"327 35th St NE Cedar Rapids IA 52402",
    "addr:housenumber":"327",
    "addr:postcode":"52402",
    "addr:street":"35Th St Ne",
    "iso:country":"US",
    "sg:address":"327 35th St NE",
    "sg:city":"Cedar Rapids",
    "sg:classifiers":[
        {
            "category":"Organizations",
            "subcategory":"Religious Organization",
            "type":"Services"
        }
    ],
    "sg:phone":"+1 319 363 0281",
    "sg:postcode":"52402",
    "sg:province":"IA",
    "sg:tags":[
        "church"
    ],
    "wof:name":"Kenwood Park Presbyterian Chr",
    "wof:placetype":"venue"
},
  "geometry": {"coordinates":[-91.636515,42.013379],"type":"Point"}
}