{
  "type": "Feature",
  "properties": {
    "iso:country":"US",
    "sg:address":"22 Dillman Dr",
    "sg:city":"Council Bluffs",
    "sg:classifiers":[
        {
            "category":"Retail",
            "subcategory":"Event Space",
            "type":"Services"
        }
    ],
    "sg:phone":"+1 712 323 7188",
    "sg:postcode":"51503",
    "sg:province":"IA",
    "sg:tags":[
        "venue"
    ],
    "wof:name":"St Paul's Episcopal Church",
    "wof:placetype":"venue"
},
  "geometry": {"coordinates":[-95.82820100000001,41.274899],"type":"Point"}
}