{
  "type": "Feature",
  "properties": {
    "iso:country":"US",
    "sg:address":"1857 250th St",
    "sg:city":"Denver",
    "sg:classifiers":[
        {
            "category":"Farming",
            "subcategory":"Livestock Farm",
            "type":"Manufacturing & Wholesale Goods"
        }
    ],
    "sg:phone":"+1 319 984 5229",
    "sg:postcode":"50622",
    "sg:province":"IA",
    "sg:tags":[
        "beef",
        "feedlot",
        "cattle"
    ],
    "wof:name":"Nelson White",
    "wof:placetype":"venue"
},
  "geometry": {"coordinates":[-92.38587099999999,42.685829],"type":"Point"}
}