{
  "type": "Feature",
  "properties": {
    "iso:country":"US",
    "sg:address":"2769 130th St",
    "sg:city":"Afton",
    "sg:classifiers":[
        {
            "category":"Building & Trades",
            "subcategory":"Construction",
            "type":"Services"
        }
    ],
    "sg:phone":"+1 641 763 2402",
    "sg:postcode":"50830",
    "sg:province":"IA",
    "sg:tags":[
        "contractor"
    ],
    "wof:name":"T & H Construction",
    "wof:placetype":"venue"
},
  "geometry": {"coordinates":[-94.13017499999999,41.106504],"type":"Point"}
}