{
  "type": "Feature",
  "properties": {
    "iso:country":"US",
    "sg:address":"1134 9th St SE",
    "sg:city":"Cedar Rapids",
    "sg:classifiers":[
        {
            "category":"Food & Beverages",
            "subcategory":"Groceries & Convenience Stores",
            "type":"Retail Goods"
        }
    ],
    "sg:phone":"+1 319 364 5301",
    "sg:postcode":"52401",
    "sg:province":"IA",
    "sg:tags":[
        "grocer"
    ],
    "wof:name":"Baker's Oven",
    "wof:placetype":"venue"
},
  "geometry": {"coordinates":[-91.651518,41.974202],"type":"Point"}
}