{
  "type": "Feature",
  "properties": {
    "iso:country":"US",
    "sg:address":"1530 Ave C",
    "sg:city":"Council Bluffs",
    "sg:classifiers":[
        {
            "category":"Autos & Motor Vehicles",
            "subcategory":"Automobile Sales",
            "type":"Retail Goods"
        }
    ],
    "sg:phone":"+1 712 323 2203",
    "sg:postcode":"51501",
    "sg:province":"IA",
    "sg:tags":[
        "car",
        "dealer"
    ],
    "wof:name":"Driver Motors Inc",
    "wof:placetype":"venue"
},
  "geometry": {"coordinates":[-95.867118,41.264574],"type":"Point"}
}