{
  "type": "Feature",
  "properties": {
    "iso:country":"US",
    "sg:address":"600 3rd St SE Ste 300",
    "sg:city":"Cedar Rapids",
    "sg:classifiers":[
        {
            "category":"Shopping",
            "subcategory":"Stationery & Office Supplies",
            "type":"Retail Goods"
        },
        {
            "category":"Building & Trades",
            "subcategory":"Construction",
            "type":"Services"
        }
    ],
    "sg:phone":"+1 319 365 6967",
    "sg:postcode":"52401",
    "sg:province":"IA",
    "sg:tags":[
        "interior",
        "equipment",
        "design"
    ],
    "sg:website":"www.saxtoninc.com",
    "wof:name":"Saxton Inc",
    "wof:placetype":"venue"
},
  "geometry": {"coordinates":[-91.662429,41.974393],"type":"Point"}
}