{
  "type": "Feature",
  "properties": {
    "iso:country":"US",
    "sg:address":"127 Tonawanda Dr",
    "sg:city":"Des Moines",
    "sg:classifiers":[
        {
            "category":"Shopping",
            "subcategory":"Florist",
            "type":"Retail Goods"
        }
    ],
    "sg:phone":"+1 515 277 7274",
    "sg:postcode":"50312",
    "sg:province":"IA",
    "wof:name":"Diannes Floral Designs",
    "wof:placetype":"venue"
},
  "geometry": {"coordinates":[-93.67041500000001,41.578095],"type":"Point"}
}