{
  "type": "Feature",
  "properties": {
    "addr:full":"1302 E 2nd Ave Indianola IA 50125",
    "addr:housenumber":"1302",
    "addr:postcode":"50125",
    "addr:street":"E 2Nd Ave",
    "iso:country":"US",
    "sg:address":"1302 E 2nd Ave",
    "sg:city":"Indianola",
    "sg:classifiers":[
        {
            "category":"Health Services",
            "subcategory":"Nursing And Care Facility",
            "type":"Services"
        }
    ],
    "sg:phone":"+1 515 961 6673",
    "sg:postcode":"50125",
    "sg:province":"IA",
    "sg:tags":[
        "home",
        "retirement",
        "community"
    ],
    "wof:name":"Shirlee's Retirement Home",
    "wof:placetype":"venue"
},
  "geometry": {"coordinates":[-93.54113599999999,41.357979],"type":"Point"}
}