{
  "type": "Feature",
  "properties": {
    "iso:country":"US",
    "sg:address":"209 High Ave E",
    "sg:city":"Oskaloosa",
    "sg:classifiers":[
        {
            "category":"Personal",
            "subcategory":"Beauty Salon",
            "type":"Services"
        }
    ],
    "sg:phone":"+1 641 673 7264",
    "sg:postcode":"52577",
    "sg:province":"IA",
    "wof:name":"Hair Clinique",
    "wof:placetype":"venue"
},
  "geometry": {"coordinates":[-92.642712,41.295433],"type":"Point"}
}