{
  "type": "Feature",
  "properties": {
    "iso:country":"US",
    "sg:address":"7477 Macon Dr",
    "sg:city":"Cedar Rapids",
    "sg:classifiers":[
        {
            "category":"Professional",
            "subcategory":"Computer Services",
            "type":"Services"
        }
    ],
    "sg:phone":"+1 319 393 6575",
    "sg:postcode":"52411",
    "sg:province":"IA",
    "wof:name":"Y 1 Solutions",
    "wof:placetype":"venue"
},
  "geometry": {"coordinates":[-91.741319,42.060215],"type":"Point"}
}