{
  "type": "Feature",
  "properties": {
    "iso:country":"US",
    "sg:address":"2188 W Kimberly Rd",
    "sg:city":"Davenport",
    "sg:classifiers":[
        {
            "category":"Retail",
            "subcategory":"Laundry & Dry Cleaning",
            "type":"Services"
        }
    ],
    "sg:phone":"+1 563 386 9151",
    "sg:postcode":"52806",
    "sg:province":"IA",
    "sg:tags":[
        "cleaners",
        "rug",
        "carpet"
    ],
    "wof:name":"Total Carpet Clean Solutions",
    "wof:placetype":"venue"
},
  "geometry": {"coordinates":[-90.607288,41.560197],"type":"Point"}
}