{
  "type": "Feature",
  "properties": {
    "iso:country":"US",
    "sg:address":"26067 141st Rd",
    "sg:city":"Stockport",
    "sg:classifiers":[
        {
            "category":"Retail",
            "subcategory":"Laundry & Dry Cleaning",
            "type":"Services"
        }
    ],
    "sg:phone":"+1 319 796 4471",
    "sg:postcode":"52651",
    "sg:province":"IA",
    "sg:tags":[
        "cleaners",
        "rug",
        "carpet"
    ],
    "wof:name":"Captain Clean",
    "wof:placetype":"venue"
},
  "geometry": {"coordinates":[-91.870333,40.841451],"type":"Point"}
}