{
  "type": "Feature",
  "properties": {
    "iso:country":"US",
    "sg:address":"711 2nd Ave",
    "sg:city":"Sheldon",
    "sg:classifiers":[
        {
            "category":"Autos & Motor Vehicles",
            "subcategory":"Auto Supplies",
            "type":"Retail Goods"
        }
    ],
    "sg:phone":"+1 712 324 2574",
    "sg:postcode":"51201",
    "sg:province":"IA",
    "sg:tags":[
        "automobile",
        "parts"
    ],
    "wof:name":"Arnold Motor Supply",
    "wof:placetype":"venue"
},
  "geometry": {"coordinates":[-95.855253,43.183222],"type":"Point"}
}