{
  "type": "Feature",
  "properties": {
    "addr:full":"109 E Bremer Ave Waverly IA 50677",
    "addr:housenumber":"109",
    "addr:postcode":"50677",
    "addr:street":"E Bremer Ave",
    "iso:country":"US",
    "sg:address":"109 E Bremer Ave",
    "sg:city":"Waverly",
    "sg:classifiers":[
        {
            "category":"Professional",
            "subcategory":"Accounting & Tax Preparation",
            "type":"Services"
        }
    ],
    "sg:phone":"+1 319 352 4217",
    "sg:postcode":"50677",
    "sg:province":"IA",
    "sg:tags":[
        "accountant"
    ],
    "wof:name":"Gosling & Co",
    "wof:placetype":"venue"
},
  "geometry": {"coordinates":[-92.468175,42.725872],"type":"Point"}
}