{
  "type": "Feature",
  "properties": {
    "iso:country":"US",
    "sg:address":"855 A Ave NE Ste 300",
    "sg:city":"Cedar Rapids",
    "sg:classifiers":[
        {
            "category":"Health Services",
            "subcategory":"Doctor",
            "type":"Services"
        }
    ],
    "sg:phone":"+1 319 368 9301",
    "sg:postcode":"52402",
    "sg:province":"IA",
    "sg:website":"www.stlukescr.org",
    "wof:name":"Cedar Rapids Pediatrics",
    "wof:placetype":"venue"
},
  "geometry": {"coordinates":[-91.661598,41.9841],"type":"Point"}
}