{
  "type": "Feature",
  "properties": {
    "iso:country":"US",
    "sg:address":"1667 148th St",
    "sg:city":"Ladora",
    "sg:classifiers":[
        {
            "category":"Building & Trades",
            "subcategory":"Construction",
            "type":"Services"
        }
    ],
    "sg:phone":"+1 319 623 3064",
    "sg:postcode":"52251",
    "sg:province":"IA",
    "sg:tags":[
        "hanging",
        "contractor"
    ],
    "wof:name":"Wille Painting",
    "wof:placetype":"venue"
},
  "geometry": {"coordinates":[-92.167332,41.793578],"type":"Point"}
}