{
  "type": "Feature",
  "properties": {
    "addr:full":"604 Whittier St Whiting IA 51063",
    "addr:housenumber":"604",
    "addr:postcode":"51063",
    "addr:street":"Whittier St",
    "iso:country":"US",
    "sg:address":"604 Whittier St",
    "sg:city":"Whiting",
    "sg:classifiers":[
        {
            "category":"Retail",
            "subcategory":"Portrait Studio",
            "type":"Services"
        }
    ],
    "sg:phone":"+1 712 458 2552",
    "sg:postcode":"51063",
    "sg:province":"IA",
    "sg:tags":[
        "photographer"
    ],
    "wof:name":"Lakeside Studio & Gallery",
    "wof:placetype":"venue"
},
  "geometry": {"coordinates":[-96.152627,42.127367],"type":"Point"}
}