{
  "type": "Feature",
  "properties": {
    "iso:country":"US",
    "sg:address":"401 Main St",
    "sg:city":"New Market",
    "sg:classifiers":[
        {
            "category":"Bars & Pubs",
            "type":"Food & Drink"
        }
    ],
    "sg:phone":"+1 712 585 3500",
    "sg:postcode":"51646",
    "sg:province":"IA",
    "wof:name":"Bix's Bar",
    "wof:placetype":"venue"
},
  "geometry": {"coordinates":[-94.899305,40.730562],"type":"Point"}
}