{
  "type": "Feature",
  "properties": {
    "addr:full":"24001 Cottonwood Rd Council Bluffs IA 51503",
    "addr:housenumber":"24001",
    "addr:postcode":"51503",
    "addr:street":"Cottonwood Rd",
    "iso:country":"US",
    "sg:address":"24001 Cottonwood Rd",
    "sg:city":"Council Bluffs",
    "sg:classifiers":[
        {
            "category":"Building & Trades",
            "subcategory":"Construction",
            "type":"Services"
        }
    ],
    "sg:phone":"+1 712 328 9065",
    "sg:postcode":"51503",
    "sg:province":"IA",
    "sg:tags":[
        "house"
    ],
    "wof:name":"Hilderbrand Construction Inc",
    "wof:placetype":"venue"
},
  "geometry": {"coordinates":[-95.727181,41.252353],"type":"Point"}
}