{
  "type": "Feature",
  "properties": {
    "iso:country":"US",
    "sg:address":"1700 4th Ave SE",
    "sg:city":"Cedar Rapids",
    "sg:classifiers":[
        {
            "category":"Personal",
            "subcategory":"Barber",
            "type":"Services"
        }
    ],
    "sg:phone":"+1 319 261 0978",
    "sg:postcode":"52403",
    "sg:province":"IA",
    "wof:name":"Peoples Choice",
    "wof:placetype":"venue"
},
  "geometry": {"coordinates":[-91.646552,41.983697],"type":"Point"}
}