{
  "type": "Feature",
  "properties": {
    "iso:country":"US",
    "sg:address":"2928 230th St",
    "sg:city":"Charles City",
    "sg:classifiers":[
        {
            "category":"Retail",
            "subcategory":"Repair Shop",
            "type":"Services"
        },
        {
            "category":"Building & Trades",
            "subcategory":"Construction",
            "type":"Services"
        }
    ],
    "sg:phone":"+1 641 228 5197",
    "sg:postcode":"50616",
    "sg:province":"IA",
    "sg:tags":[
        "glass"
    ],
    "wof:name":"Weber Mobile Glass Repair",
    "wof:placetype":"venue"
},
  "geometry": {"coordinates":[-92.64784299999999,43.023565],"type":"Point"}
}