{
  "type": "Feature",
  "properties": {
    "iso:country":"US",
    "sg:address":"714 Jackson St",
    "sg:city":"Sioux City",
    "sg:classifiers":[
        {
            "category":"Professional",
            "subcategory":"Detective & Security Services",
            "type":"Services"
        }
    ],
    "sg:phone":"+1 712 252 3003",
    "sg:postcode":"51105",
    "sg:province":"IA",
    "sg:tags":[
        "guard",
        "patrol"
    ],
    "wof:name":"Sioux City Night Patrol",
    "wof:placetype":"venue"
},
  "geometry": {"coordinates":[-96.40195900000001,42.498378],"type":"Point"}
}