{
  "type": "Feature",
  "properties": {
    "iso:country":"US",
    "sg:address":"101 W Water St",
    "sg:city":"Decorah",
    "sg:classifiers":[
        {
            "category":"Shopping",
            "subcategory":"Clothing, Apparel, & Fashions",
            "type":"Retail Goods"
        },
        {
            "category":"Personal",
            "subcategory":"Beauty Salon",
            "type":"Services"
        },
        {
            "category":"Shopping",
            "subcategory":"Jewelry",
            "type":"Retail Goods"
        },
        {
            "category":"Shopping",
            "subcategory":"Department Store",
            "type":"Retail Goods"
        },
        {
            "category":"Shopping",
            "subcategory":"Shoes",
            "type":"Retail Goods"
        }
    ],
    "sg:phone":"+1 563 382 3441",
    "sg:postcode":"52101",
    "sg:province":"IA",
    "sg:tags":[
        "apparel",
        "women's",
        "men's",
        "clothing",
        "jeweler"
    ],
    "sg:website":"http://jcpenney.com",
    "wof:name":"J C Penney Co",
    "wof:placetype":"venue"
},
  "geometry": {"coordinates":[-91.78589599999999,43.304211],"type":"Point"}
}