{
  "type": "Feature",
  "properties": {
    "iso:country":"US",
    "sg:address":"110 SW 1st St",
    "sg:city":"Hopkinton",
    "sg:classifiers":[
        {
            "category":"Education",
            "subcategory":"Library",
            "type":"Public Place"
        }
    ],
    "sg:phone":"+1 563 926 2514",
    "sg:postcode":"52237",
    "sg:province":"IA",
    "wof:name":"Hopkinton Public Library",
    "wof:placetype":"venue"
},
  "geometry": {"coordinates":[-91.249686,42.344143],"type":"Point"}
}