{
  "type": "Feature",
  "properties": {
    "iso:country":"US",
    "sg:address":"310 E Marion St",
    "sg:city":"Des Moines",
    "sg:classifiers":[
        {
            "category":"Building & Trades",
            "subcategory":"Construction",
            "type":"Services"
        }
    ],
    "sg:phone":"+1 515 287 4982",
    "sg:postcode":"50315",
    "sg:province":"IA",
    "sg:tags":[
        "house"
    ],
    "wof:name":"Davids Quality Home Imprvs",
    "wof:placetype":"venue"
},
  "geometry": {"coordinates":[-93.606624,41.547124],"type":"Point"}
}