{
  "type": "Feature",
  "properties": {
    "addr:full":"329 E 7th St Glidden IA 51443",
    "addr:housenumber":"329",
    "addr:postcode":"51443",
    "addr:street":"E 7Th St",
    "iso:country":"US",
    "sg:address":"329 E 7th St",
    "sg:city":"Glidden",
    "sg:classifiers":[
        {
            "category":"Organizations",
            "subcategory":"Religious Organization",
            "type":"Services"
        }
    ],
    "sg:phone":"+1 712 659 3893",
    "sg:postcode":"51443",
    "sg:province":"IA",
    "wof:name":"Grace Baptist Church",
    "wof:placetype":"venue"
},
  "geometry": {"coordinates":[-94.724964,42.06179],"type":"Point"}
}