{
  "type": "Feature",
  "properties": {
    "iso:country":"US",
    "sg:address":"3426 10th St",
    "sg:city":"Le Roy",
    "sg:classifiers":[
        {
            "category":"Retail",
            "subcategory":"Repair Shop",
            "type":"Services"
        }
    ],
    "sg:phone":"+1 507 324 5385",
    "sg:postcode":"55951",
    "sg:province":"IA",
    "wof:name":"Country Repair",
    "wof:placetype":"venue"
},
  "geometry": {"coordinates":[-92.51429400000001,43.500168],"type":"Point"}
}