{
  "type": "Feature",
  "properties": {
    "iso:country":"US",
    "sg:address":"208 W Mulberry St",
    "sg:city":"Ogden",
    "sg:classifiers":[
        {
            "category":"Education",
            "subcategory":"Library",
            "type":"Public Place"
        }
    ],
    "sg:phone":"+1 515 275 4550",
    "sg:postcode":"50212",
    "sg:province":"IA",
    "wof:name":"Leonard A Good Community Libr",
    "wof:placetype":"venue"
},
  "geometry": {"coordinates":[-94.030683,42.03797],"type":"Point"}
}