{
  "type": "Feature",
  "properties": {
    "iso:country":"US",
    "sg:address":"1723 W Kimberly Rd",
    "sg:city":"Davenport",
    "sg:classifiers":[
        {
            "category":"Shopping",
            "subcategory":"Gifts & Souvenirs",
            "type":"Retail Goods"
        }
    ],
    "sg:phone":"+1 563 391 4084",
    "sg:postcode":"52806",
    "sg:province":"IA",
    "sg:tags":[
        "shop"
    ],
    "wof:name":"P J's Country Treasures",
    "wof:placetype":"venue"
},
  "geometry": {"coordinates":[-90.601579,41.559975],"type":"Point"}
}