{
  "type": "Feature",
  "properties": {
    "iso:country":"US",
    "sg:address":"1426 E Commercial St",
    "sg:city":"Algona",
    "sg:classifiers":[
        {
            "category":"Retail",
            "subcategory":"Repair Shop",
            "type":"Services"
        }
    ],
    "sg:phone":"+1 515 295 2159",
    "sg:postcode":"50511",
    "sg:province":"IA",
    "sg:tags":[
        "antique",
        "restoring"
    ],
    "wof:name":"Rick's Body & Paint",
    "wof:placetype":"venue"
},
  "geometry": {"coordinates":[-94.21819499999999,43.075575],"type":"Point"}
}