{
  "type": "Feature",
  "properties": {
    "iso:country":"US",
    "sg:address":"1015 Orchard Dr",
    "sg:city":"Cedar Falls",
    "sg:classifiers":[
        {
            "category":"Real Estate",
            "subcategory":"Real Estate Agent",
            "type":"Services"
        }
    ],
    "sg:phone":"+1 319 277 5916",
    "sg:postcode":"50613",
    "sg:province":"IA",
    "wof:name":"Patterson Properties",
    "wof:placetype":"venue"
},
  "geometry": {"coordinates":[-92.43502599999999,42.505765],"type":"Point"}
}