{
  "type": "Feature",
  "properties": {
    "iso:country":"US",
    "sg:address":"310 W Conger St",
    "sg:city":"Waterloo",
    "sg:classifiers":[
        {
            "category":"Education",
            "subcategory":"Dance Studio",
            "type":"Public Place"
        }
    ],
    "sg:phone":"+1 319 233 3050",
    "sg:postcode":"50701",
    "sg:province":"IA",
    "sg:tags":[
        "ballroom"
    ],
    "wof:name":"Electric Park Ballroom",
    "wof:placetype":"venue"
},
  "geometry": {"coordinates":[-92.36762899999999,42.510543],"type":"Point"}
}