{
  "type": "Feature",
  "properties": {
    "addr:full":"815 4th Ave S Clear Lake IA 50428",
    "addr:housenumber":"815",
    "addr:postcode":"50428",
    "addr:street":"4Th Ave S Clear",
    "iso:country":"US",
    "sg:address":"815 4th Ave S",
    "sg:city":"Clear Lake",
    "sg:classifiers":[
        {
            "category":"Insurance",
            "subcategory":"Insurance Agent",
            "type":"Services"
        }
    ],
    "sg:phone":"+1 641 357 6117",
    "sg:postcode":"50428",
    "sg:province":"IA",
    "wof:name":"First Gabrielson Agency",
    "wof:placetype":"venue"
},
  "geometry": {"coordinates":[-93.37727099999999,43.133722],"type":"Point"}
}