{
  "type": "Feature",
  "properties": {
    "iso:country":"US",
    "sg:address":"22919 McPherson Ave",
    "sg:city":"Council Bluffs",
    "sg:classifiers":[
        {
            "category":"Building & Trades",
            "subcategory":"Landscaping Services",
            "type":"Services"
        }
    ],
    "sg:phone":"+1 712 325 0644",
    "sg:postcode":"51503",
    "sg:province":"IA",
    "wof:name":"Preferred Lawn & Landscaping",
    "wof:placetype":"venue"
},
  "geometry": {"coordinates":[-95.758923,41.26409],"type":"Point"}
}