{
  "type": "Feature",
  "properties": {
    "iso:country":"US",
    "sg:address":"106 S Main St",
    "sg:city":"St Olaf",
    "sg:classifiers":[
        {
            "category":"Restaurant",
            "type":"Food & Drink"
        }
    ],
    "sg:phone":"+1 563 783 7723",
    "sg:postcode":"52072",
    "sg:province":"IA",
    "wof:name":"St Olaf Tavern",
    "wof:placetype":"venue"
},
  "geometry": {"coordinates":[-91.386088,42.928289],"type":"Point"}
}