{
  "type": "Feature",
  "properties": {
    "addr:full":"240 160th Ave Donnellson IA 52625",
    "addr:housenumber":"240",
    "addr:postcode":"52625",
    "addr:street":"160Th Ave",
    "iso:country":"US",
    "sg:address":"240 160th Ave",
    "sg:city":"Donnellson",
    "sg:classifiers":[
        {
            "category":"Shopping",
            "subcategory":"Computers & Home Electronics",
            "type":"Retail Goods"
        }
    ],
    "sg:phone":"+1 319 835 3912",
    "sg:postcode":"52625",
    "sg:province":"IA",
    "sg:tags":[
        "antenna"
    ],
    "wof:name":"Country Cable & Antennas",
    "wof:placetype":"venue"
},
  "geometry": {"coordinates":[-91.602959,40.785073],"type":"Point"}
}