{
  "type": "Feature",
  "properties": {
    "iso:country":"US",
    "sg:address":"89 US Hwy 6",
    "sg:city":"Coralville",
    "sg:classifiers":[
        {
            "category":"Home & Garden",
            "subcategory":"Furniture",
            "type":"Retail Goods"
        }
    ],
    "sg:phone":"+1 319 341 0400",
    "sg:postcode":"52241",
    "sg:province":"IA",
    "sg:tags":[
        "futon"
    ],
    "wof:name":"Coralville Futon",
    "wof:placetype":"venue"
},
  "geometry": {"coordinates":[-91.561159,41.666948],"type":"Point"}
}