{
  "type": "Feature",
  "properties": {
    "iso:country":"US",
    "sg:address":"1828 State Hwy 9",
    "sg:city":"Lansing",
    "sg:classifiers":[
        {
            "category":"Autos & Motor Vehicles",
            "subcategory":"Automobile Sales",
            "type":"Retail Goods"
        }
    ],
    "sg:phone":"+1 563 538 4970",
    "sg:postcode":"52151",
    "sg:province":"IA",
    "sg:tags":[
        "car",
        "dealer"
    ],
    "wof:name":"Gary's Automotive",
    "wof:placetype":"venue"
},
  "geometry": {"coordinates":[-91.242007,43.361161],"type":"Point"}
}