{
  "type": "Feature",
  "properties": {
    "iso:country":"US",
    "sg:address":"106 34th St W",
    "sg:city":"Clear Lake",
    "sg:classifiers":[
        {
            "category":"Real Estate",
            "subcategory":"Real Estate Agent",
            "type":"Services"
        }
    ],
    "sg:phone":"+1 641 357 4770",
    "sg:postcode":"50428",
    "sg:province":"IA",
    "wof:name":"E Charles Madson Realtor",
    "wof:placetype":"venue"
},
  "geometry": {"coordinates":[-93.42997200000001,43.13529],"type":"Point"}
}