{
  "type": "Feature",
  "properties": {
    "addr:full":"1502 Walnut St Dallas Center IA 50063",
    "addr:housenumber":"1502",
    "addr:postcode":"50063",
    "addr:street":"Walnut St",
    "iso:country":"US",
    "sg:address":"1502 Walnut St",
    "sg:city":"Dallas Center",
    "sg:classifiers":[
        {
            "category":"Government",
            "subcategory":"Office",
            "type":"Public Place"
        }
    ],
    "sg:phone":"+1 515 992 3725",
    "sg:postcode":"50063",
    "sg:province":"IA",
    "sg:tags":[
        "city"
    ],
    "wof:name":"Dallas Center City Hall",
    "wof:placetype":"venue"
},
  "geometry": {"coordinates":[-93.963724,41.684285],"type":"Point"}
}