{
  "type": "Feature",
  "properties": {
    "addr:full":"4005 Glass Rd NE Cedar Rapids IA 52402",
    "addr:housenumber":"4005",
    "addr:postcode":"52402",
    "addr:street":"Glass Rd Ne",
    "iso:country":"US",
    "sg:address":"4005 Glass Rd NE",
    "sg:city":"Cedar Rapids",
    "sg:classifiers":[
        {
            "category":"Banks & Credit Unions",
            "subcategory":"Bank",
            "type":"Services"
        }
    ],
    "sg:phone":"+1 319 393 5104",
    "sg:postcode":"52402",
    "sg:province":"IA",
    "sg:tags":[
        "loan"
    ],
    "sg:website":"www.hamiltonmortgage.com",
    "wof:name":"Hamilton Mortgage",
    "wof:placetype":"venue"
},
  "geometry": {"coordinates":[-91.69945,42.016959],"type":"Point"}
}