{
  "type": "Feature",
  "properties": {
    "iso:country":"US",
    "sg:address":"250 S Main St",
    "sg:city":"Dubuque",
    "sg:classifiers":[
        {
            "category":"Home & Garden",
            "subcategory":"Building Materials",
            "type":"Retail Goods"
        }
    ],
    "sg:phone":"+1 563 557 9920",
    "sg:postcode":"52003",
    "sg:province":"IA",
    "sg:tags":[
        "roofing"
    ],
    "wof:name":"ABC Supply Co",
    "wof:placetype":"venue"
},
  "geometry": {"coordinates":[-90.660578,42.488891],"type":"Point"}
}