{
  "type": "Feature",
  "properties": {
    "iso:country":"US",
    "sg:address":"2304 Sampson St",
    "sg:city":"Muscatine",
    "sg:classifiers":[
        {
            "category":"Wholesale",
            "subcategory":"Groceries",
            "type":"Manufacturing & Wholesale Goods"
        }
    ],
    "sg:phone":"+1 563 263 9077",
    "sg:postcode":"52761",
    "sg:province":"IA",
    "sg:tags":[
        "beverage"
    ],
    "wof:name":"Pepsi-Cola Distribution Ctr",
    "wof:placetype":"venue"
},
  "geometry": {"coordinates":[-91.071966,41.399441],"type":"Point"}
}