{
  "type": "Feature",
  "properties": {
    "iso:country":"US",
    "sg:address":"107 12th St SE",
    "sg:city":"Le Mars",
    "sg:classifiers":[
        {
            "category":"Retail",
            "subcategory":"Funeral Services",
            "type":"Services"
        }
    ],
    "sg:phone":"+1 712 546 7107",
    "sg:postcode":"51031",
    "sg:province":"IA",
    "sg:tags":[
        "director"
    ],
    "wof:name":"Carlsen Funeral Home",
    "wof:placetype":"venue"
},
  "geometry": {"coordinates":[-96.165092,42.77883],"type":"Point"}
}