{
  "type": "Feature",
  "properties": {
    "iso:country":"US",
    "sg:address":"240 Classic Car Ct SW",
    "sg:city":"Cedar Rapids",
    "sg:classifiers":[
        {
            "category":"Social Services",
            "type":"Services"
        }
    ],
    "sg:phone":"+1 319 363 8335",
    "sg:postcode":"52404",
    "sg:province":"IA",
    "sg:tags":[
        "youth",
        "organization",
        "center"
    ],
    "wof:name":"Mississippi Valley Girl Scouts",
    "wof:placetype":"venue"
},
  "geometry": {"coordinates":[-91.66810700000001,41.942669],"type":"Point"}
}