{
  "type": "Feature",
  "properties": {
    "iso:country":"US",
    "sg:address":"913 S Dubuque St",
    "sg:city":"Iowa City",
    "sg:classifiers":[
        {
            "category":"Government",
            "subcategory":"Office",
            "type":"Public Place"
        }
    ],
    "sg:phone":"+1 319 356 6066",
    "sg:postcode":"52240",
    "sg:province":"IA",
    "sg:tags":[
        "city",
        "taxation"
    ],
    "wof:name":"Iowa City Assessor",
    "wof:placetype":"venue"
},
  "geometry": {"coordinates":[-91.533272,41.651059],"type":"Point"}
}