{
  "type": "Feature",
  "properties": {
    "addr:full":"4413 Fleur Dr Des Moines IA 50321",
    "addr:housenumber":"4413",
    "addr:postcode":"50321",
    "addr:street":"Fleur Dr",
    "iso:country":"US",
    "sg:address":"4413 Fleur Dr",
    "sg:city":"Des Moines",
    "sg:classifiers":[
        {
            "category":"Bars & Pubs",
            "type":"Food & Drink"
        }
    ],
    "sg:phone":"+1 515 285 7173",
    "sg:postcode":"50321",
    "sg:province":"IA",
    "sg:tags":[
        "lounge",
        "cocktail"
    ],
    "wof:name":"All In The Family",
    "wof:placetype":"venue"
},
  "geometry": {"coordinates":[-93.64487800000001,41.541092],"type":"Point"}
}