{
  "type": "Feature",
  "properties": {
    "iso:country":"US",
    "sg:address":"25188 218th Ave",
    "sg:city":"Delhi",
    "sg:classifiers":[
        {
            "category":"Manufacturing",
            "subcategory":"Retail Goods",
            "type":"Manufacturing & Wholesale Goods"
        }
    ],
    "sg:phone":"+1 563 922 9026",
    "sg:postcode":"52223",
    "sg:province":"IA",
    "sg:tags":[
        "manufacturer"
    ],
    "wof:name":"Hillside Manufacturing Inc",
    "wof:placetype":"venue"
},
  "geometry": {"coordinates":[-91.36543500000001,42.424662],"type":"Point"}
}