{
  "type": "Feature",
  "properties": {
    "addr:full":"204 W 5th St Carroll IA 51401",
    "addr:housenumber":"204",
    "addr:postcode":"51401",
    "addr:street":"W 5Th St",
    "iso:country":"US",
    "sg:address":"204 W 5th St",
    "sg:city":"Carroll",
    "sg:classifiers":[
        {
            "category":"Travel",
            "subcategory":"Travel Agent",
            "type":"Entertainment"
        }
    ],
    "sg:phone":"+1 712 792 4431",
    "sg:postcode":"51401",
    "sg:province":"IA",
    "sg:tags":[
        "agency",
        "bureau"
    ],
    "wof:name":"Jacobsen Travel Agency",
    "wof:placetype":"venue"
},
  "geometry": {"coordinates":[-94.870547,42.065362],"type":"Point"}
}