{
  "type": "Feature",
  "properties": {
    "iso:country":"US",
    "sg:address":"605 S Center St",
    "sg:city":"Marshalltown",
    "sg:classifiers":[
        {
            "category":"Building & Trades",
            "subcategory":"Construction",
            "type":"Services"
        }
    ],
    "sg:phone":"+1 641 753 3603",
    "sg:postcode":"50158",
    "sg:province":"IA",
    "sg:tags":[
        "roofing",
        "contractor"
    ],
    "wof:name":"Vis Roofing & Sheet Metal",
    "wof:placetype":"venue"
},
  "geometry": {"coordinates":[-92.912932,42.041884],"type":"Point"}
}