{
  "type": "Feature",
  "properties": {
    "iso:country":"US",
    "sg:address":"116 N Main St",
    "sg:city":"Moulton",
    "sg:classifiers":[
        {
            "category":"Insurance",
            "subcategory":"Insurance Agent",
            "type":"Services"
        },
        {
            "category":"Banks & Credit Unions",
            "subcategory":"Investment Brokerage",
            "type":"Services"
        },
        {
            "category":"Insurance",
            "subcategory":"Hazard Insurance",
            "type":"Services"
        },
        {
            "category":"Banks & Credit Unions",
            "subcategory":"Financial Services",
            "type":"Services"
        },
        {
            "category":"Insurance",
            "subcategory":"Life Insurance",
            "type":"Services"
        }
    ],
    "sg:phone":"+1 641 642 3612",
    "sg:postcode":"52572",
    "sg:province":"IA",
    "sg:tags":[
        "retirement",
        "business",
        "resume",
        "profit",
        "annuity",
        "sharing",
        "commercial",
        "planning",
        "plan",
        "auto",
        "pension"
    ],
    "sg:website":"http://progressive.com",
    "wof:name":"Cook Insurance",
    "wof:placetype":"venue"
},
  "geometry": {"coordinates":[-92.677143,40.685062],"type":"Point"}
}