{
  "type": "Feature",
  "properties": {
    "iso:country":"US",
    "sg:address":"403 N Cass St",
    "sg:city":"Mt Ayr",
    "sg:classifiers":[
        {
            "category":"Freight",
            "type":"Transportation"
        }
    ],
    "sg:phone":"+1 641 464 2600",
    "sg:postcode":"50854",
    "sg:province":"IA",
    "sg:tags":[
        "frozen",
        "food",
        "locker",
        "plant"
    ],
    "wof:name":"Community Meat Processors",
    "wof:placetype":"venue"
},
  "geometry": {"coordinates":[-94.242577,40.718028],"type":"Point"}
}