{
  "type": "Feature",
  "properties": {
    "iso:country":"US",
    "sg:address":"906 E 9th St",
    "sg:city":"Muscatine",
    "sg:classifiers":[
        {
            "category":"Farming",
            "subcategory":"Farm",
            "type":"Manufacturing & Wholesale Goods"
        },
        {
            "category":"Personal",
            "subcategory":"Barber",
            "type":"Services"
        }
    ],
    "sg:phone":"+1 563 262 3742",
    "sg:postcode":"52761",
    "sg:province":"IA",
    "sg:tags":[
        "crop",
        "general"
    ],
    "wof:name":"Ken's Classic Cut",
    "wof:placetype":"venue"
},
  "geometry": {"coordinates":[-91.041691,41.432097],"type":"Point"}
}