{
  "type": "Feature",
  "properties": {
    "iso:country":"US",
    "sg:address":"2604 W Locust St",
    "sg:city":"Davenport",
    "sg:classifiers":[
        {
            "category":"Shopping",
            "subcategory":"Department Store",
            "type":"Retail Goods"
        }
    ],
    "sg:phone":"+1 563 391 0747",
    "sg:postcode":"52804",
    "sg:province":"IA",
    "sg:tags":[
        "shop"
    ],
    "wof:name":"Dollar General",
    "wof:placetype":"venue"
},
  "geometry": {"coordinates":[-90.61558599999999,41.538281],"type":"Point"}
}