{
  "type": "Feature",
  "properties": {
    "addr:full":"710 2nd Ave SW Cresco IA 52136",
    "addr:housenumber":"710",
    "addr:postcode":"52136",
    "addr:street":"2Nd Ave Sw",
    "iso:country":"US",
    "sg:address":"710 2nd Ave SW",
    "sg:city":"Cresco",
    "sg:classifiers":[
        {
            "category":"Retail",
            "subcategory":"Auto Repair",
            "type":"Services"
        }
    ],
    "sg:phone":"+1 563 547 4910",
    "sg:postcode":"52136",
    "sg:province":"IA",
    "sg:tags":[
        "repairing",
        "automobile"
    ],
    "wof:name":"H & S Motors",
    "wof:placetype":"venue"
},
  "geometry": {"coordinates":[-92.127368,43.371187],"type":"Point"}
}