{
  "type": "Feature",
  "properties": {
    "addr:full":"3425 S 11th Ave Eldridge IA 52748",
    "addr:housenumber":"3425",
    "addr:postcode":"52748",
    "addr:street":"S 11Th Ave",
    "iso:country":"US",
    "sg:address":"3425 S 11th Ave",
    "sg:city":"Eldridge",
    "sg:classifiers":[
        {
            "category":"Building & Trades",
            "subcategory":"Construction",
            "type":"Services"
        }
    ],
    "sg:phone":"+1 563 285 4344",
    "sg:postcode":"52748",
    "sg:province":"IA",
    "sg:tags":[
        "general",
        "contractor"
    ],
    "sg:website":"www.qcqc.com",
    "wof:name":"Quality Construction Svc",
    "wof:placetype":"venue"
},
  "geometry": {"coordinates":[-90.56965599999999,41.624011],"type":"Point"}
}