{
  "type": "Feature",
  "properties": {
    "iso:country":"US",
    "sg:address":"8550 New York Ave",
    "sg:city":"Urbandale",
    "sg:classifiers":[
        {
            "category":"Building & Trades",
            "subcategory":"Plumbing",
            "type":"Services"
        }
    ],
    "sg:phone":"+1 515 681 4364",
    "sg:postcode":"50322",
    "sg:province":"IA",
    "sg:tags":[
        "contractor"
    ],
    "wof:name":"Eagle Mechanical Inc",
    "wof:placetype":"venue"
},
  "geometry": {"coordinates":[-93.735747,41.620412],"type":"Point"}
}