{
  "type": "Feature",
  "properties": {
    "iso:country":"US",
    "sg:address":"130 N Main St",
    "sg:city":"Elkader",
    "sg:classifiers":[
        {
            "category":"Education",
            "subcategory":"Library",
            "type":"Public Place"
        }
    ],
    "sg:phone":"+1 563 245 1446",
    "sg:postcode":"52043",
    "sg:province":"IA",
    "wof:name":"Elkader Public Library",
    "wof:placetype":"venue"
},
  "geometry": {"coordinates":[-91.404923,42.855099],"type":"Point"}
}