{
  "type": "Feature",
  "properties": {
    "iso:country":"US",
    "sg:address":"22075 115th St",
    "sg:city":"Iowa Falls",
    "sg:classifiers":[
        {
            "category":"Utilities",
            "subcategory":"Fuel Oil & Lpg",
            "type":"Services"
        }
    ],
    "sg:phone":"+1 641 648 3597",
    "sg:postcode":"50126",
    "sg:province":"IA",
    "sg:tags":[
        "propane",
        "gas"
    ],
    "wof:name":"Maguire Supply",
    "wof:placetype":"venue"
},
  "geometry": {"coordinates":[-93.24749300000001,42.536128],"type":"Point"}
}