{
  "type": "Feature",
  "properties": {
    "iso:country":"US",
    "sg:address":"301 E Main St",
    "sg:city":"Wayland",
    "sg:classifiers":[
        {
            "category":"Real Estate",
            "subcategory":"Real Estate Agent",
            "type":"Services"
        }
    ],
    "sg:phone":"+1 319 256 6267",
    "sg:postcode":"52654",
    "sg:province":"IA",
    "sg:tags":[
        "appraiser"
    ],
    "wof:name":"Nebel Appraisal Svc",
    "wof:placetype":"venue"
},
  "geometry": {"coordinates":[-91.65455300000001,41.147134],"type":"Point"}
}