{
  "type": "Feature",
  "properties": {
    "iso:country":"US",
    "sg:address":"450 Kaufmann Ave",
    "sg:city":"Dubuque",
    "sg:classifiers":[
        {
            "category":"Building & Trades",
            "subcategory":"Construction",
            "type":"Services"
        }
    ],
    "sg:phone":"+1 563 583 7729",
    "sg:postcode":"52001",
    "sg:province":"IA",
    "sg:tags":[
        "house"
    ],
    "wof:name":"Steuer Construction",
    "wof:placetype":"venue"
},
  "geometry": {"coordinates":[-90.678601,42.514078],"type":"Point"}
}