{
  "type": "Feature",
  "properties": {
    "iso:country":"US",
    "sg:address":"1776 Hamilton Blvd",
    "sg:city":"Sioux City",
    "sg:classifiers":[
        {
            "category":"Banks & Credit Unions",
            "subcategory":"Bank",
            "type":"Services"
        }
    ],
    "sg:phone":"+1 712 252 9771",
    "sg:postcode":"51103",
    "sg:province":"IA",
    "sg:tags":[
        "financing"
    ],
    "wof:name":"Citi Financial",
    "wof:placetype":"venue"
},
  "geometry": {"coordinates":[-96.416646,42.508639],"type":"Point"}
}