{
  "type": "Feature",
  "properties": {
    "iso:country":"US",
    "sg:address":"203 Way St",
    "sg:city":"Wesley",
    "sg:classifiers":[
        {
            "category":"Real Estate",
            "subcategory":"Real Estate Operator",
            "type":"Services"
        }
    ],
    "sg:phone":"+1 515 679 4250",
    "sg:postcode":"50483",
    "sg:province":"IA",
    "sg:tags":[
        "property",
        "lessor"
    ],
    "wof:name":"Alvin Becker",
    "wof:placetype":"venue"
},
  "geometry": {"coordinates":[-93.98757999999999,43.08342],"type":"Point"}
}