{
  "type": "Feature",
  "properties": {
    "iso:country":"US",
    "sg:address":"1025 170th St",
    "sg:city":"Fonda",
    "sg:phone":"+1 712 288 5801",
    "sg:postcode":"50540",
    "sg:province":"IA",
    "sg:tags":[
        "farm",
        "grain",
        "cash"
    ],
    "wof:name":"William Daniel",
    "wof:placetype":"venue"
},
  "geometry": {"coordinates":[-94.910437,42.546911],"type":"Point"}
}