{
  "type": "Feature",
  "properties": {
    "addr:full":"2000 Ellis Blvd NW Cedar Rapids IA 52405",
    "addr:housenumber":"2000",
    "addr:postcode":"52405",
    "addr:street":"Ellis Blvd Nw",
    "iso:country":"US",
    "sg:address":"2000 Ellis Blvd NW",
    "sg:city":"Cedar Rapids",
    "sg:classifiers":[
        {
            "category":"Recreation",
            "type":"Entertainment"
        }
    ],
    "sg:phone":"+1 319 286 5793",
    "sg:postcode":"52405",
    "sg:province":"IA",
    "sg:tags":[
        "pool",
        "swimming"
    ],
    "wof:name":"Ellis Pool",
    "wof:placetype":"venue"
},
  "geometry": {"coordinates":[-91.68581399999999,41.997173],"type":"Point"}
}