{
  "type": "Feature",
  "properties": {
    "iso:country":"US",
    "sg:address":"520 Montgomery St",
    "sg:city":"Decorah",
    "sg:classifiers":[
        {
            "category":"Wholesale",
            "subcategory":"Electrical",
            "type":"Manufacturing & Wholesale Goods"
        }
    ],
    "sg:phone":"+1 563 382 9582",
    "sg:postcode":"52101",
    "sg:province":"IA",
    "sg:tags":[
        "communication",
        "radio",
        "system"
    ],
    "wof:name":"Racom Corp",
    "wof:placetype":"venue"
},
  "geometry": {"coordinates":[-91.774109,43.298846],"type":"Point"}
}