{
  "type": "Feature",
  "properties": {
    "addr:full":"1020 N Sanborn St Canton IA 57013",
    "addr:housenumber":"1020",
    "addr:postcode":"57013",
    "addr:street":"N Sanborn St",
    "iso:country":"US",
    "sg:address":"1020 N Sanborn St",
    "sg:city":"Canton",
    "sg:classifiers":[
        {
            "category":"Insurance",
            "subcategory":"Insurance Agent",
            "type":"Services"
        }
    ],
    "sg:phone":"+1 605 987 2117",
    "sg:postcode":"57013",
    "sg:province":"IA",
    "wof:name":"Verley Financial",
    "wof:placetype":"venue"
},
  "geometry": {"coordinates":[-96.58202799999999,43.310143],"type":"Point"}
}