{
  "type": "Feature",
  "properties": {
    "iso:country":"US",
    "sg:address":"1358 Jaguar Ave",
    "sg:city":"Creston",
    "sg:classifiers":[
        {
            "category":"Professional",
            "subcategory":"Business Services",
            "type":"Services"
        }
    ],
    "sg:phone":"+1 641 782 6675",
    "sg:postcode":"50801",
    "sg:province":"IA",
    "wof:name":"B A Enterprise",
    "wof:placetype":"venue"
},
  "geometry": {"coordinates":[-94.299119,41.1029],"type":"Point"}
}