{
  "type": "Feature",
  "properties": {
    "iso:country":"US",
    "sg:address":"1272 330th St",
    "sg:city":"Moscow",
    "sg:phone":"+1 563 732 3706",
    "sg:postcode":"52760",
    "sg:province":"IA",
    "sg:tags":[
        "farm",
        "corn",
        "soybean"
    ],
    "wof:name":"Dale Marolf",
    "wof:placetype":"venue"
},
  "geometry": {"coordinates":[-91.11778700000001,41.611543],"type":"Point"}
}