{
  "type": "Feature",
  "properties": {
    "iso:country":"US",
    "sg:address":"401 E Hickory St",
    "sg:city":"Anamosa",
    "sg:classifiers":[
        {
            "category":"Building & Trades",
            "subcategory":"Construction",
            "type":"Services"
        }
    ],
    "sg:phone":"+1 319 462 3442",
    "sg:postcode":"52205",
    "sg:province":"IA",
    "sg:tags":[
        "contractor"
    ],
    "wof:name":"Quality Siding",
    "wof:placetype":"venue"
},
  "geometry": {"coordinates":[-91.291544,42.105881],"type":"Point"}
}