{
  "type": "Feature",
  "properties": {
    "iso:country":"US",
    "sg:address":"7404 Railway St",
    "sg:city":"Palo",
    "sg:classifiers":[
        {
            "category":"Professional",
            "subcategory":"Business Services",
            "type":"Services"
        }
    ],
    "sg:phone":"+1 319 390 5484",
    "sg:postcode":"52324",
    "sg:province":"IA",
    "wof:name":"J&J Sales Inc",
    "wof:placetype":"venue"
},
  "geometry": {"coordinates":[-91.768534,42.004771],"type":"Point"}
}