{
  "type": "Feature",
  "properties": {
    "iso:country":"US",
    "sg:address":"905 Court St",
    "sg:city":"Harlan",
    "sg:classifiers":[
        {
            "category":"Utilities",
            "subcategory":"Refuse",
            "type":"Services"
        }
    ],
    "sg:phone":"+1 712 755 7256",
    "sg:postcode":"51537",
    "sg:province":"IA",
    "sg:tags":[
        "garbage",
        "collection"
    ],
    "wof:name":"Kroger Hauling Svc",
    "wof:placetype":"venue"
},
  "geometry": {"coordinates":[-95.32140200000001,41.657602],"type":"Point"}
}