{
  "type": "Feature",
  "properties": {
    "iso:country":"US",
    "sg:address":"808 Pershing St",
    "sg:city":"Donnellson",
    "sg:classifiers":[
        {
            "category":"Health Services",
            "subcategory":"Doctor",
            "type":"Services"
        }
    ],
    "sg:phone":"+1 319 835 5662",
    "sg:postcode":"52625",
    "sg:province":"IA",
    "sg:tags":[
        "dentist"
    ],
    "wof:name":"Family Dentistry",
    "wof:placetype":"venue"
},
  "geometry": {"coordinates":[-91.569748,40.646197],"type":"Point"}
}