{
  "type": "Feature",
  "properties": {
    "addr:full":"221 21st St Ames IA 50010",
    "addr:housenumber":"221",
    "addr:postcode":"50010",
    "addr:street":"21St St",
    "iso:country":"US",
    "sg:address":"221 21st St",
    "sg:city":"Ames",
    "sg:classifiers":[
        {
            "category":"Building & Trades",
            "subcategory":"Construction",
            "type":"Services"
        }
    ],
    "sg:phone":"+1 515 233 5293",
    "sg:postcode":"50010",
    "sg:province":"IA",
    "sg:tags":[
        "handyman"
    ],
    "wof:name":"Aspen Home Repair",
    "wof:placetype":"venue"
},
  "geometry": {"coordinates":[-93.614589,42.043045],"type":"Point"}
}