{
  "type": "Feature",
  "properties": {
    "addr:full":"2827 220th St Winthrop IA 50682",
    "addr:housenumber":"2827",
    "addr:postcode":"50682",
    "addr:street":"220Th St",
    "iso:country":"US",
    "sg:address":"2827 220th St",
    "sg:city":"Winthrop",
    "sg:classifiers":[
        {
            "category":"Manufacturing",
            "subcategory":"Tools & Machinery",
            "type":"Manufacturing & Wholesale Goods"
        }
    ],
    "sg:phone":"+1 319 935 3848",
    "sg:postcode":"50682",
    "sg:province":"IA",
    "sg:tags":[
        "farm",
        "mfg"
    ],
    "wof:name":"Schmitt Equipment",
    "wof:placetype":"venue"
},
  "geometry": {"coordinates":[-91.724862,42.468536],"type":"Point"}
}