{
  "type": "Feature",
  "properties": {
    "iso:country":"US",
    "sg:address":"700 Harmon St",
    "sg:city":"Tama",
    "sg:classifiers":[
        {
            "category":"Organizations",
            "subcategory":"Religious Organization",
            "type":"Services"
        }
    ],
    "sg:phone":"+1 641 484 4411",
    "sg:postcode":"52339",
    "sg:province":"IA",
    "sg:tags":[
        "church"
    ],
    "wof:name":"St Paul Lutheran Church",
    "wof:placetype":"venue"
},
  "geometry": {"coordinates":[-92.57559999999999,41.966598],"type":"Point"}
}