{
  "type": "Feature",
  "properties": {
    "iso:country":"US",
    "sg:address":"12395 N Ave",
    "sg:city":"Parkersburg",
    "sg:classifiers":[
        {
            "category":"Farming",
            "subcategory":"Livestock Farm",
            "type":"Manufacturing & Wholesale Goods"
        }
    ],
    "sg:phone":"+1 319 346 2244",
    "sg:postcode":"50665",
    "sg:province":"IA",
    "sg:tags":[
        "beef",
        "corn",
        "cash",
        "grain",
        "cattle",
        "feedlot"
    ],
    "wof:name":"Jerald Eilderts",
    "wof:placetype":"venue"
},
  "geometry": {"coordinates":[-92.77025500000001,42.521696],"type":"Point"}
}