{
  "type": "Feature",
  "properties": {
    "addr:full":"716 Story St Fl 2 Boone IA 50036",
    "addr:housenumber":"716;2",
    "addr:postcode":"50036",
    "addr:street":"Story St",
    "iso:country":"US",
    "sg:address":"716 Story St Fl 2",
    "sg:city":"Boone",
    "sg:classifiers":[
        {
            "category":"Fast Food",
            "type":"Food & Drink"
        },
        {
            "category":"Restaurant",
            "type":"Food & Drink"
        }
    ],
    "sg:phone":"+1 515 432 8089",
    "sg:postcode":"50036",
    "sg:province":"IA",
    "sg:tags":[
        "pan",
        "asian",
        "chinese",
        "take"
    ],
    "wof:name":"New China",
    "wof:placetype":"venue"
},
  "geometry": {"coordinates":[-93.880014,42.062888],"type":"Point"}
}