{
  "type": "Feature",
  "properties": {
    "addr:full":"212 3rd Ave NE Independence IA 50644",
    "addr:housenumber":"212",
    "addr:postcode":"50644",
    "addr:street":"3Rd Ave Ne",
    "iso:country":"US",
    "sg:address":"212 3rd Ave NE",
    "sg:city":"Independence",
    "sg:classifiers":[
        {
            "category":"Building & Trades",
            "subcategory":"Plumbing",
            "type":"Services"
        }
    ],
    "sg:phone":"+1 319 334 2853",
    "sg:postcode":"50644",
    "sg:province":"IA",
    "sg:tags":[
        "contractor"
    ],
    "wof:name":"Erdmans Plumbing & Heating",
    "wof:placetype":"venue"
},
  "geometry": {"coordinates":[-91.891732,42.470775],"type":"Point"}
}