{
  "type": "Feature",
  "properties": {
    "iso:country":"US",
    "sg:address":"12284 Hedge Ave",
    "sg:city":"Le Mars",
    "sg:classifiers":[
        {
            "category":"Professional",
            "subcategory":"Secretarial Services",
            "type":"Services"
        }
    ],
    "sg:phone":"+1 712 277 2656",
    "sg:postcode":"51031",
    "sg:province":"IA",
    "sg:tags":[
        "convention",
        "court",
        "reporter"
    ],
    "wof:name":"A-1 Court Reporting Svc",
    "wof:placetype":"venue"
},
  "geometry": {"coordinates":[-96.351591,42.875907],"type":"Point"}
}