{
  "type": "Feature",
  "properties": {
    "iso:country":"US",
    "sg:address":"400 E 1st St",
    "sg:city":"Des Moines",
    "sg:classifiers":[
        {
            "category":"Government",
            "subcategory":"Office",
            "type":"Public Place"
        }
    ],
    "sg:phone":"+1 515 283 4944",
    "sg:postcode":"50309",
    "sg:province":"IA",
    "sg:tags":[
        "executive"
    ],
    "wof:name":"City Council",
    "wof:placetype":"venue"
},
  "geometry": {"coordinates":[-93.616412,41.589651],"type":"Point"}
}