{
  "type": "Feature",
  "properties": {
    "iso:country":"US",
    "sg:address":"8313 N 19th Ave W",
    "sg:city":"Colfax",
    "sg:classifiers":[
        {
            "category":"Building & Trades",
            "subcategory":"Electrical",
            "type":"Services"
        }
    ],
    "sg:phone":"+1 515 674 4595",
    "sg:postcode":"50054",
    "sg:province":"IA",
    "sg:tags":[
        "electrical",
        "electric",
        "contractor"
    ],
    "wof:name":"B K Electric Inc",
    "wof:placetype":"venue"
},
  "geometry": {"coordinates":[-93.18488499999999,41.717358],"type":"Point"}
}