{
  "type": "Feature",
  "properties": {
    "addr:full":"159 Appanoose Ct Iowa City IA 52240",
    "addr:housenumber":"159",
    "addr:postcode":"52240",
    "addr:street":"Appanoose Ct",
    "iso:country":"US",
    "sg:address":"159 Appanoose Ct",
    "sg:city":"Iowa City",
    "sg:classifiers":[
        {
            "category":"Professional",
            "subcategory":"Advertising",
            "type":"Services"
        }
    ],
    "sg:phone":"+1 319 338 9350",
    "sg:postcode":"52240",
    "sg:province":"IA",
    "wof:name":"Craig Associates",
    "wof:placetype":"venue"
},
  "geometry": {"coordinates":[-91.496263,41.627135],"type":"Point"}
}