{
  "type": "Feature",
  "properties": {
    "iso:country":"US",
    "sg:address":"514 Jefferson St",
    "sg:city":"Burlington",
    "sg:classifiers":[
        {
            "category":"Professional",
            "subcategory":"Accounting & Tax Preparation",
            "type":"Services"
        }
    ],
    "sg:phone":"+1 319 752 4551",
    "sg:postcode":"52601",
    "sg:province":"IA",
    "sg:tags":[
        "accountant"
    ],
    "wof:name":"Marti Lynch & Co",
    "wof:placetype":"venue"
},
  "geometry": {"coordinates":[-91.105948,40.81066],"type":"Point"}
}