{
  "type": "Feature",
  "properties": {
    "iso:country":"US",
    "sg:address":"208 Courtright St",
    "sg:city":"Mapleton",
    "sg:classifiers":[
        {
            "category":"Shopping",
            "subcategory":"Used Merchandise",
            "type":"Retail Goods"
        }
    ],
    "sg:phone":"+1 712 882 2775",
    "sg:postcode":"51034",
    "sg:province":"IA",
    "sg:tags":[
        "clothing"
    ],
    "wof:name":"Tina's Treasures",
    "wof:placetype":"venue"
},
  "geometry": {"coordinates":[-95.79578100000001,42.164584],"type":"Point"}
}