{
  "type": "Feature",
  "properties": {
    "iso:country":"US",
    "sg:address":"400 Cedar St",
    "sg:city":"Tipton",
    "sg:classifiers":[
        {
            "category":"Government",
            "subcategory":"Office",
            "type":"Public Place"
        }
    ],
    "sg:phone":"+1 563 886 2226",
    "sg:postcode":"52772",
    "sg:province":"IA",
    "sg:tags":[
        "county",
        "program",
        "health"
    ],
    "wof:name":"Cedar County Public Health",
    "wof:placetype":"venue"
},
  "geometry": {"coordinates":[-91.12840799999999,41.769995],"type":"Point"}
}