{
  "type": "Feature",
  "properties": {
    "iso:country":"US",
    "sg:address":"1529 Prairie du Chien Rd",
    "sg:city":"Iowa City",
    "sg:classifiers":[
        {
            "category":"Freight",
            "type":"Transportation"
        }
    ],
    "sg:phone":"+1 319 338 0260",
    "sg:postcode":"52245",
    "sg:province":"IA",
    "sg:tags":[
        "relocation"
    ],
    "wof:name":"Bgi",
    "wof:placetype":"venue"
},
  "geometry": {"coordinates":[-91.52238,41.683522],"type":"Point"}
}