{
  "type": "Feature",
  "properties": {
    "addr:full":"1501 30th St Bettendorf IA 52722",
    "addr:housenumber":"1501",
    "addr:postcode":"52722",
    "addr:street":"30Th St",
    "iso:country":"US",
    "sg:address":"1501 30th St",
    "sg:city":"Bettendorf",
    "sg:classifiers":[
        {
            "category":"Organizations",
            "subcategory":"Religious Organization",
            "type":"Services"
        }
    ],
    "sg:phone":"+1 563 359 9260",
    "sg:postcode":"52722",
    "sg:province":"IA",
    "sg:tags":[
        "church"
    ],
    "wof:name":"Community Of Christ",
    "wof:placetype":"venue"
},
  "geometry": {"coordinates":[-90.49069299999999,41.536828],"type":"Point"}
}