{
  "type": "Feature",
  "properties": {
    "addr:full":"227 S 6th St Council Bluffs IA 51501",
    "addr:housenumber":"227",
    "addr:postcode":"51501",
    "addr:street":"S 6Th St",
    "iso:country":"US",
    "sg:address":"227 S 6th St",
    "sg:city":"Council Bluffs",
    "sg:classifiers":[
        {
            "category":"Government",
            "subcategory":"Office",
            "type":"Public Place"
        }
    ],
    "sg:phone":"+1 712 328 5617",
    "sg:postcode":"51501",
    "sg:province":"IA",
    "sg:tags":[
        "county",
        "taxation"
    ],
    "sg:website":"www.pottco.org",
    "wof:name":"Pottawattamie County Assessor",
    "wof:placetype":"venue"
},
  "geometry": {"coordinates":[-95.85291700000001,41.257163],"type":"Point"}
}