{
  "type": "Feature",
  "properties": {
    "iso:country":"US",
    "sg:address":"702 Story St",
    "sg:city":"Boone",
    "sg:classifiers":[
        {
            "category":"Sports & Exercise",
            "subcategory":"Gym",
            "type":"Entertainment"
        }
    ],
    "sg:phone":"+1 515 432 2705",
    "sg:postcode":"50036",
    "sg:province":"IA",
    "sg:tags":[
        "club",
        "health",
        "studio",
        "gymnasium"
    ],
    "wof:name":"Curves For Women",
    "wof:placetype":"venue"
},
  "geometry": {"coordinates":[-93.879936,42.063787],"type":"Point"}
}