{
  "type": "Feature",
  "properties": {
    "iso:country":"US",
    "sg:address":"730 S Dubuque St",
    "sg:city":"Iowa City",
    "sg:classifiers":[
        {
            "category":"Social Services",
            "type":"Services"
        }
    ],
    "sg:phone":"+1 319 338 3870",
    "sg:postcode":"52240",
    "sg:province":"IA",
    "sg:tags":[
        "organization",
        "welfare"
    ],
    "wof:name":"Evert Conner Rights & Resource",
    "wof:placetype":"venue"
},
  "geometry": {"coordinates":[-91.533123,41.652585],"type":"Point"}
}