{
  "type": "Feature",
  "properties": {
    "addr:full":"110 Waukee Ave Waukee IA 50263",
    "addr:housenumber":"110",
    "addr:postcode":"50263",
    "addr:street":"Waukee Ave",
    "iso:country":"US",
    "sg:address":"110 Waukee Ave",
    "sg:city":"Waukee",
    "sg:classifiers":[
        {
            "category":"Freight",
            "type":"Transportation"
        }
    ],
    "sg:phone":"+1 515 987 4957",
    "sg:postcode":"50263",
    "sg:province":"IA",
    "sg:tags":[
        "building",
        "house",
        "mover"
    ],
    "wof:name":"Harold Bissell House Moving",
    "wof:placetype":"venue"
},
  "geometry": {"coordinates":[-93.87784000000001,41.605357],"type":"Point"}
}