{
  "type": "Feature",
  "properties": {
    "addr:full":"2080 Washburn Ave Masonville IA 50654",
    "addr:housenumber":"2080",
    "addr:postcode":"50654",
    "addr:street":"Washburn Ave",
    "iso:country":"US",
    "sg:address":"2080 Washburn Ave",
    "sg:city":"Masonville",
    "sg:classifiers":[
        {
            "category":"Professional",
            "subcategory":"Testing Lab",
            "type":"Services"
        }
    ],
    "sg:phone":"+1 563 927 5371",
    "sg:postcode":"50654",
    "sg:province":"IA",
    "sg:tags":[
        "laboratory"
    ],
    "wof:name":"Services On Site Health",
    "wof:placetype":"venue"
},
  "geometry": {"coordinates":[-91.647825,42.486207],"type":"Point"}
}