{
  "type": "Feature",
  "properties": {
    "iso:country":"US",
    "sg:address":"15551 Haberkorn Rd",
    "sg:city":"Sherrill",
    "sg:classifiers":[
        {
            "category":"Building & Trades",
            "subcategory":"Construction",
            "type":"Services"
        }
    ],
    "sg:phone":"+1 563 552 2733",
    "sg:postcode":"52073",
    "sg:province":"IA",
    "sg:tags":[
        "masonry",
        "contractor"
    ],
    "wof:name":"Cummer Masonry Inc",
    "wof:placetype":"venue"
},
  "geometry": {"coordinates":[-90.793103,42.605367],"type":"Point"}
}