{
  "type": "Feature",
  "properties": {
    "iso:country":"US",
    "sg:address":"11416 S 128th Ave W",
    "sg:city":"Runnells",
    "sg:phone":"+1 515 966 2137",
    "sg:postcode":"50237",
    "sg:province":"IA",
    "sg:tags":[
        "farm",
        "corn"
    ],
    "wof:name":"Kenneth Shepley",
    "wof:placetype":"venue"
},
  "geometry": {"coordinates":[-93.26929800000001,41.508121],"type":"Point"}
}