{
  "type": "Feature",
  "properties": {
    "addr:full":"216 S Market St Oskaloosa IA 52577",
    "addr:housenumber":"216",
    "addr:postcode":"52577",
    "addr:street":"S Market St",
    "iso:country":"US",
    "sg:address":"216 S Market St",
    "sg:city":"Oskaloosa",
    "sg:classifiers":[
        {
            "category":"Restaurant",
            "type":"Food & Drink"
        }
    ],
    "sg:phone":"+1 641 673 5306",
    "sg:postcode":"52577",
    "sg:province":"IA",
    "wof:name":"Judy's Market Street Cafe",
    "wof:placetype":"venue"
},
  "geometry": {"coordinates":[-92.64497900000001,41.294283],"type":"Point"}
}