{
  "type": "Feature",
  "properties": {
    "addr:full":"1000 Industrial Ave Harlan IA 51537",
    "addr:housenumber":"1000",
    "addr:postcode":"51537",
    "addr:street":"Industrial Ave",
    "iso:country":"US",
    "sg:address":"1000 Industrial Ave",
    "sg:city":"Harlan",
    "sg:classifiers":[
        {
            "category":"Utilities",
            "subcategory":"Electric",
            "type":"Services"
        }
    ],
    "sg:phone":"+1 712 755 2074",
    "sg:postcode":"51537",
    "sg:province":"IA",
    "sg:tags":[
        "company"
    ],
    "wof:name":"Harlan Municipal Utilities",
    "wof:placetype":"venue"
},
  "geometry": {"coordinates":[-95.32516699999999,41.640656],"type":"Point"}
}