{
  "type": "Feature",
  "properties": {
    "iso:country":"US",
    "sg:address":"1400 Walnut St",
    "sg:city":"Dallas Center",
    "sg:classifiers":[
        {
            "category":"Social Services",
            "type":"Services"
        }
    ],
    "sg:phone":"+1 515 992 3427",
    "sg:postcode":"50063",
    "sg:province":"IA",
    "sg:tags":[
        "senior",
        "citizen"
    ],
    "wof:name":"Senior Community Ctr",
    "wof:placetype":"venue"
},
  "geometry": {"coordinates":[-93.962462,41.68436],"type":"Point"}
}