{
  "type": "Feature",
  "properties": {
    "iso:country":"US",
    "sg:address":"802 5th St",
    "sg:city":"Durant",
    "sg:classifiers":[
        {
            "category":"Professional",
            "subcategory":"Lawyer & Legal Services",
            "type":"Services"
        }
    ],
    "sg:phone":"+1 563 785 6611",
    "sg:postcode":"52747",
    "sg:province":"IA",
    "sg:tags":[
        "attorney"
    ],
    "wof:name":"Robert C Meyer",
    "wof:placetype":"venue"
},
  "geometry": {"coordinates":[-90.90851000000001,41.60039],"type":"Point"}
}