{
  "type": "Feature",
  "properties": {
    "iso:country":"US",
    "sg:address":"114 1st Ave E",
    "sg:city":"Newton",
    "sg:classifiers":[
        {
            "category":"Personal",
            "subcategory":"Barber",
            "type":"Services"
        }
    ],
    "sg:phone":"+1 641 792 3646",
    "sg:postcode":"50208",
    "sg:province":"IA",
    "sg:tags":[
        "shop"
    ],
    "wof:name":"Rialto Barber Shop",
    "wof:placetype":"venue"
},
  "geometry": {"coordinates":[-93.052475,41.699618],"type":"Point"}
}