{
  "type": "Feature",
  "properties": {
    "iso:country":"US",
    "sg:address":"400 S 14th Ave",
    "sg:city":"Eldridge",
    "sg:classifiers":[
        {
            "category":"Manufacturing",
            "subcategory":"Printing",
            "type":"Manufacturing & Wholesale Goods"
        }
    ],
    "sg:phone":"+1 563 285 4800",
    "sg:postcode":"52748",
    "sg:province":"IA",
    "sg:tags":[
        "printer"
    ],
    "sg:website":"www.vonhoffmann.com",
    "wof:name":"Von Hoffmann Corp",
    "wof:placetype":"venue"
},
  "geometry": {"coordinates":[-90.566348,41.651458],"type":"Point"}
}