{
  "type": "Feature",
  "properties": {
    "iso:country":"US",
    "sg:address":"1801 Falls Ave",
    "sg:city":"Waterloo",
    "sg:classifiers":[
        {
            "category":"Building & Trades",
            "subcategory":"Plumbing",
            "type":"Services"
        }
    ],
    "sg:phone":"+1 319 233 6101",
    "sg:postcode":"50701",
    "sg:province":"IA",
    "sg:tags":[
        "mechanical",
        "contractor"
    ],
    "wof:name":"WBC Mechanical Inc",
    "wof:placetype":"venue"
},
  "geometry": {"coordinates":[-92.370035,42.499328],"type":"Point"}
}