{
  "type": "Feature",
  "properties": {
    "iso:country":"US",
    "sg:address":"112 N Main St",
    "sg:city":"Danville",
    "sg:classifiers":[
        {
            "category":"Personal",
            "subcategory":"Beauty Salon",
            "type":"Services"
        }
    ],
    "sg:phone":"+1 319 392 4129",
    "sg:postcode":"52623",
    "sg:province":"IA",
    "wof:name":"Danville Hair Place",
    "wof:placetype":"venue"
},
  "geometry": {"coordinates":[-91.31451800000001,40.866569],"type":"Point"}
}