{
  "type": "Feature",
  "properties": {
    "iso:country":"US",
    "sg:address":"820 Pearl St",
    "sg:city":"Sioux City",
    "sg:classifiers":[
        {
            "category":"Home & Garden",
            "subcategory":"Building Materials",
            "type":"Retail Goods"
        }
    ],
    "sg:phone":"+1 712 252 9088",
    "sg:postcode":"51101",
    "sg:province":"IA",
    "sg:tags":[
        "glass",
        "window",
        "plate"
    ],
    "sg:website":"www.dakotaland.com",
    "wof:name":"Mobile Auto Glass",
    "wof:placetype":"venue"
},
  "geometry": {"coordinates":[-96.407853,42.498877],"type":"Point"}
}