{
  "type": "Feature",
  "properties": {
    "iso:country":"US",
    "sg:address":"1946 Fig Ave",
    "sg:city":"Alvord",
    "sg:phone":"+1 712 473 2410",
    "sg:postcode":"51230",
    "sg:province":"IA",
    "sg:tags":[
        "wheat",
        "farm",
        "corn",
        "crop",
        "field",
        "soybean"
    ],
    "wof:name":"Don Thiessen",
    "wof:placetype":"venue"
},
  "geometry": {"coordinates":[-96.273905,43.368379],"type":"Point"}
}