{
  "type": "Feature",
  "properties": {
    "addr:full":"1091 Main St Dubuque IA 52001",
    "addr:housenumber":"1091",
    "addr:postcode":"52001",
    "addr:street":"Main St",
    "iso:country":"US",
    "sg:address":"1091 Main St",
    "sg:city":"Dubuque",
    "sg:classifiers":[
        {
            "category":"Restaurant",
            "type":"Food & Drink"
        }
    ],
    "sg:phone":"+1 563 588 2880",
    "sg:postcode":"52001",
    "sg:province":"IA",
    "wof:name":"Salsa's",
    "wof:placetype":"venue"
},
  "geometry": {"coordinates":[-90.66820300000001,42.502487],"type":"Point"}
}