{
  "type": "Feature",
  "properties": {
    "addr:full":"111 1st Ave N Humboldt IA 50548",
    "addr:housenumber":"111",
    "addr:postcode":"50548",
    "addr:street":"1St Ave N",
    "iso:country":"US",
    "sg:address":"111 1st Ave N",
    "sg:city":"Humboldt",
    "sg:classifiers":[
        {
            "category":"Freight",
            "type":"Transportation"
        }
    ],
    "sg:phone":"+1 515 332 5254",
    "sg:postcode":"50548",
    "sg:province":"IA",
    "sg:tags":[
        "operator",
        "trucking"
    ],
    "wof:name":"Robert Aukland",
    "wof:placetype":"venue"
},
  "geometry": {"coordinates":[-94.20738799999999,42.722421],"type":"Point"}
}