{
  "type": "Feature",
  "properties": {
    "iso:country":"US",
    "sg:address":"1806 Richland Dr",
    "sg:city":"Storm Lake",
    "sg:classifiers":[
        {
            "category":"Wholesale",
            "subcategory":"Machinery & Supplies",
            "type":"Manufacturing & Wholesale Goods"
        }
    ],
    "sg:phone":"+1 712 749 2940",
    "sg:postcode":"50588",
    "sg:province":"IA",
    "sg:tags":[
        "janitor"
    ],
    "wof:name":"Table Ease",
    "wof:placetype":"venue"
},
  "geometry": {"coordinates":[-95.174678,42.640841],"type":"Point"}
}