{
  "type": "Feature",
  "properties": {
    "addr:full":"321 8th Ave W Cresco IA 52136",
    "addr:housenumber":"321",
    "addr:postcode":"52136",
    "addr:street":"8Th Ave W Cresco",
    "iso:country":"US",
    "sg:address":"321 8th Ave W",
    "sg:city":"Cresco",
    "sg:classifiers":[
        {
            "category":"Health Services",
            "subcategory":"Doctor",
            "type":"Services"
        }
    ],
    "sg:phone":"+1 563 547 2022",
    "sg:postcode":"52136",
    "sg:province":"IA",
    "sg:tags":[
        "clinic"
    ],
    "wof:name":"Cresco Medical Clinic",
    "wof:placetype":"venue"
},
  "geometry": {"coordinates":[-92.118189,43.38184],"type":"Point"}
}