{
  "type": "Feature",
  "properties": {
    "iso:country":"US",
    "sg:address":"18 6th St SE",
    "sg:city":"West Bend",
    "sg:classifiers":[
        {
            "category":"Building & Trades",
            "subcategory":"Electrical",
            "type":"Services"
        }
    ],
    "sg:phone":"+1 515 887 3841",
    "sg:postcode":"50597",
    "sg:province":"IA",
    "sg:tags":[
        "electric",
        "contractor"
    ],
    "wof:name":"T Z Electric",
    "wof:placetype":"venue"
},
  "geometry": {"coordinates":[-94.44408300000001,42.955048],"type":"Point"}
}