{
  "type": "Feature",
  "properties": {
    "iso:country":"US",
    "sg:address":"827 Fir Rd",
    "sg:city":"Portsmouth",
    "sg:phone":"+1 712 744 3327",
    "sg:postcode":"51565",
    "sg:province":"IA",
    "sg:tags":[
        "beef",
        "farm",
        "corn",
        "soybean",
        "cattle",
        "feedlot"
    ],
    "wof:name":"Ernest Peters",
    "wof:placetype":"venue"
},
  "geometry": {"coordinates":[-95.460812,41.62287],"type":"Point"}
}