{
  "type": "Feature",
  "properties": {
    "iso:country":"US",
    "sg:address":"809 Avenue E",
    "sg:city":"Hawarden",
    "sg:classifiers":[
        {
            "category":"Autos & Motor Vehicles",
            "subcategory":"Auto Supplies",
            "type":"Retail Goods"
        }
    ],
    "sg:phone":"+1 712 551 2513",
    "sg:postcode":"51023",
    "sg:province":"SD",
    "sg:tags":[
        "tire"
    ],
    "wof:name":"Foreman Tire Svc",
    "wof:placetype":"venue"
},
  "geometry": {"coordinates":[-96.488176,42.995519],"type":"Point"}
}