{
  "type": "Feature",
  "properties": {
    "addr:full":"1327 3rd Ave S Fort Dodge IA 50501",
    "addr:housenumber":"1327",
    "addr:postcode":"50501",
    "addr:street":"3Rd Ave S",
    "iso:country":"US",
    "sg:address":"1327 3rd Ave S",
    "sg:city":"Fort Dodge",
    "sg:classifiers":[
        {
            "category":"Wholesale",
            "subcategory":"Vending Machines",
            "type":"Manufacturing & Wholesale Goods"
        }
    ],
    "sg:phone":"+1 515 573 4731",
    "sg:postcode":"50501",
    "sg:province":"IA",
    "sg:tags":[
        "operator"
    ],
    "wof:name":"Gommels Darrel Vending Service",
    "wof:placetype":"venue"
},
  "geometry": {"coordinates":[-94.180696,42.503027],"type":"Point"}
}