{
  "type": "Feature",
  "properties": {
    "addr:full":"201 E Division St Clarinda IA 51632",
    "addr:housenumber":"201",
    "addr:postcode":"51632",
    "addr:street":"E Division St",
    "iso:country":"US",
    "sg:address":"201 E Division St",
    "sg:city":"Clarinda",
    "sg:classifiers":[
        {
            "category":"Education",
            "subcategory":"School",
            "type":"Public Place"
        }
    ],
    "sg:phone":"+1 712 542 4510",
    "sg:postcode":"51632",
    "sg:province":"IA",
    "wof:name":"Garfield Elementary School",
    "wof:placetype":"venue"
},
  "geometry": {"coordinates":[-95.03643700000001,40.73093],"type":"Point"}
}