{
  "type": "Feature",
  "properties": {
    "iso:country":"US",
    "sg:address":"405 US Hwy 61",
    "sg:city":"Wapello",
    "sg:classifiers":[
        {
            "category":"Travel",
            "subcategory":"Hotels & Motels",
            "type":"Entertainment"
        }
    ],
    "sg:phone":"+1 319 523 2111",
    "sg:postcode":"52653",
    "sg:province":"IA",
    "wof:name":"Roy-El Motel",
    "wof:placetype":"venue"
},
  "geometry": {"coordinates":[-91.195905,41.184798],"type":"Point"}
}