{
  "type": "Feature",
  "properties": {
    "iso:country":"US",
    "sg:address":"4817 Heins Rd",
    "sg:city":"Center Point",
    "sg:classifiers":[
        {
            "category":"Farming",
            "subcategory":"Farm",
            "type":"Manufacturing & Wholesale Goods"
        }
    ],
    "sg:phone":"+1 319 849 1426",
    "sg:postcode":"52213",
    "sg:province":"IA",
    "sg:tags":[
        "crop",
        "general"
    ],
    "wof:name":"Hanson Farm",
    "wof:placetype":"venue"
},
  "geometry": {"coordinates":[-91.783483,42.221432],"type":"Point"}
}