{
  "type": "Feature",
  "properties": {
    "addr:full":"1002 N Lincoln St Knoxville IA 50138",
    "addr:housenumber":"1002",
    "addr:postcode":"50138",
    "addr:street":"N Lincoln St",
    "iso:country":"US",
    "sg:address":"1002 N Lincoln St",
    "sg:city":"Knoxville",
    "sg:classifiers":[
        {
            "category":"Health Services",
            "subcategory":"Hospital",
            "type":"Services"
        }
    ],
    "sg:phone":"+1 641 842 2151",
    "sg:postcode":"50138",
    "sg:province":"IA",
    "sg:website":"www.kach.org",
    "wof:name":"Knoxville Community Hospital",
    "wof:placetype":"venue"
},
  "geometry": {"coordinates":[-93.10956899999999,41.326739],"type":"Point"}
}