{
  "type": "Feature",
  "properties": {
    "addr:full":"510 US Hwy 6 Oakland IA 51560",
    "addr:housenumber":"510",
    "addr:postcode":"51560",
    "addr:street":"Us Hwy 6",
    "iso:country":"US",
    "sg:address":"510 US Hwy 6",
    "sg:city":"Oakland",
    "sg:classifiers":[
        {
            "category":"Retail",
            "subcategory":"Veterinary Services",
            "type":"Services"
        }
    ],
    "sg:phone":"+1 712 482 6868",
    "sg:postcode":"51560",
    "sg:province":"IA",
    "sg:tags":[
        "veterinarian"
    ],
    "wof:name":"Oakland Veterinary Clinic",
    "wof:placetype":"venue"
},
  "geometry": {"coordinates":[-95.38749900000001,41.317241],"type":"Point"}
}