{
  "type": "Feature",
  "properties": {
    "iso:country":"US",
    "sg:address":"3061 Esther Ave",
    "sg:city":"Odebolt",
    "sg:classifiers":[
        {
            "category":"Professional",
            "type":"Services"
        }
    ],
    "sg:phone":"+1 712 668 2671",
    "sg:postcode":"51458",
    "sg:province":"IA",
    "sg:tags":[
        "establishment"
    ],
    "wof:name":"Scott Mandernach-Shop",
    "wof:placetype":"venue"
},
  "geometry": {"coordinates":[-95.26446900000001,42.346785],"type":"Point"}
}