{
  "type": "Feature",
  "properties": {
    "iso:country":"US",
    "sg:address":"2360 Hwy 38",
    "sg:city":"Delhi",
    "sg:classifiers":[
        {
            "category":"Real Estate",
            "subcategory":"Real Estate Operator",
            "type":"Services"
        }
    ],
    "sg:phone":"+1 563 922 2623",
    "sg:postcode":"52223",
    "sg:province":"IA",
    "sg:tags":[
        "property",
        "lessor"
    ],
    "wof:name":"Billings Farm",
    "wof:placetype":"venue"
},
  "geometry": {"coordinates":[-91.33528099999999,42.451522],"type":"Point"}
}