{
  "type": "Feature",
  "properties": {
    "iso:country":"US",
    "sg:address":"210 S Prospect St",
    "sg:city":"Maquoketa",
    "sg:classifiers":[
        {
            "category":"Shopping",
            "subcategory":"Gifts & Souvenirs",
            "type":"Retail Goods"
        }
    ],
    "sg:phone":"+1 563 652 9741",
    "sg:postcode":"52060",
    "sg:province":"IA",
    "wof:name":"Wildwoods Chainsaw Carvings",
    "wof:placetype":"venue"
},
  "geometry": {"coordinates":[-90.67171,42.067036],"type":"Point"}
}