{
  "type": "Feature",
  "properties": {
    "iso:country":"US",
    "sg:address":"520 S Schenck Rd",
    "sg:city":"Clarinda",
    "sg:classifiers":[
        {
            "category":"Wholesale",
            "subcategory":"Farm Supplies",
            "type":"Manufacturing & Wholesale Goods"
        }
    ],
    "sg:phone":"+1 712 542 2146",
    "sg:postcode":"51632",
    "sg:province":"IA",
    "sg:tags":[
        "feed"
    ],
    "wof:name":"Clarinda Co-Op",
    "wof:placetype":"venue"
},
  "geometry": {"coordinates":[-95.021635,40.734967],"type":"Point"}
}