{
  "type": "Feature",
  "properties": {
    "iso:country":"US",
    "sg:address":"311 SW Walnut St",
    "sg:city":"Ankeny",
    "sg:classifiers":[
        {
            "category":"Education",
            "subcategory":"Dance Studio",
            "type":"Public Place"
        }
    ],
    "sg:phone":"+1 515 963 8977",
    "sg:postcode":"50023",
    "sg:province":"IA",
    "sg:tags":[
        "instruction",
        "dancing"
    ],
    "wof:name":"Nicole's School Of Dance",
    "wof:placetype":"venue"
},
  "geometry": {"coordinates":[-93.605874,41.728704],"type":"Point"}
}