{
  "type": "Feature",
  "properties": {
    "iso:country":"US",
    "sg:address":"5438 State Hwy 224 N",
    "sg:city":"Kellogg",
    "sg:classifiers":[
        {
            "category":"Real Estate",
            "subcategory":"Real Estate Operator",
            "type":"Services"
        }
    ],
    "sg:phone":"+1 641 526 3396",
    "sg:postcode":"50135",
    "sg:province":"IA",
    "sg:tags":[
        "property",
        "lessor"
    ],
    "wof:name":"Robert Cooper",
    "wof:placetype":"venue"
},
  "geometry": {"coordinates":[-92.902664,41.754839],"type":"Point"}
}