{
  "type": "Feature",
  "properties": {
    "addr:full":"2143 US Hwy 6 Victor IA 52347",
    "addr:housenumber":"2143",
    "addr:postcode":"ia 52347",
    "addr:street":"Us Hwy 6",
    "iso:country":"US",
    "sg:address":"2143 US Hwy 6",
    "sg:city":"Victor",
    "sg:phone":"+1 319 647 3784",
    "sg:postcode":"52347",
    "sg:province":"IA",
    "sg:tags":[
        "farm",
        "grain",
        "cash"
    ],
    "wof:name":"Barbara Verdeck",
    "wof:placetype":"venue"
},
  "geometry": {"coordinates":[-92.364834,41.746355],"type":"Point"}
}