{
  "type": "Feature",
  "properties": {
    "iso:country":"US",
    "sg:address":"312 W Washington St",
    "sg:city":"Exira",
    "sg:classifiers":[
        {
            "category":"Restaurant",
            "type":"Food & Drink"
        }
    ],
    "sg:menulink":"http://www.allmenus.com/ia/exira/225894-caseys-general-store/menu/",
    "sg:phone":"+1 712 268 2317",
    "sg:postcode":"50076",
    "sg:province":"IA",
    "sg:tags":[
        "american",
        "pizza"
    ],
    "wof:name":"Casey's General Store",
    "wof:placetype":"venue"
},
  "geometry": {"coordinates":[-94.878912,41.591152],"type":"Point"}
}