{
  "type": "Feature",
  "properties": {
    "iso:country":"US",
    "sg:address":"1708 59th St",
    "sg:city":"Des Moines",
    "sg:classifiers":[
        {
            "category":"Manufacturing",
            "subcategory":"Furniture",
            "type":"Manufacturing & Wholesale Goods"
        }
    ],
    "sg:phone":"+1 515 279 6639",
    "sg:postcode":"50322",
    "sg:province":"IA",
    "sg:tags":[
        "upholstered",
        "household",
        "wood",
        "mfg"
    ],
    "wof:name":"Perkins Miniatures",
    "wof:placetype":"venue"
},
  "geometry": {"coordinates":[-93.69891,41.608983],"type":"Point"}
}