{
  "type": "Feature",
  "properties": {
    "iso:country":"US",
    "sg:address":"1606 Coffelt Ave",
    "sg:city":"Davenport",
    "sg:classifiers":[
        {
            "category":"Professional",
            "subcategory":"Engineering",
            "type":"Services"
        }
    ],
    "sg:phone":"+1 563 355 7643",
    "sg:postcode":"52803",
    "sg:province":"IA",
    "sg:tags":[
        "value"
    ],
    "wof:name":"T Richmond Associates",
    "wof:placetype":"venue"
},
  "geometry": {"coordinates":[-90.523385,41.535274],"type":"Point"}
}