{
  "type": "Feature",
  "properties": {
    "iso:country":"US",
    "sg:address":"3307 115th Ave",
    "sg:city":"Bancroft",
    "sg:classifiers":[
        {
            "category":"Farming",
            "subcategory":"Farm",
            "type":"Manufacturing & Wholesale Goods"
        }
    ],
    "sg:phone":"+1 515 885 2552",
    "sg:postcode":"50517",
    "sg:province":"IA",
    "sg:tags":[
        "consulting",
        "crop",
        "business",
        "general"
    ],
    "wof:name":"Robert F Rahe",
    "wof:placetype":"venue"
},
  "geometry": {"coordinates":[-94.236358,43.250347],"type":"Point"}
}