{
  "type": "Feature",
  "properties": {
    "addr:full":"1610 W Townline St Creston IA 50801",
    "addr:housenumber":"1610",
    "addr:postcode":"50801",
    "addr:street":"W Townline St",
    "iso:country":"US",
    "sg:address":"1610 W Townline St",
    "sg:city":"Creston",
    "sg:classifiers":[
        {
            "category":"Professional",
            "subcategory":"Employment Agencies",
            "type":"Services"
        }
    ],
    "sg:phone":"+1 641 782 2131",
    "sg:postcode":"50801",
    "sg:province":"IA",
    "wof:name":"Young Sheryl Arnp",
    "wof:placetype":"venue"
},
  "geometry": {"coordinates":[-94.382092,41.071078],"type":"Point"}
}