{
  "type": "Feature",
  "properties": {
    "iso:country":"US",
    "sg:address":"5055 NW 2nd St",
    "sg:city":"Des Moines",
    "sg:classifiers":[
        {
            "category":"Personal",
            "type":"Services"
        }
    ],
    "sg:phone":"+1 515 246 8730",
    "sg:postcode":"50313",
    "sg:province":"IA",
    "wof:name":"Halloween Express",
    "wof:placetype":"venue"
},
  "geometry": {"coordinates":[-93.619834,41.651495],"type":"Point"}
}