{
  "type": "Feature",
  "properties": {
    "iso:country":"US",
    "sg:address":"708 1st Ave S",
    "sg:city":"Altoona",
    "sg:classifiers":[
        {
            "category":"Health Services",
            "subcategory":"Doctor",
            "type":"Services"
        }
    ],
    "sg:phone":"+1 515 967 6611",
    "sg:postcode":"50009",
    "sg:province":"IA",
    "sg:tags":[
        "dentist"
    ],
    "wof:name":"Des Moines Dental Group",
    "wof:placetype":"venue"
},
  "geometry": {"coordinates":[-93.464691,41.645486],"type":"Point"}
}