{
  "type": "Feature",
  "properties": {
    "addr:full":"310 W Washington St Centerville IA 52544",
    "addr:housenumber":"310",
    "addr:postcode":"52544",
    "addr:street":"W Washington St",
    "iso:country":"US",
    "sg:address":"310 W Washington St",
    "sg:city":"Centerville",
    "sg:classifiers":[
        {
            "category":"Personal",
            "subcategory":"Beauty Salon",
            "type":"Services"
        }
    ],
    "sg:phone":"+1 641 856 8735",
    "sg:postcode":"52544",
    "sg:province":"IA",
    "sg:tags":[
        "shop"
    ],
    "wof:name":"Main Attractions",
    "wof:placetype":"venue"
},
  "geometry": {"coordinates":[-92.87572,40.735876],"type":"Point"}
}