{
  "type": "Feature",
  "properties": {
    "addr:full":"6230 SE 14th St Des Moines IA 50320",
    "addr:postcode":"6230;50320",
    "addr:street":"Se 14Th St",
    "iso:country":"US",
    "sg:address":"6230 SE 14th St",
    "sg:city":"Des Moines",
    "sg:classifiers":[
        {
            "category":"Restaurant",
            "type":"Food & Drink"
        }
    ],
    "sg:menulink":"http://www.allmenus.com/ia/bloomfield/174887-popeyes-chicken--biscuits/menu/",
    "sg:phone":"+1 515 285 1900",
    "sg:postcode":"50320",
    "sg:province":"IA",
    "sg:tags":[
        "american",
        "wing"
    ],
    "wof:name":"Popeyes Chicken & Biscuits",
    "wof:placetype":"venue"
},
  "geometry": {"coordinates":[-93.597005,41.528319],"type":"Point"}
}