{
  "type": "Feature",
  "properties": {
    "iso:country":"US",
    "sg:address":"1001 N Division St",
    "sg:city":"Sumner",
    "sg:classifiers":[
        {
            "category":"Government",
            "subcategory":"Office",
            "type":"Public Place"
        }
    ],
    "sg:phone":"+1 563 578 5724",
    "sg:postcode":"50674",
    "sg:province":"IA",
    "sg:tags":[
        "village"
    ],
    "wof:name":"Sumner Waste Water Plant",
    "wof:placetype":"venue"
},
  "geometry": {"coordinates":[-92.10149699999999,42.855829],"type":"Point"}
}