{
  "type": "Feature",
  "properties": {
    "addr:full":"1449 Euclid Ave Des Moines IA 50313",
    "addr:housenumber":"1449",
    "addr:postcode":"50313",
    "addr:street":"Euclid Ave",
    "iso:country":"US",
    "sg:address":"1449 Euclid Ave",
    "sg:city":"Des Moines",
    "sg:classifiers":[
        {
            "category":"Restaurant",
            "type":"Food & Drink"
        }
    ],
    "sg:phone":"+1 515 266 5517",
    "sg:postcode":"50313",
    "sg:province":"IA",
    "sg:tags":[
        "eating"
    ],
    "wof:name":"Sonic Drive-In",
    "wof:placetype":"venue"
},
  "geometry": {"coordinates":[-93.638807,41.627737],"type":"Point"}
}