{
  "type": "Feature",
  "properties": {
    "iso:country":"US",
    "sg:address":"211 S Iowa Ave",
    "sg:city":"Washington",
    "sg:classifiers":[
        {
            "category":"Food & Beverages",
            "subcategory":"Groceries & Convenience Stores",
            "type":"Retail Goods"
        }
    ],
    "sg:phone":"+1 319 653 2429",
    "sg:postcode":"52353",
    "sg:province":"IA",
    "wof:name":"Iowa Market Access Inc",
    "wof:placetype":"venue"
},
  "geometry": {"coordinates":[-91.691711,41.298266],"type":"Point"}
}