{
  "type": "Feature",
  "properties": {
    "iso:country":"US",
    "sg:address":"131 W 2nd St",
    "sg:city":"Davenport",
    "sg:classifiers":[
        {
            "category":"Restaurant",
            "type":"Food & Drink"
        }
    ],
    "sg:menulink":"http://www.allmenus.com/ia/davenport/249267-centro/menu/",
    "sg:phone":"+1 563 323 0300",
    "sg:postcode":"52801",
    "sg:province":"IA",
    "sg:tags":[
        "italian"
    ],
    "wof:name":"Centro",
    "wof:placetype":"venue"
},
  "geometry": {"coordinates":[-90.574522,41.521319],"type":"Point"}
}