{
  "type": "Feature",
  "properties": {
    "addr:full":"422 Tracy St Audubon IA 50025",
    "addr:housenumber":"422",
    "addr:postcode":"50025",
    "addr:street":"Tracy St",
    "iso:country":"US",
    "sg:address":"422 Tracy St",
    "sg:city":"Audubon",
    "sg:classifiers":[
        {
            "category":"Health Services",
            "subcategory":"Doctor",
            "type":"Services"
        }
    ],
    "sg:phone":"+1 712 563 4263",
    "sg:postcode":"50025",
    "sg:province":"IA",
    "sg:tags":[
        "dentist"
    ],
    "wof:name":"Audubon Family Dental Clinic",
    "wof:placetype":"venue"
},
  "geometry": {"coordinates":[-94.931162,41.720782],"type":"Point"}
}