{
  "type": "Feature",
  "properties": {
    "addr:full":"302 E Maple St Central City IA 52214",
    "addr:housenumber":"302",
    "addr:postcode":"52214",
    "addr:street":"E Maple St",
    "iso:country":"US",
    "sg:address":"302 E Maple St",
    "sg:city":"Central City",
    "sg:classifiers":[
        {
            "category":"Health Services",
            "subcategory":"Chiropractor",
            "type":"Services"
        }
    ],
    "sg:phone":"+1 319 438 1089",
    "sg:postcode":"52214",
    "sg:province":"IA",
    "wof:name":"Kubovec Chiropractic",
    "wof:placetype":"venue"
},
  "geometry": {"coordinates":[-91.525668,42.203049],"type":"Point"}
}