{
  "type": "Feature",
  "properties": {
    "iso:country":"US",
    "sg:address":"2846 215 St",
    "sg:city":"Sidney",
    "sg:classifiers":[
        {
            "category":"Farming",
            "subcategory":"Farm",
            "type":"Manufacturing & Wholesale Goods"
        }
    ],
    "sg:phone":"+1 712 374 2215",
    "sg:postcode":"51652",
    "sg:province":"IA",
    "sg:tags":[
        "crop",
        "general"
    ],
    "wof:name":"Debbie Boykin",
    "wof:placetype":"venue"
},
  "geometry": {"coordinates":[-95.66325500000001,40.736155],"type":"Point"}
}