{
  "type": "Feature",
  "properties": {
    "iso:country":"US",
    "sg:address":"706 Colleen Ave",
    "sg:city":"Evansdale",
    "sg:classifiers":[
        {
            "category":"Organizations",
            "subcategory":"Non-profit Organization",
            "type":"Services"
        }
    ],
    "sg:phone":"+1 319 232 5873",
    "sg:postcode":"50707",
    "sg:province":"IA",
    "wof:name":"Amvet",
    "wof:placetype":"venue"
},
  "geometry": {"coordinates":[-92.29227,42.468469],"type":"Point"}
}