{
  "type": "Feature",
  "properties": {
    "addr:full":"3320 Harry Langdon Blvd Council Bluffs IA 51503",
    "addr:housenumber":"3320",
    "addr:postcode":"51503",
    "addr:street":"Harry Langdon Blvd",
    "iso:country":"US",
    "sg:address":"3320 Harry Langdon Blvd",
    "sg:city":"Council Bluffs",
    "sg:classifiers":[
        {
            "category":"Organizations",
            "subcategory":"Religious Organization",
            "type":"Services"
        }
    ],
    "sg:phone":"+1 712 323 7721",
    "sg:postcode":"51503",
    "sg:province":"IA",
    "sg:tags":[
        "church"
    ],
    "wof:name":"First Assembly Of God",
    "wof:placetype":"venue"
},
  "geometry": {"coordinates":[-95.826086,41.228311],"type":"Point"}
}