{
  "type": "Feature",
  "properties": {
    "addr:full":"2241 N West St Carroll IA 51401",
    "addr:housenumber":"2241",
    "addr:postcode":"51401",
    "addr:street":"N West St",
    "iso:country":"US",
    "sg:address":"2241 N West St",
    "sg:city":"Carroll",
    "sg:classifiers":[
        {
            "category":"Health Services",
            "subcategory":"Nursing And Care Facility",
            "type":"Services"
        }
    ],
    "sg:phone":"+1 712 792 9284",
    "sg:postcode":"51401",
    "sg:province":"IA",
    "sg:tags":[
        "home",
        "convalescent"
    ],
    "wof:name":"Carroll Health Ctr",
    "wof:placetype":"venue"
},
  "geometry": {"coordinates":[-94.868999,42.082618],"type":"Point"}
}