{
  "type": "Feature",
  "properties": {
    "addr:full":"37856 Graham Rd Colesburg IA 52035",
    "addr:housenumber":"37856",
    "addr:postcode":"52035",
    "addr:street":"Graham Rd",
    "iso:country":"US",
    "sg:address":"37856 Graham Rd",
    "sg:city":"Colesburg",
    "sg:classifiers":[
        {
            "category":"Building & Trades",
            "subcategory":"Construction",
            "type":"Services"
        }
    ],
    "sg:phone":"+1 563 252 2326",
    "sg:postcode":"52035",
    "sg:province":"IA",
    "sg:tags":[
        "general",
        "contractor"
    ],
    "wof:name":"Bailey's Concrete & Carpentry",
    "wof:placetype":"venue"
},
  "geometry": {"coordinates":[-91.121336,42.679831],"type":"Point"}
}