{
  "type": "Feature",
  "properties": {
    "addr:full":"4777 180th St Cushing IA 51018",
    "addr:housenumber":"4777",
    "addr:postcode":"51018",
    "addr:street":"180Th St",
    "iso:country":"US",
    "sg:address":"4777 180th St",
    "sg:city":"Cushing",
    "sg:phone":"+1 712 384 2280",
    "sg:postcode":"51018",
    "sg:province":"IA",
    "sg:tags":[
        "farm",
        "corn",
        "grain",
        "cash"
    ],
    "wof:name":"Gerald Nissen",
    "wof:placetype":"venue"
},
  "geometry": {"coordinates":[-95.682631,42.443111],"type":"Point"}
}