{
  "type": "Feature",
  "properties": {
    "addr:full":"50071 State Hwy 64 Miles IA 52064",
    "addr:housenumber":"50071",
    "addr:postcode":"52064",
    "addr:street":"State Hwy 64",
    "iso:country":"US",
    "sg:address":"50071 State Hwy 64",
    "sg:city":"Miles",
    "sg:classifiers":[
        {
            "category":"Manufacturing",
            "subcategory":"Chemicals & Compounds",
            "type":"Manufacturing & Wholesale Goods"
        }
    ],
    "sg:phone":"+1 563 682 7313",
    "sg:postcode":"52064",
    "sg:province":"IA",
    "sg:tags":[
        "fertilizer",
        "mixing",
        "only"
    ],
    "wof:name":"New Horizons FS Inc",
    "wof:placetype":"venue"
},
  "geometry": {"coordinates":[-90.31453999999999,42.050196],"type":"Point"}
}