{
  "type": "Feature",
  "properties": {
    "iso:country":"US",
    "sg:address":"201 Ohio St",
    "sg:city":"Meservey",
    "sg:classifiers":[
        {
            "category":"Retail",
            "subcategory":"Funeral Services",
            "type":"Services"
        }
    ],
    "sg:phone":"+1 641 358 6105",
    "sg:postcode":"50457",
    "sg:province":"IA",
    "sg:tags":[
        "director"
    ],
    "wof:name":"Retz Grarup Funeral Home",
    "wof:placetype":"venue"
},
  "geometry": {"coordinates":[-93.47545,42.914653],"type":"Point"}
}