{
  "type": "Feature",
  "properties": {
    "iso:country":"US",
    "sg:address":"11 Deborah Dr",
    "sg:city":"Bloomfield",
    "sg:classifiers":[
        {
            "category":"Social Services",
            "subcategory":"Adult Care",
            "type":"Services"
        }
    ],
    "sg:phone":"+1 641 664 2523",
    "sg:postcode":"52537",
    "sg:province":"IA",
    "sg:tags":[
        "home",
        "residential"
    ],
    "wof:name":"Mulberry Place",
    "wof:placetype":"venue"
},
  "geometry": {"coordinates":[-92.416855,40.760261],"type":"Point"}
}