{
  "type": "Feature",
  "properties": {
    "addr:full":"29476 240th Ave Long Grove IA 52756",
    "addr:housenumber":"29476",
    "addr:postcode":"52756",
    "addr:street":"240Th Ave",
    "iso:country":"US",
    "sg:address":"29476 240th Ave",
    "sg:city":"Long Grove",
    "sg:classifiers":[
        {
            "category":"Wholesale",
            "subcategory":"Farm Supplies",
            "type":"Manufacturing & Wholesale Goods"
        }
    ],
    "sg:phone":"+1 563 225 3333",
    "sg:postcode":"52756",
    "sg:province":"IA",
    "sg:tags":[
        "feed"
    ],
    "wof:name":"Flenker Feed Co",
    "wof:placetype":"venue"
},
  "geometry": {"coordinates":[-90.44170800000001,41.735234],"type":"Point"}
}