{
  "type": "Feature",
  "properties": {
    "addr:full":"302 2nd St Coralville IA 52241",
    "addr:housenumber":"302",
    "addr:postcode":"52241",
    "addr:street":"2Nd St",
    "iso:country":"US",
    "sg:address":"302 2nd St",
    "sg:city":"Coralville",
    "sg:classifiers":[
        {
            "category":"Shopping",
            "type":"Retail Goods"
        }
    ],
    "sg:phone":"+1 319 358 1200",
    "sg:postcode":"52241",
    "sg:province":"IA",
    "sg:tags":[
        "tropical",
        "fish"
    ],
    "wof:name":"Coralville Bay",
    "wof:placetype":"venue"
},
  "geometry": {"coordinates":[-91.56943200000001,41.669995],"type":"Point"}
}