{
  "type": "Feature",
  "properties": {
    "iso:country":"US",
    "sg:address":"718 Geneseo St",
    "sg:city":"Storm Lake",
    "sg:classifiers":[
        {
            "category":"Building & Trades",
            "subcategory":"Construction",
            "type":"Services"
        },
        {
            "category":"Manufacturing",
            "subcategory":"Lumber",
            "type":"Manufacturing & Wholesale Goods"
        }
    ],
    "sg:phone":"+1 712 732 1496",
    "sg:postcode":"50588",
    "sg:province":"IA",
    "sg:tags":[
        "hardwood",
        "repairing",
        "mill",
        "remodeling",
        "contractor"
    ],
    "wof:name":"Jeff's Custom Carpentry",
    "wof:placetype":"venue"
},
  "geometry": {"coordinates":[-95.20338599999999,42.646587],"type":"Point"}
}