{
  "type": "Feature",
  "properties": {
    "iso:country":"US",
    "sg:address":"1641 Yellowstone Ave",
    "sg:city":"Clearfield",
    "sg:classifiers":[
        {
            "category":"Food & Beverages",
            "subcategory":"Groceries & Convenience Stores",
            "type":"Retail Goods"
        }
    ],
    "sg:phone":"+1 641 336 2292",
    "sg:postcode":"50840",
    "sg:province":"IA",
    "sg:tags":[
        "grocer"
    ],
    "wof:name":"Sun Best Foods",
    "wof:placetype":"venue"
},
  "geometry": {"coordinates":[-94.490836,40.808428],"type":"Point"}
}