{
  "type": "Feature",
  "properties": {
    "iso:country":"US",
    "sg:address":"11878 290th St",
    "sg:city":"Silver City",
    "sg:phone":"+1 712 526 2024",
    "sg:postcode":"51571",
    "sg:province":"IA",
    "sg:tags":[
        "farm",
        "corn",
        "soybean"
    ],
    "wof:name":"Byron Mass",
    "wof:placetype":"venue"
},
  "geometry": {"coordinates":[-95.632229,41.186585],"type":"Point"}
}