{
  "type": "Feature",
  "properties": {
    "iso:country":"US",
    "sg:address":"905 N Elm St",
    "sg:city":"Jefferson",
    "sg:classifiers":[
        {
            "category":"Autos & Motor Vehicles",
            "subcategory":"Automobile Sales",
            "type":"Retail Goods"
        }
    ],
    "sg:phone":"+1 515 386 2328",
    "sg:postcode":"50129",
    "sg:province":"IA",
    "sg:tags":[
        "car",
        "dealer"
    ],
    "wof:name":"Joe's Autos",
    "wof:placetype":"venue"
},
  "geometry": {"coordinates":[-94.377504,42.02414],"type":"Point"}
}