{
  "type": "Feature",
  "properties": {
    "addr:full":"6018 400th St Primghar IA 51245",
    "addr:housenumber":"6018",
    "addr:postcode":"51245",
    "addr:street":"400Th St",
    "iso:country":"US",
    "sg:address":"6018 400th St",
    "sg:city":"Primghar",
    "sg:phone":"+1 712 757 1287",
    "sg:postcode":"51245",
    "sg:province":"IA",
    "sg:tags":[
        "farm",
        "corn",
        "cash",
        "crop",
        "field",
        "grain",
        "soybean"
    ],
    "wof:name":"Beryl & Janice Hicks",
    "wof:placetype":"venue"
},
  "geometry": {"coordinates":[-95.60143600000001,43.069871],"type":"Point"}
}