{
  "type": "Feature",
  "properties": {
    "iso:country":"US",
    "sg:address":"27657 US Hwy 52",
    "sg:city":"New Vienna",
    "sg:classifiers":[
        {
            "category":"Professional",
            "subcategory":"Business Services",
            "type":"Services"
        }
    ],
    "sg:phone":"+1 563 870 2008",
    "sg:postcode":"52065",
    "sg:province":"IA",
    "wof:name":"Wulfekuhle Injection & Pumping",
    "wof:placetype":"venue"
},
  "geometry": {"coordinates":[-91.0339,42.600127],"type":"Point"}
}