{
  "type": "Feature",
  "properties": {
    "iso:country":"US",
    "sg:address":"2214 Woodlands Pkwy",
    "sg:city":"Clive",
    "sg:classifiers":[
        {
            "category":"Personal",
            "subcategory":"Beauty Salon",
            "type":"Services"
        }
    ],
    "sg:phone":"+1 515 224 1578",
    "sg:postcode":"50325",
    "sg:province":"IA",
    "wof:name":"Clip Art",
    "wof:placetype":"venue"
},
  "geometry": {"coordinates":[-93.800281,41.613378],"type":"Point"}
}