{
  "type": "Feature",
  "properties": {
    "iso:country":"US",
    "sg:address":"1024 5th St",
    "sg:city":"Sioux City",
    "sg:classifiers":[
        {
            "category":"Building & Trades",
            "subcategory":"Landscaping Services",
            "type":"Services"
        }
    ],
    "sg:phone":"+1 712 255 0100",
    "sg:postcode":"51101",
    "sg:province":"IA",
    "sg:tags":[
        "lawn",
        "maintenance",
        "grounds"
    ],
    "wof:name":"Ground Fx Inc",
    "wof:placetype":"venue"
},
  "geometry": {"coordinates":[-96.396691,42.495205],"type":"Point"}
}