{
  "type": "Feature",
  "properties": {
    "addr:full":"820 E Main St Lake City IA 51449",
    "addr:housenumber":"820",
    "addr:postcode":"51449",
    "addr:street":"E Main St",
    "iso:country":"US",
    "sg:address":"820 E Main St",
    "sg:city":"Lake City",
    "sg:classifiers":[
        {
            "category":"Food & Beverages",
            "subcategory":"Groceries & Convenience Stores",
            "type":"Retail Goods"
        }
    ],
    "sg:phone":"+1 712 464 7970",
    "sg:postcode":"51449",
    "sg:province":"IA",
    "sg:tags":[
        "grocer"
    ],
    "wof:name":"Supervalu",
    "wof:placetype":"venue"
},
  "geometry": {"coordinates":[-94.725145,42.26746],"type":"Point"}
}