{
  "type": "Feature",
  "properties": {
    "addr:full":"6456 190th Ave Newell IA 50568",
    "addr:housenumber":"6456",
    "addr:postcode":"50568",
    "addr:street":"190Th Ave",
    "iso:country":"US",
    "sg:address":"6456 190th Ave",
    "sg:city":"Newell",
    "sg:classifiers":[
        {
            "category":"Farming",
            "subcategory":"Farm",
            "type":"Manufacturing & Wholesale Goods"
        }
    ],
    "sg:phone":"+1 712 272 4660",
    "sg:postcode":"50568",
    "sg:province":"IA",
    "sg:tags":[
        "crop",
        "general"
    ],
    "wof:name":"Paul Bjorklund",
    "wof:placetype":"venue"
},
  "geometry": {"coordinates":[-95.03305400000001,42.586769],"type":"Point"}
}