{
  "type": "Feature",
  "properties": {
    "iso:country":"US",
    "sg:address":"1103 Buckeye Ave",
    "sg:city":"Ames",
    "sg:classifiers":[
        {
            "category":"Banks & Credit Unions",
            "subcategory":"Bank",
            "type":"Services"
        }
    ],
    "sg:phone":"+1 515 233 1245",
    "sg:postcode":"50010",
    "sg:province":"IA",
    "wof:name":"Valley Bank",
    "wof:placetype":"venue"
},
  "geometry": {"coordinates":[-93.611287,42.01312],"type":"Point"}
}