{
  "type": "Feature",
  "properties": {
    "iso:country":"US",
    "sg:address":"2011 225th Ave",
    "sg:city":"Osceola",
    "sg:classifiers":[
        {
            "category":"Retail",
            "subcategory":"Repair Shop",
            "type":"Services"
        }
    ],
    "sg:phone":"+1 641 342 6262",
    "sg:postcode":"50213",
    "sg:province":"IA",
    "sg:tags":[
        "appliance"
    ],
    "wof:name":"Mike's Kustom Kraft Appliance",
    "wof:placetype":"venue"
},
  "geometry": {"coordinates":[-93.77917100000001,41.013681],"type":"Point"}
}