{
  "type": "Feature",
  "properties": {
    "iso:country":"US",
    "sg:address":"201 Washington St",
    "sg:city":"Fayette",
    "sg:classifiers":[
        {
            "category":"Government",
            "subcategory":"Office",
            "type":"Public Place"
        }
    ],
    "sg:phone":"+1 563 425 3371",
    "sg:postcode":"52142",
    "sg:province":"IA",
    "sg:tags":[
        "state"
    ],
    "wof:name":"Natural Resources Dept",
    "wof:placetype":"venue"
},
  "geometry": {"coordinates":[-91.80099,42.843302],"type":"Point"}
}