{
  "type": "Feature",
  "properties": {
    "addr:full":"7530 Hickman Rd Windsor Heights IA 50322",
    "addr:housenumber":"7530",
    "addr:postcode":"50322",
    "addr:street":"Hickman Rd",
    "iso:country":"US",
    "sg:address":"7530 Hickman Rd",
    "sg:city":"Windsor Heights",
    "sg:classifiers":[
        {
            "category":"Insurance",
            "subcategory":"Insurance Agent",
            "type":"Services"
        }
    ],
    "sg:phone":"+1 515 274 4066",
    "sg:postcode":"50322",
    "sg:province":"IA",
    "wof:name":"Best Agency Inc",
    "wof:placetype":"venue"
},
  "geometry": {"coordinates":[-93.721525,41.614593],"type":"Point"}
}