{
  "type": "Feature",
  "properties": {
    "iso:country":"US",
    "sg:address":"209 1st St SE",
    "sg:city":"Orange City",
    "sg:classifiers":[
        {
            "category":"Health Services",
            "subcategory":"Hospital",
            "type":"Services"
        }
    ],
    "sg:phone":"+1 712 737 2635",
    "sg:postcode":"51041",
    "sg:province":"IA",
    "sg:tags":[
        "mental"
    ],
    "wof:name":"Bethesda Christian Counseling",
    "wof:placetype":"venue"
},
  "geometry": {"coordinates":[-96.056697,43.006146],"type":"Point"}
}