{
  "type": "Feature",
  "properties": {
    "iso:country":"US",
    "sg:address":"420 S Main St",
    "sg:city":"Denison",
    "sg:classifiers":[
        {
            "category":"Retail",
            "subcategory":"Auto Repair",
            "type":"Services"
        }
    ],
    "sg:phone":"+1 712 263 3687",
    "sg:postcode":"51442",
    "sg:province":"IA",
    "sg:tags":[
        "wrecker"
    ],
    "wof:name":"Waderich Towing",
    "wof:placetype":"venue"
},
  "geometry": {"coordinates":[-95.35529099999999,42.01213],"type":"Point"}
}