{
  "type": "Feature",
  "properties": {
    "iso:country":"US",
    "sg:address":"227 S Main St",
    "sg:city":"Paullina",
    "sg:classifiers":[
        {
            "category":"Restaurant",
            "type":"Food & Drink"
        }
    ],
    "sg:phone":"+1 712 448 3782",
    "sg:postcode":"51046",
    "sg:province":"IA",
    "wof:name":"White House Inn",
    "wof:placetype":"venue"
},
  "geometry": {"coordinates":[-95.687611,42.977498],"type":"Point"}
}