{
  "type": "Feature",
  "properties": {
    "iso:country":"US",
    "sg:address":"5095 NW 114th St",
    "sg:city":"Grimes",
    "sg:classifiers":[
        {
            "category":"Building & Trades",
            "subcategory":"Construction",
            "type":"Services"
        }
    ],
    "sg:phone":"+1 515 986 4479",
    "sg:postcode":"50111",
    "sg:province":"IA",
    "sg:tags":[
        "steel",
        "erectors"
    ],
    "wof:name":"Ace Construction",
    "wof:placetype":"venue"
},
  "geometry": {"coordinates":[-93.77498799999999,41.655232],"type":"Point"}
}