{
  "type": "Feature",
  "properties": {
    "addr:full":"2670 106th St Urbandale IA 50322",
    "addr:housenumber":"2670",
    "addr:postcode":"50322",
    "addr:street":"106Th St",
    "iso:country":"US",
    "sg:address":"2670 106th St",
    "sg:city":"Urbandale",
    "sg:classifiers":[
        {
            "category":"Real Estate",
            "subcategory":"Architect",
            "type":"Services"
        }
    ],
    "sg:phone":"+1 515 334 9446",
    "sg:postcode":"50322",
    "sg:province":"IA",
    "sg:tags":[
        "home",
        "planning",
        "design"
    ],
    "wof:name":"Ahmann Design Inc",
    "wof:placetype":"venue"
},
  "geometry": {"coordinates":[-93.763475,41.61903],"type":"Point"}
}