{
  "type": "Feature",
  "properties": {
    "iso:country":"US",
    "sg:address":"4105 66th St",
    "sg:city":"Urbandale",
    "sg:classifiers":[
        {
            "category":"Freight",
            "type":"Transportation"
        }
    ],
    "sg:phone":"+1 515 276 6158",
    "sg:postcode":"50322",
    "sg:province":"IA",
    "sg:tags":[
        "broker",
        "trucking"
    ],
    "wof:name":"DOT Compliance Svc",
    "wof:placetype":"venue"
},
  "geometry": {"coordinates":[-93.707323,41.636575],"type":"Point"}
}