{
  "type": "Feature",
  "properties": {
    "iso:country":"US",
    "sg:address":"901 Birmingham Ave",
    "sg:city":"Waterloo",
    "sg:classifiers":[
        {
            "category":"Autos & Motor Vehicles",
            "subcategory":"Automobile Sales",
            "type":"Retail Goods"
        }
    ],
    "sg:phone":"+1 319 232 0517",
    "sg:postcode":"50702",
    "sg:province":"IA",
    "sg:tags":[
        "car",
        "dealer"
    ],
    "wof:name":"Custom Auto Sales Of Iowa",
    "wof:placetype":"venue"
},
  "geometry": {"coordinates":[-92.32095200000001,42.477979],"type":"Point"}
}