{
  "type": "Feature",
  "properties": {
    "addr:full":"1236 Heires Ave Carroll IA 51401",
    "addr:housenumber":"1236",
    "addr:postcode":"51401",
    "addr:street":"Heires Ave",
    "iso:country":"US",
    "sg:address":"1236 Heires Ave",
    "sg:city":"Carroll",
    "sg:classifiers":[
        {
            "category":"Health Services",
            "subcategory":"Optometrist",
            "type":"Services"
        }
    ],
    "sg:phone":"+1 712 792 3318",
    "sg:postcode":"51401",
    "sg:province":"IA",
    "wof:name":"Carroll Eye Clinic",
    "wof:placetype":"venue"
},
  "geometry": {"coordinates":[-94.879778,42.076476],"type":"Point"}
}