{
  "type": "Feature",
  "properties": {
    "iso:country":"US",
    "sg:address":"2010 Philadelphia St",
    "sg:city":"Ames",
    "sg:classifiers":[
        {
            "category":"Home & Garden",
            "subcategory":"Home Furnishings",
            "type":"Retail Goods"
        }
    ],
    "sg:phone":"+1 515 233 9690",
    "sg:postcode":"50010",
    "sg:province":"IA",
    "sg:tags":[
        "pottery"
    ],
    "wof:name":"Puttin' On The Paint",
    "wof:placetype":"venue"
},
  "geometry": {"coordinates":[-93.58556799999999,42.035334],"type":"Point"}
}