{
  "type": "Feature",
  "properties": {
    "addr:full":"202 W Smith St Russell IA 50238",
    "addr:housenumber":"202",
    "addr:postcode":"50238",
    "addr:street":"W Smith St",
    "iso:country":"US",
    "sg:address":"202 W Smith St",
    "sg:city":"Russell",
    "sg:classifiers":[
        {
            "category":"Organizations",
            "subcategory":"Religious Organization",
            "type":"Services"
        }
    ],
    "sg:phone":"+1 641 535 2126",
    "sg:postcode":"50238",
    "sg:province":"IA",
    "wof:name":"First Baptist Church",
    "wof:placetype":"venue"
},
  "geometry": {"coordinates":[-93.200354,40.98186],"type":"Point"}
}