{
  "type": "Feature",
  "properties": {
    "iso:country":"US",
    "sg:address":"500 W Broadway",
    "sg:city":"Council Bluffs",
    "sg:classifiers":[
        {
            "category":"Professional",
            "subcategory":"Lawyer & Legal Services",
            "type":"Services"
        }
    ],
    "sg:phone":"+1 712 322 5588",
    "sg:postcode":"51503",
    "sg:province":"IA",
    "wof:name":"Ebke Stephen C Lwyr",
    "wof:placetype":"venue"
},
  "geometry": {"coordinates":[-95.8498,41.260899],"type":"Point"}
}