{
  "type": "Feature",
  "properties": {
    "iso:country":"US",
    "sg:address":"113 S Main St",
    "sg:city":"Pomeroy",
    "sg:classifiers":[
        {
            "category":"Building & Trades",
            "subcategory":"Electrical",
            "type":"Services"
        }
    ],
    "sg:phone":"+1 712 468 2537",
    "sg:postcode":"50575",
    "sg:province":"IA",
    "sg:tags":[
        "electric",
        "contractor"
    ],
    "wof:name":"Meyer Electric",
    "wof:placetype":"venue"
},
  "geometry": {"coordinates":[-94.685182,42.551136],"type":"Point"}
}