{
  "type": "Feature",
  "properties": {
    "iso:country":"US",
    "sg:address":"1522 50th St",
    "sg:city":"Iowa Falls",
    "sg:classifiers":[
        {
            "category":"Farming",
            "subcategory":"Farm",
            "type":"Manufacturing & Wholesale Goods"
        }
    ],
    "sg:phone":"+1 641 648 5477",
    "sg:postcode":"50126",
    "sg:province":"IA",
    "sg:tags":[
        "crop",
        "general"
    ],
    "wof:name":"Don Swieter",
    "wof:placetype":"venue"
},
  "geometry": {"coordinates":[-93.21761600000001,42.601038],"type":"Point"}
}