{
  "type": "Feature",
  "properties": {
    "iso:country":"US",
    "sg:address":"1198 Grand Ave",
    "sg:city":"Marion",
    "sg:classifiers":[
        {
            "category":"Building & Trades",
            "subcategory":"Construction",
            "type":"Services"
        }
    ],
    "sg:phone":"+1 319 377 0231",
    "sg:postcode":"52302",
    "sg:province":"IA",
    "sg:tags":[
        "tile",
        "dealer"
    ],
    "wof:name":"Adams Tile & Stone",
    "wof:placetype":"venue"
},
  "geometry": {"coordinates":[-91.59820499999999,42.020623],"type":"Point"}
}