{
  "type": "Feature",
  "properties": {
    "iso:country":"US",
    "sg:address":"1665 200 St",
    "sg:city":"Red Oak",
    "sg:classifiers":[
        {
            "category":"Wholesale",
            "subcategory":"Machinery & Supplies",
            "type":"Manufacturing & Wholesale Goods"
        }
    ],
    "sg:phone":"+1 712 623 4858",
    "sg:postcode":"51566",
    "sg:province":"IA",
    "sg:tags":[
        "farm",
        "equipment"
    ],
    "sg:website":"www.swie.com",
    "wof:name":"Southwest Iowa Equipment",
    "wof:placetype":"venue"
},
  "geometry": {"coordinates":[-95.23274000000001,41.016683],"type":"Point"}
}