{
  "type": "Feature",
  "properties": {
    "addr:full":"1691 Asbury Rd Dubuque IA 52001",
    "addr:housenumber":"1691",
    "addr:postcode":"52001",
    "addr:street":"Asbury Rd",
    "iso:country":"US",
    "sg:address":"1691 Asbury Rd",
    "sg:city":"Dubuque",
    "sg:classifiers":[
        {
            "category":"Food & Beverages",
            "subcategory":"Liquor & Beverages",
            "type":"Retail Goods"
        }
    ],
    "sg:phone":"+1 563 556 2623",
    "sg:postcode":"52001",
    "sg:province":"IA",
    "wof:name":"Beecher Beverage Co",
    "wof:placetype":"venue"
},
  "geometry": {"coordinates":[-90.69641900000001,42.499749],"type":"Point"}
}