{
  "type": "Feature",
  "properties": {
    "iso:country":"US",
    "sg:address":"2428 Taylor Ave",
    "sg:city":"Sac City",
    "sg:classifiers":[
        {
            "category":"Farming",
            "subcategory":"Farm",
            "type":"Manufacturing & Wholesale Goods"
        }
    ],
    "sg:phone":"+1 712 662 4431",
    "sg:postcode":"50583",
    "sg:province":"IA",
    "sg:tags":[
        "crop",
        "general"
    ],
    "wof:name":"Evergreen Farms",
    "wof:placetype":"venue"
},
  "geometry": {"coordinates":[-94.973185,42.434506],"type":"Point"}
}