{
  "type": "Feature",
  "properties": {
    "iso:country":"US",
    "sg:address":"4722 Hwy 21",
    "sg:city":"Deep River",
    "sg:classifiers":[
        {
            "category":"Wholesale",
            "subcategory":"Farm Supplies",
            "type":"Manufacturing & Wholesale Goods"
        },
        {
            "category":"Government",
            "subcategory":"Office",
            "type":"Public Place"
        }
    ],
    "sg:phone":"+1 641 595 3888",
    "sg:postcode":"52222",
    "sg:province":"IA",
    "sg:tags":[
        "county"
    ],
    "wof:name":"Poweshiek County Feeders",
    "wof:placetype":"venue"
},
  "geometry": {"coordinates":[-92.35754799999999,41.61255],"type":"Point"}
}