{
  "type": "Feature",
  "properties": {
    "iso:country":"US",
    "sg:address":"2504 27th St",
    "sg:city":"Des Moines",
    "sg:classifiers":[
        {
            "category":"Retail",
            "subcategory":"Repair Shop",
            "type":"Services"
        }
    ],
    "sg:phone":"+1 515 279 4422",
    "sg:postcode":"50310",
    "sg:province":"IA",
    "wof:name":"B & N Upholstery",
    "wof:placetype":"venue"
},
  "geometry": {"coordinates":[-93.65366,41.617277],"type":"Point"}
}