{
  "type": "Feature",
  "properties": {
    "iso:country":"US",
    "sg:address":"381 Center Point Dr",
    "sg:city":"Montezuma",
    "sg:classifiers":[
        {
            "category":"Shopping",
            "subcategory":"Discount & Variety Stores",
            "type":"Retail Goods"
        }
    ],
    "sg:phone":"+1 641 623 5567",
    "sg:postcode":"50171",
    "sg:province":"IA",
    "sg:tags":[
        "merchandise",
        "general"
    ],
    "wof:name":"Eighth Air Force Historic Soc",
    "wof:placetype":"venue"
},
  "geometry": {"coordinates":[-92.58528099999999,41.584623],"type":"Point"}
}