{
  "type": "Feature",
  "properties": {
    "addr:full":"8657 Douglas Ave Urbandale IA 50322",
    "addr:housenumber":"8657",
    "addr:postcode":"50322",
    "addr:street":"Douglas Ave",
    "iso:country":"US",
    "sg:address":"8657 Douglas Ave",
    "sg:city":"Urbandale",
    "sg:classifiers":[
        {
            "category":"Wholesale",
            "subcategory":"Medical Equipment & Supplies",
            "type":"Manufacturing & Wholesale Goods"
        }
    ],
    "sg:phone":"+1 515 270 8477",
    "sg:postcode":"50322",
    "sg:province":"IA",
    "sg:tags":[
        "alarm"
    ],
    "wof:name":"Responselink Of Des Moines",
    "wof:placetype":"venue"
},
  "geometry": {"coordinates":[-93.738439,41.629404],"type":"Point"}
}