{
  "type": "Feature",
  "properties": {
    "addr:full":"11245 Aurora Ave Urbandale IA 50322",
    "addr:housenumber":"11245",
    "addr:postcode":"50322",
    "addr:street":"Aurora Ave",
    "iso:country":"US",
    "sg:address":"11245 Aurora Ave",
    "sg:city":"Urbandale",
    "sg:classifiers":[
        {
            "category":"Food & Beverages",
            "subcategory":"Bakery",
            "type":"Retail Goods"
        }
    ],
    "sg:phone":"+1 515 334 9529",
    "sg:postcode":"50322",
    "sg:province":"IA",
    "sg:tags":[
        "baker"
    ],
    "wof:name":"Pepperidge Farm Inc",
    "wof:placetype":"venue"
},
  "geometry": {"coordinates":[-93.769958,41.638201],"type":"Point"}
}