{
  "type": "Feature",
  "properties": {
    "addr:full":"515 Grand Ave Ames IA 50010",
    "addr:housenumber":"515",
    "addr:postcode":"50010",
    "addr:street":"Grand Ave",
    "iso:country":"US",
    "sg:address":"515 Grand Ave",
    "sg:city":"Ames",
    "sg:classifiers":[
        {
            "category":"Health Services",
            "subcategory":"Doctor",
            "type":"Services"
        }
    ],
    "sg:phone":"+1 515 233 4013",
    "sg:postcode":"50010",
    "sg:province":"IA",
    "sg:tags":[
        "dentist"
    ],
    "wof:name":"Periodontal Specialists/ Ames",
    "wof:placetype":"venue"
},
  "geometry": {"coordinates":[-93.620272,42.026078],"type":"Point"}
}