{
  "type": "Feature",
  "properties": {
    "iso:country":"US",
    "sg:address":"6900 Dubuque Rd",
    "sg:city":"Raymond",
    "sg:classifiers":[
        {
            "category":"Mining & Drilling",
            "type":"Manufacturing & Wholesale Goods"
        }
    ],
    "sg:phone":"+1 319 232 8524",
    "sg:postcode":"50648",
    "sg:province":"IA",
    "sg:tags":[
        "stone"
    ],
    "wof:name":"Basic Materials Corp",
    "wof:placetype":"venue"
},
  "geometry": {"coordinates":[-92.20223,42.468685],"type":"Point"}
}