{
  "type": "Feature",
  "properties": {
    "addr:full":"2929 State Hwy 175 Dayton IA 50530",
    "addr:housenumber":"2929",
    "addr:postcode":"50530",
    "addr:street":"State Hwy 175",
    "iso:country":"US",
    "sg:address":"2929 State Hwy 175",
    "sg:city":"Dayton",
    "sg:classifiers":[
        {
            "category":"Professional",
            "type":"Services"
        }
    ],
    "sg:phone":"+1 515 547 3330",
    "sg:postcode":"50530",
    "sg:province":"IA",
    "sg:tags":[
        "establishment"
    ],
    "wof:name":"Pirie Motors",
    "wof:placetype":"venue"
},
  "geometry": {"coordinates":[-94.022662,42.245996],"type":"Point"}
}