{
  "type": "Feature",
  "properties": {
    "iso:country":"US",
    "sg:address":"2727 Dodge St",
    "sg:city":"Dubuque",
    "sg:classifiers":[
        {
            "category":"Food & Beverages",
            "subcategory":"Liquor & Beverages",
            "type":"Retail Goods"
        }
    ],
    "sg:phone":"+1 563 583 1879",
    "sg:postcode":"52003",
    "sg:province":"IA",
    "wof:name":"Sid's Liquor Store",
    "wof:placetype":"venue"
},
  "geometry": {"coordinates":[-90.711039,42.492376],"type":"Point"}
}