{
  "type": "Feature",
  "properties": {
    "addr:full":"3294 190th St Granger IA 50109",
    "addr:housenumber":"3294",
    "addr:postcode":"50109",
    "addr:street":"190Th St",
    "iso:country":"US",
    "sg:address":"3294 190th St",
    "sg:city":"Granger",
    "sg:classifiers":[
        {
            "category":"Manufacturing",
            "subcategory":"Jewelry",
            "type":"Manufacturing & Wholesale Goods"
        }
    ],
    "sg:phone":"+1 515 999 2981",
    "sg:postcode":"50109",
    "sg:province":"IA",
    "sg:tags":[
        "costume",
        "mfg"
    ],
    "wof:name":"Jennifers Jewels",
    "wof:placetype":"venue"
},
  "geometry": {"coordinates":[-93.832465,41.760972],"type":"Point"}
}