{
  "type": "Feature",
  "properties": {
    "iso:country":"US",
    "sg:address":"217 S 7th St",
    "sg:city":"Council Bluffs",
    "sg:classifiers":[
        {
            "category":"Professional",
            "subcategory":"Lawyer & Legal Services",
            "type":"Services"
        }
    ],
    "sg:phone":"+1 712 322 6100",
    "sg:postcode":"51501",
    "sg:province":"IA",
    "wof:name":"Gross & Welch PC",
    "wof:placetype":"venue"
},
  "geometry": {"coordinates":[-95.854646,41.257129],"type":"Point"}
}