{
  "type": "Feature",
  "properties": {
    "iso:country":"US",
    "sg:address":"24420 Bluff Rd",
    "sg:city":"Princeton",
    "sg:classifiers":[
        {
            "category":"Building & Trades",
            "subcategory":"Construction",
            "type":"Services"
        }
    ],
    "sg:phone":"+1 563 289 3628",
    "sg:postcode":"52768",
    "sg:province":"IA",
    "sg:tags":[
        "general",
        "contractor"
    ],
    "wof:name":"Haase Construction Co Inc",
    "wof:placetype":"venue"
},
  "geometry": {"coordinates":[-90.4276,41.713854],"type":"Point"}
}