{
  "type": "Feature",
  "properties": {
    "iso:country":"US",
    "sg:address":"2614 S Olive St",
    "sg:city":"Sioux City",
    "sg:classifiers":[
        {
            "category":"Building & Trades",
            "subcategory":"Cleaning & Sanitation",
            "type":"Services"
        }
    ],
    "sg:phone":"+1 712 276 4305",
    "sg:postcode":"51106",
    "sg:province":"IA",
    "sg:tags":[
        "maintenance"
    ],
    "wof:name":"All Shine Service",
    "wof:placetype":"venue"
},
  "geometry": {"coordinates":[-96.33815300000001,42.46363],"type":"Point"}
}