{
  "type": "Feature",
  "properties": {
    "addr:full":"2009 260th St Rockwell City IA 50579",
    "addr:housenumber":"2009",
    "addr:postcode":"50579",
    "addr:street":"260Th St",
    "iso:country":"US",
    "sg:address":"2009 260th St",
    "sg:city":"Rockwell City",
    "sg:classifiers":[
        {
            "category":"Building & Trades",
            "subcategory":"Plumbing",
            "type":"Services"
        }
    ],
    "sg:phone":"+1 712 297 8636",
    "sg:postcode":"50579",
    "sg:province":"IA",
    "sg:tags":[
        "contractor"
    ],
    "wof:name":"Letco Ltd",
    "wof:placetype":"venue"
},
  "geometry": {"coordinates":[-94.72612599999999,42.413363],"type":"Point"}
}