{
  "type": "Feature",
  "properties": {
    "iso:country":"US",
    "sg:address":"8421 University Blvd",
    "sg:city":"Clive",
    "sg:classifiers":[
        {
            "category":"Health Services",
            "subcategory":"Clinic",
            "type":"Services"
        }
    ],
    "sg:phone":"+1 515 222 1550",
    "sg:postcode":"50325",
    "sg:province":"IA",
    "sg:tags":[
        "home"
    ],
    "sg:website":"www.rightathome.net/desmoines",
    "wof:name":"Right At Home Rah Staffing",
    "wof:placetype":"venue"
},
  "geometry": {"coordinates":[-93.73589699999999,41.605655],"type":"Point"}
}