{
  "type": "Feature",
  "properties": {
    "iso:country":"US",
    "sg:address":"1248 295th Ave",
    "sg:city":"Fort Atkinson",
    "sg:classifiers":[
        {
            "category":"Wholesale",
            "subcategory":"Meat",
            "type":"Manufacturing & Wholesale Goods"
        }
    ],
    "sg:phone":"+1 563 534 7306",
    "sg:postcode":"52144",
    "sg:province":"IA",
    "sg:tags":[
        "poultry",
        "plant",
        "processing"
    ],
    "wof:name":"Sue's Pin & Feather",
    "wof:placetype":"venue"
},
  "geometry": {"coordinates":[-91.982804,43.117598],"type":"Point"}
}