{
  "type": "Feature",
  "properties": {
    "iso:country":"US",
    "sg:address":"1875 W Ridgeway Ave",
    "sg:city":"Waterloo",
    "sg:classifiers":[
        {
            "category":"Government",
            "subcategory":"Office",
            "type":"Public Place"
        }
    ],
    "sg:phone":"+1 319 233 4689",
    "sg:postcode":"50701",
    "sg:province":"IA",
    "wof:name":"Transportation-Materials Lab",
    "wof:placetype":"venue"
},
  "geometry": {"coordinates":[-92.384636,42.469317],"type":"Point"}
}