{
  "type": "Feature",
  "properties": {
    "iso:country":"US",
    "sg:address":"16224 525th St",
    "sg:city":"Griswold",
    "sg:classifiers":[
        {
            "category":"Real Estate",
            "subcategory":"Real Estate Operator",
            "type":"Services"
        }
    ],
    "sg:phone":"+1 712 778 2238",
    "sg:postcode":"51535",
    "sg:province":"IA",
    "sg:tags":[
        "property",
        "lessor"
    ],
    "wof:name":"Charles Drake",
    "wof:placetype":"venue"
},
  "geometry": {"coordinates":[-95.181483,41.259727],"type":"Point"}
}