{
  "type": "Feature",
  "properties": {
    "addr:full":"1010 Court Ave Bedford IA 50833",
    "addr:housenumber":"1010",
    "addr:postcode":"50833",
    "addr:street":"Court Ave",
    "iso:country":"US",
    "sg:address":"1010 Court Ave",
    "sg:city":"Bedford",
    "sg:classifiers":[
        {
            "category":"Shopping",
            "subcategory":"Used Merchandise",
            "type":"Retail Goods"
        }
    ],
    "sg:phone":"+1 712 523 2804",
    "sg:postcode":"50833",
    "sg:province":"IA",
    "sg:tags":[
        "antique"
    ],
    "wof:name":"Vintage Lampshades & Lighting",
    "wof:placetype":"venue"
},
  "geometry": {"coordinates":[-94.72021100000001,40.671021],"type":"Point"}
}