{
  "type": "Feature",
  "properties": {
    "addr:full":"810 E Main St Marshalltown IA 50158",
    "addr:housenumber":"810",
    "addr:postcode":"50158",
    "addr:street":"E Main St",
    "iso:country":"US",
    "sg:address":"810 E Main St",
    "sg:city":"Marshalltown",
    "sg:classifiers":[
        {
            "category":"Retail",
            "subcategory":"Auto Repair",
            "type":"Services"
        }
    ],
    "sg:phone":"+1 641 753 8611",
    "sg:postcode":"50158",
    "sg:province":"IA",
    "sg:tags":[
        "truck"
    ],
    "wof:name":"Scott's Diesel Repair & Refrig",
    "wof:placetype":"venue"
},
  "geometry": {"coordinates":[-92.898707,42.049284],"type":"Point"}
}