{
  "type": "Feature",
  "properties": {
    "iso:country":"US",
    "sg:address":"5900 NW 86th St",
    "sg:city":"Johnston",
    "sg:classifiers":[
        {
            "category":"Health Services",
            "subcategory":"Doctor",
            "type":"Services"
        }
    ],
    "sg:phone":"+1 515 276 6133",
    "sg:postcode":"50131",
    "sg:province":"IA",
    "sg:tags":[
        "physician",
        "surgeon"
    ],
    "wof:name":"Johnston Family Practice",
    "wof:placetype":"venue"
},
  "geometry": {"coordinates":[-93.73647099999999,41.668535],"type":"Point"}
}