{
  "type": "Feature",
  "properties": {
    "addr:city":"Sioux City",
    "addr:full":"1000 Larsen Park Rd Sioux City, Ia 51103",
    "addr:house_number":"1000",
    "addr:housenumber":"1000",
    "addr:phone":"+1 712-279-0198",
    "addr:postcode":"51103",
    "addr:road":"Larsen Park Rd",
    "addr:state":"IA",
    "addr:street":"Larsen Park Rd",
    "iso:country":"US",
    "sg:address":"1000 Larsen Park Rd",
    "sg:city":"Sioux City",
    "sg:classifiers":[
        {
            "category":"Government",
            "subcategory":"Office",
            "type":"Public Place"
        }
    ],
    "sg:phone":"+1 712 279 0198",
    "sg:postcode":"51103",
    "sg:province":"IA",
    "sg:tags":[
        "village"
    ],
    "wof:airports":[
        102526703
    ],
    "wof:name":"Sgt Floyd River Museum",
    "wof:placetype":"venue"
},
  "geometry": {"coordinates":[-96.4174,42.49891],"type":"Point"}
}