{
  "type": "Feature",
  "properties": {
    "addr:full":"555 33rd Ave SW Cedar Rapids IA 52404",
    "addr:housenumber":"555",
    "addr:postcode":"52404",
    "addr:street":"33Rd Ave Sw",
    "iso:country":"US",
    "sg:address":"555 33rd Ave SW",
    "sg:city":"Cedar Rapids",
    "sg:classifiers":[
        {
            "category":"Restaurant",
            "type":"Food & Drink"
        }
    ],
    "sg:menulink":"http://www.allmenus.com/ia/cedar-rapids/196108-taco-bell/menu/",
    "sg:postcode":"52404",
    "sg:province":"IA",
    "sg:tags":[
        "mexican"
    ],
    "wof:name":"Taco Bell",
    "wof:placetype":"venue"
},
  "geometry": {"coordinates":[-91.674673,41.94323],"type":"Point"}
}