{
  "type": "Feature",
  "properties": {
    "iso:country":"US",
    "sg:address":"3924 Sherman Blvd",
    "sg:city":"Des Moines",
    "sg:classifiers":[
        {
            "category":"Shopping",
            "subcategory":"Gifts & Souvenirs",
            "type":"Retail Goods"
        }
    ],
    "sg:phone":"+1 515 278 5478",
    "sg:postcode":"50310",
    "sg:province":"IA",
    "wof:name":"Gifts From Heart",
    "wof:placetype":"venue"
},
  "geometry": {"coordinates":[-93.679614,41.632919],"type":"Point"}
}