{
  "type": "Feature",
  "properties": {
    "addr:full":"1131 Dayton Ave Ames IA 50010",
    "addr:housenumber":"1131",
    "addr:postcode":"50010",
    "addr:street":"Dayton Ave",
    "iso:country":"US",
    "sg:address":"1131 Dayton Ave",
    "sg:city":"Ames",
    "sg:classifiers":[
        {
            "category":"Wholesale",
            "subcategory":"Meat",
            "type":"Manufacturing & Wholesale Goods"
        }
    ],
    "sg:phone":"+1 515 232 2273",
    "sg:postcode":"50010",
    "sg:province":"IA",
    "sg:tags":[
        "packer"
    ],
    "wof:name":"Grand Choice Foods Inc",
    "wof:placetype":"venue"
},
  "geometry": {"coordinates":[-93.58161800000001,42.035968],"type":"Point"}
}