{
  "type": "Feature",
  "properties": {
    "iso:country":"US",
    "sg:address":"2614 Northwestern Ave",
    "sg:city":"Ames",
    "sg:classifiers":[
        {
            "category":"Retail",
            "subcategory":"Laundry & Dry Cleaning",
            "type":"Services"
        }
    ],
    "sg:phone":"+1 515 233 9940",
    "sg:postcode":"50010",
    "sg:province":"IA",
    "sg:tags":[
        "cleaners",
        "rug",
        "carpet"
    ],
    "wof:name":"Heaven's Best Carpet/Upholster",
    "wof:placetype":"venue"
},
  "geometry": {"coordinates":[-93.626323,42.048289],"type":"Point"}
}