{
  "type": "Feature",
  "properties": {
    "addr:full":"950 Main St Dubuque IA 52001",
    "addr:housenumber":"950",
    "addr:postcode":"52001",
    "addr:street":"Main St",
    "iso:country":"US",
    "sg:address":"950 Main St",
    "sg:city":"Dubuque",
    "sg:classifiers":[
        {
            "category":"Retail",
            "subcategory":"Laundry & Dry Cleaning",
            "type":"Services"
        }
    ],
    "sg:phone":"+1 563 556 6168",
    "sg:postcode":"52001",
    "sg:province":"IA",
    "sg:tags":[
        "cleaner",
        "rug",
        "carpet"
    ],
    "wof:name":"Kann Do, Inc",
    "wof:placetype":"venue"
},
  "geometry": {"coordinates":[-90.66780900000001,42.502077],"type":"Point"}
}