{
  "type": "Feature",
  "properties": {
    "iso:country":"US",
    "sg:address":"701 West St",
    "sg:city":"Reinbeck",
    "sg:classifiers":[
        {
            "category":"Organizations",
            "subcategory":"Membership Organization",
            "type":"Services"
        }
    ],
    "sg:phone":"+1 319 345 6047",
    "sg:postcode":"50669",
    "sg:province":"IA",
    "wof:name":"UCCR Committee",
    "wof:placetype":"venue"
},
  "geometry": {"coordinates":[-92.60059699999999,42.319295],"type":"Point"}
}