{
  "type": "Feature",
  "properties": {
    "addr:full":"818 Pepper Dr Iowa City IA 52240",
    "addr:housenumber":"818",
    "addr:postcode":"52240",
    "addr:street":"Pepper Dr",
    "iso:country":"US",
    "sg:address":"818 Pepper Dr",
    "sg:city":"Iowa City",
    "sg:classifiers":[
        {
            "category":"Organizations",
            "subcategory":"Religious Organization",
            "type":"Services"
        }
    ],
    "sg:phone":"+1 319 338 1334",
    "sg:postcode":"52240",
    "sg:province":"IA",
    "sg:tags":[
        "church"
    ],
    "wof:name":"First Assembly Of God",
    "wof:placetype":"venue"
},
  "geometry": {"coordinates":[-91.524598,41.635437],"type":"Point"}
}