{
  "type": "Feature",
  "properties": {
    "addr:full":"919 Superior St Webster City IA 50595",
    "addr:housenumber":"919",
    "addr:postcode":"50595",
    "addr:street":"Superior St",
    "iso:country":"US",
    "sg:address":"919 Superior St",
    "sg:city":"Webster City",
    "sg:classifiers":[
        {
            "category":"Government",
            "subcategory":"Fire Station",
            "type":"Public Place"
        }
    ],
    "sg:phone":"+1 515 832 9131",
    "sg:postcode":"50595",
    "sg:province":"IA",
    "sg:tags":[
        "department"
    ],
    "wof:name":"Webster City Fire Dept",
    "wof:placetype":"venue"
},
  "geometry": {"coordinates":[-93.815938,42.467313],"type":"Point"}
}