{
  "type": "Feature",
  "properties": {
    "iso:country":"US",
    "sg:address":"1306 17th Ave",
    "sg:city":"Eldora",
    "sg:classifiers":[
        {
            "category":"Social Services",
            "subcategory":"Adult Care",
            "type":"Services"
        }
    ],
    "sg:phone":"+1 641 858 5152",
    "sg:postcode":"50627",
    "sg:province":"IA",
    "sg:tags":[
        "organization",
        "senior",
        "citizen"
    ],
    "wof:name":"Dorothy's Senior Ctr",
    "wof:placetype":"venue"
},
  "geometry": {"coordinates":[-93.09952,42.357066],"type":"Point"}
}