{
  "type": "Feature",
  "properties": {
    "iso:country":"US",
    "sg:address":"3478 State St",
    "sg:city":"Bettendorf",
    "sg:classifiers":[
        {
            "category":"Food & Beverages",
            "subcategory":"Liquor & Beverages",
            "type":"Retail Goods"
        }
    ],
    "sg:phone":"+1 563 344 1365",
    "sg:postcode":"52722",
    "sg:province":"IA",
    "sg:tags":[
        "beer",
        "spirit",
        "wine"
    ],
    "wof:name":"Lot A Spirits",
    "wof:placetype":"venue"
},
  "geometry": {"coordinates":[-90.485264,41.527908],"type":"Point"}
}