{
  "type": "Feature",
  "properties": {
    "iso:country":"US",
    "sg:address":"5454 N Gaines St",
    "sg:city":"Davenport",
    "sg:classifiers":[
        {
            "category":"Real Estate",
            "subcategory":"Real Estate Operator",
            "type":"Services"
        }
    ],
    "sg:phone":"+1 563 388 8543",
    "sg:postcode":"52806",
    "sg:province":"IA",
    "sg:tags":[
        "apartment"
    ],
    "wof:name":"Luther Crest",
    "wof:placetype":"venue"
},
  "geometry": {"coordinates":[-90.581757,41.575798],"type":"Point"}
}