{
  "type": "Feature",
  "properties": {
    "addr:full":"86 Main Ave Clinton IA 52732",
    "addr:housenumber":"86",
    "addr:postcode":"52732",
    "addr:street":"Main Ave",
    "iso:country":"US",
    "sg:address":"86 Main Ave",
    "sg:city":"Clinton",
    "sg:classifiers":[
        {
            "category":"Shopping",
            "type":"Retail Goods"
        }
    ],
    "sg:phone":"+1 563 242 6527",
    "sg:postcode":"52732",
    "sg:province":"IA",
    "sg:tags":[
        "art",
        "gallery",
        "dealer"
    ],
    "wof:name":"Riverbank Arts",
    "wof:placetype":"venue"
},
  "geometry": {"coordinates":[-90.178601,41.872451],"type":"Point"}
}