{
  "type": "Feature",
  "properties": {
    "addr:full":"998 Fremont Ave Dubuque IA 52003",
    "addr:housenumber":"998",
    "addr:postcode":"52003",
    "addr:street":"Fremont Ave",
    "iso:country":"US",
    "sg:address":"998 Fremont Ave",
    "sg:city":"Dubuque",
    "sg:classifiers":[
        {
            "category":"Professional",
            "subcategory":"Computer Services",
            "type":"Services"
        }
    ],
    "sg:phone":"+1 563 584 8440",
    "sg:postcode":"52003",
    "sg:province":"IA",
    "sg:tags":[
        "programming"
    ],
    "wof:name":"Amisys LLC",
    "wof:placetype":"venue"
},
  "geometry": {"coordinates":[-90.70458499999999,42.475204],"type":"Point"}
}