{
  "type": "Feature",
  "properties": {
    "iso:country":"US",
    "sg:address":"1132 A St",
    "sg:city":"Fort Dodge",
    "sg:classifiers":[
        {
            "category":"Organizations",
            "subcategory":"Religious Organization",
            "type":"Services"
        }
    ],
    "sg:phone":"+1 515 955 3737",
    "sg:postcode":"50501",
    "sg:province":"IA",
    "sg:tags":[
        "church"
    ],
    "wof:name":"Church Of Christ West Side",
    "wof:placetype":"venue"
},
  "geometry": {"coordinates":[-94.207499,42.490574],"type":"Point"}
}