{
  "type": "Feature",
  "properties": {
    "iso:country":"US",
    "sg:address":"2057 290th Ave",
    "sg:city":"Fort Madison",
    "sg:phone":"+1 319 372 1103",
    "sg:postcode":"52627",
    "sg:province":"IA",
    "sg:tags":[
        "farm",
        "corn",
        "soybean"
    ],
    "wof:name":"Ralph Wiggenjost",
    "wof:placetype":"venue"
},
  "geometry": {"coordinates":[-91.34917799999999,40.661687],"type":"Point"}
}