{
  "type": "Feature",
  "properties": {
    "iso:country":"US",
    "sg:address":"604 7th St",
    "sg:city":"Van Horne",
    "sg:classifiers":[
        {
            "category":"Professional",
            "subcategory":"Computer Services",
            "type":"Services"
        }
    ],
    "sg:phone":"+1 319 228 8781",
    "sg:postcode":"52346",
    "sg:province":"IA",
    "sg:tags":[
        "prepackaged",
        "software"
    ],
    "wof:name":"Rational Software",
    "wof:placetype":"venue"
},
  "geometry": {"coordinates":[-92.094044,42.012941],"type":"Point"}
}