{
  "type": "Feature",
  "properties": {
    "iso:country":"US",
    "sg:address":"614 S Oak St",
    "sg:city":"Iowa Falls",
    "sg:classifiers":[
        {
            "category":"Personal",
            "subcategory":"Beauty Salon",
            "type":"Services"
        }
    ],
    "sg:phone":"+1 641 648 5405",
    "sg:postcode":"50126",
    "sg:province":"IA",
    "wof:name":"Trends & Traditions",
    "wof:placetype":"venue"
},
  "geometry": {"coordinates":[-93.262304,42.507078],"type":"Point"}
}