{
  "type": "Feature",
  "properties": {
    "iso:country":"US",
    "sg:address":"602 N 1st Ave",
    "sg:city":"Iowa City",
    "sg:classifiers":[
        {
            "category":"Professional",
            "subcategory":"Advertising",
            "type":"Services"
        }
    ],
    "sg:phone":"+1 319 337 2445",
    "sg:postcode":"52245",
    "sg:province":"IA",
    "wof:name":"Yellow Page Control Ltd",
    "wof:placetype":"venue"
},
  "geometry": {"coordinates":[-91.50176,41.670036],"type":"Point"}
}