{
  "type": "Feature",
  "properties": {
    "iso:country":"US",
    "sg:address":"12345 University Ave",
    "sg:city":"Clive",
    "sg:classifiers":[
        {
            "category":"Banks & Credit Unions",
            "subcategory":"Investment Brokerage",
            "type":"Services"
        }
    ],
    "sg:phone":"+1 515 440 2199",
    "sg:postcode":"50325",
    "sg:province":"IA",
    "sg:tags":[
        "consultant",
        "financing"
    ],
    "wof:name":"Lend Trade Inc",
    "wof:placetype":"venue"
},
  "geometry": {"coordinates":[-93.79039899999999,41.600501],"type":"Point"}
}