{
  "type": "Feature",
  "properties": {
    "iso:country":"US",
    "sg:address":"707 5th St",
    "sg:city":"Ames",
    "sg:classifiers":[
        {
            "category":"Professional",
            "subcategory":"Accounting & Tax Preparation",
            "type":"Services"
        }
    ],
    "sg:phone":"+1 515 232 2505",
    "sg:postcode":"50010",
    "sg:province":"IA",
    "sg:tags":[
        "accountant"
    ],
    "wof:name":"D D Pyle Co",
    "wof:placetype":"venue"
},
  "geometry": {"coordinates":[-93.621798,42.025874],"type":"Point"}
}