{
  "type": "Feature",
  "properties": {
    "iso:country":"US",
    "sg:address":"1120 Red Oak Ave",
    "sg:city":"Riverside",
    "sg:phone":"+1 319 648 3725",
    "sg:postcode":"52327",
    "sg:province":"IA",
    "sg:tags":[
        "farm",
        "corn"
    ],
    "wof:name":"Wilbur Mast Farm",
    "wof:placetype":"venue"
},
  "geometry": {"coordinates":[-91.60842700000001,41.4978],"type":"Point"}
}