{
  "type": "Feature",
  "properties": {
    "iso:country":"US",
    "sg:address":"2920 Woodland Ave",
    "sg:city":"Truro",
    "sg:classifiers":[
        {
            "category":"Building & Trades",
            "subcategory":"Construction",
            "type":"Services"
        }
    ],
    "sg:phone":"+1 515 238 8193",
    "sg:postcode":"50257",
    "sg:province":"IA",
    "sg:tags":[
        "contractor"
    ],
    "wof:name":"Sharpe Tile & Stone",
    "wof:placetype":"venue"
},
  "geometry": {"coordinates":[-93.80383999999999,41.248709],"type":"Point"}
}