{
  "type": "Feature",
  "properties": {
    "addr:full":"301 W Lowell Ave Shenandoah IA 51601",
    "addr:housenumber":"301",
    "addr:postcode":"51601",
    "addr:street":"W Lowell Ave",
    "iso:country":"US",
    "sg:address":"301 W Lowell Ave",
    "sg:city":"Shenandoah",
    "sg:classifiers":[
        {
            "category":"Social Services",
            "subcategory":"Job Training",
            "type":"Services"
        }
    ],
    "sg:phone":"+1 712 246 3060",
    "sg:postcode":"51601",
    "sg:province":"IA",
    "sg:tags":[
        "rehabilitation"
    ],
    "wof:name":"Lowell House",
    "wof:placetype":"venue"
},
  "geometry": {"coordinates":[-95.369885,40.766864],"type":"Point"}
}