{
  "type": "Feature",
  "properties": {
    "iso:country":"US",
    "sg:address":"1013 Main St",
    "sg:city":"Pella",
    "sg:classifiers":[
        {
            "category":"Organizations",
            "subcategory":"Membership Organization",
            "type":"Services"
        }
    ],
    "sg:phone":"+1 641 628 3862",
    "sg:postcode":"50219",
    "sg:province":"IA",
    "wof:name":"American Mock Trial Assn",
    "wof:placetype":"venue"
},
  "geometry": {"coordinates":[-92.916498,41.410523],"type":"Point"}
}