{
  "type": "Feature",
  "properties": {
    "iso:country":"US",
    "sg:address":"813 7th Ave",
    "sg:city":"Sheldon",
    "sg:classifiers":[
        {
            "category":"Building & Trades",
            "subcategory":"Construction",
            "type":"Services"
        }
    ],
    "sg:phone":"+1 712 324 7009",
    "sg:postcode":"51201",
    "sg:province":"IA",
    "sg:tags":[
        "hanging",
        "contractor"
    ],
    "wof:name":"Barnes Painting & Drywall",
    "wof:placetype":"venue"
},
  "geometry": {"coordinates":[-95.84897100000001,43.180573],"type":"Point"}
}