{
  "type": "Feature",
  "properties": {
    "iso:country":"US",
    "sg:address":"1133 584th Ave",
    "sg:city":"Sabula",
    "sg:classifiers":[
        {
            "category":"Farming",
            "subcategory":"Farm",
            "type":"Manufacturing & Wholesale Goods"
        }
    ],
    "sg:phone":"+1 563 682 7472",
    "sg:postcode":"52070",
    "sg:province":"IA",
    "wof:name":"Rixen Brothers",
    "wof:placetype":"venue"
},
  "geometry": {"coordinates":[-90.218102,42.046774],"type":"Point"}
}