{
  "type": "Feature",
  "properties": {
    "iso:country":"US",
    "sg:address":"100 E 7th St",
    "sg:city":"Atlantic",
    "sg:classifiers":[
        {
            "category":"Utilities",
            "subcategory":"Electric",
            "type":"Services"
        }
    ],
    "sg:phone":"+1 712 243 9847",
    "sg:postcode":"50022",
    "sg:province":"IA",
    "sg:tags":[
        "company"
    ],
    "wof:name":"Power Wash Atlantic",
    "wof:placetype":"venue"
},
  "geometry": {"coordinates":[-95.011622,41.40397],"type":"Point"}
}