{
  "type": "Feature",
  "properties": {
    "iso:country":"US",
    "sg:address":"902 10th St",
    "sg:city":"Milford",
    "sg:classifiers":[
        {
            "category":"Education",
            "subcategory":"College",
            "type":"Public Place"
        }
    ],
    "sg:phone":"+1 712 338 2424",
    "sg:postcode":"51351",
    "sg:province":"IA",
    "sg:tags":[
        "academic",
        "school"
    ],
    "wof:name":"University Of Okoboji",
    "wof:placetype":"venue"
},
  "geometry": {"coordinates":[-95.14997200000001,43.324967],"type":"Point"}
}