{
  "type": "Feature",
  "properties": {
    "addr:full":"704 Story St Boone IA 50036",
    "addr:housenumber":"704",
    "addr:postcode":"50036",
    "addr:street":"Story St",
    "iso:country":"US",
    "sg:address":"704 Story St",
    "sg:city":"Boone",
    "sg:classifiers":[
        {
            "category":"Health Services",
            "subcategory":"Hospital",
            "type":"Services"
        }
    ],
    "sg:phone":"+1 515 432 7288",
    "sg:postcode":"50036",
    "sg:province":"IA",
    "sg:tags":[
        "mental"
    ],
    "sg:website":"www.genesisdevelopment.com",
    "wof:name":"Genesis Development",
    "wof:placetype":"venue"
},
  "geometry": {"coordinates":[-93.879936,42.063765],"type":"Point"}
}