{
  "type": "Feature",
  "properties": {
    "iso:country":"US",
    "sg:address":"4931 Crestmoor Dr",
    "sg:city":"Des Moines",
    "sg:classifiers":[
        {
            "category":"Banks & Credit Unions",
            "subcategory":"Financial Services",
            "type":"Services"
        }
    ],
    "sg:phone":"+1 515 252 0396",
    "sg:postcode":"50310",
    "sg:province":"IA",
    "sg:tags":[
        "trust",
        "investment",
        "real estate"
    ],
    "wof:name":"Tfi LLC",
    "wof:placetype":"venue"
},
  "geometry": {"coordinates":[-93.683522,41.643249],"type":"Point"}
}