{
  "type": "Feature",
  "properties": {
    "iso:country":"US",
    "sg:address":"203 9th Ave",
    "sg:city":"De Witt",
    "sg:classifiers":[
        {
            "category":"Professional",
            "type":"Services"
        }
    ],
    "sg:phone":"+1 563 659 9751",
    "sg:postcode":"52742",
    "sg:province":"IA",
    "wof:name":"Ricks Tree Service Inc",
    "wof:placetype":"venue"
},
  "geometry": {"coordinates":[-90.543395,41.818043],"type":"Point"}
}