{
  "type": "Feature",
  "properties": {
    "iso:country":"US",
    "sg:address":"1561 Nelson Ave",
    "sg:city":"Fort Dodge",
    "sg:classifiers":[
        {
            "category":"Building & Trades",
            "subcategory":"Pest Control",
            "type":"Services"
        }
    ],
    "sg:phone":"+1 515 955 3633",
    "sg:postcode":"50501",
    "sg:province":"IA",
    "wof:name":"Jerry's Pest Control",
    "wof:placetype":"venue"
},
  "geometry": {"coordinates":[-94.178074,42.563748],"type":"Point"}
}