{
  "type": "Feature",
  "properties": {
    "addr:full":"2570 Holiday Rd Coralville IA 52241",
    "addr:housenumber":"2570",
    "addr:postcode":"52241",
    "addr:street":"Holiday Rd",
    "iso:country":"US",
    "sg:address":"2570 Holiday Rd",
    "sg:city":"Coralville",
    "sg:classifiers":[
        {
            "category":"Professional",
            "subcategory":"Engineering",
            "type":"Services"
        }
    ],
    "sg:phone":"+1 319 338 4939",
    "sg:postcode":"52241",
    "sg:province":"IA",
    "sg:tags":[
        "engineer"
    ],
    "sg:website":"www.vjengineering.com",
    "wof:name":"Van Winkle-Jacob Engineering",
    "wof:placetype":"venue"
},
  "geometry": {"coordinates":[-91.605654,41.699321],"type":"Point"}
}