{
  "type": "Feature",
  "properties": {
    "iso:country":"US",
    "sg:address":"1252 230th St",
    "sg:city":"Waverly",
    "sg:classifiers":[
        {
            "category":"Farming",
            "subcategory":"Farm",
            "type":"Manufacturing & Wholesale Goods"
        }
    ],
    "sg:phone":"+1 319 352 3499",
    "sg:postcode":"50677",
    "sg:province":"IA",
    "sg:tags":[
        "crop",
        "general"
    ],
    "wof:name":"Neil H Smith Jr",
    "wof:placetype":"venue"
},
  "geometry": {"coordinates":[-92.512477,42.714946],"type":"Point"}
}