{
  "type": "Feature",
  "properties": {
    "iso:country":"US",
    "sg:address":"2801 West St",
    "sg:city":"Ames",
    "sg:classifiers":[
        {
            "category":"Personal",
            "subcategory":"Barber",
            "type":"Services"
        }
    ],
    "sg:phone":"+1 515 292 3131",
    "sg:postcode":"50014",
    "sg:province":"IA",
    "sg:tags":[
        "shop"
    ],
    "wof:name":"Monty's Barber Shop",
    "wof:placetype":"venue"
},
  "geometry": {"coordinates":[-93.657017,42.02533],"type":"Point"}
}