{
  "type": "Feature",
  "properties": {
    "iso:country":"US",
    "sg:address":"2356 260th St",
    "sg:city":"Rockwell City",
    "sg:classifiers":[
        {
            "category":"Manufacturing",
            "subcategory":"Tools & Machinery",
            "type":"Manufacturing & Wholesale Goods"
        }
    ],
    "sg:phone":"+1 712 297 7951",
    "sg:postcode":"50579",
    "sg:province":"IA",
    "sg:tags":[
        "machine",
        "shop"
    ],
    "wof:name":"Ray's Machine Shop",
    "wof:placetype":"venue"
},
  "geometry": {"coordinates":[-94.659516,42.413244],"type":"Point"}
}