{
  "type": "Feature",
  "properties": {
    "iso:country":"US",
    "sg:address":"528 2nd Ave S",
    "sg:city":"Clinton",
    "sg:classifiers":[
        {
            "category":"Social Services",
            "subcategory":"Child Care",
            "type":"Services"
        }
    ],
    "sg:phone":"+1 563 242 0337",
    "sg:postcode":"52732",
    "sg:province":"IA",
    "sg:tags":[
        "day"
    ],
    "wof:name":"Family Daycare",
    "wof:placetype":"venue"
},
  "geometry": {"coordinates":[-90.19811199999999,41.844545],"type":"Point"}
}