{
  "type": "Feature",
  "properties": {
    "iso:country":"US",
    "sg:address":"4204 SW 9th St",
    "sg:city":"Des Moines",
    "sg:classifiers":[
        {
            "category":"Wholesale",
            "subcategory":"Electrical",
            "type":"Manufacturing & Wholesale Goods"
        }
    ],
    "sg:phone":"+1 515 243 1210",
    "sg:postcode":"50315",
    "sg:province":"IA",
    "sg:tags":[
        "control",
        "security",
        "system"
    ],
    "sg:website":"www.actnowusa.com",
    "wof:name":"Access Control Technologies",
    "wof:placetype":"venue"
},
  "geometry": {"coordinates":[-93.625818,41.545817],"type":"Point"}
}