{
  "type": "Feature",
  "properties": {
    "iso:country":"US",
    "sg:address":"651 W Milwaukee St",
    "sg:city":"New Hampton",
    "sg:classifiers":[
        {
            "category":"Manufacturing",
            "subcategory":"Printing",
            "type":"Manufacturing & Wholesale Goods"
        }
    ],
    "sg:phone":"+1 641 394 5701",
    "sg:postcode":"50659",
    "sg:province":"IA",
    "sg:tags":[
        "screen"
    ],
    "wof:name":"Screen Prints To Go",
    "wof:placetype":"venue"
},
  "geometry": {"coordinates":[-92.324921,43.066908],"type":"Point"}
}