{
  "type": "Feature",
  "properties": {
    "iso:country":"US",
    "sg:address":"1901 W 5th St",
    "sg:city":"Vinton",
    "sg:classifiers":[
        {
            "category":"Real Estate",
            "subcategory":"Real Estate Operator",
            "type":"Services"
        }
    ],
    "sg:phone":"+1 319 472 2480",
    "sg:postcode":"52349",
    "sg:province":"IA",
    "sg:tags":[
        "building",
        "apartment"
    ],
    "wof:name":"Country Gardens Apts Vinton",
    "wof:placetype":"venue"
},
  "geometry": {"coordinates":[-92.043308,42.166718],"type":"Point"}
}