{
  "type": "Feature",
  "properties": {
    "iso:country":"US",
    "sg:address":"325 W Central Park Ave",
    "sg:city":"Davenport",
    "sg:classifiers":[
        {
            "category":"Building & Trades",
            "subcategory":"Landscaping Services",
            "type":"Services"
        }
    ],
    "sg:phone":"+1 563 322 1288",
    "sg:postcode":"52803",
    "sg:province":"IA",
    "wof:name":"SD Tree Service",
    "wof:placetype":"venue"
},
  "geometry": {"coordinates":[-90.57754,41.545457],"type":"Point"}
}