{
  "type": "Feature",
  "properties": {
    "addr:full":"6605 Dubuque Rd Raymond IA 50648",
    "addr:housenumber":"6605",
    "addr:postcode":"50648",
    "addr:street":"Dubuque Rd",
    "iso:country":"US",
    "sg:address":"6605 Dubuque Rd",
    "sg:city":"Raymond",
    "sg:classifiers":[
        {
            "category":"Real Estate",
            "subcategory":"Real Estate Agent",
            "type":"Services"
        }
    ],
    "sg:phone":"+1 319 226 3396",
    "sg:postcode":"50648",
    "sg:province":"IA",
    "wof:name":"Backes Realty",
    "wof:placetype":"venue"
},
  "geometry": {"coordinates":[-92.207888,42.468712],"type":"Point"}
}