{
  "type": "Feature",
  "properties": {
    "iso:country":"US",
    "sg:address":"418 S Elm St",
    "sg:city":"Avoca",
    "sg:classifiers":[
        {
            "category":"Government",
            "subcategory":"Office",
            "type":"Public Place"
        }
    ],
    "sg:phone":"+1 712 343 6792",
    "sg:postcode":"51521",
    "sg:province":"IA",
    "sg:tags":[
        "county",
        "program",
        "health"
    ],
    "wof:name":"Pottawattamie Public Health",
    "wof:placetype":"venue"
},
  "geometry": {"coordinates":[-95.33954900000001,41.474227],"type":"Point"}
}