{
  "type": "Feature",
  "properties": {
    "addr:full":"1506 NW Beechwood St Ankeny IA 50023",
    "addr:housenumber":"1506",
    "addr:postcode":"50023",
    "addr:street":"Nw Beechwood St",
    "iso:country":"US",
    "sg:address":"1506 NW Beechwood St",
    "sg:city":"Ankeny",
    "sg:classifiers":[
        {
            "category":"Farming",
            "subcategory":"Farm & Veterinary Services",
            "type":"Manufacturing & Wholesale Goods"
        }
    ],
    "sg:phone":"+1 515 965 4527",
    "sg:postcode":"50023",
    "sg:province":"IA",
    "sg:tags":[
        "labor",
        "trade",
        "contractor"
    ],
    "wof:name":"Xtreme Contractors & Services",
    "wof:placetype":"venue"
},
  "geometry": {"coordinates":[-93.629993,41.742547],"type":"Point"}
}