{
  "type": "Feature",
  "properties": {
    "iso:country":"US",
    "sg:address":"203 S Main St",
    "sg:city":"Protivin",
    "sg:classifiers":[
        {
            "category":"Personal",
            "subcategory":"Beauty Salon",
            "type":"Services"
        }
    ],
    "sg:phone":"+1 563 569 8582",
    "sg:postcode":"52163",
    "sg:province":"IA",
    "wof:name":"Janes Little Villa Salon",
    "wof:placetype":"venue"
},
  "geometry": {"coordinates":[-92.090855,43.215954],"type":"Point"}
}