{
  "type": "Feature",
  "properties": {
    "addr:full":"1384 Twixt Town Rd Marion IA 52302",
    "addr:housenumber":"1384",
    "addr:postcode":"52302",
    "addr:street":"Twixt Town Rd",
    "iso:country":"US",
    "sg:address":"1384 Twixt Town Rd",
    "sg:city":"Marion",
    "sg:classifiers":[
        {
            "category":"Insurance",
            "subcategory":"Health Insurance",
            "type":"Services"
        }
    ],
    "sg:phone":"+1 319 377 3334",
    "sg:postcode":"52302",
    "sg:province":"IA",
    "sg:tags":[
        "market"
    ],
    "sg:website":"www.gnc.com",
    "wof:name":"General Nutrition Center",
    "wof:placetype":"venue"
},
  "geometry": {"coordinates":[-91.623901,42.027699],"type":"Point"}
}