{
  "type": "Feature",
  "properties": {
    "iso:country":"US",
    "sg:address":"2520 Melrose Dr",
    "sg:city":"Cedar Falls",
    "sg:classifiers":[
        {
            "category":"Personal",
            "subcategory":"Beauty Salon",
            "type":"Services"
        }
    ],
    "sg:phone":"+1 319 277 0860",
    "sg:postcode":"50613",
    "sg:province":"IA",
    "wof:name":"Studio 4",
    "wof:placetype":"venue"
},
  "geometry": {"coordinates":[-92.431197,42.513569],"type":"Point"}
}