{
  "type": "Feature",
  "properties": {
    "iso:country":"US",
    "sg:address":"6442 State Hwy 136",
    "sg:city":"Worthington",
    "sg:classifiers":[
        {
            "category":"Building & Trades",
            "subcategory":"Construction",
            "type":"Services"
        }
    ],
    "sg:phone":"+1 563 855 2735",
    "sg:postcode":"52078",
    "sg:province":"IA",
    "sg:tags":[
        "excavation",
        "excavating",
        "contractor"
    ],
    "wof:name":"Dale Digmann Construction",
    "wof:placetype":"venue"
},
  "geometry": {"coordinates":[-91.116069,42.392538],"type":"Point"}
}