{
  "type": "Feature",
  "properties": {
    "iso:country":"US",
    "sg:address":"1247 Redwood Ave",
    "sg:city":"Brighton",
    "sg:classifiers":[
        {
            "category":"Farming",
            "subcategory":"Farm",
            "type":"Manufacturing & Wholesale Goods"
        }
    ],
    "sg:phone":"+1 319 694 3671",
    "sg:postcode":"52540",
    "sg:province":"IA",
    "sg:tags":[
        "crop",
        "general"
    ],
    "wof:name":"Kenneth Baker",
    "wof:placetype":"venue"
},
  "geometry": {"coordinates":[-91.850438,41.125772],"type":"Point"}
}