{
  "type": "Feature",
  "properties": {
    "iso:country":"US",
    "sg:address":"116 E May St",
    "sg:city":"Osceola",
    "sg:classifiers":[
        {
            "category":"Retail",
            "subcategory":"Repair Shop",
            "type":"Services"
        }
    ],
    "sg:phone":"+1 641 342 4361",
    "sg:postcode":"50213",
    "sg:province":"IA",
    "wof:name":"William J Davenport",
    "wof:placetype":"venue"
},
  "geometry": {"coordinates":[-93.76489100000001,41.025454],"type":"Point"}
}