{
  "type": "Feature",
  "properties": {
    "addr:full":"5515 NW 88th St Johnston IA 50131",
    "addr:housenumber":"5515",
    "addr:postcode":"50131",
    "addr:street":"Nw 88Th St",
    "iso:country":"US",
    "sg:address":"5515 NW 88th St",
    "sg:city":"Johnston",
    "sg:classifiers":[
        {
            "category":"Banks & Credit Unions",
            "subcategory":"Financial Services",
            "type":"Services"
        }
    ],
    "sg:phone":"+1 515 276 6800",
    "sg:postcode":"50131",
    "sg:province":"IA",
    "sg:tags":[
        "company",
        "holding"
    ],
    "sg:website":"www.kcholdingsinc.com",
    "wof:name":"K C Holdings",
    "wof:placetype":"venue"
},
  "geometry": {"coordinates":[-93.74038899999999,41.659724],"type":"Point"}
}