{
  "type": "Feature",
  "properties": {
    "iso:country":"US",
    "sg:address":"910 Heather Dr",
    "sg:city":"Dorchester",
    "sg:classifiers":[
        {
            "category":"Farming",
            "subcategory":"Livestock Farm",
            "type":"Manufacturing & Wholesale Goods"
        }
    ],
    "sg:phone":"+1 563 497 3229",
    "sg:postcode":"52140",
    "sg:province":"IA",
    "sg:tags":[
        "ranch",
        "feedlot",
        "beef",
        "cattle"
    ],
    "wof:name":"Thomas Wiemerslage",
    "wof:placetype":"venue"
},
  "geometry": {"coordinates":[-91.455596,43.456011],"type":"Point"}
}