{
  "type": "Feature",
  "properties": {
    "iso:country":"US",
    "sg:address":"520 7th St",
    "sg:city":"Hawarden",
    "sg:classifiers":[
        {
            "category":"Sports & Exercise",
            "subcategory":"Bowling",
            "type":"Entertainment"
        }
    ],
    "sg:phone":"+1 712 551 1415",
    "sg:postcode":"51023",
    "sg:province":"IA",
    "sg:tags":[
        "center"
    ],
    "wof:name":"Sportsman's Lanes & Lounge",
    "wof:placetype":"venue"
},
  "geometry": {"coordinates":[-96.487279,42.994269],"type":"Point"}
}