{
  "type": "Feature",
  "properties": {
    "iso:country":"US",
    "sg:address":"602 Coates St",
    "sg:city":"Parkersburg",
    "sg:classifiers":[
        {
            "category":"Government",
            "subcategory":"Post Office",
            "type":"Public Place"
        }
    ],
    "sg:phone":"+1 319 346 1567",
    "sg:postcode":"50665",
    "sg:province":"IA",
    "wof:name":"US Post Office",
    "wof:placetype":"venue"
},
  "geometry": {"coordinates":[-92.787189,42.577384],"type":"Point"}
}