{
  "type": "Feature",
  "properties": {
    "iso:country":"US",
    "sg:address":"223 Broadway St",
    "sg:city":"Audubon",
    "sg:classifiers":[
        {
            "category":"Shopping",
            "subcategory":"Books",
            "type":"Retail Goods"
        }
    ],
    "sg:phone":"+1 712 563 3335",
    "sg:postcode":"50025",
    "sg:province":"IA",
    "sg:tags":[
        "dealer"
    ],
    "wof:name":"Hansen Illustration",
    "wof:placetype":"venue"
},
  "geometry": {"coordinates":[-94.932835,41.720572],"type":"Point"}
}