{
  "type": "Feature",
  "properties": {
    "addr:full":"1560 US Hwy 65 Hampton IA 50441",
    "addr:housenumber":"1560",
    "addr:postcode":"50441",
    "addr:street":"Us Hwy 65",
    "iso:country":"US",
    "sg:address":"1560 US Hwy 65",
    "sg:city":"Hampton",
    "sg:classifiers":[
        {
            "category":"Utilities",
            "subcategory":"Electric",
            "type":"Services"
        }
    ],
    "sg:phone":"+1 641 456 2557",
    "sg:postcode":"50441",
    "sg:province":"IA",
    "sg:tags":[
        "company"
    ],
    "wof:name":"Franklin Rural Electric Co-Op",
    "wof:placetype":"venue"
},
  "geometry": {"coordinates":[-93.202349,42.768484],"type":"Point"}
}