{
  "type": "Feature",
  "properties": {
    "iso:country":"US",
    "sg:address":"628 2nd St",
    "sg:city":"Webster City",
    "sg:classifiers":[
        {
            "category":"Organizations",
            "subcategory":"Professional Association",
            "type":"Services"
        }
    ],
    "sg:phone":"+1 515 832 2564",
    "sg:postcode":"50595",
    "sg:province":"IA",
    "sg:tags":[
        "chambers",
        "commerce"
    ],
    "wof:name":"Webster City Abi",
    "wof:placetype":"venue"
},
  "geometry": {"coordinates":[-93.82090599999999,42.469367],"type":"Point"}
}