{
  "type": "Feature",
  "properties": {
    "iso:country":"US",
    "sg:address":"1124 1st St SW",
    "sg:city":"Cedar Rapids",
    "sg:classifiers":[
        {
            "category":"Park",
            "type":"Public Place"
        }
    ],
    "sg:phone":"+1 319 364 1713",
    "sg:postcode":"52404",
    "sg:province":"IA",
    "wof:name":"Hubbard Industrial Park",
    "wof:placetype":"venue"
},
  "geometry": {"coordinates":[-91.667047,41.966838],"type":"Point"}
}