{
  "type": "Feature",
  "properties": {
    "addr:full":"713 32nd St West Des Moines IA 50265",
    "addr:housenumber":"713",
    "addr:postcode":"50265",
    "addr:street":"32Nd St",
    "iso:country":"US",
    "sg:address":"713 32nd St",
    "sg:city":"West Des Moines",
    "sg:classifiers":[
        {
            "category":"Building & Trades",
            "subcategory":"Construction",
            "type":"Services"
        }
    ],
    "sg:phone":"+1 515 249 6505",
    "sg:postcode":"50265",
    "sg:province":"IA",
    "sg:tags":[
        "house"
    ],
    "wof:name":"Seiler Construction",
    "wof:placetype":"venue"
},
  "geometry": {"coordinates":[-93.74665400000001,41.582033],"type":"Point"}
}