{
  "type": "Feature",
  "properties": {
    "iso:country":"US",
    "sg:address":"2007 Pine Ave",
    "sg:city":"Fairfield",
    "sg:classifiers":[
        {
            "category":"Farming",
            "subcategory":"Livestock Farm",
            "type":"Manufacturing & Wholesale Goods"
        }
    ],
    "sg:phone":"+1 641 472 0597",
    "sg:postcode":"52556",
    "sg:province":"IA",
    "sg:tags":[
        "animal",
        "general"
    ],
    "wof:name":"Angstead Rentals",
    "wof:placetype":"venue"
},
  "geometry": {"coordinates":[-91.890467,41.015623],"type":"Point"}
}