{
  "type": "Feature",
  "properties": {
    "iso:country":"US",
    "sg:address":"175 Lake St",
    "sg:city":"Lake View",
    "sg:classifiers":[
        {
            "category":"Manufacturing",
            "subcategory":"Tools & Machinery",
            "type":"Manufacturing & Wholesale Goods"
        }
    ],
    "sg:phone":"+1 712 657 3073",
    "sg:postcode":"51450",
    "sg:province":"IA",
    "sg:tags":[
        "equipment",
        "petroleum"
    ],
    "wof:name":"Westmore Industries",
    "wof:placetype":"venue"
},
  "geometry": {"coordinates":[-95.047455,42.305198],"type":"Point"}
}