{
  "type": "Feature",
  "properties": {
    "iso:country":"US",
    "sg:address":"2712 Stange Rd",
    "sg:city":"Ames",
    "sg:classifiers":[
        {
            "category":"Real Estate",
            "subcategory":"Architect",
            "type":"Services"
        }
    ],
    "sg:phone":"+1 515 268 5155",
    "sg:postcode":"50010",
    "sg:province":"IA",
    "sg:website":"www.architectsrld.com",
    "wof:name":"Architects Rudi-Lee-Dreyer",
    "wof:placetype":"venue"
},
  "geometry": {"coordinates":[-93.64466299999999,42.050353],"type":"Point"}
}