{
  "type": "Feature",
  "properties": {
    "addr:full":"1030 Blairs Ferry Rd NE Cedar Rapids IA 52402",
    "addr:housenumber":"1030",
    "addr:postcode":"52402",
    "addr:street":"Blairs Ferry Rd Ne",
    "iso:country":"US",
    "sg:address":"1030 Blairs Ferry Rd NE",
    "sg:city":"Cedar Rapids",
    "sg:classifiers":[
        {
            "category":"Shopping",
            "subcategory":"Department Store",
            "type":"Retail Goods"
        }
    ],
    "sg:phone":"+1 319 393 1600",
    "sg:postcode":"52402",
    "sg:province":"IA",
    "sg:website":"www.target.com",
    "wof:name":"Target",
    "wof:placetype":"venue"
},
  "geometry": {"coordinates":[-91.65216599999999,42.035233],"type":"Point"}
}