{
  "type": "Feature",
  "properties": {
    "iso:country":"US",
    "sg:address":"213 N 3rd St",
    "sg:city":"Burlington",
    "sg:classifiers":[
        {
            "category":"Banks & Credit Unions",
            "subcategory":"Investment Brokerage",
            "type":"Services"
        }
    ],
    "sg:phone":"+1 319 753 6653",
    "sg:postcode":"52601",
    "sg:province":"IA",
    "sg:tags":[
        "consultant",
        "planning",
        "financial"
    ],
    "wof:name":"American Express Financial Adv",
    "wof:placetype":"venue"
},
  "geometry": {"coordinates":[-91.10281000000001,40.809876],"type":"Point"}
}