{
  "type": "Feature",
  "properties": {
    "iso:country":"US",
    "sg:address":"6369 24th Ave",
    "sg:city":"Vinton",
    "sg:classifiers":[
        {
            "category":"Building & Trades",
            "subcategory":"Construction",
            "type":"Services"
        }
    ],
    "sg:phone":"+1 319 472 4092",
    "sg:postcode":"52349",
    "sg:province":"IA",
    "sg:tags":[
        "hanging",
        "contractor"
    ],
    "wof:name":"Barb Becker Pntg & Papering",
    "wof:placetype":"venue"
},
  "geometry": {"coordinates":[-92.029095,42.095524],"type":"Point"}
}