{
  "type": "Feature",
  "properties": {
    "iso:country":"US",
    "sg:address":"701 11th St",
    "sg:city":"Nevada",
    "sg:classifiers":[
        {
            "category":"Organizations",
            "subcategory":"Religious Organization",
            "type":"Services"
        }
    ],
    "sg:phone":"+1 515 382 6509",
    "sg:postcode":"50201",
    "sg:province":"IA",
    "sg:tags":[
        "church"
    ],
    "wof:name":"Memorial Lutheran Church",
    "wof:placetype":"venue"
},
  "geometry": {"coordinates":[-93.444688,42.017452],"type":"Point"}
}