{
  "type": "Feature",
  "properties": {
    "addr:full":"15509 Harbor Dr Spirit Lake IA 51360",
    "addr:housenumber":"15509",
    "addr:postcode":"51360",
    "addr:street":"Harbor Dr",
    "iso:country":"US",
    "sg:address":"15509 Harbor Dr",
    "sg:city":"Spirit Lake",
    "sg:classifiers":[
        {
            "category":"Professional",
            "subcategory":"Management & Consulting",
            "type":"Services"
        }
    ],
    "sg:phone":"+1 712 336 5280",
    "sg:postcode":"51360",
    "sg:province":"IA",
    "sg:tags":[
        "consultant"
    ],
    "wof:name":"Agknowldge Limited",
    "wof:placetype":"venue"
},
  "geometry": {"coordinates":[-95.18207099999999,43.421846],"type":"Point"}
}