{
  "type": "Feature",
  "properties": {
    "addr:full":"502 W North St Zearing IA 50278",
    "addr:housenumber":"502",
    "addr:postcode":"50278",
    "addr:street":"W North St",
    "iso:country":"US",
    "sg:address":"502 W North St",
    "sg:city":"Zearing",
    "sg:classifiers":[
        {
            "category":"Autos & Motor Vehicles",
            "subcategory":"Automobile Sales",
            "type":"Retail Goods"
        }
    ],
    "sg:phone":"+1 641 487 7898",
    "sg:postcode":"50278",
    "sg:province":"IA",
    "sg:tags":[
        "car",
        "dealer"
    ],
    "wof:name":"Scott's Auto Sales & Svc",
    "wof:placetype":"venue"
},
  "geometry": {"coordinates":[-93.30309099999999,42.162617],"type":"Point"}
}