{
  "type": "Feature",
  "properties": {
    "addr:full":"1111 M Ave Milford IA 51351",
    "addr:housenumber":"1111",
    "addr:postcode":"51351",
    "addr:street":"M Ave",
    "iso:country":"US",
    "sg:address":"1111 M Ave",
    "sg:city":"Milford",
    "sg:classifiers":[
        {
            "category":"Professional",
            "subcategory":"Advertising",
            "type":"Services"
        }
    ],
    "sg:phone":"+1 712 338 2153",
    "sg:postcode":"51351",
    "sg:province":"IA",
    "sg:tags":[
        "distribution"
    ],
    "wof:name":"Nationwide Distributing Co",
    "wof:placetype":"venue"
},
  "geometry": {"coordinates":[-95.15285799999999,43.327843],"type":"Point"}
}