{
  "type": "Feature",
  "properties": {
    "addr:full":"501 S 3rd Ave Villisca IA 50864",
    "addr:housenumber":"501",
    "addr:postcode":"50864",
    "addr:street":"S 3Rd Ave",
    "iso:country":"US",
    "sg:address":"501 S 3rd Ave",
    "sg:city":"Villisca",
    "sg:classifiers":[
        {
            "category":"Building & Trades",
            "subcategory":"Construction",
            "type":"Services"
        }
    ],
    "sg:phone":"+1 712 826 3079",
    "sg:postcode":"50864",
    "sg:province":"IA",
    "sg:tags":[
        "concrete",
        "contractor"
    ],
    "wof:name":"Dennis Hammerstrom Poured",
    "wof:placetype":"venue"
},
  "geometry": {"coordinates":[-94.97721799999999,40.927695],"type":"Point"}
}