{
  "type": "Feature",
  "properties": {
    "iso:country":"US",
    "sg:address":"2160 275th Ave",
    "sg:city":"De Witt",
    "sg:phone":"+1 563 659 3617",
    "sg:postcode":"52742",
    "sg:province":"IA",
    "sg:tags":[
        "farm",
        "corn",
        "cash",
        "crop",
        "field",
        "grain",
        "soybean"
    ],
    "wof:name":"Ddj Farming Ltd",
    "wof:placetype":"venue"
},
  "geometry": {"coordinates":[-90.558379,41.862522],"type":"Point"}
}