{
  "type": "Feature",
  "properties": {
    "iso:country":"US",
    "sg:address":"716 W 7th St",
    "sg:city":"Atlantic",
    "sg:classifiers":[
        {
            "category":"Shopping",
            "subcategory":"Used Merchandise",
            "type":"Retail Goods"
        }
    ],
    "sg:phone":"+1 712 243 2575",
    "sg:postcode":"50022",
    "sg:province":"IA",
    "sg:tags":[
        "shop",
        "thrift"
    ],
    "wof:name":"Salvation Army Thrift Store",
    "wof:placetype":"venue"
},
  "geometry": {"coordinates":[-95.022612,41.404133],"type":"Point"}
}