{
  "type": "Feature",
  "properties": {
    "addr:full":"421 Stonehaven Dr Ames IA 50010",
    "addr:housenumber":"421",
    "addr:postcode":"50010",
    "addr:street":"Stonehaven Dr",
    "iso:country":"US",
    "sg:address":"421 Stonehaven Dr",
    "sg:city":"Ames",
    "sg:classifiers":[
        {
            "category":"Real Estate",
            "subcategory":"Real Estate Operator",
            "type":"Services"
        }
    ],
    "sg:phone":"+1 515 232 2021",
    "sg:postcode":"50010",
    "sg:province":"IA",
    "sg:tags":[
        "apartment"
    ],
    "wof:name":"Stonehaven Apartments",
    "wof:placetype":"venue"
},
  "geometry": {"coordinates":[-93.618358,42.01877],"type":"Point"}
}