{
  "type": "Feature",
  "properties": {
    "iso:country":"US",
    "sg:address":"1973 NW 157th St",
    "sg:city":"Clive",
    "sg:classifiers":[
        {
            "category":"Professional",
            "subcategory":"Computer Services",
            "type":"Services"
        }
    ],
    "sg:phone":"+1 515 987 2813",
    "sg:postcode":"50325",
    "sg:province":"IA",
    "sg:tags":[
        "website",
        "design"
    ],
    "wof:name":"Case Innovations",
    "wof:placetype":"venue"
},
  "geometry": {"coordinates":[-93.83457199999999,41.610922],"type":"Point"}
}