{
  "type": "Feature",
  "properties": {
    "addr:full":"221 W High St Toledo IA 52342",
    "addr:housenumber":"221",
    "addr:postcode":"52342",
    "addr:street":"W High St",
    "iso:country":"US",
    "sg:address":"221 W High St",
    "sg:city":"Toledo",
    "sg:classifiers":[
        {
            "category":"Organizations",
            "subcategory":"Non-profit Organization",
            "type":"Services"
        }
    ],
    "sg:phone":"+1 641 484 5353",
    "sg:postcode":"52342",
    "sg:province":"IA",
    "sg:tags":[
        "human"
    ],
    "wof:name":"CASA Program",
    "wof:placetype":"venue"
},
  "geometry": {"coordinates":[-92.581171,41.995703],"type":"Point"}
}