{
  "type": "Feature",
  "properties": {
    "addr:full":"68330 120th St Zearing IA 50278",
    "addr:housenumber":"68330",
    "addr:postcode":"50278",
    "addr:street":"120Th St",
    "iso:country":"US",
    "sg:address":"68330 120th St",
    "sg:city":"Zearing",
    "sg:classifiers":[
        {
            "category":"Retail",
            "subcategory":"Repair Shop",
            "type":"Services"
        }
    ],
    "sg:phone":"+1 641 487 7590",
    "sg:postcode":"50278",
    "sg:province":"IA",
    "sg:tags":[
        "taxidermist"
    ],
    "wof:name":"Don Henderson Taxidermist",
    "wof:placetype":"venue"
},
  "geometry": {"coordinates":[-93.34211000000001,42.180765],"type":"Point"}
}