{
  "type": "Feature",
  "properties": {
    "iso:country":"US",
    "sg:address":"3600 SW 9th St",
    "sg:city":"Des Moines",
    "sg:classifiers":[
        {
            "category":"Professional",
            "type":"Services"
        }
    ],
    "sg:phone":"+1 515 280 6307",
    "sg:postcode":"50315",
    "sg:province":"IA",
    "wof:name":"S W 9th Standard Inc",
    "wof:placetype":"venue"
},
  "geometry": {"coordinates":[-93.625744,41.550913],"type":"Point"}
}