{
  "type": "Feature",
  "properties": {
    "addr:full":"3225 100th St Urbandale IA 50322",
    "addr:housenumber":"3225",
    "addr:postcode":"50322",
    "addr:street":"100Th St",
    "iso:country":"US",
    "sg:address":"3225 100th St",
    "sg:city":"Urbandale",
    "sg:classifiers":[
        {
            "category":"Personal",
            "subcategory":"Beauty Salon",
            "type":"Services"
        }
    ],
    "sg:phone":"+1 515 276 3500",
    "sg:postcode":"50322",
    "sg:province":"IA",
    "wof:name":"Katie Mc Grath Studio",
    "wof:placetype":"venue"
},
  "geometry": {"coordinates":[-93.75577199999999,41.62501],"type":"Point"}
}