{
  "type": "Feature",
  "properties": {
    "iso:country":"US",
    "sg:address":"16139 Contrail Ave",
    "sg:city":"Griswold",
    "sg:phone":"+1 712 778 2187",
    "sg:postcode":"51535",
    "sg:province":"IA",
    "sg:tags":[
        "farm",
        "corn",
        "soybean"
    ],
    "wof:name":"Stanley Krisinger",
    "wof:placetype":"venue"
},
  "geometry": {"coordinates":[-95.18148100000001,41.259771],"type":"Point"}
}