{
  "type": "Feature",
  "properties": {
    "iso:country":"US",
    "sg:address":"19491 240th St",
    "sg:city":"Grundy Center",
    "sg:phone":"+1 319 824 3585",
    "sg:postcode":"50638",
    "sg:province":"IA",
    "sg:tags":[
        "beef",
        "farm",
        "corn",
        "soybean",
        "cattle",
        "feedlot"
    ],
    "wof:name":"Leland Bentley",
    "wof:placetype":"venue"
},
  "geometry": {"coordinates":[-92.885975,42.354026],"type":"Point"}
}