{
  "type": "Feature",
  "properties": {
    "addr:full":"8131 Fillmore St Reasnor IA 50232",
    "addr:housenumber":"8131",
    "addr:postcode":"50232",
    "addr:street":"Fillmore St",
    "iso:country":"US",
    "sg:address":"8131 Fillmore St",
    "sg:city":"Reasnor",
    "sg:classifiers":[
        {
            "category":"Retail",
            "subcategory":"Auto Repair",
            "type":"Services"
        }
    ],
    "sg:phone":"+1 641 793 2244",
    "sg:postcode":"50232",
    "sg:province":"IA",
    "sg:tags":[
        "body",
        "automobile",
        "used"
    ],
    "wof:name":"Pleimas Auto",
    "wof:placetype":"venue"
},
  "geometry": {"coordinates":[-92.945488,41.558025],"type":"Point"}
}