{
  "type": "Feature",
  "properties": {
    "iso:country":"US",
    "sg:address":"1108 E 5th St",
    "sg:city":"Muscatine",
    "sg:classifiers":[
        {
            "category":"Wholesale",
            "subcategory":"Scrap",
            "type":"Manufacturing & Wholesale Goods"
        }
    ],
    "sg:phone":"+1 563 264 3031",
    "sg:postcode":"52761",
    "sg:province":"IA",
    "sg:tags":[
        "metal"
    ],
    "wof:name":"Weikert Iron & Metal Recycling",
    "wof:placetype":"venue"
},
  "geometry": {"coordinates":[-91.03634,41.430151],"type":"Point"}
}