{
  "type": "Feature",
  "properties": {
    "iso:country":"US",
    "sg:address":"2225 220th St",
    "sg:city":"Humboldt",
    "sg:classifiers":[
        {
            "category":"Autos & Motor Vehicles",
            "subcategory":"Automobile Sales",
            "type":"Retail Goods"
        }
    ],
    "sg:phone":"+1 515 332 2764",
    "sg:postcode":"50548",
    "sg:province":"IA",
    "sg:tags":[
        "car",
        "dealer"
    ],
    "wof:name":"Humboldt Motor Sales",
    "wof:placetype":"venue"
},
  "geometry": {"coordinates":[-94.202984,42.731663],"type":"Point"}
}