{
  "type": "Feature",
  "properties": {
    "iso:country":"US",
    "sg:address":"410 S 1st Ave",
    "sg:city":"Danville",
    "sg:classifiers":[
        {
            "category":"Freight",
            "type":"Transportation"
        }
    ],
    "sg:phone":"+1 319 392 4579",
    "sg:postcode":"52623",
    "sg:province":"IA",
    "sg:tags":[
        "operator",
        "local",
        "trucking"
    ],
    "wof:name":"Heald Enterprises Trucking",
    "wof:placetype":"venue"
},
  "geometry": {"coordinates":[-91.31341999999999,40.862286],"type":"Point"}
}