{
  "type": "Feature",
  "properties": {
    "addr:full":"770 Cedar Cross Rd Dubuque IA 52003",
    "addr:housenumber":"770",
    "addr:postcode":"52003",
    "addr:street":"Cedar Cross Rd",
    "iso:country":"US",
    "sg:address":"770 Cedar Cross Rd",
    "sg:city":"Dubuque",
    "sg:classifiers":[
        {
            "category":"Retail",
            "subcategory":"Auto Repair",
            "type":"Services"
        }
    ],
    "sg:phone":"+1 563 582 5725",
    "sg:postcode":"52003",
    "sg:province":"IA",
    "sg:tags":[
        "body",
        "automobile",
        "painting"
    ],
    "wof:name":"Miller Auto Body & Alignment",
    "wof:placetype":"venue"
},
  "geometry": {"coordinates":[-90.712587,42.481721],"type":"Point"}
}