{
  "type": "Feature",
  "properties": {
    "iso:country":"US",
    "sg:address":"1102 Southern Hills Dr",
    "sg:city":"Ames",
    "sg:classifiers":[
        {
            "category":"Freight",
            "type":"Transportation"
        }
    ],
    "sg:phone":"+1 515 232 6605",
    "sg:postcode":"50010",
    "sg:province":"IA",
    "sg:tags":[
        "mover"
    ],
    "sg:website":"www.sevderelocation.com",
    "wof:name":"Sevde Relocation",
    "wof:placetype":"venue"
},
  "geometry": {"coordinates":[-93.627163,42.002361],"type":"Point"}
}