{
  "type": "Feature",
  "properties": {
    "iso:country":"US",
    "sg:address":"110 N Columbus St",
    "sg:city":"West Liberty",
    "sg:classifiers":[
        {
            "category":"Wholesale",
            "subcategory":"Machinery & Supplies",
            "type":"Manufacturing & Wholesale Goods"
        }
    ],
    "sg:phone":"+1 319 627 2011",
    "sg:postcode":"52776",
    "sg:province":"IA",
    "sg:tags":[
        "farm",
        "equipment"
    ],
    "sg:website":"www.hdclineco.com",
    "wof:name":"H D Cline Co",
    "wof:placetype":"venue"
},
  "geometry": {"coordinates":[-91.260732,41.568332],"type":"Point"}
}