{
  "type": "Feature",
  "properties": {
    "iso:country":"US",
    "sg:address":"800 School St",
    "sg:city":"Carlisle",
    "sg:classifiers":[
        {
            "category":"Health Services",
            "subcategory":"Clinic",
            "type":"Services"
        },
        {
            "category":"Shopping",
            "subcategory":"Pharmacy",
            "type":"Retail Goods"
        }
    ],
    "sg:phone":"+1 515 989 3261",
    "sg:postcode":"50047",
    "sg:province":"IA",
    "sg:tags":[
        "medical",
        "drugstore"
    ],
    "sg:website":"www.medicap.com/carlisle",
    "wof:name":"Medicap Pharmacy",
    "wof:placetype":"venue"
},
  "geometry": {"coordinates":[-93.495412,41.498389],"type":"Point"}
}