{
  "type": "Feature",
  "properties": {
    "iso:country":"US",
    "sg:address":"1720 Fuller Rd",
    "sg:city":"West Des Moines",
    "sg:classifiers":[
        {
            "category":"Freight",
            "type":"Transportation"
        }
    ],
    "sg:phone":"+1 515 440 6424",
    "sg:postcode":"50265",
    "sg:province":"IA",
    "sg:tags":[
        "trucking"
    ],
    "wof:name":"Alliance Shippers Inc",
    "wof:placetype":"venue"
},
  "geometry": {"coordinates":[-93.726765,41.565862],"type":"Point"}
}