{
  "type": "Feature",
  "properties": {
    "iso:country":"US",
    "sg:address":"1001 Industrial Park Rd",
    "sg:city":"Oelwein",
    "sg:classifiers":[
        {
            "category":"Building & Trades",
            "subcategory":"Construction",
            "type":"Services"
        },
        {
            "category":"Manufacturing",
            "subcategory":"Tools & Machinery",
            "type":"Manufacturing & Wholesale Goods"
        }
    ],
    "sg:phone":"+1 319 283 7147",
    "sg:postcode":"50662",
    "sg:province":"IA",
    "sg:tags":[
        "fabricator",
        "industrial",
        "metal",
        "mfg"
    ],
    "wof:name":"Blessing Industries Inc",
    "wof:placetype":"venue"
},
  "geometry": {"coordinates":[-91.90900499999999,42.663579],"type":"Point"}
}