{
  "type": "Feature",
  "properties": {
    "iso:country":"US",
    "sg:address":"504 W 4th St",
    "sg:city":"Vinton",
    "sg:classifiers":[
        {
            "category":"Shopping",
            "subcategory":"Used Merchandise",
            "type":"Retail Goods"
        }
    ],
    "sg:phone":"+1 319 472 4946",
    "sg:postcode":"52349",
    "sg:province":"IA",
    "wof:name":"White Haus Antiques",
    "wof:placetype":"venue"
},
  "geometry": {"coordinates":[-92.03121299999999,42.167713],"type":"Point"}
}