{
  "type": "Feature",
  "properties": {
    "iso:country":"US",
    "sg:address":"16282 US Hwy 34",
    "sg:city":"West Burlington",
    "sg:classifiers":[
        {
            "category":"Organizations",
            "subcategory":"Labor Organization",
            "type":"Services"
        }
    ],
    "sg:phone":"+1 319 754 5753",
    "sg:postcode":"52655",
    "sg:province":"IA",
    "wof:name":"International Association-Mach",
    "wof:placetype":"venue"
},
  "geometry": {"coordinates":[-91.24826299999999,40.827178],"type":"Point"}
}