{
  "type": "Feature",
  "properties": {
    "iso:country":"US",
    "sg:address":"1259 550th St",
    "sg:city":"Cherokee",
    "sg:phone":"+1 712 225 4014",
    "sg:postcode":"51012",
    "sg:province":"IA",
    "sg:tags":[
        "farm",
        "corn",
        "soybean"
    ],
    "wof:name":"Robert Werthman",
    "wof:placetype":"venue"
},
  "geometry": {"coordinates":[-95.632177,42.720917],"type":"Point"}
}