{
  "type": "Feature",
  "properties": {
    "iso:country":"US",
    "sg:address":"46299 US Hwy 6",
    "sg:city":"Oakland",
    "sg:classifiers":[
        {
            "category":"Utilities",
            "subcategory":"Natural Gas",
            "type":"Services"
        }
    ],
    "sg:phone":"+1 712 482 6444",
    "sg:postcode":"51560",
    "sg:province":"IA",
    "sg:tags":[
        "company"
    ],
    "wof:name":"Northern Natural Gas Co",
    "wof:placetype":"venue"
},
  "geometry": {"coordinates":[-95.29507,41.318029],"type":"Point"}
}