{
  "type": "Feature",
  "properties": {
    "iso:country":"US",
    "sg:address":"1005 Central Ave SW",
    "sg:city":"Le Mars",
    "sg:phone":"+1 712 546 8019",
    "sg:postcode":"51031",
    "sg:province":"IA",
    "sg:tags":[
        "hog",
        "beef",
        "f",
        "farm",
        "corn",
        "soybean",
        "cattle",
        "feedlot"
    ],
    "wof:name":"Edward Dempster",
    "wof:placetype":"venue"
},
  "geometry": {"coordinates":[-96.166552,42.781211],"type":"Point"}
}