{
  "type": "Feature",
  "properties": {
    "addr:full":"716 S Jefferson Ave Mason City IA 50401",
    "addr:housenumber":"716",
    "addr:postcode":"50401",
    "addr:street":"S Jefferson Ave",
    "iso:country":"US",
    "sg:address":"716 S Jefferson Ave",
    "sg:city":"Mason City",
    "sg:classifiers":[
        {
            "category":"Home & Garden",
            "subcategory":"Building Materials",
            "type":"Retail Goods"
        }
    ],
    "sg:phone":"+1 641 424 4001",
    "sg:postcode":"50401",
    "sg:province":"IA",
    "sg:tags":[
        "lumber"
    ],
    "wof:name":"Home Lumber & Builders Inc",
    "wof:placetype":"venue"
},
  "geometry": {"coordinates":[-93.206073,43.144595],"type":"Point"}
}