{
  "type": "Feature",
  "properties": {
    "addr:full":"2720 1st Ave NE Cedar Rapids IA 52402",
    "addr:housenumber":"2720",
    "addr:postcode":"52402",
    "addr:street":"1St Ave Ne",
    "iso:country":"US",
    "sg:address":"2720 1st Ave NE",
    "sg:city":"Cedar Rapids",
    "sg:classifiers":[
        {
            "category":"Professional",
            "subcategory":"Lawyer & Legal Services",
            "type":"Services"
        }
    ],
    "sg:phone":"+1 319 366 7331",
    "sg:postcode":"52402",
    "sg:province":"IA",
    "sg:tags":[
        "personal",
        "injury"
    ],
    "wof:name":"Wallrichs Brenda K Lwyr",
    "wof:placetype":"venue"
},
  "geometry": {"coordinates":[-91.63649700000001,42.003799],"type":"Point"}
}