{
  "type": "Feature",
  "properties": {
    "iso:country":"US",
    "sg:address":"29776 US Hwy 34",
    "sg:city":"Malvern",
    "sg:phone":"+1 712 624 8761",
    "sg:postcode":"51551",
    "sg:province":"IA",
    "sg:tags":[
        "farm",
        "corn",
        "soybean"
    ],
    "wof:name":"Emmett Stephens",
    "wof:placetype":"venue"
},
  "geometry": {"coordinates":[-95.614318,41.030608],"type":"Point"}
}