{
  "type": "Feature",
  "properties": {
    "addr:full":"496 Raven Ave Geneva IA 50633",
    "addr:housenumber":"496",
    "addr:postcode":"50633",
    "addr:street":"Raven Ave",
    "iso:country":"US",
    "sg:address":"496 Raven Ave",
    "sg:city":"Geneva",
    "sg:classifiers":[
        {
            "category":"Organizations",
            "subcategory":"Religious Organization",
            "type":"Services"
        }
    ],
    "sg:phone":"+1 641 847 3157",
    "sg:postcode":"50633",
    "sg:province":"IA",
    "wof:name":"St Peters United Church Christ",
    "wof:placetype":"venue"
},
  "geometry": {"coordinates":[-93.164286,42.614154],"type":"Point"}
}