{
  "type": "Feature",
  "properties": {
    "addr:full":"973 Hawkeye Ave SW Le Mars IA 51031",
    "addr:housenumber":"973",
    "addr:postcode":"51031",
    "addr:street":"Hawkeye Ave Sw",
    "iso:country":"US",
    "sg:address":"973 Hawkeye Ave SW",
    "sg:city":"Le Mars",
    "sg:classifiers":[
        {
            "category":"Shopping",
            "subcategory":"Used Merchandise",
            "type":"Retail Goods"
        }
    ],
    "sg:phone":"+1 712 546 1438",
    "sg:postcode":"51031",
    "sg:province":"IA",
    "sg:tags":[
        "shop",
        "thrift"
    ],
    "wof:name":"Goodwill Industries",
    "wof:placetype":"venue"
},
  "geometry": {"coordinates":[-96.179828,42.782877],"type":"Point"}
}