{
  "type": "Feature",
  "properties": {
    "addr:full":"102 2nd Ave Coralville IA 52241",
    "addr:housenumber":"102",
    "addr:postcode":"52241",
    "addr:street":"2Nd Ave",
    "iso:country":"US",
    "sg:address":"102 2nd Ave",
    "sg:city":"Coralville",
    "sg:classifiers":[
        {
            "category":"Restaurant",
            "type":"Food & Drink"
        }
    ],
    "sg:menulink":"http://www.allmenus.com/ia/west-lucas/249256-el-dorado/menu/",
    "sg:phone":"+1 319 688 5237",
    "sg:postcode":"52241",
    "sg:province":"IA",
    "sg:tags":[
        "mexican"
    ],
    "wof:name":"El Dorado",
    "wof:placetype":"venue"
},
  "geometry": {"coordinates":[-91.56866100000001,41.668279],"type":"Point"}
}