{
  "type": "Feature",
  "properties": {
    "iso:country":"US",
    "sg:address":"3691 230th St",
    "sg:city":"Lytton",
    "sg:phone":"+1 712 466 2687",
    "sg:postcode":"50561",
    "sg:province":"IA",
    "sg:tags":[
        "farm",
        "corn",
        "soybean"
    ],
    "wof:name":"Earl Helmbrecht",
    "wof:placetype":"venue"
},
  "geometry": {"coordinates":[-94.86302000000001,42.457438],"type":"Point"}
}