{
  "type": "Feature",
  "properties": {
    "addr:full":"1133 S 22nd St Fort Dodge IA 50501",
    "addr:housenumber":"1133",
    "addr:postcode":"50501",
    "addr:street":"S 22Nd St",
    "iso:country":"US",
    "sg:address":"1133 S 22nd St",
    "sg:city":"Fort Dodge",
    "sg:classifiers":[
        {
            "category":"Restaurant",
            "type":"Food & Drink"
        },
        {
            "category":"Food & Beverages",
            "subcategory":"Groceries & Convenience Stores",
            "type":"Retail Goods"
        }
    ],
    "sg:menulink":"http://www.allmenus.com/ia/fort-dodge/225904-caseys-general-store/menu/",
    "sg:phone":"+1 515 955 5576",
    "sg:postcode":"50501",
    "sg:province":"IA",
    "sg:tags":[
        "american",
        "pizza"
    ],
    "wof:name":"Casey's General Store",
    "wof:placetype":"venue"
},
  "geometry": {"coordinates":[-94.167872,42.492467],"type":"Point"}
}