{
  "type": "Feature",
  "properties": {
    "addr:full":"3500 2nd Ave Des Moines IA 50313",
    "addr:housenumber":"3500",
    "addr:postcode":"50313",
    "addr:street":"2Nd Ave",
    "iso:country":"US",
    "sg:address":"3500 2nd Ave",
    "sg:city":"Des Moines",
    "sg:classifiers":[
        {
            "category":"Social Services",
            "type":"Services"
        }
    ],
    "sg:phone":"+1 515 283 2465",
    "sg:postcode":"50313",
    "sg:province":"IA",
    "sg:tags":[
        "organization",
        "welfare"
    ],
    "wof:name":"HRS Erase Inc",
    "wof:placetype":"venue"
},
  "geometry": {"coordinates":[-93.620019,41.62681],"type":"Point"}
}