{
  "type": "Feature",
  "properties": {
    "addr:full":"1394 Twixt Town Rd Marion IA 52302",
    "addr:housenumber":"1394",
    "addr:postcode":"52302",
    "addr:street":"Twixt Town Rd",
    "iso:country":"US",
    "sg:address":"1394 Twixt Town Rd",
    "sg:city":"Marion",
    "sg:classifiers":[
        {
            "category":"Restaurant",
            "type":"Food & Drink"
        }
    ],
    "sg:phone":"+1 319 377 2160",
    "sg:postcode":"52302",
    "sg:province":"IA",
    "wof:name":"Hungry Hobo",
    "wof:placetype":"venue"
},
  "geometry": {"coordinates":[-91.618242,42.027803],"type":"Point"}
}