{
  "type": "Feature",
  "properties": {
    "iso:country":"US",
    "sg:address":"202 S 9th St",
    "sg:city":"Adel",
    "sg:classifiers":[
        {
            "category":"Shopping",
            "subcategory":"Gifts & Souvenirs",
            "type":"Retail Goods"
        }
    ],
    "sg:phone":"+1 515 993 2034",
    "sg:postcode":"50003",
    "sg:province":"IA",
    "sg:tags":[
        "shop"
    ],
    "wof:name":"Atherton House",
    "wof:placetype":"venue"
},
  "geometry": {"coordinates":[-94.01879099999999,41.616268],"type":"Point"}
}