{
  "type": "Feature",
  "properties": {
    "addr:full":"3100 10th Ave Marion IA 52302",
    "addr:housenumber":"3100",
    "addr:postcode":"52302",
    "addr:street":"10Th Ave",
    "iso:country":"US",
    "sg:address":"3100 10th Ave",
    "sg:city":"Marion",
    "sg:classifiers":[
        {
            "category":"Social Services",
            "type":"Services"
        }
    ],
    "sg:phone":"+1 319 377 7361",
    "sg:postcode":"52302",
    "sg:province":"IA",
    "sg:tags":[
        "organization",
        "welfare"
    ],
    "sg:website":"www.crmetroymca.org",
    "wof:name":"YMCA",
    "wof:placetype":"venue"
},
  "geometry": {"coordinates":[-91.57705,42.035993],"type":"Point"}
}