{
  "type": "Feature",
  "properties": {
    "addr:full":"1605 21st St Des Moines IA 50311",
    "addr:housenumber":"1605",
    "addr:postcode":"50311",
    "addr:street":"21St St",
    "iso:country":"US",
    "sg:address":"1605 21st St",
    "sg:city":"Des Moines",
    "sg:classifiers":[
        {
            "category":"Shopping",
            "subcategory":"Computers & Home Electronics",
            "type":"Retail Goods"
        }
    ],
    "sg:phone":"+1 515 440 2881",
    "sg:postcode":"50311",
    "sg:province":"IA",
    "sg:tags":[
        "equipment",
        "satellite",
        "system"
    ],
    "wof:name":"Crystal Clear Communications",
    "wof:placetype":"venue"
},
  "geometry": {"coordinates":[-93.645804,41.607504],"type":"Point"}
}