{
  "type": "Feature",
  "properties": {
    "iso:country":"US",
    "sg:address":"506 West St",
    "sg:city":"Alden",
    "sg:classifiers":[
        {
            "category":"Organizations",
            "subcategory":"Community Association",
            "type":"Services"
        }
    ],
    "sg:phone":"+1 515 859 7681",
    "sg:postcode":"50006",
    "sg:province":"IA",
    "sg:tags":[
        "military"
    ],
    "wof:name":"American Legion",
    "wof:placetype":"venue"
},
  "geometry": {"coordinates":[-93.38065899999999,42.519238],"type":"Point"}
}