{
  "type": "Feature",
  "properties": {
    "iso:country":"US",
    "sg:address":"409 Elm St",
    "sg:city":"Riceville",
    "sg:classifiers":[
        {
            "category":"Professional",
            "subcategory":"Business Services",
            "type":"Services"
        }
    ],
    "sg:phone":"+1 641 985 2150",
    "sg:postcode":"50466",
    "sg:province":"IA",
    "sg:tags":[
        "auctioneer"
    ],
    "wof:name":"J Dean Eastman",
    "wof:placetype":"venue"
},
  "geometry": {"coordinates":[-92.549605,43.362026],"type":"Point"}
}