{
  "type": "Feature",
  "properties": {
    "iso:country":"US",
    "sg:address":"301 E Oak St",
    "sg:city":"Lawton",
    "sg:classifiers":[
        {
            "category":"Building & Trades",
            "subcategory":"Construction",
            "type":"Services"
        }
    ],
    "sg:phone":"+1 712 944 5228",
    "sg:postcode":"51030",
    "sg:province":"IA",
    "sg:tags":[
        "concrete",
        "contractor"
    ],
    "wof:name":"Concrete Complete",
    "wof:placetype":"venue"
},
  "geometry": {"coordinates":[-96.181033,42.480764],"type":"Point"}
}