{
  "type": "Feature",
  "properties": {
    "addr:full":"2730 Ford St Ames IA 50010",
    "addr:housenumber":"2730",
    "addr:postcode":"50010",
    "addr:street":"Ford St",
    "iso:country":"US",
    "sg:address":"2730 Ford St",
    "sg:city":"Ames",
    "sg:classifiers":[
        {
            "category":"Professional",
            "subcategory":"Engineering",
            "type":"Services"
        }
    ],
    "sg:phone":"+1 515 233 6100",
    "sg:postcode":"50010",
    "sg:province":"IA",
    "sg:tags":[
        "engineer"
    ],
    "wof:name":"Bolton & Menk Inc",
    "wof:placetype":"venue"
},
  "geometry": {"coordinates":[-93.57624199999999,42.02673],"type":"Point"}
}