{
  "type": "Feature",
  "properties": {
    "iso:country":"US",
    "sg:address":"5140 340th St",
    "sg:city":"Archer",
    "sg:phone":"+1 712 324 2067",
    "sg:postcode":"51231",
    "sg:province":"IA",
    "sg:tags":[
        "farm",
        "corn",
        "soybean"
    ],
    "wof:name":"Feekes John",
    "wof:placetype":"venue"
},
  "geometry": {"coordinates":[-95.776601,43.156972],"type":"Point"}
}