{
  "type": "Feature",
  "properties": {
    "iso:country":"US",
    "sg:address":"1816 Beaver Ave",
    "sg:city":"Des Moines",
    "sg:classifiers":[
        {
            "category":"Health Services",
            "subcategory":"Doctor",
            "type":"Services"
        }
    ],
    "sg:phone":"+1 515 277 7786",
    "sg:postcode":"50310",
    "sg:province":"IA",
    "sg:tags":[
        "dentist"
    ],
    "wof:name":"Mosier Dental Assoc",
    "wof:placetype":"venue"
},
  "geometry": {"coordinates":[-93.673089,41.611214],"type":"Point"}
}