{
  "type": "Feature",
  "properties": {
    "iso:country":"US",
    "sg:address":"1211 Wiley Blvd SW",
    "sg:city":"Cedar Rapids",
    "sg:classifiers":[
        {
            "category":"Professional",
            "type":"Services"
        },
        {
            "category":"Retail",
            "subcategory":"Event Space",
            "type":"Services"
        }
    ],
    "sg:phone":"+1 319 366 0701",
    "sg:postcode":"52404",
    "sg:province":"IA",
    "sg:tags":[
        "venue",
        "caterer"
    ],
    "sg:website":"www.dostalcatering.com",
    "wof:name":"Dostal Catering Service",
    "wof:placetype":"venue"
},
  "geometry": {"coordinates":[-91.725776,41.965589],"type":"Point"}
}