{
  "type": "Feature",
  "properties": {
    "iso:country":"US",
    "sg:address":"2053 Schiller St",
    "sg:city":"Dubuque",
    "sg:classifiers":[
        {
            "category":"Building & Trades",
            "subcategory":"Construction",
            "type":"Services"
        }
    ],
    "sg:phone":"+1 563 582 5657",
    "sg:postcode":"52001",
    "sg:province":"IA",
    "sg:tags":[
        "wallcoverings-installation",
        "wallpaper",
        "painting",
        "contractor"
    ],
    "wof:name":"Platinum Painting",
    "wof:placetype":"venue"
},
  "geometry": {"coordinates":[-90.661681,42.518786],"type":"Point"}
}