{
  "type": "Feature",
  "properties": {
    "iso:country":"US",
    "sg:address":"227 Rosebud Ave",
    "sg:city":"Waterloo",
    "sg:classifiers":[
        {
            "category":"Shopping",
            "type":"Retail Goods"
        }
    ],
    "sg:phone":"+1 319 234 5299",
    "sg:postcode":"50701",
    "sg:province":"IA",
    "sg:tags":[
        "merchandise"
    ],
    "wof:name":"Rosebuds Silk Creations",
    "wof:placetype":"venue"
},
  "geometry": {"coordinates":[-92.358222,42.477005],"type":"Point"}
}