{
  "type": "Feature",
  "properties": {
    "addr:full":"116 W Main St Lacona IA 50139",
    "addr:housenumber":"116",
    "addr:postcode":"50139",
    "addr:street":"W Main St",
    "iso:country":"US",
    "sg:address":"116 W Main St",
    "sg:city":"Lacona",
    "sg:classifiers":[
        {
            "category":"Retail",
            "subcategory":"Auto Repair",
            "type":"Services"
        }
    ],
    "sg:phone":"+1 641 534 3702",
    "sg:postcode":"50139",
    "sg:province":"IA",
    "sg:tags":[
        "body",
        "automobile",
        "painting"
    ],
    "wof:name":"Seuferers Body Shop",
    "wof:placetype":"venue"
},
  "geometry": {"coordinates":[-93.385532,41.189478],"type":"Point"}
}