{
  "type": "Feature",
  "properties": {
    "iso:country":"US",
    "sg:address":"1717 Grant St",
    "sg:city":"Bettendorf",
    "sg:classifiers":[
        {
            "category":"Retail",
            "subcategory":"Auto Repair",
            "type":"Services"
        }
    ],
    "sg:phone":"+1 563 355 6610",
    "sg:postcode":"52722",
    "sg:province":"IA",
    "sg:tags":[
        "muffler",
        "exhaust",
        "system"
    ],
    "wof:name":"Bettendorf Muffler Inc",
    "wof:placetype":"venue"
},
  "geometry": {"coordinates":[-90.507794,41.526196],"type":"Point"}
}