{
  "type": "Feature",
  "properties": {
    "addr:full":"412 Highland Ave Iowa City IA 52240",
    "addr:housenumber":"412",
    "addr:postcode":"52240",
    "addr:street":"Highland Ave",
    "iso:country":"US",
    "sg:address":"412 Highland Ave",
    "sg:city":"Iowa City",
    "sg:classifiers":[
        {
            "category":"Health Services",
            "subcategory":"Chiropractor",
            "type":"Services"
        }
    ],
    "sg:phone":"+1 319 337 3856",
    "sg:postcode":"52240",
    "sg:province":"IA",
    "wof:name":"Creating Health Chiropractic",
    "wof:placetype":"venue"
},
  "geometry": {"coordinates":[-91.52844899999999,41.645876],"type":"Point"}
}