{
  "type": "Feature",
  "properties": {
    "iso:country":"US",
    "sg:address":"104 North St",
    "sg:city":"Williamsburg",
    "sg:classifiers":[
        {
            "category":"Building & Trades",
            "subcategory":"Cleaning & Sanitation",
            "type":"Services"
        }
    ],
    "sg:phone":"+1 319 668 1557",
    "sg:postcode":"52361",
    "sg:province":"IA",
    "sg:tags":[
        "janitorial"
    ],
    "wof:name":"Mary K Cochran",
    "wof:placetype":"venue"
},
  "geometry": {"coordinates":[-92.00863099999999,41.664761],"type":"Point"}
}