{
  "type": "Feature",
  "properties": {
    "iso:country":"US",
    "sg:address":"4209 Fleur Dr",
    "sg:city":"Des Moines",
    "sg:classifiers":[
        {
            "category":"Personal",
            "subcategory":"Tanning Parlor",
            "type":"Services"
        }
    ],
    "sg:phone":"+1 515 285 2500",
    "sg:postcode":"50321",
    "sg:province":"IA",
    "sg:tags":[
        "salon"
    ],
    "sg:website":"www.4visualimpact.com",
    "wof:name":"Visual Impact Hair & Tanning",
    "wof:placetype":"venue"
},
  "geometry": {"coordinates":[-93.64487699999999,41.544683],"type":"Point"}
}