{
  "type": "Feature",
  "properties": {
    "iso:country":"US",
    "sg:address":"3418 Merle Hay Rd",
    "sg:city":"Des Moines",
    "sg:classifiers":[
        {
            "category":"Personal",
            "subcategory":"Beauty Salon",
            "type":"Services"
        }
    ],
    "sg:phone":"+1 515 270 6602",
    "sg:postcode":"50310",
    "sg:province":"IA",
    "wof:name":"Great Clips",
    "wof:placetype":"venue"
},
  "geometry": {"coordinates":[-93.69781999999999,41.626686],"type":"Point"}
}