{
  "type": "Feature",
  "properties": {
    "iso:country":"US",
    "sg:address":"1441 270th St",
    "sg:city":"Letts",
    "sg:classifiers":[
        {
            "category":"Freight",
            "type":"Transportation"
        }
    ],
    "sg:phone":"+1 319 726 3204",
    "sg:postcode":"52754",
    "sg:province":"IA",
    "sg:tags":[
        "trucking"
    ],
    "wof:name":"B & D Transport Inc",
    "wof:placetype":"venue"
},
  "geometry": {"coordinates":[-91.285135,41.350239],"type":"Point"}
}