{
  "type": "Feature",
  "properties": {
    "iso:country":"US",
    "sg:address":"2569 State St",
    "sg:city":"Bettendorf",
    "sg:classifiers":[
        {
            "category":"Home & Garden",
            "subcategory":"Furniture",
            "type":"Retail Goods"
        }
    ],
    "sg:phone":"+1 563 355 3864",
    "sg:postcode":"52722",
    "sg:province":"IA",
    "sg:tags":[
        "cabinet"
    ],
    "wof:name":"Milltown Wood Products Inc",
    "wof:placetype":"venue"
},
  "geometry": {"coordinates":[-90.500016,41.525494],"type":"Point"}
}