{
  "type": "Feature",
  "properties": {
    "iso:country":"US",
    "sg:address":"4334 N Brady St",
    "sg:city":"Davenport",
    "sg:classifiers":[
        {
            "category":"Restaurant",
            "type":"Food & Drink"
        }
    ],
    "sg:phone":"+1 563 386 2475",
    "sg:postcode":"52806",
    "sg:province":"IA",
    "wof:name":"Rudy's Tacos",
    "wof:placetype":"venue"
},
  "geometry": {"coordinates":[-90.567696,41.564801],"type":"Point"}
}