{
  "type": "Feature",
  "properties": {
    "addr:city":"Toledo",
    "addr:full":"200 N Broadway St Toledo, Ia 52342",
    "addr:house_number":"200",
    "addr:housenumber":"200",
    "addr:phone":"+1 641-484-6767",
    "addr:postcode":"52342",
    "addr:road":"N Broadway St",
    "addr:state":"IA",
    "addr:street":"N Broadway St",
    "iso:country":"US",
    "sg:address":"200 N Broadway St",
    "sg:city":"Toledo",
    "sg:classifiers":[
        {
            "category":"Education",
            "subcategory":"Library",
            "type":"Public Place"
        }
    ],
    "sg:phone":"+1 641 484 6767",
    "sg:postcode":"52342",
    "sg:province":"IA",
    "wof:name":"Tama County Historical Society",
    "wof:placetype":"venue"
},
  "geometry": {"coordinates":[-92.5782,41.99683],"type":"Point"}
}