{
  "type": "Feature",
  "properties": {
    "iso:country":"US",
    "sg:address":"200 N Broadway St",
    "sg:city":"Toledo",
    "sg:classifiers":[
        {
            "category":"Education",
            "subcategory":"Library",
            "type":"Public Place"
        }
    ],
    "sg:phone":"+1 641 484 6767",
    "sg:postcode":"52342",
    "sg:province":"IA",
    "wof:name":"Tama County Historical Society",
    "wof:placetype":"venue"
},
  "geometry": {"coordinates":[-92.578265,41.998177],"type":"Point"}
}