{
  "type": "Feature",
  "properties": {
    "iso:country":"US",
    "sg:address":"708 US Hwy 69",
    "sg:city":"Huxley",
    "sg:classifiers":[
        {
            "category":"Professional",
            "subcategory":"Lawyer & Legal Services",
            "type":"Services"
        }
    ],
    "sg:phone":"+1 515 597 2594",
    "sg:postcode":"50124",
    "sg:province":"IA",
    "sg:tags":[
        "attorney"
    ],
    "wof:name":"Lewis Law Firm",
    "wof:placetype":"venue"
},
  "geometry": {"coordinates":[-93.60537100000001,41.899979],"type":"Point"}
}