{
  "type": "Feature",
  "properties": {
    "iso:country":"US",
    "sg:address":"3098 I Ave",
    "sg:city":"Toledo",
    "sg:classifiers":[
        {
            "category":"Organizations",
            "subcategory":"Religious Organization",
            "type":"Services"
        }
    ],
    "sg:phone":"+1 641 484 3451",
    "sg:postcode":"52342",
    "sg:province":"IA",
    "wof:name":"Grace Believers Church",
    "wof:placetype":"venue"
},
  "geometry": {"coordinates":[-92.59997799999999,41.993009],"type":"Point"}
}