{
  "type": "Feature",
  "properties": {
    "addr:full":"101 4th St Batavia IA 52533",
    "addr:housenumber":"101",
    "addr:postcode":"52533",
    "addr:street":"4Th St",
    "iso:country":"US",
    "sg:address":"101 4th St",
    "sg:city":"Batavia",
    "sg:classifiers":[
        {
            "category":"Retail",
            "subcategory":"Repair Shop",
            "type":"Services"
        }
    ],
    "sg:phone":"+1 641 662 2722",
    "sg:postcode":"52533",
    "sg:province":"IA",
    "wof:name":"Cartwright Gifts & Crafts",
    "wof:placetype":"venue"
},
  "geometry": {"coordinates":[-92.168486,41.002607],"type":"Point"}
}