{
  "type": "Feature",
  "properties": {
    "addr:full":"302 S Carroll St Rock Rapids IA 51246",
    "addr:housenumber":"302",
    "addr:postcode":"51246",
    "addr:street":"S Carroll St",
    "iso:country":"US",
    "sg:address":"302 S Carroll St",
    "sg:city":"Rock Rapids",
    "sg:classifiers":[
        {
            "category":"Organizations",
            "subcategory":"Religious Organization",
            "type":"Services"
        }
    ],
    "sg:phone":"+1 712 472 3473",
    "sg:postcode":"51246",
    "sg:province":"IA",
    "sg:tags":[
        "church"
    ],
    "wof:name":"United Methodist Church",
    "wof:placetype":"venue"
},
  "geometry": {"coordinates":[-96.172411,43.429747],"type":"Point"}
}