{
  "type": "Feature",
  "properties": {
    "iso:country":"US",
    "sg:address":"758 22nd Ave",
    "sg:city":"Coralville",
    "sg:classifiers":[
        {
            "category":"Home & Garden",
            "subcategory":"Building Materials",
            "type":"Retail Goods"
        }
    ],
    "sg:phone":"+1 319 338 0089",
    "sg:postcode":"52241",
    "sg:province":"IA",
    "sg:tags":[
        "lumber"
    ],
    "sg:website":"www.gilcrestjewett.com",
    "wof:name":"Gilcrest Jewett Lumber Co",
    "wof:placetype":"venue"
},
  "geometry": {"coordinates":[-91.597246,41.678472],"type":"Point"}
}