{
  "type": "Feature",
  "properties": {
    "addr:full":"755 Maplewood Dr Coralville IA 52241",
    "addr:housenumber":"755",
    "addr:postcode":"52241",
    "addr:street":"Maplewood Dr",
    "iso:country":"US",
    "sg:address":"755 Maplewood Dr",
    "sg:city":"Coralville",
    "sg:classifiers":[
        {
            "category":"Professional",
            "type":"Services"
        }
    ],
    "sg:phone":"+1 319 354 9177",
    "sg:postcode":"52241",
    "sg:province":"IA",
    "wof:name":"Codebarn Co",
    "wof:placetype":"venue"
},
  "geometry": {"coordinates":[-91.57893900000001,41.711308],"type":"Point"}
}