{
  "type": "Feature",
  "properties": {
    "iso:country":"US",
    "sg:address":"2912 Beaver Ave",
    "sg:city":"Des Moines",
    "sg:classifiers":[
        {
            "category":"Professional",
            "subcategory":"Lawyer & Legal Services",
            "type":"Services"
        }
    ],
    "sg:phone":"+1 515 271 5730",
    "sg:postcode":"50310",
    "sg:province":"IA",
    "sg:tags":[
        "attorney"
    ],
    "wof:name":"Benzoni Law Offices",
    "wof:placetype":"venue"
},
  "geometry": {"coordinates":[-93.673951,41.622195],"type":"Point"}
}