{
  "type": "Feature",
  "properties": {
    "iso:country":"US",
    "sg:address":"720 Commercial St",
    "sg:city":"Stratford",
    "sg:classifiers":[
        {
            "category":"Government",
            "subcategory":"Office",
            "type":"Public Place"
        }
    ],
    "sg:phone":"+1 515 838 2452",
    "sg:postcode":"50249",
    "sg:province":"IA",
    "sg:tags":[
        "executive"
    ],
    "wof:name":"Hamilton County Maintenance Sp",
    "wof:placetype":"venue"
},
  "geometry": {"coordinates":[-93.930162,42.269223],"type":"Point"}
}