{
  "type": "Feature",
  "properties": {
    "iso:country":"US",
    "sg:address":"412 N Court St",
    "sg:city":"Fairfield",
    "sg:classifiers":[
        {
            "category":"Professional",
            "subcategory":"Management & Consulting",
            "type":"Services"
        }
    ],
    "sg:phone":"+1 641 472 8432",
    "sg:postcode":"52556",
    "sg:province":"IA",
    "sg:tags":[
        "public",
        "relations"
    ],
    "wof:name":"Tarun Inc",
    "wof:placetype":"venue"
},
  "geometry": {"coordinates":[-91.962518,41.011426],"type":"Point"}
}