{
  "type": "Feature",
  "properties": {
    "iso:country":"US",
    "sg:address":"1511 18th St",
    "sg:city":"Spirit Lake",
    "sg:classifiers":[
        {
            "category":"Restaurant",
            "type":"Food & Drink"
        }
    ],
    "sg:phone":"+1 712 336 9956",
    "sg:postcode":"51360",
    "sg:province":"IA",
    "wof:name":"Remington's Restaurant & Lnge",
    "wof:placetype":"venue"
},
  "geometry": {"coordinates":[-95.11077400000001,43.422516],"type":"Point"}
}