{
  "type": "Feature",
  "properties": {
    "addr:full":"3273 Dubuque St NE Iowa City IA 52240",
    "addr:housenumber":"3273",
    "addr:postcode":"52240",
    "addr:street":"Dubuque St Ne",
    "iso:country":"US",
    "sg:address":"3273 Dubuque St NE",
    "sg:city":"Iowa City",
    "sg:classifiers":[
        {
            "category":"Mining & Drilling",
            "type":"Manufacturing & Wholesale Goods"
        }
    ],
    "sg:phone":"+1 319 338 1184",
    "sg:postcode":"52240",
    "sg:province":"IA",
    "sg:tags":[
        "stone"
    ],
    "sg:website":"www.riverproducts.com",
    "wof:name":"River Products Co",
    "wof:placetype":"venue"
},
  "geometry": {"coordinates":[-91.547256,41.692097],"type":"Point"}
}