{
  "type": "Feature",
  "properties": {
    "iso:country":"US",
    "sg:address":"1004 19th St",
    "sg:city":"Spirit Lake",
    "sg:classifiers":[
        {
            "category":"Building & Trades",
            "subcategory":"Construction",
            "type":"Services"
        }
    ],
    "sg:phone":"+1 712 336 3222",
    "sg:postcode":"51360",
    "sg:province":"IA",
    "sg:tags":[
        "grading",
        "contractor"
    ],
    "wof:name":"Dickinson Road Maintenance",
    "wof:placetype":"venue"
},
  "geometry": {"coordinates":[-95.106224,43.421781],"type":"Point"}
}