{
  "type": "Feature",
  "properties": {
    "addr:full":"3445 Lafayette Rd Evansdale IA 50707",
    "addr:housenumber":"3445",
    "addr:postcode":"50707",
    "addr:street":"Rd",
    "iso:country":"US",
    "sg:address":"3445 Lafayette Rd",
    "sg:city":"Evansdale",
    "sg:classifiers":[
        {
            "category":"Shopping",
            "subcategory":"Tobacco",
            "type":"Retail Goods"
        }
    ],
    "sg:phone":"+1 319 287 4708",
    "sg:postcode":"50707",
    "sg:province":"IA",
    "sg:tags":[
        "cigarette",
        "cigar",
        "dealer"
    ],
    "wof:name":"Evansdale Pipe & Tobacco",
    "wof:placetype":"venue"
},
  "geometry": {"coordinates":[-92.293418,42.479184],"type":"Point"}
}