{
  "type": "Feature",
  "properties": {
    "iso:country":"US",
    "sg:address":"606 Diagonal St",
    "sg:city":"Algona",
    "sg:classifiers":[
        {
            "category":"Utilities",
            "subcategory":"Refuse",
            "type":"Services"
        },
        {
            "category":"Wholesale",
            "subcategory":"Scrap",
            "type":"Manufacturing & Wholesale Goods"
        }
    ],
    "sg:phone":"+1 515 295 7187",
    "sg:postcode":"50511",
    "sg:province":"IA",
    "sg:tags":[
        "recycling",
        "center",
        "system"
    ],
    "wof:name":"J J 's Can Redemption",
    "wof:placetype":"venue"
},
  "geometry": {"coordinates":[-94.221951,43.074368],"type":"Point"}
}