{
  "type": "Feature",
  "properties": {
    "iso:country":"US",
    "sg:address":"812 S Summit St",
    "sg:city":"Iowa City",
    "sg:classifiers":[
        {
            "category":"Food & Beverages",
            "subcategory":"Bakery",
            "type":"Retail Goods"
        }
    ],
    "sg:phone":"+1 319 338 5000",
    "sg:postcode":"52240",
    "sg:province":"IA",
    "sg:tags":[
        "baker"
    ],
    "wof:name":"Deluxe Cakes & Pastries",
    "wof:placetype":"venue"
},
  "geometry": {"coordinates":[-91.520965,41.651583],"type":"Point"}
}