{
  "type": "Feature",
  "properties": {
    "iso:country":"US",
    "sg:address":"1405 250th St",
    "sg:city":"Moorland",
    "sg:classifiers":[
        {
            "category":"Farming",
            "subcategory":"Farm",
            "type":"Manufacturing & Wholesale Goods"
        }
    ],
    "sg:phone":"+1 515 549 3700",
    "sg:postcode":"50566",
    "sg:province":"IA",
    "sg:tags":[
        "crop",
        "general"
    ],
    "wof:name":"Alan Croonquist",
    "wof:placetype":"venue"
},
  "geometry": {"coordinates":[-94.319721,42.427002],"type":"Point"}
}