{
  "type": "Feature",
  "properties": {
    "iso:country":"US",
    "sg:address":"107 W 5th St",
    "sg:city":"Riceville",
    "sg:classifiers":[
        {
            "category":"Wholesale",
            "subcategory":"Farm Supplies",
            "type":"Manufacturing & Wholesale Goods"
        }
    ],
    "sg:phone":"+1 641 985 2136",
    "sg:postcode":"50466",
    "sg:province":"IA",
    "sg:tags":[
        "livestock"
    ],
    "wof:name":"Hormel",
    "wof:placetype":"venue"
},
  "geometry": {"coordinates":[-92.555868,43.35968],"type":"Point"}
}