{
  "type": "Feature",
  "properties": {
    "iso:country":"US",
    "sg:address":"1703 C Ave",
    "sg:city":"Vinton",
    "sg:classifiers":[
        {
            "category":"Recreation",
            "type":"Entertainment"
        }
    ],
    "sg:phone":"+1 319 472 5168",
    "sg:postcode":"52349",
    "sg:province":"IA",
    "sg:tags":[
        "skating",
        "rink"
    ],
    "wof:name":"Vinton Skate & Activity Ctr",
    "wof:placetype":"venue"
},
  "geometry": {"coordinates":[-92.02803,42.155771],"type":"Point"}
}