{
  "type": "Feature",
  "properties": {
    "iso:country":"US",
    "sg:address":"2565 24th Ave",
    "sg:city":"Marion",
    "sg:classifiers":[
        {
            "category":"Building & Trades",
            "subcategory":"Plumbing",
            "type":"Services"
        }
    ],
    "sg:phone":"+1 319 447 9129",
    "sg:postcode":"52302",
    "sg:province":"IA",
    "sg:tags":[
        "contractor"
    ],
    "wof:name":"Rabbit Rooter",
    "wof:placetype":"venue"
},
  "geometry": {"coordinates":[-91.586444,42.046524],"type":"Point"}
}