{
  "type": "Feature",
  "properties": {
    "addr:full":"1905 Binford Ave State Center IA 50247",
    "addr:housenumber":"1905",
    "addr:postcode":"50247",
    "addr:street":"Binford Ave",
    "iso:country":"US",
    "sg:address":"1905 Binford Ave",
    "sg:city":"State Center",
    "sg:phone":"+1 641 477 8387",
    "sg:postcode":"50247",
    "sg:province":"IA",
    "sg:tags":[
        "farm",
        "soybean"
    ],
    "wof:name":"Caryl Kuhlman Farm",
    "wof:placetype":"venue"
},
  "geometry": {"coordinates":[-93.214786,42.076904],"type":"Point"}
}