{
  "type": "Feature",
  "properties": {
    "iso:country":"US",
    "sg:address":"534 7th St",
    "sg:city":"Jesup",
    "sg:classifiers":[
        {
            "category":"Retail",
            "subcategory":"Laundry & Dry Cleaning",
            "type":"Services"
        }
    ],
    "sg:phone":"+1 319 827 6466",
    "sg:postcode":"50648",
    "sg:province":"IA",
    "wof:name":"Brass Button",
    "wof:placetype":"venue"
},
  "geometry": {"coordinates":[-92.06220500000001,42.478168],"type":"Point"}
}