{
  "type": "Feature",
  "properties": {
    "iso:country":"US",
    "sg:address":"501 Market St",
    "sg:city":"Audubon",
    "sg:classifiers":[
        {
            "category":"Shopping",
            "subcategory":"Bicycles & Sporting Goods",
            "type":"Retail Goods"
        }
    ],
    "sg:phone":"+1 712 563 2346",
    "sg:postcode":"50025",
    "sg:province":"IA",
    "sg:tags":[
        "gun",
        "gunsmith"
    ],
    "wof:name":"Gun Shop",
    "wof:placetype":"venue"
},
  "geometry": {"coordinates":[-94.933145,41.718773],"type":"Point"}
}