{
  "type": "Feature",
  "properties": {
    "addr:full":"201 4th St Castana IA 51010",
    "addr:housenumber":"201",
    "addr:postcode":"51010",
    "addr:street":"4Th St",
    "iso:country":"US",
    "sg:address":"201 4th St",
    "sg:city":"Castana",
    "sg:classifiers":[
        {
            "category":"Professional",
            "type":"Services"
        }
    ],
    "sg:phone":"+1 712 353 6698",
    "sg:postcode":"51010",
    "sg:province":"IA",
    "sg:tags":[
        "establishment"
    ],
    "wof:name":"Taasco LLC",
    "wof:placetype":"venue"
},
  "geometry": {"coordinates":[-95.907449,42.073197],"type":"Point"}
}