{
  "type": "Feature",
  "properties": {
    "addr:full":"4330 E 14th St Des Moines IA 50313",
    "addr:housenumber":"4330",
    "addr:postcode":"50313",
    "addr:street":"E 14Th St",
    "iso:country":"US",
    "sg:address":"4330 E 14th St",
    "sg:city":"Des Moines",
    "sg:classifiers":[
        {
            "category":"Building & Trades",
            "subcategory":"Plumbing",
            "type":"Services"
        }
    ],
    "sg:phone":"+1 515 266 3117",
    "sg:postcode":"50313",
    "sg:province":"IA",
    "sg:tags":[
        "mechanical",
        "contractor"
    ],
    "wof:name":"Accurate Mechanical Co",
    "wof:placetype":"venue"
},
  "geometry": {"coordinates":[-93.600534,41.639863],"type":"Point"}
}