{
  "type": "Feature",
  "properties": {
    "iso:country":"US",
    "sg:address":"220 Lewis Blvd",
    "sg:city":"Sioux City",
    "sg:classifiers":[
        {
            "category":"Shopping",
            "subcategory":"Clothing, Apparel, & Fashions",
            "type":"Retail Goods"
        }
    ],
    "sg:phone":"+1 712 224 2700",
    "sg:postcode":"51101",
    "sg:province":"IA",
    "sg:tags":[
        "alteration"
    ],
    "wof:name":"Threaded Needle",
    "wof:placetype":"venue"
},
  "geometry": {"coordinates":[-96.378967,42.491451],"type":"Point"}
}