{
  "type": "Feature",
  "properties": {
    "iso:country":"US",
    "sg:address":"718 Market St",
    "sg:city":"Harlan",
    "sg:classifiers":[
        {
            "category":"Real Estate",
            "subcategory":"Real Estate Agent",
            "type":"Services"
        }
    ],
    "sg:phone":"+1 712 755 2018",
    "sg:postcode":"51537",
    "sg:province":"IA",
    "wof:name":"Plumb Real Estate",
    "wof:placetype":"venue"
},
  "geometry": {"coordinates":[-95.31935900000001,41.658624],"type":"Point"}
}