{
  "type": "Feature",
  "properties": {
    "addr:full":"117 S East St Laurens IA 50554",
    "addr:housenumber":"117",
    "addr:postcode":"50554",
    "addr:street":"S East St",
    "iso:country":"US",
    "sg:address":"117 S East St",
    "sg:city":"Laurens",
    "sg:classifiers":[
        {
            "category":"Professional",
            "type":"Services"
        }
    ],
    "sg:phone":"+1 712 841 6557",
    "sg:postcode":"50554",
    "sg:province":"IA",
    "sg:tags":[
        "establishment"
    ],
    "wof:name":"Fuchs Construction",
    "wof:placetype":"venue"
},
  "geometry": {"coordinates":[-94.84141700000001,42.846303],"type":"Point"}
}