{
  "type": "Feature",
  "properties": {
    "iso:country":"US",
    "sg:address":"1314 Early St",
    "sg:city":"Sac City",
    "sg:classifiers":[
        {
            "category":"Wholesale",
            "subcategory":"Scrap",
            "type":"Manufacturing & Wholesale Goods"
        }
    ],
    "sg:phone":"+1 712 662 7272",
    "sg:postcode":"50583",
    "sg:province":"IA",
    "sg:tags":[
        "recycling",
        "center"
    ],
    "wof:name":"Sac Area Recycling Ctr",
    "wof:placetype":"venue"
},
  "geometry": {"coordinates":[-95.000435,42.423847],"type":"Point"}
}