{
  "type": "Feature",
  "properties": {
    "iso:country":"US",
    "sg:address":"1001 S Hazel St",
    "sg:city":"Glenwood",
    "sg:classifiers":[
        {
            "category":"Arts & Performance",
            "subcategory":"Theater",
            "type":"Entertainment"
        }
    ],
    "sg:phone":"+1 712 527 2998",
    "sg:postcode":"51534",
    "sg:province":"IA",
    "wof:name":"Omaha Theater Ballet",
    "wof:placetype":"venue"
},
  "geometry": {"coordinates":[-95.745278,41.03682],"type":"Point"}
}