{
  "type": "Feature",
  "properties": {
    "addr:full":"115 Washington St Decorah IA 52101",
    "addr:housenumber":"115",
    "addr:postcode":"52101",
    "addr:street":"Washington St",
    "iso:country":"US",
    "sg:address":"115 Washington St",
    "sg:city":"Decorah",
    "sg:classifiers":[
        {
            "category":"Banks & Credit Unions",
            "subcategory":"Bank",
            "type":"Services"
        }
    ],
    "sg:phone":"+1 563 382 9661",
    "sg:postcode":"52101",
    "sg:province":"IA",
    "sg:website":"www.decorahbank.com",
    "wof:name":"Decorah Bank & Trust Co",
    "wof:placetype":"venue"
},
  "geometry": {"coordinates":[-91.786011,43.304037],"type":"Point"}
}