{
  "type": "Feature",
  "properties": {
    "addr:full":"2720 1st Ave NE Ste 208 Cedar Rapids IA 52402",
    "addr:housenumber":"2720",
    "addr:postcode":"52402",
    "addr:street":"1St Ave Ne Ste 208",
    "iso:country":"US",
    "sg:address":"2720 1st Ave NE Ste 208",
    "sg:city":"Cedar Rapids",
    "sg:classifiers":[
        {
            "category":"Professional",
            "subcategory":"Accounting & Tax Preparation",
            "type":"Services"
        }
    ],
    "sg:phone":"+1 319 362 3856",
    "sg:postcode":"52402",
    "sg:province":"IA",
    "sg:tags":[
        "accountant"
    ],
    "wof:name":"Koch Platner & Reed PC",
    "wof:placetype":"venue"
},
  "geometry": {"coordinates":[-91.634829,42.003832],"type":"Point"}
}