{
  "type": "Feature",
  "properties": {
    "iso:country":"US",
    "sg:address":"1125 Lincoln St",
    "sg:city":"Cedar Falls",
    "sg:classifiers":[
        {
            "category":"Building & Trades",
            "subcategory":"Construction",
            "type":"Services"
        }
    ],
    "sg:phone":"+1 319 277 7503",
    "sg:postcode":"50613",
    "sg:province":"IA",
    "sg:tags":[
        "excavating",
        "contractor"
    ],
    "sg:website":"www.k-welectric.com",
    "wof:name":"KWS Inc",
    "wof:placetype":"venue"
},
  "geometry": {"coordinates":[-92.428164,42.541323],"type":"Point"}
}