{
  "type": "Feature",
  "properties": {
    "addr:full":"51826 Whippoorwill Rd Walnut IA 51577",
    "addr:housenumber":"51826",
    "addr:postcode":"51577",
    "addr:street":"Whippoorwill Rd",
    "iso:country":"US",
    "sg:address":"51826 Whippoorwill Rd",
    "sg:city":"Walnut",
    "sg:classifiers":[
        {
            "category":"Farming",
            "subcategory":"Livestock Farm",
            "type":"Manufacturing & Wholesale Goods"
        }
    ],
    "sg:phone":"+1 712 784 3769",
    "sg:postcode":"51577",
    "sg:province":"IA",
    "sg:tags":[
        "hog",
        "or",
        "feedlot"
    ],
    "wof:name":"J P Six Farm",
    "wof:placetype":"venue"
},
  "geometry": {"coordinates":[-95.200423,41.490649],"type":"Point"}
}