{
  "type": "Feature",
  "properties": {
    "addr:full":"15699 175th St Elma IA 50628",
    "addr:housenumber":"15699",
    "addr:postcode":"50628",
    "addr:street":"175Th St",
    "iso:country":"US",
    "sg:address":"15699 175th St",
    "sg:city":"Elma",
    "sg:classifiers":[
        {
            "category":"Wholesale",
            "subcategory":"Machinery & Supplies",
            "type":"Manufacturing & Wholesale Goods"
        }
    ],
    "sg:phone":"+1 641 393 2696",
    "sg:postcode":"50628",
    "sg:province":"IA",
    "sg:tags":[
        "trailer"
    ],
    "sg:website":"www.ssduraline.com",
    "wof:name":"S & S Dura Line",
    "wof:placetype":"venue"
},
  "geometry": {"coordinates":[-92.265103,43.26235],"type":"Point"}
}