{
  "type": "Feature",
  "properties": {
    "addr:full":"540 Oneida St Storm Lake IA 50588",
    "addr:housenumber":"540",
    "addr:postcode":"50588",
    "addr:street":"Oneida St",
    "iso:country":"US",
    "sg:address":"540 Oneida St",
    "sg:city":"Storm Lake",
    "sg:classifiers":[
        {
            "category":"Professional",
            "subcategory":"Business Services",
            "type":"Services"
        }
    ],
    "sg:phone":"+1 712 732 5506",
    "sg:postcode":"50588",
    "sg:province":"IA",
    "sg:tags":[
        "interior",
        "consultant",
        "design",
        "decorator"
    ],
    "wof:name":"3 D Interiors",
    "wof:placetype":"venue"
},
  "geometry": {"coordinates":[-95.195566,42.643615],"type":"Point"}
}