{
  "type": "Feature",
  "properties": {
    "iso:country":"US",
    "sg:address":"1909 170th St",
    "sg:city":"Lawton",
    "sg:classifiers":[
        {
            "category":"Professional",
            "subcategory":"Engineering",
            "type":"Services"
        }
    ],
    "sg:phone":"+1 712 944 5108",
    "sg:postcode":"51030",
    "sg:province":"IA",
    "wof:name":"Calhoun Engineering",
    "wof:placetype":"venue"
},
  "geometry": {"coordinates":[-96.223011,42.460438],"type":"Point"}
}