{
  "type": "Feature",
  "properties": {
    "iso:country":"US",
    "sg:address":"822 Central Ave",
    "sg:city":"Fort Dodge",
    "sg:classifiers":[
        {
            "category":"Professional",
            "subcategory":"Lawyer & Legal Services",
            "type":"Services"
        }
    ],
    "sg:phone":"+1 515 573 2181",
    "sg:postcode":"50501",
    "sg:province":"IA",
    "sg:tags":[
        "attorney"
    ],
    "wof:name":"Johnson Erb Bice Kramer Good",
    "wof:placetype":"venue"
},
  "geometry": {"coordinates":[-94.186334,42.505281],"type":"Point"}
}