{
  "type": "Feature",
  "properties": {
    "iso:country":"US",
    "sg:address":"5272 200th St",
    "sg:city":"Sibley",
    "sg:classifiers":[
        {
            "category":"Farming",
            "subcategory":"Dairy Farm",
            "type":"Manufacturing & Wholesale Goods"
        }
    ],
    "sg:phone":"+1 712 754 3291",
    "sg:postcode":"51249",
    "sg:province":"IA",
    "wof:name":"Sibley Dairy LLP",
    "wof:placetype":"venue"
},
  "geometry": {"coordinates":[-95.74470599999999,43.360562],"type":"Point"}
}