{
  "type": "Feature",
  "properties": {
    "iso:country":"US",
    "sg:address":"2404 Chamberlain St",
    "sg:city":"Ames",
    "sg:classifiers":[
        {
            "category":"Retail",
            "subcategory":"Laundry & Dry Cleaning",
            "type":"Services"
        }
    ],
    "sg:phone":"+1 515 292 5110",
    "sg:postcode":"50014",
    "sg:province":"IA",
    "wof:name":"Custom Sewing By Gail",
    "wof:placetype":"venue"
},
  "geometry": {"coordinates":[-93.650048,42.021387],"type":"Point"}
}