{
  "type": "Feature",
  "properties": {
    "addr:full":"3002 Twin City Dr Council Bluffs IA 51501",
    "addr:housenumber":"3002",
    "addr:postcode":"51501",
    "addr:street":"Twin City Dr",
    "iso:country":"US",
    "sg:address":"3002 Twin City Dr",
    "sg:city":"Council Bluffs",
    "sg:classifiers":[
        {
            "category":"Building & Trades",
            "subcategory":"Landscaping Services",
            "type":"Services"
        }
    ],
    "sg:phone":"+1 712 366 1270",
    "sg:postcode":"51501",
    "sg:province":"IA",
    "wof:name":"Green Side Up",
    "wof:placetype":"venue"
},
  "geometry": {"coordinates":[-95.89255,41.218697],"type":"Point"}
}