{
  "type": "Feature",
  "properties": {
    "iso:country":"US",
    "sg:address":"5550 NE 22nd St",
    "sg:city":"Des Moines",
    "sg:classifiers":[
        {
            "category":"Professional",
            "subcategory":"Management & Consulting",
            "type":"Services"
        }
    ],
    "sg:phone":"+1 515 266 5173",
    "sg:postcode":"50313",
    "sg:province":"IA",
    "sg:tags":[
        "consultant",
        "business"
    ],
    "sg:website":"www.rasmussengroup.com",
    "wof:name":"Rasmussen Group Inc",
    "wof:placetype":"venue"
},
  "geometry": {"coordinates":[-93.581326,41.662642],"type":"Point"}
}