{
  "type": "Feature",
  "properties": {
    "iso:country":"US",
    "sg:address":"102 N Lake St",
    "sg:city":"Lake Mills",
    "sg:classifiers":[
        {
            "category":"Food & Beverages",
            "subcategory":"Groceries & Convenience Stores",
            "type":"Retail Goods"
        }
    ],
    "sg:phone":"+1 641 592 0015",
    "sg:postcode":"50450",
    "sg:province":"IA",
    "wof:name":"Corner Stop",
    "wof:placetype":"venue"
},
  "geometry": {"coordinates":[-93.532402,43.420181],"type":"Point"}
}