{
  "type": "Feature",
  "properties": {
    "iso:country":"US",
    "sg:address":"112 E Robinson St",
    "sg:city":"Knoxville",
    "sg:classifiers":[
        {
            "category":"Home & Garden",
            "subcategory":"Home Furnishings",
            "type":"Retail Goods"
        }
    ],
    "sg:phone":"+1 641 842 7485",
    "sg:postcode":"50138",
    "sg:province":"IA",
    "wof:name":"Cottage Comforts",
    "wof:placetype":"venue"
},
  "geometry": {"coordinates":[-93.097731,41.317952],"type":"Point"}
}