{
  "type": "Feature",
  "properties": {
    "iso:country":"US",
    "sg:address":"208 Broadway St",
    "sg:city":"Larchwood",
    "sg:classifiers":[
        {
            "category":"Bars & Pubs",
            "type":"Food & Drink"
        }
    ],
    "sg:phone":"+1 712 477 2737",
    "sg:postcode":"51241",
    "sg:province":"IA",
    "wof:name":"B & B Bar",
    "wof:placetype":"venue"
},
  "geometry": {"coordinates":[-96.43412499999999,43.45383],"type":"Point"}
}