{
  "type": "Feature",
  "properties": {
    "addr:full":"601 W Depot Ave Fairfield IA 52556",
    "addr:housenumber":"601",
    "addr:postcode":"52556",
    "addr:street":"W Depot Ave",
    "iso:country":"US",
    "sg:address":"601 W Depot Ave",
    "sg:city":"Fairfield",
    "sg:classifiers":[
        {
            "category":"Shopping",
            "type":"Retail Goods"
        }
    ],
    "sg:phone":"+1 641 472 4104",
    "sg:postcode":"52556",
    "sg:province":"IA",
    "sg:tags":[
        "monument"
    ],
    "sg:website":"www.whitneymonument.com",
    "wof:name":"Whitney Monument Works",
    "wof:placetype":"venue"
},
  "geometry": {"coordinates":[-91.97120099999999,41.010993],"type":"Point"}
}