{
  "type": "Feature",
  "properties": {
    "iso:country":"US",
    "sg:address":"148 S Central Ave",
    "sg:city":"Hartley",
    "sg:classifiers":[
        {
            "category":"Professional",
            "subcategory":"Lawyer & Legal Services",
            "type":"Services"
        }
    ],
    "sg:phone":"+1 712 728 2033",
    "sg:postcode":"51346",
    "sg:province":"IA",
    "sg:tags":[
        "attorney"
    ],
    "wof:name":"Sease Law Office",
    "wof:placetype":"venue"
},
  "geometry": {"coordinates":[-95.476935,43.179351],"type":"Point"}
}