{
  "type": "Feature",
  "properties": {
    "iso:country":"US",
    "sg:address":"1716 9th Ave",
    "sg:city":"Camanche",
    "sg:classifiers":[
        {
            "category":"Personal",
            "subcategory":"Beauty Salon",
            "type":"Services"
        }
    ],
    "sg:phone":"+1 563 259 1360",
    "sg:postcode":"52730",
    "sg:province":"IA",
    "wof:name":"Char's Shop",
    "wof:placetype":"venue"
},
  "geometry": {"coordinates":[-90.26982,41.795211],"type":"Point"}
}