{
  "type": "Feature",
  "properties": {
    "iso:country":"US",
    "sg:address":"407 Elm St",
    "sg:city":"Rolfe",
    "sg:phone":"+1 712 848 3917",
    "sg:postcode":"50581",
    "sg:province":"IA",
    "sg:tags":[
        "farm",
        "corn",
        "soybean"
    ],
    "wof:name":"Elaine Bennett",
    "wof:placetype":"venue"
},
  "geometry": {"coordinates":[-94.527126,42.814771],"type":"Point"}
}