{
  "type": "Feature",
  "properties": {
    "addr:full":"2907 Mulberry Ave Muscatine IA 52761",
    "addr:housenumber":"2907",
    "addr:postcode":"52761",
    "addr:street":"Mulberry Ave",
    "iso:country":"US",
    "sg:address":"2907 Mulberry Ave",
    "sg:city":"Muscatine",
    "sg:classifiers":[
        {
            "category":"Real Estate",
            "subcategory":"Developer",
            "type":"Services"
        }
    ],
    "sg:phone":"+1 563 263 8842",
    "sg:postcode":"52761",
    "sg:province":"IA",
    "sg:tags":[
        "cemetery",
        "merchandise"
    ],
    "wof:name":"Memorial Park Cemetery",
    "wof:placetype":"venue"
},
  "geometry": {"coordinates":[-91.068552,41.443769],"type":"Point"}
}