{
  "type": "Feature",
  "properties": {
    "addr:full":"126 Sherman St Dysart IA 52224",
    "addr:housenumber":"126",
    "addr:postcode":"52224",
    "addr:street":"Sherman St",
    "iso:country":"US",
    "sg:address":"126 Sherman St",
    "sg:city":"Dysart",
    "sg:classifiers":[
        {
            "category":"Retail",
            "subcategory":"Car Wash",
            "type":"Services"
        }
    ],
    "sg:phone":"+1 319 476 4041",
    "sg:postcode":"52224",
    "sg:province":"IA",
    "sg:tags":[
        "polishing",
        "washing"
    ],
    "wof:name":"Kavalier Car Wash & Kavalier",
    "wof:placetype":"venue"
},
  "geometry": {"coordinates":[-92.299999,42.166686],"type":"Point"}
}