{
  "type": "Feature",
  "properties": {
    "iso:country":"US",
    "sg:address":"212 Lafayette Ave",
    "sg:city":"Story City",
    "sg:classifiers":[
        {
            "category":"Health Services",
            "subcategory":"Nursing And Care Facility",
            "type":"Services"
        }
    ],
    "sg:phone":"+1 515 733 6500",
    "sg:postcode":"50248",
    "sg:province":"IA",
    "sg:tags":[
        "intermediate"
    ],
    "wof:name":"Timberland Village Senior Inde",
    "wof:placetype":"venue"
},
  "geometry": {"coordinates":[-93.592449,42.182522],"type":"Point"}
}