{
  "type": "Feature",
  "properties": {
    "iso:country":"US",
    "sg:address":"1107 A Ave W",
    "sg:city":"Oskaloosa",
    "sg:classifiers":[
        {
            "category":"Restaurant",
            "type":"Food & Drink"
        }
    ],
    "sg:phone":"+1 641 673 0474",
    "sg:postcode":"52577",
    "sg:province":"IA",
    "wof:name":"Happy Joe's Pizza & Ice Cream",
    "wof:placetype":"venue"
},
  "geometry": {"coordinates":[-92.657945,41.2963],"type":"Point"}
}