{
  "type": "Feature",
  "properties": {
    "addr:full":"30 N Frederick Ave Oelwein IA 50662",
    "addr:housenumber":"30",
    "addr:postcode":"50662",
    "addr:street":"N Frederick Ave",
    "iso:country":"US",
    "sg:address":"30 N Frederick Ave",
    "sg:city":"Oelwein",
    "sg:classifiers":[
        {
            "category":"Professional",
            "subcategory":"Business Services",
            "type":"Services"
        }
    ],
    "sg:phone":"+1 319 283 1006",
    "sg:postcode":"50662",
    "sg:province":"IA",
    "wof:name":"Advanced Data-Comm Inc",
    "wof:placetype":"venue"
},
  "geometry": {"coordinates":[-91.91343999999999,42.678866],"type":"Point"}
}