{
  "type": "Feature",
  "properties": {
    "addr:full":"1444 Glendale Blvd Sioux City IA 51105",
    "addr:housenumber":"1444",
    "addr:postcode":"51105",
    "addr:street":"Glendale Blvd",
    "iso:country":"US",
    "sg:address":"1444 Glendale Blvd",
    "sg:city":"Sioux City",
    "sg:phone":"+1 712 255 6218",
    "sg:postcode":"51105",
    "sg:province":"IA",
    "sg:tags":[
        "farm",
        "corn",
        "soybean"
    ],
    "wof:name":"Herbert Payne",
    "wof:placetype":"venue"
},
  "geometry": {"coordinates":[-96.369876,42.50609],"type":"Point"}
}