{
  "type": "Feature",
  "properties": {
    "addr:full":"203 River Ave S Belmond IA 50421",
    "addr:housenumber":"203",
    "addr:postcode":"50421",
    "addr:street":"River Ave S",
    "iso:country":"US",
    "sg:address":"203 River Ave S",
    "sg:city":"Belmond",
    "sg:classifiers":[
        {
            "category":"Restaurant",
            "type":"Food & Drink"
        }
    ],
    "sg:menulink":"http://www.allmenus.com/ia/pleasant/32060-pizza-ranch/menu/",
    "sg:phone":"+1 641 444 4696",
    "sg:postcode":"50421",
    "sg:province":"IA",
    "sg:tags":[
        "american",
        "pizza"
    ],
    "wof:name":"Pizza Ranch",
    "wof:placetype":"venue"
},
  "geometry": {"coordinates":[-93.616834,42.844824],"type":"Point"}
}