{
  "type": "Feature",
  "properties": {
    "addr:full":"2448 150th St West Point IA 52656",
    "addr:housenumber":"2448",
    "addr:postcode":"52656",
    "addr:street":"150Th St",
    "iso:country":"US",
    "sg:address":"2448 150th St",
    "sg:city":"West Point",
    "sg:classifiers":[
        {
            "category":"Farming",
            "subcategory":"Farm",
            "type":"Manufacturing & Wholesale Goods"
        }
    ],
    "sg:phone":"+1 319 837 6652",
    "sg:postcode":"52656",
    "sg:province":"IA",
    "sg:tags":[
        "crop",
        "general"
    ],
    "wof:name":"Jay D Fullenkamp",
    "wof:placetype":"venue"
},
  "geometry": {"coordinates":[-91.439739,40.740354],"type":"Point"}
}