{
  "type": "Feature",
  "properties": {
    "addr:full":"4013 14th St Des Moines IA 50313",
    "addr:housenumber":"4013",
    "addr:postcode":"50313",
    "addr:street":"14Th St",
    "iso:country":"US",
    "sg:address":"4013 14th St",
    "sg:city":"Des Moines",
    "sg:classifiers":[
        {
            "category":"Shopping",
            "subcategory":"Gifts & Souvenirs",
            "type":"Retail Goods"
        }
    ],
    "sg:phone":"+1 515 282 9728",
    "sg:postcode":"50313",
    "sg:province":"IA",
    "wof:name":"ABRA Craft Mall",
    "wof:placetype":"venue"
},
  "geometry": {"coordinates":[-93.636797,41.634729],"type":"Point"}
}