{
  "type": "Feature",
  "properties": {
    "iso:country":"US",
    "sg:address":"104 W 1st St",
    "sg:city":"Long Grove",
    "sg:classifiers":[
        {
            "category":"Government",
            "subcategory":"Office",
            "type":"Public Place"
        }
    ],
    "sg:phone":"+1 563 285 7201",
    "sg:postcode":"52758",
    "sg:province":"IA",
    "sg:tags":[
        "village"
    ],
    "wof:name":"Maintenance Building",
    "wof:placetype":"venue"
},
  "geometry": {"coordinates":[-90.445483,41.742787],"type":"Point"}
}