{
  "type": "Feature",
  "properties": {
    "iso:country":"US",
    "sg:address":"3412 1st Ave NE",
    "sg:city":"Cedar Rapids",
    "sg:classifiers":[
        {
            "category":"Food & Beverages",
            "subcategory":"Liquor & Beverages",
            "type":"Retail Goods"
        }
    ],
    "sg:phone":"+1 319 298 9463",
    "sg:postcode":"52402",
    "sg:province":"IA",
    "sg:tags":[
        "beer",
        "spirit",
        "wine"
    ],
    "wof:name":"1st Avenue Wine House",
    "wof:placetype":"venue"
},
  "geometry": {"coordinates":[-91.6371,42.0098],"type":"Point"}
}