{
  "type": "Feature",
  "properties": {
    "iso:country":"US",
    "sg:address":"2405 21st St",
    "sg:city":"Emmetsburg",
    "sg:classifiers":[
        {
            "category":"Health Services",
            "subcategory":"Nursing And Care Facility",
            "type":"Services"
        }
    ],
    "sg:phone":"+1 712 852 4266",
    "sg:postcode":"50536",
    "sg:province":"IA",
    "sg:tags":[
        "home",
        "convalescent"
    ],
    "sg:website":"www.abcmcorp.com",
    "wof:name":"Emmetsburg Care Ctr",
    "wof:placetype":"venue"
},
  "geometry": {"coordinates":[-94.682106,43.101236],"type":"Point"}
}