{
  "type": "Feature",
  "properties": {
    "iso:country":"US",
    "sg:address":"4525 Sheridan St",
    "sg:city":"Davenport",
    "sg:classifiers":[
        {
            "category":"Shopping",
            "subcategory":"Computers & Home Electronics",
            "type":"Retail Goods"
        }
    ],
    "sg:phone":"+1 563 388 0210",
    "sg:postcode":"52806",
    "sg:province":"IA",
    "sg:tags":[
        "television",
        "radio"
    ],
    "wof:name":"Fleet Disposal TV",
    "wof:placetype":"venue"
},
  "geometry": {"coordinates":[-90.574786,41.5667],"type":"Point"}
}