{
  "type": "Feature",
  "properties": {
    "iso:country":"US",
    "sg:address":"606 NW Chapel Dr",
    "sg:city":"Ankeny",
    "sg:classifiers":[
        {
            "category":"Building & Trades",
            "subcategory":"Construction",
            "type":"Services"
        }
    ],
    "sg:phone":"+1 515 965 5690",
    "sg:postcode":"50023",
    "sg:province":"IA",
    "sg:tags":[
        "siding",
        "contractor"
    ],
    "sg:website":"www.burchbetterhomes.com",
    "wof:name":"Burch Better Homes",
    "wof:placetype":"venue"
},
  "geometry": {"coordinates":[-93.620486,41.738482],"type":"Point"}
}