{
  "type": "Feature",
  "properties": {
    "addr:full":"2725 Ingersoll Ave Des Moines IA 50312",
    "addr:housenumber":"2725",
    "addr:postcode":"50312",
    "addr:street":"Ingersoll Ave",
    "iso:country":"US",
    "sg:address":"2725 Ingersoll Ave",
    "sg:city":"Des Moines",
    "sg:classifiers":[
        {
            "category":"Shopping",
            "subcategory":"Clothing, Apparel, & Fashions",
            "type":"Retail Goods"
        }
    ],
    "sg:phone":"+1 515 283 2725",
    "sg:postcode":"50312",
    "sg:province":"IA",
    "sg:tags":[
        "wear",
        "accessory"
    ],
    "wof:name":"Silver Fox Corporation",
    "wof:placetype":"venue"
},
  "geometry": {"coordinates":[-93.653357,41.585773],"type":"Point"}
}