{
  "type": "Feature",
  "properties": {
    "iso:country":"US",
    "sg:address":"2836 Robins Rd",
    "sg:city":"Robins",
    "sg:classifiers":[
        {
            "category":"Real Estate",
            "subcategory":"Real Estate Operator",
            "type":"Services"
        }
    ],
    "sg:phone":"+1 319 393 0496",
    "sg:postcode":"52328",
    "sg:province":"IA",
    "sg:tags":[
        "property",
        "lessor"
    ],
    "wof:name":"Robert Hampton Farm",
    "wof:placetype":"venue"
},
  "geometry": {"coordinates":[-91.673343,42.067752],"type":"Point"}
}