{
  "type": "Feature",
  "properties": {
    "addr:full":"2415 18th St Bettendorf IA 52722",
    "addr:housenumber":"2415",
    "addr:postcode":"52722",
    "addr:street":"18Th St",
    "iso:country":"US",
    "sg:address":"2415 18th St",
    "sg:city":"Bettendorf",
    "sg:classifiers":[
        {
            "category":"Professional",
            "subcategory":"Computer Services",
            "type":"Services"
        }
    ],
    "sg:phone":"+1 563 355 8074",
    "sg:postcode":"52722",
    "sg:province":"IA",
    "sg:tags":[
        "website",
        "design"
    ],
    "sg:website":"www.gah.com",
    "wof:name":"Gackle Anderson Henningsen Inc",
    "wof:placetype":"venue"
},
  "geometry": {"coordinates":[-90.504965,41.548293],"type":"Point"}
}