{
  "type": "Feature",
  "properties": {
    "iso:country":"US",
    "sg:address":"11110 Aurora Ave",
    "sg:city":"Urbandale",
    "sg:classifiers":[
        {
            "category":"Professional",
            "subcategory":"Computer Services",
            "type":"Services"
        }
    ],
    "sg:phone":"+1 515 270 1114",
    "sg:postcode":"50322",
    "sg:province":"IA",
    "sg:tags":[
        "internet"
    ],
    "wof:name":"Ipoint Communications Inc",
    "wof:placetype":"venue"
},
  "geometry": {"coordinates":[-93.771676,41.637772],"type":"Point"}
}