{
  "type": "Feature",
  "properties": {
    "addr:full":"2911 7th Ave S Fort Dodge IA 50501",
    "addr:housenumber":"2911",
    "addr:postcode":"50501",
    "addr:street":"7Th Ave S",
    "iso:country":"US",
    "sg:address":"2911 7th Ave S",
    "sg:city":"Fort Dodge",
    "sg:classifiers":[
        {
            "category":"Home & Garden",
            "subcategory":"Furniture",
            "type":"Retail Goods"
        }
    ],
    "sg:phone":"+1 515 955 5337",
    "sg:postcode":"50501",
    "sg:province":"IA",
    "sg:tags":[
        "top",
        "counter"
    ],
    "wof:name":"Midwest Hardwood Floors",
    "wof:placetype":"venue"
},
  "geometry": {"coordinates":[-94.157927,42.499174],"type":"Point"}
}