{
  "type": "Feature",
  "properties": {
    "addr:full":"300 W 4th St Spencer IA 51301",
    "addr:housenumber":"300",
    "addr:postcode":"51301",
    "addr:street":"W 4Th St",
    "iso:country":"US",
    "sg:address":"300 W 4th St",
    "sg:city":"Spencer",
    "sg:classifiers":[
        {
            "category":"Government",
            "subcategory":"Office",
            "type":"Public Place"
        }
    ],
    "sg:phone":"+1 712 262 2179",
    "sg:postcode":"51301",
    "sg:province":"IA",
    "sg:tags":[
        "county",
        "taxation"
    ],
    "wof:name":"Clay County Treasurer",
    "wof:placetype":"venue"
},
  "geometry": {"coordinates":[-95.148859,43.141176],"type":"Point"}
}