{
  "type": "Feature",
  "properties": {
    "iso:country":"US",
    "sg:address":"5420 Quail Ave",
    "sg:city":"Monroe",
    "sg:classifiers":[
        {
            "category":"Professional",
            "subcategory":"Management & Consulting",
            "type":"Services"
        }
    ],
    "sg:phone":"+1 641 259 2391",
    "sg:postcode":"50170",
    "sg:province":"IA",
    "sg:tags":[
        "business"
    ],
    "wof:name":"Robert Dunaway",
    "wof:placetype":"venue"
},
  "geometry": {"coordinates":[-93.119952,41.545169],"type":"Point"}
}