{
  "type": "Feature",
  "properties": {
    "iso:country":"US",
    "sg:address":"1524 240th St",
    "sg:city":"Webster City",
    "sg:classifiers":[
        {
            "category":"Airport",
            "type":"Transportation"
        }
    ],
    "sg:phone":"+1 515 832 3723",
    "sg:postcode":"50595",
    "sg:province":"IA",
    "sg:website":"www.stormflyingservice.com",
    "wof:name":"Storm Flying Svc",
    "wof:placetype":"venue"
},
  "geometry": {"coordinates":[-93.871241,42.441712],"type":"Point"}
}