{
  "type": "Feature",
  "properties": {
    "iso:country":"US",
    "sg:address":"121 S 5th St",
    "sg:city":"Eldridge",
    "sg:classifiers":[
        {
            "category":"Education",
            "subcategory":"School",
            "type":"Public Place"
        }
    ],
    "sg:phone":"+1 563 285 4544",
    "sg:postcode":"52748",
    "sg:province":"IA",
    "wof:name":"Edward White Elementary",
    "wof:placetype":"venue"
},
  "geometry": {"coordinates":[-90.58815300000001,41.653988],"type":"Point"}
}