{
  "type": "Feature",
  "properties": {
    "iso:country":"US",
    "sg:address":"301 9th St",
    "sg:city":"Sheldon",
    "sg:classifiers":[
        {
            "category":"Shopping",
            "subcategory":"Gifts & Souvenirs",
            "type":"Retail Goods"
        }
    ],
    "sg:phone":"+1 712 324 8190",
    "sg:postcode":"51201",
    "sg:province":"IA",
    "sg:tags":[
        "shop"
    ],
    "wof:name":"Picket Fences",
    "wof:placetype":"venue"
},
  "geometry": {"coordinates":[-95.854878,43.180873],"type":"Point"}
}