{
  "type": "Feature",
  "properties": {
    "addr:full":"6 1st Ave S Fort Dodge IA 50501",
    "addr:housenumber":"6",
    "addr:postcode":"50501",
    "addr:street":"1St Ave S",
    "iso:country":"US",
    "sg:address":"6 1st Ave S",
    "sg:city":"Fort Dodge",
    "sg:classifiers":[
        {
            "category":"Building & Trades",
            "subcategory":"Construction",
            "type":"Services"
        }
    ],
    "sg:phone":"+1 515 576 5147",
    "sg:postcode":"50501",
    "sg:province":"IA",
    "sg:tags":[
        "roofing",
        "contractor"
    ],
    "wof:name":"Central States Roofing",
    "wof:placetype":"venue"
},
  "geometry": {"coordinates":[-94.195943,42.502995],"type":"Point"}
}