{
  "type": "Feature",
  "properties": {
    "iso:country":"US",
    "sg:address":"8050 NE 109th St",
    "sg:city":"Mitchellville",
    "sg:classifiers":[
        {
            "category":"Organizations",
            "subcategory":"Religious Organization",
            "type":"Services"
        }
    ],
    "sg:phone":"+1 515 967 3388",
    "sg:postcode":"50169",
    "sg:province":"IA",
    "sg:tags":[
        "church"
    ],
    "wof:name":"Santiago United Methodist Chr",
    "wof:placetype":"venue"
},
  "geometry": {"coordinates":[-93.37534599999999,41.70565],"type":"Point"}
}