{
  "type": "Feature",
  "properties": {
    "iso:country":"US",
    "sg:address":"1105 N Frederick Ave",
    "sg:city":"Oelwein",
    "sg:classifiers":[
        {
            "category":"Wholesale",
            "subcategory":"Machinery & Supplies",
            "type":"Manufacturing & Wholesale Goods"
        }
    ],
    "sg:phone":"+1 319 283 5820",
    "sg:postcode":"50662",
    "sg:province":"IA",
    "sg:tags":[
        "equipment",
        "dryer",
        "grain",
        "drying"
    ],
    "wof:name":"G S Supply",
    "wof:placetype":"venue"
},
  "geometry": {"coordinates":[-91.91316999999999,42.689992],"type":"Point"}
}