{
  "type": "Feature",
  "properties": {
    "iso:country":"US",
    "sg:address":"307 Main St",
    "sg:city":"Readlyn",
    "sg:classifiers":[
        {
            "category":"Professional",
            "subcategory":"Lawyer & Legal Services",
            "type":"Services"
        }
    ],
    "sg:phone":"+1 319 279 3185",
    "sg:postcode":"50668",
    "sg:province":"IA",
    "sg:tags":[
        "attorney"
    ],
    "wof:name":"Englebrecht Ackerman & Hassman",
    "wof:placetype":"venue"
},
  "geometry": {"coordinates":[-92.225425,42.703588],"type":"Point"}
}