{
  "type": "Feature",
  "properties": {
    "iso:country":"US",
    "sg:address":"1113 Ave H",
    "sg:city":"Fort Madison",
    "sg:classifiers":[
        {
            "category":"Building & Trades",
            "subcategory":"Construction",
            "type":"Services"
        }
    ],
    "sg:phone":"+1 319 372 3554",
    "sg:postcode":"52627",
    "sg:province":"IA",
    "sg:tags":[
        "foundation"
    ],
    "wof:name":"Bix Service",
    "wof:placetype":"venue"
},
  "geometry": {"coordinates":[-91.318837,40.63018],"type":"Point"}
}