{
  "type": "Feature",
  "properties": {
    "iso:country":"US",
    "sg:address":"562 Palisades Access Rd",
    "sg:city":"Ely",
    "sg:classifiers":[
        {
            "category":"Retail",
            "subcategory":"Portrait Studio",
            "type":"Services"
        }
    ],
    "sg:phone":"+1 319 848 7532",
    "sg:postcode":"52227",
    "sg:province":"IA",
    "sg:tags":[
        "photographer"
    ],
    "wof:name":"Robert Burrell Photography",
    "wof:placetype":"venue"
},
  "geometry": {"coordinates":[-91.533068,41.897121],"type":"Point"}
}