{
  "type": "Feature",
  "properties": {
    "iso:country":"US",
    "sg:address":"18306 120th St",
    "sg:city":"Akron",
    "sg:classifiers":[
        {
            "category":"Farming",
            "subcategory":"Livestock Farm",
            "type":"Manufacturing & Wholesale Goods"
        }
    ],
    "sg:phone":"+1 712 568 2516",
    "sg:postcode":"51001",
    "sg:province":"IA",
    "sg:tags":[
        "beef",
        "feedlot",
        "soybean",
        "cattle"
    ],
    "wof:name":"Wendell Schneider",
    "wof:placetype":"venue"
},
  "geometry": {"coordinates":[-96.466122,42.880129],"type":"Point"}
}