{
  "type": "Feature",
  "properties": {
    "iso:country":"US",
    "sg:address":"109 S Greene St",
    "sg:city":"Rock Rapids",
    "sg:classifiers":[
        {
            "category":"Insurance",
            "subcategory":"Hazard Insurance",
            "type":"Services"
        }
    ],
    "sg:phone":"+1 712 472 4799",
    "sg:postcode":"51246",
    "sg:province":"IA",
    "sg:tags":[
        "bond"
    ],
    "wof:name":"Lederman Bonding Co",
    "wof:placetype":"venue"
},
  "geometry": {"coordinates":[-96.17101700000001,43.431768],"type":"Point"}
}