{
  "type": "Feature",
  "properties": {
    "iso:country":"US",
    "sg:address":"706 Fairfield St",
    "sg:city":"Floyd",
    "sg:classifiers":[
        {
            "category":"Organizations",
            "subcategory":"Community Association",
            "type":"Services"
        }
    ],
    "sg:phone":"+1 641 398 2845",
    "sg:postcode":"50435",
    "sg:province":"IA",
    "wof:name":"Floyd Community Ctr",
    "wof:placetype":"venue"
},
  "geometry": {"coordinates":[-92.739029,43.125216],"type":"Point"}
}