{
  "type": "Feature",
  "properties": {
    "addr:full":"5309 N US Hwy 75 Sioux City IA 51108",
    "addr:housenumber":"5309",
    "addr:postcode":"51108",
    "addr:street":"N Us Hwy 75",
    "iso:country":"US",
    "sg:address":"5309 N US Hwy 75",
    "sg:city":"Sioux City",
    "sg:classifiers":[
        {
            "category":"Real Estate",
            "subcategory":"Developer",
            "type":"Services"
        }
    ],
    "sg:phone":"+1 712 239 1665",
    "sg:postcode":"51108",
    "sg:province":"IA",
    "sg:tags":[
        "mobile",
        "home"
    ],
    "wof:name":"Evergreen Village",
    "wof:placetype":"venue"
},
  "geometry": {"coordinates":[-96.332027,42.561114],"type":"Point"}
}