{
  "type": "Feature",
  "properties": {
    "addr:full":"6678 NW 62nd Ave Johnston IA 50131",
    "addr:housenumber":"6678",
    "addr:postcode":"50131",
    "addr:street":"Nw 62Nd Ave",
    "iso:country":"US",
    "sg:address":"6678 NW 62nd Ave",
    "sg:city":"Johnston",
    "sg:classifiers":[
        {
            "category":"Building & Trades",
            "subcategory":"Construction",
            "type":"Services"
        }
    ],
    "sg:phone":"+1 515 276 6162",
    "sg:postcode":"50131",
    "sg:province":"IA",
    "sg:tags":[
        "bridge",
        "builder"
    ],
    "wof:name":"United Contractors",
    "wof:placetype":"venue"
},
  "geometry": {"coordinates":[-93.70993900000001,41.672808],"type":"Point"}
}