{
  "type": "Feature",
  "properties": {
    "iso:country":"US",
    "sg:address":"1631 4th St SE",
    "sg:city":"Mason City",
    "sg:classifiers":[
        {
            "category":"Restaurant",
            "type":"Food & Drink"
        }
    ],
    "sg:phone":"+1 641 424 2166",
    "sg:postcode":"50401",
    "sg:province":"IA",
    "sg:tags":[
        "eating"
    ],
    "wof:name":"Pies & More",
    "wof:placetype":"venue"
},
  "geometry": {"coordinates":[-93.164025,43.148033],"type":"Point"}
}