{
  "type": "Feature",
  "properties": {
    "addr:full":"3264 N Center Point Rd Marion IA 52302",
    "addr:housenumber":"3264",
    "addr:postcode":"52302",
    "addr:street":"N Center Point Rd",
    "iso:country":"US",
    "sg:address":"3264 N Center Point Rd",
    "sg:city":"Marion",
    "sg:classifiers":[
        {
            "category":"Organizations",
            "subcategory":"Religious Organization",
            "type":"Services"
        }
    ],
    "sg:phone":"+1 319 393 5502",
    "sg:postcode":"52302",
    "sg:province":"IA",
    "sg:tags":[
        "church"
    ],
    "wof:name":"Toddville Church Of Christ",
    "wof:placetype":"venue"
},
  "geometry": {"coordinates":[-91.697036,42.100916],"type":"Point"}
}