{
  "type": "Feature",
  "properties": {
    "iso:country":"US",
    "sg:address":"2309 Heinz Rd",
    "sg:city":"Iowa City",
    "sg:classifiers":[
        {
            "category":"Wholesale",
            "subcategory":"Groceries",
            "type":"Manufacturing & Wholesale Goods"
        }
    ],
    "sg:phone":"+1 319 354 0769",
    "sg:postcode":"52240",
    "sg:province":"IA",
    "sg:tags":[
        "food",
        "product"
    ],
    "wof:name":"General Mill Inc",
    "wof:placetype":"venue"
},
  "geometry": {"coordinates":[-91.489604,41.634578],"type":"Point"}
}