{
  "type": "Feature",
  "properties": {
    "addr:full":"5550 Carey Ave Davenport IA 52807",
    "addr:housenumber":"5550",
    "addr:postcode":"52807",
    "addr:street":"Carey Ave",
    "iso:country":"US",
    "sg:address":"5550 Carey Ave",
    "sg:city":"Davenport",
    "sg:classifiers":[
        {
            "category":"Wholesale",
            "subcategory":"Machinery & Supplies",
            "type":"Manufacturing & Wholesale Goods"
        }
    ],
    "sg:phone":"+1 563 391 1736",
    "sg:postcode":"52807",
    "sg:province":"IA",
    "sg:tags":[
        "fitting",
        "hose",
        "coupling"
    ],
    "wof:name":"Dadco Corp",
    "wof:placetype":"venue"
},
  "geometry": {"coordinates":[-90.558269,41.577981],"type":"Point"}
}