{
  "type": "Feature",
  "properties": {
    "iso:country":"US",
    "sg:address":"303 S Main St",
    "sg:city":"Danville",
    "sg:classifiers":[
        {
            "category":"Freight",
            "type":"Transportation"
        }
    ],
    "sg:phone":"+1 319 392 4512",
    "sg:postcode":"52623",
    "sg:province":"IA",
    "sg:tags":[
        "trucking"
    ],
    "wof:name":"Koontz Trucking Inc",
    "wof:placetype":"venue"
},
  "geometry": {"coordinates":[-91.31469199999999,40.863613],"type":"Point"}
}