{
  "type": "Feature",
  "properties": {
    "iso:country":"US",
    "sg:address":"5006 120th St",
    "sg:city":"Sibley",
    "sg:classifiers":[
        {
            "category":"Farming",
            "subcategory":"Dairy Farm",
            "type":"Manufacturing & Wholesale Goods"
        }
    ],
    "sg:phone":"+1 712 754 3018",
    "sg:postcode":"51249",
    "sg:province":"IA",
    "wof:name":"Clifford Wynia",
    "wof:placetype":"venue"
},
  "geometry": {"coordinates":[-95.80007500000001,43.476155],"type":"Point"}
}