{
  "type": "Feature",
  "properties": {
    "iso:country":"US",
    "sg:address":"800 7th Ave SW",
    "sg:city":"Independence",
    "sg:classifiers":[
        {
            "category":"Building & Trades",
            "subcategory":"Plumbing",
            "type":"Services"
        }
    ],
    "sg:phone":"+1 319 882 4282",
    "sg:postcode":"50644",
    "sg:province":"IA",
    "sg:tags":[
        "plumbing",
        "contractor"
    ],
    "wof:name":"K C Plumbing & Heating",
    "wof:placetype":"venue"
},
  "geometry": {"coordinates":[-91.90133899999999,42.462634],"type":"Point"}
}