{
  "type": "Feature",
  "properties": {
    "addr:full":"709 W 8th Ave N Estherville IA 51334",
    "addr:housenumber":"709",
    "addr:postcode":"51334",
    "addr:street":"W 8Th Ave N",
    "iso:country":"US",
    "sg:address":"709 W 8th Ave N",
    "sg:city":"Estherville",
    "sg:classifiers":[
        {
            "category":"Manufacturing",
            "subcategory":"Buildings",
            "type":"Manufacturing & Wholesale Goods"
        },
        {
            "category":"Building & Trades",
            "subcategory":"Construction",
            "type":"Services"
        }
    ],
    "sg:phone":"+1 712 362 2730",
    "sg:postcode":"51334",
    "sg:province":"IA",
    "sg:tags":[
        "altering",
        "home",
        "builder",
        "remodeling",
        "contractor"
    ],
    "wof:name":"Rudens Painting & Construction",
    "wof:placetype":"venue"
},
  "geometry": {"coordinates":[-94.853911,43.410001],"type":"Point"}
}