{
  "type": "Feature",
  "properties": {
    "iso:country":"US",
    "sg:address":"306 Main St",
    "sg:city":"Reinbeck",
    "sg:classifiers":[
        {
            "category":"Shopping",
            "subcategory":"Used Merchandise",
            "type":"Retail Goods"
        }
    ],
    "sg:phone":"+1 319 345 6205",
    "sg:postcode":"50669",
    "sg:province":"IA",
    "sg:tags":[
        "antique"
    ],
    "wof:name":"Country School Antiques",
    "wof:placetype":"venue"
},
  "geometry": {"coordinates":[-92.597675,42.324613],"type":"Point"}
}