{
  "type": "Feature",
  "properties": {
    "addr:full":"3470 US Hwy 71 Brayton IA 50042",
    "addr:housenumber":"3470",
    "addr:postcode":"50042",
    "addr:street":"Us Hwy 71",
    "iso:country":"US",
    "sg:address":"3470 US Hwy 71",
    "sg:city":"Brayton",
    "sg:classifiers":[
        {
            "category":"Farming",
            "subcategory":"Nursery",
            "type":"Manufacturing & Wholesale Goods"
        }
    ],
    "sg:phone":"+1 712 549 4372",
    "sg:postcode":"50042",
    "sg:province":"IA",
    "sg:tags":[
        "greenhouse"
    ],
    "wof:name":"Bountiful Harvest & Co",
    "wof:placetype":"venue"
},
  "geometry": {"coordinates":[-94.94308599999999,41.507203],"type":"Point"}
}