{
  "type": "Feature",
  "properties": {
    "iso:country":"US",
    "sg:address":"10400 18th St SW",
    "sg:city":"Cedar Rapids",
    "sg:classifiers":[
        {
            "category":"Government",
            "subcategory":"Office",
            "type":"Public Place"
        }
    ],
    "sg:phone":"+1 319 363 4511",
    "sg:postcode":"52338",
    "sg:province":"IA",
    "sg:tags":[
        "state",
        "security"
    ],
    "wof:name":"Iowa National Guard Hdqrs",
    "wof:placetype":"venue"
},
  "geometry": {"coordinates":[-91.695122,41.884993],"type":"Point"}
}