{
  "type": "Feature",
  "properties": {
    "addr:full":"1850 Madison Ave Council Bluffs IA 51503",
    "addr:housenumber":"1850",
    "addr:postcode":"51503",
    "addr:street":"Madison Ave",
    "iso:country":"US",
    "sg:address":"1850 Madison Ave",
    "sg:city":"Council Bluffs",
    "sg:classifiers":[
        {
            "category":"Shopping",
            "subcategory":"Used Merchandise",
            "type":"Retail Goods"
        }
    ],
    "sg:phone":"+1 712 328 8911",
    "sg:postcode":"51503",
    "sg:province":"IA",
    "sg:tags":[
        "shop",
        "thrift"
    ],
    "wof:name":"Goodwill Industries",
    "wof:placetype":"venue"
},
  "geometry": {"coordinates":[-95.827067,41.243861],"type":"Point"}
}