{
  "type": "Feature",
  "properties": {
    "iso:country":"US",
    "sg:address":"305 2nd Ave",
    "sg:city":"Marion",
    "sg:classifiers":[
        {
            "category":"Organizations",
            "subcategory":"Religious Organization",
            "type":"Services"
        }
    ],
    "sg:phone":"+1 319 373 2470",
    "sg:postcode":"52302",
    "sg:province":"IA",
    "sg:tags":[
        "church"
    ],
    "wof:name":"Gospel Light Baptist Church",
    "wof:placetype":"venue"
},
  "geometry": {"coordinates":[-91.606697,42.028809],"type":"Point"}
}