{
  "type": "Feature",
  "properties": {
    "iso:country":"US",
    "sg:address":"621 S Illinois Ave",
    "sg:city":"Mason City",
    "sg:classifiers":[
        {
            "category":"Health Services",
            "subcategory":"Doctor",
            "type":"Services"
        }
    ],
    "sg:phone":"+1 641 424 3990",
    "sg:postcode":"50401",
    "sg:province":"IA",
    "sg:tags":[
        "medical"
    ],
    "wof:name":"Lindstrom Lori L Dr",
    "wof:placetype":"venue"
},
  "geometry": {"coordinates":[-93.17109600000001,43.145456],"type":"Point"}
}