{
  "type": "Feature",
  "properties": {
    "addr:full":"2110 US Hwy 71 Audubon IA 50025",
    "addr:housenumber":"2110",
    "addr:postcode":"50025",
    "addr:street":"Us Hwy 71",
    "iso:country":"US",
    "sg:address":"2110 US Hwy 71",
    "sg:city":"Audubon",
    "sg:classifiers":[
        {
            "category":"Airport",
            "type":"Transportation"
        }
    ],
    "sg:phone":"+1 712 563 2710",
    "sg:postcode":"50025",
    "sg:province":"IA",
    "wof:name":"Audubon Airways",
    "wof:placetype":"venue"
},
  "geometry": {"coordinates":[-94.922152,41.700998],"type":"Point"}
}