{
  "type": "Feature",
  "properties": {
    "iso:country":"US",
    "sg:address":"728 McKenzie Ave",
    "sg:city":"Council Bluffs",
    "sg:classifiers":[
        {
            "category":"Building & Trades",
            "subcategory":"Cleaning & Sanitation",
            "type":"Services"
        }
    ],
    "sg:phone":"+1 712 325 8601",
    "sg:postcode":"51503",
    "sg:province":"IA",
    "sg:tags":[
        "carpet"
    ],
    "wof:name":"Reliable Maintenance Services - CLOSED",
    "wof:placetype":"venue"
},
  "geometry": {"coordinates":[-95.82150300000001,41.285099],"type":"Point"}
}