{
  "type": "Feature",
  "properties": {
    "iso:country":"US",
    "sg:address":"816 Summer Ave",
    "sg:city":"Riverton",
    "sg:classifiers":[
        {
            "category":"Banks & Credit Unions",
            "subcategory":"Bank",
            "type":"Services"
        }
    ],
    "sg:phone":"+1 712 387 2671",
    "sg:postcode":"51650",
    "sg:province":"IA",
    "wof:name":"Great Western Bank",
    "wof:placetype":"venue"
},
  "geometry": {"coordinates":[-95.568535,40.68674],"type":"Point"}
}