{
  "type": "Feature",
  "properties": {
    "iso:country":"US",
    "sg:address":"607 Lincoln St",
    "sg:city":"Pella",
    "sg:classifiers":[
        {
            "category":"Building & Trades",
            "subcategory":"Construction",
            "type":"Services"
        }
    ],
    "sg:phone":"+1 641 628 3274",
    "sg:postcode":"50219",
    "sg:province":"IA",
    "sg:tags":[
        "house"
    ],
    "wof:name":"Saunders Remodeling",
    "wof:placetype":"venue"
},
  "geometry": {"coordinates":[-92.91525300000001,41.410598],"type":"Point"}
}