{
  "type": "Feature",
  "properties": {
    "iso:country":"US",
    "sg:address":"518 S Fremont St",
    "sg:city":"Shenandoah",
    "sg:classifiers":[
        {
            "category":"Professional",
            "subcategory":"Employment Agencies",
            "type":"Services"
        }
    ],
    "sg:phone":"+1 866 301 1590",
    "sg:postcode":"51601",
    "sg:province":"IA",
    "sg:tags":[
        "temporary",
        "contractor"
    ],
    "sg:website":"http://national.citysearch.com/profile/external/33690091/shenandoah_ia/manpower.html?publisher=yellowpages&reference_id=1&placement=ypwebsitemip",
    "wof:name":"Manpower",
    "wof:placetype":"venue"
},
  "geometry": {"coordinates":[-95.385007,40.770836],"type":"Point"}
}