{
  "type": "Feature",
  "properties": {
    "iso:country":"US",
    "sg:address":"1728 Central Ave",
    "sg:city":"Fort Dodge",
    "sg:classifiers":[
        {
            "category":"Professional",
            "subcategory":"Lawyer & Legal Services",
            "type":"Services"
        }
    ],
    "sg:phone":"+1 515 576 0333",
    "sg:postcode":"50501",
    "sg:province":"IA",
    "sg:tags":[
        "attorney"
    ],
    "wof:name":"David A Sergeant Law Office",
    "wof:placetype":"venue"
},
  "geometry": {"coordinates":[-94.17465799999999,42.506278],"type":"Point"}
}