{
  "type": "Feature",
  "properties": {
    "addr:full":"405 N 3rd St Red Oak IA 51566",
    "addr:housenumber":"405",
    "addr:postcode":"51566",
    "addr:street":"N 3Rd St",
    "iso:country":"US",
    "sg:address":"405 N 3rd St",
    "sg:city":"Red Oak",
    "sg:classifiers":[
        {
            "category":"Building & Trades",
            "subcategory":"Plumbing",
            "type":"Services"
        }
    ],
    "sg:phone":"+1 712 623 2408",
    "sg:postcode":"51566",
    "sg:province":"IA",
    "sg:tags":[
        "plumbing",
        "contractor"
    ],
    "wof:name":"Eagan Plumbing & Heating",
    "wof:placetype":"venue"
},
  "geometry": {"coordinates":[-95.22922,41.008422],"type":"Point"}
}