{
  "type": "Feature",
  "properties": {
    "iso:country":"US",
    "sg:address":"1 E Main St",
    "sg:city":"Marshalltown",
    "sg:classifiers":[
        {
            "category":"Education",
            "subcategory":"Dance Studio",
            "type":"Public Place"
        }
    ],
    "sg:phone":"+1 641 753 1035",
    "sg:postcode":"50158",
    "sg:province":"IA",
    "sg:tags":[
        "instruction",
        "dancing"
    ],
    "wof:name":"Tayna's Studio Of Dance",
    "wof:placetype":"venue"
},
  "geometry": {"coordinates":[-92.912949,42.049161],"type":"Point"}
}