{
  "type": "Feature",
  "properties": {
    "iso:country":"US",
    "sg:address":"714 Country Club Dr",
    "sg:city":"Maquoketa",
    "sg:classifiers":[
        {
            "category":"Farming",
            "subcategory":"Livestock Farm",
            "type":"Manufacturing & Wholesale Goods"
        }
    ],
    "sg:phone":"+1 563 652 3209",
    "sg:postcode":"52060",
    "sg:province":"IA",
    "sg:tags":[
        "animal",
        "general"
    ],
    "wof:name":"Adrian Farms Inc",
    "wof:placetype":"venue"
},
  "geometry": {"coordinates":[-90.685265,42.059193],"type":"Point"}
}