{
  "type": "Feature",
  "properties": {
    "addr:full":"104 S Fillmore St Osceola IA 50213",
    "addr:housenumber":"104",
    "addr:postcode":"50213",
    "addr:street":"S Fillmore St",
    "iso:country":"US",
    "sg:address":"104 S Fillmore St",
    "sg:city":"Osceola",
    "sg:classifiers":[
        {
            "category":"Government",
            "subcategory":"Post Office",
            "type":"Public Place"
        }
    ],
    "sg:phone":"+1 641 342 2311",
    "sg:postcode":"50213",
    "sg:province":"IA",
    "wof:name":"US Post Office",
    "wof:placetype":"venue"
},
  "geometry": {"coordinates":[-93.76758700000001,41.034267],"type":"Point"}
}