{
  "type": "Feature",
  "properties": {
    "iso:country":"US",
    "sg:address":"59433 585th St",
    "sg:city":"Atlantic",
    "sg:classifiers":[
        {
            "category":"Farming",
            "subcategory":"Farm",
            "type":"Manufacturing & Wholesale Goods"
        }
    ],
    "sg:phone":"+1 712 243 5485",
    "sg:postcode":"50022",
    "sg:province":"IA",
    "sg:tags":[
        "crop",
        "general"
    ],
    "wof:name":"Nicholas Hunt",
    "wof:placetype":"venue"
},
  "geometry": {"coordinates":[-95.070115,41.349922],"type":"Point"}
}