{
  "type": "Feature",
  "properties": {
    "addr:full":"331 Sumner Ave Humboldt IA 50548",
    "addr:housenumber":"331",
    "addr:postcode":"50548",
    "addr:street":"Sumner Ave",
    "iso:country":"US",
    "sg:address":"331 Sumner Ave",
    "sg:city":"Humboldt",
    "sg:classifiers":[
        {
            "category":"Autos & Motor Vehicles",
            "subcategory":"Fuel & Gas Station",
            "type":"Retail Goods"
        }
    ],
    "sg:phone":"+1 515 332 1932",
    "sg:postcode":"50548",
    "sg:province":"IA",
    "sg:tags":[
        "oil"
    ],
    "wof:name":"Christensen's Phillips 66",
    "wof:placetype":"venue"
},
  "geometry": {"coordinates":[-94.211794,42.721267],"type":"Point"}
}