{
  "type": "Feature",
  "properties": {
    "addr:full":"1510 N Jefferson Way Indianola IA 50125",
    "addr:housenumber":"1510",
    "addr:postcode":"50125",
    "addr:street":"N Jefferson Way",
    "iso:country":"US",
    "sg:address":"1510 N Jefferson Way",
    "sg:city":"Indianola",
    "sg:classifiers":[
        {
            "category":"Food & Beverages",
            "subcategory":"Groceries & Convenience Stores",
            "type":"Retail Goods"
        }
    ],
    "sg:phone":"+1 515 000 1111",
    "sg:postcode":"50125",
    "sg:province":"IA",
    "sg:tags":[
        "grocer"
    ],
    "wof:name":"Aldi",
    "wof:placetype":"venue"
},
  "geometry": {"coordinates":[-93.558361,41.374939],"type":"Point"}
}