{
  "type": "Feature",
  "properties": {
    "iso:country":"US",
    "sg:address":"3091 Jackson Ave",
    "sg:city":"Boyden",
    "sg:classifiers":[
        {
            "category":"Farming",
            "subcategory":"Livestock Farm",
            "type":"Manufacturing & Wholesale Goods"
        }
    ],
    "sg:phone":"+1 712 439 2615",
    "sg:postcode":"51234",
    "sg:province":"IA",
    "sg:tags":[
        "feedlot",
        "hog",
        "corn",
        "or",
        "soybean"
    ],
    "wof:name":"Van Batavia  Bert L",
    "wof:placetype":"venue"
},
  "geometry": {"coordinates":[-96.060187,43.201944],"type":"Point"}
}