{
  "type": "Feature",
  "properties": {
    "addr:full":"200 S Vermont St Maquoketa IA 52060",
    "addr:housenumber":"200",
    "addr:postcode":"52060",
    "addr:street":"S Vermont St",
    "iso:country":"US",
    "sg:address":"200 S Vermont St",
    "sg:city":"Maquoketa",
    "sg:classifiers":[
        {
            "category":"Organizations",
            "subcategory":"Religious Organization",
            "type":"Services"
        }
    ],
    "sg:phone":"+1 563 652 6931",
    "sg:postcode":"52060",
    "sg:province":"IA",
    "sg:tags":[
        "church"
    ],
    "sg:website":"www.sacredheartmaquoketa.org",
    "wof:name":"Sacred Heart Parish",
    "wof:placetype":"venue"
},
  "geometry": {"coordinates":[-90.67321699999999,42.067035],"type":"Point"}
}