{
  "type": "Feature",
  "properties": {
    "addr:full":"515 S Schenck Rd Clarinda IA 51632",
    "addr:housenumber":"515",
    "addr:postcode":"51632",
    "addr:street":"S Schenck Rd",
    "iso:country":"US",
    "sg:address":"515 S Schenck Rd",
    "sg:city":"Clarinda",
    "sg:classifiers":[
        {
            "category":"Freight",
            "type":"Transportation"
        }
    ],
    "sg:phone":"+1 712 542 6527",
    "sg:postcode":"51632",
    "sg:province":"IA",
    "sg:tags":[
        "hauling",
        "trucking"
    ],
    "wof:name":"Drennen Enterprises Co",
    "wof:placetype":"venue"
},
  "geometry": {"coordinates":[-95.02178600000001,40.73497],"type":"Point"}
}