{
  "type": "Feature",
  "properties": {
    "iso:country":"US",
    "sg:address":"301 W Bennett Ave",
    "sg:city":"Council Bluffs",
    "sg:classifiers":[
        {
            "category":"Retail",
            "subcategory":"Portrait Studio",
            "type":"Services"
        },
        {
            "category":"Shopping",
            "subcategory":"Pharmacy",
            "type":"Retail Goods"
        }
    ],
    "sg:phone":"+1 712 325 0600",
    "sg:postcode":"51503",
    "sg:province":"IA",
    "sg:tags":[
        "photography",
        "drugstore",
        "store"
    ],
    "sg:website":"www.walgreens.com",
    "wof:name":"Walgreen Drug Stores",
    "wof:placetype":"venue"
},
  "geometry": {"coordinates":[-95.829399,41.244999],"type":"Point"}
}