{
  "type": "Feature",
  "properties": {
    "iso:country":"US",
    "sg:address":"509 W Market St",
    "sg:city":"New Sharon",
    "sg:classifiers":[
        {
            "category":"Building & Trades",
            "subcategory":"Construction",
            "type":"Services"
        }
    ],
    "sg:phone":"+1 641 637 4470",
    "sg:postcode":"50207",
    "sg:province":"IA",
    "sg:tags":[
        "hanging",
        "contractor"
    ],
    "wof:name":"Dieleman Painting and Wall Cvg",
    "wof:placetype":"venue"
},
  "geometry": {"coordinates":[-92.656319,41.469772],"type":"Point"}
}