{
  "type": "Feature",
  "properties": {
    "addr:full":"1210 B Ave W Oskaloosa IA 52577",
    "addr:housenumber":"1210",
    "addr:postcode":"52577",
    "addr:street":"B Ave W Oskaloosa",
    "iso:country":"US",
    "sg:address":"1210 B Ave W",
    "sg:city":"Oskaloosa",
    "sg:classifiers":[
        {
            "category":"Personal",
            "subcategory":"Beauty Salon",
            "type":"Services"
        }
    ],
    "sg:phone":"+1 641 673 5170",
    "sg:postcode":"52577",
    "sg:province":"IA",
    "wof:name":"Hair Designers",
    "wof:placetype":"venue"
},
  "geometry": {"coordinates":[-92.658096,41.297031],"type":"Point"}
}