{
  "type": "Feature",
  "properties": {
    "iso:country":"US",
    "sg:address":"406 Church St",
    "sg:city":"Deep River",
    "sg:classifiers":[
        {
            "category":"Freight",
            "type":"Transportation"
        }
    ],
    "sg:phone":"+1 641 595 6785",
    "sg:postcode":"52222",
    "sg:province":"IA",
    "sg:tags":[
        "hauling",
        "trucking"
    ],
    "wof:name":"Bob Schmidt Trucking",
    "wof:placetype":"venue"
},
  "geometry": {"coordinates":[-92.372507,41.58206],"type":"Point"}
}