{
  "type": "Feature",
  "properties": {
    "iso:country":"US",
    "sg:address":"1644 300th Ave",
    "sg:city":"Dyersville",
    "sg:classifiers":[
        {
            "category":"Home & Garden",
            "subcategory":"Household Appliances",
            "type":"Retail Goods"
        }
    ],
    "sg:phone":"+1 563 875 8000",
    "sg:postcode":"52040",
    "sg:province":"IA",
    "sg:tags":[
        "pump"
    ],
    "wof:name":"Budden Pump Svc",
    "wof:placetype":"venue"
},
  "geometry": {"coordinates":[-91.21351199999999,42.552963],"type":"Point"}
}