{
  "type": "Feature",
  "properties": {
    "iso:country":"US",
    "sg:address":"1709 Valley View Ct",
    "sg:city":"Fairfield",
    "sg:classifiers":[
        {
            "category":"Professional",
            "subcategory":"Business Services",
            "type":"Services"
        }
    ],
    "sg:phone":"+1 641 469 3542",
    "sg:postcode":"52556",
    "sg:province":"IA",
    "wof:name":"Cg Enterprizes",
    "wof:placetype":"venue"
},
  "geometry": {"coordinates":[-91.914987,41.061234],"type":"Point"}
}