{
  "type": "Feature",
  "properties": {
    "iso:country":"US",
    "sg:address":"518 N 2nd Ave E",
    "sg:city":"Newton",
    "sg:classifiers":[
        {
            "category":"Building & Trades",
            "subcategory":"Plumbing",
            "type":"Services"
        }
    ],
    "sg:phone":"+1 641 791 2665",
    "sg:postcode":"50208",
    "sg:province":"IA",
    "sg:tags":[
        "contractor"
    ],
    "wof:name":"Cook Plumbing",
    "wof:placetype":"venue"
},
  "geometry": {"coordinates":[-93.04758099999999,41.70059],"type":"Point"}
}