{
  "type": "Feature",
  "properties": {
    "iso:country":"US",
    "sg:address":"1795 150th St",
    "sg:city":"Lost Nation",
    "sg:classifiers":[
        {
            "category":"Farming",
            "subcategory":"Farm",
            "type":"Manufacturing & Wholesale Goods"
        }
    ],
    "sg:phone":"+1 563 678 2439",
    "sg:postcode":"52254",
    "sg:province":"IA",
    "sg:tags":[
        "crop",
        "general"
    ],
    "wof:name":"Alan Andersen Farm",
    "wof:placetype":"venue"
},
  "geometry": {"coordinates":[-90.743999,41.960648],"type":"Point"}
}