{
  "type": "Feature",
  "properties": {
    "addr:full":"1204 H Ave Nevada IA 50201",
    "addr:housenumber":"1204 h",
    "addr:postcode":"50201",
    "addr:street":"Ave Nevada",
    "iso:country":"US",
    "sg:address":"1204 H Ave",
    "sg:city":"Nevada",
    "sg:classifiers":[
        {
            "category":"Recreation",
            "type":"Entertainment"
        }
    ],
    "sg:phone":"+1 515 382 6684",
    "sg:postcode":"50201",
    "sg:province":"IA",
    "sg:tags":[
        "historical"
    ],
    "wof:name":"Nevada Historical Society",
    "wof:placetype":"venue"
},
  "geometry": {"coordinates":[-93.443746,42.019086],"type":"Point"}
}