{
  "type": "Feature",
  "properties": {
    "addr:full":"3000 6th St SW Cedar Rapids IA 52404",
    "addr:housenumber":"3000",
    "addr:postcode":"52404",
    "addr:street":"6Th St Sw",
    "iso:country":"US",
    "sg:address":"3000 6th St SW",
    "sg:city":"Cedar Rapids",
    "sg:classifiers":[
        {
            "category":"Bars & Pubs",
            "type":"Food & Drink"
        }
    ],
    "sg:phone":"+1 319 366 4748",
    "sg:postcode":"52404",
    "sg:province":"IA",
    "sg:tags":[
        "lounge",
        "cocktail"
    ],
    "wof:name":"Dancer's Ranch",
    "wof:placetype":"venue"
},
  "geometry": {"coordinates":[-91.676627,41.947035],"type":"Point"}
}