{
  "type": "Feature",
  "properties": {
    "addr:full":"615 Northwest Rd Shenandoah IA 51601",
    "addr:housenumber":"615",
    "addr:postcode":"51601",
    "addr:street":"Northwest Rd",
    "iso:country":"US",
    "sg:address":"615 Northwest Rd",
    "sg:city":"Shenandoah",
    "sg:classifiers":[
        {
            "category":"Building & Trades",
            "subcategory":"Electrical",
            "type":"Services"
        }
    ],
    "sg:phone":"+1 712 246 2728",
    "sg:postcode":"51601",
    "sg:province":"IA",
    "sg:tags":[
        "electric",
        "contractor"
    ],
    "wof:name":"Novinger Electric",
    "wof:placetype":"venue"
},
  "geometry": {"coordinates":[-95.378607,40.77252],"type":"Point"}
}