{
  "type": "Feature",
  "properties": {
    "addr:full":"315 Main St Manning IA 51455",
    "addr:housenumber":"315",
    "addr:postcode":"51455",
    "addr:street":"Main St",
    "iso:country":"US",
    "sg:address":"315 Main St",
    "sg:city":"Manning",
    "sg:classifiers":[
        {
            "category":"Personal",
            "subcategory":"Beauty Salon",
            "type":"Services"
        }
    ],
    "sg:phone":"+1 712 655 2558",
    "sg:postcode":"51455",
    "sg:province":"IA",
    "sg:tags":[
        "shop"
    ],
    "wof:name":"Upper Cut",
    "wof:placetype":"venue"
},
  "geometry": {"coordinates":[-95.065206,41.908228],"type":"Point"}
}