{
  "type": "Feature",
  "properties": {
    "addr:full":"2830 Mount Pleasant St Burlington IA 52601",
    "addr:housenumber":"2830",
    "addr:postcode":"52601",
    "addr:street":"Mount Pleasant St",
    "iso:country":"US",
    "sg:address":"2830 Mount Pleasant St",
    "sg:city":"Burlington",
    "sg:classifiers":[
        {
            "category":"Food & Beverages",
            "subcategory":"Bakery",
            "type":"Retail Goods"
        }
    ],
    "sg:phone":"+1 319 752 9786",
    "sg:postcode":"52601",
    "sg:province":"IA",
    "sg:tags":[
        "baker"
    ],
    "wof:name":"Wonder Hostess Thrift Shop",
    "wof:placetype":"venue"
},
  "geometry": {"coordinates":[-91.141159,40.825945],"type":"Point"}
}