{
  "type": "Feature",
  "properties": {
    "addr:full":"100 Levering St Traer IA 50675",
    "addr:housenumber":"100",
    "addr:postcode":"50675",
    "addr:street":"Levering St",
    "iso:country":"US",
    "sg:address":"100 Levering St",
    "sg:city":"Traer",
    "sg:classifiers":[
        {
            "category":"Personal",
            "subcategory":"Beauty Salon",
            "type":"Services"
        }
    ],
    "sg:phone":"+1 319 478 2570",
    "sg:postcode":"50675",
    "sg:province":"IA",
    "sg:tags":[
        "shop"
    ],
    "wof:name":"Carols Cut & Curl",
    "wof:placetype":"venue"
},
  "geometry": {"coordinates":[-92.46114900000001,42.195534],"type":"Point"}
}