{
  "type": "Feature",
  "properties": {
    "iso:country":"US",
    "sg:address":"615 N 21st St",
    "sg:city":"Fort Dodge",
    "sg:classifiers":[
        {
            "category":"Social Services",
            "subcategory":"Child Care",
            "type":"Services"
        }
    ],
    "sg:phone":"+1 515 573 7659",
    "sg:postcode":"50501",
    "sg:province":"IA",
    "sg:tags":[
        "day"
    ],
    "wof:name":"Angels Little Daycare",
    "wof:placetype":"venue"
},
  "geometry": {"coordinates":[-94.16947399999999,42.512767],"type":"Point"}
}