{
  "type": "Feature",
  "properties": {
    "iso:country":"US",
    "sg:address":"1350 Boyson Rd",
    "sg:city":"Hiawatha",
    "sg:classifiers":[
        {
            "category":"Real Estate",
            "subcategory":"Real Estate Services",
            "type":"Services"
        }
    ],
    "sg:phone":"+1 319 378 8370",
    "sg:postcode":"52233",
    "sg:province":"IA",
    "sg:tags":[
        "company",
        "title"
    ],
    "wof:name":"All American Escrow & Title",
    "wof:placetype":"venue"
},
  "geometry": {"coordinates":[-91.690066,42.044294],"type":"Point"}
}