{
  "type": "Feature",
  "properties": {
    "iso:country":"US",
    "sg:address":"2847 185th Ln",
    "sg:city":"Woodbine",
    "sg:phone":"+1 712 647 2672",
    "sg:postcode":"51579",
    "sg:province":"IA",
    "sg:tags":[
        "farm",
        "corn"
    ],
    "wof:name":"Dorothy Barry",
    "wof:placetype":"venue"
},
  "geometry": {"coordinates":[-95.754795,41.740217],"type":"Point"}
}