{
  "type": "Feature",
  "properties": {
    "iso:country":"US",
    "sg:address":"24289 265th St",
    "sg:city":"Allison",
    "sg:classifiers":[
        {
            "category":"Farming",
            "subcategory":"Livestock Farm",
            "type":"Manufacturing & Wholesale Goods"
        }
    ],
    "sg:phone":"+1 319 267 2893",
    "sg:postcode":"50602",
    "sg:province":"IA",
    "sg:tags":[
        "hog",
        "or",
        "feedlot"
    ],
    "wof:name":"Luebbers Gerhard Farm",
    "wof:placetype":"venue"
},
  "geometry": {"coordinates":[-92.732232,42.66433],"type":"Point"}
}