{
  "type": "Feature",
  "properties": {
    "addr:full":"5167 Old 21 Rd Cherokee IA 51012",
    "addr:housenumber":"5167",
    "addr:postcode":"51012",
    "addr:street":"Old 21 Rd",
    "iso:country":"US",
    "sg:address":"5167 Old 21 Rd",
    "sg:city":"Cherokee",
    "sg:classifiers":[
        {
            "category":"Manufacturing",
            "subcategory":"Petroleum Products",
            "type":"Manufacturing & Wholesale Goods"
        }
    ],
    "sg:phone":"+1 712 225 1331",
    "sg:postcode":"51012",
    "sg:province":"IA",
    "sg:tags":[
        "oil",
        "recovery"
    ],
    "wof:name":"Filter Recycling Inc",
    "wof:placetype":"venue"
},
  "geometry": {"coordinates":[-95.53038599999999,42.773634],"type":"Point"}
}