{
  "type": "Feature",
  "properties": {
    "iso:country":"US",
    "sg:address":"3115 Valley View Rd",
    "sg:city":"Ames",
    "sg:classifiers":[
        {
            "category":"Building & Trades",
            "subcategory":"Construction",
            "type":"Services"
        }
    ],
    "sg:phone":"+1 515 296 2920",
    "sg:postcode":"50014",
    "sg:province":"IA",
    "sg:tags":[
        "house"
    ],
    "wof:name":"John Richardson Construction",
    "wof:placetype":"venue"
},
  "geometry": {"coordinates":[-93.65117600000001,42.051801],"type":"Point"}
}