{
  "type": "Feature",
  "properties": {
    "iso:country":"US",
    "sg:address":"1316 W Locust St",
    "sg:city":"Davenport",
    "sg:classifiers":[
        {
            "category":"Retail",
            "subcategory":"Veterinary Services",
            "type":"Services"
        }
    ],
    "sg:phone":"+1 563 322 4901",
    "sg:postcode":"52804",
    "sg:province":"IA",
    "sg:tags":[
        "veterinarian"
    ],
    "wof:name":"Bell Animal Hospital",
    "wof:placetype":"venue"
},
  "geometry": {"coordinates":[-90.59184399999999,41.53834],"type":"Point"}
}