{
  "type": "Feature",
  "properties": {
    "iso:country":"US",
    "sg:address":"1040 Patrick Ct",
    "sg:city":"Waterloo",
    "sg:classifiers":[
        {
            "category":"Real Estate",
            "subcategory":"Real Estate Operator",
            "type":"Services"
        }
    ],
    "sg:phone":"+1 319 232 1884",
    "sg:postcode":"50701",
    "sg:province":"IA",
    "sg:tags":[
        "apartment"
    ],
    "wof:name":"Brookside Apartments",
    "wof:placetype":"venue"
},
  "geometry": {"coordinates":[-92.37969699999999,42.472698],"type":"Point"}
}