{
  "type": "Feature",
  "properties": {
    "iso:country":"US",
    "sg:address":"3210 297th St",
    "sg:city":"Crawfordsville",
    "sg:phone":"+1 319 658 2901",
    "sg:postcode":"52621",
    "sg:province":"IA",
    "sg:tags":[
        "farm",
        "grain",
        "cash"
    ],
    "wof:name":"James Edgar",
    "wof:placetype":"venue"
},
  "geometry": {"coordinates":[-91.499072,41.226507],"type":"Point"}
}