{
  "type": "Feature",
  "properties": {
    "addr:full":"118 15th St NE Cedar Rapids IA 52402",
    "addr:housenumber":"118",
    "addr:postcode":"52402",
    "addr:street":"15Th St Ne",
    "iso:country":"US",
    "sg:address":"118 15th St NE",
    "sg:city":"Cedar Rapids",
    "sg:classifiers":[
        {
            "category":"Shopping",
            "subcategory":"Mobile Phones",
            "type":"Retail Goods"
        }
    ],
    "sg:phone":"+1 319 362 1227",
    "sg:postcode":"52402",
    "sg:province":"IA",
    "wof:name":"Wireless Solutions",
    "wof:placetype":"venue"
},
  "geometry": {"coordinates":[-91.65230200000001,41.988378],"type":"Point"}
}