{
  "type": "Feature",
  "properties": {
    "iso:country":"US",
    "sg:address":"4185 Alyssa Ct",
    "sg:city":"Iowa City",
    "sg:classifiers":[
        {
            "category":"Wholesale",
            "subcategory":"Electrical",
            "type":"Manufacturing & Wholesale Goods"
        }
    ],
    "sg:phone":"+1 319 354 4588",
    "sg:postcode":"52240",
    "sg:province":"IA",
    "sg:tags":[
        "control",
        "security",
        "system"
    ],
    "wof:name":"Freeman Lock & Alarm Inc",
    "wof:placetype":"venue"
},
  "geometry": {"coordinates":[-91.57020199999999,41.629431],"type":"Point"}
}