{
  "type": "Feature",
  "properties": {
    "addr:full":"2238 308th Ave De Witt IA 52742",
    "addr:housenumber":"2238",
    "addr:postcode":"52742",
    "addr:street":"308Th Ave De",
    "iso:country":"US",
    "sg:address":"2238 308th Ave",
    "sg:city":"De Witt",
    "sg:classifiers":[
        {
            "category":"Wholesale",
            "subcategory":"Farm Supplies",
            "type":"Manufacturing & Wholesale Goods"
        }
    ],
    "sg:phone":"+1 563 659 3087",
    "sg:postcode":"52742",
    "sg:province":"IA",
    "sg:tags":[
        "corn",
        "livestock"
    ],
    "wof:name":"Arey John",
    "wof:placetype":"venue"
},
  "geometry": {"coordinates":[-90.495474,41.853428],"type":"Point"}
}