{
  "type": "Feature",
  "properties": {
    "iso:country":"US",
    "sg:address":"803 N Shore Dr",
    "sg:city":"Clear Lake",
    "sg:classifiers":[
        {
            "category":"Autos & Motor Vehicles",
            "subcategory":"Boat Sales",
            "type":"Retail Goods"
        }
    ],
    "sg:phone":"+1 641 357 6600",
    "sg:postcode":"50428",
    "sg:province":"IA",
    "sg:tags":[
        "equipment",
        "supply"
    ],
    "wof:name":"Boat Docks Direct",
    "wof:placetype":"venue"
},
  "geometry": {"coordinates":[-93.398203,43.141248],"type":"Point"}
}