{
  "type": "Feature",
  "properties": {
    "iso:country":"US",
    "sg:address":"8555 Harbach Blvd",
    "sg:city":"Clive",
    "sg:classifiers":[
        {
            "category":"Professional",
            "subcategory":"Accounting & Tax Preparation",
            "type":"Services"
        }
    ],
    "sg:phone":"+1 515 223 8862",
    "sg:postcode":"50325",
    "sg:province":"IA",
    "sg:tags":[
        "accountant"
    ],
    "wof:name":"Medical Dental Business",
    "wof:placetype":"venue"
},
  "geometry": {"coordinates":[-93.735393,41.607726],"type":"Point"}
}