{
  "type": "Feature",
  "properties": {
    "iso:country":"US",
    "sg:address":"6110 N Brady St",
    "sg:city":"Davenport",
    "sg:classifiers":[
        {
            "category":"Wholesale",
            "subcategory":"Medical Equipment & Supplies",
            "type":"Manufacturing & Wholesale Goods"
        }
    ],
    "sg:phone":"+1 563 386 3030",
    "sg:postcode":"52806",
    "sg:province":"IA",
    "sg:tags":[
        "optical"
    ],
    "wof:name":"Soderberg Inc",
    "wof:placetype":"venue"
},
  "geometry": {"coordinates":[-90.57137899999999,41.582623],"type":"Point"}
}