{
  "type": "Feature",
  "properties": {
    "iso:country":"US",
    "sg:address":"867 Lynkaylee Dr",
    "sg:city":"Waterloo",
    "sg:classifiers":[
        {
            "category":"Recreation",
            "subcategory":"Arcade",
            "type":"Entertainment"
        }
    ],
    "sg:phone":"+1 319 234 1875",
    "sg:postcode":"50701",
    "sg:province":"IA",
    "sg:tags":[
        "amusement",
        "devices"
    ],
    "wof:name":"Ace Amusements",
    "wof:placetype":"venue"
},
  "geometry": {"coordinates":[-92.37105099999999,42.462446],"type":"Point"}
}