{
  "type": "Feature",
  "properties": {
    "addr:full":"504 12th St Kalona IA 52247",
    "addr:housenumber":"504",
    "addr:postcode":"52247",
    "addr:street":"12Th St",
    "iso:country":"US",
    "sg:address":"504 12th St",
    "sg:city":"Kalona",
    "sg:classifiers":[
        {
            "category":"Retail",
            "subcategory":"Funeral Services",
            "type":"Services"
        }
    ],
    "sg:phone":"+1 319 656 3100",
    "sg:postcode":"52247",
    "sg:province":"IA",
    "sg:tags":[
        "plan"
    ],
    "wof:name":"Funeral News Yoder-Powell",
    "wof:placetype":"venue"
},
  "geometry": {"coordinates":[-91.697318,41.486609],"type":"Point"}
}