{
  "type": "Feature",
  "properties": {
    "addr:full":"2080 Yankee Ave Durant IA 52747",
    "addr:housenumber":"2080",
    "addr:postcode":"52747",
    "addr:street":"Yankee Ave",
    "iso:country":"US",
    "sg:address":"2080 Yankee Ave",
    "sg:city":"Durant",
    "sg:classifiers":[
        {
            "category":"Farming",
            "subcategory":"Livestock Farm",
            "type":"Manufacturing & Wholesale Goods"
        }
    ],
    "sg:phone":"+1 563 785 6520",
    "sg:postcode":"52747",
    "sg:province":"IA",
    "sg:tags":[
        "animal",
        "general"
    ],
    "wof:name":"Grant Lilienthal Farm",
    "wof:placetype":"venue"
},
  "geometry": {"coordinates":[-90.91907999999999,41.643578],"type":"Point"}
}