{
  "type": "Feature",
  "properties": {
    "addr:full":"11021 Red Fox Ridge Council Bluffs IA 51503",
    "addr:housenumber":"11021",
    "addr:postcode":"51503",
    "addr:street":"Red Fox Ridge",
    "iso:country":"US",
    "sg:address":"11021 Red Fox Ridge",
    "sg:city":"Council Bluffs",
    "sg:classifiers":[
        {
            "category":"Wholesale",
            "subcategory":"Home Furnishings",
            "type":"Manufacturing & Wholesale Goods"
        }
    ],
    "sg:phone":"+1 712 366 1787",
    "sg:postcode":"51503",
    "sg:province":"IA",
    "wof:name":"Swansons Reflections",
    "wof:placetype":"venue"
},
  "geometry": {"coordinates":[-95.759325,41.174571],"type":"Point"}
}