{
  "type": "Feature",
  "properties": {
    "iso:country":"US",
    "sg:address":"120 35th St",
    "sg:city":"Marion",
    "sg:classifiers":[
        {
            "category":"Building & Trades",
            "subcategory":"Construction",
            "type":"Services"
        }
    ],
    "sg:phone":"+1 319 377 6970",
    "sg:postcode":"52302",
    "sg:province":"IA",
    "sg:tags":[
        "concrete",
        "contractor"
    ],
    "wof:name":"Delaney & Kelly Construction",
    "wof:placetype":"venue"
},
  "geometry": {"coordinates":[-91.57437,42.029309],"type":"Point"}
}