{
  "type": "Feature",
  "properties": {
    "addr:full":"57293 150th St Story City IA 50236",
    "addr:housenumber":"57293",
    "addr:postcode":"50236",
    "addr:street":"150Th St",
    "iso:country":"US",
    "sg:address":"57293 150th St",
    "sg:city":"Story City",
    "sg:classifiers":[
        {
            "category":"Retail",
            "subcategory":"Repair Shop",
            "type":"Services"
        }
    ],
    "sg:phone":"+1 515 733 4184",
    "sg:postcode":"50236",
    "sg:province":"IA",
    "sg:tags":[
        "taxidermist"
    ],
    "wof:name":"Mike Peterson Taxidermy",
    "wof:placetype":"venue"
},
  "geometry": {"coordinates":[-93.557725,42.137412],"type":"Point"}
}