{
  "type": "Feature",
  "properties": {
    "iso:country":"US",
    "sg:address":"1210 Walworth Ave",
    "sg:city":"Anamosa",
    "sg:classifiers":[
        {
            "category":"Government",
            "subcategory":"Office",
            "type":"Public Place"
        }
    ],
    "sg:phone":"+1 319 462 2566",
    "sg:postcode":"52205",
    "sg:province":"IA",
    "sg:tags":[
        "village"
    ],
    "wof:name":"Anamosa City Public Svc",
    "wof:placetype":"venue"
},
  "geometry": {"coordinates":[-91.29070299999999,42.102748],"type":"Point"}
}