{
  "type": "Feature",
  "properties": {
    "iso:country":"US",
    "sg:address":"113 Reynolds Pl",
    "sg:city":"Hiawatha",
    "sg:classifiers":[
        {
            "category":"Utilities",
            "subcategory":"Refuse",
            "type":"Services"
        }
    ],
    "sg:phone":"+1 319 395 7219",
    "sg:postcode":"52233",
    "sg:province":"IA",
    "sg:tags":[
        "garbage",
        "collection"
    ],
    "wof:name":"Carter's Leasing",
    "wof:placetype":"venue"
},
  "geometry": {"coordinates":[-91.67203000000001,42.046992],"type":"Point"}
}