{
  "type": "Feature",
  "properties": {
    "iso:country":"US",
    "sg:address":"76486 Carroll Ln",
    "sg:city":"Anita",
    "sg:classifiers":[
        {
            "category":"Farming",
            "subcategory":"Livestock Farm",
            "type":"Manufacturing & Wholesale Goods"
        }
    ],
    "sg:phone":"+1 712 762 3234",
    "sg:postcode":"50020",
    "sg:province":"IA",
    "sg:tags":[
        "beef",
        "feedlot",
        "cattle"
    ],
    "wof:name":"Ronald Wittrock",
    "wof:placetype":"venue"
},
  "geometry": {"coordinates":[-94.724739,41.468022],"type":"Point"}
}