{
  "type": "Feature",
  "properties": {
    "addr:full":"1316 US Hwy 61 Delmar IA 52037",
    "addr:housenumber":"1316",
    "addr:postcode":"52037",
    "addr:street":"Us Hwy 61",
    "iso:country":"US",
    "sg:address":"1316 US Hwy 61",
    "sg:city":"Delmar",
    "sg:classifiers":[
        {
            "category":"Farming",
            "subcategory":"Farm",
            "type":"Manufacturing & Wholesale Goods"
        }
    ],
    "sg:phone":"+1 563 674 4292",
    "sg:postcode":"52037",
    "sg:province":"IA",
    "sg:tags":[
        "crop",
        "general"
    ],
    "wof:name":"McAndrew John",
    "wof:placetype":"venue"
},
  "geometry": {"coordinates":[-90.65507599999999,41.986558],"type":"Point"}
}