{
  "type": "Feature",
  "properties": {
    "addr:full":"1012 4th Ave E Oskaloosa IA 52577",
    "addr:housenumber":"1012",
    "addr:postcode":"52577",
    "addr:street":"4Th Ave E Oskaloosa",
    "iso:country":"US",
    "sg:address":"1012 4th Ave E",
    "sg:city":"Oskaloosa",
    "sg:classifiers":[
        {
            "category":"Building & Trades",
            "subcategory":"Construction",
            "type":"Services"
        }
    ],
    "sg:phone":"+1 641 673 9210",
    "sg:postcode":"52577",
    "sg:province":"IA",
    "sg:tags":[
        "general",
        "contractor"
    ],
    "wof:name":"Buck Vander Wilt Builders",
    "wof:placetype":"venue"
},
  "geometry": {"coordinates":[-92.63195899999999,41.291726],"type":"Point"}
}