{
  "type": "Feature",
  "properties": {
    "addr:full":"101 Ram Dr Jefferson IA 50129",
    "addr:housenumber":"101",
    "addr:postcode":"50129",
    "addr:street":"Ram Dr",
    "iso:country":"US",
    "sg:address":"101 Ram Dr",
    "sg:city":"Jefferson",
    "sg:classifiers":[
        {
            "category":"Education",
            "subcategory":"School",
            "type":"Public Place"
        }
    ],
    "sg:phone":"+1 515 386 2188",
    "sg:postcode":"50129",
    "sg:province":"IA",
    "sg:website":"www.jefferson-scranton.k12.ia.us",
    "wof:name":"Jefferson Senior High School",
    "wof:placetype":"venue"
},
  "geometry": {"coordinates":[-94.37477699999999,42.002691],"type":"Point"}
}