{
  "type": "Feature",
  "properties": {
    "addr:full":"2660 Sheridan St Davenport IA 52803",
    "addr:housenumber":"2660",
    "addr:postcode":"52803",
    "addr:street":"Sheridan St",
    "iso:country":"US",
    "sg:address":"2660 Sheridan St",
    "sg:city":"Davenport",
    "sg:classifiers":[
        {
            "category":"Farming",
            "subcategory":"Farm",
            "type":"Manufacturing & Wholesale Goods"
        }
    ],
    "sg:phone":"+1 563 324 2397",
    "sg:postcode":"52803",
    "sg:province":"IA",
    "wof:name":"Three Corner Farms",
    "wof:placetype":"venue"
},
  "geometry": {"coordinates":[-90.57451,41.547288],"type":"Point"}
}