{
  "type": "Feature",
  "properties": {
    "iso:country":"US",
    "sg:address":"128 E High St",
    "sg:city":"Toledo",
    "sg:classifiers":[
        {
            "category":"Insurance",
            "subcategory":"Insurance Agent",
            "type":"Services"
        }
    ],
    "sg:phone":"+1 641 484 5002",
    "sg:postcode":"52342",
    "sg:province":"IA",
    "wof:name":"William Moulton",
    "wof:placetype":"venue"
},
  "geometry": {"coordinates":[-92.577941,41.995529],"type":"Point"}
}