{
  "type": "Feature",
  "properties": {
    "addr:full":"2456 Mission Ave New Hampton IA 50659",
    "addr:housenumber":"2456",
    "addr:postcode":"50659",
    "addr:street":"Mission Ave",
    "iso:country":"US",
    "sg:address":"2456 Mission Ave",
    "sg:city":"New Hampton",
    "sg:classifiers":[
        {
            "category":"Retail",
            "subcategory":"Repair Shop",
            "type":"Services"
        }
    ],
    "sg:phone":"+1 641 394 2609",
    "sg:postcode":"50659",
    "sg:province":"IA",
    "wof:name":"Heit Repair",
    "wof:placetype":"venue"
},
  "geometry": {"coordinates":[-92.29854400000001,43.000206],"type":"Point"}
}