{
  "type": "Feature",
  "properties": {
    "iso:country":"US",
    "sg:address":"3124 Aspen Rd",
    "sg:city":"Ames",
    "sg:classifiers":[
        {
            "category":"Building & Trades",
            "subcategory":"Construction",
            "type":"Services"
        }
    ],
    "sg:phone":"+1 515 296 1060",
    "sg:postcode":"50014",
    "sg:province":"IA",
    "sg:tags":[
        "company"
    ],
    "wof:name":"Jon Hunziker Construction",
    "wof:placetype":"venue"
},
  "geometry": {"coordinates":[-93.654043,42.051587],"type":"Point"}
}