{
  "type": "Feature",
  "properties": {
    "iso:country":"US",
    "sg:address":"3116 W 73rd St",
    "sg:city":"Davenport",
    "sg:classifiers":[
        {
            "category":"Autos & Motor Vehicles",
            "subcategory":"Auto Supplies",
            "type":"Retail Goods"
        }
    ],
    "sg:phone":"+1 563 386 8470",
    "sg:postcode":"52806",
    "sg:province":"IA",
    "sg:tags":[
        "recap",
        "repair",
        "retread",
        "tire"
    ],
    "sg:website":"http://www.bauerbuilt.com",
    "wof:name":"Bauer Built Tire",
    "wof:placetype":"venue"
},
  "geometry": {"coordinates":[-90.620699,41.594912],"type":"Point"}
}