{
  "type": "Feature",
  "properties": {
    "iso:country":"US",
    "sg:address":"443 N Lawler St",
    "sg:city":"Postville",
    "sg:classifiers":[
        {
            "category":"Professional",
            "subcategory":"Lawyer & Legal Services",
            "type":"Services"
        }
    ],
    "sg:phone":"+1 563 864 7290",
    "sg:postcode":"52162",
    "sg:province":"IA",
    "sg:tags":[
        "attorney"
    ],
    "wof:name":"Mueller Law Office",
    "wof:placetype":"venue"
},
  "geometry": {"coordinates":[-91.56831,43.088797],"type":"Point"}
}