{
  "type": "Feature",
  "properties": {
    "iso:country":"US",
    "sg:address":"709 Creek Top",
    "sg:city":"Council Bluffs",
    "sg:classifiers":[
        {
            "category":"Shopping",
            "type":"Retail Goods"
        }
    ],
    "sg:phone":"+1 712 328 0660",
    "sg:postcode":"51503",
    "sg:province":"IA",
    "sg:tags":[
        "monument"
    ],
    "wof:name":"J F Bloom Monument Co",
    "wof:placetype":"venue"
},
  "geometry": {"coordinates":[-95.85592800000001,41.262193],"type":"Point"}
}