{
  "type": "Feature",
  "properties": {
    "iso:country":"US",
    "sg:address":"104 S 15th St",
    "sg:city":"Denison",
    "sg:classifiers":[
        {
            "category":"Travel",
            "subcategory":"Hotels & Motels",
            "type":"Entertainment"
        }
    ],
    "sg:phone":"+1 712 263 8826",
    "sg:postcode":"51442",
    "sg:province":"IA",
    "sg:tags":[
        "breakfast",
        "accommodation",
        "bed"
    ],
    "wof:name":"Conner's Corner Bed & Brkfst",
    "wof:placetype":"venue"
},
  "geometry": {"coordinates":[-95.351811,42.015563],"type":"Point"}
}