{
  "type": "Feature",
  "properties": {
    "iso:country":"US",
    "sg:address":"13847 780th Ave",
    "sg:city":"Le Roy",
    "sg:classifiers":[
        {
            "category":"Farming",
            "subcategory":"Livestock Farm",
            "type":"Manufacturing & Wholesale Goods"
        }
    ],
    "sg:phone":"+1 507 324 5946",
    "sg:postcode":"55951",
    "sg:province":"IA",
    "sg:tags":[
        "beef",
        "feedlot",
        "cattle"
    ],
    "wof:name":"David Kasten",
    "wof:placetype":"venue"
},
  "geometry": {"coordinates":[-92.48939900000001,43.558136],"type":"Point"}
}