{
  "type": "Feature",
  "properties": {
    "addr:full":"305 3rd St Wall Lake IA 51466",
    "addr:housenumber":"305",
    "addr:postcode":"51466",
    "addr:street":"3Rd St",
    "iso:country":"US",
    "sg:address":"305 3rd St",
    "sg:city":"Wall Lake",
    "sg:classifiers":[
        {
            "category":"Recreation",
            "type":"Entertainment"
        }
    ],
    "sg:phone":"+1 712 664 2875",
    "sg:postcode":"51466",
    "sg:province":"IA",
    "sg:tags":[
        "pool",
        "swimming"
    ],
    "wof:name":"Wall Lake Swimming Pool",
    "wof:placetype":"venue"
},
  "geometry": {"coordinates":[-95.08735799999999,42.271807],"type":"Point"}
}