{
  "type": "Feature",
  "properties": {
    "iso:country":"US",
    "sg:address":"3727 240th St",
    "sg:city":"Victor",
    "sg:phone":"+1 319 647 3563",
    "sg:postcode":"52347",
    "sg:province":"IA",
    "sg:tags":[
        "farm",
        "corn",
        "soybean"
    ],
    "wof:name":"Mark McGrory",
    "wof:placetype":"venue"
},
  "geometry": {"coordinates":[-92.31870499999999,41.757811],"type":"Point"}
}