{
  "type": "Feature",
  "properties": {
    "addr:full":"210 Shaw St Russell IA 50238",
    "addr:housenumber":"210",
    "addr:postcode":"50238",
    "addr:street":"Shaw St",
    "iso:country":"US",
    "sg:address":"210 Shaw St",
    "sg:city":"Russell",
    "sg:classifiers":[
        {
            "category":"Bars & Pubs",
            "type":"Food & Drink"
        }
    ],
    "sg:phone":"+1 641 535 4802",
    "sg:postcode":"50238",
    "sg:province":"IA",
    "sg:tags":[
        "drinking"
    ],
    "wof:name":"Southside",
    "wof:placetype":"venue"
},
  "geometry": {"coordinates":[-93.19604200000001,40.98371],"type":"Point"}
}