{
  "type": "Feature",
  "properties": {
    "iso:country":"US",
    "sg:address":"112 E Main St",
    "sg:city":"Lime Springs",
    "sg:classifiers":[
        {
            "category":"Education",
            "subcategory":"Library",
            "type":"Public Place"
        }
    ],
    "sg:phone":"+1 563 566 2207",
    "sg:postcode":"52155",
    "sg:province":"IA",
    "wof:name":"Public Library",
    "wof:placetype":"venue"
},
  "geometry": {"coordinates":[-92.28211,43.449546],"type":"Point"}
}