{
  "type": "Feature",
  "properties": {
    "iso:country":"US",
    "sg:address":"2476 NE 46th Ave",
    "sg:city":"Des Moines",
    "sg:classifiers":[
        {
            "category":"Wholesale",
            "subcategory":"Auto Parts",
            "type":"Manufacturing & Wholesale Goods"
        }
    ],
    "sg:phone":"+1 515 265 0611",
    "sg:postcode":"50317",
    "sg:province":"IA",
    "sg:tags":[
        "automobile",
        "rebuilt"
    ],
    "wof:name":"Gil's Auto Svc & Parts",
    "wof:placetype":"venue"
},
  "geometry": {"coordinates":[-93.57556099999999,41.644109],"type":"Point"}
}