{
  "type": "Feature",
  "properties": {
    "iso:country":"US",
    "sg:address":"605 E State St",
    "sg:city":"Algona",
    "sg:classifiers":[
        {
            "category":"Government",
            "subcategory":"Office",
            "type":"Public Place"
        }
    ],
    "sg:phone":"+1 515 295 7782",
    "sg:postcode":"50511",
    "sg:province":"IA",
    "wof:name":"Farm Service Agency",
    "wof:placetype":"venue"
},
  "geometry": {"coordinates":[-94.230514,43.06897],"type":"Point"}
}