{
  "type": "Feature",
  "properties": {
    "iso:country":"US",
    "sg:address":"505 W Hwy",
    "sg:city":"Alta",
    "sg:classifiers":[
        {
            "category":"Organizations",
            "subcategory":"Religious Organization",
            "type":"Services"
        }
    ],
    "sg:phone":"+1 712 200 2321",
    "sg:postcode":"51002",
    "sg:province":"IA",
    "sg:tags":[
        "church"
    ],
    "wof:name":"Church Of Christ",
    "wof:placetype":"venue"
},
  "geometry": {"coordinates":[-95.308988,42.670458],"type":"Point"}
}