{
  "type": "Feature",
  "properties": {
    "iso:country":"US",
    "sg:address":"306 200th St",
    "sg:city":"Whittemore",
    "sg:phone":"+1 515 884 2705",
    "sg:postcode":"50598",
    "sg:province":"IA",
    "sg:tags":[
        "agricultural",
        "product"
    ],
    "wof:name":"Dahlhauser Agricultural LTD",
    "wof:placetype":"venue"
},
  "geometry": {"coordinates":[-94.402461,43.052816],"type":"Point"}
}