{
  "type": "Feature",
  "properties": {
    "iso:country":"US",
    "sg:address":"2455 Apache Ct",
    "sg:city":"Sioux City",
    "sg:classifiers":[
        {
            "category":"Professional",
            "type":"Services"
        }
    ],
    "sg:phone":"+1 712 239 5229",
    "sg:postcode":"51104",
    "sg:province":"IA",
    "wof:name":"Johns Home Service",
    "wof:placetype":"venue"
},
  "geometry": {"coordinates":[-96.378787,42.534635],"type":"Point"}
}