{
  "type": "Feature",
  "properties": {
    "iso:country":"US",
    "sg:address":"2790 N Dodge St",
    "sg:city":"Iowa City",
    "sg:classifiers":[
        {
            "category":"Restaurant",
            "type":"Food & Drink"
        }
    ],
    "sg:phone":"+1 319 351 3051",
    "sg:postcode":"52245",
    "sg:province":"IA",
    "wof:name":"A & W Family Restaurant",
    "wof:placetype":"venue"
},
  "geometry": {"coordinates":[-91.49850000000001,41.687985],"type":"Point"}
}