{
  "type": "Feature",
  "properties": {
    "addr:full":"726 N E St Oskaloosa IA 52577",
    "addr:housenumber":"726",
    "addr:postcode":"52577",
    "addr:street":"N E St",
    "iso:country":"US",
    "sg:address":"726 N E St",
    "sg:city":"Oskaloosa",
    "sg:classifiers":[
        {
            "category":"Education",
            "subcategory":"School",
            "type":"Public Place"
        }
    ],
    "sg:phone":"+1 641 672 2174",
    "sg:postcode":"52577",
    "sg:province":"IA",
    "sg:website":"www.oskaloosa.pvt.k12.ia.us",
    "wof:name":"Oskaloosa Christian School",
    "wof:placetype":"venue"
},
  "geometry": {"coordinates":[-92.65051800000001,41.301595],"type":"Point"}
}