{
  "type": "Feature",
  "properties": {
    "iso:country":"US",
    "sg:address":"220 17th Ave",
    "sg:city":"Council Bluffs",
    "sg:classifiers":[
        {
            "category":"Retail",
            "subcategory":"Auto Repair",
            "type":"Services"
        }
    ],
    "sg:phone":"+1 712 388 3772",
    "sg:postcode":"51503",
    "sg:province":"IA",
    "wof:name":"Terry's Auto Repair Inc",
    "wof:placetype":"venue"
},
  "geometry": {"coordinates":[-95.846603,41.245701],"type":"Point"}
}