{
  "type": "Feature",
  "properties": {
    "iso:country":"US",
    "sg:address":"1095 Walnut Ave",
    "sg:city":"Riverside",
    "sg:classifiers":[
        {
            "category":"Building & Trades",
            "subcategory":"Landscaping Services",
            "type":"Services"
        }
    ],
    "sg:phone":"+1 319 648 4072",
    "sg:postcode":"52327",
    "sg:province":"IA",
    "wof:name":"Green Acres",
    "wof:placetype":"venue"
},
  "geometry": {"coordinates":[-91.534845,41.497374],"type":"Point"}
}