{
  "type": "Feature",
  "properties": {
    "iso:country":"US",
    "sg:address":"204 Iowa Ave NW",
    "sg:city":"Orange City",
    "sg:classifiers":[
        {
            "category":"Professional",
            "subcategory":"Management & Consulting",
            "type":"Services"
        }
    ],
    "sg:phone":"+1 712 737 8920",
    "sg:postcode":"51041",
    "sg:province":"IA",
    "sg:tags":[
        "business"
    ],
    "wof:name":"Sherwood Forest Grants LLC",
    "wof:placetype":"venue"
},
  "geometry": {"coordinates":[-96.06671799999999,43.008346],"type":"Point"}
}