{
  "type": "Feature",
  "properties": {
    "iso:country":"US",
    "sg:address":"202 Kentucky Ave SW",
    "sg:city":"Orange City",
    "sg:classifiers":[
        {
            "category":"Shopping",
            "type":"Retail Goods"
        }
    ],
    "sg:phone":"+1 712 737 4143",
    "sg:postcode":"51041",
    "sg:province":"IA",
    "sg:tags":[
        "outdoor",
        "lighting",
        "specialty"
    ],
    "wof:name":"Holiday Lites & Trim",
    "wof:placetype":"venue"
},
  "geometry": {"coordinates":[-96.06926799999999,43.00491],"type":"Point"}
}