{
  "type": "Feature",
  "properties": {
    "iso:country":"US",
    "sg:address":"223 2nd Ave SW",
    "sg:city":"Cresco",
    "sg:classifiers":[
        {
            "category":"Manufacturing",
            "subcategory":"Signs",
            "type":"Manufacturing & Wholesale Goods"
        }
    ],
    "sg:phone":"+1 563 547 4476",
    "sg:postcode":"52136",
    "sg:province":"IA",
    "wof:name":"Signs & Designs",
    "wof:placetype":"venue"
},
  "geometry": {"coordinates":[-92.118951,43.371049],"type":"Point"}
}