{
  "type": "Feature",
  "properties": {
    "addr:full":"3911 Calhoun Ave Ames IA 50010",
    "addr:housenumber":"3911",
    "addr:postcode":"50010",
    "addr:street":"Calhoun Ave",
    "iso:country":"US",
    "sg:address":"3911 Calhoun Ave",
    "sg:city":"Ames",
    "sg:classifiers":[
        {
            "category":"Social Services",
            "subcategory":"Adult Care",
            "type":"Services"
        }
    ],
    "sg:phone":"+1 515 233 1323",
    "sg:postcode":"50010",
    "sg:province":"IA",
    "sg:tags":[
        "home",
        "group"
    ],
    "wof:name":"Community Life Program",
    "wof:placetype":"venue"
},
  "geometry": {"coordinates":[-93.62415799999999,42.058902],"type":"Point"}
}