{
  "type": "Feature",
  "properties": {
    "addr:full":"1212 S Gilbert Ct Iowa City IA 52240",
    "addr:housenumber":"1212",
    "addr:postcode":"52240",
    "addr:street":"S Gilbert Ct",
    "iso:country":"US",
    "sg:address":"1212 S Gilbert Ct",
    "sg:city":"Iowa City",
    "sg:classifiers":[
        {
            "category":"Retail",
            "subcategory":"Auto Repair",
            "type":"Services"
        }
    ],
    "sg:phone":"+1 319 354 1055",
    "sg:postcode":"52240",
    "sg:province":"IA",
    "sg:tags":[
        "repairing",
        "automobile"
    ],
    "wof:name":"Farnsworth Automotive Air",
    "wof:placetype":"venue"
},
  "geometry": {"coordinates":[-91.529775,41.646505],"type":"Point"}
}