{
  "type": "Feature",
  "properties": {
    "iso:country":"US",
    "sg:address":"1000 Cedar Cross Rd",
    "sg:city":"Dubuque",
    "sg:classifiers":[
        {
            "category":"Home & Garden",
            "subcategory":"Furniture",
            "type":"Retail Goods"
        }
    ],
    "sg:phone":"+1 563 557 1177",
    "sg:postcode":"52003",
    "sg:province":"IA",
    "sg:tags":[
        "equipment",
        "kitchen",
        "cabinet"
    ],
    "wof:name":"Tri-State Kitchens",
    "wof:placetype":"venue"
},
  "geometry": {"coordinates":[-90.709076,42.479464],"type":"Point"}
}