{
  "type": "Feature",
  "properties": {
    "iso:country":"US",
    "sg:address":"2690 Rockdale Rd",
    "sg:city":"Dubuque",
    "sg:classifiers":[
        {
            "category":"Banks & Credit Unions",
            "subcategory":"Bank",
            "type":"Services"
        }
    ],
    "sg:phone":"+1 563 589 2170",
    "sg:postcode":"52003",
    "sg:province":"IA",
    "wof:name":"Dubuque Bank & Trust",
    "wof:placetype":"venue"
},
  "geometry": {"coordinates":[-90.672847,42.470204],"type":"Point"}
}