{
  "type": "Feature",
  "properties": {
    "iso:country":"US",
    "sg:address":"6200 Aurora Ave",
    "sg:city":"Urbandale",
    "sg:classifiers":[
        {
            "category":"Professional",
            "subcategory":"Advertising",
            "type":"Services"
        }
    ],
    "sg:phone":"+1 515 331 3206",
    "sg:postcode":"50322",
    "sg:province":"IA",
    "sg:tags":[
        "counselor"
    ],
    "wof:name":"Insight Advertising Marketing",
    "wof:placetype":"venue"
},
  "geometry": {"coordinates":[-93.70407,41.636658],"type":"Point"}
}