{
  "type": "Feature",
  "properties": {
    "addr:full":"518 Main St Dumont IA 50625",
    "addr:housenumber":"518",
    "addr:postcode":"50625",
    "addr:street":"Main St",
    "iso:country":"US",
    "sg:address":"518 Main St",
    "sg:city":"Dumont",
    "sg:classifiers":[
        {
            "category":"Sports & Exercise",
            "subcategory":"Bowling",
            "type":"Entertainment"
        }
    ],
    "sg:phone":"+1 641 857 3787",
    "sg:postcode":"50625",
    "sg:province":"IA",
    "sg:tags":[
        "center"
    ],
    "wof:name":"Community Bowl Of Dumont",
    "wof:placetype":"venue"
},
  "geometry": {"coordinates":[-92.97307600000001,42.749919],"type":"Point"}
}