{
  "type": "Feature",
  "properties": {
    "addr:full":"4522 W 55D Ave N Newton IA 50208",
    "addr:housenumber":"4522",
    "addr:postcode":"50208",
    "addr:street":"W 55D Ave N",
    "iso:country":"US",
    "sg:address":"4522 W 55D Ave N",
    "sg:city":"Newton",
    "sg:classifiers":[
        {
            "category":"Education",
            "subcategory":"Special Training",
            "type":"Public Place"
        }
    ],
    "sg:phone":"+1 641 791 0631",
    "sg:postcode":"50208",
    "sg:province":"IA",
    "sg:tags":[
        "program"
    ],
    "wof:name":"Dale Carnegie Training",
    "wof:placetype":"venue"
},
  "geometry": {"coordinates":[-93.110991,41.7537],"type":"Point"}
}