{
  "type": "Feature",
  "properties": {
    "addr:full":"2318 W 10th St Davenport IA 52804",
    "addr:housenumber":"2318",
    "addr:postcode":"52804",
    "addr:street":"W 10Th St",
    "iso:country":"US",
    "sg:address":"2318 W 10th St",
    "sg:city":"Davenport",
    "sg:classifiers":[
        {
            "category":"Organizations",
            "subcategory":"Religious Organization",
            "type":"Services"
        }
    ],
    "sg:phone":"+1 563 324 6610",
    "sg:postcode":"52804",
    "sg:province":"IA",
    "wof:name":"Baha'i Center",
    "wof:placetype":"venue"
},
  "geometry": {"coordinates":[-90.61209599999999,41.530179],"type":"Point"}
}