{
  "type": "Feature",
  "properties": {
    "iso:country":"US",
    "sg:address":"2701 Westown Pkwy",
    "sg:city":"West Des Moines",
    "sg:classifiers":[
        {
            "category":"Travel",
            "subcategory":"Hotels & Motels",
            "type":"Entertainment"
        }
    ],
    "sg:phone":"+1 515 327 9100",
    "sg:postcode":"50266",
    "sg:province":"IA",
    "wof:name":"Studio Plus Hotels Inc",
    "wof:placetype":"venue"
},
  "geometry": {"coordinates":[-93.74203300000001,41.596267],"type":"Point"}
}