{
  "type": "Feature",
  "properties": {
    "addr:full":"3434 W Broadway Council Bluffs IA 51501",
    "addr:housenumber":"3434",
    "addr:postcode":"51501",
    "addr:street":"W Broadway",
    "iso:country":"US",
    "sg:address":"3434 W Broadway",
    "sg:city":"Council Bluffs",
    "sg:classifiers":[
        {
            "category":"Health Services",
            "subcategory":"Doctor",
            "type":"Services"
        }
    ],
    "sg:phone":"+1 712 328 7182",
    "sg:postcode":"51501",
    "sg:province":"IA",
    "wof:name":"Jennie Edmundson Physical Therapy",
    "wof:placetype":"venue"
},
  "geometry": {"coordinates":[-95.900221,41.262067],"type":"Point"}
}