{
  "type": "Feature",
  "properties": {
    "iso:country":"US",
    "sg:address":"5820 320th St",
    "sg:city":"Sanborn",
    "sg:classifiers":[
        {
            "category":"Autos & Motor Vehicles",
            "subcategory":"Automobile Sales",
            "type":"Retail Goods"
        },
        {
            "category":"Retail",
            "subcategory":"Auto Repair",
            "type":"Services"
        }
    ],
    "sg:phone":"+1 712 729 3397",
    "sg:postcode":"51248",
    "sg:province":"IA",
    "sg:tags":[
        "automotive",
        "dealer",
        "car"
    ],
    "wof:name":"Sampson Auto Center",
    "wof:placetype":"venue"
},
  "geometry": {"coordinates":[-95.64017200000001,43.186045],"type":"Point"}
}