{
  "type": "Feature",
  "properties": {
    "iso:country":"US",
    "sg:address":"4472 Fagan Rd",
    "sg:city":"Zwingle",
    "sg:classifiers":[
        {
            "category":"Wholesale",
            "subcategory":"Meat",
            "type":"Manufacturing & Wholesale Goods"
        }
    ],
    "sg:phone":"+1 563 879 3711",
    "sg:postcode":"52079",
    "sg:province":"IA",
    "sg:tags":[
        "broker"
    ],
    "wof:name":"Genesis Brokerage",
    "wof:placetype":"venue"
},
  "geometry": {"coordinates":[-90.763125,42.356304],"type":"Point"}
}