{
  "type": "Feature",
  "properties": {
    "addr:full":"207 Buffalo St Strawberry Point IA 52076",
    "addr:housenumber":"207",
    "addr:postcode":"52076",
    "addr:street":"Buffalo St",
    "iso:country":"US",
    "sg:address":"207 Buffalo St",
    "sg:city":"Strawberry Point",
    "sg:classifiers":[
        {
            "category":"Organizations",
            "subcategory":"Religious Organization",
            "type":"Services"
        }
    ],
    "sg:phone":"+1 563 933 4100",
    "sg:postcode":"52076",
    "sg:province":"IA",
    "sg:tags":[
        "clergy"
    ],
    "wof:name":"Albert Hock",
    "wof:placetype":"venue"
},
  "geometry": {"coordinates":[-91.53956100000001,42.682254],"type":"Point"}
}