{
  "type": "Feature",
  "properties": {
    "addr:full":"21551 375th Ave Bellevue IA 52031",
    "addr:housenumber":"21551",
    "addr:postcode":"52031",
    "addr:street":"375Th Ave",
    "iso:country":"US",
    "sg:address":"21551 375th Ave",
    "sg:city":"Bellevue",
    "sg:classifiers":[
        {
            "category":"Real Estate",
            "subcategory":"Real Estate Operator",
            "type":"Services"
        }
    ],
    "sg:phone":"+1 563 872 5481",
    "sg:postcode":"52031",
    "sg:province":"IA",
    "sg:tags":[
        "property",
        "lessor"
    ],
    "wof:name":"Dale Manders",
    "wof:placetype":"venue"
},
  "geometry": {"coordinates":[-90.476348,42.208034],"type":"Point"}
}