{
  "type": "Feature",
  "properties": {
    "addr:full":"1603 Hillside Dr NW Cedar Rapids IA 52405",
    "addr:housenumber":"1603",
    "addr:postcode":"52405",
    "addr:street":"Hillside Dr Nw",
    "iso:country":"US",
    "sg:address":"1603 Hillside Dr NW",
    "sg:city":"Cedar Rapids",
    "sg:classifiers":[
        {
            "category":"Building & Trades",
            "subcategory":"Cleaning & Sanitation",
            "type":"Services"
        }
    ],
    "sg:phone":"+1 319 261 0895",
    "sg:postcode":"52405",
    "sg:province":"IA",
    "sg:tags":[
        "home"
    ],
    "sg:website":"www.classactcleaning.org",
    "wof:name":"Class Act Cleaning Service",
    "wof:placetype":"venue"
},
  "geometry": {"coordinates":[-91.712416,41.98943],"type":"Point"}
}