{
  "type": "Feature",
  "properties": {
    "iso:country":"US",
    "sg:address":"901 11th St SW",
    "sg:city":"Spencer",
    "sg:classifiers":[
        {
            "category":"Sports & Exercise",
            "subcategory":"Gym",
            "type":"Entertainment"
        }
    ],
    "sg:phone":"+1 712 264 8888",
    "sg:postcode":"51301",
    "sg:province":"IA",
    "sg:tags":[
        "club",
        "health",
        "studio",
        "gymnasium"
    ],
    "wof:name":"Curves For Women",
    "wof:placetype":"venue"
},
  "geometry": {"coordinates":[-95.157212,43.126976],"type":"Point"}
}