{
  "type": "Feature",
  "properties": {
    "iso:country":"US",
    "sg:address":"2407 Towncrest Dr",
    "sg:city":"Iowa City",
    "sg:classifiers":[
        {
            "category":"Health Services",
            "subcategory":"Doctor",
            "type":"Services"
        }
    ],
    "sg:phone":"+1 319 338 1197",
    "sg:postcode":"52240",
    "sg:province":"IA",
    "sg:tags":[
        "physician",
        "surgeon"
    ],
    "sg:website":"www.ua-ic.com",
    "wof:name":"Urologic Associates",
    "wof:placetype":"venue"
},
  "geometry": {"coordinates":[-91.500676,41.648287],"type":"Point"}
}