{
  "type": "Feature",
  "properties": {
    "iso:country":"US",
    "sg:address":"221 SE Magazine Rd",
    "sg:city":"Ankeny",
    "sg:classifiers":[
        {
            "category":"Home & Garden",
            "subcategory":"Garden Supply",
            "type":"Retail Goods"
        }
    ],
    "sg:phone":"+1 515 964 9513",
    "sg:postcode":"50021",
    "sg:province":"IA",
    "sg:tags":[
        "equipment",
        "snow",
        "removal"
    ],
    "wof:name":"Mower City Plus",
    "wof:placetype":"venue"
},
  "geometry": {"coordinates":[-93.59528,41.717304],"type":"Point"}
}