{
  "type": "Feature",
  "properties": {
    "addr:full":"417 Church St Ottumwa IA 52501",
    "addr:housenumber":"417",
    "addr:postcode":"52501",
    "addr:street":"Church St",
    "iso:country":"US",
    "sg:address":"417 Church St",
    "sg:city":"Ottumwa",
    "sg:classifiers":[
        {
            "category":"Retail",
            "subcategory":"Laundry & Dry Cleaning",
            "type":"Services"
        },
        {
            "category":"Shopping",
            "subcategory":"Clothing, Apparel, & Fashions",
            "type":"Retail Goods"
        }
    ],
    "sg:phone":"+1 641 682 6109",
    "sg:postcode":"52501",
    "sg:province":"IA",
    "sg:tags":[
        "alteration"
    ],
    "wof:name":"Denise's Alterations",
    "wof:placetype":"venue"
},
  "geometry": {"coordinates":[-92.417323,41.010572],"type":"Point"}
}