{
  "type": "Feature",
  "properties": {
    "iso:country":"US",
    "sg:address":"21105 Holden Dr",
    "sg:city":"Davenport",
    "sg:classifiers":[
        {
            "category":"Building & Trades",
            "subcategory":"Plumbing",
            "type":"Services"
        }
    ],
    "sg:phone":"+1 563 391 5531",
    "sg:postcode":"52804",
    "sg:province":"IA",
    "sg:tags":[
        "plumbing",
        "contractor"
    ],
    "wof:name":"Archer Mechanical Contractors",
    "wof:placetype":"venue"
},
  "geometry": {"coordinates":[-90.56987700000001,41.611276],"type":"Point"}
}