{
  "type": "Feature",
  "properties": {
    "addr:full":"1005 Highway 5 Carlisle IA 50047",
    "addr:housenumber":"1005",
    "addr:postcode":"50047",
    "addr:street":"Highway 5",
    "iso:country":"US",
    "sg:address":"1005 Highway 5",
    "sg:city":"Carlisle",
    "sg:classifiers":[
        {
            "category":"Restaurant",
            "type":"Food & Drink"
        }
    ],
    "sg:phone":"+1 515 989 0011",
    "sg:postcode":"50047",
    "sg:province":"IA",
    "sg:tags":[
        "pizza"
    ],
    "sg:website":"www.caseys.com",
    "wof:name":"Casey's Carry Out Pizza",
    "wof:placetype":"venue"
},
  "geometry": {"coordinates":[-93.497803,41.498402],"type":"Point"}
}