{
  "type": "Feature",
  "properties": {
    "addr:full":"1101 Sunnyside Ln Atlantic IA 50022",
    "addr:housenumber":"1101",
    "addr:postcode":"50022",
    "addr:street":"Sunnyside Ln",
    "iso:country":"US",
    "sg:address":"1101 Sunnyside Ln",
    "sg:city":"Atlantic",
    "sg:classifiers":[
        {
            "category":"Shopping",
            "subcategory":"Department Store",
            "type":"Retail Goods"
        }
    ],
    "sg:phone":"+1 712 243 4040",
    "sg:postcode":"50022",
    "sg:province":"IA",
    "sg:tags":[
        "shop"
    ],
    "sg:website":"www.pamida.com",
    "wof:name":"Pamida",
    "wof:placetype":"venue"
},
  "geometry": {"coordinates":[-95.027762,41.400862],"type":"Point"}
}