{
  "type": "Feature",
  "properties": {
    "iso:country":"US",
    "sg:address":"111 Mulberry Ave",
    "sg:city":"Muscatine",
    "sg:classifiers":[
        {
            "category":"Autos & Motor Vehicles",
            "subcategory":"Fuel & Gas Station",
            "type":"Retail Goods"
        }
    ],
    "sg:phone":"+1 563 263 9176",
    "sg:postcode":"52761",
    "sg:province":"IA",
    "sg:tags":[
        "oil"
    ],
    "sg:website":"www.grosjeanstire.com",
    "wof:name":"Grosjean Tire & Svc",
    "wof:placetype":"venue"
},
  "geometry": {"coordinates":[-91.040649,41.422935],"type":"Point"}
}