{
  "type": "Feature",
  "properties": {
    "iso:country":"US",
    "sg:address":"1347 220th Ave",
    "sg:city":"Calmar",
    "sg:classifiers":[
        {
            "category":"Farming",
            "subcategory":"Dairy Farm",
            "type":"Manufacturing & Wholesale Goods"
        }
    ],
    "sg:phone":"+1 563 534 7794",
    "sg:postcode":"52132",
    "sg:province":"IA",
    "wof:name":"Rudy & Germaine Holthaus",
    "wof:placetype":"venue"
},
  "geometry": {"coordinates":[-91.83895699999999,43.134962],"type":"Point"}
}