{
  "type": "Feature",
  "properties": {
    "iso:country":"US",
    "sg:address":"210 2nd St",
    "sg:city":"Kirkville",
    "sg:classifiers":[
        {
            "category":"Personal",
            "type":"Services"
        }
    ],
    "sg:phone":"+1 641 933 4847",
    "sg:postcode":"52533",
    "sg:province":"IA",
    "sg:tags":[
        "pet",
        "exercising"
    ],
    "wof:name":"Jo's Pet Sitting",
    "wof:placetype":"venue"
},
  "geometry": {"coordinates":[-92.50361700000001,41.141845],"type":"Point"}
}