{
  "type": "Feature",
  "properties": {
    "addr:full":"31554 Delta Ave Manning IA 51455",
    "addr:housenumber":"31554",
    "addr:postcode":"51455",
    "addr:street":"Delta Ave",
    "iso:country":"US",
    "sg:address":"31554 Delta Ave",
    "sg:city":"Manning",
    "sg:classifiers":[
        {
            "category":"Farming",
            "subcategory":"Livestock Farm",
            "type":"Manufacturing & Wholesale Goods"
        }
    ],
    "sg:phone":"+1 712 653 3678",
    "sg:postcode":"51455",
    "sg:province":"IA",
    "sg:tags":[
        "producer"
    ],
    "wof:name":"Wiese & Sons Hereford Breeders",
    "wof:placetype":"venue"
},
  "geometry": {"coordinates":[-95.034756,41.90208],"type":"Point"}
}