{
  "type": "Feature",
  "properties": {
    "addr:full":"605 4th St NE Hampton IA 50441",
    "addr:housenumber":"605",
    "addr:postcode":"50441",
    "addr:street":"4Th St Ne",
    "iso:country":"US",
    "sg:address":"605 4th St NE",
    "sg:city":"Hampton",
    "sg:classifiers":[
        {
            "category":"Organizations",
            "subcategory":"Religious Organization",
            "type":"Services"
        }
    ],
    "sg:phone":"+1 641 456 2285",
    "sg:postcode":"50441",
    "sg:province":"IA",
    "sg:tags":[
        "church"
    ],
    "wof:name":"First Christian Church",
    "wof:placetype":"venue"
},
  "geometry": {"coordinates":[-93.20240200000001,42.748424],"type":"Point"}
}