{
  "type": "Feature",
  "properties": {
    "iso:country":"US",
    "sg:address":"1705 14th St",
    "sg:city":"Bettendorf",
    "sg:classifiers":[
        {
            "category":"Organizations",
            "subcategory":"Community Association",
            "type":"Services"
        }
    ],
    "sg:phone":"+1 563 359 1944",
    "sg:postcode":"52722",
    "sg:province":"IA",
    "wof:name":"United Parents",
    "wof:placetype":"venue"
},
  "geometry": {"coordinates":[-90.512714,41.541619],"type":"Point"}
}