{
  "type": "Feature",
  "properties": {
    "iso:country":"US",
    "sg:address":"102 S County Rd",
    "sg:city":"Toledo",
    "sg:classifiers":[
        {
            "category":"Building & Trades",
            "subcategory":"Construction",
            "type":"Services"
        }
    ],
    "sg:phone":"+1 641 484 2304",
    "sg:postcode":"52342",
    "sg:province":"IA",
    "sg:tags":[
        "marking",
        "maintenance",
        "parking"
    ],
    "wof:name":"Toledo Public Works Mntnce",
    "wof:placetype":"venue"
},
  "geometry": {"coordinates":[-92.58172,41.99561],"type":"Point"}
}