{
  "type": "Feature",
  "properties": {
    "addr:full":"670 Mill St Toronto IA 52777",
    "addr:housenumber":"670",
    "addr:postcode":"52777",
    "addr:street":"Mill St",
    "iso:country":"US",
    "sg:address":"670 Mill St",
    "sg:city":"Toronto",
    "sg:classifiers":[
        {
            "category":"Organizations",
            "subcategory":"Religious Organization",
            "type":"Services"
        }
    ],
    "sg:phone":"+1 563 374 1761",
    "sg:postcode":"52777",
    "sg:province":"IA",
    "sg:tags":[
        "church"
    ],
    "wof:name":"St James Catholic Church",
    "wof:placetype":"venue"
},
  "geometry": {"coordinates":[-90.86455100000001,41.900312],"type":"Point"}
}