{
  "type": "Feature",
  "properties": {
    "addr:full":"752 S Oak St Iowa Falls IA 50126",
    "addr:housenumber":"752",
    "addr:postcode":"50126",
    "addr:street":"S Oak St",
    "iso:country":"US",
    "sg:address":"752 S Oak St",
    "sg:city":"Iowa Falls",
    "sg:classifiers":[
        {
            "category":"Health Services",
            "subcategory":"Chiropractor",
            "type":"Services"
        }
    ],
    "sg:phone":"+1 641 648 4211",
    "sg:postcode":"50126",
    "sg:province":"IA",
    "wof:name":"Hoover Chiropractic",
    "wof:placetype":"venue"
},
  "geometry": {"coordinates":[-93.262304,42.507035],"type":"Point"}
}