{
  "type": "Feature",
  "properties": {
    "iso:country":"US",
    "sg:address":"661 57th St",
    "sg:city":"Des Moines",
    "sg:classifiers":[
        {
            "category":"Professional",
            "subcategory":"Business Services",
            "type":"Services"
        }
    ],
    "sg:phone":"+1 515 255 2589",
    "sg:postcode":"50312",
    "sg:province":"IA",
    "sg:tags":[
        "security",
        "investigation",
        "background",
        "government"
    ],
    "wof:name":"David T Oxler",
    "wof:placetype":"venue"
},
  "geometry": {"coordinates":[-93.6948,41.588223],"type":"Point"}
}