{
  "type": "Feature",
  "properties": {
    "addr:full":"121 N Main St Holstein IA 51025",
    "addr:housenumber":"121",
    "addr:postcode":"51025",
    "addr:street":"N Main St",
    "iso:country":"US",
    "sg:address":"121 N Main St",
    "sg:city":"Holstein",
    "sg:classifiers":[
        {
            "category":"Organizations",
            "subcategory":"Community Association",
            "type":"Services"
        }
    ],
    "sg:phone":"+1 712 368 2597",
    "sg:postcode":"51025",
    "sg:province":"IA",
    "sg:tags":[
        "building",
        "nonresidential"
    ],
    "wof:name":"Veterans Memorial Hall",
    "wof:placetype":"venue"
},
  "geometry": {"coordinates":[-95.54485699999999,42.49034],"type":"Point"}
}