{
  "type": "Feature",
  "properties": {
    "iso:country":"US",
    "sg:address":"619 5th St",
    "sg:city":"Durant",
    "sg:classifiers":[
        {
            "category":"Health Services",
            "subcategory":"Doctor",
            "type":"Services"
        }
    ],
    "sg:phone":"+1 563 785 6664",
    "sg:postcode":"52747",
    "sg:province":"IA",
    "sg:tags":[
        "physician",
        "surgeon"
    ],
    "wof:name":"Orthopedic Care",
    "wof:placetype":"venue"
},
  "geometry": {"coordinates":[-90.91142499999999,41.60086],"type":"Point"}
}