{
  "type": "Feature",
  "properties": {
    "iso:country":"US",
    "sg:address":"938 Boston Way",
    "sg:city":"Coralville",
    "sg:classifiers":[
        {
            "category":"Professional",
            "type":"Services"
        }
    ],
    "sg:phone":"+1 319 351 2960",
    "sg:postcode":"52241",
    "sg:province":"IA",
    "wof:name":"Tailored Services",
    "wof:placetype":"venue"
},
  "geometry": {"coordinates":[-91.599418,41.686152],"type":"Point"}
}