{
  "type": "Feature",
  "properties": {
    "iso:country":"US",
    "sg:address":"2700 S Martha St",
    "sg:city":"Sioux City",
    "sg:classifiers":[
        {
            "category":"Education",
            "subcategory":"Special Training",
            "type":"Public Place"
        }
    ],
    "sg:phone":"+1 712 274 1289",
    "sg:postcode":"51106",
    "sg:province":"SD",
    "wof:name":"Story Weavers Inc",
    "wof:placetype":"venue"
},
  "geometry": {"coordinates":[-96.36090299999999,42.459894],"type":"Point"}
}