{
  "type": "Feature",
  "properties": {
    "addr:full":"3526 Jersey Ridge Rd Davenport IA 52807",
    "addr:housenumber":"3526",
    "addr:postcode":"52807",
    "addr:street":"Jersey Ridge Rd",
    "iso:country":"US",
    "sg:address":"3526 Jersey Ridge Rd",
    "sg:city":"Davenport",
    "sg:classifiers":[
        {
            "category":"Health Services",
            "subcategory":"Podiatrist",
            "type":"Services"
        }
    ],
    "sg:phone":"+1 563 355 3233",
    "sg:postcode":"52807",
    "sg:province":"IA",
    "wof:name":"Gregory S Duncan DPM",
    "wof:placetype":"venue"
},
  "geometry": {"coordinates":[-90.54176200000001,41.555949],"type":"Point"}
}