{
  "type": "Feature",
  "properties": {
    "iso:country":"US",
    "sg:address":"417 3rd Ave SW",
    "sg:city":"Cedar Rapids",
    "sg:classifiers":[
        {
            "category":"Personal",
            "subcategory":"Tattoo Parlor",
            "type":"Services"
        }
    ],
    "sg:phone":"+1 319 362 3400",
    "sg:postcode":"52404",
    "sg:province":"IA",
    "sg:tags":[
        "tattooing"
    ],
    "wof:name":"Beef's Tattooing",
    "wof:placetype":"venue"
},
  "geometry": {"coordinates":[-91.676872,41.972825],"type":"Point"}
}