{
  "type": "Feature",
  "properties": {
    "addr:full":"24748 245th St Onawa IA 51040",
    "addr:housenumber":"24748",
    "addr:postcode":"51040",
    "addr:street":"245Th St",
    "iso:country":"US",
    "sg:address":"24748 245th St",
    "sg:city":"Onawa",
    "sg:phone":"+1 712 423 2736",
    "sg:postcode":"51040",
    "sg:province":"IA",
    "sg:tags":[
        "farm",
        "corn"
    ],
    "wof:name":"Allen Carrier",
    "wof:placetype":"venue"
},
  "geometry": {"coordinates":[-96.063929,42.001371],"type":"Point"}
}