{
  "type": "Feature",
  "properties": {
    "addr:full":"1180 E Price St Eldridge IA 52748",
    "addr:housenumber":"1180",
    "addr:postcode":"52748",
    "addr:street":"E Price St",
    "iso:country":"US",
    "sg:address":"1180 E Price St",
    "sg:city":"Eldridge",
    "sg:classifiers":[
        {
            "category":"Building & Trades",
            "subcategory":"Construction",
            "type":"Services"
        }
    ],
    "sg:phone":"+1 563 285 9575",
    "sg:postcode":"52748",
    "sg:province":"IA",
    "sg:tags":[
        "home",
        "builder"
    ],
    "wof:name":"Design Homes",
    "wof:placetype":"venue"
},
  "geometry": {"coordinates":[-90.56900899999999,41.660336],"type":"Point"}
}