{
  "type": "Feature",
  "properties": {
    "addr:full":"402 W Bremer Ave Waverly IA 50677",
    "addr:housenumber":"402",
    "addr:postcode":"50677",
    "addr:street":"W Bremer Ave",
    "iso:country":"US",
    "sg:address":"402 W Bremer Ave",
    "sg:city":"Waverly",
    "sg:classifiers":[
        {
            "category":"Museum",
            "type":"Entertainment"
        }
    ],
    "sg:phone":"+1 319 352 2072",
    "sg:postcode":"50677",
    "sg:province":"IA",
    "wof:name":"Waverly House/Bremer Cnty Msm",
    "wof:placetype":"venue"
},
  "geometry": {"coordinates":[-92.475689,42.725807],"type":"Point"}
}