{
  "type": "Feature",
  "properties": {
    "iso:country":"US",
    "sg:address":"36913 Hennepin Rd",
    "sg:city":"Edgewood",
    "sg:classifiers":[
        {
            "category":"Farming",
            "subcategory":"Farm",
            "type":"Manufacturing & Wholesale Goods"
        }
    ],
    "sg:phone":"+1 563 928 6259",
    "sg:postcode":"52042",
    "sg:province":"IA",
    "sg:tags":[
        "crop",
        "general"
    ],
    "wof:name":"Carl Coonfare",
    "wof:placetype":"venue"
},
  "geometry": {"coordinates":[-91.30422,42.690801],"type":"Point"}
}