{
  "type": "Feature",
  "properties": {
    "iso:country":"US",
    "sg:address":"102 E Main St",
    "sg:city":"Steamboat Rock",
    "sg:classifiers":[
        {
            "category":"Food & Beverages",
            "subcategory":"Groceries & Convenience Stores",
            "type":"Retail Goods"
        }
    ],
    "sg:phone":"+1 641 868 2138",
    "sg:postcode":"50672",
    "sg:province":"IA",
    "wof:name":"Rock Stop",
    "wof:placetype":"venue"
},
  "geometry": {"coordinates":[-93.062133,42.407401],"type":"Point"}
}