{
  "type": "Feature",
  "properties": {
    "addr:full":"305 W Industrial Rd Canton IA 57013",
    "addr:housenumber":"305",
    "addr:postcode":"57013",
    "addr:street":"W Industrial Rd",
    "iso:country":"US",
    "sg:address":"305 W Industrial Rd",
    "sg:city":"Canton",
    "sg:classifiers":[
        {
            "category":"Retail",
            "subcategory":"Auto Rental",
            "type":"Services"
        }
    ],
    "sg:phone":"+1 605 987 4201",
    "sg:postcode":"57013",
    "sg:province":"IA",
    "sg:tags":[
        "truck",
        "leasing"
    ],
    "wof:name":"Complete Equipment Inc",
    "wof:placetype":"venue"
},
  "geometry": {"coordinates":[-96.621521,43.301004],"type":"Point"}
}