{
  "type": "Feature",
  "properties": {
    "addr:full":"2314 150th St Lawton IA 51030",
    "addr:housenumber":"2314",
    "addr:postcode":"51030",
    "addr:street":"150Th St",
    "iso:country":"US",
    "sg:address":"2314 150th St",
    "sg:city":"Lawton",
    "sg:phone":"+1 712 944 5616",
    "sg:postcode":"51030",
    "sg:province":"IA",
    "sg:tags":[
        "farm",
        "chicken",
        "grain",
        "cash",
        "beef"
    ],
    "wof:name":"Mike Willer",
    "wof:placetype":"venue"
},
  "geometry": {"coordinates":[-96.151556,42.489506],"type":"Point"}
}