{
  "type": "Feature",
  "properties": {
    "iso:country":"US",
    "sg:address":"101 E Oak St",
    "sg:city":"Red Oak",
    "sg:classifiers":[
        {
            "category":"Autos & Motor Vehicles",
            "subcategory":"Automobile Sales",
            "type":"Retail Goods"
        }
    ],
    "sg:phone":"+1 712 623 3270",
    "sg:postcode":"51566",
    "sg:province":"IA",
    "sg:tags":[
        "car",
        "dealer"
    ],
    "wof:name":"Roby's Cars",
    "wof:placetype":"venue"
},
  "geometry": {"coordinates":[-95.231509,41.016681],"type":"Point"}
}