{
  "type": "Feature",
  "properties": {
    "iso:country":"US",
    "sg:address":"2089 270th St",
    "sg:city":"Winterset",
    "sg:classifiers":[
        {
            "category":"Home & Garden",
            "subcategory":"Garden Supply",
            "type":"Retail Goods"
        }
    ],
    "sg:phone":"+1 515 462 1783",
    "sg:postcode":"50273",
    "sg:province":"IA",
    "sg:tags":[
        "lawn",
        "mower"
    ],
    "wof:name":"G & C Sales & Svc",
    "wof:placetype":"venue"
},
  "geometry": {"coordinates":[-94.041539,41.258081],"type":"Point"}
}