{
  "type": "Feature",
  "properties": {
    "addr:full":"203 Grove St Fredericksburg IA 50630",
    "addr:housenumber":"203",
    "addr:postcode":"50630",
    "addr:street":"Grove St",
    "iso:country":"US",
    "sg:address":"203 Grove St",
    "sg:city":"Fredericksburg",
    "sg:classifiers":[
        {
            "category":"Home & Garden",
            "subcategory":"Furniture",
            "type":"Retail Goods"
        }
    ],
    "sg:phone":"+1 563 237 5802",
    "sg:postcode":"50630",
    "sg:province":"IA",
    "sg:tags":[
        "cabinet"
    ],
    "wof:name":"Bearish Woodshop & Constr",
    "wof:placetype":"venue"
},
  "geometry": {"coordinates":[-92.20422600000001,42.962815],"type":"Point"}
}