{
  "type": "Feature",
  "properties": {
    "iso:country":"US",
    "sg:address":"532 N Genessee St",
    "sg:city":"Blue Grass",
    "sg:classifiers":[
        {
            "category":"Building & Trades",
            "subcategory":"Plumbing",
            "type":"Services"
        }
    ],
    "sg:phone":"+1 563 381 2135",
    "sg:postcode":"52726",
    "sg:province":"IA",
    "sg:tags":[
        "mechanical",
        "contractor"
    ],
    "sg:website":"www.gpsmech.com",
    "wof:name":"General Plant Svc",
    "wof:placetype":"venue"
},
  "geometry": {"coordinates":[-90.763049,41.513253],"type":"Point"}
}