{
  "type": "Feature",
  "properties": {
    "iso:country":"US",
    "sg:address":"1633 Angle Rd SW",
    "sg:city":"Kalona",
    "sg:phone":"+1 319 683 2378",
    "sg:postcode":"52247",
    "sg:province":"IA",
    "sg:tags":[
        "farm",
        "corn"
    ],
    "wof:name":"Herschel B Yoder",
    "wof:placetype":"venue"
},
  "geometry": {"coordinates":[-91.77342,41.544716],"type":"Point"}
}