{
  "type": "Feature",
  "properties": {
    "iso:country":"US",
    "sg:address":"310 N 2nd Ave E",
    "sg:city":"Rock Rapids",
    "sg:classifiers":[
        {
            "category":"Retail",
            "subcategory":"Auto Repair",
            "type":"Services"
        }
    ],
    "sg:phone":"+1 712 472 4673",
    "sg:postcode":"51246",
    "sg:province":"IA",
    "sg:tags":[
        "body",
        "automobile",
        "painting"
    ],
    "wof:name":"Dusty's Auto Body",
    "wof:placetype":"venue"
},
  "geometry": {"coordinates":[-96.160646,43.43286],"type":"Point"}
}