{
  "type": "Feature",
  "properties": {
    "addr:full":"420 2nd Ave Vinton IA 52349",
    "addr:housenumber":"420",
    "addr:postcode":"52349",
    "addr:street":"2Nd Ave",
    "iso:country":"US",
    "sg:address":"420 2nd Ave",
    "sg:city":"Vinton",
    "sg:classifiers":[
        {
            "category":"Home & Garden",
            "subcategory":"Building Materials",
            "type":"Retail Goods"
        }
    ],
    "sg:phone":"+1 319 472 2363",
    "sg:postcode":"52349",
    "sg:province":"IA",
    "sg:tags":[
        "lumber"
    ],
    "wof:name":"Mc Dowells",
    "wof:placetype":"venue"
},
  "geometry": {"coordinates":[-92.022899,42.167479],"type":"Point"}
}