{
  "type": "Feature",
  "properties": {
    "iso:country":"US",
    "sg:address":"1930 Maplecrest Dr",
    "sg:city":"Marion",
    "sg:classifiers":[
        {
            "category":"Manufacturing",
            "subcategory":"Retail Goods",
            "type":"Manufacturing & Wholesale Goods"
        }
    ],
    "sg:phone":"+1 319 377 7339",
    "sg:postcode":"52302",
    "sg:province":"IA",
    "sg:tags":[
        "product",
        "mfg"
    ],
    "wof:name":"Cordell Designs Rae",
    "wof:placetype":"venue"
},
  "geometry": {"coordinates":[-91.58974499999999,42.043473],"type":"Point"}
}