{
  "type": "Feature",
  "properties": {
    "addr:full":"1008 N Jacob St Grimes IA 50111",
    "addr:housenumber":"1008",
    "addr:postcode":"50111",
    "addr:street":"N Jacob St",
    "iso:country":"US",
    "sg:address":"1008 N Jacob St",
    "sg:city":"Grimes",
    "sg:classifiers":[
        {
            "category":"Building & Trades",
            "subcategory":"Construction",
            "type":"Services"
        }
    ],
    "sg:phone":"+1 515 577 9906",
    "sg:postcode":"50111",
    "sg:province":"IA",
    "sg:tags":[
        "siding",
        "contractor"
    ],
    "wof:name":"Miller Construction Siding",
    "wof:placetype":"venue"
},
  "geometry": {"coordinates":[-93.789495,41.69754],"type":"Point"}
}