{
  "type": "Feature",
  "properties": {
    "addr:full":"204 S 8th St Clear Lake IA 50428",
    "addr:housenumber":"204",
    "addr:postcode":"50428",
    "addr:street":"S 8Th St",
    "iso:country":"US",
    "sg:address":"204 S 8th St",
    "sg:city":"Clear Lake",
    "sg:classifiers":[
        {
            "category":"Shopping",
            "type":"Retail Goods"
        }
    ],
    "sg:phone":"+1 641 357 7998",
    "sg:postcode":"50428",
    "sg:province":"IA",
    "sg:tags":[
        "cosmetic",
        "perfume"
    ],
    "wof:name":"Mary Kay Cosmetics",
    "wof:placetype":"venue"
},
  "geometry": {"coordinates":[-93.378687,43.135493],"type":"Point"}
}