{
  "type": "Feature",
  "properties": {
    "iso:country":"US",
    "sg:address":"28936 270th St",
    "sg:city":"Shell Rock",
    "sg:classifiers":[
        {
            "category":"Retail",
            "subcategory":"Auto Repair",
            "type":"Services"
        }
    ],
    "sg:phone":"+1 319 885 4372",
    "sg:postcode":"50670",
    "sg:province":"IA",
    "sg:tags":[
        "automobile",
        "restoration",
        "classic"
    ],
    "wof:name":"Bob's Repair",
    "wof:placetype":"venue"
},
  "geometry": {"coordinates":[-92.654297,42.656803],"type":"Point"}
}