{
  "type": "Feature",
  "properties": {
    "iso:country":"US",
    "sg:address":"707 S 11th St",
    "sg:city":"Sac City",
    "sg:classifiers":[
        {
            "category":"Organizations",
            "subcategory":"Religious Organization",
            "type":"Services"
        }
    ],
    "sg:phone":"+1 712 662 7714",
    "sg:postcode":"50583",
    "sg:province":"IA",
    "wof:name":"Church of Christ Inc",
    "wof:placetype":"venue"
},
  "geometry": {"coordinates":[-94.997564,42.414483],"type":"Point"}
}