{
  "type": "Feature",
  "properties": {
    "iso:country":"US",
    "sg:address":"609 1st Ave N",
    "sg:city":"Estherville",
    "sg:classifiers":[
        {
            "category":"Social Services",
            "type":"Services"
        }
    ],
    "sg:phone":"+1 712 362 5729",
    "sg:postcode":"51334",
    "sg:province":"IA",
    "sg:tags":[
        "probation"
    ],
    "wof:name":"Emmet Juvenile Probation Ofc",
    "wof:placetype":"venue"
},
  "geometry": {"coordinates":[-94.835483,43.40303],"type":"Point"}
}