{
  "type": "Feature",
  "properties": {
    "iso:country":"US",
    "sg:address":"3000 Risen Son Blvd",
    "sg:city":"Council Bluffs",
    "sg:classifiers":[
        {
            "category":"Social Services",
            "subcategory":"Job Training",
            "type":"Services"
        }
    ],
    "sg:phone":"+1 712 366 0480",
    "sg:postcode":"51503",
    "sg:province":"IA",
    "sg:tags":[
        "rehabilitation"
    ],
    "wof:name":"Rehabcare Therapy",
    "wof:placetype":"venue"
},
  "geometry": {"coordinates":[-95.800781,41.231328],"type":"Point"}
}