{
  "type": "Feature",
  "properties": {
    "iso:country":"US",
    "sg:address":"2104 E 14th St",
    "sg:city":"Des Moines",
    "sg:classifiers":[
        {
            "category":"Home & Garden",
            "subcategory":"Carpets & Floor Coverings",
            "type":"Retail Goods"
        }
    ],
    "sg:phone":"+1 515 265 0642",
    "sg:postcode":"50316",
    "sg:province":"IA",
    "sg:tags":[
        "material"
    ],
    "wof:name":"Advance Floor Covering Inc",
    "wof:placetype":"venue"
},
  "geometry": {"coordinates":[-93.60063,41.613944],"type":"Point"}
}