{
  "type": "Feature",
  "properties": {
    "iso:country":"US",
    "sg:address":"708 E 2nd Ave",
    "sg:city":"Coralville",
    "sg:classifiers":[
        {
            "category":"Building & Trades",
            "subcategory":"Construction",
            "type":"Services"
        }
    ],
    "sg:phone":"+1 563 326 2418",
    "sg:postcode":"52241",
    "sg:province":"IA",
    "sg:tags":[
        "concrete",
        "restoration",
        "cleaning",
        "repair"
    ],
    "wof:name":"Cole Concrete Releveling",
    "wof:placetype":"venue"
},
  "geometry": {"coordinates":[-91.563241,41.681557],"type":"Point"}
}