{
  "type": "Feature",
  "properties": {
    "iso:country":"US",
    "sg:address":"129 N Mill St",
    "sg:city":"Wadena",
    "sg:classifiers":[
        {
            "category":"Food & Beverages",
            "subcategory":"Groceries & Convenience Stores",
            "type":"Retail Goods"
        }
    ],
    "sg:phone":"+1 563 774 2700",
    "sg:postcode":"52169",
    "sg:province":"IA",
    "wof:name":"Charley's Gas Gage",
    "wof:placetype":"venue"
},
  "geometry": {"coordinates":[-91.656947,42.841253],"type":"Point"}
}