{
  "type": "Feature",
  "properties": {
    "iso:country":"US",
    "sg:address":"508 Iowa Ave",
    "sg:city":"Essex",
    "sg:classifiers":[
        {
            "category":"Education",
            "subcategory":"Library",
            "type":"Public Place"
        }
    ],
    "sg:phone":"+1 712 379 3355",
    "sg:postcode":"51638",
    "sg:province":"IA",
    "wof:name":"Essex Public Library",
    "wof:placetype":"venue"
},
  "geometry": {"coordinates":[-95.307197,40.83337],"type":"Point"}
}