{
  "type": "Feature",
  "properties": {
    "addr:full":"3720 Queen Ct SW Ste 1 Cedar Rapids IA 52404",
    "addr:housenumber":"3720",
    "addr:postcode":"52404",
    "addr:street":"Queen Ct Sw Ste 1",
    "iso:country":"US",
    "sg:address":"3720 Queen Ct SW Ste 1",
    "sg:city":"Cedar Rapids",
    "sg:classifiers":[
        {
            "category":"Health Services",
            "subcategory":"Health Practitioner",
            "type":"Services"
        }
    ],
    "sg:phone":"+1 319 364 0300",
    "sg:postcode":"52404",
    "sg:province":"IA",
    "sg:tags":[
        "therapy",
        "physical"
    ],
    "wof:name":"Accelerated Rehabilitation Centers",
    "wof:placetype":"venue"
},
  "geometry": {"coordinates":[-91.71497599999999,41.941592],"type":"Point"}
}