{
  "type": "Feature",
  "properties": {
    "iso:country":"US",
    "sg:address":"1013 Adams Ave",
    "sg:city":"Stratford",
    "sg:classifiers":[
        {
            "category":"Retail",
            "subcategory":"Repair Shop",
            "type":"Services"
        }
    ],
    "sg:phone":"+1 515 838 2125",
    "sg:postcode":"50249",
    "sg:province":"IA",
    "sg:tags":[
        "refinishing",
        "furniture"
    ],
    "wof:name":"Landreth Furniture Restoration",
    "wof:placetype":"venue"
},
  "geometry": {"coordinates":[-93.92031,42.273634],"type":"Point"}
}