{
  "type": "Feature",
  "properties": {
    "iso:country":"US",
    "sg:address":"305 South St",
    "sg:city":"Tabor",
    "sg:classifiers":[
        {
            "category":"Personal",
            "subcategory":"Beauty Salon",
            "type":"Services"
        }
    ],
    "sg:phone":"+1 712 629 7155",
    "sg:postcode":"51653",
    "sg:province":"IA",
    "sg:tags":[
        "shop"
    ],
    "wof:name":"South Street Styles",
    "wof:placetype":"venue"
},
  "geometry": {"coordinates":[-95.67606600000001,40.892833],"type":"Point"}
}