{
  "type": "Feature",
  "properties": {
    "addr:full":"503 New Salem Rd Marshalltown IA 50158",
    "addr:housenumber":"503",
    "addr:postcode":"50158",
    "addr:street":"New Salem Rd",
    "iso:country":"US",
    "sg:address":"503 New Salem Rd",
    "sg:city":"Marshalltown",
    "sg:classifiers":[
        {
            "category":"Wholesale",
            "subcategory":"Farm Supplies",
            "type":"Manufacturing & Wholesale Goods"
        }
    ],
    "sg:phone":"+1 641 752 4104",
    "sg:postcode":"50158",
    "sg:province":"IA",
    "wof:name":"Mandsager Johnson Farm Lt",
    "wof:placetype":"venue"
},
  "geometry": {"coordinates":[-92.94898999999999,42.044899],"type":"Point"}
}