{
  "type": "Feature",
  "properties": {
    "iso:country":"US",
    "sg:address":"1016 3rd Ave",
    "sg:city":"Alton",
    "sg:classifiers":[
        {
            "category":"Sports & Exercise",
            "subcategory":"Bowling",
            "type":"Entertainment"
        }
    ],
    "sg:phone":"+1 712 756 4044",
    "sg:postcode":"51003",
    "sg:province":"IA",
    "sg:tags":[
        "center"
    ],
    "wof:name":"Alton's Main Event Lanes",
    "wof:placetype":"venue"
},
  "geometry": {"coordinates":[-96.010285,42.987515],"type":"Point"}
}