{
  "type": "Feature",
  "properties": {
    "addr:full":"1854 200th St Mount Pleasant IA 52641",
    "addr:housenumber":"1854",
    "addr:postcode":"52641",
    "addr:street":"200Th St",
    "iso:country":"US",
    "sg:address":"1854 200th St",
    "sg:city":"Mount Pleasant",
    "sg:classifiers":[
        {
            "category":"Professional",
            "subcategory":"Computer Services",
            "type":"Services"
        }
    ],
    "sg:phone":"+1 319 385 4019",
    "sg:postcode":"52641",
    "sg:province":"IA",
    "sg:tags":[
        "related"
    ],
    "wof:name":"PC Concepts",
    "wof:placetype":"venue"
},
  "geometry": {"coordinates":[-91.55292300000001,41.017426],"type":"Point"}
}