{
  "type": "Feature",
  "properties": {
    "iso:country":"US",
    "sg:address":"2294 Carter Ave",
    "sg:city":"Moorland",
    "sg:phone":"+1 515 549 3723",
    "sg:postcode":"50566",
    "sg:province":"IA",
    "sg:tags":[
        "farm",
        "corn",
        "soybean"
    ],
    "wof:name":"William Byrne",
    "wof:placetype":"venue"
},
  "geometry": {"coordinates":[-94.359256,42.457072],"type":"Point"}
}