{
  "type": "Feature",
  "properties": {
    "addr:full":"1004 Market St Carlisle IA 50047",
    "addr:housenumber":"1004",
    "addr:postcode":"50047",
    "addr:street":"Market St",
    "iso:country":"US",
    "sg:address":"1004 Market St",
    "sg:city":"Carlisle",
    "sg:classifiers":[
        {
            "category":"Health Services",
            "subcategory":"Chiropractor",
            "type":"Services"
        }
    ],
    "sg:phone":"+1 515 352 3880",
    "sg:postcode":"50047",
    "sg:province":"IA",
    "wof:name":"Gowrie Family Chiro Clinic",
    "wof:placetype":"venue"
},
  "geometry": {"coordinates":[-93.49785799999999,41.500696],"type":"Point"}
}