{
  "type": "Feature",
  "properties": {
    "addr:full":"818 Maiden Ln Iowa City IA 52240",
    "addr:housenumber":"818",
    "addr:postcode":"52240",
    "addr:street":"Maiden Ln",
    "iso:country":"US",
    "sg:address":"818 Maiden Ln",
    "sg:city":"Iowa City",
    "sg:classifiers":[
        {
            "category":"Insurance",
            "subcategory":"Insurance Agent",
            "type":"Services"
        }
    ],
    "sg:phone":"+1 319 341 6025",
    "sg:postcode":"52240",
    "sg:province":"IA",
    "sg:website":"www.sinnottagency.com",
    "wof:name":"Sinnott Insurance Inc",
    "wof:placetype":"venue"
},
  "geometry": {"coordinates":[-91.53071,41.651137],"type":"Point"}
}