{
  "type": "Feature",
  "properties": {
    "iso:country":"US",
    "sg:address":"1781 US Hwy 18",
    "sg:city":"Rudd",
    "sg:classifiers":[
        {
            "category":"Shopping",
            "subcategory":"Hobbies, Toys, & Games",
            "type":"Retail Goods"
        },
        {
            "category":"Shopping",
            "subcategory":"Gifts & Souvenirs",
            "type":"Retail Goods"
        }
    ],
    "sg:phone":"+1 641 395 2953",
    "sg:postcode":"50401",
    "sg:province":"IA",
    "sg:tags":[
        "equipment",
        "ceramic",
        "supply"
    ],
    "wof:name":"Gruis's Open Gate",
    "wof:placetype":"venue"
},
  "geometry": {"coordinates":[-93.22745,43.148271],"type":"Point"}
}