{
  "type": "Feature",
  "properties": {
    "addr:full":"1060 State Hwy 86 Spirit Lake IA 51360",
    "addr:housenumber":"1060",
    "addr:postcode":"51360",
    "addr:street":"State Hwy 86",
    "iso:country":"US",
    "sg:address":"1060 State Hwy 86",
    "sg:city":"Spirit Lake",
    "sg:classifiers":[
        {
            "category":"Shopping",
            "type":"Retail Goods"
        }
    ],
    "sg:phone":"+1 712 338 4650",
    "sg:postcode":"51360",
    "sg:province":"IA",
    "sg:tags":[
        "craft",
        "gallery",
        "dealer"
    ],
    "wof:name":"Country Time Farm",
    "wof:placetype":"venue"
},
  "geometry": {"coordinates":[-95.181117,43.493507],"type":"Point"}
}