{
  "type": "Feature",
  "properties": {
    "iso:country":"US",
    "sg:address":"607 213th Ave",
    "sg:city":"Carlisle",
    "sg:classifiers":[
        {
            "category":"Real Estate",
            "subcategory":"Real Estate Operator",
            "type":"Services"
        }
    ],
    "sg:phone":"+1 515 989 0269",
    "sg:postcode":"50047",
    "sg:province":"IA",
    "sg:tags":[
        "property",
        "lessor"
    ],
    "wof:name":"Jim Wiley",
    "wof:placetype":"venue"
},
  "geometry": {"coordinates":[-93.40009999999999,41.43605],"type":"Point"}
}