{
  "type": "Feature",
  "properties": {
    "iso:country":"US",
    "sg:address":"4515 Fleur Dr",
    "sg:city":"Des Moines",
    "sg:classifiers":[
        {
            "category":"Banks & Credit Unions",
            "subcategory":"Bank",
            "type":"Services"
        }
    ],
    "sg:phone":"+1 515 248 7780",
    "sg:postcode":"50321",
    "sg:province":"IA",
    "wof:name":"US Bank",
    "wof:placetype":"venue"
},
  "geometry": {"coordinates":[-93.644874,41.542019],"type":"Point"}
}