{
  "type": "Feature",
  "properties": {
    "iso:country":"US",
    "sg:address":"1555 255th St",
    "sg:city":"Sheffield",
    "sg:classifiers":[
        {
            "category":"Manufacturing",
            "subcategory":"Tools & Machinery",
            "type":"Manufacturing & Wholesale Goods"
        }
    ],
    "sg:phone":"+1 641 892 4222",
    "sg:postcode":"50475",
    "sg:province":"IA",
    "sg:tags":[
        "farm",
        "equipment"
    ],
    "sg:website":"www.sukupmfg.com",
    "wof:name":"Sukup Manufacturing Co",
    "wof:placetype":"venue"
},
  "geometry": {"coordinates":[-93.207358,42.898571],"type":"Point"}
}