{
  "type": "Feature",
  "properties": {
    "iso:country":"US",
    "sg:address":"4093 383rd Ave",
    "sg:city":"Preston",
    "sg:classifiers":[
        {
            "category":"Retail",
            "subcategory":"Auto Repair",
            "type":"Services"
        }
    ],
    "sg:phone":"+1 563 689 6192",
    "sg:postcode":"52074",
    "sg:province":"IA",
    "sg:tags":[
        "repairing",
        "automobile",
        "general"
    ],
    "wof:name":"Saids Auto Repair",
    "wof:placetype":"venue"
},
  "geometry": {"coordinates":[-90.452073,42.069709],"type":"Point"}
}