{
  "type": "Feature",
  "properties": {
    "addr:full":"2516 12th St NW Waverly IA 50677",
    "addr:housenumber":"2516",
    "addr:postcode":"50677",
    "addr:street":"12Th St Nw",
    "iso:country":"US",
    "sg:address":"2516 12th St NW",
    "sg:city":"Waverly",
    "sg:classifiers":[
        {
            "category":"Shopping",
            "subcategory":"Used Merchandise",
            "type":"Retail Goods"
        }
    ],
    "sg:phone":"+1 319 352 1350",
    "sg:postcode":"50677",
    "sg:province":"IA",
    "sg:tags":[
        "appliance"
    ],
    "wof:name":"Mel's Reconditioned Appliances",
    "wof:placetype":"venue"
},
  "geometry": {"coordinates":[-92.485051,42.744737],"type":"Point"}
}