{
  "type": "Feature",
  "properties": {
    "iso:country":"US",
    "sg:address":"30436 335th St",
    "sg:city":"Coon Rapids",
    "sg:classifiers":[
        {
            "category":"Farming",
            "subcategory":"Livestock Farm",
            "type":"Manufacturing & Wholesale Goods"
        }
    ],
    "sg:phone":"+1 712 684 2409",
    "sg:postcode":"50058",
    "sg:province":"IA",
    "sg:tags":[
        "beef",
        "feedlot",
        "cattle"
    ],
    "wof:name":"Km Cattle Company",
    "wof:placetype":"venue"
},
  "geometry": {"coordinates":[-94.707864,41.869582],"type":"Point"}
}