{
  "type": "Feature",
  "properties": {
    "iso:country":"US",
    "sg:address":"42374 Panther Creek Hollow Rd",
    "sg:city":"Holy Cross",
    "sg:classifiers":[
        {
            "category":"Farming",
            "subcategory":"Dairy Farm",
            "type":"Manufacturing & Wholesale Goods"
        }
    ],
    "sg:phone":"+1 563 252 1639",
    "sg:postcode":"52053",
    "sg:province":"IA",
    "wof:name":"R Schmerbach",
    "wof:placetype":"venue"
},
  "geometry": {"coordinates":[-90.96726099999999,42.674368],"type":"Point"}
}