{
  "type": "Feature",
  "properties": {
    "addr:full":"200 2nd Ave NE Independence IA 50644",
    "addr:housenumber":"200",
    "addr:postcode":"50644",
    "addr:street":"2Nd Ave Ne",
    "iso:country":"US",
    "sg:address":"200 2nd Ave NE",
    "sg:city":"Independence",
    "sg:classifiers":[
        {
            "category":"Government",
            "subcategory":"Post Office",
            "type":"Public Place"
        }
    ],
    "sg:phone":"+1 319 334 2495",
    "sg:postcode":"50644",
    "sg:province":"IA",
    "wof:name":"US Post Office",
    "wof:placetype":"venue"
},
  "geometry": {"coordinates":[-91.893253,42.470904],"type":"Point"}
}