{
  "type": "Feature",
  "properties": {
    "iso:country":"US",
    "sg:address":"4900 University Ave",
    "sg:city":"West Des Moines",
    "sg:classifiers":[
        {
            "category":"Professional",
            "subcategory":"Accounting & Tax Preparation",
            "type":"Services"
        }
    ],
    "sg:phone":"+1 515 224 9745",
    "sg:postcode":"50266",
    "sg:province":"IA",
    "sg:tags":[
        "payroll"
    ],
    "wof:name":"ADP",
    "wof:placetype":"venue"
},
  "geometry": {"coordinates":[-93.771157,41.600368],"type":"Point"}
}