{
  "type": "Feature",
  "properties": {
    "iso:country":"US",
    "sg:address":"2850 Winchester Dr",
    "sg:city":"Marion",
    "sg:classifiers":[
        {
            "category":"Building & Trades",
            "subcategory":"Construction",
            "type":"Services"
        }
    ],
    "sg:phone":"+1 319 377 9723",
    "sg:postcode":"52302",
    "sg:province":"IA",
    "sg:tags":[
        "painter"
    ],
    "wof:name":"Ty-Co Painting Inc",
    "wof:placetype":"venue"
},
  "geometry": {"coordinates":[-91.56838399999999,42.049034],"type":"Point"}
}