{
  "type": "Feature",
  "properties": {
    "iso:country":"US",
    "sg:address":"501 Main St",
    "sg:city":"Brandon",
    "sg:classifiers":[
        {
            "category":"Restaurant",
            "type":"Food & Drink"
        }
    ],
    "sg:phone":"+1 319 474 2200",
    "sg:postcode":"52210",
    "sg:province":"IA",
    "wof:name":"Brandon Homestyle Cafe",
    "wof:placetype":"venue"
},
  "geometry": {"coordinates":[-92.00341899999999,42.31445],"type":"Point"}
}