{
  "type": "Feature",
  "properties": {
    "iso:country":"US",
    "sg:address":"2422 Hwy 92",
    "sg:city":"Oskaloosa",
    "sg:classifiers":[
        {
            "category":"Retail",
            "subcategory":"Repair Shop",
            "type":"Services"
        }
    ],
    "sg:phone":"+1 641 673 4427",
    "sg:postcode":"52577",
    "sg:province":"IA",
    "sg:tags":[
        "appliance"
    ],
    "wof:name":"Van Roekel Appliance Svc",
    "wof:placetype":"venue"
},
  "geometry": {"coordinates":[-92.591787,41.296245],"type":"Point"}
}