{
  "type": "Feature",
  "properties": {
    "addr:full":"2100 S 4th St Burlington IA 52601",
    "addr:housenumber":"2100",
    "addr:postcode":"52601",
    "addr:street":"S 4Th St",
    "iso:country":"US",
    "sg:address":"2100 S 4th St",
    "sg:city":"Burlington",
    "sg:classifiers":[
        {
            "category":"Professional",
            "subcategory":"Computer Services",
            "type":"Services"
        }
    ],
    "sg:phone":"+1 319 758 0506",
    "sg:postcode":"52601",
    "sg:province":"IA",
    "sg:tags":[
        "processing"
    ],
    "wof:name":"Intat",
    "wof:placetype":"venue"
},
  "geometry": {"coordinates":[-91.10095099999999,40.788631],"type":"Point"}
}