{
  "type": "Feature",
  "properties": {
    "addr:full":"1115 Warford St Perry IA 50220",
    "addr:housenumber":"1115",
    "addr:postcode":"50220",
    "addr:street":"Warford St",
    "iso:country":"US",
    "sg:address":"1115 Warford St",
    "sg:city":"Perry",
    "sg:classifiers":[
        {
            "category":"Restaurant",
            "type":"Food & Drink"
        }
    ],
    "sg:phone":"+1 515 465 3863",
    "sg:postcode":"50220",
    "sg:province":"IA",
    "wof:name":"Perry Bowl",
    "wof:placetype":"venue"
},
  "geometry": {"coordinates":[-94.106424,41.839476],"type":"Point"}
}