{
  "type": "Feature",
  "properties": {
    "iso:country":"US",
    "sg:address":"7984 W 108th St N",
    "sg:city":"Mingo",
    "sg:phone":"+1 641 363 4359",
    "sg:postcode":"50168",
    "sg:province":"IA",
    "sg:tags":[
        "farm",
        "corn"
    ],
    "wof:name":"Robert Stock",
    "wof:placetype":"venue"
},
  "geometry": {"coordinates":[-93.25117899999999,41.795031],"type":"Point"}
}