{
  "type": "Feature",
  "properties": {
    "iso:country":"US",
    "sg:address":"915 Marion Rd S",
    "sg:city":"Central City",
    "sg:classifiers":[
        {
            "category":"Building & Trades",
            "subcategory":"Construction",
            "type":"Services"
        }
    ],
    "sg:phone":"+1 319 438 6014",
    "sg:postcode":"52214",
    "sg:province":"IA",
    "sg:tags":[
        "general",
        "contractor"
    ],
    "wof:name":"Central Foundation Inc",
    "wof:placetype":"venue"
},
  "geometry": {"coordinates":[-91.531041,42.194087],"type":"Point"}
}