{
  "type": "Feature",
  "properties": {
    "addr:full":"401 5th Ave SW Le Mars IA 51031",
    "addr:housenumber":"401",
    "addr:postcode":"51031",
    "addr:street":"5Th Ave Sw",
    "iso:country":"US",
    "sg:address":"401 5th Ave SW",
    "sg:city":"Le Mars",
    "sg:classifiers":[
        {
            "category":"Shopping",
            "subcategory":"Department Store",
            "type":"Retail Goods"
        }
    ],
    "sg:phone":"+1 712 546 8904",
    "sg:postcode":"51031",
    "sg:province":"IA",
    "sg:tags":[
        "shop"
    ],
    "wof:name":"Dollar General",
    "wof:placetype":"venue"
},
  "geometry": {"coordinates":[-96.173761,42.788177],"type":"Point"}
}