{
  "type": "Feature",
  "properties": {
    "iso:country":"US",
    "sg:address":"1086 S 3rd St",
    "sg:city":"Manchester",
    "sg:classifiers":[
        {
            "category":"Manufacturing",
            "subcategory":"Motor Vehicles & Parts",
            "type":"Manufacturing & Wholesale Goods"
        }
    ],
    "sg:phone":"+1 563 927 4884",
    "sg:postcode":"52057",
    "sg:province":"IA",
    "sg:tags":[
        "truck",
        "trailer",
        "mfg"
    ],
    "wof:name":"X-L Specialized Trailers Inc",
    "wof:placetype":"venue"
},
  "geometry": {"coordinates":[-91.457269,42.469655],"type":"Point"}
}