{
  "type": "Feature",
  "properties": {
    "addr:full":"1510 Hill Ave Spirit Lake IA 51360",
    "addr:housenumber":"1510",
    "addr:postcode":"51360",
    "addr:street":"Hill Ave",
    "iso:country":"US",
    "sg:address":"1510 Hill Ave",
    "sg:city":"Spirit Lake",
    "sg:classifiers":[
        {
            "category":"Professional",
            "subcategory":"Lawyer & Legal Services",
            "type":"Services"
        }
    ],
    "sg:phone":"+1 712 336 5999",
    "sg:postcode":"51360",
    "sg:province":"IA",
    "sg:tags":[
        "attorney"
    ],
    "wof:name":"Wilcke Law Office",
    "wof:placetype":"venue"
},
  "geometry": {"coordinates":[-95.10236399999999,43.42545],"type":"Point"}
}