{
  "type": "Feature",
  "properties": {
    "addr:full":"910 S Main St Traer IA 50675",
    "addr:housenumber":"910",
    "addr:postcode":"50675",
    "addr:street":"S Main St",
    "iso:country":"US",
    "sg:address":"910 S Main St",
    "sg:city":"Traer",
    "sg:classifiers":[
        {
            "category":"Wholesale",
            "subcategory":"Construction Materials",
            "type":"Manufacturing & Wholesale Goods"
        }
    ],
    "sg:phone":"+1 319 478 2002",
    "sg:postcode":"50675",
    "sg:province":"IA",
    "sg:tags":[
        "marble"
    ],
    "wof:name":"Huntley Marble Co",
    "wof:placetype":"venue"
},
  "geometry": {"coordinates":[-92.46556200000001,42.186129],"type":"Point"}
}