{
  "type": "Feature",
  "properties": {
    "iso:country":"US",
    "sg:address":"1966 210th Ave",
    "sg:city":"Grand Mound",
    "sg:classifiers":[
        {
            "category":"Farming",
            "subcategory":"Farm",
            "type":"Manufacturing & Wholesale Goods"
        }
    ],
    "sg:phone":"+1 563 847 5792",
    "sg:postcode":"52751",
    "sg:province":"IA",
    "wof:name":"Diercks Family Farms Ltd",
    "wof:placetype":"venue"
},
  "geometry": {"coordinates":[-90.684634,41.891959],"type":"Point"}
}