{
  "type": "Feature",
  "properties": {
    "iso:country":"US",
    "sg:address":"56042 340th St",
    "sg:city":"Hastings",
    "sg:classifiers":[
        {
            "category":"Organizations",
            "subcategory":"Religious Organization",
            "type":"Services"
        }
    ],
    "sg:phone":"+1 712 624 8891",
    "sg:postcode":"51540",
    "sg:province":"IA",
    "sg:tags":[
        "church"
    ],
    "wof:name":"St John Lutheran Church",
    "wof:placetype":"venue"
},
  "geometry": {"coordinates":[-95.537351,41.072305],"type":"Point"}
}