{
  "type": "Feature",
  "properties": {
    "iso:country":"US",
    "sg:address":"512 Lybrand St",
    "sg:city":"Postville",
    "sg:classifiers":[
        {
            "category":"Building & Trades",
            "subcategory":"Construction",
            "type":"Services"
        }
    ],
    "sg:phone":"+1 563 864 3501",
    "sg:postcode":"52162",
    "sg:province":"IA",
    "sg:tags":[
        "siding",
        "contractor"
    ],
    "wof:name":"Bartlein Construction",
    "wof:placetype":"venue"
},
  "geometry": {"coordinates":[-91.558126,43.088089],"type":"Point"}
}