{
  "type": "Feature",
  "properties": {
    "iso:country":"US",
    "sg:address":"1803 Chandler St SW",
    "sg:city":"Cedar Rapids",
    "sg:classifiers":[
        {
            "category":"Restaurant",
            "type":"Food & Drink"
        }
    ],
    "sg:phone":"+1 319 363 6597",
    "sg:postcode":"52404",
    "sg:province":"IA",
    "sg:tags":[
        "eating"
    ],
    "wof:name":"Hathaway Restaurants Inc",
    "wof:placetype":"venue"
},
  "geometry": {"coordinates":[-91.698836,41.96904],"type":"Point"}
}