{
  "type": "Feature",
  "properties": {
    "iso:country":"US",
    "sg:address":"2435 180th St",
    "sg:city":"Clarion",
    "sg:classifiers":[
        {
            "category":"Restaurant",
            "type":"Food & Drink"
        }
    ],
    "sg:phone":"+1 515 532 2027",
    "sg:postcode":"50421",
    "sg:province":"IA",
    "sg:tags":[
        "caterer"
    ],
    "sg:website":"www.fancythatcateringonline.com",
    "wof:name":"Fancy That Catering",
    "wof:placetype":"venue"
},
  "geometry": {"coordinates":[-93.680953,42.789943],"type":"Point"}
}