{
  "type": "Feature",
  "properties": {
    "iso:country":"US",
    "sg:address":"5025 Wolff Rd",
    "sg:city":"Dubuque",
    "sg:classifiers":[
        {
            "category":"Manufacturing",
            "subcategory":"Printing",
            "type":"Manufacturing & Wholesale Goods"
        }
    ],
    "sg:phone":"+1 563 583 3336",
    "sg:postcode":"52002",
    "sg:province":"IA",
    "sg:tags":[
        "publisher",
        "book"
    ],
    "wof:name":"William H Sadlier Inc",
    "wof:placetype":"venue"
},
  "geometry": {"coordinates":[-90.753181,42.503046],"type":"Point"}
}