{
  "type": "Feature",
  "properties": {
    "iso:country":"US",
    "sg:address":"4217 University Ave",
    "sg:city":"Des Moines",
    "sg:classifiers":[
        {
            "category":"Personal",
            "type":"Services"
        }
    ],
    "sg:phone":"+1 515 360 6623",
    "sg:postcode":"50311",
    "sg:province":"IA",
    "sg:tags":[
        "therapist",
        "massage"
    ],
    "wof:name":"Linda Bacon",
    "wof:placetype":"venue"
},
  "geometry": {"coordinates":[-93.67585200000001,41.600416],"type":"Point"}
}