{
  "type": "Feature",
  "properties": {
    "iso:country":"US",
    "sg:address":"1048 Davis Ave",
    "sg:city":"Des Moines",
    "sg:classifiers":[
        {
            "category":"Education",
            "subcategory":"Special Training",
            "type":"Public Place"
        }
    ],
    "sg:phone":"+1 515 285 7254",
    "sg:postcode":"50315",
    "sg:province":"IA",
    "sg:tags":[
        "instruction",
        "music"
    ],
    "wof:name":"Southside Music Studio",
    "wof:placetype":"venue"
},
  "geometry": {"coordinates":[-93.628523,41.565785],"type":"Point"}
}