{
  "type": "Feature",
  "properties": {
    "addr:full":"2312 Edison St Ames IA 50010",
    "addr:housenumber":"2312",
    "addr:postcode":"50010",
    "addr:street":"Edison St",
    "iso:country":"US",
    "sg:address":"2312 Edison St",
    "sg:city":"Ames",
    "sg:classifiers":[
        {
            "category":"Building & Trades",
            "subcategory":"Plumbing",
            "type":"Services"
        }
    ],
    "sg:phone":"+1 515 233 1175",
    "sg:postcode":"50010",
    "sg:province":"IA",
    "sg:tags":[
        "heating",
        "contractor"
    ],
    "wof:name":"C & K Heating Air Cond & Plumb",
    "wof:placetype":"venue"
},
  "geometry": {"coordinates":[-93.58202799999999,42.025235],"type":"Point"}
}