{
  "type": "Feature",
  "properties": {
    "iso:country":"US",
    "sg:address":"450 Marion Blvd",
    "sg:city":"Marion",
    "sg:classifiers":[
        {
            "category":"Insurance",
            "subcategory":"Insurance Agent",
            "type":"Services"
        }
    ],
    "sg:phone":"+1 319 377 5603",
    "sg:postcode":"52302",
    "sg:province":"IA",
    "wof:name":"American Family Insurance",
    "wof:placetype":"venue"
},
  "geometry": {"coordinates":[-91.616682,42.028409],"type":"Point"}
}