{
  "type": "Feature",
  "properties": {
    "iso:country":"US",
    "sg:address":"4366 Napoleon St SE",
    "sg:city":"Iowa City",
    "sg:classifiers":[
        {
            "category":"Government",
            "subcategory":"Office",
            "type":"Public Place"
        }
    ],
    "sg:phone":"+1 319 356 5170",
    "sg:postcode":"52240",
    "sg:province":"IA",
    "sg:tags":[
        "village"
    ],
    "wof:name":"Wastewater Plant",
    "wof:placetype":"venue"
},
  "geometry": {"coordinates":[-91.509423,41.59863],"type":"Point"}
}