{
  "type": "Feature",
  "properties": {
    "iso:country":"US",
    "sg:address":"501 E 2nd St",
    "sg:city":"Madrid",
    "sg:classifiers":[
        {
            "category":"Food & Beverages",
            "subcategory":"Groceries & Convenience Stores",
            "type":"Retail Goods"
        }
    ],
    "sg:phone":"+1 515 795 3806",
    "sg:postcode":"50156",
    "sg:province":"IA",
    "wof:name":"Git N Go",
    "wof:placetype":"venue"
},
  "geometry": {"coordinates":[-93.81568900000001,41.875907],"type":"Point"}
}