{
  "type": "Feature",
  "properties": {
    "addr:full":"200 Stanton Ave Ames IA 50014",
    "addr:housenumber":"200",
    "addr:postcode":"50014",
    "addr:street":"Stanton Ave",
    "iso:country":"US",
    "sg:address":"200 Stanton Ave",
    "sg:city":"Ames",
    "sg:classifiers":[
        {
            "category":"Restaurant",
            "type":"Food & Drink"
        }
    ],
    "sg:phone":"+1 515 598 9302",
    "sg:postcode":"50014",
    "sg:province":"IA",
    "sg:tags":[
        "shop",
        "coffee"
    ],
    "wof:name":"Lava Java Coffee Shop",
    "wof:placetype":"venue"
},
  "geometry": {"coordinates":[-93.64848499999999,42.020052],"type":"Point"}
}