{
  "type": "Feature",
  "properties": {
    "addr:full":"1140 24th St Des Moines IA 50311",
    "addr:housenumber":"1140",
    "addr:postcode":"50311",
    "addr:street":"24Th St",
    "iso:country":"US",
    "sg:address":"1140 24th St",
    "sg:city":"Des Moines",
    "sg:classifiers":[
        {
            "category":"Travel",
            "subcategory":"Hotels & Motels",
            "type":"Entertainment"
        }
    ],
    "sg:phone":"+1 515 255 4000",
    "sg:postcode":"50311",
    "sg:province":"IA",
    "sg:website":"www.hiexpress.com",
    "wof:name":"Holiday Inn Express Des Moines",
    "wof:placetype":"venue"
},
  "geometry": {"coordinates":[-93.64978000000001,41.59945],"type":"Point"}
}