{
  "type": "Feature",
  "properties": {
    "addr:full":"2505 N Broadway St Red Oak IA 51566",
    "addr:housenumber":"2505",
    "addr:postcode":"51566",
    "addr:street":"N Broadway St",
    "iso:country":"US",
    "sg:address":"2505 N Broadway St",
    "sg:city":"Red Oak",
    "sg:classifiers":[
        {
            "category":"Government",
            "subcategory":"Office",
            "type":"Public Place"
        }
    ],
    "sg:phone":"+1 712 623 9680",
    "sg:postcode":"51566",
    "sg:province":"IA",
    "sg:tags":[
        "federal"
    ],
    "wof:name":"Natural Resources Conservation",
    "wof:placetype":"venue"
},
  "geometry": {"coordinates":[-95.23293099999999,41.027675],"type":"Point"}
}