{
  "type": "Feature",
  "properties": {
    "iso:country":"US",
    "sg:address":"559 160th St",
    "sg:city":"Latimer",
    "sg:classifiers":[
        {
            "category":"Farming",
            "subcategory":"Farm",
            "type":"Manufacturing & Wholesale Goods"
        }
    ],
    "sg:phone":"+1 641 579 6106",
    "sg:postcode":"50452",
    "sg:province":"IA",
    "sg:tags":[
        "crop",
        "general"
    ],
    "wof:name":"Gordon C & Denise Passehl",
    "wof:placetype":"venue"
},
  "geometry": {"coordinates":[-93.40758599999999,42.76009],"type":"Point"}
}