{
  "type": "Feature",
  "properties": {
    "iso:country":"US",
    "sg:address":"2909 Myrtle St",
    "sg:city":"Sioux City",
    "sg:classifiers":[
        {
            "category":"Retail",
            "subcategory":"Animal Services",
            "type":"Services"
        }
    ],
    "sg:phone":"+1 712 252 9500",
    "sg:postcode":"51103",
    "sg:province":"IA",
    "sg:tags":[
        "pet",
        "boarding",
        "sitting"
    ],
    "wof:name":"Critter Sitters Pet Sitting",
    "wof:placetype":"venue"
},
  "geometry": {"coordinates":[-96.422782,42.520026],"type":"Point"}
}