{
  "type": "Feature",
  "properties": {
    "addr:full":"15378 NE 42nd St Cambridge IA 50046",
    "addr:housenumber":"15378",
    "addr:postcode":"50046",
    "addr:street":"Ne 42Nd St",
    "iso:country":"US",
    "sg:address":"15378 NE 42nd St",
    "sg:city":"Cambridge",
    "sg:classifiers":[
        {
            "category":"Building & Trades",
            "subcategory":"Construction",
            "type":"Services"
        }
    ],
    "sg:phone":"+1 515 202 5930",
    "sg:postcode":"50046",
    "sg:province":"IA",
    "sg:tags":[
        "repairing",
        "remodeling",
        "contractor"
    ],
    "wof:name":"Hoff's Remodeling",
    "wof:placetype":"venue"
},
  "geometry": {"coordinates":[-93.531593,41.847108],"type":"Point"}
}