{
  "type": "Feature",
  "properties": {
    "iso:country":"US",
    "sg:address":"804 Kenyon Rd",
    "sg:city":"Fort Dodge",
    "sg:classifiers":[
        {
            "category":"Health Services",
            "subcategory":"Doctor",
            "type":"Services"
        }
    ],
    "sg:phone":"+1 515 574 6141",
    "sg:postcode":"50501",
    "sg:province":"IA",
    "sg:tags":[
        "physician",
        "surgeon"
    ],
    "wof:name":"Associated Internists",
    "wof:placetype":"venue"
},
  "geometry": {"coordinates":[-94.189029,42.494243],"type":"Point"}
}