{
  "type": "Feature",
  "properties": {
    "iso:country":"US",
    "sg:address":"1520 210th St",
    "sg:city":"Schleswig",
    "sg:phone":"+1 712 676 3875",
    "sg:postcode":"51461",
    "sg:province":"IA",
    "sg:tags":[
        "farm",
        "corn",
        "grain",
        "cash"
    ],
    "wof:name":"Bahnsen Gaylen",
    "wof:placetype":"venue"
},
  "geometry": {"coordinates":[-95.45901499999999,42.135346],"type":"Point"}
}