{
  "type": "Feature",
  "properties": {
    "addr:full":"308 7th Ave Hiawatha IA 52233",
    "addr:housenumber":"308",
    "addr:postcode":"52233",
    "addr:street":"7Th Ave",
    "iso:country":"US",
    "sg:address":"308 7th Ave",
    "sg:city":"Hiawatha",
    "sg:classifiers":[
        {
            "category":"Insurance",
            "subcategory":"Insurance Agent",
            "type":"Services"
        }
    ],
    "sg:phone":"+1 319 378 0954",
    "sg:postcode":"52233",
    "sg:province":"IA",
    "wof:name":"American Family Insurance",
    "wof:placetype":"venue"
},
  "geometry": {"coordinates":[-91.679007,42.035889],"type":"Point"}
}