{
  "type": "Feature",
  "properties": {
    "iso:country":"US",
    "sg:address":"3863 W River Dr",
    "sg:city":"Davenport",
    "sg:classifiers":[
        {
            "category":"Freight",
            "type":"Transportation"
        }
    ],
    "sg:phone":"+1 563 345 6005",
    "sg:postcode":"52802",
    "sg:province":"IA",
    "sg:tags":[
        "trucking"
    ],
    "wof:name":"Blachowski Trucking",
    "wof:placetype":"venue"
},
  "geometry": {"coordinates":[-90.63235,41.501439],"type":"Point"}
}