{
  "type": "Feature",
  "properties": {
    "addr:full":"2754 Mount Pleasant St Burlington IA 52601",
    "addr:housenumber":"2754",
    "addr:postcode":"52601",
    "addr:street":"Mount Pleasant St",
    "iso:country":"US",
    "sg:address":"2754 Mount Pleasant St",
    "sg:city":"Burlington",
    "sg:classifiers":[
        {
            "category":"Autos & Motor Vehicles",
            "subcategory":"Automobile Sales",
            "type":"Retail Goods"
        },
        {
            "category":"Retail",
            "subcategory":"Auto Rental",
            "type":"Services"
        },
        {
            "category":"Building & Trades",
            "subcategory":"Equipment Rental",
            "type":"Services"
        }
    ],
    "sg:phone":"+1 319 752 9827",
    "sg:postcode":"52601",
    "sg:province":"IA",
    "sg:tags":[
        "truck",
        "used",
        "moving"
    ],
    "sg:website":"http://budgettruck.com/IYP_tl",
    "wof:name":"Hidden Treasures Llc DBA/Budget Truck Rental",
    "wof:placetype":"venue"
},
  "geometry": {"coordinates":[-91.13686300000001,40.825662],"type":"Point"}
}