{
  "type": "Feature",
  "properties": {
    "iso:country":"US",
    "sg:address":"11607 Rickard Rd",
    "sg:city":"Jesup",
    "sg:classifiers":[
        {
            "category":"Farming",
            "subcategory":"Farm & Veterinary Services",
            "type":"Manufacturing & Wholesale Goods"
        }
    ],
    "sg:phone":"+1 319 827 6060",
    "sg:postcode":"50648",
    "sg:province":"IA",
    "wof:name":"Blue Diamond Farming Co",
    "wof:placetype":"venue"
},
  "geometry": {"coordinates":[-92.113529,42.398952],"type":"Point"}
}