{
  "type": "Feature",
  "properties": {
    "addr:full":"2905 W 1st St Ankeny IA 50023",
    "addr:housenumber":"2905",
    "addr:postcode":"50023",
    "addr:street":"W 1St St",
    "iso:country":"US",
    "sg:address":"2905 W 1st St",
    "sg:city":"Ankeny",
    "sg:classifiers":[
        {
            "category":"Food & Beverages",
            "subcategory":"Groceries & Convenience Stores",
            "type":"Retail Goods"
        }
    ],
    "sg:phone":"+1 515 964 9607",
    "sg:postcode":"50023",
    "sg:province":"IA",
    "sg:website":"www.caseys.com",
    "wof:name":"Casey's General Store",
    "wof:placetype":"venue"
},
  "geometry": {"coordinates":[-93.636922,41.731842],"type":"Point"}
}