{
  "type": "Feature",
  "properties": {
    "iso:country":"US",
    "sg:address":"920 4th St",
    "sg:city":"Allison",
    "sg:classifiers":[
        {
            "category":"Recreation",
            "type":"Entertainment"
        }
    ],
    "sg:phone":"+1 319 267 2762",
    "sg:postcode":"50602",
    "sg:province":"IA",
    "sg:tags":[
        "pool",
        "swimming"
    ],
    "wof:name":"Allison Swimming Pool",
    "wof:placetype":"venue"
},
  "geometry": {"coordinates":[-92.80033400000001,42.753737],"type":"Point"}
}