{
  "type": "Feature",
  "properties": {
    "iso:country":"US",
    "sg:address":"111 Oskaloosa St",
    "sg:city":"Pella",
    "sg:classifiers":[
        {
            "category":"Professional",
            "subcategory":"Art Services",
            "type":"Services"
        }
    ],
    "sg:phone":"+1 641 628 2640",
    "sg:postcode":"50219",
    "sg:province":"IA",
    "sg:tags":[
        "photography",
        "commercial"
    ],
    "wof:name":"Van Derbeek Photography",
    "wof:placetype":"venue"
},
  "geometry": {"coordinates":[-92.908546,41.398293],"type":"Point"}
}