{
  "type": "Feature",
  "properties": {
    "iso:country":"US",
    "sg:address":"5833 Ave O",
    "sg:city":"Fort Madison",
    "sg:classifiers":[
        {
            "category":"Restaurant",
            "type":"Food & Drink"
        }
    ],
    "sg:phone":"+1 319 372 5043",
    "sg:postcode":"52627",
    "sg:province":"IA",
    "wof:name":"Cottage Cafe",
    "wof:placetype":"venue"
},
  "geometry": {"coordinates":[-91.391445,40.624407],"type":"Point"}
}