{
  "type": "Feature",
  "properties": {
    "addr:full":"1940 E Hull Ave Des Moines IA 50313",
    "addr:housenumber":"1940",
    "addr:postcode":"50313",
    "addr:street":"E Hull Ave",
    "iso:country":"US",
    "sg:address":"1940 E Hull Ave",
    "sg:city":"Des Moines",
    "sg:classifiers":[
        {
            "category":"Wholesale",
            "subcategory":"Groceries",
            "type":"Manufacturing & Wholesale Goods"
        }
    ],
    "sg:phone":"+1 515 263 2112",
    "sg:postcode":"50313",
    "sg:province":"IA",
    "sg:tags":[
        "product",
        "soybean"
    ],
    "sg:website":"www.admworld.com",
    "wof:name":"Archer Daniels Midland Co",
    "wof:placetype":"venue"
},
  "geometry": {"coordinates":[-93.58507899999999,41.622361],"type":"Point"}
}