{
  "type": "Feature",
  "properties": {
    "addr:full":"2277 Iowa Ave Independence IA 50644",
    "addr:housenumber":"2277",
    "addr:postcode":"50644",
    "addr:street":"Iowa Ave",
    "iso:country":"US",
    "sg:address":"2277 Iowa Ave",
    "sg:city":"Independence",
    "sg:classifiers":[
        {
            "category":"Banks & Credit Unions",
            "subcategory":"Bank",
            "type":"Services"
        }
    ],
    "sg:phone":"+1 319 334 5348",
    "sg:postcode":"50644",
    "sg:province":"IA",
    "wof:name":"Mhi Independence Employee CU",
    "wof:placetype":"venue"
},
  "geometry": {"coordinates":[-91.919652,42.461396],"type":"Point"}
}