{
  "type": "Feature",
  "properties": {
    "addr:full":"79 Commercial Dr Iowa City IA 52246",
    "addr:housenumber":"79",
    "addr:postcode":"52246",
    "addr:street":"Commercial Dr",
    "iso:country":"US",
    "sg:address":"79 Commercial Dr",
    "sg:city":"Iowa City",
    "sg:classifiers":[
        {
            "category":"Retail",
            "subcategory":"Repair Shop",
            "type":"Services"
        }
    ],
    "sg:phone":"+1 319 338 6799",
    "sg:postcode":"52246",
    "sg:province":"IA",
    "sg:tags":[
        "refinishing",
        "furniture"
    ],
    "wof:name":"Little Shop",
    "wof:placetype":"venue"
},
  "geometry": {"coordinates":[-91.537772,41.633604],"type":"Point"}
}