{
  "type": "Feature",
  "properties": {
    "iso:country":"US",
    "sg:address":"62897 542nd St",
    "sg:city":"Lewis",
    "sg:classifiers":[
        {
            "category":"Professional",
            "type":"Services"
        }
    ],
    "sg:phone":"+1 712 769 2500",
    "sg:postcode":"51544",
    "sg:province":"IA",
    "sg:tags":[
        "establishment"
    ],
    "wof:name":"R & B Improvements",
    "wof:placetype":"venue"
},
  "geometry": {"coordinates":[-95.151774,41.32022],"type":"Point"}
}