{
  "type": "Feature",
  "properties": {
    "iso:country":"US",
    "sg:address":"666 Grand Ave",
    "sg:city":"Des Moines",
    "sg:classifiers":[
        {
            "category":"Banks & Credit Unions",
            "subcategory":"Financial Services",
            "type":"Services"
        }
    ],
    "sg:phone":"+1 515 242 4300",
    "sg:postcode":"50309",
    "sg:province":"IA",
    "sg:tags":[
        "company",
        "utility"
    ],
    "wof:name":"Midamerican Energy Holdings Co",
    "wof:placetype":"venue"
},
  "geometry": {"coordinates":[-93.625344,41.587745],"type":"Point"}
}