{
  "type": "Feature",
  "properties": {
    "addr:full":"950 Senate Ave Red Oak IA 51566",
    "addr:housenumber":"950",
    "addr:postcode":"51566",
    "addr:street":"Senate Ave",
    "iso:country":"US",
    "sg:address":"950 Senate Ave",
    "sg:city":"Red Oak",
    "sg:classifiers":[
        {
            "category":"Health Services",
            "subcategory":"Clinic",
            "type":"Services"
        }
    ],
    "sg:phone":"+1 712 623 5546",
    "sg:postcode":"51566",
    "sg:province":"IA",
    "sg:website":"www.farmbureau.com",
    "wof:name":"Farm Bureau Insurance",
    "wof:placetype":"venue"
},
  "geometry": {"coordinates":[-95.22148300000001,41.026139],"type":"Point"}
}