{
  "type": "Feature",
  "properties": {
    "iso:country":"US",
    "sg:address":"117 3rd Ave SE",
    "sg:city":"Independence",
    "sg:classifiers":[
        {
            "category":"Building & Trades",
            "subcategory":"Landscaping Services",
            "type":"Services"
        }
    ],
    "sg:phone":"+1 319 334 2615",
    "sg:postcode":"50644",
    "sg:province":"IA",
    "sg:tags":[
        "lawn",
        "maintenance",
        "grounds"
    ],
    "wof:name":"Roy's Feed & Seed",
    "wof:placetype":"venue"
},
  "geometry": {"coordinates":[-91.89183,42.468538],"type":"Point"}
}