{
  "type": "Feature",
  "properties": {
    "addr:full":"4611 Buckeye St Davenport IA 52802",
    "addr:housenumber":"4611",
    "addr:postcode":"52802",
    "addr:street":"Buckeye St",
    "iso:country":"US",
    "sg:address":"4611 Buckeye St",
    "sg:city":"Davenport",
    "sg:phone":"+1 563 323 7625",
    "sg:postcode":"52802",
    "sg:province":"IA",
    "sg:tags":[
        "oil"
    ],
    "wof:name":"Rock Valley Oil & Chemical Co",
    "wof:placetype":"venue"
},
  "geometry": {"coordinates":[-90.638677,41.500516],"type":"Point"}
}