{
  "type": "Feature",
  "properties": {
    "iso:country":"US",
    "sg:address":"406 S West Ave",
    "sg:city":"Baxter",
    "sg:classifiers":[
        {
            "category":"Autos & Motor Vehicles",
            "subcategory":"Auto Supplies",
            "type":"Retail Goods"
        }
    ],
    "sg:phone":"+1 641 227 3608",
    "sg:postcode":"50028",
    "sg:province":"IA",
    "sg:tags":[
        "tire"
    ],
    "wof:name":"Thatcher Auto Ctr Inc",
    "wof:placetype":"venue"
},
  "geometry": {"coordinates":[-93.154477,41.821759],"type":"Point"}
}