{
  "type": "Feature",
  "properties": {
    "iso:country":"US",
    "sg:address":"2875 220th St",
    "sg:city":"Ainsworth",
    "sg:classifiers":[
        {
            "category":"Wholesale",
            "subcategory":"Farm Supplies",
            "type":"Manufacturing & Wholesale Goods"
        }
    ],
    "sg:phone":"+1 319 657 3792",
    "sg:postcode":"52201",
    "sg:province":"IA",
    "sg:tags":[
        "raw",
        "product",
        "material"
    ],
    "wof:name":"Witthoft Pork Inc",
    "wof:placetype":"venue"
},
  "geometry": {"coordinates":[-91.585866,41.337499],"type":"Point"}
}