{
  "type": "Feature",
  "properties": {
    "addr:full":"107 N Harlan St Algona IA 50511",
    "addr:housenumber":"107",
    "addr:postcode":"50511",
    "addr:street":"N Harlan St",
    "iso:country":"US",
    "sg:address":"107 N Harlan St",
    "sg:city":"Algona",
    "sg:classifiers":[
        {
            "category":"Professional",
            "subcategory":"Lawyer & Legal Services",
            "type":"Services"
        }
    ],
    "sg:phone":"+1 515 295 9361",
    "sg:postcode":"50511",
    "sg:province":"IA",
    "sg:tags":[
        "attorney"
    ],
    "wof:name":"Fenchel Doster & Buck",
    "wof:placetype":"venue"
},
  "geometry": {"coordinates":[-94.234323,43.069804],"type":"Point"}
}