{
  "type": "Feature",
  "properties": {
    "addr:full":"107 Sunset St Strawberry Point IA 52076",
    "addr:housenumber":"107",
    "addr:postcode":"52076",
    "addr:street":"Sunset St",
    "iso:country":"US",
    "sg:address":"107 Sunset St",
    "sg:city":"Strawberry Point",
    "sg:classifiers":[
        {
            "category":"Wholesale",
            "subcategory":"Machinery & Supplies",
            "type":"Manufacturing & Wholesale Goods"
        }
    ],
    "sg:phone":"+1 563 933 6155",
    "sg:postcode":"52076",
    "sg:province":"IA",
    "sg:tags":[
        "equipment",
        "establishment"
    ],
    "wof:name":"Burs Distributing",
    "wof:placetype":"venue"
},
  "geometry": {"coordinates":[-91.548332,42.681187],"type":"Point"}
}