{
  "type": "Feature",
  "properties": {
    "iso:country":"US",
    "sg:address":"221 W Greene St",
    "sg:city":"Clarksville",
    "sg:classifiers":[
        {
            "category":"Retail",
            "subcategory":"Funeral Services",
            "type":"Services"
        }
    ],
    "sg:phone":"+1 319 278 4245",
    "sg:postcode":"50619",
    "sg:province":"IA",
    "sg:tags":[
        "plan"
    ],
    "wof:name":"Redman-Schwartz Funeral Homes",
    "wof:placetype":"venue"
},
  "geometry": {"coordinates":[-92.670174,42.783704],"type":"Point"}
}