{
  "type": "Feature",
  "properties": {
    "iso:country":"US",
    "sg:address":"427 7th St NW",
    "sg:city":"Sioux Center",
    "sg:classifiers":[
        {
            "category":"Manufacturing",
            "subcategory":"Retail Goods",
            "type":"Manufacturing & Wholesale Goods"
        }
    ],
    "sg:phone":"+1 712 722 3174",
    "sg:postcode":"51250",
    "sg:province":"IA",
    "sg:tags":[
        "manufacturer"
    ],
    "wof:name":"Negus Manufacturing",
    "wof:placetype":"venue"
},
  "geometry": {"coordinates":[-96.182039,43.084215],"type":"Point"}
}