{
  "type": "Feature",
  "properties": {
    "addr:full":"4519 Urbandale Ave Des Moines IA 50310",
    "addr:housenumber":"4519",
    "addr:postcode":"50310",
    "addr:street":"Urbandale Ave",
    "iso:country":"US",
    "sg:address":"4519 Urbandale Ave",
    "sg:city":"Des Moines",
    "sg:classifiers":[
        {
            "category":"Building & Trades",
            "subcategory":"Construction",
            "type":"Services"
        }
    ],
    "sg:phone":"+1 515 276 9018",
    "sg:postcode":"50310",
    "sg:province":"IA",
    "sg:tags":[
        "operator",
        "apartment",
        "commercial",
        "contractor"
    ],
    "wof:name":"Clason Builders",
    "wof:placetype":"venue"
},
  "geometry": {"coordinates":[-93.680342,41.622294],"type":"Point"}
}