{
  "type": "Feature",
  "properties": {
    "iso:country":"US",
    "sg:address":"115 1st Ave E",
    "sg:city":"Newton",
    "sg:classifiers":[
        {
            "category":"Professional",
            "subcategory":"Business Services",
            "type":"Services"
        }
    ],
    "sg:phone":"+1 641 792 0019",
    "sg:postcode":"50208",
    "sg:province":"IA",
    "wof:name":"C S I-Central States Home Insp",
    "wof:placetype":"venue"
},
  "geometry": {"coordinates":[-93.052475,41.699468],"type":"Point"}
}