{
  "type": "Feature",
  "properties": {
    "iso:country":"US",
    "sg:address":"650 NE 52nd Ave",
    "sg:city":"Des Moines",
    "sg:classifiers":[
        {
            "category":"Organizations",
            "subcategory":"Religious Organization",
            "type":"Services"
        }
    ],
    "sg:phone":"+1 515 265 5001",
    "sg:postcode":"50313",
    "sg:province":"IA",
    "sg:tags":[
        "church"
    ],
    "sg:website":"www.dmallsaints.org",
    "wof:name":"All Saints Catholic Church",
    "wof:placetype":"venue"
},
  "geometry": {"coordinates":[-93.602299,41.654612],"type":"Point"}
}