{
  "type": "Feature",
  "properties": {
    "iso:country":"US",
    "sg:address":"120 Main St",
    "sg:city":"Columbus Jct",
    "sg:classifiers":[
        {
            "category":"Bars & Pubs",
            "type":"Food & Drink"
        }
    ],
    "sg:phone":"+1 319 728 7002",
    "sg:postcode":"52738",
    "sg:province":"IA",
    "wof:name":"LA Hacienda Bar",
    "wof:placetype":"venue"
},
  "geometry": {"coordinates":[-91.36059400000001,41.280755],"type":"Point"}
}