{
  "type": "Feature",
  "properties": {
    "addr:full":"31502 320th St Coon Rapids IA 50058",
    "addr:housenumber":"31502",
    "addr:postcode":"50058",
    "addr:street":"320Th St",
    "iso:country":"US",
    "sg:address":"31502 320th St",
    "sg:city":"Coon Rapids",
    "sg:phone":"+1 712 684 2902",
    "sg:postcode":"50058",
    "sg:province":"IA",
    "sg:tags":[
        "farm",
        "corn",
        "soybean"
    ],
    "wof:name":"Richard Hart",
    "wof:placetype":"venue"
},
  "geometry": {"coordinates":[-94.663442,41.891439],"type":"Point"}
}