{
  "type": "Feature",
  "properties": {
    "iso:country":"US",
    "sg:address":"2040 W Broadway",
    "sg:city":"Council Bluffs",
    "sg:classifiers":[
        {
            "category":"Shopping",
            "subcategory":"Gifts & Souvenirs",
            "type":"Retail Goods"
        }
    ],
    "sg:phone":"+1 712 323 4172",
    "sg:postcode":"51501",
    "sg:province":"IA",
    "wof:name":"Classic Sports Cards & Crafts",
    "wof:placetype":"venue"
},
  "geometry": {"coordinates":[-95.874726,41.261974],"type":"Point"}
}