{
  "type": "Feature",
  "properties": {
    "addr:full":"22548 185th St Allison IA 50602",
    "addr:housenumber":"22548",
    "addr:postcode":"50602",
    "addr:street":"185Th St",
    "iso:country":"US",
    "sg:address":"22548 185th St",
    "sg:city":"Allison",
    "sg:classifiers":[
        {
            "category":"Building & Trades",
            "subcategory":"Construction",
            "type":"Services"
        }
    ],
    "sg:phone":"+1 319 267 2793",
    "sg:postcode":"50602",
    "sg:province":"IA",
    "sg:tags":[
        "nonresidential"
    ],
    "wof:name":"Doyle Brocka",
    "wof:placetype":"venue"
},
  "geometry": {"coordinates":[-92.77772899999999,42.781543],"type":"Point"}
}