{
  "type": "Feature",
  "properties": {
    "addr:full":"104 Parkview Dr Webster City IA 50595",
    "addr:housenumber":"104",
    "addr:postcode":"50595",
    "addr:street":"Parkview Dr",
    "iso:country":"US",
    "sg:address":"104 Parkview Dr",
    "sg:city":"Webster City",
    "sg:classifiers":[
        {
            "category":"Shopping",
            "subcategory":"Gifts & Souvenirs",
            "type":"Retail Goods"
        }
    ],
    "sg:phone":"+1 515 832 1834",
    "sg:postcode":"50595",
    "sg:province":"IA",
    "wof:name":"First Class Klaver",
    "wof:placetype":"venue"
},
  "geometry": {"coordinates":[-93.823645,42.452669],"type":"Point"}
}