{
  "type": "Feature",
  "properties": {
    "addr:full":"101 Kirlin St Missouri Valley IA 51555",
    "addr:housenumber":"101",
    "addr:postcode":"51555",
    "addr:street":"Kirlin St",
    "iso:country":"US",
    "sg:address":"101 Kirlin St",
    "sg:city":"Missouri Valley",
    "sg:classifiers":[
        {
            "category":"Government",
            "subcategory":"Office",
            "type":"Public Place"
        }
    ],
    "sg:phone":"+1 712 642 2191",
    "sg:postcode":"51555",
    "sg:province":"IA",
    "sg:tags":[
        "village"
    ],
    "wof:name":"Maintenance Garage",
    "wof:placetype":"venue"
},
  "geometry": {"coordinates":[-95.897272,41.554247],"type":"Point"}
}