{
  "type": "Feature",
  "properties": {
    "addr:full":"4925 Utica Ridge Rd Davenport IA 52807",
    "addr:housenumber":"4925",
    "addr:postcode":"52807",
    "addr:street":"Utica Ridge Rd",
    "iso:country":"US",
    "sg:address":"4925 Utica Ridge Rd",
    "sg:city":"Davenport",
    "sg:classifiers":[
        {
            "category":"Food & Beverages",
            "subcategory":"Bakery",
            "type":"Retail Goods"
        }
    ],
    "sg:phone":"+1 563 332 8400",
    "sg:postcode":"52807",
    "sg:province":"IA",
    "sg:tags":[
        "baker"
    ],
    "wof:name":"Great Harvest Bread Co",
    "wof:placetype":"venue"
},
  "geometry": {"coordinates":[-90.515612,41.57016],"type":"Point"}
}