{
  "type": "Feature",
  "properties": {
    "iso:country":"US",
    "sg:address":"1033 Reed Ave",
    "sg:city":"Belmond",
    "sg:phone":"+1 641 444 4355",
    "sg:postcode":"50421",
    "sg:province":"IA",
    "sg:tags":[
        "farm",
        "field",
        "corn",
        "crop"
    ],
    "wof:name":"Foundry & Machine Shop",
    "wof:placetype":"venue"
},
  "geometry": {"coordinates":[-93.641266,42.902452],"type":"Point"}
}