{
  "type": "Feature",
  "properties": {
    "iso:country":"US",
    "sg:address":"430 180th St",
    "sg:city":"Corwith",
    "sg:phone":"+1 515 583 2005",
    "sg:postcode":"50430",
    "sg:province":"IA",
    "sg:tags":[
        "farm",
        "hog",
        "corn",
        "or",
        "feedlot"
    ],
    "wof:name":"Lawrence Luppen",
    "wof:placetype":"venue"
},
  "geometry": {"coordinates":[-93.89729,43.023823],"type":"Point"}
}