{
  "type": "Feature",
  "properties": {
    "iso:country":"US",
    "sg:address":"3636 Cottage Grove Ave SE",
    "sg:city":"Cedar Rapids",
    "sg:classifiers":[
        {
            "category":"Education",
            "subcategory":"Preschool",
            "type":"Public Place"
        },
        {
            "category":"Education",
            "subcategory":"School",
            "type":"Public Place"
        }
    ],
    "sg:phone":"+1 319 366 7462",
    "sg:postcode":"52403",
    "sg:province":"IA",
    "sg:tags":[
        "high",
        "middle",
        "elementary"
    ],
    "sg:website":"www.cedarvalley.org",
    "wof:name":"Cedar Valley Christian School",
    "wof:placetype":"venue"
},
  "geometry": {"coordinates":[-91.61509700000001,41.994999],"type":"Point"}
}