{
  "type": "Feature",
  "properties": {
    "iso:country":"US",
    "sg:address":"601 28th St",
    "sg:city":"Ames",
    "sg:classifiers":[
        {
            "category":"Education",
            "subcategory":"School",
            "type":"Public Place"
        }
    ],
    "sg:phone":"+1 515 239 3780",
    "sg:postcode":"50010",
    "sg:province":"IA",
    "sg:website":"www.ames.k12.ia.us",
    "wof:name":"Northwood Elementary School",
    "wof:placetype":"venue"
},
  "geometry": {"coordinates":[-93.61921100000001,42.049474],"type":"Point"}
}