{
  "type": "Feature",
  "properties": {
    "addr:full":"3140 16th Ave SW Cedar Rapids IA 52404",
    "addr:housenumber":"3140",
    "addr:postcode":"52404",
    "addr:street":"16Th Ave Sw",
    "iso:country":"US",
    "sg:address":"3140 16th Ave SW",
    "sg:city":"Cedar Rapids",
    "sg:classifiers":[
        {
            "category":"Cinema",
            "subcategory":"Movie Rental",
            "type":"Entertainment"
        }
    ],
    "sg:phone":"+1 319 364 6580",
    "sg:postcode":"52404",
    "sg:province":"IA",
    "sg:tags":[
        "game",
        "video"
    ],
    "sg:website":"www.blockbuster.com",
    "wof:name":"Blockbuster Video",
    "wof:placetype":"venue"
},
  "geometry": {"coordinates":[-91.713303,41.963402],"type":"Point"}
}