{
  "type": "Feature",
  "properties": {
    "addr:full":"105 W 2nd St N Newton IA 50208",
    "addr:housenumber":"105",
    "addr:postcode":"50208",
    "addr:street":"W 2Nd St N",
    "iso:country":"US",
    "sg:address":"105 W 2nd St N",
    "sg:city":"Newton",
    "sg:classifiers":[
        {
            "category":"Shopping",
            "subcategory":"Gifts & Souvenirs",
            "type":"Retail Goods"
        }
    ],
    "sg:phone":"+1 641 791 3063",
    "sg:postcode":"50208",
    "sg:province":"IA",
    "sg:tags":[
        "shop"
    ],
    "wof:name":"My Favorite Things",
    "wof:placetype":"venue"
},
  "geometry": {"coordinates":[-93.054937,41.700435],"type":"Point"}
}