{
  "type": "Feature",
  "properties": {
    "iso:country":"US",
    "sg:address":"403 Westridge Dr SW",
    "sg:city":"Cedar Rapids",
    "sg:classifiers":[
        {
            "category":"Personal",
            "type":"Services"
        }
    ],
    "sg:phone":"+1 319 265 4255",
    "sg:postcode":"52404",
    "sg:province":"IA",
    "sg:tags":[
        "party",
        "planning",
        "event"
    ],
    "wof:name":"Creative Occasions",
    "wof:placetype":"venue"
},
  "geometry": {"coordinates":[-91.762725,41.967156],"type":"Point"}
}