{
  "type": "Feature",
  "properties": {
    "iso:country":"US",
    "sg:address":"3003 SE 14th St",
    "sg:city":"Des Moines",
    "sg:classifiers":[
        {
            "category":"Retail",
            "subcategory":"Veterinary Services",
            "type":"Services"
        }
    ],
    "sg:phone":"+1 515 280 5336",
    "sg:postcode":"50320",
    "sg:province":"IA",
    "sg:tags":[
        "veterinarian"
    ],
    "wof:name":"Afford-A-Care Pet Hospital",
    "wof:placetype":"venue"
},
  "geometry": {"coordinates":[-93.596717,41.557464],"type":"Point"}
}