{
  "type": "Feature",
  "properties": {
    "iso:country":"US",
    "sg:address":"2147 US Hwy 61",
    "sg:city":"Muscatine",
    "sg:classifiers":[
        {
            "category":"Food & Beverages",
            "subcategory":"Fruits & Vegetables",
            "type":"Retail Goods"
        }
    ],
    "sg:phone":"+1 563 263 8886",
    "sg:postcode":"52761",
    "sg:province":"IA",
    "sg:tags":[
        "produce"
    ],
    "wof:name":"Mary Ann's Market",
    "wof:placetype":"venue"
},
  "geometry": {"coordinates":[-91.030266,41.445156],"type":"Point"}
}