{
  "type": "Feature",
  "properties": {
    "addr:full":"2680 2nd Ave Marion IA 52302",
    "addr:housenumber":"2680",
    "addr:postcode":"52302",
    "addr:street":"2Nd Ave",
    "iso:country":"US",
    "sg:address":"2680 2nd Ave",
    "sg:city":"Marion",
    "sg:classifiers":[
        {
            "category":"Building & Trades",
            "subcategory":"Construction",
            "type":"Services"
        }
    ],
    "sg:phone":"+1 319 377 5573",
    "sg:postcode":"52302",
    "sg:province":"IA",
    "sg:tags":[
        "repairing",
        "remodeling",
        "contractor"
    ],
    "wof:name":"Warner Brothers Inc",
    "wof:placetype":"venue"
},
  "geometry": {"coordinates":[-91.585112,42.029043],"type":"Point"}
}