{
  "type": "Feature",
  "properties": {
    "iso:country":"US",
    "sg:address":"1183 W Ave",
    "sg:city":"Amana",
    "sg:classifiers":[
        {
            "category":"Building & Trades",
            "subcategory":"Construction",
            "type":"Services"
        }
    ],
    "sg:phone":"+1 319 560 3037",
    "sg:postcode":"52203",
    "sg:province":"IA",
    "sg:tags":[
        "general",
        "contractor"
    ],
    "wof:name":"Schmidt Construction",
    "wof:placetype":"venue"
},
  "geometry": {"coordinates":[-91.869821,41.834404],"type":"Point"}
}