{
  "type": "Feature",
  "properties": {
    "iso:country":"US",
    "sg:address":"600 NE 6th St",
    "sg:city":"Pocahontas",
    "sg:classifiers":[
        {
            "category":"Building & Trades",
            "subcategory":"Construction",
            "type":"Services"
        }
    ],
    "sg:phone":"+1 712 335 3807",
    "sg:postcode":"50574",
    "sg:province":"IA",
    "sg:tags":[
        "excavating",
        "contractor"
    ],
    "wof:name":"Schoon Backhoe Svc",
    "wof:placetype":"venue"
},
  "geometry": {"coordinates":[-94.65891999999999,42.738561],"type":"Point"}
}