{
  "type": "Feature",
  "properties": {
    "iso:country":"US",
    "sg:address":"333 9th Ave",
    "sg:city":"De Witt",
    "sg:phone":"+1 563 659 8714",
    "sg:postcode":"52742",
    "sg:province":"IA",
    "sg:tags":[
        "farm",
        "corn",
        "soybean"
    ],
    "wof:name":"Glenita Acres Inc",
    "wof:placetype":"venue"
},
  "geometry": {"coordinates":[-90.54340000000001,41.818791],"type":"Point"}
}