{
  "type": "Feature",
  "properties": {
    "iso:country":"US",
    "sg:address":"1210 E 29th St",
    "sg:city":"Des Moines",
    "sg:classifiers":[
        {
            "category":"Retail",
            "subcategory":"Auto Repair",
            "type":"Services"
        }
    ],
    "sg:phone":"+1 515 262 5556",
    "sg:postcode":"50317",
    "sg:province":"IA",
    "sg:tags":[
        "body",
        "automobile",
        "painting"
    ],
    "wof:name":"Blake's Auto Body & Exhaust",
    "wof:placetype":"venue"
},
  "geometry": {"coordinates":[-93.561181,41.600986],"type":"Point"}
}