{
  "type": "Feature",
  "properties": {
    "addr:full":"2412 Park Ave Muscatine IA 52761",
    "addr:housenumber":"2412",
    "addr:postcode":"52761",
    "addr:street":"Park Ave",
    "iso:country":"US",
    "sg:address":"2412 Park Ave",
    "sg:city":"Muscatine",
    "sg:classifiers":[
        {
            "category":"Autos & Motor Vehicles",
            "subcategory":"Auto Supplies",
            "type":"Retail Goods"
        },
        {
            "category":"Retail",
            "subcategory":"Auto Repair",
            "type":"Services"
        }
    ],
    "sg:phone":"+1 563 264 3628",
    "sg:postcode":"52761",
    "sg:province":"IA",
    "sg:tags":[
        "automotive",
        "lube",
        "oil",
        "tune"
    ],
    "sg:website":"http://www.valvoline.com",
    "wof:name":"Valvoline Instant Oil Change",
    "wof:placetype":"venue"
},
  "geometry": {"coordinates":[-91.030248,41.449081],"type":"Point"}
}