{
  "type": "Feature",
  "properties": {
    "addr:full":"4829 Gifford Rd Council Bluffs IA 51501",
    "addr:housenumber":"4829",
    "addr:postcode":"51501",
    "addr:street":"Gifford Rd",
    "iso:country":"US",
    "sg:address":"4829 Gifford Rd",
    "sg:city":"Council Bluffs",
    "sg:classifiers":[
        {
            "category":"Building & Trades",
            "subcategory":"Construction",
            "type":"Services"
        }
    ],
    "sg:phone":"+1 712 366 1714",
    "sg:postcode":"51501",
    "sg:province":"IA",
    "sg:tags":[
        "contracting",
        "general"
    ],
    "wof:name":"Quigley Enterprises",
    "wof:placetype":"venue"
},
  "geometry": {"coordinates":[-95.880044,41.212933],"type":"Point"}
}