{
  "type": "Feature",
  "properties": {
    "addr:full":"1443 Hartong Dr Lansing IA 52151",
    "addr:housenumber":"1443",
    "addr:postcode":"52151",
    "addr:street":"Hartong Dr",
    "iso:country":"US",
    "sg:address":"1443 Hartong Dr",
    "sg:city":"Lansing",
    "sg:classifiers":[
        {
            "category":"Farming",
            "subcategory":"Dairy Farm",
            "type":"Manufacturing & Wholesale Goods"
        }
    ],
    "sg:phone":"+1 563 535 7487",
    "sg:postcode":"52151",
    "sg:province":"IA",
    "wof:name":"Larkin Acres",
    "wof:placetype":"venue"
},
  "geometry": {"coordinates":[-91.343136,43.319565],"type":"Point"}
}