{
  "type": "Feature",
  "properties": {
    "iso:country":"US",
    "sg:address":"2651 Telegraph Rd",
    "sg:city":"Davenport",
    "sg:classifiers":[
        {
            "category":"Education",
            "subcategory":"Preschool",
            "type":"Public Place"
        },
        {
            "category":"Education",
            "subcategory":"School",
            "type":"Public Place"
        }
    ],
    "sg:phone":"+1 563 323 4367",
    "sg:postcode":"52804",
    "sg:province":"IA",
    "sg:tags":[
        "elementary"
    ],
    "wof:name":"Head Start Centers",
    "wof:placetype":"venue"
},
  "geometry": {"coordinates":[-90.61900300000001,41.5201],"type":"Point"}
}