{
  "type": "Feature",
  "properties": {
    "iso:country":"US",
    "sg:address":"214 E 1st St",
    "sg:city":"Sumner",
    "sg:classifiers":[
        {
            "category":"Professional",
            "subcategory":"Computer Services",
            "type":"Services"
        }
    ],
    "sg:phone":"+1 563 578 1311",
    "sg:postcode":"50674",
    "sg:province":"IA",
    "wof:name":"Wescom",
    "wof:placetype":"venue"
},
  "geometry": {"coordinates":[-92.09638200000001,42.847534],"type":"Point"}
}