{
  "type": "Feature",
  "properties": {
    "iso:country":"US",
    "sg:address":"2001 University Ave",
    "sg:city":"Des Moines",
    "sg:classifiers":[
        {
            "category":"Retail",
            "subcategory":"Auto Repair",
            "type":"Services"
        }
    ],
    "sg:phone":"+1 515 243 9273",
    "sg:postcode":"50311",
    "sg:province":"IA",
    "sg:tags":[
        "wrecker"
    ],
    "wof:name":"Perry's Service & Towing",
    "wof:placetype":"venue"
},
  "geometry": {"coordinates":[-93.64494500000001,41.600412],"type":"Point"}
}