{
  "type": "Feature",
  "properties": {
    "addr:full":"961 Miller Ave Iowa City IA 52246",
    "addr:housenumber":"961",
    "addr:postcode":"52246",
    "addr:street":"Miller Ave",
    "iso:country":"US",
    "sg:address":"961 Miller Ave",
    "sg:city":"Iowa City",
    "sg:classifiers":[
        {
            "category":"Professional",
            "subcategory":"Business Services",
            "type":"Services"
        }
    ],
    "sg:phone":"+1 319 339 0111",
    "sg:postcode":"52246",
    "sg:province":"IA",
    "sg:tags":[
        "embroidery"
    ],
    "wof:name":"First Choice Embroidery",
    "wof:placetype":"venue"
},
  "geometry": {"coordinates":[-91.546678,41.649026],"type":"Point"}
}