{
  "type": "Feature",
  "properties": {
    "iso:country":"US",
    "sg:address":"712 Arden St",
    "sg:city":"Boone",
    "sg:classifiers":[
        {
            "category":"Professional",
            "subcategory":"Lawyer & Legal Services",
            "type":"Services"
        }
    ],
    "sg:phone":"+1 515 432 6618",
    "sg:postcode":"50036",
    "sg:province":"IA",
    "sg:tags":[
        "attorney"
    ],
    "wof:name":"Kruse & Dakin Law Office",
    "wof:placetype":"venue"
},
  "geometry": {"coordinates":[-93.88216300000001,42.063663],"type":"Point"}
}