{
  "type": "Feature",
  "properties": {
    "iso:country":"US",
    "sg:address":"1510 Main St",
    "sg:city":"Rock Valley",
    "sg:classifiers":[
        {
            "category":"Personal",
            "subcategory":"Beauty Salon",
            "type":"Services"
        }
    ],
    "sg:phone":"+1 712 476 9678",
    "sg:postcode":"51247",
    "sg:province":"IA",
    "wof:name":"Main Look's",
    "wof:placetype":"venue"
},
  "geometry": {"coordinates":[-96.294853,43.206141],"type":"Point"}
}