{
  "type": "Feature",
  "properties": {
    "addr:full":"504 E Jaycee St Avoca IA 51521",
    "addr:housenumber":"504",
    "addr:postcode":"51521",
    "addr:street":"E Jaycee St",
    "iso:country":"US",
    "sg:address":"504 E Jaycee St",
    "sg:city":"Avoca",
    "sg:classifiers":[
        {
            "category":"Farming",
            "subcategory":"Farm",
            "type":"Manufacturing & Wholesale Goods"
        }
    ],
    "sg:phone":"+1 712 343 2389",
    "sg:postcode":"51521",
    "sg:province":"IA",
    "sg:tags":[
        "crop",
        "general"
    ],
    "wof:name":"Willis Krummel",
    "wof:placetype":"venue"
},
  "geometry": {"coordinates":[-95.333794,41.489383],"type":"Point"}
}