{
  "type": "Feature",
  "properties": {
    "iso:country":"US",
    "sg:address":"3429 Miller Ave",
    "sg:city":"Davenport",
    "sg:classifiers":[
        {
            "category":"Professional",
            "type":"Services"
        }
    ],
    "sg:phone":"+1 563 322 6891",
    "sg:postcode":"52802",
    "sg:province":"IA",
    "sg:tags":[
        "establishment"
    ],
    "wof:name":"Silent Thunder",
    "wof:placetype":"venue"
},
  "geometry": {"coordinates":[-90.626108,41.494121],"type":"Point"}
}