{
  "type": "Feature",
  "properties": {
    "iso:country":"US",
    "sg:address":"1300 N 2nd St",
    "sg:city":"Cherokee",
    "sg:classifiers":[
        {
            "category":"Professional",
            "type":"Services"
        }
    ],
    "sg:phone":"+1 712 225 4047",
    "sg:postcode":"51012",
    "sg:province":"IA",
    "sg:tags":[
        "establishment"
    ],
    "wof:name":"Digital Plus",
    "wof:placetype":"venue"
},
  "geometry": {"coordinates":[-95.55242699999999,42.76477],"type":"Point"}
}