{
  "type": "Feature",
  "properties": {
    "iso:country":"US",
    "sg:address":"5158 NW Beaver Dr",
    "sg:city":"Johnston",
    "sg:classifiers":[
        {
            "category":"Wholesale",
            "subcategory":"Construction Materials",
            "type":"Manufacturing & Wholesale Goods"
        }
    ],
    "sg:phone":"+1 515 270 6227",
    "sg:postcode":"50131",
    "sg:province":"IA",
    "sg:tags":[
        "fence"
    ],
    "wof:name":"Des Moines Steel Fence Co",
    "wof:placetype":"venue"
},
  "geometry": {"coordinates":[-93.684681,41.657413],"type":"Point"}
}