{
  "type": "Feature",
  "properties": {
    "iso:country":"US",
    "sg:address":"101 1st St SW",
    "sg:city":"Oelwein",
    "sg:classifiers":[
        {
            "category":"Home & Garden",
            "subcategory":"Furniture",
            "type":"Retail Goods"
        }
    ],
    "sg:phone":"+1 319 283 1111",
    "sg:postcode":"50662",
    "sg:province":"IA",
    "wof:name":"Kempker Furniture",
    "wof:placetype":"venue"
},
  "geometry": {"coordinates":[-91.91530299999999,42.677074],"type":"Point"}
}