{
  "type": "Feature",
  "properties": {
    "iso:country":"US",
    "sg:address":"575 Huff St",
    "sg:city":"Dubuque",
    "sg:classifiers":[
        {
            "category":"Shopping",
            "subcategory":"Stationery & Office Supplies",
            "type":"Retail Goods"
        }
    ],
    "sg:phone":"+1 563 690 0158",
    "sg:postcode":"52003",
    "sg:province":"IA",
    "sg:website":"www.bizpads.com",
    "wof:name":"BIZPADS.COM",
    "wof:placetype":"venue"
},
  "geometry": {"coordinates":[-90.66153799999999,42.486169],"type":"Point"}
}