{
  "type": "Feature",
  "properties": {
    "addr:full":"1444 NW 124th Ct Des Moines IA 50325",
    "addr:housenumber":"1444",
    "addr:postcode":"50325",
    "addr:street":"Nw 124Th Ct",
    "iso:country":"US",
    "sg:address":"1444 NW 124th Ct",
    "sg:city":"Des Moines",
    "sg:classifiers":[
        {
            "category":"Real Estate",
            "subcategory":"Architect",
            "type":"Services"
        }
    ],
    "sg:phone":"+1 515 273 1111",
    "sg:postcode":"50325",
    "sg:province":"IA",
    "wof:name":"William J Ludwig & Assoc",
    "wof:placetype":"venue"
},
  "geometry": {"coordinates":[-93.78833400000001,41.602321],"type":"Point"}
}