{
  "type": "Feature",
  "properties": {
    "iso:country":"US",
    "sg:address":"4220 Regency Ct",
    "sg:city":"Davenport",
    "sg:classifiers":[
        {
            "category":"Real Estate",
            "subcategory":"Real Estate Agent",
            "type":"Services"
        }
    ],
    "sg:phone":"+1 563 388 2092",
    "sg:postcode":"52806",
    "sg:province":"IA",
    "wof:name":"Pheiffer Realty",
    "wof:placetype":"venue"
},
  "geometry": {"coordinates":[-90.608762,41.563463],"type":"Point"}
}