{
  "type": "Feature",
  "properties": {
    "iso:country":"US",
    "sg:address":"328 Broadway St",
    "sg:city":"Audubon",
    "sg:classifiers":[
        {
            "category":"Shopping",
            "subcategory":"Florist",
            "type":"Retail Goods"
        }
    ],
    "sg:phone":"+1 712 563 2253",
    "sg:postcode":"50025",
    "sg:province":"IA",
    "wof:name":"Lori's Flowers & Gifts",
    "wof:placetype":"venue"
},
  "geometry": {"coordinates":[-94.931764,41.721133],"type":"Point"}
}