{
  "type": "Feature",
  "properties": {
    "addr:full":"841 W Monroe St Washington IA 52353",
    "addr:housenumber":"841",
    "addr:postcode":"52353",
    "addr:street":"W Monroe St",
    "iso:country":"US",
    "sg:address":"841 W Monroe St",
    "sg:city":"Washington",
    "sg:classifiers":[
        {
            "category":"Real Estate",
            "subcategory":"Real Estate Operator",
            "type":"Services"
        },
        {
            "category":"Building & Trades",
            "subcategory":"Construction",
            "type":"Services"
        }
    ],
    "sg:phone":"+1 319 653 6804",
    "sg:postcode":"52353",
    "sg:province":"IA",
    "sg:tags":[
        "builder",
        "apartment",
        "operative"
    ],
    "wof:name":"Autumn Park of Washington",
    "wof:placetype":"venue"
},
  "geometry": {"coordinates":[-91.70246899999999,41.295547],"type":"Point"}
}