{
  "type": "Feature",
  "properties": {
    "iso:country":"US",
    "sg:address":"409 S 19th St",
    "sg:city":"Fort Dodge",
    "sg:classifiers":[
        {
            "category":"Retail",
            "subcategory":"Auto Repair",
            "type":"Services"
        }
    ],
    "sg:phone":"+1 515 576 1945",
    "sg:postcode":"50501",
    "sg:province":"IA",
    "sg:tags":[
        "automobile",
        "top",
        "upholstery"
    ],
    "wof:name":"Phil's Upholstery",
    "wof:placetype":"venue"
},
  "geometry": {"coordinates":[-94.172062,42.502042],"type":"Point"}
}