{
  "type": "Feature",
  "properties": {
    "iso:country":"US",
    "sg:address":"2029 215th St",
    "sg:city":"Grand Mound",
    "sg:classifiers":[
        {
            "category":"Retail",
            "subcategory":"Animal Services",
            "type":"Services"
        }
    ],
    "sg:phone":"+1 563 246 2857",
    "sg:postcode":"52751",
    "sg:province":"IA",
    "wof:name":"Irish Eyes Kennels",
    "wof:placetype":"venue"
},
  "geometry": {"coordinates":[-90.699089,41.865438],"type":"Point"}
}