{
  "type": "Feature",
  "properties": {
    "iso:country":"US",
    "sg:address":"2301 University Ave",
    "sg:city":"Des Moines",
    "sg:classifiers":[
        {
            "category":"Personal",
            "subcategory":"Barber",
            "type":"Services"
        }
    ],
    "sg:phone":"+1 515 255 4555",
    "sg:postcode":"50311",
    "sg:province":"IA",
    "wof:name":"Platinum Kuts",
    "wof:placetype":"venue"
},
  "geometry": {"coordinates":[-93.649709,41.600398],"type":"Point"}
}