{
  "type": "Feature",
  "properties": {
    "iso:country":"US",
    "sg:address":"220 52nd St",
    "sg:city":"Des Moines",
    "sg:classifiers":[
        {
            "category":"Insurance",
            "subcategory":"Insurance Agent",
            "type":"Services"
        }
    ],
    "sg:phone":"+1 515 279 3932",
    "sg:postcode":"50312",
    "sg:province":"IA",
    "wof:name":"Brauer Financial Services",
    "wof:placetype":"venue"
},
  "geometry": {"coordinates":[-93.688157,41.581981],"type":"Point"}
}