{
  "type": "Feature",
  "properties": {
    "iso:country":"US",
    "sg:address":"619 Court Ave",
    "sg:city":"Bedford",
    "sg:classifiers":[
        {
            "category":"Insurance",
            "subcategory":"Insurance Agent",
            "type":"Services"
        }
    ],
    "sg:phone":"+1 712 523 2918",
    "sg:postcode":"50833",
    "sg:province":"IA",
    "wof:name":"AFLAC",
    "wof:placetype":"venue"
},
  "geometry": {"coordinates":[-94.720106,40.667295],"type":"Point"}
}