{
  "type": "Feature",
  "properties": {
    "iso:country":"US",
    "sg:address":"1017 17th St",
    "sg:city":"Perry",
    "sg:classifiers":[
        {
            "category":"Retail",
            "subcategory":"Repair Shop",
            "type":"Services"
        }
    ],
    "sg:phone":"+1 515 465 2368",
    "sg:postcode":"50220",
    "sg:province":"IA",
    "sg:tags":[
        "upholsterer"
    ],
    "wof:name":"Martin Upholstery",
    "wof:placetype":"venue"
},
  "geometry": {"coordinates":[-94.08471,41.838289],"type":"Point"}
}