{
  "type": "Feature",
  "properties": {
    "iso:country":"US",
    "sg:address":"836 1st Ave NE",
    "sg:city":"Cedar Rapids",
    "sg:classifiers":[
        {
            "category":"Restaurant",
            "type":"Food & Drink"
        }
    ],
    "sg:phone":"+1 319 364 4779",
    "sg:postcode":"52402",
    "sg:province":"IA",
    "sg:tags":[
        "diner"
    ],
    "wof:name":"Riley's Cafe",
    "wof:placetype":"venue"
},
  "geometry": {"coordinates":[-91.661283,41.983103],"type":"Point"}
}