{
  "type": "Feature",
  "properties": {
    "iso:country":"US",
    "sg:address":"801 Grand Ave",
    "sg:city":"Des Moines",
    "sg:classifiers":[
        {
            "category":"Food & Beverages",
            "subcategory":"Specialty",
            "type":"Retail Goods"
        }
    ],
    "sg:phone":"+1 515 244 3934",
    "sg:postcode":"50309",
    "sg:province":"IA",
    "sg:tags":[
        "tea",
        "coffee"
    ],
    "wof:name":"Friedrich's World Coffees",
    "wof:placetype":"venue"
},
  "geometry": {"coordinates":[-93.62898,41.586969],"type":"Point"}
}