{
  "type": "Feature",
  "properties": {
    "iso:country":"US",
    "sg:address":"25448 320th St",
    "sg:city":"Minden",
    "sg:classifiers":[
        {
            "category":"Farming",
            "subcategory":"Farm",
            "type":"Manufacturing & Wholesale Goods"
        }
    ],
    "sg:phone":"+1 712 566 2532",
    "sg:postcode":"51553",
    "sg:province":"IA",
    "wof:name":"Windy Hill Farms Inc",
    "wof:placetype":"venue"
},
  "geometry": {"coordinates":[-95.57504400000001,41.38261],"type":"Point"}
}