{
  "type": "Feature",
  "properties": {
    "addr:full":"1200 Hwy 175 Stratford IA 50249",
    "addr:housenumber":"1200",
    "addr:postcode":"50249",
    "addr:street":"Hwy 175",
    "iso:country":"US",
    "sg:address":"1200 Hwy 175",
    "sg:city":"Stratford",
    "sg:classifiers":[
        {
            "category":"Health Services",
            "subcategory":"Nursing And Care Facility",
            "type":"Services"
        }
    ],
    "sg:phone":"+1 515 838 2795",
    "sg:postcode":"50249",
    "sg:province":"IA",
    "sg:tags":[
        "home",
        "convalescent"
    ],
    "wof:name":"Stratford Nursing & Rehab Ctr",
    "wof:placetype":"venue"
},
  "geometry": {"coordinates":[-93.923098,42.2678],"type":"Point"}
}