{
  "type": "Feature",
  "properties": {
    "iso:country":"US",
    "sg:address":"6190 320th St",
    "sg:city":"Sanborn",
    "sg:phone":"+1 712 729 3174",
    "sg:postcode":"51248",
    "sg:province":"IA",
    "sg:tags":[
        "beef",
        "farm",
        "corn",
        "soybean",
        "cattle",
        "feedlot"
    ],
    "wof:name":"Jay Solsma",
    "wof:placetype":"venue"
},
  "geometry": {"coordinates":[-95.566738,43.18544],"type":"Point"}
}