{
  "type": "Feature",
  "properties": {
    "iso:country":"US",
    "sg:address":"124 W 4th St",
    "sg:city":"Kanawha",
    "sg:classifiers":[
        {
            "category":"Local Transit",
            "type":"Transportation"
        }
    ],
    "sg:phone":"+1 641 762 3542",
    "sg:postcode":"50447",
    "sg:province":"IA",
    "sg:tags":[
        "passenger"
    ],
    "wof:name":"Nick Verbrugge",
    "wof:placetype":"venue"
},
  "geometry": {"coordinates":[-93.793623,42.937415],"type":"Point"}
}