{
  "type": "Feature",
  "properties": {
    "addr:full":"300 American Ave Jefferson IA 50129",
    "addr:housenumber":"300",
    "addr:postcode":"50129",
    "addr:street":"American Ave",
    "iso:country":"US",
    "sg:address":"300 American Ave",
    "sg:city":"Jefferson",
    "sg:classifiers":[
        {
            "category":"Wholesale",
            "subcategory":"Farm Supplies",
            "type":"Manufacturing & Wholesale Goods"
        }
    ],
    "sg:phone":"+1 515 386 8121",
    "sg:postcode":"50129",
    "sg:province":"IA",
    "sg:tags":[
        "bulb",
        "seed"
    ],
    "wof:name":"Syngenta Seeds Inc",
    "wof:placetype":"venue"
},
  "geometry": {"coordinates":[-94.37783899999999,42.032191],"type":"Point"}
}