{
  "type": "Feature",
  "properties": {
    "addr:full":"1350 John F Kennedy Rd Dubuque IA 52002",
    "addr:housenumber":"1350",
    "addr:postcode":"52002",
    "addr:street":"John F Kennedy Rd",
    "iso:country":"US",
    "sg:address":"1350 John F Kennedy Rd",
    "sg:city":"Dubuque",
    "sg:classifiers":[
        {
            "category":"Restaurant",
            "type":"Food & Drink"
        }
    ],
    "sg:menulink":"http://www.allmenus.com/ia/dubuque/160752-burger-king/menu/",
    "sg:phone":"+1 563 556 3621",
    "sg:postcode":"52002",
    "sg:province":"IA",
    "sg:tags":[
        "burger",
        "american"
    ],
    "wof:name":"Burger King",
    "wof:placetype":"venue"
},
  "geometry": {"coordinates":[-90.72005299999999,42.495915],"type":"Point"}
}