{
  "type": "Feature",
  "properties": {
    "iso:country":"US",
    "sg:address":"1012 Jeffreys Dr",
    "sg:city":"Osceola",
    "sg:classifiers":[
        {
            "category":"Shopping",
            "subcategory":"Department Store",
            "type":"Retail Goods"
        }
    ],
    "sg:phone":"+1 641 342 6511",
    "sg:postcode":"50213",
    "sg:province":"IA",
    "sg:tags":[
        "shop"
    ],
    "wof:name":"Pamida",
    "wof:placetype":"venue"
},
  "geometry": {"coordinates":[-93.779456,41.029867],"type":"Point"}
}