{
  "type": "Feature",
  "properties": {
    "iso:country":"US",
    "sg:address":"1551 Valley West Dr",
    "sg:city":"West Des Moines",
    "sg:classifiers":[
        {
            "category":"Shopping",
            "subcategory":"Shoes",
            "type":"Retail Goods"
        }
    ],
    "sg:phone":"+1 515 225 2824",
    "sg:postcode":"50266",
    "sg:province":"IA",
    "wof:name":"Walker's Shoe Store",
    "wof:placetype":"venue"
},
  "geometry": {"coordinates":[-93.752071,41.596133],"type":"Point"}
}