{
  "type": "Feature",
  "properties": {
    "iso:country":"US",
    "sg:address":"2325 Q Ave",
    "sg:city":"Clarinda",
    "sg:classifiers":[
        {
            "category":"Farming",
            "subcategory":"Livestock Farm",
            "type":"Manufacturing & Wholesale Goods"
        }
    ],
    "sg:phone":"+1 712 542 3028",
    "sg:postcode":"51632",
    "sg:province":"IA",
    "sg:tags":[
        "beef",
        "corn",
        "cash",
        "grain",
        "cattle",
        "feedlot"
    ],
    "wof:name":"Vic Blume",
    "wof:placetype":"venue"
},
  "geometry": {"coordinates":[-95.06713499999999,40.706667],"type":"Point"}
}