{
  "type": "Feature",
  "properties": {
    "addr:full":"512 S Union St Rock Rapids IA 51246",
    "addr:housenumber":"512",
    "addr:postcode":"51246",
    "addr:street":"S Union St",
    "iso:country":"US",
    "sg:address":"512 S Union St",
    "sg:city":"Rock Rapids",
    "sg:classifiers":[
        {
            "category":"Organizations",
            "subcategory":"Religious Organization",
            "type":"Services"
        }
    ],
    "sg:phone":"+1 712 472 3729",
    "sg:postcode":"51246",
    "sg:province":"IA",
    "sg:tags":[
        "church"
    ],
    "wof:name":"First Reformed Church",
    "wof:placetype":"venue"
},
  "geometry": {"coordinates":[-96.175546,43.42723],"type":"Point"}
}