{
  "type": "Feature",
  "properties": {
    "iso:country":"US",
    "sg:address":"710 Ave F",
    "sg:city":"Fort Madison",
    "sg:classifiers":[
        {
            "category":"Professional",
            "subcategory":"Lawyer & Legal Services",
            "type":"Services"
        }
    ],
    "sg:phone":"+1 319 372 5673",
    "sg:postcode":"52627",
    "sg:province":"IA",
    "sg:tags":[
        "attorney"
    ],
    "wof:name":"Lee County Attorney's Office",
    "wof:placetype":"venue"
},
  "geometry": {"coordinates":[-91.311418,40.63191],"type":"Point"}
}