{
  "type": "Feature",
  "properties": {
    "iso:country":"US",
    "sg:address":"142 3rd St",
    "sg:city":"Underwood",
    "sg:classifiers":[
        {
            "category":"Animal Shelter",
            "type":"Public Place"
        },
        {
            "category":"Retail",
            "subcategory":"Veterinary Services",
            "type":"Services"
        }
    ],
    "sg:phone":"+1 712 566 3233",
    "sg:postcode":"51576",
    "sg:province":"IA",
    "sg:tags":[
        "specialty"
    ],
    "wof:name":"Pottawattamie County Animal Control",
    "wof:placetype":"venue"
},
  "geometry": {"coordinates":[-95.677092,41.387131],"type":"Point"}
}