{
  "type": "Feature",
  "properties": {
    "addr:full":"1410 Independence Ave Waterloo IA 50703",
    "addr:housenumber":"1410",
    "addr:postcode":"50703",
    "addr:street":"Independence Ave",
    "iso:country":"US",
    "sg:address":"1410 Independence Ave",
    "sg:city":"Waterloo",
    "sg:classifiers":[
        {
            "category":"Education",
            "subcategory":"School",
            "type":"Public Place"
        }
    ],
    "sg:phone":"+1 319 433 2630",
    "sg:postcode":"50703",
    "sg:province":"IA",
    "wof:name":"Mc Kinstry Elementary School",
    "wof:placetype":"venue"
},
  "geometry": {"coordinates":[-92.309089,42.498309],"type":"Point"}
}