{
  "type": "Feature",
  "properties": {
    "addr:full":"217 1st Ave E Oskaloosa IA 52577",
    "addr:housenumber":"217",
    "addr:postcode":"52577",
    "addr:street":"1St Ave E Oskaloosa",
    "iso:country":"US",
    "sg:address":"217 1st Ave E",
    "sg:city":"Oskaloosa",
    "sg:classifiers":[
        {
            "category":"Banks & Credit Unions",
            "subcategory":"Investment Brokerage",
            "type":"Services"
        }
    ],
    "sg:phone":"+1 641 673 8691",
    "sg:postcode":"52577",
    "sg:province":"IA",
    "sg:tags":[
        "stock",
        "bond"
    ],
    "wof:name":"Edward Jones Co",
    "wof:placetype":"venue"
},
  "geometry": {"coordinates":[-92.643688,41.294512],"type":"Point"}
}