{
  "type": "Feature",
  "properties": {
    "addr:full":"1904 N Division St Davenport IA 52804",
    "addr:housenumber":"1904",
    "addr:postcode":"52804",
    "addr:street":"N Division St",
    "iso:country":"US",
    "sg:address":"1904 N Division St",
    "sg:city":"Davenport",
    "sg:classifiers":[
        {
            "category":"Restaurant",
            "type":"Food & Drink"
        }
    ],
    "sg:phone":"+1 563 323 0069",
    "sg:postcode":"52804",
    "sg:province":"IA",
    "sg:tags":[
        "pizza"
    ],
    "wof:name":"Pizza Chef",
    "wof:placetype":"venue"
},
  "geometry": {"coordinates":[-90.60111999999999,41.539193],"type":"Point"}
}