{
  "type": "Feature",
  "properties": {
    "addr:full":"1454 30th St Des Moines IA 50311",
    "addr:housenumber":"1454",
    "addr:postcode":"50311",
    "addr:street":"30Th St",
    "iso:country":"US",
    "sg:address":"1454 30th St",
    "sg:city":"Des Moines",
    "sg:classifiers":[
        {
            "category":"Insurance",
            "subcategory":"Hazard Insurance",
            "type":"Services"
        }
    ],
    "sg:phone":"+1 515 224 9400",
    "sg:postcode":"50311",
    "sg:province":"IA",
    "sg:tags":[
        "employee",
        "benefit",
        "compensation",
        "plan"
    ],
    "sg:website":"www.kabelbiz.com",
    "wof:name":"Kabel Business Svc",
    "wof:placetype":"venue"
},
  "geometry": {"coordinates":[-93.658517,41.604796],"type":"Point"}
}