{
  "type": "Feature",
  "properties": {
    "addr:full":"3034 Underwood Ave Gilman IA 50106",
    "addr:housenumber":"3034",
    "addr:postcode":"50106",
    "addr:street":"Underwood Ave",
    "iso:country":"US",
    "sg:address":"3034 Underwood Ave",
    "sg:city":"Gilman",
    "sg:phone":"+1 641 478 3355",
    "sg:postcode":"50106",
    "sg:province":"IA",
    "sg:tags":[
        "farm",
        "corn"
    ],
    "wof:name":"Donald Lutes",
    "wof:placetype":"venue"
},
  "geometry": {"coordinates":[-92.857615,41.917755],"type":"Point"}
}