{
  "type": "Feature",
  "properties": {
    "addr:full":"2511 Jackson Cir Spirit Lake IA 51360",
    "addr:housenumber":"2511",
    "addr:postcode":"51360",
    "addr:street":"Jackson Cir",
    "iso:country":"US",
    "sg:address":"2511 Jackson Cir",
    "sg:city":"Spirit Lake",
    "sg:classifiers":[
        {
            "category":"Home & Garden",
            "subcategory":"Home Furnishings",
            "type":"Retail Goods"
        }
    ],
    "sg:phone":"+1 712 336 3167",
    "sg:postcode":"51360",
    "sg:province":"IA",
    "sg:tags":[
        "curtain",
        "made",
        "drapery"
    ],
    "wof:name":"Mary Q's Draperies",
    "wof:placetype":"venue"
},
  "geometry": {"coordinates":[-95.104722,43.417304],"type":"Point"}
}