{
  "type": "Feature",
  "properties": {
    "addr:full":"1556 W Locust St Davenport IA 52804",
    "addr:housenumber":"1556",
    "addr:postcode":"52804",
    "addr:street":"W Locust St",
    "iso:country":"US",
    "sg:address":"1556 W Locust St",
    "sg:city":"Davenport",
    "sg:classifiers":[
        {
            "category":"Autos & Motor Vehicles",
            "subcategory":"Fuel & Gas Station",
            "type":"Retail Goods"
        }
    ],
    "sg:phone":"+1 563 322 7230",
    "sg:postcode":"52804",
    "sg:province":"IA",
    "sg:tags":[
        "oil"
    ],
    "wof:name":"Hagen's Amoco Inc",
    "wof:placetype":"venue"
},
  "geometry": {"coordinates":[-90.598493,41.538325],"type":"Point"}
}