{
  "type": "Feature",
  "properties": {
    "iso:country":"US",
    "sg:address":"11129 NW 54th Ave",
    "sg:city":"Grimes",
    "sg:classifiers":[
        {
            "category":"Manufacturing",
            "subcategory":"Tools & Machinery",
            "type":"Manufacturing & Wholesale Goods"
        }
    ],
    "sg:phone":"+1 515 986 4111",
    "sg:postcode":"50111",
    "sg:province":"IA",
    "sg:tags":[
        "interlock",
        "ignition",
        "devices"
    ],
    "wof:name":"Affordable Ignition Interlock",
    "wof:placetype":"venue"
},
  "geometry": {"coordinates":[-93.77220800000001,41.658579],"type":"Point"}
}