{
  "type": "Feature",
  "properties": {
    "iso:country":"US",
    "sg:address":"721 7th St",
    "sg:city":"Hawarden",
    "sg:classifiers":[
        {
            "category":"Government",
            "subcategory":"Fire Station",
            "type":"Public Place"
        }
    ],
    "sg:phone":"+1 712 551 4434",
    "sg:postcode":"51023",
    "sg:province":"IA",
    "sg:tags":[
        "department"
    ],
    "wof:name":"Hawarden Fire Station",
    "wof:placetype":"venue"
},
  "geometry": {"coordinates":[-96.48493000000001,42.99342],"type":"Point"}
}