{
  "type": "Feature",
  "properties": {
    "iso:country":"US",
    "sg:address":"7191 Aspen Dr",
    "sg:city":"West Des Moines",
    "sg:classifiers":[
        {
            "category":"Building & Trades",
            "subcategory":"Construction",
            "type":"Services"
        }
    ],
    "sg:phone":"+1 515 225 8943",
    "sg:postcode":"50266",
    "sg:province":"IA",
    "sg:tags":[
        "hanging",
        "contractor"
    ],
    "wof:name":"CT Painting",
    "wof:placetype":"venue"
},
  "geometry": {"coordinates":[-93.805368,41.579604],"type":"Point"}
}