{
  "type": "Feature",
  "properties": {
    "addr:full":"72 Main Ave S Britt IA 50423",
    "addr:housenumber":"72",
    "addr:postcode":"50423",
    "addr:street":"Main Ave S",
    "iso:country":"US",
    "sg:address":"72 Main Ave S",
    "sg:city":"Britt",
    "sg:classifiers":[
        {
            "category":"Restaurant",
            "type":"Food & Drink"
        }
    ],
    "sg:phone":"+1 641 843 3840",
    "sg:postcode":"50423",
    "sg:province":"IA",
    "wof:name":"Mary Jo's Hobo House & Ctrng",
    "wof:placetype":"venue"
},
  "geometry": {"coordinates":[-93.801897,43.096267],"type":"Point"}
}