{
  "type": "Feature",
  "properties": {
    "iso:country":"US",
    "sg:address":"1510 Ohio St",
    "sg:city":"Des Moines",
    "sg:classifiers":[
        {
            "category":"Restaurant",
            "type":"Food & Drink"
        }
    ],
    "sg:phone":"+1 515 244 7194",
    "sg:postcode":"50314",
    "sg:province":"IA",
    "sg:tags":[
        "banquet",
        "rooms"
    ],
    "wof:name":"Water Wheel",
    "wof:placetype":"venue"
},
  "geometry": {"coordinates":[-93.617391,41.607452],"type":"Point"}
}