{
  "type": "Feature",
  "properties": {
    "iso:country":"US",
    "sg:address":"5324 N Pine St",
    "sg:city":"Davenport",
    "sg:classifiers":[
        {
            "category":"Retail",
            "subcategory":"Auto Repair",
            "type":"Services"
        }
    ],
    "sg:phone":"+1 563 386 2090",
    "sg:postcode":"52806",
    "sg:province":"IA",
    "sg:tags":[
        "repairing",
        "automobile"
    ],
    "wof:name":"Kimberly Auto Ctr",
    "wof:placetype":"venue"
},
  "geometry": {"coordinates":[-90.610226,41.574789],"type":"Point"}
}