{
  "type": "Feature",
  "properties": {
    "iso:country":"US",
    "sg:address":"14587 300th Ct",
    "sg:city":"Mason City",
    "sg:classifiers":[
        {
            "category":"Building & Trades",
            "subcategory":"Construction",
            "type":"Services"
        }
    ],
    "sg:phone":"+1 641 422 0541",
    "sg:postcode":"50401",
    "sg:province":"IA",
    "sg:tags":[
        "stucco",
        "contractor"
    ],
    "wof:name":"Universal Wall Systems Inc",
    "wof:placetype":"venue"
},
  "geometry": {"coordinates":[-93.226359,43.198524],"type":"Point"}
}