{
  "type": "Feature",
  "properties": {
    "addr:full":"1921 18th St Sioux City IA 51105",
    "addr:housenumber":"1921",
    "addr:postcode":"51105",
    "addr:street":"18Th St",
    "iso:country":"US",
    "sg:address":"1921 18th St",
    "sg:city":"Sioux City",
    "sg:classifiers":[
        {
            "category":"Government",
            "subcategory":"Office",
            "type":"Public Place"
        }
    ],
    "sg:phone":"+1 712 279 6217",
    "sg:postcode":"51105",
    "sg:province":"IA",
    "sg:tags":[
        "village"
    ],
    "sg:website":"www.sioux-city.org",
    "wof:name":"Sewer Maintenance/Backups",
    "wof:placetype":"venue"
},
  "geometry": {"coordinates":[-96.383954,42.508437],"type":"Point"}
}