{
  "type": "Feature",
  "properties": {
    "addr:full":"16008 Eddyville Rd Ottumwa IA 52501",
    "addr:postcode":"16008;52501",
    "addr:street":"Eddyville Rd",
    "iso:country":"US",
    "sg:address":"16008 Eddyville Rd",
    "sg:city":"Ottumwa",
    "sg:classifiers":[
        {
            "category":"Wholesale",
            "subcategory":"Construction Materials",
            "type":"Manufacturing & Wholesale Goods"
        }
    ],
    "sg:phone":"+1 641 684 4691",
    "sg:postcode":"52501",
    "sg:province":"IA",
    "sg:tags":[
        "sand",
        "gravel"
    ],
    "wof:name":"Douds Stone",
    "wof:placetype":"venue"
},
  "geometry": {"coordinates":[-92.466458,41.058334],"type":"Point"}
}