{
  "type": "Feature",
  "properties": {
    "addr:full":"3405 Oakory Ln Bettendorf IA 52722",
    "addr:housenumber":"3405",
    "addr:postcode":"52722",
    "addr:street":"Oakory Ln",
    "iso:country":"US",
    "sg:address":"3405 Oakory Ln",
    "sg:city":"Bettendorf",
    "sg:classifiers":[
        {
            "category":"Home & Garden",
            "subcategory":"Home Furnishings",
            "type":"Retail Goods"
        }
    ],
    "sg:phone":"+1 563 359 7233",
    "sg:postcode":"52722",
    "sg:province":"IA",
    "sg:tags":[
        "housewares"
    ],
    "wof:name":"Ideal Party Sales",
    "wof:placetype":"venue"
},
  "geometry": {"coordinates":[-90.484573,41.540421],"type":"Point"}
}