{
  "type": "Feature",
  "properties": {
    "addr:full":"522 Main St Luana IA 52156",
    "addr:housenumber":"522",
    "addr:postcode":"52156",
    "addr:street":"Main St",
    "iso:country":"US",
    "sg:address":"522 Main St",
    "sg:city":"Luana",
    "sg:classifiers":[
        {
            "category":"Social Services",
            "type":"Services"
        }
    ],
    "sg:phone":"+1 563 539 2477",
    "sg:postcode":"52156",
    "sg:province":"IA",
    "sg:tags":[
        "organization",
        "welfare"
    ],
    "wof:name":"Northeast Iowa Action Corp",
    "wof:placetype":"venue"
},
  "geometry": {"coordinates":[-91.461603,43.060707],"type":"Point"}
}