{
  "type": "Feature",
  "properties": {
    "addr:full":"512 5th St SE Belmond IA 50421",
    "addr:housenumber":"512",
    "addr:postcode":"50421",
    "addr:street":"5Th St Se",
    "iso:country":"US",
    "sg:address":"512 5th St SE",
    "sg:city":"Belmond",
    "sg:classifiers":[
        {
            "category":"Government",
            "subcategory":"Office",
            "type":"Public Place"
        }
    ],
    "sg:phone":"+1 641 444 3267",
    "sg:postcode":"50421",
    "sg:province":"IA",
    "wof:name":"County Shed",
    "wof:placetype":"venue"
},
  "geometry": {"coordinates":[-93.61146100000001,42.841509],"type":"Point"}
}