{
  "type": "Feature",
  "properties": {
    "iso:country":"US",
    "sg:address":"1096 212 Pl",
    "sg:city":"Shenandoah",
    "sg:classifiers":[
        {
            "category":"Personal",
            "subcategory":"Beauty Salon",
            "type":"Services"
        }
    ],
    "sg:phone":"+1 712 246 3526",
    "sg:postcode":"51601",
    "sg:province":"IA",
    "sg:tags":[
        "shop"
    ],
    "wof:name":"Connie Quists Tanning Salon",
    "wof:placetype":"venue"
},
  "geometry": {"coordinates":[-95.369725,40.741186],"type":"Point"}
}