{
  "type": "Feature",
  "properties": {
    "iso:country":"US",
    "sg:address":"11639 290th St",
    "sg:city":"Manning",
    "sg:classifiers":[
        {
            "category":"Farming",
            "subcategory":"Farm",
            "type":"Manufacturing & Wholesale Goods"
        }
    ],
    "sg:phone":"+1 712 653 2062",
    "sg:postcode":"51455",
    "sg:province":"IA",
    "sg:tags":[
        "crop",
        "general"
    ],
    "wof:name":"Kevin Behrans",
    "wof:placetype":"venue"
},
  "geometry": {"coordinates":[-95.061601,41.935563],"type":"Point"}
}