{
  "type": "Feature",
  "properties": {
    "addr:full":"2122 SE 14th St Des Moines IA 50320",
    "addr:housenumber":"2122",
    "addr:postcode":"50320",
    "addr:street":"Se 14Th St",
    "iso:country":"US",
    "sg:address":"2122 SE 14th St",
    "sg:city":"Des Moines",
    "sg:classifiers":[
        {
            "category":"Retail",
            "subcategory":"Auto Repair",
            "type":"Services"
        }
    ],
    "sg:phone":"+1 515 243 3139",
    "sg:postcode":"50320",
    "sg:province":"IA",
    "sg:tags":[
        "automobile",
        "electric"
    ],
    "wof:name":"Pioneer Electric",
    "wof:placetype":"venue"
},
  "geometry": {"coordinates":[-93.597008,41.567719],"type":"Point"}
}