{
  "type": "Feature",
  "properties": {
    "addr:full":"2397 55th St Vinton IA 52349",
    "addr:housenumber":"2397",
    "addr:postcode":"52349",
    "addr:street":"55Th St",
    "iso:country":"US",
    "sg:address":"2397 55th St",
    "sg:city":"Vinton",
    "sg:classifiers":[
        {
            "category":"Farming",
            "subcategory":"Farm",
            "type":"Manufacturing & Wholesale Goods"
        }
    ],
    "sg:phone":"+1 319 472 2105",
    "sg:postcode":"52349",
    "sg:province":"IA",
    "sg:tags":[
        "crop",
        "general"
    ],
    "wof:name":"Jill Marlow",
    "wof:placetype":"venue"
},
  "geometry": {"coordinates":[-92.030444,42.224956],"type":"Point"}
}