{
  "type": "Feature",
  "properties": {
    "addr:full":"311 W Marengo Rd Tiffin IA 52340",
    "addr:housenumber":"311",
    "addr:postcode":"52340",
    "addr:street":"W Marengo Rd",
    "iso:country":"US",
    "sg:address":"311 W Marengo Rd",
    "sg:city":"Tiffin",
    "sg:classifiers":[
        {
            "category":"Education",
            "subcategory":"School",
            "type":"Public Place"
        }
    ],
    "sg:phone":"+1 319 645 2361",
    "sg:postcode":"52340",
    "sg:province":"IA",
    "sg:website":"www.cc-amana.k12.ia.us",
    "wof:name":"Clear Creek High School",
    "wof:placetype":"venue"
},
  "geometry": {"coordinates":[-91.666798,41.707173],"type":"Point"}
}