{
  "type": "Feature",
  "properties": {
    "addr:full":"1010 W Lincolnway Marshalltown IA 50158",
    "addr:housenumber":"1010",
    "addr:postcode":"50158",
    "addr:street":"W Lincolnway",
    "iso:country":"US",
    "sg:address":"1010 W Lincolnway",
    "sg:city":"Marshalltown",
    "sg:classifiers":[
        {
            "category":"Restaurant",
            "type":"Food & Drink"
        }
    ],
    "sg:phone":"+1 641 753 4693",
    "sg:postcode":"50158",
    "sg:province":"IA",
    "sg:tags":[
        "banquet",
        "rooms"
    ],
    "wof:name":"Memories Banquet & Reception",
    "wof:placetype":"venue"
},
  "geometry": {"coordinates":[-92.929006,42.04177],"type":"Point"}
}