{
  "type": "Feature",
  "properties": {
    "addr:full":"6365 190th Ave Newell IA 50568",
    "addr:housenumber":"6365",
    "addr:postcode":"50568",
    "addr:street":"190Th Ave",
    "iso:country":"US",
    "sg:address":"6365 190th Ave",
    "sg:city":"Newell",
    "sg:phone":"+1 712 272 4574",
    "sg:postcode":"50568",
    "sg:province":"IA",
    "sg:tags":[
        "beef",
        "farm",
        "corn",
        "soybean",
        "cattle",
        "feedlot"
    ],
    "wof:name":"Quentin Bodholdt",
    "wof:placetype":"venue"
},
  "geometry": {"coordinates":[-95.033226,42.595049],"type":"Point"}
}