{
  "type": "Feature",
  "properties": {
    "iso:country":"US",
    "sg:address":"618 10th Ave E",
    "sg:city":"Spencer",
    "sg:classifiers":[
        {
            "category":"Wholesale",
            "subcategory":"Machinery & Supplies",
            "type":"Manufacturing & Wholesale Goods"
        }
    ],
    "sg:phone":"+1 712 262 9313",
    "sg:postcode":"51301",
    "sg:province":"IA",
    "wof:name":"Piston Engine Parts Warehouse",
    "wof:placetype":"venue"
},
  "geometry": {"coordinates":[-95.13074400000001,43.14514],"type":"Point"}
}