{
  "type": "Feature",
  "properties": {
    "iso:country":"US",
    "sg:address":"1573 Elm St",
    "sg:city":"Dubuque",
    "sg:classifiers":[
        {
            "category":"Personal",
            "subcategory":"Barber",
            "type":"Services"
        }
    ],
    "sg:phone":"+1 563 556 7081",
    "sg:postcode":"52001",
    "sg:province":"IA",
    "sg:tags":[
        "shop"
    ],
    "wof:name":"Ruffs Alpine Barber Shop",
    "wof:placetype":"venue"
},
  "geometry": {"coordinates":[-90.664489,42.508527],"type":"Point"}
}