{
  "type": "Feature",
  "properties": {
    "iso:country":"US",
    "sg:address":"206 W 7th St",
    "sg:city":"Carroll",
    "sg:classifiers":[
        {
            "category":"Autos & Motor Vehicles",
            "subcategory":"Automobile Sales",
            "type":"Retail Goods"
        }
    ],
    "sg:phone":"+1 712 792 9600",
    "sg:postcode":"51401",
    "sg:province":"IA",
    "sg:tags":[
        "aircraft"
    ],
    "wof:name":"Schettler Enterprise Inc",
    "wof:placetype":"venue"
},
  "geometry": {"coordinates":[-94.869525,42.067501],"type":"Point"}
}