{
  "type": "Feature",
  "properties": {
    "iso:country":"US",
    "sg:address":"226 Linden Dr",
    "sg:city":"Brooklyn",
    "sg:phone":"+1 641 522 7877",
    "sg:postcode":"52211",
    "sg:province":"IA",
    "sg:tags":[
        "beef",
        "farm",
        "corn",
        "soybean",
        "cattle",
        "feedlot"
    ],
    "wof:name":"Keith Brannian",
    "wof:placetype":"venue"
},
  "geometry": {"coordinates":[-92.45006100000001,41.729446],"type":"Point"}
}