{
  "type": "Feature",
  "properties": {
    "iso:country":"US",
    "sg:address":"943 S 23rd St",
    "sg:city":"Fort Dodge",
    "sg:classifiers":[
        {
            "category":"Retail",
            "subcategory":"Auto Repair",
            "type":"Services"
        }
    ],
    "sg:phone":"+1 515 576 6278",
    "sg:postcode":"50501",
    "sg:province":"IA",
    "sg:tags":[
        "repairing",
        "automobile"
    ],
    "wof:name":"Robert's Auto Repair",
    "wof:placetype":"venue"
},
  "geometry": {"coordinates":[-94.166484,42.494952],"type":"Point"}
}