{
  "type": "Feature",
  "properties": {
    "addr:full":"2724 Brady St Davenport IA 52803",
    "addr:housenumber":"2724",
    "addr:postcode":"52803",
    "addr:street":"Brady St",
    "iso:country":"US",
    "sg:address":"2724 Brady St",
    "sg:city":"Davenport",
    "sg:classifiers":[
        {
            "category":"Shopping",
            "type":"Retail Goods"
        }
    ],
    "sg:phone":"+1 563 323 7008",
    "sg:postcode":"52803",
    "sg:province":"IA",
    "sg:tags":[
        "wedding",
        "supply"
    ],
    "wof:name":"Cake Creations",
    "wof:placetype":"venue"
},
  "geometry": {"coordinates":[-90.571215,41.54861],"type":"Point"}
}