{
  "type": "Feature",
  "properties": {
    "addr:full":"1510 Logan Ave Waterloo IA 50703",
    "addr:housenumber":"1510",
    "addr:postcode":"50703",
    "addr:street":"Logan Ave",
    "iso:country":"US",
    "sg:address":"1510 Logan Ave",
    "sg:city":"Waterloo",
    "sg:classifiers":[
        {
            "category":"Social Services",
            "type":"Services"
        }
    ],
    "sg:phone":"+1 319 233 3579",
    "sg:postcode":"50703",
    "sg:province":"IA",
    "sg:tags":[
        "organization",
        "welfare"
    ],
    "sg:website":"www.lsiowa.org",
    "wof:name":"Lutheran Social Svc",
    "wof:placetype":"venue"
},
  "geometry": {"coordinates":[-92.33757300000001,42.522389],"type":"Point"}
}