{
  "type": "Feature",
  "properties": {
    "addr:full":"112 W Main St Webb IA 51366",
    "addr:housenumber":"112",
    "addr:postcode":"51366",
    "addr:street":"W Main St",
    "iso:country":"US",
    "sg:address":"112 W Main St",
    "sg:city":"Webb",
    "sg:classifiers":[
        {
            "category":"Manufacturing",
            "subcategory":"Apparel",
            "type":"Manufacturing & Wholesale Goods"
        }
    ],
    "sg:phone":"+1 712 838 4347",
    "sg:postcode":"51366",
    "sg:province":"IA",
    "sg:tags":[
        "mfg"
    ],
    "wof:name":"Younique Creations",
    "wof:placetype":"venue"
},
  "geometry": {"coordinates":[-95.01304500000001,42.948695],"type":"Point"}
}