{
  "type": "Feature",
  "properties": {
    "iso:country":"US",
    "sg:address":"206 2nd St NE",
    "sg:city":"Worthington",
    "sg:classifiers":[
        {
            "category":"Building & Trades",
            "subcategory":"Construction",
            "type":"Services"
        }
    ],
    "sg:phone":"+1 563 855 2115",
    "sg:postcode":"52078",
    "sg:province":"IA",
    "sg:tags":[
        "general",
        "contractor"
    ],
    "wof:name":"Greiner Construction Co",
    "wof:placetype":"venue"
},
  "geometry": {"coordinates":[-91.1178,42.398215],"type":"Point"}
}