{
  "type": "Feature",
  "properties": {
    "iso:country":"US",
    "sg:address":"3326 Nebraska Ave",
    "sg:city":"Council Bluffs",
    "sg:classifiers":[
        {
            "category":"Wholesale",
            "subcategory":"Hardware",
            "type":"Manufacturing & Wholesale Goods"
        }
    ],
    "sg:phone":"+1 712 322 8824",
    "sg:postcode":"51501",
    "sg:province":"IA",
    "sg:tags":[
        "parts",
        "refrigerating"
    ],
    "wof:name":"Dennis Supply Co",
    "wof:placetype":"venue"
},
  "geometry": {"coordinates":[-95.8907,41.245516],"type":"Point"}
}