{
  "type": "Feature",
  "properties": {
    "iso:country":"US",
    "sg:address":"201 W Ridgeway Ave",
    "sg:city":"Waterloo",
    "sg:classifiers":[
        {
            "category":"Health Services",
            "subcategory":"Nursing And Care Facility",
            "type":"Services"
        }
    ],
    "sg:phone":"+1 319 234 7777",
    "sg:postcode":"50701",
    "sg:province":"IA",
    "sg:tags":[
        "home",
        "convalescent"
    ],
    "wof:name":"Manor Care Health Svc",
    "wof:placetype":"venue"
},
  "geometry": {"coordinates":[-92.35906199999999,42.469417],"type":"Point"}
}