{
  "type": "Feature",
  "properties": {
    "addr:full":"414 2nd Ave NE Le Mars IA 51031",
    "addr:housenumber":"414",
    "addr:postcode":"51031",
    "addr:street":"2Nd Ave Ne",
    "iso:country":"US",
    "sg:address":"414 2nd Ave NE",
    "sg:city":"Le Mars",
    "sg:classifiers":[
        {
            "category":"Building & Trades",
            "subcategory":"Construction",
            "type":"Services"
        }
    ],
    "sg:phone":"+1 712 546 8505",
    "sg:postcode":"51031",
    "sg:province":"IA",
    "sg:tags":[
        "general",
        "contractor"
    ],
    "wof:name":"O H Livermore Construction Shp",
    "wof:placetype":"venue"
},
  "geometry": {"coordinates":[-96.16357499999999,42.800003],"type":"Point"}
}