{
  "type": "Feature",
  "properties": {
    "iso:country":"US",
    "sg:address":"206 W 5th St",
    "sg:city":"Storm Lake",
    "sg:classifiers":[
        {
            "category":"Professional",
            "type":"Services"
        }
    ],
    "sg:phone":"+1 712 213 1100",
    "sg:postcode":"50588",
    "sg:province":"IA",
    "sg:tags":[
        "establishment"
    ],
    "wof:name":"Servi Systems",
    "wof:placetype":"venue"
},
  "geometry": {"coordinates":[-95.20329099999999,42.644369],"type":"Point"}
}