{
  "type": "Feature",
  "properties": {
    "addr:full":"1510 S Grand Ave Charles City IA 50616",
    "addr:housenumber":"1510",
    "addr:postcode":"50616",
    "addr:street":"S Grand Ave",
    "iso:country":"US",
    "sg:address":"1510 S Grand Ave",
    "sg:city":"Charles City",
    "sg:classifiers":[
        {
            "category":"Restaurant",
            "type":"Food & Drink"
        }
    ],
    "sg:menulink":"http://www.allmenus.com/ia/charles-city/151633-aw-restaurant/menu/",
    "sg:phone":"+1 641 228 1004",
    "sg:postcode":"50616",
    "sg:province":"IA",
    "sg:tags":[
        "burger",
        "american",
        "dog",
        "pub",
        "hot"
    ],
    "wof:name":"A&W Restaurant",
    "wof:placetype":"venue"
},
  "geometry": {"coordinates":[-92.67246299999999,43.052588],"type":"Point"}
}