{
  "type": "Feature",
  "properties": {
    "addr:full":"3540 W Broadway Council Bluffs IA 51501",
    "addr:housenumber":"3540",
    "addr:postcode":"51501",
    "addr:street":"W Broadway",
    "iso:country":"US",
    "sg:address":"3540 W Broadway",
    "sg:city":"Council Bluffs",
    "sg:classifiers":[
        {
            "category":"Autos & Motor Vehicles",
            "subcategory":"Fuel & Gas Station",
            "type":"Retail Goods"
        }
    ],
    "sg:phone":"+1 712 328 2466",
    "sg:postcode":"51501",
    "sg:province":"IA",
    "sg:tags":[
        "oil"
    ],
    "wof:name":"G's Amoco",
    "wof:placetype":"venue"
},
  "geometry": {"coordinates":[-95.903345,41.261991],"type":"Point"}
}