{
  "type": "Feature",
  "properties": {
    "iso:country":"US",
    "sg:address":"505 W Lane St",
    "sg:city":"Centerville",
    "sg:classifiers":[
        {
            "category":"Professional",
            "type":"Services"
        }
    ],
    "sg:phone":"+1 641 856 6479",
    "sg:postcode":"52544",
    "sg:province":"IA",
    "wof:name":"Write At Your Service",
    "wof:placetype":"venue"
},
  "geometry": {"coordinates":[-92.877748,40.730013],"type":"Point"}
}