{
  "type": "Feature",
  "properties": {
    "iso:country":"US",
    "sg:address":"1418 E Grand Ave",
    "sg:city":"Des Moines",
    "sg:classifiers":[
        {
            "category":"Restaurant",
            "type":"Food & Drink"
        }
    ],
    "sg:phone":"+1 515 266 4242",
    "sg:postcode":"50316",
    "sg:province":"IA",
    "wof:name":"Tasty Tacos",
    "wof:placetype":"venue"
},
  "geometry": {"coordinates":[-93.59796799999999,41.593391],"type":"Point"}
}