{
  "type": "Feature",
  "properties": {
    "iso:country":"US",
    "sg:address":"1559 Fir Ave",
    "sg:city":"Coon Rapids",
    "sg:phone":"+1 712 684 5373",
    "sg:postcode":"50058",
    "sg:province":"IA",
    "sg:tags":[
        "farm",
        "corn",
        "equine",
        "soybean"
    ],
    "wof:name":"Clair Crosier",
    "wof:placetype":"venue"
},
  "geometry": {"coordinates":[-94.63797599999999,41.782478],"type":"Point"}
}