{
  "type": "Feature",
  "properties": {
    "iso:country":"US",
    "sg:address":"2866 Quail Ave",
    "sg:city":"Arthur",
    "sg:classifiers":[
        {
            "category":"Wholesale",
            "subcategory":"Machinery & Supplies",
            "type":"Manufacturing & Wholesale Goods"
        }
    ],
    "sg:phone":"+1 712 675 4554",
    "sg:postcode":"51431",
    "sg:province":"IA",
    "sg:tags":[
        "equipment",
        "parts",
        "tractor"
    ],
    "wof:name":"Bergman Manufacturing Inc",
    "wof:placetype":"venue"
},
  "geometry": {"coordinates":[-95.342483,42.287456],"type":"Point"}
}