{
  "type": "Feature",
  "properties": {
    "iso:country":"US",
    "sg:address":"16 S Commercial Aly",
    "sg:city":"Mason City",
    "sg:classifiers":[
        {
            "category":"Restaurant",
            "type":"Food & Drink"
        }
    ],
    "sg:phone":"+1 641 423 0121",
    "sg:postcode":"50401",
    "sg:province":"IA",
    "wof:name":"Hungry Mind",
    "wof:placetype":"venue"
},
  "geometry": {"coordinates":[-93.200295,43.151708],"type":"Point"}
}