{
  "type": "Feature",
  "properties": {
    "addr:full":"501 Poplar St Atlantic IA 50022",
    "addr:housenumber":"501",
    "addr:postcode":"50022",
    "addr:street":"Poplar St",
    "iso:country":"US",
    "sg:address":"501 Poplar St",
    "sg:city":"Atlantic",
    "sg:classifiers":[
        {
            "category":"Travel",
            "subcategory":"Hotels & Motels",
            "type":"Entertainment"
        }
    ],
    "sg:phone":"+1 712 243 2317",
    "sg:postcode":"50022",
    "sg:province":"IA",
    "sg:tags":[
        "operation"
    ],
    "wof:name":"Elks Lodge",
    "wof:placetype":"venue"
},
  "geometry": {"coordinates":[-95.014421,41.406008],"type":"Point"}
}