{
  "type": "Feature",
  "properties": {
    "addr:full":"207 E Boiler Ave George IA 51237",
    "addr:housenumber":"207",
    "addr:postcode":"51237",
    "addr:street":"E Boiler Ave",
    "iso:country":"US",
    "sg:address":"207 E Boiler Ave",
    "sg:city":"George",
    "sg:classifiers":[
        {
            "category":"Government",
            "subcategory":"Office",
            "type":"Public Place"
        }
    ],
    "sg:phone":"+1 712 475 3366",
    "sg:postcode":"51237",
    "sg:province":"IA",
    "sg:tags":[
        "village"
    ],
    "wof:name":"George Rescue Station",
    "wof:placetype":"venue"
},
  "geometry": {"coordinates":[-96.00183199999999,43.342396],"type":"Point"}
}