{
  "type": "Feature",
  "properties": {
    "iso:country":"US",
    "sg:address":"1675 Neola Ave",
    "sg:city":"Jefferson",
    "sg:classifiers":[
        {
            "category":"Building & Trades",
            "subcategory":"Electrical",
            "type":"Services"
        }
    ],
    "sg:phone":"+1 515 386 5471",
    "sg:postcode":"50129",
    "sg:province":"IA",
    "sg:tags":[
        "electric",
        "contractor"
    ],
    "wof:name":"Wright Electric LLC",
    "wof:placetype":"venue"
},
  "geometry": {"coordinates":[-94.367423,41.991027],"type":"Point"}
}