{
  "type": "Feature",
  "properties": {
    "iso:country":"US",
    "sg:address":"629 Ellis Blvd NW",
    "sg:city":"Cedar Rapids",
    "sg:classifiers":[
        {
            "category":"Bars & Pubs",
            "type":"Food & Drink"
        }
    ],
    "sg:phone":"+1 319 366 7979",
    "sg:postcode":"52405",
    "sg:province":"IA",
    "sg:tags":[
        "pizza"
    ],
    "wof:name":"Double Inn",
    "wof:placetype":"venue"
},
  "geometry": {"coordinates":[-91.682198,41.978298],"type":"Point"}
}