{
  "type": "Feature",
  "properties": {
    "iso:country":"US",
    "sg:address":"205 McKinsie Ct NE",
    "sg:city":"Cedar Rapids",
    "sg:classifiers":[
        {
            "category":"Building & Trades",
            "subcategory":"Equipment Rental",
            "type":"Services"
        }
    ],
    "sg:phone":"+1 319 393 0068",
    "sg:postcode":"52402",
    "sg:province":"IA",
    "wof:name":"Kaas Air Inc",
    "wof:placetype":"venue"
},
  "geometry": {"coordinates":[-91.687602,42.006108],"type":"Point"}
}