{
  "type": "Feature",
  "properties": {
    "iso:country":"US",
    "sg:address":"3355 Midway Rd",
    "sg:city":"Marion",
    "sg:classifiers":[
        {
            "category":"Professional",
            "type":"Services"
        }
    ],
    "sg:phone":"+1 319 393 1617",
    "sg:postcode":"52302",
    "sg:province":"IA",
    "wof:name":"D B Tree Service",
    "wof:placetype":"venue"
},
  "geometry": {"coordinates":[-91.692255,42.106345],"type":"Point"}
}