{
  "type": "Feature",
  "properties": {
    "iso:country":"US",
    "sg:address":"806 SE Rio Cir",
    "sg:city":"Ankeny",
    "sg:classifiers":[
        {
            "category":"Retail",
            "subcategory":"Laundry & Dry Cleaning",
            "type":"Services"
        }
    ],
    "sg:phone":"+1 515 287 6490",
    "sg:postcode":"50021",
    "sg:province":"IA",
    "sg:tags":[
        "cleaners",
        "rug",
        "carpet"
    ],
    "wof:name":"Chem-Dry Mc Graw Carpet Clng",
    "wof:placetype":"venue"
},
  "geometry": {"coordinates":[-93.58852400000001,41.722569],"type":"Point"}
}