{
  "type": "Feature",
  "properties": {
    "iso:country":"US",
    "sg:address":"5815 Council St NE",
    "sg:city":"Cedar Rapids",
    "sg:classifiers":[
        {
            "category":"Insurance",
            "subcategory":"Insurance Agent",
            "type":"Services"
        }
    ],
    "sg:phone":"+1 319 743 0109",
    "sg:postcode":"52402",
    "sg:province":"IA",
    "wof:name":"MSI Insurance",
    "wof:placetype":"venue"
},
  "geometry": {"coordinates":[-91.658396,42.036621],"type":"Point"}
}