{
  "type": "Feature",
  "properties": {
    "addr:full":"953 E Main St Manchester IA 52057",
    "addr:housenumber":"953",
    "addr:postcode":"52057",
    "addr:street":"E Main St",
    "iso:country":"US",
    "sg:address":"953 E Main St",
    "sg:city":"Manchester",
    "sg:classifiers":[
        {
            "category":"Wholesale",
            "subcategory":"Medical Equipment & Supplies",
            "type":"Manufacturing & Wholesale Goods"
        }
    ],
    "sg:phone":"+1 563 927 9194",
    "sg:postcode":"52057",
    "sg:province":"IA",
    "sg:tags":[
        "massage"
    ],
    "wof:name":"Tranquil Health Massage Thrpy",
    "wof:placetype":"venue"
},
  "geometry": {"coordinates":[-91.441603,42.483969],"type":"Point"}
}