{
  "type": "Feature",
  "properties": {
    "iso:country":"US",
    "sg:address":"8435 University Blvd",
    "sg:city":"Des Moines",
    "sg:classifiers":[
        {
            "category":"Personal",
            "subcategory":"Beauty Salon",
            "type":"Services"
        }
    ],
    "sg:phone":"+1 515 224 7200",
    "sg:postcode":"50325",
    "sg:province":"IA",
    "wof:name":"Mary Allie Salon & Kiddles",
    "wof:placetype":"venue"
},
  "geometry": {"coordinates":[-93.735707,41.605547],"type":"Point"}
}