{
  "type": "Feature",
  "properties": {
    "addr:full":"110 SE Grant St Ankeny IA 50021",
    "addr:housenumber":"110",
    "addr:postcode":"50021",
    "addr:street":"Se Grant St",
    "iso:country":"US",
    "sg:address":"110 SE Grant St",
    "sg:city":"Ankeny",
    "sg:classifiers":[
        {
            "category":"Organizations",
            "subcategory":"Religious Organization",
            "type":"Services"
        }
    ],
    "sg:phone":"+1 515 964 4816",
    "sg:postcode":"50021",
    "sg:province":"IA",
    "sg:tags":[
        "church"
    ],
    "wof:name":"Church Of The Brethren",
    "wof:placetype":"venue"
},
  "geometry": {"coordinates":[-93.59851999999999,41.730592],"type":"Point"}
}