{
  "type": "Feature",
  "properties": {
    "iso:country":"US",
    "sg:address":"3241 Keokuk Ave",
    "sg:city":"Woolstock",
    "sg:classifiers":[
        {
            "category":"Professional",
            "type":"Services"
        }
    ],
    "sg:phone":"+1 515 839 5852",
    "sg:postcode":"50599",
    "sg:province":"IA",
    "sg:tags":[
        "establishment"
    ],
    "wof:name":"Tweeten's Shop",
    "wof:placetype":"venue"
},
  "geometry": {"coordinates":[-93.77436400000001,42.580353],"type":"Point"}
}