{
  "type": "Feature",
  "properties": {
    "addr:full":"3831 Hope Ave Odebolt IA 51458",
    "addr:housenumber":"3831",
    "addr:postcode":"51458",
    "addr:street":"Hope Ave",
    "iso:country":"US",
    "sg:address":"3831 Hope Ave",
    "sg:city":"Odebolt",
    "sg:phone":"+1 712 668 4313",
    "sg:postcode":"51458",
    "sg:province":"IA",
    "sg:tags":[
        "farm",
        "corn",
        "soybean"
    ],
    "wof:name":"Donald Cowlham",
    "wof:placetype":"venue"
},
  "geometry": {"coordinates":[-95.206897,42.234825],"type":"Point"}
}