{
  "type": "Feature",
  "properties": {
    "addr:full":"909 N Sumner Ave Creston IA 50801",
    "addr:housenumber":"909",
    "addr:postcode":"50801",
    "addr:street":"N Sumner Ave",
    "iso:country":"US",
    "sg:address":"909 N Sumner Ave",
    "sg:city":"Creston",
    "sg:classifiers":[
        {
            "category":"Shopping",
            "subcategory":"Florist",
            "type":"Retail Goods"
        }
    ],
    "sg:phone":"+1 641 782 2171",
    "sg:postcode":"50801",
    "sg:province":"IA",
    "wof:name":"Kelly's Flower Shop",
    "wof:placetype":"venue"
},
  "geometry": {"coordinates":[-94.372496,41.067894],"type":"Point"}
}