{
  "type": "Feature",
  "properties": {
    "iso:country":"US",
    "sg:address":"21426 Scenic Rd",
    "sg:city":"Waucoma",
    "sg:classifiers":[
        {
            "category":"Farming",
            "subcategory":"Dairy Farm",
            "type":"Manufacturing & Wholesale Goods"
        }
    ],
    "sg:phone":"+1 563 776 6055",
    "sg:postcode":"52171",
    "sg:province":"IA",
    "wof:name":"Larry Drilling",
    "wof:placetype":"venue"
},
  "geometry": {"coordinates":[-92.01067999999999,43.059572],"type":"Point"}
}