{
  "type": "Feature",
  "properties": {
    "iso:country":"US",
    "sg:address":"3626 University Ave",
    "sg:city":"Waterloo",
    "sg:classifiers":[
        {
            "category":"Wholesale",
            "subcategory":"Electrical",
            "type":"Manufacturing & Wholesale Goods"
        }
    ],
    "sg:phone":"+1 319 233 3601",
    "sg:postcode":"50701",
    "sg:province":"IA",
    "sg:tags":[
        "telecommunication"
    ],
    "wof:name":"MTC Systems",
    "wof:placetype":"venue"
},
  "geometry": {"coordinates":[-92.400345,42.504487],"type":"Point"}
}