{
  "type": "Feature",
  "properties": {
    "addr:full":"2064 196 Ave Percival IA 51648",
    "addr:housenumber":"2064",
    "addr:postcode":"51648",
    "addr:street":"196 Ave",
    "iso:country":"US",
    "sg:address":"2064 196 Ave",
    "sg:city":"Percival",
    "sg:classifiers":[
        {
            "category":"Retail",
            "subcategory":"Auto Repair",
            "type":"Services"
        }
    ],
    "sg:phone":"+1 712 529 4280",
    "sg:postcode":"51648",
    "sg:province":"IA",
    "sg:tags":[
        "repairing",
        "automobile"
    ],
    "wof:name":"Dale Chaney's Repair Shop",
    "wof:placetype":"venue"
},
  "geometry": {"coordinates":[-95.81164099999999,40.749897],"type":"Point"}
}