{
  "type": "Feature",
  "properties": {
    "iso:country":"US",
    "sg:address":"7251 Ashland Rd",
    "sg:city":"Agency",
    "sg:classifiers":[
        {
            "category":"Farming",
            "subcategory":"Nursery",
            "type":"Manufacturing & Wholesale Goods"
        }
    ],
    "sg:phone":"+1 641 937 5261",
    "sg:postcode":"52554",
    "sg:province":"IA",
    "sg:tags":[
        "greenhouse"
    ],
    "wof:name":"Herrmann's Greenhouse & Mower",
    "wof:placetype":"venue"
},
  "geometry": {"coordinates":[-92.29998000000001,40.991027],"type":"Point"}
}