{
  "type": "Feature",
  "properties": {
    "addr:full":"305 S 12th Ave W Lake Mills IA 50450",
    "addr:housenumber":"305",
    "addr:postcode":"50450",
    "addr:street":"S 12Th Ave W",
    "iso:country":"US",
    "sg:address":"305 S 12th Ave W",
    "sg:city":"Lake Mills",
    "sg:classifiers":[
        {
            "category":"Building & Trades",
            "subcategory":"Construction",
            "type":"Services"
        }
    ],
    "sg:phone":"+1 641 592 1010",
    "sg:postcode":"50450",
    "sg:province":"IA",
    "sg:tags":[
        "general",
        "contractor"
    ],
    "wof:name":"Brekken Construction",
    "wof:placetype":"venue"
},
  "geometry": {"coordinates":[-93.535848,43.408376],"type":"Point"}
}