{
  "type": "Feature",
  "properties": {
    "iso:country":"US",
    "sg:address":"1075 J Ave",
    "sg:city":"Ute",
    "sg:classifiers":[
        {
            "category":"Farming",
            "subcategory":"Farm",
            "type":"Manufacturing & Wholesale Goods"
        }
    ],
    "sg:phone":"+1 712 885 2506",
    "sg:postcode":"51060",
    "sg:province":"IA",
    "sg:tags":[
        "crop",
        "general"
    ],
    "wof:name":"Donald Kragel",
    "wof:placetype":"venue"
},
  "geometry": {"coordinates":[-95.656587,42.080844],"type":"Point"}
}