{
  "type": "Feature",
  "properties": {
    "iso:country":"US",
    "sg:address":"819 Timber Ct",
    "sg:city":"Coralville",
    "sg:classifiers":[
        {
            "category":"Professional",
            "subcategory":"Computer Services",
            "type":"Services"
        }
    ],
    "sg:phone":"+1 319 354 3748",
    "sg:postcode":"52241",
    "sg:province":"IA",
    "sg:tags":[
        "repair"
    ],
    "wof:name":"Computer Wizards",
    "wof:placetype":"venue"
},
  "geometry": {"coordinates":[-91.57990599999999,41.70048],"type":"Point"}
}