{
  "type": "Feature",
  "properties": {
    "iso:country":"US",
    "sg:address":"2050 US Hwy 65",
    "sg:city":"Sheffield",
    "sg:classifiers":[
        {
            "category":"Farming",
            "subcategory":"Farm",
            "type":"Manufacturing & Wholesale Goods"
        }
    ],
    "sg:phone":"+1 641 892 4269",
    "sg:postcode":"50475",
    "sg:province":"IA",
    "sg:tags":[
        "crop",
        "general"
    ],
    "wof:name":"Jon Schmitt",
    "wof:placetype":"venue"
},
  "geometry": {"coordinates":[-93.202297,42.843806],"type":"Point"}
}