{
  "type": "Feature",
  "properties": {
    "addr:full":"1941 310th St Rockwell City IA 50579",
    "addr:housenumber":"1941",
    "addr:postcode":"50579",
    "addr:street":"310Th St",
    "iso:country":"US",
    "sg:address":"1941 310th St",
    "sg:city":"Rockwell City",
    "sg:classifiers":[
        {
            "category":"Food & Beverages",
            "subcategory":"Specialty",
            "type":"Retail Goods"
        }
    ],
    "sg:phone":"+1 712 464 3661",
    "sg:postcode":"50579",
    "sg:province":"IA",
    "sg:tags":[
        "spice"
    ],
    "wof:name":"Midwest Flavors LLC",
    "wof:placetype":"venue"
},
  "geometry": {"coordinates":[-94.73910600000001,42.339564],"type":"Point"}
}