{
  "type": "Feature",
  "properties": {
    "iso:country":"US",
    "sg:address":"2728 Asbury Rd",
    "sg:city":"Dubuque",
    "sg:classifiers":[
        {
            "category":"Health Services",
            "subcategory":"Doctor",
            "type":"Services"
        }
    ],
    "sg:phone":"+1 563 583 6424",
    "sg:postcode":"52001",
    "sg:province":"IA",
    "sg:tags":[
        "dentist"
    ],
    "wof:name":"Kuttler Dental Team",
    "wof:placetype":"venue"
},
  "geometry": {"coordinates":[-90.708924,42.508535],"type":"Point"}
}