{
  "type": "Feature",
  "properties": {
    "iso:country":"US",
    "sg:address":"1948 NW 92nd Ct",
    "sg:city":"Clive",
    "sg:classifiers":[
        {
            "category":"Education",
            "subcategory":"Special Training",
            "type":"Public Place"
        }
    ],
    "sg:phone":"+1 515 224 4349",
    "sg:postcode":"50325",
    "sg:province":"IA",
    "sg:tags":[
        "program"
    ],
    "wof:name":"Iowa Electrical Apprentices",
    "wof:placetype":"venue"
},
  "geometry": {"coordinates":[-93.744219,41.610292],"type":"Point"}
}