{
  "type": "Feature",
  "properties": {
    "iso:country":"US",
    "sg:address":"507 N Iowa St",
    "sg:city":"Charles City",
    "sg:classifiers":[
        {
            "category":"Retail",
            "subcategory":"Repair Shop",
            "type":"Services"
        }
    ],
    "sg:phone":"+1 641 228 5419",
    "sg:postcode":"50616",
    "sg:province":"IA",
    "sg:tags":[
        "lock",
        "locksmith"
    ],
    "wof:name":"Shorty's Lock",
    "wof:placetype":"venue"
},
  "geometry": {"coordinates":[-92.67927,43.071909],"type":"Point"}
}