{
  "type": "Feature",
  "properties": {
    "iso:country":"US",
    "sg:address":"801 9th St",
    "sg:city":"Harlan",
    "sg:classifiers":[
        {
            "category":"Professional",
            "subcategory":"Management & Consulting",
            "type":"Services"
        }
    ],
    "sg:phone":"+1 712 744 3700",
    "sg:postcode":"51537",
    "sg:province":"IA",
    "sg:tags":[
        "consultant",
        "telecommunication"
    ],
    "wof:name":"CRT",
    "wof:placetype":"venue"
},
  "geometry": {"coordinates":[-95.3214,41.659906],"type":"Point"}
}