{
  "type": "Feature",
  "properties": {
    "iso:country":"US",
    "sg:address":"422 Oak Rd",
    "sg:city":"Avoca",
    "sg:phone":"+1 712 343 2544",
    "sg:postcode":"51521",
    "sg:province":"IA",
    "sg:tags":[
        "farm",
        "corn",
        "soybean"
    ],
    "wof:name":"Richard Lee",
    "wof:placetype":"venue"
},
  "geometry": {"coordinates":[-95.28915499999999,41.549851],"type":"Point"}
}