{
  "type": "Feature",
  "properties": {
    "iso:country":"US",
    "sg:address":"425 US Hwy 30",
    "sg:city":"Carroll",
    "sg:classifiers":[
        {
            "category":"Utilities",
            "subcategory":"Mobile Phone",
            "type":"Services"
        }
    ],
    "sg:phone":"+1 712 792 3456",
    "sg:postcode":"51401",
    "sg:province":"IA",
    "sg:tags":[
        "communication",
        "radiotelephone",
        "merchandise"
    ],
    "wof:name":"US Cellular Walmart Location",
    "wof:placetype":"venue"
},
  "geometry": {"coordinates":[-94.86251799999999,42.064473],"type":"Point"}
}