{
  "type": "Feature",
  "properties": {
    "iso:country":"US",
    "sg:address":"388 410th Ave",
    "sg:city":"Grinnell",
    "sg:classifiers":[
        {
            "category":"Wholesale",
            "subcategory":"Auto Parts",
            "type":"Manufacturing & Wholesale Goods"
        }
    ],
    "sg:phone":"+1 641 236 3363",
    "sg:postcode":"50112",
    "sg:province":"IA",
    "sg:tags":[
        "automobile",
        "wrecking"
    ],
    "wof:name":"Larry Criswell Enterprises",
    "wof:placetype":"venue"
},
  "geometry": {"coordinates":[-92.710831,41.702451],"type":"Point"}
}