{
  "type": "Feature",
  "properties": {
    "iso:country":"US",
    "sg:address":"222 5th St",
    "sg:city":"West Des Moines",
    "sg:classifiers":[
        {
            "category":"Personal",
            "subcategory":"Barber",
            "type":"Services"
        }
    ],
    "sg:phone":"+1 515 255 4951",
    "sg:postcode":"50265",
    "sg:province":"IA",
    "sg:tags":[
        "shop"
    ],
    "wof:name":"Penrod Barber Shop",
    "wof:placetype":"venue"
},
  "geometry": {"coordinates":[-93.70896399999999,41.572187],"type":"Point"}
}