{
  "type": "Feature",
  "properties": {
    "addr:full":"3111 10th St Marion IA 52302",
    "addr:housenumber":"3111",
    "addr:postcode":"52302",
    "addr:street":"10Th St",
    "iso:country":"US",
    "sg:address":"3111 10th St",
    "sg:city":"Marion",
    "sg:classifiers":[
        {
            "category":"Education",
            "subcategory":"School",
            "type":"Public Place"
        }
    ],
    "sg:phone":"+1 319 447 3040",
    "sg:postcode":"52302",
    "sg:province":"IA",
    "sg:website":"www.linnmar.k12.ia.us",
    "wof:name":"Linn-Mar High School",
    "wof:placetype":"venue"
},
  "geometry": {"coordinates":[-91.59931,42.0533],"type":"Point"}
}