{
  "type": "Feature",
  "properties": {
    "iso:country":"US",
    "sg:address":"500 E 14th St",
    "sg:city":"Atlantic",
    "sg:classifiers":[
        {
            "category":"Education",
            "subcategory":"School",
            "type":"Public Place"
        }
    ],
    "sg:phone":"+1 712 243 5234",
    "sg:postcode":"50022",
    "sg:province":"IA",
    "wof:name":"Washington Elementary",
    "wof:placetype":"venue"
},
  "geometry": {"coordinates":[-95.006218,41.396706],"type":"Point"}
}