{
  "type": "Feature",
  "properties": {
    "iso:country":"US",
    "sg:address":"84 Main St",
    "sg:city":"Maxwell",
    "sg:classifiers":[
        {
            "category":"Recreation",
            "type":"Entertainment"
        }
    ],
    "sg:phone":"+1 515 387 8584",
    "sg:postcode":"50161",
    "sg:province":"IA",
    "sg:tags":[
        "hall",
        "auditorium"
    ],
    "wof:name":"Maxwell Area Community Ctr",
    "wof:placetype":"venue"
},
  "geometry": {"coordinates":[-93.39971199999999,41.886997],"type":"Point"}
}