{
  "type": "Feature",
  "properties": {
    "iso:country":"US",
    "sg:address":"12341 US Hwy 18",
    "sg:city":"Postville",
    "sg:classifiers":[
        {
            "category":"Autos & Motor Vehicles",
            "subcategory":"Automobile Sales",
            "type":"Retail Goods"
        }
    ],
    "sg:phone":"+1 563 864 3978",
    "sg:postcode":"52162",
    "sg:province":"IA",
    "sg:tags":[
        "car",
        "dealer"
    ],
    "wof:name":"John Falb Co",
    "wof:placetype":"venue"
},
  "geometry": {"coordinates":[-91.56218,43.081222],"type":"Point"}
}