{
  "type": "Feature",
  "properties": {
    "addr:full":"1285 3rd Ave SE Cedar Rapids IA 52403",
    "addr:housenumber":"1285",
    "addr:postcode":"52403",
    "addr:street":"3Rd Ave Se",
    "iso:country":"US",
    "sg:address":"1285 3rd Ave SE",
    "sg:city":"Cedar Rapids",
    "sg:classifiers":[
        {
            "category":"Organizations",
            "subcategory":"Religious Organization",
            "type":"Services"
        }
    ],
    "sg:phone":"+1 319 366 7185",
    "sg:postcode":"52403",
    "sg:province":"IA",
    "sg:tags":[
        "church"
    ],
    "sg:website":"www.crwpc.org",
    "wof:name":"Westminster Presbyterian Church",
    "wof:placetype":"venue"
},
  "geometry": {"coordinates":[-91.653504,41.98468],"type":"Point"}
}