{
  "type": "Feature",
  "properties": {
    "iso:country":"US",
    "sg:address":"805 10th St",
    "sg:city":"Sioux City",
    "sg:classifiers":[
        {
            "category":"Retail",
            "subcategory":"Funeral Services",
            "type":"Services"
        }
    ],
    "sg:phone":"+1 712 258 4576",
    "sg:postcode":"51105",
    "sg:province":"IA",
    "sg:tags":[
        "director"
    ],
    "wof:name":"Anderson-Perasso Funeral Home",
    "wof:placetype":"venue"
},
  "geometry": {"coordinates":[-96.399447,42.500829],"type":"Point"}
}