{
  "type": "Feature",
  "properties": {
    "iso:country":"US",
    "sg:address":"10225 Ivy Rd",
    "sg:city":"Fayette",
    "sg:classifiers":[
        {
            "category":"Recreation",
            "type":"Entertainment"
        }
    ],
    "sg:phone":"+1 563 425 4161",
    "sg:postcode":"52142",
    "sg:province":"IA",
    "sg:tags":[
        "parks"
    ],
    "wof:name":"Volga River Recreation Area",
    "wof:placetype":"venue"
},
  "geometry": {"coordinates":[-91.783993,42.880339],"type":"Point"}
}