{
  "type": "Feature",
  "properties": {
    "iso:country":"US",
    "sg:address":"118 E Ashland Ave",
    "sg:city":"Indianola",
    "sg:classifiers":[
        {
            "category":"Bars & Pubs",
            "type":"Food & Drink"
        }
    ],
    "sg:phone":"+1 515 961 9026",
    "sg:postcode":"50125",
    "sg:province":"IA",
    "wof:name":"Patrons",
    "wof:placetype":"venue"
},
  "geometry": {"coordinates":[-93.55976099999999,41.361388],"type":"Point"}
}