{
  "type": "Feature",
  "properties": {
    "addr:full":"920 Central Ave E Clarion IA 50525",
    "addr:housenumber":"920",
    "addr:postcode":"50525",
    "addr:street":"Central Ave E Clarion",
    "iso:country":"US",
    "sg:address":"920 Central Ave E",
    "sg:city":"Clarion",
    "sg:classifiers":[
        {
            "category":"Travel",
            "subcategory":"Travel Agent",
            "type":"Entertainment"
        }
    ],
    "sg:phone":"+1 515 532 6691",
    "sg:postcode":"50525",
    "sg:province":"IA",
    "sg:tags":[
        "agency",
        "bureau"
    ],
    "wof:name":"Travel Connection",
    "wof:placetype":"venue"
},
  "geometry": {"coordinates":[-93.72242799999999,42.731709],"type":"Point"}
}