{
  "type": "Feature",
  "properties": {
    "addr:full":"12 4th St SW Spencer IA 51301",
    "addr:housenumber":"12",
    "addr:postcode":"51301",
    "addr:street":"4Th St Sw",
    "iso:country":"US",
    "sg:address":"12 4th St SW",
    "sg:city":"Spencer",
    "sg:classifiers":[
        {
            "category":"Personal",
            "subcategory":"Beauty Salon",
            "type":"Services"
        }
    ],
    "sg:phone":"+1 712 262 1900",
    "sg:postcode":"51301",
    "sg:province":"IA",
    "wof:name":"Yellow Strawberry Salon",
    "wof:placetype":"venue"
},
  "geometry": {"coordinates":[-95.14427000000001,43.134066],"type":"Point"}
}