{
  "type": "Feature",
  "properties": {
    "iso:country":"US",
    "sg:address":"112 E College St",
    "sg:city":"Iowa City",
    "sg:classifiers":[
        {
            "category":"Shopping",
            "subcategory":"Books",
            "type":"Retail Goods"
        }
    ],
    "sg:phone":"+1 319 354 6632",
    "sg:postcode":"52240",
    "sg:province":"IA",
    "sg:tags":[
        "comic"
    ],
    "wof:name":"Daydreams Comics",
    "wof:placetype":"venue"
},
  "geometry": {"coordinates":[-91.53321,41.658894],"type":"Point"}
}