{
  "type": "Feature",
  "properties": {
    "iso:country":"US",
    "sg:address":"115 N Broadway Ave",
    "sg:city":"New Hampton",
    "sg:classifiers":[
        {
            "category":"Retail",
            "subcategory":"Funeral Services",
            "type":"Services"
        }
    ],
    "sg:phone":"+1 641 394 4331",
    "sg:postcode":"50659",
    "sg:province":"IA",
    "sg:tags":[
        "director"
    ],
    "wof:name":"Conway-Kolbet Funeral Home",
    "wof:placetype":"venue"
},
  "geometry": {"coordinates":[-92.319016,43.060528],"type":"Point"}
}