{
  "type": "Feature",
  "properties": {
    "iso:country":"US",
    "sg:address":"940 S Taft Ave",
    "sg:city":"Mason City",
    "sg:classifiers":[
        {
            "category":"Wholesale",
            "subcategory":"Electrical",
            "type":"Manufacturing & Wholesale Goods"
        }
    ],
    "sg:phone":"+1 641 423 7181",
    "sg:postcode":"50401",
    "sg:province":"IA",
    "sg:tags":[
        "equipment",
        "electric",
        "supply"
    ],
    "wof:name":"Van Meter Industrial",
    "wof:placetype":"venue"
},
  "geometry": {"coordinates":[-93.240641,43.144453],"type":"Point"}
}