{
  "type": "Feature",
  "properties": {
    "iso:country":"US",
    "sg:address":"359 Rock Island Ave",
    "sg:city":"Waterloo",
    "sg:classifiers":[
        {
            "category":"Food & Beverages",
            "subcategory":"Groceries & Convenience Stores",
            "type":"Retail Goods"
        }
    ],
    "sg:phone":"+1 319 233 0200",
    "sg:postcode":"50701",
    "sg:province":"IA",
    "wof:name":"All Stop Convenience Stores",
    "wof:placetype":"venue"
},
  "geometry": {"coordinates":[-92.366159,42.50128],"type":"Point"}
}