{
  "type": "Feature",
  "properties": {
    "iso:country":"US",
    "sg:address":"604 W Thomas Ave",
    "sg:city":"Shenandoah",
    "sg:classifiers":[
        {
            "category":"Wholesale",
            "subcategory":"Farm Supplies",
            "type":"Manufacturing & Wholesale Goods"
        }
    ],
    "sg:phone":"+1 712 246 4000",
    "sg:postcode":"51601",
    "sg:province":"IA",
    "sg:tags":[
        "product",
        "health",
        "animal"
    ],
    "wof:name":"Lloyd Inc/Vet-A-Mix",
    "wof:placetype":"venue"
},
  "geometry": {"coordinates":[-95.37253800000001,40.76495],"type":"Point"}
}