{
  "type": "Feature",
  "properties": {
    "iso:country":"US",
    "sg:address":"1106 S 32nd St",
    "sg:city":"Fort Dodge",
    "sg:classifiers":[
        {
            "category":"Building & Trades",
            "subcategory":"Equipment Rental",
            "type":"Services"
        }
    ],
    "sg:phone":"+1 515 576 3816",
    "sg:postcode":"50501",
    "sg:province":"IA",
    "sg:tags":[
        "crane"
    ],
    "wof:name":"Kolacia Crane Svc",
    "wof:placetype":"venue"
},
  "geometry": {"coordinates":[-94.14851400000001,42.49332],"type":"Point"}
}