{
  "type": "Feature",
  "properties": {
    "addr:full":"105 Liberty St Stacyville IA 50476",
    "addr:housenumber":"105",
    "addr:postcode":"50476",
    "addr:street":"Liberty St",
    "iso:country":"US",
    "sg:address":"105 Liberty St",
    "sg:city":"Stacyville",
    "sg:classifiers":[
        {
            "category":"Retail",
            "subcategory":"Auto Repair",
            "type":"Services"
        }
    ],
    "sg:phone":"+1 641 710 2539",
    "sg:postcode":"50476",
    "sg:province":"IA",
    "sg:tags":[
        "body",
        "automobile",
        "painting"
    ],
    "wof:name":"Curt's Auto Body",
    "wof:placetype":"venue"
},
  "geometry": {"coordinates":[-92.787333,43.437006],"type":"Point"}
}