{
  "type": "Feature",
  "properties": {
    "addr:full":"1314 4th St SW Mason City IA 50401",
    "addr:housenumber":"1314",
    "addr:postcode":"50401",
    "addr:street":"4Th St Sw",
    "iso:country":"US",
    "sg:address":"1314 4th St SW",
    "sg:city":"Mason City",
    "sg:classifiers":[
        {
            "category":"Building & Trades",
            "subcategory":"Construction",
            "type":"Services"
        }
    ],
    "sg:phone":"+1 641 424 0071",
    "sg:postcode":"50401",
    "sg:province":"IA",
    "sg:tags":[
        "roofing",
        "contractor"
    ],
    "wof:name":"Reroof America Corp",
    "wof:placetype":"venue"
},
  "geometry": {"coordinates":[-93.221554,43.148496],"type":"Point"}
}