{
  "type": "Feature",
  "properties": {
    "addr:full":"12 Washington Ave W Albia IA 52531",
    "addr:housenumber":"12",
    "addr:postcode":"52531",
    "addr:street":"Washington Ave W Albia",
    "iso:country":"US",
    "sg:address":"12 Washington Ave W",
    "sg:city":"Albia",
    "sg:classifiers":[
        {
            "category":"Health Services",
            "subcategory":"Clinic",
            "type":"Services"
        }
    ],
    "sg:phone":"+1 641 932 5960",
    "sg:postcode":"52531",
    "sg:province":"IA",
    "sg:tags":[
        "specialty",
        "outpatient"
    ],
    "wof:name":"Southern Iowa Ecnomic Dev Assn",
    "wof:placetype":"venue"
},
  "geometry": {"coordinates":[-92.80952600000001,41.0261],"type":"Point"}
}