{
  "type": "Feature",
  "properties": {
    "iso:country":"US",
    "sg:address":"3509 J St SW",
    "sg:city":"Cedar Rapids",
    "sg:classifiers":[
        {
            "category":"Wholesale",
            "subcategory":"Machinery & Supplies",
            "type":"Manufacturing & Wholesale Goods"
        }
    ],
    "sg:phone":"+1 319 247 1121",
    "sg:postcode":"52404",
    "sg:province":"IA",
    "sg:tags":[
        "bearing"
    ],
    "wof:name":"Applied Industrial Technology",
    "wof:placetype":"venue"
},
  "geometry": {"coordinates":[-91.666693,41.943036],"type":"Point"}
}