{
  "type": "Feature",
  "properties": {
    "iso:country":"US",
    "sg:address":"23 Imperial Ct",
    "sg:city":"Iowa City",
    "sg:classifiers":[
        {
            "category":"Manufacturing",
            "subcategory":"Printing",
            "type":"Manufacturing & Wholesale Goods"
        }
    ],
    "sg:phone":"+1 319 351 4175",
    "sg:postcode":"52246",
    "sg:province":"IA",
    "sg:tags":[
        "screen"
    ],
    "wof:name":"Hollywood Graphics",
    "wof:placetype":"venue"
},
  "geometry": {"coordinates":[-91.53783900000001,41.634877],"type":"Point"}
}