{
  "type": "Feature",
  "properties": {
    "iso:country":"US",
    "sg:address":"6047 Thunder Rd",
    "sg:city":"Holy Cross",
    "sg:classifiers":[
        {
            "category":"Freight",
            "type":"Transportation"
        }
    ],
    "sg:phone":"+1 563 870 2445",
    "sg:postcode":"52053",
    "sg:province":"IA",
    "sg:tags":[
        "frozen",
        "food",
        "locker",
        "plant"
    ],
    "wof:name":"Holy Cross Locker",
    "wof:placetype":"venue"
},
  "geometry": {"coordinates":[-90.99707100000001,42.602432],"type":"Point"}
}