{
  "type": "Feature",
  "properties": {
    "addr:full":"701 W 6th St Cedar Falls IA 50613",
    "addr:housenumber":"701",
    "addr:postcode":"50613",
    "addr:street":"W 6Th St",
    "iso:country":"US",
    "sg:address":"701 W 6th St",
    "sg:city":"Cedar Falls",
    "sg:classifiers":[
        {
            "category":"Organizations",
            "subcategory":"Religious Organization",
            "type":"Services"
        }
    ],
    "sg:phone":"+1 319 268 1240",
    "sg:postcode":"50613",
    "sg:province":"IA",
    "sg:tags":[
        "church"
    ],
    "wof:name":"First Church-Christ Scientist",
    "wof:placetype":"venue"
},
  "geometry": {"coordinates":[-92.454646,42.533226],"type":"Point"}
}