{
  "type": "Feature",
  "properties": {
    "iso:country":"US",
    "sg:address":"523 5th Ave N",
    "sg:city":"Clinton",
    "sg:classifiers":[
        {
            "category":"Professional",
            "type":"Services"
        }
    ],
    "sg:phone":"+1 563 243 4108",
    "sg:postcode":"52732",
    "sg:province":"IA",
    "wof:name":"Raymond Kerr",
    "wof:placetype":"venue"
},
  "geometry": {"coordinates":[-90.19635599999999,41.850249],"type":"Point"}
}