{
  "type": "Feature",
  "properties": {
    "iso:country":"US",
    "sg:address":"801 Iowa Ave",
    "sg:city":"Onawa",
    "sg:classifiers":[
        {
            "category":"Government",
            "subcategory":"Office",
            "type":"Public Place"
        }
    ],
    "sg:phone":"+1 712 423 2155",
    "sg:postcode":"51040",
    "sg:province":"IA",
    "sg:tags":[
        "federal"
    ],
    "wof:name":"Natural Resources Conservation",
    "wof:placetype":"venue"
},
  "geometry": {"coordinates":[-96.095894,42.026702],"type":"Point"}
}