{
  "type": "Feature",
  "properties": {
    "addr:full":"905 E Main St Manchester IA 52057",
    "addr:housenumber":"905",
    "addr:postcode":"52057",
    "addr:street":"E Main St",
    "iso:country":"US",
    "sg:address":"905 E Main St",
    "sg:city":"Manchester",
    "sg:classifiers":[
        {
            "category":"Autos & Motor Vehicles",
            "subcategory":"Auto Supplies",
            "type":"Retail Goods"
        }
    ],
    "sg:phone":"+1 563 927 3912",
    "sg:postcode":"52057",
    "sg:province":"IA",
    "sg:tags":[
        "tire"
    ],
    "wof:name":"Boubin Tire & Automotive",
    "wof:placetype":"venue"
},
  "geometry": {"coordinates":[-91.44511199999999,42.483953],"type":"Point"}
}