{
  "type": "Feature",
  "properties": {
    "addr:full":"101 E Mission St Strawberry Point IA 52076",
    "addr:housenumber":"101",
    "addr:postcode":"52076",
    "addr:street":"E Mission St",
    "iso:country":"US",
    "sg:address":"101 E Mission St",
    "sg:city":"Strawberry Point",
    "sg:classifiers":[
        {
            "category":"Personal",
            "subcategory":"Beauty Salon",
            "type":"Services"
        }
    ],
    "sg:phone":"+1 563 933 4002",
    "sg:postcode":"52076",
    "sg:province":"IA",
    "wof:name":"Country Parlor",
    "wof:placetype":"venue"
},
  "geometry": {"coordinates":[-91.53423600000001,42.683472],"type":"Point"}
}