{
  "type": "Feature",
  "properties": {
    "iso:country":"US",
    "sg:address":"2306 Park Ave",
    "sg:city":"Muscatine",
    "sg:classifiers":[
        {
            "category":"Restaurant",
            "type":"Food & Drink"
        }
    ],
    "sg:menulink":"http://www.allmenus.com/ia/bloomington/160779-burger-king/menu/",
    "sg:phone":"+1 319 264 1226",
    "sg:postcode":"52761",
    "sg:province":"IA",
    "sg:tags":[
        "burger",
        "american"
    ],
    "wof:name":"Burger King",
    "wof:placetype":"venue"
},
  "geometry": {"coordinates":[-91.030433,41.448227],"type":"Point"}
}