{
  "type": "Feature",
  "properties": {
    "addr:full":"1895 Middle Rd Bettendorf IA 52722",
    "addr:housenumber":"1895",
    "addr:postcode":"52722",
    "addr:street":"Middle Rd",
    "iso:country":"US",
    "sg:address":"1895 Middle Rd",
    "sg:city":"Bettendorf",
    "sg:classifiers":[
        {
            "category":"Health Services",
            "subcategory":"Doctor",
            "type":"Services"
        }
    ],
    "sg:phone":"+1 563 355 7884",
    "sg:postcode":"52722",
    "sg:province":"IA",
    "sg:tags":[
        "dentist"
    ],
    "wof:name":"Michael J Doyle DDS",
    "wof:placetype":"venue"
},
  "geometry": {"coordinates":[-90.505788,41.544512],"type":"Point"}
}