{
  "type": "Feature",
  "properties": {
    "addr:full":"250 Main St N Titonka IA 50480",
    "addr:housenumber":"250",
    "addr:postcode":"50480",
    "addr:street":"Main St N",
    "iso:country":"US",
    "sg:address":"250 Main St N",
    "sg:city":"Titonka",
    "sg:classifiers":[
        {
            "category":"Government",
            "subcategory":"Office",
            "type":"Public Place"
        }
    ],
    "sg:phone":"+1 515 928 2020",
    "sg:postcode":"50480",
    "sg:province":"IA",
    "sg:tags":[
        "civil",
        "defense",
        "agency"
    ],
    "wof:name":"Titonka Emergency Svc Bldg",
    "wof:placetype":"venue"
},
  "geometry": {"coordinates":[-94.041308,43.237364],"type":"Point"}
}