{
  "type": "Feature",
  "properties": {
    "addr:full":"922 Okoboji Ave Milford IA 51351",
    "addr:housenumber":"922",
    "addr:postcode":"51351",
    "addr:street":"Okoboji Ave",
    "iso:country":"US",
    "sg:address":"922 Okoboji Ave",
    "sg:city":"Milford",
    "sg:classifiers":[
        {
            "category":"Home & Garden",
            "subcategory":"Household Appliances",
            "type":"Retail Goods"
        }
    ],
    "sg:phone":"+1 712 338 2414",
    "sg:postcode":"51351",
    "sg:province":"IA",
    "wof:name":"Melander's TV Appliance",
    "wof:placetype":"venue"
},
  "geometry": {"coordinates":[-95.149919,43.324662],"type":"Point"}
}