{
  "type": "Feature",
  "properties": {
    "iso:country":"US",
    "sg:address":"1020 W Penn St",
    "sg:city":"North Liberty",
    "sg:classifiers":[
        {
            "category":"Freight",
            "type":"Transportation"
        }
    ],
    "sg:phone":"+1 319 626 3770",
    "sg:postcode":"52317",
    "sg:province":"IA",
    "sg:tags":[
        "commercial",
        "storage"
    ],
    "wof:name":"Penn Street Mini Storage",
    "wof:placetype":"venue"
},
  "geometry": {"coordinates":[-91.616584,41.752395],"type":"Point"}
}