{
  "type": "Feature",
  "properties": {
    "iso:country":"US",
    "sg:address":"2000 Indian Hills Dr",
    "sg:city":"Sioux City",
    "sg:classifiers":[
        {
            "category":"Professional",
            "subcategory":"Management & Consulting",
            "type":"Services"
        }
    ],
    "sg:phone":"+1 712 239 2010",
    "sg:postcode":"51104",
    "sg:province":"IA",
    "sg:tags":[
        "marketing",
        "program"
    ],
    "wof:name":"Powell Marketing",
    "wof:placetype":"venue"
},
  "geometry": {"coordinates":[-96.383611,42.534296],"type":"Point"}
}