{
  "type": "Feature",
  "properties": {
    "iso:country":"US",
    "sg:address":"2360 300th St",
    "sg:city":"Rock Valley",
    "sg:classifiers":[
        {
            "category":"Utilities",
            "subcategory":"Refuse",
            "type":"Services"
        }
    ],
    "sg:phone":"+1 712 476 2111",
    "sg:postcode":"51247",
    "sg:province":"IA",
    "sg:tags":[
        "garbage",
        "collection"
    ],
    "wof:name":"Herm's Sanitation Inc",
    "wof:placetype":"venue"
},
  "geometry": {"coordinates":[-96.322649,43.21436],"type":"Point"}
}