{
  "type": "Feature",
  "properties": {
    "iso:country":"US",
    "sg:address":"821 Iowa Ave",
    "sg:city":"Onawa",
    "sg:classifiers":[
        {
            "category":"Shopping",
            "subcategory":"Pharmacy",
            "type":"Retail Goods"
        }
    ],
    "sg:phone":"+1 712 423 1131",
    "sg:postcode":"51040",
    "sg:province":"IA",
    "sg:website":"www.stangelpharmacy.com",
    "wof:name":"Stangel Pharmacy",
    "wof:placetype":"venue"
},
  "geometry": {"coordinates":[-96.09562200000001,42.026624],"type":"Point"}
}