{
  "type": "Feature",
  "properties": {
    "addr:full":"1900 18th St Spirit Lake IA 51360",
    "addr:housenumber":"1900",
    "addr:postcode":"51360",
    "addr:street":"18Th St",
    "iso:country":"US",
    "sg:address":"1900 18th St",
    "sg:city":"Spirit Lake",
    "sg:classifiers":[
        {
            "category":"Manufacturing",
            "subcategory":"Toys & Sporting Goods",
            "type":"Manufacturing & Wholesale Goods"
        }
    ],
    "sg:phone":"+1 712 336 1520",
    "sg:postcode":"51360",
    "sg:province":"IA",
    "sg:tags":[
        "athletic"
    ],
    "wof:name":"Pure Fishing",
    "wof:placetype":"venue"
},
  "geometry": {"coordinates":[-95.11569,43.422712],"type":"Point"}
}