{
  "type": "Feature",
  "properties": {
    "iso:country":"US",
    "sg:address":"503 2nd St NE",
    "sg:city":"Hampton",
    "sg:classifiers":[
        {
            "category":"Personal",
            "subcategory":"Beauty Salon",
            "type":"Services"
        }
    ],
    "sg:phone":"+1 641 456 4778",
    "sg:postcode":"50441",
    "sg:province":"IA",
    "sg:tags":[
        "shop"
    ],
    "wof:name":"Marilyn's Boutique",
    "wof:placetype":"venue"
},
  "geometry": {"coordinates":[-93.20483900000001,42.747308],"type":"Point"}
}