{
  "type": "Feature",
  "properties": {
    "iso:country":"US",
    "sg:address":"505 W Jefferson St",
    "sg:city":"Bloomfield",
    "sg:classifiers":[
        {
            "category":"Health Services",
            "subcategory":"Doctor",
            "type":"Services"
        }
    ],
    "sg:phone":"+1 641 664 1799",
    "sg:postcode":"52537",
    "sg:province":"IA",
    "sg:tags":[
        "physician",
        "surgeon"
    ],
    "wof:name":"Sean D Brodale DO",
    "wof:placetype":"venue"
},
  "geometry": {"coordinates":[-92.420587,40.751178],"type":"Point"}
}