{
  "type": "Feature",
  "properties": {
    "iso:country":"US",
    "sg:address":"1120 33rd Ave SW",
    "sg:city":"Cedar Rapids",
    "sg:classifiers":[
        {
            "category":"Shopping",
            "subcategory":"Clothing, Apparel, & Fashions",
            "type":"Retail Goods"
        }
    ],
    "sg:phone":"+1 319 368 0339",
    "sg:postcode":"52404",
    "sg:province":"IA",
    "wof:name":"Starter Outlet Stores",
    "wof:placetype":"venue"
},
  "geometry": {"coordinates":[-91.683413,41.94329],"type":"Point"}
}