{
  "type": "Feature",
  "properties": {
    "addr:full":"2164 315th St Washington IA 52353",
    "addr:housenumber":"2164",
    "addr:postcode":"52353",
    "addr:street":"315Th St",
    "iso:country":"US",
    "sg:address":"2164 315th St",
    "sg:city":"Washington",
    "sg:phone":"+1 319 653 4776",
    "sg:postcode":"52353",
    "sg:province":"IA",
    "sg:tags":[
        "hog",
        "farm",
        "corn",
        "soybean",
        "or",
        "feedlot"
    ],
    "wof:name":"Ronald L Janecek",
    "wof:placetype":"venue"
},
  "geometry": {"coordinates":[-91.72666099999999,41.199161],"type":"Point"}
}