{
  "type": "Feature",
  "properties": {
    "iso:country":"US",
    "sg:address":"1337 Ave G",
    "sg:city":"Fort Madison",
    "sg:classifiers":[
        {
            "category":"Arts & Performance",
            "subcategory":"Theater",
            "type":"Entertainment"
        }
    ],
    "sg:phone":"+1 319 372 2556",
    "sg:postcode":"52627",
    "sg:province":"IA",
    "sg:tags":[
        "entertainer"
    ],
    "wof:name":"Cabaret",
    "wof:placetype":"venue"
},
  "geometry": {"coordinates":[-91.322113,40.631126],"type":"Point"}
}