{
  "type": "Feature",
  "properties": {
    "addr:full":"1115 W South Omaha Bridge Rd Council Bluffs IA 51501",
    "addr:housenumber":"1115",
    "addr:postcode":"51501",
    "addr:street":"W South;Bridge Rd",
    "iso:country":"US",
    "sg:address":"1115 W South Omaha Bridge Rd",
    "sg:city":"Council Bluffs",
    "sg:classifiers":[
        {
            "category":"Food & Beverages",
            "subcategory":"Groceries & Convenience Stores",
            "type":"Retail Goods"
        }
    ],
    "sg:phone":"+1 712 366 1156",
    "sg:postcode":"51501",
    "sg:province":"IA",
    "wof:name":"Lake Manawa Convenience",
    "wof:placetype":"venue"
},
  "geometry": {"coordinates":[-95.861581,41.219531],"type":"Point"}
}