{
  "type": "Feature",
  "properties": {
    "iso:country":"US",
    "sg:address":"204 S 9th St",
    "sg:city":"Indianola",
    "sg:classifiers":[
        {
            "category":"Education",
            "subcategory":"Dance Studio",
            "type":"Public Place"
        }
    ],
    "sg:phone":"+1 515 962 9705",
    "sg:postcode":"50125",
    "sg:province":"IA",
    "sg:tags":[
        "instruction",
        "dancing"
    ],
    "wof:name":"Indianola Tumbling Ctr",
    "wof:placetype":"venue"
},
  "geometry": {"coordinates":[-93.54741799999999,41.358104],"type":"Point"}
}