{
  "type": "Feature",
  "properties": {
    "addr:full":"2600 Edgewood Rd SW Ofc Cedar Rapids IA 52404",
    "addr:housenumber":"2600",
    "addr:postcode":"52404",
    "addr:street":"Edgewood Rd Sw",
    "iso:country":"US",
    "sg:address":"2600 Edgewood Rd SW Ofc",
    "sg:city":"Cedar Rapids",
    "sg:classifiers":[
        {
            "category":"Shopping",
            "subcategory":"Mobile Phones",
            "type":"Retail Goods"
        }
    ],
    "sg:phone":"+1 319 390 4989",
    "sg:postcode":"52404",
    "sg:province":"IA",
    "wof:name":"Wireless World",
    "wof:placetype":"venue"
},
  "geometry": {"coordinates":[-91.716103,41.953899],"type":"Point"}
}