{
  "type": "Feature",
  "properties": {
    "iso:country":"US",
    "sg:address":"408 Main St",
    "sg:city":"Fontanelle",
    "sg:classifiers":[
        {
            "category":"Shopping",
            "subcategory":"Hobbies, Toys, & Games",
            "type":"Retail Goods"
        }
    ],
    "sg:phone":"+1 641 745 4043",
    "sg:postcode":"50846",
    "sg:province":"IA",
    "sg:tags":[
        "craft"
    ],
    "wof:name":"S & S Crafts & Ceramics",
    "wof:placetype":"venue"
},
  "geometry": {"coordinates":[-94.561725,41.290563],"type":"Point"}
}