{
  "type": "Feature",
  "properties": {
    "iso:country":"US",
    "sg:address":"212 Fairmount St",
    "sg:city":"Sioux City",
    "sg:classifiers":[
        {
            "category":"Wholesale",
            "subcategory":"Electrical",
            "type":"Manufacturing & Wholesale Goods"
        }
    ],
    "sg:phone":"+1 712 277 2023",
    "sg:postcode":"51106",
    "sg:province":"SD",
    "sg:tags":[
        "equipment",
        "electric",
        "supply"
    ],
    "wof:name":"Consolidated Electrical Distr",
    "wof:placetype":"venue"
},
  "geometry": {"coordinates":[-96.374317,42.491563],"type":"Point"}
}