{
  "type": "Feature",
  "properties": {
    "addr:full":"501 5th St Defiance IA 51578",
    "addr:housenumber":"501",
    "addr:postcode":"51578",
    "addr:street":"5Th St",
    "iso:country":"US",
    "sg:address":"501 5th St",
    "sg:city":"Defiance",
    "sg:classifiers":[
        {
            "category":"Organizations",
            "subcategory":"Religious Organization",
            "type":"Services"
        }
    ],
    "sg:phone":"+1 712 748 3501",
    "sg:postcode":"51578",
    "sg:province":"IA",
    "sg:tags":[
        "church"
    ],
    "wof:name":"St Peter's Catholic Church",
    "wof:placetype":"venue"
},
  "geometry": {"coordinates":[-95.344236,41.824489],"type":"Point"}
}