{
  "type": "Feature",
  "properties": {
    "iso:country":"US",
    "sg:address":"411 W Water St",
    "sg:city":"Decorah",
    "sg:classifiers":[
        {
            "category":"Professional",
            "subcategory":"Business Services",
            "type":"Services"
        }
    ],
    "sg:phone":"+1 563 382 1227",
    "sg:postcode":"52101",
    "sg:province":"IA",
    "wof:name":"Maurland Elisabeth Studio",
    "wof:placetype":"venue"
},
  "geometry": {"coordinates":[-91.790798,43.304076],"type":"Point"}
}