{
  "type": "Feature",
  "properties": {
    "addr:full":"2205 Main St Emmetsburg IA 50536",
    "addr:housenumber":"2205",
    "addr:postcode":"50536",
    "addr:street":"Main St",
    "iso:country":"US",
    "sg:address":"2205 Main St",
    "sg:city":"Emmetsburg",
    "sg:classifiers":[
        {
            "category":"Cinema",
            "subcategory":"Movie Rental",
            "type":"Entertainment"
        }
    ],
    "sg:phone":"+1 712 852 3911",
    "sg:postcode":"50536",
    "sg:province":"IA",
    "sg:tags":[
        "leasing",
        "video",
        "disc",
        "tape"
    ],
    "wof:name":"Video Warehouse",
    "wof:placetype":"venue"
},
  "geometry": {"coordinates":[-94.679564,43.112071],"type":"Point"}
}