{
  "type": "Feature",
  "properties": {
    "addr:full":"23489 Robin Ave Bonaparte IA 52620",
    "addr:housenumber":"23489",
    "addr:postcode":"52620",
    "addr:street":"Robin Ave",
    "iso:country":"US",
    "sg:address":"23489 Robin Ave",
    "sg:city":"Bonaparte",
    "sg:classifiers":[
        {
            "category":"Organizations",
            "subcategory":"Religious Organization",
            "type":"Services"
        }
    ],
    "sg:phone":"+1 319 592 3613",
    "sg:postcode":"52620",
    "sg:province":"IA",
    "wof:name":"Bonaparte Baptist Church",
    "wof:placetype":"venue"
},
  "geometry": {"coordinates":[-91.843689,40.704799],"type":"Point"}
}