{
  "type": "Feature",
  "properties": {
    "iso:country":"US",
    "sg:address":"11356 260th St",
    "sg:city":"Manning",
    "sg:phone":"+1 712 653 2626",
    "sg:postcode":"51455",
    "sg:province":"IA",
    "sg:tags":[
        "farm",
        "corn",
        "soybean"
    ],
    "wof:name":"Donald Lampman",
    "wof:placetype":"venue"
},
  "geometry": {"coordinates":[-95.05825,41.979386],"type":"Point"}
}