{
  "type": "Feature",
  "properties": {
    "addr:full":"1370 NW 114th St Clive IA 50325",
    "addr:housenumber":"1370",
    "addr:postcode":"50325",
    "addr:street":"Nw 114Th St",
    "iso:country":"US",
    "sg:address":"1370 NW 114th St",
    "sg:city":"Clive",
    "sg:classifiers":[
        {
            "category":"Banks & Credit Unions",
            "subcategory":"Bank",
            "type":"Services"
        }
    ],
    "sg:phone":"+1 515 440 6567",
    "sg:postcode":"50325",
    "sg:province":"IA",
    "sg:tags":[
        "financing"
    ],
    "wof:name":"Ashworth Funding",
    "wof:placetype":"venue"
},
  "geometry": {"coordinates":[-93.771477,41.602107],"type":"Point"}
}