{
  "type": "Feature",
  "properties": {
    "iso:country":"US",
    "sg:address":"1715 Summit St",
    "sg:city":"Sioux City",
    "sg:classifiers":[
        {
            "category":"Professional",
            "subcategory":"Accounting & Tax Preparation",
            "type":"Services"
        }
    ],
    "sg:phone":"+1 712 252 4946",
    "sg:postcode":"51105",
    "sg:province":"IA",
    "wof:name":"Backman and Associates",
    "wof:placetype":"venue"
},
  "geometry": {"coordinates":[-96.409606,42.509022],"type":"Point"}
}