{
  "type": "Feature",
  "properties": {
    "addr:full":"96 Lakeshore Dr Storm Lake IA 50588",
    "addr:housenumber":"96",
    "addr:postcode":"50588",
    "addr:street":"Lakeshore Dr",
    "iso:country":"US",
    "sg:address":"96 Lakeshore Dr",
    "sg:city":"Storm Lake",
    "sg:classifiers":[
        {
            "category":"Recreation",
            "subcategory":"Marina",
            "type":"Entertainment"
        }
    ],
    "sg:phone":"+1 712 732 7465",
    "sg:postcode":"50588",
    "sg:province":"IA",
    "wof:name":"Lakeside Marina",
    "wof:placetype":"venue"
},
  "geometry": {"coordinates":[-95.17395399999999,42.622696],"type":"Point"}
}