{
  "type": "Feature",
  "properties": {
    "iso:country":"US",
    "sg:address":"1600 Pierce St",
    "sg:city":"Sioux City",
    "sg:classifiers":[
        {
            "category":"Shopping",
            "subcategory":"Hobbies, Toys, & Games",
            "type":"Retail Goods"
        }
    ],
    "sg:phone":"+1 712 258 1010",
    "sg:postcode":"51105",
    "sg:province":"IA",
    "sg:tags":[
        "model",
        "supply"
    ],
    "wof:name":"Patch-Craft Hobby Shop",
    "wof:placetype":"venue"
},
  "geometry": {"coordinates":[-96.405075,42.508146],"type":"Point"}
}