{
  "type": "Feature",
  "properties": {
    "iso:country":"US",
    "sg:address":"900 56th St",
    "sg:city":"Des Moines",
    "sg:classifiers":[
        {
            "category":"Health Services",
            "subcategory":"Nursing And Care Facility",
            "type":"Services"
        }
    ],
    "sg:phone":"+1 515 255 0857",
    "sg:postcode":"50312",
    "sg:province":"IA",
    "sg:tags":[
        "hospice"
    ],
    "sg:website":"www.hospiceofcentraliowa.org",
    "wof:name":"Kavanagh House",
    "wof:placetype":"venue"
},
  "geometry": {"coordinates":[-93.69376200000001,41.592918],"type":"Point"}
}