{
  "type": "Feature",
  "properties": {
    "iso:country":"US",
    "sg:address":"239 Westside Dr",
    "sg:city":"Iowa City",
    "sg:classifiers":[
        {
            "category":"Building & Trades",
            "subcategory":"Electrical",
            "type":"Services"
        }
    ],
    "sg:phone":"+1 319 331 8738",
    "sg:postcode":"52246",
    "sg:province":"IA",
    "sg:tags":[
        "electric",
        "contractor"
    ],
    "wof:name":"Tri T Electric LC",
    "wof:placetype":"venue"
},
  "geometry": {"coordinates":[-91.565849,41.639796],"type":"Point"}
}