{
  "type": "Feature",
  "properties": {
    "iso:country":"US",
    "sg:address":"115 E Main St",
    "sg:city":"New Hampton",
    "sg:classifiers":[
        {
            "category":"Food & Beverages",
            "subcategory":"Groceries & Convenience Stores",
            "type":"Retail Goods"
        }
    ],
    "sg:phone":"+1 641 394 3785",
    "sg:postcode":"50659",
    "sg:province":"IA",
    "wof:name":"KWIK Star",
    "wof:placetype":"venue"
},
  "geometry": {"coordinates":[-92.314069,43.05924],"type":"Point"}
}