{
  "type": "Feature",
  "properties": {
    "iso:country":"US",
    "sg:address":"27887 Timber Rd",
    "sg:city":"Kelley",
    "sg:classifiers":[
        {
            "category":"Home & Garden",
            "subcategory":"Garden Supply",
            "type":"Retail Goods"
        }
    ],
    "sg:phone":"+1 515 769 2446",
    "sg:postcode":"50134",
    "sg:province":"IA",
    "sg:tags":[
        "pottery",
        "product",
        "mfg"
    ],
    "sg:website":"www.bonsaitrees.com",
    "wof:name":"Dasu Bonsai Studio",
    "wof:placetype":"venue"
},
  "geometry": {"coordinates":[-93.625884,41.952374],"type":"Point"}
}