{
  "type": "Feature",
  "properties": {
    "addr:full":"1148 E 11th St Washington IA 52353",
    "addr:housenumber":"1148",
    "addr:postcode":"52353",
    "addr:street":"E 11Th St",
    "iso:country":"US",
    "sg:address":"1148 E 11th St",
    "sg:city":"Washington",
    "sg:classifiers":[
        {
            "category":"Government",
            "subcategory":"Office",
            "type":"Public Place"
        }
    ],
    "sg:phone":"+1 319 653 3233",
    "sg:postcode":"52353",
    "sg:province":"IA",
    "wof:name":"Maintenance Garage",
    "wof:placetype":"venue"
},
  "geometry": {"coordinates":[-91.674717,41.309188],"type":"Point"}
}