{
  "type": "Feature",
  "properties": {
    "iso:country":"US",
    "sg:address":"3338 Canterbury Ct",
    "sg:city":"Ames",
    "sg:classifiers":[
        {
            "category":"Manufacturing",
            "subcategory":"Building Materials",
            "type":"Manufacturing & Wholesale Goods"
        }
    ],
    "sg:phone":"+1 515 233 1686",
    "sg:postcode":"50014",
    "sg:province":"IA",
    "sg:tags":[
        "mfg"
    ],
    "wof:name":"Terrones Woodworking",
    "wof:placetype":"venue"
},
  "geometry": {"coordinates":[-93.661964,42.036285],"type":"Point"}
}