{
  "type": "Feature",
  "properties": {
    "iso:country":"US",
    "sg:address":"1959 Isaac Ave",
    "sg:city":"Independence",
    "sg:phone":"+1 319 334 7329",
    "sg:postcode":"50644",
    "sg:province":"IA",
    "sg:tags":[
        "farm",
        "soybean"
    ],
    "wof:name":"Darrell Starling",
    "wof:placetype":"venue"
},
  "geometry": {"coordinates":[-91.914264,42.503282],"type":"Point"}
}