{
  "type": "Feature",
  "properties": {
    "iso:country":"US",
    "sg:address":"1543 State St",
    "sg:city":"Bettendorf",
    "sg:classifiers":[
        {
            "category":"Food & Beverages",
            "subcategory":"Groceries & Convenience Stores",
            "type":"Retail Goods"
        }
    ],
    "sg:phone":"+1 563 359 8600",
    "sg:postcode":"52722",
    "sg:province":"IA",
    "wof:name":"Saru Food Mart",
    "wof:placetype":"venue"
},
  "geometry": {"coordinates":[-90.51129299999999,41.525121],"type":"Point"}
}