{
  "type": "Feature",
  "properties": {
    "iso:country":"US",
    "sg:address":"220 S Dubuque St",
    "sg:city":"Iowa City",
    "sg:classifiers":[
        {
            "category":"Government",
            "subcategory":"Office",
            "type":"Public Place"
        }
    ],
    "sg:phone":"+1 319 356 5092",
    "sg:postcode":"52240",
    "sg:province":"IA",
    "sg:tags":[
        "village"
    ],
    "wof:name":"Parking Systems",
    "wof:placetype":"venue"
},
  "geometry": {"coordinates":[-91.533064,41.658194],"type":"Point"}
}