{
  "type": "Feature",
  "properties": {
    "iso:country":"US",
    "sg:address":"2333 Rompot St SE",
    "sg:city":"Cedar Rapids",
    "sg:classifiers":[
        {
            "category":"Building & Trades",
            "subcategory":"Construction",
            "type":"Services"
        }
    ],
    "sg:phone":"+1 319 366 2627",
    "sg:postcode":"52403",
    "sg:province":"IA",
    "sg:tags":[
        "hanging",
        "contractor"
    ],
    "wof:name":"Johnstone Painting Dwight",
    "wof:placetype":"venue"
},
  "geometry": {"coordinates":[-91.631721,41.953227],"type":"Point"}
}