{
  "type": "Feature",
  "properties": {
    "addr:full":"535 Hill St Dubuque IA 52001",
    "addr:housenumber":"535",
    "addr:postcode":"52001",
    "addr:street":"Hill St",
    "iso:country":"US",
    "sg:address":"535 Hill St",
    "sg:city":"Dubuque",
    "sg:classifiers":[
        {
            "category":"Shopping",
            "subcategory":"Pharmacy",
            "type":"Retail Goods"
        }
    ],
    "sg:phone":"+1 563 588 4033",
    "sg:postcode":"52001",
    "sg:province":"IA",
    "wof:name":"Mercy Care Mor",
    "wof:placetype":"venue"
},
  "geometry": {"coordinates":[-90.673834,42.497167],"type":"Point"}
}