{
  "type": "Feature",
  "properties": {
    "addr:full":"610 13th St Sioux City IA 51105",
    "addr:housenumber":"610",
    "addr:postcode":"51105",
    "addr:street":"13Th St",
    "iso:country":"US",
    "sg:address":"610 13th St",
    "sg:city":"Sioux City",
    "sg:classifiers":[
        {
            "category":"Real Estate",
            "subcategory":"Real Estate Operator",
            "type":"Services"
        }
    ],
    "sg:phone":"+1 712 224 5678",
    "sg:postcode":"51105",
    "sg:province":"IA",
    "sg:tags":[
        "apartment"
    ],
    "wof:name":"Castle On The Hill Apartments",
    "wof:placetype":"venue"
},
  "geometry": {"coordinates":[-96.402919,42.503923],"type":"Point"}
}