{
  "type": "Feature",
  "properties": {
    "addr:full":"1477 130th Ave Farmington IA 52626",
    "addr:housenumber":"1477",
    "addr:postcode":"52626",
    "addr:street":"130Th Ave",
    "iso:country":"US",
    "sg:address":"1477 130th Ave",
    "sg:city":"Farmington",
    "sg:phone":"+1 319 836 2226",
    "sg:postcode":"52626",
    "sg:province":"IA",
    "sg:tags":[
        "farm",
        "corn",
        "soybean"
    ],
    "wof:name":"Sander John",
    "wof:placetype":"venue"
},
  "geometry": {"coordinates":[-91.660543,40.744194],"type":"Point"}
}