{
  "type": "Feature",
  "properties": {
    "addr:full":"2031 Greenwood Dr Ottumwa IA 52501",
    "addr:housenumber":"2031",
    "addr:postcode":"52501",
    "addr:street":"Greenwood Dr",
    "iso:country":"US",
    "sg:address":"2031 Greenwood Dr",
    "sg:city":"Ottumwa",
    "sg:classifiers":[
        {
            "category":"Building & Trades",
            "subcategory":"Construction",
            "type":"Services"
        }
    ],
    "sg:phone":"+1 641 682 4995",
    "sg:postcode":"52501",
    "sg:province":"IA",
    "sg:tags":[
        "roofing",
        "contractor"
    ],
    "wof:name":"Dobson Construction",
    "wof:placetype":"venue"
},
  "geometry": {"coordinates":[-92.456898,41.0056],"type":"Point"}
}