{
  "type": "Feature",
  "properties": {
    "iso:country":"US",
    "sg:address":"610 Antique Country Dr",
    "sg:city":"Casey",
    "sg:classifiers":[
        {
            "category":"Education",
            "subcategory":"Library",
            "type":"Public Place"
        }
    ],
    "sg:phone":"+1 641 746 2670",
    "sg:postcode":"50048",
    "sg:province":"IA",
    "wof:name":"Duncan Memorial Library",
    "wof:placetype":"venue"
},
  "geometry": {"coordinates":[-94.519317,41.506045],"type":"Point"}
}