{
  "type": "Feature",
  "properties": {
    "addr:full":"5754 Locust Rd SW Cedar Rapids IA 52404",
    "addr:housenumber":"5754",
    "addr:postcode":"52404",
    "addr:street":"Locust Rd Sw",
    "iso:country":"US",
    "sg:address":"5754 Locust Rd SW",
    "sg:city":"Cedar Rapids",
    "sg:classifiers":[
        {
            "category":"Wholesale",
            "subcategory":"Farm Supplies",
            "type":"Manufacturing & Wholesale Goods"
        }
    ],
    "sg:phone":"+1 319 398 0820",
    "sg:postcode":"52404",
    "sg:province":"IA",
    "sg:tags":[
        "grain"
    ],
    "sg:website":"www.admworld.com",
    "wof:name":"ADM Growmark",
    "wof:placetype":"venue"
},
  "geometry": {"coordinates":[-91.686314,41.921715],"type":"Point"}
}