{
  "type": "Feature",
  "properties": {
    "iso:country":"US",
    "sg:address":"22387 Glen Hall Rd",
    "sg:city":"Shell Rock",
    "sg:classifiers":[
        {
            "category":"Building & Trades",
            "subcategory":"Construction",
            "type":"Services"
        }
    ],
    "sg:phone":"+1 319 885 4629",
    "sg:postcode":"50670",
    "sg:province":"IA",
    "sg:tags":[
        "house"
    ],
    "wof:name":"Charlie Droste Construction",
    "wof:placetype":"venue"
},
  "geometry": {"coordinates":[-92.57910099999999,42.724001],"type":"Point"}
}