{
  "type": "Feature",
  "properties": {
    "iso:country":"US",
    "sg:address":"111 E Main St",
    "sg:city":"Panora",
    "sg:classifiers":[
        {
            "category":"Manufacturing",
            "subcategory":"Printing",
            "type":"Manufacturing & Wholesale Goods"
        }
    ],
    "sg:phone":"+1 641 755 2115",
    "sg:postcode":"50216",
    "sg:province":"IA",
    "sg:tags":[
        "newspaper"
    ],
    "wof:name":"Guthrie County Vedette",
    "wof:placetype":"venue"
},
  "geometry": {"coordinates":[-94.36421199999999,41.691759],"type":"Point"}
}