{
  "type": "Feature",
  "properties": {
    "iso:country":"US",
    "sg:address":"702 17th St",
    "sg:city":"Belle Plaine",
    "sg:classifiers":[
        {
            "category":"Shopping",
            "subcategory":"Hobbies, Toys, & Games",
            "type":"Retail Goods"
        }
    ],
    "sg:phone":"+1 319 444 3332",
    "sg:postcode":"52208",
    "sg:province":"IA",
    "wof:name":"Board & Pollette",
    "wof:placetype":"venue"
},
  "geometry": {"coordinates":[-92.27752599999999,41.901706],"type":"Point"}
}