{
  "type": "Feature",
  "properties": {
    "iso:country":"US",
    "sg:address":"630 SW 9th St",
    "sg:city":"Des Moines",
    "sg:classifiers":[
        {
            "category":"Autos & Motor Vehicles",
            "subcategory":"Fuel & Gas Station",
            "type":"Retail Goods"
        }
    ],
    "sg:phone":"+1 515 280 6284",
    "sg:postcode":"50309",
    "sg:province":"IA",
    "sg:tags":[
        "station",
        "gasoline"
    ],
    "wof:name":"Krueger Enterprises Inc",
    "wof:placetype":"venue"
},
  "geometry": {"coordinates":[-93.624551,41.575221],"type":"Point"}
}