{
  "type": "Feature",
  "properties": {
    "addr:full":"79 University Ave Des Moines IA 50314",
    "addr:housenumber":"79",
    "addr:postcode":"50314",
    "addr:street":"University Ave",
    "iso:country":"US",
    "sg:address":"79 University Ave",
    "sg:city":"Des Moines",
    "sg:classifiers":[
        {
            "category":"Restaurant",
            "type":"Food & Drink"
        }
    ],
    "sg:phone":"+1 515 222 9338",
    "sg:postcode":"50314",
    "sg:province":"IA",
    "sg:tags":[
        "caterer"
    ],
    "sg:website":"www.inthebag-lunches.com",
    "wof:name":"In The Bag Corp Cuisine",
    "wof:placetype":"venue"
},
  "geometry": {"coordinates":[-93.616553,41.600465],"type":"Point"}
}