{
  "type": "Feature",
  "properties": {
    "iso:country":"US",
    "sg:address":"300 Main St",
    "sg:city":"Keokuk",
    "sg:classifiers":[
        {
            "category":"Personal",
            "subcategory":"Beauty Salon",
            "type":"Services"
        }
    ],
    "sg:phone":"+1 319 524 4949",
    "sg:postcode":"52632",
    "sg:province":"IA",
    "sg:tags":[
        "manicuring"
    ],
    "wof:name":"Magic Nails",
    "wof:placetype":"venue"
},
  "geometry": {"coordinates":[-91.38248299999999,40.394984],"type":"Point"}
}