{
  "type": "Feature",
  "properties": {
    "iso:country":"US",
    "sg:address":"225 E 6th St",
    "sg:city":"Waterloo",
    "sg:classifiers":[
        {
            "category":"Government",
            "subcategory":"Police Station",
            "type":"Public Place"
        }
    ],
    "sg:phone":"+1 319 291 2587",
    "sg:postcode":"50703",
    "sg:province":"IA",
    "sg:tags":[
        "sheriff"
    ],
    "wof:name":"Black Hawk Sheriff's Office",
    "wof:placetype":"venue"
},
  "geometry": {"coordinates":[-92.333097,42.497512],"type":"Point"}
}