{
  "type": "Feature",
  "properties": {
    "iso:country":"US",
    "sg:address":"3305 Big Woods Rd",
    "sg:city":"Cedar Falls",
    "sg:classifiers":[
        {
            "category":"Wholesale",
            "subcategory":"Motor Vehicles",
            "type":"Manufacturing & Wholesale Goods"
        }
    ],
    "sg:phone":"+1 319 277 8227",
    "sg:postcode":"50613",
    "sg:province":"IA",
    "sg:tags":[
        "auction",
        "automobile"
    ],
    "wof:name":"Lenders & Insurers Auto Auctn",
    "wof:placetype":"venue"
},
  "geometry": {"coordinates":[-92.436244,42.566102],"type":"Point"}
}