{
  "type": "Feature",
  "properties": {
    "iso:country":"US",
    "sg:address":"106 S Wilson St",
    "sg:city":"Jefferson",
    "sg:classifiers":[
        {
            "category":"Social Services",
            "type":"Services"
        }
    ],
    "sg:phone":"+1 515 386 4519",
    "sg:postcode":"50129",
    "sg:province":"IA",
    "sg:tags":[
        "youth",
        "organization",
        "center"
    ],
    "wof:name":"Rock",
    "wof:placetype":"venue"
},
  "geometry": {"coordinates":[-94.374821,42.01522],"type":"Point"}
}