{
  "type": "Feature",
  "properties": {
    "addr:full":"2158 Furrow Ave Moorland IA 50566",
    "addr:housenumber":"2158",
    "addr:postcode":"50566",
    "addr:street":"Furrow Ave",
    "iso:country":"US",
    "sg:address":"2158 Furrow Ave",
    "sg:city":"Moorland",
    "sg:classifiers":[
        {
            "category":"Building & Trades",
            "subcategory":"Electrical",
            "type":"Services"
        }
    ],
    "sg:phone":"+1 515 542 3278",
    "sg:postcode":"50566",
    "sg:province":"IA",
    "sg:tags":[
        "work",
        "electrical"
    ],
    "wof:name":"Walsh Electric",
    "wof:placetype":"venue"
},
  "geometry": {"coordinates":[-94.32999700000001,42.477624],"type":"Point"}
}