{
  "type": "Feature",
  "properties": {
    "addr:full":"15624 Timber Ave Glidden IA 51443",
    "addr:housenumber":"15624",
    "addr:postcode":"51443",
    "addr:street":"Timber Ave",
    "iso:country":"US",
    "sg:address":"15624 Timber Ave",
    "sg:city":"Glidden",
    "sg:classifiers":[
        {
            "category":"Freight",
            "type":"Transportation"
        }
    ],
    "sg:phone":"+1 712 659 7017",
    "sg:postcode":"51443",
    "sg:province":"IA",
    "sg:tags":[
        "trucking"
    ],
    "wof:name":"Jeff Behrens Trucking Inc",
    "wof:placetype":"venue"
},
  "geometry": {"coordinates":[-94.72576599999999,42.123029],"type":"Point"}
}