{
  "type": "Feature",
  "properties": {
    "addr:full":"13769 Crappie Cir Moravia IA 52571",
    "addr:housenumber":"13769",
    "addr:postcode":"52571",
    "addr:street":"Crappie Cir",
    "iso:country":"US",
    "sg:address":"13769 Crappie Cir",
    "sg:city":"Moravia",
    "sg:classifiers":[
        {
            "category":"Government",
            "subcategory":"Office",
            "type":"Public Place"
        }
    ],
    "sg:phone":"+1 641 724 3206",
    "sg:postcode":"52571",
    "sg:province":"IA",
    "sg:tags":[
        "federal"
    ],
    "wof:name":"US Army Corps Of Engineers",
    "wof:placetype":"venue"
},
  "geometry": {"coordinates":[-92.871921,40.842066],"type":"Point"}
}