{
  "type": "Feature",
  "properties": {
    "addr:full":"506 E Columbia Ave Davenport IA 52803",
    "addr:housenumber":"506",
    "addr:postcode":"52803",
    "addr:street":"E Columbia Ave",
    "iso:country":"US",
    "sg:address":"506 E Columbia Ave",
    "sg:city":"Davenport",
    "sg:classifiers":[
        {
            "category":"Professional",
            "subcategory":"Management & Consulting",
            "type":"Services"
        }
    ],
    "sg:phone":"+1 563 323 4173",
    "sg:postcode":"52803",
    "sg:province":"IA",
    "sg:tags":[
        "business"
    ],
    "wof:name":"PNP Inc",
    "wof:placetype":"venue"
},
  "geometry": {"coordinates":[-90.56778300000001,41.547296],"type":"Point"}
}