{
  "type": "Feature",
  "properties": {
    "iso:country":"US",
    "sg:address":"124 E 18th St",
    "sg:city":"Cedar Falls",
    "sg:classifiers":[
        {
            "category":"Retail",
            "subcategory":"Repair Shop",
            "type":"Services"
        }
    ],
    "sg:phone":"+1 319 268 9455",
    "sg:postcode":"50613",
    "sg:province":"IA",
    "sg:tags":[
        "lock",
        "locksmith"
    ],
    "wof:name":"Polk's Locksmith Svc",
    "wof:placetype":"venue"
},
  "geometry": {"coordinates":[-92.444199,42.522125],"type":"Point"}
}