{
  "type": "Feature",
  "properties": {
    "addr:full":"528 S Clinton St Iowa City IA 52240",
    "addr:housenumber":"528",
    "addr:postcode":"52240",
    "addr:street":"S Clinton St",
    "iso:country":"US",
    "sg:address":"528 S Clinton St",
    "sg:city":"Iowa City",
    "sg:classifiers":[
        {
            "category":"Professional",
            "subcategory":"Lawyer & Legal Services",
            "type":"Services"
        }
    ],
    "sg:phone":"+1 319 339 4415",
    "sg:postcode":"52240",
    "sg:province":"IA",
    "sg:tags":[
        "attorney"
    ],
    "wof:name":"Martin Diaz Law Firm",
    "wof:placetype":"venue"
},
  "geometry": {"coordinates":[-91.53460699999999,41.654733],"type":"Point"}
}