{
  "type": "Feature",
  "properties": {
    "addr:full":"400 S County Rd Toledo IA 52342",
    "addr:housenumber":"400",
    "addr:postcode":"52342",
    "addr:street":"S County Rd",
    "iso:country":"US",
    "sg:address":"400 S County Rd",
    "sg:city":"Toledo",
    "sg:classifiers":[
        {
            "category":"Restaurant",
            "type":"Food & Drink"
        }
    ],
    "sg:phone":"+1 641 484 5413",
    "sg:postcode":"52342",
    "sg:province":"IA",
    "sg:tags":[
        "pizza"
    ],
    "wof:name":"Casey's Carry Out Pizza",
    "wof:placetype":"venue"
},
  "geometry": {"coordinates":[-92.58168499999999,41.99287],"type":"Point"}
}