{
  "type": "Feature",
  "properties": {
    "iso:country":"US",
    "sg:address":"2410 Crossroads Blvd",
    "sg:city":"Waterloo",
    "sg:classifiers":[
        {
            "category":"Home & Garden",
            "subcategory":"Furniture",
            "type":"Retail Goods"
        }
    ],
    "sg:phone":"+1 319 234 7575",
    "sg:postcode":"50702",
    "sg:province":"IA",
    "wof:name":"Mc Gregor Furniture Co",
    "wof:placetype":"venue"
},
  "geometry": {"coordinates":[-92.322472,42.459194],"type":"Point"}
}