{
  "type": "Feature",
  "properties": {
    "iso:country":"US",
    "sg:address":"1360 Quail Rd",
    "sg:city":"Bagley",
    "sg:classifiers":[
        {
            "category":"Retail",
            "subcategory":"Repair Shop",
            "type":"Services"
        },
        {
            "category":"Building & Trades",
            "subcategory":"Construction",
            "type":"Services"
        }
    ],
    "sg:phone":"+1 641 427 5635",
    "sg:postcode":"50026",
    "sg:province":"IA",
    "sg:tags":[
        "welding",
        "contractor"
    ],
    "wof:name":"Kastner Welding",
    "wof:placetype":"venue"
},
  "geometry": {"coordinates":[-94.435101,41.811267],"type":"Point"}
}