{
  "type": "Feature",
  "properties": {
    "iso:country":"US",
    "sg:address":"107 N Main St",
    "sg:city":"Kimballton",
    "sg:classifiers":[
        {
            "category":"Home & Garden",
            "subcategory":"Garden Supply",
            "type":"Retail Goods"
        }
    ],
    "sg:phone":"+1 712 773 2112",
    "sg:postcode":"51543",
    "sg:province":"IA",
    "sg:tags":[
        "engine"
    ],
    "wof:name":"Firstline Auto Svc",
    "wof:placetype":"venue"
},
  "geometry": {"coordinates":[-95.072772,41.627574],"type":"Point"}
}