{
  "type": "Feature",
  "properties": {
    "addr:full":"539 46th St Des Moines IA 50312",
    "addr:housenumber":"539",
    "addr:postcode":"50312",
    "addr:street":"46Th St",
    "iso:country":"US",
    "sg:address":"539 46th St",
    "sg:city":"Des Moines",
    "sg:classifiers":[
        {
            "category":"Professional",
            "type":"Services"
        }
    ],
    "sg:phone":"+1 515 255 5874",
    "sg:postcode":"50312",
    "sg:province":"IA",
    "wof:name":"Atkinson Foundation",
    "wof:placetype":"venue"
},
  "geometry": {"coordinates":[-93.680295,41.585781],"type":"Point"}
}