{
  "type": "Feature",
  "properties": {
    "iso:country":"US",
    "sg:address":"2701 SE 14th St",
    "sg:city":"Des Moines",
    "sg:classifiers":[
        {
            "category":"Travel",
            "subcategory":"Hotels & Motels",
            "type":"Entertainment"
        }
    ],
    "sg:phone":"+1 515 244 8828",
    "sg:postcode":"50320",
    "sg:province":"IA",
    "wof:name":"Hawkeye Motel",
    "wof:placetype":"venue"
},
  "geometry": {"coordinates":[-93.59678599999999,41.560937],"type":"Point"}
}