{
  "type": "Feature",
  "properties": {
    "addr:full":"1033 Evans Ave West Liberty IA 52776",
    "addr:housenumber":"1033",
    "addr:postcode":"52776",
    "addr:street":"Evans Ave West",
    "iso:country":"US",
    "sg:address":"1033 Evans Ave",
    "sg:city":"West Liberty",
    "sg:classifiers":[
        {
            "category":"Real Estate",
            "subcategory":"Real Estate Agent",
            "type":"Services"
        }
    ],
    "sg:phone":"+1 319 627 6847",
    "sg:postcode":"52776",
    "sg:province":"IA",
    "wof:name":"Wild Prairie Development",
    "wof:placetype":"venue"
},
  "geometry": {"coordinates":[-91.27002299999999,41.583549],"type":"Point"}
}