{
  "type": "Feature",
  "properties": {
    "iso:country":"US",
    "sg:address":"2415 300th St",
    "sg:city":"Ventura",
    "sg:phone":"+1 641 829 4490",
    "sg:postcode":"50482",
    "sg:province":"IA",
    "sg:tags":[
        "farm",
        "corn",
        "grain",
        "cash"
    ],
    "wof:name":"Roenfanz Farm Inc",
    "wof:placetype":"venue"
},
  "geometry": {"coordinates":[-93.514714,43.198719],"type":"Point"}
}