{
  "type": "Feature",
  "properties": {
    "iso:country":"US",
    "sg:address":"610 Auburn Ave",
    "sg:city":"Chariton",
    "sg:classifiers":[
        {
            "category":"Building & Trades",
            "subcategory":"Cleaning & Sanitation",
            "type":"Services"
        }
    ],
    "sg:phone":"+1 641 774 8056",
    "sg:postcode":"50049",
    "sg:province":"IA",
    "sg:tags":[
        "fireplace",
        "chimney"
    ],
    "wof:name":"Top Notch Chimney Sweep & Svc",
    "wof:placetype":"venue"
},
  "geometry": {"coordinates":[-93.302108,41.018057],"type":"Point"}
}