{
  "type": "Feature",
  "properties": {
    "iso:country":"US",
    "sg:address":"104 7th Ave",
    "sg:city":"Sully",
    "sg:classifiers":[
        {
            "category":"Home & Garden",
            "subcategory":"Garden Supply",
            "type":"Retail Goods"
        }
    ],
    "sg:phone":"+1 641 594 3299",
    "sg:postcode":"50251",
    "sg:province":"IA",
    "sg:tags":[
        "lawn",
        "mower"
    ],
    "wof:name":"Matt's Mowers",
    "wof:placetype":"venue"
},
  "geometry": {"coordinates":[-92.846164,41.581031],"type":"Point"}
}