{
  "type": "Feature",
  "properties": {
    "addr:full":"106 Greely St Cantril IA 52542",
    "addr:housenumber":"106",
    "addr:postcode":"52542",
    "addr:street":"Greely St",
    "iso:country":"US",
    "sg:address":"106 Greely St",
    "sg:city":"Cantril",
    "sg:classifiers":[
        {
            "category":"Personal",
            "subcategory":"Beauty Salon",
            "type":"Services"
        }
    ],
    "sg:phone":"+1 319 397 2389",
    "sg:postcode":"52542",
    "sg:province":"IA",
    "wof:name":"Connie's Salon",
    "wof:placetype":"venue"
},
  "geometry": {"coordinates":[-92.07211,40.644645],"type":"Point"}
}