{
  "type": "Feature",
  "properties": {
    "iso:country":"US",
    "sg:address":"2700 Mount Pleasant St",
    "sg:city":"Burlington",
    "sg:classifiers":[
        {
            "category":"Real Estate",
            "subcategory":"Real Estate Agent",
            "type":"Services"
        }
    ],
    "sg:phone":"+1 319 752 7653",
    "sg:postcode":"52601",
    "sg:province":"IA",
    "wof:name":"Great River Realty",
    "wof:placetype":"venue"
},
  "geometry": {"coordinates":[-91.140569,40.825841],"type":"Point"}
}