{
  "type": "Feature",
  "properties": {
    "addr:full":"105 S Delaware Ave Mason City IA 50401",
    "addr:housenumber":"105",
    "addr:postcode":"50401",
    "addr:street":"S Delaware Ave",
    "iso:country":"US",
    "sg:address":"105 S Delaware Ave",
    "sg:city":"Mason City",
    "sg:classifiers":[
        {
            "category":"Professional",
            "subcategory":"Employment Agencies",
            "type":"Services"
        }
    ],
    "sg:phone":"+1 641 424 3614",
    "sg:postcode":"50401",
    "sg:province":"IA",
    "sg:tags":[
        "help",
        "contractor"
    ],
    "wof:name":"Kelly Services Inc",
    "wof:placetype":"venue"
},
  "geometry": {"coordinates":[-93.199353,43.150845],"type":"Point"}
}