{
  "type": "Feature",
  "properties": {
    "iso:country":"US",
    "sg:address":"39978 Pinoak Rd",
    "sg:city":"Hancock",
    "sg:classifiers":[
        {
            "category":"Building & Trades",
            "subcategory":"Construction",
            "type":"Services"
        }
    ],
    "sg:phone":"+1 712 741 5539",
    "sg:postcode":"51536",
    "sg:province":"IA",
    "sg:tags":[
        "foundation"
    ],
    "wof:name":"Shatto Construction",
    "wof:placetype":"venue"
},
  "geometry": {"coordinates":[-95.431455,41.404896],"type":"Point"}
}