{
  "type": "Feature",
  "properties": {
    "iso:country":"US",
    "sg:address":"2635 Hubbell Ave",
    "sg:city":"Des Moines",
    "sg:classifiers":[
        {
            "category":"Professional",
            "subcategory":"Lawyer & Legal Services",
            "type":"Services"
        }
    ],
    "sg:phone":"+1 515 265 8877",
    "sg:postcode":"50317",
    "sg:province":"IA",
    "sg:tags":[
        "attorney"
    ],
    "wof:name":"John Spellman",
    "wof:placetype":"venue"
},
  "geometry": {"coordinates":[-93.56639300000001,41.6143],"type":"Point"}
}