{
  "type": "Feature",
  "properties": {
    "iso:country":"US",
    "sg:address":"1200 W Cedar Loop",
    "sg:city":"Cherokee",
    "sg:classifiers":[
        {
            "category":"Organizations",
            "subcategory":"Non-profit Organization",
            "type":"Services"
        }
    ],
    "sg:phone":"+1 712 225 2441",
    "sg:postcode":"51012",
    "sg:province":"IA",
    "sg:tags":[
        "information",
        "alcoholism",
        "treatment"
    ],
    "wof:name":"Synergy Center",
    "wof:placetype":"venue"
},
  "geometry": {"coordinates":[-95.567634,42.753727],"type":"Point"}
}