{
  "type": "Feature",
  "properties": {
    "iso:country":"US",
    "sg:address":"1633 N 29th St",
    "sg:city":"Fort Dodge",
    "sg:classifiers":[
        {
            "category":"Organizations",
            "subcategory":"Religious Organization",
            "type":"Services"
        }
    ],
    "sg:phone":"+1 515 576 0022",
    "sg:postcode":"50501",
    "sg:province":"IA",
    "wof:name":"Evangelical Mennonite Church",
    "wof:placetype":"venue"
},
  "geometry": {"coordinates":[-94.15797000000001,42.521605],"type":"Point"}
}