{
  "type": "Feature",
  "properties": {
    "addr:full":"2220 Hamilton Blvd Sioux City IA 51104",
    "addr:housenumber":"2220",
    "addr:postcode":"51104",
    "addr:street":"Hamilton Blvd",
    "iso:country":"US",
    "sg:address":"2220 Hamilton Blvd",
    "sg:city":"Sioux City",
    "sg:classifiers":[
        {
            "category":"Banks & Credit Unions",
            "subcategory":"Bank",
            "type":"Services"
        }
    ],
    "sg:phone":"+1 712 233 4500",
    "sg:postcode":"51104",
    "sg:province":"IA",
    "wof:name":"Wells Fargo Bank",
    "wof:placetype":"venue"
},
  "geometry": {"coordinates":[-96.416749,42.514034],"type":"Point"}
}