{
  "type": "Feature",
  "properties": {
    "iso:country":"US",
    "sg:address":"1606 17th Ave",
    "sg:city":"Eldora",
    "sg:classifiers":[
        {
            "category":"Government",
            "subcategory":"Office",
            "type":"Public Place"
        }
    ],
    "sg:phone":"+1 641 939 3944",
    "sg:postcode":"50627",
    "sg:province":"IA",
    "sg:tags":[
        "village"
    ],
    "wof:name":"Eldora Street Maintenance",
    "wof:placetype":"venue"
},
  "geometry": {"coordinates":[-93.10327599999999,42.357043],"type":"Point"}
}