{
  "type": "Feature",
  "properties": {
    "iso:country":"US",
    "sg:address":"801 S Minnesota St",
    "sg:city":"Algona",
    "sg:classifiers":[
        {
            "category":"Restaurant",
            "type":"Food & Drink"
        }
    ],
    "sg:phone":"+1 515 295 9403",
    "sg:postcode":"50511",
    "sg:province":"IA",
    "sg:tags":[
        "caterer"
    ],
    "sg:website":"www.dadsbelgianwaffles.com",
    "wof:name":"Dad's Belgian Waffles",
    "wof:placetype":"venue"
},
  "geometry": {"coordinates":[-94.231758,43.062357],"type":"Point"}
}