{
  "type": "Feature",
  "properties": {
    "iso:country":"US",
    "sg:address":"6879 Cedar St",
    "sg:city":"Wapello",
    "sg:classifiers":[
        {
            "category":"Building & Trades",
            "subcategory":"Construction",
            "type":"Services"
        }
    ],
    "sg:phone":"+1 319 766 4017",
    "sg:postcode":"52653",
    "sg:province":"IA",
    "sg:tags":[
        "underground",
        "trenching",
        "contractor"
    ],
    "wof:name":"Brockert Construction Inc",
    "wof:placetype":"venue"
},
  "geometry": {"coordinates":[-91.062501,41.139711],"type":"Point"}
}