{
  "type": "Feature",
  "properties": {
    "iso:country":"US",
    "sg:address":"1340 Delhi St",
    "sg:city":"Dubuque",
    "sg:classifiers":[
        {
            "category":"Health Services",
            "subcategory":"Doctor",
            "type":"Services"
        }
    ],
    "sg:phone":"+1 563 588 2585",
    "sg:postcode":"52001",
    "sg:province":"IA",
    "sg:tags":[
        "dentist"
    ],
    "wof:name":"Mc Coy Dental Ctr",
    "wof:placetype":"venue"
},
  "geometry": {"coordinates":[-90.685255,42.497902],"type":"Point"}
}