{
  "type": "Feature",
  "properties": {
    "iso:country":"US",
    "sg:address":"1 NE 46th Pl",
    "sg:city":"Des Moines",
    "sg:classifiers":[
        {
            "category":"Autos & Motor Vehicles",
            "subcategory":"Automobile Sales",
            "type":"Retail Goods"
        }
    ],
    "sg:phone":"+1 515 244 9499",
    "sg:postcode":"50313",
    "sg:province":"IA",
    "sg:tags":[
        "car",
        "used",
        "dealer"
    ],
    "wof:name":"A B U Motor Cars",
    "wof:placetype":"venue"
},
  "geometry": {"coordinates":[-93.61511299999999,41.645502],"type":"Point"}
}