{
  "type": "Feature",
  "properties": {
    "iso:country":"US",
    "sg:address":"1030 Hwy 146",
    "sg:city":"New Sharon",
    "sg:classifiers":[
        {
            "category":"Manufacturing",
            "subcategory":"Metals",
            "type":"Manufacturing & Wholesale Goods"
        }
    ],
    "sg:phone":"+1 641 637 4455",
    "sg:postcode":"50207",
    "sg:province":"IA",
    "sg:website":"www.dejongmfg.com",
    "wof:name":"De Jong Mfg Inc",
    "wof:placetype":"venue"
},
  "geometry": {"coordinates":[-92.651544,41.504634],"type":"Point"}
}