{
  "type": "Feature",
  "properties": {
    "iso:country":"US",
    "sg:address":"7545 28th Ave",
    "sg:city":"Watkins",
    "sg:classifiers":[
        {
            "category":"Retail",
            "subcategory":"Animal Services",
            "type":"Services"
        }
    ],
    "sg:phone":"+1 319 227 6378",
    "sg:postcode":"52354",
    "sg:province":"IA",
    "wof:name":"I C Kennels",
    "wof:placetype":"venue"
},
  "geometry": {"coordinates":[-91.9492,41.927512],"type":"Point"}
}