{
  "type": "Feature",
  "properties": {
    "addr:full":"620 Michigan St Storm Lake IA 50588",
    "addr:housenumber":"620",
    "addr:postcode":"50588",
    "addr:street":"Michigan St",
    "iso:country":"US",
    "sg:address":"620 Michigan St",
    "sg:city":"Storm Lake",
    "sg:classifiers":[
        {
            "category":"Professional",
            "subcategory":"Management & Consulting",
            "type":"Services"
        }
    ],
    "sg:phone":"+1 712 213 1000",
    "sg:postcode":"50588",
    "sg:province":"IA",
    "sg:tags":[
        "marketing",
        "consultant"
    ],
    "wof:name":"Hurley & Assoc",
    "wof:placetype":"venue"
},
  "geometry": {"coordinates":[-95.20211999999999,42.645271],"type":"Point"}
}