{
  "type": "Feature",
  "properties": {
    "iso:country":"US",
    "sg:address":"2744 Fleur Dr",
    "sg:city":"Des Moines",
    "sg:classifiers":[
        {
            "category":"Professional",
            "subcategory":"Computer Services",
            "type":"Services"
        }
    ],
    "sg:phone":"+1 515 276 1011",
    "sg:postcode":"50321",
    "sg:province":"IA",
    "sg:tags":[
        "consulting",
        "it"
    ],
    "wof:name":"Garfield Group Inc",
    "wof:placetype":"venue"
},
  "geometry": {"coordinates":[-93.64512999999999,41.559481],"type":"Point"}
}