{
  "type": "Feature",
  "properties": {
    "addr:full":"1109 5th St Durant IA 52747",
    "addr:housenumber":"1109",
    "addr:postcode":"52747",
    "addr:street":"5Th St",
    "iso:country":"US",
    "sg:address":"1109 5th St",
    "sg:city":"Durant",
    "sg:classifiers":[
        {
            "category":"Building & Trades",
            "subcategory":"Construction",
            "type":"Services"
        }
    ],
    "sg:phone":"+1 563 785 4727",
    "sg:postcode":"52747",
    "sg:province":"IA",
    "sg:tags":[
        "general",
        "contractor"
    ],
    "wof:name":"Tri County Builders",
    "wof:placetype":"venue"
},
  "geometry": {"coordinates":[-90.90410300000001,41.599664],"type":"Point"}
}