{
  "type": "Feature",
  "properties": {
    "iso:country":"US",
    "sg:address":"1722 Commercial St",
    "sg:city":"Waterloo",
    "sg:classifiers":[
        {
            "category":"Building & Trades",
            "subcategory":"Construction",
            "type":"Services"
        }
    ],
    "sg:phone":"+1 319 232 7079",
    "sg:postcode":"50702",
    "sg:province":"IA",
    "sg:tags":[
        "repairing",
        "remodeling",
        "contractor"
    ],
    "wof:name":"Waterloo Building Maintenance",
    "wof:placetype":"venue"
},
  "geometry": {"coordinates":[-92.327282,42.48688],"type":"Point"}
}