{
  "type": "Feature",
  "properties": {
    "iso:country":"US",
    "sg:address":"1132 44th St",
    "sg:city":"Des Moines",
    "sg:classifiers":[
        {
            "category":"Social Services",
            "type":"Services"
        }
    ],
    "sg:phone":"+1 515 279 2008",
    "sg:postcode":"50311",
    "sg:province":"IA",
    "sg:tags":[
        "youth",
        "organization",
        "center"
    ],
    "sg:website":"www.yhma.org",
    "wof:name":"Youth Homes Of Mid America",
    "wof:placetype":"venue"
},
  "geometry": {"coordinates":[-93.67693,41.59786],"type":"Point"}
}