{
  "type": "Feature",
  "properties": {
    "addr:full":"2522 Gabriel Ave Independence IA 50644",
    "addr:housenumber":"2522",
    "addr:postcode":"50644",
    "addr:street":"Gabriel Ave",
    "iso:country":"US",
    "sg:address":"2522 Gabriel Ave",
    "sg:city":"Independence",
    "sg:phone":"+1 319 334 2013",
    "sg:postcode":"50644",
    "sg:province":"IA",
    "sg:tags":[
        "farm",
        "corn"
    ],
    "wof:name":"Fred Staton & Virginia",
    "wof:placetype":"venue"
},
  "geometry": {"coordinates":[-91.96736199999999,42.424893],"type":"Point"}
}