{
  "type": "Feature",
  "properties": {
    "iso:country":"US",
    "sg:address":"2865 Winchester Dr",
    "sg:city":"Marion",
    "sg:classifiers":[
        {
            "category":"Building & Trades",
            "subcategory":"Construction",
            "type":"Services"
        }
    ],
    "sg:phone":"+1 319 373 2124",
    "sg:postcode":"52302",
    "sg:province":"IA",
    "sg:tags":[
        "general",
        "contractor"
    ],
    "wof:name":"CBN Enterprises Inc",
    "wof:placetype":"venue"
},
  "geometry": {"coordinates":[-91.568236,42.048909],"type":"Point"}
}