{
  "type": "Feature",
  "properties": {
    "iso:country":"US",
    "sg:address":"1262 240th St",
    "sg:city":"Modale",
    "sg:phone":"+1 712 646 2107",
    "sg:postcode":"51556",
    "sg:province":"IA",
    "sg:tags":[
        "farm",
        "corn",
        "soybean"
    ],
    "wof:name":"Dorothy Rychner",
    "wof:placetype":"venue"
},
  "geometry": {"coordinates":[-96.06777700000001,41.661387],"type":"Point"}
}