{
  "type": "Feature",
  "properties": {
    "addr:full":"1551 18th St Spirit Lake IA 51360",
    "addr:housenumber":"1551",
    "addr:postcode":"51360",
    "addr:street":"18Th St",
    "iso:country":"US",
    "sg:address":"1551 18th St",
    "sg:city":"Spirit Lake",
    "sg:classifiers":[
        {
            "category":"Shopping",
            "subcategory":"Clothing, Apparel, & Fashions",
            "type":"Retail Goods"
        }
    ],
    "sg:phone":"+1 712 336 3824",
    "sg:postcode":"51360",
    "sg:province":"IA",
    "wof:name":"Fashion Formula",
    "wof:placetype":"venue"
},
  "geometry": {"coordinates":[-95.11093099999999,43.422517],"type":"Point"}
}