{
  "type": "Feature",
  "properties": {
    "iso:country":"US",
    "sg:address":"103 Main St",
    "sg:city":"Kiron",
    "sg:classifiers":[
        {
            "category":"Home & Garden",
            "subcategory":"Building Materials",
            "type":"Retail Goods"
        }
    ],
    "sg:phone":"+1 712 675 4266",
    "sg:postcode":"51448",
    "sg:province":"IA",
    "sg:tags":[
        "lumber"
    ],
    "wof:name":"Kiron Lumber Store",
    "wof:placetype":"venue"
},
  "geometry": {"coordinates":[-95.328853,42.194557],"type":"Point"}
}