{
  "type": "Feature",
  "properties": {
    "iso:country":"US",
    "sg:address":"872 Main St",
    "sg:city":"Holy Cross",
    "sg:classifiers":[
        {
            "category":"Retail",
            "subcategory":"Auto Repair",
            "type":"Services"
        }
    ],
    "sg:phone":"+1 563 870 2275",
    "sg:postcode":"52053",
    "sg:province":"IA",
    "sg:tags":[
        "repairing",
        "automobile"
    ],
    "wof:name":"Maiers Auto Svc",
    "wof:placetype":"venue"
},
  "geometry": {"coordinates":[-90.99597,42.602247],"type":"Point"}
}