{
  "type": "Feature",
  "properties": {
    "iso:country":"US",
    "sg:address":"33722 130th St",
    "sg:city":"Cedar Falls",
    "sg:classifiers":[
        {
            "category":"Farming",
            "subcategory":"Farm",
            "type":"Manufacturing & Wholesale Goods"
        }
    ],
    "sg:phone":"+1 319 266 9565",
    "sg:postcode":"50613",
    "sg:province":"IA",
    "sg:tags":[
        "crop",
        "general"
    ],
    "wof:name":"Terry Stukenberg",
    "wof:placetype":"venue"
},
  "geometry": {"coordinates":[-92.567497,42.513165],"type":"Point"}
}