{
  "type": "Feature",
  "properties": {
    "addr:full":"308 Broadway St Diagonal IA 50845",
    "addr:housenumber":"308",
    "addr:postcode":"50845",
    "addr:street":"Broadway St",
    "iso:country":"US",
    "sg:address":"308 Broadway St",
    "sg:city":"Diagonal",
    "sg:classifiers":[
        {
            "category":"Government",
            "subcategory":"Office",
            "type":"Public Place"
        }
    ],
    "sg:phone":"+1 641 734 5491",
    "sg:postcode":"50845",
    "sg:province":"IA",
    "sg:tags":[
        "city"
    ],
    "wof:name":"Diagonal City Hall",
    "wof:placetype":"venue"
},
  "geometry": {"coordinates":[-94.339618,40.809301],"type":"Point"}
}