{
  "type": "Feature",
  "properties": {
    "addr:full":"2807 Memorial Dr Sioux City IA 51103",
    "addr:housenumber":"2807",
    "addr:postcode":"51103",
    "addr:street":"Memorial Dr",
    "iso:country":"US",
    "sg:address":"2807 Memorial Dr",
    "sg:city":"Sioux City",
    "sg:classifiers":[
        {
            "category":"Building & Trades",
            "subcategory":"Landscaping Services",
            "type":"Services"
        }
    ],
    "sg:phone":"+1 712 233 2323",
    "sg:postcode":"51103",
    "sg:province":"IA",
    "sg:tags":[
        "landscape",
        "contractor"
    ],
    "wof:name":"Waterfalls By Wisner",
    "wof:placetype":"venue"
},
  "geometry": {"coordinates":[-96.453115,42.551003],"type":"Point"}
}