{
  "type": "Feature",
  "properties": {
    "addr:full":"6082 NE 14th St Des Moines IA 50313",
    "addr:housenumber":"6082",
    "addr:postcode":"50313",
    "addr:street":"Ne 14Th St",
    "iso:country":"US",
    "sg:address":"6082 NE 14th St",
    "sg:city":"Des Moines",
    "sg:classifiers":[
        {
            "category":"Manufacturing",
            "subcategory":"Printing",
            "type":"Manufacturing & Wholesale Goods"
        }
    ],
    "sg:phone":"+1 515 289 4464",
    "sg:postcode":"50313",
    "sg:province":"IA",
    "sg:tags":[
        "decal"
    ],
    "sg:website":"www.schneidergraphics.com",
    "wof:name":"Schneider Graphics Inc",
    "wof:placetype":"venue"
},
  "geometry": {"coordinates":[-93.600807,41.672386],"type":"Point"}
}