{
  "type": "Feature",
  "properties": {
    "addr:full":"619 Lombard St Clarence IA 52216",
    "addr:housenumber":"619",
    "addr:postcode":"52216",
    "addr:street":"Lombard St",
    "iso:country":"US",
    "sg:address":"619 Lombard St",
    "sg:city":"Clarence",
    "sg:classifiers":[
        {
            "category":"Manufacturing",
            "subcategory":"Pet Food",
            "type":"Manufacturing & Wholesale Goods"
        }
    ],
    "sg:phone":"+1 563 452 3805",
    "sg:postcode":"52216",
    "sg:province":"IA",
    "sg:tags":[
        "feed"
    ],
    "sg:website":"www.clarencecoop.com",
    "wof:name":"River Valley Cooperative",
    "wof:placetype":"venue"
},
  "geometry": {"coordinates":[-91.05446000000001,41.888826],"type":"Point"}
}