{
  "type": "Feature",
  "properties": {
    "iso:country":"US",
    "sg:address":"1706 Ithaca Ave",
    "sg:city":"Spirit Lake",
    "sg:classifiers":[
        {
            "category":"Manufacturing",
            "subcategory":"Printing",
            "type":"Manufacturing & Wholesale Goods"
        }
    ],
    "sg:phone":"+1 712 336 1211",
    "sg:postcode":"51360",
    "sg:province":"IA",
    "sg:tags":[
        "newspaper"
    ],
    "wof:name":"Dickinson County News Inc",
    "wof:placetype":"venue"
},
  "geometry": {"coordinates":[-95.10371600000001,43.423385],"type":"Point"}
}