{
  "type": "Feature",
  "properties": {
    "iso:country":"US",
    "sg:address":"9401 Winston Ave",
    "sg:city":"Urbandale",
    "sg:classifiers":[
        {
            "category":"Real Estate",
            "subcategory":"Real Estate Agent",
            "type":"Services"
        }
    ],
    "sg:phone":"+1 515 270 3877",
    "sg:postcode":"50322",
    "sg:province":"IA",
    "sg:tags":[
        "appraiser"
    ],
    "wof:name":"Accurate Appraisals",
    "wof:placetype":"venue"
},
  "geometry": {"coordinates":[-93.74801100000001,41.635559],"type":"Point"}
}