{
  "type": "Feature",
  "properties": {
    "iso:country":"US",
    "sg:address":"1462 230th St",
    "sg:city":"Shenandoah",
    "sg:phone":"+1 712 246 3954",
    "sg:postcode":"51601",
    "sg:province":"IA",
    "sg:tags":[
        "farm",
        "real",
        "corn",
        "property",
        "lessor"
    ],
    "wof:name":"Desart Newell",
    "wof:placetype":"venue"
},
  "geometry": {"coordinates":[-95.301869,40.712914],"type":"Point"}
}