{
  "type": "Feature",
  "properties": {
    "iso:country":"US",
    "sg:address":"401 W 2nd St",
    "sg:city":"Brooklyn",
    "sg:classifiers":[
        {
            "category":"Retail",
            "subcategory":"Veterinary Services",
            "type":"Services"
        }
    ],
    "sg:phone":"+1 641 522 7055",
    "sg:postcode":"52211",
    "sg:province":"IA",
    "sg:tags":[
        "veterinarian"
    ],
    "wof:name":"Brooklyn Veterinary Clinic",
    "wof:placetype":"venue"
},
  "geometry": {"coordinates":[-92.44883400000001,41.730466],"type":"Point"}
}