{
  "type": "Feature",
  "properties": {
    "addr:full":"646 Marlou Pkwy Des Moines IA 50320",
    "addr:housenumber":"646",
    "addr:postcode":"50320",
    "addr:street":"Marlou Pkwy",
    "iso:country":"US",
    "sg:address":"646 Marlou Pkwy",
    "sg:city":"Des Moines",
    "sg:classifiers":[
        {
            "category":"Real Estate",
            "subcategory":"Real Estate Agent",
            "type":"Services"
        }
    ],
    "sg:phone":"+1 515 276 8740",
    "sg:postcode":"50320",
    "sg:province":"IA",
    "wof:name":"Creative Homes Inc",
    "wof:placetype":"venue"
},
  "geometry": {"coordinates":[-93.600534,41.505729],"type":"Point"}
}