{
  "type": "Feature",
  "properties": {
    "iso:country":"US",
    "sg:address":"1220 Plato Rd",
    "sg:city":"West Branch",
    "sg:classifiers":[
        {
            "category":"Farming",
            "subcategory":"Livestock Farm",
            "type":"Manufacturing & Wholesale Goods"
        }
    ],
    "sg:phone":"+1 319 643 5872",
    "sg:postcode":"52358",
    "sg:province":"IA",
    "sg:tags":[
        "hog",
        "beef",
        "far",
        "corn",
        "cattle",
        "or",
        "feedlot"
    ],
    "wof:name":"Alfred Worrell",
    "wof:placetype":"venue"
},
  "geometry": {"coordinates":[-91.32300499999999,41.769104],"type":"Point"}
}