{
  "type": "Feature",
  "properties": {
    "iso:country":"US",
    "sg:address":"1103 Locust St",
    "sg:city":"Carter Lake",
    "sg:classifiers":[
        {
            "category":"Retail",
            "subcategory":"Auto Repair",
            "type":"Services"
        }
    ],
    "sg:phone":"+1 712 347 5000",
    "sg:postcode":"51510",
    "sg:province":"IA",
    "wof:name":"City Motor Center",
    "wof:placetype":"venue"
},
  "geometry": {"coordinates":[-95.916298,41.285099],"type":"Point"}
}