{
  "type": "Feature",
  "properties": {
    "iso:country":"US",
    "sg:address":"2469 180th St",
    "sg:city":"Rock Rapids",
    "sg:phone":"+1 712 473 2516",
    "sg:postcode":"51246",
    "sg:province":"IA",
    "sg:tags":[
        "farm",
        "soybean"
    ],
    "wof:name":"Koedam Kountry Kennels",
    "wof:placetype":"venue"
},
  "geometry": {"coordinates":[-96.301889,43.389531],"type":"Point"}
}