{
  "type": "Feature",
  "properties": {
    "addr:full":"1138 200th St Yale IA 50277",
    "addr:housenumber":"1138",
    "addr:postcode":"50277",
    "addr:street":"200Th St",
    "iso:country":"US",
    "sg:address":"1138 200th St",
    "sg:city":"Yale",
    "sg:classifiers":[
        {
            "category":"Farming",
            "subcategory":"Farm",
            "type":"Manufacturing & Wholesale Goods"
        }
    ],
    "sg:phone":"+1 641 439 2236",
    "sg:postcode":"50277",
    "sg:province":"IA",
    "wof:name":"Clark Farms",
    "wof:placetype":"venue"
},
  "geometry": {"coordinates":[-94.26064700000001,41.746103],"type":"Point"}
}