{
  "type": "Feature",
  "properties": {
    "iso:country":"US",
    "sg:address":"3353 Plymouth Ave",
    "sg:city":"Eddyville",
    "sg:classifiers":[
        {
            "category":"Wholesale",
            "subcategory":"Sporting Goods",
            "type":"Manufacturing & Wholesale Goods"
        }
    ],
    "sg:phone":"+1 641 969 4387",
    "sg:postcode":"52553",
    "sg:province":"IA",
    "sg:tags":[
        "range",
        "trap",
        "skeet"
    ],
    "wof:name":"Steelclay Shooting Sports",
    "wof:placetype":"venue"
},
  "geometry": {"coordinates":[-92.578439,41.165312],"type":"Point"}
}