{
  "type": "Feature",
  "properties": {
    "addr:full":"4028 75th St Urbandale IA 50322",
    "addr:housenumber":"4028",
    "addr:postcode":"50322",
    "addr:street":"75Th St",
    "iso:country":"US",
    "sg:address":"4028 75th St",
    "sg:city":"Urbandale",
    "sg:classifiers":[
        {
            "category":"Professional",
            "subcategory":"Business Services",
            "type":"Services"
        }
    ],
    "sg:phone":"+1 515 254 0375",
    "sg:postcode":"50322",
    "sg:province":"IA",
    "sg:tags":[
        "interior",
        "design"
    ],
    "wof:name":"I-Design",
    "wof:placetype":"venue"
},
  "geometry": {"coordinates":[-93.72139900000001,41.634708],"type":"Point"}
}