{
  "type": "Feature",
  "properties": {
    "addr:full":"119 4th St SW Waverly IA 50677",
    "addr:housenumber":"119",
    "addr:postcode":"50677",
    "addr:street":"4Th St Sw",
    "iso:country":"US",
    "sg:address":"119 4th St SW",
    "sg:city":"Waverly",
    "sg:classifiers":[
        {
            "category":"Retail",
            "subcategory":"Auto Repair",
            "type":"Services"
        }
    ],
    "sg:phone":"+1 319 352 3574",
    "sg:postcode":"50677",
    "sg:province":"IA",
    "sg:tags":[
        "repairing",
        "automobile"
    ],
    "wof:name":"Dale's Service",
    "wof:placetype":"venue"
},
  "geometry": {"coordinates":[-92.475594,42.725647],"type":"Point"}
}