{
  "type": "Feature",
  "properties": {
    "addr:full":"148 5th Ave S Clinton IA 52732",
    "addr:housenumber":"148",
    "addr:postcode":"52732",
    "addr:street":"5Th Ave S",
    "iso:country":"US",
    "sg:address":"148 5th Ave S",
    "sg:city":"Clinton",
    "sg:classifiers":[
        {
            "category":"Insurance",
            "subcategory":"Insurance Agent",
            "type":"Services"
        }
    ],
    "sg:phone":"+1 563 242 8814",
    "sg:postcode":"52732",
    "sg:province":"IA",
    "wof:name":"State Farm Insurance",
    "wof:placetype":"venue"
},
  "geometry": {"coordinates":[-90.187134,41.841285],"type":"Point"}
}