{
  "type": "Feature",
  "properties": {
    "addr:full":"3063 Rebecca St Sioux City IA 51103",
    "addr:housenumber":"3063",
    "addr:postcode":"51103",
    "addr:street":"Rebecca St",
    "iso:country":"US",
    "sg:address":"3063 Rebecca St",
    "sg:city":"Sioux City",
    "sg:classifiers":[
        {
            "category":"Retail",
            "subcategory":"Laundry & Dry Cleaning",
            "type":"Services"
        }
    ],
    "sg:phone":"+1 712 252 5014",
    "sg:postcode":"51103",
    "sg:province":"IA",
    "sg:tags":[
        "cleaners",
        "rug",
        "carpet"
    ],
    "wof:name":"Kobes Karpet Kleaners",
    "wof:placetype":"venue"
},
  "geometry": {"coordinates":[-96.425719,42.523272],"type":"Point"}
}