{
  "type": "Feature",
  "properties": {
    "addr:full":"5001 J St SW Cedar Rapids IA 52404",
    "addr:housenumber":"5001",
    "addr:postcode":"52404",
    "addr:street":"J St Sw",
    "iso:country":"US",
    "sg:address":"5001 J St SW",
    "sg:city":"Cedar Rapids",
    "sg:classifiers":[
        {
            "category":"Wholesale",
            "subcategory":"Machinery & Supplies",
            "type":"Manufacturing & Wholesale Goods"
        }
    ],
    "sg:phone":"+1 319 364 1592",
    "sg:postcode":"52404",
    "sg:province":"IA",
    "sg:tags":[
        "equipment",
        "laundry"
    ],
    "sg:website":"www.centurylaundry.com",
    "wof:name":"Century Laundry Distributing",
    "wof:placetype":"venue"
},
  "geometry": {"coordinates":[-91.66647399999999,41.928222],"type":"Point"}
}