{
  "type": "Feature",
  "properties": {
    "iso:country":"US",
    "sg:address":"340 N 2nd St",
    "sg:city":"Wapello",
    "sg:classifiers":[
        {
            "category":"Food & Beverages",
            "subcategory":"Groceries & Convenience Stores",
            "type":"Retail Goods"
        }
    ],
    "sg:phone":"+1 319 523 2205",
    "sg:postcode":"52653",
    "sg:province":"IA",
    "sg:tags":[
        "grocer"
    ],
    "wof:name":"Wapello Food Ctr",
    "wof:placetype":"venue"
},
  "geometry": {"coordinates":[-91.18561099999999,41.182385],"type":"Point"}
}