{
  "type": "Feature",
  "properties": {
    "iso:country":"US",
    "sg:address":"58588 Ebaugh St",
    "sg:city":"Glenwood",
    "sg:classifiers":[
        {
            "category":"Health Services",
            "subcategory":"Doctor",
            "type":"Services"
        }
    ],
    "sg:phone":"+1 712 527 5204",
    "sg:postcode":"51534",
    "sg:province":"IA",
    "sg:tags":[
        "physician",
        "surgeon"
    ],
    "wof:name":"Glenwood Physicians Clinic",
    "wof:placetype":"venue"
},
  "geometry": {"coordinates":[-95.749838,41.037607],"type":"Point"}
}