{
  "type": "Feature",
  "properties": {
    "iso:country":"US",
    "sg:address":"7729 Drake Ct",
    "sg:city":"Clive",
    "sg:classifiers":[
        {
            "category":"Travel",
            "subcategory":"Travel Agent",
            "type":"Entertainment"
        }
    ],
    "sg:phone":"+1 515 255 6115",
    "sg:postcode":"50325",
    "sg:province":"IA",
    "sg:tags":[
        "agency",
        "bureau"
    ],
    "wof:name":"Budget Travel",
    "wof:placetype":"venue"
},
  "geometry": {"coordinates":[-93.723257,41.603838],"type":"Point"}
}