{
  "type": "Feature",
  "properties": {
    "iso:country":"US",
    "sg:address":"504 Front St",
    "sg:city":"Stuart",
    "sg:classifiers":[
        {
            "category":"Wholesale",
            "subcategory":"Farm Supplies",
            "type":"Manufacturing & Wholesale Goods"
        }
    ],
    "sg:phone":"+1 515 523 2351",
    "sg:postcode":"50250",
    "sg:province":"IA",
    "sg:tags":[
        "fertilizer"
    ],
    "wof:name":"Pelgrow",
    "wof:placetype":"venue"
},
  "geometry": {"coordinates":[-94.30889500000001,41.503764],"type":"Point"}
}