{
  "type": "Feature",
  "properties": {
    "iso:country":"US",
    "sg:address":"435 1st St S",
    "sg:city":"Charter Oak",
    "sg:classifiers":[
        {
            "category":"Banks & Credit Unions",
            "subcategory":"Bank",
            "type":"Services"
        }
    ],
    "sg:phone":"+1 712 678 3556",
    "sg:postcode":"51439",
    "sg:province":"IA",
    "sg:tags":[
        "loan"
    ],
    "wof:name":"United Bank Of Ia",
    "wof:placetype":"venue"
},
  "geometry": {"coordinates":[-95.590864,42.06841],"type":"Point"}
}