{
  "type": "Feature",
  "properties": {
    "addr:full":"845 Jackson St Lamont IA 50650",
    "addr:housenumber":"845",
    "addr:postcode":"50650",
    "addr:street":"Jackson St",
    "iso:country":"US",
    "sg:address":"845 Jackson St",
    "sg:city":"Lamont",
    "sg:phone":"+1 563 924 2205",
    "sg:postcode":"50650",
    "sg:province":"IA",
    "sg:tags":[
        "farm",
        "corn",
        "soybean"
    ],
    "wof:name":"Stuart Seedorff",
    "wof:placetype":"venue"
},
  "geometry": {"coordinates":[-91.643193,42.602266],"type":"Point"}
}