{
  "type": "Feature",
  "properties": {
    "iso:country":"US",
    "sg:address":"1201 E Bell Ave",
    "sg:city":"Des Moines",
    "sg:classifiers":[
        {
            "category":"Real Estate",
            "subcategory":"Real Estate Agent",
            "type":"Services"
        },
        {
            "category":"Real Estate",
            "subcategory":"Real Estate Operator",
            "type":"Services"
        }
    ],
    "sg:phone":"+1 515 243 3344",
    "sg:postcode":"50315",
    "sg:province":"IA",
    "sg:tags":[
        "apartment"
    ],
    "wof:name":"Bell Avenue Apartments",
    "wof:placetype":"venue"
},
  "geometry": {"coordinates":[-93.599114,41.562548],"type":"Point"}
}