{
  "type": "Feature",
  "properties": {
    "addr:full":"204 Central Ave Fort Dodge IA 50501",
    "addr:housenumber":"204",
    "addr:postcode":"50501",
    "addr:street":"Central Ave",
    "iso:country":"US",
    "sg:address":"204 Central Ave",
    "sg:city":"Fort Dodge",
    "sg:classifiers":[
        {
            "category":"Professional",
            "subcategory":"Business Services",
            "type":"Services"
        }
    ],
    "sg:phone":"+1 515 573 4474",
    "sg:postcode":"50501",
    "sg:province":"IA",
    "sg:tags":[
        "telemarketing"
    ],
    "sg:website":"www.truckerschoice.com",
    "wof:name":"Truckers Choice Inc",
    "wof:placetype":"venue"
},
  "geometry": {"coordinates":[-94.19423399999999,42.504252],"type":"Point"}
}