{
  "type": "Feature",
  "properties": {
    "addr:full":"2281 630th St Newell IA 50568",
    "addr:housenumber":"2281",
    "addr:postcode":"50568",
    "addr:street":"630Th St",
    "iso:country":"US",
    "sg:address":"2281 630th St",
    "sg:city":"Newell",
    "sg:classifiers":[
        {
            "category":"Professional",
            "type":"Services"
        }
    ],
    "sg:phone":"+1 712 272 3411",
    "sg:postcode":"50568",
    "sg:province":"IA",
    "sg:tags":[
        "establishment"
    ],
    "wof:name":"Nutra Tech Nursery",
    "wof:placetype":"venue"
},
  "geometry": {"coordinates":[-94.95967,42.604098],"type":"Point"}
}