{
  "type": "Feature",
  "properties": {
    "addr:full":"119 1st Ave SE Cedar Rapids IA 52402",
    "addr:housenumber":"119",
    "addr:postcode":"52402",
    "addr:street":"1St Ave Se",
    "iso:country":"US",
    "sg:address":"119 1st Ave SE",
    "sg:city":"Cedar Rapids",
    "sg:classifiers":[
        {
            "category":"Professional",
            "subcategory":"Business Services",
            "type":"Services"
        }
    ],
    "sg:phone":"+1 319 398 5009",
    "sg:postcode":"52402",
    "sg:province":"IA",
    "sg:tags":[
        "information",
        "bureau",
        "convention"
    ],
    "wof:name":"Cedar Rapids Convention",
    "wof:placetype":"venue"
},
  "geometry": {"coordinates":[-91.668826,41.978546],"type":"Point"}
}