{
  "type": "Feature",
  "properties": {
    "addr:full":"3120 Kimball Ave Waterloo IA 50702",
    "addr:housenumber":"3120",
    "addr:postcode":"50702",
    "addr:street":"Kimball Ave",
    "iso:country":"US",
    "sg:address":"3120 Kimball Ave",
    "sg:city":"Waterloo",
    "sg:classifiers":[
        {
            "category":"Home & Garden",
            "subcategory":"Mobile Homes",
            "type":"Retail Goods"
        }
    ],
    "sg:phone":"+1 319 233 2390",
    "sg:postcode":"50702",
    "sg:province":"IA",
    "wof:name":"Hawkeye Mobile Homes",
    "wof:placetype":"venue"
},
  "geometry": {"coordinates":[-92.35691,42.467051],"type":"Point"}
}