{
  "type": "Feature",
  "properties": {
    "iso:country":"US",
    "sg:address":"324 N Main St",
    "sg:city":"Pocahontas",
    "sg:classifiers":[
        {
            "category":"Cinema",
            "subcategory":"Movie Theater",
            "type":"Entertainment"
        }
    ],
    "sg:phone":"+1 712 335 3434",
    "sg:postcode":"50574",
    "sg:province":"IA",
    "wof:name":"Rialto Theatre",
    "wof:placetype":"venue"
},
  "geometry": {"coordinates":[-94.668828,42.734535],"type":"Point"}
}