{
  "type": "Feature",
  "properties": {
    "iso:country":"US",
    "sg:address":"407 310th St",
    "sg:city":"Fenton",
    "sg:phone":"+1 515 925 3679",
    "sg:postcode":"50539",
    "sg:province":"IA",
    "sg:tags":[
        "farm",
        "grain",
        "cash"
    ],
    "wof:name":"D Krause Farm",
    "wof:placetype":"venue"
},
  "geometry": {"coordinates":[-94.37803099999999,43.212364],"type":"Point"}
}