{
  "type": "Feature",
  "properties": {
    "addr:full":"408 W Mission St Strawberry Point IA 52076",
    "addr:housenumber":"408",
    "addr:postcode":"52076",
    "addr:street":"W Mission St",
    "iso:country":"US",
    "sg:address":"408 W Mission St",
    "sg:city":"Strawberry Point",
    "sg:classifiers":[
        {
            "category":"Manufacturing",
            "subcategory":"Glass & Minerals",
            "type":"Manufacturing & Wholesale Goods"
        }
    ],
    "sg:phone":"+1 563 933 2321",
    "sg:postcode":"52076",
    "sg:province":"IA",
    "sg:tags":[
        "ready"
    ],
    "wof:name":"Bard Concrete",
    "wof:placetype":"venue"
},
  "geometry": {"coordinates":[-91.542697,42.684951],"type":"Point"}
}