{
  "type": "Feature",
  "properties": {
    "addr:full":"250 Mercy Dr Dubuque IA 52001",
    "addr:housenumber":"250",
    "addr:postcode":"52001",
    "addr:street":"Mercy Dr",
    "iso:country":"US",
    "sg:address":"250 Mercy Dr",
    "sg:city":"Dubuque",
    "sg:classifiers":[
        {
            "category":"Health Services",
            "subcategory":"Doctor",
            "type":"Services"
        }
    ],
    "sg:phone":"+1 563 589 9666",
    "sg:postcode":"52001",
    "sg:province":"IA",
    "sg:tags":[
        "physician",
        "surgeon"
    ],
    "wof:name":"Dubuque Emergency Physicians",
    "wof:placetype":"venue"
},
  "geometry": {"coordinates":[-90.67372,42.492995],"type":"Point"}
}