{
  "type": "Feature",
  "properties": {
    "addr:full":"4995 NW 6th Dr Des Moines IA 50313",
    "addr:housenumber":"4995",
    "addr:postcode":"50313",
    "addr:street":"Nw 6Th Dr",
    "iso:country":"US",
    "sg:address":"4995 NW 6th Dr",
    "sg:city":"Des Moines",
    "sg:classifiers":[
        {
            "category":"Retail",
            "subcategory":"Auto Repair",
            "type":"Services"
        }
    ],
    "sg:phone":"+1 515 280 7866",
    "sg:postcode":"50313",
    "sg:province":"IA",
    "sg:tags":[
        "body",
        "automobile",
        "painting"
    ],
    "wof:name":"Hall's Auto Body",
    "wof:placetype":"venue"
},
  "geometry": {"coordinates":[-93.627977,41.651743],"type":"Point"}
}