{
  "type": "Feature",
  "properties": {
    "iso:country":"US",
    "sg:address":"167 Jacolyn Dr NW",
    "sg:city":"Cedar Rapids",
    "sg:classifiers":[
        {
            "category":"Banks & Credit Unions",
            "subcategory":"Bank",
            "type":"Services"
        }
    ],
    "sg:phone":"+1 319 362 5900",
    "sg:postcode":"52405",
    "sg:province":"IA",
    "sg:tags":[
        "loan",
        "real estate"
    ],
    "wof:name":"Mc Afee Mortgage",
    "wof:placetype":"venue"
},
  "geometry": {"coordinates":[-91.732116,41.96995],"type":"Point"}
}