{
  "type": "Feature",
  "properties": {
    "iso:country":"US",
    "sg:address":"1136 E 9th St",
    "sg:city":"Muscatine",
    "sg:classifiers":[
        {
            "category":"Professional",
            "subcategory":"Business Services",
            "type":"Services"
        }
    ],
    "sg:phone":"+1 563 264 3147",
    "sg:postcode":"52761",
    "sg:province":"IA",
    "sg:tags":[
        "embroidery"
    ],
    "wof:name":"Phoenix Products",
    "wof:placetype":"venue"
},
  "geometry": {"coordinates":[-91.039379,41.433373],"type":"Point"}
}