{
  "type": "Feature",
  "properties": {
    "iso:country":"US",
    "sg:address":"2559 Hubbell Ave",
    "sg:city":"Des Moines",
    "sg:classifiers":[
        {
            "category":"Education",
            "subcategory":"Library",
            "type":"Public Place"
        }
    ],
    "sg:phone":"+1 515 283 4152",
    "sg:postcode":"50317",
    "sg:province":"IA",
    "wof:name":"Des Moines East Side Library",
    "wof:placetype":"venue"
},
  "geometry": {"coordinates":[-93.568016,41.61161],"type":"Point"}
}