{
  "type": "Feature",
  "properties": {
    "iso:country":"US",
    "sg:address":"403 S 1st St",
    "sg:city":"Winterset",
    "sg:classifiers":[
        {
            "category":"Food & Beverages",
            "subcategory":"Groceries & Convenience Stores",
            "type":"Retail Goods"
        }
    ],
    "sg:phone":"+1 515 462 4062",
    "sg:postcode":"50273",
    "sg:province":"IA",
    "wof:name":"Git-N-Go Convenience Store",
    "wof:placetype":"venue"
},
  "geometry": {"coordinates":[-94.013302,41.331718],"type":"Point"}
}