{
  "type": "Feature",
  "properties": {
    "addr:full":"2212 Merle Hay Rd Des Moines IA 50310",
    "addr:housenumber":"2212",
    "addr:postcode":"50310",
    "addr:street":"Merle Hay Rd Des",
    "iso:country":"US",
    "sg:address":"2212 Merle Hay Rd",
    "sg:city":"Des Moines",
    "sg:classifiers":[
        {
            "category":"Real Estate",
            "subcategory":"Real Estate Operator",
            "type":"Services"
        }
    ],
    "sg:phone":"+1 515 246 8016",
    "sg:postcode":"50310",
    "sg:province":"IA",
    "sg:tags":[
        "apartment"
    ],
    "wof:name":"Conlin Properties Inc",
    "wof:placetype":"venue"
},
  "geometry": {"coordinates":[-93.69782499999999,41.614754],"type":"Point"}
}