{
  "type": "Feature",
  "properties": {
    "iso:country":"US",
    "sg:address":"1805 Freedom St",
    "sg:city":"Osceola",
    "sg:phone":"+1 641 342 2984",
    "sg:postcode":"50213",
    "sg:province":"IA",
    "sg:tags":[
        "farm",
        "corn"
    ],
    "wof:name":"Charles Garrett Farm",
    "wof:placetype":"venue"
},
  "geometry": {"coordinates":[-93.864335,40.97019],"type":"Point"}
}