{
  "type": "Feature",
  "properties": {
    "addr:full":"1855 Bristol Dr Dubuque IA 52001",
    "addr:housenumber":"1855",
    "addr:postcode":"52001",
    "addr:street":"Bristol Dr",
    "iso:country":"US",
    "sg:address":"1855 Bristol Dr",
    "sg:city":"Dubuque",
    "sg:classifiers":[
        {
            "category":"Building & Trades",
            "subcategory":"Construction",
            "type":"Services"
        }
    ],
    "sg:phone":"+1 563 583 4783",
    "sg:postcode":"52001",
    "sg:province":"IA",
    "sg:tags":[
        "painter"
    ],
    "wof:name":"Grant Painting & Decorating",
    "wof:placetype":"venue"
},
  "geometry": {"coordinates":[-90.709372,42.501166],"type":"Point"}
}