{
  "type": "Feature",
  "properties": {
    "iso:country":"US",
    "sg:address":"855 Boone St",
    "sg:city":"Webster City",
    "sg:classifiers":[
        {
            "category":"Farming",
            "subcategory":"Farm & Veterinary Services",
            "type":"Manufacturing & Wholesale Goods"
        }
    ],
    "sg:phone":"+1 515 832 2385",
    "sg:postcode":"50595",
    "sg:province":"IA",
    "sg:tags":[
        "livestock"
    ],
    "wof:name":"Pruismann Trucking",
    "wof:placetype":"venue"
},
  "geometry": {"coordinates":[-93.82516800000001,42.463077],"type":"Point"}
}