{
  "type": "Feature",
  "properties": {
    "addr:full":"1795 58th St Garrison IA 52229",
    "addr:housenumber":"1795",
    "addr:postcode":"52229",
    "addr:street":"58Th St",
    "iso:country":"US",
    "sg:address":"1795 58th St",
    "sg:city":"Garrison",
    "sg:classifiers":[
        {
            "category":"Manufacturing",
            "subcategory":"Lumber",
            "type":"Manufacturing & Wholesale Goods"
        }
    ],
    "sg:phone":"+1 319 477 3845",
    "sg:postcode":"52229",
    "sg:province":"IA",
    "sg:tags":[
        "planing",
        "mills",
        "sawmill"
    ],
    "wof:name":"Becker Sawmill",
    "wof:placetype":"venue"
},
  "geometry": {"coordinates":[-92.152681,42.181025],"type":"Point"}
}