{
  "type": "Feature",
  "properties": {
    "addr:full":"1301 Main St Osage IA 50461",
    "addr:housenumber":"1301",
    "addr:postcode":"50461",
    "addr:street":"Main St",
    "iso:country":"US",
    "sg:address":"1301 Main St",
    "sg:city":"Osage",
    "sg:classifiers":[
        {
            "category":"Autos & Motor Vehicles",
            "subcategory":"Fuel & Gas Station",
            "type":"Retail Goods"
        }
    ],
    "sg:phone":"+1 641 732 5835",
    "sg:postcode":"50461",
    "sg:province":"IA",
    "sg:tags":[
        "oil"
    ],
    "wof:name":"Small's Service",
    "wof:placetype":"venue"
},
  "geometry": {"coordinates":[-92.80072199999999,43.284155],"type":"Point"}
}