{
  "type": "Feature",
  "properties": {
    "addr:full":"705 Perdock Ct Washington IA 52353",
    "addr:housenumber":"705",
    "addr:postcode":"52353",
    "addr:street":"Perdock Ct",
    "iso:country":"US",
    "sg:address":"705 Perdock Ct",
    "sg:city":"Washington",
    "sg:classifiers":[
        {
            "category":"Organizations",
            "subcategory":"Membership Organization",
            "type":"Services"
        }
    ],
    "sg:phone":"+1 319 653 2558",
    "sg:postcode":"52353",
    "sg:province":"IA",
    "wof:name":"Better Health Care For Iowians",
    "wof:placetype":"venue"
},
  "geometry": {"coordinates":[-91.68222900000001,41.29329],"type":"Point"}
}