{
  "type": "Feature",
  "properties": {
    "addr:full":"235 Collins Rd NE Cedar Rapids IA 52402",
    "addr:housenumber":"235",
    "addr:postcode":"52402",
    "addr:street":"Collins Rd Ne",
    "iso:country":"US",
    "sg:address":"235 Collins Rd NE",
    "sg:city":"Cedar Rapids",
    "sg:classifiers":[
        {
            "category":"Restaurant",
            "type":"Food & Drink"
        }
    ],
    "sg:menulink":"http://www.allmenus.com/ia/cedar-rapids/158476-arbys/menu/",
    "sg:phone":"+1 319 393 7447",
    "sg:postcode":"52402",
    "sg:province":"IA",
    "sg:tags":[
        "burger",
        "american"
    ],
    "wof:name":"Arby's",
    "wof:placetype":"venue"
},
  "geometry": {"coordinates":[-91.626383,42.027665],"type":"Point"}
}