{
  "type": "Feature",
  "properties": {
    "addr:full":"2850 Prairie du Chien Rd NE Iowa City IA 52240",
    "addr:housenumber":"2850",
    "addr:postcode":"52240",
    "addr:street":"Prairie Du Chien Rd Ne",
    "iso:country":"US",
    "sg:address":"2850 Prairie du Chien Rd NE",
    "sg:city":"Iowa City",
    "sg:classifiers":[
        {
            "category":"Travel",
            "subcategory":"Campground",
            "type":"Entertainment"
        }
    ],
    "sg:phone":"+1 319 338 3685",
    "sg:postcode":"52240",
    "sg:province":"IA",
    "wof:name":"United States Government",
    "wof:placetype":"venue"
},
  "geometry": {"coordinates":[-91.52222500000001,41.723781],"type":"Point"}
}