{
  "type": "Feature",
  "properties": {
    "addr:full":"1120 4th Ave Council Bluffs IA 51501",
    "addr:housenumber":"1120",
    "addr:postcode":"51501",
    "addr:street":"4Th Ave",
    "iso:country":"US",
    "sg:address":"1120 4th Ave",
    "sg:city":"Council Bluffs",
    "sg:classifiers":[
        {
            "category":"Building & Trades",
            "subcategory":"Construction",
            "type":"Services"
        }
    ],
    "sg:phone":"+1 712 323 6929",
    "sg:postcode":"51501",
    "sg:province":"IA",
    "sg:tags":[
        "concrete",
        "contractor"
    ],
    "wof:name":"Brad Nelson Carpenter",
    "wof:placetype":"venue"
},
  "geometry": {"coordinates":[-95.861536,41.257948],"type":"Point"}
}