{
  "type": "Feature",
  "properties": {
    "iso:country":"US",
    "sg:address":"3635 Iowa 9 St",
    "sg:city":"Rock Rapids",
    "sg:phone":"+1 712 472 3153",
    "sg:postcode":"51246",
    "sg:province":"IA",
    "sg:tags":[
        "farm",
        "corn",
        "cash",
        "crop",
        "field",
        "grain",
        "soybean"
    ],
    "wof:name":"Joseph Gacke",
    "wof:placetype":"venue"
},
  "geometry": {"coordinates":[-96.064836,43.432694],"type":"Point"}
}