{
  "type": "Feature",
  "properties": {
    "addr:full":"1212 Pleasant St Des Moines IA 50309",
    "addr:housenumber":"1212",
    "addr:postcode":"50309",
    "addr:street":"Pleasant St",
    "iso:country":"US",
    "sg:address":"1212 Pleasant St",
    "sg:city":"Des Moines",
    "sg:classifiers":[
        {
            "category":"Wholesale",
            "subcategory":"Chemicals & Plastics",
            "type":"Manufacturing & Wholesale Goods"
        }
    ],
    "sg:phone":"+1 515 241 4663",
    "sg:postcode":"50309",
    "sg:province":"IA",
    "sg:tags":[
        "oxygen"
    ],
    "wof:name":"Iowa Health Home Care-Intrust",
    "wof:placetype":"venue"
},
  "geometry": {"coordinates":[-93.63658100000001,41.589785],"type":"Point"}
}