{
  "type": "Feature",
  "properties": {
    "addr:full":"914 Ave G Fort Madison IA 52627",
    "addr:housenumber":"914",
    "addr:postcode":"52627",
    "addr:street":"Ave G",
    "iso:country":"US",
    "sg:address":"914 Ave G",
    "sg:city":"Fort Madison",
    "sg:classifiers":[
        {
            "category":"Health Services",
            "subcategory":"Optometrist",
            "type":"Services"
        }
    ],
    "sg:phone":"+1 319 372 5181",
    "sg:postcode":"52627",
    "sg:province":"IA",
    "wof:name":"Smith & Smith",
    "wof:placetype":"venue"
},
  "geometry": {"coordinates":[-91.31510900000001,40.630904],"type":"Point"}
}