{
  "type": "Feature",
  "properties": {
    "addr:full":"704 May St Marshalltown IA 50158",
    "addr:housenumber":"704",
    "addr:postcode":"50158",
    "addr:street":"May St",
    "iso:country":"US",
    "sg:address":"704 May St",
    "sg:city":"Marshalltown",
    "sg:classifiers":[
        {
            "category":"Social Services",
            "type":"Services"
        }
    ],
    "sg:phone":"+1 641 752 7159",
    "sg:postcode":"50158",
    "sg:province":"IA",
    "sg:tags":[
        "information",
        "planning",
        "center",
        "family"
    ],
    "wof:name":"Women's Health & Education Ctr",
    "wof:placetype":"venue"
},
  "geometry": {"coordinates":[-92.90127699999999,42.039494],"type":"Point"}
}