{
  "type": "Feature",
  "properties": {
    "addr:full":"1017 Dubuque St Sioux City IA 51105",
    "addr:housenumber":"1017",
    "addr:postcode":"51105",
    "addr:street":"Dubuque St",
    "iso:country":"US",
    "sg:address":"1017 Dubuque St",
    "sg:city":"Sioux City",
    "sg:classifiers":[
        {
            "category":"Retail",
            "subcategory":"Auto Repair",
            "type":"Services"
        }
    ],
    "sg:phone":"+1 712 279 9636",
    "sg:postcode":"51105",
    "sg:province":"IA",
    "sg:tags":[
        "automotive"
    ],
    "wof:name":"Rons Towing",
    "wof:placetype":"venue"
},
  "geometry": {"coordinates":[-96.376929,42.501586],"type":"Point"}
}