{
  "type": "Feature",
  "properties": {
    "iso:country":"US",
    "sg:address":"214 4th Ave NE",
    "sg:city":"Dyersville",
    "sg:classifiers":[
        {
            "category":"Wholesale",
            "subcategory":"Farm Supplies",
            "type":"Manufacturing & Wholesale Goods"
        }
    ],
    "sg:phone":"+1 563 875 2711",
    "sg:postcode":"52040",
    "sg:province":"IA",
    "sg:tags":[
        "fertilizer"
    ],
    "wof:name":"Crop Production Svc Inc",
    "wof:placetype":"venue"
},
  "geometry": {"coordinates":[-91.121709,42.487397],"type":"Point"}
}