{
  "type": "Feature",
  "properties": {
    "addr:full":"2035 John F Kennedy Rd  Dubuque IA 52002",
    "addr:housenumber":"2035",
    "addr:postcode":"52002",
    "addr:street":"John F Kennedy Rd",
    "iso:country":"US",
    "sg:address":"2035 John F Kennedy Rd ",
    "sg:city":"Dubuque",
    "sg:classifiers":[
        {
            "category":"Restaurant",
            "type":"Food & Drink"
        }
    ],
    "sg:menulink":"http://www.allmenus.com/ia/dubuque/291847-bandanas-bbq/menu/",
    "sg:phone":"+1 563 556 5525",
    "sg:postcode":"52002",
    "sg:province":"IA",
    "sg:tags":[
        "barbecue"
    ],
    "wof:name":"Bandana's BBQ",
    "wof:placetype":"venue"
},
  "geometry": {"coordinates":[-90.720615,42.506649],"type":"Point"}
}