{
  "type": "Feature",
  "properties": {
    "iso:country":"US",
    "sg:address":"1628 S 20th St",
    "sg:city":"Centerville",
    "sg:classifiers":[
        {
            "category":"Manufacturing",
            "subcategory":"Tools & Machinery",
            "type":"Manufacturing & Wholesale Goods"
        }
    ],
    "sg:phone":"+1 641 856 8288",
    "sg:postcode":"52544",
    "sg:province":"IA",
    "sg:tags":[
        "machine",
        "shop"
    ],
    "sg:website":"www.candcmachining.net",
    "wof:name":"C & C Machining",
    "wof:placetype":"venue"
},
  "geometry": {"coordinates":[-92.86534,40.718813],"type":"Point"}
}