{
  "type": "Feature",
  "properties": {
    "iso:country":"US",
    "sg:address":"1075 State Hwy 4",
    "sg:city":"Bagley",
    "sg:classifiers":[
        {
            "category":"Shopping",
            "subcategory":"Bicycles & Sporting Goods",
            "type":"Retail Goods"
        }
    ],
    "sg:phone":"+1 641 427 5795",
    "sg:postcode":"50026",
    "sg:province":"IA",
    "wof:name":"Breakaway Bike Shop",
    "wof:placetype":"venue"
},
  "geometry": {"coordinates":[-94.367272,41.852563],"type":"Point"}
}