{
  "type": "Feature",
  "properties": {
    "addr:full":"701 11th St De Witt IA 52742",
    "addr:housenumber":"701",
    "addr:postcode":"52742",
    "addr:street":"11Th St",
    "iso:country":"US",
    "sg:address":"701 11th St",
    "sg:city":"De Witt",
    "sg:classifiers":[
        {
            "category":"Building & Trades",
            "subcategory":"Construction",
            "type":"Services"
        }
    ],
    "sg:phone":"+1 563 659 5230",
    "sg:postcode":"52742",
    "sg:province":"IA",
    "sg:tags":[
        "hanging",
        "contractor"
    ],
    "wof:name":"Keefe Painting",
    "wof:placetype":"venue"
},
  "geometry": {"coordinates":[-90.540466,41.826185],"type":"Point"}
}