{
  "type": "Feature",
  "properties": {
    "addr:full":"2801 Bell Ave Des Moines IA 50321",
    "addr:housenumber":"2801",
    "addr:postcode":"50321",
    "addr:street":"Bell Ave",
    "iso:country":"US",
    "sg:address":"2801 Bell Ave",
    "sg:city":"Des Moines",
    "sg:classifiers":[
        {
            "category":"Professional",
            "subcategory":"Detective & Security Services",
            "type":"Services"
        }
    ],
    "sg:phone":"+1 515 245 4370",
    "sg:postcode":"50321",
    "sg:province":"IA",
    "sg:tags":[
        "guard",
        "patrol"
    ],
    "sg:website":"www.marsden.com",
    "wof:name":"American Security Corp",
    "wof:placetype":"venue"
},
  "geometry": {"coordinates":[-93.651422,41.562798],"type":"Point"}
}