{
  "type": "Feature",
  "properties": {
    "addr:full":"4700 4th St SW Mason City IA 50401",
    "addr:housenumber":"4700",
    "addr:postcode":"50401",
    "addr:street":"4Th St Sw",
    "iso:country":"US",
    "sg:address":"4700 4th St SW",
    "sg:city":"Mason City",
    "sg:classifiers":[
        {
            "category":"Education",
            "subcategory":"Special Training",
            "type":"Public Place"
        }
    ],
    "sg:phone":"+1 641 422 9929",
    "sg:postcode":"50401",
    "sg:province":"IA",
    "sg:tags":[
        "tutoring"
    ],
    "wof:name":"Sylvan Learning Ctr",
    "wof:placetype":"venue"
},
  "geometry": {"coordinates":[-93.267628,43.148529],"type":"Point"}
}