{
  "type": "Feature",
  "properties": {
    "iso:country":"US",
    "sg:address":"215 Main St",
    "sg:city":"Ames",
    "sg:classifiers":[
        {
            "category":"Shopping",
            "subcategory":"Shoes",
            "type":"Retail Goods"
        }
    ],
    "sg:phone":"+1 515 232 3473",
    "sg:postcode":"50010",
    "sg:province":"IA",
    "wof:name":"Emerhoff's Footwear",
    "wof:placetype":"venue"
},
  "geometry": {"coordinates":[-93.613544,42.025201],"type":"Point"}
}