{
  "type": "Feature",
  "properties": {
    "addr:full":"10340 Military Rd Dubuque IA 52003",
    "addr:housenumber":"10340",
    "addr:postcode":"52003",
    "addr:street":"Military Rd",
    "iso:country":"US",
    "sg:address":"10340 Military Rd",
    "sg:city":"Dubuque",
    "sg:classifiers":[
        {
            "category":"Manufacturing",
            "subcategory":"Chemicals & Compounds",
            "type":"Manufacturing & Wholesale Goods"
        }
    ],
    "sg:phone":"+1 563 556 4114",
    "sg:postcode":"52003",
    "sg:province":"IA",
    "sg:tags":[
        "biological",
        "product"
    ],
    "wof:name":"Serum Technologies",
    "wof:placetype":"venue"
},
  "geometry": {"coordinates":[-90.689539,42.445386],"type":"Point"}
}