{
  "type": "Feature",
  "properties": {
    "addr:full":"220 E Coolbaugh St Red Oak IA 51566",
    "addr:housenumber":"220",
    "addr:postcode":"51566",
    "addr:street":"E Coolbaugh St",
    "iso:country":"US",
    "sg:address":"220 E Coolbaugh St",
    "sg:city":"Red Oak",
    "sg:classifiers":[
        {
            "category":"Professional",
            "subcategory":"Advertising",
            "type":"Services"
        }
    ],
    "sg:phone":"+1 712 623 2100",
    "sg:postcode":"51566",
    "sg:province":"IA",
    "wof:name":"Red Oak Concepts",
    "wof:placetype":"venue"
},
  "geometry": {"coordinates":[-95.23383,41.008844],"type":"Point"}
}