{
  "type": "Feature",
  "properties": {
    "addr:full":"9360 Feeney Rd Dubuque IA 52003",
    "addr:postcode":"9360;52003",
    "addr:street":"Feeney Rd",
    "iso:country":"US",
    "sg:address":"9360 Feeney Rd",
    "sg:city":"Dubuque",
    "sg:classifiers":[
        {
            "category":"Restaurant",
            "type":"Food & Drink"
        }
    ],
    "sg:phone":"+1 563 556 6759",
    "sg:postcode":"52003",
    "sg:province":"IA",
    "wof:name":"Sky Line",
    "wof:placetype":"venue"
},
  "geometry": {"coordinates":[-90.670436,42.382152],"type":"Point"}
}