{
  "type": "Feature",
  "properties": {
    "addr:full":"266 Blairs Ferry Rd NE Cedar Rapids IA 52402",
    "addr:housenumber":"266",
    "addr:postcode":"52402",
    "addr:street":"Blairs Ferry Rd Ne",
    "iso:country":"US",
    "sg:address":"266 Blairs Ferry Rd NE",
    "sg:city":"Cedar Rapids",
    "sg:classifiers":[
        {
            "category":"Health Services",
            "subcategory":"Health Practitioner",
            "type":"Services"
        }
    ],
    "sg:phone":"+1 319 396 0222",
    "sg:postcode":"52402",
    "sg:province":"IA",
    "sg:tags":[
        "therapy",
        "physical"
    ],
    "sg:website":"www.myphysio.com",
    "wof:name":"Physiotherapy Associates",
    "wof:placetype":"venue"
},
  "geometry": {"coordinates":[-91.637097,42.0347],"type":"Point"}
}