{
  "type": "Feature",
  "properties": {
    "iso:country":"US",
    "sg:address":"104 N Main St",
    "sg:city":"New Providence",
    "sg:classifiers":[
        {
            "category":"Social Services",
            "type":"Services"
        }
    ],
    "sg:phone":"+1 641 497 5398",
    "sg:postcode":"50206",
    "sg:province":"IA",
    "wof:name":"New Providence Roundhouse",
    "wof:placetype":"venue"
},
  "geometry": {"coordinates":[-93.171665,42.283678],"type":"Point"}
}