{
  "type": "Feature",
  "properties": {
    "addr:full":"444 E State St Tiffin IA 52361",
    "addr:housenumber":"444",
    "addr:postcode":"52361",
    "addr:street":"E State St",
    "iso:country":"US",
    "sg:address":"444 E State St",
    "sg:city":"Tiffin",
    "sg:classifiers":[
        {
            "category":"Banks & Credit Unions",
            "subcategory":"Bank",
            "type":"Services"
        }
    ],
    "sg:phone":"+1 319 545 2226",
    "sg:postcode":"52361",
    "sg:province":"IA",
    "wof:name":"Solon State Bank",
    "wof:placetype":"venue"
},
  "geometry": {"coordinates":[-92.00206300000001,41.66167],"type":"Point"}
}