{
  "type": "Feature",
  "properties": {
    "iso:country":"US",
    "sg:address":"205 N Washington St",
    "sg:city":"Bloomfield",
    "sg:classifiers":[
        {
            "category":"Education",
            "subcategory":"Dance Studio",
            "type":"Public Place"
        }
    ],
    "sg:phone":"+1 641 664 2166",
    "sg:postcode":"52537",
    "sg:province":"IA",
    "sg:tags":[
        "instruction",
        "dancing"
    ],
    "wof:name":"Dancin' School Of Dance",
    "wof:placetype":"venue"
},
  "geometry": {"coordinates":[-92.413732,40.753647],"type":"Point"}
}