{
  "type": "Feature",
  "properties": {
    "iso:country":"US",
    "sg:address":"1838 Central Ave",
    "sg:city":"Dubuque",
    "sg:classifiers":[
        {
            "category":"Shopping",
            "subcategory":"Crafts & Fabrics",
            "type":"Retail Goods"
        }
    ],
    "sg:phone":"+1 563 588 2652",
    "sg:postcode":"52001",
    "sg:province":"IA",
    "sg:tags":[
        "shop",
        "sewing",
        "machines-household"
    ],
    "wof:name":"And Sew On",
    "wof:placetype":"venue"
},
  "geometry": {"coordinates":[-90.669251,42.50995],"type":"Point"}
}