{
  "type": "Feature",
  "properties": {
    "iso:country":"US",
    "sg:address":"205 S Main St",
    "sg:city":"Elkader",
    "sg:classifiers":[
        {
            "category":"Government",
            "subcategory":"Court House",
            "type":"Public Place"
        }
    ],
    "sg:phone":"+1 563 245 2490",
    "sg:postcode":"52043",
    "sg:province":"IA",
    "sg:tags":[
        "county",
        "counsel"
    ],
    "wof:name":"Clayton County Asst Attorney",
    "wof:placetype":"venue"
},
  "geometry": {"coordinates":[-91.40360099999999,42.853839],"type":"Point"}
}