{
  "type": "Feature",
  "properties": {
    "iso:country":"US",
    "sg:address":"111 E 3rd St",
    "sg:city":"Davenport",
    "sg:classifiers":[
        {
            "category":"Professional",
            "subcategory":"Lawyer & Legal Services",
            "type":"Services"
        }
    ],
    "sg:phone":"+1 563 326 4491",
    "sg:postcode":"52801",
    "sg:province":"IA",
    "sg:tags":[
        "attorney"
    ],
    "sg:website":"www.bettylawfirm.com",
    "wof:name":"Betty Neuman & Mc Mahon",
    "wof:placetype":"venue"
},
  "geometry": {"coordinates":[-90.572723,41.522343],"type":"Point"}
}