{
  "type": "Feature",
  "properties": {
    "iso:country":"US",
    "sg:address":"4515 20th Ave SW",
    "sg:city":"Cedar Rapids",
    "sg:classifiers":[
        {
            "category":"Professional",
            "subcategory":"Business Services",
            "type":"Services"
        }
    ],
    "sg:phone":"+1 319 390 8900",
    "sg:postcode":"52404",
    "sg:province":"IA",
    "sg:tags":[
        "telemarketing"
    ],
    "sg:website":"www.accdir.com",
    "wof:name":"Access Direct Telemarketing",
    "wof:placetype":"venue"
},
  "geometry": {"coordinates":[-91.727869,41.960129],"type":"Point"}
}