{
  "type": "Feature",
  "properties": {
    "iso:country":"US",
    "sg:address":"215 5th St",
    "sg:city":"West Des Moines",
    "sg:classifiers":[
        {
            "category":"Shopping",
            "subcategory":"Stationery & Office Supplies",
            "type":"Retail Goods"
        }
    ],
    "sg:phone":"+1 515 277 5719",
    "sg:postcode":"50265",
    "sg:province":"IA",
    "sg:tags":[
        "rubber",
        "stamp",
        "plastic"
    ],
    "wof:name":"Outstamping Designs Inc",
    "wof:placetype":"venue"
},
  "geometry": {"coordinates":[-93.708814,41.572302],"type":"Point"}
}