{
  "type": "Feature",
  "properties": {
    "iso:country":"US",
    "sg:address":"121 W Locust St",
    "sg:city":"Davenport",
    "sg:classifiers":[
        {
            "category":"Health Services",
            "subcategory":"Doctor",
            "type":"Services"
        }
    ],
    "sg:phone":"+1 563 326 3603",
    "sg:postcode":"52803",
    "sg:province":"IA",
    "sg:tags":[
        "physician",
        "surgeon"
    ],
    "wof:name":"Truce T Ordona PC",
    "wof:placetype":"venue"
},
  "geometry": {"coordinates":[-90.574366,41.538188],"type":"Point"}
}