{
  "type": "Feature",
  "properties": {
    "iso:country":"US",
    "sg:address":"1110 Albany Pl SE",
    "sg:city":"Orange City",
    "sg:classifiers":[
        {
            "category":"Home & Garden",
            "subcategory":"Building Materials",
            "type":"Retail Goods"
        }
    ],
    "sg:phone":"+1 712 737 8880",
    "sg:postcode":"51041",
    "sg:province":"IA",
    "sg:tags":[
        "paint"
    ],
    "sg:website":"www.vogeltraffic.com",
    "wof:name":"Diamond Vogel Paint Inc",
    "wof:placetype":"venue"
},
  "geometry": {"coordinates":[-96.056978,42.994238],"type":"Point"}
}