{
  "type": "Feature",
  "properties": {
    "iso:country":"US",
    "sg:address":"110 Weare St",
    "sg:city":"Woodbine",
    "sg:classifiers":[
        {
            "category":"Shopping",
            "subcategory":"Gifts & Souvenirs",
            "type":"Retail Goods"
        }
    ],
    "sg:phone":"+1 712 647 2661",
    "sg:postcode":"51579",
    "sg:province":"IA",
    "wof:name":"Gifts N More",
    "wof:placetype":"venue"
},
  "geometry": {"coordinates":[-95.70644799999999,41.733862],"type":"Point"}
}