{
  "type": "Feature",
  "properties": {
    "addr:full":"936 Dogwood Rd Portsmouth IA 51565",
    "addr:housenumber":"936",
    "addr:postcode":"51565",
    "addr:street":"Dogwood Rd",
    "iso:country":"US",
    "sg:address":"936 Dogwood Rd",
    "sg:city":"Portsmouth",
    "sg:phone":"+1 712 743 5873",
    "sg:postcode":"51565",
    "sg:province":"IA",
    "sg:tags":[
        "farm",
        "corn",
        "beef",
        "feedlot",
        "cattle"
    ],
    "wof:name":"Jack Wendt",
    "wof:placetype":"venue"
},
  "geometry": {"coordinates":[-95.49955300000001,41.631686],"type":"Point"}
}