{
  "type": "Feature",
  "properties": {
    "iso:country":"US",
    "sg:address":"2400 1st Ave",
    "sg:city":"Coralville",
    "sg:classifiers":[
        {
            "category":"Utilities",
            "subcategory":"Telephone",
            "type":"Services"
        }
    ],
    "sg:phone":"+1 319 358 2442",
    "sg:postcode":"52241",
    "sg:province":"IA",
    "sg:tags":[
        "communications",
        "radiotelephone",
        "communication"
    ],
    "wof:name":"Excel Communications",
    "wof:placetype":"venue"
},
  "geometry": {"coordinates":[-91.563327,41.696903],"type":"Point"}
}