{
  "type": "Feature",
  "properties": {
    "addr:full":"136 5th St West Des Moines IA 50265",
    "addr:housenumber":"136",
    "addr:postcode":"50265",
    "addr:street":"5Th St",
    "iso:country":"US",
    "sg:address":"136 5th St",
    "sg:city":"West Des Moines",
    "sg:classifiers":[
        {
            "category":"Shopping",
            "subcategory":"Gifts & Souvenirs",
            "type":"Retail Goods"
        }
    ],
    "sg:phone":"+1 515 279 9590",
    "sg:postcode":"50265",
    "sg:province":"IA",
    "sg:tags":[
        "shop"
    ],
    "wof:name":"A Touch Of Italy",
    "wof:placetype":"venue"
},
  "geometry": {"coordinates":[-93.70896500000001,41.569594],"type":"Point"}
}