{
  "type": "Feature",
  "properties": {
    "iso:country":"US",
    "sg:address":"114 State Hwy 44",
    "sg:city":"Portsmouth",
    "sg:classifiers":[
        {
            "category":"Farming",
            "subcategory":"Farm",
            "type":"Manufacturing & Wholesale Goods"
        }
    ],
    "sg:phone":"+1 712 743 2691",
    "sg:postcode":"51565",
    "sg:province":"IA",
    "wof:name":"Martens Farm LTD",
    "wof:placetype":"venue"
},
  "geometry": {"coordinates":[-95.555513,41.645882],"type":"Point"}
}