{
  "type": "Feature",
  "properties": {
    "iso:country":"US",
    "sg:address":"519 Grove St",
    "sg:city":"Central City",
    "sg:classifiers":[
        {
            "category":"Building & Trades",
            "subcategory":"Cleaning & Sanitation",
            "type":"Services"
        }
    ],
    "sg:phone":"+1 319 936 1800",
    "sg:postcode":"52214",
    "sg:province":"IA",
    "sg:tags":[
        "janitor"
    ],
    "wof:name":"American Dream Carpet Care",
    "wof:placetype":"venue"
},
  "geometry": {"coordinates":[-91.52315400000001,42.207207],"type":"Point"}
}