{
  "type": "Feature",
  "properties": {
    "iso:country":"US",
    "sg:address":"57 Wilson Blvd",
    "sg:city":"Fairfield",
    "sg:classifiers":[
        {
            "category":"Professional",
            "subcategory":"Advertising",
            "type":"Services"
        }
    ],
    "sg:phone":"+1 641 469 5010",
    "sg:postcode":"52556",
    "sg:province":"IA",
    "sg:tags":[
        "counselor"
    ],
    "wof:name":"Koepell Direct",
    "wof:placetype":"venue"
},
  "geometry": {"coordinates":[-91.958499,40.997531],"type":"Point"}
}