{
  "type": "Feature",
  "properties": {
    "addr:full":"1277 5th St SW Dyersville IA 52040",
    "addr:housenumber":"1277",
    "addr:postcode":"52040",
    "addr:street":"5Th St Sw",
    "iso:country":"US",
    "sg:address":"1277 5th St SW",
    "sg:city":"Dyersville",
    "sg:classifiers":[
        {
            "category":"Retail",
            "subcategory":"Repair Shop",
            "type":"Services"
        }
    ],
    "sg:phone":"+1 563 875 7044",
    "sg:postcode":"52040",
    "sg:province":"IA",
    "sg:tags":[
        "farm",
        "equipment",
        "parts"
    ],
    "wof:name":"Rahe's Machinery Repair",
    "wof:placetype":"venue"
},
  "geometry": {"coordinates":[-91.13251099999999,42.47386],"type":"Point"}
}