{
  "type": "Feature",
  "properties": {
    "iso:country":"US",
    "sg:address":"10479 Timothy St",
    "sg:city":"Dubuque",
    "sg:classifiers":[
        {
            "category":"Building & Trades",
            "subcategory":"Construction",
            "type":"Services"
        }
    ],
    "sg:phone":"+1 563 556 4284",
    "sg:postcode":"52003",
    "sg:province":"IA",
    "sg:tags":[
        "house"
    ],
    "wof:name":"Benchmark Construction",
    "wof:placetype":"venue"
},
  "geometry": {"coordinates":[-90.683125,42.444482],"type":"Point"}
}