{
  "type": "Feature",
  "properties": {
    "addr:full":"23586 Centerville Rd La Motte IA 52054",
    "addr:housenumber":"23586",
    "addr:postcode":"52054",
    "addr:street":"Centerville Rd",
    "iso:country":"US",
    "sg:address":"23586 Centerville Rd",
    "sg:city":"La Motte",
    "sg:classifiers":[
        {
            "category":"Farming",
            "subcategory":"Farm",
            "type":"Manufacturing & Wholesale Goods"
        }
    ],
    "sg:phone":"+1 563 773 8889",
    "sg:postcode":"52054",
    "sg:province":"IA",
    "wof:name":"Eagle Ridge Of Iowa",
    "wof:placetype":"venue"
},
  "geometry": {"coordinates":[-90.62045500000001,42.34721],"type":"Point"}
}