{
  "type": "Feature",
  "properties": {
    "addr:full":"206 Center St Des Moines IA 50309",
    "addr:housenumber":"206",
    "addr:postcode":"50309",
    "addr:street":"Center St",
    "iso:country":"US",
    "sg:address":"206 Center St",
    "sg:city":"Des Moines",
    "sg:classifiers":[
        {
            "category":"Organizations",
            "subcategory":"Professional Association",
            "type":"Services"
        }
    ],
    "sg:phone":"+1 515 471 8040",
    "sg:postcode":"50309",
    "sg:province":"IA",
    "wof:name":"Des Moines Education Assn",
    "wof:placetype":"venue"
},
  "geometry": {"coordinates":[-93.621437,41.591491],"type":"Point"}
}