{
  "type": "Feature",
  "properties": {
    "addr:full":"324 W Agency Rd West Burlington IA 52655",
    "addr:housenumber":"324",
    "addr:postcode":"52655",
    "addr:street":"W Agency Rd",
    "iso:country":"US",
    "sg:address":"324 W Agency Rd",
    "sg:city":"West Burlington",
    "sg:classifiers":[
        {
            "category":"Shopping",
            "subcategory":"Department Store",
            "type":"Retail Goods"
        }
    ],
    "sg:phone":"+1 319 753 5648",
    "sg:postcode":"52655",
    "sg:province":"IA",
    "wof:name":"Wal-Mart Supercenter",
    "wof:placetype":"venue"
},
  "geometry": {"coordinates":[-91.159177,40.813047],"type":"Point"}
}