{
  "type": "Feature",
  "properties": {
    "addr:full":"2823 Hickory Hill St Dubuque IA 52001",
    "addr:housenumber":"2823",
    "addr:postcode":"52001",
    "addr:street":"Hickory Hill St",
    "iso:country":"US",
    "sg:address":"2823 Hickory Hill St",
    "sg:city":"Dubuque",
    "sg:classifiers":[
        {
            "category":"Professional",
            "subcategory":"Management & Consulting",
            "type":"Services"
        }
    ],
    "sg:phone":"+1 563 583 5865",
    "sg:postcode":"52001",
    "sg:province":"IA",
    "sg:tags":[
        "business"
    ],
    "wof:name":"Brotherton Consulting",
    "wof:placetype":"venue"
},
  "geometry": {"coordinates":[-90.711556,42.518768],"type":"Point"}
}