{
  "type": "Feature",
  "properties": {
    "iso:country":"US",
    "sg:address":"111 N 7th St",
    "sg:city":"Sac City",
    "sg:classifiers":[
        {
            "category":"Farming",
            "subcategory":"Farm",
            "type":"Manufacturing & Wholesale Goods"
        }
    ],
    "sg:phone":"+1 712 662 7376",
    "sg:postcode":"50583",
    "sg:province":"IA",
    "sg:tags":[
        "crop",
        "general"
    ],
    "wof:name":"Christian Wilmer Inc",
    "wof:placetype":"venue"
},
  "geometry": {"coordinates":[-94.991934,42.422944],"type":"Point"}
}