{
  "type": "Feature",
  "properties": {
    "iso:country":"US",
    "sg:address":"1045 N Grand Ave",
    "sg:city":"Mt Pleasant",
    "sg:classifiers":[
        {
            "category":"Shopping",
            "subcategory":"Department Store",
            "type":"Retail Goods"
        }
    ],
    "sg:phone":"+1 319 385 4600",
    "sg:postcode":"52641",
    "sg:province":"IA",
    "sg:website":"www.walmart.com",
    "wof:name":"Wal-Mart",
    "wof:placetype":"venue"
},
  "geometry": {"coordinates":[-91.540272,40.981362],"type":"Point"}
}