{
  "type": "Feature",
  "properties": {
    "iso:country":"US",
    "sg:address":"103 S 2nd Ave",
    "sg:city":"Marshalltown",
    "sg:classifiers":[
        {
            "category":"Personal",
            "subcategory":"Beauty Salon",
            "type":"Services"
        }
    ],
    "sg:phone":"+1 641 752 3655",
    "sg:postcode":"50158",
    "sg:province":"IA",
    "wof:name":"Free Style",
    "wof:placetype":"venue"
},
  "geometry": {"coordinates":[-92.909711,42.047897],"type":"Point"}
}