{
  "type": "Feature",
  "properties": {
    "iso:country":"US",
    "sg:address":"817 15th St SE",
    "sg:city":"Cedar Rapids",
    "sg:classifiers":[
        {
            "category":"Personal",
            "type":"Services"
        }
    ],
    "sg:phone":"+1 319 981 8011",
    "sg:postcode":"52403",
    "sg:province":"IA",
    "sg:tags":[
        "towing"
    ],
    "sg:website":"www.AffordableTowingIA.com",
    "wof:name":"Affordable Towing",
    "wof:placetype":"venue"
},
  "geometry": {"coordinates":[-91.650885,41.978922],"type":"Point"}
}