{
  "type": "Feature",
  "properties": {
    "addr:full":"445 8th Ave SW Britt IA 50423",
    "addr:housenumber":"445",
    "addr:postcode":"50423",
    "addr:street":"8Th Ave Sw",
    "iso:country":"US",
    "sg:address":"445 8th Ave SW",
    "sg:city":"Britt",
    "sg:classifiers":[
        {
            "category":"Health Services",
            "subcategory":"Nursing And Care Facility",
            "type":"Services"
        }
    ],
    "sg:phone":"+1 641 843 3835",
    "sg:postcode":"50423",
    "sg:province":"IA",
    "sg:tags":[
        "home",
        "convalescent"
    ],
    "wof:name":"Westview Care Ctr",
    "wof:placetype":"venue"
},
  "geometry": {"coordinates":[-93.811964,43.092902],"type":"Point"}
}