{
  "type": "Feature",
  "properties": {
    "iso:country":"US",
    "sg:address":"2007 1200th St",
    "sg:city":"Harlan",
    "sg:classifiers":[
        {
            "category":"Farming",
            "subcategory":"Livestock Farm",
            "type":"Manufacturing & Wholesale Goods"
        }
    ],
    "sg:phone":"+1 712 799 4261",
    "sg:postcode":"51537",
    "sg:province":"IA",
    "sg:tags":[
        "beef",
        "feedlot",
        "cattle"
    ],
    "wof:name":"Lyle Behrens",
    "wof:placetype":"venue"
},
  "geometry": {"coordinates":[-95.187727,41.674318],"type":"Point"}
}