{
  "type": "Feature",
  "properties": {
    "addr:full":"1324 180th St Clemons IA 50051",
    "addr:housenumber":"1324",
    "addr:postcode":"50051",
    "addr:street":"180Th St",
    "iso:country":"US",
    "sg:address":"1324 180th St",
    "sg:city":"Clemons",
    "sg:classifiers":[
        {
            "category":"Retail",
            "subcategory":"Repair Shop",
            "type":"Services"
        }
    ],
    "sg:phone":"+1 641 477 8303",
    "sg:postcode":"50051",
    "sg:province":"IA",
    "sg:tags":[
        "repairing",
        "lawn",
        "mower"
    ],
    "wof:name":"Warner's Repair Shop",
    "wof:placetype":"venue"
},
  "geometry": {"coordinates":[-93.158365,42.092061],"type":"Point"}
}