{
  "type": "Feature",
  "properties": {
    "iso:country":"US",
    "sg:address":"1529 State Hwy 86",
    "sg:city":"Spirit Lake",
    "sg:classifiers":[
        {
            "category":"Building & Trades",
            "subcategory":"Construction",
            "type":"Services"
        }
    ],
    "sg:phone":"+1 712 336 2619",
    "sg:postcode":"51360",
    "sg:province":"IA",
    "sg:tags":[
        "general",
        "contractor"
    ],
    "wof:name":"Berg Construction & Landscpg",
    "wof:placetype":"venue"
},
  "geometry": {"coordinates":[-95.182771,43.425789],"type":"Point"}
}