{
  "type": "Feature",
  "properties": {
    "iso:country":"US",
    "sg:address":"2346 Mormon Trek Blvd",
    "sg:city":"Iowa City",
    "sg:classifiers":[
        {
            "category":"Banks & Credit Unions",
            "subcategory":"Bank",
            "type":"Services"
        }
    ],
    "sg:phone":"+1 319 358 6882",
    "sg:postcode":"52246",
    "sg:province":"IA",
    "sg:tags":[
        "loan",
        "real estate"
    ],
    "wof:name":"Countrywide Home Loans",
    "wof:placetype":"venue"
},
  "geometry": {"coordinates":[-91.567319,41.637056],"type":"Point"}
}