{
  "type": "Feature",
  "properties": {
    "iso:country":"US",
    "sg:address":"550 N 2nd Ave W",
    "sg:city":"Newton",
    "sg:classifiers":[
        {
            "category":"Government",
            "subcategory":"Office",
            "type":"Public Place"
        }
    ],
    "sg:phone":"+1 641 792 6433",
    "sg:postcode":"50208",
    "sg:province":"IA",
    "wof:name":"Jasper County Extension Svc",
    "wof:placetype":"venue"
},
  "geometry": {"coordinates":[-93.059231,41.700512],"type":"Point"}
}