{
  "type": "Feature",
  "properties": {
    "addr:full":"2930 E University Ave Des Moines IA 50317",
    "addr:housenumber":"2930",
    "addr:postcode":"50317",
    "addr:street":"E University Ave",
    "iso:country":"US",
    "sg:address":"2930 E University Ave",
    "sg:city":"Des Moines",
    "sg:classifiers":[
        {
            "category":"Shopping",
            "subcategory":"Pharmacy",
            "type":"Retail Goods"
        }
    ],
    "sg:phone":"+1 515 299 5171",
    "sg:postcode":"50317",
    "sg:province":"IA",
    "sg:website":"www.walgreens.com",
    "wof:name":"Walgreens",
    "wof:placetype":"venue"
},
  "geometry": {"coordinates":[-93.560266,41.600591],"type":"Point"}
}