{
  "type": "Feature",
  "properties": {
    "addr:full":"421 W Water St Decorah IA 52101",
    "addr:housenumber":"421",
    "addr:postcode":"52101",
    "addr:street":"W Water St",
    "iso:country":"US",
    "sg:address":"421 W Water St",
    "sg:city":"Decorah",
    "sg:classifiers":[
        {
            "category":"Professional",
            "subcategory":"Accounting & Tax Preparation",
            "type":"Services"
        }
    ],
    "sg:phone":"+1 563 382 8995",
    "sg:postcode":"52101",
    "sg:province":"IA",
    "sg:tags":[
        "accountant"
    ],
    "wof:name":"Magnuson Consulting Fincl Svcs",
    "wof:placetype":"venue"
},
  "geometry": {"coordinates":[-91.79070400000001,43.304076],"type":"Point"}
}