{
  "type": "Feature",
  "properties": {
    "addr:full":"5305 University Ave Cedar Falls IA 50613",
    "addr:housenumber":"5305",
    "addr:postcode":"50613",
    "addr:street":"University Ave",
    "iso:country":"US",
    "sg:address":"5305 University Ave",
    "sg:city":"Cedar Falls",
    "sg:classifiers":[
        {
            "category":"Retail",
            "subcategory":"Veterinary Services",
            "type":"Services"
        }
    ],
    "sg:phone":"+1 319 268 0129",
    "sg:postcode":"50613",
    "sg:province":"IA",
    "sg:tags":[
        "veterinarian"
    ],
    "wof:name":"Cedar Heights Pet Clinic",
    "wof:placetype":"venue"
},
  "geometry": {"coordinates":[-92.4241,42.51155],"type":"Point"}
}