{
  "type": "Feature",
  "properties": {
    "iso:country":"US",
    "sg:address":"2519 S Federal Ave",
    "sg:city":"Mason City",
    "sg:classifiers":[
        {
            "category":"Wholesale",
            "subcategory":"Stationery",
            "type":"Manufacturing & Wholesale Goods"
        }
    ],
    "sg:phone":"+1 641 423 1833",
    "sg:postcode":"50401",
    "sg:province":"IA",
    "sg:tags":[
        "product",
        "paper"
    ],
    "wof:name":"Hewett Wholesale Inc",
    "wof:placetype":"venue"
},
  "geometry": {"coordinates":[-93.201042,43.127914],"type":"Point"}
}