{
  "type": "Feature",
  "properties": {
    "iso:country":"US",
    "sg:address":"20521 Larpenteur Memorial Rd",
    "sg:city":"Onawa",
    "sg:classifiers":[
        {
            "category":"Wholesale",
            "subcategory":"Machinery & Supplies",
            "type":"Manufacturing & Wholesale Goods"
        }
    ],
    "sg:phone":"+1 712 353 6388",
    "sg:postcode":"51040",
    "sg:province":"IA",
    "sg:tags":[
        "farm",
        "equipment",
        "power",
        "mfg"
    ],
    "wof:name":"Fox Implement Co",
    "wof:placetype":"venue"
},
  "geometry": {"coordinates":[-95.98483299999999,42.063616],"type":"Point"}
}