{
  "type": "Feature",
  "properties": {
    "iso:country":"US",
    "sg:address":"201 3rd St SE",
    "sg:city":"Cedar Rapids",
    "sg:classifiers":[
        {
            "category":"Manufacturing",
            "subcategory":"Printing",
            "type":"Manufacturing & Wholesale Goods"
        }
    ],
    "sg:phone":"+1 319 366 1100",
    "sg:postcode":"52401",
    "sg:province":"IA",
    "sg:tags":[
        "miscellaneous",
        "publishing"
    ],
    "wof:name":"Info Amer Phone Bks Inc Mich",
    "wof:placetype":"venue"
},
  "geometry": {"coordinates":[-91.66581600000001,41.977663],"type":"Point"}
}