{
  "type": "Feature",
  "properties": {
    "iso:country":"US",
    "sg:address":"1000 5th Ave",
    "sg:city":"Charles City",
    "sg:classifiers":[
        {
            "category":"Retail",
            "subcategory":"Auto Repair",
            "type":"Services"
        }
    ],
    "sg:phone":"+1 641 228 3088",
    "sg:postcode":"50616",
    "sg:province":"IA",
    "sg:tags":[
        "body",
        "automobile",
        "painting"
    ],
    "wof:name":"Huffman Auto Body Inc",
    "wof:placetype":"venue"
},
  "geometry": {"coordinates":[-92.658226,43.067357],"type":"Point"}
}