{
  "type": "Feature",
  "properties": {
    "iso:country":"US",
    "sg:address":"1802 18th Ave",
    "sg:city":"Rock Valley",
    "sg:classifiers":[
        {
            "category":"Shopping",
            "type":"Retail Goods"
        }
    ],
    "sg:phone":"+1 712 476 2358",
    "sg:postcode":"51247",
    "sg:province":"IA",
    "sg:tags":[
        "art",
        "gallery",
        "dealer"
    ],
    "wof:name":"Den Boer Art & Nelva",
    "wof:placetype":"venue"
},
  "geometry": {"coordinates":[-96.291223,43.209202],"type":"Point"}
}