{
  "type": "Feature",
  "properties": {
    "iso:country":"US",
    "sg:address":"208 35th Street Dr SE",
    "sg:city":"Cedar Rapids",
    "sg:classifiers":[
        {
            "category":"Professional",
            "subcategory":"Management & Consulting",
            "type":"Services"
        }
    ],
    "sg:phone":"+1 319 363 6105",
    "sg:postcode":"52403",
    "sg:province":"IA",
    "sg:tags":[
        "fuel"
    ],
    "wof:name":"Senior Housing Management",
    "wof:placetype":"venue"
},
  "geometry": {"coordinates":[-91.628624,42.013399],"type":"Point"}
}