{
  "type": "Feature",
  "properties": {
    "addr:full":"403 2nd Ave NE Rockford IA 50468",
    "addr:housenumber":"403",
    "addr:postcode":"50468",
    "addr:street":"2Nd Ave Ne",
    "iso:country":"US",
    "sg:address":"403 2nd Ave NE",
    "sg:city":"Rockford",
    "sg:classifiers":[
        {
            "category":"Building & Trades",
            "subcategory":"Construction",
            "type":"Services"
        }
    ],
    "sg:phone":"+1 641 756 3644",
    "sg:postcode":"50468",
    "sg:province":"IA",
    "sg:tags":[
        "marking",
        "maintenance",
        "parking"
    ],
    "wof:name":"Rockford Public Works Dept",
    "wof:placetype":"venue"
},
  "geometry": {"coordinates":[-92.944084,43.054411],"type":"Point"}
}