{
  "type": "Feature",
  "properties": {
    "iso:country":"US",
    "sg:address":"2690 Mineral St",
    "sg:city":"Dubuque",
    "sg:classifiers":[
        {
            "category":"Insurance",
            "subcategory":"Insurance Agent",
            "type":"Services"
        }
    ],
    "sg:phone":"+1 563 588 0028",
    "sg:postcode":"52001",
    "sg:province":"IA",
    "wof:name":"Hennagir & Eggers Insurance",
    "wof:placetype":"venue"
},
  "geometry": {"coordinates":[-90.702538,42.494648],"type":"Point"}
}