{
  "type": "Feature",
  "properties": {
    "iso:country":"US",
    "sg:address":"4800 Asbury Rd",
    "sg:city":"Dubuque",
    "sg:classifiers":[
        {
            "category":"Personal",
            "subcategory":"Shoe Repair & Shine",
            "type":"Services"
        }
    ],
    "sg:phone":"+1 563 583 2199",
    "sg:postcode":"52002",
    "sg:province":"IA",
    "sg:tags":[
        "repairing",
        "boot"
    ],
    "wof:name":"Hy-Vee Food Stores",
    "wof:placetype":"venue"
},
  "geometry": {"coordinates":[-90.746988,42.514976],"type":"Point"}
}