{
  "type": "Feature",
  "properties": {
    "iso:country":"US",
    "sg:address":"316 225th St",
    "sg:city":"Scranton",
    "sg:phone":"+1 712 652 3443",
    "sg:postcode":"51462",
    "sg:province":"IA",
    "sg:tags":[
        "farm",
        "corn",
        "soybean"
    ],
    "wof:name":"Harry Wampler",
    "wof:placetype":"venue"
},
  "geometry": {"coordinates":[-94.587332,42.030082],"type":"Point"}
}