{
  "type": "Feature",
  "properties": {
    "addr:full":"4227 State St Bettendorf IA 52722",
    "addr:housenumber":"4227",
    "addr:postcode":"52722",
    "addr:street":"State St",
    "iso:country":"US",
    "sg:address":"4227 State St",
    "sg:city":"Bettendorf",
    "sg:classifiers":[
        {
            "category":"Professional",
            "subcategory":"Business Services",
            "type":"Services"
        }
    ],
    "sg:phone":"+1 563 359 8666",
    "sg:postcode":"52722",
    "sg:province":"IA",
    "wof:name":"Mw Group Inc",
    "wof:placetype":"venue"
},
  "geometry": {"coordinates":[-90.47539399999999,41.532435],"type":"Point"}
}