{
  "type": "Feature",
  "properties": {
    "iso:country":"US",
    "sg:address":"4875 Merle Hay Rd",
    "sg:city":"Des Moines",
    "sg:classifiers":[
        {
            "category":"Local Transit",
            "type":"Transportation"
        }
    ],
    "sg:phone":"+1 515 280 7948",
    "sg:postcode":"50322",
    "sg:province":"IA",
    "sg:tags":[
        "limousine"
    ],
    "wof:name":"Classic Limo",
    "wof:placetype":"venue"
},
  "geometry": {"coordinates":[-93.697622,41.647107],"type":"Point"}
}