{
  "type": "Feature",
  "properties": {
    "iso:country":"US",
    "sg:address":"406 2nd St",
    "sg:city":"Gladbrook",
    "sg:classifiers":[
        {
            "category":"Shopping",
            "subcategory":"Gifts & Souvenirs",
            "type":"Retail Goods"
        }
    ],
    "sg:phone":"+1 641 473 2264",
    "sg:postcode":"50635",
    "sg:province":"IA",
    "sg:tags":[
        "shop"
    ],
    "wof:name":"Lucy's Tole",
    "wof:placetype":"venue"
},
  "geometry": {"coordinates":[-92.715149,42.18762],"type":"Point"}
}