{
  "type": "Feature",
  "properties": {
    "iso:country":"US",
    "sg:address":"1000 27th Ave SW",
    "sg:city":"Cedar Rapids",
    "sg:classifiers":[
        {
            "category":"Shopping",
            "subcategory":"Mobile Phones",
            "type":"Retail Goods"
        }
    ],
    "sg:phone":"+1 319 364 1814",
    "sg:postcode":"52404",
    "sg:province":"IA",
    "wof:name":"Skytel",
    "wof:placetype":"venue"
},
  "geometry": {"coordinates":[-91.683369,41.951302],"type":"Point"}
}