{
  "type": "Feature",
  "properties": {
    "iso:country":"US",
    "sg:address":"625 W 3rd St",
    "sg:city":"Garner",
    "sg:classifiers":[
        {
            "category":"Autos & Motor Vehicles",
            "subcategory":"Auto Supplies",
            "type":"Retail Goods"
        }
    ],
    "sg:phone":"+1 641 923 3653",
    "sg:postcode":"50438",
    "sg:province":"IA",
    "sg:tags":[
        "automobile",
        "parts"
    ],
    "wof:name":"Arnold Motor Supply",
    "wof:placetype":"venue"
},
  "geometry": {"coordinates":[-93.610924,43.102292],"type":"Point"}
}