{
  "type": "Feature",
  "properties": {
    "addr:full":"3414 L Ave Adel IA 50003",
    "addr:housenumber":"3414",
    "addr:postcode":"50003",
    "addr:street":"L Ave",
    "iso:country":"US",
    "sg:address":"3414 L Ave",
    "sg:city":"Adel",
    "sg:classifiers":[
        {
            "category":"Organizations",
            "subcategory":"Religious Organization",
            "type":"Services"
        }
    ],
    "sg:phone":"+1 515 834 2527",
    "sg:postcode":"50003",
    "sg:province":"IA",
    "wof:name":"Peace Lutheran Church",
    "wof:placetype":"venue"
},
  "geometry": {"coordinates":[-94.079711,41.543037],"type":"Point"}
}