{
  "type": "Feature",
  "properties": {
    "iso:country":"US",
    "sg:address":"3200 16th Ave SW Ste H",
    "sg:city":"Cedar Rapids",
    "sg:classifiers":[
        {
            "category":"Personal",
            "subcategory":"Tanning Parlor",
            "type":"Services"
        }
    ],
    "sg:phone":"+1 319 363 6581",
    "sg:postcode":"52404",
    "sg:province":"IA",
    "wof:name":"Tan World of Cedar Rapids",
    "wof:placetype":"venue"
},
  "geometry": {"coordinates":[-91.71416000000001,41.96359],"type":"Point"}
}