{
  "type": "Feature",
  "properties": {
    "addr:full":"1601 Monroe St Emmetsburg IA 50536",
    "addr:housenumber":"1601",
    "addr:postcode":"50536",
    "addr:street":"Monroe St",
    "iso:country":"US",
    "sg:address":"1601 Monroe St",
    "sg:city":"Emmetsburg",
    "sg:classifiers":[
        {
            "category":"Retail",
            "subcategory":"Repair Shop",
            "type":"Services"
        }
    ],
    "sg:phone":"+1 712 852 2078",
    "sg:postcode":"50536",
    "sg:province":"IA",
    "sg:tags":[
        "tractor"
    ],
    "wof:name":"Randy's Repair",
    "wof:placetype":"venue"
},
  "geometry": {"coordinates":[-94.673851,43.105599],"type":"Point"}
}