{
  "type": "Feature",
  "properties": {
    "addr:full":"600 36th St SE Cedar Rapids IA 52403",
    "addr:housenumber":"600",
    "addr:postcode":"52403",
    "addr:street":"36Th St Se",
    "iso:country":"US",
    "sg:address":"600 36th St SE",
    "sg:city":"Cedar Rapids",
    "sg:classifiers":[
        {
            "category":"Social Services",
            "subcategory":"Child Care",
            "type":"Services"
        },
        {
            "category":"Education",
            "subcategory":"School",
            "type":"Public Place"
        }
    ],
    "sg:phone":"+1 319 398 5942",
    "sg:postcode":"52403",
    "sg:province":"IA",
    "sg:tags":[
        "high",
        "middle",
        "day",
        "elementary"
    ],
    "wof:name":"Waypoint",
    "wof:placetype":"venue"
},
  "geometry": {"coordinates":[-91.616203,41.9795],"type":"Point"}
}