{
  "type": "Feature",
  "properties": {
    "iso:country":"US",
    "sg:address":"412 E Grove St",
    "sg:city":"Lawler",
    "sg:classifiers":[
        {
            "category":"Education",
            "subcategory":"Library",
            "type":"Public Place"
        }
    ],
    "sg:phone":"+1 563 238 2191",
    "sg:postcode":"52154",
    "sg:province":"IA",
    "wof:name":"Lawler Public Library",
    "wof:placetype":"venue"
},
  "geometry": {"coordinates":[-92.150662,43.069491],"type":"Point"}
}