{
  "type": "Feature",
  "properties": {
    "addr:full":"120 E 2nd St Muscatine IA 52761",
    "addr:housenumber":"120",
    "addr:postcode":"52761",
    "addr:street":"E 2Nd St",
    "iso:country":"US",
    "sg:address":"120 E 2nd St",
    "sg:city":"Muscatine",
    "sg:classifiers":[
        {
            "category":"Home & Garden",
            "subcategory":"Building Materials",
            "type":"Retail Goods"
        }
    ],
    "sg:phone":"+1 563 263 3041",
    "sg:postcode":"52761",
    "sg:province":"IA",
    "sg:tags":[
        "paint"
    ],
    "wof:name":"Sherwin-Williams Paints",
    "wof:placetype":"venue"
},
  "geometry": {"coordinates":[-91.044736,41.42173],"type":"Point"}
}