{
  "type": "Feature",
  "properties": {
    "addr:full":"2929 Sunnyside Ave Burlington IA 52601",
    "addr:housenumber":"2929",
    "addr:postcode":"52601",
    "addr:street":"Sunnyside Ave",
    "iso:country":"US",
    "sg:address":"2929 Sunnyside Ave",
    "sg:city":"Burlington",
    "sg:classifiers":[
        {
            "category":"Home & Garden",
            "subcategory":"Furniture",
            "type":"Retail Goods"
        }
    ],
    "sg:phone":"+1 319 753 2131",
    "sg:postcode":"52601",
    "sg:province":"IA",
    "sg:tags":[
        "equipment",
        "kitchen",
        "cabinet"
    ],
    "wof:name":"Kitchen Solvers",
    "wof:placetype":"venue"
},
  "geometry": {"coordinates":[-91.136449,40.833659],"type":"Point"}
}