{
  "type": "Feature",
  "properties": {
    "iso:country":"US",
    "sg:address":"319 E 2nd St",
    "sg:city":"Muscatine",
    "sg:classifiers":[
        {
            "category":"Professional",
            "subcategory":"Lawyer & Legal Services",
            "type":"Services"
        }
    ],
    "sg:phone":"+1 563 264 8926",
    "sg:postcode":"52761",
    "sg:province":"IA",
    "sg:tags":[
        "attorney"
    ],
    "wof:name":"Goedken & Creasey",
    "wof:placetype":"venue"
},
  "geometry": {"coordinates":[-91.0427,41.423041],"type":"Point"}
}