{
  "type": "Feature",
  "properties": {
    "iso:country":"US",
    "sg:address":"19980 300th St",
    "sg:city":"Long Grove",
    "sg:classifiers":[
        {
            "category":"Farming",
            "subcategory":"Livestock Farm",
            "type":"Manufacturing & Wholesale Goods"
        }
    ],
    "sg:phone":"+1 563 285 8177",
    "sg:postcode":"52756",
    "sg:province":"IA",
    "sg:tags":[
        "beef",
        "feedlot",
        "cattle"
    ],
    "wof:name":"Dennis Claussen",
    "wof:placetype":"venue"
},
  "geometry": {"coordinates":[-90.511616,41.742508],"type":"Point"}
}