{
  "type": "Feature",
  "properties": {
    "iso:country":"US",
    "sg:address":"322 W 7th St",
    "sg:city":"Sioux City",
    "sg:classifiers":[
        {
            "category":"Building & Trades",
            "subcategory":"Plumbing",
            "type":"Services"
        }
    ],
    "sg:phone":"+1 712 258 3388",
    "sg:postcode":"51103",
    "sg:province":"IA",
    "sg:tags":[
        "plumbing",
        "contractor"
    ],
    "wof:name":"Foulk Bros Plumbing & Heating",
    "wof:placetype":"venue"
},
  "geometry": {"coordinates":[-96.412065,42.500035],"type":"Point"}
}