{
  "type": "Feature",
  "properties": {
    "addr:full":"9609 Elm Rd Arlington IA 50606",
    "addr:housenumber":"9609",
    "addr:postcode":"50606",
    "addr:street":"Elm Rd",
    "iso:country":"US",
    "sg:address":"9609 Elm Rd",
    "sg:city":"Arlington",
    "sg:classifiers":[
        {
            "category":"Farming",
            "subcategory":"Farm",
            "type":"Manufacturing & Wholesale Goods"
        }
    ],
    "sg:phone":"+1 563 633 6795",
    "sg:postcode":"50606",
    "sg:province":"IA",
    "sg:tags":[
        "crop",
        "general"
    ],
    "wof:name":"John M Fedeler",
    "wof:placetype":"venue"
},
  "geometry": {"coordinates":[-91.70309399999999,42.770086],"type":"Point"}
}