{
  "type": "Feature",
  "properties": {
    "iso:country":"US",
    "sg:address":"301 Closz Dr",
    "sg:city":"Webster City",
    "sg:classifiers":[
        {
            "category":"Autos & Motor Vehicles",
            "subcategory":"Recreational Vehicle Sales",
            "type":"Retail Goods"
        }
    ],
    "sg:phone":"+1 515 832 5715",
    "sg:postcode":"50595",
    "sg:province":"IA",
    "wof:name":"Webster City RV",
    "wof:placetype":"venue"
},
  "geometry": {"coordinates":[-93.812331,42.445291],"type":"Point"}
}