{
  "type": "Feature",
  "properties": {
    "iso:country":"US",
    "sg:address":"2801 Grand Ave",
    "sg:city":"Ames",
    "sg:classifiers":[
        {
            "category":"Shopping",
            "subcategory":"Department Store",
            "type":"Retail Goods"
        }
    ],
    "sg:phone":"+1 515 233 0669",
    "sg:postcode":"50010",
    "sg:province":"IA",
    "wof:name":"Eddie Bauer",
    "wof:placetype":"venue"
},
  "geometry": {"coordinates":[-93.620651,42.049403],"type":"Point"}
}