{
  "type": "Feature",
  "properties": {
    "addr:full":"2206 6th St Harlan IA 51537",
    "addr:housenumber":"2206",
    "addr:postcode":"51537",
    "addr:street":"6Th St",
    "iso:country":"US",
    "sg:address":"2206 6th St",
    "sg:city":"Harlan",
    "sg:classifiers":[
        {
            "category":"Home & Garden",
            "subcategory":"Building Materials",
            "type":"Retail Goods"
        }
    ],
    "sg:phone":"+1 712 755 5722",
    "sg:postcode":"51537",
    "sg:province":"IA",
    "sg:tags":[
        "mixed",
        "concrete"
    ],
    "wof:name":"Stowe Red-E-Mix",
    "wof:placetype":"venue"
},
  "geometry": {"coordinates":[-95.317476,41.647738],"type":"Point"}
}