{
  "type": "Feature",
  "properties": {
    "iso:country":"US",
    "sg:address":"930 W 3rd St",
    "sg:city":"Waterloo",
    "sg:classifiers":[
        {
            "category":"Social Services",
            "subcategory":"Child Care",
            "type":"Services"
        }
    ],
    "sg:phone":"+1 319 233 2500",
    "sg:postcode":"50701",
    "sg:province":"IA",
    "wof:name":"Little Blessings Day Care",
    "wof:placetype":"venue"
},
  "geometry": {"coordinates":[-92.35010800000001,42.490193],"type":"Point"}
}