{
  "type": "Feature",
  "properties": {
    "addr:full":"814 Byron Ave Waterloo IA 50702",
    "addr:housenumber":"814",
    "addr:postcode":"50702",
    "addr:street":"Byron Ave",
    "iso:country":"US",
    "sg:address":"814 Byron Ave",
    "sg:city":"Waterloo",
    "sg:classifiers":[
        {
            "category":"Building & Trades",
            "subcategory":"Construction",
            "type":"Services"
        }
    ],
    "sg:phone":"+1 319 233 6901",
    "sg:postcode":"50702",
    "sg:province":"IA",
    "sg:tags":[
        "house"
    ],
    "wof:name":"Langs Home Maint & Repr",
    "wof:placetype":"venue"
},
  "geometry": {"coordinates":[-92.345815,42.480222],"type":"Point"}
}