{
  "type": "Feature",
  "properties": {
    "iso:country":"US",
    "sg:address":"17700 US Hwy 52",
    "sg:city":"Durango",
    "sg:classifiers":[
        {
            "category":"Wholesale",
            "subcategory":"Wine & Distilled Alcoholic Beverages",
            "type":"Manufacturing & Wholesale Goods"
        }
    ],
    "sg:phone":"+1 563 552 1200",
    "sg:postcode":"52039",
    "sg:province":"IA",
    "wof:name":"Stone Cliff Winery",
    "wof:placetype":"venue"
},
  "geometry": {"coordinates":[-90.82620300000001,42.578313],"type":"Point"}
}