{
  "type": "Feature",
  "properties": {
    "addr:full":"404 Dodge St Keosauqua IA 52565",
    "addr:housenumber":"404",
    "addr:postcode":"52565",
    "addr:street":"Dodge St",
    "iso:country":"US",
    "sg:address":"404 Dodge St",
    "sg:city":"Keosauqua",
    "sg:classifiers":[
        {
            "category":"Government",
            "subcategory":"Office",
            "type":"Public Place"
        }
    ],
    "sg:phone":"+1 319 293 3865",
    "sg:postcode":"52565",
    "sg:province":"IA",
    "sg:tags":[
        "state",
        "program"
    ],
    "wof:name":"Transportation Dept",
    "wof:placetype":"venue"
},
  "geometry": {"coordinates":[-91.96396300000001,40.733198],"type":"Point"}
}