{
  "type": "Feature",
  "properties": {
    "addr:full":"885 275th St West Branch IA 52358",
    "addr:housenumber":"885",
    "addr:postcode":"52358",
    "addr:street":"275Th St",
    "iso:country":"US",
    "sg:address":"885 275th St",
    "sg:city":"West Branch",
    "sg:classifiers":[
        {
            "category":"Building & Trades",
            "subcategory":"Construction",
            "type":"Services"
        }
    ],
    "sg:phone":"+1 319 643 5565",
    "sg:postcode":"52358",
    "sg:province":"IA",
    "sg:tags":[
        "contractor"
    ],
    "wof:name":"Maxson Masonry",
    "wof:placetype":"venue"
},
  "geometry": {"coordinates":[-91.20939799999999,41.692212],"type":"Point"}
}