{
  "type": "Feature",
  "properties": {
    "iso:country":"US",
    "sg:address":"308 State St",
    "sg:city":"Tama",
    "sg:classifiers":[
        {
            "category":"Retail",
            "subcategory":"Auto Repair",
            "type":"Services"
        }
    ],
    "sg:phone":"+1 641 484 3703",
    "sg:postcode":"52339",
    "sg:province":"IA",
    "sg:tags":[
        "general"
    ],
    "wof:name":"Murtys Repair",
    "wof:placetype":"venue"
},
  "geometry": {"coordinates":[-92.576702,41.962366],"type":"Point"}
}