{
  "type": "Feature",
  "properties": {
    "iso:country":"US",
    "sg:address":"2608 S 24th St",
    "sg:city":"Council Bluffs",
    "sg:classifiers":[
        {
            "category":"Freight",
            "type":"Transportation"
        }
    ],
    "sg:phone":"+1 712 328 8779",
    "sg:postcode":"51501",
    "sg:province":"IA",
    "sg:tags":[
        "hauling",
        "trucking"
    ],
    "wof:name":"Truckers Express Inc",
    "wof:placetype":"venue"
},
  "geometry": {"coordinates":[-95.879211,41.23812],"type":"Point"}
}