{
  "type": "Feature",
  "properties": {
    "addr:full":"115 S Central Ave Burlington IA 52601",
    "addr:housenumber":"115",
    "addr:postcode":"52601",
    "addr:street":"S Central Ave",
    "iso:country":"US",
    "sg:address":"115 S Central Ave",
    "sg:city":"Burlington",
    "sg:classifiers":[
        {
            "category":"Organizations",
            "subcategory":"Religious Organization",
            "type":"Services"
        }
    ],
    "sg:phone":"+1 319 752 2946",
    "sg:postcode":"52601",
    "sg:province":"IA",
    "sg:tags":[
        "church"
    ],
    "wof:name":"Trinity Lutheran Church",
    "wof:placetype":"venue"
},
  "geometry": {"coordinates":[-91.112493,40.808966],"type":"Point"}
}