{
  "type": "Feature",
  "properties": {
    "iso:country":"US",
    "sg:address":"4969 Q Ave",
    "sg:city":"Morning Sun",
    "sg:classifiers":[
        {
            "category":"Retail",
            "subcategory":"Auto Repair",
            "type":"Services"
        }
    ],
    "sg:phone":"+1 319 868 4262",
    "sg:postcode":"52640",
    "sg:province":"IA",
    "sg:tags":[
        "general"
    ],
    "wof:name":"C&C Auto Crushing",
    "wof:placetype":"venue"
},
  "geometry": {"coordinates":[-91.31307200000001,41.132772],"type":"Point"}
}