{
  "type": "Feature",
  "properties": {
    "addr:full":"43406 250th St Ute IA 51060",
    "addr:housenumber":"43406",
    "addr:postcode":"51060",
    "addr:street":"250Th St",
    "iso:country":"US",
    "sg:address":"43406 250th St",
    "sg:city":"Ute",
    "sg:classifiers":[
        {
            "category":"Farming",
            "subcategory":"Farm",
            "type":"Manufacturing & Wholesale Goods"
        }
    ],
    "sg:phone":"+1 712 885 3379",
    "sg:postcode":"51060",
    "sg:province":"IA",
    "sg:tags":[
        "crop",
        "general"
    ],
    "wof:name":"Glen Hanson",
    "wof:placetype":"venue"
},
  "geometry": {"coordinates":[-95.699071,41.99388],"type":"Point"}
}