{
  "type": "Feature",
  "properties": {
    "iso:country":"US",
    "sg:address":"63 5th St NW",
    "sg:city":"Sioux Center",
    "sg:classifiers":[
        {
            "category":"Autos & Motor Vehicles",
            "subcategory":"Auto Supplies",
            "type":"Retail Goods"
        }
    ],
    "sg:phone":"+1 712 722 3468",
    "sg:postcode":"51250",
    "sg:province":"IA",
    "sg:tags":[
        "tire"
    ],
    "wof:name":"Central Tire Shop",
    "wof:placetype":"venue"
},
  "geometry": {"coordinates":[-96.1763,43.081955],"type":"Point"}
}