{
  "type": "Feature",
  "properties": {
    "addr:full":"2310 Jersey Ridge Rd Davenport IA 52803",
    "addr:housenumber":"2310",
    "addr:postcode":"52803",
    "addr:street":"Jersey Ridge Rd",
    "iso:country":"US",
    "sg:address":"2310 Jersey Ridge Rd",
    "sg:city":"Davenport",
    "sg:classifiers":[
        {
            "category":"Insurance",
            "subcategory":"Insurance Agent",
            "type":"Services"
        }
    ],
    "sg:phone":"+1 563 359 0353",
    "sg:postcode":"52803",
    "sg:province":"IA",
    "sg:website":"www.marsh.com",
    "wof:name":"Marsh",
    "wof:placetype":"venue"
},
  "geometry": {"coordinates":[-90.541882,41.543623],"type":"Point"}
}