{
  "type": "Feature",
  "properties": {
    "iso:country":"US",
    "sg:address":"629 12th Ave SE",
    "sg:city":"Cedar Rapids",
    "sg:classifiers":[
        {
            "category":"Retail",
            "subcategory":"Auto Repair",
            "type":"Services"
        }
    ],
    "sg:phone":"+1 319 362 1306",
    "sg:postcode":"52401",
    "sg:province":"IA",
    "sg:tags":[
        "repairing",
        "automobile"
    ],
    "wof:name":"Village Auto Repair",
    "wof:placetype":"venue"
},
  "geometry": {"coordinates":[-91.653927,41.972508],"type":"Point"}
}