{
  "type": "Feature",
  "properties": {
    "iso:country":"US",
    "sg:address":"1877 110th St",
    "sg:city":"Hazleton",
    "sg:classifiers":[
        {
            "category":"Building & Trades",
            "subcategory":"Construction",
            "type":"Services"
        }
    ],
    "sg:phone":"+1 319 636 3742",
    "sg:postcode":"50641",
    "sg:province":"IA",
    "sg:tags":[
        "contractor"
    ],
    "wof:name":"F S Stuctures Of Iowa",
    "wof:placetype":"venue"
},
  "geometry": {"coordinates":[-91.914502,42.628392],"type":"Point"}
}