{
  "type": "Feature",
  "properties": {
    "addr:full":"310 Antique City Dr Walnut IA 51577",
    "addr:housenumber":"310",
    "addr:postcode":"51577",
    "addr:street":"Antique City Dr",
    "iso:country":"US",
    "sg:address":"310 Antique City Dr",
    "sg:city":"Walnut",
    "sg:classifiers":[
        {
            "category":"Shopping",
            "subcategory":"Used Merchandise",
            "type":"Retail Goods"
        }
    ],
    "sg:phone":"+1 712 784 2277",
    "sg:postcode":"51577",
    "sg:province":"IA",
    "sg:tags":[
        "antique"
    ],
    "wof:name":"Don's Antiques",
    "wof:placetype":"venue"
},
  "geometry": {"coordinates":[-95.222194,41.478193],"type":"Point"}
}