{
  "type": "Feature",
  "properties": {
    "iso:country":"US",
    "sg:address":"32902 620th Ave",
    "sg:city":"Maxwell",
    "sg:classifiers":[
        {
            "category":"Professional",
            "type":"Services"
        }
    ],
    "sg:phone":"+1 515 387 8990",
    "sg:postcode":"50161",
    "sg:province":"IA",
    "sg:tags":[
        "establishment"
    ],
    "wof:name":"Testroet Kids",
    "wof:placetype":"venue"
},
  "geometry": {"coordinates":[-93.46345100000001,41.877679],"type":"Point"}
}