{
  "type": "Feature",
  "properties": {
    "iso:country":"US",
    "sg:address":"120 N 16th St",
    "sg:city":"Clarinda",
    "sg:classifiers":[
        {
            "category":"Insurance",
            "subcategory":"Insurance Agent",
            "type":"Services"
        }
    ],
    "sg:phone":"+1 712 542 4975",
    "sg:postcode":"51632",
    "sg:province":"IA",
    "wof:name":"Merlin R Hicks Insurance",
    "wof:placetype":"venue"
},
  "geometry": {"coordinates":[-95.03791699999999,40.739161],"type":"Point"}
}