{
  "type": "Feature",
  "properties": {
    "iso:country":"US",
    "sg:address":"2711 130th St",
    "sg:city":"Bagley",
    "sg:classifiers":[
        {
            "category":"Farming",
            "subcategory":"Farm",
            "type":"Manufacturing & Wholesale Goods"
        }
    ],
    "sg:phone":"+1 641 427 5258",
    "sg:postcode":"50026",
    "sg:province":"IA",
    "sg:tags":[
        "crop",
        "general"
    ],
    "wof:name":"Vangundy Farms",
    "wof:placetype":"venue"
},
  "geometry": {"coordinates":[-94.41387,41.820315],"type":"Point"}
}