{
  "type": "Feature",
  "properties": {
    "iso:country":"US",
    "sg:address":"7177 Hickman Rd",
    "sg:city":"Urbandale",
    "sg:classifiers":[
        {
            "category":"Social Services",
            "type":"Services"
        }
    ],
    "sg:phone":"+1 515 251 4900",
    "sg:postcode":"50322",
    "sg:province":"IA",
    "sg:tags":[
        "counselor",
        "marriage",
        "family"
    ],
    "wof:name":"Lutheran Family Svc Of Iowa",
    "wof:placetype":"venue"
},
  "geometry": {"coordinates":[-93.713993,41.614599],"type":"Point"}
}