{
  "type": "Feature",
  "properties": {
    "addr:full":"3919 Jefferson St Sioux City IA 51108",
    "addr:housenumber":"3919",
    "addr:postcode":"51108",
    "addr:street":"Jefferson St",
    "iso:country":"US",
    "sg:address":"3919 Jefferson St",
    "sg:city":"Sioux City",
    "sg:classifiers":[
        {
            "category":"Social Services",
            "subcategory":"Child Care",
            "type":"Services"
        }
    ],
    "sg:phone":"+1 712 239 9061",
    "sg:postcode":"51108",
    "sg:province":"IA",
    "wof:name":"B B's Preschool & Child Care",
    "wof:placetype":"venue"
},
  "geometry": {"coordinates":[-96.36778700000001,42.536865],"type":"Point"}
}