{
  "type": "Feature",
  "properties": {
    "iso:country":"US",
    "sg:address":"250 4th St",
    "sg:city":"Patterson",
    "sg:classifiers":[
        {
            "category":"Real Estate",
            "subcategory":"Developer",
            "type":"Services"
        }
    ],
    "sg:phone":"+1 515 462 4107",
    "sg:postcode":"50218",
    "sg:province":"IA",
    "sg:tags":[
        "mobile",
        "home"
    ],
    "wof:name":"Pleasant Valley Mobile Home",
    "wof:placetype":"venue"
},
  "geometry": {"coordinates":[-93.880438,41.349442],"type":"Point"}
}