{
  "type": "Feature",
  "properties": {
    "iso:country":"US",
    "sg:address":"118 S Main St",
    "sg:city":"Clarion",
    "sg:classifiers":[
        {
            "category":"Shopping",
            "subcategory":"Used Merchandise",
            "type":"Retail Goods"
        }
    ],
    "sg:phone":"+1 515 532 6493",
    "sg:postcode":"50525",
    "sg:province":"IA",
    "sg:tags":[
        "shop",
        "thrift"
    ],
    "wof:name":"Thrift & Gift Boutique",
    "wof:placetype":"venue"
},
  "geometry": {"coordinates":[-93.73293099999999,42.731511],"type":"Point"}
}