{
  "type": "Feature",
  "properties": {
    "addr:full":"36704 140th Ave Forest City IA 50436",
    "addr:housenumber":"36704",
    "addr:postcode":"50436",
    "addr:street":"140Th Ave",
    "iso:country":"US",
    "sg:address":"36704 140th Ave",
    "sg:city":"Forest City",
    "sg:phone":"+1 641 581 3515",
    "sg:postcode":"50436",
    "sg:province":"IA",
    "sg:tags":[
        "farm",
        "corn",
        "soybean"
    ],
    "wof:name":"Luther Alm",
    "wof:placetype":"venue"
},
  "geometry": {"coordinates":[-93.696006,43.284318],"type":"Point"}
}