{
  "type": "Feature",
  "properties": {
    "addr:full":"5512 Blairs Forest Way NE Cedar Rapids IA 52402",
    "addr:housenumber":"5512",
    "addr:postcode":"52402",
    "addr:street":"Blairs Forest Way Ne",
    "iso:country":"US",
    "sg:address":"5512 Blairs Forest Way NE",
    "sg:city":"Cedar Rapids",
    "sg:classifiers":[
        {
            "category":"Restaurant",
            "type":"Food & Drink"
        }
    ],
    "sg:phone":"+1 319 393 4403",
    "sg:postcode":"52402",
    "sg:province":"IA",
    "sg:website":"www.subway.com",
    "wof:name":"Subway Sandwiches & Salads",
    "wof:placetype":"venue"
},
  "geometry": {"coordinates":[-91.681602,42.030451],"type":"Point"}
}