{
  "type": "Feature",
  "properties": {
    "addr:full":"1202 E Locust St Carter Lake IA 51510",
    "addr:housenumber":"1202",
    "addr:postcode":"51510",
    "addr:street":"E Locust St",
    "iso:country":"US",
    "sg:address":"1202 E Locust St",
    "sg:city":"Carter Lake",
    "sg:classifiers":[
        {
            "category":"Food & Beverages",
            "subcategory":"Groceries & Convenience Stores",
            "type":"Retail Goods"
        }
    ],
    "sg:phone":"+1 712 347 6948",
    "sg:postcode":"51510",
    "sg:province":"IA",
    "wof:name":"KWIK Shop",
    "wof:placetype":"venue"
},
  "geometry": {"coordinates":[-95.914661,41.285016],"type":"Point"}
}