{
  "type": "Feature",
  "properties": {
    "addr:full":"2146 Koala Ave Guthrie Center IA 50115",
    "addr:housenumber":"2146",
    "addr:postcode":"50115",
    "addr:street":"Koala Ave",
    "iso:country":"US",
    "sg:address":"2146 Koala Ave",
    "sg:city":"Guthrie Center",
    "sg:classifiers":[
        {
            "category":"Food & Beverages",
            "subcategory":"Meat & Fish",
            "type":"Retail Goods"
        }
    ],
    "sg:phone":"+1 641 747 9956",
    "sg:postcode":"50115",
    "sg:province":"IA",
    "wof:name":"Sheeder Farms",
    "wof:placetype":"venue"
},
  "geometry": {"coordinates":[-94.550855,41.701019],"type":"Point"}
}