{
  "type": "Feature",
  "properties": {
    "iso:country":"US",
    "sg:address":"500 8th Ave SE",
    "sg:city":"Cedar Rapids",
    "sg:classifiers":[
        {
            "category":"Bakery",
            "type":"Food & Drink"
        }
    ],
    "sg:phone":"+1 319 366 0391",
    "sg:postcode":"52401",
    "sg:province":"IA",
    "wof:name":"Dolly Madison Cake",
    "wof:placetype":"venue"
},
  "geometry": {"coordinates":[-91.659302,41.974701],"type":"Point"}
}