{
  "type": "Feature",
  "properties": {
    "addr:full":"1823 1st Ave E Spencer IA 51301",
    "addr:housenumber":"1823",
    "addr:postcode":"51301",
    "addr:street":"1St Ave E",
    "iso:country":"US",
    "sg:address":"1823 1st Ave E",
    "sg:city":"Spencer",
    "sg:classifiers":[
        {
            "category":"Banks & Credit Unions",
            "subcategory":"Investment Brokerage",
            "type":"Services"
        }
    ],
    "sg:phone":"+1 712 262 1777",
    "sg:postcode":"51301",
    "sg:province":"IA",
    "sg:tags":[
        "consultant",
        "planning",
        "financial"
    ],
    "wof:name":"American Express Financial Adv",
    "wof:placetype":"venue"
},
  "geometry": {"coordinates":[-95.144373,43.156682],"type":"Point"}
}