{
  "type": "Feature",
  "properties": {
    "iso:country":"US",
    "sg:address":"5665 Hazelwood Ave SW",
    "sg:city":"Kalona",
    "sg:classifiers":[
        {
            "category":"Farming",
            "subcategory":"Nursery",
            "type":"Manufacturing & Wholesale Goods"
        }
    ],
    "sg:phone":"+1 319 656 2589",
    "sg:postcode":"52247",
    "sg:province":"IA",
    "sg:tags":[
        "greenhouse"
    ],
    "wof:name":"Sunnyview Greenhouse",
    "wof:placetype":"venue"
},
  "geometry": {"coordinates":[-91.695424,41.520841],"type":"Point"}
}