{
  "type": "Feature",
  "properties": {
    "iso:country":"US",
    "sg:address":"1450 N 2nd St",
    "sg:city":"Cherokee",
    "sg:classifiers":[
        {
            "category":"Autos & Motor Vehicles",
            "subcategory":"Motorcycle Sales",
            "type":"Retail Goods"
        }
    ],
    "sg:phone":"+1 712 225 6104",
    "sg:postcode":"51012",
    "sg:province":"IA",
    "sg:tags":[
        "scooter"
    ],
    "wof:name":"Cherokee Harley-Davidson",
    "wof:placetype":"venue"
},
  "geometry": {"coordinates":[-95.55252,42.76531],"type":"Point"}
}