{
  "type": "Feature",
  "properties": {
    "iso:country":"US",
    "sg:address":"14501 Hwy 20",
    "sg:city":"Dubuque",
    "sg:classifiers":[
        {
            "category":"Utilities",
            "subcategory":"Refuse",
            "type":"Services"
        }
    ],
    "sg:phone":"+1 563 589 1720",
    "sg:postcode":"52068",
    "sg:province":"IA",
    "sg:tags":[
        "disposal",
        "waste"
    ],
    "wof:name":"Household Hazardous Materials",
    "wof:placetype":"venue"
},
  "geometry": {"coordinates":[-90.77113199999999,42.462109],"type":"Point"}
}