{
  "type": "Feature",
  "properties": {
    "iso:country":"US",
    "sg:address":"292 Red Maple Ave",
    "sg:city":"Cresco",
    "sg:classifiers":[
        {
            "category":"Personal",
            "subcategory":"Beauty Salon",
            "type":"Services"
        }
    ],
    "sg:phone":"+1 563 547 2538",
    "sg:postcode":"52136",
    "sg:province":"IA",
    "sg:tags":[
        "hair",
        "stylist"
    ],
    "wof:name":"Klippett Hair Shoppe",
    "wof:placetype":"venue"
},
  "geometry": {"coordinates":[-92.11922199999999,43.383773],"type":"Point"}
}