{
  "type": "Feature",
  "properties": {
    "addr:full":"101 2nd St SE Ste 904 Cedar Rapids IA 52401",
    "addr:housenumber":"101",
    "addr:postcode":"52401",
    "addr:street":"2Nd St Se Ste 904",
    "iso:country":"US",
    "sg:address":"101 2nd St SE Ste 904",
    "sg:city":"Cedar Rapids",
    "sg:classifiers":[
        {
            "category":"Organizations",
            "subcategory":"Non-profit Organization",
            "type":"Services"
        }
    ],
    "sg:phone":"+1 319 365 2222",
    "sg:postcode":"52401",
    "sg:province":"IA",
    "sg:tags":[
        "service/non-profit",
        "community"
    ],
    "wof:name":"American Board of Certification",
    "wof:placetype":"venue"
},
  "geometry": {"coordinates":[-91.668829,41.978582],"type":"Point"}
}