{
  "type": "Feature",
  "properties": {
    "addr:full":"117 N 16th St Council Bluffs IA 51501",
    "addr:housenumber":"117",
    "addr:postcode":"51501",
    "addr:street":"N 16Th St",
    "iso:country":"US",
    "sg:address":"117 N 16th St",
    "sg:city":"Council Bluffs",
    "sg:classifiers":[
        {
            "category":"Utilities",
            "subcategory":"Mobile Phone",
            "type":"Services"
        }
    ],
    "sg:phone":"+1 712 328 2297",
    "sg:postcode":"51501",
    "sg:province":"IA",
    "sg:tags":[
        "telephone",
        "cellular"
    ],
    "wof:name":"Radio Shack",
    "wof:placetype":"venue"
},
  "geometry": {"coordinates":[-95.867377,41.2635],"type":"Point"}
}