{
  "type": "Feature",
  "properties": {
    "iso:country":"US",
    "sg:address":"109 E Main St",
    "sg:city":"Riceville",
    "sg:classifiers":[
        {
            "category":"Real Estate",
            "subcategory":"Real Estate Agent",
            "type":"Services"
        }
    ],
    "sg:phone":"+1 641 985 4030",
    "sg:postcode":"50466",
    "sg:province":"IA",
    "sg:tags":[
        "contractor"
    ],
    "wof:name":"Govern Business Building",
    "wof:placetype":"venue"
},
  "geometry": {"coordinates":[-92.55432999999999,43.363818],"type":"Point"}
}