{
  "type": "Feature",
  "properties": {
    "iso:country":"US",
    "sg:address":"204 N Main St",
    "sg:city":"Leon",
    "sg:classifiers":[
        {
            "category":"Shopping",
            "subcategory":"Pharmacy",
            "type":"Retail Goods"
        }
    ],
    "sg:phone":"+1 641 446 4136",
    "sg:postcode":"50144",
    "sg:province":"IA",
    "wof:name":"Decatur Family Pharmacy",
    "wof:placetype":"venue"
},
  "geometry": {"coordinates":[-93.74702600000001,40.740337],"type":"Point"}
}