{
  "type": "Feature",
  "properties": {
    "addr:full":"3601 Adventureland Dr Altoona IA 50009",
    "addr:housenumber":"3601",
    "addr:postcode":"50009",
    "addr:street":"Adventureland Dr",
    "iso:country":"US",
    "sg:address":"3601 Adventureland Dr",
    "sg:city":"Altoona",
    "sg:classifiers":[
        {
            "category":"Autos & Motor Vehicles",
            "subcategory":"Automobile Sales",
            "type":"Retail Goods"
        }
    ],
    "sg:phone":"+1 515 967 3500",
    "sg:postcode":"50009",
    "sg:province":"IA",
    "sg:tags":[
        "truck"
    ],
    "sg:website":"www.freightlinerdesmoines.com",
    "wof:name":"Freightliner Of Des Moines Inc",
    "wof:placetype":"venue"
},
  "geometry": {"coordinates":[-93.500668,41.6586],"type":"Point"}
}