{
  "type": "Feature",
  "properties": {
    "iso:country":"US",
    "sg:address":"4550 University Ave",
    "sg:city":"West Des Moines",
    "sg:classifiers":[
        {
            "category":"Shopping",
            "subcategory":"Books",
            "type":"Retail Goods"
        }
    ],
    "sg:phone":"+1 515 221 9171",
    "sg:postcode":"50266",
    "sg:province":"IA",
    "sg:tags":[
        "dealer"
    ],
    "wof:name":"Barnes & Noble Booksellers",
    "wof:placetype":"venue"
},
  "geometry": {"coordinates":[-93.767724,41.600443],"type":"Point"}
}