{
  "type": "Feature",
  "properties": {
    "iso:country":"US",
    "sg:address":"130 N 4th St",
    "sg:city":"Clinton",
    "sg:classifiers":[
        {
            "category":"Professional",
            "type":"Services"
        }
    ],
    "sg:phone":"+1 563 243 4442",
    "sg:postcode":"52732",
    "sg:province":"IA",
    "sg:tags":[
        "establishment"
    ],
    "wof:name":"D J's",
    "wof:placetype":"venue"
},
  "geometry": {"coordinates":[-90.193369,41.845702],"type":"Point"}
}