{
  "type": "Feature",
  "properties": {
    "addr:full":"50 S 9th St Fairfield IA 52556",
    "addr:housenumber":"50",
    "addr:postcode":"52556",
    "addr:street":"S 9Th St",
    "iso:country":"US",
    "sg:address":"50 S 9th St",
    "sg:city":"Fairfield",
    "sg:classifiers":[
        {
            "category":"Autos & Motor Vehicles",
            "subcategory":"Automobile Sales",
            "type":"Retail Goods"
        }
    ],
    "sg:phone":"+1 641 472 1402",
    "sg:postcode":"52556",
    "sg:province":"IA",
    "sg:tags":[
        "car",
        "dealer"
    ],
    "wof:name":"Pro Motors",
    "wof:placetype":"venue"
},
  "geometry": {"coordinates":[-91.974352,41.006273],"type":"Point"}
}