{
  "type": "Feature",
  "properties": {
    "iso:country":"US",
    "sg:address":"1188 140th Ave",
    "sg:city":"Strawberry Point",
    "sg:classifiers":[
        {
            "category":"Retail",
            "subcategory":"Repair Shop",
            "type":"Services"
        }
    ],
    "sg:phone":"+1 563 924 2187",
    "sg:postcode":"52076",
    "sg:province":"IA",
    "wof:name":"Bob Meyer Repair Services",
    "wof:placetype":"venue"
},
  "geometry": {"coordinates":[-91.52828,42.618359],"type":"Point"}
}