{
  "type": "Feature",
  "properties": {
    "iso:country":"US",
    "sg:address":"2001 Hamilton Blvd",
    "sg:city":"Sioux City",
    "sg:classifiers":[
        {
            "category":"Shopping",
            "subcategory":"Gifts & Souvenirs",
            "type":"Retail Goods"
        }
    ],
    "sg:phone":"+1 712 255 5500",
    "sg:postcode":"51104",
    "sg:province":"IA",
    "sg:tags":[
        "collectible"
    ],
    "wof:name":"Rainbow Sports Cards",
    "wof:placetype":"venue"
},
  "geometry": {"coordinates":[-96.416804,42.512541],"type":"Point"}
}