{
  "type": "Feature",
  "properties": {
    "addr:full":"643 Bush St Lamont IA 50650",
    "addr:housenumber":"643",
    "addr:postcode":"50650",
    "addr:street":"Bush St",
    "iso:country":"US",
    "sg:address":"643 Bush St",
    "sg:city":"Lamont",
    "sg:classifiers":[
        {
            "category":"Bars & Pubs",
            "type":"Food & Drink"
        }
    ],
    "sg:phone":"+1 563 924 2104",
    "sg:postcode":"50650",
    "sg:province":"IA",
    "wof:name":"Alibi",
    "wof:placetype":"venue"
},
  "geometry": {"coordinates":[-91.641903,42.599367],"type":"Point"}
}