{
  "type": "Feature",
  "properties": {
    "iso:country":"US",
    "sg:address":"605 Lyon St",
    "sg:city":"Des Moines",
    "sg:classifiers":[
        {
            "category":"Retail",
            "subcategory":"Funeral Services",
            "type":"Services"
        }
    ],
    "sg:phone":"+1 515 243 5221",
    "sg:postcode":"50309",
    "sg:province":"IA",
    "sg:tags":[
        "director"
    ],
    "sg:website":"www.hamiltonsfuneralhome.com",
    "wof:name":"Hamilton's Funeral Home",
    "wof:placetype":"venue"
},
  "geometry": {"coordinates":[-93.60948999999999,41.59323],"type":"Point"}
}