{
  "type": "Feature",
  "properties": {
    "addr:full":"3027 W 11th St Davenport IA 52804",
    "addr:housenumber":"3027",
    "addr:postcode":"52804",
    "addr:street":"W 11Th St",
    "iso:country":"US",
    "sg:address":"3027 W 11th St",
    "sg:city":"Davenport",
    "sg:classifiers":[
        {
            "category":"Building & Trades",
            "subcategory":"Construction",
            "type":"Services"
        }
    ],
    "sg:phone":"+1 563 343 7264",
    "sg:postcode":"52804",
    "sg:province":"IA",
    "sg:tags":[
        "house"
    ],
    "wof:name":"Runge Construction",
    "wof:placetype":"venue"
},
  "geometry": {"coordinates":[-90.621191,41.531326],"type":"Point"}
}