{
  "type": "Feature",
  "properties": {
    "iso:country":"US",
    "sg:address":"54209 110th St",
    "sg:city":"Lyle",
    "sg:phone":"+1 507 325 2381",
    "sg:postcode":"55953",
    "sg:province":"IA",
    "sg:tags":[
        "farm",
        "corn",
        "soybean"
    ],
    "wof:name":"Robert Norregaard",
    "wof:placetype":"venue"
},
  "geometry": {"coordinates":[-92.965513,43.514256],"type":"Point"}
}