{
  "type": "Feature",
  "properties": {
    "iso:country":"US",
    "sg:address":"1125 N 10th St",
    "sg:city":"Clinton",
    "sg:phone":"+1 563 242 6904",
    "sg:postcode":"52732",
    "sg:province":"IA",
    "sg:tags":[
        "farm",
        "soybean"
    ],
    "wof:name":"Rick Bull",
    "wof:placetype":"venue"
},
  "geometry": {"coordinates":[-90.209373,41.856619],"type":"Point"}
}