{
  "type": "Feature",
  "properties": {
    "iso:country":"US",
    "sg:address":"4764 NE 22nd St",
    "sg:city":"Des Moines",
    "sg:classifiers":[
        {
            "category":"Building & Trades",
            "subcategory":"Construction",
            "type":"Services"
        }
    ],
    "sg:phone":"+1 515 323 5888",
    "sg:postcode":"50313",
    "sg:province":"IA",
    "sg:tags":[
        "general",
        "contractor"
    ],
    "wof:name":"Phoenix C & D Recycling",
    "wof:placetype":"venue"
},
  "geometry": {"coordinates":[-93.58141000000001,41.645314],"type":"Point"}
}