{
  "type": "Feature",
  "properties": {
    "addr:full":"37330 70th Ave Forest City IA 50436",
    "addr:housenumber":"37330",
    "addr:postcode":"50436",
    "addr:street":"70Th Ave",
    "iso:country":"US",
    "sg:address":"37330 70th Ave",
    "sg:city":"Forest City",
    "sg:classifiers":[
        {
            "category":"Building & Trades",
            "subcategory":"Electrical",
            "type":"Services"
        }
    ],
    "sg:phone":"+1 641 584 2122",
    "sg:postcode":"50436",
    "sg:province":"IA",
    "sg:tags":[
        "electric",
        "contractor"
    ],
    "wof:name":"Larson Electric & Supply",
    "wof:placetype":"venue"
},
  "geometry": {"coordinates":[-93.833102,43.308516],"type":"Point"}
}