{
  "type": "Feature",
  "properties": {
    "iso:country":"US",
    "sg:address":"601 E Bloomington St",
    "sg:city":"Iowa City",
    "sg:classifiers":[
        {
            "category":"Health Services",
            "subcategory":"Doctor",
            "type":"Services"
        }
    ],
    "sg:phone":"+1 319 354 8777",
    "sg:postcode":"52245",
    "sg:province":"IA",
    "sg:tags":[
        "physician",
        "surgeon"
    ],
    "wof:name":"Cancer Treatment Ctr-Iowa City",
    "wof:placetype":"venue"
},
  "geometry": {"coordinates":[-91.525719,41.664615],"type":"Point"}
}