{
  "type": "Feature",
  "properties": {
    "addr:full":"1104 Kimberly Rd Bettendorf IA 52722",
    "addr:housenumber":"1104",
    "addr:postcode":"52722",
    "addr:street":"Kimberly Rd",
    "iso:country":"US",
    "sg:address":"1104 Kimberly Rd",
    "sg:city":"Bettendorf",
    "sg:classifiers":[
        {
            "category":"Real Estate",
            "subcategory":"Real Estate Operator",
            "type":"Services"
        }
    ],
    "sg:phone":"+1 563 355 2411",
    "sg:postcode":"52722",
    "sg:province":"IA",
    "sg:tags":[
        "condominium"
    ],
    "wof:name":"Manor",
    "wof:placetype":"venue"
},
  "geometry": {"coordinates":[-90.516532,41.530955],"type":"Point"}
}