{
  "type": "Feature",
  "properties": {
    "addr:full":"300 E 2nd St Muscatine IA 52761",
    "addr:housenumber":"300",
    "addr:postcode":"52761",
    "addr:street":"E 2Nd St",
    "iso:country":"US",
    "sg:address":"300 E 2nd St",
    "sg:city":"Muscatine",
    "sg:classifiers":[
        {
            "category":"Banks & Credit Unions",
            "subcategory":"Investment Brokerage",
            "type":"Services"
        }
    ],
    "sg:phone":"+1 563 263 7771",
    "sg:postcode":"52761",
    "sg:province":"IA",
    "sg:tags":[
        "consultant",
        "planning",
        "financial"
    ],
    "wof:name":"Eagle One Investment",
    "wof:placetype":"venue"
},
  "geometry": {"coordinates":[-91.04250999999999,41.423086],"type":"Point"}
}