{
  "type": "Feature",
  "properties": {
    "addr:full":"510 E 4th St N Newton IA 50208",
    "addr:housenumber":"510",
    "addr:postcode":"50208",
    "addr:street":"E 4Th St N",
    "iso:country":"US",
    "sg:address":"510 E 4th St N",
    "sg:city":"Newton",
    "sg:classifiers":[
        {
            "category":"Building & Trades",
            "subcategory":"Cleaning & Sanitation",
            "type":"Services"
        }
    ],
    "sg:phone":"+1 641 792 2887",
    "sg:postcode":"50208",
    "sg:province":"IA",
    "sg:tags":[
        "window"
    ],
    "wof:name":"Carl's Window Svc",
    "wof:placetype":"venue"
},
  "geometry": {"coordinates":[-93.049739,41.703167],"type":"Point"}
}