{
  "type": "Feature",
  "properties": {
    "iso:country":"US",
    "sg:address":"2922 Indian Ave",
    "sg:city":"Hull",
    "sg:classifiers":[
        {
            "category":"Building & Trades",
            "subcategory":"Construction",
            "type":"Services"
        }
    ],
    "sg:phone":"+1 712 439 1106",
    "sg:postcode":"51239",
    "sg:province":"IA",
    "sg:tags":[
        "excavating",
        "contractor"
    ],
    "wof:name":"Vollink Backhoe Svc",
    "wof:placetype":"venue"
},
  "geometry": {"coordinates":[-96.097927,43.226314],"type":"Point"}
}