{
  "type": "Feature",
  "properties": {
    "addr:full":"8528 E 56th St S Reasnor IA 50232",
    "addr:housenumber":"8528",
    "addr:postcode":"50232",
    "addr:street":"E 56Th St S",
    "iso:country":"US",
    "sg:address":"8528 E 56th St S",
    "sg:city":"Reasnor",
    "sg:classifiers":[
        {
            "category":"Farming",
            "subcategory":"Livestock Farm",
            "type":"Manufacturing & Wholesale Goods"
        }
    ],
    "sg:phone":"+1 641 793 2722",
    "sg:postcode":"50232",
    "sg:province":"IA",
    "sg:tags":[
        "hog",
        "or",
        "feedlot"
    ],
    "wof:name":"Eugene Sjaardena Farm",
    "wof:placetype":"venue"
},
  "geometry": {"coordinates":[-92.986694,41.585201],"type":"Point"}
}