{
  "type": "Feature",
  "properties": {
    "addr:full":"120 W Water St Decorah IA 52101",
    "addr:housenumber":"120",
    "addr:postcode":"52101",
    "addr:street":"W Water St",
    "iso:country":"US",
    "sg:address":"120 W Water St",
    "sg:city":"Decorah",
    "sg:classifiers":[
        {
            "category":"Banks & Credit Unions",
            "subcategory":"Bank",
            "type":"Services"
        }
    ],
    "sg:phone":"+1 563 382 2991",
    "sg:postcode":"52101",
    "sg:province":"IA",
    "sg:website":"www.communityfirst.com",
    "wof:name":"Bank Of The West",
    "wof:placetype":"venue"
},
  "geometry": {"coordinates":[-91.78698900000001,43.304244],"type":"Point"}
}