{
  "type": "Feature",
  "properties": {
    "iso:country":"US",
    "sg:address":"746 Broad St",
    "sg:city":"Granville",
    "sg:classifiers":[
        {
            "category":"Retail",
            "subcategory":"Auto Repair",
            "type":"Services"
        }
    ],
    "sg:phone":"+1 712 727 3273",
    "sg:postcode":"51022",
    "sg:province":"IA",
    "sg:tags":[
        "repairing",
        "automobile"
    ],
    "wof:name":"Terry's Repair & Auto Parts",
    "wof:placetype":"venue"
},
  "geometry": {"coordinates":[-95.87434399999999,42.984715],"type":"Point"}
}