{
  "type": "Feature",
  "properties": {
    "iso:country":"US",
    "sg:address":"1201 Avenue H",
    "sg:city":"Carter Lake",
    "sg:classifiers":[
        {
            "category":"Travel",
            "subcategory":"Hotels & Motels",
            "type":"Entertainment"
        }
    ],
    "sg:phone":"+1 712 347 6595",
    "sg:postcode":"51510",
    "sg:province":"IA",
    "wof:name":"Wingate Inn",
    "wof:placetype":"venue"
},
  "geometry": {"coordinates":[-95.914001,41.281399],"type":"Point"}
}