{
  "type": "Feature",
  "properties": {
    "iso:country":"US",
    "sg:address":"400 Walnut St",
    "sg:city":"Des Moines",
    "sg:classifiers":[
        {
            "category":"Real Estate",
            "subcategory":"Real Estate Agent",
            "type":"Services"
        }
    ],
    "sg:phone":"+1 515 244 6161",
    "sg:postcode":"50309",
    "sg:province":"IA",
    "sg:tags":[
        "investment"
    ],
    "wof:name":"Coppola Properties",
    "wof:placetype":"venue"
},
  "geometry": {"coordinates":[-93.62338200000001,41.586149],"type":"Point"}
}