{
  "type": "Feature",
  "properties": {
    "iso:country":"US",
    "sg:address":"10224 NW 107 Pl",
    "sg:city":"Granger",
    "sg:classifiers":[
        {
            "category":"Real Estate",
            "subcategory":"Real Estate Agent",
            "type":"Services"
        }
    ],
    "sg:phone":"+1 515 999 2750",
    "sg:postcode":"50109",
    "sg:province":"IA",
    "sg:tags":[
        "inspection"
    ],
    "wof:name":"England Home Inspection Svc",
    "wof:placetype":"venue"
},
  "geometry": {"coordinates":[-93.759821,41.756868],"type":"Point"}
}