{
  "type": "Feature",
  "properties": {
    "iso:country":"US",
    "sg:address":"1924 160th St",
    "sg:city":"New Sharon",
    "sg:classifiers":[
        {
            "category":"Farming",
            "subcategory":"Farm",
            "type":"Manufacturing & Wholesale Goods"
        }
    ],
    "sg:phone":"+1 641 637 2880",
    "sg:postcode":"50207",
    "sg:province":"IA",
    "sg:tags":[
        "crop",
        "general"
    ],
    "wof:name":"Floyd W Everett",
    "wof:placetype":"venue"
},
  "geometry": {"coordinates":[-92.69208399999999,41.422358],"type":"Point"}
}