{
  "type": "Feature",
  "properties": {
    "iso:country":"US",
    "sg:address":"306 Lynn St",
    "sg:city":"Tipton",
    "sg:classifiers":[
        {
            "category":"Retail",
            "subcategory":"Auto Repair",
            "type":"Services"
        }
    ],
    "sg:phone":"+1 563 886 2322",
    "sg:postcode":"52772",
    "sg:province":"IA",
    "sg:tags":[
        "repairing",
        "automobile"
    ],
    "wof:name":"Tipton Tire & Auto/Goodyear",
    "wof:placetype":"venue"
},
  "geometry": {"coordinates":[-91.129741,41.768891],"type":"Point"}
}