{
  "type": "Feature",
  "properties": {
    "iso:country":"US",
    "sg:address":"1899 230th St",
    "sg:city":"Waverly",
    "sg:classifiers":[
        {
            "category":"Retail",
            "subcategory":"Auto Repair",
            "type":"Services"
        }
    ],
    "sg:phone":"+1 319 352 4487",
    "sg:postcode":"50677",
    "sg:province":"IA",
    "sg:tags":[
        "body",
        "automobile",
        "painting"
    ],
    "wof:name":"Elsamiller Auto Body Inc",
    "wof:placetype":"venue"
},
  "geometry": {"coordinates":[-92.37472699999999,42.714969],"type":"Point"}
}