{
  "type": "Feature",
  "properties": {
    "iso:country":"US",
    "sg:address":"2350 Kerper Blvd",
    "sg:city":"Dubuque",
    "sg:classifiers":[
        {
            "category":"Manufacturing",
            "subcategory":"Retail Goods",
            "type":"Manufacturing & Wholesale Goods"
        }
    ],
    "sg:phone":"+1 563 588 6244",
    "sg:postcode":"52001",
    "sg:province":"IA",
    "sg:tags":[
        "manufacturer"
    ],
    "wof:name":"SKW Nature Products",
    "wof:placetype":"venue"
},
  "geometry": {"coordinates":[-90.655497,42.519792],"type":"Point"}
}