{
  "type": "Feature",
  "properties": {
    "iso:country":"US",
    "sg:address":"803 10th St",
    "sg:city":"Hawarden",
    "sg:classifiers":[
        {
            "category":"Education",
            "subcategory":"Library",
            "type":"Public Place"
        }
    ],
    "sg:phone":"+1 712 551 2244",
    "sg:postcode":"51023",
    "sg:province":"SD",
    "sg:website":"www.hawardenlibrary.org",
    "wof:name":"Hawarden Public Library",
    "wof:placetype":"venue"
},
  "geometry": {"coordinates":[-96.483791,42.996851],"type":"Point"}
}