{
  "type": "Feature",
  "properties": {
    "iso:country":"US",
    "sg:address":"115 W Robins Ave",
    "sg:city":"Graettinger",
    "sg:classifiers":[
        {
            "category":"Education",
            "subcategory":"Library",
            "type":"Public Place"
        }
    ],
    "sg:phone":"+1 712 859 3592",
    "sg:postcode":"51342",
    "sg:province":"IA",
    "wof:name":"Graettinger City Library",
    "wof:placetype":"venue"
},
  "geometry": {"coordinates":[-94.755503,43.237904],"type":"Point"}
}