{
  "type": "Feature",
  "properties": {
    "addr:full":"1806 240th St Inwood IA 51240",
    "addr:housenumber":"1806",
    "addr:postcode":"51240",
    "addr:street":"240Th St",
    "iso:country":"US",
    "sg:address":"1806 240th St",
    "sg:city":"Inwood",
    "sg:classifiers":[
        {
            "category":"Shopping",
            "subcategory":"Florist",
            "type":"Retail Goods"
        }
    ],
    "sg:phone":"+1 712 753 2858",
    "sg:postcode":"51240",
    "sg:province":"IA",
    "wof:name":"Floral Gallery LTD",
    "wof:placetype":"venue"
},
  "geometry": {"coordinates":[-96.42592999999999,43.30199],"type":"Point"}
}