{
  "type": "Feature",
  "properties": {
    "iso:country":"US",
    "sg:address":"216 S Kellogg Ave",
    "sg:city":"Ames",
    "sg:classifiers":[
        {
            "category":"Professional",
            "type":"Services"
        }
    ],
    "sg:phone":"+1 515 233 3014",
    "sg:postcode":"50010",
    "sg:province":"IA",
    "sg:tags":[
        "establishment"
    ],
    "wof:name":"Open Com Inc",
    "wof:placetype":"venue"
},
  "geometry": {"coordinates":[-93.61354300000001,42.020429],"type":"Point"}
}