{
  "type": "Feature",
  "properties": {
    "iso:country":"US",
    "sg:address":"2349 Jamestown Ave",
    "sg:city":"Independence",
    "sg:classifiers":[
        {
            "category":"Professional",
            "subcategory":"Advertising",
            "type":"Services"
        }
    ],
    "sg:phone":"+1 319 334 5115",
    "sg:postcode":"50644",
    "sg:province":"IA",
    "sg:tags":[
        "counselor"
    ],
    "sg:website":"www.ecreativegroup.com",
    "wof:name":"Ecreative Group",
    "wof:placetype":"venue"
},
  "geometry": {"coordinates":[-91.890193,42.446031],"type":"Point"}
}