{
  "type": "Feature",
  "properties": {
    "addr:full":"3812 Wolcott Ave Des Moines IA 50321",
    "addr:housenumber":"3812",
    "addr:postcode":"50321",
    "addr:street":"Wolcott Ave",
    "iso:country":"US",
    "sg:address":"3812 Wolcott Ave",
    "sg:city":"Des Moines",
    "sg:classifiers":[
        {
            "category":"Building & Trades",
            "subcategory":"Construction",
            "type":"Services"
        }
    ],
    "sg:phone":"+1 515 974 1777",
    "sg:postcode":"50321",
    "sg:province":"IA",
    "sg:tags":[
        "general",
        "contractor"
    ],
    "wof:name":"Job Shops Co",
    "wof:placetype":"venue"
},
  "geometry": {"coordinates":[-93.668903,41.551633],"type":"Point"}
}