{
  "type": "Feature",
  "properties": {
    "iso:country":"US",
    "sg:address":"3210 S 7th St",
    "sg:city":"Council Bluffs",
    "sg:classifiers":[
        {
            "category":"Restaurant",
            "type":"Food & Drink"
        }
    ],
    "sg:phone":"+1 712 366 2217",
    "sg:postcode":"51501",
    "sg:province":"IA",
    "sg:tags":[
        "pizza"
    ],
    "wof:name":"Travel Centers of America",
    "wof:placetype":"venue"
},
  "geometry": {"coordinates":[-95.852898,41.228001],"type":"Point"}
}