{
  "type": "Feature",
  "properties": {
    "iso:country":"US",
    "sg:address":"820 N Main St",
    "sg:city":"Sigourney",
    "sg:classifiers":[
        {
            "category":"Government",
            "subcategory":"Office",
            "type":"Public Place"
        }
    ],
    "sg:phone":"+1 641 622 2343",
    "sg:postcode":"52591",
    "sg:province":"IA",
    "sg:tags":[
        "village"
    ],
    "wof:name":"Sigourney Maintenance Shop",
    "wof:placetype":"venue"
},
  "geometry": {"coordinates":[-92.205191,41.344011],"type":"Point"}
}