{
  "type": "Feature",
  "properties": {
    "iso:country":"US",
    "sg:address":"4457 E 56th St",
    "sg:city":"Davenport",
    "sg:classifiers":[
        {
            "category":"Social Services",
            "type":"Services"
        }
    ],
    "sg:phone":"+1 563 359 9389",
    "sg:postcode":"52807",
    "sg:province":"IA",
    "sg:tags":[
        "youth",
        "organization",
        "center"
    ],
    "wof:name":"Student Hunger Drive Inc",
    "wof:placetype":"venue"
},
  "geometry": {"coordinates":[-90.512417,41.578914],"type":"Point"}
}