{
  "type": "Feature",
  "properties": {
    "iso:country":"US",
    "sg:address":"2730 Ave L",
    "sg:city":"Fort Madison",
    "sg:classifiers":[
        {
            "category":"Personal",
            "subcategory":"Barber",
            "type":"Services"
        }
    ],
    "sg:phone":"+1 319 372 8293",
    "sg:postcode":"52627",
    "sg:province":"IA",
    "wof:name":"Hair Club",
    "wof:placetype":"venue"
},
  "geometry": {"coordinates":[-91.34510899999999,40.626877],"type":"Point"}
}