{
  "type": "Feature",
  "properties": {
    "iso:country":"US",
    "sg:address":"411 1st Ave E",
    "sg:city":"Dyersville",
    "sg:classifiers":[
        {
            "category":"Personal",
            "subcategory":"Beauty Salon",
            "type":"Services"
        }
    ],
    "sg:phone":"+1 563 875 2069",
    "sg:postcode":"52040",
    "sg:province":"IA",
    "sg:tags":[
        "manicuring"
    ],
    "wof:name":"Shear Fashions Hair Design",
    "wof:placetype":"venue"
},
  "geometry": {"coordinates":[-91.119196,42.484595],"type":"Point"}
}