{
  "type": "Feature",
  "properties": {
    "iso:country":"US",
    "sg:address":"12587 Apricot Rd",
    "sg:city":"Postville",
    "sg:classifiers":[
        {
            "category":"Freight",
            "type":"Transportation"
        }
    ],
    "sg:phone":"+1 563 864 7175",
    "sg:postcode":"52162",
    "sg:province":"IA",
    "sg:tags":[
        "trucking"
    ],
    "wof:name":"Zuercher Trucking/Wapsie Pump",
    "wof:placetype":"venue"
},
  "geometry": {"coordinates":[-91.55689700000001,43.023244],"type":"Point"}
}