{
  "type": "Feature",
  "properties": {
    "iso:country":"US",
    "sg:address":"2846 530th Ave",
    "sg:city":"Ringsted",
    "sg:classifiers":[
        {
            "category":"Home & Garden",
            "subcategory":"Garden Supply",
            "type":"Retail Goods"
        }
    ],
    "sg:phone":"+1 515 889 2232",
    "sg:postcode":"50578",
    "sg:province":"IA",
    "sg:tags":[
        "bulb",
        "seed"
    ],
    "wof:name":"Stewart Ohrtman Seed",
    "wof:placetype":"venue"
},
  "geometry": {"coordinates":[-94.54145699999999,43.234488],"type":"Point"}
}