{
  "type": "Feature",
  "properties": {
    "iso:country":"US",
    "sg:address":"3031 Flint Hills Dr",
    "sg:city":"Burlington",
    "sg:classifiers":[
        {
            "category":"Health Services",
            "subcategory":"Optometrist",
            "type":"Services"
        }
    ],
    "sg:phone":"+1 319 754 5518",
    "sg:postcode":"52601",
    "sg:province":"IA",
    "wof:name":"Larry J Taylor OD",
    "wof:placetype":"venue"
},
  "geometry": {"coordinates":[-91.13882099999999,40.80863],"type":"Point"}
}