{
  "type": "Feature",
  "properties": {
    "iso:country":"US",
    "sg:address":"1754 Hamilton Blvd",
    "sg:city":"Sioux City",
    "sg:classifiers":[
        {
            "category":"Real Estate",
            "subcategory":"Real Estate Agent",
            "type":"Services"
        }
    ],
    "sg:phone":"+1 712 233 2333",
    "sg:postcode":"51103",
    "sg:province":"IA",
    "wof:name":"Davis Realty",
    "wof:placetype":"venue"
},
  "geometry": {"coordinates":[-96.41664900000001,42.508886],"type":"Point"}
}