{
  "type": "Feature",
  "properties": {
    "addr:full":"2924 Willis Ave Perry IA 50220",
    "addr:housenumber":"2924",
    "addr:postcode":"50220",
    "addr:street":"Willis Ave",
    "iso:country":"US",
    "sg:address":"2924 Willis Ave",
    "sg:city":"Perry",
    "sg:classifiers":[
        {
            "category":"Home & Garden",
            "subcategory":"Garden Supply",
            "type":"Retail Goods"
        }
    ],
    "sg:phone":"+1 515 465 2248",
    "sg:postcode":"50220",
    "sg:province":"IA",
    "sg:tags":[
        "lawn",
        "mower"
    ],
    "wof:name":"Naylor Service & Sales",
    "wof:placetype":"venue"
},
  "geometry": {"coordinates":[-94.078067,41.838566],"type":"Point"}
}