{
  "type": "Feature",
  "properties": {
    "iso:country":"US",
    "sg:address":"44 Park View Dr",
    "sg:city":"Eldridge",
    "sg:classifiers":[
        {
            "category":"Restaurant",
            "type":"Food & Drink"
        }
    ],
    "sg:phone":"+1 563 285 7073",
    "sg:postcode":"52748",
    "sg:province":"IA",
    "wof:name":"Pizza King & Restaurant",
    "wof:placetype":"venue"
},
  "geometry": {"coordinates":[-90.54136200000001,41.696937],"type":"Point"}
}