{
  "type": "Feature",
  "properties": {
    "addr:full":"18 E 18th St Dubuque IA 52001",
    "addr:housenumber":"18",
    "addr:postcode":"52001",
    "addr:street":"E 18Th St",
    "iso:country":"US",
    "sg:address":"18 E 18th St",
    "sg:city":"Dubuque",
    "sg:classifiers":[
        {
            "category":"Building & Trades",
            "subcategory":"Construction",
            "type":"Services"
        }
    ],
    "sg:phone":"+1 888 822 8165",
    "sg:postcode":"52001",
    "sg:province":"IA",
    "sg:tags":[
        "system",
        "specialty",
        "heating",
        "ventilating",
        "contractor",
        "air conditioning"
    ],
    "sg:website":"http://www.advantagesheetmetal.com",
    "wof:name":"Advantage Sheet Metal",
    "wof:placetype":"venue"
},
  "geometry": {"coordinates":[-90.669292,42.509778],"type":"Point"}
}