{
  "type": "Feature",
  "properties": {
    "iso:country":"US",
    "sg:address":"200 1st St SE",
    "sg:city":"Cedar Rapids",
    "sg:classifiers":[
        {
            "category":"Building & Trades",
            "subcategory":"Construction",
            "type":"Services"
        }
    ],
    "sg:phone":"+1 319 362 1017",
    "sg:postcode":"52401",
    "sg:province":"IA",
    "sg:tags":[
        "elevator"
    ],
    "wof:name":"Schumacher Elevator Co",
    "wof:placetype":"venue"
},
  "geometry": {"coordinates":[-91.66807,41.97635],"type":"Point"}
}