{
  "type": "Feature",
  "properties": {
    "iso:country":"US",
    "sg:address":"1127 N 2nd St",
    "sg:city":"Clinton",
    "sg:classifiers":[
        {
            "category":"Professional",
            "subcategory":"Lawyer & Legal Services",
            "type":"Services"
        }
    ],
    "sg:phone":"+1 563 243 2450",
    "sg:postcode":"52732",
    "sg:province":"IA",
    "sg:tags":[
        "attorney",
        "accident",
        "personal",
        "automobile",
        "injury",
        "law"
    ],
    "wof:name":"James L. Pillers, JD, PC",
    "wof:placetype":"venue"
},
  "geometry": {"coordinates":[-90.185608,41.856381],"type":"Point"}
}