{
  "type": "Feature",
  "properties": {
    "iso:country":"US",
    "sg:address":"2570 Hubbell Ave",
    "sg:city":"Des Moines",
    "sg:classifiers":[
        {
            "category":"Shopping",
            "subcategory":"Department Store",
            "type":"Retail Goods"
        }
    ],
    "sg:phone":"+1 515 265 8141",
    "sg:postcode":"50317",
    "sg:province":"IA",
    "sg:tags":[
        "shop"
    ],
    "wof:name":"Dollar General",
    "wof:placetype":"venue"
},
  "geometry": {"coordinates":[-93.56849800000001,41.610906],"type":"Point"}
}