{
  "type": "Feature",
  "properties": {
    "addr:full":"9274 Golden Valley Dr Norwalk IA 50211",
    "addr:housenumber":"9274",
    "addr:postcode":"50211",
    "addr:street":"Golden Valley Dr",
    "iso:country":"US",
    "sg:address":"9274 Golden Valley Dr",
    "sg:city":"Norwalk",
    "sg:classifiers":[
        {
            "category":"Building & Trades",
            "subcategory":"Landscaping Services",
            "type":"Services"
        }
    ],
    "sg:phone":"+1 515 285 3439",
    "sg:postcode":"50211",
    "sg:province":"IA",
    "sg:tags":[
        "tree"
    ],
    "wof:name":"Daniel's Tree Svc",
    "wof:placetype":"venue"
},
  "geometry": {"coordinates":[-93.677057,41.498284],"type":"Point"}
}