{
  "type": "Feature",
  "properties": {
    "iso:country":"US",
    "sg:address":"207 S Randolph St",
    "sg:city":"Stacyville",
    "sg:classifiers":[
        {
            "category":"Wholesale",
            "subcategory":"Farm Supplies",
            "type":"Manufacturing & Wholesale Goods"
        }
    ],
    "sg:phone":"+1 641 710 2390",
    "sg:postcode":"50476",
    "sg:province":"IA",
    "wof:name":"Steward Supply Co",
    "wof:placetype":"venue"
},
  "geometry": {"coordinates":[-92.78486100000001,43.435238],"type":"Point"}
}