{
  "type": "Feature",
  "properties": {
    "iso:country":"US",
    "sg:address":"14537 Jimtown Rd",
    "sg:city":"Danville",
    "sg:phone":"+1 319 392 4513",
    "sg:postcode":"52623",
    "sg:province":"IA",
    "sg:tags":[
        "farm",
        "corn"
    ],
    "wof:name":"Gary Oetken",
    "wof:placetype":"venue"
},
  "geometry": {"coordinates":[-91.34324100000001,40.895063],"type":"Point"}
}