{
  "type": "Feature",
  "properties": {
    "addr:full":"1417 Broadway Denison IA 51442",
    "addr:housenumber":"1417",
    "addr:postcode":"51442",
    "addr:street":"Broadway",
    "iso:country":"US",
    "sg:address":"1417 Broadway",
    "sg:city":"Denison",
    "sg:classifiers":[
        {
            "category":"Real Estate",
            "subcategory":"Real Estate Agent",
            "type":"Services"
        }
    ],
    "sg:phone":"+1 712 263 5051",
    "sg:postcode":"51442",
    "sg:province":"IA",
    "sg:tags":[
        "appraisal"
    ],
    "wof:name":"Zenk Real Estate Appraisals",
    "wof:placetype":"venue"
},
  "geometry": {"coordinates":[-95.35359200000001,42.016659],"type":"Point"}
}