{
  "type": "Feature",
  "properties": {
    "iso:country":"US",
    "sg:address":"28 S Clinton St",
    "sg:city":"Iowa City",
    "sg:classifiers":[
        {
            "category":"Shopping",
            "subcategory":"Clothing, Apparel, & Fashions",
            "type":"Retail Goods"
        }
    ],
    "sg:phone":"+1 319 337 3345",
    "sg:postcode":"52240",
    "sg:province":"IA",
    "sg:tags":[
        "furnishing"
    ],
    "wof:name":"Ewers Mens Store",
    "wof:placetype":"venue"
},
  "geometry": {"coordinates":[-91.534537,41.660419],"type":"Point"}
}