{
  "type": "Feature",
  "properties": {
    "addr:full":"66 W 32nd St Dubuque IA 52001",
    "addr:housenumber":"66",
    "addr:postcode":"52001",
    "addr:street":"W 32Nd St",
    "iso:country":"US",
    "sg:address":"66 W 32nd St",
    "sg:city":"Dubuque",
    "sg:classifiers":[
        {
            "category":"Banks & Credit Unions",
            "subcategory":"Bank",
            "type":"Services"
        }
    ],
    "sg:phone":"+1 563 583 1196",
    "sg:postcode":"52001",
    "sg:province":"IA",
    "wof:name":"Bilt-Well Credit Union",
    "wof:placetype":"venue"
},
  "geometry": {"coordinates":[-90.683165,42.527232],"type":"Point"}
}