{
  "type": "Feature",
  "properties": {
    "iso:country":"US",
    "sg:address":"505 N Hayes St",
    "sg:city":"Mt Ayr",
    "sg:classifiers":[
        {
            "category":"Building & Trades",
            "subcategory":"Construction",
            "type":"Services"
        }
    ],
    "sg:phone":"+1 641 464 2048",
    "sg:postcode":"50854",
    "sg:province":"IA",
    "sg:tags":[
        "general",
        "contractor"
    ],
    "wof:name":"Corll Seamless Gutters",
    "wof:placetype":"venue"
},
  "geometry": {"coordinates":[-94.23322400000001,40.721995],"type":"Point"}
}