{
  "type": "Feature",
  "properties": {
    "iso:country":"US",
    "sg:address":"1501 Superior St",
    "sg:city":"Webster City",
    "sg:classifiers":[
        {
            "category":"Real Estate",
            "subcategory":"Real Estate Agent",
            "type":"Services"
        }
    ],
    "sg:phone":"+1 515 832 4223",
    "sg:postcode":"50595",
    "sg:province":"IA",
    "sg:website":"www.jimfortunerealty.com",
    "wof:name":"Jim Fortune Realty",
    "wof:placetype":"venue"
},
  "geometry": {"coordinates":[-93.81585699999999,42.462924],"type":"Point"}
}