{
  "type": "Feature",
  "properties": {
    "iso:country":"US",
    "sg:address":"1394 Randall Dr NW",
    "sg:city":"Swisher",
    "sg:classifiers":[
        {
            "category":"Building & Trades",
            "subcategory":"Construction",
            "type":"Services"
        }
    ],
    "sg:phone":"+1 319 857 5398",
    "sg:postcode":"52338",
    "sg:province":"IA",
    "sg:tags":[
        "general",
        "contractor"
    ],
    "wof:name":"Siemering Construction",
    "wof:placetype":"venue"
},
  "geometry": {"coordinates":[-91.66575400000001,41.835901],"type":"Point"}
}