{
  "type": "Feature",
  "properties": {
    "addr:full":"307 Maple St Early IA 50535",
    "addr:housenumber":"307",
    "addr:postcode":"50535",
    "addr:street":"Maple St",
    "iso:country":"US",
    "sg:address":"307 Maple St",
    "sg:city":"Early",
    "sg:classifiers":[
        {
            "category":"Real Estate",
            "subcategory":"Real Estate Operator",
            "type":"Services"
        }
    ],
    "sg:phone":"+1 712 273 5391",
    "sg:postcode":"50535",
    "sg:province":"IA",
    "sg:tags":[
        "property",
        "lessor"
    ],
    "wof:name":"Marvin Tiefenthaler Farm",
    "wof:placetype":"venue"
},
  "geometry": {"coordinates":[-95.14908,42.463945],"type":"Point"}
}