{
  "type": "Feature",
  "properties": {
    "iso:country":"US",
    "sg:address":"2020 E River Dr",
    "sg:city":"Davenport",
    "sg:classifiers":[
        {
            "category":"Personal",
            "subcategory":"Beauty Salon",
            "type":"Services"
        }
    ],
    "sg:phone":"+1 563 322 0595",
    "sg:postcode":"52803",
    "sg:province":"IA",
    "sg:tags":[
        "manicuring"
    ],
    "wof:name":"Perfect 10",
    "wof:placetype":"venue"
},
  "geometry": {"coordinates":[-90.548112,41.529701],"type":"Point"}
}