{
  "type": "Feature",
  "properties": {
    "iso:country":"US",
    "sg:address":"3533 Main St",
    "sg:city":"Keokuk",
    "sg:classifiers":[
        {
            "category":"Building & Trades",
            "subcategory":"Construction",
            "type":"Services"
        }
    ],
    "sg:phone":"+1 319 524 8672",
    "sg:postcode":"52632",
    "sg:province":"IA",
    "sg:tags":[
        "system",
        "specialty",
        "heating",
        "contractor",
        "ventilating",
        "air conditioning"
    ],
    "wof:name":"Enderle Heating & Air Conditioning",
    "wof:placetype":"venue"
},
  "geometry": {"coordinates":[-91.410265,40.422472],"type":"Point"}
}