{
  "type": "Feature",
  "properties": {
    "addr:full":"6240 Streeter Rd Cedar Falls IA 50613",
    "addr:postcode":"6240;50613",
    "addr:street":"Streeter Rd",
    "iso:country":"US",
    "sg:address":"6240 Streeter Rd",
    "sg:city":"Cedar Falls",
    "sg:classifiers":[
        {
            "category":"Building & Trades",
            "subcategory":"Construction",
            "type":"Services"
        }
    ],
    "sg:phone":"+1 319 233 4718",
    "sg:postcode":"50613",
    "sg:province":"IA",
    "sg:website":"www.midwestbldgs.com",
    "wof:name":"Midwest Buildings Inc",
    "wof:placetype":"venue"
},
  "geometry": {"coordinates":[-92.39665100000001,42.588887],"type":"Point"}
}