{
  "type": "Feature",
  "properties": {
    "iso:country":"US",
    "sg:address":"2152 Johnson Street Rd",
    "sg:city":"Keokuk",
    "sg:classifiers":[
        {
            "category":"Building & Trades",
            "subcategory":"Construction",
            "type":"Services"
        }
    ],
    "sg:phone":"+1 319 524 4345",
    "sg:postcode":"52632",
    "sg:province":"IA",
    "sg:tags":[
        "system",
        "specialty",
        "heating",
        "contractor",
        "air conditioning"
    ],
    "wof:name":"Eagle Rest Heating & A & Appl",
    "wof:placetype":"venue"
},
  "geometry": {"coordinates":[-91.49993499999999,40.422423],"type":"Point"}
}