{
  "type": "Feature",
  "properties": {
    "addr:full":"2997 160th St Fort Atkinson IA 52144",
    "addr:housenumber":"2997",
    "addr:postcode":"52144",
    "addr:street":"160Th St",
    "iso:country":"US",
    "sg:address":"2997 160th St",
    "sg:city":"Fort Atkinson",
    "sg:classifiers":[
        {
            "category":"Farming",
            "subcategory":"Farm",
            "type":"Manufacturing & Wholesale Goods"
        }
    ],
    "sg:phone":"+1 563 534 7490",
    "sg:postcode":"52144",
    "sg:province":"IA",
    "sg:tags":[
        "dairy",
        "livestock",
        "crop",
        "general"
    ],
    "wof:name":"William Timp",
    "wof:placetype":"venue"
},
  "geometry": {"coordinates":[-91.991649,43.169018],"type":"Point"}
}