{
  "type": "Feature",
  "properties": {
    "iso:country":"US",
    "sg:address":"102 S Central Ave",
    "sg:city":"Lacona",
    "sg:classifiers":[
        {
            "category":"Restaurant",
            "type":"Food & Drink"
        }
    ],
    "sg:phone":"+1 641 534 4343",
    "sg:postcode":"50139",
    "sg:province":"IA",
    "wof:name":"Rudy's Rendezvous",
    "wof:placetype":"venue"
},
  "geometry": {"coordinates":[-93.385428,41.188544],"type":"Point"}
}