{
  "type": "Feature",
  "properties": {
    "iso:country":"US",
    "sg:address":"23977 Claybanks Dr",
    "sg:city":"Nora Springs",
    "sg:classifiers":[
        {
            "category":"Farming",
            "subcategory":"Farm & Veterinary Services",
            "type":"Manufacturing & Wholesale Goods"
        }
    ],
    "sg:phone":"+1 641 749 5297",
    "sg:postcode":"50458",
    "sg:province":"IA",
    "sg:tags":[
        "breeder",
        "livestock"
    ],
    "wof:name":"Hunters Farm Inc",
    "wof:placetype":"venue"
},
  "geometry": {"coordinates":[-93.04429399999999,43.099417],"type":"Point"}
}