{
  "type": "Feature",
  "properties": {
    "iso:country":"US",
    "sg:address":"121 Washington Ave W",
    "sg:city":"Albia",
    "sg:classifiers":[
        {
            "category":"Personal",
            "subcategory":"Beauty Salon",
            "type":"Services"
        }
    ],
    "sg:phone":"+1 641 932 5917",
    "sg:postcode":"52531",
    "sg:province":"IA",
    "wof:name":"Hair Mechanic & Tans",
    "wof:placetype":"venue"
},
  "geometry": {"coordinates":[-92.814149,41.025927],"type":"Point"}
}