{
  "type": "Feature",
  "properties": {
    "iso:country":"US",
    "sg:address":"501 Kelly St",
    "sg:city":"Charles City",
    "sg:classifiers":[
        {
            "category":"Home & Garden",
            "subcategory":"Building Materials",
            "type":"Retail Goods"
        }
    ],
    "sg:phone":"+1 641 228 4463",
    "sg:postcode":"50616",
    "sg:province":"IA",
    "wof:name":"Regel Glass",
    "wof:placetype":"venue"
},
  "geometry": {"coordinates":[-92.680196,43.069137],"type":"Point"}
}