{
  "type": "Feature",
  "properties": {
    "addr:full":"710 Grant Wood Dr SE Cedar Rapids IA 52403",
    "addr:housenumber":"710",
    "addr:postcode":"52403",
    "addr:street":"Grant Wood Dr Se",
    "iso:country":"US",
    "sg:address":"710 Grant Wood Dr SE",
    "sg:city":"Cedar Rapids",
    "sg:classifiers":[
        {
            "category":"Real Estate",
            "subcategory":"Real Estate Services",
            "type":"Services"
        }
    ],
    "sg:phone":"+1 319 560 1001",
    "sg:postcode":"52403",
    "sg:province":"IA",
    "sg:tags":[
        "home",
        "inspector"
    ],
    "wof:name":"Terry Steinbach",
    "wof:placetype":"venue"
},
  "geometry": {"coordinates":[-91.629344,41.979267],"type":"Point"}
}