{
  "type": "Feature",
  "properties": {
    "iso:country":"US",
    "sg:address":"118 S Market St",
    "sg:city":"Lake Park",
    "sg:classifiers":[
        {
            "category":"Personal",
            "subcategory":"Beauty Salon",
            "type":"Services"
        }
    ],
    "sg:phone":"+1 712 832 3559",
    "sg:postcode":"51347",
    "sg:province":"IA",
    "wof:name":"Gilly's Hair Salon",
    "wof:placetype":"venue"
},
  "geometry": {"coordinates":[-95.32244900000001,43.453079],"type":"Point"}
}