{
  "type": "Feature",
  "properties": {
    "iso:country":"US",
    "sg:address":"2100 NW 100th St",
    "sg:city":"Clive",
    "sg:classifiers":[
        {
            "category":"Health Services",
            "subcategory":"Doctor",
            "type":"Services"
        }
    ],
    "sg:phone":"+1 515 270 0351",
    "sg:postcode":"50325",
    "sg:province":"IA",
    "sg:tags":[
        "physician",
        "surgeon"
    ],
    "wof:name":"Jane Schrader MD",
    "wof:placetype":"venue"
},
  "geometry": {"coordinates":[-93.75576100000001,41.608912],"type":"Point"}
}