{
  "type": "Feature",
  "properties": {
    "addr:full":"100 3rd St Frederika IA 50631",
    "addr:housenumber":"100",
    "addr:postcode":"50631",
    "addr:street":"3Rd St",
    "iso:country":"US",
    "sg:address":"100 3rd St",
    "sg:city":"Frederika",
    "sg:classifiers":[
        {
            "category":"Freight",
            "type":"Transportation"
        }
    ],
    "sg:phone":"+1 319 275 4362",
    "sg:postcode":"50631",
    "sg:province":"IA",
    "sg:tags":[
        "frozen",
        "food",
        "locker",
        "plant"
    ],
    "wof:name":"Frederika Locker",
    "wof:placetype":"venue"
},
  "geometry": {"coordinates":[-92.30798299999999,42.881501],"type":"Point"}
}