{
  "type": "Feature",
  "properties": {
    "iso:country":"US",
    "sg:address":"1415 Coral Ridge Ave",
    "sg:city":"Coralville",
    "sg:classifiers":[
        {
            "category":"Cinema",
            "subcategory":"Movie Theater",
            "type":"Entertainment"
        }
    ],
    "sg:phone":"+1 319 625 2100",
    "sg:postcode":"52241",
    "sg:province":"IA",
    "wof:name":"Coral Ridge 10 Theatres",
    "wof:placetype":"venue"
},
  "geometry": {"coordinates":[-91.608332,41.691461],"type":"Point"}
}