{
  "type": "Feature",
  "properties": {
    "iso:country":"US",
    "sg:address":"3505 104th St",
    "sg:city":"Urbandale",
    "sg:classifiers":[
        {
            "category":"Wholesale",
            "subcategory":"Machinery & Supplies",
            "type":"Manufacturing & Wholesale Goods"
        }
    ],
    "sg:phone":"+1 515 278 5422",
    "sg:postcode":"50322",
    "sg:province":"IA",
    "sg:tags":[
        "equipment",
        "safety",
        "clothing"
    ],
    "sg:website":"www.omarksafety.com",
    "wof:name":"Omark Corp",
    "wof:placetype":"venue"
},
  "geometry": {"coordinates":[-93.760583,41.625864],"type":"Point"}
}