{
  "type": "Feature",
  "properties": {
    "addr:full":"915 W Milwaukee Ave Storm Lake IA 50588",
    "addr:housenumber":"915",
    "addr:postcode":"50588",
    "addr:street":"W Milwaukee Ave",
    "iso:country":"US",
    "sg:address":"915 W Milwaukee Ave",
    "sg:city":"Storm Lake",
    "sg:classifiers":[
        {
            "category":"Autos & Motor Vehicles",
            "subcategory":"Automobile Sales",
            "type":"Retail Goods"
        }
    ],
    "sg:phone":"+1 712 732 1431",
    "sg:postcode":"50588",
    "sg:province":"IA",
    "sg:tags":[
        "car",
        "dealer"
    ],
    "wof:name":"D E & A Auto Sale",
    "wof:placetype":"venue"
},
  "geometry": {"coordinates":[-95.214038,42.647545],"type":"Point"}
}