{
  "type": "Feature",
  "properties": {
    "iso:country":"US",
    "sg:address":"2057 Rose Rd",
    "sg:city":"Madrid",
    "sg:phone":"+1 515 795 3337",
    "sg:postcode":"50156",
    "sg:province":"IA",
    "sg:tags":[
        "farm",
        "corn",
        "grain",
        "cash"
    ],
    "wof:name":"Larry Shearer",
    "wof:placetype":"venue"
},
  "geometry": {"coordinates":[-93.832004,41.917322],"type":"Point"}
}