{
  "type": "Feature",
  "properties": {
    "iso:country":"US",
    "sg:address":"208 E Washington St",
    "sg:city":"Exira",
    "sg:classifiers":[
        {
            "category":"Autos & Motor Vehicles",
            "subcategory":"Fuel & Gas Station",
            "type":"Retail Goods"
        }
    ],
    "sg:phone":"+1 712 268 2600",
    "sg:postcode":"50076",
    "sg:province":"IA",
    "sg:tags":[
        "oil"
    ],
    "wof:name":"Exira Farm Svc",
    "wof:placetype":"venue"
},
  "geometry": {"coordinates":[-94.875451,41.591196],"type":"Point"}
}