{
  "type": "Feature",
  "properties": {
    "iso:country":"US",
    "sg:address":"102 W Kimberly Rd",
    "sg:city":"Davenport",
    "sg:classifiers":[
        {
            "category":"Shopping",
            "subcategory":"Gifts & Souvenirs",
            "type":"Retail Goods"
        }
    ],
    "sg:phone":"+1 563 388 1521",
    "sg:postcode":"52806",
    "sg:province":"IA",
    "sg:tags":[
        "shop"
    ],
    "wof:name":"Gifts Greetings & Gourmet",
    "wof:placetype":"venue"
},
  "geometry": {"coordinates":[-90.58023300000001,41.560279],"type":"Point"}
}