{
  "type": "Feature",
  "properties": {
    "addr:full":"15720 Copperhead Rd Ottumwa IA 52501",
    "addr:postcode":"15720;52501",
    "addr:street":"Copperhead Rd",
    "iso:country":"US",
    "sg:address":"15720 Copperhead Rd",
    "sg:city":"Ottumwa",
    "sg:classifiers":[
        {
            "category":"Organizations",
            "subcategory":"Religious Organization",
            "type":"Services"
        }
    ],
    "sg:phone":"+1 641 684 6218",
    "sg:postcode":"52501",
    "sg:province":"IA",
    "wof:name":"Zion Community Church Of God",
    "wof:placetype":"venue"
},
  "geometry": {"coordinates":[-92.463561,40.944783],"type":"Point"}
}