{
  "type": "Feature",
  "properties": {
    "addr:full":"1652 Derby Ave NW Swisher IA 52338",
    "addr:housenumber":"1652",
    "addr:postcode":"52338",
    "addr:street":"Derby Ave Nw",
    "iso:country":"US",
    "sg:address":"1652 Derby Ave NW",
    "sg:city":"Swisher",
    "sg:classifiers":[
        {
            "category":"Building & Trades",
            "subcategory":"Construction",
            "type":"Services"
        }
    ],
    "sg:phone":"+1 319 846 2088",
    "sg:postcode":"52338",
    "sg:province":"IA",
    "sg:tags":[
        "boring",
        "drilling",
        "contractor"
    ],
    "wof:name":"Terrell Construction Inc",
    "wof:placetype":"venue"
},
  "geometry": {"coordinates":[-91.76335899999999,41.811963],"type":"Point"}
}