{
  "type": "Feature",
  "properties": {
    "iso:country":"US",
    "sg:address":"30 N 25th St",
    "sg:city":"Fort Dodge",
    "sg:classifiers":[
        {
            "category":"Wholesale",
            "subcategory":"Machinery & Supplies",
            "type":"Manufacturing & Wholesale Goods"
        }
    ],
    "sg:phone":"+1 515 573 8129",
    "sg:postcode":"50501",
    "sg:province":"IA",
    "sg:tags":[
        "equipment",
        "hydraulic"
    ],
    "sg:website":"www.forceamerica.com",
    "wof:name":"Force America",
    "wof:placetype":"venue"
},
  "geometry": {"coordinates":[-94.163222,42.507017],"type":"Point"}
}