{
  "type": "Feature",
  "properties": {
    "iso:country":"US",
    "sg:address":"114 Union St",
    "sg:city":"West Union",
    "sg:classifiers":[
        {
            "category":"Government",
            "subcategory":"Office",
            "type":"Public Place"
        }
    ],
    "sg:phone":"+1 563 422 3687",
    "sg:postcode":"52175",
    "sg:province":"IA",
    "wof:name":"Fayette County Recorder",
    "wof:placetype":"venue"
},
  "geometry": {"coordinates":[-91.810558,42.959815],"type":"Point"}
}