{
  "type": "Feature",
  "properties": {
    "addr:full":"419 7th Ave SW Le Mars IA 51031",
    "addr:housenumber":"419",
    "addr:postcode":"51031",
    "addr:street":"7Th Ave Sw",
    "iso:country":"US",
    "sg:address":"419 7th Ave SW",
    "sg:city":"Le Mars",
    "sg:classifiers":[
        {
            "category":"Manufacturing",
            "subcategory":"Textiles",
            "type":"Manufacturing & Wholesale Goods"
        }
    ],
    "sg:phone":"+1 712 546 9473",
    "sg:postcode":"51031",
    "sg:province":"IA",
    "sg:tags":[
        "mfg"
    ],
    "wof:name":"Eggs By Elaine",
    "wof:placetype":"venue"
},
  "geometry": {"coordinates":[-96.176799,42.787953],"type":"Point"}
}