{
  "type": "Feature",
  "properties": {
    "addr:full":"706 W 7th St Sioux City IA 51103",
    "addr:housenumber":"706",
    "addr:postcode":"51103",
    "addr:street":"W 7Th St",
    "iso:country":"US",
    "sg:address":"706 W 7th St",
    "sg:city":"Sioux City",
    "sg:classifiers":[
        {
            "category":"Retail",
            "subcategory":"Auto Repair",
            "type":"Services"
        }
    ],
    "sg:phone":"+1 712 277 8385",
    "sg:postcode":"51103",
    "sg:province":"IA",
    "sg:tags":[
        "repairing",
        "automobile"
    ],
    "wof:name":"John's Auto Repair",
    "wof:placetype":"venue"
},
  "geometry": {"coordinates":[-96.41663699999999,42.502234],"type":"Point"}
}