{
  "type": "Feature",
  "properties": {
    "iso:country":"US",
    "sg:address":"815 Maple St",
    "sg:city":"Burlington",
    "sg:classifiers":[
        {
            "category":"Personal",
            "subcategory":"Barber",
            "type":"Services"
        }
    ],
    "sg:phone":"+1 319 753 0630",
    "sg:postcode":"52601",
    "sg:province":"IA",
    "sg:tags":[
        "shop"
    ],
    "wof:name":"Krieger's Barber Shop",
    "wof:placetype":"venue"
},
  "geometry": {"coordinates":[-91.109523,40.804646],"type":"Point"}
}