{
  "type": "Feature",
  "properties": {
    "iso:country":"US",
    "sg:address":"2317 Quinton Ave",
    "sg:city":"Rockwell City",
    "sg:phone":"+1 712 297 9000",
    "sg:postcode":"50579",
    "sg:province":"IA",
    "sg:tags":[
        "farm",
        "soybean"
    ],
    "wof:name":"Strandberg Farms",
    "wof:placetype":"venue"
},
  "geometry": {"coordinates":[-94.592584,42.454397],"type":"Point"}
}