{
  "type": "Feature",
  "properties": {
    "addr:full":"707 W Sheridan Ave Shenandoah IA 51601",
    "addr:housenumber":"707",
    "addr:postcode":"51601",
    "addr:street":"W Sheridan Ave",
    "iso:country":"US",
    "sg:address":"707 W Sheridan Ave",
    "sg:city":"Shenandoah",
    "sg:classifiers":[
        {
            "category":"Personal",
            "subcategory":"Beauty Salon",
            "type":"Services"
        }
    ],
    "sg:phone":"+1 712 246 4080",
    "sg:postcode":"51601",
    "sg:province":"IA",
    "wof:name":"Hair Professionals",
    "wof:placetype":"venue"
},
  "geometry": {"coordinates":[-95.375078,40.766012],"type":"Point"}
}