{
  "type": "Feature",
  "properties": {
    "addr:full":"718 NE Broadway Ave Des Moines IA 50313",
    "addr:housenumber":"718",
    "addr:postcode":"50313",
    "addr:street":"Ne Broadway Ave",
    "iso:country":"US",
    "sg:address":"718 NE Broadway Ave",
    "sg:city":"Des Moines",
    "sg:classifiers":[
        {
            "category":"Retail",
            "subcategory":"Auto Repair",
            "type":"Services"
        }
    ],
    "sg:phone":"+1 515 280 1103",
    "sg:postcode":"50313",
    "sg:province":"IA",
    "sg:tags":[
        "body",
        "automobile",
        "painting"
    ],
    "wof:name":"Auto Mend",
    "wof:placetype":"venue"
},
  "geometry": {"coordinates":[-93.60811,41.644121],"type":"Point"}
}