{
  "type": "Feature",
  "properties": {
    "iso:country":"US",
    "sg:address":"2782 Fairgrounds Rd",
    "sg:city":"Adel",
    "sg:classifiers":[
        {
            "category":"Home & Garden",
            "subcategory":"Hardware",
            "type":"Retail Goods"
        }
    ],
    "sg:phone":"+1 515 993 4831",
    "sg:postcode":"50003",
    "sg:province":"IA",
    "sg:tags":[
        "saw"
    ],
    "wof:name":"Annear Equipment Inc",
    "wof:placetype":"venue"
},
  "geometry": {"coordinates":[-94.02083500000001,41.630196],"type":"Point"}
}