{
  "type": "Feature",
  "properties": {
    "addr:full":"4908 230th St Ashton IA 51232",
    "addr:housenumber":"4908",
    "addr:postcode":"51232",
    "addr:street":"230Th St",
    "iso:country":"US",
    "sg:address":"4908 230th St",
    "sg:city":"Ashton",
    "sg:phone":"+1 712 724 6146",
    "sg:postcode":"51232",
    "sg:province":"IA",
    "sg:tags":[
        "beef",
        "farm",
        "cash",
        "grain",
        "cattle",
        "feedlot"
    ],
    "wof:name":"Larry Strouth",
    "wof:placetype":"venue"
},
  "geometry": {"coordinates":[-95.820589,43.315995],"type":"Point"}
}