{
  "type": "Feature",
  "properties": {
    "addr:full":"304 6th Ave Clarence IA 52216",
    "addr:housenumber":"304",
    "addr:postcode":"52216",
    "addr:street":"6Th Ave",
    "iso:country":"US",
    "sg:address":"304 6th Ave",
    "sg:city":"Clarence",
    "sg:classifiers":[
        {
            "category":"Organizations",
            "subcategory":"Community Association",
            "type":"Services"
        }
    ],
    "sg:phone":"+1 563 452 3492",
    "sg:postcode":"52216",
    "sg:province":"IA",
    "sg:tags":[
        "military"
    ],
    "wof:name":"American Legion",
    "wof:placetype":"venue"
},
  "geometry": {"coordinates":[-91.056438,41.888667],"type":"Point"}
}