{
  "type": "Feature",
  "properties": {
    "addr:full":"26202 S Ave Reinbeck IA 50669",
    "addr:housenumber":"26202",
    "addr:postcode":"50669",
    "addr:street":"S Ave",
    "iso:country":"US",
    "sg:address":"26202 S Ave",
    "sg:city":"Reinbeck",
    "sg:classifiers":[
        {
            "category":"Farming",
            "subcategory":"Livestock Farm",
            "type":"Manufacturing & Wholesale Goods"
        }
    ],
    "sg:phone":"+1 319 345 2695",
    "sg:postcode":"50669",
    "sg:province":"IA",
    "sg:tags":[
        "feedlot",
        "hog",
        "or",
        "beef",
        "cattle"
    ],
    "wof:name":"Michael Lovell",
    "wof:placetype":"venue"
},
  "geometry": {"coordinates":[-92.67053199999999,42.322827],"type":"Point"}
}