{
  "type": "Feature",
  "properties": {
    "addr:full":"3121 140th St Sumner IA 50674",
    "addr:housenumber":"3121",
    "addr:postcode":"50674",
    "addr:street":"140Th St",
    "iso:country":"US",
    "sg:address":"3121 140th St",
    "sg:city":"Sumner",
    "sg:classifiers":[
        {
            "category":"Building & Trades",
            "subcategory":"Landscaping Services",
            "type":"Services"
        }
    ],
    "sg:phone":"+1 563 578 5443",
    "sg:postcode":"50674",
    "sg:province":"IA",
    "sg:tags":[
        "landscape",
        "contractor"
    ],
    "wof:name":"Extra Touch Lawn Care",
    "wof:placetype":"venue"
},
  "geometry": {"coordinates":[-92.13781899999999,42.847527],"type":"Point"}
}