{
  "type": "Feature",
  "properties": {
    "iso:country":"US",
    "sg:address":"302 E 7th St",
    "sg:city":"Carroll",
    "sg:classifiers":[
        {
            "category":"Professional",
            "subcategory":"Lawyer & Legal Services",
            "type":"Services"
        }
    ],
    "sg:phone":"+1 712 792 1300",
    "sg:postcode":"51401",
    "sg:province":"IA",
    "sg:tags":[
        "attorney"
    ],
    "wof:name":"Wilcox Polking Gerken Copeland",
    "wof:placetype":"venue"
},
  "geometry": {"coordinates":[-94.86384,42.065876],"type":"Point"}
}