{
  "type": "Feature",
  "properties": {
    "iso:country":"US",
    "sg:address":"1315 E San Marnan Dr",
    "sg:city":"Waterloo",
    "sg:classifiers":[
        {
            "category":"Restaurant",
            "type":"Food & Drink"
        }
    ],
    "sg:menulink":"http://www.allmenus.com/ia/waterloo/14004-olive-garden-italian-restaurant/menu/",
    "sg:phone":"+1 319 235 6494",
    "sg:postcode":"50702",
    "sg:province":"IA",
    "sg:tags":[
        "italian"
    ],
    "wof:name":"Olive Garden Italian Restaurant",
    "wof:placetype":"venue"
},
  "geometry": {"coordinates":[-92.330479,42.461619],"type":"Point"}
}