{
  "type": "Feature",
  "properties": {
    "iso:country":"US",
    "sg:address":"520 10th Ave",
    "sg:city":"Coralville",
    "sg:classifiers":[
        {
            "category":"Shopping",
            "subcategory":"Computers & Home Electronics",
            "type":"Retail Goods"
        }
    ],
    "sg:phone":"+1 319 337 9800",
    "sg:postcode":"52241",
    "sg:province":"IA",
    "sg:tags":[
        "software"
    ],
    "sg:website":"www.appliedsystems.com",
    "wof:name":"Applied Systems",
    "wof:placetype":"venue"
},
  "geometry": {"coordinates":[-91.57826900000001,41.676208],"type":"Point"}
}