{
  "type": "Feature",
  "properties": {
    "addr:full":"1551 Indian Hills Dr Sioux City IA 51104",
    "addr:housenumber":"1551",
    "addr:postcode":"51104",
    "addr:street":"Indian Hills Dr",
    "iso:country":"US",
    "sg:address":"1551 Indian Hills Dr",
    "sg:city":"Sioux City",
    "sg:classifiers":[
        {
            "category":"Health Services",
            "subcategory":"Doctor",
            "type":"Services"
        }
    ],
    "sg:phone":"+1 712 277 1311",
    "sg:postcode":"51104",
    "sg:province":"IA",
    "sg:tags":[
        "dentist"
    ],
    "wof:name":"Mitchell C Kulawik DDS",
    "wof:placetype":"venue"
},
  "geometry": {"coordinates":[-96.390355,42.532606],"type":"Point"}
}