{
  "type": "Feature",
  "properties": {
    "iso:country":"US",
    "sg:address":"204 N Jefferson St",
    "sg:city":"Mt Pleasant",
    "sg:classifiers":[
        {
            "category":"Health Services",
            "subcategory":"Doctor",
            "type":"Services"
        }
    ],
    "sg:phone":"+1 319 385 8805",
    "sg:postcode":"52641",
    "sg:province":"IA",
    "sg:tags":[
        "physician",
        "surgeon"
    ],
    "wof:name":"Hometown Medical Ctr",
    "wof:placetype":"venue"
},
  "geometry": {"coordinates":[-91.554221,40.968364],"type":"Point"}
}