{
  "type": "Feature",
  "properties": {
    "iso:country":"US",
    "sg:address":"319 Grand Ave",
    "sg:city":"Spencer",
    "sg:classifiers":[
        {
            "category":"Professional",
            "subcategory":"Employment Agencies",
            "type":"Services"
        }
    ],
    "sg:phone":"+1 712 262 5990",
    "sg:postcode":"51301",
    "sg:province":"IA",
    "sg:tags":[
        "opportunity"
    ],
    "wof:name":"Rudy Salem Staffing Svc",
    "wof:placetype":"venue"
},
  "geometry": {"coordinates":[-95.144752,43.14116],"type":"Point"}
}