{
  "type": "Feature",
  "properties": {
    "addr:full":"3104 230th St Ridgeway IA 52165",
    "addr:housenumber":"3104",
    "addr:postcode":"52165",
    "addr:street":"230Th St",
    "iso:country":"US",
    "sg:address":"3104 230th St",
    "sg:city":"Ridgeway",
    "sg:classifiers":[
        {
            "category":"Building & Trades",
            "subcategory":"Construction",
            "type":"Services"
        }
    ],
    "sg:phone":"+1 563 737 2486",
    "sg:postcode":"52165",
    "sg:province":"IA",
    "sg:tags":[
        "contractor"
    ],
    "wof:name":"Turkey River Tile Inc",
    "wof:placetype":"venue"
},
  "geometry": {"coordinates":[-92.017049,43.270009],"type":"Point"}
}