{
  "type": "Feature",
  "properties": {
    "addr:full":"2418 Wilkes Ave Davenport IA 52804",
    "addr:housenumber":"2418",
    "addr:postcode":"52804",
    "addr:street":"Wilkes Ave",
    "iso:country":"US",
    "sg:address":"2418 Wilkes Ave",
    "sg:city":"Davenport",
    "sg:classifiers":[
        {
            "category":"Retail",
            "subcategory":"Auto Repair",
            "type":"Services"
        }
    ],
    "sg:phone":"+1 563 326 5144",
    "sg:postcode":"52804",
    "sg:province":"IA",
    "sg:tags":[
        "automobile",
        "restoration",
        "classic"
    ],
    "wof:name":"Phoenix Restoration",
    "wof:placetype":"venue"
},
  "geometry": {"coordinates":[-90.603245,41.545323],"type":"Point"}
}