{
  "type": "Feature",
  "properties": {
    "addr:full":"214 Main St Norwalk IA 50211",
    "addr:housenumber":"214",
    "addr:postcode":"50211",
    "addr:street":"Main St",
    "iso:country":"US",
    "sg:address":"214 Main St",
    "sg:city":"Norwalk",
    "sg:classifiers":[
        {
            "category":"Professional",
            "subcategory":"Detective & Security Services",
            "type":"Services"
        }
    ],
    "sg:phone":"+1 515 210 8660",
    "sg:postcode":"50211",
    "sg:province":"IA",
    "sg:tags":[
        "guard"
    ],
    "wof:name":"Philip Grimm",
    "wof:placetype":"venue"
},
  "geometry": {"coordinates":[-93.678769,41.470192],"type":"Point"}
}