{
  "type": "Feature",
  "properties": {
    "iso:country":"US",
    "sg:address":"1100 S Grand Ave",
    "sg:city":"Charles City",
    "sg:classifiers":[
        {
            "category":"Restaurant",
            "type":"Food & Drink"
        }
    ],
    "sg:phone":"+1 641 228 2115",
    "sg:postcode":"50616",
    "sg:province":"IA",
    "wof:name":"Comet Bowl",
    "wof:placetype":"venue"
},
  "geometry": {"coordinates":[-92.672561,43.056978],"type":"Point"}
}