{
  "type": "Feature",
  "properties": {
    "addr:full":"31616 State Hwy 92 Council Bluffs IA 51503",
    "addr:housenumber":"31616",
    "addr:postcode":"51503",
    "addr:street":"State Hwy 92",
    "iso:country":"US",
    "sg:address":"31616 State Hwy 92",
    "sg:city":"Council Bluffs",
    "sg:classifiers":[
        {
            "category":"Wholesale",
            "subcategory":"Farm Supplies",
            "type":"Manufacturing & Wholesale Goods"
        }
    ],
    "sg:phone":"+1 712 487 3223",
    "sg:postcode":"51503",
    "sg:province":"IA",
    "sg:tags":[
        "feed"
    ],
    "wof:name":"Farm Service Co",
    "wof:placetype":"venue"
},
  "geometry": {"coordinates":[-95.582632,41.232712],"type":"Point"}
}