{
  "type": "Feature",
  "properties": {
    "addr:full":"737 Mormon Trek Blvd Iowa City IA 52246",
    "addr:housenumber":"737",
    "addr:postcode":"52246",
    "addr:street":"Mormon Trek Blvd",
    "iso:country":"US",
    "sg:address":"737 Mormon Trek Blvd",
    "sg:city":"Iowa City",
    "sg:classifiers":[
        {
            "category":"Retail",
            "subcategory":"Self-service Laundry",
            "type":"Services"
        }
    ],
    "sg:phone":"+1 319 337 7368",
    "sg:postcode":"52246",
    "sg:province":"IA",
    "sg:tags":[
        "coin"
    ],
    "wof:name":"Laundromania 24 Hour",
    "wof:placetype":"venue"
},
  "geometry": {"coordinates":[-91.57406400000001,41.650833],"type":"Point"}
}