{
  "type": "Feature",
  "properties": {
    "iso:country":"US",
    "sg:address":"1517 Charles Ave",
    "sg:city":"West Branch",
    "sg:classifiers":[
        {
            "category":"Farming",
            "subcategory":"Livestock Farm",
            "type":"Manufacturing & Wholesale Goods"
        }
    ],
    "sg:phone":"+1 319 643 5966",
    "sg:postcode":"52358",
    "sg:province":"IA",
    "sg:tags":[
        "beef",
        "feedlot",
        "cattle"
    ],
    "wof:name":"Karl Jennings",
    "wof:placetype":"venue"
},
  "geometry": {"coordinates":[-91.327117,41.727396],"type":"Point"}
}