{
  "type": "Feature",
  "properties": {
    "iso:country":"US",
    "sg:address":"300 E Washington St",
    "sg:city":"Mt Pleasant",
    "sg:classifiers":[
        {
            "category":"Organizations",
            "subcategory":"Religious Organization",
            "type":"Services"
        }
    ],
    "sg:phone":"+1 319 385 3447",
    "sg:postcode":"52641",
    "sg:province":"IA",
    "sg:tags":[
        "church"
    ],
    "wof:name":"Congregational-Universalist",
    "wof:placetype":"venue"
},
  "geometry": {"coordinates":[-91.550641,40.965179],"type":"Point"}
}