{
  "type": "Feature",
  "properties": {
    "iso:country":"US",
    "sg:address":"10098 S 12th Ave E",
    "sg:city":"Kellogg",
    "sg:classifiers":[
        {
            "category":"Farming",
            "subcategory":"Farm",
            "type":"Manufacturing & Wholesale Goods"
        }
    ],
    "sg:phone":"+1 641 526 3473",
    "sg:postcode":"50135",
    "sg:province":"IA",
    "sg:tags":[
        "crop",
        "general"
    ],
    "wof:name":"Al Hansen",
    "wof:placetype":"venue"
},
  "geometry": {"coordinates":[-92.897311,41.688204],"type":"Point"}
}