{
  "type": "Feature",
  "properties": {
    "addr:full":"1427 Western Ave Marengo IA 52301",
    "addr:housenumber":"1427",
    "addr:postcode":"52301",
    "addr:street":"Western Ave",
    "iso:country":"US",
    "sg:address":"1427 Western Ave",
    "sg:city":"Marengo",
    "sg:classifiers":[
        {
            "category":"Building & Trades",
            "subcategory":"Construction",
            "type":"Services"
        }
    ],
    "sg:phone":"+1 319 642 7114",
    "sg:postcode":"52301",
    "sg:province":"IA",
    "sg:tags":[
        "house"
    ],
    "wof:name":"Fiser Construction",
    "wof:placetype":"venue"
},
  "geometry": {"coordinates":[-92.07415399999999,41.803981],"type":"Point"}
}