{
  "type": "Feature",
  "properties": {
    "addr:full":"24880 145th Ave Eldridge IA 52748",
    "addr:housenumber":"24880",
    "addr:postcode":"52748",
    "addr:street":"145Th Ave",
    "iso:country":"US",
    "sg:address":"24880 145th Ave",
    "sg:city":"Eldridge",
    "sg:classifiers":[
        {
            "category":"Wholesale",
            "subcategory":"Non-durable Goods",
            "type":"Manufacturing & Wholesale Goods"
        }
    ],
    "sg:phone":"+1 563 285 7009",
    "sg:postcode":"52748",
    "sg:province":"IA",
    "sg:tags":[
        "product",
        "mfg"
    ],
    "wof:name":"Buttons-N-More",
    "wof:placetype":"venue"
},
  "geometry": {"coordinates":[-90.61723600000001,41.669218],"type":"Point"}
}