{
  "type": "Feature",
  "properties": {
    "iso:country":"US",
    "sg:address":"605 Garfield St",
    "sg:city":"Gladbrook",
    "sg:classifiers":[
        {
            "category":"Health Services",
            "subcategory":"Nursing And Care Facility",
            "type":"Services"
        }
    ],
    "sg:phone":"+1 641 473 2016",
    "sg:postcode":"50635",
    "sg:province":"IA",
    "sg:tags":[
        "home",
        "convalescent"
    ],
    "wof:name":"Westbrook Acres",
    "wof:placetype":"venue"
},
  "geometry": {"coordinates":[-92.720181,42.183403],"type":"Point"}
}