{
  "type": "Feature",
  "properties": {
    "iso:country":"US",
    "sg:address":"131 6th St",
    "sg:city":"De Witt",
    "sg:classifiers":[
        {
            "category":"Wholesale",
            "subcategory":"Machinery & Supplies",
            "type":"Manufacturing & Wholesale Goods"
        }
    ],
    "sg:phone":"+1 563 659 9221",
    "sg:postcode":"52742",
    "sg:province":"IA",
    "sg:tags":[
        "rubber",
        "product"
    ],
    "wof:name":"Mark Gassman Gates Corp",
    "wof:placetype":"venue"
},
  "geometry": {"coordinates":[-90.532106,41.8212],"type":"Point"}
}