{
  "type": "Feature",
  "properties": {
    "addr:full":"221 N Pine St Creston IA 50801",
    "addr:housenumber":"221",
    "addr:postcode":"50801",
    "addr:street":"N Pine St",
    "iso:country":"US",
    "sg:address":"221 N Pine St",
    "sg:city":"Creston",
    "sg:classifiers":[
        {
            "category":"Autos & Motor Vehicles",
            "subcategory":"Auto Supplies",
            "type":"Retail Goods"
        }
    ],
    "sg:phone":"+1 641 782 2125",
    "sg:postcode":"50801",
    "sg:province":"IA",
    "sg:tags":[
        "automobile",
        "parts"
    ],
    "wof:name":"NAPA-Creston",
    "wof:placetype":"venue"
},
  "geometry": {"coordinates":[-94.361411,41.059457],"type":"Point"}
}