{
  "type": "Feature",
  "properties": {
    "iso:country":"US",
    "sg:address":"2764 Wheatland Rd",
    "sg:city":"New Albin",
    "sg:phone":"+1 563 544 4312",
    "sg:postcode":"52160",
    "sg:province":"IA",
    "sg:tags":[
        "farm",
        "corn"
    ],
    "wof:name":"Alan Heitman",
    "wof:placetype":"venue"
},
  "geometry": {"coordinates":[-91.39657699999999,43.459745],"type":"Point"}
}