{
  "type": "Feature",
  "properties": {
    "addr:full":"24271 215th St Bloomfield IA 52537",
    "addr:housenumber":"24271",
    "addr:postcode":"52537",
    "addr:street":"215Th St",
    "iso:country":"US",
    "sg:address":"24271 215th St",
    "sg:city":"Bloomfield",
    "sg:classifiers":[
        {
            "category":"Wholesale",
            "subcategory":"Stationery",
            "type":"Manufacturing & Wholesale Goods"
        }
    ],
    "sg:phone":"+1 641 664 2829",
    "sg:postcode":"52537",
    "sg:province":"IA",
    "sg:tags":[
        "business",
        "form",
        "system"
    ],
    "wof:name":"J & J Business",
    "wof:placetype":"venue"
},
  "geometry": {"coordinates":[-92.38007899999999,40.747586],"type":"Point"}
}