{
  "type": "Feature",
  "properties": {
    "iso:country":"US",
    "sg:address":"116 S Main St",
    "sg:city":"Mt Pleasant",
    "sg:classifiers":[
        {
            "category":"Shopping",
            "subcategory":"Clothing, Apparel, & Fashions",
            "type":"Retail Goods"
        }
    ],
    "sg:phone":"+1 319 385 3030",
    "sg:postcode":"52641",
    "sg:province":"IA",
    "wof:name":"Halltree",
    "wof:placetype":"venue"
},
  "geometry": {"coordinates":[-91.553141,40.966376],"type":"Point"}
}