{
  "type": "Feature",
  "properties": {
    "addr:full":"403 W 7th St Sioux City IA 51103",
    "addr:housenumber":"403",
    "addr:postcode":"51103",
    "addr:street":"W 7Th St",
    "iso:country":"US",
    "sg:address":"403 W 7th St",
    "sg:city":"Sioux City",
    "sg:classifiers":[
        {
            "category":"Retail",
            "subcategory":"Auto Repair",
            "type":"Services"
        }
    ],
    "sg:phone":"+1 712 277 4198",
    "sg:postcode":"51103",
    "sg:province":"IA",
    "sg:tags":[
        "repairing",
        "automobile"
    ],
    "wof:name":"J & J Auto Repair",
    "wof:placetype":"venue"
},
  "geometry": {"coordinates":[-96.413394,42.500852],"type":"Point"}
}