{
  "type": "Feature",
  "properties": {
    "addr:full":"806 7th St Boone IA 50036",
    "addr:housenumber":"806",
    "addr:postcode":"50036",
    "addr:street":"7Th St",
    "iso:country":"US",
    "sg:address":"806 7th St",
    "sg:city":"Boone",
    "sg:classifiers":[
        {
            "category":"Organizations",
            "subcategory":"Religious Organization",
            "type":"Services"
        }
    ],
    "sg:phone":"+1 515 433 6133",
    "sg:postcode":"50036",
    "sg:province":"IA",
    "sg:tags":[
        "church"
    ],
    "wof:name":"Grace Community Church",
    "wof:placetype":"venue"
},
  "geometry": {"coordinates":[-93.881237,42.062648],"type":"Point"}
}