{
  "type": "Feature",
  "properties": {
    "iso:country":"US",
    "sg:address":"520 4th St S",
    "sg:city":"Albert City",
    "sg:classifiers":[
        {
            "category":"Building & Trades",
            "subcategory":"Construction",
            "type":"Services"
        }
    ],
    "sg:phone":"+1 712 843 5757",
    "sg:postcode":"50510",
    "sg:province":"IA",
    "sg:tags":[
        "general",
        "contractor"
    ],
    "wof:name":"Delwyn Johnson Construction",
    "wof:placetype":"venue"
},
  "geometry": {"coordinates":[-94.951465,42.777413],"type":"Point"}
}