{
  "type": "Feature",
  "properties": {
    "addr:full":"205 2nd St Keosauqua IA 52565",
    "addr:housenumber":"205",
    "addr:postcode":"52565",
    "addr:street":"2Nd St",
    "iso:country":"US",
    "sg:address":"205 2nd St",
    "sg:city":"Keosauqua",
    "sg:classifiers":[
        {
            "category":"Farming",
            "subcategory":"Livestock Farm",
            "type":"Manufacturing & Wholesale Goods"
        }
    ],
    "sg:phone":"+1 319 494 5536",
    "sg:postcode":"52565",
    "sg:province":"IA",
    "sg:tags":[
        "beef",
        "feedlot",
        "soybean",
        "cattle"
    ],
    "wof:name":"Gordy Russel",
    "wof:placetype":"venue"
},
  "geometry": {"coordinates":[-91.965778,40.728464],"type":"Point"}
}