{
  "type": "Feature",
  "properties": {
    "addr:full":"901 S 4th St Clinton IA 52732",
    "addr:housenumber":"901",
    "addr:postcode":"52732",
    "addr:street":"S 4Th St",
    "iso:country":"US",
    "sg:address":"901 S 4th St",
    "sg:city":"Clinton",
    "sg:classifiers":[
        {
            "category":"Retail",
            "subcategory":"Photofinishing",
            "type":"Services"
        },
        {
            "category":"Food & Beverages",
            "subcategory":"Groceries & Convenience Stores",
            "type":"Retail Goods"
        },
        {
            "category":"Shopping",
            "subcategory":"Pharmacy",
            "type":"Retail Goods"
        },
        {
            "category":"Shopping",
            "subcategory":"Florist",
            "type":"Retail Goods"
        }
    ],
    "sg:phone":"+1 563 243 6162",
    "sg:postcode":"52732",
    "sg:province":"IA",
    "sg:tags":[
        "photo",
        "product",
        "health",
        "finishing",
        "wellness"
    ],
    "sg:website":"http://www.hy-vee.com",
    "wof:name":"Hy-Vee",
    "wof:placetype":"venue"
},
  "geometry": {"coordinates":[-90.193214,41.836517],"type":"Point"}
}