{
  "type": "Feature",
  "properties": {
    "addr:full":"1205 Sunnyside Ln Atlantic IA 50022",
    "addr:housenumber":"1205",
    "addr:postcode":"50022",
    "addr:street":"Sunnyside Ln",
    "iso:country":"US",
    "sg:address":"1205 Sunnyside Ln",
    "sg:city":"Atlantic",
    "sg:classifiers":[
        {
            "category":"Professional",
            "subcategory":"Accounting & Tax Preparation",
            "type":"Services"
        }
    ],
    "sg:phone":"+1 712 243 4268",
    "sg:postcode":"50022",
    "sg:province":"IA",
    "sg:tags":[
        "return",
        "filing"
    ],
    "wof:name":"H & R Block Tax Svc",
    "wof:placetype":"venue"
},
  "geometry": {"coordinates":[-95.028256,41.399746],"type":"Point"}
}