{
  "type": "Feature",
  "properties": {
    "iso:country":"US",
    "sg:address":"611 Douglas Ave",
    "sg:city":"Ackley",
    "sg:classifiers":[
        {
            "category":"Building & Trades",
            "subcategory":"Construction",
            "type":"Services"
        }
    ],
    "sg:phone":"+1 641 847 2234",
    "sg:postcode":"50601",
    "sg:province":"IA",
    "sg:tags":[
        "company"
    ],
    "wof:name":"Boekholder Construction Co",
    "wof:placetype":"venue"
},
  "geometry": {"coordinates":[-93.063756,42.555797],"type":"Point"}
}