{
  "type": "Feature",
  "properties": {
    "addr:full":"3433 Virginia St Sioux City IA 51104",
    "addr:housenumber":"3433",
    "addr:postcode":"51104",
    "addr:street":"Virginia St",
    "iso:country":"US",
    "sg:address":"3433 Virginia St",
    "sg:city":"Sioux City",
    "sg:classifiers":[
        {
            "category":"Retail",
            "subcategory":"Laundry & Dry Cleaning",
            "type":"Services"
        }
    ],
    "sg:phone":"+1 712 277 2777",
    "sg:postcode":"51104",
    "sg:province":"IA",
    "sg:tags":[
        "cleaners",
        "rug",
        "carpet"
    ],
    "wof:name":"Harstad Carpet Cleaning",
    "wof:placetype":"venue"
},
  "geometry": {"coordinates":[-96.398048,42.529913],"type":"Point"}
}