{
  "type": "Feature",
  "properties": {
    "iso:country":"US",
    "sg:address":"3142 225th St",
    "sg:city":"Worthington",
    "sg:classifiers":[
        {
            "category":"Farming",
            "subcategory":"Dairy Farm",
            "type":"Manufacturing & Wholesale Goods"
        }
    ],
    "sg:phone":"+1 563 875 8520",
    "sg:postcode":"52078",
    "sg:province":"IA",
    "sg:tags":[
        "hog",
        "or",
        "feedlot"
    ],
    "wof:name":"Loras Bagge",
    "wof:placetype":"venue"
},
  "geometry": {"coordinates":[-91.177792,42.462788],"type":"Point"}
}