{
  "type": "Feature",
  "properties": {
    "iso:country":"US",
    "sg:address":"6716 29th Ave",
    "sg:city":"Shellsburg",
    "sg:phone":"+1 319 436 2918",
    "sg:postcode":"52332",
    "sg:province":"IA",
    "sg:tags":[
        "hog",
        "farm",
        "cash",
        "grain",
        "or",
        "feedlot"
    ],
    "wof:name":"Mark Bierschenk",
    "wof:placetype":"venue"
},
  "geometry": {"coordinates":[-91.93219000000001,42.048416],"type":"Point"}
}