{
  "type": "Feature",
  "properties": {
    "addr:full":"2190 140th St Kalona IA 52247",
    "addr:housenumber":"2190",
    "addr:postcode":"52247",
    "addr:street":"140Th St",
    "iso:country":"US",
    "sg:address":"2190 140th St",
    "sg:city":"Kalona",
    "sg:classifiers":[
        {
            "category":"Shopping",
            "subcategory":"Florist",
            "type":"Retail Goods"
        }
    ],
    "sg:phone":"+1 319 656 3987",
    "sg:postcode":"52247",
    "sg:province":"IA",
    "wof:name":"Diannes Garden",
    "wof:placetype":"venue"
},
  "geometry": {"coordinates":[-91.716536,41.453277],"type":"Point"}
}