{
  "type": "Feature",
  "properties": {
    "iso:country":"US",
    "sg:address":"2500 S Center St",
    "sg:city":"Marshalltown",
    "sg:classifiers":[
        {
            "category":"Cinema",
            "subcategory":"Movie Theater",
            "type":"Entertainment"
        }
    ],
    "sg:phone":"+1 641 752 6115",
    "sg:postcode":"50158",
    "sg:province":"IA",
    "wof:name":"Plaza 5 Theatres",
    "wof:placetype":"venue"
},
  "geometry": {"coordinates":[-92.91215,42.016777],"type":"Point"}
}