{
  "type": "Feature",
  "properties": {
    "iso:country":"US",
    "sg:address":"1249 McKinley Ave",
    "sg:city":"Des Moines",
    "sg:classifiers":[
        {
            "category":"Government",
            "subcategory":"Fire Station",
            "type":"Public Place"
        }
    ],
    "sg:phone":"+1 515 248 6008",
    "sg:postcode":"50315",
    "sg:province":"IA",
    "sg:tags":[
        "department"
    ],
    "wof:name":"Des Moines Fire Dept",
    "wof:placetype":"venue"
},
  "geometry": {"coordinates":[-93.632109,41.541065],"type":"Point"}
}