{
  "type": "Feature",
  "properties": {
    "iso:country":"US",
    "sg:address":"130 4th Ave NE",
    "sg:city":"Le Mars",
    "sg:classifiers":[
        {
            "category":"Shopping",
            "type":"Retail Goods"
        }
    ],
    "sg:phone":"+1 712 546 6446",
    "sg:postcode":"51031",
    "sg:province":"IA",
    "sg:tags":[
        "trophy",
        "medal",
        "award"
    ],
    "wof:name":"Drico Products Inc",
    "wof:placetype":"venue"
},
  "geometry": {"coordinates":[-96.16056399999999,42.794896],"type":"Point"}
}