{
  "type": "Feature",
  "properties": {
    "iso:country":"US",
    "sg:address":"5721 Merle Hay Rd",
    "sg:city":"Johnston",
    "sg:classifiers":[
        {
            "category":"Health Services",
            "subcategory":"Doctor",
            "type":"Services"
        }
    ],
    "sg:phone":"+1 515 278 2379",
    "sg:postcode":"50131",
    "sg:province":"IA",
    "sg:tags":[
        "dentist"
    ],
    "wof:name":"Richard M Reay DDS",
    "wof:placetype":"venue"
},
  "geometry": {"coordinates":[-93.69759000000001,41.662449],"type":"Point"}
}