{
  "type": "Feature",
  "properties": {
    "iso:country":"US",
    "sg:address":"1006 11th St",
    "sg:city":"Manson",
    "sg:classifiers":[
        {
            "category":"Government",
            "subcategory":"Post Office",
            "type":"Public Place"
        }
    ],
    "sg:phone":"+1 712 469 3714",
    "sg:postcode":"50563",
    "sg:province":"IA",
    "wof:name":"US Post Office",
    "wof:placetype":"venue"
},
  "geometry": {"coordinates":[-94.535572,42.530229],"type":"Point"}
}