{
  "type": "Feature",
  "properties": {
    "addr:full":"900 Hubbel St Kelley IA 50134",
    "addr:housenumber":"900",
    "addr:postcode":"50134",
    "addr:street":"Hubbel St",
    "iso:country":"US",
    "sg:address":"900 Hubbel St",
    "sg:city":"Kelley",
    "sg:classifiers":[
        {
            "category":"Building & Trades",
            "subcategory":"Electrical",
            "type":"Services"
        }
    ],
    "sg:phone":"+1 515 769 2375",
    "sg:postcode":"50134",
    "sg:province":"IA",
    "sg:tags":[
        "electric",
        "contractor"
    ],
    "wof:name":"Lighthouse Electric",
    "wof:placetype":"venue"
},
  "geometry": {"coordinates":[-93.66523100000001,41.949852],"type":"Point"}
}