{
  "type": "Feature",
  "properties": {
    "iso:country":"US",
    "sg:address":"108 W 7th St",
    "sg:city":"Carroll",
    "sg:classifiers":[
        {
            "category":"Manufacturing",
            "subcategory":"Printing",
            "type":"Manufacturing & Wholesale Goods"
        }
    ],
    "sg:phone":"+1 712 792 3901",
    "sg:postcode":"51401",
    "sg:province":"IA",
    "sg:tags":[
        "commercial"
    ],
    "wof:name":"Stone Printing Office Products",
    "wof:placetype":"venue"
},
  "geometry": {"coordinates":[-94.868076,42.06712],"type":"Point"}
}