{
  "type": "Feature",
  "properties": {
    "iso:country":"US",
    "sg:address":"105 E Main St",
    "sg:city":"Waukon",
    "sg:classifiers":[
        {
            "category":"Health Services",
            "subcategory":"Doctor",
            "type":"Services"
        }
    ],
    "sg:phone":"+1 563 568 3449",
    "sg:postcode":"52172",
    "sg:province":"IA",
    "sg:tags":[
        "clinic"
    ],
    "wof:name":"Franciscan Skemp Healthcare",
    "wof:placetype":"venue"
},
  "geometry": {"coordinates":[-91.473074,43.269179],"type":"Point"}
}