{
  "type": "Feature",
  "properties": {
    "addr:full":"933 Prairie St Grinnell IA 50112",
    "addr:housenumber":"933",
    "addr:postcode":"50112",
    "addr:street":"Prairie St",
    "iso:country":"US",
    "sg:address":"933 Prairie St",
    "sg:city":"Grinnell",
    "sg:classifiers":[
        {
            "category":"Building & Trades",
            "subcategory":"Construction",
            "type":"Services"
        }
    ],
    "sg:phone":"+1 641 236 4664",
    "sg:postcode":"50112",
    "sg:province":"IA",
    "sg:tags":[
        "painter"
    ],
    "wof:name":"Blom & Criswell Painting Inc",
    "wof:placetype":"venue"
},
  "geometry": {"coordinates":[-92.734754,41.744638],"type":"Point"}
}