{
  "type": "Feature",
  "properties": {
    "iso:country":"US",
    "sg:address":"923 F Ave NW",
    "sg:city":"Cedar Rapids",
    "sg:classifiers":[
        {
            "category":"Home & Garden",
            "subcategory":"Home Furnishings",
            "type":"Retail Goods"
        }
    ],
    "sg:phone":"+1 319 366 3370",
    "sg:postcode":"52405",
    "sg:province":"IA",
    "sg:tags":[
        "blind",
        "curtain",
        "made",
        "drapery",
        "shade"
    ],
    "wof:name":"Iiams Nanci Draperies",
    "wof:placetype":"venue"
},
  "geometry": {"coordinates":[-91.68620300000001,41.979],"type":"Point"}
}