{
  "type": "Feature",
  "properties": {
    "iso:country":"US",
    "sg:address":"926 Dale Dr",
    "sg:city":"Hudson",
    "sg:classifiers":[
        {
            "category":"Building & Trades",
            "subcategory":"Plumbing",
            "type":"Services"
        }
    ],
    "sg:phone":"+1 319 988 3253",
    "sg:postcode":"50643",
    "sg:province":"IA",
    "sg:tags":[
        "plumbing",
        "contractor"
    ],
    "wof:name":"All Star Plumbing & Heating",
    "wof:placetype":"venue"
},
  "geometry": {"coordinates":[-92.453328,42.410125],"type":"Point"}
}