{
  "type": "Feature",
  "properties": {
    "iso:country":"US",
    "sg:address":"1234 E River Dr",
    "sg:city":"Davenport",
    "sg:classifiers":[
        {
            "category":"Social Services",
            "type":"Services"
        }
    ],
    "sg:phone":"+1 563 326 7504",
    "sg:postcode":"52803",
    "sg:province":"IA",
    "sg:tags":[
        "information",
        "cancer"
    ],
    "sg:website":"www.gildasclubqc.org",
    "wof:name":"Gilda's Club Quad Cities",
    "wof:placetype":"venue"
},
  "geometry": {"coordinates":[-90.556371,41.527401],"type":"Point"}
}