{
  "type": "Feature",
  "properties": {
    "iso:country":"US",
    "sg:address":"2616 Orchard Dr",
    "sg:city":"Cedar Falls",
    "sg:classifiers":[
        {
            "category":"Health Services",
            "subcategory":"Clinic",
            "type":"Services"
        }
    ],
    "sg:phone":"+1 319 277 1936",
    "sg:postcode":"50613",
    "sg:province":"IA",
    "sg:tags":[
        "home"
    ],
    "wof:name":"Comfort Care",
    "wof:placetype":"venue"
},
  "geometry": {"coordinates":[-92.411305,42.504778],"type":"Point"}
}