{
  "type": "Feature",
  "properties": {
    "iso:country":"US",
    "sg:address":"10500 Buena Vista Ct",
    "sg:city":"Des Moines",
    "sg:classifiers":[
        {
            "category":"Government",
            "subcategory":"Office",
            "type":"Public Place"
        }
    ],
    "sg:phone":"+1 515 254 1540",
    "sg:postcode":"50322",
    "sg:province":"IA",
    "sg:tags":[
        "federal"
    ],
    "wof:name":"Us Consolidated Farm Svc Agcy",
    "wof:placetype":"venue"
},
  "geometry": {"coordinates":[-93.761577,41.621045],"type":"Point"}
}