{
  "type": "Feature",
  "properties": {
    "iso:country":"US",
    "sg:address":"1007 E Anson St",
    "sg:city":"Marshalltown",
    "sg:classifiers":[
        {
            "category":"Building & Trades",
            "subcategory":"Construction",
            "type":"Services"
        }
    ],
    "sg:phone":"+1 641 752 3361",
    "sg:postcode":"50158",
    "sg:province":"IA",
    "sg:tags":[
        "house"
    ],
    "wof:name":"McLaughlin Construction Co",
    "wof:placetype":"venue"
},
  "geometry": {"coordinates":[-92.89709999999999,42.038223],"type":"Point"}
}