{
  "type": "Feature",
  "properties": {
    "iso:country":"US",
    "sg:address":"17026 Mountain Ridge",
    "sg:city":"Dubuque",
    "sg:classifiers":[
        {
            "category":"Building & Trades",
            "subcategory":"Electrical",
            "type":"Services"
        }
    ],
    "sg:phone":"+1 563 588 3572",
    "sg:postcode":"52002",
    "sg:province":"IA",
    "sg:tags":[
        "electric",
        "contractor"
    ],
    "wof:name":"Lewis Electric",
    "wof:placetype":"venue"
},
  "geometry": {"coordinates":[-90.82181300000001,42.500798],"type":"Point"}
}