{
  "type": "Feature",
  "properties": {
    "iso:country":"US",
    "sg:address":"421 S Sycamore St",
    "sg:city":"Monticello",
    "sg:classifiers":[
        {
            "category":"Personal",
            "type":"Services"
        }
    ],
    "sg:phone":"+1 319 465 6313",
    "sg:postcode":"52310",
    "sg:province":"IA",
    "wof:name":"Bc Handyman Service",
    "wof:placetype":"venue"
},
  "geometry": {"coordinates":[-91.188137,42.234871],"type":"Point"}
}