{
  "type": "Feature",
  "properties": {
    "iso:country":"US",
    "sg:address":"935 US Hwy 30",
    "sg:city":"Lisbon",
    "sg:classifiers":[
        {
            "category":"Wholesale",
            "subcategory":"Machinery & Supplies",
            "type":"Manufacturing & Wholesale Goods"
        }
    ],
    "sg:phone":"+1 319 455 2200",
    "sg:postcode":"52253",
    "sg:province":"IA",
    "sg:tags":[
        "farm",
        "equipment"
    ],
    "sg:website":"www.iowaimp.com",
    "wof:name":"Iowa Implement Inc",
    "wof:placetype":"venue"
},
  "geometry": {"coordinates":[-91.40146,41.917222],"type":"Point"}
}