{
  "type": "Feature",
  "properties": {
    "addr:full":"4302 University Ave Cedar Falls IA 50613",
    "addr:housenumber":"4302",
    "addr:postcode":"50613",
    "addr:street":"University Ave",
    "iso:country":"US",
    "sg:address":"4302 University Ave",
    "sg:city":"Cedar Falls",
    "sg:classifiers":[
        {
            "category":"Restaurant",
            "type":"Food & Drink"
        }
    ],
    "sg:menulink":"http://www.allmenus.com/ia/cedar-falls/18545-east-china/menu/",
    "sg:phone":"+1 319 277 0022",
    "sg:postcode":"50613",
    "sg:province":"IA",
    "sg:tags":[
        "asian",
        "chinese"
    ],
    "wof:name":"East China",
    "wof:placetype":"venue"
},
  "geometry": {"coordinates":[-92.408951,42.506276],"type":"Point"}
}