{
  "type": "Feature",
  "properties": {
    "iso:country":"US",
    "sg:address":"608 N 15th St",
    "sg:city":"Indianola",
    "sg:classifiers":[
        {
            "category":"Social Services",
            "subcategory":"Adult Care",
            "type":"Services"
        }
    ],
    "sg:phone":"+1 515 961 8900",
    "sg:postcode":"50125",
    "sg:province":"IA",
    "sg:tags":[
        "home",
        "residential"
    ],
    "wof:name":"Windsor Manor",
    "wof:placetype":"venue"
},
  "geometry": {"coordinates":[-93.53963899999999,41.365263],"type":"Point"}
}