{
  "type": "Feature",
  "properties": {
    "iso:country":"US",
    "sg:address":"201 C Ave",
    "sg:city":"Vinton",
    "sg:classifiers":[
        {
            "category":"Retail",
            "subcategory":"Repair Shop",
            "type":"Services"
        }
    ],
    "sg:phone":"+1 319 472 2793",
    "sg:postcode":"52349",
    "sg:province":"IA",
    "wof:name":"Ernies Watch & Clock Repair",
    "wof:placetype":"venue"
},
  "geometry": {"coordinates":[-92.027854,42.169165],"type":"Point"}
}