{
  "type": "Feature",
  "properties": {
    "iso:country":"US",
    "sg:address":"2400 86th St",
    "sg:city":"Urbandale",
    "sg:classifiers":[
        {
            "category":"Banks & Credit Unions",
            "subcategory":"Investment Brokerage",
            "type":"Services"
        }
    ],
    "sg:phone":"+1 515 276 2873",
    "sg:postcode":"50322",
    "sg:province":"IA",
    "sg:tags":[
        "advisory"
    ],
    "wof:name":"Key Financial Services Ltd",
    "wof:placetype":"venue"
},
  "geometry": {"coordinates":[-93.736645,41.616327],"type":"Point"}
}