{
  "type": "Feature",
  "properties": {
    "addr:full":"508 Pierce St Sioux City IA 51101",
    "addr:housenumber":"508",
    "addr:postcode":"51101",
    "addr:street":"Pierce St",
    "iso:country":"US",
    "sg:address":"508 Pierce St",
    "sg:city":"Sioux City",
    "sg:classifiers":[
        {
            "category":"Real Estate",
            "subcategory":"Real Estate Services",
            "type":"Services"
        }
    ],
    "sg:phone":"+1 712 258 5569",
    "sg:postcode":"51101",
    "sg:province":"IA",
    "wof:name":"Talley Harvey & Co Abstracters",
    "wof:placetype":"venue"
},
  "geometry": {"coordinates":[-96.404875,42.496254],"type":"Point"}
}