{
  "type": "Feature",
  "properties": {
    "iso:country":"US",
    "sg:address":"2620 27th Ave",
    "sg:city":"Marion",
    "sg:classifiers":[
        {
            "category":"Home & Garden",
            "subcategory":"Carpets & Floor Coverings",
            "type":"Retail Goods"
        }
    ],
    "sg:phone":"+1 319 377 2097",
    "sg:postcode":"52302",
    "sg:province":"IA",
    "wof:name":"Superior Floors Of Marion",
    "wof:placetype":"venue"
},
  "geometry": {"coordinates":[-91.585731,42.049082],"type":"Point"}
}