{
  "type": "Feature",
  "properties": {
    "addr:full":"307 Edgewood Rd SW Cedar Rapids IA 52404",
    "addr:housenumber":"307",
    "addr:postcode":"52404",
    "addr:street":"Edgewood Rd Sw",
    "iso:country":"US",
    "sg:address":"307 Edgewood Rd SW",
    "sg:city":"Cedar Rapids",
    "sg:classifiers":[
        {
            "category":"Health Services",
            "subcategory":"Nursing And Care Facility",
            "type":"Services"
        }
    ],
    "sg:phone":"+1 319 365 4116",
    "sg:postcode":"52404",
    "sg:province":"IA",
    "sg:tags":[
        "home",
        "apartment",
        "convalescent"
    ],
    "sg:website":"www.evergreenestates.biz",
    "wof:name":"Evergreen Estates 1",
    "wof:placetype":"venue"
},
  "geometry": {"coordinates":[-91.716003,41.966],"type":"Point"}
}