{
  "type": "Feature",
  "properties": {
    "iso:country":"US",
    "sg:address":"1020 N Center Point Rd",
    "sg:city":"Hiawatha",
    "sg:classifiers":[
        {
            "category":"Autos & Motor Vehicles",
            "subcategory":"Automobile Sales",
            "type":"Retail Goods"
        }
    ],
    "sg:phone":"+1 319 393 6850",
    "sg:postcode":"52233",
    "sg:province":"IA",
    "sg:tags":[
        "car",
        "dealer"
    ],
    "sg:website":"www.saturnofcr.com",
    "wof:name":"Saturn",
    "wof:placetype":"venue"
},
  "geometry": {"coordinates":[-91.683055,42.046877],"type":"Point"}
}