{
  "type": "Feature",
  "properties": {
    "iso:country":"US",
    "sg:address":"118 2nd St SE",
    "sg:city":"Cedar Rapids",
    "sg:classifiers":[
        {
            "category":"Local Transit",
            "type":"Transportation"
        }
    ],
    "sg:phone":"+1 319 363 5700",
    "sg:postcode":"52401",
    "sg:province":"IA",
    "wof:name":"MJN Svc",
    "wof:placetype":"venue"
},
  "geometry": {"coordinates":[-91.667888,41.978082],"type":"Point"}
}