{
  "type": "Feature",
  "properties": {
    "addr:full":"1112 Lakeshore Dr Brooklyn IA 52211",
    "addr:housenumber":"1112",
    "addr:postcode":"52211",
    "addr:street":"Lakeshore Dr",
    "iso:country":"US",
    "sg:address":"1112 Lakeshore Dr",
    "sg:city":"Brooklyn",
    "sg:classifiers":[
        {
            "category":"Professional",
            "type":"Services"
        }
    ],
    "sg:phone":"+1 641 522 5257",
    "sg:postcode":"52211",
    "sg:province":"IA",
    "sg:tags":[
        "establishment"
    ],
    "wof:name":"Kadlec Cabin",
    "wof:placetype":"venue"
},
  "geometry": {"coordinates":[-92.44750999999999,41.814638],"type":"Point"}
}