{
  "type": "Feature",
  "properties": {
    "iso:country":"US",
    "sg:address":"800 Lincoln Way",
    "sg:city":"Ames",
    "sg:classifiers":[
        {
            "category":"Government",
            "subcategory":"Office",
            "type":"Public Place"
        }
    ],
    "sg:phone":"+1 515 239 1661",
    "sg:postcode":"50010",
    "sg:province":"IA",
    "wof:name":"Planning & Programming Div",
    "wof:placetype":"venue"
},
  "geometry": {"coordinates":[-93.622975,42.02287],"type":"Point"}
}