{
  "type": "Feature",
  "properties": {
    "iso:country":"US",
    "sg:address":"2445 130th St",
    "sg:city":"Delmar",
    "sg:classifiers":[
        {
            "category":"Farming",
            "subcategory":"Farm",
            "type":"Manufacturing & Wholesale Goods"
        }
    ],
    "sg:phone":"+1 563 574 9900",
    "sg:postcode":"52037",
    "sg:province":"IA",
    "wof:name":"Costello Farms",
    "wof:placetype":"venue"
},
  "geometry": {"coordinates":[-90.618002,41.989057],"type":"Point"}
}