{
  "type": "Feature",
  "properties": {
    "iso:country":"US",
    "sg:address":"317 N Hancock St",
    "sg:city":"Ottumwa",
    "sg:classifiers":[
        {
            "category":"Building & Trades",
            "subcategory":"Construction",
            "type":"Services"
        }
    ],
    "sg:phone":"+1 641 684 4785",
    "sg:postcode":"52501",
    "sg:province":"IA",
    "sg:tags":[
        "house"
    ],
    "wof:name":"Metkalf & Fisher Construction",
    "wof:placetype":"venue"
},
  "geometry": {"coordinates":[-92.41616500000001,41.005114],"type":"Point"}
}