{
  "type": "Feature",
  "properties": {
    "iso:country":"US",
    "sg:address":"1705 Ross St",
    "sg:city":"Sioux City",
    "sg:classifiers":[
        {
            "category":"Professional",
            "subcategory":"Accounting & Tax Preparation",
            "type":"Services"
        }
    ],
    "sg:phone":"+1 712 258 2737",
    "sg:postcode":"51103",
    "sg:province":"IA",
    "sg:tags":[
        "accountant",
        "return"
    ],
    "wof:name":"Associated Business Service",
    "wof:placetype":"venue"
},
  "geometry": {"coordinates":[-96.42860400000001,42.508757],"type":"Point"}
}