{
  "type": "Feature",
  "properties": {
    "iso:country":"US",
    "sg:address":"625 Davis Ave",
    "sg:city":"Corning",
    "sg:classifiers":[
        {
            "category":"Shopping",
            "subcategory":"Gifts & Souvenirs",
            "type":"Retail Goods"
        }
    ],
    "sg:phone":"+1 641 322 3454",
    "sg:postcode":"50841",
    "sg:province":"IA",
    "sg:tags":[
        "shop"
    ],
    "wof:name":"Mc Mahon Drug Store",
    "wof:placetype":"venue"
},
  "geometry": {"coordinates":[-94.73448500000001,40.988313],"type":"Point"}
}