{
  "type": "Feature",
  "properties": {
    "iso:country":"US",
    "sg:address":"600 17th St SE",
    "sg:city":"Independence",
    "sg:classifiers":[
        {
            "category":"Building & Trades",
            "subcategory":"Construction",
            "type":"Services"
        }
    ],
    "sg:phone":"+1 319 334 7061",
    "sg:postcode":"50644",
    "sg:province":"IA",
    "sg:tags":[
        "general",
        "contractor"
    ],
    "wof:name":"Larson Construction Co",
    "wof:placetype":"venue"
},
  "geometry": {"coordinates":[-91.88933,42.453911],"type":"Point"}
}