{
  "type": "Feature",
  "properties": {
    "iso:country":"US",
    "sg:address":"23055 265th St",
    "sg:city":"Delhi",
    "sg:classifiers":[
        {
            "category":"Professional",
            "subcategory":"Research",
            "type":"Services"
        }
    ],
    "sg:phone":"+1 319 465 4199",
    "sg:postcode":"52223",
    "sg:province":"IA",
    "sg:tags":[
        "nonphysical",
        "commercial"
    ],
    "wof:name":"Fpb",
    "wof:placetype":"venue"
},
  "geometry": {"coordinates":[-91.342885,42.402653],"type":"Point"}
}