{
  "type": "Feature",
  "properties": {
    "iso:country":"US",
    "sg:address":"2806 Bloomington Ln",
    "sg:city":"Muscatine",
    "sg:classifiers":[
        {
            "category":"Government",
            "subcategory":"Office",
            "type":"Public Place"
        }
    ],
    "sg:phone":"+1 563 264 0667",
    "sg:postcode":"52761",
    "sg:province":"IA",
    "sg:tags":[
        "village"
    ],
    "wof:name":"Muscatine Public Housing",
    "wof:placetype":"venue"
},
  "geometry": {"coordinates":[-91.078047,41.413447],"type":"Point"}
}