{
  "type": "Feature",
  "properties": {
    "addr:full":"402 E White St Preston IA 52069",
    "addr:housenumber":"402",
    "addr:postcode":"52069",
    "addr:street":"E White St",
    "iso:country":"US",
    "sg:address":"402 E White St",
    "sg:city":"Preston",
    "sg:classifiers":[
        {
            "category":"Building & Trades",
            "subcategory":"Plumbing",
            "type":"Services"
        }
    ],
    "sg:phone":"+1 563 689 3450",
    "sg:postcode":"52069",
    "sg:province":"IA",
    "sg:tags":[
        "conditioning",
        "air",
        "system",
        "contractor"
    ],
    "wof:name":"Total Comfort Heating-Cooling",
    "wof:placetype":"venue"
},
  "geometry": {"coordinates":[-90.38859600000001,42.052995],"type":"Point"}
}