{
  "type": "Feature",
  "properties": {
    "iso:country":"US",
    "sg:address":"4803 Lincoln Way",
    "sg:city":"Ames",
    "sg:classifiers":[
        {
            "category":"Professional",
            "subcategory":"Testing Lab",
            "type":"Services"
        }
    ],
    "sg:phone":"+1 515 292 1422",
    "sg:postcode":"50014",
    "sg:province":"IA",
    "sg:tags":[
        "laboratory"
    ],
    "sg:website":"www.skarshaug.com",
    "wof:name":"Skarshaug Testing",
    "wof:placetype":"venue"
},
  "geometry": {"coordinates":[-93.67876699999999,42.023038],"type":"Point"}
}