{
  "type": "Feature",
  "properties": {
    "iso:country":"US",
    "sg:address":"1343 Lily Ave",
    "sg:city":"Little Rock",
    "sg:classifiers":[
        {
            "category":"Freight",
            "type":"Transportation"
        }
    ],
    "sg:phone":"+1 712 479 2762",
    "sg:postcode":"51243",
    "sg:province":"IA",
    "sg:tags":[
        "livestock",
        "hauling"
    ],
    "wof:name":"Arends Livestock Hauling",
    "wof:placetype":"venue"
},
  "geometry": {"coordinates":[-95.920393,43.455454],"type":"Point"}
}