{
  "type": "Feature",
  "properties": {
    "addr:full":"1060 130th Ave Lake Park IA 51347",
    "addr:housenumber":"1060",
    "addr:postcode":"51347",
    "addr:street":"130Th Ave",
    "iso:country":"US",
    "sg:address":"1060 130th Ave",
    "sg:city":"Lake Park",
    "sg:classifiers":[
        {
            "category":"Farming",
            "subcategory":"Farm",
            "type":"Manufacturing & Wholesale Goods"
        }
    ],
    "sg:phone":"+1 712 832 3189",
    "sg:postcode":"51347",
    "sg:province":"IA",
    "wof:name":"Ihnen Family Farms",
    "wof:placetype":"venue"
},
  "geometry": {"coordinates":[-95.328846,43.493023],"type":"Point"}
}