{
  "type": "Feature",
  "properties": {
    "iso:country":"US",
    "sg:address":"2301 T Ave",
    "sg:city":"Williamsburg",
    "sg:classifiers":[
        {
            "category":"Retail",
            "subcategory":"Repair Shop",
            "type":"Services"
        }
    ],
    "sg:phone":"+1 319 668 1421",
    "sg:postcode":"52361",
    "sg:province":"IA",
    "wof:name":"Iburg Repair",
    "wof:placetype":"venue"
},
  "geometry": {"coordinates":[-91.92996599999999,41.675256],"type":"Point"}
}