{
  "type": "Feature",
  "properties": {
    "iso:country":"US",
    "sg:address":"506 E 4th St",
    "sg:city":"Sutherland",
    "sg:classifiers":[
        {
            "category":"Health Services",
            "subcategory":"Nursing And Care Facility",
            "type":"Services"
        }
    ],
    "sg:phone":"+1 712 446 3857",
    "sg:postcode":"51058",
    "sg:province":"IA",
    "sg:tags":[
        "home",
        "convalescent"
    ],
    "wof:name":"Sutherland Care Ctr",
    "wof:placetype":"venue"
},
  "geometry": {"coordinates":[-95.491286,42.971724],"type":"Point"}
}