{
  "type": "Feature",
  "properties": {
    "iso:country":"US",
    "sg:address":"806 Wacker Dr",
    "sg:city":"Dubuque",
    "sg:classifiers":[
        {
            "category":"Autos & Motor Vehicles",
            "subcategory":"Auto Supplies",
            "type":"Retail Goods"
        }
    ],
    "sg:phone":"+1 563 557 9331",
    "sg:postcode":"52002",
    "sg:province":"IA",
    "sg:tags":[
        "automobile",
        "parts"
    ],
    "wof:name":"Advance Auto Parts",
    "wof:placetype":"venue"
},
  "geometry": {"coordinates":[-90.72038499999999,42.493564],"type":"Point"}
}