{
  "type": "Feature",
  "properties": {
    "iso:country":"US",
    "sg:address":"1201 12th St NE",
    "sg:city":"Independence",
    "sg:classifiers":[
        {
            "category":"Manufacturing",
            "subcategory":"Building Materials",
            "type":"Manufacturing & Wholesale Goods"
        }
    ],
    "sg:phone":"+1 319 334 6041",
    "sg:postcode":"50644",
    "sg:province":"IA",
    "sg:tags":[
        "member",
        "wood",
        "structural"
    ],
    "wof:name":"Spahn & Rose Distribution",
    "wof:placetype":"venue"
},
  "geometry": {"coordinates":[-91.878501,42.480306],"type":"Point"}
}