{
  "type": "Feature",
  "properties": {
    "addr:full":"2700 Mount Pleasant St Burlington IA 52601",
    "addr:housenumber":"2700",
    "addr:postcode":"52601",
    "addr:street":"Mount Pleasant St",
    "iso:country":"US",
    "sg:address":"2700 Mount Pleasant St",
    "sg:city":"Burlington",
    "sg:classifiers":[
        {
            "category":"Personal",
            "type":"Services"
        }
    ],
    "sg:phone":"+1 319 752 3040",
    "sg:postcode":"52601",
    "sg:province":"IA",
    "sg:tags":[
        "program",
        "physical",
        "exercise",
        "fitness"
    ],
    "wof:name":"Shapes N 30",
    "wof:placetype":"venue"
},
  "geometry": {"coordinates":[-91.140569,40.825841],"type":"Point"}
}