{
  "type": "Feature",
  "properties": {
    "iso:country":"US",
    "sg:address":"1454 Iowa St",
    "sg:city":"Dubuque",
    "sg:classifiers":[
        {
            "category":"Organizations",
            "subcategory":"Non-profit Organization",
            "type":"Services"
        }
    ],
    "sg:phone":"+1 563 556 6200",
    "sg:postcode":"52001",
    "sg:province":"IA",
    "wof:name":"VISITING Nurse Assn",
    "wof:placetype":"venue"
},
  "geometry": {"coordinates":[-90.668887,42.506467],"type":"Point"}
}