{
  "type": "Feature",
  "properties": {
    "iso:country":"US",
    "sg:address":"839 13th Ave N",
    "sg:city":"Clinton",
    "sg:classifiers":[
        {
            "category":"Health Services",
            "subcategory":"Nursing And Care Facility",
            "type":"Services"
        }
    ],
    "sg:phone":"+1 563 242 1010",
    "sg:postcode":"52732",
    "sg:province":"IA",
    "sg:tags":[
        "home",
        "retirement",
        "community"
    ],
    "wof:name":"Regency Retirement Residence",
    "wof:placetype":"venue"
},
  "geometry": {"coordinates":[-90.19772399999999,41.859301],"type":"Point"}
}