{
  "type": "Feature",
  "properties": {
    "iso:country":"US",
    "sg:address":"314 E Division St",
    "sg:city":"Audubon",
    "sg:classifiers":[
        {
            "category":"Insurance",
            "subcategory":"Insurance Agent",
            "type":"Services"
        }
    ],
    "sg:phone":"+1 712 563 9969",
    "sg:postcode":"50025",
    "sg:province":"IA",
    "wof:name":"EMC Insurance Group Inc",
    "wof:placetype":"venue"
},
  "geometry": {"coordinates":[-94.92747799999999,41.720828],"type":"Point"}
}