{
  "type": "Feature",
  "properties": {
    "addr:full":"5325 State Hwy 9 Sibley IA 51249",
    "addr:housenumber":"5325",
    "addr:postcode":"51249",
    "addr:street":"State Hwy 9",
    "iso:country":"US",
    "sg:address":"5325 State Hwy 9",
    "sg:city":"Sibley",
    "sg:classifiers":[
        {
            "category":"Wholesale",
            "subcategory":"Machinery & Supplies",
            "type":"Manufacturing & Wholesale Goods"
        }
    ],
    "sg:phone":"+1 712 754 3741",
    "sg:postcode":"51249",
    "sg:province":"IA",
    "sg:tags":[
        "farm",
        "equipment"
    ],
    "wof:name":"Sibley Equipment",
    "wof:placetype":"venue"
},
  "geometry": {"coordinates":[-95.736633,43.432674],"type":"Point"}
}