{
  "type": "Feature",
  "properties": {
    "iso:country":"US",
    "sg:address":"804 Poplar St",
    "sg:city":"Atlantic",
    "sg:classifiers":[
        {
            "category":"Social Services",
            "type":"Services"
        }
    ],
    "sg:phone":"+1 712 243 2920",
    "sg:postcode":"50022",
    "sg:province":"IA",
    "sg:tags":[
        "organization",
        "welfare"
    ],
    "wof:name":"Lutheran Social Svc",
    "wof:placetype":"venue"
},
  "geometry": {"coordinates":[-95.014381,41.402953],"type":"Point"}
}