{
  "type": "Feature",
  "properties": {
    "addr:full":"4718 200th St Cushing IA 51018",
    "addr:housenumber":"4718",
    "addr:postcode":"51018",
    "addr:street":"200Th St",
    "iso:country":"US",
    "sg:address":"4718 200th St",
    "sg:city":"Cushing",
    "sg:classifiers":[
        {
            "category":"Farming",
            "subcategory":"Livestock Farm",
            "type":"Manufacturing & Wholesale Goods"
        }
    ],
    "sg:phone":"+1 712 384 2270",
    "sg:postcode":"51018",
    "sg:province":"IA",
    "sg:tags":[
        "animal",
        "general"
    ],
    "wof:name":"Dennis Krager",
    "wof:placetype":"venue"
},
  "geometry": {"coordinates":[-95.68919,42.414047],"type":"Point"}
}