{
  "type": "Feature",
  "properties": {
    "iso:country":"US",
    "sg:address":"123 1st Ave",
    "sg:city":"Little Rock",
    "sg:classifiers":[
        {
            "category":"Organizations",
            "subcategory":"Religious Organization",
            "type":"Services"
        }
    ],
    "sg:phone":"+1 712 479 2214",
    "sg:postcode":"51243",
    "sg:province":"IA",
    "sg:tags":[
        "church"
    ],
    "wof:name":"Salem Reformed Church",
    "wof:placetype":"venue"
},
  "geometry": {"coordinates":[-95.881885,43.442073],"type":"Point"}
}