{
  "type": "Feature",
  "properties": {
    "iso:country":"US",
    "sg:address":"102 Kimball Rd",
    "sg:city":"Ventura",
    "sg:phone":"+1 641 829 4420",
    "sg:postcode":"50482",
    "sg:province":"IA",
    "sg:tags":[
        "farm",
        "corn",
        "grain",
        "cash"
    ],
    "wof:name":"Scott Rayhons",
    "wof:placetype":"venue"
},
  "geometry": {"coordinates":[-93.469683,43.127292],"type":"Point"}
}