{
  "type": "Feature",
  "properties": {
    "iso:country":"US",
    "sg:address":"1529 Ranier Dr",
    "sg:city":"Iowa City",
    "sg:classifiers":[
        {
            "category":"Government",
            "subcategory":"Office",
            "type":"Public Place"
        }
    ],
    "sg:phone":"+1 319 358 1411",
    "sg:postcode":"52246",
    "sg:province":"IA",
    "wof:name":"US Experess",
    "wof:placetype":"venue"
},
  "geometry": {"coordinates":[-91.57804400000001,41.645739],"type":"Point"}
}