{
  "type": "Feature",
  "properties": {
    "iso:country":"US",
    "sg:address":"3018 340th Ave",
    "sg:city":"Ruthven",
    "sg:classifiers":[
        {
            "category":"Manufacturing",
            "subcategory":"Printing",
            "type":"Manufacturing & Wholesale Goods"
        }
    ],
    "sg:phone":"+1 712 837 5564",
    "sg:postcode":"51358",
    "sg:province":"IA",
    "sg:tags":[
        "screen"
    ],
    "wof:name":"Relativity Printing Inc",
    "wof:placetype":"venue"
},
  "geometry": {"coordinates":[-94.913585,43.208025],"type":"Point"}
}