{
  "type": "Feature",
  "properties": {
    "iso:country":"US",
    "sg:address":"1215 8th Ave",
    "sg:city":"Wellman",
    "sg:classifiers":[
        {
            "category":"Organizations",
            "subcategory":"Religious Organization",
            "type":"Services"
        }
    ],
    "sg:phone":"+1 319 646 2532",
    "sg:postcode":"52356",
    "sg:province":"IA",
    "sg:tags":[
        "church"
    ],
    "wof:name":"Wellman Mennonite Church",
    "wof:placetype":"venue"
},
  "geometry": {"coordinates":[-91.83774699999999,41.473391],"type":"Point"}
}