{
  "type": "Feature",
  "properties": {
    "addr:full":"21037 Holden Dr Davenport IA 52804",
    "addr:housenumber":"21037",
    "addr:postcode":"52804",
    "addr:street":"Holden Dr",
    "iso:country":"US",
    "sg:address":"21037 Holden Dr",
    "sg:city":"Davenport",
    "sg:classifiers":[
        {
            "category":"Banks & Credit Unions",
            "subcategory":"Investment Brokerage",
            "type":"Services"
        }
    ],
    "sg:phone":"+1 563 391 8001",
    "sg:postcode":"52804",
    "sg:province":"IA",
    "sg:tags":[
        "commodity"
    ],
    "wof:name":"Lohman Futures",
    "wof:placetype":"venue"
},
  "geometry": {"coordinates":[-90.56955600000001,41.61232],"type":"Point"}
}