{
  "type": "Feature",
  "properties": {
    "iso:country":"US",
    "sg:address":"20 Central Ave NE",
    "sg:city":"Le Mars",
    "sg:classifiers":[
        {
            "category":"Professional",
            "subcategory":"Lawyer & Legal Services",
            "type":"Services"
        }
    ],
    "sg:phone":"+1 712 546 4306",
    "sg:postcode":"51031",
    "sg:province":"IA",
    "sg:tags":[
        "attorney"
    ],
    "wof:name":"Thomas J Hoffman",
    "wof:placetype":"venue"
},
  "geometry": {"coordinates":[-96.166391,42.794051],"type":"Point"}
}