{
  "type": "Feature",
  "properties": {
    "iso:country":"US",
    "sg:address":"104 N Oak St",
    "sg:city":"Creston",
    "sg:classifiers":[
        {
            "category":"Organizations",
            "subcategory":"Religious Organization",
            "type":"Services"
        }
    ],
    "sg:phone":"+1 641 782 4439",
    "sg:postcode":"50801",
    "sg:province":"IA",
    "wof:name":"Christian Science Reading Room",
    "wof:placetype":"venue"
},
  "geometry": {"coordinates":[-94.36512500000001,41.057781],"type":"Point"}
}