{
  "type": "Feature",
  "properties": {
    "iso:country":"US",
    "sg:address":"2246 Jet Rd",
    "sg:city":"Greeley",
    "sg:classifiers":[
        {
            "category":"Farming",
            "subcategory":"Livestock Farm",
            "type":"Manufacturing & Wholesale Goods"
        }
    ],
    "sg:phone":"+1 563 925 2359",
    "sg:postcode":"52050",
    "sg:province":"IA",
    "sg:tags":[
        "feedlot",
        "hog",
        "corn",
        "or",
        "soybean"
    ],
    "wof:name":"Charles Robinson",
    "wof:placetype":"venue"
},
  "geometry": {"coordinates":[-91.358948,42.590837],"type":"Point"}
}