{
  "type": "Feature",
  "properties": {
    "addr:full":"705 Railroad Ave West Des Moines IA 50265",
    "addr:housenumber":"705",
    "addr:postcode":"50265",
    "addr:street":"Railroad Ave",
    "iso:country":"US",
    "sg:address":"705 Railroad Ave",
    "sg:city":"West Des Moines",
    "sg:classifiers":[
        {
            "category":"Professional",
            "subcategory":"Business Services",
            "type":"Services"
        }
    ],
    "sg:phone":"+1 515 277 6250",
    "sg:postcode":"50265",
    "sg:province":"IA",
    "sg:tags":[
        "water",
        "treatment"
    ],
    "wof:name":"Kinetico",
    "wof:placetype":"venue"
},
  "geometry": {"coordinates":[-93.71299999999999,41.569744],"type":"Point"}
}