{
  "type": "Feature",
  "properties": {
    "iso:country":"US",
    "sg:address":"203 N Commercial Ave",
    "sg:city":"Eagle Grove",
    "sg:classifiers":[
        {
            "category":"Autos & Motor Vehicles",
            "subcategory":"Motorcycle Sales",
            "type":"Retail Goods"
        }
    ],
    "sg:phone":"+1 515 603 6856",
    "sg:postcode":"50533",
    "sg:province":"IA",
    "sg:tags":[
        "scooter"
    ],
    "wof:name":"Vimrock Motoring Inc",
    "wof:placetype":"venue"
},
  "geometry": {"coordinates":[-93.904585,42.666241],"type":"Point"}
}