{
  "type": "Feature",
  "properties": {
    "iso:country":"US",
    "sg:address":"2415 Mount Pleasant St",
    "sg:city":"Burlington",
    "sg:classifiers":[
        {
            "category":"Fast Food",
            "type":"Food & Drink"
        },
        {
            "category":"Restaurant",
            "type":"Food & Drink"
        }
    ],
    "sg:phone":"+1 319 754 8459",
    "sg:postcode":"52601",
    "sg:province":"IA",
    "sg:tags":[
        "mexican",
        "take"
    ],
    "wof:name":"El Taco Casa",
    "wof:placetype":"venue"
},
  "geometry": {"coordinates":[-91.130655,40.823149],"type":"Point"}
}