{
  "type": "Feature",
  "properties": {
    "iso:country":"US",
    "sg:address":"210 N Main St",
    "sg:city":"Hedrick",
    "sg:classifiers":[
        {
            "category":"Personal",
            "subcategory":"Beauty Salon",
            "type":"Services"
        }
    ],
    "sg:phone":"+1 641 653 2334",
    "sg:postcode":"52563",
    "sg:province":"IA",
    "wof:name":"Dixie's Mane Street Salon",
    "wof:placetype":"venue"
},
  "geometry": {"coordinates":[-92.308948,41.173221],"type":"Point"}
}