{
  "type": "Feature",
  "properties": {
    "iso:country":"US",
    "sg:address":"2637 Pettibone Ave",
    "sg:city":"Muscatine",
    "sg:classifiers":[
        {
            "category":"Wholesale",
            "subcategory":"Farm Supplies",
            "type":"Manufacturing & Wholesale Goods"
        }
    ],
    "sg:phone":"+1 563 264 1721",
    "sg:postcode":"52761",
    "sg:province":"IA",
    "sg:tags":[
        "fertilizer"
    ],
    "wof:name":"Agriliance",
    "wof:placetype":"venue"
},
  "geometry": {"coordinates":[-91.07630399999999,41.358487],"type":"Point"}
}