{
  "type": "Feature",
  "properties": {
    "addr:full":"512 S 20th St Fort Dodge IA 50501",
    "addr:housenumber":"512",
    "addr:postcode":"50501",
    "addr:street":"S 20Th St",
    "iso:country":"US",
    "sg:address":"512 S 20th St",
    "sg:city":"Fort Dodge",
    "sg:classifiers":[
        {
            "category":"Building & Trades",
            "subcategory":"Cleaning & Sanitation",
            "type":"Services"
        }
    ],
    "sg:phone":"+1 515 576 4887",
    "sg:postcode":"50501",
    "sg:province":"IA",
    "sg:tags":[
        "ventilating",
        "system"
    ],
    "wof:name":"Quality Air Care",
    "wof:placetype":"venue"
},
  "geometry": {"coordinates":[-94.170822,42.500999],"type":"Point"}
}