{
  "type": "Feature",
  "properties": {
    "iso:country":"US",
    "sg:address":"4741 Inverness Ct",
    "sg:city":"Iowa City",
    "sg:classifiers":[
        {
            "category":"Shopping",
            "subcategory":"Books",
            "type":"Retail Goods"
        }
    ],
    "sg:phone":"+1 319 338 0341",
    "sg:postcode":"52245",
    "sg:province":"IA",
    "sg:tags":[
        "wholesale",
        "publishing"
    ],
    "wof:name":"Azimuth Publishing",
    "wof:placetype":"venue"
},
  "geometry": {"coordinates":[-91.46663599999999,41.651312],"type":"Point"}
}