{
  "type": "Feature",
  "properties": {
    "iso:country":"US",
    "sg:address":"1126 167th Ave",
    "sg:city":"Ossian",
    "sg:phone":"+1 563 532 9268",
    "sg:postcode":"52161",
    "sg:province":"IA",
    "sg:tags":[
        "farm",
        "corn"
    ],
    "wof:name":"Darrell Eide",
    "wof:placetype":"venue"
},
  "geometry": {"coordinates":[-91.734683,43.096078],"type":"Point"}
}