{
  "type": "Feature",
  "properties": {
    "iso:country":"US",
    "sg:address":"94 E Bremer Ave",
    "sg:city":"Waverly",
    "sg:classifiers":[
        {
            "category":"Building & Trades",
            "subcategory":"Construction",
            "type":"Services"
        }
    ],
    "sg:phone":"+1 319 352 4573",
    "sg:postcode":"50677",
    "sg:province":"IA",
    "sg:tags":[
        "designer"
    ],
    "wof:name":"Form I",
    "wof:placetype":"venue"
},
  "geometry": {"coordinates":[-92.469802,42.725708],"type":"Point"}
}