{
  "type": "Feature",
  "properties": {
    "addr:full":"1508 G Ave Grundy Center IA 50638",
    "addr:housenumber":"1508",
    "addr:postcode":"50638",
    "addr:street":"G Ave",
    "iso:country":"US",
    "sg:address":"1508 G Ave",
    "sg:city":"Grundy Center",
    "sg:classifiers":[
        {
            "category":"Building & Trades",
            "subcategory":"Plumbing",
            "type":"Services"
        }
    ],
    "sg:phone":"+1 319 824 6214",
    "sg:postcode":"50638",
    "sg:province":"IA",
    "sg:tags":[
        "plumbing",
        "contractor"
    ],
    "wof:name":"Brockway Inc",
    "wof:placetype":"venue"
},
  "geometry": {"coordinates":[-92.78598700000001,42.361514],"type":"Point"}
}