{
  "type": "Feature",
  "properties": {
    "iso:country":"US",
    "sg:address":"62606 Indian Creek St",
    "sg:city":"Lewis",
    "sg:classifiers":[
        {
            "category":"Retail",
            "subcategory":"Repair Shop",
            "type":"Services"
        }
    ],
    "sg:phone":"+1 712 769 2415",
    "sg:postcode":"51544",
    "sg:province":"IA",
    "sg:tags":[
        "welding"
    ],
    "wof:name":"Weirich Welding",
    "wof:placetype":"venue"
},
  "geometry": {"coordinates":[-95.13717800000001,41.331835],"type":"Point"}
}