{
  "type": "Feature",
  "properties": {
    "iso:country":"US",
    "sg:address":"1715 Pikes Peak Ct NE",
    "sg:city":"Cedar Rapids",
    "sg:classifiers":[
        {
            "category":"Organizations",
            "subcategory":"Religious Organization",
            "type":"Services"
        }
    ],
    "sg:phone":"+1 319 294 4871",
    "sg:postcode":"52402",
    "sg:province":"IA",
    "wof:name":"Embroiderers Guild of America",
    "wof:placetype":"venue"
},
  "geometry": {"coordinates":[-91.677933,42.005276],"type":"Point"}
}