{
  "type": "Feature",
  "properties": {
    "iso:country":"US",
    "sg:address":"306 Main St",
    "sg:city":"Bayard",
    "sg:classifiers":[
        {
            "category":"Bars & Pubs",
            "type":"Food & Drink"
        }
    ],
    "sg:phone":"+1 712 651 2451",
    "sg:postcode":"50029",
    "sg:province":"IA",
    "wof:name":"Shack's Lounge",
    "wof:placetype":"venue"
},
  "geometry": {"coordinates":[-94.557954,41.85169],"type":"Point"}
}