{
  "type": "Feature",
  "properties": {
    "iso:country":"US",
    "sg:address":"4330 Czech Ln NE",
    "sg:city":"Cedar Rapids",
    "sg:classifiers":[
        {
            "category":"Shopping",
            "subcategory":"Jewelry",
            "type":"Retail Goods"
        }
    ],
    "sg:phone":"+1 319 393 0304",
    "sg:postcode":"52402",
    "sg:province":"IA",
    "wof:name":"Brandon Michaels",
    "wof:placetype":"venue"
},
  "geometry": {"coordinates":[-91.666496,42.022701],"type":"Point"}
}