{
  "type": "Feature",
  "properties": {
    "addr:full":"314 7th St Menlo IA 50164",
    "addr:housenumber":"314",
    "addr:postcode":"50164",
    "addr:street":"7Th St",
    "iso:country":"US",
    "sg:address":"314 7th St",
    "sg:city":"Menlo",
    "sg:classifiers":[
        {
            "category":"Retail",
            "subcategory":"Repair Shop",
            "type":"Services"
        }
    ],
    "sg:phone":"+1 641 524 5164",
    "sg:postcode":"50164",
    "sg:province":"IA",
    "sg:tags":[
        "related"
    ],
    "wof:name":"Dick's Repair Shop",
    "wof:placetype":"venue"
},
  "geometry": {"coordinates":[-94.40656199999999,41.51828],"type":"Point"}
}