{
  "type": "Feature",
  "properties": {
    "iso:country":"US",
    "sg:address":"11369 Aurora Ave",
    "sg:city":"Urbandale",
    "sg:classifiers":[
        {
            "category":"Professional",
            "subcategory":"Management & Consulting",
            "type":"Services"
        }
    ],
    "sg:phone":"+1 515 331 9300",
    "sg:postcode":"50322",
    "sg:province":"IA",
    "sg:tags":[
        "agricultural",
        "consultant"
    ],
    "wof:name":"John Deere Credit Co",
    "wof:placetype":"venue"
},
  "geometry": {"coordinates":[-93.76835699999999,41.638622],"type":"Point"}
}