{
  "type": "Feature",
  "properties": {
    "iso:country":"US",
    "sg:address":"105 W Main St",
    "sg:city":"Stacyville",
    "sg:classifiers":[
        {
            "category":"Education",
            "subcategory":"Library",
            "type":"Public Place"
        }
    ],
    "sg:phone":"+1 641 710 2531",
    "sg:postcode":"50476",
    "sg:province":"IA",
    "wof:name":"Stacyville Public Library",
    "wof:placetype":"venue"
},
  "geometry": {"coordinates":[-92.78278299999999,43.436279],"type":"Point"}
}