{
  "type": "Feature",
  "properties": {
    "iso:country":"US",
    "sg:address":"503 Story St",
    "sg:city":"Boone",
    "sg:classifiers":[
        {
            "category":"Retail",
            "subcategory":"Funeral Services",
            "type":"Services"
        }
    ],
    "sg:phone":"+1 515 432 1922",
    "sg:postcode":"50036",
    "sg:province":"IA",
    "sg:tags":[
        "director"
    ],
    "wof:name":"Schroeder-Walter Funeral Home",
    "wof:placetype":"venue"
},
  "geometry": {"coordinates":[-93.880076,42.061655],"type":"Point"}
}