{
  "type": "Feature",
  "properties": {
    "addr:full":"1302 Angle Rd SW Kalona IA 52247",
    "addr:housenumber":"1302",
    "addr:postcode":"52247",
    "addr:street":"Angle Rd Sw",
    "iso:country":"US",
    "sg:address":"1302 Angle Rd SW",
    "sg:city":"Kalona",
    "sg:classifiers":[
        {
            "category":"Building & Trades",
            "subcategory":"Plumbing",
            "type":"Services"
        }
    ],
    "sg:phone":"+1 319 683 2448",
    "sg:postcode":"52247",
    "sg:province":"IA",
    "sg:tags":[
        "heating",
        "contractor"
    ],
    "wof:name":"Graber Heating & Air Cond",
    "wof:placetype":"venue"
},
  "geometry": {"coordinates":[-91.790646,41.532876],"type":"Point"}
}