{
  "type": "Feature",
  "properties": {
    "iso:country":"US",
    "sg:address":"712 E Milwaukee St",
    "sg:city":"Spencer",
    "sg:classifiers":[
        {
            "category":"Wholesale",
            "subcategory":"Scrap",
            "type":"Manufacturing & Wholesale Goods"
        }
    ],
    "sg:phone":"+1 712 262 4877",
    "sg:postcode":"51301",
    "sg:province":"IA",
    "sg:tags":[
        "recycling",
        "center"
    ],
    "wof:name":"Complete Recovery",
    "wof:placetype":"venue"
},
  "geometry": {"coordinates":[-95.135108,43.14427],"type":"Point"}
}