{
  "type": "Feature",
  "properties": {
    "iso:country":"US",
    "sg:address":"455 Elbow Creek Rd",
    "sg:city":"Mount Vernon",
    "sg:phone":"+1 319 482 7551",
    "sg:postcode":"52314",
    "sg:province":"IA",
    "sg:tags":[
        "farm",
        "corn",
        "soybean"
    ],
    "wof:name":"Richard Strother",
    "wof:placetype":"venue"
},
  "geometry": {"coordinates":[-91.412012,42.00532],"type":"Point"}
}