{
  "type": "Feature",
  "properties": {
    "iso:country":"US",
    "sg:address":"2343 340th Ave",
    "sg:city":"Terril",
    "sg:classifiers":[
        {
            "category":"Farming",
            "subcategory":"Farm",
            "type":"Manufacturing & Wholesale Goods"
        }
    ],
    "sg:phone":"+1 712 853 6523",
    "sg:postcode":"51364",
    "sg:province":"IA",
    "sg:tags":[
        "crop",
        "general"
    ],
    "wof:name":"Dwayne Sidles",
    "wof:placetype":"venue"
},
  "geometry": {"coordinates":[-94.914053,43.306807],"type":"Point"}
}