{
  "type": "Feature",
  "properties": {
    "addr:full":"11 N 25th St Fort Dodge IA 50501",
    "addr:housenumber":"11",
    "addr:postcode":"50501",
    "addr:street":"N 25Th St",
    "iso:country":"US",
    "sg:address":"11 N 25th St",
    "sg:city":"Fort Dodge",
    "sg:classifiers":[
        {
            "category":"Autos & Motor Vehicles",
            "subcategory":"Automobile Sales",
            "type":"Retail Goods"
        }
    ],
    "sg:phone":"+1 515 955 5555",
    "sg:postcode":"50501",
    "sg:province":"IA",
    "sg:tags":[
        "car",
        "dealer"
    ],
    "wof:name":"Crossroads Motors",
    "wof:placetype":"venue"
},
  "geometry": {"coordinates":[-94.163059,42.506425],"type":"Point"}
}