{
  "type": "Feature",
  "properties": {
    "iso:country":"US",
    "sg:address":"20727 160th St",
    "sg:city":"Akron",
    "sg:phone":"+1 712 568 2754",
    "sg:postcode":"51001",
    "sg:province":"IA",
    "sg:tags":[
        "farm",
        "corn"
    ],
    "wof:name":"Tapper Gaylen",
    "wof:placetype":"venue"
},
  "geometry": {"coordinates":[-96.416376,42.822224],"type":"Point"}
}