{
  "type": "Feature",
  "properties": {
    "iso:country":"US",
    "sg:address":"409 Park Dr",
    "sg:city":"Norway",
    "sg:classifiers":[
        {
            "category":"Shopping",
            "subcategory":"Computers & Home Electronics",
            "type":"Retail Goods"
        }
    ],
    "sg:phone":"+1 319 227 6461",
    "sg:postcode":"52318",
    "sg:province":"IA",
    "sg:tags":[
        "software"
    ],
    "wof:name":"Tri Software",
    "wof:placetype":"venue"
},
  "geometry": {"coordinates":[-91.926205,41.905359],"type":"Point"}
}