{
  "type": "Feature",
  "properties": {
    "iso:country":"US",
    "sg:address":"205 2nd Ave NW",
    "sg:city":"Waukon",
    "sg:classifiers":[
        {
            "category":"Personal",
            "subcategory":"Beauty Salon",
            "type":"Services"
        }
    ],
    "sg:phone":"+1 563 568 3200",
    "sg:postcode":"52172",
    "sg:province":"IA",
    "sg:tags":[
        "shop"
    ],
    "wof:name":"Needham's Hair Salon",
    "wof:placetype":"venue"
},
  "geometry": {"coordinates":[-91.47984599999999,43.271007],"type":"Point"}
}