{
  "type": "Feature",
  "properties": {
    "iso:country":"US",
    "sg:address":"209 S 10th St",
    "sg:city":"Adel",
    "sg:classifiers":[
        {
            "category":"Shopping",
            "subcategory":"Used Merchandise",
            "type":"Retail Goods"
        }
    ],
    "sg:phone":"+1 515 993 3572",
    "sg:postcode":"50003",
    "sg:province":"IA",
    "sg:tags":[
        "antique"
    ],
    "wof:name":"Garden Gates Antiques",
    "wof:placetype":"venue"
},
  "geometry": {"coordinates":[-94.019851,41.616205],"type":"Point"}
}