{
  "type": "Feature",
  "properties": {
    "iso:country":"US",
    "sg:address":"1180 Birch Ave",
    "sg:city":"Larchwood",
    "sg:phone":"+1 712 477 2221",
    "sg:postcode":"51241",
    "sg:province":"IA",
    "sg:tags":[
        "beef",
        "farm",
        "corn",
        "crop",
        "field",
        "cattle",
        "feedlot"
    ],
    "wof:name":"Tony Kerkvliet",
    "wof:placetype":"venue"
},
  "geometry": {"coordinates":[-96.48680299999999,43.478967],"type":"Point"}
}