{
  "type": "Feature",
  "properties": {
    "iso:country":"US",
    "sg:address":"402 N Adams St",
    "sg:city":"Carroll",
    "sg:classifiers":[
        {
            "category":"Personal",
            "subcategory":"Beauty Salon",
            "type":"Services"
        }
    ],
    "sg:phone":"+1 712 792 5347",
    "sg:postcode":"51401",
    "sg:province":"IA",
    "sg:tags":[
        "shop",
        "merchandise"
    ],
    "wof:name":"Kathys Head",
    "wof:placetype":"venue"
},
  "geometry": {"coordinates":[-94.869145,42.064918],"type":"Point"}
}