{
  "type": "Feature",
  "properties": {
    "addr:full":"418 B Ave Kalona IA 52247",
    "addr:housenumber":"418",
    "addr:postcode":"52247",
    "addr:street":"B Ave",
    "iso:country":"US",
    "sg:address":"418 B Ave",
    "sg:city":"Kalona",
    "sg:classifiers":[
        {
            "category":"Shopping",
            "subcategory":"Crafts & Fabrics",
            "type":"Retail Goods"
        }
    ],
    "sg:phone":"+1 319 656 3939",
    "sg:postcode":"52247",
    "sg:province":"IA",
    "sg:tags":[
        "shop"
    ],
    "wof:name":"Willow Creek Collectibles",
    "wof:placetype":"venue"
},
  "geometry": {"coordinates":[-91.707577,41.483052],"type":"Point"}
}