{
  "type": "Feature",
  "properties": {
    "iso:country":"US",
    "sg:address":"622 Campbell Ave",
    "sg:city":"Waterloo",
    "sg:classifiers":[
        {
            "category":"Professional",
            "subcategory":"Business Services",
            "type":"Services"
        }
    ],
    "sg:phone":"+1 319 232 1923",
    "sg:postcode":"50701",
    "sg:province":"IA",
    "wof:name":"Certified Home Inspections",
    "wof:placetype":"venue"
},
  "geometry": {"coordinates":[-92.36501699999999,42.484008],"type":"Point"}
}