{
  "type": "Feature",
  "properties": {
    "iso:country":"US",
    "sg:address":"1165 220th St",
    "sg:city":"Jesup",
    "sg:classifiers":[
        {
            "category":"Wholesale",
            "subcategory":"Construction Materials",
            "type":"Manufacturing & Wholesale Goods"
        }
    ],
    "sg:phone":"+1 319 827 6660",
    "sg:postcode":"50648",
    "sg:province":"IA",
    "wof:name":"Paul Niemann Construction Co",
    "wof:placetype":"venue"
},
  "geometry": {"coordinates":[-92.04357899999999,42.468172],"type":"Point"}
}