{
  "type": "Feature",
  "properties": {
    "iso:country":"US",
    "sg:address":"400 Locust St",
    "sg:city":"Des Moines",
    "sg:classifiers":[
        {
            "category":"Restaurant",
            "type":"Food & Drink"
        }
    ],
    "sg:phone":"+1 515 288 9909",
    "sg:postcode":"50309",
    "sg:province":"IA",
    "wof:name":"Downtown Azteca",
    "wof:placetype":"venue"
},
  "geometry": {"coordinates":[-93.62373100000001,41.587097],"type":"Point"}
}