{
  "type": "Feature",
  "properties": {
    "addr:full":"1130 Seymour Ave Iowa City IA 52240",
    "addr:housenumber":"1130",
    "addr:postcode":"52240",
    "addr:street":"Seymour Ave",
    "iso:country":"US",
    "sg:address":"1130 Seymour Ave",
    "sg:city":"Iowa City",
    "sg:classifiers":[
        {
            "category":"Education",
            "subcategory":"School",
            "type":"Public Place"
        }
    ],
    "sg:phone":"+1 319 688 1135",
    "sg:postcode":"52240",
    "sg:province":"IA",
    "sg:website":"www.iowa-city.k12.ia.us",
    "wof:name":"Longfellow Elementary School",
    "wof:placetype":"venue"
},
  "geometry": {"coordinates":[-91.51687800000001,41.653567],"type":"Point"}
}