{
  "type": "Feature",
  "properties": {
    "iso:country":"US",
    "sg:address":"254 5th St",
    "sg:city":"Manilla",
    "sg:classifiers":[
        {
            "category":"Building & Trades",
            "subcategory":"Construction",
            "type":"Services"
        }
    ],
    "sg:phone":"+1 712 654 2752",
    "sg:postcode":"51454",
    "sg:province":"IA",
    "sg:tags":[
        "general",
        "contractor"
    ],
    "wof:name":"Rasmussen Lumber Co",
    "wof:placetype":"venue"
},
  "geometry": {"coordinates":[-95.232057,41.891579],"type":"Point"}
}