{
  "type": "Feature",
  "properties": {
    "addr:full":"1249 Morningside Ave Sioux City IA 51106",
    "addr:housenumber":"1249",
    "addr:postcode":"51106",
    "addr:street":"Morningside Ave",
    "iso:country":"US",
    "sg:address":"1249 Morningside Ave",
    "sg:city":"Sioux City",
    "sg:classifiers":[
        {
            "category":"Real Estate",
            "subcategory":"Real Estate Agent",
            "type":"Services"
        }
    ],
    "sg:phone":"+1 712 202 0229",
    "sg:postcode":"51106",
    "sg:province":"IA",
    "wof:name":"American Dream Realty",
    "wof:placetype":"venue"
},
  "geometry": {"coordinates":[-96.360805,42.477897],"type":"Point"}
}