{
  "type": "Feature",
  "properties": {
    "iso:country":"US",
    "sg:address":"132 W Main St",
    "sg:city":"Lime Springs",
    "sg:classifiers":[
        {
            "category":"Banks & Credit Unions",
            "subcategory":"Bank",
            "type":"Services"
        }
    ],
    "sg:phone":"+1 563 566 2215",
    "sg:postcode":"52155",
    "sg:province":"IA",
    "wof:name":"Cresco Union Savings Bank",
    "wof:placetype":"venue"
},
  "geometry": {"coordinates":[-92.27971100000001,43.448378],"type":"Point"}
}