{
  "type": "Feature",
  "properties": {
    "iso:country":"US",
    "sg:address":"215 SW Walnut St",
    "sg:city":"Ankeny",
    "sg:classifiers":[
        {
            "category":"Health Services",
            "subcategory":"Doctor",
            "type":"Services"
        }
    ],
    "sg:phone":"+1 515 964 7965",
    "sg:postcode":"50023",
    "sg:province":"IA",
    "sg:tags":[
        "physician",
        "surgeon"
    ],
    "wof:name":"Craig S Gerhart MD",
    "wof:placetype":"venue"
},
  "geometry": {"coordinates":[-93.605868,41.729789],"type":"Point"}
}