{
  "type": "Feature",
  "properties": {
    "iso:country":"US",
    "sg:address":"2481 33rd St S",
    "sg:city":"Muscatine",
    "sg:classifiers":[
        {
            "category":"Building & Trades",
            "subcategory":"Construction",
            "type":"Services"
        }
    ],
    "sg:phone":"+1 563 263 2361",
    "sg:postcode":"52761",
    "sg:province":"IA",
    "sg:tags":[
        "concrete",
        "contractor"
    ],
    "wof:name":"C & C Contractors",
    "wof:placetype":"venue"
},
  "geometry": {"coordinates":[-91.084132,41.38496],"type":"Point"}
}