{
  "type": "Feature",
  "properties": {
    "addr:full":"4113 350th St Emmetsburg IA 50536",
    "addr:housenumber":"4113",
    "addr:postcode":"50536",
    "addr:street":"350Th St",
    "iso:country":"US",
    "sg:address":"4113 350th St",
    "sg:city":"Emmetsburg",
    "sg:classifiers":[
        {
            "category":"Building & Trades",
            "subcategory":"Construction",
            "type":"Services"
        }
    ],
    "sg:phone":"+1 712 852 2136",
    "sg:postcode":"50536",
    "sg:province":"IA",
    "sg:tags":[
        "general",
        "contractor"
    ],
    "wof:name":"Helgeson Construction",
    "wof:placetype":"venue"
},
  "geometry": {"coordinates":[-94.75998199999999,43.141193],"type":"Point"}
}