{
  "type": "Feature",
  "properties": {
    "iso:country":"US",
    "sg:address":"514 W Central Ave",
    "sg:city":"Estherville",
    "sg:classifiers":[
        {
            "category":"Shopping",
            "subcategory":"Computers & Home Electronics",
            "type":"Retail Goods"
        }
    ],
    "sg:phone":"+1 712 362 4667",
    "sg:postcode":"51334",
    "sg:province":"IA",
    "sg:tags":[
        "repair"
    ],
    "wof:name":"Steves Sales & Service",
    "wof:placetype":"venue"
},
  "geometry": {"coordinates":[-94.85139700000001,43.402748],"type":"Point"}
}