{
  "type": "Feature",
  "properties": {
    "addr:full":"2923 Kingman Blvd Des Moines IA 50311",
    "addr:housenumber":"2923",
    "addr:postcode":"50311",
    "addr:street":"Kingman Blvd",
    "iso:country":"US",
    "sg:address":"2923 Kingman Blvd",
    "sg:city":"Des Moines",
    "sg:classifiers":[
        {
            "category":"Professional",
            "subcategory":"Business Services",
            "type":"Services"
        }
    ],
    "sg:phone":"+1 515 279 1242",
    "sg:postcode":"50311",
    "sg:province":"IA",
    "wof:name":"Toastmistress Internation",
    "wof:placetype":"venue"
},
  "geometry": {"coordinates":[-93.65913999999999,41.596663],"type":"Point"}
}