{
  "type": "Feature",
  "properties": {
    "addr:full":"1014 4th St NE Hampton IA 50441",
    "addr:housenumber":"1014",
    "addr:postcode":"50441",
    "addr:street":"4Th St Ne",
    "iso:country":"US",
    "sg:address":"1014 4th St NE",
    "sg:city":"Hampton",
    "sg:classifiers":[
        {
            "category":"Autos & Motor Vehicles",
            "subcategory":"Automobile Sales",
            "type":"Retail Goods"
        }
    ],
    "sg:phone":"+1 641 456 4559",
    "sg:postcode":"50441",
    "sg:province":"IA",
    "sg:tags":[
        "car",
        "dealer"
    ],
    "wof:name":"BSA Auto Sales",
    "wof:placetype":"venue"
},
  "geometry": {"coordinates":[-93.20250900000001,42.751628],"type":"Point"}
}