{
  "type": "Feature",
  "properties": {
    "iso:country":"US",
    "sg:address":"205 5th Ave",
    "sg:city":"Springville",
    "sg:classifiers":[
        {
            "category":"Home & Garden",
            "subcategory":"Building Materials",
            "type":"Retail Goods"
        }
    ],
    "sg:phone":"+1 319 854 7388",
    "sg:postcode":"52336",
    "sg:province":"IA",
    "sg:tags":[
        "windows"
    ],
    "wof:name":"Bill Reed Construction",
    "wof:placetype":"venue"
},
  "geometry": {"coordinates":[-91.443029,42.061549],"type":"Point"}
}