{
  "type": "Feature",
  "properties": {
    "iso:country":"US",
    "sg:address":"700 E University Ave",
    "sg:city":"Des Moines",
    "sg:classifiers":[
        {
            "category":"Health Services",
            "subcategory":"Doctor",
            "type":"Services"
        }
    ],
    "sg:phone":"+1 515 263 5599",
    "sg:postcode":"50316",
    "sg:province":"IA",
    "sg:tags":[
        "physician",
        "surgeon"
    ],
    "wof:name":"Regional Laboratory Consultnts",
    "wof:placetype":"venue"
},
  "geometry": {"coordinates":[-93.610176,41.600373],"type":"Point"}
}