{
  "type": "Feature",
  "properties": {
    "addr:full":"18206 130th St Aplington IA 50604",
    "addr:housenumber":"18206",
    "addr:postcode":"50604",
    "addr:street":"130Th St",
    "iso:country":"US",
    "sg:address":"18206 130th St",
    "sg:city":"Aplington",
    "sg:classifiers":[
        {
            "category":"Retail",
            "subcategory":"Auto Repair",
            "type":"Services"
        }
    ],
    "sg:phone":"+1 319 347 2814",
    "sg:postcode":"50604",
    "sg:province":"IA",
    "sg:tags":[
        "truck"
    ],
    "wof:name":"Lee's Diesel",
    "wof:placetype":"venue"
},
  "geometry": {"coordinates":[-92.86635800000001,42.514013],"type":"Point"}
}