{
  "type": "Feature",
  "properties": {
    "iso:country":"US",
    "sg:address":"112 NE Main St",
    "sg:city":"Melcher",
    "sg:classifiers":[
        {
            "category":"Recreation",
            "type":"Entertainment"
        }
    ],
    "sg:phone":"+1 641 947 6321",
    "sg:postcode":"50163",
    "sg:province":"IA",
    "sg:tags":[
        "hall",
        "auditorium"
    ],
    "wof:name":"Melcher-Dallas Community Ctr",
    "wof:placetype":"venue"
},
  "geometry": {"coordinates":[-93.241747,41.223873],"type":"Point"}
}