{
  "type": "Feature",
  "properties": {
    "iso:country":"US",
    "sg:address":"150 Des Moines St",
    "sg:city":"Des Moines",
    "sg:classifiers":[
        {
            "category":"Government",
            "subcategory":"Office",
            "type":"Public Place"
        }
    ],
    "sg:phone":"+1 515 281 5387",
    "sg:postcode":"50309",
    "sg:province":"IA",
    "sg:tags":[
        "state",
        "resource"
    ],
    "wof:name":"IOWA Workforce Development",
    "wof:placetype":"venue"
},
  "geometry": {"coordinates":[-93.615855,41.5909],"type":"Point"}
}