{
  "type": "Feature",
  "properties": {
    "addr:full":"1421 Washington St Cedar Falls IA 50613",
    "addr:housenumber":"1421",
    "addr:postcode":"50613",
    "addr:street":"Washington St",
    "iso:country":"US",
    "sg:address":"1421 Washington St",
    "sg:city":"Cedar Falls",
    "sg:classifiers":[
        {
            "category":"Shopping",
            "subcategory":"Crafts & Fabrics",
            "type":"Retail Goods"
        }
    ],
    "sg:phone":"+1 319 277 8303",
    "sg:postcode":"50613",
    "sg:province":"IA",
    "sg:tags":[
        "material",
        "quilting",
        "supply"
    ],
    "wof:name":"Aunt Emma's Attic Inc",
    "wof:placetype":"venue"
},
  "geometry": {"coordinates":[-92.446887,42.525105],"type":"Point"}
}