{
  "type": "Feature",
  "properties": {
    "iso:country":"US",
    "sg:address":"3697 190th St",
    "sg:city":"Goose Lake",
    "sg:classifiers":[
        {
            "category":"Farming",
            "subcategory":"Farm",
            "type":"Manufacturing & Wholesale Goods"
        }
    ],
    "sg:phone":"+1 563 522 2469",
    "sg:postcode":"52750",
    "sg:province":"IA",
    "sg:tags":[
        "crop",
        "general"
    ],
    "wof:name":"Herbert Meyermann",
    "wof:placetype":"venue"
},
  "geometry": {"coordinates":[-90.373923,41.902412],"type":"Point"}
}