{
  "type": "Feature",
  "properties": {
    "iso:country":"US",
    "sg:address":"1511 Okoboji Ave",
    "sg:city":"Milford",
    "sg:classifiers":[
        {
            "category":"Travel",
            "subcategory":"Hotels & Motels",
            "type":"Entertainment"
        }
    ],
    "sg:phone":"+1 712 338 4701",
    "sg:postcode":"51351",
    "sg:province":"IA",
    "wof:name":"Okoboji Avenue Inn",
    "wof:placetype":"venue"
},
  "geometry": {"coordinates":[-95.150057,43.330636],"type":"Point"}
}