{
  "type": "Feature",
  "properties": {
    "addr:full":"2174 Key Blvd Fairfield IA 52556",
    "addr:housenumber":"2174",
    "addr:postcode":"52556",
    "addr:street":"Key Blvd",
    "iso:country":"US",
    "sg:address":"2174 Key Blvd",
    "sg:city":"Fairfield",
    "sg:classifiers":[
        {
            "category":"Retail",
            "subcategory":"Animal Services",
            "type":"Services"
        }
    ],
    "sg:phone":"+1 641 472 6080",
    "sg:postcode":"52556",
    "sg:province":"IA",
    "sg:tags":[
        "shelter"
    ],
    "wof:name":"Noah's Ark Animal Foundation",
    "wof:placetype":"venue"
},
  "geometry": {"coordinates":[-91.980716,40.989291],"type":"Point"}
}