{
  "type": "Feature",
  "properties": {
    "addr:full":"12643 Ansborough Ave Hudson IA 50643",
    "addr:housenumber":"12643",
    "addr:postcode":"50643",
    "addr:street":"Ansborough Ave",
    "iso:country":"US",
    "sg:address":"12643 Ansborough Ave",
    "sg:city":"Hudson",
    "sg:phone":"+1 319 988 3147",
    "sg:postcode":"50643",
    "sg:province":"IA",
    "sg:tags":[
        "farm",
        "corn",
        "soybean"
    ],
    "wof:name":"Kevin Seda",
    "wof:placetype":"venue"
},
  "geometry": {"coordinates":[-92.376818,42.331799],"type":"Point"}
}