{
  "type": "Feature",
  "properties": {
    "iso:country":"US",
    "sg:address":"3233 150th St",
    "sg:city":"Dysart",
    "sg:phone":"+1 319 476 3226",
    "sg:postcode":"52224",
    "sg:province":"IA",
    "sg:tags":[
        "farm",
        "corn",
        "grain",
        "cash"
    ],
    "wof:name":"David Vogeler",
    "wof:placetype":"venue"
},
  "geometry": {"coordinates":[-92.337619,42.225372],"type":"Point"}
}