{
  "type": "Feature",
  "properties": {
    "iso:country":"US",
    "sg:address":"611 Mill Ave",
    "sg:city":"Springville",
    "sg:classifiers":[
        {
            "category":"Real Estate",
            "subcategory":"Real Estate Operator",
            "type":"Services"
        }
    ],
    "sg:phone":"+1 319 854 7195",
    "sg:postcode":"52336",
    "sg:province":"IA",
    "sg:tags":[
        "property",
        "lessor"
    ],
    "wof:name":"Allen Wittenburg",
    "wof:placetype":"venue"
},
  "geometry": {"coordinates":[-91.448212,42.053494],"type":"Point"}
}