{
  "type": "Feature",
  "properties": {
    "iso:country":"US",
    "sg:address":"112 W Bremer Ave",
    "sg:city":"Waverly",
    "sg:classifiers":[
        {
            "category":"Personal",
            "subcategory":"Beauty Salon",
            "type":"Services"
        }
    ],
    "sg:phone":"+1 319 352 6325",
    "sg:postcode":"50677",
    "sg:province":"IA",
    "wof:name":"Expressions Total Image Studio",
    "wof:placetype":"venue"
},
  "geometry": {"coordinates":[-92.473101,42.725829],"type":"Point"}
}