{
  "type": "Feature",
  "properties": {
    "addr:full":"1905 5th Ave S Fort Dodge IA 50501",
    "addr:housenumber":"1905",
    "addr:postcode":"50501",
    "addr:street":"5Th Ave S",
    "iso:country":"US",
    "sg:address":"1905 5th Ave S",
    "sg:city":"Fort Dodge",
    "sg:classifiers":[
        {
            "category":"Recreation",
            "subcategory":"Arcade",
            "type":"Entertainment"
        }
    ],
    "sg:phone":"+1 515 955 1942",
    "sg:postcode":"50501",
    "sg:province":"IA",
    "sg:tags":[
        "amusement",
        "devices"
    ],
    "wof:name":"Sunset Amusements",
    "wof:placetype":"venue"
},
  "geometry": {"coordinates":[-94.172089,42.501054],"type":"Point"}
}