{
  "type": "Feature",
  "properties": {
    "iso:country":"US",
    "sg:address":"915 Short St",
    "sg:city":"Decorah",
    "sg:classifiers":[
        {
            "category":"Restaurant",
            "type":"Food & Drink"
        }
    ],
    "sg:phone":"+1 563 382 0320",
    "sg:postcode":"52101",
    "sg:province":"IA",
    "wof:name":"Great Dragon Chinese Rstrnt",
    "wof:placetype":"venue"
},
  "geometry": {"coordinates":[-91.79703499999999,43.291522],"type":"Point"}
}