{
  "type": "Feature",
  "properties": {
    "iso:country":"US",
    "sg:address":"18 4th Ave E",
    "sg:city":"Spencer",
    "sg:classifiers":[
        {
            "category":"Autos & Motor Vehicles",
            "subcategory":"Motorcycle Sales",
            "type":"Retail Goods"
        }
    ],
    "sg:phone":"+1 712 262 8910",
    "sg:postcode":"51301",
    "sg:province":"IA",
    "sg:tags":[
        "scooter"
    ],
    "wof:name":"Chrome Horse",
    "wof:placetype":"venue"
},
  "geometry": {"coordinates":[-95.139084,43.137978],"type":"Point"}
}