{
  "type": "Feature",
  "properties": {
    "iso:country":"US",
    "sg:address":"713 Story St",
    "sg:city":"Boone",
    "sg:classifiers":[
        {
            "category":"Shopping",
            "subcategory":"Gifts & Souvenirs",
            "type":"Retail Goods"
        }
    ],
    "sg:phone":"+1 515 432 8272",
    "sg:postcode":"50036",
    "sg:province":"IA",
    "sg:tags":[
        "shop"
    ],
    "wof:name":"Walt's Hallmark Shop",
    "wof:placetype":"venue"
},
  "geometry": {"coordinates":[-93.88008600000001,42.063676],"type":"Point"}
}