{
  "type": "Feature",
  "properties": {
    "addr:full":"503 Melrose Ave Iowa City IA 52246",
    "addr:housenumber":"503",
    "addr:postcode":"52246",
    "addr:street":"Melrose Ave",
    "iso:country":"US",
    "sg:address":"503 Melrose Ave",
    "sg:city":"Iowa City",
    "sg:classifiers":[
        {
            "category":"Organizations",
            "subcategory":"Religious Organization",
            "type":"Services"
        }
    ],
    "sg:phone":"+1 319 354 3414",
    "sg:postcode":"52246",
    "sg:province":"IA",
    "sg:tags":[
        "church"
    ],
    "wof:name":"Iowa City Institute-Religion",
    "wof:placetype":"venue"
},
  "geometry": {"coordinates":[-91.54672100000001,41.656758],"type":"Point"}
}