{
  "type": "Feature",
  "properties": {
    "addr:full":"3025 86th St Urbandale IA 50322",
    "addr:housenumber":"3025",
    "addr:postcode":"50322",
    "addr:street":"86Th St",
    "iso:country":"US",
    "sg:address":"3025 86th St",
    "sg:city":"Urbandale",
    "sg:classifiers":[
        {
            "category":"Banks & Credit Unions",
            "subcategory":"Bank",
            "type":"Services"
        }
    ],
    "sg:phone":"+1 515 727 1891",
    "sg:postcode":"50322",
    "sg:province":"IA",
    "sg:tags":[
        "loan",
        "real estate"
    ],
    "wof:name":"Mortgage Solutions",
    "wof:placetype":"venue"
},
  "geometry": {"coordinates":[-93.73644400000001,41.622977],"type":"Point"}
}