{
  "type": "Feature",
  "properties": {
    "iso:country":"US",
    "sg:address":"3300 NE 150th Ave",
    "sg:city":"Cambridge",
    "sg:classifiers":[
        {
            "category":"Arts & Performance",
            "subcategory":"Theater",
            "type":"Entertainment"
        }
    ],
    "sg:phone":"+1 515 367 4845",
    "sg:postcode":"50046",
    "sg:province":"IA",
    "sg:tags":[
        "group"
    ],
    "wof:name":"Maple Street Jazz Band",
    "wof:placetype":"venue"
},
  "geometry": {"coordinates":[-93.557086,41.834875],"type":"Point"}
}