{
  "type": "Feature",
  "properties": {
    "iso:country":"US",
    "sg:address":"550 39th St",
    "sg:city":"Des Moines",
    "sg:classifiers":[
        {
            "category":"Health Services",
            "subcategory":"Health Practitioner",
            "type":"Services"
        }
    ],
    "sg:phone":"+1 515 274 3378",
    "sg:postcode":"50312",
    "sg:province":"IA",
    "wof:name":"Wright Jeanette Ms Atr",
    "wof:placetype":"venue"
},
  "geometry": {"coordinates":[-93.669819,41.585405],"type":"Point"}
}