{
  "type": "Feature",
  "properties": {
    "iso:country":"US",
    "sg:address":"7 W Airline Hwy",
    "sg:city":"Waterloo",
    "sg:classifiers":[
        {
            "category":"Home & Garden",
            "subcategory":"Hardware",
            "type":"Retail Goods"
        }
    ],
    "sg:phone":"+1 319 232 6225",
    "sg:postcode":"50703",
    "sg:province":"IA",
    "wof:name":"Dheins Hardware",
    "wof:placetype":"venue"
},
  "geometry": {"coordinates":[-92.341887,42.542079],"type":"Point"}
}