{
  "type": "Feature",
  "properties": {
    "iso:country":"US",
    "sg:address":"1290 Park View Dr",
    "sg:city":"Story City",
    "sg:classifiers":[
        {
            "category":"Professional",
            "subcategory":"Computer Services",
            "type":"Services"
        }
    ],
    "sg:phone":"+1 515 733 5289",
    "sg:postcode":"50248",
    "sg:province":"IA",
    "sg:tags":[
        "internet"
    ],
    "wof:name":"A Tech Group",
    "wof:placetype":"venue"
},
  "geometry": {"coordinates":[-93.582354,42.183003],"type":"Point"}
}