{
  "type": "Feature",
  "properties": {
    "iso:country":"US",
    "sg:address":"2153 390th St",
    "sg:city":"Grafton",
    "sg:classifiers":[
        {
            "category":"Personal",
            "subcategory":"Beauty Salon",
            "type":"Services"
        }
    ],
    "sg:phone":"+1 641 748 2350",
    "sg:postcode":"50440",
    "sg:province":"IA",
    "wof:name":"Lori's Country Hair Care",
    "wof:placetype":"venue"
},
  "geometry": {"coordinates":[-93.103487,43.327642],"type":"Point"}
}