{
  "type": "Feature",
  "properties": {
    "iso:country":"US",
    "sg:address":"403 E 6th St",
    "sg:city":"Logan",
    "sg:classifiers":[
        {
            "category":"Food & Beverages",
            "subcategory":"Groceries & Convenience Stores",
            "type":"Retail Goods"
        }
    ],
    "sg:phone":"+1 712 644 2280",
    "sg:postcode":"51546",
    "sg:province":"IA",
    "sg:tags":[
        "grocer"
    ],
    "wof:name":"Harvey's Fine Foods",
    "wof:placetype":"venue"
},
  "geometry": {"coordinates":[-95.785149,41.644139],"type":"Point"}
}