{
  "type": "Feature",
  "properties": {
    "iso:country":"US",
    "sg:address":"339 Nederhiser Rd",
    "sg:city":"Ely",
    "sg:classifiers":[
        {
            "category":"Building & Trades",
            "subcategory":"Landscaping Services",
            "type":"Services"
        }
    ],
    "sg:phone":"+1 319 848 4838",
    "sg:postcode":"52227",
    "sg:province":"IA",
    "sg:tags":[
        "lawn",
        "maintenance",
        "grounds"
    ],
    "wof:name":"Grass Carpet Lawn Svc",
    "wof:placetype":"venue"
},
  "geometry": {"coordinates":[-91.52512400000001,41.875646],"type":"Point"}
}