{
  "type": "Feature",
  "properties": {
    "addr:full":"218 N 3rd St Burlington IA 52601",
    "addr:housenumber":"218",
    "addr:postcode":"52601",
    "addr:street":"N 3Rd St",
    "iso:country":"US",
    "sg:address":"218 N 3rd St",
    "sg:city":"Burlington",
    "sg:classifiers":[
        {
            "category":"Professional",
            "subcategory":"Accounting & Tax Preparation",
            "type":"Services"
        }
    ],
    "sg:phone":"+1 319 753 2838",
    "sg:postcode":"52601",
    "sg:province":"IA",
    "sg:tags":[
        "accountant"
    ],
    "wof:name":"First Rate Accounting Service",
    "wof:placetype":"venue"
},
  "geometry": {"coordinates":[-91.102677,40.80979],"type":"Point"}
}