{
  "type": "Feature",
  "properties": {
    "iso:country":"US",
    "sg:address":"222 9th Ave",
    "sg:city":"De Witt",
    "sg:classifiers":[
        {
            "category":"Building & Trades",
            "subcategory":"Cleaning & Sanitation",
            "type":"Services"
        }
    ],
    "sg:phone":"+1 563 659 3321",
    "sg:postcode":"52742",
    "sg:province":"IA",
    "sg:tags":[
        "maintenance"
    ],
    "wof:name":"Bills Window Washing",
    "wof:placetype":"venue"
},
  "geometry": {"coordinates":[-90.543244,41.817825],"type":"Point"}
}