{
  "type": "Feature",
  "properties": {
    "iso:country":"US",
    "sg:address":"1803 Gary Ave",
    "sg:city":"Spirit Lake",
    "sg:classifiers":[
        {
            "category":"Retail",
            "subcategory":"Portrait Studio",
            "type":"Services"
        }
    ],
    "sg:phone":"+1 712 336 2378",
    "sg:postcode":"51360",
    "sg:province":"IA",
    "sg:tags":[
        "photo"
    ],
    "wof:name":"Focal Image",
    "wof:placetype":"venue"
},
  "geometry": {"coordinates":[-95.10063700000001,43.422608],"type":"Point"}
}