{
  "type": "Feature",
  "properties": {
    "iso:country":"US",
    "sg:address":"1768 D Ave",
    "sg:city":"Knoxville",
    "sg:classifiers":[
        {
            "category":"Farming",
            "subcategory":"Livestock Farm",
            "type":"Manufacturing & Wholesale Goods"
        }
    ],
    "sg:phone":"+1 641 842 6815",
    "sg:postcode":"50138",
    "sg:province":"IA",
    "sg:tags":[
        "hog",
        "or",
        "feedlot"
    ],
    "wof:name":"Dan Zickel",
    "wof:placetype":"venue"
},
  "geometry": {"coordinates":[-93.009271,41.267522],"type":"Point"}
}