{
  "type": "Feature",
  "properties": {
    "iso:country":"US",
    "sg:address":"3235 Jackson Ave",
    "sg:city":"Odebolt",
    "sg:phone":"+1 712 668 4372",
    "sg:postcode":"51458",
    "sg:province":"IA",
    "sg:tags":[
        "farm",
        "corn",
        "wheat"
    ],
    "wof:name":"Fred Schultz",
    "wof:placetype":"venue"
},
  "geometry": {"coordinates":[-95.16783599999999,42.321188],"type":"Point"}
}