{
  "type": "Feature",
  "properties": {
    "iso:country":"US",
    "sg:address":"1340 3rd Ave SE",
    "sg:city":"Cedar Rapids",
    "sg:classifiers":[
        {
            "category":"Social Services",
            "subcategory":"Child Care",
            "type":"Services"
        }
    ],
    "sg:phone":"+1 319 363 6349",
    "sg:postcode":"52403",
    "sg:province":"IA",
    "sg:tags":[
        "elementary",
        "kindergarten",
        "school",
        "academic"
    ],
    "wof:name":"St Paul's Early Childhood Programs",
    "wof:placetype":"venue"
},
  "geometry": {"coordinates":[-91.652901,41.984901],"type":"Point"}
}