{
  "type": "Feature",
  "properties": {
    "iso:country":"US",
    "sg:address":"837 Washington St",
    "sg:city":"Pella",
    "sg:classifiers":[
        {
            "category":"Organizations",
            "subcategory":"Religious Organization",
            "type":"Services"
        }
    ],
    "sg:phone":"+1 641 628 3707",
    "sg:postcode":"50219",
    "sg:province":"IA",
    "sg:tags":[
        "church"
    ],
    "wof:name":"Open Bible Church",
    "wof:placetype":"venue"
},
  "geometry": {"coordinates":[-92.919517,41.408006],"type":"Point"}
}