{
  "type": "Feature",
  "properties": {
    "iso:country":"US",
    "sg:address":"1533 Central Ave",
    "sg:city":"Dubuque",
    "sg:classifiers":[
        {
            "category":"Wholesale",
            "subcategory":"Office Equipment",
            "type":"Manufacturing & Wholesale Goods"
        }
    ],
    "sg:phone":"+1 563 556 3455",
    "sg:postcode":"52001",
    "sg:province":"IA",
    "sg:tags":[
        "machine",
        "duplicating",
        "copying"
    ],
    "wof:name":"American Imaging Supplies",
    "wof:placetype":"venue"
},
  "geometry": {"coordinates":[-90.66857400000001,42.507687],"type":"Point"}
}