{
  "type": "Feature",
  "properties": {
    "addr:full":"2386 330th Ave Hartwick IA 52232",
    "addr:housenumber":"2386",
    "addr:postcode":"52232",
    "addr:street":"330Th Ave",
    "iso:country":"US",
    "sg:address":"2386 330th Ave",
    "sg:city":"Hartwick",
    "sg:classifiers":[
        {
            "category":"Real Estate",
            "subcategory":"Real Estate Operator",
            "type":"Services"
        }
    ],
    "sg:phone":"+1 319 525 3153",
    "sg:postcode":"52232",
    "sg:province":"IA",
    "sg:tags":[
        "property",
        "lessor"
    ],
    "wof:name":"Craig Merle",
    "wof:placetype":"venue"
},
  "geometry": {"coordinates":[-92.334261,41.819497],"type":"Point"}
}