{
  "type": "Feature",
  "properties": {
    "iso:country":"US",
    "sg:address":"57131 245th St",
    "sg:city":"Ames",
    "sg:phone":"+1 515 232 6456",
    "sg:postcode":"50010",
    "sg:province":"IA",
    "sg:tags":[
        "farm",
        "corn",
        "soybean"
    ],
    "wof:name":"Dennis Kingsbury",
    "wof:placetype":"venue"
},
  "geometry": {"coordinates":[-93.560585,42.001345],"type":"Point"}
}