{
  "type": "Feature",
  "properties": {
    "iso:country":"US",
    "sg:address":"546 Main St",
    "sg:city":"Ames",
    "sg:classifiers":[
        {
            "category":"Shopping",
            "subcategory":"Clothing, Apparel, & Fashions",
            "type":"Retail Goods"
        }
    ],
    "sg:phone":"+1 515 663 9748",
    "sg:postcode":"50010",
    "sg:province":"IA",
    "wof:name":"Talbots",
    "wof:placetype":"venue"
},
  "geometry": {"coordinates":[-93.618724,42.024966],"type":"Point"}
}