{
  "type": "Feature",
  "properties": {
    "iso:country":"US",
    "sg:address":"221 Northwestern Ave",
    "sg:city":"Chariton",
    "sg:classifiers":[
        {
            "category":"Education",
            "subcategory":"Special Training",
            "type":"Public Place"
        }
    ],
    "sg:phone":"+1 641 774 7471",
    "sg:postcode":"50049",
    "sg:province":"IA",
    "sg:tags":[
        "center"
    ],
    "wof:name":"Detention Ctr Education Progrm",
    "wof:placetype":"venue"
},
  "geometry": {"coordinates":[-93.29591000000001,41.002977],"type":"Point"}
}