{
  "type": "Feature",
  "properties": {
    "addr:full":"4904 Millbrook Ct NE Cedar Rapids IA 52411",
    "addr:housenumber":"4904",
    "addr:postcode":"52411",
    "addr:street":"Millbrook Ct Ne",
    "iso:country":"US",
    "sg:address":"4904 Millbrook Ct NE",
    "sg:city":"Cedar Rapids",
    "sg:classifiers":[
        {
            "category":"Professional",
            "subcategory":"Business Services",
            "type":"Services"
        }
    ],
    "sg:phone":"+1 319 378 1965",
    "sg:postcode":"52411",
    "sg:province":"IA",
    "wof:name":"Blue Cow Enterprises LLC",
    "wof:placetype":"venue"
},
  "geometry": {"coordinates":[-91.70898800000001,42.025366],"type":"Point"}
}