{
  "type": "Feature",
  "properties": {
    "addr:full":"1504 Madison St Bedford IA 50833",
    "addr:housenumber":"1504",
    "addr:postcode":"50833",
    "addr:street":"Madison St",
    "iso:country":"US",
    "sg:address":"1504 Madison St",
    "sg:city":"Bedford",
    "sg:classifiers":[
        {
            "category":"Real Estate",
            "subcategory":"Real Estate Operator",
            "type":"Services"
        }
    ],
    "sg:phone":"+1 712 268 2351",
    "sg:postcode":"50833",
    "sg:province":"IA",
    "sg:tags":[
        "apartment"
    ],
    "wof:name":"Bedford Community Housing Assn",
    "wof:placetype":"venue"
},
  "geometry": {"coordinates":[-94.721305,40.674904],"type":"Point"}
}