{
  "type": "Feature",
  "properties": {
    "iso:country":"US",
    "sg:address":"700 Main St",
    "sg:city":"Pella",
    "sg:classifiers":[
        {
            "category":"Professional",
            "subcategory":"Accounting & Tax Preparation",
            "type":"Services"
        }
    ],
    "sg:phone":"+1 641 628 2246",
    "sg:postcode":"50219",
    "sg:province":"IA",
    "sg:tags":[
        "accountant"
    ],
    "wof:name":"De Waard Financial & Acctg",
    "wof:placetype":"venue"
},
  "geometry": {"coordinates":[-92.916471,41.406713],"type":"Point"}
}