{
  "type": "Feature",
  "properties": {
    "iso:country":"US",
    "sg:address":"6322 University Ave",
    "sg:city":"Cedar Falls",
    "sg:classifiers":[
        {
            "category":"Personal",
            "subcategory":"Beauty Salon",
            "type":"Services"
        }
    ],
    "sg:phone":"+1 319 277 2150",
    "sg:postcode":"50613",
    "sg:province":"IA",
    "sg:tags":[
        "spa",
        "day"
    ],
    "sg:website":"www.lajamesinternational.com",
    "wof:name":"La' James College",
    "wof:placetype":"venue"
},
  "geometry": {"coordinates":[-92.43476,42.513455],"type":"Point"}
}