{
  "type": "Feature",
  "properties": {
    "iso:country":"US",
    "sg:address":"905 Sycamore St",
    "sg:city":"Waterloo",
    "sg:classifiers":[
        {
            "category":"Building & Trades",
            "subcategory":"Construction",
            "type":"Services"
        }
    ],
    "sg:phone":"+1 319 433 1217",
    "sg:postcode":"50703",
    "sg:province":"IA",
    "sg:tags":[
        "acoustical",
        "contractor"
    ],
    "wof:name":"D B Acoustics Inc",
    "wof:placetype":"venue"
},
  "geometry": {"coordinates":[-92.331694,42.495575],"type":"Point"}
}