{
  "type": "Feature",
  "properties": {
    "addr:full":"4824 Norwood Dr Bettendorf IA 52722",
    "addr:housenumber":"4824",
    "addr:postcode":"52722",
    "addr:street":"Norwood Dr",
    "iso:country":"US",
    "sg:address":"4824 Norwood Dr",
    "sg:city":"Bettendorf",
    "sg:classifiers":[
        {
            "category":"Home & Garden",
            "subcategory":"Home Furnishings",
            "type":"Retail Goods"
        }
    ],
    "sg:phone":"+1 563 332 9618",
    "sg:postcode":"52722",
    "sg:province":"IA",
    "sg:tags":[
        "lighting"
    ],
    "wof:name":"Holophane Lighting Co",
    "wof:placetype":"venue"
},
  "geometry": {"coordinates":[-90.466069,41.557582],"type":"Point"}
}