{
  "type": "Feature",
  "properties": {
    "iso:country":"US",
    "sg:address":"3533 Main St",
    "sg:city":"Keokuk",
    "sg:classifiers":[
        {
            "category":"Banks & Credit Unions",
            "subcategory":"Bank",
            "type":"Services"
        }
    ],
    "sg:phone":"+1 319 524 9961",
    "sg:postcode":"52632",
    "sg:province":"IA",
    "sg:tags":[
        "financing"
    ],
    "wof:name":"Wells Fargo Financial",
    "wof:placetype":"venue"
},
  "geometry": {"coordinates":[-91.41117300000001,40.424336],"type":"Point"}
}