{
  "type": "Feature",
  "properties": {
    "addr:full":"808 North Ave Norwalk IA 50211",
    "addr:housenumber":"808",
    "addr:postcode":"50211",
    "addr:street":"North Ave",
    "iso:country":"US",
    "sg:address":"808 North Ave",
    "sg:city":"Norwalk",
    "sg:classifiers":[
        {
            "category":"Freight",
            "type":"Transportation"
        }
    ],
    "sg:phone":"+1 515 981 9021",
    "sg:postcode":"50211",
    "sg:province":"IA",
    "sg:tags":[
        "commercial",
        "storage"
    ],
    "wof:name":"Norwalk Mini-Storage",
    "wof:placetype":"venue"
},
  "geometry": {"coordinates":[-93.67873899999999,41.475247],"type":"Point"}
}