{
  "type": "Feature",
  "properties": {
    "iso:country":"US",
    "sg:address":"17209 Cedar Ave",
    "sg:city":"Postville",
    "sg:phone":"+1 563 539 4323",
    "sg:postcode":"52162",
    "sg:province":"IA",
    "sg:tags":[
        "farm",
        "corn"
    ],
    "wof:name":"Mark Landsgard",
    "wof:placetype":"venue"
},
  "geometry": {"coordinates":[-91.50841800000001,42.974933],"type":"Point"}
}