{
  "type": "Feature",
  "properties": {
    "iso:country":"US",
    "sg:address":"109 Conant St",
    "sg:city":"Jefferson",
    "sg:classifiers":[
        {
            "category":"Retail",
            "subcategory":"Auto Repair",
            "type":"Services"
        }
    ],
    "sg:phone":"+1 515 386 2439",
    "sg:postcode":"50129",
    "sg:province":"IA",
    "sg:tags":[
        "general"
    ],
    "wof:name":"Gary Akin",
    "wof:placetype":"venue"
},
  "geometry": {"coordinates":[-94.447654,42.075095],"type":"Point"}
}