{
  "type": "Feature",
  "properties": {
    "iso:country":"US",
    "sg:address":"209 Isabella St",
    "sg:city":"Radcliffe",
    "sg:classifiers":[
        {
            "category":"Shopping",
            "subcategory":"Used Merchandise",
            "type":"Retail Goods"
        }
    ],
    "sg:phone":"+1 515 899 2129",
    "sg:postcode":"50230",
    "sg:province":"IA",
    "sg:tags":[
        "shop",
        "consignment"
    ],
    "wof:name":"Hidden Treasure",
    "wof:placetype":"venue"
},
  "geometry": {"coordinates":[-93.434303,42.313987],"type":"Point"}
}