{
  "type": "Feature",
  "properties": {
    "iso:country":"US",
    "sg:address":"1641 S Bluff Blvd",
    "sg:city":"Clinton",
    "sg:classifiers":[
        {
            "category":"Autos & Motor Vehicles",
            "subcategory":"Fuel & Gas Station",
            "type":"Retail Goods"
        }
    ],
    "sg:phone":"+1 563 242 0456",
    "sg:postcode":"52732",
    "sg:province":"IA",
    "sg:tags":[
        "oil"
    ],
    "wof:name":"Bluff 76 Svc Ctr Inc",
    "wof:placetype":"venue"
},
  "geometry": {"coordinates":[-90.224245,41.833608],"type":"Point"}
}