{
  "type": "Feature",
  "properties": {
    "iso:country":"US",
    "sg:address":"68030 US Hwy 30",
    "sg:city":"Colo",
    "sg:classifiers":[
        {
            "category":"Sports & Exercise",
            "subcategory":"Golf",
            "type":"Entertainment"
        }
    ],
    "sg:phone":"+1 641 377 2245",
    "sg:postcode":"50056",
    "sg:province":"IA",
    "sg:tags":[
        "course"
    ],
    "wof:name":"Twin Anchors Golf Club",
    "wof:placetype":"venue"
},
  "geometry": {"coordinates":[-93.344084,42.008177],"type":"Point"}
}