{
  "type": "Feature",
  "properties": {
    "iso:country":"US",
    "sg:address":"201 Center St",
    "sg:city":"Lime Springs",
    "sg:classifiers":[
        {
            "category":"Government",
            "subcategory":"Office",
            "type":"Public Place"
        }
    ],
    "sg:phone":"+1 563 566 4405",
    "sg:postcode":"52155",
    "sg:province":"IA",
    "sg:tags":[
        "city"
    ],
    "wof:name":"Lime Springs Community Ctr",
    "wof:placetype":"venue"
},
  "geometry": {"coordinates":[-92.280974,43.447948],"type":"Point"}
}