{
  "type": "Feature",
  "properties": {
    "iso:country":"US",
    "sg:address":"1200 Venbury Dr",
    "sg:city":"Altoona",
    "sg:classifiers":[
        {
            "category":"Recreation",
            "type":"Entertainment"
        }
    ],
    "sg:phone":"+1 515 967 9566",
    "sg:postcode":"50009",
    "sg:province":"IA",
    "sg:tags":[
        "pool",
        "swimming"
    ],
    "wof:name":"Altoona Municipal Pool",
    "wof:placetype":"venue"
},
  "geometry": {"coordinates":[-93.475717,41.639252],"type":"Point"}
}