{
  "type": "Feature",
  "properties": {
    "iso:country":"US",
    "sg:address":"414 James St",
    "sg:city":"Waterloo",
    "sg:classifiers":[
        {
            "category":"Building & Trades",
            "subcategory":"Plumbing",
            "type":"Services"
        }
    ],
    "sg:phone":"+1 319 235 6367",
    "sg:postcode":"50702",
    "sg:province":"IA",
    "sg:tags":[
        "contractor"
    ],
    "wof:name":"Poyner Plumbing",
    "wof:placetype":"venue"
},
  "geometry": {"coordinates":[-92.32049600000001,42.481368],"type":"Point"}
}