{
  "type": "Feature",
  "properties": {
    "iso:country":"US",
    "sg:address":"38 Prospect St SW",
    "sg:city":"Le Mars",
    "sg:classifiers":[
        {
            "category":"Personal",
            "subcategory":"Beauty Salon",
            "type":"Services"
        }
    ],
    "sg:phone":"+1 712 546 5353",
    "sg:postcode":"51031",
    "sg:province":"IA",
    "sg:tags":[
        "shop"
    ],
    "wof:name":"Judy's Beauty Salon",
    "wof:placetype":"venue"
},
  "geometry": {"coordinates":[-96.168108,42.776633],"type":"Point"}
}