{
  "type": "Feature",
  "properties": {
    "iso:country":"US",
    "sg:address":"1099 Bridgeview Pl",
    "sg:city":"Le Claire",
    "sg:classifiers":[
        {
            "category":"Shopping",
            "type":"Retail Goods"
        }
    ],
    "sg:phone":"+1 563 289 9014",
    "sg:postcode":"52753",
    "sg:province":"IA",
    "sg:tags":[
        "merchandise"
    ],
    "wof:name":"Blankies By Katherine",
    "wof:placetype":"venue"
},
  "geometry": {"coordinates":[-90.353213,41.593644],"type":"Point"}
}