{
  "type": "Feature",
  "properties": {
    "addr:full":"933 Norwood Dr SE Cedar Rapids IA 52403",
    "addr:housenumber":"933",
    "addr:postcode":"52403",
    "addr:street":"Norwood Dr Se",
    "iso:country":"US",
    "sg:address":"933 Norwood Dr SE",
    "sg:city":"Cedar Rapids",
    "sg:classifiers":[
        {
            "category":"Manufacturing",
            "subcategory":"Apparel",
            "type":"Manufacturing & Wholesale Goods"
        }
    ],
    "sg:phone":"+1 319 363 3829",
    "sg:postcode":"52403",
    "sg:province":"IA",
    "wof:name":"Embroidery By Lois",
    "wof:placetype":"venue"
},
  "geometry": {"coordinates":[-91.62959499999999,41.975305],"type":"Point"}
}