{
  "type": "Feature",
  "properties": {
    "addr:full":"114 S Franklin St Manchester IA 52057",
    "addr:housenumber":"114",
    "addr:postcode":"52057",
    "addr:street":"S Franklin St",
    "iso:country":"US",
    "sg:address":"114 S Franklin St",
    "sg:city":"Manchester",
    "sg:classifiers":[
        {
            "category":"Shopping",
            "subcategory":"Gifts & Souvenirs",
            "type":"Retail Goods"
        }
    ],
    "sg:phone":"+1 563 927 4189",
    "sg:postcode":"52057",
    "sg:province":"IA",
    "sg:tags":[
        "shop"
    ],
    "wof:name":"Treasure Alley",
    "wof:placetype":"venue"
},
  "geometry": {"coordinates":[-91.45782800000001,42.48384],"type":"Point"}
}