{
  "type": "Feature",
  "properties": {
    "addr:full":"3520 Utica Ridge Rd Bettendorf IA 52807",
    "addr:housenumber":"3520",
    "addr:postcode":"52807",
    "addr:street":"Utica Ridge Rd",
    "iso:country":"US",
    "sg:address":"3520 Utica Ridge Rd",
    "sg:city":"Bettendorf",
    "sg:classifiers":[
        {
            "category":"Health Services",
            "subcategory":"Doctor",
            "type":"Services"
        }
    ],
    "sg:phone":"+1 563 359 9165",
    "sg:postcode":"52807",
    "sg:province":"IA",
    "sg:tags":[
        "dentist"
    ],
    "wof:name":"Dentistry Unlimited",
    "wof:placetype":"venue"
},
  "geometry": {"coordinates":[-90.517089,41.558361],"type":"Point"}
}