{
  "type": "Feature",
  "properties": {
    "addr:full":"35938 Beechnut Rd Carson IA 51549",
    "addr:housenumber":"35938",
    "addr:postcode":"51549",
    "addr:street":"Beechnut Rd",
    "iso:country":"US",
    "sg:address":"35938 Beechnut Rd",
    "sg:city":"Carson",
    "sg:classifiers":[
        {
            "category":"Organizations",
            "subcategory":"Community Association",
            "type":"Services"
        }
    ],
    "sg:phone":"+1 712 486 2440",
    "sg:postcode":"51549",
    "sg:province":"IA",
    "wof:name":"Optimist International",
    "wof:placetype":"venue"
},
  "geometry": {"coordinates":[-95.510114,41.203613],"type":"Point"}
}