{
  "type": "Feature",
  "properties": {
    "iso:country":"US",
    "sg:address":"763 8th Ave",
    "sg:city":"Marion",
    "sg:classifiers":[
        {
            "category":"Retail",
            "subcategory":"Repair Shop",
            "type":"Services"
        }
    ],
    "sg:phone":"+1 319 377 0677",
    "sg:postcode":"52302",
    "sg:province":"IA",
    "sg:tags":[
        "upholsterer"
    ],
    "wof:name":"Curls Upholstering & Furniture",
    "wof:placetype":"venue"
},
  "geometry": {"coordinates":[-91.60218,42.034113],"type":"Point"}
}