{
  "type": "Feature",
  "properties": {
    "iso:country":"US",
    "sg:address":"201 1st Ave SW",
    "sg:city":"Cedar Rapids",
    "sg:classifiers":[
        {
            "category":"Shopping",
            "type":"Retail Goods"
        }
    ],
    "sg:phone":"+1 319 362 5597",
    "sg:postcode":"52405",
    "sg:province":"IA",
    "sg:tags":[
        "pet",
        "shop"
    ],
    "wof:name":"Pet's Playhouse",
    "wof:placetype":"venue"
},
  "geometry": {"coordinates":[-91.67569399999999,41.975681],"type":"Point"}
}