{
  "type": "Feature",
  "properties": {
    "addr:full":"29722 180th St Dike IA 50624",
    "addr:housenumber":"29722",
    "addr:postcode":"50624",
    "addr:street":"180Th St",
    "iso:country":"US",
    "sg:address":"29722 180th St",
    "sg:city":"Dike",
    "sg:phone":"+1 319 989 2753",
    "sg:postcode":"50624",
    "sg:province":"IA",
    "sg:tags":[
        "farm",
        "corn",
        "soybean"
    ],
    "wof:name":"Dennis Viet",
    "wof:placetype":"venue"
},
  "geometry": {"coordinates":[-92.63862899999999,42.44191],"type":"Point"}
}