{
  "type": "Feature",
  "properties": {
    "iso:country":"US",
    "sg:address":"5817 Stone Ave",
    "sg:city":"Sioux City",
    "sg:classifiers":[
        {
            "category":"Retail",
            "subcategory":"Laundry & Dry Cleaning",
            "type":"Services"
        }
    ],
    "sg:phone":"+1 712 266 1177",
    "sg:postcode":"51106",
    "sg:province":"SD",
    "sg:tags":[
        "cleaners",
        "rug",
        "carpet"
    ],
    "wof:name":"Chem-Dry Of Siouxland",
    "wof:placetype":"venue"
},
  "geometry": {"coordinates":[-96.33116200000001,42.479094],"type":"Point"}
}