{
  "type": "Feature",
  "properties": {
    "addr:full":"1838 State St Bettendorf IA 52722",
    "addr:housenumber":"1838",
    "addr:postcode":"52722",
    "addr:street":"State St",
    "iso:country":"US",
    "sg:address":"1838 State St",
    "sg:city":"Bettendorf",
    "sg:classifiers":[
        {
            "category":"Autos & Motor Vehicles",
            "subcategory":"Automobile Sales",
            "type":"Retail Goods"
        }
    ],
    "sg:phone":"+1 563 359 1074",
    "sg:postcode":"52722",
    "sg:province":"IA",
    "sg:tags":[
        "classic"
    ],
    "wof:name":"Veit's Vettes & Collector Cars",
    "wof:placetype":"venue"
},
  "geometry": {"coordinates":[-90.50632299999999,41.525363],"type":"Point"}
}