{
  "type": "Feature",
  "properties": {
    "iso:country":"US",
    "sg:address":"314 S Elm Ave",
    "sg:city":"Logan",
    "sg:classifiers":[
        {
            "category":"Health Services",
            "subcategory":"Nursing And Care Facility",
            "type":"Services"
        }
    ],
    "sg:phone":"+1 712 644 2922",
    "sg:postcode":"51546",
    "sg:province":"IA",
    "sg:tags":[
        "home",
        "convalescent"
    ],
    "wof:name":"Westmont Care",
    "wof:placetype":"venue"
},
  "geometry": {"coordinates":[-95.793295,41.64012],"type":"Point"}
}