{
  "type": "Feature",
  "properties": {
    "iso:country":"US",
    "sg:address":"2023 S Federal Ave",
    "sg:city":"Mason City",
    "sg:classifiers":[
        {
            "category":"Government",
            "subcategory":"Office",
            "type":"Public Place"
        }
    ],
    "sg:phone":"+1 641 423 0844",
    "sg:postcode":"50401",
    "sg:province":"IA",
    "wof:name":"Cerro Gordo County Extension",
    "wof:placetype":"venue"
},
  "geometry": {"coordinates":[-93.20102300000001,43.132321],"type":"Point"}
}