{
  "type": "Feature",
  "properties": {
    "addr:full":"1623 Prairie St Grinnell IA 50112",
    "addr:housenumber":"1623",
    "addr:postcode":"50112",
    "addr:street":"Prairie St",
    "iso:country":"US",
    "sg:address":"1623 Prairie St",
    "sg:city":"Grinnell",
    "sg:classifiers":[
        {
            "category":"Building & Trades",
            "subcategory":"Construction",
            "type":"Services"
        }
    ],
    "sg:phone":"+1 641 236 6032",
    "sg:postcode":"50112",
    "sg:province":"IA",
    "sg:tags":[
        "general",
        "contractor"
    ],
    "wof:name":"Glasgow's Inc Construction",
    "wof:placetype":"venue"
},
  "geometry": {"coordinates":[-92.734092,41.755205],"type":"Point"}
}