{
  "type": "Feature",
  "properties": {
    "iso:country":"US",
    "sg:address":"322 W Milwaukee Ave",
    "sg:city":"Storm Lake",
    "sg:classifiers":[
        {
            "category":"Home & Garden",
            "subcategory":"Household Appliances",
            "type":"Retail Goods"
        },
        {
            "category":"Shopping",
            "subcategory":"Gifts & Souvenirs",
            "type":"Retail Goods"
        }
    ],
    "sg:phone":"+1 712 732 3695",
    "sg:postcode":"50588",
    "sg:province":"IA",
    "sg:tags":[
        "repair",
        "vacuum",
        "electrical",
        "cleaners"
    ],
    "wof:name":"Mickelson Vacuum Sales & Repr",
    "wof:placetype":"venue"
},
  "geometry": {"coordinates":[-95.204448,42.64739],"type":"Point"}
}