{
  "type": "Feature",
  "properties": {
    "iso:country":"US",
    "sg:address":"323 N Harrison St",
    "sg:city":"Davenport",
    "sg:classifiers":[
        {
            "category":"Wholesale",
            "subcategory":"Machinery & Supplies",
            "type":"Manufacturing & Wholesale Goods"
        }
    ],
    "sg:phone":"+1 563 322 2122",
    "sg:postcode":"52801",
    "sg:province":"IA",
    "sg:tags":[
        "shoe",
        "findings"
    ],
    "wof:name":"Kambach & Kettman",
    "wof:placetype":"venue"
},
  "geometry": {"coordinates":[-90.57696799999999,41.522744],"type":"Point"}
}