{
  "type": "Feature",
  "properties": {
    "addr:full":"2275 Flint Hill Dr Dubuque IA 52003",
    "addr:housenumber":"2275",
    "addr:postcode":"52003",
    "addr:street":"Flint Hill Dr",
    "iso:country":"US",
    "sg:address":"2275 Flint Hill Dr",
    "sg:city":"Dubuque",
    "sg:classifiers":[
        {
            "category":"Food & Beverages",
            "subcategory":"Bakery",
            "type":"Retail Goods"
        }
    ],
    "sg:phone":"+1 563 585 2055",
    "sg:postcode":"52003",
    "sg:province":"IA",
    "sg:tags":[
        "baker"
    ],
    "wof:name":"Sara Lee Bakery Group",
    "wof:placetype":"venue"
},
  "geometry": {"coordinates":[-90.675122,42.458762],"type":"Point"}
}