{
  "type": "Feature",
  "properties": {
    "addr:full":"2267 Valley View Trl Adel IA 50003",
    "addr:housenumber":"2267",
    "addr:postcode":"50003",
    "addr:street":"Valley View Trl",
    "iso:country":"US",
    "sg:address":"2267 Valley View Trl",
    "sg:city":"Adel",
    "sg:classifiers":[
        {
            "category":"Sports & Exercise",
            "subcategory":"Golf",
            "type":"Entertainment"
        }
    ],
    "sg:phone":"+1 515 993 4029",
    "sg:postcode":"50003",
    "sg:province":"IA",
    "sg:tags":[
        "course"
    ],
    "sg:website":"www.rivervalleygolf.com",
    "wof:name":"River Valley Golf Course",
    "wof:placetype":"venue"
},
  "geometry": {"coordinates":[-94.031644,41.650234],"type":"Point"}
}