{
  "type": "Feature",
  "properties": {
    "iso:country":"US",
    "sg:address":"207 3rd St SW",
    "sg:city":"State Center",
    "sg:classifiers":[
        {
            "category":"Education",
            "subcategory":"School",
            "type":"Public Place"
        }
    ],
    "sg:phone":"+1 641 483 2671",
    "sg:postcode":"50247",
    "sg:province":"IA",
    "wof:name":"West Marshall Elementary Schl",
    "wof:placetype":"venue"
},
  "geometry": {"coordinates":[-93.164773,42.014805],"type":"Point"}
}