{
  "type": "Feature",
  "properties": {
    "iso:country":"US",
    "sg:address":"1201 Wade St",
    "sg:city":"Iowa City",
    "sg:classifiers":[
        {
            "category":"Health Services",
            "subcategory":"Health Practitioner",
            "type":"Services"
        }
    ],
    "sg:phone":"+1 319 341 0031",
    "sg:postcode":"52240",
    "sg:province":"IA",
    "sg:tags":[
        "acupuncture"
    ],
    "sg:website":"www.acupunctureofiowa.com",
    "wof:name":"Wellsprings Acupuncture Ctr",
    "wof:placetype":"venue"
},
  "geometry": {"coordinates":[-91.500756,41.646296],"type":"Point"}
}