{
  "type": "Feature",
  "properties": {
    "addr:full":"6616 N Brady St Davenport IA 52806",
    "addr:housenumber":"6616",
    "addr:postcode":"52806",
    "addr:street":"N Brady St",
    "iso:country":"US",
    "sg:address":"6616 N Brady St",
    "sg:city":"Davenport",
    "sg:classifiers":[
        {
            "category":"Building & Trades",
            "subcategory":"Pest Control",
            "type":"Services"
        }
    ],
    "sg:phone":"+1 563 322 1115",
    "sg:postcode":"52806",
    "sg:province":"IA",
    "wof:name":"Springer Pest Solutions",
    "wof:placetype":"venue"
},
  "geometry": {"coordinates":[-90.57133899999999,41.585561],"type":"Point"}
}