{
  "type": "Feature",
  "properties": {
    "iso:country":"US",
    "sg:address":"19250 250th St",
    "sg:city":"Morning Sun",
    "sg:phone":"+1 319 868 7996",
    "sg:postcode":"52640",
    "sg:province":"IA",
    "sg:tags":[
        "farm",
        "corn",
        "soybean"
    ],
    "wof:name":"Doug Fischer",
    "wof:placetype":"venue"
},
  "geometry": {"coordinates":[-91.299329,41.04565],"type":"Point"}
}