{
  "type": "Feature",
  "properties": {
    "iso:country":"US",
    "sg:address":"2846 Mount Vernon Rd SE",
    "sg:city":"Cedar Rapids",
    "sg:classifiers":[
        {
            "category":"Shopping",
            "subcategory":"Tobacco",
            "type":"Retail Goods"
        }
    ],
    "sg:phone":"+1 319 364 8016",
    "sg:postcode":"52403",
    "sg:province":"IA",
    "sg:tags":[
        "shop"
    ],
    "wof:name":"Tobacco Outlet Plus # 560",
    "wof:placetype":"venue"
},
  "geometry": {"coordinates":[-91.621498,41.976799],"type":"Point"}
}