{
  "type": "Feature",
  "properties": {
    "iso:country":"US",
    "sg:address":"99 University Ave",
    "sg:city":"Des Moines",
    "sg:classifiers":[
        {
            "category":"Restaurant",
            "type":"Food & Drink"
        }
    ],
    "sg:phone":"+1 515 245 9108",
    "sg:postcode":"50314",
    "sg:province":"IA",
    "wof:name":"Top's Steak House",
    "wof:placetype":"venue"
},
  "geometry": {"coordinates":[-93.617885,41.600464],"type":"Point"}
}