{
  "type": "Feature",
  "properties": {
    "addr:full":"1309 E Ave NE Cedar Rapids IA 52402",
    "addr:housenumber":"1309",
    "addr:postcode":"52402",
    "addr:street":"E Ave Ne",
    "iso:country":"US",
    "sg:address":"1309 E Ave NE",
    "sg:city":"Cedar Rapids",
    "sg:classifiers":[
        {
            "category":"Wholesale",
            "subcategory":"Durable Goods & Equipment",
            "type":"Manufacturing & Wholesale Goods"
        }
    ],
    "sg:phone":"+1 319 363 2789",
    "sg:postcode":"52402",
    "sg:province":"IA",
    "sg:tags":[
        "representative",
        "manufacturer"
    ],
    "wof:name":"Clancey Co",
    "wof:placetype":"venue"
},
  "geometry": {"coordinates":[-91.658247,41.991342],"type":"Point"}
}