{
  "type": "Feature",
  "properties": {
    "iso:country":"US",
    "sg:address":"7089 15th Ave",
    "sg:city":"Keystone",
    "sg:classifiers":[
        {
            "category":"Wholesale",
            "subcategory":"Machinery & Supplies",
            "type":"Manufacturing & Wholesale Goods"
        }
    ],
    "sg:phone":"+1 319 442 3249",
    "sg:postcode":"52249",
    "sg:province":"IA",
    "sg:tags":[
        "farm",
        "equipment"
    ],
    "sg:website":"www.sindt.com",
    "wof:name":"Sindt Implement Co",
    "wof:placetype":"venue"
},
  "geometry": {"coordinates":[-92.202146,41.993771],"type":"Point"}
}