{
  "type": "Feature",
  "properties": {
    "addr:full":"510 S Pennsylvania Ave Mason City IA 50401",
    "addr:housenumber":"510",
    "addr:postcode":"50401",
    "addr:street":"S Pennsylvania Ave",
    "iso:country":"US",
    "sg:address":"510 S Pennsylvania Ave",
    "sg:city":"Mason City",
    "sg:classifiers":[
        {
            "category":"Shopping",
            "subcategory":"Optical Goods",
            "type":"Retail Goods"
        }
    ],
    "sg:phone":"+1 641 424 0385",
    "sg:postcode":"50401",
    "sg:province":"IA",
    "sg:tags":[
        "optician"
    ],
    "wof:name":"In Home Optics",
    "wof:placetype":"venue"
},
  "geometry": {"coordinates":[-93.198499,43.147059],"type":"Point"}
}