{
  "type": "Feature",
  "properties": {
    "iso:country":"US",
    "sg:address":"1570 42nd St NE",
    "sg:city":"Cedar Rapids",
    "sg:classifiers":[
        {
            "category":"Health Services",
            "subcategory":"Dentist",
            "type":"Services"
        }
    ],
    "sg:phone":"+1 319 393 6363",
    "sg:postcode":"52402",
    "sg:province":"IA",
    "wof:name":"Van Cleve Dental PC",
    "wof:placetype":"venue"
},
  "geometry": {"coordinates":[-91.660698,42.021301],"type":"Point"}
}