{
  "type": "Feature",
  "properties": {
    "addr:full":"314 S Main St Charles City IA 50616",
    "addr:housenumber":"314",
    "addr:postcode":"50616",
    "addr:street":"S Main",
    "iso:country":"US",
    "sg:address":"314 S Main St",
    "sg:city":"Charles City",
    "sg:classifiers":[
        {
            "category":"Personal",
            "subcategory":"Barber",
            "type":"Services"
        }
    ],
    "sg:phone":"+1 641 228 1643",
    "sg:postcode":"50616",
    "sg:province":"IA",
    "wof:name":"Barbers Four",
    "wof:placetype":"venue"
},
  "geometry": {"coordinates":[-92.681842,43.063827],"type":"Point"}
}