{
  "type": "Feature",
  "properties": {
    "iso:country":"US",
    "sg:address":"2718 Falls Ave",
    "sg:city":"Waterloo",
    "sg:classifiers":[
        {
            "category":"Professional",
            "subcategory":"Advertising",
            "type":"Services"
        }
    ],
    "sg:phone":"+1 319 234 7753",
    "sg:postcode":"50701",
    "sg:province":"IA",
    "wof:name":"Lamar Advertising Co",
    "wof:placetype":"venue"
},
  "geometry": {"coordinates":[-92.38107599999999,42.500013],"type":"Point"}
}