{
  "type": "Feature",
  "properties": {
    "addr:full":"413 Jefferson St Plainfield IA 50666",
    "addr:housenumber":"413",
    "addr:postcode":"50666",
    "addr:street":"Jefferson St",
    "iso:country":"US",
    "sg:address":"413 Jefferson St",
    "sg:city":"Plainfield",
    "sg:classifiers":[
        {
            "category":"Building & Trades",
            "subcategory":"Construction",
            "type":"Services"
        }
    ],
    "sg:phone":"+1 319 276 4409",
    "sg:postcode":"50666",
    "sg:province":"IA",
    "sg:tags":[
        "siding",
        "contractor"
    ],
    "wof:name":"Mills Home Improvement",
    "wof:placetype":"venue"
},
  "geometry": {"coordinates":[-92.533796,42.842448],"type":"Point"}
}