{
  "type": "Feature",
  "properties": {
    "addr:full":"1002 S 11th St Oskaloosa IA 52577",
    "addr:housenumber":"1002",
    "addr:postcode":"52577",
    "addr:street":"S 11Th St",
    "iso:country":"US",
    "sg:address":"1002 S 11th St",
    "sg:city":"Oskaloosa",
    "sg:classifiers":[
        {
            "category":"Insurance",
            "subcategory":"Insurance Agent",
            "type":"Services"
        }
    ],
    "sg:phone":"+1 641 672 2160",
    "sg:postcode":"52577",
    "sg:province":"IA",
    "wof:name":"State Farm Insurance",
    "wof:placetype":"venue"
},
  "geometry": {"coordinates":[-92.63188,41.286996],"type":"Point"}
}