{
  "type": "Feature",
  "properties": {
    "addr:full":"600 S 7th St Eldridge IA 52748",
    "addr:housenumber":"600",
    "addr:postcode":"52748",
    "addr:street":"S 7Th St",
    "iso:country":"US",
    "sg:address":"600 S 7th St",
    "sg:city":"Eldridge",
    "sg:classifiers":[
        {
            "category":"Building & Trades",
            "subcategory":"Pest Control",
            "type":"Services"
        }
    ],
    "sg:phone":"+1 563 285 5911",
    "sg:postcode":"52748",
    "sg:province":"IA",
    "sg:tags":[
        "mothproofing"
    ],
    "wof:name":"Premier Pest Mgmt Svcs",
    "wof:placetype":"venue"
},
  "geometry": {"coordinates":[-90.591148,41.650021],"type":"Point"}
}