{
  "type": "Feature",
  "properties": {
    "iso:country":"US",
    "sg:address":"422 E 3rd St",
    "sg:city":"Washington",
    "sg:classifiers":[
        {
            "category":"Utilities",
            "subcategory":"Refuse",
            "type":"Services"
        }
    ],
    "sg:phone":"+1 319 653 2463",
    "sg:postcode":"52353",
    "sg:province":"IA",
    "sg:tags":[
        "garbage",
        "collection"
    ],
    "wof:name":"Mark's Sanitation Svc",
    "wof:placetype":"venue"
},
  "geometry": {"coordinates":[-91.687557,41.301382],"type":"Point"}
}