{
  "type": "Feature",
  "properties": {
    "iso:country":"US",
    "sg:address":"518 US Hwy 65",
    "sg:city":"Colo",
    "sg:classifiers":[
        {
            "category":"Wholesale",
            "subcategory":"Farm Supplies",
            "type":"Manufacturing & Wholesale Goods"
        }
    ],
    "sg:phone":"+1 641 377 2221",
    "sg:postcode":"50056",
    "sg:province":"IA",
    "sg:tags":[
        "grain"
    ],
    "wof:name":"Frohwein & Sons Inc",
    "wof:placetype":"venue"
},
  "geometry": {"coordinates":[-93.30950900000001,42.017287],"type":"Point"}
}