{
  "type": "Feature",
  "properties": {
    "iso:country":"US",
    "sg:address":"231 9th St",
    "sg:city":"Sibley",
    "sg:classifiers":[
        {
            "category":"Professional",
            "subcategory":"Lawyer & Legal Services",
            "type":"Services"
        }
    ],
    "sg:phone":"+1 712 754 3626",
    "sg:postcode":"51249",
    "sg:province":"IA",
    "sg:tags":[
        "attorney",
        "practice"
    ],
    "sg:website":"http://www.ehphiliphlawfirm.com/",
    "wof:name":"Philip, E H Law Office",
    "wof:placetype":"venue"
},
  "geometry": {"coordinates":[-95.751407,43.399357],"type":"Point"}
}