{
  "type": "Feature",
  "properties": {
    "iso:country":"US",
    "sg:address":"2436 Sampson St",
    "sg:city":"Muscatine",
    "sg:classifiers":[
        {
            "category":"Real Estate",
            "subcategory":"Developer",
            "type":"Services"
        },
        {
            "category":"Real Estate",
            "subcategory":"Real Estate Operator",
            "type":"Services"
        }
    ],
    "sg:phone":"+1 563 263 0509",
    "sg:postcode":"52761",
    "sg:province":"IA",
    "sg:tags":[
        "mobile",
        "home",
        "site"
    ],
    "wof:name":"Van Acker's Mobile Home Park",
    "wof:placetype":"venue"
},
  "geometry": {"coordinates":[-91.07144599999999,41.399431],"type":"Point"}
}