{
  "type": "Feature",
  "properties": {
    "iso:country":"US",
    "sg:address":"822 Central Ave",
    "sg:city":"Hawarden",
    "sg:classifiers":[
        {
            "category":"Insurance",
            "subcategory":"Insurance Agent",
            "type":"Services"
        }
    ],
    "sg:phone":"+1 712 551 2365",
    "sg:postcode":"51023",
    "sg:province":"IA",
    "wof:name":"Agency One Svc",
    "wof:placetype":"venue"
},
  "geometry": {"coordinates":[-96.48515,42.995324],"type":"Point"}
}