{
  "type": "Feature",
  "properties": {
    "addr:full":"4264 Birch Ave Hawarden SD 51023",
    "addr:housenumber":"4264",
    "addr:postcode":"51023",
    "addr:street":"Birch Ave",
    "iso:country":"US",
    "sg:address":"4264 Birch Ave",
    "sg:city":"Hawarden",
    "sg:classifiers":[
        {
            "category":"Professional",
            "subcategory":"Engineering",
            "type":"Services"
        }
    ],
    "sg:phone":"+1 712 552 2330",
    "sg:postcode":"51023",
    "sg:province":"SD",
    "sg:tags":[
        "general",
        "contractor"
    ],
    "wof:name":"Zoeller Engineering",
    "wof:placetype":"venue"
},
  "geometry": {"coordinates":[-96.489418,43.030572],"type":"Point"}
}