{
  "type": "Feature",
  "properties": {
    "iso:country":"US",
    "sg:address":"575 W 3rd St",
    "sg:city":"Garner",
    "sg:classifiers":[
        {
            "category":"Professional",
            "type":"Services"
        }
    ],
    "sg:phone":"+1 641 923 2546",
    "sg:postcode":"50438",
    "sg:province":"IA",
    "sg:tags":[
        "establishment"
    ],
    "wof:name":"GVAS Ctr",
    "wof:placetype":"venue"
},
  "geometry": {"coordinates":[-93.608253,43.102286],"type":"Point"}
}