{
  "type": "Feature",
  "properties": {
    "iso:country":"US",
    "sg:address":"2427 Elm Dr",
    "sg:city":"Fort Dodge",
    "sg:classifiers":[
        {
            "category":"Manufacturing",
            "subcategory":"Tools & Machinery",
            "type":"Manufacturing & Wholesale Goods"
        }
    ],
    "sg:phone":"+1 515 972 4500",
    "sg:postcode":"50501",
    "sg:province":"IA",
    "sg:tags":[
        "farm",
        "equipment"
    ],
    "wof:name":"Elkhorn Equipment Co",
    "wof:placetype":"venue"
},
  "geometry": {"coordinates":[-94.131328,42.44019],"type":"Point"}
}