{
  "type": "Feature",
  "properties": {
    "addr:full":"4012 E 14th St Des Moines IA 50313",
    "addr:housenumber":"4012",
    "addr:postcode":"50313",
    "addr:street":"E 14Th St",
    "iso:country":"US",
    "sg:address":"4012 E 14th St",
    "sg:city":"Des Moines",
    "sg:classifiers":[
        {
            "category":"Retail",
            "subcategory":"Auto Repair",
            "type":"Services"
        }
    ],
    "sg:phone":"+1 515 244 2802",
    "sg:postcode":"50313",
    "sg:province":"IA",
    "sg:tags":[
        "automobile",
        "top",
        "upholstery"
    ],
    "wof:name":"Iowa Auto Top & Upholstery",
    "wof:placetype":"venue"
},
  "geometry": {"coordinates":[-93.600616,41.634742],"type":"Point"}
}