{
  "type": "Feature",
  "properties": {
    "iso:country":"US",
    "sg:address":"7884 200th Ave",
    "sg:city":"Danville",
    "sg:classifiers":[
        {
            "category":"Building & Trades",
            "subcategory":"Construction",
            "type":"Services"
        }
    ],
    "sg:phone":"+1 319 392 8333",
    "sg:postcode":"52623",
    "sg:province":"IA",
    "sg:tags":[
        "general",
        "contractor"
    ],
    "wof:name":"A R Enterprises",
    "wof:placetype":"venue"
},
  "geometry": {"coordinates":[-91.314582,40.795507],"type":"Point"}
}