{
  "type": "Feature",
  "properties": {
    "iso:country":"US",
    "sg:address":"2009 Ridgeway Dr",
    "sg:city":"Iowa City",
    "sg:classifiers":[
        {
            "category":"Professional",
            "subcategory":"Management & Consulting",
            "type":"Services"
        }
    ],
    "sg:phone":"+1 319 338 5477",
    "sg:postcode":"52245",
    "sg:province":"IA",
    "sg:tags":[
        "business"
    ],
    "wof:name":"Gregory Consulting",
    "wof:placetype":"venue"
},
  "geometry": {"coordinates":[-91.50456,41.661934],"type":"Point"}
}