{
  "type": "Feature",
  "properties": {
    "iso:country":"US",
    "sg:address":"2505 Carriage Trl",
    "sg:city":"Winterset",
    "sg:classifiers":[
        {
            "category":"Farming",
            "subcategory":"Livestock Farm",
            "type":"Manufacturing & Wholesale Goods"
        }
    ],
    "sg:phone":"+1 515 462 4768",
    "sg:postcode":"50273",
    "sg:province":"IA",
    "sg:tags":[
        "specialty",
        "animal"
    ],
    "wof:name":"Honey Randol Farm",
    "wof:placetype":"venue"
},
  "geometry": {"coordinates":[-94.184529,41.286865],"type":"Point"}
}