{
  "type": "Feature",
  "properties": {
    "addr:full":"1848 Evergreen Ave Red Oak IA 51566",
    "addr:housenumber":"1848",
    "addr:postcode":"51566",
    "addr:street":"Evergreen Ave",
    "iso:country":"US",
    "sg:address":"1848 Evergreen Ave",
    "sg:city":"Red Oak",
    "sg:classifiers":[
        {
            "category":"Manufacturing",
            "subcategory":"Watercraft",
            "type":"Manufacturing & Wholesale Goods"
        }
    ],
    "sg:phone":"+1 712 623 5068",
    "sg:postcode":"51566",
    "sg:province":"IA",
    "sg:tags":[
        "mfg"
    ],
    "wof:name":"Graham Fabrication",
    "wof:placetype":"venue"
},
  "geometry": {"coordinates":[-95.279866,41.038049],"type":"Point"}
}