{
  "type": "Feature",
  "properties": {
    "addr:full":"2223 Highway Blvd Spencer IA 51301",
    "addr:housenumber":"2223",
    "addr:postcode":"51301",
    "addr:street":"Highway Blvd",
    "iso:country":"US",
    "sg:address":"2223 Highway Blvd",
    "sg:city":"Spencer",
    "sg:classifiers":[
        {
            "category":"Home & Garden",
            "subcategory":"Building Materials",
            "type":"Retail Goods"
        }
    ],
    "sg:phone":"+1 712 262 6530",
    "sg:postcode":"51301",
    "sg:province":"IA",
    "sg:tags":[
        "lumber"
    ],
    "wof:name":"Schoeneman Brothers Co",
    "wof:placetype":"venue"
},
  "geometry": {"coordinates":[-95.147915,43.159616],"type":"Point"}
}