{
  "type": "Feature",
  "properties": {
    "addr:full":"1475 US Hwy 6 West Liberty IA 52776",
    "addr:housenumber":"1475",
    "addr:postcode":"52776",
    "addr:street":"Us Hwy 6 West",
    "iso:country":"US",
    "sg:address":"1475 US Hwy 6",
    "sg:city":"West Liberty",
    "sg:classifiers":[
        {
            "category":"Freight",
            "type":"Transportation"
        }
    ],
    "sg:phone":"+1 319 627 2678",
    "sg:postcode":"52776",
    "sg:province":"IA",
    "sg:tags":[
        "trucking"
    ],
    "sg:website":"www.florilli.com",
    "wof:name":"Florilli Corp",
    "wof:placetype":"venue"
},
  "geometry": {"coordinates":[-91.269819,41.582708],"type":"Point"}
}