{
  "type": "Feature",
  "properties": {
    "iso:country":"US",
    "sg:address":"207 S Liberty St",
    "sg:city":"Cincinnati",
    "sg:classifiers":[
        {
            "category":"Freight",
            "type":"Transportation"
        }
    ],
    "sg:phone":"+1 641 658 2695",
    "sg:postcode":"52549",
    "sg:province":"IA",
    "sg:tags":[
        "operator",
        "local",
        "trucking"
    ],
    "wof:name":"Houser Trucking",
    "wof:placetype":"venue"
},
  "geometry": {"coordinates":[-92.924532,40.628882],"type":"Point"}
}