{
  "type": "Feature",
  "properties": {
    "iso:country":"US",
    "sg:address":"511 S Capitol St",
    "sg:city":"Iowa City",
    "sg:classifiers":[
        {
            "category":"Government",
            "subcategory":"Office",
            "type":"Public Place"
        }
    ],
    "sg:phone":"+1 319 356 6028",
    "sg:postcode":"52244",
    "sg:province":"IA",
    "sg:tags":[
        "county",
        "safety",
        "order"
    ],
    "wof:name":"Johnson County Emergency Mgmt",
    "wof:placetype":"venue"
},
  "geometry": {"coordinates":[-91.53630800000001,41.654537],"type":"Point"}
}