{
  "type": "Feature",
  "properties": {
    "iso:country":"US",
    "sg:address":"607 W Sheridan Ave",
    "sg:city":"Shenandoah",
    "sg:classifiers":[
        {
            "category":"Shopping",
            "type":"Retail Goods"
        }
    ],
    "sg:phone":"+1 712 246 2033",
    "sg:postcode":"51601",
    "sg:province":"IA",
    "sg:tags":[
        "merchandise"
    ],
    "wof:name":"Dreamers Unlimited Inc",
    "wof:placetype":"venue"
},
  "geometry": {"coordinates":[-95.373768,40.766016],"type":"Point"}
}