{
  "type": "Feature",
  "properties": {
    "addr:full":"3528 Kimberly Downs Rd Davenport IA 52807",
    "addr:housenumber":"3528",
    "addr:postcode":"52807",
    "addr:street":"Kimberly Downs Rd",
    "iso:country":"US",
    "sg:address":"3528 Kimberly Downs Rd",
    "sg:city":"Davenport",
    "sg:classifiers":[
        {
            "category":"Place Of Worship",
            "type":"Public Place"
        },
        {
            "category":"Place Of Worship",
            "subcategory":"Temple",
            "type":"Public Place"
        }
    ],
    "sg:phone":"+1 563 391 0750",
    "sg:postcode":"52807",
    "sg:province":"IA",
    "sg:tags":[
        "church"
    ],
    "wof:name":"Jeremiah Temple",
    "wof:placetype":"venue"
},
  "geometry": {"coordinates":[-90.558319,41.555073],"type":"Point"}
}