{
  "type": "Feature",
  "properties": {
    "iso:country":"US",
    "sg:address":"3116 W 15th St",
    "sg:city":"Sioux City",
    "sg:classifiers":[
        {
            "category":"Shopping",
            "subcategory":"Clothing, Apparel, & Fashions",
            "type":"Retail Goods"
        }
    ],
    "sg:phone":"+1 712 258 5282",
    "sg:postcode":"51103",
    "sg:province":"IA",
    "wof:name":"Kenneth L McParland",
    "wof:placetype":"venue"
},
  "geometry": {"coordinates":[-96.449746,42.505168],"type":"Point"}
}