{
  "type": "Feature",
  "properties": {
    "addr:full":"616 Main St Lowden IA 52255",
    "addr:housenumber":"616",
    "addr:postcode":"52255",
    "addr:street":"Main St",
    "iso:country":"US",
    "sg:address":"616 Main St",
    "sg:city":"Lowden",
    "sg:classifiers":[
        {
            "category":"Building & Trades",
            "subcategory":"Plumbing",
            "type":"Services"
        }
    ],
    "sg:phone":"+1 563 941 5889",
    "sg:postcode":"52255",
    "sg:province":"IA",
    "sg:tags":[
        "conditioning",
        "air",
        "system",
        "contractor"
    ],
    "wof:name":"Lowden Plumbing & Heating",
    "wof:placetype":"venue"
},
  "geometry": {"coordinates":[-90.92854800000001,41.85771],"type":"Point"}
}