{
  "type": "Feature",
  "properties": {
    "iso:country":"US",
    "sg:address":"216 N 2nd St",
    "sg:city":"Clinton",
    "sg:classifiers":[
        {
            "category":"Building & Trades",
            "subcategory":"Electrical",
            "type":"Services"
        }
    ],
    "sg:phone":"+1 563 243 4254",
    "sg:postcode":"52732",
    "sg:province":"IA",
    "sg:tags":[
        "electric",
        "contractor"
    ],
    "wof:name":"Mike May Electric Inc",
    "wof:placetype":"venue"
},
  "geometry": {"coordinates":[-90.188363,41.847068],"type":"Point"}
}