{
  "type": "Feature",
  "properties": {
    "addr:full":"122 E Main St Anamosa IA 52205",
    "addr:housenumber":"122",
    "addr:postcode":"52205",
    "addr:street":"E Main St",
    "iso:country":"US",
    "sg:address":"122 E Main St",
    "sg:city":"Anamosa",
    "sg:classifiers":[
        {
            "category":"Restaurant",
            "type":"Food & Drink"
        }
    ],
    "sg:phone":"+1 319 462 5533",
    "sg:postcode":"52205",
    "sg:province":"IA",
    "wof:name":"Tyler & Downing's Eatery",
    "wof:placetype":"venue"
},
  "geometry": {"coordinates":[-91.285315,42.108346],"type":"Point"}
}