{
  "type": "Feature",
  "properties": {
    "addr:full":"15152 55th Ave Onslow IA 52321",
    "addr:housenumber":"15152",
    "addr:postcode":"52321",
    "addr:street":"55Th Ave",
    "iso:country":"US",
    "sg:address":"15152 55th Ave",
    "sg:city":"Onslow",
    "sg:phone":"+1 563 485 3831",
    "sg:postcode":"52321",
    "sg:province":"IA",
    "sg:tags":[
        "farm",
        "corn"
    ],
    "wof:name":"Dale Chatterton",
    "wof:placetype":"venue"
},
  "geometry": {"coordinates":[-90.987967,42.152686],"type":"Point"}
}