{
  "type": "Feature",
  "properties": {
    "iso:country":"US",
    "sg:address":"425 Flindt Dr",
    "sg:city":"Storm Lake",
    "sg:classifiers":[
        {
            "category":"Autos & Motor Vehicles",
            "subcategory":"Auto Supplies",
            "type":"Retail Goods"
        }
    ],
    "sg:phone":"+1 712 732 1038",
    "sg:postcode":"50588",
    "sg:province":"IA",
    "sg:tags":[
        "automobile",
        "parts"
    ],
    "wof:name":"Arnold Motor Supply",
    "wof:placetype":"venue"
},
  "geometry": {"coordinates":[-95.18613999999999,42.63907],"type":"Point"}
}