{
  "type": "Feature",
  "properties": {
    "iso:country":"US",
    "sg:address":"100 30th Street Dr SE",
    "sg:city":"Cedar Rapids",
    "sg:classifiers":[
        {
            "category":"Retail",
            "subcategory":"Portrait Studio",
            "type":"Services"
        }
    ],
    "sg:phone":"+1 319 366 8250",
    "sg:postcode":"52403",
    "sg:province":"IA",
    "sg:tags":[
        "photo",
        "video"
    ],
    "wof:name":"Miracles Phtgrphy Video Studio",
    "wof:placetype":"venue"
},
  "geometry": {"coordinates":[-91.632701,42.007264],"type":"Point"}
}