{
  "type": "Feature",
  "properties": {
    "addr:full":"1500 22nd St West Des Moines IA 50266",
    "addr:housenumber":"1500",
    "addr:postcode":"50266",
    "addr:street":"22Nd St",
    "iso:country":"US",
    "sg:address":"1500 22nd St",
    "sg:city":"West Des Moines",
    "sg:classifiers":[
        {
            "category":"Shopping",
            "type":"Retail Goods"
        }
    ],
    "sg:phone":"+1 515 223 0254",
    "sg:postcode":"50266",
    "sg:province":"IA",
    "sg:tags":[
        "pet",
        "shop"
    ],
    "wof:name":"Iowa Pet Foods & Aquatics",
    "wof:placetype":"venue"
},
  "geometry": {"coordinates":[-93.736221,41.593632],"type":"Point"}
}