{
  "type": "Feature",
  "properties": {
    "addr:full":"200 W Water St Decorah IA 52101",
    "addr:housenumber":"200",
    "addr:postcode":"52101",
    "addr:street":"W Water St",
    "iso:country":"US",
    "sg:address":"200 W Water St",
    "sg:city":"Decorah",
    "sg:classifiers":[
        {
            "category":"Shopping",
            "subcategory":"Jewelry",
            "type":"Retail Goods"
        }
    ],
    "sg:phone":"+1 563 382 3903",
    "sg:postcode":"52101",
    "sg:province":"IA",
    "sg:tags":[
        "jeweler"
    ],
    "wof:name":"M G Jewelry",
    "wof:placetype":"venue"
},
  "geometry": {"coordinates":[-91.788393,43.304159],"type":"Point"}
}