{
  "type": "Feature",
  "properties": {
    "addr:full":"23283 300th St Ollie IA 52576",
    "addr:housenumber":"23283",
    "addr:postcode":"52576",
    "addr:street":"300Th St",
    "iso:country":"US",
    "sg:address":"23283 300th St",
    "sg:city":"Ollie",
    "sg:phone":"+1 641 667 2871",
    "sg:postcode":"52576",
    "sg:province":"IA",
    "sg:tags":[
        "farm",
        "corn",
        "beef",
        "feedlot",
        "cattle"
    ],
    "wof:name":"Gary Schultz",
    "wof:placetype":"venue"
},
  "geometry": {"coordinates":[-92.15447,41.220728],"type":"Point"}
}