{
  "type": "Feature",
  "properties": {
    "addr:full":"5035 NE 14th St Des Moines IA 50313",
    "addr:housenumber":"5035",
    "addr:postcode":"50313",
    "addr:street":"Ne 14Th St",
    "iso:country":"US",
    "sg:address":"5035 NE 14th St",
    "sg:city":"Des Moines",
    "sg:classifiers":[
        {
            "category":"Shopping",
            "subcategory":"Shoes",
            "type":"Retail Goods"
        }
    ],
    "sg:phone":"+1 515 262 7972",
    "sg:postcode":"50313",
    "sg:province":"IA",
    "wof:name":"Red Wing Shoe Store",
    "wof:placetype":"venue"
},
  "geometry": {"coordinates":[-93.600274,41.653085],"type":"Point"}
}