{
  "type": "Feature",
  "properties": {
    "addr:full":"3980 Poweshiek St SE Iowa City IA 52240",
    "addr:housenumber":"3980",
    "addr:postcode":"52240",
    "addr:street":"Poweshiek St Se",
    "iso:country":"US",
    "sg:address":"3980 Poweshiek St SE",
    "sg:city":"Iowa City",
    "sg:classifiers":[
        {
            "category":"Organizations",
            "subcategory":"Religious Organization",
            "type":"Services"
        }
    ],
    "sg:phone":"+1 319 337 9907",
    "sg:postcode":"52240",
    "sg:province":"IA",
    "sg:tags":[
        "church"
    ],
    "sg:website":"www.gfcic.org",
    "wof:name":"Grace Fellowship",
    "wof:placetype":"venue"
},
  "geometry": {"coordinates":[-91.54328099999999,41.597332],"type":"Point"}
}