{
  "type": "Feature",
  "properties": {
    "iso:country":"US",
    "sg:address":"3270 Central Ave",
    "sg:city":"Dubuque",
    "sg:classifiers":[
        {
            "category":"Home & Garden",
            "subcategory":"Furniture",
            "type":"Retail Goods"
        }
    ],
    "sg:phone":"+1 563 556 0608",
    "sg:postcode":"52001",
    "sg:province":"IA",
    "wof:name":"Amish Furniture-N-More",
    "wof:placetype":"venue"
},
  "geometry": {"coordinates":[-90.68303400000001,42.527772],"type":"Point"}
}