{
  "type": "Feature",
  "properties": {
    "iso:country":"US",
    "sg:address":"123 Main Ave",
    "sg:city":"Clinton",
    "sg:classifiers":[
        {
            "category":"Restaurant",
            "type":"Food & Drink"
        }
    ],
    "sg:phone":"+1 563 242 2007",
    "sg:postcode":"52732",
    "sg:province":"IA",
    "sg:tags":[
        "shop",
        "coffee"
    ],
    "wof:name":"Crossroads Christian Coffee Hs",
    "wof:placetype":"venue"
},
  "geometry": {"coordinates":[-90.17956599999999,41.872568],"type":"Point"}
}