{
  "type": "Feature",
  "properties": {
    "iso:country":"US",
    "sg:address":"3004 N 13th St",
    "sg:city":"Carter Lake",
    "sg:classifiers":[
        {
            "category":"Health Services",
            "subcategory":"Doctor",
            "type":"Services"
        }
    ],
    "sg:phone":"+1 712 347 6151",
    "sg:postcode":"51510",
    "sg:province":"IA",
    "sg:tags":[
        "surgeon",
        "oral"
    ],
    "sg:website":"www.tricitydental.net",
    "wof:name":"Hurley Robert DDS",
    "wof:placetype":"venue"
},
  "geometry": {"coordinates":[-95.913101,41.286098],"type":"Point"}
}