{
  "type": "Feature",
  "properties": {
    "addr:full":"608 8th St Alton IA 51003",
    "addr:housenumber":"608",
    "addr:postcode":"51003",
    "addr:street":"8Th St",
    "iso:country":"US",
    "sg:address":"608 8th St",
    "sg:city":"Alton",
    "sg:classifiers":[
        {
            "category":"Freight",
            "type":"Transportation"
        }
    ],
    "sg:phone":"+1 712 756 4271",
    "sg:postcode":"51003",
    "sg:province":"IA",
    "sg:tags":[
        "livestock",
        "hauling"
    ],
    "wof:name":"Paul Tebrink Trucking",
    "wof:placetype":"venue"
},
  "geometry": {"coordinates":[-96.01670900000001,42.986539],"type":"Point"}
}