{
  "type": "Feature",
  "properties": {
    "iso:country":"US",
    "sg:address":"108 Normal St",
    "sg:city":"Woodbine",
    "sg:classifiers":[
        {
            "category":"Government",
            "subcategory":"Fire Station",
            "type":"Public Place"
        }
    ],
    "sg:phone":"+1 712 000 1111",
    "sg:postcode":"51579",
    "sg:province":"IA",
    "sg:tags":[
        "department"
    ],
    "wof:name":"Woodbine Fire Dept",
    "wof:placetype":"venue"
},
  "geometry": {"coordinates":[-95.708135,41.732876],"type":"Point"}
}