{
  "type": "Feature",
  "properties": {
    "iso:country":"US",
    "sg:address":"15 Nightingale Ln",
    "sg:city":"Dubuque",
    "sg:classifiers":[
        {
            "category":"Autos & Motor Vehicles",
            "subcategory":"Motorcycle Sales",
            "type":"Retail Goods"
        }
    ],
    "sg:phone":"+1 563 557 8818",
    "sg:postcode":"52003",
    "sg:province":"IA",
    "sg:tags":[
        "car",
        "golf",
        "cart"
    ],
    "wof:name":"Wilwert's Golf Cars Inc",
    "wof:placetype":"venue"
},
  "geometry": {"coordinates":[-90.718487,42.483529],"type":"Point"}
}