{
  "type": "Feature",
  "properties": {
    "iso:country":"US",
    "sg:address":"880 White St",
    "sg:city":"Dubuque",
    "sg:classifiers":[
        {
            "category":"Wholesale",
            "subcategory":"Construction Materials",
            "type":"Manufacturing & Wholesale Goods"
        }
    ],
    "sg:phone":"+1 563 583 1493",
    "sg:postcode":"52001",
    "sg:province":"IA",
    "sg:tags":[
        "equipment",
        "siding"
    ],
    "wof:name":"Central Siding Supply Inc",
    "wof:placetype":"venue"
},
  "geometry": {"coordinates":[-90.664137,42.501913],"type":"Point"}
}