{
  "type": "Feature",
  "properties": {
    "addr:full":"2905 US Hwy 61 Muscatine IA 52761",
    "addr:housenumber":"2905",
    "addr:postcode":"52761",
    "addr:street":"Us Hwy 61",
    "iso:country":"US",
    "sg:address":"2905 US Hwy 61",
    "sg:city":"Muscatine",
    "sg:classifiers":[
        {
            "category":"Retail",
            "subcategory":"Auto Repair",
            "type":"Services"
        }
    ],
    "sg:phone":"+1 563 262 1400",
    "sg:postcode":"52761",
    "sg:province":"IA",
    "sg:tags":[
        "repairing",
        "tire"
    ],
    "sg:website":"www.bandag.com",
    "wof:name":"Bandag Inc",
    "wof:placetype":"venue"
},
  "geometry": {"coordinates":[-91.026736,41.455009],"type":"Point"}
}