{
  "type": "Feature",
  "properties": {
    "addr:full":"544 193rd St Ames IA 50010",
    "addr:housenumber":"544",
    "addr:postcode":"50010",
    "addr:street":"193Rd St",
    "iso:country":"US",
    "sg:address":"544 193rd St",
    "sg:city":"Ames",
    "sg:phone":"+1 515 233 2448",
    "sg:postcode":"50010",
    "sg:province":"IA",
    "sg:tags":[
        "farm",
        "corn",
        "soybean"
    ],
    "wof:name":"Lee Amundson",
    "wof:placetype":"venue"
},
  "geometry": {"coordinates":[-93.61825899999999,42.075351],"type":"Point"}
}