{
  "type": "Feature",
  "properties": {
    "iso:country":"US",
    "sg:address":"3415 290th St",
    "sg:city":"Braddyville",
    "sg:classifiers":[
        {
            "category":"Building & Trades",
            "subcategory":"Construction",
            "type":"Services"
        }
    ],
    "sg:phone":"+1 712 589 3306",
    "sg:postcode":"51631",
    "sg:province":"IA",
    "sg:tags":[
        "house"
    ],
    "wof:name":"Mike Ridnour",
    "wof:placetype":"venue"
},
  "geometry": {"coordinates":[-94.93057899999999,40.621102],"type":"Point"}
}