{
  "type": "Feature",
  "properties": {
    "addr:full":"16132 Irish Ridge Rd Burlington IA 52601",
    "addr:housenumber":"16132",
    "addr:postcode":"52601",
    "addr:street":"Irish Ridge Rd",
    "iso:country":"US",
    "sg:address":"16132 Irish Ridge Rd",
    "sg:city":"Burlington",
    "sg:classifiers":[
        {
            "category":"Transit Center",
            "subcategory":"Freight",
            "type":"Transportation"
        },
        {
            "category":"Freight",
            "type":"Transportation"
        }
    ],
    "sg:phone":"+1 319 985 2560",
    "sg:postcode":"52601",
    "sg:province":"IA",
    "sg:tags":[
        "trucking-motor",
        "trucking"
    ],
    "wof:name":"Oetken Brothers Trucking, Inc",
    "wof:placetype":"venue"
},
  "geometry": {"coordinates":[-91.12221099999999,40.911594],"type":"Point"}
}