{
  "type": "Feature",
  "properties": {
    "addr:full":"105 S Jefferson St Sigourney IA 52591",
    "addr:housenumber":"105",
    "addr:postcode":"52591",
    "addr:street":"S Jefferson St",
    "iso:country":"US",
    "sg:address":"105 S Jefferson St",
    "sg:city":"Sigourney",
    "sg:classifiers":[
        {
            "category":"Shopping",
            "subcategory":"Pharmacy",
            "type":"Retail Goods"
        }
    ],
    "sg:phone":"+1 641 622 3020",
    "sg:postcode":"52591",
    "sg:province":"IA",
    "wof:name":"Cooke Drugs",
    "wof:placetype":"venue"
},
  "geometry": {"coordinates":[-92.203812,41.333624],"type":"Point"}
}