{
  "type": "Feature",
  "properties": {
    "addr:full":"5525 Meredith Dr Des Moines IA 50310",
    "addr:housenumber":"5525",
    "addr:postcode":"50310",
    "addr:street":"Meredith Dr",
    "iso:country":"US",
    "sg:address":"5525 Meredith Dr",
    "sg:city":"Des Moines",
    "sg:classifiers":[
        {
            "category":"Professional",
            "subcategory":"Engineering",
            "type":"Services"
        }
    ],
    "sg:phone":"+1 515 331 1325",
    "sg:postcode":"50310",
    "sg:province":"IA",
    "sg:tags":[
        "engineer"
    ],
    "wof:name":"Brown Engineering Co",
    "wof:placetype":"venue"
},
  "geometry": {"coordinates":[-93.69658800000001,41.644006],"type":"Point"}
}