{
  "type": "Feature",
  "properties": {
    "iso:country":"US",
    "sg:address":"507 Rutland St",
    "sg:city":"Kingsley",
    "sg:classifiers":[
        {
            "category":"Building & Trades",
            "subcategory":"Construction",
            "type":"Services"
        }
    ],
    "sg:phone":"+1 712 378 2766",
    "sg:postcode":"51028",
    "sg:province":"IA",
    "sg:tags":[
        "contractor"
    ],
    "wof:name":"Mark Kuchel Construction",
    "wof:placetype":"venue"
},
  "geometry": {"coordinates":[-95.96409800000001,42.594902],"type":"Point"}
}