{
  "type": "Feature",
  "properties": {
    "addr:full":"2807 NE 46th Ave Des Moines IA 50317",
    "addr:housenumber":"2807",
    "addr:postcode":"50317",
    "addr:street":"Ne 46Th Ave",
    "iso:country":"US",
    "sg:address":"2807 NE 46th Ave",
    "sg:city":"Des Moines",
    "sg:classifiers":[
        {
            "category":"Local Transit",
            "type":"Transportation"
        }
    ],
    "sg:phone":"+1 515 266 4469",
    "sg:postcode":"50317",
    "sg:province":"IA",
    "sg:tags":[
        "airport"
    ],
    "wof:name":"Out Of Town Svc",
    "wof:placetype":"venue"
},
  "geometry": {"coordinates":[-93.561255,41.643911],"type":"Point"}
}