{
  "type": "Feature",
  "properties": {
    "iso:country":"US",
    "sg:address":"346 W Main St",
    "sg:city":"West Branch",
    "sg:classifiers":[
        {
            "category":"Autos & Motor Vehicles",
            "subcategory":"Automobile Sales",
            "type":"Retail Goods"
        }
    ],
    "sg:phone":"+1 319 643 3673",
    "sg:postcode":"52358",
    "sg:province":"IA",
    "sg:tags":[
        "car",
        "dealer"
    ],
    "sg:website":"www.westbranchford.com",
    "wof:name":"West Branch Ford",
    "wof:placetype":"venue"
},
  "geometry": {"coordinates":[-91.350206,41.671335],"type":"Point"}
}