{
  "type": "Feature",
  "properties": {
    "addr:full":"216 12th St Boone IA 50036",
    "addr:housenumber":"216",
    "addr:postcode":"50036",
    "addr:street":"12Th St",
    "iso:country":"US",
    "sg:address":"216 12th St",
    "sg:city":"Boone",
    "sg:classifiers":[
        {
            "category":"Organizations",
            "subcategory":"Professional Association",
            "type":"Services"
        }
    ],
    "sg:phone":"+1 515 432 3001",
    "sg:postcode":"50036",
    "sg:province":"IA",
    "wof:name":"Winged Warriors Natl B-Body",
    "wof:placetype":"venue"
},
  "geometry": {"coordinates":[-93.89159600000001,42.067841],"type":"Point"}
}