{
  "type": "Feature",
  "properties": {
    "iso:country":"US",
    "sg:address":"1500 State St",
    "sg:city":"Bellevue",
    "sg:classifiers":[
        {
            "category":"Manufacturing",
            "subcategory":"Retail Goods",
            "type":"Manufacturing & Wholesale Goods"
        }
    ],
    "sg:phone":"+1 563 872 4096",
    "sg:postcode":"52031",
    "sg:province":"IA",
    "sg:tags":[
        "assembly",
        "fabricating"
    ],
    "wof:name":"Rockwell Collins Inc",
    "wof:placetype":"venue"
},
  "geometry": {"coordinates":[-90.440048,42.254271],"type":"Point"}
}