{
  "type": "Feature",
  "properties": {
    "iso:country":"US",
    "sg:address":"607 180th St",
    "sg:city":"Algona",
    "sg:classifiers":[
        {
            "category":"Farming",
            "subcategory":"Farm",
            "type":"Manufacturing & Wholesale Goods"
        }
    ],
    "sg:phone":"+1 515 295 5060",
    "sg:postcode":"50511",
    "sg:province":"IA",
    "sg:tags":[
        "crop",
        "general"
    ],
    "wof:name":"Gerber Robert",
    "wof:placetype":"venue"
},
  "geometry": {"coordinates":[-94.33524199999999,43.024118],"type":"Point"}
}