{
  "type": "Feature",
  "properties": {
    "iso:country":"US",
    "sg:address":"1518 120th St",
    "sg:city":"Wayland",
    "sg:classifiers":[
        {
            "category":"Real Estate",
            "subcategory":"Real Estate Operator",
            "type":"Services"
        }
    ],
    "sg:phone":"+1 319 256 5861",
    "sg:postcode":"52654",
    "sg:province":"IA",
    "sg:tags":[
        "property",
        "lessor"
    ],
    "wof:name":"Elmer Schrock",
    "wof:placetype":"venue"
},
  "geometry": {"coordinates":[-91.619901,41.134346],"type":"Point"}
}