{
  "type": "Feature",
  "properties": {
    "iso:country":"US",
    "sg:address":"1803 Lucas Rd",
    "sg:city":"Muscatine",
    "sg:classifiers":[
        {
            "category":"Organizations",
            "subcategory":"Professional Association",
            "type":"Services"
        }
    ],
    "sg:phone":"+1 563 263 3607",
    "sg:postcode":"52761",
    "sg:province":"IA",
    "sg:tags":[
        "business"
    ],
    "wof:name":"Purple Flower Gang",
    "wof:placetype":"venue"
},
  "geometry": {"coordinates":[-91.063813,41.420055],"type":"Point"}
}