{
  "type": "Feature",
  "properties": {
    "iso:country":"US",
    "sg:address":"4148 Main St",
    "sg:city":"Keokuk",
    "sg:classifiers":[
        {
            "category":"Manufacturing",
            "subcategory":"Food",
            "type":"Manufacturing & Wholesale Goods"
        },
        {
            "category":"Farming",
            "subcategory":"Farm",
            "type":"Manufacturing & Wholesale Goods"
        }
    ],
    "sg:phone":"+1 319 524 4589",
    "sg:postcode":"52632",
    "sg:province":"IA",
    "sg:tags":[
        "corn",
        "product"
    ],
    "wof:name":"Robert Leu",
    "wof:placetype":"venue"
},
  "geometry": {"coordinates":[-91.414573,40.428225],"type":"Point"}
}