{
  "type": "Feature",
  "properties": {
    "iso:country":"US",
    "sg:address":"536 2nd St",
    "sg:city":"Webster City",
    "sg:classifiers":[
        {
            "category":"Shopping",
            "subcategory":"Used Merchandise",
            "type":"Retail Goods"
        }
    ],
    "sg:phone":"+1 515 832 4866",
    "sg:postcode":"50595",
    "sg:province":"IA",
    "sg:tags":[
        "second",
        "store",
        "hand"
    ],
    "wof:name":"Tots & Treasures",
    "wof:placetype":"venue"
},
  "geometry": {"coordinates":[-93.818596,42.469349],"type":"Point"}
}