{
  "type": "Feature",
  "properties": {
    "iso:country":"US",
    "sg:address":"520 N Georgia Ave",
    "sg:city":"Mason City",
    "sg:classifiers":[
        {
            "category":"Professional",
            "type":"Services"
        }
    ],
    "sg:phone":"+1 641 422 9987",
    "sg:postcode":"50401",
    "sg:province":"IA",
    "sg:tags":[
        "establishment"
    ],
    "wof:name":"WSKT Inc",
    "wof:placetype":"venue"
},
  "geometry": {"coordinates":[-93.196287,43.156555],"type":"Point"}
}