{
  "type": "Feature",
  "properties": {
    "iso:country":"US",
    "sg:address":"2341 E 57th St",
    "sg:city":"Davenport",
    "sg:classifiers":[
        {
            "category":"Building & Trades",
            "subcategory":"Construction",
            "type":"Services"
        }
    ],
    "sg:phone":"+1 563 359 5029",
    "sg:postcode":"52807",
    "sg:province":"IA",
    "sg:tags":[
        "general",
        "contractor"
    ],
    "wof:name":"Bunde Construction & Design",
    "wof:placetype":"venue"
},
  "geometry": {"coordinates":[-90.545799,41.578707],"type":"Point"}
}