{
  "type": "Feature",
  "properties": {
    "iso:country":"US",
    "sg:address":"2049 235th St",
    "sg:city":"New Hampton",
    "sg:classifiers":[
        {
            "category":"Banks & Credit Unions",
            "subcategory":"Financial Services",
            "type":"Services"
        }
    ],
    "sg:phone":"+1 641 394 3901",
    "sg:postcode":"50659",
    "sg:province":"IA",
    "sg:tags":[
        "trust",
        "management"
    ],
    "wof:name":"Franklin & Patsy Booth Trust",
    "wof:placetype":"venue"
},
  "geometry": {"coordinates":[-92.356324,43.01565],"type":"Point"}
}