{
  "type": "Feature",
  "properties": {
    "iso:country":"US",
    "sg:address":"206 S 2nd Ave",
    "sg:city":"Rock Rapids",
    "sg:classifiers":[
        {
            "category":"Government",
            "subcategory":"Office",
            "type":"Public Place"
        }
    ],
    "sg:phone":"+1 712 472 2811",
    "sg:postcode":"51246",
    "sg:province":"IA",
    "wof:name":"Lyon County Judicial Cnfrnc",
    "wof:placetype":"venue"
},
  "geometry": {"coordinates":[-96.16802800000001,43.430697],"type":"Point"}
}