{
  "type": "Feature",
  "properties": {
    "addr:full":"209 Pearl St Council Bluffs IA 51503",
    "addr:housenumber":"209",
    "addr:postcode":"51503",
    "addr:street":"Pearl St",
    "iso:country":"US",
    "sg:address":"209 Pearl St",
    "sg:city":"Council Bluffs",
    "sg:classifiers":[
        {
            "category":"Government",
            "subcategory":"Office",
            "type":"Public Place"
        }
    ],
    "sg:phone":"+1 712 328 4605",
    "sg:postcode":"51503",
    "sg:province":"IA",
    "sg:tags":[
        "village"
    ],
    "wof:name":"Council Bluffs Finance",
    "wof:placetype":"venue"
},
  "geometry": {"coordinates":[-95.851029,41.258438],"type":"Point"}
}