{
  "type": "Feature",
  "properties": {
    "addr:full":"108 E South Ave Early IA 50535",
    "addr:housenumber":"108 e",
    "addr:postcode":"50535",
    "addr:street":"South Ave",
    "iso:country":"US",
    "sg:address":"108 E South Ave",
    "sg:city":"Early",
    "sg:classifiers":[
        {
            "category":"Wholesale",
            "subcategory":"Motor Vehicles",
            "type":"Manufacturing & Wholesale Goods"
        }
    ],
    "sg:phone":"+1 712 273 5167",
    "sg:postcode":"50535",
    "sg:province":"IA",
    "sg:tags":[
        "trailer"
    ],
    "wof:name":"Corn Belt Mfg Inc",
    "wof:placetype":"venue"
},
  "geometry": {"coordinates":[-95.150317,42.458215],"type":"Point"}
}