{
  "type": "Feature",
  "properties": {
    "iso:country":"US",
    "sg:address":"4664 86th St",
    "sg:city":"Urbandale",
    "sg:classifiers":[
        {
            "category":"Retail",
            "subcategory":"Laundry & Dry Cleaning",
            "type":"Services"
        }
    ],
    "sg:phone":"+1 515 334 0677",
    "sg:postcode":"50322",
    "sg:province":"IA",
    "sg:tags":[
        "cleaners"
    ],
    "wof:name":"Victoria Dry Cleaners",
    "wof:placetype":"venue"
},
  "geometry": {"coordinates":[-93.73654999999999,41.644274],"type":"Point"}
}