{
  "type": "Feature",
  "properties": {
    "addr:full":"719 W Jackson St Sigourney IA 52591",
    "addr:housenumber":"719",
    "addr:postcode":"52591",
    "addr:street":"W Jackson St",
    "iso:country":"US",
    "sg:address":"719 W Jackson St",
    "sg:city":"Sigourney",
    "sg:classifiers":[
        {
            "category":"Organizations",
            "subcategory":"Labor Organization",
            "type":"Services"
        }
    ],
    "sg:phone":"+1 641 622 9090",
    "sg:postcode":"52591",
    "sg:province":"IA",
    "wof:name":"PPME Local 2003",
    "wof:placetype":"venue"
},
  "geometry": {"coordinates":[-92.214817,41.336703],"type":"Point"}
}