{
  "type": "Feature",
  "properties": {
    "addr:full":"2431 Park St Sheldon IA 51201",
    "addr:housenumber":"2431",
    "addr:postcode":"51201",
    "addr:street":"Park St",
    "iso:country":"US",
    "sg:address":"2431 Park St",
    "sg:city":"Sheldon",
    "sg:classifiers":[
        {
            "category":"Wholesale",
            "subcategory":"Construction Materials",
            "type":"Manufacturing & Wholesale Goods"
        }
    ],
    "sg:phone":"+1 712 324 2190",
    "sg:postcode":"51201",
    "sg:province":"IA",
    "sg:tags":[
        "carpentry",
        "contractor"
    ],
    "wof:name":"Kitchen Tune-Up",
    "wof:placetype":"venue"
},
  "geometry": {"coordinates":[-95.822394,43.186108],"type":"Point"}
}