{
  "type": "Feature",
  "properties": {
    "iso:country":"US",
    "sg:address":"550 S Roosevelt Ave",
    "sg:city":"Burlington",
    "sg:classifiers":[
        {
            "category":"Real Estate",
            "subcategory":"Real Estate Agent",
            "type":"Services"
        }
    ],
    "sg:phone":"+1 319 753 6000",
    "sg:postcode":"52601",
    "sg:province":"IA",
    "wof:name":"Property Professionals",
    "wof:placetype":"venue"
},
  "geometry": {"coordinates":[-91.141554,40.804545],"type":"Point"}
}