{
  "type": "Feature",
  "properties": {
    "iso:country":"US",
    "sg:address":"1940 Windover Dr",
    "sg:city":"Ankeny",
    "sg:classifiers":[
        {
            "category":"Building & Trades",
            "subcategory":"Construction",
            "type":"Services"
        }
    ],
    "sg:phone":"+1 515 965 2095",
    "sg:postcode":"50021",
    "sg:province":"IA",
    "sg:tags":[
        "hanging",
        "contractor"
    ],
    "wof:name":"McWilliams Painting Rd",
    "wof:placetype":"venue"
},
  "geometry": {"coordinates":[-93.592083,41.708185],"type":"Point"}
}