{
  "type": "Feature",
  "properties": {
    "addr:full":"41598 310th St Kingsley IA 51028",
    "addr:housenumber":"41598",
    "addr:postcode":"51028",
    "addr:street":"310Th St",
    "iso:country":"US",
    "sg:address":"41598 310th St",
    "sg:city":"Kingsley",
    "sg:classifiers":[
        {
            "category":"Freight",
            "type":"Transportation"
        }
    ],
    "sg:phone":"+1 712 378 3770",
    "sg:postcode":"51028",
    "sg:province":"IA",
    "sg:tags":[
        "building",
        "house",
        "mover"
    ],
    "wof:name":"Move U",
    "wof:placetype":"venue"
},
  "geometry": {"coordinates":[-96.01218799999999,42.604161],"type":"Point"}
}