{
  "type": "Feature",
  "properties": {
    "iso:country":"US",
    "sg:address":"219 E 6th St",
    "sg:city":"Canton",
    "sg:classifiers":[
        {
            "category":"Restaurant",
            "type":"Food & Drink"
        }
    ],
    "sg:phone":"+1 605 987 5339",
    "sg:postcode":"57013",
    "sg:province":"IA",
    "wof:name":"Laurie's Cafe",
    "wof:placetype":"venue"
},
  "geometry": {"coordinates":[-96.591325,43.29989],"type":"Point"}
}