{
  "type": "Feature",
  "properties": {
    "iso:country":"US",
    "sg:address":"3082 120th St",
    "sg:city":"Kingsley",
    "sg:classifiers":[
        {
            "category":"Farming",
            "subcategory":"Farm",
            "type":"Manufacturing & Wholesale Goods"
        }
    ],
    "sg:phone":"+1 712 873 3850",
    "sg:postcode":"51028",
    "sg:province":"IA",
    "sg:tags":[
        "crop",
        "general"
    ],
    "wof:name":"Glenn Bappe",
    "wof:placetype":"venue"
},
  "geometry": {"coordinates":[-95.99890000000001,42.53292],"type":"Point"}
}