{
  "type": "Feature",
  "properties": {
    "addr:full":"1634 Forest Ave New Market IA 51646",
    "addr:housenumber":"1634",
    "addr:postcode":"51646",
    "addr:street":"Forest Ave",
    "iso:country":"US",
    "sg:address":"1634 Forest Ave",
    "sg:city":"New Market",
    "sg:phone":"+1 712 537 2550",
    "sg:postcode":"51646",
    "sg:province":"IA",
    "sg:tags":[
        "farm",
        "grain",
        "cash"
    ],
    "wof:name":"Garry Stamps Farm",
    "wof:placetype":"venue"
},
  "geometry": {"coordinates":[-94.833511,40.808341],"type":"Point"}
}