{
  "type": "Feature",
  "properties": {
    "iso:country":"US",
    "sg:address":"729 Main St",
    "sg:city":"Rockwell City",
    "sg:classifiers":[
        {
            "category":"Building & Trades",
            "subcategory":"Pest Control",
            "type":"Services"
        }
    ],
    "sg:phone":"+1 712 297 5359",
    "sg:postcode":"50579",
    "sg:province":"IA",
    "wof:name":"Lyons Pest Control",
    "wof:placetype":"venue"
},
  "geometry": {"coordinates":[-94.639016,42.395678],"type":"Point"}
}