{
  "type": "Feature",
  "properties": {
    "addr:full":"1546 305th St Brighton IA 52540",
    "addr:housenumber":"1546",
    "addr:postcode":"52540",
    "addr:street":"305Th St",
    "iso:country":"US",
    "sg:address":"1546 305th St",
    "sg:city":"Brighton",
    "sg:classifiers":[
        {
            "category":"Farming",
            "subcategory":"Livestock Farm",
            "type":"Manufacturing & Wholesale Goods"
        }
    ],
    "sg:phone":"+1 319 694 2242",
    "sg:postcode":"52540",
    "sg:province":"IA",
    "sg:tags":[
        "producer"
    ],
    "wof:name":"Springtown Ranch LTD",
    "wof:placetype":"venue"
},
  "geometry": {"coordinates":[-91.8404,41.214388],"type":"Point"}
}