{
  "type": "Feature",
  "properties": {
    "addr:full":"1406 US Hwy 71 Carroll IA 51401",
    "addr:housenumber":"1406",
    "addr:postcode":"51401",
    "addr:street":"Us Hwy 71",
    "iso:country":"US",
    "sg:address":"1406 US Hwy 71",
    "sg:city":"Carroll",
    "sg:classifiers":[
        {
            "category":"Travel",
            "subcategory":"Hotels & Motels",
            "type":"Entertainment"
        }
    ],
    "sg:phone":"+1 712 792 1100",
    "sg:postcode":"51401",
    "sg:province":"IA",
    "wof:name":"Motel 71-30",
    "wof:placetype":"venue"
},
  "geometry": {"coordinates":[-94.878657,42.07376],"type":"Point"}
}