{
  "type": "Feature",
  "properties": {
    "iso:country":"US",
    "sg:address":"12225 Fox Rd",
    "sg:city":"Jesup",
    "sg:classifiers":[
        {
            "category":"Real Estate",
            "subcategory":"Real Estate Operator",
            "type":"Services"
        }
    ],
    "sg:phone":"+1 319 827 1423",
    "sg:postcode":"50648",
    "sg:province":"IA",
    "sg:tags":[
        "property",
        "lessor"
    ],
    "wof:name":"Joseph W Sadler",
    "wof:placetype":"venue"
},
  "geometry": {"coordinates":[-92.10025,42.428058],"type":"Point"}
}