{
  "type": "Feature",
  "properties": {
    "iso:country":"US",
    "sg:address":"116 E Washington St",
    "sg:city":"Clarinda",
    "sg:classifiers":[
        {
            "category":"Health Services",
            "subcategory":"Optometrist",
            "type":"Services"
        }
    ],
    "sg:phone":"+1 712 542 6513",
    "sg:postcode":"51632",
    "sg:province":"IA",
    "wof:name":"Mid Plains Eyecare Center PC",
    "wof:placetype":"venue"
},
  "geometry": {"coordinates":[-95.037678,40.739352],"type":"Point"}
}