{
  "type": "Feature",
  "properties": {
    "iso:country":"US",
    "sg:address":"6670 30th Avenue Dr",
    "sg:city":"Shellsburg",
    "sg:classifiers":[
        {
            "category":"Shopping",
            "subcategory":"Catalog Store",
            "type":"Retail Goods"
        }
    ],
    "sg:phone":"+1 319 446 7668",
    "sg:postcode":"52332",
    "sg:province":"IA",
    "sg:tags":[
        "house",
        "mail"
    ],
    "wof:name":"Timber Ridge Knits",
    "wof:placetype":"venue"
},
  "geometry": {"coordinates":[-91.903066,42.057576],"type":"Point"}
}