{
  "type": "Feature",
  "properties": {
    "iso:country":"US",
    "sg:address":"2556 NE 96th Ave",
    "sg:city":"Ankeny",
    "sg:classifiers":[
        {
            "category":"Professional",
            "subcategory":"Management & Consulting",
            "type":"Services"
        }
    ],
    "sg:phone":"+1 515 964 7066",
    "sg:postcode":"50021",
    "sg:province":"IA",
    "sg:tags":[
        "consultant",
        "business"
    ],
    "wof:name":"Park Group",
    "wof:placetype":"venue"
},
  "geometry": {"coordinates":[-93.568737,41.735621],"type":"Point"}
}