{
  "type": "Feature",
  "properties": {
    "addr:full":"2867 280th Pl Waukee IA 50263",
    "addr:housenumber":"2867",
    "addr:postcode":"50263",
    "addr:street":"280Th Pl",
    "iso:country":"US",
    "sg:address":"2867 280th Pl",
    "sg:city":"Waukee",
    "sg:phone":"+1 515 987 5310",
    "sg:postcode":"50263",
    "sg:province":"IA",
    "sg:tags":[
        "farm",
        "corn"
    ],
    "wof:name":"Don Embree",
    "wof:placetype":"venue"
},
  "geometry": {"coordinates":[-93.923385,41.62938],"type":"Point"}
}