{
  "type": "Feature",
  "properties": {
    "iso:country":"US",
    "sg:address":"4301 E 53rd St Suite 300",
    "sg:city":"Davenport",
    "sg:classifiers":[
        {
            "category":"Professional",
            "subcategory":"Lawyer & Legal Services",
            "type":"Services"
        }
    ],
    "sg:phone":"+1 563 388 8417",
    "sg:postcode":"52807",
    "sg:province":"IA",
    "sg:tags":[
        "attorney",
        "business",
        "estate",
        "planning",
        "law"
    ],
    "wof:name":"Leddin , Matthew A. - Gallagher, Millage",
    "wof:placetype":"venue"
},
  "geometry": {"coordinates":[-90.513397,41.574841],"type":"Point"}
}