{
  "type": "Feature",
  "properties": {
    "iso:country":"US",
    "sg:address":"634 Willow Ave",
    "sg:city":"Council Bluffs",
    "sg:classifiers":[
        {
            "category":"Organizations",
            "subcategory":"Religious Organization",
            "type":"Services"
        }
    ],
    "sg:phone":"+1 712 323 7129",
    "sg:postcode":"51501",
    "sg:province":"IA",
    "sg:tags":[
        "church"
    ],
    "wof:name":"First Presbyterian Church",
    "wof:placetype":"venue"
},
  "geometry": {"coordinates":[-95.853908,41.258958],"type":"Point"}
}