{
  "type": "Feature",
  "properties": {
    "addr:full":"317 58th Ct West Des Moines IA 50266",
    "addr:housenumber":"317",
    "addr:postcode":"50266",
    "addr:street":"58Th Ct",
    "iso:country":"US",
    "sg:address":"317 58th Ct",
    "sg:city":"West Des Moines",
    "sg:classifiers":[
        {
            "category":"Shopping",
            "subcategory":"Clothing, Apparel, & Fashions",
            "type":"Retail Goods"
        }
    ],
    "sg:phone":"+1 515 223 5347",
    "sg:postcode":"50266",
    "sg:province":"IA",
    "wof:name":"Pat Langel Clothiers",
    "wof:placetype":"venue"
},
  "geometry": {"coordinates":[-93.787217,41.574824],"type":"Point"}
}