{
  "type": "Feature",
  "properties": {
    "addr:full":"835 Ave G Fort Madison IA 52627",
    "addr:housenumber":"835",
    "addr:postcode":"52627",
    "addr:street":"Ave G",
    "iso:country":"US",
    "sg:address":"835 Ave G",
    "sg:city":"Fort Madison",
    "sg:classifiers":[
        {
            "category":"Restaurant",
            "type":"Food & Drink"
        }
    ],
    "sg:phone":"+1 319 372 3400",
    "sg:postcode":"52627",
    "sg:province":"IA",
    "wof:name":"Jenna Marie's",
    "wof:placetype":"venue"
},
  "geometry": {"coordinates":[-91.312865,40.631014],"type":"Point"}
}