{
  "type": "Feature",
  "properties": {
    "iso:country":"US",
    "sg:address":"7961 260th St",
    "sg:city":"Dixon",
    "sg:phone":"+1 563 843 3910",
    "sg:postcode":"52773",
    "sg:province":"IA",
    "sg:tags":[
        "farm",
        "corn"
    ],
    "wof:name":"Mark Rock",
    "wof:placetype":"venue"
},
  "geometry": {"coordinates":[-90.736009,41.683658],"type":"Point"}
}