{
  "type": "Feature",
  "properties": {
    "iso:country":"US",
    "sg:address":"1601 60th St",
    "sg:city":"Des Moines",
    "sg:classifiers":[
        {
            "category":"Shopping",
            "subcategory":"Computers & Home Electronics",
            "type":"Retail Goods"
        }
    ],
    "sg:phone":"+1 515 440 0582",
    "sg:postcode":"50322",
    "sg:province":"IA",
    "sg:tags":[
        "software"
    ],
    "wof:name":"MSS Technologies",
    "wof:placetype":"venue"
},
  "geometry": {"coordinates":[-93.6999,41.609957],"type":"Point"}
}