{
  "type": "Feature",
  "properties": {
    "iso:country":"US",
    "sg:address":"401 Walnut St",
    "sg:city":"Muscatine",
    "sg:classifiers":[
        {
            "category":"Government",
            "subcategory":"Jail",
            "type":"Public Place"
        }
    ],
    "sg:phone":"+1 563 263 5903",
    "sg:postcode":"52761",
    "sg:province":"IA",
    "sg:tags":[
        "probation",
        "officer"
    ],
    "wof:name":"Juvenile Probation Officer",
    "wof:placetype":"venue"
},
  "geometry": {"coordinates":[-91.04441199999999,41.425017],"type":"Point"}
}