{
  "type": "Feature",
  "properties": {
    "addr:full":"611 Jones Rd Evansdale IA 50707",
    "addr:housenumber":"611",
    "addr:postcode":"50707",
    "addr:street":"Jones Rd",
    "iso:country":"US",
    "sg:address":"611 Jones Rd",
    "sg:city":"Evansdale",
    "sg:classifiers":[
        {
            "category":"Real Estate",
            "subcategory":"Real Estate Operator",
            "type":"Services"
        }
    ],
    "sg:phone":"+1 319 234 1782",
    "sg:postcode":"50707",
    "sg:province":"IA",
    "sg:tags":[
        "apartment"
    ],
    "wof:name":"Wellington Park Apartments",
    "wof:placetype":"venue"
},
  "geometry": {"coordinates":[-92.29474999999999,42.470255],"type":"Point"}
}