{
  "type": "Feature",
  "properties": {
    "iso:country":"US",
    "sg:address":"530 E Eagle Rd",
    "sg:city":"Waterloo",
    "sg:classifiers":[
        {
            "category":"Farming",
            "subcategory":"Orchard",
            "type":"Manufacturing & Wholesale Goods"
        }
    ],
    "sg:phone":"+1 319 342 3220",
    "sg:postcode":"50701",
    "sg:province":"IA",
    "sg:tags":[
        "grove",
        "management"
    ],
    "wof:name":"Sergio Fuggiti Orchard",
    "wof:placetype":"venue"
},
  "geometry": {"coordinates":[-92.338099,42.340872],"type":"Point"}
}