{
  "type": "Feature",
  "properties": {
    "iso:country":"US",
    "sg:address":"111 S Linn St",
    "sg:city":"Iowa City",
    "sg:classifiers":[
        {
            "category":"Personal",
            "subcategory":"Barber",
            "type":"Services"
        }
    ],
    "sg:phone":"+1 319 351 2861",
    "sg:postcode":"52240",
    "sg:province":"IA",
    "wof:name":"Stan's Barber Stylists",
    "wof:placetype":"venue"
},
  "geometry": {"coordinates":[-91.53173200000001,41.659073],"type":"Point"}
}