{
  "type": "Feature",
  "properties": {
    "iso:country":"US",
    "sg:address":"425 NW 6th St",
    "sg:city":"Earlham",
    "sg:classifiers":[
        {
            "category":"Building & Trades",
            "subcategory":"Plumbing",
            "type":"Services"
        }
    ],
    "sg:phone":"+1 515 758 2769",
    "sg:postcode":"50072",
    "sg:province":"IA",
    "sg:tags":[
        "plumbing",
        "contractor"
    ],
    "wof:name":"Randy Lillie Plumbing Heating",
    "wof:placetype":"venue"
},
  "geometry": {"coordinates":[-94.128294,41.496207],"type":"Point"}
}