{
  "type": "Feature",
  "properties": {
    "iso:country":"US",
    "sg:address":"106 Main St",
    "sg:city":"Panama",
    "sg:classifiers":[
        {
            "category":"Restaurant",
            "type":"Food & Drink"
        }
    ],
    "sg:phone":"+1 712 489 2786",
    "sg:postcode":"51562",
    "sg:province":"IA",
    "wof:name":"Pauleys Pub",
    "wof:placetype":"venue"
},
  "geometry": {"coordinates":[-95.472233,41.726099],"type":"Point"}
}