{
  "type": "Feature",
  "properties": {
    "addr:full":"309 E Church St Marshalltown IA 50158",
    "addr:housenumber":"309",
    "addr:postcode":"50158",
    "addr:street":"E Church St",
    "iso:country":"US",
    "sg:address":"309 E Church St",
    "sg:city":"Marshalltown",
    "sg:classifiers":[
        {
            "category":"Health Services",
            "subcategory":"Doctor",
            "type":"Services"
        }
    ],
    "sg:phone":"+1 641 754 6263",
    "sg:postcode":"50158",
    "sg:province":"IA",
    "sg:tags":[
        "physician",
        "surgeon"
    ],
    "wof:name":"Wolfe Clinic",
    "wof:placetype":"venue"
},
  "geometry": {"coordinates":[-92.90791900000001,42.047844],"type":"Point"}
}