{
  "type": "Feature",
  "properties": {
    "iso:country":"US",
    "sg:address":"812 13th St N",
    "sg:city":"Humboldt",
    "sg:classifiers":[
        {
            "category":"Travel",
            "subcategory":"Hotels & Motels",
            "type":"Entertainment"
        }
    ],
    "sg:phone":"+1 515 332 3545",
    "sg:postcode":"50548",
    "sg:province":"IA",
    "wof:name":"Broadway Inn",
    "wof:placetype":"venue"
},
  "geometry": {"coordinates":[-94.227102,42.730929],"type":"Point"}
}