{
  "type": "Feature",
  "properties": {
    "iso:country":"US",
    "sg:address":"313 11th St",
    "sg:city":"De Witt",
    "sg:classifiers":[
        {
            "category":"Autos & Motor Vehicles",
            "subcategory":"Fuel & Gas Station",
            "type":"Retail Goods"
        }
    ],
    "sg:phone":"+1 563 659 5411",
    "sg:postcode":"52742",
    "sg:province":"IA",
    "sg:tags":[
        "oil"
    ],
    "wof:name":"Corson's Full Svc Ctr",
    "wof:placetype":"venue"
},
  "geometry": {"coordinates":[-90.534651,41.826208],"type":"Point"}
}