{
  "type": "Feature",
  "properties": {
    "iso:country":"US",
    "sg:address":"248 W Clark St",
    "sg:city":"Readlyn",
    "sg:classifiers":[
        {
            "category":"Freight",
            "type":"Transportation"
        }
    ],
    "sg:phone":"+1 319 279 3293",
    "sg:postcode":"50668",
    "sg:province":"IA",
    "sg:tags":[
        "trucking"
    ],
    "wof:name":"Hartman Trucking Inc",
    "wof:placetype":"venue"
},
  "geometry": {"coordinates":[-92.227958,42.706989],"type":"Point"}
}