{
  "type": "Feature",
  "properties": {
    "addr:full":"28322 Great River Rd Princeton IA 52768",
    "addr:housenumber":"28322",
    "addr:postcode":"52768",
    "addr:street":"Great River Rd",
    "iso:country":"US",
    "sg:address":"28322 Great River Rd",
    "sg:city":"Princeton",
    "sg:classifiers":[
        {
            "category":"Recreation",
            "subcategory":"Amusement Park",
            "type":"Entertainment"
        }
    ],
    "sg:phone":"+1 563 289 9999",
    "sg:postcode":"52768",
    "sg:province":"IA",
    "wof:name":"Amazing Maize Maze",
    "wof:placetype":"venue"
},
  "geometry": {"coordinates":[-90.359905,41.719271],"type":"Point"}
}