{
  "type": "Feature",
  "properties": {
    "iso:country":"US",
    "sg:address":"309 6th St",
    "sg:city":"Griswold",
    "sg:classifiers":[
        {
            "category":"Farming",
            "subcategory":"Livestock Farm",
            "type":"Manufacturing & Wholesale Goods"
        }
    ],
    "sg:phone":"+1 712 778 4575",
    "sg:postcode":"51535",
    "sg:province":"IA",
    "sg:tags":[
        "beef",
        "feedlot",
        "cattle"
    ],
    "wof:name":"Peck Cattle Company",
    "wof:placetype":"venue"
},
  "geometry": {"coordinates":[-95.144198,41.232005],"type":"Point"}
}