{
  "type": "Feature",
  "properties": {
    "iso:country":"US",
    "sg:address":"2435 Kimberly Rd",
    "sg:city":"Bettendorf",
    "sg:classifiers":[
        {
            "category":"Home & Garden",
            "subcategory":"Building Materials",
            "type":"Retail Goods"
        }
    ],
    "sg:phone":"+1 563 355 0660",
    "sg:postcode":"52722",
    "sg:province":"IA",
    "sg:tags":[
        "product",
        "lumber"
    ],
    "wof:name":"President Homes Inc",
    "wof:placetype":"venue"
},
  "geometry": {"coordinates":[-90.522344,41.544627],"type":"Point"}
}