{
  "type": "Feature",
  "properties": {
    "iso:country":"US",
    "sg:address":"203 Carmichael St",
    "sg:city":"Chelsea",
    "sg:classifiers":[
        {
            "category":"Real Estate",
            "subcategory":"Real Estate Agent",
            "type":"Services"
        }
    ],
    "sg:phone":"+1 641 489 2050",
    "sg:postcode":"52215",
    "sg:province":"IA",
    "sg:tags":[
        "cooperative"
    ],
    "wof:name":"Farmers Four County Co Op",
    "wof:placetype":"venue"
},
  "geometry": {"coordinates":[-92.395072,41.919921],"type":"Point"}
}