{
  "type": "Feature",
  "properties": {
    "iso:country":"US",
    "sg:address":"16026 33rd St SE",
    "sg:city":"Mason City",
    "sg:classifiers":[
        {
            "category":"Building & Trades",
            "subcategory":"Cleaning & Sanitation",
            "type":"Services"
        }
    ],
    "sg:phone":"+1 641 424 3500",
    "sg:postcode":"50401",
    "sg:province":"IA",
    "sg:tags":[
        "janitor"
    ],
    "wof:name":"Concept One Profession Clng",
    "wof:placetype":"venue"
},
  "geometry": {"coordinates":[-93.201072,43.121316],"type":"Point"}
}