{
  "type": "Feature",
  "properties": {
    "addr:full":"4505 270th Ave Webb IA 51366",
    "addr:housenumber":"4505",
    "addr:postcode":"51366",
    "addr:street":"270Th Ave",
    "iso:country":"US",
    "sg:address":"4505 270th Ave",
    "sg:city":"Webb",
    "sg:classifiers":[
        {
            "category":"Organizations",
            "subcategory":"Religious Organization",
            "type":"Services"
        }
    ],
    "sg:phone":"+1 712 838 4801",
    "sg:postcode":"51366",
    "sg:province":"IA",
    "wof:name":"Parsons Tonna",
    "wof:placetype":"venue"
},
  "geometry": {"coordinates":[-95.053179,42.995329],"type":"Point"}
}