{
  "type": "Feature",
  "properties": {
    "iso:country":"US",
    "sg:address":"107 S Fulton St",
    "sg:city":"Newell",
    "sg:classifiers":[
        {
            "category":"Insurance",
            "subcategory":"Insurance Agent",
            "type":"Services"
        }
    ],
    "sg:phone":"+1 712 272 4422",
    "sg:postcode":"50568",
    "sg:province":"IA",
    "wof:name":"Olsen-Culp Inc",
    "wof:placetype":"venue"
},
  "geometry": {"coordinates":[-95.00240700000001,42.606402],"type":"Point"}
}