{
  "type": "Feature",
  "properties": {
    "iso:country":"US",
    "sg:address":"1530 E Fleming Ave",
    "sg:city":"Des Moines",
    "sg:classifiers":[
        {
            "category":"Retail",
            "subcategory":"Auto Repair",
            "type":"Services"
        }
    ],
    "sg:phone":"+1 515 266 1525",
    "sg:postcode":"50313",
    "sg:province":"IA",
    "sg:tags":[
        "truck"
    ],
    "wof:name":"Overton Truck Repair",
    "wof:placetype":"venue"
},
  "geometry": {"coordinates":[-93.598944,41.632341],"type":"Point"}
}