{
  "type": "Feature",
  "properties": {
    "iso:country":"US",
    "sg:address":"401 S Center St",
    "sg:city":"Marshalltown",
    "sg:classifiers":[
        {
            "category":"Bars & Pubs",
            "type":"Food & Drink"
        }
    ],
    "sg:phone":"+1 641 753 1023",
    "sg:postcode":"50158",
    "sg:province":"IA",
    "wof:name":"Old Timer Tavern",
    "wof:placetype":"venue"
},
  "geometry": {"coordinates":[-92.91289399999999,42.044261],"type":"Point"}
}