{
  "type": "Feature",
  "properties": {
    "addr:full":"923 Main St Grinnell IA 50112",
    "addr:housenumber":"923",
    "addr:postcode":"50112",
    "addr:street":"Main St",
    "iso:country":"US",
    "sg:address":"923 Main St",
    "sg:city":"Grinnell",
    "sg:classifiers":[
        {
            "category":"Insurance",
            "subcategory":"Insurance Agent",
            "type":"Services"
        }
    ],
    "sg:phone":"+1 641 236 5420",
    "sg:postcode":"50112",
    "sg:province":"IA",
    "wof:name":"State Farm Insurance",
    "wof:placetype":"venue"
},
  "geometry": {"coordinates":[-92.72582800000001,41.744368],"type":"Point"}
}