{
  "type": "Feature",
  "properties": {
    "iso:country":"US",
    "sg:address":"5279 460th St",
    "sg:city":"West Bend",
    "sg:classifiers":[
        {
            "category":"Farming",
            "subcategory":"Nursery",
            "type":"Manufacturing & Wholesale Goods"
        }
    ],
    "sg:phone":"+1 515 887 5383",
    "sg:postcode":"50597",
    "sg:province":"IA",
    "sg:tags":[
        "greenhouse"
    ],
    "wof:name":"Madsen's Country Greenhouse",
    "wof:placetype":"venue"
},
  "geometry": {"coordinates":[-94.54481800000001,42.981029],"type":"Point"}
}