{
  "type": "Feature",
  "properties": {
    "addr:full":"4580 Mount Vernon Rd SE Cedar Rapids IA 52403",
    "addr:housenumber":"4580",
    "addr:postcode":"52403",
    "addr:street":"Mount Vernon Rd Se",
    "iso:country":"US",
    "sg:address":"4580 Mount Vernon Rd SE",
    "sg:city":"Cedar Rapids",
    "sg:classifiers":[
        {
            "category":"Retail",
            "subcategory":"Auto Repair",
            "type":"Services"
        }
    ],
    "sg:phone":"+1 319 365 5505",
    "sg:postcode":"52403",
    "sg:province":"IA",
    "sg:tags":[
        "repairing",
        "automobile"
    ],
    "wof:name":"Mefferd's Auto Svc",
    "wof:placetype":"venue"
},
  "geometry": {"coordinates":[-91.595473,41.976879],"type":"Point"}
}