{
  "type": "Feature",
  "properties": {
    "addr:full":"790 W South St Marengo IA 52301",
    "addr:housenumber":"790",
    "addr:postcode":"52301",
    "addr:street":"W South St",
    "iso:country":"US",
    "sg:address":"790 W South St",
    "sg:city":"Marengo",
    "sg:classifiers":[
        {
            "category":"Retail",
            "subcategory":"Car Wash",
            "type":"Services"
        }
    ],
    "sg:phone":"+1 319 642 3037",
    "sg:postcode":"52301",
    "sg:province":"IA",
    "sg:tags":[
        "polishing",
        "washing"
    ],
    "wof:name":"West Side Super Wash",
    "wof:placetype":"venue"
},
  "geometry": {"coordinates":[-92.078793,41.797055],"type":"Point"}
}