{
  "type": "Feature",
  "properties": {
    "addr:full":"1214 Dolen Pl Iowa City IA 52246",
    "addr:housenumber":"1214",
    "addr:postcode":"52246",
    "addr:street":"Dolen Pl",
    "iso:country":"US",
    "sg:address":"1214 Dolen Pl",
    "sg:city":"Iowa City",
    "sg:classifiers":[
        {
            "category":"Professional",
            "type":"Services"
        }
    ],
    "sg:phone":"+1 319 339 7551",
    "sg:postcode":"52246",
    "sg:province":"IA",
    "wof:name":"Postl Company Inc",
    "wof:placetype":"venue"
},
  "geometry": {"coordinates":[-91.57337800000001,41.643415],"type":"Point"}
}