{
  "type": "Feature",
  "properties": {
    "iso:country":"US",
    "sg:address":"3032 420th Ave",
    "sg:city":"Graettinger",
    "sg:classifiers":[
        {
            "category":"Utilities",
            "subcategory":"Refuse",
            "type":"Services"
        }
    ],
    "sg:phone":"+1 712 859 3185",
    "sg:postcode":"51342",
    "sg:province":"IA",
    "sg:tags":[
        "garbage",
        "collection"
    ],
    "wof:name":"Northern Plains Regional Lndfl",
    "wof:placetype":"venue"
},
  "geometry": {"coordinates":[-94.758224,43.207444],"type":"Point"}
}