{
  "type": "Feature",
  "properties": {
    "iso:country":"US",
    "sg:address":"5143 T Ave",
    "sg:city":"Cherokee",
    "sg:classifiers":[
        {
            "category":"Farming",
            "subcategory":"Livestock Farm",
            "type":"Manufacturing & Wholesale Goods"
        }
    ],
    "sg:phone":"+1 712 225 2860",
    "sg:postcode":"51012",
    "sg:province":"IA",
    "sg:tags":[
        "hog",
        "or",
        "feedlot"
    ],
    "wof:name":"Scott Koch",
    "wof:placetype":"venue"
},
  "geometry": {"coordinates":[-95.485946,42.771044],"type":"Point"}
}