{
  "type": "Feature",
  "properties": {
    "iso:country":"US",
    "sg:address":"401 2nd St",
    "sg:city":"Bayard",
    "sg:classifiers":[
        {
            "category":"Organizations",
            "subcategory":"Religious Organization",
            "type":"Services"
        }
    ],
    "sg:phone":"+1 712 651 2905",
    "sg:postcode":"50029",
    "sg:province":"IA",
    "sg:tags":[
        "church"
    ],
    "wof:name":"Church Of Christ",
    "wof:placetype":"venue"
},
  "geometry": {"coordinates":[-94.55803899999999,41.850753],"type":"Point"}
}