{
  "type": "Feature",
  "properties": {
    "addr:full":"101 W 1st St Leon IA 50144",
    "addr:housenumber":"101",
    "addr:postcode":"50144",
    "addr:street":"W 1St",
    "iso:country":"US",
    "sg:address":"101 W 1st St",
    "sg:city":"Leon",
    "sg:classifiers":[
        {
            "category":"Bars & Pubs",
            "type":"Food & Drink"
        }
    ],
    "sg:phone":"+1 641 446 6222",
    "sg:postcode":"50144",
    "sg:province":"IA",
    "wof:name":"Bears Den Pub",
    "wof:placetype":"venue"
},
  "geometry": {"coordinates":[-93.748008,40.739498],"type":"Point"}
}