{
  "type": "Feature",
  "properties": {
    "iso:country":"US",
    "sg:address":"1767 210th St",
    "sg:city":"Diagonal",
    "sg:phone":"+1 641 336 2934",
    "sg:postcode":"50848",
    "sg:province":"IA",
    "sg:tags":[
        "farm"
    ],
    "wof:name":"Kent Kiburz",
    "wof:placetype":"venue"
},
  "geometry": {"coordinates":[-94.782431,40.740937],"type":"Point"}
}