{
  "type": "Feature",
  "properties": {
    "addr:full":"903 N Sumner Ave Creston IA 50801",
    "addr:housenumber":"903",
    "addr:postcode":"50801",
    "addr:street":"N Sumner Ave",
    "iso:country":"US",
    "sg:address":"903 N Sumner Ave",
    "sg:city":"Creston",
    "sg:classifiers":[
        {
            "category":"Food & Beverages",
            "subcategory":"Groceries & Convenience Stores",
            "type":"Retail Goods"
        }
    ],
    "sg:phone":"+1 641 782 4267",
    "sg:postcode":"50801",
    "sg:province":"IA",
    "wof:name":"Kum & Go",
    "wof:placetype":"venue"
},
  "geometry": {"coordinates":[-94.372494,41.068009],"type":"Point"}
}