{
  "type": "Feature",
  "properties": {
    "addr:full":"1447 Main St Rock Valley IA 51247",
    "addr:housenumber":"1447",
    "addr:postcode":"51247",
    "addr:street":"Main St",
    "iso:country":"US",
    "sg:address":"1447 Main St",
    "sg:city":"Rock Valley",
    "sg:classifiers":[
        {
            "category":"Shopping",
            "subcategory":"Florist",
            "type":"Retail Goods"
        }
    ],
    "sg:phone":"+1 712 476 2588",
    "sg:postcode":"51247",
    "sg:province":"IA",
    "wof:name":"Something Special",
    "wof:placetype":"venue"
},
  "geometry": {"coordinates":[-96.294991,43.204706],"type":"Point"}
}