{
  "type": "Feature",
  "properties": {
    "iso:country":"US",
    "sg:address":"1600 E Grand Ave",
    "sg:city":"Des Moines",
    "sg:classifiers":[
        {
            "category":"Personal",
            "subcategory":"Beauty Salon",
            "type":"Services"
        }
    ],
    "sg:phone":"+1 515 299 3500",
    "sg:postcode":"50316",
    "sg:province":"IA",
    "wof:name":"Secretos Beauty Shop",
    "wof:placetype":"venue"
},
  "geometry": {"coordinates":[-93.58993100000001,41.595017],"type":"Point"}
}