{
  "type": "Feature",
  "properties": {
    "iso:country":"US",
    "sg:address":"215 Main St",
    "sg:city":"Danbury",
    "sg:classifiers":[
        {
            "category":"Education",
            "subcategory":"Library",
            "type":"Public Place"
        }
    ],
    "sg:phone":"+1 712 883 2207",
    "sg:postcode":"51019",
    "sg:province":"IA",
    "wof:name":"Danbury Library",
    "wof:placetype":"venue"
},
  "geometry": {"coordinates":[-95.72189400000001,42.235298],"type":"Point"}
}