{
  "type": "Feature",
  "properties": {
    "addr:full":"11054 Hickory Ave Monona IA 52159",
    "addr:housenumber":"11054",
    "addr:postcode":"52159",
    "addr:street":"Hickory Ave",
    "iso:country":"US",
    "sg:address":"11054 Hickory Ave",
    "sg:city":"Monona",
    "sg:phone":"+1 563 539 2857",
    "sg:postcode":"52159",
    "sg:province":"IA",
    "sg:tags":[
        "farm",
        "corn"
    ],
    "wof:name":"Kruse Nile",
    "wof:placetype":"venue"
},
  "geometry": {"coordinates":[-91.330111,43.065995],"type":"Point"}
}