{
  "type": "Feature",
  "properties": {
    "addr:full":"21912 160th St Sumner IA 50674",
    "addr:housenumber":"21912",
    "addr:postcode":"50674",
    "addr:street":"160Th St",
    "iso:country":"US",
    "sg:address":"21912 160th St",
    "sg:city":"Sumner",
    "sg:classifiers":[
        {
            "category":"Building & Trades",
            "subcategory":"Landscaping Services",
            "type":"Services"
        }
    ],
    "sg:phone":"+1 563 578 5564",
    "sg:postcode":"50674",
    "sg:province":"IA",
    "sg:tags":[
        "landscape",
        "contractor"
    ],
    "wof:name":"Maifeld Landscaping",
    "wof:placetype":"venue"
},
  "geometry": {"coordinates":[-92.021944,42.862116],"type":"Point"}
}