{
  "type": "Feature",
  "properties": {
    "iso:country":"US",
    "sg:address":"422 S Leebrick St",
    "sg:city":"Burlington",
    "sg:classifiers":[
        {
            "category":"Personal",
            "subcategory":"Beauty Salon",
            "type":"Services"
        }
    ],
    "sg:phone":"+1 319 753 2238",
    "sg:postcode":"52601",
    "sg:province":"IA",
    "wof:name":"Kimberly's",
    "wof:placetype":"venue"
},
  "geometry": {"coordinates":[-91.12025,40.806197],"type":"Point"}
}