{
  "type": "Feature",
  "properties": {
    "addr:full":"2288 Orient Ave Logan IA 51546",
    "addr:housenumber":"2288",
    "addr:postcode":"51546",
    "addr:street":"Orient Ave",
    "iso:country":"US",
    "sg:address":"2288 Orient Ave",
    "sg:city":"Logan",
    "sg:phone":"+1 712 644 3239",
    "sg:postcode":"51546",
    "sg:province":"IA",
    "sg:tags":[
        "farm",
        "corn",
        "soybean"
    ],
    "wof:name":"Econ Farms",
    "wof:placetype":"venue"
},
  "geometry": {"coordinates":[-95.779973,41.687708],"type":"Point"}
}