{
  "type": "Feature",
  "properties": {
    "iso:country":"US",
    "sg:address":"1005 Hillcrest Dr",
    "sg:city":"Fairfield",
    "sg:classifiers":[
        {
            "category":"Real Estate",
            "subcategory":"Real Estate Operator",
            "type":"Services"
        }
    ],
    "sg:phone":"+1 641 472 2750",
    "sg:postcode":"52556",
    "sg:province":"IA",
    "sg:tags":[
        "property",
        "lessor"
    ],
    "wof:name":"Koontz Rental Properties",
    "wof:placetype":"venue"
},
  "geometry": {"coordinates":[-91.94898000000001,41.000208],"type":"Point"}
}