{
  "type": "Feature",
  "properties": {
    "iso:country":"US",
    "sg:address":"1102 River Rd S",
    "sg:city":"Steamboat Rock",
    "sg:classifiers":[
        {
            "category":"Government",
            "subcategory":"Office",
            "type":"Public Place"
        }
    ],
    "sg:phone":"+1 641 868 2314",
    "sg:postcode":"50672",
    "sg:province":"IA",
    "sg:tags":[
        "village"
    ],
    "wof:name":"Sewage Treatment Plant",
    "wof:placetype":"venue"
},
  "geometry": {"coordinates":[-93.07591499999999,42.404614],"type":"Point"}
}