{
  "type": "Feature",
  "properties": {
    "addr:full":"1402 S 7th St Keokuk IA 52632",
    "addr:housenumber":"1402",
    "addr:postcode":"52632",
    "addr:street":"S 7Th St",
    "iso:country":"US",
    "sg:address":"1402 S 7th St",
    "sg:city":"Keokuk",
    "sg:classifiers":[
        {
            "category":"Education",
            "subcategory":"School",
            "type":"Public Place"
        }
    ],
    "sg:phone":"+1 319 524 2460",
    "sg:postcode":"52632",
    "sg:province":"IA",
    "wof:name":"Lincoln Elementary School",
    "wof:placetype":"venue"
},
  "geometry": {"coordinates":[-91.400201,40.391145],"type":"Point"}
}