{
  "type": "Feature",
  "properties": {
    "iso:country":"US",
    "sg:address":"1133 66th St",
    "sg:city":"Windsor Heights",
    "sg:classifiers":[
        {
            "category":"Utilities",
            "subcategory":"Water",
            "type":"Services"
        }
    ],
    "sg:phone":"+1 515 279 3662",
    "sg:postcode":"50311",
    "sg:province":"IA",
    "sg:tags":[
        "company",
        "sewage"
    ],
    "wof:name":"Windsor Heights Water Dept",
    "wof:placetype":"venue"
},
  "geometry": {"coordinates":[-93.708555,41.599607],"type":"Point"}
}