{
  "type": "Feature",
  "properties": {
    "iso:country":"US",
    "sg:address":"3433 Ave O",
    "sg:city":"Fort Madison",
    "sg:classifiers":[
        {
            "category":"Social Services",
            "subcategory":"Child Care",
            "type":"Services"
        }
    ],
    "sg:phone":"+1 319 372 4475",
    "sg:postcode":"52627",
    "sg:province":"IA",
    "wof:name":"Fort Madison Head Start Ctr",
    "wof:placetype":"venue"
},
  "geometry": {"coordinates":[-91.35692,40.624091],"type":"Point"}
}