{
  "type": "Feature",
  "properties": {
    "iso:country":"US",
    "sg:address":"117 Main St",
    "sg:city":"Prairieburg",
    "sg:classifiers":[
        {
            "category":"Retail",
            "subcategory":"Animal Services",
            "type":"Services"
        }
    ],
    "sg:phone":"+1 319 437 4591",
    "sg:postcode":"52205",
    "sg:province":"IA",
    "sg:tags":[
        "pet"
    ],
    "wof:name":"Denco Bird Dog Breeding",
    "wof:placetype":"venue"
},
  "geometry": {"coordinates":[-91.417625,42.238396],"type":"Point"}
}