{
  "type": "Feature",
  "properties": {
    "iso:country":"US",
    "sg:address":"8421 University Blvd",
    "sg:city":"Clive",
    "sg:classifiers":[
        {
            "category":"Professional",
            "subcategory":"Business Services",
            "type":"Services"
        }
    ],
    "sg:phone":"+1 515 288 3549",
    "sg:postcode":"50325",
    "sg:province":"IA",
    "sg:tags":[
        "paging",
        "answering"
    ],
    "wof:name":"Answer Plus Inc",
    "wof:placetype":"venue"
},
  "geometry": {"coordinates":[-93.73589699999999,41.605655],"type":"Point"}
}