{
  "type": "Feature",
  "properties": {
    "iso:country":"US",
    "sg:address":"611 4th St",
    "sg:city":"Nevada",
    "sg:classifiers":[
        {
            "category":"Retail",
            "subcategory":"Veterinary Services",
            "type":"Services"
        }
    ],
    "sg:phone":"+1 515 382 2400",
    "sg:postcode":"50201",
    "sg:province":"IA",
    "sg:tags":[
        "veterinarian"
    ],
    "wof:name":"Nevada Veterinary Clinic",
    "wof:placetype":"venue"
},
  "geometry": {"coordinates":[-93.454914,42.017501],"type":"Point"}
}