{
  "type": "Feature",
  "properties": {
    "iso:country":"US",
    "sg:address":"960 32nd Ave SW",
    "sg:city":"Cedar Rapids",
    "sg:classifiers":[
        {
            "category":"Wholesale",
            "subcategory":"Auto Parts",
            "type":"Manufacturing & Wholesale Goods"
        }
    ],
    "sg:phone":"+1 319 364 3742",
    "sg:postcode":"52404",
    "sg:province":"IA",
    "sg:tags":[
        "tire"
    ],
    "wof:name":"Us Tire & Exhaust",
    "wof:placetype":"venue"
},
  "geometry": {"coordinates":[-91.682124,41.945384],"type":"Point"}
}