{
  "type": "Feature",
  "properties": {
    "addr:full":"208 Parker St Tracy IA 50256",
    "addr:housenumber":"208",
    "addr:postcode":"50256",
    "addr:street":"Parker St",
    "iso:country":"US",
    "sg:address":"208 Parker St",
    "sg:city":"Tracy",
    "sg:classifiers":[
        {
            "category":"Personal",
            "subcategory":"Beauty Salon",
            "type":"Services"
        }
    ],
    "sg:phone":"+1 641 949 6375",
    "sg:postcode":"50256",
    "sg:province":"IA",
    "sg:tags":[
        "shop"
    ],
    "wof:name":"Main Street Hairstyling II",
    "wof:placetype":"venue"
},
  "geometry": {"coordinates":[-92.875315,41.27859],"type":"Point"}
}