{
  "type": "Feature",
  "properties": {
    "iso:country":"US",
    "sg:address":"1110 Bluff St",
    "sg:city":"Dubuque",
    "sg:classifiers":[
        {
            "category":"Real Estate",
            "subcategory":"Architect",
            "type":"Services"
        }
    ],
    "sg:phone":"+1 563 582 7334",
    "sg:postcode":"52001",
    "sg:province":"IA",
    "wof:name":"Steven Ulstad Architects",
    "wof:placetype":"venue"
},
  "geometry": {"coordinates":[-90.670722,42.503514],"type":"Point"}
}