{
  "type": "Feature",
  "properties": {
    "iso:country":"US",
    "sg:address":"407 Lynn St",
    "sg:city":"Tipton",
    "sg:classifiers":[
        {
            "category":"Government",
            "subcategory":"Office",
            "type":"Public Place"
        }
    ],
    "sg:phone":"+1 563 886 6564",
    "sg:postcode":"52772",
    "sg:province":"IA",
    "sg:tags":[
        "village"
    ],
    "wof:name":"City Coordinator",
    "wof:placetype":"venue"
},
  "geometry": {"coordinates":[-91.12988900000001,41.769938],"type":"Point"}
}