{
  "type": "Feature",
  "properties": {
    "iso:country":"US",
    "sg:address":"8807 Rickard Rd",
    "sg:city":"La Porte City",
    "sg:classifiers":[
        {
            "category":"Wholesale",
            "subcategory":"Farm Supplies",
            "type":"Manufacturing & Wholesale Goods"
        }
    ],
    "sg:phone":"+1 319 342 2997",
    "sg:postcode":"50651",
    "sg:province":"IA",
    "sg:tags":[
        "feed"
    ],
    "wof:name":"Schmitz Vigortone Products",
    "wof:placetype":"venue"
},
  "geometry": {"coordinates":[-92.165415,42.39915],"type":"Point"}
}