{
  "type": "Feature",
  "properties": {
    "iso:country":"US",
    "sg:address":"916 4th Ave S",
    "sg:city":"Denison",
    "sg:classifiers":[
        {
            "category":"Travel",
            "subcategory":"Hotels & Motels",
            "type":"Entertainment"
        }
    ],
    "sg:phone":"+1 712 263 3843",
    "sg:postcode":"51442",
    "sg:province":"IA",
    "wof:name":"Ho Hum Motel",
    "wof:placetype":"venue"
},
  "geometry": {"coordinates":[-95.361058,42.012461],"type":"Point"}
}