{
  "type": "Feature",
  "properties": {
    "addr:full":"222 W 4th St St Ansgar IA 50472",
    "addr:housenumber":"222",
    "addr:postcode":"50472",
    "addr:street":"W 4Th St",
    "iso:country":"US",
    "sg:address":"222 W 4th St",
    "sg:city":"St Ansgar",
    "sg:classifiers":[
        {
            "category":"Insurance",
            "subcategory":"Insurance Agent",
            "type":"Services"
        }
    ],
    "sg:phone":"+1 641 713 4899",
    "sg:postcode":"50472",
    "sg:province":"IA",
    "wof:name":"Farm Bureau Insurance",
    "wof:placetype":"venue"
},
  "geometry": {"coordinates":[-92.921359,43.378399],"type":"Point"}
}