{
  "type": "Feature",
  "properties": {
    "iso:country":"US",
    "sg:address":"803 7th St",
    "sg:city":"Corning",
    "sg:classifiers":[
        {
            "category":"Health Services",
            "subcategory":"Clinic",
            "type":"Services"
        }
    ],
    "sg:phone":"+1 641 322 3505",
    "sg:postcode":"50841",
    "sg:province":"IA",
    "sg:tags":[
        "home",
        "care"
    ],
    "wof:name":"Simply Safe Home Monitoring",
    "wof:placetype":"venue"
},
  "geometry": {"coordinates":[-94.739302,40.98898],"type":"Point"}
}