{
  "type": "Feature",
  "properties": {
    "addr:full":"102 Cedar St Fruitland IA 52749",
    "addr:housenumber":"102",
    "addr:postcode":"52749",
    "addr:street":"Cedar St",
    "iso:country":"US",
    "sg:address":"102 Cedar St",
    "sg:city":"Fruitland",
    "sg:classifiers":[
        {
            "category":"Bars & Pubs",
            "type":"Food & Drink"
        }
    ],
    "sg:phone":"+1 563 263 3355",
    "sg:postcode":"52749",
    "sg:province":"IA",
    "wof:name":"Mad Marv's Place",
    "wof:placetype":"venue"
},
  "geometry": {"coordinates":[-91.128725,41.359245],"type":"Point"}
}