{
  "type": "Feature",
  "properties": {
    "iso:country":"US",
    "sg:address":"1112 Bridge Ave",
    "sg:city":"Davenport",
    "sg:classifiers":[
        {
            "category":"Social Services",
            "type":"Services"
        }
    ],
    "sg:phone":"+1 563 324 8298",
    "sg:postcode":"52803",
    "sg:province":"IA",
    "sg:tags":[
        "organization",
        "welfare"
    ],
    "wof:name":"Anchorage House",
    "wof:placetype":"venue"
},
  "geometry": {"coordinates":[-90.55793300000001,41.531612],"type":"Point"}
}