{
  "type": "Feature",
  "properties": {
    "iso:country":"US",
    "sg:address":"2055 Kimball Ave",
    "sg:city":"Waterloo",
    "sg:classifiers":[
        {
            "category":"Health Services",
            "subcategory":"Doctor",
            "type":"Services"
        }
    ],
    "sg:phone":"+1 319 272 2112",
    "sg:postcode":"50702",
    "sg:province":"IA",
    "sg:tags":[
        "physician",
        "surgeon"
    ],
    "sg:website":"www.familypracticecenter.org",
    "wof:name":"Family Practice Ctr",
    "wof:placetype":"venue"
},
  "geometry": {"coordinates":[-92.356819,42.469462],"type":"Point"}
}