{
  "type": "Feature",
  "properties": {
    "addr:full":"709 W Main St Lake City IA 51449",
    "addr:housenumber":"709",
    "addr:postcode":"51449",
    "addr:street":"W Main St",
    "iso:country":"US",
    "sg:address":"709 W Main St",
    "sg:city":"Lake City",
    "sg:classifiers":[
        {
            "category":"Education",
            "subcategory":"School",
            "type":"Public Place"
        }
    ],
    "sg:phone":"+1 712 464 3134",
    "sg:postcode":"51449",
    "sg:province":"IA",
    "wof:name":"Lake City Vocational Ag Dept",
    "wof:placetype":"venue"
},
  "geometry": {"coordinates":[-94.74195400000001,42.267251],"type":"Point"}
}