{
  "type": "Feature",
  "properties": {
    "iso:country":"US",
    "sg:address":"301 N Madison St",
    "sg:city":"Bloomfield",
    "sg:classifiers":[
        {
            "category":"Organizations",
            "subcategory":"Religious Organization",
            "type":"Services"
        }
    ],
    "sg:phone":"+1 641 664 1216",
    "sg:postcode":"52537",
    "sg:province":"IA",
    "sg:tags":[
        "church"
    ],
    "wof:name":"Justin Hill Ministries",
    "wof:placetype":"venue"
},
  "geometry": {"coordinates":[-92.41502800000001,40.754691],"type":"Point"}
}