{
  "type": "Feature",
  "properties": {
    "iso:country":"US",
    "sg:address":"2725 6th Ave",
    "sg:city":"Council Bluffs",
    "sg:classifiers":[
        {
            "category":"Real Estate",
            "subcategory":"Real Estate Agent",
            "type":"Services"
        }
    ],
    "sg:phone":"+1 712 323 2278",
    "sg:postcode":"51501",
    "sg:province":"IA",
    "sg:tags":[
        "agency",
        "rental"
    ],
    "wof:name":"KERN Rental Inc",
    "wof:placetype":"venue"
},
  "geometry": {"coordinates":[-95.888668,41.256248],"type":"Point"}
}