{
  "type": "Feature",
  "properties": {
    "addr:full":"589 E 53rd St Davenport IA 52807",
    "addr:housenumber":"589",
    "addr:postcode":"52807",
    "addr:street":"E 53Rd St",
    "iso:country":"US",
    "sg:address":"589 E 53rd St",
    "sg:city":"Davenport",
    "sg:classifiers":[
        {
            "category":"Restaurant",
            "type":"Food & Drink"
        }
    ],
    "sg:phone":"+1 563 445 8898",
    "sg:postcode":"52807",
    "sg:province":"IA",
    "sg:tags":[
        "asian",
        "chinese",
        "pan"
    ],
    "wof:name":"Crazy Wok",
    "wof:placetype":"venue"
},
  "geometry": {"coordinates":[-90.565878,41.574592],"type":"Point"}
}