{
  "type": "Feature",
  "properties": {
    "addr:full":"283 Hayes Dr Pleasantville IA 50225",
    "addr:housenumber":"283",
    "addr:postcode":"50225",
    "addr:street":"Hayes Dr",
    "iso:country":"US",
    "sg:address":"283 Hayes Dr",
    "sg:city":"Pleasantville",
    "sg:classifiers":[
        {
            "category":"Farming",
            "subcategory":"Dairy Farm",
            "type":"Manufacturing & Wholesale Goods"
        }
    ],
    "sg:phone":"+1 515 848 5791",
    "sg:postcode":"50225",
    "sg:province":"IA",
    "wof:name":"Dairy Farm",
    "wof:placetype":"venue"
},
  "geometry": {"coordinates":[-93.28665100000001,41.392641],"type":"Point"}
}