{
  "type": "Feature",
  "properties": {
    "iso:country":"US",
    "sg:address":"974 Merle Hay Mall",
    "sg:city":"Des Moines",
    "sg:classifiers":[
        {
            "category":"Restaurant",
            "type":"Food & Drink"
        }
    ],
    "sg:menulink":"http://www.allmenus.com/ia/des-moines/158448-arbys/menu/",
    "sg:phone":"+1 515 254 0590",
    "sg:postcode":"50310",
    "sg:province":"IA",
    "sg:tags":[
        "burger",
        "american"
    ],
    "wof:name":"Arby's",
    "wof:placetype":"venue"
},
  "geometry": {"coordinates":[-93.698528,41.632924],"type":"Point"}
}