{
  "type": "Feature",
  "properties": {
    "iso:country":"US",
    "sg:address":"3 Blue Grass Ct",
    "sg:city":"Davenport",
    "sg:classifiers":[
        {
            "category":"Building & Trades",
            "subcategory":"Landscaping Services",
            "type":"Services"
        }
    ],
    "sg:phone":"+1 563 529 3752",
    "sg:postcode":"52802",
    "sg:province":"IA",
    "sg:tags":[
        "tree"
    ],
    "wof:name":"Dawg The Tree Expert",
    "wof:placetype":"venue"
},
  "geometry": {"coordinates":[-90.652304,41.508029],"type":"Point"}
}