{
  "type": "Feature",
  "properties": {
    "addr:full":"1510 S Garfield Pl Mason City IA 50401",
    "addr:housenumber":"1510",
    "addr:postcode":"50401",
    "addr:street":"S Garfield Pl",
    "iso:country":"US",
    "sg:address":"1510 S Garfield Pl",
    "sg:city":"Mason City",
    "sg:classifiers":[
        {
            "category":"Wholesale",
            "subcategory":"Groceries",
            "type":"Manufacturing & Wholesale Goods"
        }
    ],
    "sg:phone":"+1 641 423 0334",
    "sg:postcode":"50401",
    "sg:province":"IA",
    "sg:tags":[
        "food",
        "broker"
    ],
    "wof:name":"Heartland Paper Co",
    "wof:placetype":"venue"
},
  "geometry": {"coordinates":[-93.226375,43.137419],"type":"Point"}
}