{
  "type": "Feature",
  "properties": {
    "iso:country":"US",
    "sg:address":"1467 170th St",
    "sg:city":"Boone",
    "sg:phone":"+1 515 432 6989",
    "sg:postcode":"50036",
    "sg:province":"IA",
    "sg:tags":[
        "farm",
        "corn"
    ],
    "wof:name":"Alan Doran",
    "wof:placetype":"venue"
},
  "geometry": {"coordinates":[-93.881018,42.10704],"type":"Point"}
}