{
  "type": "Feature",
  "properties": {
    "iso:country":"US",
    "sg:address":"215 11th St NE",
    "sg:city":"Dyersville",
    "sg:classifiers":[
        {
            "category":"Wholesale",
            "subcategory":"Farm Supplies",
            "type":"Manufacturing & Wholesale Goods"
        }
    ],
    "sg:phone":"+1 563 875 2411",
    "sg:postcode":"52040",
    "sg:province":"IA",
    "sg:tags":[
        "buyer",
        "livestock"
    ],
    "wof:name":"Lynch Livestock Inc",
    "wof:placetype":"venue"
},
  "geometry": {"coordinates":[-91.110552,42.483175],"type":"Point"}
}