{
  "type": "Feature",
  "properties": {
    "iso:country":"US",
    "sg:address":"2700 1st Ave S",
    "sg:city":"Fort Dodge",
    "sg:classifiers":[
        {
            "category":"Government",
            "subcategory":"Office",
            "type":"Public Place"
        }
    ],
    "sg:phone":"+1 515 955 5695",
    "sg:postcode":"50501",
    "sg:province":"IA",
    "wof:name":"Iowa Central Training Prog",
    "wof:placetype":"venue"
},
  "geometry": {"coordinates":[-94.160686,42.505306],"type":"Point"}
}