{
  "type": "Feature",
  "properties": {
    "iso:country":"US",
    "sg:address":"805 W Valley Ave",
    "sg:city":"Shenandoah",
    "sg:classifiers":[
        {
            "category":"Retail",
            "subcategory":"Auto Repair",
            "type":"Services"
        }
    ],
    "sg:phone":"+1 712 246 5803",
    "sg:postcode":"51601",
    "sg:province":"IA",
    "sg:tags":[
        "repairing",
        "automobile"
    ],
    "wof:name":"Lee's Auto Svc",
    "wof:placetype":"venue"
},
  "geometry": {"coordinates":[-95.376199,40.767794],"type":"Point"}
}