{
  "type": "Feature",
  "properties": {
    "iso:country":"US",
    "sg:address":"405 Dodge St",
    "sg:city":"Keosauqua",
    "sg:classifiers":[
        {
            "category":"Insurance",
            "subcategory":"Insurance Agent",
            "type":"Services"
        }
    ],
    "sg:phone":"+1 319 293 3783",
    "sg:postcode":"52565",
    "sg:province":"IA",
    "wof:name":"Umphrey Insurance Inc",
    "wof:placetype":"venue"
},
  "geometry": {"coordinates":[-91.96405799999999,40.733081],"type":"Point"}
}