{
  "type": "Feature",
  "properties": {
    "addr:full":"21385 520th St Pocahontas IA 50574",
    "addr:housenumber":"21385",
    "addr:postcode":"50574",
    "addr:street":"520Th St",
    "iso:country":"US",
    "sg:address":"21385 520th St",
    "sg:city":"Pocahontas",
    "sg:classifiers":[
        {
            "category":"Farming",
            "subcategory":"Livestock Farm",
            "type":"Manufacturing & Wholesale Goods"
        }
    ],
    "sg:phone":"+1 712 335 4285",
    "sg:postcode":"50574",
    "sg:province":"IA",
    "sg:tags":[
        "ranch"
    ],
    "wof:name":"Bar J Ranch Inc",
    "wof:placetype":"venue"
},
  "geometry": {"coordinates":[-94.697107,42.73265],"type":"Point"}
}