{
  "type": "Feature",
  "properties": {
    "iso:country":"US",
    "sg:address":"16053 170th St",
    "sg:city":"Rockwell",
    "sg:classifiers":[
        {
            "category":"Shopping",
            "subcategory":"Bicycles & Sporting Goods",
            "type":"Retail Goods"
        }
    ],
    "sg:phone":"+1 641 822 3625",
    "sg:postcode":"50469",
    "sg:province":"IA",
    "sg:tags":[
        "gun",
        "gunsmith"
    ],
    "wof:name":"Circle G-Gunsmithing",
    "wof:placetype":"venue"
},
  "geometry": {"coordinates":[-93.200868,43.008829],"type":"Point"}
}