{
  "type": "Feature",
  "properties": {
    "iso:country":"US",
    "sg:address":"223 S Walnut Ave",
    "sg:city":"Ames",
    "sg:classifiers":[
        {
            "category":"Government",
            "subcategory":"Office",
            "type":"Public Place"
        }
    ],
    "sg:phone":"+1 515 232 5785",
    "sg:postcode":"50010",
    "sg:province":"IA",
    "wof:name":"US Veterinary Biologics Field",
    "wof:placetype":"venue"
},
  "geometry": {"coordinates":[-93.616974,42.020506],"type":"Point"}
}