{
  "type": "Feature",
  "properties": {
    "addr:full":"405 E Cedar St Massena IA 50853",
    "addr:housenumber":"405",
    "addr:postcode":"50853",
    "addr:street":"E Cedar St",
    "iso:country":"US",
    "sg:address":"405 E Cedar St",
    "sg:city":"Massena",
    "sg:phone":"+1 712 779 3407",
    "sg:postcode":"50853",
    "sg:province":"IA",
    "sg:tags":[
        "farm",
        "corn",
        "soybean"
    ],
    "wof:name":"Ellen Aupperle",
    "wof:placetype":"venue"
},
  "geometry": {"coordinates":[-94.766396,41.252033],"type":"Point"}
}