{
  "type": "Feature",
  "properties": {
    "iso:country":"US",
    "sg:address":"123 W Water St",
    "sg:city":"Decorah",
    "sg:classifiers":[
        {
            "category":"Professional",
            "subcategory":"Accounting & Tax Preparation",
            "type":"Services"
        }
    ],
    "sg:phone":"+1 563 382 3637",
    "sg:postcode":"52101",
    "sg:province":"IA",
    "sg:tags":[
        "accountant"
    ],
    "wof:name":"Hacker Nelson & Co",
    "wof:placetype":"venue"
},
  "geometry": {"coordinates":[-91.78697,43.304094],"type":"Point"}
}