{
  "type": "Feature",
  "properties": {
    "addr:full":"17 1st St SW Hampton IA 50441",
    "addr:housenumber":"17",
    "addr:postcode":"50441",
    "addr:street":"1St St Sw",
    "iso:country":"US",
    "sg:address":"17 1st St SW",
    "sg:city":"Hampton",
    "sg:classifiers":[
        {
            "category":"Personal",
            "subcategory":"Tanning Parlor",
            "type":"Services"
        }
    ],
    "sg:phone":"+1 641 456 3344",
    "sg:postcode":"50441",
    "sg:province":"IA",
    "sg:tags":[
        "salon"
    ],
    "wof:name":"Caribbean Sun",
    "wof:placetype":"venue"
},
  "geometry": {"coordinates":[-93.20874999999999,42.74164],"type":"Point"}
}