{
  "type": "Feature",
  "properties": {
    "iso:country":"US",
    "sg:address":"211 6th St SW",
    "sg:city":"Britt",
    "sg:classifiers":[
        {
            "category":"Farming",
            "subcategory":"Farm",
            "type":"Manufacturing & Wholesale Goods"
        }
    ],
    "sg:phone":"+1 641 843 4428",
    "sg:postcode":"50423",
    "sg:province":"IA",
    "sg:tags":[
        "crop",
        "general"
    ],
    "wof:name":"Craig Goepel",
    "wof:placetype":"venue"
},
  "geometry": {"coordinates":[-93.805249,43.09141],"type":"Point"}
}