{
  "type": "Feature",
  "properties": {
    "addr:full":"4897 Warbler Ave Sutherland IA 51058",
    "addr:housenumber":"4897",
    "addr:postcode":"51058",
    "addr:street":"Warbler Ave",
    "iso:country":"US",
    "sg:address":"4897 Warbler Ave",
    "sg:city":"Sutherland",
    "sg:classifiers":[
        {
            "category":"Recreation",
            "type":"Entertainment"
        }
    ],
    "sg:phone":"+1 712 448 2254",
    "sg:postcode":"51058",
    "sg:province":"IA",
    "sg:tags":[
        "parks"
    ],
    "wof:name":"Dog Creek Park",
    "wof:placetype":"venue"
},
  "geometry": {"coordinates":[-95.46675999999999,42.939993],"type":"Point"}
}