{
  "type": "Feature",
  "properties": {
    "iso:country":"US",
    "sg:address":"2919 Quinlan Ave",
    "sg:city":"Fredericksburg",
    "sg:classifiers":[
        {
            "category":"Real Estate",
            "subcategory":"Real Estate Operator",
            "type":"Services"
        }
    ],
    "sg:phone":"+1 563 237 5860",
    "sg:postcode":"50630",
    "sg:province":"IA",
    "sg:tags":[
        "property",
        "lessor"
    ],
    "wof:name":"Everett Steege",
    "wof:placetype":"venue"
},
  "geometry": {"coordinates":[-92.209063,42.933245],"type":"Point"}
}