{
  "type": "Feature",
  "properties": {
    "iso:country":"US",
    "sg:address":"3098 28th Ave",
    "sg:city":"Marion",
    "sg:classifiers":[
        {
            "category":"Insurance",
            "subcategory":"Insurance Agent",
            "type":"Services"
        }
    ],
    "sg:phone":"+1 319 373 2067",
    "sg:postcode":"52302",
    "sg:province":"IA",
    "sg:tags":[
        "adjuster"
    ],
    "wof:name":"Heartland Claimcare",
    "wof:placetype":"venue"
},
  "geometry": {"coordinates":[-91.57927599999999,42.049659],"type":"Point"}
}