{
  "type": "Feature",
  "properties": {
    "addr:full":"2554 Dillon Rd Marshalltown IA 50158",
    "addr:housenumber":"2554",
    "addr:postcode":"50158",
    "addr:street":"Dillon Rd",
    "iso:country":"US",
    "sg:address":"2554 Dillon Rd",
    "sg:city":"Marshalltown",
    "sg:phone":"+1 641 479 2632",
    "sg:postcode":"50158",
    "sg:province":"IA",
    "sg:tags":[
        "farm",
        "corn",
        "soybean"
    ],
    "wof:name":"Craig Jacobson",
    "wof:placetype":"venue"
},
  "geometry": {"coordinates":[-92.82386099999999,41.984383],"type":"Point"}
}