{
  "type": "Feature",
  "properties": {
    "iso:country":"US",
    "sg:address":"607 Highland St",
    "sg:city":"Walnut",
    "sg:classifiers":[
        {
            "category":"Organizations",
            "subcategory":"Professional Association",
            "type":"Services"
        }
    ],
    "sg:phone":"+1 712 784 2100",
    "sg:postcode":"51577",
    "sg:province":"IA",
    "sg:tags":[
        "chambers",
        "commerce"
    ],
    "wof:name":"Walnut Chamber Of Commerce",
    "wof:placetype":"venue"
},
  "geometry": {"coordinates":[-95.22206199999999,41.477141],"type":"Point"}
}