{
  "type": "Feature",
  "properties": {
    "iso:country":"US",
    "sg:address":"2850 S Saint Marys St",
    "sg:city":"Sioux City",
    "sg:classifiers":[
        {
            "category":"Professional",
            "subcategory":"Computer Services",
            "type":"Services"
        }
    ],
    "sg:phone":"+1 712 276 2080",
    "sg:postcode":"51106",
    "sg:province":"SD",
    "sg:tags":[
        "home",
        "consulting",
        "page",
        "dev",
        "internet"
    ],
    "sg:website":"www.tripleorbit.com",
    "wof:name":"Triple Orbit Web Development",
    "wof:placetype":"venue"
},
  "geometry": {"coordinates":[-96.359151,42.458871],"type":"Point"}
}