{
  "type": "Feature",
  "properties": {
    "iso:country":"US",
    "sg:address":"405 8th St",
    "sg:city":"Sheldon",
    "sg:classifiers":[
        {
            "category":"Manufacturing",
            "subcategory":"Tools & Machinery",
            "type":"Manufacturing & Wholesale Goods"
        }
    ],
    "sg:phone":"+1 712 324 3404",
    "sg:postcode":"51201",
    "sg:province":"IA",
    "sg:tags":[
        "system",
        "refuse",
        "local",
        "industry",
        "mfg"
    ],
    "wof:name":"De Kruif Disposal",
    "wof:placetype":"venue"
},
  "geometry": {"coordinates":[-95.853021,43.181717],"type":"Point"}
}