{
  "type": "Feature",
  "properties": {
    "iso:country":"US",
    "sg:address":"120 Jackson St",
    "sg:city":"Brooklyn",
    "sg:classifiers":[
        {
            "category":"Shopping",
            "subcategory":"Pharmacy",
            "type":"Retail Goods"
        }
    ],
    "sg:phone":"+1 641 522 7813",
    "sg:postcode":"52211",
    "sg:province":"IA",
    "wof:name":"Village Pharmacy",
    "wof:placetype":"venue"
},
  "geometry": {"coordinates":[-92.44551,41.72967],"type":"Point"}
}