{
  "type": "Feature",
  "properties": {
    "iso:country":"US",
    "sg:address":"2385 70th St",
    "sg:city":"Van Horne",
    "sg:phone":"+1 319 223 6100",
    "sg:postcode":"52346",
    "sg:province":"IA",
    "sg:tags":[
        "farm",
        "corn",
        "soybean"
    ],
    "wof:name":"Duane Rinderknecht",
    "wof:placetype":"venue"
},
  "geometry": {"coordinates":[-92.03643599999999,42.0072],"type":"Point"}
}