{
  "type": "Feature",
  "properties": {
    "addr:full":"1111 80th St NW Cedar Rapids IA 52405",
    "addr:housenumber":"1111",
    "addr:postcode":"52405",
    "addr:street":"80Th St Nw",
    "iso:country":"US",
    "sg:address":"1111 80th St NW",
    "sg:city":"Cedar Rapids",
    "sg:classifiers":[
        {
            "category":"Building & Trades",
            "subcategory":"Landscaping Services",
            "type":"Services"
        }
    ],
    "sg:phone":"+1 319 396 5296",
    "sg:postcode":"52405",
    "sg:province":"IA",
    "sg:tags":[
        "tree"
    ],
    "wof:name":"Breeden Tree Svc",
    "wof:placetype":"venue"
},
  "geometry": {"coordinates":[-91.774507,41.985353],"type":"Point"}
}