{
  "type": "Feature",
  "properties": {
    "addr:full":"5001 N Brady St Davenport IA 52806",
    "addr:housenumber":"5001",
    "addr:postcode":"52806",
    "addr:street":"N Brady St",
    "iso:country":"US",
    "sg:address":"5001 N Brady St",
    "sg:city":"Davenport",
    "sg:classifiers":[
        {
            "category":"Retail",
            "subcategory":"Animal Services",
            "type":"Services"
        }
    ],
    "sg:phone":"+1 563 391 1729",
    "sg:postcode":"52806",
    "sg:province":"IA",
    "sg:tags":[
        "training",
        "dog"
    ],
    "wof:name":"Contented Canines",
    "wof:placetype":"venue"
},
  "geometry": {"coordinates":[-90.568822,41.571452],"type":"Point"}
}