{
  "type": "Feature",
  "properties": {
    "iso:country":"US",
    "sg:address":"27 Central Ave SW",
    "sg:city":"Le Mars",
    "sg:classifiers":[
        {
            "category":"Health Services",
            "subcategory":"Doctor",
            "type":"Services"
        }
    ],
    "sg:phone":"+1 712 546 4417",
    "sg:postcode":"51031",
    "sg:province":"IA",
    "sg:tags":[
        "dentist"
    ],
    "wof:name":"Dennis L Henrich DDS",
    "wof:placetype":"venue"
},
  "geometry": {"coordinates":[-96.16654,42.792738],"type":"Point"}
}