{
  "type": "Feature",
  "properties": {
    "iso:country":"US",
    "sg:address":"682 37th St",
    "sg:city":"Des Moines",
    "sg:classifiers":[
        {
            "category":"Real Estate",
            "subcategory":"Real Estate Agent",
            "type":"Services"
        }
    ],
    "sg:phone":"+1 515 279 9574",
    "sg:postcode":"50312",
    "sg:province":"IA",
    "sg:tags":[
        "appraiser"
    ],
    "wof:name":"Des Moines Real Estate Svc",
    "wof:placetype":"venue"
},
  "geometry": {"coordinates":[-93.66685200000001,41.590957],"type":"Point"}
}