{
  "type": "Feature",
  "properties": {
    "addr:full":"613 N Edna St Lake City IA 51449",
    "addr:housenumber":"613",
    "addr:postcode":"51449",
    "addr:street":"N Edna St",
    "iso:country":"US",
    "sg:address":"613 N Edna St",
    "sg:city":"Lake City",
    "sg:classifiers":[
        {
            "category":"Personal",
            "subcategory":"Beauty Salon",
            "type":"Services"
        }
    ],
    "sg:phone":"+1 712 464 8616",
    "sg:postcode":"51449",
    "sg:province":"IA",
    "wof:name":"Total Outlook",
    "wof:placetype":"venue"
},
  "geometry": {"coordinates":[-94.72904,42.272676],"type":"Point"}
}