{
  "type": "Feature",
  "properties": {
    "addr:full":"105 E Jackson St Corydon IA 50060",
    "addr:housenumber":"105",
    "addr:postcode":"50060",
    "addr:street":"E Jackson St",
    "iso:country":"US",
    "sg:address":"105 E Jackson St",
    "sg:city":"Corydon",
    "sg:classifiers":[
        {
            "category":"Shopping",
            "subcategory":"Department Store",
            "type":"Retail Goods"
        }
    ],
    "sg:phone":"+1 641 872 1050",
    "sg:postcode":"50060",
    "sg:province":"IA",
    "wof:name":"Pamida",
    "wof:placetype":"venue"
},
  "geometry": {"coordinates":[-93.317262,40.758516],"type":"Point"}
}