{
  "type": "Feature",
  "properties": {
    "iso:country":"US",
    "sg:address":"3137 Maplewood Rd",
    "sg:city":"Ames",
    "sg:classifiers":[
        {
            "category":"Farming",
            "subcategory":"Farm",
            "type":"Manufacturing & Wholesale Goods"
        }
    ],
    "sg:phone":"+1 515 268 6706",
    "sg:postcode":"50014",
    "sg:province":"IA",
    "sg:tags":[
        "crop",
        "general"
    ],
    "wof:name":"Payne Family Farms Inc",
    "wof:placetype":"venue"
},
  "geometry": {"coordinates":[-93.654371,42.047942],"type":"Point"}
}