{
  "type": "Feature",
  "properties": {
    "iso:country":"US",
    "sg:address":"5515 Utica Ridge Rd",
    "sg:city":"Davenport",
    "sg:classifiers":[
        {
            "category":"Banks & Credit Unions",
            "subcategory":"Bank",
            "type":"Services"
        }
    ],
    "sg:phone":"+1 563 459 0100",
    "sg:postcode":"52807",
    "sg:province":"IA",
    "sg:website":"www.qcbt.com",
    "wof:name":"Quad City Bank & Trust",
    "wof:placetype":"venue"
},
  "geometry": {"coordinates":[-90.512641,41.577585],"type":"Point"}
}