{
  "type": "Feature",
  "properties": {
    "iso:country":"US",
    "sg:address":"5005 Blairs Forest Ct NE",
    "sg:city":"Cedar Rapids",
    "sg:classifiers":[
        {
            "category":"Professional",
            "subcategory":"Research",
            "type":"Services"
        }
    ],
    "sg:phone":"+1 319 363 6070",
    "sg:postcode":"52402",
    "sg:province":"IA",
    "sg:tags":[
        "market",
        "analysis"
    ],
    "wof:name":"Shopper's Hotline Inc",
    "wof:placetype":"venue"
},
  "geometry": {"coordinates":[-91.679001,42.03283],"type":"Point"}
}