{
  "type": "Feature",
  "properties": {
    "addr:full":"5517 N Towne Pl NE Cedar Rapids IA 52402",
    "addr:housenumber":"5517",
    "addr:postcode":"52402",
    "addr:street":"N Towne Pl Ne",
    "iso:country":"US",
    "sg:address":"5517 N Towne Pl NE",
    "sg:city":"Cedar Rapids",
    "sg:classifiers":[
        {
            "category":"Retail",
            "subcategory":"Animal Services",
            "type":"Services"
        }
    ],
    "sg:phone":"+1 319 378 9364",
    "sg:postcode":"52402",
    "sg:province":"IA",
    "sg:tags":[
        "pet"
    ],
    "wof:name":"Dog Zone Too the",
    "wof:placetype":"venue"
},
  "geometry": {"coordinates":[-91.659599,42.026299],"type":"Point"}
}