{
  "type": "Feature",
  "properties": {
    "iso:country":"US",
    "sg:address":"2505 Grand Ave",
    "sg:city":"Ames",
    "sg:classifiers":[
        {
            "category":"Personal",
            "subcategory":"Beauty Salon",
            "type":"Services"
        }
    ],
    "sg:phone":"+1 515 232 0413",
    "sg:postcode":"50010",
    "sg:province":"IA",
    "wof:name":"Finesse Spa Salon",
    "wof:placetype":"venue"
},
  "geometry": {"coordinates":[-93.620711,42.04844],"type":"Point"}
}