{
  "type": "Feature",
  "properties": {
    "iso:country":"US",
    "sg:address":"107 1st St NW",
    "sg:city":"Epworth",
    "sg:classifiers":[
        {
            "category":"Health Services",
            "subcategory":"Chiropractor",
            "type":"Services"
        }
    ],
    "sg:phone":"+1 563 876 3231",
    "sg:postcode":"52045",
    "sg:province":"IA",
    "wof:name":"Epworth Family Chiropractic",
    "wof:placetype":"venue"
},
  "geometry": {"coordinates":[-90.931878,42.446147],"type":"Point"}
}