{
  "type": "Feature",
  "properties": {
    "addr:full":"1125 E San Marnan Dr Waterloo IA 50702",
    "addr:housenumber":"1125",
    "addr:postcode":"50702",
    "addr:street":"E;Dr",
    "iso:country":"US",
    "sg:address":"1125 E San Marnan Dr",
    "sg:city":"Waterloo",
    "sg:classifiers":[
        {
            "category":"Home & Garden",
            "subcategory":"Building Materials",
            "type":"Retail Goods"
        }
    ],
    "sg:phone":"+1 319 234 1500",
    "sg:postcode":"50702",
    "sg:province":"IA",
    "sg:tags":[
        "center"
    ],
    "wof:name":"Menards",
    "wof:placetype":"venue"
},
  "geometry": {"coordinates":[-92.33287799999999,42.459283],"type":"Point"}
}