{
  "type": "Feature",
  "properties": {
    "iso:country":"US",
    "sg:address":"1100 Dace Ave",
    "sg:city":"Sioux City",
    "sg:classifiers":[
        {
            "category":"Wholesale",
            "subcategory":"Machinery & Supplies",
            "type":"Manufacturing & Wholesale Goods"
        }
    ],
    "sg:phone":"+1 712 258 6501",
    "sg:postcode":"51101",
    "sg:province":"IA",
    "sg:tags":[
        "bearing"
    ],
    "wof:name":"Standard Bearings",
    "wof:placetype":"venue"
},
  "geometry": {"coordinates":[-96.395111,42.488715],"type":"Point"}
}