{
  "type": "Feature",
  "properties": {
    "iso:country":"US",
    "sg:address":"5140 Rapid Creek Rd NE",
    "sg:city":"Iowa City",
    "sg:classifiers":[
        {
            "category":"Food & Beverages",
            "subcategory":"Candy",
            "type":"Retail Goods"
        }
    ],
    "sg:phone":"+1 319 643 5873",
    "sg:postcode":"52240",
    "sg:province":"IA",
    "wof:name":"Fae Ridge Farm",
    "wof:placetype":"venue"
},
  "geometry": {"coordinates":[-91.431792,41.715745],"type":"Point"}
}