{
  "type": "Feature",
  "properties": {
    "addr:full":"5140 Rapid Creek Rd NE Iowa City IA 52240",
    "addr:housenumber":"5140",
    "addr:postcode":"52240",
    "addr:street":"Rapid Creek Rd Ne",
    "iso:country":"US",
    "sg:address":"5140 Rapid Creek Rd NE",
    "sg:city":"Iowa City",
    "sg:classifiers":[
        {
            "category":"Food & Beverages",
            "subcategory":"Candy",
            "type":"Retail Goods"
        }
    ],
    "sg:phone":"+1 319 643 5873",
    "sg:postcode":"52240",
    "sg:province":"IA",
    "wof:name":"Fae Ridge Farm",
    "wof:placetype":"venue"
},
  "geometry": {"coordinates":[-91.431792,41.715745],"type":"Point"}
}