{
  "type": "Feature",
  "properties": {
    "iso:country":"US",
    "sg:address":"123 31st St SW",
    "sg:city":"Cedar Rapids",
    "sg:classifiers":[
        {
            "category":"Wholesale",
            "subcategory":"Electrical",
            "type":"Manufacturing & Wholesale Goods"
        }
    ],
    "sg:phone":"+1 319 286 9196",
    "sg:postcode":"52404",
    "sg:province":"IA",
    "sg:tags":[
        "telecommunication"
    ],
    "wof:name":"CRPSSST",
    "wof:placetype":"venue"
},
  "geometry": {"coordinates":[-91.711731,41.967213],"type":"Point"}
}