{
  "type": "Feature",
  "properties": {
    "iso:country":"US",
    "sg:address":"201 Lakeview Dr",
    "sg:city":"Ida Grove",
    "sg:classifiers":[
        {
            "category":"Professional",
            "type":"Services"
        }
    ],
    "sg:phone":"+1 712 364 4276",
    "sg:postcode":"51445",
    "sg:province":"IA",
    "wof:name":"Darin Schau",
    "wof:placetype":"venue"
},
  "geometry": {"coordinates":[-95.44781999999999,42.335755],"type":"Point"}
}