{
  "type": "Feature",
  "properties": {
    "addr:full":"2309 150th St New Sharon IA 50207",
    "addr:housenumber":"2309",
    "addr:postcode":"50207",
    "addr:street":"150Th St",
    "iso:country":"US",
    "sg:address":"2309 150th St",
    "sg:city":"New Sharon",
    "sg:classifiers":[
        {
            "category":"Farming",
            "subcategory":"Livestock Farm",
            "type":"Manufacturing & Wholesale Goods"
        }
    ],
    "sg:phone":"+1 641 637 2861",
    "sg:postcode":"50207",
    "sg:province":"IA",
    "sg:tags":[
        "hog",
        "or",
        "feedlot"
    ],
    "wof:name":"G & S Farms",
    "wof:placetype":"venue"
},
  "geometry": {"coordinates":[-92.61476500000001,41.437243],"type":"Point"}
}