{
  "type": "Feature",
  "properties": {
    "iso:country":"US",
    "sg:address":"120 SW 7th St",
    "sg:city":"Ogden",
    "sg:classifiers":[
        {
            "category":"Retail",
            "subcategory":"Repair Shop",
            "type":"Services"
        }
    ],
    "sg:phone":"+1 515 275 3189",
    "sg:postcode":"50212",
    "sg:province":"IA",
    "sg:tags":[
        "welding"
    ],
    "wof:name":"Hiser Welding",
    "wof:placetype":"venue"
},
  "geometry": {"coordinates":[-94.036305,42.038533],"type":"Point"}
}