{
  "type": "Feature",
  "properties": {
    "iso:country":"US",
    "sg:address":"2102 SE Creekview Dr",
    "sg:city":"Ankeny",
    "sg:classifiers":[
        {
            "category":"Wholesale",
            "subcategory":"Auto Parts",
            "type":"Manufacturing & Wholesale Goods"
        }
    ],
    "sg:phone":"+1 515 965 1472",
    "sg:postcode":"50021",
    "sg:province":"IA",
    "wof:name":"Engine Parts Warehouse Inc",
    "wof:placetype":"venue"
},
  "geometry": {"coordinates":[-93.569163,41.709548],"type":"Point"}
}