{
  "type": "Feature",
  "properties": {
    "addr:full":"1814 Jefferson St Waterloo IA 50702",
    "addr:housenumber":"1814",
    "addr:postcode":"50702",
    "addr:street":"Jefferson St",
    "iso:country":"US",
    "sg:address":"1814 Jefferson St",
    "sg:city":"Waterloo",
    "sg:classifiers":[
        {
            "category":"Autos & Motor Vehicles",
            "subcategory":"Automobile Sales",
            "type":"Retail Goods"
        }
    ],
    "sg:phone":"+1 319 234 1030",
    "sg:postcode":"50702",
    "sg:province":"IA",
    "sg:tags":[
        "car",
        "dealer"
    ],
    "wof:name":"Champion Motors",
    "wof:placetype":"venue"
},
  "geometry": {"coordinates":[-92.327147,42.48537],"type":"Point"}
}