{
  "type": "Feature",
  "properties": {
    "iso:country":"US",
    "sg:address":"310 Main St",
    "sg:city":"Ames",
    "sg:classifiers":[
        {
            "category":"Shopping",
            "subcategory":"Clothing, Apparel, & Fashions",
            "type":"Retail Goods"
        }
    ],
    "sg:phone":"+1 515 233 1876",
    "sg:postcode":"50010",
    "sg:province":"IA",
    "wof:name":"Savvy Shopper Inc",
    "wof:placetype":"venue"
},
  "geometry": {"coordinates":[-93.61526499999999,42.025016],"type":"Point"}
}