{
  "type": "Feature",
  "properties": {
    "iso:country":"US",
    "sg:address":"1200 1st Ave E",
    "sg:city":"Spencer",
    "sg:classifiers":[
        {
            "category":"Health Services",
            "subcategory":"Nursing And Care Facility",
            "type":"Services"
        }
    ],
    "sg:phone":"+1 712 264 6365",
    "sg:postcode":"51301",
    "sg:province":"IA",
    "sg:tags":[
        "hospice"
    ],
    "wof:name":"Hospice Of Northwest Iowa",
    "wof:placetype":"venue"
},
  "geometry": {"coordinates":[-95.143924,43.150845],"type":"Point"}
}