{
  "type": "Feature",
  "properties": {
    "iso:country":"US",
    "sg:address":"507 2nd St",
    "sg:city":"Parkersburg",
    "sg:classifiers":[
        {
            "category":"Retail",
            "subcategory":"Funeral Services",
            "type":"Services"
        }
    ],
    "sg:phone":"+1 319 346 1534",
    "sg:postcode":"50665",
    "sg:province":"IA",
    "sg:tags":[
        "director"
    ],
    "wof:name":"Redman-Schwartz Funeral Homes",
    "wof:placetype":"venue"
},
  "geometry": {"coordinates":[-92.786086,42.575211],"type":"Point"}
}