{
  "type": "Feature",
  "properties": {
    "addr:full":"2162 E Kimberly Rd Davenport IA 52807",
    "addr:housenumber":"2162",
    "addr:postcode":"52807",
    "addr:street":"E Kimberly Rd",
    "iso:country":"US",
    "sg:address":"2162 E Kimberly Rd",
    "sg:city":"Davenport",
    "sg:classifiers":[
        {
            "category":"Banks & Credit Unions",
            "subcategory":"Bank",
            "type":"Services"
        }
    ],
    "sg:phone":"+1 563 359 7800",
    "sg:postcode":"52807",
    "sg:province":"IA",
    "sg:tags":[
        "cashing",
        "check"
    ],
    "wof:name":"Check 'n Go",
    "wof:placetype":"venue"
},
  "geometry": {"coordinates":[-90.54736800000001,41.557081],"type":"Point"}
}