{
  "type": "Feature",
  "properties": {
    "iso:country":"US",
    "sg:address":"2415 255th St",
    "sg:city":"Oskaloosa",
    "sg:classifiers":[
        {
            "category":"Personal",
            "type":"Services"
        }
    ],
    "sg:phone":"+1 641 672 1699",
    "sg:postcode":"52577",
    "sg:province":"IA",
    "wof:name":"Honey Do & More",
    "wof:placetype":"venue"
},
  "geometry": {"coordinates":[-92.60123900000001,41.285434],"type":"Point"}
}