{
  "type": "Feature",
  "properties": {
    "iso:country":"US",
    "sg:address":"1150 6th Ave",
    "sg:city":"Des Moines",
    "sg:classifiers":[
        {
            "category":"Social Services",
            "subcategory":"Child Care",
            "type":"Services"
        }
    ],
    "sg:phone":"+1 515 243 6232",
    "sg:postcode":"50314",
    "sg:province":"IA",
    "wof:name":"Mercy Child Development Ctr",
    "wof:placetype":"venue"
},
  "geometry": {"coordinates":[-93.62575,41.600014],"type":"Point"}
}