{
  "type": "Feature",
  "properties": {
    "iso:country":"US",
    "sg:address":"1100 2nd St NE",
    "sg:city":"Independence",
    "sg:classifiers":[
        {
            "category":"Personal",
            "type":"Services"
        }
    ],
    "sg:phone":"+1 319 334 2423",
    "sg:postcode":"50644",
    "sg:province":"IA",
    "wof:name":"Richard Woods",
    "wof:placetype":"venue"
},
  "geometry": {"coordinates":[-91.880044,42.469874],"type":"Point"}
}