{
  "type": "Feature",
  "properties": {
    "iso:country":"US",
    "sg:address":"2608 Shields Ave",
    "sg:city":"Sioux City",
    "sg:classifiers":[
        {
            "category":"Professional",
            "type":"Services"
        }
    ],
    "sg:phone":"+1 712 276 7662",
    "sg:postcode":"51106",
    "sg:province":"IA",
    "wof:name":"Midwest Millwright Svc",
    "wof:placetype":"venue"
},
  "geometry": {"coordinates":[-96.37598699999999,42.473494],"type":"Point"}
}