{
  "type": "Feature",
  "properties": {
    "iso:country":"US",
    "sg:address":"2175 C Ave",
    "sg:city":"Shenandoah",
    "sg:classifiers":[
        {
            "category":"Wholesale",
            "subcategory":"Plants",
            "type":"Manufacturing & Wholesale Goods"
        }
    ],
    "sg:phone":"+1 712 246 4819",
    "sg:postcode":"51601",
    "sg:province":"IA",
    "sg:tags":[
        "nursery",
        "tree"
    ],
    "wof:name":"Mc Laren Nursery Sales Inc",
    "wof:placetype":"venue"
},
  "geometry": {"coordinates":[-95.327877,40.731696],"type":"Point"}
}