{
  "type": "Feature",
  "properties": {
    "addr:full":"3 N Frederick Ave Oelwein IA 50662",
    "addr:housenumber":"3",
    "addr:postcode":"50662",
    "addr:street":"N Frederick Ave",
    "iso:country":"US",
    "sg:address":"3 N Frederick Ave",
    "sg:city":"Oelwein",
    "sg:classifiers":[
        {
            "category":"Shopping",
            "type":"Retail Goods"
        }
    ],
    "sg:phone":"+1 319 283 1475",
    "sg:postcode":"50662",
    "sg:province":"IA",
    "sg:tags":[
        "craft",
        "gallery",
        "dealer"
    ],
    "wof:name":"Cupboard",
    "wof:placetype":"venue"
},
  "geometry": {"coordinates":[-91.913273,42.679254],"type":"Point"}
}