{
  "type": "Feature",
  "properties": {
    "addr:full":"807 S Fremont St Shenandoah IA 51601",
    "addr:housenumber":"807",
    "addr:postcode":"51601",
    "addr:street":"S Fremont St",
    "iso:country":"US",
    "sg:address":"807 S Fremont St",
    "sg:city":"Shenandoah",
    "sg:classifiers":[
        {
            "category":"Restaurant",
            "type":"Food & Drink"
        },
        {
            "category":"Food & Beverages",
            "subcategory":"Groceries & Convenience Stores",
            "type":"Retail Goods"
        }
    ],
    "sg:phone":"+1 712 246 1310",
    "sg:postcode":"51601",
    "sg:province":"IA",
    "sg:tags":[
        "pizza"
    ],
    "sg:website":"http://caseys.com",
    "wof:name":"Casey's General Store",
    "wof:placetype":"venue"
},
  "geometry": {"coordinates":[-95.38513,40.758304],"type":"Point"}
}