{
  "type": "Feature",
  "properties": {
    "addr:full":"2617 S Magnolia St Sioux City SD 51106",
    "addr:housenumber":"2617",
    "addr:postcode":"51106",
    "addr:street":"S Magnolia St",
    "iso:country":"US",
    "sg:address":"2617 S Magnolia St",
    "sg:city":"Sioux City",
    "sg:classifiers":[
        {
            "category":"Retail",
            "subcategory":"Repair Shop",
            "type":"Services"
        }
    ],
    "sg:phone":"+1 712 266 0624",
    "sg:postcode":"51106",
    "sg:province":"SD",
    "wof:name":"Bogue Repair",
    "wof:placetype":"venue"
},
  "geometry": {"coordinates":[-96.337208,42.4629],"type":"Point"}
}