{
  "type": "Feature",
  "properties": {
    "iso:country":"US",
    "sg:address":"1210 1st Ave",
    "sg:city":"Coralville",
    "sg:classifiers":[
        {
            "category":"Restaurant",
            "type":"Food & Drink"
        }
    ],
    "sg:phone":"+1 319 351 1551",
    "sg:postcode":"52241",
    "sg:province":"IA",
    "wof:name":"River City Beefstro Bar Grille",
    "wof:placetype":"venue"
},
  "geometry": {"coordinates":[-91.56646000000001,41.692181],"type":"Point"}
}