{
  "type": "Feature",
  "properties": {
    "iso:country":"US",
    "sg:address":"3320 220th St",
    "sg:city":"De Witt",
    "sg:classifiers":[
        {
            "category":"Farming",
            "subcategory":"Farm",
            "type":"Manufacturing & Wholesale Goods"
        }
    ],
    "sg:phone":"+1 563 659 5982",
    "sg:postcode":"52742",
    "sg:province":"IA",
    "sg:tags":[
        "crop",
        "general"
    ],
    "wof:name":"James and Gala Reed",
    "wof:placetype":"venue"
},
  "geometry": {"coordinates":[-90.44243299999999,41.85901],"type":"Point"}
}