{
  "type": "Feature",
  "properties": {
    "iso:country":"US",
    "sg:address":"1418 Thayer Ave",
    "sg:city":"Wilton",
    "sg:phone":"+1 563 732 2131",
    "sg:postcode":"52778",
    "sg:province":"IA",
    "sg:tags":[
        "farm",
        "corn",
        "soybean"
    ],
    "wof:name":"Melvin Bohnsack",
    "wof:placetype":"venue"
},
  "geometry": {"coordinates":[-90.97737600000001,41.551719],"type":"Point"}
}