{
  "type": "Feature",
  "properties": {
    "iso:country":"US",
    "sg:address":"1399 240th St",
    "sg:city":"Tipton",
    "sg:phone":"+1 563 886 2496",
    "sg:postcode":"52772",
    "sg:province":"IA",
    "sg:tags":[
        "farm",
        "corn",
        "soybean"
    ],
    "wof:name":"Dave Urmie",
    "wof:placetype":"venue"
},
  "geometry": {"coordinates":[-91.094708,41.742757],"type":"Point"}
}