{
  "type": "Feature",
  "properties": {
    "iso:country":"US",
    "sg:address":"2230 Jersey Ridge Rd",
    "sg:city":"Davenport",
    "sg:classifiers":[
        {
            "category":"Health Services",
            "subcategory":"Chiropractor",
            "type":"Services"
        }
    ],
    "sg:phone":"+1 563 884 8093",
    "sg:postcode":"52803",
    "sg:province":"IA",
    "wof:name":"Jersey Ridge Chiropractic",
    "wof:placetype":"venue"
},
  "geometry": {"coordinates":[-90.541887,41.541744],"type":"Point"}
}