{
  "type": "Feature",
  "properties": {
    "iso:country":"US",
    "sg:address":"129 Central Ave NW",
    "sg:city":"Le Mars",
    "sg:classifiers":[
        {
            "category":"Retail",
            "subcategory":"Self-service Laundry",
            "type":"Services"
        }
    ],
    "sg:phone":"+1 712 546 5925",
    "sg:postcode":"51031",
    "sg:province":"IA",
    "sg:tags":[
        "coin"
    ],
    "wof:name":"Lemars Laundromat",
    "wof:placetype":"venue"
},
  "geometry": {"coordinates":[-96.16654200000001,42.795147],"type":"Point"}
}