{
  "type": "Feature",
  "properties": {
    "iso:country":"US",
    "sg:address":"5870 Merle Hay Rd",
    "sg:city":"Johnston",
    "sg:classifiers":[
        {
            "category":"Recreation",
            "type":"Entertainment"
        }
    ],
    "sg:phone":"+1 515 270 6777",
    "sg:postcode":"50131",
    "sg:province":"IA",
    "sg:tags":[
        "martial",
        "arts",
        "instruction"
    ],
    "wof:name":"Central Iowa Martial Arts",
    "wof:placetype":"venue"
},
  "geometry": {"coordinates":[-93.697738,41.666656],"type":"Point"}
}