{
  "type": "Feature",
  "properties": {
    "addr:full":"1391 Circle Dr Brooklyn IA 52211",
    "addr:housenumber":"1391",
    "addr:postcode":"52211",
    "addr:street":"Circle Dr",
    "iso:country":"US",
    "sg:address":"1391 Circle Dr",
    "sg:city":"Brooklyn",
    "sg:classifiers":[
        {
            "category":"Building & Trades",
            "subcategory":"Construction",
            "type":"Services"
        }
    ],
    "sg:phone":"+1 641 522 4775",
    "sg:postcode":"52211",
    "sg:province":"IA",
    "sg:tags":[
        "concrete",
        "contractor"
    ],
    "wof:name":"Kevin Irwin Construction",
    "wof:placetype":"venue"
},
  "geometry": {"coordinates":[-92.44415600000001,41.810724],"type":"Point"}
}