{
  "type": "Feature",
  "properties": {
    "addr:full":"640 Arbutus Ave Evansdale IA 50707",
    "addr:housenumber":"640",
    "addr:postcode":"50707",
    "addr:street":"Arbutus Ave",
    "iso:country":"US",
    "sg:address":"640 Arbutus Ave",
    "sg:city":"Evansdale",
    "sg:classifiers":[
        {
            "category":"Professional",
            "type":"Services"
        }
    ],
    "sg:phone":"+1 319 287 3899",
    "sg:postcode":"50707",
    "sg:province":"IA",
    "sg:tags":[
        "establishment"
    ],
    "wof:name":"Arbutus Lift Station-Evansdale",
    "wof:placetype":"venue"
},
  "geometry": {"coordinates":[-92.28484899999999,42.461461],"type":"Point"}
}