{
  "type": "Feature",
  "properties": {
    "addr:full":"325 W 1st St Dubuque IA 52001",
    "addr:housenumber":"325",
    "addr:postcode":"52001",
    "addr:street":"W 1St St",
    "iso:country":"US",
    "sg:address":"325 W 1st St",
    "sg:city":"Dubuque",
    "sg:classifiers":[
        {
            "category":"Banks & Credit Unions",
            "subcategory":"Investment Brokerage",
            "type":"Services"
        }
    ],
    "sg:phone":"+1 563 582 4865",
    "sg:postcode":"52001",
    "sg:province":"IA",
    "sg:tags":[
        "security"
    ],
    "wof:name":"Heartland Investment Assoc",
    "wof:placetype":"venue"
},
  "geometry": {"coordinates":[-90.666026,42.494535],"type":"Point"}
}