{
  "type": "Feature",
  "properties": {
    "addr:full":"3530 Jersey Ridge Rd Davenport IA 52807",
    "addr:housenumber":"3530",
    "addr:postcode":"52807",
    "addr:street":"Jersey Ridge Rd",
    "iso:country":"US",
    "sg:address":"3530 Jersey Ridge Rd",
    "sg:city":"Davenport",
    "sg:classifiers":[
        {
            "category":"Health Services",
            "subcategory":"Doctor",
            "type":"Services"
        }
    ],
    "sg:phone":"+1 563 344 4848",
    "sg:postcode":"52807",
    "sg:province":"IA",
    "sg:tags":[
        "dentist"
    ],
    "wof:name":"Stephanie K Rudish DDS",
    "wof:placetype":"venue"
},
  "geometry": {"coordinates":[-90.54176200000001,41.555895],"type":"Point"}
}