{
  "type": "Feature",
  "properties": {
    "addr:full":"2840 7th Ave Marion IA 52302",
    "addr:housenumber":"2840",
    "addr:postcode":"52302",
    "addr:street":"7Th Ave",
    "iso:country":"US",
    "sg:address":"2840 7th Ave",
    "sg:city":"Marion",
    "sg:classifiers":[
        {
            "category":"Professional",
            "subcategory":"Accounting & Tax Preparation",
            "type":"Services"
        }
    ],
    "sg:phone":"+1 319 377 5794",
    "sg:postcode":"52302",
    "sg:province":"IA",
    "sg:tags":[
        "return",
        "filing"
    ],
    "wof:name":"H & R Block Tax Svc",
    "wof:placetype":"venue"
},
  "geometry": {"coordinates":[-91.581737,42.033307],"type":"Point"}
}