{
  "type": "Feature",
  "properties": {
    "iso:country":"US",
    "sg:address":"5880 Merle Hay Rd",
    "sg:city":"Johnston",
    "sg:classifiers":[
        {
            "category":"Banks & Credit Unions",
            "subcategory":"Bank",
            "type":"Services"
        }
    ],
    "sg:phone":"+1 515 237 5388",
    "sg:postcode":"50131",
    "sg:province":"IA",
    "wof:name":"Wells Fargo Bank",
    "wof:placetype":"venue"
},
  "geometry": {"coordinates":[-93.697738,41.666529],"type":"Point"}
}