{
  "type": "Feature",
  "properties": {
    "iso:country":"US",
    "sg:address":"602 E 1st St",
    "sg:city":"Des Moines",
    "sg:classifiers":[
        {
            "category":"Government",
            "subcategory":"Office",
            "type":"Public Place"
        }
    ],
    "sg:phone":"+1 515 283 4997",
    "sg:postcode":"50309",
    "sg:province":"IA",
    "sg:tags":[
        "village"
    ],
    "wof:name":"Neighbor Inspection Div",
    "wof:placetype":"venue"
},
  "geometry": {"coordinates":[-93.61671699999999,41.590124],"type":"Point"}
}