{
  "type": "Feature",
  "properties": {
    "iso:country":"US",
    "sg:address":"117 3rd St SE",
    "sg:city":"Dyersville",
    "sg:classifiers":[
        {
            "category":"Real Estate",
            "subcategory":"Real Estate Agent",
            "type":"Services"
        }
    ],
    "sg:phone":"+1 563 875 9238",
    "sg:postcode":"52040",
    "sg:province":"IA",
    "sg:website":"www.gassmannrealty.com",
    "wof:name":"Gassmann Realty",
    "wof:placetype":"venue"
},
  "geometry": {"coordinates":[-91.121461,42.484486],"type":"Point"}
}