{
  "type": "Feature",
  "properties": {
    "iso:country":"US",
    "sg:address":"905 Seneca St",
    "sg:city":"Webster City",
    "sg:classifiers":[
        {
            "category":"Professional",
            "subcategory":"Management & Consulting",
            "type":"Services"
        }
    ],
    "sg:phone":"+1 515 832 2274",
    "sg:postcode":"50595",
    "sg:province":"IA",
    "sg:tags":[
        "consultant",
        "safety"
    ],
    "wof:name":"GST Svc",
    "wof:placetype":"venue"
},
  "geometry": {"coordinates":[-93.817199,42.467333],"type":"Point"}
}