{
  "type": "Feature",
  "properties": {
    "iso:country":"US",
    "sg:address":"201 E 5th St",
    "sg:city":"Malvern",
    "sg:classifiers":[
        {
            "category":"Organizations",
            "subcategory":"Religious Organization",
            "type":"Services"
        }
    ],
    "sg:phone":"+1 712 624 8320",
    "sg:postcode":"51551",
    "sg:province":"IA",
    "sg:tags":[
        "church"
    ],
    "wof:name":"United Methodist Church",
    "wof:placetype":"venue"
},
  "geometry": {"coordinates":[-95.58240000000001,41.003344],"type":"Point"}
}