{
  "type": "Feature",
  "properties": {
    "iso:country":"US",
    "sg:address":"1012 Grand Ave",
    "sg:city":"West Des Moines",
    "sg:classifiers":[
        {
            "category":"Professional",
            "subcategory":"Lawyer & Legal Services",
            "type":"Services"
        }
    ],
    "sg:phone":"+1 515 225 6512",
    "sg:postcode":"50265",
    "sg:province":"IA",
    "sg:tags":[
        "attorney"
    ],
    "wof:name":"K L Smith Law Offices",
    "wof:placetype":"venue"
},
  "geometry": {"coordinates":[-93.717005,41.582015],"type":"Point"}
}