{
  "type": "Feature",
  "properties": {
    "iso:country":"US",
    "sg:address":"30 Oak Dr",
    "sg:city":"Mason City",
    "sg:classifiers":[
        {
            "category":"Food & Beverages",
            "subcategory":"Specialty",
            "type":"Retail Goods"
        }
    ],
    "sg:phone":"+1 641 424 2265",
    "sg:postcode":"50401",
    "sg:province":"IA",
    "sg:tags":[
        "miscellaneous"
    ],
    "wof:name":"Herbalife Distributor",
    "wof:placetype":"venue"
},
  "geometry": {"coordinates":[-93.21424500000001,43.151676],"type":"Point"}
}