{
  "type": "Feature",
  "properties": {
    "iso:country":"US",
    "sg:address":"1505 Oasis Ave",
    "sg:city":"Winfield",
    "sg:classifiers":[
        {
            "category":"Farming",
            "subcategory":"Farm",
            "type":"Manufacturing & Wholesale Goods"
        }
    ],
    "sg:phone":"+1 319 257 3171",
    "sg:postcode":"52659",
    "sg:province":"IA",
    "sg:tags":[
        "crop",
        "general"
    ],
    "wof:name":"Wedor Farms Inc",
    "wof:placetype":"venue"
},
  "geometry": {"coordinates":[-91.43808,41.088857],"type":"Point"}
}