{
  "type": "Feature",
  "properties": {
    "iso:country":"US",
    "sg:address":"2485 270th St",
    "sg:city":"Adel",
    "sg:classifiers":[
        {
            "category":"Professional",
            "subcategory":"Computer Services",
            "type":"Services"
        }
    ],
    "sg:phone":"+1 515 992 4374",
    "sg:postcode":"50003",
    "sg:province":"IA",
    "sg:tags":[
        "datum"
    ],
    "wof:name":"Kevin Wichtendahl",
    "wof:placetype":"venue"
},
  "geometry": {"coordinates":[-93.98976399999999,41.643834],"type":"Point"}
}