{
  "type": "Feature",
  "properties": {
    "iso:country":"US",
    "sg:address":"1206 100th Ave",
    "sg:city":"Bode",
    "sg:classifiers":[
        {
            "category":"Farming",
            "subcategory":"Farm",
            "type":"Manufacturing & Wholesale Goods"
        }
    ],
    "sg:phone":"+1 515 379 1832",
    "sg:postcode":"50519",
    "sg:province":"IA",
    "sg:tags":[
        "crop",
        "general"
    ],
    "wof:name":"Thilges Brothers",
    "wof:placetype":"venue"
},
  "geometry": {"coordinates":[-94.266403,42.940461],"type":"Point"}
}