{
  "type": "Feature",
  "properties": {
    "iso:country":"US",
    "sg:address":"101 W Pine St",
    "sg:city":"Hillsboro",
    "sg:classifiers":[
        {
            "category":"Building & Trades",
            "subcategory":"Construction",
            "type":"Services"
        }
    ],
    "sg:phone":"+1 319 253 5203",
    "sg:postcode":"52630",
    "sg:province":"IA",
    "sg:tags":[
        "marking",
        "maintenance",
        "parking"
    ],
    "wof:name":"V & A Striping",
    "wof:placetype":"venue"
},
  "geometry": {"coordinates":[-91.716329,40.83728],"type":"Point"}
}