{
  "type": "Feature",
  "properties": {
    "addr:full":"108 Washington St Decorah IA 52101",
    "addr:housenumber":"108",
    "addr:postcode":"52101",
    "addr:street":"Washington St",
    "iso:country":"US",
    "sg:address":"108 Washington St",
    "sg:city":"Decorah",
    "sg:classifiers":[
        {
            "category":"Manufacturing",
            "subcategory":"Printing",
            "type":"Manufacturing & Wholesale Goods"
        }
    ],
    "sg:phone":"+1 563 382 4295",
    "sg:postcode":"52101",
    "sg:province":"IA",
    "sg:tags":[
        "commercial"
    ],
    "sg:website":"www.anundsenpubl.com",
    "wof:name":"Anundsen Publishing Co",
    "wof:placetype":"venue"
},
  "geometry": {"coordinates":[-91.78586199999999,43.304096],"type":"Point"}
}