{
  "type": "Feature",
  "properties": {
    "iso:country":"US",
    "sg:address":"204 US Hwy 69",
    "sg:city":"Huxley",
    "sg:classifiers":[
        {
            "category":"Personal",
            "subcategory":"Beauty Salon",
            "type":"Services"
        }
    ],
    "sg:phone":"+1 515 597 4040",
    "sg:postcode":"50124",
    "sg:province":"IA",
    "wof:name":"A Sharp Image",
    "wof:placetype":"venue"
},
  "geometry": {"coordinates":[-93.60053499999999,41.893712],"type":"Point"}
}