{
  "type": "Feature",
  "properties": {
    "addr:full":"301 W Main St Lamoni IA 50140",
    "addr:housenumber":"301",
    "addr:postcode":"50140",
    "addr:street":"W Main St",
    "iso:country":"US",
    "sg:address":"301 W Main St",
    "sg:city":"Lamoni",
    "sg:classifiers":[
        {
            "category":"Education",
            "subcategory":"Library",
            "type":"Public Place"
        }
    ],
    "sg:phone":"+1 641 784 6686",
    "sg:postcode":"50140",
    "sg:province":"IA",
    "wof:name":"Lamoni Public Library",
    "wof:placetype":"venue"
},
  "geometry": {"coordinates":[-93.936722,40.623669],"type":"Point"}
}