{
  "type": "Feature",
  "properties": {
    "addr:full":"13465 Hartman Rd Zwingle IA 52079",
    "addr:postcode":"13465;52079",
    "addr:street":"Hartman Rd",
    "iso:country":"US",
    "sg:address":"13465 Hartman Rd",
    "sg:city":"Zwingle",
    "sg:classifiers":[
        {
            "category":"Farming",
            "subcategory":"Livestock Farm",
            "type":"Manufacturing & Wholesale Goods"
        }
    ],
    "sg:phone":"+1 563 557 8157",
    "sg:postcode":"52079",
    "sg:province":"IA",
    "sg:tags":[
        "beef",
        "feedlot",
        "cattle"
    ],
    "wof:name":"Kringle John",
    "wof:placetype":"venue"
},
  "geometry": {"coordinates":[-90.753381,42.340145],"type":"Point"}
}