{
  "type": "Feature",
  "properties": {
    "iso:country":"US",
    "sg:address":"4236 Hickory Ln",
    "sg:city":"Sioux City",
    "sg:classifiers":[
        {
            "category":"Real Estate",
            "subcategory":"Real Estate Operator",
            "type":"Services"
        }
    ],
    "sg:phone":"+1 712 266 8492",
    "sg:postcode":"51106",
    "sg:province":"SD",
    "sg:tags":[
        "apartment"
    ],
    "wof:name":"Shire Apts",
    "wof:placetype":"venue"
},
  "geometry": {"coordinates":[-96.355128,42.445186],"type":"Point"}
}