{
  "type": "Feature",
  "properties": {
    "addr:full":"3501 W Broadway Council Bluffs IA 51501",
    "addr:housenumber":"3501",
    "addr:postcode":"51501",
    "addr:street":"W Broadway",
    "iso:country":"US",
    "sg:address":"3501 W Broadway",
    "sg:city":"Council Bluffs",
    "sg:classifiers":[
        {
            "category":"Food & Beverages",
            "subcategory":"Groceries & Convenience Stores",
            "type":"Retail Goods"
        }
    ],
    "sg:phone":"+1 712 322 2268",
    "sg:postcode":"51501",
    "sg:province":"IA",
    "sg:website":"www.buckysexpress.com",
    "wof:name":"Bucky's Express",
    "wof:placetype":"venue"
},
  "geometry": {"coordinates":[-95.902027,41.261793],"type":"Point"}
}