{
  "type": "Feature",
  "properties": {
    "iso:country":"US",
    "sg:address":"980 Main St",
    "sg:city":"Dubuque",
    "sg:classifiers":[
        {
            "category":"Shopping",
            "subcategory":"Clothing, Apparel, & Fashions",
            "type":"Retail Goods"
        }
    ],
    "sg:phone":"+1 563 582 6930",
    "sg:postcode":"52001",
    "sg:province":"IA",
    "sg:tags":[
        "shop",
        "bridal"
    ],
    "wof:name":"Cheryl-Ann Bridals",
    "wof:placetype":"venue"
},
  "geometry": {"coordinates":[-90.667655,42.501834],"type":"Point"}
}