{
  "type": "Feature",
  "properties": {
    "iso:country":"US",
    "sg:address":"3813 Utica Ridge Rd",
    "sg:city":"Bettendorf",
    "sg:classifiers":[
        {
            "category":"Professional",
            "subcategory":"Business Services",
            "type":"Services"
        }
    ],
    "sg:phone":"+1 563 355 0496",
    "sg:postcode":"52722",
    "sg:province":"IA",
    "sg:tags":[
        "engraving"
    ],
    "wof:name":"Gemco Engraving Co",
    "wof:placetype":"venue"
},
  "geometry": {"coordinates":[-90.517303,41.560894],"type":"Point"}
}