{
  "type": "Feature",
  "properties": {
    "addr:full":"1201 1st Ave SE Cedar Rapids IA 52402",
    "addr:housenumber":"1201",
    "addr:postcode":"52402",
    "addr:street":"1St Ave Se",
    "iso:country":"US",
    "sg:address":"1201 1st Ave SE",
    "sg:city":"Cedar Rapids",
    "sg:classifiers":[
        {
            "category":"Food & Beverages",
            "subcategory":"Groceries & Convenience Stores",
            "type":"Retail Goods"
        }
    ],
    "sg:phone":"+1 319 362 6436",
    "sg:postcode":"52402",
    "sg:province":"IA",
    "sg:website":"www.caseys.com",
    "wof:name":"Casey's General Store",
    "wof:placetype":"venue"
},
  "geometry": {"coordinates":[-91.657701,41.98482],"type":"Point"}
}