{
  "type": "Feature",
  "properties": {
    "addr:full":"410 W Main St Manchester IA 52057",
    "addr:housenumber":"410",
    "addr:postcode":"52057",
    "addr:street":"W Main St",
    "iso:country":"US",
    "sg:address":"410 W Main St",
    "sg:city":"Manchester",
    "sg:classifiers":[
        {
            "category":"Retail",
            "subcategory":"Auto Repair",
            "type":"Services"
        }
    ],
    "sg:phone":"+1 563 927 4013",
    "sg:postcode":"52057",
    "sg:province":"IA",
    "sg:tags":[
        "wheel",
        "axle",
        "alignment"
    ],
    "wof:name":"Hosek's Service Ctr",
    "wof:placetype":"venue"
},
  "geometry": {"coordinates":[-91.462147,42.483853],"type":"Point"}
}