{
  "type": "Feature",
  "properties": {
    "addr:full":"6603 201st St Albia IA 52531",
    "addr:housenumber":"6603",
    "addr:postcode":"52531",
    "addr:street":"201St St",
    "iso:country":"US",
    "sg:address":"6603 201st St",
    "sg:city":"Albia",
    "sg:classifiers":[
        {
            "category":"Retail",
            "subcategory":"Auto Repair",
            "type":"Services"
        }
    ],
    "sg:phone":"+1 641 932 3060",
    "sg:postcode":"52531",
    "sg:province":"IA",
    "sg:tags":[
        "body",
        "automobile",
        "painting"
    ],
    "wof:name":"3-D Paint & Body",
    "wof:placetype":"venue"
},
  "geometry": {"coordinates":[-92.774264,41.002701],"type":"Point"}
}