{
  "type": "Feature",
  "properties": {
    "iso:country":"US",
    "sg:address":"2644 Perkins Rd",
    "sg:city":"Danville",
    "sg:classifiers":[
        {
            "category":"Education",
            "subcategory":"Special Training",
            "type":"Public Place"
        }
    ],
    "sg:phone":"+1 319 392 4894",
    "sg:postcode":"52623",
    "sg:province":"IA",
    "sg:tags":[
        "tutoring"
    ],
    "wof:name":"Clubz In Home Tutoring",
    "wof:placetype":"venue"
},
  "geometry": {"coordinates":[-91.401717,40.843257],"type":"Point"}
}