{
  "type": "Feature",
  "properties": {
    "iso:country":"US",
    "sg:address":"2200 E Ovid Ave",
    "sg:city":"Des Moines",
    "sg:classifiers":[
        {
            "category":"Manufacturing",
            "subcategory":"Building Materials",
            "type":"Manufacturing & Wholesale Goods"
        }
    ],
    "sg:phone":"+1 515 265 4441",
    "sg:postcode":"50313",
    "sg:province":"IA",
    "sg:website":"www.dimensional-arts.com",
    "wof:name":"Architectural Arts",
    "wof:placetype":"venue"
},
  "geometry": {"coordinates":[-93.578732,41.626025],"type":"Point"}
}