{
  "type": "Feature",
  "properties": {
    "iso:country":"US",
    "sg:address":"13668 Surrey Ln",
    "sg:city":"Dubuque",
    "sg:classifiers":[
        {
            "category":"Real Estate",
            "subcategory":"Real Estate Agent",
            "type":"Services"
        }
    ],
    "sg:phone":"+1 563 556 1421",
    "sg:postcode":"52002",
    "sg:province":"IA",
    "sg:tags":[
        "investment"
    ],
    "wof:name":"Herrig Realty",
    "wof:placetype":"venue"
},
  "geometry": {"coordinates":[-90.754794,42.535945],"type":"Point"}
}