{
  "type": "Feature",
  "properties": {
    "addr:full":"108 S Main St Schaller IA 51053",
    "addr:housenumber":"108",
    "addr:postcode":"51053",
    "addr:street":"S Main St",
    "iso:country":"US",
    "sg:address":"108 S Main St",
    "sg:city":"Schaller",
    "sg:classifiers":[
        {
            "category":"Restaurant",
            "type":"Food & Drink"
        }
    ],
    "sg:phone":"+1 712 275 4596",
    "sg:postcode":"51053",
    "sg:province":"IA",
    "wof:name":"Sidelines Inc",
    "wof:placetype":"venue"
},
  "geometry": {"coordinates":[-95.293513,42.500418],"type":"Point"}
}