{
  "type": "Feature",
  "properties": {
    "iso:country":"US",
    "sg:address":"405 W Division St",
    "sg:city":"Anthon",
    "sg:phone":"+1 712 373 5192",
    "sg:postcode":"51004",
    "sg:province":"IA",
    "sg:tags":[
        "farm",
        "field",
        "crop"
    ],
    "wof:name":"Wallace W Parker",
    "wof:placetype":"venue"
},
  "geometry": {"coordinates":[-95.871353,42.385561],"type":"Point"}
}