{
  "type": "Feature",
  "properties": {
    "iso:country":"US",
    "sg:address":"1707 S Main St",
    "sg:city":"Fairfield",
    "sg:classifiers":[
        {
            "category":"Organizations",
            "subcategory":"Community Association",
            "type":"Services"
        }
    ],
    "sg:phone":"+1 641 472 2811",
    "sg:postcode":"52556",
    "sg:province":"IA",
    "sg:tags":[
        "fraternal"
    ],
    "wof:name":"Fraternal Order Of Eagles",
    "wof:placetype":"venue"
},
  "geometry": {"coordinates":[-91.96303,40.991795],"type":"Point"}
}