{
  "type": "Feature",
  "properties": {
    "addr:full":"103 N 5th St Bellevue IA 52031",
    "addr:housenumber":"103",
    "addr:postcode":"52031",
    "addr:street":"N 5Th St",
    "iso:country":"US",
    "sg:address":"103 N 5th St",
    "sg:city":"Bellevue",
    "sg:classifiers":[
        {
            "category":"Shopping",
            "subcategory":"Gifts & Souvenirs",
            "type":"Retail Goods"
        }
    ],
    "sg:phone":"+1 563 872 4133",
    "sg:postcode":"52031",
    "sg:province":"IA",
    "sg:tags":[
        "shop"
    ],
    "wof:name":"Tomorrows Keepsakes",
    "wof:placetype":"venue"
},
  "geometry": {"coordinates":[-90.42798999999999,42.258485],"type":"Point"}
}