{
  "type": "Feature",
  "properties": {
    "iso:country":"US",
    "sg:address":"6584 NE 14th St",
    "sg:city":"Des Moines",
    "sg:classifiers":[
        {
            "category":"Bars & Pubs",
            "type":"Food & Drink"
        }
    ],
    "sg:phone":"+1 515 289 2096",
    "sg:postcode":"50313",
    "sg:province":"IA",
    "wof:name":"Mary Go Round Lounge",
    "wof:placetype":"venue"
},
  "geometry": {"coordinates":[-93.600692,41.675856],"type":"Point"}
}