{
  "type": "Feature",
  "properties": {
    "iso:country":"US",
    "sg:address":"12 S 11th St",
    "sg:city":"Fort Dodge",
    "sg:classifiers":[
        {
            "category":"Shopping",
            "type":"Retail Goods"
        }
    ],
    "sg:phone":"+1 515 955 6223",
    "sg:postcode":"50501",
    "sg:province":"IA",
    "sg:tags":[
        "coin",
        "dealer",
        "supply"
    ],
    "wof:name":"Peters Coins",
    "wof:placetype":"venue"
},
  "geometry": {"coordinates":[-94.18349600000001,42.505526],"type":"Point"}
}