{
  "type": "Feature",
  "properties": {
    "iso:country":"US",
    "sg:address":"2325 Grande Ave SE",
    "sg:city":"Cedar Rapids",
    "sg:classifiers":[
        {
            "category":"Travel",
            "subcategory":"Hotels & Motels",
            "type":"Entertainment"
        }
    ],
    "sg:phone":"+1 319 363 5389",
    "sg:postcode":"52403",
    "sg:province":"IA",
    "sg:tags":[
        "breakfast",
        "accommodation",
        "bed"
    ],
    "wof:name":"Homestay",
    "wof:placetype":"venue"
},
  "geometry": {"coordinates":[-91.63278,41.986607],"type":"Point"}
}