{
  "type": "Feature",
  "properties": {
    "iso:country":"US",
    "sg:address":"3200 Ave C",
    "sg:city":"Council Bluffs",
    "sg:classifiers":[
        {
            "category":"Organizations",
            "subcategory":"Religious Organization",
            "type":"Services"
        }
    ],
    "sg:phone":"+1 712 322 8725",
    "sg:postcode":"51501",
    "sg:province":"IA",
    "sg:tags":[
        "church"
    ],
    "wof:name":"Dodge Memorial Church",
    "wof:placetype":"venue"
},
  "geometry": {"coordinates":[-95.89943100000001,41.264576],"type":"Point"}
}