{
  "type": "Feature",
  "properties": {
    "addr:full":"216 E 2nd St Muscatine IA 52761",
    "addr:housenumber":"216",
    "addr:postcode":"52761",
    "addr:street":"E 2Nd St",
    "iso:country":"US",
    "sg:address":"216 E 2nd St",
    "sg:city":"Muscatine",
    "sg:classifiers":[
        {
            "category":"Personal",
            "subcategory":"Massage",
            "type":"Services"
        },
        {
            "category":"Personal",
            "subcategory":"Beauty Salon",
            "type":"Services"
        }
    ],
    "sg:phone":"+1 563 262 3744",
    "sg:postcode":"52761",
    "sg:province":"IA",
    "wof:name":"Salon Incognito",
    "wof:placetype":"venue"
},
  "geometry": {"coordinates":[-91.04449700000001,41.422049],"type":"Point"}
}