{
  "type": "Feature",
  "properties": {
    "addr:full":"2522 E 38th St Davenport IA 52807",
    "addr:housenumber":"2522",
    "addr:postcode":"52807",
    "addr:street":"E 38Th St",
    "iso:country":"US",
    "sg:address":"2522 E 38th St",
    "sg:city":"Davenport",
    "sg:classifiers":[
        {
            "category":"Professional",
            "subcategory":"Management & Consulting",
            "type":"Services"
        }
    ],
    "sg:phone":"+1 563 359 7395",
    "sg:postcode":"52807",
    "sg:province":"IA",
    "wof:name":"Uscs Capitol Assets",
    "wof:placetype":"venue"
},
  "geometry": {"coordinates":[-90.538754,41.559065],"type":"Point"}
}