{
  "type": "Feature",
  "properties": {
    "addr:full":"1066 Center Point Rd NE Cedar Rapids IA 52402",
    "addr:housenumber":"1066",
    "addr:postcode":"52402",
    "addr:street":"Center Point Rd Ne",
    "iso:country":"US",
    "sg:address":"1066 Center Point Rd NE",
    "sg:city":"Cedar Rapids",
    "sg:classifiers":[
        {
            "category":"Shopping",
            "subcategory":"Antiques",
            "type":"Retail Goods"
        }
    ],
    "sg:phone":"+1 319 364 4919",
    "sg:postcode":"52402",
    "sg:province":"IA",
    "wof:name":"Home Again Antiques & Collectibles",
    "wof:placetype":"venue"
},
  "geometry": {"coordinates":[-91.66247300000001,41.998922],"type":"Point"}
}