{
  "type": "Feature",
  "properties": {
    "addr:full":"3445 Adventureland Dr Altoona IA 50009",
    "addr:housenumber":"3445",
    "addr:postcode":"50009",
    "addr:street":"Adventureland Dr",
    "iso:country":"US",
    "sg:address":"3445 Adventureland Dr",
    "sg:city":"Altoona",
    "sg:classifiers":[
        {
            "category":"Retail",
            "subcategory":"Auto Repair",
            "type":"Services"
        }
    ],
    "sg:phone":"+1 515 967 0355",
    "sg:postcode":"50009",
    "sg:province":"IA",
    "sg:tags":[
        "truck"
    ],
    "sg:website":"www.pbtruck.com",
    "wof:name":"Peterbilt Of Des Moines",
    "wof:placetype":"venue"
},
  "geometry": {"coordinates":[-93.50172999999999,41.658606],"type":"Point"}
}