{
  "type": "Feature",
  "properties": {
    "iso:country":"US",
    "sg:address":"1103 N Ave",
    "sg:city":"Milford",
    "sg:classifiers":[
        {
            "category":"Shopping",
            "subcategory":"Gifts & Souvenirs",
            "type":"Retail Goods"
        }
    ],
    "sg:phone":"+1 712 338 2094",
    "sg:postcode":"51351",
    "sg:province":"IA",
    "sg:tags":[
        "food"
    ],
    "wof:name":"Linda Aakhus",
    "wof:placetype":"venue"
},
  "geometry": {"coordinates":[-95.151465,43.327931],"type":"Point"}
}