{
  "type": "Feature",
  "properties": {
    "addr:full":"15653 Union Ave Clarksville IA 50619",
    "addr:housenumber":"15653",
    "addr:postcode":"50619",
    "addr:street":"Union Ave",
    "iso:country":"US",
    "sg:address":"15653 Union Ave",
    "sg:city":"Clarksville",
    "sg:classifiers":[
        {
            "category":"Real Estate",
            "subcategory":"Real Estate Operator",
            "type":"Services"
        }
    ],
    "sg:phone":"+1 319 276 3060",
    "sg:postcode":"50619",
    "sg:province":"IA",
    "sg:tags":[
        "property",
        "lessor"
    ],
    "wof:name":"Lyle Barnett",
    "wof:placetype":"venue"
},
  "geometry": {"coordinates":[-92.633583,42.821735],"type":"Point"}
}