{
  "type": "Feature",
  "properties": {
    "iso:country":"US",
    "sg:address":"1711 19th St",
    "sg:city":"West Des Moines",
    "sg:classifiers":[
        {
            "category":"Professional",
            "subcategory":"Management & Consulting",
            "type":"Services"
        }
    ],
    "sg:phone":"+1 515 221 2322",
    "sg:postcode":"50265",
    "sg:province":"IA",
    "sg:tags":[
        "party",
        "planning"
    ],
    "sg:website":"www.littleelfevents.com",
    "wof:name":"Little Elf",
    "wof:placetype":"venue"
},
  "geometry": {"coordinates":[-93.730417,41.594866],"type":"Point"}
}