{
  "type": "Feature",
  "properties": {
    "addr:full":"385 Collins Rd NE Cedar Rapids IA 52402",
    "addr:housenumber":"385",
    "addr:postcode":"52402",
    "addr:street":"Collins Rd Ne",
    "iso:country":"US",
    "sg:address":"385 Collins Rd NE",
    "sg:city":"Cedar Rapids",
    "sg:classifiers":[
        {
            "category":"Real Estate",
            "subcategory":"Real Estate Agent",
            "type":"Services"
        }
    ],
    "sg:phone":"+1 319 378 6607",
    "sg:postcode":"52402",
    "sg:province":"IA",
    "wof:name":"Don Sparrow",
    "wof:placetype":"venue"
},
  "geometry": {"coordinates":[-91.637435,42.027992],"type":"Point"}
}