{
  "type": "Feature",
  "properties": {
    "iso:country":"US",
    "sg:address":"406 Main St",
    "sg:city":"Osage",
    "sg:classifiers":[
        {
            "category":"Education",
            "subcategory":"Library",
            "type":"Public Place"
        }
    ],
    "sg:phone":"+1 641 732 3323",
    "sg:postcode":"50461",
    "sg:province":"IA",
    "wof:name":"Osage Public Library",
    "wof:placetype":"venue"
},
  "geometry": {"coordinates":[-92.81628499999999,43.283997],"type":"Point"}
}