{
  "type": "Feature",
  "properties": {
    "iso:country":"US",
    "sg:address":"1901 Dakota Ave",
    "sg:city":"Waverly",
    "sg:classifiers":[
        {
            "category":"Building & Trades",
            "subcategory":"Landscaping Services",
            "type":"Services"
        }
    ],
    "sg:phone":"+1 319 352 3778",
    "sg:postcode":"50677",
    "sg:province":"IA",
    "wof:name":"Rw Home & Lawn",
    "wof:placetype":"venue"
},
  "geometry": {"coordinates":[-92.49514600000001,42.766381],"type":"Point"}
}