{
  "type": "Feature",
  "properties": {
    "iso:country":"US",
    "sg:address":"107 W Division St",
    "sg:city":"West Bend",
    "sg:classifiers":[
        {
            "category":"Health Services",
            "subcategory":"Doctor",
            "type":"Services"
        }
    ],
    "sg:phone":"+1 515 887 7881",
    "sg:postcode":"50597",
    "sg:province":"IA",
    "sg:tags":[
        "physician",
        "surgeon"
    ],
    "wof:name":"Palo Alto County Health System",
    "wof:placetype":"venue"
},
  "geometry": {"coordinates":[-94.447593,42.960539],"type":"Point"}
}