{
  "type": "Feature",
  "properties": {
    "iso:country":"US",
    "sg:address":"214 5th St",
    "sg:city":"Kensett",
    "sg:classifiers":[
        {
            "category":"Education",
            "subcategory":"Library",
            "type":"Public Place"
        }
    ],
    "sg:phone":"+1 641 845 2222",
    "sg:postcode":"50448",
    "sg:province":"IA",
    "wof:name":"Kensett Library",
    "wof:placetype":"venue"
},
  "geometry": {"coordinates":[-93.209003,43.354477],"type":"Point"}
}