{
  "type": "Feature",
  "properties": {
    "iso:country":"US",
    "sg:address":"204 West St",
    "sg:city":"Protivin",
    "sg:classifiers":[
        {
            "category":"Building & Trades",
            "subcategory":"Construction",
            "type":"Services"
        }
    ],
    "sg:phone":"+1 563 569 8530",
    "sg:postcode":"52163",
    "sg:province":"IA",
    "sg:tags":[
        "contractor"
    ],
    "wof:name":"J P Building Svc",
    "wof:placetype":"venue"
},
  "geometry": {"coordinates":[-92.09356,43.215964],"type":"Point"}
}