{
  "type": "Feature",
  "properties": {
    "iso:country":"US",
    "sg:address":"320 W Lake View St",
    "sg:city":"North English",
    "sg:classifiers":[
        {
            "category":"Real Estate",
            "subcategory":"Real Estate Operator",
            "type":"Services"
        }
    ],
    "sg:phone":"+1 319 664 3000",
    "sg:postcode":"52316",
    "sg:province":"IA",
    "sg:tags":[
        "apartment"
    ],
    "wof:name":"North English Park Apartments",
    "wof:placetype":"venue"
},
  "geometry": {"coordinates":[-92.078478,41.511859],"type":"Point"}
}