{
  "type": "Feature",
  "properties": {
    "addr:full":"1851 Madison Ave Council Bluffs IA 51503",
    "addr:housenumber":"1851",
    "addr:postcode":"51503",
    "addr:street":"Madison Ave",
    "iso:country":"US",
    "sg:address":"1851 Madison Ave",
    "sg:city":"Council Bluffs",
    "sg:classifiers":[
        {
            "category":"Restaurant",
            "type":"Food & Drink"
        }
    ],
    "sg:phone":"+1 712 256 7712",
    "sg:postcode":"51503",
    "sg:province":"IA",
    "sg:tags":[
        "pizza"
    ],
    "wof:name":"Sam & Louie's New York Pizzeria",
    "wof:placetype":"venue"
},
  "geometry": {"coordinates":[-95.822231,41.241781],"type":"Point"}
}