{
  "type": "Feature",
  "properties": {
    "addr:full":"201 1st Ave SW Dayton IA 50530",
    "addr:housenumber":"201",
    "addr:postcode":"50530",
    "addr:street":"1St Ave Sw",
    "iso:country":"US",
    "sg:address":"201 1st Ave SW",
    "sg:city":"Dayton",
    "sg:classifiers":[
        {
            "category":"Organizations",
            "subcategory":"Religious Organization",
            "type":"Services"
        }
    ],
    "sg:phone":"+1 515 547 2431",
    "sg:postcode":"50530",
    "sg:province":"IA",
    "sg:tags":[
        "church"
    ],
    "wof:name":"Trinity Lutheran Church",
    "wof:placetype":"venue"
},
  "geometry": {"coordinates":[-94.072294,42.260601],"type":"Point"}
}