{
  "type": "Feature",
  "properties": {
    "iso:country":"US",
    "sg:address":"1838 Red Haw Rd",
    "sg:city":"Mount Vernon",
    "sg:classifiers":[
        {
            "category":"Professional",
            "subcategory":"Lawyer & Legal Services",
            "type":"Services"
        }
    ],
    "sg:phone":"+1 319 298 9036",
    "sg:postcode":"52314",
    "sg:province":"IA",
    "wof:name":"David Havercamp",
    "wof:placetype":"venue"
},
  "geometry": {"coordinates":[-91.502515,41.993566],"type":"Point"}
}