{
  "type": "Feature",
  "properties": {
    "addr:full":"917 E 1st St Ankeny IA 50021",
    "addr:housenumber":"917",
    "addr:postcode":"50021",
    "addr:street":"E 1St St",
    "iso:country":"US",
    "sg:address":"917 E 1st St",
    "sg:city":"Ankeny",
    "sg:classifiers":[
        {
            "category":"Shopping",
            "subcategory":"Jewelry",
            "type":"Retail Goods"
        }
    ],
    "sg:phone":"+1 515 964 5584",
    "sg:postcode":"50021",
    "sg:province":"IA",
    "sg:tags":[
        "jeweler"
    ],
    "wof:name":"Dave's Jewelry",
    "wof:placetype":"venue"
},
  "geometry": {"coordinates":[-93.587644,41.731791],"type":"Point"}
}