{
  "type": "Feature",
  "properties": {
    "iso:country":"US",
    "sg:address":"15633 650th Ave",
    "sg:city":"Mc Callsburg",
    "sg:phone":"+1 515 434 2898",
    "sg:postcode":"50154",
    "sg:province":"IA",
    "sg:tags":[
        "farm",
        "grain",
        "cash"
    ],
    "wof:name":"Gary Hendrick Farm",
    "wof:placetype":"venue"
},
  "geometry": {"coordinates":[-93.405536,42.128363],"type":"Point"}
}