{
  "type": "Feature",
  "properties": {
    "iso:country":"US",
    "sg:address":"1003 NW Church St",
    "sg:city":"Leon",
    "sg:classifiers":[
        {
            "category":"Organizations",
            "subcategory":"Religious Organization",
            "type":"Services"
        }
    ],
    "sg:phone":"+1 641 446 4789",
    "sg:postcode":"50144",
    "sg:province":"IA",
    "sg:tags":[
        "church"
    ],
    "wof:name":"Catholic Church",
    "wof:placetype":"venue"
},
  "geometry": {"coordinates":[-93.747744,40.746711],"type":"Point"}
}