{
  "type": "Feature",
  "properties": {
    "iso:country":"US",
    "sg:address":"906 School St",
    "sg:city":"Norwalk",
    "sg:classifiers":[
        {
            "category":"Education",
            "subcategory":"School",
            "type":"Public Place"
        }
    ],
    "sg:phone":"+1 515 981 0676",
    "sg:postcode":"50211",
    "sg:province":"IA",
    "wof:name":"Norwalk Schools Central Office",
    "wof:placetype":"venue"
},
  "geometry": {"coordinates":[-93.677488,41.473122],"type":"Point"}
}