{
  "type": "Feature",
  "properties": {
    "iso:country":"US",
    "sg:address":"2250 Vienna Ave",
    "sg:city":"Portsmouth",
    "sg:phone":"+1 712 743 3846",
    "sg:postcode":"51565",
    "sg:province":"IA",
    "sg:tags":[
        "farm",
        "corn",
        "grain",
        "cash"
    ],
    "wof:name":"Mark Bruck",
    "wof:placetype":"venue"
},
  "geometry": {"coordinates":[-95.57715899999999,41.686178],"type":"Point"}
}