{
  "type": "Feature",
  "properties": {
    "addr:full":"12 Park St Treynor IA 51575",
    "addr:housenumber":"12",
    "addr:postcode":"51575",
    "addr:street":"Park St",
    "iso:country":"US",
    "sg:address":"12 Park St",
    "sg:city":"Treynor",
    "sg:classifiers":[
        {
            "category":"Organizations",
            "subcategory":"Religious Organization",
            "type":"Services"
        }
    ],
    "sg:phone":"+1 712 487 3880",
    "sg:postcode":"51575",
    "sg:province":"IA",
    "sg:tags":[
        "church"
    ],
    "wof:name":"St Paul's Lutheran Church",
    "wof:placetype":"venue"
},
  "geometry": {"coordinates":[-95.610039,41.230611],"type":"Point"}
}