{
  "type": "Feature",
  "properties": {
    "iso:country":"US",
    "sg:address":"3846 100th St",
    "sg:city":"Urbandale",
    "sg:classifiers":[
        {
            "category":"Restaurant",
            "type":"Food & Drink"
        }
    ],
    "sg:phone":"+1 515 270 8781",
    "sg:postcode":"50322",
    "sg:province":"IA",
    "sg:tags":[
        "eating"
    ],
    "wof:name":"Tsing Tsao West",
    "wof:placetype":"venue"
},
  "geometry": {"coordinates":[-93.755984,41.629976],"type":"Point"}
}