{
  "type": "Feature",
  "properties": {
    "iso:country":"US",
    "sg:address":"2490 Joplin Ave",
    "sg:city":"Denver",
    "sg:classifiers":[
        {
            "category":"Building & Trades",
            "subcategory":"Construction",
            "type":"Services"
        }
    ],
    "sg:phone":"+1 319 266 0664",
    "sg:postcode":"50622",
    "sg:province":"IA",
    "sg:tags":[
        "downspouts",
        "gutter"
    ],
    "wof:name":"Superior Siding & Home Imprvmt",
    "wof:placetype":"venue"
},
  "geometry": {"coordinates":[-92.376659,42.686696],"type":"Point"}
}