{
  "type": "Feature",
  "properties": {
    "iso:country":"US",
    "sg:address":"201 S 1st Ave",
    "sg:city":"Anthon",
    "sg:classifiers":[
        {
            "category":"Manufacturing",
            "subcategory":"Metals",
            "type":"Manufacturing & Wholesale Goods"
        }
    ],
    "sg:phone":"+1 712 373 5172",
    "sg:postcode":"51004",
    "sg:province":"IA",
    "sg:tags":[
        "small",
        "product",
        "arms",
        "mfg"
    ],
    "wof:name":"Jdw Mfg",
    "wof:placetype":"venue"
},
  "geometry": {"coordinates":[-95.86820299999999,42.387316],"type":"Point"}
}