{
  "type": "Feature",
  "properties": {
    "iso:country":"US",
    "sg:address":"4211 Glass Rd NE Ste A",
    "sg:city":"Cedar Rapids",
    "sg:classifiers":[
        {
            "category":"Communications",
            "type":"Services"
        },
        {
            "category":"Professional",
            "subcategory":"Computer Services",
            "type":"Services"
        }
    ],
    "sg:phone":"+1 319 221 1667",
    "sg:postcode":"52402",
    "sg:province":"IA",
    "sg:tags":[
        "repair",
        "design",
        "web"
    ],
    "sg:website":"www.geonetric.com",
    "wof:name":"Geonetric Technologies",
    "wof:placetype":"venue"
},
  "geometry": {"coordinates":[-91.70070800000001,42.015919],"type":"Point"}
}