{
  "type": "Feature",
  "properties": {
    "iso:country":"US",
    "sg:address":"122 4th St SW",
    "sg:city":"Waverly",
    "sg:classifiers":[
        {
            "category":"Restaurant",
            "type":"Food & Drink"
        },
        {
            "category":"Ice Cream",
            "type":"Food & Drink"
        }
    ],
    "sg:menulink":"http://www.allmenus.com/ia/waverly/172783-dairy-queen/menu/",
    "sg:phone":"+1 319 352 3256",
    "sg:postcode":"50677",
    "sg:province":"IA",
    "sg:tags":[
        "burger",
        "american",
        "ice",
        "cream"
    ],
    "wof:name":"Dairy Queen",
    "wof:placetype":"venue"
},
  "geometry": {"coordinates":[-92.47564,42.725439],"type":"Point"}
}