{
  "type": "Feature",
  "properties": {
    "iso:country":"US",
    "sg:address":"2635 Hubbell Ave",
    "sg:city":"Des Moines",
    "sg:classifiers":[
        {
            "category":"Professional",
            "subcategory":"Accounting & Tax Preparation",
            "type":"Services"
        }
    ],
    "sg:phone":"+1 515 266 4845",
    "sg:postcode":"50317",
    "sg:province":"IA",
    "wof:name":"Ronald E Grohe CPA",
    "wof:placetype":"venue"
},
  "geometry": {"coordinates":[-93.56639300000001,41.6143],"type":"Point"}
}