{
  "type": "Feature",
  "properties": {
    "iso:country":"US",
    "sg:address":"822 Central Ave",
    "sg:city":"Fort Dodge",
    "sg:classifiers":[
        {
            "category":"Professional",
            "type":"Services"
        }
    ],
    "sg:phone":"+1 515 955 4076",
    "sg:postcode":"50501",
    "sg:province":"IA",
    "sg:tags":[
        "establishment"
    ],
    "wof:name":"Intl Simulation & Training",
    "wof:placetype":"venue"
},
  "geometry": {"coordinates":[-94.186334,42.505281],"type":"Point"}
}