{
  "type": "Feature",
  "properties": {
    "addr:full":"1425 60th St NE Cedar Rapids IA 52402",
    "addr:housenumber":"1425",
    "addr:postcode":"52402",
    "addr:street":"60Th St Ne",
    "iso:country":"US",
    "sg:address":"1425 60th St NE",
    "sg:city":"Cedar Rapids",
    "sg:classifiers":[
        {
            "category":"Professional",
            "subcategory":"Computer Services",
            "type":"Services"
        }
    ],
    "sg:phone":"+1 319 294 6664",
    "sg:postcode":"52402",
    "sg:province":"IA",
    "sg:tags":[
        "web",
        "designer",
        "design",
        "consultant"
    ],
    "sg:website":"www.fastekintl.com",
    "wof:name":"Fastek",
    "wof:placetype":"venue"
},
  "geometry": {"coordinates":[-91.657402,42.037701],"type":"Point"}
}