{
  "type": "Feature",
  "properties": {
    "addr:full":"720 Central Ave Dubuque IA 52001",
    "addr:housenumber":"720",
    "addr:postcode":"52001",
    "addr:street":"Central Ave",
    "iso:country":"US",
    "sg:address":"720 Central Ave",
    "sg:city":"Dubuque",
    "sg:classifiers":[
        {
            "category":"Government",
            "subcategory":"Office",
            "type":"Public Place"
        }
    ],
    "sg:phone":"+1 563 589 4479",
    "sg:postcode":"52001",
    "sg:province":"IA",
    "wof:name":"Maintenance Dept",
    "wof:placetype":"venue"
},
  "geometry": {"coordinates":[-90.664935,42.501313],"type":"Point"}
}