{
  "type": "Feature",
  "properties": {
    "iso:country":"US",
    "sg:address":"508 N Main St",
    "sg:city":"Allison",
    "sg:classifiers":[
        {
            "category":"Organizations",
            "subcategory":"Religious Organization",
            "type":"Services"
        }
    ],
    "sg:phone":"+1 319 267 2333",
    "sg:postcode":"50602",
    "sg:province":"IA",
    "wof:name":"United Church Of Christ",
    "wof:placetype":"venue"
},
  "geometry": {"coordinates":[-92.795044,42.755189],"type":"Point"}
}