{
  "type": "Feature",
  "properties": {
    "iso:country":"US",
    "sg:address":"2404 Hawaii Ave",
    "sg:city":"Humboldt",
    "sg:classifiers":[
        {
            "category":"Building & Trades",
            "subcategory":"Construction",
            "type":"Services"
        }
    ],
    "sg:phone":"+1 515 571 7045",
    "sg:postcode":"50548",
    "sg:province":"IA",
    "sg:tags":[
        "painter"
    ],
    "wof:name":"Johnson Painting",
    "wof:placetype":"venue"
},
  "geometry": {"coordinates":[-94.30458400000001,42.70202],"type":"Point"}
}