{
  "type": "Feature",
  "properties": {
    "iso:country":"US",
    "sg:address":"612 Central Ave",
    "sg:city":"Bedford",
    "sg:classifiers":[
        {
            "category":"Banks & Credit Unions",
            "subcategory":"Financial Services",
            "type":"Services"
        }
    ],
    "sg:phone":"+1 712 523 2131",
    "sg:postcode":"50833",
    "sg:province":"IA",
    "sg:tags":[
        "company",
        "holding"
    ],
    "wof:name":"Bedford Bancorp",
    "wof:placetype":"venue"
},
  "geometry": {"coordinates":[-94.719066,40.667348],"type":"Point"}
}