{
  "type": "Feature",
  "properties": {
    "addr:full":"508 Clifton Ave Des Moines IA 50315",
    "addr:housenumber":"508",
    "addr:postcode":"50315",
    "addr:street":"Clifton Ave",
    "iso:country":"US",
    "sg:address":"508 Clifton Ave",
    "sg:city":"Des Moines",
    "sg:classifiers":[
        {
            "category":"Bars & Pubs",
            "type":"Food & Drink"
        }
    ],
    "sg:phone":"+1 515 284 1074",
    "sg:postcode":"50315",
    "sg:province":"IA",
    "sg:tags":[
        "club",
        "night"
    ],
    "wof:name":"Frat House Night Club",
    "wof:placetype":"venue"
},
  "geometry": {"coordinates":[-93.62204699999999,41.572415],"type":"Point"}
}