{
  "type": "Feature",
  "properties": {
    "iso:country":"US",
    "sg:address":"2604 2nd Ave",
    "sg:city":"Muscatine",
    "sg:classifiers":[
        {
            "category":"Social Services",
            "subcategory":"Job Training",
            "type":"Services"
        }
    ],
    "sg:phone":"+1 563 262 0253",
    "sg:postcode":"52761",
    "sg:province":"IA",
    "sg:tags":[
        "rehabilitation"
    ],
    "wof:name":"Comprehensive Rehab Inc",
    "wof:placetype":"venue"
},
  "geometry": {"coordinates":[-91.03535599999999,41.45078],"type":"Point"}
}