{
  "type": "Feature",
  "properties": {
    "iso:country":"US",
    "sg:address":"1426 N 32nd St",
    "sg:city":"Fort Dodge",
    "sg:classifiers":[
        {
            "category":"Organizations",
            "subcategory":"Religious Organization",
            "type":"Services"
        }
    ],
    "sg:phone":"+1 515 573 8734",
    "sg:postcode":"50501",
    "sg:province":"IA",
    "wof:name":"Church of Jesus Christ of Ltte",
    "wof:placetype":"venue"
},
  "geometry": {"coordinates":[-94.14875000000001,42.519482],"type":"Point"}
}