{
  "type": "Feature",
  "properties": {
    "iso:country":"US",
    "sg:address":"107 W 2nd St S",
    "sg:city":"Newton",
    "sg:classifiers":[
        {
            "category":"Professional",
            "subcategory":"Lawyer & Legal Services",
            "type":"Services"
        }
    ],
    "sg:phone":"+1 641 792 3600",
    "sg:postcode":"50208",
    "sg:province":"IA",
    "sg:tags":[
        "attorney"
    ],
    "wof:name":"David G Sorenson Attorney",
    "wof:placetype":"venue"
},
  "geometry": {"coordinates":[-93.054929,41.699473],"type":"Point"}
}