{
  "type": "Feature",
  "properties": {
    "iso:country":"US",
    "sg:address":"2130 Kimball Ave",
    "sg:city":"Waterloo",
    "sg:classifiers":[
        {
            "category":"Home & Garden",
            "subcategory":"Hardware",
            "type":"Retail Goods"
        }
    ],
    "sg:phone":"+1 319 234 0383",
    "sg:postcode":"50702",
    "sg:province":"IA",
    "wof:name":"Ridgeway True Value Hardware",
    "wof:placetype":"venue"
},
  "geometry": {"coordinates":[-92.356979,42.470064],"type":"Point"}
}