{
  "type": "Feature",
  "properties": {
    "iso:country":"US",
    "sg:address":"1479 Elon Dr",
    "sg:city":"Waterville",
    "sg:classifiers":[
        {
            "category":"Bus Charters",
            "type":"Transportation"
        }
    ],
    "sg:phone":"+1 563 535 1000",
    "sg:postcode":"52170",
    "sg:province":"IA",
    "sg:tags":[
        "rental"
    ],
    "wof:name":"Black Coyote Lines",
    "wof:placetype":"venue"
},
  "geometry": {"coordinates":[-91.335233,43.262789],"type":"Point"}
}