{
  "type": "Feature",
  "properties": {
    "addr:full":"315 Cedar St Tipton IA 52772",
    "addr:housenumber":"315",
    "addr:postcode":"52772",
    "addr:street":"Cedar St",
    "iso:country":"US",
    "sg:address":"315 Cedar St",
    "sg:city":"Tipton",
    "sg:classifiers":[
        {
            "category":"Building & Trades",
            "subcategory":"Plumbing",
            "type":"Services"
        }
    ],
    "sg:phone":"+1 563 886 2885",
    "sg:postcode":"52772",
    "sg:province":"IA",
    "sg:tags":[
        "plumbing",
        "contractor"
    ],
    "wof:name":"Fiers Plumbing Heating & Air",
    "wof:placetype":"venue"
},
  "geometry": {"coordinates":[-91.128486,41.768807],"type":"Point"}
}