{
  "type": "Feature",
  "properties": {
    "iso:country":"US",
    "sg:address":"2538 73rd St",
    "sg:city":"Urbandale",
    "sg:classifiers":[
        {
            "category":"Professional",
            "subcategory":"Employment Agencies",
            "type":"Services"
        }
    ],
    "sg:phone":"+1 515 251 5802",
    "sg:postcode":"50322",
    "sg:province":"IA",
    "sg:tags":[
        "opportunity"
    ],
    "sg:website":"www.intelistaf.com",
    "wof:name":"Inteli Staf Healthcare",
    "wof:placetype":"venue"
},
  "geometry": {"coordinates":[-93.718146,41.6169],"type":"Point"}
}