{
  "type": "Feature",
  "properties": {
    "iso:country":"US",
    "sg:address":"1014 S Mill St",
    "sg:city":"Decorah",
    "sg:classifiers":[
        {
            "category":"Personal",
            "type":"Services"
        }
    ],
    "sg:phone":"+1 563 382 8495",
    "sg:postcode":"52101",
    "sg:province":"IA",
    "sg:tags":[
        "therapist",
        "massage"
    ],
    "wof:name":"Windemere Holistic Therapies",
    "wof:placetype":"venue"
},
  "geometry": {"coordinates":[-91.792058,43.294093],"type":"Point"}
}