{
  "type": "Feature",
  "properties": {
    "iso:country":"US",
    "sg:address":"311 Main St",
    "sg:city":"Dysart",
    "sg:classifiers":[
        {
            "category":"Retail",
            "subcategory":"Auto Repair",
            "type":"Services"
        }
    ],
    "sg:phone":"+1 319 476 3200",
    "sg:postcode":"52224",
    "sg:province":"IA",
    "sg:tags":[
        "machine",
        "automobile",
        "shop"
    ],
    "wof:name":"Heckt Power Products",
    "wof:placetype":"venue"
},
  "geometry": {"coordinates":[-92.306397,42.171714],"type":"Point"}
}