{
  "type": "Feature",
  "properties": {
    "addr:full":"409 Vanderbilt St Fairfax IA 52228",
    "addr:housenumber":"409",
    "addr:postcode":"52228",
    "addr:street":"Vanderbilt St",
    "iso:country":"US",
    "sg:address":"409 Vanderbilt St",
    "sg:city":"Fairfax",
    "sg:classifiers":[
        {
            "category":"Banks & Credit Unions",
            "subcategory":"Bank",
            "type":"Services"
        }
    ],
    "sg:phone":"+1 319 846 2300",
    "sg:postcode":"52228",
    "sg:province":"IA",
    "sg:website":"www.thebankhere.com",
    "wof:name":"Fairfax State Savings Bank",
    "wof:placetype":"venue"
},
  "geometry": {"coordinates":[-91.77359800000001,41.927502],"type":"Point"}
}