{
  "type": "Feature",
  "properties": {
    "iso:country":"US",
    "sg:address":"402 Main St",
    "sg:city":"Nashua",
    "sg:classifiers":[
        {
            "category":"Government",
            "subcategory":"Office",
            "type":"Public Place"
        }
    ],
    "sg:phone":"+1 641 435 4156",
    "sg:postcode":"50658",
    "sg:province":"IA",
    "sg:tags":[
        "city"
    ],
    "wof:name":"Nashua City Clerk",
    "wof:placetype":"venue"
},
  "geometry": {"coordinates":[-92.536321,42.951695],"type":"Point"}
}