{
  "type": "Feature",
  "properties": {
    "iso:country":"US",
    "sg:address":"2557 110th St",
    "sg:city":"Liscomb",
    "sg:classifiers":[
        {
            "category":"Farming",
            "subcategory":"Livestock Farm",
            "type":"Manufacturing & Wholesale Goods"
        }
    ],
    "sg:phone":"+1 641 366 2107",
    "sg:postcode":"50621",
    "sg:province":"IA",
    "sg:tags":[
        "hog",
        "or",
        "feedlot"
    ],
    "wof:name":"Tom Schmitt",
    "wof:placetype":"venue"
},
  "geometry": {"coordinates":[-92.93331000000001,42.195405],"type":"Point"}
}