{
  "type": "Feature",
  "properties": {
    "iso:country":"US",
    "sg:address":"2650 Easton Blvd",
    "sg:city":"Des Moines",
    "sg:classifiers":[
        {
            "category":"Education",
            "subcategory":"Dance Studio",
            "type":"Public Place"
        }
    ],
    "sg:phone":"+1 515 263 0441",
    "sg:postcode":"50317",
    "sg:province":"IA",
    "sg:tags":[
        "instruction",
        "dancing"
    ],
    "wof:name":"Charlene's Dance Studio",
    "wof:placetype":"venue"
},
  "geometry": {"coordinates":[-93.566632,41.608559],"type":"Point"}
}