{
  "type": "Feature",
  "properties": {
    "iso:country":"US",
    "sg:address":"3244 Echo Valley Rd",
    "sg:city":"Decorah",
    "sg:classifiers":[
        {
            "category":"Shopping",
            "subcategory":"Clothing, Apparel, & Fashions",
            "type":"Retail Goods"
        }
    ],
    "sg:phone":"+1 563 546 7720",
    "sg:postcode":"52101",
    "sg:province":"IA",
    "sg:tags":[
        "sport",
        "licensed"
    ],
    "wof:name":"Jeffs Allsports",
    "wof:placetype":"venue"
},
  "geometry": {"coordinates":[-91.66658099999999,43.40651],"type":"Point"}
}