{
  "type": "Feature",
  "properties": {
    "addr:full":"3621 Beaver Ave Des Moines IA 50310",
    "addr:housenumber":"3621",
    "addr:postcode":"50310",
    "addr:street":"Beaver Ave",
    "iso:country":"US",
    "sg:address":"3621 Beaver Ave",
    "sg:city":"Des Moines",
    "sg:classifiers":[
        {
            "category":"Personal",
            "subcategory":"Tanning Parlor",
            "type":"Services"
        }
    ],
    "sg:phone":"+1 515 277 4100",
    "sg:postcode":"50310",
    "sg:province":"IA",
    "sg:tags":[
        "salon"
    ],
    "wof:name":"Tanning Zone",
    "wof:placetype":"venue"
},
  "geometry": {"coordinates":[-93.677206,41.627965],"type":"Point"}
}