{
  "type": "Feature",
  "properties": {
    "iso:country":"US",
    "sg:address":"403 4th Ave W",
    "sg:city":"Swea City",
    "sg:classifiers":[
        {
            "category":"Wholesale",
            "subcategory":"Farm Supplies",
            "type":"Manufacturing & Wholesale Goods"
        }
    ],
    "sg:phone":"+1 515 272 4830",
    "sg:postcode":"50590",
    "sg:province":"IA",
    "sg:tags":[
        "grain"
    ],
    "wof:name":"Cenex Harvest States",
    "wof:placetype":"venue"
},
  "geometry": {"coordinates":[-94.312321,43.385068],"type":"Point"}
}