{
  "type": "Feature",
  "properties": {
    "addr:full":"111 E 2nd St Davenport IA 52801",
    "addr:housenumber":"111",
    "addr:postcode":"52801",
    "addr:street":"E 2Nd St",
    "iso:country":"US",
    "sg:address":"111 E 2nd St",
    "sg:city":"Davenport",
    "sg:classifiers":[
        {
            "category":"Travel",
            "subcategory":"Hotels & Motels",
            "type":"Entertainment"
        },
        {
            "category":"Personal",
            "type":"Services"
        },
        {
            "category":"Restaurant",
            "type":"Food & Drink"
        },
        {
            "category":"Retail",
            "subcategory":"Event Space",
            "type":"Services"
        }
    ],
    "sg:phone":"+1 563 322 2200",
    "sg:postcode":"52801",
    "sg:province":"IA",
    "sg:tags":[
        "facility",
        "hall",
        "planning",
        "reception",
        "lodging",
        "party",
        "meeting",
        "banquet"
    ],
    "sg:website":"http://www.radisson.com/davenportia",
    "wof:name":"Radisson Quad City Plaza",
    "wof:placetype":"venue"
},
  "geometry": {"coordinates":[-90.573947,41.521331],"type":"Point"}
}