{
  "type": "Feature",
  "properties": {
    "iso:country":"US",
    "sg:address":"1309 W Ferguson Ave",
    "sg:city":"Shenandoah",
    "sg:classifiers":[
        {
            "category":"Wholesale",
            "subcategory":"Farm Supplies",
            "type":"Manufacturing & Wholesale Goods"
        }
    ],
    "sg:phone":"+1 712 246 3692",
    "sg:postcode":"51601",
    "sg:province":"IA",
    "sg:tags":[
        "auction",
        "livestock",
        "market"
    ],
    "wof:name":"Shenandoah Livestock Auction",
    "wof:placetype":"venue"
},
  "geometry": {"coordinates":[-95.38341,40.771778],"type":"Point"}
}