{
  "type": "Feature",
  "properties": {
    "iso:country":"US",
    "sg:address":"201 Gray Ave",
    "sg:city":"Ames",
    "sg:classifiers":[
        {
            "category":"Organizations",
            "subcategory":"Community Association",
            "type":"Services"
        }
    ],
    "sg:phone":"+1 515 292 3880",
    "sg:postcode":"50014",
    "sg:province":"IA",
    "sg:tags":[
        "sorority",
        "fraternity"
    ],
    "wof:name":"Alpha Gamma Rho",
    "wof:placetype":"venue"
},
  "geometry": {"coordinates":[-93.64200700000001,42.021446],"type":"Point"}
}