{
  "type": "Feature",
  "properties": {
    "iso:country":"US",
    "sg:address":"120 S Walnut Ave",
    "sg:city":"Ames",
    "sg:classifiers":[
        {
            "category":"Autos & Motor Vehicles",
            "subcategory":"Auto Supplies",
            "type":"Retail Goods"
        }
    ],
    "sg:phone":"+1 515 232 2520",
    "sg:postcode":"50010",
    "sg:province":"IA",
    "sg:tags":[
        "automobile",
        "parts"
    ],
    "sg:website":"www.arnoldmotorsupply.com",
    "wof:name":"Arnold Motor Supply",
    "wof:placetype":"venue"
},
  "geometry": {"coordinates":[-93.616854,42.022584],"type":"Point"}
}