{
  "type": "Feature",
  "properties": {
    "iso:country":"US",
    "sg:address":"202 South St",
    "sg:city":"Dumont",
    "sg:classifiers":[
        {
            "category":"Home & Garden",
            "subcategory":"Garden Supply",
            "type":"Retail Goods"
        }
    ],
    "sg:phone":"+1 641 857 6645",
    "sg:postcode":"50625",
    "sg:province":"IA",
    "sg:tags":[
        "lawn"
    ],
    "wof:name":"Dumont Lawn & Garden Ctr",
    "wof:placetype":"venue"
},
  "geometry": {"coordinates":[-92.967883,42.744913],"type":"Point"}
}