{
  "type": "Feature",
  "properties": {
    "iso:country":"US",
    "sg:address":"116 N Main Ave",
    "sg:city":"Sioux Center",
    "sg:classifiers":[
        {
            "category":"Insurance",
            "subcategory":"Insurance Agent",
            "type":"Services"
        }
    ],
    "sg:phone":"+1 712 722 2571",
    "sg:postcode":"51250",
    "sg:province":"IA",
    "wof:name":"German Farmers Mutual Ins Assn",
    "wof:placetype":"venue"
},
  "geometry": {"coordinates":[-96.175439,43.078433],"type":"Point"}
}