{
  "type": "Feature",
  "properties": {
    "iso:country":"US",
    "sg:address":"1800 NW 86th St",
    "sg:city":"Clive",
    "sg:classifiers":[
        {
            "category":"Personal",
            "subcategory":"Beauty Salon",
            "type":"Services"
        }
    ],
    "sg:phone":"+1 515 270 2552",
    "sg:postcode":"50325",
    "sg:province":"IA",
    "sg:tags":[
        "manicuring"
    ],
    "wof:name":"Nail Design",
    "wof:placetype":"venue"
},
  "geometry": {"coordinates":[-93.736374,41.609435],"type":"Point"}
}