{
  "type": "Feature",
  "properties": {
    "addr:full":"1000 Blunt Pkwy Charles City IA 50616",
    "addr:housenumber":"1000",
    "addr:postcode":"50616",
    "addr:street":"Blunt Pkwy",
    "iso:country":"US",
    "sg:address":"1000 Blunt Pkwy",
    "sg:city":"Charles City",
    "sg:classifiers":[
        {
            "category":"Restaurant",
            "type":"Food & Drink"
        }
    ],
    "sg:menulink":"http://www.allmenus.com/ia/charles-city/32062-pizza-ranch/menu/",
    "sg:phone":"+1 641 228 4100",
    "sg:postcode":"50616",
    "sg:province":"IA",
    "sg:tags":[
        "american",
        "pizza"
    ],
    "wof:name":"Pizza Ranch",
    "wof:placetype":"venue"
},
  "geometry": {"coordinates":[-92.673785,43.067142],"type":"Point"}
}