{
  "type": "Feature",
  "properties": {
    "iso:country":"US",
    "sg:address":"2116 Brown St",
    "sg:city":"Davenport",
    "sg:classifiers":[
        {
            "category":"Organizations",
            "subcategory":"Membership Organization",
            "type":"Services"
        }
    ],
    "sg:phone":"+1 563 326 2645",
    "sg:postcode":"52804",
    "sg:province":"IA",
    "wof:name":"National Womens 500 Bowl CLB",
    "wof:placetype":"venue"
},
  "geometry": {"coordinates":[-90.584322,41.541639],"type":"Point"}
}