{
  "type": "Feature",
  "properties": {
    "iso:country":"US",
    "sg:address":"101 E Main St",
    "sg:city":"New Hampton",
    "sg:classifiers":[
        {
            "category":"Health Services",
            "subcategory":"Chiropractor",
            "type":"Services"
        }
    ],
    "sg:phone":"+1 641 394 4847",
    "sg:postcode":"50659",
    "sg:province":"IA",
    "wof:name":"Hurd Chiropractic",
    "wof:placetype":"venue"
},
  "geometry": {"coordinates":[-92.314505,43.059238],"type":"Point"}
}