{
  "type": "Feature",
  "properties": {
    "addr:full":"13646 B M R Ln Dubuque IA 52002",
    "addr:housenumber":"13646 b",
    "addr:postcode":"52002",
    "addr:street":"M R Ln",
    "iso:country":"US",
    "sg:address":"13646 B M R Ln",
    "sg:city":"Dubuque",
    "sg:classifiers":[
        {
            "category":"Building & Trades",
            "subcategory":"Construction",
            "type":"Services"
        }
    ],
    "sg:phone":"+1 563 556 3850",
    "sg:postcode":"52002",
    "sg:province":"IA",
    "sg:tags":[
        "masonry",
        "contractor"
    ],
    "wof:name":"Berns Masonry Inc",
    "wof:placetype":"venue"
},
  "geometry": {"coordinates":[-90.79683,42.489843],"type":"Point"}
}