{
  "type": "Feature",
  "properties": {
    "iso:country":"US",
    "sg:address":"209 Pacific Ave",
    "sg:city":"Audubon",
    "sg:phone":"+1 712 563 3927",
    "sg:postcode":"50025",
    "sg:province":"IA",
    "sg:tags":[
        "farm",
        "corn",
        "soybean"
    ],
    "wof:name":"Eric Jorgensen",
    "wof:placetype":"venue"
},
  "geometry": {"coordinates":[-94.938901,41.721553],"type":"Point"}
}