{
  "type": "Feature",
  "properties": {
    "iso:country":"US",
    "sg:address":"3800 Wilson Ave SW",
    "sg:city":"Cedar Rapids",
    "sg:classifiers":[
        {
            "category":"Personal",
            "subcategory":"Beauty Salon",
            "type":"Services"
        }
    ],
    "sg:phone":"+1 319 396 5227",
    "sg:postcode":"52404",
    "sg:province":"IA",
    "wof:name":"Urban Trends",
    "wof:placetype":"venue"
},
  "geometry": {"coordinates":[-91.721554,41.956456],"type":"Point"}
}