{
  "type": "Feature",
  "properties": {
    "iso:country":"US",
    "sg:address":"424 S Leebrick St",
    "sg:city":"Burlington",
    "sg:classifiers":[
        {
            "category":"Shopping",
            "subcategory":"Used Merchandise",
            "type":"Retail Goods"
        }
    ],
    "sg:phone":"+1 319 752 5933",
    "sg:postcode":"52601",
    "sg:province":"IA",
    "sg:tags":[
        "clothing"
    ],
    "wof:name":"Dolores' Resale Shop",
    "wof:placetype":"venue"
},
  "geometry": {"coordinates":[-91.12025,40.806171],"type":"Point"}
}