{
  "type": "Feature",
  "properties": {
    "addr:full":"311 Grove St Calamus IA 52729",
    "addr:housenumber":"311",
    "addr:postcode":"52729",
    "addr:street":"Grove St",
    "iso:country":"US",
    "sg:address":"311 Grove St",
    "sg:city":"Calamus",
    "sg:classifiers":[
        {
            "category":"Professional",
            "subcategory":"Business Services",
            "type":"Services"
        }
    ],
    "sg:phone":"+1 563 246 2367",
    "sg:postcode":"52729",
    "sg:province":"IA",
    "wof:name":"LMS Enterprises",
    "wof:placetype":"venue"
},
  "geometry": {"coordinates":[-90.756637,41.824338],"type":"Point"}
}