{
  "type": "Feature",
  "properties": {
    "addr:full":"2748 Harts Mill Rd Clinton IA 52732",
    "addr:housenumber":"2748",
    "addr:postcode":"52732",
    "addr:street":"Harts Mill Rd",
    "iso:country":"US",
    "sg:address":"2748 Harts Mill Rd",
    "sg:city":"Clinton",
    "sg:classifiers":[
        {
            "category":"Real Estate",
            "subcategory":"Developer",
            "type":"Services"
        }
    ],
    "sg:phone":"+1 563 242 7853",
    "sg:postcode":"52732",
    "sg:province":"IA",
    "sg:tags":[
        "cemetery"
    ],
    "wof:name":"Pine Grove Cemetary Assn",
    "wof:placetype":"venue"
},
  "geometry": {"coordinates":[-90.24486400000001,41.829298],"type":"Point"}
}