{
  "type": "Feature",
  "properties": {
    "addr:full":"46326 Chestnut Rd Griswold IA 51535",
    "addr:housenumber":"46326",
    "addr:postcode":"51535",
    "addr:street":"Chestnut Rd",
    "iso:country":"US",
    "sg:address":"46326 Chestnut Rd",
    "sg:city":"Griswold",
    "sg:classifiers":[
        {
            "category":"Building & Trades",
            "subcategory":"Construction",
            "type":"Services"
        }
    ],
    "sg:phone":"+1 712 484 3493",
    "sg:postcode":"51535",
    "sg:province":"IA",
    "sg:tags":[
        "house"
    ],
    "wof:name":"Ray Shannon",
    "wof:placetype":"venue"
},
  "geometry": {"coordinates":[-95.304035,41.217927],"type":"Point"}
}