{
  "type": "Feature",
  "properties": {
    "addr:full":"221 Central Ave E Clarion IA 50525",
    "addr:housenumber":"221",
    "addr:postcode":"50525",
    "addr:street":"Central Ave E Clarion",
    "iso:country":"US",
    "sg:address":"221 Central Ave E",
    "sg:city":"Clarion",
    "sg:classifiers":[
        {
            "category":"Travel",
            "subcategory":"Hotels & Motels",
            "type":"Entertainment"
        }
    ],
    "sg:phone":"+1 515 532 6832",
    "sg:postcode":"50525",
    "sg:province":"IA",
    "wof:name":"Clarion Inn B & B",
    "wof:placetype":"venue"
},
  "geometry": {"coordinates":[-93.73137699999999,42.731767],"type":"Point"}
}