{
  "type": "Feature",
  "properties": {
    "iso:country":"US",
    "sg:address":"3752 F Ave NE",
    "sg:city":"Cedar Rapids",
    "sg:classifiers":[
        {
            "category":"Building & Trades",
            "subcategory":"Landscaping Services",
            "type":"Services"
        }
    ],
    "sg:phone":"+1 319 389 2044",
    "sg:postcode":"52402",
    "sg:province":"IA",
    "sg:tags":[
        "lawn",
        "maintenance",
        "grounds"
    ],
    "wof:name":"Scotland Yard Mowing",
    "wof:placetype":"venue"
},
  "geometry": {"coordinates":[-91.643387,42.016312],"type":"Point"}
}