{
  "type": "Feature",
  "properties": {
    "iso:country":"US",
    "sg:address":"1284 E Ave",
    "sg:city":"Gladbrook",
    "sg:classifiers":[
        {
            "category":"Retail",
            "subcategory":"Portrait Studio",
            "type":"Services"
        }
    ],
    "sg:phone":"+1 641 473 2063",
    "sg:postcode":"50635",
    "sg:province":"IA",
    "sg:tags":[
        "photographer",
        "photo"
    ],
    "sg:website":"www.waynesphotography.net",
    "wof:name":"Wayne's Photography",
    "wof:placetype":"venue"
},
  "geometry": {"coordinates":[-92.689894,42.250386],"type":"Point"}
}