{
  "type": "Feature",
  "properties": {
    "iso:country":"US",
    "sg:address":"1310 E Howard St",
    "sg:city":"Creston",
    "sg:classifiers":[
        {
            "category":"Manufacturing",
            "subcategory":"Retail Goods",
            "type":"Manufacturing & Wholesale Goods"
        }
    ],
    "sg:phone":"+1 641 782 2336",
    "sg:postcode":"50801",
    "sg:province":"IA",
    "sg:tags":[
        "manufacturer"
    ],
    "sg:website":"www.debruce.com",
    "wof:name":"Creston Bean Processing",
    "wof:placetype":"venue"
},
  "geometry": {"coordinates":[-94.34513800000001,41.060837],"type":"Point"}
}