{
  "type": "Feature",
  "properties": {
    "iso:country":"US",
    "sg:address":"26877 Grandview Rd",
    "sg:city":"Elkport",
    "sg:classifiers":[
        {
            "category":"Autos & Motor Vehicles",
            "subcategory":"Fuel & Gas Station",
            "type":"Retail Goods"
        }
    ],
    "sg:phone":"+1 563 255 2674",
    "sg:postcode":"52044",
    "sg:province":"IA",
    "sg:tags":[
        "oil"
    ],
    "wof:name":"Sear's 66",
    "wof:placetype":"venue"
},
  "geometry": {"coordinates":[-91.27200499999999,42.743752],"type":"Point"}
}