{
  "type": "Feature",
  "properties": {
    "iso:country":"US",
    "sg:address":"1451 Coral Ridge Ave",
    "sg:city":"Coralville",
    "sg:classifiers":[
        {
            "category":"Shopping",
            "subcategory":"Shoes",
            "type":"Retail Goods"
        }
    ],
    "sg:phone":"+1 319 625 2699",
    "sg:postcode":"52241",
    "sg:province":"IA",
    "wof:name":"Journeys",
    "wof:placetype":"venue"
},
  "geometry": {"coordinates":[-91.608328,41.691708],"type":"Point"}
}