{
  "type": "Feature",
  "properties": {
    "iso:country":"US",
    "sg:address":"1622 S Federal Ave",
    "sg:city":"Mason City",
    "sg:classifiers":[
        {
            "category":"Government",
            "subcategory":"Office",
            "type":"Public Place"
        }
    ],
    "sg:phone":"+1 641 380 0377",
    "sg:postcode":"50401",
    "sg:province":"IA",
    "wof:name":"Satellite Treasures Office",
    "wof:placetype":"venue"
},
  "geometry": {"coordinates":[-93.20115699999999,43.136037],"type":"Point"}
}