{
  "type": "Feature",
  "properties": {
    "addr:full":"21385 Horseshoe Rd Sherrill IA 52073",
    "addr:housenumber":"21385",
    "addr:postcode":"52073",
    "addr:street":"Horseshoe Rd",
    "iso:country":"US",
    "sg:address":"21385 Horseshoe Rd",
    "sg:city":"Sherrill",
    "sg:phone":"+1 563 552 1757",
    "sg:postcode":"52073",
    "sg:province":"IA",
    "sg:tags":[
        "farm",
        "corn"
    ],
    "wof:name":"Loras Link",
    "wof:placetype":"venue"
},
  "geometry": {"coordinates":[-90.889745,42.608926],"type":"Point"}
}