{
  "type": "Feature",
  "properties": {
    "addr:full":"1830 Pershing Blvd Clinton IA 52732",
    "addr:housenumber":"1830",
    "addr:postcode":"52732",
    "addr:street":"Pershing Blvd",
    "iso:country":"US",
    "sg:address":"1830 Pershing Blvd",
    "sg:city":"Clinton",
    "sg:classifiers":[
        {
            "category":"Manufacturing",
            "subcategory":"Paper Products",
            "type":"Manufacturing & Wholesale Goods"
        }
    ],
    "sg:phone":"+1 563 243 4814",
    "sg:postcode":"52732",
    "sg:province":"IA",
    "sg:tags":[
        "mill"
    ],
    "wof:name":"Splintle Mania",
    "wof:placetype":"venue"
},
  "geometry": {"coordinates":[-90.183592,41.866078],"type":"Point"}
}