{
  "type": "Feature",
  "properties": {
    "iso:country":"US",
    "sg:address":"1228 8th St",
    "sg:city":"West Des Moines",
    "sg:classifiers":[
        {
            "category":"Professional",
            "subcategory":"Management & Consulting",
            "type":"Services"
        }
    ],
    "sg:phone":"+1 515 327 1960",
    "sg:postcode":"50265",
    "sg:province":"IA",
    "wof:name":"Jeffrey S Mumma Cfp",
    "wof:placetype":"venue"
},
  "geometry": {"coordinates":[-93.713292,41.589572],"type":"Point"}
}