{
  "type": "Feature",
  "properties": {
    "addr:full":"2520 Melrose Dr Cedar Falls IA 50613",
    "addr:housenumber":"2520",
    "addr:postcode":"50613",
    "addr:street":"Melrose Dr",
    "iso:country":"US",
    "sg:address":"2520 Melrose Dr",
    "sg:city":"Cedar Falls",
    "sg:classifiers":[
        {
            "category":"Personal",
            "subcategory":"Tanning Parlor",
            "type":"Services"
        }
    ],
    "sg:phone":"+1 319 277 3261",
    "sg:postcode":"50613",
    "sg:province":"IA",
    "sg:tags":[
        "salon"
    ],
    "wof:name":"Tan Talizing Tans",
    "wof:placetype":"venue"
},
  "geometry": {"coordinates":[-92.431197,42.513569],"type":"Point"}
}