{
  "type": "Feature",
  "properties": {
    "iso:country":"US",
    "sg:address":"408 W Main St",
    "sg:city":"Anamosa",
    "sg:classifiers":[
        {
            "category":"Real Estate",
            "subcategory":"Real Estate Services",
            "type":"Services"
        }
    ],
    "sg:phone":"+1 319 462 4168",
    "sg:postcode":"52205",
    "sg:province":"IA",
    "sg:website":"www.jonescountyabstract.com",
    "wof:name":"Jones County Abstract Co",
    "wof:placetype":"venue"
},
  "geometry": {"coordinates":[-91.28934700000001,42.108298],"type":"Point"}
}