{
  "type": "Feature",
  "properties": {
    "iso:country":"US",
    "sg:address":"320 H Ave",
    "sg:city":"Grundy Center",
    "sg:classifiers":[
        {
            "category":"Shopping",
            "subcategory":"Florist",
            "type":"Retail Goods"
        }
    ],
    "sg:phone":"+1 319 824 5414",
    "sg:postcode":"50638",
    "sg:province":"IA",
    "wof:name":"Buseman's Flowers",
    "wof:placetype":"venue"
},
  "geometry": {"coordinates":[-92.767387,42.360422],"type":"Point"}
}