{
  "type": "Feature",
  "properties": {
    "iso:country":"US",
    "sg:address":"1023 Peoples Sq",
    "sg:city":"Waterloo",
    "sg:classifiers":[
        {
            "category":"Food & Beverages",
            "subcategory":"Specialty",
            "type":"Retail Goods"
        }
    ],
    "sg:phone":"+1 319 235 0246",
    "sg:postcode":"50702",
    "sg:province":"IA",
    "sg:tags":[
        "herb"
    ],
    "wof:name":"TNK Natural Health Food",
    "wof:placetype":"venue"
},
  "geometry": {"coordinates":[-92.357569,42.458391],"type":"Point"}
}