{
  "type": "Feature",
  "properties": {
    "iso:country":"US",
    "sg:address":"1901 Wright Ave",
    "sg:city":"Alexander",
    "sg:classifiers":[
        {
            "category":"Farming",
            "subcategory":"Farm",
            "type":"Manufacturing & Wholesale Goods"
        }
    ],
    "sg:phone":"+1 641 692 3374",
    "sg:postcode":"50420",
    "sg:province":"IA",
    "sg:tags":[
        "crop",
        "general"
    ],
    "wof:name":"Hopkey Marlin",
    "wof:placetype":"venue"
},
  "geometry": {"coordinates":[-93.49870199999999,42.834148],"type":"Point"}
}