{
  "type": "Feature",
  "properties": {
    "iso:country":"US",
    "sg:address":"1016 Broadway",
    "sg:city":"Denison",
    "sg:classifiers":[
        {
            "category":"Retail",
            "subcategory":"Repair Shop",
            "type":"Services"
        }
    ],
    "sg:phone":"+1 712 263 6698",
    "sg:postcode":"51442",
    "sg:province":"IA",
    "sg:tags":[
        "related"
    ],
    "wof:name":"K & H Repair",
    "wof:placetype":"venue"
},
  "geometry": {"coordinates":[-95.359071,42.01683],"type":"Point"}
}