{
  "type": "Feature",
  "properties": {
    "iso:country":"US",
    "sg:address":"3998 Fenton Ave",
    "sg:city":"Stratford",
    "sg:classifiers":[
        {
            "category":"Organizations",
            "subcategory":"Religious Organization",
            "type":"Services"
        }
    ],
    "sg:phone":"+1 515 838 2549",
    "sg:postcode":"50249",
    "sg:province":"IA",
    "wof:name":"Countryside",
    "wof:placetype":"venue"
},
  "geometry": {"coordinates":[-93.874144,42.209779],"type":"Point"}
}