{
  "type": "Feature",
  "properties": {
    "iso:country":"US",
    "sg:address":"325 W 11th St",
    "sg:city":"Waterloo",
    "sg:classifiers":[
        {
            "category":"Wholesale",
            "subcategory":"Auto Parts",
            "type":"Manufacturing & Wholesale Goods"
        }
    ],
    "sg:phone":"+1 319 235 1455",
    "sg:postcode":"50702",
    "sg:province":"IA",
    "sg:tags":[
        "automobile",
        "supply"
    ],
    "sg:website":"www.cedarvalleysupply.com",
    "wof:name":"Cedar Valley Supply Parts Plus",
    "wof:placetype":"venue"
},
  "geometry": {"coordinates":[-92.333962,42.488823],"type":"Point"}
}