{
  "type": "Feature",
  "properties": {
    "iso:country":"US",
    "sg:address":"2012 145th Ave",
    "sg:city":"Manchester",
    "sg:classifiers":[
        {
            "category":"Farming",
            "subcategory":"Farm",
            "type":"Manufacturing & Wholesale Goods"
        }
    ],
    "sg:phone":"+1 563 927 4682",
    "sg:postcode":"52057",
    "sg:province":"IA",
    "sg:tags":[
        "crop",
        "general"
    ],
    "wof:name":"Craig Saunders",
    "wof:placetype":"venue"
},
  "geometry": {"coordinates":[-91.51954499999999,42.498484],"type":"Point"}
}