{
  "type": "Feature",
  "properties": {
    "addr:full":"800 Adair St De Soto IA 50069",
    "addr:housenumber":"800",
    "addr:postcode":"50069",
    "addr:street":"Adair St",
    "iso:country":"US",
    "sg:address":"800 Adair St",
    "sg:city":"De Soto",
    "sg:classifiers":[
        {
            "category":"Professional",
            "subcategory":"Advertising",
            "type":"Services"
        }
    ],
    "sg:phone":"+1 515 834 2740",
    "sg:postcode":"50069",
    "sg:province":"IA",
    "sg:tags":[
        "mail"
    ],
    "sg:website":"www.cpamc.com",
    "wof:name":"Custom Printing & Mailing Co",
    "wof:placetype":"venue"
},
  "geometry": {"coordinates":[-94.01105099999999,41.535622],"type":"Point"}
}