{
  "type": "Feature",
  "properties": {
    "iso:country":"US",
    "sg:address":"719 Nebraska St",
    "sg:city":"Sioux City",
    "sg:classifiers":[
        {
            "category":"Wholesale",
            "subcategory":"Farm Supplies",
            "type":"Manufacturing & Wholesale Goods"
        }
    ],
    "sg:phone":"+1 712 258 0933",
    "sg:postcode":"51101",
    "sg:province":"IA",
    "sg:tags":[
        "feed"
    ],
    "wof:name":"Land O'Lakes Feed Ingredients",
    "wof:placetype":"venue"
},
  "geometry": {"coordinates":[-96.40358500000001,42.498311],"type":"Point"}
}