{
  "type": "Feature",
  "properties": {
    "iso:country":"US",
    "sg:address":"1412 Willis Ave",
    "sg:city":"Perry",
    "sg:classifiers":[
        {
            "category":"Building & Trades",
            "subcategory":"Pest Control",
            "type":"Services"
        }
    ],
    "sg:phone":"+1 515 465 3690",
    "sg:postcode":"50220",
    "sg:province":"IA",
    "wof:name":"Wilson Brothers Pest Control",
    "wof:placetype":"venue"
},
  "geometry": {"coordinates":[-94.101209,41.838554],"type":"Point"}
}