{
  "type": "Feature",
  "properties": {
    "addr:full":"901 29th Ave SW Cedar Rapids IA 52404",
    "addr:housenumber":"901",
    "addr:postcode":"52404",
    "addr:street":"29Th Ave Sw",
    "iso:country":"US",
    "sg:address":"901 29th Ave SW",
    "sg:city":"Cedar Rapids",
    "sg:classifiers":[
        {
            "category":"Government",
            "subcategory":"Jail",
            "type":"Public Place"
        }
    ],
    "sg:phone":"+1 319 398 3907",
    "sg:postcode":"52404",
    "sg:province":"IA",
    "sg:tags":[
        "county",
        "govt",
        "institution"
    ],
    "wof:name":"Linn County Correctional Svc",
    "wof:placetype":"venue"
},
  "geometry": {"coordinates":[-91.679255,41.948882],"type":"Point"}
}