{
  "type": "Feature",
  "properties": {
    "iso:country":"US",
    "sg:address":"1226 E 37th St",
    "sg:city":"Davenport",
    "sg:classifiers":[
        {
            "category":"Wholesale",
            "subcategory":"Electrical",
            "type":"Manufacturing & Wholesale Goods"
        }
    ],
    "sg:phone":"+1 563 386 1640",
    "sg:postcode":"52807",
    "sg:province":"IA",
    "sg:tags":[
        "telecommunication"
    ],
    "sg:website":"www.procomqc.com",
    "wof:name":"Professional Communications",
    "wof:placetype":"venue"
},
  "geometry": {"coordinates":[-90.556275,41.558403],"type":"Point"}
}