{
  "type": "Feature",
  "properties": {
    "addr:full":"77837 Chicago Rd Anita IA 50020",
    "addr:housenumber":"77837",
    "addr:postcode":"50020",
    "addr:street":"Chicago Rd",
    "iso:country":"US",
    "sg:address":"77837 Chicago Rd",
    "sg:city":"Anita",
    "sg:phone":"+1 712 762 3329",
    "sg:postcode":"50020",
    "sg:province":"IA",
    "sg:tags":[
        "hog",
        "beef",
        "f",
        "farm",
        "corn",
        "soybean",
        "cattle",
        "feedlot"
    ],
    "wof:name":"Dean Pierce",
    "wof:placetype":"venue"
},
  "geometry": {"coordinates":[-94.708719,41.475306],"type":"Point"}
}