{
  "type": "Feature",
  "properties": {
    "addr:full":"609 1600th St Panama IA 51562",
    "addr:housenumber":"609",
    "addr:postcode":"51562",
    "addr:street":"1600Th St",
    "iso:country":"US",
    "sg:address":"609 1600th St",
    "sg:city":"Panama",
    "sg:phone":"+1 712 489 2034",
    "sg:postcode":"51562",
    "sg:province":"IA",
    "sg:tags":[
        "farm",
        "corn",
        "soybean"
    ],
    "wof:name":"Rodney Kenkel",
    "wof:placetype":"venue"
},
  "geometry": {"coordinates":[-95.458507,41.732691],"type":"Point"}
}