{
  "type": "Feature",
  "properties": {
    "iso:country":"US",
    "sg:address":"1001 W 1st St",
    "sg:city":"Leon",
    "sg:classifiers":[
        {
            "category":"Home & Garden",
            "subcategory":"Furniture",
            "type":"Retail Goods"
        }
    ],
    "sg:phone":"+1 641 446 4187",
    "sg:postcode":"50144",
    "sg:province":"IA",
    "wof:name":"Plaza Furniture & Carpet",
    "wof:placetype":"venue"
},
  "geometry": {"coordinates":[-93.75659,40.739577],"type":"Point"}
}