{
  "type": "Feature",
  "properties": {
    "iso:country":"US",
    "sg:address":"2222 Martin Luther King Jr Pkwy",
    "sg:city":"Des Moines",
    "sg:classifiers":[
        {
            "category":"Restaurant",
            "type":"Food & Drink"
        }
    ],
    "sg:menulink":"http://www.allmenus.com/ia/des-moines/160774-burger-king/menu/",
    "sg:phone":"+1 515 277 3255",
    "sg:postcode":"50314",
    "sg:province":"IA",
    "sg:tags":[
        "burger",
        "american"
    ],
    "wof:name":"Burger King",
    "wof:placetype":"venue"
},
  "geometry": {"coordinates":[-93.646396,41.614404],"type":"Point"}
}