{
  "type": "Feature",
  "properties": {
    "iso:country":"US",
    "sg:address":"3255 Williams Blvd SW",
    "sg:city":"Cedar Rapids",
    "sg:classifiers":[
        {
            "category":"Health Services",
            "subcategory":"Optometrist",
            "type":"Services"
        }
    ],
    "sg:phone":"+1 319 364 2311",
    "sg:postcode":"52404",
    "sg:province":"IA",
    "sg:website":"www.spandainc.com",
    "wof:name":"Vision In Motion",
    "wof:placetype":"venue"
},
  "geometry": {"coordinates":[-91.712677,41.960171],"type":"Point"}
}