{
  "type": "Feature",
  "properties": {
    "iso:country":"US",
    "sg:address":"2 S Main St",
    "sg:city":"Fayette",
    "sg:classifiers":[
        {
            "category":"Autos & Motor Vehicles",
            "subcategory":"Auto Supplies",
            "type":"Retail Goods"
        }
    ],
    "sg:phone":"+1 563 425 3354",
    "sg:postcode":"52142",
    "sg:province":"IA",
    "sg:tags":[
        "tire"
    ],
    "wof:name":"Voshell's Service",
    "wof:placetype":"venue"
},
  "geometry": {"coordinates":[-91.802352,42.845602],"type":"Point"}
}