{
  "type": "Feature",
  "properties": {
    "iso:country":"US",
    "sg:address":"1231 260th St",
    "sg:city":"Bridgewater",
    "sg:classifiers":[
        {
            "category":"Farming",
            "subcategory":"Farm & Veterinary Services",
            "type":"Manufacturing & Wholesale Goods"
        }
    ],
    "sg:phone":"+1 641 369 4741",
    "sg:postcode":"50837",
    "sg:province":"IA",
    "wof:name":"Eblen & Sons Simmental",
    "wof:placetype":"venue"
},
  "geometry": {"coordinates":[-94.65585900000001,41.273027],"type":"Point"}
}