{
  "type": "Feature",
  "properties": {
    "addr:full":"408 Ijem Ave Nichols IA 52766",
    "addr:housenumber":"408",
    "addr:postcode":"52766",
    "addr:street":"Ijem Ave",
    "iso:country":"US",
    "sg:address":"408 Ijem Ave",
    "sg:city":"Nichols",
    "sg:classifiers":[
        {
            "category":"Organizations",
            "subcategory":"Professional Association",
            "type":"Services"
        }
    ],
    "sg:phone":"+1 319 723 4587",
    "sg:postcode":"52766",
    "sg:province":"IA",
    "wof:name":"Business Assn",
    "wof:placetype":"venue"
},
  "geometry": {"coordinates":[-91.308859,41.481067],"type":"Point"}
}