{
  "type": "Feature",
  "properties": {
    "iso:country":"US",
    "sg:address":"517 2nd St",
    "sg:city":"Manning",
    "sg:classifiers":[
        {
            "category":"Organizations",
            "subcategory":"Religious Organization",
            "type":"Services"
        }
    ],
    "sg:phone":"+1 712 655 3395",
    "sg:postcode":"51455",
    "sg:province":"IA",
    "wof:name":"Presbyterian Church First",
    "wof:placetype":"venue"
},
  "geometry": {"coordinates":[-95.061222,41.910196],"type":"Point"}
}