{
  "type": "Feature",
  "properties": {
    "iso:country":"US",
    "sg:address":"2485 State Hwy 92",
    "sg:city":"Washington",
    "sg:classifiers":[
        {
            "category":"Wholesale",
            "subcategory":"Farm Supplies",
            "type":"Manufacturing & Wholesale Goods"
        }
    ],
    "sg:phone":"+1 319 653 2288",
    "sg:postcode":"52353",
    "sg:province":"IA",
    "wof:name":"Pork N More",
    "wof:placetype":"venue"
},
  "geometry": {"coordinates":[-91.71551599999999,41.308851],"type":"Point"}
}