{
  "type": "Feature",
  "properties": {
    "iso:country":"US",
    "sg:address":"1000 Main St",
    "sg:city":"Dubuque",
    "sg:classifiers":[
        {
            "category":"Building & Trades",
            "subcategory":"Plumbing",
            "type":"Services"
        }
    ],
    "sg:phone":"+1 563 584 7666",
    "sg:postcode":"52001",
    "sg:province":"IA",
    "sg:tags":[
        "product",
        "management",
        "energy",
        "system"
    ],
    "wof:name":"Alliant Energy",
    "wof:placetype":"venue"
},
  "geometry": {"coordinates":[-90.668539,42.503294],"type":"Point"}
}