{
  "type": "Feature",
  "properties": {
    "iso:country":"US",
    "sg:address":"24571 170th St",
    "sg:city":"Rockford",
    "sg:classifiers":[
        {
            "category":"Farming",
            "subcategory":"Farm",
            "type":"Manufacturing & Wholesale Goods"
        }
    ],
    "sg:phone":"+1 641 822 4571",
    "sg:postcode":"50468",
    "sg:province":"IA",
    "sg:tags":[
        "crop",
        "general"
    ],
    "wof:name":"Brian Trevett",
    "wof:placetype":"venue"
},
  "geometry": {"coordinates":[-93.032625,43.008947],"type":"Point"}
}