{
  "type": "Feature",
  "properties": {
    "iso:country":"US",
    "sg:address":"3380 170th St",
    "sg:city":"Creston",
    "sg:phone":"+1 641 782 8067",
    "sg:postcode":"50801",
    "sg:province":"IA",
    "sg:tags":[
        "farm",
        "corn",
        "soybean"
    ],
    "wof:name":"Buxton Burdette",
    "wof:placetype":"venue"
},
  "geometry": {"coordinates":[-94.47438699999999,41.057943],"type":"Point"}
}