{
  "type": "Feature",
  "properties": {
    "iso:country":"US",
    "sg:address":"4705 Johnson Ave NW",
    "sg:city":"Cedar Rapids",
    "sg:classifiers":[
        {
            "category":"Autos & Motor Vehicles",
            "subcategory":"Automobile Sales",
            "type":"Retail Goods"
        }
    ],
    "sg:phone":"+1 319 390 3599",
    "sg:postcode":"52405",
    "sg:province":"IA",
    "sg:tags":[
        "car",
        "dealer"
    ],
    "sg:website":"www.fourguysauto.com",
    "wof:name":"Four Guys Auto",
    "wof:placetype":"venue"
},
  "geometry": {"coordinates":[-91.730238,41.969648],"type":"Point"}
}