{
  "type": "Feature",
  "properties": {
    "iso:country":"US",
    "sg:address":"1202 260th St",
    "sg:city":"Moorland",
    "sg:classifiers":[
        {
            "category":"Organizations",
            "subcategory":"Religious Organization",
            "type":"Services"
        }
    ],
    "sg:phone":"+1 515 549 3560",
    "sg:postcode":"50566",
    "sg:province":"IA",
    "wof:name":"Fulton Lutheran Church",
    "wof:placetype":"venue"
},
  "geometry": {"coordinates":[-94.358574,42.41251],"type":"Point"}
}