{
  "type": "Feature",
  "properties": {
    "addr:full":"814 Okoboji Ave Milford IA 51351",
    "addr:housenumber":"814",
    "addr:postcode":"51351",
    "addr:street":"Okoboji Ave",
    "iso:country":"US",
    "sg:address":"814 Okoboji Ave",
    "sg:city":"Milford",
    "sg:classifiers":[
        {
            "category":"Freight",
            "type":"Transportation"
        }
    ],
    "sg:phone":"+1 712 338 4191",
    "sg:postcode":"51351",
    "sg:province":"IA",
    "sg:tags":[
        "broker",
        "trucking"
    ],
    "wof:name":"Pioneer Transfer",
    "wof:placetype":"venue"
},
  "geometry": {"coordinates":[-95.149911,43.323725],"type":"Point"}
}