{
  "type": "Feature",
  "properties": {
    "iso:country":"US",
    "sg:address":"140 W 1st St",
    "sg:city":"Earlham",
    "sg:classifiers":[
        {
            "category":"Organizations",
            "subcategory":"Religious Organization",
            "type":"Services"
        }
    ],
    "sg:phone":"+1 515 758 2990",
    "sg:postcode":"50072",
    "sg:province":"IA",
    "sg:tags":[
        "church"
    ],
    "wof:name":"Crossroad Evangelical Free Chr",
    "wof:placetype":"venue"
},
  "geometry": {"coordinates":[-94.123983,41.491493],"type":"Point"}
}