{
  "type": "Feature",
  "properties": {
    "iso:country":"US",
    "sg:address":"1848 W 4th St",
    "sg:city":"Davenport",
    "sg:classifiers":[
        {
            "category":"Building & Trades",
            "subcategory":"Construction",
            "type":"Services"
        }
    ],
    "sg:phone":"+1 563 349 6027",
    "sg:postcode":"52802",
    "sg:province":"IA",
    "sg:tags":[
        "repairing",
        "remodeling",
        "contractor"
    ],
    "wof:name":"Complete Remodeling",
    "wof:placetype":"venue"
},
  "geometry": {"coordinates":[-90.60446399999999,41.523484],"type":"Point"}
}