{
  "type": "Feature",
  "properties": {
    "addr:full":"1811 1st St W Independence IA 50644",
    "addr:housenumber":"1811",
    "addr:postcode":"50644",
    "addr:street":"1St St W",
    "iso:country":"US",
    "sg:address":"1811 1st St W",
    "sg:city":"Independence",
    "sg:classifiers":[
        {
            "category":"Restaurant",
            "type":"Food & Drink"
        }
    ],
    "sg:menulink":"http://www.allmenus.com/ia/washington/202704-mcdonalds/menu/",
    "sg:postcode":"50644",
    "sg:province":"IA",
    "sg:tags":[
        "burger",
        "american"
    ],
    "wof:name":"McDonald's",
    "wof:placetype":"venue"
},
  "geometry": {"coordinates":[-91.90871300000001,42.468538],"type":"Point"}
}