{
  "type": "Feature",
  "properties": {
    "iso:country":"US",
    "sg:address":"201 Ridge St Ste 301",
    "sg:city":"Council Bluffs",
    "sg:classifiers":[
        {
            "category":"Health Services",
            "subcategory":"Doctor",
            "type":"Services"
        }
    ],
    "sg:phone":"+1 712 325 0980",
    "sg:postcode":"51503",
    "sg:province":"IA",
    "sg:tags":[
        "dermatologist"
    ],
    "wof:name":"Dolezal James F MD",
    "wof:placetype":"venue"
},
  "geometry": {"coordinates":[-95.834976,41.267865],"type":"Point"}
}