{
  "type": "Feature",
  "properties": {
    "iso:country":"US",
    "sg:address":"2655 State Hwy 2",
    "sg:city":"Fort Madison",
    "sg:classifiers":[
        {
            "category":"Home & Garden",
            "subcategory":"Garden Supply",
            "type":"Retail Goods"
        }
    ],
    "sg:phone":"+1 319 372 0573",
    "sg:postcode":"52627",
    "sg:province":"IA",
    "sg:tags":[
        "engine"
    ],
    "wof:name":"Tim's Repair Shop",
    "wof:placetype":"venue"
},
  "geometry": {"coordinates":[-91.343367,40.627082],"type":"Point"}
}