{
  "type": "Feature",
  "properties": {
    "addr:full":"907 Alice Ave Riverton IA 51650",
    "addr:housenumber":"907",
    "addr:postcode":"51650",
    "addr:street":"Alice Ave",
    "iso:country":"US",
    "sg:address":"907 Alice Ave",
    "sg:city":"Riverton",
    "sg:classifiers":[
        {
            "category":"Retail",
            "subcategory":"Funeral Services",
            "type":"Services"
        }
    ],
    "sg:phone":"+1 712 387 2401",
    "sg:postcode":"51650",
    "sg:province":"IA",
    "sg:tags":[
        "director"
    ],
    "wof:name":"Shull-Gude Funeral Home",
    "wof:placetype":"venue"
},
  "geometry": {"coordinates":[-95.56488,40.687957],"type":"Point"}
}