{
  "type": "Feature",
  "properties": {
    "addr:full":"1283 Primrose Rd Donnellson IA 52625",
    "addr:housenumber":"1283",
    "addr:postcode":"52625",
    "addr:street":"Primrose Rd",
    "iso:country":"US",
    "sg:address":"1283 Primrose Rd",
    "sg:city":"Donnellson",
    "sg:classifiers":[
        {
            "category":"Farming",
            "subcategory":"Livestock Farm",
            "type":"Manufacturing & Wholesale Goods"
        }
    ],
    "sg:phone":"+1 319 836 2217",
    "sg:postcode":"52625",
    "sg:province":"IA",
    "sg:tags":[
        "hog",
        "beef",
        "crop",
        "field",
        "cattle",
        "or",
        "feedlot"
    ],
    "wof:name":"Jerry McCarty",
    "wof:placetype":"venue"
},
  "geometry": {"coordinates":[-91.674347,40.663971],"type":"Point"}
}