{
  "type": "Feature",
  "properties": {
    "iso:country":"US",
    "sg:address":"106 N Front St",
    "sg:city":"Montezuma",
    "sg:classifiers":[
        {
            "category":"Restaurant",
            "type":"Food & Drink"
        }
    ],
    "sg:phone":"+1 641 623 3678",
    "sg:postcode":"50171",
    "sg:province":"IA",
    "wof:name":"Home Town Restaurant",
    "wof:placetype":"venue"
},
  "geometry": {"coordinates":[-92.527308,41.586275],"type":"Point"}
}