{
  "type": "Feature",
  "properties": {
    "iso:country":"US",
    "sg:address":"11395 S 60th Ave W",
    "sg:city":"Prairie City",
    "sg:phone":"+1 515 994 2842",
    "sg:postcode":"50228",
    "sg:province":"IA",
    "sg:tags":[
        "farm",
        "field",
        "corn",
        "soybean",
        "crop"
    ],
    "wof:name":"Marvin Mc Reynolds",
    "wof:placetype":"venue"
},
  "geometry": {"coordinates":[-93.271034,41.630148],"type":"Point"}
}