{
  "type": "Feature",
  "properties": {
    "iso:country":"US",
    "sg:address":"3000 4th St SW",
    "sg:city":"Mason City",
    "sg:classifiers":[
        {
            "category":"Restaurant",
            "type":"Food & Drink"
        }
    ],
    "sg:phone":"+1 641 424 8153",
    "sg:postcode":"50401",
    "sg:province":"IA",
    "wof:name":"Prime N' Wine",
    "wof:placetype":"venue"
},
  "geometry": {"coordinates":[-93.246988,43.148467],"type":"Point"}
}