{
  "type": "Feature",
  "properties": {
    "iso:country":"US",
    "sg:address":"109 W 4th St",
    "sg:city":"Moulton",
    "sg:classifiers":[
        {
            "category":"Personal",
            "subcategory":"Beauty Salon",
            "type":"Services"
        }
    ],
    "sg:phone":"+1 641 642 3116",
    "sg:postcode":"52572",
    "sg:province":"IA",
    "sg:tags":[
        "hair",
        "stylist"
    ],
    "wof:name":"Cuttn' Up",
    "wof:placetype":"venue"
},
  "geometry": {"coordinates":[-92.677249,40.684891],"type":"Point"}
}