{
  "type": "Feature",
  "properties": {
    "addr:full":"11651 NW 121st St Granger IA 50109",
    "addr:housenumber":"11651",
    "addr:postcode":"50109",
    "addr:street":"Nw 121St St",
    "iso:country":"US",
    "sg:address":"11651 NW 121st St",
    "sg:city":"Granger",
    "sg:classifiers":[
        {
            "category":"Building & Trades",
            "subcategory":"Construction",
            "type":"Services"
        }
    ],
    "sg:phone":"+1 515 999 2393",
    "sg:postcode":"50109",
    "sg:province":"IA",
    "sg:tags":[
        "residential"
    ],
    "wof:name":"Umthun Construction",
    "wof:placetype":"venue"
},
  "geometry": {"coordinates":[-93.784492,41.773817],"type":"Point"}
}