{
  "type": "Feature",
  "properties": {
    "iso:country":"US",
    "sg:address":"308 Adams St SE",
    "sg:city":"Cascade",
    "sg:classifiers":[
        {
            "category":"Building & Trades",
            "subcategory":"Construction",
            "type":"Services"
        }
    ],
    "sg:phone":"+1 563 852 7649",
    "sg:postcode":"52033",
    "sg:province":"IA",
    "sg:tags":[
        "general",
        "contractor"
    ],
    "wof:name":"B & L Manternach Construction",
    "wof:placetype":"venue"
},
  "geometry": {"coordinates":[-91.000394,42.300471],"type":"Point"}
}