{
  "type": "Feature",
  "properties": {
    "addr:full":"1920 Florida Ave Bradgate IA 50520",
    "addr:housenumber":"1920",
    "addr:postcode":"50520",
    "addr:street":"Florida Ave Bradgate",
    "iso:country":"US",
    "sg:address":"1920 Florida Ave",
    "sg:city":"Bradgate",
    "sg:classifiers":[
        {
            "category":"Shopping",
            "type":"Retail Goods"
        }
    ],
    "sg:phone":"+1 515 332 2804",
    "sg:postcode":"50520",
    "sg:province":"IA",
    "sg:tags":[
        "cosmetic",
        "perfume"
    ],
    "wof:name":"Mary Kay Cosmetics",
    "wof:placetype":"venue"
},
  "geometry": {"coordinates":[-94.339845,42.768339],"type":"Point"}
}