{
  "type": "Feature",
  "properties": {
    "addr:full":"300 School St Goldfield IA 50542",
    "addr:housenumber":"300",
    "addr:postcode":"50542",
    "addr:street":"School St",
    "iso:country":"US",
    "sg:address":"300 School St",
    "sg:city":"Goldfield",
    "sg:classifiers":[
        {
            "category":"Education",
            "subcategory":"School",
            "type":"Public Place"
        }
    ],
    "sg:phone":"+1 515 825 3173",
    "sg:postcode":"50542",
    "sg:province":"IA",
    "wof:name":"Goldfield Elementary School",
    "wof:placetype":"venue"
},
  "geometry": {"coordinates":[-93.924414,42.734269],"type":"Point"}
}