{
  "type": "Feature",
  "properties": {
    "iso:country":"US",
    "sg:address":"504 3rd Ave NW",
    "sg:city":"Farley",
    "sg:classifiers":[
        {
            "category":"Arts & Performance",
            "subcategory":"Theater",
            "type":"Entertainment"
        }
    ],
    "sg:phone":"+1 563 744 3608",
    "sg:postcode":"52046",
    "sg:province":"IA",
    "sg:tags":[
        "live",
        "music"
    ],
    "wof:name":"Rich Reinhardt's Soundwave",
    "wof:placetype":"venue"
},
  "geometry": {"coordinates":[-91.011115,42.444517],"type":"Point"}
}