{
  "type": "Feature",
  "properties": {
    "addr:full":"721 W Cedar St Cherokee IA 51012",
    "addr:housenumber":"721",
    "addr:postcode":"51012",
    "addr:street":"W Cedar St",
    "iso:country":"US",
    "sg:address":"721 W Cedar St",
    "sg:city":"Cherokee",
    "sg:classifiers":[
        {
            "category":"Organizations",
            "subcategory":"Religious Organization",
            "type":"Services"
        }
    ],
    "sg:phone":"+1 712 225 4572",
    "sg:postcode":"51012",
    "sg:province":"IA",
    "wof:name":"Hall Immaculate Conception",
    "wof:placetype":"venue"
},
  "geometry": {"coordinates":[-95.560068,42.751719],"type":"Point"}
}