{
  "type": "Feature",
  "properties": {
    "iso:country":"US",
    "sg:address":"308 Franklin St",
    "sg:city":"Delhi",
    "sg:classifiers":[
        {
            "category":"Restaurant",
            "type":"Food & Drink"
        }
    ],
    "sg:phone":"+1 563 922 2782",
    "sg:postcode":"52223",
    "sg:province":"IA",
    "wof:name":"Delhi Stadium",
    "wof:placetype":"venue"
},
  "geometry": {"coordinates":[-91.332426,42.429743],"type":"Point"}
}