{
  "type": "Feature",
  "properties": {
    "addr:full":"215 Main St Beaman IA 50609",
    "addr:housenumber":"215",
    "addr:postcode":"50609",
    "addr:street":"Main St",
    "iso:country":"US",
    "sg:address":"215 Main St",
    "sg:city":"Beaman",
    "sg:classifiers":[
        {
            "category":"Recreation",
            "type":"Entertainment"
        }
    ],
    "sg:phone":"+1 641 366 2798",
    "sg:postcode":"50609",
    "sg:province":"IA",
    "sg:tags":[
        "hall",
        "auditorium"
    ],
    "wof:name":"Beaman Memorial Hall",
    "wof:placetype":"venue"
},
  "geometry": {"coordinates":[-92.823516,42.22024],"type":"Point"}
}