{
  "type": "Feature",
  "properties": {
    "addr:full":"306 W 1st St Leon IA 50144",
    "addr:housenumber":"306",
    "addr:postcode":"50144",
    "addr:street":"W 1St",
    "iso:country":"US",
    "sg:address":"306 W 1st St",
    "sg:city":"Leon",
    "sg:classifiers":[
        {
            "category":"Shopping",
            "type":"Retail Goods"
        }
    ],
    "sg:phone":"+1 641 446 4349",
    "sg:postcode":"50144",
    "sg:province":"IA",
    "sg:tags":[
        "merchandise",
        "monument"
    ],
    "wof:name":"Goughnour Monument",
    "wof:placetype":"venue"
},
  "geometry": {"coordinates":[-93.749273,40.739592],"type":"Point"}
}