{
  "type": "Feature",
  "properties": {
    "addr:full":"2147 Underwood Ave Charles City IA 50616",
    "addr:housenumber":"2147",
    "addr:postcode":"50616",
    "addr:street":"Underwood Ave",
    "iso:country":"US",
    "sg:address":"2147 Underwood Ave",
    "sg:city":"Charles City",
    "sg:classifiers":[
        {
            "category":"Sports & Exercise",
            "subcategory":"Golf",
            "type":"Entertainment"
        }
    ],
    "sg:phone":"+1 641 228 6465",
    "sg:postcode":"50616",
    "sg:province":"IA",
    "sg:tags":[
        "course"
    ],
    "wof:name":"Charles City Golf Course",
    "wof:placetype":"venue"
},
  "geometry": {"coordinates":[-92.633426,43.047685],"type":"Point"}
}