{
  "type": "Feature",
  "properties": {
    "addr:full":"1824 Iowa St Davenport IA 52803",
    "addr:housenumber":"1824",
    "addr:postcode":"52803",
    "addr:street":"Iowa St",
    "iso:country":"US",
    "sg:address":"1824 Iowa St",
    "sg:city":"Davenport",
    "sg:classifiers":[
        {
            "category":"Personal",
            "subcategory":"Beauty Salon",
            "type":"Services"
        }
    ],
    "sg:phone":"+1 563 322 3193",
    "sg:postcode":"52803",
    "sg:province":"IA",
    "sg:tags":[
        "shop"
    ],
    "wof:name":"Maxine's Beauty Shop",
    "wof:placetype":"venue"
},
  "geometry": {"coordinates":[-90.569744,41.53776],"type":"Point"}
}