{
  "type": "Feature",
  "properties": {
    "addr:full":"305 N 1st St Marshalltown IA 50158",
    "addr:housenumber":"305",
    "addr:postcode":"50158",
    "addr:street":"N 1St St",
    "iso:country":"US",
    "sg:address":"305 N 1st St",
    "sg:city":"Marshalltown",
    "sg:classifiers":[
        {
            "category":"Arts & Performance",
            "subcategory":"Theater",
            "type":"Entertainment"
        }
    ],
    "sg:phone":"+1 641 752 4183",
    "sg:postcode":"50158",
    "sg:province":"IA",
    "sg:tags":[
        "group"
    ],
    "wof:name":"Soundwave D JS",
    "wof:placetype":"venue"
},
  "geometry": {"coordinates":[-92.914536,42.054395],"type":"Point"}
}