{
  "type": "Feature",
  "properties": {
    "iso:country":"US",
    "sg:address":"103 E 9th St",
    "sg:city":"New Market",
    "sg:classifiers":[
        {
            "category":"Building & Trades",
            "subcategory":"Construction",
            "type":"Services"
        }
    ],
    "sg:phone":"+1 712 585 3379",
    "sg:postcode":"51646",
    "sg:province":"IA",
    "sg:tags":[
        "house"
    ],
    "wof:name":"3 D Construction",
    "wof:placetype":"venue"
},
  "geometry": {"coordinates":[-94.897514,40.73605],"type":"Point"}
}