{
  "type": "Feature",
  "properties": {
    "addr:full":"719 W 10th St Spencer IA 51301",
    "addr:housenumber":"719",
    "addr:postcode":"51301",
    "addr:street":"W 10Th St",
    "iso:country":"US",
    "sg:address":"719 W 10th St",
    "sg:city":"Spencer",
    "sg:classifiers":[
        {
            "category":"Home & Garden",
            "subcategory":"Garden Supply",
            "type":"Retail Goods"
        }
    ],
    "sg:phone":"+1 712 580 7102",
    "sg:postcode":"51301",
    "sg:province":"IA",
    "sg:tags":[
        "bulb",
        "seed"
    ],
    "wof:name":"NK Seeds",
    "wof:placetype":"venue"
},
  "geometry": {"coordinates":[-95.156486,43.147627],"type":"Point"}
}