{
  "type": "Feature",
  "properties": {
    "addr:full":"1228 Zimmerman Dr Grinnell IA 50112",
    "addr:housenumber":"1228",
    "addr:postcode":"50112",
    "addr:street":"Zimmerman Dr",
    "iso:country":"US",
    "sg:address":"1228 Zimmerman Dr",
    "sg:city":"Grinnell",
    "sg:classifiers":[
        {
            "category":"Manufacturing",
            "subcategory":"Tools & Machinery",
            "type":"Manufacturing & Wholesale Goods"
        }
    ],
    "sg:phone":"+1 641 236 5312",
    "sg:postcode":"50112",
    "sg:province":"IA",
    "sg:tags":[
        "farm",
        "equipment"
    ],
    "wof:name":"H W Brand",
    "wof:placetype":"venue"
},
  "geometry": {"coordinates":[-92.725604,41.716568],"type":"Point"}
}