{
  "type": "Feature",
  "properties": {
    "iso:country":"US",
    "sg:address":"1065 403rd Ave",
    "sg:city":"Estherville",
    "sg:classifiers":[
        {
            "category":"Transit Center",
            "subcategory":"Freight",
            "type":"Transportation"
        },
        {
            "category":"Freight",
            "type":"Transportation"
        }
    ],
    "sg:phone":"+1 712 362 2998",
    "sg:postcode":"51334",
    "sg:province":"IA",
    "sg:tags":[
        "local",
        "trucking-motor",
        "trucking"
    ],
    "wof:name":"Verlin Heinrichs Trucking",
    "wof:placetype":"venue"
},
  "geometry": {"coordinates":[-94.791878,43.490648],"type":"Point"}
}