{
  "type": "Feature",
  "properties": {
    "iso:country":"US",
    "sg:address":"908 S 2nd St",
    "sg:city":"Cherokee",
    "sg:classifiers":[
        {
            "category":"Retail",
            "subcategory":"Veterinary Services",
            "type":"Services"
        }
    ],
    "sg:phone":"+1 712 225 5200",
    "sg:postcode":"51012",
    "sg:province":"IA",
    "sg:tags":[
        "veterinarian"
    ],
    "wof:name":"Valley Veterinary Ctr",
    "wof:placetype":"venue"
},
  "geometry": {"coordinates":[-95.55151600000001,42.742316],"type":"Point"}
}