{
  "type": "Feature",
  "properties": {
    "iso:country":"US",
    "sg:address":"1777 140th St",
    "sg:city":"Lake Park",
    "sg:phone":"+1 712 832 3815",
    "sg:postcode":"51347",
    "sg:province":"IA",
    "sg:tags":[
        "farm",
        "corn",
        "soybean"
    ],
    "wof:name":"Jon P & Margaret A Gunderson",
    "wof:placetype":"venue"
},
  "geometry": {"coordinates":[-95.23087200000001,43.44485],"type":"Point"}
}