{
  "type": "Feature",
  "properties": {
    "iso:country":"US",
    "sg:address":"757 S Gilbert St",
    "sg:city":"Iowa City",
    "sg:classifiers":[
        {
            "category":"Insurance",
            "subcategory":"Insurance Agent",
            "type":"Services"
        }
    ],
    "sg:phone":"+1 319 351 2244",
    "sg:postcode":"52240",
    "sg:province":"IA",
    "sg:website":"www.freemanins.com",
    "wof:name":"Freeman Insurance Inc",
    "wof:placetype":"venue"
},
  "geometry": {"coordinates":[-91.531015,41.652936],"type":"Point"}
}