{
  "type": "Feature",
  "properties": {
    "addr:full":"105 N 6th St Knoxville IA 50138",
    "addr:housenumber":"105",
    "addr:postcode":"50138",
    "addr:street":"N 6Th St",
    "iso:country":"US",
    "sg:address":"105 N 6th St",
    "sg:city":"Knoxville",
    "sg:classifiers":[
        {
            "category":"Building & Trades",
            "subcategory":"Electrical",
            "type":"Services"
        }
    ],
    "sg:phone":"+1 641 842 2696",
    "sg:postcode":"50138",
    "sg:province":"IA",
    "sg:tags":[
        "electric",
        "contractor"
    ],
    "wof:name":"Advanced Electrical",
    "wof:placetype":"venue"
},
  "geometry": {"coordinates":[-93.092855,41.318975],"type":"Point"}
}