{
  "type": "Feature",
  "properties": {
    "iso:country":"US",
    "sg:address":"2952 Brady St",
    "sg:city":"Davenport",
    "sg:classifiers":[
        {
            "category":"Shopping",
            "subcategory":"Bicycles & Sporting Goods",
            "type":"Retail Goods"
        }
    ],
    "sg:phone":"+1 563 324 3209",
    "sg:postcode":"52803",
    "sg:province":"IA",
    "wof:name":"Proconnection Proshop",
    "wof:placetype":"venue"
},
  "geometry": {"coordinates":[-90.57055699999999,41.550176],"type":"Point"}
}