{
  "type": "Feature",
  "properties": {
    "addr:full":"909 E River Dr Des Moines IA 50316",
    "addr:housenumber":"909",
    "addr:postcode":"50316",
    "addr:street":"E River Dr",
    "iso:country":"US",
    "sg:address":"909 E River Dr",
    "sg:city":"Des Moines",
    "sg:classifiers":[
        {
            "category":"Shopping",
            "subcategory":"Gifts & Souvenirs",
            "type":"Retail Goods"
        }
    ],
    "sg:phone":"+1 515 323 8907",
    "sg:postcode":"50316",
    "sg:province":"IA",
    "sg:tags":[
        "executive"
    ],
    "wof:name":"Botanical Center",
    "wof:placetype":"venue"
},
  "geometry": {"coordinates":[-93.61471,41.596554],"type":"Point"}
}