{
  "type": "Feature",
  "properties": {
    "iso:country":"US",
    "sg:address":"17407 Iowa City Rd",
    "sg:city":"Sperry",
    "sg:phone":"+1 319 985 2411",
    "sg:postcode":"52650",
    "sg:province":"IA",
    "sg:tags":[
        "farm",
        "corn"
    ],
    "wof:name":"Jo Taeger",
    "wof:placetype":"venue"
},
  "geometry": {"coordinates":[-91.179744,40.933026],"type":"Point"}
}