{
  "type": "Feature",
  "properties": {
    "addr:full":"425 Main Ave Clear Lake IA 50428",
    "addr:housenumber":"425",
    "addr:postcode":"50428",
    "addr:street":"Main Ave",
    "iso:country":"US",
    "sg:address":"425 Main Ave",
    "sg:city":"Clear Lake",
    "sg:classifiers":[
        {
            "category":"Restaurant",
            "type":"Food & Drink"
        }
    ],
    "sg:phone":"+1 641 357 1740",
    "sg:postcode":"50428",
    "sg:province":"IA",
    "wof:name":"Azzolina's Hole In The Wall",
    "wof:placetype":"venue"
},
  "geometry": {"coordinates":[-93.380157,43.136919],"type":"Point"}
}