{
  "type": "Feature",
  "properties": {
    "addr:full":"433 Westwood Dr Ames IA 50014",
    "addr:housenumber":"433",
    "addr:postcode":"50014",
    "addr:street":"Westwood Dr",
    "iso:country":"US",
    "sg:address":"433 Westwood Dr",
    "sg:city":"Ames",
    "sg:classifiers":[
        {
            "category":"Real Estate",
            "subcategory":"Real Estate Agent",
            "type":"Services"
        }
    ],
    "sg:phone":"+1 515 292 4517",
    "sg:postcode":"50014",
    "sg:province":"IA",
    "wof:name":"CPM Inc",
    "wof:placetype":"venue"
},
  "geometry": {"coordinates":[-93.668142,42.02769],"type":"Point"}
}