{
  "type": "Feature",
  "properties": {
    "iso:country":"US",
    "sg:address":"3103 Michel Ave",
    "sg:city":"Rowley",
    "sg:classifiers":[
        {
            "category":"Farming",
            "subcategory":"Farm",
            "type":"Manufacturing & Wholesale Goods"
        }
    ],
    "sg:phone":"+1 319 938 2859",
    "sg:postcode":"52329",
    "sg:province":"IA",
    "sg:tags":[
        "crop",
        "general"
    ],
    "wof:name":"Ziesers Farming",
    "wof:placetype":"venue"
},
  "geometry": {"coordinates":[-91.83093,42.341958],"type":"Point"}
}