{
  "type": "Feature",
  "properties": {
    "iso:country":"US",
    "sg:address":"223 W 7th St",
    "sg:city":"Spencer",
    "sg:classifiers":[
        {
            "category":"Retail",
            "subcategory":"Veterinary Services",
            "type":"Services"
        }
    ],
    "sg:phone":"+1 712 262 5552",
    "sg:postcode":"51301",
    "sg:province":"IA",
    "sg:tags":[
        "veterinarian"
    ],
    "sg:website":"www.siouxnationag.com",
    "wof:name":"Sioux Nation Vet & Feed Supply",
    "wof:placetype":"venue"
},
  "geometry": {"coordinates":[-95.14882799999999,43.144016],"type":"Point"}
}