{
  "type": "Feature",
  "properties": {
    "addr:full":"1450 265th St Eagle Grove IA 50533",
    "addr:housenumber":"1450",
    "addr:postcode":"50533",
    "addr:street":"265Th St",
    "iso:country":"US",
    "sg:address":"1450 265th St",
    "sg:city":"Eagle Grove",
    "sg:classifiers":[
        {
            "category":"Professional",
            "type":"Services"
        }
    ],
    "sg:phone":"+1 515 448 4979",
    "sg:postcode":"50533",
    "sg:province":"IA",
    "sg:tags":[
        "establishment"
    ],
    "wof:name":"Spangler Inc",
    "wof:placetype":"venue"
},
  "geometry": {"coordinates":[-93.88297300000001,42.666485],"type":"Point"}
}