{
  "type": "Feature",
  "properties": {
    "addr:full":"1901 9th Ave SW Cedar Rapids IA 52404",
    "addr:housenumber":"1901",
    "addr:postcode":"52404",
    "addr:street":"9Th Ave Sw",
    "iso:country":"US",
    "sg:address":"1901 9th Ave SW",
    "sg:city":"Cedar Rapids",
    "sg:classifiers":[
        {
            "category":"Real Estate",
            "subcategory":"Real Estate Agent",
            "type":"Services"
        }
    ],
    "sg:phone":"+1 319 721 7229",
    "sg:postcode":"52404",
    "sg:province":"IA",
    "wof:name":"Skogman Realtors",
    "wof:placetype":"venue"
},
  "geometry": {"coordinates":[-91.698578,41.96807],"type":"Point"}
}