{
  "type": "Feature",
  "properties": {
    "addr:full":"2075 NW 92nd Ct Clive IA 50325",
    "addr:housenumber":"2075",
    "addr:postcode":"50325",
    "addr:street":"Nw 92Nd Ct",
    "iso:country":"US",
    "sg:address":"2075 NW 92nd Ct",
    "sg:city":"Clive",
    "sg:classifiers":[
        {
            "category":"Wholesale",
            "subcategory":"Meat",
            "type":"Manufacturing & Wholesale Goods"
        }
    ],
    "sg:phone":"+1 515 225 6868",
    "sg:postcode":"50325",
    "sg:province":"IA",
    "sg:tags":[
        "product"
    ],
    "wof:name":"Iowa Quality Meats LTD",
    "wof:placetype":"venue"
},
  "geometry": {"coordinates":[-93.743302,41.609036],"type":"Point"}
}