{
  "type": "Feature",
  "properties": {
    "addr:full":"2103 Commerce Dr Grundy Center IA 50638",
    "addr:housenumber":"2103",
    "addr:postcode":"50638",
    "addr:street":"Commerce Dr",
    "iso:country":"US",
    "sg:address":"2103 Commerce Dr",
    "sg:city":"Grundy Center",
    "sg:classifiers":[
        {
            "category":"Restaurant",
            "type":"Food & Drink"
        }
    ],
    "sg:phone":"+1 319 824 6000",
    "sg:postcode":"50638",
    "sg:province":"IA",
    "sg:tags":[
        "eating"
    ],
    "wof:name":"Stoppy's All Star Restaurant",
    "wof:placetype":"venue"
},
  "geometry": {"coordinates":[-92.794088,42.361309],"type":"Point"}
}