{
  "type": "Feature",
  "properties": {
    "iso:country":"US",
    "sg:address":"1900 Ithaca Ave",
    "sg:city":"Spirit Lake",
    "sg:classifiers":[
        {
            "category":"Professional",
            "type":"Services"
        }
    ],
    "sg:phone":"+1 712 336 2136",
    "sg:postcode":"51360",
    "sg:province":"IA",
    "sg:tags":[
        "establishment"
    ],
    "wof:name":"Courthouse Annex",
    "wof:placetype":"venue"
},
  "geometry": {"coordinates":[-95.10365400000001,43.421728],"type":"Point"}
}