{
  "type": "Feature",
  "properties": {
    "iso:country":"US",
    "sg:address":"202 Winnebago St",
    "sg:city":"Decorah",
    "sg:classifiers":[
        {
            "category":"Education",
            "subcategory":"Library",
            "type":"Public Place"
        }
    ],
    "sg:phone":"+1 563 382 3717",
    "sg:postcode":"52101",
    "sg:province":"IA",
    "wof:name":"Decorah Public Library",
    "wof:placetype":"venue"
},
  "geometry": {"coordinates":[-91.787086,43.303239],"type":"Point"}
}