{
  "type": "Feature",
  "properties": {
    "iso:country":"US",
    "sg:address":"211 Plymouth St NE",
    "sg:city":"Le Mars",
    "sg:classifiers":[
        {
            "category":"Retail",
            "subcategory":"Auto Repair",
            "type":"Services"
        }
    ],
    "sg:phone":"+1 712 546 4421",
    "sg:postcode":"51031",
    "sg:province":"IA",
    "sg:tags":[
        "body",
        "automobile",
        "painting"
    ],
    "wof:name":"Singer Body & Glass Shop",
    "wof:placetype":"venue"
},
  "geometry": {"coordinates":[-96.16351400000001,42.793137],"type":"Point"}
}