{
  "type": "Feature",
  "properties": {
    "iso:country":"US",
    "sg:address":"401 State Hwy 175",
    "sg:city":"Ida Grove",
    "sg:classifiers":[
        {
            "category":"Food & Beverages",
            "subcategory":"Groceries & Convenience Stores",
            "type":"Retail Goods"
        }
    ],
    "sg:phone":"+1 712 364 4195",
    "sg:postcode":"51445",
    "sg:province":"IA",
    "wof:name":"Pronto Convenience Store",
    "wof:placetype":"venue"
},
  "geometry": {"coordinates":[-95.471797,42.35198],"type":"Point"}
}