{
  "type": "Feature",
  "properties": {
    "iso:country":"US",
    "sg:address":"1959 Apache Dr",
    "sg:city":"Marion",
    "sg:classifiers":[
        {
            "category":"Building & Trades",
            "subcategory":"Construction",
            "type":"Services"
        }
    ],
    "sg:phone":"+1 319 377 6400",
    "sg:postcode":"52302",
    "sg:province":"IA",
    "sg:tags":[
        "general",
        "contractor"
    ],
    "wof:name":"Mike's Quality Construction",
    "wof:placetype":"venue"
},
  "geometry": {"coordinates":[-91.547515,42.042287],"type":"Point"}
}