{
  "type": "Feature",
  "properties": {
    "iso:country":"US",
    "sg:address":"1801 200th St",
    "sg:city":"Algona",
    "sg:classifiers":[
        {
            "category":"Farming",
            "subcategory":"Livestock Farm",
            "type":"Manufacturing & Wholesale Goods"
        }
    ],
    "sg:phone":"+1 515 295 2941",
    "sg:postcode":"50511",
    "sg:province":"IA",
    "sg:tags":[
        "feedlot",
        "hog",
        "corn",
        "or",
        "soybean"
    ],
    "wof:name":"Russell Spear",
    "wof:placetype":"venue"
},
  "geometry": {"coordinates":[-94.089226,43.05224],"type":"Point"}
}