{
  "type": "Feature",
  "properties": {
    "iso:country":"US",
    "sg:address":"1100 E Chestnut St",
    "sg:city":"Clarinda",
    "sg:classifiers":[
        {
            "category":"Building & Trades",
            "subcategory":"Plumbing",
            "type":"Services"
        }
    ],
    "sg:phone":"+1 712 542 3007",
    "sg:postcode":"51632",
    "sg:province":"IA",
    "sg:tags":[
        "plumbing",
        "contractor"
    ],
    "wof:name":"Wallin Plumbing & Heating",
    "wof:placetype":"venue"
},
  "geometry": {"coordinates":[-95.025121,40.740241],"type":"Point"}
}