{
  "type": "Feature",
  "properties": {
    "addr:full":"105 E Amy St Baxter IA 50028",
    "addr:housenumber":"105",
    "addr:postcode":"50028",
    "addr:street":"E Amy St",
    "iso:country":"US",
    "sg:address":"105 E Amy St",
    "sg:city":"Baxter",
    "sg:classifiers":[
        {
            "category":"Manufacturing",
            "subcategory":"Glass & Minerals",
            "type":"Manufacturing & Wholesale Goods"
        }
    ],
    "sg:phone":"+1 641 227 3421",
    "sg:postcode":"50028",
    "sg:province":"IA",
    "sg:tags":[
        "ready"
    ],
    "wof:name":"American Concrete Products",
    "wof:placetype":"venue"
},
  "geometry": {"coordinates":[-93.151343,41.828862],"type":"Point"}
}