{
  "type": "Feature",
  "properties": {
    "iso:country":"US",
    "sg:address":"1236 236th Ave",
    "sg:city":"Fort Atkinson",
    "sg:classifiers":[
        {
            "category":"Wholesale",
            "subcategory":"Dairy",
            "type":"Manufacturing & Wholesale Goods"
        }
    ],
    "sg:phone":"+1 563 534 7290",
    "sg:postcode":"52144",
    "sg:province":"IA",
    "sg:tags":[
        "product"
    ],
    "wof:name":"A M P I",
    "wof:placetype":"venue"
},
  "geometry": {"coordinates":[-91.86729099999999,43.117233],"type":"Point"}
}