{
  "type": "Feature",
  "properties": {
    "addr:full":"1840 N West St Carroll IA 51401",
    "addr:housenumber":"1840",
    "addr:postcode":"51401",
    "addr:street":"N West St",
    "iso:country":"US",
    "sg:address":"1840 N West St",
    "sg:city":"Carroll",
    "sg:classifiers":[
        {
            "category":"Retail",
            "subcategory":"Repair Shop",
            "type":"Services"
        }
    ],
    "sg:phone":"+1 712 792 9821",
    "sg:postcode":"51401",
    "sg:province":"IA",
    "wof:name":"Larrys Pianoshop",
    "wof:placetype":"venue"
},
  "geometry": {"coordinates":[-94.868852,42.07919],"type":"Point"}
}