{
  "type": "Feature",
  "properties": {
    "iso:country":"US",
    "sg:address":"21 S Frederick Ave",
    "sg:city":"Oelwein",
    "sg:classifiers":[
        {
            "category":"Manufacturing",
            "subcategory":"Signs",
            "type":"Manufacturing & Wholesale Goods"
        }
    ],
    "sg:phone":"+1 319 283 3690",
    "sg:postcode":"50662",
    "sg:province":"IA",
    "wof:name":"Dsign Originals",
    "wof:placetype":"venue"
},
  "geometry": {"coordinates":[-91.913284,42.67819],"type":"Point"}
}