{
  "type": "Feature",
  "properties": {
    "addr:full":"606 N 2nd St Bellevue IA 52031",
    "addr:housenumber":"606",
    "addr:postcode":"52031",
    "addr:street":"N 2Nd St",
    "iso:country":"US",
    "sg:address":"606 N 2nd St",
    "sg:city":"Bellevue",
    "sg:classifiers":[
        {
            "category":"Building & Trades",
            "subcategory":"Landscaping Services",
            "type":"Services"
        }
    ],
    "sg:phone":"+1 563 872 4066",
    "sg:postcode":"52031",
    "sg:province":"IA",
    "wof:name":"Steve Roling Logging",
    "wof:placetype":"venue"
},
  "geometry": {"coordinates":[-90.426523,42.263443],"type":"Point"}
}