{
  "type": "Feature",
  "properties": {
    "iso:country":"US",
    "sg:address":"1415 56th St",
    "sg:city":"Garrison",
    "sg:classifiers":[
        {
            "category":"Personal",
            "type":"Services"
        }
    ],
    "sg:phone":"+1 319 342 2446",
    "sg:postcode":"52229",
    "sg:province":"IA",
    "wof:name":"Steve Vaughn",
    "wof:placetype":"venue"
},
  "geometry": {"coordinates":[-92.217731,42.210744],"type":"Point"}
}