{
  "type": "Feature",
  "properties": {
    "addr:full":"3707 Needham Ave Wall Lake IA 51466",
    "addr:housenumber":"3707",
    "addr:postcode":"51466",
    "addr:street":"Needham Ave Wall",
    "iso:country":"US",
    "sg:address":"3707 Needham Ave",
    "sg:city":"Wall Lake",
    "sg:classifiers":[
        {
            "category":"Wholesale",
            "subcategory":"Meat",
            "type":"Manufacturing & Wholesale Goods"
        }
    ],
    "sg:phone":"+1 712 664 2595",
    "sg:postcode":"51466",
    "sg:province":"IA",
    "sg:tags":[
        "product"
    ],
    "wof:name":"Swift & Co",
    "wof:placetype":"venue"
},
  "geometry": {"coordinates":[-95.090694,42.246773],"type":"Point"}
}