{
  "type": "Feature",
  "properties": {
    "iso:country":"US",
    "sg:address":"801 400th St",
    "sg:city":"Swea City",
    "sg:phone":"+1 515 272 4266",
    "sg:postcode":"50590",
    "sg:province":"IA",
    "sg:tags":[
        "farm",
        "corn",
        "soybean"
    ],
    "wof:name":"Jerry Sanftner",
    "wof:placetype":"venue"
},
  "geometry": {"coordinates":[-94.301535,43.342054],"type":"Point"}
}