{
  "type": "Feature",
  "properties": {
    "addr:full":"2525 Rockingham Rd Davenport IA 52802",
    "addr:housenumber":"2525",
    "addr:postcode":"52802",
    "addr:street":"Rockingham Rd",
    "iso:country":"US",
    "sg:address":"2525 Rockingham Rd",
    "sg:city":"Davenport",
    "sg:classifiers":[
        {
            "category":"Retail",
            "subcategory":"Auto Repair",
            "type":"Services"
        }
    ],
    "sg:phone":"+1 563 322 2265",
    "sg:postcode":"52802",
    "sg:province":"IA",
    "sg:tags":[
        "automobile",
        "diagnostic"
    ],
    "wof:name":"Southwest Automotive",
    "wof:placetype":"venue"
},
  "geometry": {"coordinates":[-90.615205,41.513269],"type":"Point"}
}