{
  "type": "Feature",
  "properties": {
    "iso:country":"US",
    "sg:address":"500 W Main St",
    "sg:city":"Anamosa",
    "sg:classifiers":[
        {
            "category":"Government",
            "subcategory":"Office",
            "type":"Public Place"
        }
    ],
    "sg:phone":"+1 319 462 4457",
    "sg:postcode":"52205",
    "sg:province":"IA",
    "wof:name":"Jones County Community Svc",
    "wof:placetype":"venue"
},
  "geometry": {"coordinates":[-91.290469,42.108222],"type":"Point"}
}