{
  "type": "Feature",
  "properties": {
    "addr:full":"224 S Clinton St Iowa City IA 52240",
    "addr:housenumber":"224",
    "addr:postcode":"52240",
    "addr:street":"S Clinton St",
    "iso:country":"US",
    "sg:address":"224 S Clinton St",
    "sg:city":"Iowa City",
    "sg:classifiers":[
        {
            "category":"Food & Beverages",
            "subcategory":"Bakery",
            "type":"Retail Goods"
        }
    ],
    "sg:phone":"+1 319 354 4246",
    "sg:postcode":"52240",
    "sg:province":"IA",
    "sg:tags":[
        "baker"
    ],
    "wof:name":"Bread Garden Bakery & Cafe",
    "wof:placetype":"venue"
},
  "geometry": {"coordinates":[-91.53456300000001,41.65811],"type":"Point"}
}