{
  "type": "Feature",
  "properties": {
    "iso:country":"US",
    "sg:address":"2496 Quail Ridge Ave",
    "sg:city":"Winterset",
    "sg:classifiers":[
        {
            "category":"Building & Trades",
            "subcategory":"Construction",
            "type":"Services"
        }
    ],
    "sg:phone":"+1 515 229 7170",
    "sg:postcode":"50273",
    "sg:province":"IA",
    "sg:tags":[
        "painter"
    ],
    "wof:name":"Mecham Painting",
    "wof:placetype":"venue"
},
  "geometry": {"coordinates":[-93.92195,41.301268],"type":"Point"}
}