{
  "type": "Feature",
  "properties": {
    "iso:country":"US",
    "sg:address":"402 S 2nd Ave",
    "sg:city":"Rock Rapids",
    "sg:classifiers":[
        {
            "category":"Shopping",
            "subcategory":"Pharmacy",
            "type":"Retail Goods"
        }
    ],
    "sg:phone":"+1 712 472 4220",
    "sg:postcode":"51246",
    "sg:province":"IA",
    "wof:name":"Lewis Drugs Inc",
    "wof:placetype":"venue"
},
  "geometry": {"coordinates":[-96.16971700000001,43.430708],"type":"Point"}
}