{
  "type": "Feature",
  "properties": {
    "addr:full":"1755 John F Kennedy Rd Dubuque IA 52002",
    "addr:housenumber":"1755",
    "addr:postcode":"52002",
    "addr:street":"John F Kennedy Rd",
    "iso:country":"US",
    "sg:address":"1755 John F Kennedy Rd",
    "sg:city":"Dubuque",
    "sg:classifiers":[
        {
            "category":"Restaurant",
            "type":"Food & Drink"
        }
    ],
    "sg:menulink":"http://www.allmenus.com/ia/dubuque/158471-arbys/menu/",
    "sg:phone":"+1 563 582 8629",
    "sg:postcode":"52002",
    "sg:province":"IA",
    "sg:tags":[
        "burger",
        "american"
    ],
    "wof:name":"Arby's",
    "wof:placetype":"venue"
},
  "geometry": {"coordinates":[-90.72130900000001,42.501863],"type":"Point"}
}