{
  "type": "Feature",
  "properties": {
    "iso:country":"US",
    "sg:address":"20194 Temple Hill Rd",
    "sg:city":"Cascade",
    "sg:classifiers":[
        {
            "category":"Farming",
            "subcategory":"Dairy Farm",
            "type":"Manufacturing & Wholesale Goods"
        }
    ],
    "sg:phone":"+1 563 852 3354",
    "sg:postcode":"52033",
    "sg:province":"IA",
    "wof:name":"Gary Kelchen",
    "wof:placetype":"venue"
},
  "geometry": {"coordinates":[-90.969167,42.218286],"type":"Point"}
}