{
  "type": "Feature",
  "properties": {
    "iso:country":"US",
    "sg:address":"6507 University Ave",
    "sg:city":"Cedar Falls",
    "sg:classifiers":[
        {
            "category":"Restaurant",
            "type":"Food & Drink"
        }
    ],
    "sg:menulink":"http://www.allmenus.com/ia/cedar-falls/105389-carlos-okellys/menu/",
    "sg:phone":"+1 319 227 1121",
    "sg:postcode":"50613",
    "sg:province":"IA",
    "sg:tags":[
        "american",
        "mexican",
        "tex-mex"
    ],
    "wof:name":"Carlos O'Kelly's",
    "wof:placetype":"venue"
},
  "geometry": {"coordinates":[-92.43682699999999,42.513002],"type":"Point"}
}