{
  "type": "Feature",
  "properties": {
    "iso:country":"US",
    "sg:address":"17684 Evergreen Ave",
    "sg:city":"Akron",
    "sg:classifiers":[
        {
            "category":"Farming",
            "subcategory":"Farm",
            "type":"Manufacturing & Wholesale Goods"
        }
    ],
    "sg:phone":"+1 712 568 2480",
    "sg:postcode":"51001",
    "sg:province":"IA",
    "sg:tags":[
        "crop",
        "general"
    ],
    "wof:name":"Samuel D & Nadine A Philips",
    "wof:placetype":"venue"
},
  "geometry": {"coordinates":[-96.44846,42.798035],"type":"Point"}
}