{
  "type": "Feature",
  "properties": {
    "addr:full":"8560 Alice Ave Clive IA 50325",
    "addr:housenumber":"8560",
    "addr:postcode":"50325",
    "addr:street":"Alice Ave",
    "iso:country":"US",
    "sg:address":"8560 Alice Ave",
    "sg:city":"Clive",
    "sg:classifiers":[
        {
            "category":"Wholesale",
            "subcategory":"Non-durable Goods",
            "type":"Manufacturing & Wholesale Goods"
        }
    ],
    "sg:phone":"+1 515 278 0988",
    "sg:postcode":"50325",
    "sg:province":"IA",
    "sg:tags":[
        "fund",
        "raising",
        "merchandise"
    ],
    "wof:name":"Distinctive Concepts",
    "wof:placetype":"venue"
},
  "geometry": {"coordinates":[-93.735242,41.609362],"type":"Point"}
}