{
  "type": "Feature",
  "properties": {
    "addr:full":"200 S 2nd St Bellevue IA 52031",
    "addr:housenumber":"200",
    "addr:postcode":"52031",
    "addr:street":"S 2Nd St",
    "iso:country":"US",
    "sg:address":"200 S 2nd St",
    "sg:city":"Bellevue",
    "sg:classifiers":[
        {
            "category":"Banks & Credit Unions",
            "subcategory":"Bank",
            "type":"Services"
        }
    ],
    "sg:phone":"+1 563 872 4911",
    "sg:postcode":"52031",
    "sg:province":"IA",
    "wof:name":"Bellevue State Bank",
    "wof:placetype":"venue"
},
  "geometry": {"coordinates":[-90.42398,42.25757],"type":"Point"}
}