{
  "type": "Feature",
  "properties": {
    "addr:full":"1745 370th St Spencer IA 51301",
    "addr:housenumber":"1745",
    "addr:postcode":"51301",
    "addr:street":"370Th St",
    "iso:country":"US",
    "sg:address":"1745 370th St",
    "sg:city":"Spencer",
    "sg:classifiers":[
        {
            "category":"Retail",
            "subcategory":"Laundry & Dry Cleaning",
            "type":"Services"
        }
    ],
    "sg:phone":"+1 712 264 8956",
    "sg:postcode":"51301",
    "sg:province":"IA",
    "wof:name":"Donnetas Alterations & Sewing",
    "wof:placetype":"venue"
},
  "geometry": {"coordinates":[-95.238012,43.112684],"type":"Point"}
}