{
  "type": "Feature",
  "properties": {
    "iso:country":"US",
    "sg:address":"8815 Oakdale Dr",
    "sg:city":"Johnston",
    "sg:classifiers":[
        {
            "category":"Wholesale",
            "subcategory":"Apparel",
            "type":"Manufacturing & Wholesale Goods"
        }
    ],
    "sg:phone":"+1 515 252 9991",
    "sg:postcode":"50131",
    "sg:province":"IA",
    "sg:tags":[
        "clothing"
    ],
    "wof:name":"Jockey International Domestic",
    "wof:placetype":"venue"
},
  "geometry": {"coordinates":[-93.738771,41.662618],"type":"Point"}
}