{
  "type": "Feature",
  "properties": {
    "addr:full":"102 W Wilcox Way Jefferson IA 50129",
    "addr:housenumber":"102",
    "addr:postcode":"50129",
    "addr:street":"W Wilcox Way",
    "iso:country":"US",
    "sg:address":"102 W Wilcox Way",
    "sg:city":"Jefferson",
    "sg:classifiers":[
        {
            "category":"Farming",
            "subcategory":"Farm",
            "type":"Manufacturing & Wholesale Goods"
        }
    ],
    "sg:phone":"+1 515 386 4486",
    "sg:postcode":"50129",
    "sg:province":"IA",
    "sg:tags":[
        "crop",
        "general"
    ],
    "wof:name":"Bennett Verle",
    "wof:placetype":"venue"
},
  "geometry": {"coordinates":[-94.37346100000001,42.004073],"type":"Point"}
}