{
  "type": "Feature",
  "properties": {
    "iso:country":"US",
    "sg:address":"32756 150th St",
    "sg:city":"Cedar Falls",
    "sg:classifiers":[
        {
            "category":"Organizations",
            "subcategory":"Religious Organization",
            "type":"Services"
        }
    ],
    "sg:phone":"+1 319 989 2065",
    "sg:postcode":"50613",
    "sg:province":"IA",
    "sg:tags":[
        "church"
    ],
    "wof:name":"Fredsville Evangelical",
    "wof:placetype":"venue"
},
  "geometry": {"coordinates":[-92.57946099999999,42.484097],"type":"Point"}
}