{
  "type": "Feature",
  "properties": {
    "iso:country":"US",
    "sg:address":"227 E 5th St",
    "sg:city":"Carroll",
    "sg:classifiers":[
        {
            "category":"Health Services",
            "subcategory":"Chiropractor",
            "type":"Services"
        }
    ],
    "sg:phone":"+1 712 792 1763",
    "sg:postcode":"51401",
    "sg:province":"IA",
    "wof:name":"Carroll Family Chiropractic",
    "wof:placetype":"venue"
},
  "geometry": {"coordinates":[-94.86590700000001,42.064163],"type":"Point"}
}