{
  "type": "Feature",
  "properties": {
    "iso:country":"US",
    "sg:address":"1353 150th St",
    "sg:city":"Waverly",
    "sg:classifiers":[
        {
            "category":"Farming",
            "subcategory":"Farm",
            "type":"Manufacturing & Wholesale Goods"
        }
    ],
    "sg:phone":"+1 319 276 4660",
    "sg:postcode":"50677",
    "sg:province":"IA",
    "sg:tags":[
        "crop",
        "general"
    ],
    "wof:name":"Ronald Liddle",
    "wof:placetype":"venue"
},
  "geometry": {"coordinates":[-92.48524500000001,42.832986],"type":"Point"}
}