{
  "type": "Feature",
  "properties": {
    "addr:full":"507 Iowa Ave W Marshalltown IA 50158",
    "addr:housenumber":"507",
    "addr:postcode":"50158",
    "addr:street":"Iowa Ave W",
    "iso:country":"US",
    "sg:address":"507 Iowa Ave W",
    "sg:city":"Marshalltown",
    "sg:classifiers":[
        {
            "category":"Shopping",
            "subcategory":"Department Store",
            "type":"Retail Goods"
        }
    ],
    "sg:phone":"+1 641 752 8888",
    "sg:postcode":"50158",
    "sg:province":"IA",
    "wof:name":"Sears Roebuck & Co",
    "wof:placetype":"venue"
},
  "geometry": {"coordinates":[-92.922011,42.007195],"type":"Point"}
}