{
  "type": "Feature",
  "properties": {
    "addr:full":"513 Sumner Ave Humboldt IA 50548",
    "addr:housenumber":"513",
    "addr:postcode":"50548",
    "addr:street":"Sumner Ave",
    "iso:country":"US",
    "sg:address":"513 Sumner Ave",
    "sg:city":"Humboldt",
    "sg:classifiers":[
        {
            "category":"Insurance",
            "subcategory":"Insurance Agent",
            "type":"Services"
        }
    ],
    "sg:phone":"+1 515 332 2953",
    "sg:postcode":"50548",
    "sg:province":"IA",
    "wof:name":"Humboldt Mutual Insurance Assn",
    "wof:placetype":"venue"
},
  "geometry": {"coordinates":[-94.215918,42.721199],"type":"Point"}
}