{
  "type": "Feature",
  "properties": {
    "iso:country":"US",
    "sg:address":"2627 29th Ave",
    "sg:city":"Marion",
    "sg:classifiers":[
        {
            "category":"Organizations",
            "subcategory":"Religious Organization",
            "type":"Services"
        }
    ],
    "sg:phone":"+1 319 377 1947",
    "sg:postcode":"52302",
    "sg:province":"IA",
    "wof:name":"Family Faith Community Church",
    "wof:placetype":"venue"
},
  "geometry": {"coordinates":[-91.58449,42.050482],"type":"Point"}
}