{
  "type": "Feature",
  "properties": {
    "iso:country":"US",
    "sg:address":"2821 Beaver Ave",
    "sg:city":"Des Moines",
    "sg:classifiers":[
        {
            "category":"Shopping",
            "subcategory":"Clothing, Apparel, & Fashions",
            "type":"Retail Goods"
        }
    ],
    "sg:phone":"+1 515 274 3485",
    "sg:postcode":"50310",
    "sg:province":"IA",
    "sg:tags":[
        "furnishing"
    ],
    "wof:name":"Bond's Of Beaverdale",
    "wof:placetype":"venue"
},
  "geometry": {"coordinates":[-93.673306,41.620604],"type":"Point"}
}