{
  "type": "Feature",
  "properties": {
    "iso:country":"US",
    "sg:address":"917 Parrott St",
    "sg:city":"Aplington",
    "sg:classifiers":[
        {
            "category":"Health Services",
            "subcategory":"Chiropractor",
            "type":"Services"
        }
    ],
    "sg:phone":"+1 319 347 2313",
    "sg:postcode":"50604",
    "sg:province":"IA",
    "wof:name":"Aplington Chiropractic Clinic",
    "wof:placetype":"venue"
},
  "geometry": {"coordinates":[-92.88441,42.583911],"type":"Point"}
}