{
  "type": "Feature",
  "properties": {
    "iso:country":"US",
    "sg:address":"1506 270th St",
    "sg:city":"Fontanelle",
    "sg:phone":"+1 641 745 8941",
    "sg:postcode":"50846",
    "sg:province":"IA",
    "sg:tags":[
        "farm",
        "corn",
        "soybean"
    ],
    "wof:name":"Timothy Gross",
    "wof:placetype":"venue"
},
  "geometry": {"coordinates":[-94.604547,41.258556],"type":"Point"}
}