{
  "type": "Feature",
  "properties": {
    "iso:country":"US",
    "sg:address":"315 10th St",
    "sg:city":"Onawa",
    "sg:classifiers":[
        {
            "category":"Restaurant",
            "type":"Food & Drink"
        }
    ],
    "sg:phone":"+1 712 433 2060",
    "sg:postcode":"51040",
    "sg:province":"IA",
    "wof:name":"Mc Donald's",
    "wof:placetype":"venue"
},
  "geometry": {"coordinates":[-96.09764,42.03615],"type":"Point"}
}