{
  "type": "Feature",
  "properties": {
    "iso:country":"US",
    "sg:address":"207 2nd Ave",
    "sg:city":"Aspinwall",
    "sg:classifiers":[
        {
            "category":"Restaurant",
            "type":"Food & Drink"
        }
    ],
    "sg:phone":"+1 712 653 2836",
    "sg:postcode":"51432",
    "sg:province":"IA",
    "wof:name":"County Shed",
    "wof:placetype":"venue"
},
  "geometry": {"coordinates":[-95.136917,41.912033],"type":"Point"}
}