{
  "type": "Feature",
  "properties": {
    "addr:full":"4010 1st St Hamlin IA 50117",
    "addr:housenumber":"4010",
    "addr:postcode":"50117",
    "addr:street":"1St St",
    "iso:country":"US",
    "sg:address":"4010 1st St",
    "sg:city":"Hamlin",
    "sg:classifiers":[
        {
            "category":"Bars & Pubs",
            "type":"Food & Drink"
        }
    ],
    "sg:phone":"+1 712 563 3922",
    "sg:postcode":"50117",
    "sg:province":"IA",
    "wof:name":"Darrell's Place",
    "wof:placetype":"venue"
},
  "geometry": {"coordinates":[-94.906085,41.666303],"type":"Point"}
}