{
  "type": "Feature",
  "properties": {
    "addr:full":"15453 200th St Hawkeye IA 52147",
    "addr:housenumber":"15453",
    "addr:postcode":"52147",
    "addr:street":"200Th St",
    "iso:country":"US",
    "sg:address":"15453 200th St",
    "sg:city":"Hawkeye",
    "sg:classifiers":[
        {
            "category":"Building & Trades",
            "subcategory":"Landscaping Services",
            "type":"Services"
        }
    ],
    "sg:phone":"+1 563 427 4828",
    "sg:postcode":"52147",
    "sg:province":"IA",
    "sg:tags":[
        "landscape"
    ],
    "wof:name":"Stonehedge Landscaping Inc",
    "wof:placetype":"venue"
},
  "geometry": {"coordinates":[-91.884574,42.920831],"type":"Point"}
}