{
  "type": "Feature",
  "properties": {
    "iso:country":"US",
    "sg:address":"2600 Delaware Ave",
    "sg:city":"Des Moines",
    "sg:classifiers":[
        {
            "category":"Wholesale",
            "subcategory":"Hardware",
            "type":"Manufacturing & Wholesale Goods"
        }
    ],
    "sg:phone":"+1 515 262 9822",
    "sg:postcode":"50317",
    "sg:province":"IA",
    "sg:tags":[
        "closer",
        "door",
        "check"
    ],
    "sg:website":"www.walshdoor.com",
    "wof:name":"Walsh Door & Hardware Co",
    "wof:placetype":"venue"
},
  "geometry": {"coordinates":[-93.58129599999999,41.621316],"type":"Point"}
}