{
  "type": "Feature",
  "properties": {
    "iso:country":"US",
    "sg:address":"27171 217th St",
    "sg:city":"Earlville",
    "sg:classifiers":[
        {
            "category":"Government",
            "subcategory":"Jail",
            "type":"Public Place"
        }
    ],
    "sg:phone":"+1 563 923 2028",
    "sg:postcode":"52041",
    "sg:province":"IA",
    "sg:tags":[
        "correctional",
        "institution"
    ],
    "wof:name":"Clothing Correction",
    "wof:placetype":"venue"
},
  "geometry": {"coordinates":[-91.268738,42.474189],"type":"Point"}
}