{
  "type": "Feature",
  "properties": {
    "addr:full":"3275 290th St Ridgeway IA 52165",
    "addr:housenumber":"3275",
    "addr:postcode":"52165",
    "addr:street":"290Th St",
    "iso:country":"US",
    "sg:address":"3275 290th St",
    "sg:city":"Ridgeway",
    "sg:phone":"+1 563 547 2109",
    "sg:postcode":"52165",
    "sg:province":"IA",
    "sg:tags":[
        "farm",
        "corn"
    ],
    "wof:name":"Robert Ryan",
    "wof:placetype":"venue"
},
  "geometry": {"coordinates":[-92.04418099999999,43.356421],"type":"Point"}
}