{
  "type": "Feature",
  "properties": {
    "iso:country":"US",
    "sg:address":"2510 State Hwy 148",
    "sg:city":"Bedford",
    "sg:classifiers":[
        {
            "category":"Restaurant",
            "type":"Food & Drink"
        }
    ],
    "sg:phone":"+1 712 523 3373",
    "sg:postcode":"50833",
    "sg:province":"IA",
    "wof:name":"Bedford Country Club Rstrnt",
    "wof:placetype":"venue"
},
  "geometry": {"coordinates":[-94.725621,40.680123],"type":"Point"}
}