{
  "type": "Feature",
  "properties": {
    "iso:country":"US",
    "sg:address":"910 E Maple Leaf Dr",
    "sg:city":"Mount Pleasant",
    "sg:classifiers":[
        {
            "category":"Organizations",
            "subcategory":"Religious Organization",
            "type":"Services"
        }
    ],
    "sg:phone":"+1 319 385 2390",
    "sg:postcode":"52641",
    "sg:province":"IA",
    "wof:name":"Keith Haerer Rev",
    "wof:placetype":"venue"
},
  "geometry": {"coordinates":[-91.54049000000001,40.973947],"type":"Point"}
}