{
  "type": "Feature",
  "properties": {
    "addr:full":"3245 Williams Blvd SW Cedar Rapids IA 52404",
    "addr:housenumber":"3245",
    "addr:postcode":"52404",
    "addr:street":"Williams Blvd Sw",
    "iso:country":"US",
    "sg:address":"3245 Williams Blvd SW",
    "sg:city":"Cedar Rapids",
    "sg:classifiers":[
        {
            "category":"Personal",
            "subcategory":"Beauty Salon",
            "type":"Services"
        }
    ],
    "sg:phone":"+1 319 364 3335",
    "sg:postcode":"52404",
    "sg:province":"IA",
    "wof:name":"Hair Madness Salon & Spa",
    "wof:placetype":"venue"
},
  "geometry": {"coordinates":[-91.715819,41.958315],"type":"Point"}
}