{
  "type": "Feature",
  "properties": {
    "addr:full":"3322 E 25th St Des Moines IA 50317",
    "addr:housenumber":"3322",
    "addr:postcode":"50317",
    "addr:street":"E 25Th St",
    "iso:country":"US",
    "sg:address":"3322 E 25th St",
    "sg:city":"Des Moines",
    "sg:classifiers":[
        {
            "category":"Organizations",
            "subcategory":"Religious Organization",
            "type":"Services"
        }
    ],
    "sg:phone":"+1 515 266 6283",
    "sg:postcode":"50317",
    "sg:province":"IA",
    "sg:tags":[
        "church"
    ],
    "wof:name":"Capitol Hill Christian Church",
    "wof:placetype":"venue"
},
  "geometry": {"coordinates":[-93.570837,41.626087],"type":"Point"}
}