{
  "type": "Feature",
  "properties": {
    "iso:country":"US",
    "sg:address":"2167 Frost Ave",
    "sg:city":"Independence",
    "sg:phone":"+1 319 334 6843",
    "sg:postcode":"50644",
    "sg:province":"IA",
    "sg:tags":[
        "farm",
        "corn"
    ],
    "wof:name":"Pint Farms",
    "wof:placetype":"venue"
},
  "geometry": {"coordinates":[-91.98301600000001,42.472249],"type":"Point"}
}