{
  "type": "Feature",
  "properties": {
    "addr:full":"7735 Ansborough Ave Waterloo IA 50701",
    "addr:housenumber":"7735",
    "addr:postcode":"50701",
    "addr:street":"Ansborough Ave",
    "iso:country":"US",
    "sg:address":"7735 Ansborough Ave",
    "sg:city":"Waterloo",
    "sg:classifiers":[
        {
            "category":"Retail",
            "subcategory":"Auto Repair",
            "type":"Services"
        }
    ],
    "sg:phone":"+1 319 296 2994",
    "sg:postcode":"50701",
    "sg:province":"IA",
    "sg:tags":[
        "repairing",
        "automobile"
    ],
    "sg:website":"www.lichty.com",
    "wof:name":"Lichty Automotive",
    "wof:placetype":"venue"
},
  "geometry": {"coordinates":[-92.37690000000001,42.402876],"type":"Point"}
}