{
  "type": "Feature",
  "properties": {
    "iso:country":"US",
    "sg:address":"1325 Copper Creek Dr",
    "sg:city":"Pleasant Hill",
    "sg:classifiers":[
        {
            "category":"Cinema",
            "subcategory":"Movie Theater",
            "type":"Entertainment"
        }
    ],
    "sg:phone":"+1 515 266 2676",
    "sg:postcode":"50327",
    "sg:province":"IA",
    "wof:name":"Copper Creek Nine",
    "wof:placetype":"venue"
},
  "geometry": {"coordinates":[-93.52385099999999,41.603561],"type":"Point"}
}