{
  "type": "Feature",
  "properties": {
    "iso:country":"US",
    "sg:address":"206 N Arcade St",
    "sg:city":"Maquoketa",
    "sg:classifiers":[
        {
            "category":"Health Services",
            "subcategory":"Doctor",
            "type":"Services"
        }
    ],
    "sg:phone":"+1 563 652 6711",
    "sg:postcode":"52060",
    "sg:province":"IA",
    "sg:tags":[
        "clinic"
    ],
    "wof:name":"Maquoketa Family Clinic",
    "wof:placetype":"venue"
},
  "geometry": {"coordinates":[-90.674846,42.073648],"type":"Point"}
}