{
  "type": "Feature",
  "properties": {
    "iso:country":"US",
    "sg:address":"629 Main St",
    "sg:city":"Keokuk",
    "sg:classifiers":[
        {
            "category":"Personal",
            "subcategory":"Beauty Salon",
            "type":"Services"
        }
    ],
    "sg:phone":"+1 319 524 3567",
    "sg:postcode":"52632",
    "sg:province":"IA",
    "wof:name":"Clip Shots",
    "wof:placetype":"venue"
},
  "geometry": {"coordinates":[-91.384663,40.397181],"type":"Point"}
}