{
  "type": "Feature",
  "properties": {
    "iso:country":"US",
    "sg:address":"702 3rd St NW",
    "sg:city":"State Center",
    "sg:classifiers":[
        {
            "category":"Health Services",
            "subcategory":"Nursing And Care Facility",
            "type":"Services"
        }
    ],
    "sg:phone":"+1 641 483 2812",
    "sg:postcode":"50247",
    "sg:province":"IA",
    "sg:tags":[
        "home",
        "convalescent"
    ],
    "wof:name":"State Center Nursing & Rehab",
    "wof:placetype":"venue"
},
  "geometry": {"coordinates":[-93.172298,42.018437],"type":"Point"}
}