{
  "type": "Feature",
  "properties": {
    "addr:full":"910 Tennyson Ave Stratford IA 50249",
    "addr:housenumber":"910",
    "addr:postcode":"50249",
    "addr:street":"Tennyson Ave",
    "iso:country":"US",
    "sg:address":"910 Tennyson Ave",
    "sg:city":"Stratford",
    "sg:classifiers":[
        {
            "category":"Wholesale",
            "subcategory":"Machinery & Supplies",
            "type":"Manufacturing & Wholesale Goods"
        }
    ],
    "sg:phone":"+1 515 838 2414",
    "sg:postcode":"50249",
    "sg:province":"IA",
    "sg:tags":[
        "equipment",
        "veterinarian"
    ],
    "sg:website":"www.jrgsupply.com",
    "wof:name":"JRG Veterinary Supply",
    "wof:placetype":"venue"
},
  "geometry": {"coordinates":[-93.927019,42.271426],"type":"Point"}
}