{
  "type": "Feature",
  "properties": {
    "addr:full":"216 E 6th St Madrid IA 50156",
    "addr:housenumber":"216",
    "addr:postcode":"50156",
    "addr:street":"E 6Th St",
    "iso:country":"US",
    "sg:address":"216 E 6th St",
    "sg:city":"Madrid",
    "sg:phone":"+1 515 795 3928",
    "sg:postcode":"50156",
    "sg:province":"IA",
    "sg:tags":[
        "equipment",
        "commercial"
    ],
    "wof:name":"J & T Distributing Inc",
    "wof:placetype":"venue"
},
  "geometry": {"coordinates":[-93.81765,41.872027],"type":"Point"}
}