{
  "type": "Feature",
  "properties": {
    "iso:country":"US",
    "sg:address":"1616 Ohio St",
    "sg:city":"Des Moines",
    "sg:phone":"+1 515 283 8370",
    "sg:postcode":"50314",
    "sg:province":"IA",
    "sg:tags":[
        "equipment",
        "supply"
    ],
    "wof:name":"Hobart Corp",
    "wof:placetype":"venue"
},
  "geometry": {"coordinates":[-93.61740899999999,41.60888],"type":"Point"}
}