{
  "type": "Feature",
  "properties": {
    "iso:country":"US",
    "sg:address":"617 Durant St",
    "sg:city":"Harlan",
    "sg:classifiers":[
        {
            "category":"Shopping",
            "subcategory":"Stationery & Office Supplies",
            "type":"Retail Goods"
        }
    ],
    "sg:phone":"+1 712 755 0386",
    "sg:postcode":"51537",
    "sg:province":"IA",
    "sg:tags":[
        "album",
        "scrapbook"
    ],
    "wof:name":"Snap N Scrap",
    "wof:placetype":"venue"
},
  "geometry": {"coordinates":[-95.31795099999999,41.656686],"type":"Point"}
}