{
  "type": "Feature",
  "properties": {
    "iso:country":"US",
    "sg:address":"20 Miller Ave SW",
    "sg:city":"Cedar Rapids",
    "sg:classifiers":[
        {
            "category":"Deli",
            "type":"Food & Drink"
        }
    ],
    "sg:menulink":"http://www.allmenus.com/ia/cedar-rapids/127082-blimpie-subs--sandwiches/menu/",
    "sg:phone":"+1 319 297 7325",
    "sg:postcode":"52404",
    "sg:province":"IA",
    "sg:tags":[
        "wrap",
        "american",
        "sandwich"
    ],
    "wof:name":"Blimpie Subs & Sandwiches",
    "wof:placetype":"venue"
},
  "geometry": {"coordinates":[-91.65781800000001,41.924486],"type":"Point"}
}