{
  "type": "Feature",
  "properties": {
    "iso:country":"US",
    "sg:address":"1901 E Bremer Ave",
    "sg:city":"Waverly",
    "sg:classifiers":[
        {
            "category":"Retail",
            "subcategory":"Animal Services",
            "type":"Services"
        }
    ],
    "sg:phone":"+1 319 352 9151",
    "sg:postcode":"50677",
    "sg:province":"IA",
    "sg:tags":[
        "pet",
        "grooming",
        "washing"
    ],
    "wof:name":"Wag'n Tails Pet Salon",
    "wof:placetype":"venue"
},
  "geometry": {"coordinates":[-92.44895200000001,42.721708],"type":"Point"}
}