{
  "type": "Feature",
  "properties": {
    "addr:full":"1090 315th Ave Waucoma IA 52171",
    "addr:housenumber":"1090",
    "addr:postcode":"52171",
    "addr:street":"315Th Ave",
    "iso:country":"US",
    "sg:address":"1090 315th Ave",
    "sg:city":"Waucoma",
    "sg:classifiers":[
        {
            "category":"Farming",
            "subcategory":"Livestock Farm",
            "type":"Manufacturing & Wholesale Goods"
        }
    ],
    "sg:phone":"+1 563 776 7311",
    "sg:postcode":"52171",
    "sg:province":"IA",
    "sg:tags":[
        "beef",
        "feedlot",
        "cattle"
    ],
    "wof:name":"Bruce Adams",
    "wof:placetype":"venue"
},
  "geometry": {"coordinates":[-92.02261799999999,43.087757],"type":"Point"}
}