{
  "type": "Feature",
  "properties": {
    "iso:country":"US",
    "sg:address":"117 E Mississippi Dr",
    "sg:city":"Muscatine",
    "sg:classifiers":[
        {
            "category":"Autos & Motor Vehicles",
            "subcategory":"Boat Sales",
            "type":"Retail Goods"
        }
    ],
    "sg:phone":"+1 563 263 0132",
    "sg:postcode":"52761",
    "sg:province":"IA",
    "sg:tags":[
        "dealer",
        "sales"
    ],
    "wof:name":"Lange's Marine",
    "wof:placetype":"venue"
},
  "geometry": {"coordinates":[-91.04400099999999,41.421074],"type":"Point"}
}