{
  "type": "Feature",
  "properties": {
    "iso:country":"US",
    "sg:address":"609 1st Ave N",
    "sg:city":"Estherville",
    "sg:classifiers":[
        {
            "category":"Government",
            "subcategory":"Office",
            "type":"Public Place"
        }
    ],
    "sg:phone":"+1 712 362 2609",
    "sg:postcode":"51334",
    "sg:province":"IA",
    "sg:tags":[
        "county",
        "taxation"
    ],
    "wof:name":"Emmet County Assessor",
    "wof:placetype":"venue"
},
  "geometry": {"coordinates":[-94.835483,43.40303],"type":"Point"}
}