{
  "type": "Feature",
  "properties": {
    "iso:country":"US",
    "sg:address":"660 W Milwaukee St",
    "sg:city":"New Hampton",
    "sg:classifiers":[
        {
            "category":"Shopping",
            "subcategory":"Department Store",
            "type":"Retail Goods"
        }
    ],
    "sg:phone":"+1 641 394 4748",
    "sg:postcode":"50659",
    "sg:province":"IA",
    "sg:tags":[
        "shop"
    ],
    "wof:name":"Pamida",
    "wof:placetype":"venue"
},
  "geometry": {"coordinates":[-92.324775,43.066747],"type":"Point"}
}