{
  "type": "Feature",
  "properties": {
    "iso:country":"US",
    "sg:address":"5270 N Park Pl NE",
    "sg:city":"Cedar Rapids",
    "sg:classifiers":[
        {
            "category":"Freight",
            "type":"Transportation"
        }
    ],
    "sg:phone":"+1 319 377 4488",
    "sg:postcode":"52402",
    "sg:province":"IA",
    "sg:tags":[
        "broker",
        "trucking"
    ],
    "wof:name":"S C Logistics",
    "wof:placetype":"venue"
},
  "geometry": {"coordinates":[-91.629317,42.029627],"type":"Point"}
}