{
  "type": "Feature",
  "properties": {
    "iso:country":"US",
    "sg:address":"5340 Ashworth Rd",
    "sg:city":"West Des Moines",
    "sg:classifiers":[
        {
            "category":"Professional",
            "type":"Services"
        }
    ],
    "sg:phone":"+1 515 440 1547",
    "sg:postcode":"50266",
    "sg:province":"IA",
    "wof:name":"Custom Bytes LLC",
    "wof:placetype":"venue"
},
  "geometry": {"coordinates":[-93.777795,41.584517],"type":"Point"}
}