{
  "type": "Feature",
  "properties": {
    "iso:country":"US",
    "sg:address":"306 Main Ave",
    "sg:city":"Clear Lake",
    "sg:classifiers":[
        {
            "category":"Professional",
            "subcategory":"Lawyer & Legal Services",
            "type":"Services"
        }
    ],
    "sg:phone":"+1 641 357 7296",
    "sg:postcode":"50428",
    "sg:province":"IA",
    "sg:tags":[
        "attorney"
    ],
    "wof:name":"Berry & Casperson",
    "wof:placetype":"venue"
},
  "geometry": {"coordinates":[-93.381103,43.136539],"type":"Point"}
}