{
  "type": "Feature",
  "properties": {
    "addr:full":"704 4th Ave Sibley IA 51249",
    "addr:housenumber":"704",
    "addr:postcode":"51249",
    "addr:street":"4Th Ave",
    "iso:country":"US",
    "sg:address":"704 4th Ave",
    "sg:city":"Sibley",
    "sg:classifiers":[
        {
            "category":"Organizations",
            "subcategory":"Religious Organization",
            "type":"Services"
        }
    ],
    "sg:phone":"+1 712 754 2455",
    "sg:postcode":"51249",
    "sg:province":"IA",
    "wof:name":"United Church Of Christ",
    "wof:placetype":"venue"
},
  "geometry": {"coordinates":[-95.74865800000001,43.401416],"type":"Point"}
}