{
  "type": "Feature",
  "properties": {
    "iso:country":"US",
    "sg:address":"20 N 16th St",
    "sg:city":"Council Bluffs",
    "sg:classifiers":[
        {
            "category":"Wholesale",
            "subcategory":"Machinery & Supplies",
            "type":"Manufacturing & Wholesale Goods"
        }
    ],
    "sg:phone":"+1 712 323 1822",
    "sg:postcode":"51501",
    "sg:province":"IA",
    "sg:tags":[
        "contractor"
    ],
    "wof:name":"Iowa Rigger's Loft Inc",
    "wof:placetype":"venue"
},
  "geometry": {"coordinates":[-95.867676,41.262054],"type":"Point"}
}