{
  "type": "Feature",
  "properties": {
    "addr:full":"4623 400th St Hospers IA 51238",
    "addr:housenumber":"4623",
    "addr:postcode":"51238",
    "addr:street":"400Th St",
    "iso:country":"US",
    "sg:address":"4623 400th St",
    "sg:city":"Hospers",
    "sg:classifiers":[
        {
            "category":"Farming",
            "subcategory":"Farm",
            "type":"Manufacturing & Wholesale Goods"
        }
    ],
    "sg:phone":"+1 712 752 8407",
    "sg:postcode":"51238",
    "sg:province":"IA",
    "wof:name":"D & D Klein",
    "wof:placetype":"venue"
},
  "geometry": {"coordinates":[-95.87597599999999,43.069123],"type":"Point"}
}