{
  "type": "Feature",
  "properties": {
    "iso:country":"US",
    "sg:address":"505 SE 2nd St",
    "sg:city":"Greenfield",
    "sg:classifiers":[
        {
            "category":"Retail",
            "subcategory":"Repair Shop",
            "type":"Services"
        }
    ],
    "sg:phone":"+1 641 743 6319",
    "sg:postcode":"50849",
    "sg:province":"IA",
    "sg:tags":[
        "sharpening"
    ],
    "wof:name":"Thompson Sharpening Svc",
    "wof:placetype":"venue"
},
  "geometry": {"coordinates":[-94.459456,41.300101],"type":"Point"}
}