{
  "type": "Feature",
  "properties": {
    "iso:country":"US",
    "sg:address":"513 E 2nd St",
    "sg:city":"Remsen",
    "sg:classifiers":[
        {
            "category":"Real Estate",
            "subcategory":"Real Estate Operator",
            "type":"Services"
        }
    ],
    "sg:phone":"+1 712 786 2981",
    "sg:postcode":"51050",
    "sg:province":"IA",
    "sg:tags":[
        "property",
        "lessor"
    ],
    "wof:name":"Herman Kluver",
    "wof:placetype":"venue"
},
  "geometry": {"coordinates":[-95.966077,42.814625],"type":"Point"}
}