{
  "type": "Feature",
  "properties": {
    "addr:full":"200 1st Ave Bagley IA 50026",
    "addr:housenumber":"200",
    "addr:postcode":"50026",
    "addr:street":"1St Ave",
    "iso:country":"US",
    "sg:address":"200 1st Ave",
    "sg:city":"Bagley",
    "sg:classifiers":[
        {
            "category":"Real Estate",
            "subcategory":"Real Estate Agent",
            "type":"Services"
        }
    ],
    "sg:phone":"+1 641 427 5262",
    "sg:postcode":"50026",
    "sg:province":"IA",
    "wof:name":"Gubser Real Estate",
    "wof:placetype":"venue"
},
  "geometry": {"coordinates":[-94.430908,41.848239],"type":"Point"}
}