{
  "type": "Feature",
  "properties": {
    "iso:country":"US",
    "sg:address":"203 1st Ave N",
    "sg:city":"Altoona",
    "sg:classifiers":[
        {
            "category":"Manufacturing",
            "subcategory":"Pet Food",
            "type":"Manufacturing & Wholesale Goods"
        }
    ],
    "sg:phone":"+1 515 967 4219",
    "sg:postcode":"50009",
    "sg:province":"IA",
    "sg:tags":[
        "feed"
    ],
    "wof:name":"Kent Feeds Inc",
    "wof:placetype":"venue"
},
  "geometry": {"coordinates":[-93.464489,41.654475],"type":"Point"}
}