{
  "type": "Feature",
  "properties": {
    "addr:full":"21 1st Ave Atkins IA 52206",
    "addr:housenumber":"21",
    "addr:postcode":"52206",
    "addr:street":"1St Ave",
    "iso:country":"US",
    "sg:address":"21 1st Ave",
    "sg:city":"Atkins",
    "sg:classifiers":[
        {
            "category":"Retail",
            "subcategory":"Auto Repair",
            "type":"Services"
        }
    ],
    "sg:phone":"+1 319 446 6200",
    "sg:postcode":"52206",
    "sg:province":"IA",
    "sg:tags":[
        "wrecker"
    ],
    "wof:name":"Havlik Engineering",
    "wof:placetype":"venue"
},
  "geometry": {"coordinates":[-91.860708,41.996878],"type":"Point"}
}