{
  "type": "Feature",
  "properties": {
    "iso:country":"US",
    "sg:address":"4162 Birch Ave",
    "sg:city":"Hawarden",
    "sg:classifiers":[
        {
            "category":"Wholesale",
            "subcategory":"Construction Materials",
            "type":"Manufacturing & Wholesale Goods"
        }
    ],
    "sg:phone":"+1 712 552 2308",
    "sg:postcode":"51023",
    "sg:province":"SD",
    "sg:tags":[
        "sand",
        "gravel"
    ],
    "wof:name":"Boyer Sand & Rock Inc",
    "wof:placetype":"venue"
},
  "geometry": {"coordinates":[-96.488816,43.044469],"type":"Point"}
}