{
  "type": "Feature",
  "properties": {
    "iso:country":"US",
    "sg:address":"1122 Country Club Dr",
    "sg:city":"Boone",
    "sg:classifiers":[
        {
            "category":"Professional",
            "subcategory":"Business Services",
            "type":"Services"
        }
    ],
    "sg:phone":"+1 515 432 9425",
    "sg:postcode":"50036",
    "sg:province":"IA",
    "sg:tags":[
        "auctioneer"
    ],
    "wof:name":"Herman Auction Svc",
    "wof:placetype":"venue"
},
  "geometry": {"coordinates":[-93.877078,42.048584],"type":"Point"}
}