{
  "type": "Feature",
  "properties": {
    "iso:country":"US",
    "sg:address":"504 S Main St",
    "sg:city":"Buffalo Center",
    "sg:classifiers":[
        {
            "category":"Real Estate",
            "subcategory":"Real Estate Operator",
            "type":"Services"
        }
    ],
    "sg:phone":"+1 641 562 2545",
    "sg:postcode":"50424",
    "sg:province":"IA",
    "sg:tags":[
        "property",
        "lessor"
    ],
    "wof:name":"Berschman Fms Ltd",
    "wof:placetype":"venue"
},
  "geometry": {"coordinates":[-93.946377,43.382198],"type":"Point"}
}