{
  "type": "Feature",
  "properties": {
    "addr:full":"609 Crestview Dr Tipton IA 52772",
    "addr:housenumber":"609",
    "addr:postcode":"52772",
    "addr:street":"Crestview Dr",
    "iso:country":"US",
    "sg:address":"609 Crestview Dr",
    "sg:city":"Tipton",
    "sg:phone":"+1 563 886 6882",
    "sg:postcode":"52772",
    "sg:province":"IA",
    "sg:tags":[
        "farm",
        "corn",
        "soybean"
    ],
    "wof:name":"Galen Sievers",
    "wof:placetype":"venue"
},
  "geometry": {"coordinates":[-91.13707700000001,41.77481],"type":"Point"}
}