{
  "type": "Feature",
  "properties": {
    "addr:full":"135 S Central St Forest City IA 50436",
    "addr:housenumber":"135",
    "addr:postcode":"50436",
    "addr:street":"S Central St",
    "iso:country":"US",
    "sg:address":"135 S Central St",
    "sg:city":"Forest City",
    "sg:classifiers":[
        {
            "category":"Government",
            "subcategory":"Office",
            "type":"Public Place"
        }
    ],
    "sg:phone":"+1 641 585 4315",
    "sg:postcode":"50436",
    "sg:province":"IA",
    "wof:name":"Winnebago County Shop",
    "wof:placetype":"venue"
},
  "geometry": {"coordinates":[-93.63555700000001,43.263041],"type":"Point"}
}