{
  "type": "Feature",
  "properties": {
    "iso:country":"US",
    "sg:address":"2641 335th St",
    "sg:city":"Missouri Valley",
    "sg:phone":"+1 712 642 4304",
    "sg:postcode":"51555",
    "sg:province":"IA",
    "sg:tags":[
        "farm",
        "corn",
        "beef",
        "feedlot",
        "cattle"
    ],
    "wof:name":"Lynn Wohlers",
    "wof:placetype":"venue"
},
  "geometry": {"coordinates":[-95.799227,41.528056],"type":"Point"}
}