{
  "type": "Feature",
  "properties": {
    "iso:country":"US",
    "sg:address":"700 S Martha St",
    "sg:city":"Sioux City",
    "sg:classifiers":[
        {
            "category":"Organizations",
            "subcategory":"Religious Organization",
            "type":"Services"
        }
    ],
    "sg:phone":"+1 712 276 2511",
    "sg:postcode":"51106",
    "sg:province":"IA",
    "sg:tags":[
        "church"
    ],
    "sg:website":"www.mlcsc.org",
    "wof:name":"Morningside Lutheran Church",
    "wof:placetype":"venue"
},
  "geometry": {"coordinates":[-96.361502,42.483881],"type":"Point"}
}