{
  "type": "Feature",
  "properties": {
    "addr:full":"322 N Main Ave Sioux Center IA 51250",
    "addr:housenumber":"322",
    "addr:postcode":"51250",
    "addr:street":"N Main Ave",
    "iso:country":"US",
    "sg:address":"322 N Main Ave",
    "sg:city":"Sioux Center",
    "sg:classifiers":[
        {
            "category":"Professional",
            "subcategory":"Business Services",
            "type":"Services"
        }
    ],
    "sg:phone":"+1 712 722 0003",
    "sg:postcode":"51250",
    "sg:province":"IA",
    "wof:name":"Els Enterprises Inc",
    "wof:placetype":"venue"
},
  "geometry": {"coordinates":[-96.1755,43.08064],"type":"Point"}
}