{
  "type": "Feature",
  "properties": {
    "addr:full":"1471 Bryantsburg Blvd Hazleton IA 50641",
    "addr:housenumber":"1471",
    "addr:postcode":"50641",
    "addr:street":"Bryantsburg Blvd",
    "iso:country":"US",
    "sg:address":"1471 Bryantsburg Blvd",
    "sg:city":"Hazleton",
    "sg:classifiers":[
        {
            "category":"Banks & Credit Unions",
            "subcategory":"Bank",
            "type":"Services"
        }
    ],
    "sg:phone":"+1 319 636 2990",
    "sg:postcode":"50641",
    "sg:province":"IA",
    "wof:name":"Oelwein-Cresco Credit Union",
    "wof:placetype":"venue"
},
  "geometry": {"coordinates":[-91.905675,42.576463],"type":"Point"}
}