{
  "type": "Feature",
  "properties": {
    "iso:country":"US",
    "sg:address":"109 East Ave",
    "sg:city":"Ames",
    "sg:classifiers":[
        {
            "category":"Building & Trades",
            "subcategory":"Construction",
            "type":"Services"
        }
    ],
    "sg:phone":"+1 515 232 8923",
    "sg:postcode":"50010",
    "sg:province":"IA",
    "sg:tags":[
        "designer",
        "dealer",
        "pool",
        "swimming"
    ],
    "wof:name":"Wci Pools & Spas",
    "wof:placetype":"venue"
},
  "geometry": {"coordinates":[-93.608214,42.023593],"type":"Point"}
}