{
  "type": "Feature",
  "properties": {
    "addr:full":"49213 230th Ave Lake Mills IA 50450",
    "addr:housenumber":"49213",
    "addr:postcode":"50450",
    "addr:street":"230Th Ave",
    "iso:country":"US",
    "sg:address":"49213 230th Ave",
    "sg:city":"Lake Mills",
    "sg:classifiers":[
        {
            "category":"Professional",
            "type":"Services"
        }
    ],
    "sg:phone":"+1 641 592 8765",
    "sg:postcode":"50450",
    "sg:province":"IA",
    "wof:name":"Kim Brackey",
    "wof:placetype":"venue"
},
  "geometry": {"coordinates":[-93.517259,43.475013],"type":"Point"}
}