{
  "type": "Feature",
  "properties": {
    "iso:country":"US",
    "sg:address":"1437 E Bell Ave",
    "sg:city":"Des Moines",
    "sg:classifiers":[
        {
            "category":"Building & Trades",
            "subcategory":"Construction",
            "type":"Services"
        }
    ],
    "sg:phone":"+1 515 282 5569",
    "sg:postcode":"50320",
    "sg:province":"IA",
    "sg:tags":[
        "contractor"
    ],
    "wof:name":"First Quality Tile LLC",
    "wof:placetype":"venue"
},
  "geometry": {"coordinates":[-93.59084799999999,41.562497],"type":"Point"}
}