{
  "type": "Feature",
  "properties": {
    "addr:full":"111 34th St NE Cedar Rapids IA 52402",
    "addr:housenumber":"111",
    "addr:postcode":"52402",
    "addr:street":"34Th St Ne",
    "iso:country":"US",
    "sg:address":"111 34th St NE",
    "sg:city":"Cedar Rapids",
    "sg:classifiers":[
        {
            "category":"Personal",
            "subcategory":"Beauty Salon",
            "type":"Services"
        }
    ],
    "sg:phone":"+1 319 363 0019",
    "sg:postcode":"52402",
    "sg:province":"IA",
    "wof:name":"Jerry's Styling On 34th",
    "wof:placetype":"venue"
},
  "geometry": {"coordinates":[-91.638301,42.012246],"type":"Point"}
}