{
  "type": "Feature",
  "properties": {
    "iso:country":"US",
    "sg:address":"5294 W Ave",
    "sg:city":"Aurelia",
    "sg:classifiers":[
        {
            "category":"Building & Trades",
            "subcategory":"Construction",
            "type":"Services"
        }
    ],
    "sg:phone":"+1 712 434 5723",
    "sg:postcode":"51005",
    "sg:province":"IA",
    "sg:tags":[
        "general",
        "contractor"
    ],
    "wof:name":"Paltz Construction",
    "wof:placetype":"venue"
},
  "geometry": {"coordinates":[-95.42698300000001,42.749153],"type":"Point"}
}