{
  "type": "Feature",
  "properties": {
    "iso:country":"US",
    "sg:address":"115 S Howard St",
    "sg:city":"Indianola",
    "sg:classifiers":[
        {
            "category":"Professional",
            "subcategory":"Lawyer & Legal Services",
            "type":"Services"
        }
    ],
    "sg:phone":"+1 515 961 2509",
    "sg:postcode":"50125",
    "sg:province":"IA",
    "sg:tags":[
        "attorney"
    ],
    "wof:name":"Hall & Schlenker Law Firm",
    "wof:placetype":"venue"
},
  "geometry": {"coordinates":[-93.561016,41.359421],"type":"Point"}
}