{
  "type": "Feature",
  "properties": {
    "iso:country":"US",
    "sg:address":"302 E Poisal St",
    "sg:city":"Clarksville",
    "sg:classifiers":[
        {
            "category":"Building & Trades",
            "subcategory":"Construction",
            "type":"Services"
        }
    ],
    "sg:phone":"+1 319 278 9091",
    "sg:postcode":"50619",
    "sg:province":"IA",
    "sg:tags":[
        "housing",
        "remodeling",
        "family",
        "contractor"
    ],
    "wof:name":"Hirsch Construction",
    "wof:placetype":"venue"
},
  "geometry": {"coordinates":[-92.665291,42.785486],"type":"Point"}
}