{
  "type": "Feature",
  "properties": {
    "addr:full":"2158 State Hwy 2 Corydon IA 50060",
    "addr:housenumber":"2158",
    "addr:postcode":"50060",
    "addr:street":"State Hwy 2",
    "iso:country":"US",
    "sg:address":"2158 State Hwy 2",
    "sg:city":"Corydon",
    "sg:classifiers":[
        {
            "category":"Retail",
            "subcategory":"Repair Shop",
            "type":"Services"
        }
    ],
    "sg:phone":"+1 641 872 2990",
    "sg:postcode":"50060",
    "sg:province":"IA",
    "sg:tags":[
        "welding"
    ],
    "wof:name":"Evitt Pipe & Welding",
    "wof:placetype":"venue"
},
  "geometry": {"coordinates":[-93.356421,40.757048],"type":"Point"}
}