{
  "type": "Feature",
  "properties": {
    "addr:full":"622 N 19th St Clarinda IA 51632",
    "addr:housenumber":"622",
    "addr:postcode":"51632",
    "addr:street":"N 19Th St",
    "iso:country":"US",
    "sg:address":"622 N 19th St",
    "sg:city":"Clarinda",
    "sg:classifiers":[
        {
            "category":"Professional",
            "subcategory":"Management & Consulting",
            "type":"Services"
        }
    ],
    "sg:phone":"+1 712 542 5025",
    "sg:postcode":"51632",
    "sg:province":"IA",
    "sg:tags":[
        "business"
    ],
    "wof:name":"Jim Computer Consultant",
    "wof:placetype":"venue"
},
  "geometry": {"coordinates":[-95.042317,40.743864],"type":"Point"}
}