{
  "type": "Feature",
  "properties": {
    "iso:country":"US",
    "sg:address":"315 S Iowa Ave",
    "sg:city":"Washington",
    "sg:classifiers":[
        {
            "category":"Professional",
            "subcategory":"Lawyer & Legal Services",
            "type":"Services"
        }
    ],
    "sg:phone":"+1 319 653 6693",
    "sg:postcode":"52353",
    "sg:province":"IA",
    "sg:tags":[
        "attorney"
    ],
    "wof:name":"Craig Arbuckle",
    "wof:placetype":"venue"
},
  "geometry": {"coordinates":[-91.691793,41.297269],"type":"Point"}
}