{
  "type": "Feature",
  "properties": {
    "iso:country":"US",
    "sg:address":"56 25th Ave N",
    "sg:city":"Clinton",
    "sg:classifiers":[
        {
            "category":"Professional",
            "type":"Services"
        }
    ],
    "sg:phone":"+1 563 243 3442",
    "sg:postcode":"52732",
    "sg:province":"IA",
    "sg:tags":[
        "establishment"
    ],
    "wof:name":"Symphony Of Lights-Clinton",
    "wof:placetype":"venue"
},
  "geometry": {"coordinates":[-90.175352,41.873204],"type":"Point"}
}