{
  "type": "Feature",
  "properties": {
    "iso:country":"US",
    "sg:address":"11407 NW Jester Park Dr",
    "sg:city":"Granger",
    "sg:classifiers":[
        {
            "category":"Government",
            "subcategory":"Office",
            "type":"Public Place"
        }
    ],
    "sg:phone":"+1 515 323 5300",
    "sg:postcode":"50109",
    "sg:province":"IA",
    "sg:tags":[
        "county"
    ],
    "sg:website":"www.conservationboard.org",
    "wof:name":"Polk County Conservation Board",
    "wof:placetype":"venue"
},
  "geometry": {"coordinates":[-93.777342,41.777272],"type":"Point"}
}