{
  "type": "Feature",
  "properties": {
    "addr:full":"5406 Merle Hay Rd Johnston IA 50131",
    "addr:housenumber":"5406",
    "addr:postcode":"50131",
    "addr:street":"Merle Hay Rd",
    "iso:country":"US",
    "sg:address":"5406 Merle Hay Rd",
    "sg:city":"Johnston",
    "sg:classifiers":[
        {
            "category":"Social Services",
            "subcategory":"Job Training",
            "type":"Services"
        }
    ],
    "sg:phone":"+1 515 253 9611",
    "sg:postcode":"50131",
    "sg:province":"IA",
    "sg:tags":[
        "retardation",
        "disabled",
        "mental",
        "dev"
    ],
    "sg:website":"www.childserv.org",
    "wof:name":"Child Serve",
    "wof:placetype":"venue"
},
  "geometry": {"coordinates":[-93.697729,41.657984],"type":"Point"}
}