{
  "type": "Feature",
  "properties": {
    "iso:country":"US",
    "sg:address":"3301 W 19th St",
    "sg:city":"Sioux City",
    "sg:classifiers":[
        {
            "category":"Education",
            "subcategory":"School",
            "type":"Public Place"
        }
    ],
    "sg:phone":"+1 712 279 6813",
    "sg:postcode":"51103",
    "sg:province":"IA",
    "wof:name":"West Middle School",
    "wof:placetype":"venue"
},
  "geometry": {"coordinates":[-96.45155,42.508484],"type":"Point"}
}