{
  "type": "Feature",
  "properties": {
    "iso:country":"US",
    "sg:address":"404 W Main St",
    "sg:city":"Ottumwa",
    "sg:classifiers":[
        {
            "category":"Shopping",
            "subcategory":"Musical Instruments",
            "type":"Retail Goods"
        }
    ],
    "sg:phone":"+1 641 682 8033",
    "sg:postcode":"52501",
    "sg:province":"IA",
    "wof:name":"West Music",
    "wof:placetype":"venue"
},
  "geometry": {"coordinates":[-92.416798,41.020815],"type":"Point"}
}