{
  "type": "Feature",
  "properties": {
    "iso:country":"US",
    "sg:address":"98 Emmons St",
    "sg:city":"Hiawatha",
    "sg:classifiers":[
        {
            "category":"Wholesale",
            "subcategory":"Electrical",
            "type":"Manufacturing & Wholesale Goods"
        }
    ],
    "sg:phone":"+1 319 393 5456",
    "sg:postcode":"52233",
    "sg:province":"IA",
    "sg:tags":[
        "communication",
        "radio",
        "system"
    ],
    "sg:website":"www.graybillinc.com",
    "wof:name":"Graybill Communications Inc",
    "wof:placetype":"venue"
},
  "geometry": {"coordinates":[-91.673562,42.038839],"type":"Point"}
}