{
  "type": "Feature",
  "properties": {
    "iso:country":"US",
    "sg:address":"417 Thomas St",
    "sg:city":"Callender",
    "sg:classifiers":[
        {
            "category":"Personal",
            "subcategory":"Beauty Salon",
            "type":"Services"
        }
    ],
    "sg:phone":"+1 515 548 3435",
    "sg:postcode":"50523",
    "sg:province":"IA",
    "wof:name":"Coiffure Beauty Shoppe",
    "wof:placetype":"venue"
},
  "geometry": {"coordinates":[-94.291827,42.361579],"type":"Point"}
}