{
  "type": "Feature",
  "properties": {
    "addr:full":"1411 E 33rd St Des Moines IA 50317",
    "addr:housenumber":"1411",
    "addr:postcode":"50317",
    "addr:street":"E 33Rd St",
    "iso:country":"US",
    "sg:address":"1411 E 33rd St",
    "sg:city":"Des Moines",
    "sg:classifiers":[
        {
            "category":"Education",
            "subcategory":"School",
            "type":"Public Place"
        }
    ],
    "sg:phone":"+1 515 242 8435",
    "sg:postcode":"50317",
    "sg:province":"IA",
    "sg:website":"www.dmps.k12.ia.us",
    "wof:name":"Stowe Elementary School",
    "wof:placetype":"venue"
},
  "geometry": {"coordinates":[-93.551401,41.605923],"type":"Point"}
}