{
  "type": "Feature",
  "properties": {
    "iso:country":"US",
    "sg:address":"11324 Aurora Ave",
    "sg:city":"Urbandale",
    "sg:classifiers":[
        {
            "category":"Professional",
            "type":"Services"
        }
    ],
    "sg:phone":"+1 515 327 8981",
    "sg:postcode":"50322",
    "sg:province":"IA",
    "sg:tags":[
        "establishment"
    ],
    "wof:name":"Rainbow Play Systems Of Iowa",
    "wof:placetype":"venue"
},
  "geometry": {"coordinates":[-93.768891,41.6384],"type":"Point"}
}