{
  "type": "Feature",
  "properties": {
    "iso:country":"US",
    "sg:address":"3584 Hwy 63",
    "sg:city":"Grinnell",
    "sg:classifiers":[
        {
            "category":"Retail",
            "subcategory":"Portrait Studio",
            "type":"Services"
        }
    ],
    "sg:phone":"+1 641 528 5022",
    "sg:postcode":"50112",
    "sg:province":"IA",
    "sg:tags":[
        "photographer",
        "photo"
    ],
    "wof:name":"Lora's Portraits To Remember",
    "wof:placetype":"venue"
},
  "geometry": {"coordinates":[-92.591264,41.777315],"type":"Point"}
}