{
  "type": "Feature",
  "properties": {
    "addr:full":"521 W Burlington Ave West Burlington IA 52655",
    "addr:housenumber":"521",
    "addr:postcode":"52655",
    "addr:street":"W Burlington Ave West",
    "iso:country":"US",
    "sg:address":"521 W Burlington Ave",
    "sg:city":"West Burlington",
    "sg:classifiers":[
        {
            "category":"Insurance",
            "subcategory":"Insurance Agent",
            "type":"Services"
        }
    ],
    "sg:phone":"+1 319 752 5122",
    "sg:postcode":"52655",
    "sg:province":"IA",
    "wof:name":"State Farm Insurance",
    "wof:placetype":"venue"
},
  "geometry": {"coordinates":[-91.15105699999999,40.821406],"type":"Point"}
}