{
  "type": "Feature",
  "properties": {
    "addr:full":"316 S Washington Blvd Camanche IA 52730",
    "addr:housenumber":"316",
    "addr:postcode":"52730",
    "addr:street":"S Washington Blvd",
    "iso:country":"US",
    "sg:address":"316 S Washington Blvd",
    "sg:city":"Camanche",
    "sg:classifiers":[
        {
            "category":"Shopping",
            "subcategory":"Gifts & Souvenirs",
            "type":"Retail Goods"
        }
    ],
    "sg:phone":"+1 563 259 1970",
    "sg:postcode":"52730",
    "sg:province":"IA",
    "wof:name":"Ceramics Cellar",
    "wof:placetype":"venue"
},
  "geometry": {"coordinates":[-90.25277800000001,41.789843],"type":"Point"}
}