{
  "type": "Feature",
  "properties": {
    "iso:country":"US",
    "sg:address":"1954 Rainbow Dr",
    "sg:city":"Waterloo",
    "sg:classifiers":[
        {
            "category":"Building & Trades",
            "subcategory":"Construction",
            "type":"Services"
        }
    ],
    "sg:phone":"+1 319 236 7199",
    "sg:postcode":"50701",
    "sg:province":"IA",
    "sg:tags":[
        "house"
    ],
    "wof:name":"Newton Construction",
    "wof:placetype":"venue"
},
  "geometry": {"coordinates":[-92.399828,42.515294],"type":"Point"}
}