{
  "type": "Feature",
  "properties": {
    "iso:country":"US",
    "sg:address":"33197 Gypsum Ave",
    "sg:city":"Sioux City",
    "sg:classifiers":[
        {
            "category":"Professional",
            "subcategory":"Business Services",
            "type":"Services"
        }
    ],
    "sg:phone":"+1 712 239 1432",
    "sg:postcode":"51108",
    "sg:province":"IA",
    "sg:tags":[
        "auctioneer"
    ],
    "wof:name":"J Ty Quade Auctioneer Appsr",
    "wof:placetype":"venue"
},
  "geometry": {"coordinates":[-96.35438000000001,42.572472],"type":"Point"}
}