{
  "type": "Feature",
  "properties": {
    "addr:full":"28963 300th St Richland IA 52585",
    "addr:housenumber":"28963",
    "addr:postcode":"52585",
    "addr:street":"300Th St",
    "iso:country":"US",
    "sg:address":"28963 300th St",
    "sg:city":"Richland",
    "sg:classifiers":[
        {
            "category":"Farming",
            "subcategory":"Livestock Farm",
            "type":"Manufacturing & Wholesale Goods"
        }
    ],
    "sg:phone":"+1 319 456 2614",
    "sg:postcode":"52585",
    "sg:province":"IA",
    "sg:tags":[
        "crop",
        "general"
    ],
    "wof:name":"Brinning Charles & Flora Belle",
    "wof:placetype":"venue"
},
  "geometry": {"coordinates":[-92.039783,41.221693],"type":"Point"}
}