{
  "type": "Feature",
  "properties": {
    "iso:country":"US",
    "sg:address":"2426 Ave L",
    "sg:city":"Fort Madison",
    "sg:classifiers":[
        {
            "category":"Utilities",
            "subcategory":"Mobile Phone",
            "type":"Services"
        }
    ],
    "sg:phone":"+1 319 372 8656",
    "sg:postcode":"52627",
    "sg:province":"IA",
    "sg:tags":[
        "telephone",
        "cellular"
    ],
    "wof:name":"Conn Communications Inc",
    "wof:placetype":"venue"
},
  "geometry": {"coordinates":[-91.34080299999999,40.627019],"type":"Point"}
}