{
  "type": "Feature",
  "properties": {
    "iso:country":"US",
    "sg:address":"1005 E 2nd St",
    "sg:city":"Muscatine",
    "sg:classifiers":[
        {
            "category":"Social Services",
            "type":"Services"
        }
    ],
    "sg:phone":"+1 563 263 8814",
    "sg:postcode":"52761",
    "sg:province":"IA",
    "sg:tags":[
        "second",
        "hand",
        "welfare"
    ],
    "sg:website":"http://www.salvationarmyusa.org",
    "wof:name":"Salvation Army",
    "wof:placetype":"venue"
},
  "geometry": {"coordinates":[-91.035828,41.426849],"type":"Point"}
}