{
  "type": "Feature",
  "properties": {
    "addr:full":"704 E Burlington Ave Fairfield IA 52556",
    "addr:housenumber":"704",
    "addr:postcode":"52556",
    "addr:street":"E Burlington Ave",
    "iso:country":"US",
    "sg:address":"704 E Burlington Ave",
    "sg:city":"Fairfield",
    "sg:classifiers":[
        {
            "category":"Communications",
            "subcategory":"Film & Video Production",
            "type":"Services"
        }
    ],
    "sg:phone":"+1 641 469 5322",
    "sg:postcode":"52556",
    "sg:province":"IA",
    "sg:tags":[
        "motion"
    ],
    "wof:name":"Mirada Productions Inc",
    "wof:placetype":"venue"
},
  "geometry": {"coordinates":[-91.95473200000001,41.006477],"type":"Point"}
}