{
  "type": "Feature",
  "properties": {
    "iso:country":"US",
    "sg:address":"10023 Bell Rd",
    "sg:city":"Arlington",
    "sg:phone":"+1 563 767 3092",
    "sg:postcode":"50606",
    "sg:province":"IA",
    "sg:tags":[
        "farm",
        "corn",
        "soybean"
    ],
    "wof:name":"Vernon Shaw",
    "wof:placetype":"venue"
},
  "geometry": {"coordinates":[-91.60268600000001,42.78904],"type":"Point"}
}