{
  "type": "Feature",
  "properties": {
    "iso:country":"US",
    "sg:address":"2570 73rd St",
    "sg:city":"Urbandale",
    "sg:classifiers":[
        {
            "category":"Professional",
            "subcategory":"Engineering",
            "type":"Services"
        }
    ],
    "sg:phone":"+1 515 331 6670",
    "sg:postcode":"50322",
    "sg:province":"IA",
    "sg:tags":[
        "engineer"
    ],
    "wof:name":"Missman Stanley & Assoc",
    "wof:placetype":"venue"
},
  "geometry": {"coordinates":[-93.718216,41.61672],"type":"Point"}
}