{
  "type": "Feature",
  "properties": {
    "addr:full":"1006 4th St La Porte City IA 50651",
    "addr:housenumber":"1006",
    "addr:postcode":"50651",
    "addr:street":"4Th St;Porte",
    "iso:country":"US",
    "sg:address":"1006 4th St",
    "sg:city":"La Porte City",
    "sg:classifiers":[
        {
            "category":"Government",
            "subcategory":"Office",
            "type":"Public Place"
        }
    ],
    "sg:phone":"+1 319 342 3323",
    "sg:postcode":"50651",
    "sg:province":"IA",
    "sg:tags":[
        "village"
    ],
    "wof:name":"LA Porte City Shed",
    "wof:placetype":"venue"
},
  "geometry": {"coordinates":[-92.18436699999999,42.313187],"type":"Point"}
}