{
  "type": "Feature",
  "properties": {
    "iso:country":"US",
    "sg:address":"823 S 17th St",
    "sg:city":"Clarinda",
    "sg:classifiers":[
        {
            "category":"Health Services",
            "subcategory":"Hospital",
            "type":"Services"
        }
    ],
    "sg:phone":"+1 712 542 2176",
    "sg:postcode":"51632",
    "sg:province":"IA",
    "sg:website":"www.clarindahealth.com",
    "wof:name":"Clarinda Regional Health Ctr",
    "wof:placetype":"venue"
},
  "geometry": {"coordinates":[-95.039226,40.730743],"type":"Point"}
}