{
  "type": "Feature",
  "properties": {
    "addr:full":"5404 NW 88th St Johnston IA 50131",
    "addr:housenumber":"5404",
    "addr:postcode":"50131",
    "addr:street":"Nw 88Th St",
    "iso:country":"US",
    "sg:address":"5404 NW 88th St",
    "sg:city":"Johnston",
    "sg:classifiers":[
        {
            "category":"Insurance",
            "subcategory":"Insurance Agent",
            "type":"Services"
        }
    ],
    "sg:phone":"+1 515 276 1527",
    "sg:postcode":"50131",
    "sg:province":"IA",
    "sg:website":"www.thrivent.com",
    "wof:name":"Thrivent Financial-Lutherans",
    "wof:placetype":"venue"
},
  "geometry": {"coordinates":[-93.740464,41.659657],"type":"Point"}
}