{
  "type": "Feature",
  "properties": {
    "addr:full":"1213 Merle Hay Rd Des Moines IA 50311",
    "addr:housenumber":"1213",
    "addr:postcode":"50311",
    "addr:street":"Merle Hay Rd Des",
    "iso:country":"US",
    "sg:address":"1213 Merle Hay Rd",
    "sg:city":"Des Moines",
    "sg:classifiers":[
        {
            "category":"Shopping",
            "subcategory":"Clothing, Apparel, & Fashions",
            "type":"Retail Goods"
        }
    ],
    "sg:phone":"+1 515 276 8790",
    "sg:postcode":"50311",
    "sg:province":"IA",
    "sg:tags":[
        "uniform"
    ],
    "wof:name":"Life Uniform & Shoe Shops",
    "wof:placetype":"venue"
},
  "geometry": {"coordinates":[-93.69765,41.601917],"type":"Point"}
}