{
  "type": "Feature",
  "properties": {
    "addr:full":"100 1st Ave NE Cedar Rapids IA 52401",
    "addr:housenumber":"100",
    "addr:postcode":"52401",
    "addr:street":"1St Ave Ne",
    "iso:country":"US",
    "sg:address":"100 1st Ave NE",
    "sg:city":"Cedar Rapids",
    "sg:classifiers":[
        {
            "category":"Real Estate",
            "subcategory":"Real Estate Services",
            "type":"Services"
        }
    ],
    "sg:phone":"+1 319 378 6722",
    "sg:postcode":"52401",
    "sg:province":"IA",
    "wof:name":"Glantz Jane Rl Est",
    "wof:placetype":"venue"
},
  "geometry": {"coordinates":[-91.66860200000001,41.978802],"type":"Point"}
}