{
  "type": "Feature",
  "properties": {
    "iso:country":"US",
    "sg:address":"324 W 4th St",
    "sg:city":"Davenport",
    "sg:classifiers":[
        {
            "category":"Retail",
            "subcategory":"Repair Shop",
            "type":"Services"
        }
    ],
    "sg:phone":"+1 563 322 8887",
    "sg:postcode":"52801",
    "sg:province":"IA",
    "wof:name":"Tuts Cycle",
    "wof:placetype":"venue"
},
  "geometry": {"coordinates":[-90.57822400000001,41.523609],"type":"Point"}
}