{
  "type": "Feature",
  "properties": {
    "iso:country":"US",
    "sg:address":"120 N Dodge St",
    "sg:city":"Algona",
    "sg:classifiers":[
        {
            "category":"Banks & Credit Unions",
            "subcategory":"Investment Brokerage",
            "type":"Services"
        }
    ],
    "sg:phone":"+1 515 295 7763",
    "sg:postcode":"50511",
    "sg:province":"IA",
    "sg:tags":[
        "stock",
        "bond"
    ],
    "wof:name":"Edward Jones Co",
    "wof:placetype":"venue"
},
  "geometry": {"coordinates":[-94.23662899999999,43.069253],"type":"Point"}
}