{
  "type": "Feature",
  "properties": {
    "iso:country":"US",
    "sg:address":"2334 550th St",
    "sg:city":"Albert City",
    "sg:classifiers":[
        {
            "category":"Manufacturing",
            "subcategory":"Pet Food",
            "type":"Manufacturing & Wholesale Goods"
        }
    ],
    "sg:phone":"+1 712 843 5474",
    "sg:postcode":"50510",
    "sg:province":"IA",
    "sg:tags":[
        "mfg"
    ],
    "wof:name":"Nutritional Edge Pet Foods",
    "wof:placetype":"venue"
},
  "geometry": {"coordinates":[-94.94727399999999,42.719616],"type":"Point"}
}