{
  "type": "Feature",
  "properties": {
    "addr:full":"1135 Frankville Rd Postville IA 52162",
    "addr:housenumber":"1135",
    "addr:postcode":"52162",
    "addr:street":"Frankville Rd",
    "iso:country":"US",
    "sg:address":"1135 Frankville Rd",
    "sg:city":"Postville",
    "sg:classifiers":[
        {
            "category":"Personal",
            "subcategory":"Beauty Salon",
            "type":"Services"
        }
    ],
    "sg:phone":"+1 563 567 8138",
    "sg:postcode":"52162",
    "sg:province":"IA",
    "sg:tags":[
        "shop"
    ],
    "wof:name":"Janet's Clip & Curl",
    "wof:placetype":"venue"
},
  "geometry": {"coordinates":[-91.618494,43.189707],"type":"Point"}
}