{
  "type": "Feature",
  "properties": {
    "iso:country":"US",
    "sg:address":"111 E South St",
    "sg:city":"Mt Ayr",
    "sg:classifiers":[
        {
            "category":"Organizations",
            "subcategory":"Religious Organization",
            "type":"Services"
        }
    ],
    "sg:phone":"+1 641 464 2424",
    "sg:postcode":"50854",
    "sg:province":"IA",
    "sg:tags":[
        "church"
    ],
    "wof:name":"First Lutheran Church",
    "wof:placetype":"venue"
},
  "geometry": {"coordinates":[-94.23638200000001,40.710913],"type":"Point"}
}