{
  "type": "Feature",
  "properties": {
    "iso:country":"US",
    "sg:address":"2019 Crossroads Blvd",
    "sg:city":"Waterloo",
    "sg:classifiers":[
        {
            "category":"Retail",
            "subcategory":"Auto Repair",
            "type":"Services"
        }
    ],
    "sg:phone":"+1 319 234 3588",
    "sg:postcode":"50702",
    "sg:province":"IA",
    "sg:tags":[
        "muffler",
        "exhaust",
        "system"
    ],
    "wof:name":"Midas Auto Svc Experts",
    "wof:placetype":"venue"
},
  "geometry": {"coordinates":[-92.31951599999999,42.463916],"type":"Point"}
}