{
  "type": "Feature",
  "properties": {
    "addr:full":"511 State St Ackley IA 50601",
    "addr:housenumber":"511",
    "addr:postcode":"50601",
    "addr:street":"State St",
    "iso:country":"US",
    "sg:address":"511 State St",
    "sg:city":"Ackley",
    "sg:classifiers":[
        {
            "category":"Education",
            "subcategory":"School",
            "type":"Public Place"
        }
    ],
    "sg:phone":"+1 641 847 2611",
    "sg:postcode":"50601",
    "sg:province":"IA",
    "wof:name":"Agwsr",
    "wof:placetype":"venue"
},
  "geometry": {"coordinates":[-93.051384,42.552102],"type":"Point"}
}