{
  "type": "Feature",
  "properties": {
    "addr:full":"4442 114th St Urbandale IA 50322",
    "addr:housenumber":"4442",
    "addr:postcode":"50322",
    "addr:street":"114Th St",
    "iso:country":"US",
    "sg:address":"4442 114th St",
    "sg:city":"Urbandale",
    "sg:classifiers":[
        {
            "category":"Wholesale",
            "subcategory":"Electrical",
            "type":"Manufacturing & Wholesale Goods"
        }
    ],
    "sg:phone":"+1 515 331 3833",
    "sg:postcode":"50322",
    "sg:province":"IA",
    "sg:tags":[
        "telecommunication"
    ],
    "wof:name":"North American Communications",
    "wof:placetype":"venue"
},
  "geometry": {"coordinates":[-93.775228,41.641864],"type":"Point"}
}