{
  "type": "Feature",
  "properties": {
    "iso:country":"US",
    "sg:address":"606 Dunn St",
    "sg:city":"Bellevue",
    "sg:classifiers":[
        {
            "category":"Building & Trades",
            "subcategory":"Construction",
            "type":"Services"
        }
    ],
    "sg:phone":"+1 563 872 3247",
    "sg:postcode":"52031",
    "sg:province":"IA",
    "sg:tags":[
        "painter"
    ],
    "wof:name":"Thielen Paintings",
    "wof:placetype":"venue"
},
  "geometry": {"coordinates":[-90.432985,42.261392],"type":"Point"}
}