{
  "type": "Feature",
  "properties": {
    "addr:full":"1743 Black Diamond Rd SW Oxford IA 52322",
    "addr:housenumber":"1743",
    "addr:postcode":"52322",
    "addr:street":"Black Diamond Rd Sw",
    "iso:country":"US",
    "sg:address":"1743 Black Diamond Rd SW",
    "sg:city":"Oxford",
    "sg:classifiers":[
        {
            "category":"Shopping",
            "type":"Retail Goods"
        }
    ],
    "sg:phone":"+1 319 828 4217",
    "sg:postcode":"52322",
    "sg:province":"IA",
    "sg:tags":[
        "merchandise"
    ],
    "wof:name":"Windham Store Inc",
    "wof:placetype":"venue"
},
  "geometry": {"coordinates":[-91.76109599999999,41.60898],"type":"Point"}
}