{
  "type": "Feature",
  "properties": {
    "addr:full":"107 E Meadow Ln Marshalltown IA 50158",
    "addr:housenumber":"107",
    "addr:postcode":"50158",
    "addr:street":"E Meadow Ln",
    "iso:country":"US",
    "sg:address":"107 E Meadow Ln",
    "sg:city":"Marshalltown",
    "sg:classifiers":[
        {
            "category":"Professional",
            "type":"Services"
        }
    ],
    "sg:phone":"+1 641 754 4049",
    "sg:postcode":"50158",
    "sg:province":"IA",
    "sg:tags":[
        "establishment"
    ],
    "wof:name":"13th Street Vacum",
    "wof:placetype":"venue"
},
  "geometry": {"coordinates":[-92.911247,42.025247],"type":"Point"}
}