{
  "type": "Feature",
  "properties": {
    "iso:country":"US",
    "sg:address":"512 Washington St",
    "sg:city":"Pella",
    "sg:classifiers":[
        {
            "category":"Personal",
            "type":"Services"
        }
    ],
    "sg:phone":"+1 641 628 2167",
    "sg:postcode":"50219",
    "sg:province":"IA",
    "wof:name":"W H & M C Schimmel",
    "wof:placetype":"venue"
},
  "geometry": {"coordinates":[-92.9147,41.408069],"type":"Point"}
}