{
  "type": "Feature",
  "properties": {
    "iso:country":"US",
    "sg:address":"520 US Hwy 18 E",
    "sg:city":"Clear Lake",
    "sg:classifiers":[
        {
            "category":"Cinema",
            "subcategory":"Movie Rental",
            "type":"Entertainment"
        }
    ],
    "sg:phone":"+1 641 357 2339",
    "sg:postcode":"50428",
    "sg:province":"IA",
    "sg:tags":[
        "leasing",
        "video",
        "disc",
        "tape"
    ],
    "wof:name":"Movies America",
    "wof:placetype":"venue"
},
  "geometry": {"coordinates":[-93.384404,43.14338],"type":"Point"}
}