{
  "type": "Feature",
  "properties": {
    "addr:full":"4430 V St Homestead IA 52236",
    "addr:housenumber":"4430",
    "addr:postcode":"52236",
    "addr:street":"V St",
    "iso:country":"US",
    "sg:address":"4430 V St",
    "sg:city":"Homestead",
    "sg:classifiers":[
        {
            "category":"Travel",
            "subcategory":"Hotels & Motels",
            "type":"Entertainment"
        }
    ],
    "sg:phone":"+1 319 622 3937",
    "sg:postcode":"52236",
    "sg:province":"IA",
    "wof:name":"Die Heimat Country Inn",
    "wof:placetype":"venue"
},
  "geometry": {"coordinates":[-91.861182,41.758909],"type":"Point"}
}