{
  "type": "Feature",
  "properties": {
    "iso:country":"US",
    "sg:address":"642 4th St",
    "sg:city":"Princeton",
    "sg:classifiers":[
        {
            "category":"Manufacturing",
            "subcategory":"Lumber",
            "type":"Manufacturing & Wholesale Goods"
        }
    ],
    "sg:phone":"+1 563 289 4570",
    "sg:postcode":"52768",
    "sg:province":"IA",
    "sg:tags":[
        "company",
        "logging"
    ],
    "wof:name":"Blunt Logging",
    "wof:placetype":"venue"
},
  "geometry": {"coordinates":[-90.343756,41.672768],"type":"Point"}
}