{
  "type": "Feature",
  "properties": {
    "iso:country":"US",
    "sg:address":"2799 Hamilton Blvd",
    "sg:city":"Sioux City",
    "sg:classifiers":[
        {
            "category":"Coffee & Tea",
            "type":"Food & Drink"
        }
    ],
    "sg:menulink":"http://www.allmenus.com/ia/sioux-city/221087-caribou-coffee/menu/",
    "sg:phone":"+1 712 252 5422",
    "sg:postcode":"51104",
    "sg:province":"IA",
    "sg:tags":[
        "american",
        "diner"
    ],
    "wof:name":"Caribou Coffee",
    "wof:placetype":"venue"
},
  "geometry": {"coordinates":[-96.41763400000001,42.518792],"type":"Point"}
}