{
  "type": "Feature",
  "properties": {
    "iso:country":"US",
    "sg:address":"920 Broadway St",
    "sg:city":"Emmetsburg",
    "sg:classifiers":[
        {
            "category":"Professional",
            "subcategory":"Lawyer & Legal Services",
            "type":"Services"
        }
    ],
    "sg:phone":"+1 712 852 3064",
    "sg:postcode":"50536",
    "sg:province":"IA",
    "sg:tags":[
        "attorney"
    ],
    "wof:name":"John F Doran",
    "wof:placetype":"venue"
},
  "geometry": {"coordinates":[-94.67878,43.111801],"type":"Point"}
}