{
  "type": "Feature",
  "properties": {
    "addr:full":"117 4th Ave S Clinton IA 52732",
    "addr:housenumber":"117",
    "addr:postcode":"52732",
    "addr:street":"4Th Ave S",
    "iso:country":"US",
    "sg:address":"117 4th Ave S",
    "sg:city":"Clinton",
    "sg:classifiers":[
        {
            "category":"Professional",
            "subcategory":"Management & Consulting",
            "type":"Services"
        },
        {
            "category":"Banks & Credit Unions",
            "subcategory":"Financial Services",
            "type":"Services"
        }
    ],
    "sg:phone":"+1 563 242 3100",
    "sg:postcode":"52732",
    "sg:province":"IA",
    "sg:tags":[
        "consultant",
        "financing",
        "planning"
    ],
    "sg:website":"http://www.ameriprise.com",
    "wof:name":"Ameriprise Financial",
    "wof:placetype":"venue"
},
  "geometry": {"coordinates":[-90.186121,41.842312],"type":"Point"}
}