{
  "type": "Feature",
  "properties": {
    "addr:full":"14917 Gibson Rd Traer IA 50675",
    "addr:housenumber":"14917",
    "addr:postcode":"50675",
    "addr:street":"Gibson Rd",
    "iso:country":"US",
    "sg:address":"14917 Gibson Rd",
    "sg:city":"Traer",
    "sg:phone":"+1 319 988 3903",
    "sg:postcode":"50675",
    "sg:province":"IA",
    "sg:tags":[
        "farm"
    ],
    "wof:name":"Ross Schmidt",
    "wof:placetype":"venue"
},
  "geometry": {"coordinates":[-92.494586,42.297149],"type":"Point"}
}