{
  "type": "Feature",
  "properties": {
    "addr:full":"192 6th Ave NE Le Mars IA 51031",
    "addr:housenumber":"192",
    "addr:postcode":"51031",
    "addr:street":"6Th Ave Ne",
    "iso:country":"US",
    "sg:address":"192 6th Ave NE",
    "sg:city":"Le Mars",
    "sg:classifiers":[
        {
            "category":"Health Services",
            "subcategory":"Podiatrist",
            "type":"Services"
        }
    ],
    "sg:phone":"+1 712 546 7490",
    "sg:postcode":"51031",
    "sg:province":"IA",
    "wof:name":"Charles Keenan Jr DPM",
    "wof:placetype":"venue"
},
  "geometry": {"coordinates":[-96.15766000000001,42.794481],"type":"Point"}
}