{
  "type": "Feature",
  "properties": {
    "iso:country":"US",
    "sg:address":"1920 Albany Pl SE",
    "sg:city":"Orange City",
    "sg:classifiers":[
        {
            "category":"Manufacturing",
            "subcategory":"Chemicals & Compounds",
            "type":"Manufacturing & Wholesale Goods"
        }
    ],
    "sg:phone":"+1 712 737 4016",
    "sg:postcode":"51041",
    "sg:province":"IA",
    "sg:tags":[
        "paint"
    ],
    "sg:website":"www.ezliner.com",
    "wof:name":"E Z Liner Industries",
    "wof:placetype":"venue"
},
  "geometry": {"coordinates":[-96.05709,42.98476],"type":"Point"}
}