{
  "type": "Feature",
  "properties": {
    "addr:full":"1419 Main St Rock Valley IA 51247",
    "addr:housenumber":"1419",
    "addr:postcode":"51247",
    "addr:street":"Main St",
    "iso:country":"US",
    "sg:address":"1419 Main St",
    "sg:city":"Rock Valley",
    "sg:classifiers":[
        {
            "category":"Restaurant",
            "type":"Food & Drink"
        }
    ],
    "sg:menulink":"http://www.allmenus.com/ia/rock/67090-pizza-hut/menu/",
    "sg:phone":"+1 712 476 2773",
    "sg:postcode":"51247",
    "sg:province":"IA",
    "sg:tags":[
        "american",
        "pizza"
    ],
    "wof:name":"Pizza Hut",
    "wof:placetype":"venue"
},
  "geometry": {"coordinates":[-96.294873,43.204364],"type":"Point"}
}