{
  "type": "Feature",
  "properties": {
    "addr:full":"1423 14th St Rock Valley IA 51247",
    "addr:housenumber":"1423",
    "addr:postcode":"51247",
    "addr:street":"14Th St",
    "iso:country":"US",
    "sg:address":"1423 14th St",
    "sg:city":"Rock Valley",
    "sg:classifiers":[
        {
            "category":"Food & Beverages",
            "subcategory":"Specialty",
            "type":"Retail Goods"
        }
    ],
    "sg:phone":"+1 712 476 2893",
    "sg:postcode":"51247",
    "sg:province":"IA",
    "sg:tags":[
        "product",
        "chinese"
    ],
    "wof:name":"Chia-Chi Enterprises",
    "wof:placetype":"venue"
},
  "geometry": {"coordinates":[-96.29797000000001,43.204204],"type":"Point"}
}