{
  "type": "Feature",
  "properties": {
    "addr:full":"2020 Grand Ave West Des Moines IA 50265",
    "addr:housenumber":"2020",
    "addr:postcode":"50265",
    "addr:street":"Grand Ave",
    "iso:country":"US",
    "sg:address":"2020 Grand Ave",
    "sg:city":"West Des Moines",
    "sg:classifiers":[
        {
            "category":"Retail",
            "subcategory":"Portrait Studio",
            "type":"Services"
        }
    ],
    "sg:phone":"+1 515 221 1060",
    "sg:postcode":"50265",
    "sg:province":"IA",
    "sg:tags":[
        "photographer"
    ],
    "wof:name":"Tim Vorland Photography",
    "wof:placetype":"venue"
},
  "geometry": {"coordinates":[-93.732495,41.569544],"type":"Point"}
}