{
  "type": "Feature",
  "properties": {
    "addr:full":"120 3rd St SW Hartley IA 51346",
    "addr:housenumber":"120",
    "addr:postcode":"51346",
    "addr:street":"3Rd St Sw",
    "iso:country":"US",
    "sg:address":"120 3rd St SW",
    "sg:city":"Hartley",
    "sg:classifiers":[
        {
            "category":"Government",
            "subcategory":"Office",
            "type":"Public Place"
        }
    ],
    "sg:phone":"+1 712 928 2829",
    "sg:postcode":"51346",
    "sg:province":"IA",
    "sg:tags":[
        "village"
    ],
    "wof:name":"Hartley Maintenance Garage",
    "wof:placetype":"venue"
},
  "geometry": {"coordinates":[-95.478803,43.177738],"type":"Point"}
}