{
  "type": "Feature",
  "properties": {
    "iso:country":"US",
    "sg:address":"2037 170th Ave",
    "sg:city":"Milford",
    "sg:classifiers":[
        {
            "category":"Farming",
            "subcategory":"Livestock Farm",
            "type":"Manufacturing & Wholesale Goods"
        }
    ],
    "sg:phone":"+1 712 338 4080",
    "sg:postcode":"51351",
    "sg:province":"IA",
    "sg:tags":[
        "hog",
        "beef",
        "far",
        "corn",
        "cattle",
        "or",
        "feedlot"
    ],
    "wof:name":"Merle Hartman",
    "wof:placetype":"venue"
},
  "geometry": {"coordinates":[-95.249489,43.35177],"type":"Point"}
}