{
  "type": "Feature",
  "properties": {
    "iso:country":"US",
    "sg:address":"164 Main St",
    "sg:city":"Dubuque",
    "sg:classifiers":[
        {
            "category":"Real Estate",
            "subcategory":"Real Estate Agent",
            "type":"Services"
        }
    ],
    "sg:phone":"+1 563 582 9414",
    "sg:postcode":"52001",
    "sg:province":"IA",
    "wof:name":"MSI Properties Corp",
    "wof:placetype":"venue"
},
  "geometry": {"coordinates":[-90.664207,42.495395],"type":"Point"}
}