{
  "type": "Feature",
  "properties": {
    "addr:full":"404 Sherman Ave Ackley IA 50601",
    "addr:housenumber":"404",
    "addr:postcode":"50601",
    "addr:street":"Sherman Ave",
    "iso:country":"US",
    "sg:address":"404 Sherman Ave",
    "sg:city":"Ackley",
    "sg:classifiers":[
        {
            "category":"Autos & Motor Vehicles",
            "subcategory":"Automobile Sales",
            "type":"Retail Goods"
        }
    ],
    "sg:phone":"+1 641 847 2135",
    "sg:postcode":"50601",
    "sg:province":"IA",
    "sg:tags":[
        "car",
        "dealer"
    ],
    "sg:website":"www.sailerford.com",
    "wof:name":"Sailer Ford Inc",
    "wof:placetype":"venue"
},
  "geometry": {"coordinates":[-93.059901,42.55669],"type":"Point"}
}