{
  "type": "Feature",
  "properties": {
    "iso:country":"US",
    "sg:address":"4920 Dubuque Rd",
    "sg:city":"Waterloo",
    "sg:classifiers":[
        {
            "category":"Building & Trades",
            "subcategory":"Construction",
            "type":"Services"
        }
    ],
    "sg:phone":"+1 319 235 9565",
    "sg:postcode":"50703",
    "sg:province":"IA",
    "sg:tags":[
        "repairing",
        "remodeling",
        "contractor"
    ],
    "sg:website":"www.tchomeimprovement.com",
    "wof:name":"Town & Country Home Imprvmnt",
    "wof:placetype":"venue"
},
  "geometry": {"coordinates":[-92.243652,42.46678],"type":"Point"}
}