{
  "type": "Feature",
  "properties": {
    "iso:country":"US",
    "sg:address":"732 2nd St",
    "sg:city":"Webster City",
    "sg:classifiers":[
        {
            "category":"Bars & Pubs",
            "type":"Food & Drink"
        }
    ],
    "sg:phone":"+1 515 832 9816",
    "sg:postcode":"50595",
    "sg:province":"IA",
    "wof:name":"Bow Lounge",
    "wof:placetype":"venue"
},
  "geometry": {"coordinates":[-93.823044,42.46938],"type":"Point"}
}