{
  "type": "Feature",
  "properties": {
    "iso:country":"US",
    "sg:address":"4455 Dodge St",
    "sg:city":"Dubuque",
    "sg:classifiers":[
        {
            "category":"Autos & Motor Vehicles",
            "subcategory":"Automobile Sales",
            "type":"Retail Goods"
        }
    ],
    "sg:phone":"+1 563 588 2326",
    "sg:postcode":"52003",
    "sg:province":"IA",
    "sg:tags":[
        "car",
        "dealer"
    ],
    "wof:name":"Riley's Mazda-Subaru",
    "wof:placetype":"venue"
},
  "geometry": {"coordinates":[-90.740212,42.48823],"type":"Point"}
}