{
  "type": "Feature",
  "properties": {
    "addr:full":"1703 Waterloo Rd Cedar Falls IA 50613",
    "addr:housenumber":"1703",
    "addr:postcode":"50613",
    "addr:street":"Waterloo Rd",
    "iso:country":"US",
    "sg:address":"1703 Waterloo Rd",
    "sg:city":"Cedar Falls",
    "sg:classifiers":[
        {
            "category":"Building & Trades",
            "subcategory":"Plumbing",
            "type":"Services"
        }
    ],
    "sg:phone":"+1 319 266 3538",
    "sg:postcode":"50613",
    "sg:province":"IA",
    "sg:tags":[
        "heating",
        "contractor"
    ],
    "wof:name":"Urban Heating & Air Cond",
    "wof:placetype":"venue"
},
  "geometry": {"coordinates":[-92.436387,42.521309],"type":"Point"}
}