{
  "type": "Feature",
  "properties": {
    "addr:full":"1940 Ventura Ave Ottumwa IA 52586",
    "addr:housenumber":"1940",
    "addr:postcode":"52586",
    "addr:street":"Ventura Ave",
    "iso:country":"US",
    "sg:address":"1940 Ventura Ave",
    "sg:city":"Ottumwa",
    "sg:classifiers":[
        {
            "category":"Utilities",
            "subcategory":"Mobile Phone",
            "type":"Services"
        }
    ],
    "sg:phone":"+1 641 683 9760",
    "sg:postcode":"52586",
    "sg:province":"IA",
    "sg:tags":[
        "telephone",
        "cellular"
    ],
    "wof:name":"U S Cellular",
    "wof:placetype":"venue"
},
  "geometry": {"coordinates":[-92.46428,41.373962],"type":"Point"}
}