{
  "type": "Feature",
  "properties": {
    "iso:country":"US",
    "sg:address":"201 Helen St NE",
    "sg:city":"Hopkinton",
    "sg:classifiers":[
        {
            "category":"Farming",
            "subcategory":"Farm",
            "type":"Manufacturing & Wholesale Goods"
        }
    ],
    "sg:phone":"+1 563 926 2546",
    "sg:postcode":"52237",
    "sg:province":"IA",
    "sg:tags":[
        "crop",
        "general"
    ],
    "wof:name":"James F Guthrie",
    "wof:placetype":"venue"
},
  "geometry": {"coordinates":[-91.240633,42.348279],"type":"Point"}
}