{
  "type": "Feature",
  "properties": {
    "iso:country":"US",
    "sg:address":"5180 NW 2nd St",
    "sg:city":"Des Moines",
    "sg:classifiers":[
        {
            "category":"Wholesale",
            "subcategory":"Electrical",
            "type":"Manufacturing & Wholesale Goods"
        }
    ],
    "sg:phone":"+1 515 244 6248",
    "sg:postcode":"50313",
    "sg:province":"IA",
    "sg:tags":[
        "supply",
        "sign"
    ],
    "wof:name":"Ameritec Sign Supplies",
    "wof:placetype":"venue"
},
  "geometry": {"coordinates":[-93.620217,41.654405],"type":"Point"}
}