{
  "type": "Feature",
  "properties": {
    "addr:full":"180 Morgan Ct Cedar Rapids IA 52411",
    "addr:housenumber":"180",
    "addr:postcode":"52411",
    "addr:street":"Morgan Ct",
    "iso:country":"US",
    "sg:address":"180 Morgan Ct",
    "sg:city":"Cedar Rapids",
    "sg:classifiers":[
        {
            "category":"Retail",
            "subcategory":"Portrait Studio",
            "type":"Services"
        }
    ],
    "sg:phone":"+1 319 378 1133",
    "sg:postcode":"52411",
    "sg:province":"IA",
    "sg:tags":[
        "photographer"
    ],
    "wof:name":"Spotlight Images",
    "wof:placetype":"venue"
},
  "geometry": {"coordinates":[-91.68947300000001,42.077038],"type":"Point"}
}