{
  "type": "Feature",
  "properties": {
    "addr:full":"717 Lyon St Des Moines IA 50309",
    "addr:housenumber":"717",
    "addr:postcode":"50309",
    "addr:street":"Lyon St",
    "iso:country":"US",
    "sg:address":"717 Lyon St",
    "sg:city":"Des Moines",
    "sg:classifiers":[
        {
            "category":"Shopping",
            "subcategory":"Pharmacy",
            "type":"Retail Goods"
        }
    ],
    "sg:phone":"+1 515 288 8424",
    "sg:postcode":"50309",
    "sg:province":"IA",
    "wof:name":"Wilden Pharmacy",
    "wof:placetype":"venue"
},
  "geometry": {"coordinates":[-93.608276,41.59347],"type":"Point"}
}