{
  "type": "Feature",
  "properties": {
    "iso:country":"US",
    "sg:address":"2010 E 38th St",
    "sg:city":"Davenport",
    "sg:classifiers":[
        {
            "category":"Organizations",
            "subcategory":"Community Association",
            "type":"Services"
        }
    ],
    "sg:phone":"+1 563 359 3795",
    "sg:postcode":"52807",
    "sg:province":"IA",
    "wof:name":"Condo Association",
    "wof:placetype":"venue"
},
  "geometry": {"coordinates":[-90.54618600000001,41.558899],"type":"Point"}
}