{
  "type": "Feature",
  "properties": {
    "iso:country":"US",
    "sg:address":"2791 15th St",
    "sg:city":"Spirit Lake",
    "sg:classifiers":[
        {
            "category":"Restaurant",
            "type":"Food & Drink"
        }
    ],
    "sg:phone":"+1 712 336 9000",
    "sg:postcode":"51360",
    "sg:province":"IA",
    "wof:name":"Oaktree Bar-B-Que",
    "wof:placetype":"venue"
},
  "geometry": {"coordinates":[-95.13496000000001,43.425495],"type":"Point"}
}