{
  "type": "Feature",
  "properties": {
    "iso:country":"US",
    "sg:address":"823 E Burlington St",
    "sg:city":"Iowa City",
    "sg:classifiers":[
        {
            "category":"Organizations",
            "subcategory":"Community Association",
            "type":"Services"
        }
    ],
    "sg:phone":"+1 319 338 7847",
    "sg:postcode":"52240",
    "sg:province":"IA",
    "sg:tags":[
        "sorority"
    ],
    "wof:name":"Kappa Alpha Theta Sorority",
    "wof:placetype":"venue"
},
  "geometry": {"coordinates":[-91.523122,41.65772],"type":"Point"}
}