{
  "type": "Feature",
  "properties": {
    "addr:full":"309 10th St Onawa IA 51040",
    "addr:housenumber":"309",
    "addr:postcode":"51040",
    "addr:street":"10Th St",
    "iso:country":"US",
    "sg:address":"309 10th St",
    "sg:city":"Onawa",
    "sg:classifiers":[
        {
            "category":"Personal",
            "type":"Services"
        }
    ],
    "sg:phone":"+1 712 423 1665",
    "sg:postcode":"51040",
    "sg:province":"IA",
    "sg:tags":[
        "therapist",
        "massage"
    ],
    "wof:name":"Soothing Touch Massage Therapy",
    "wof:placetype":"venue"
},
  "geometry": {"coordinates":[-96.097645,42.036242],"type":"Point"}
}