{
  "type": "Feature",
  "properties": {
    "addr:full":"74 Mill St Clermont IA 52135",
    "addr:housenumber":"74",
    "addr:postcode":"52135",
    "addr:street":"Mill St",
    "iso:country":"US",
    "sg:address":"74 Mill St",
    "sg:city":"Clermont",
    "sg:classifiers":[
        {
            "category":"Autos & Motor Vehicles",
            "subcategory":"Fuel & Gas Station",
            "type":"Retail Goods"
        }
    ],
    "sg:phone":"+1 563 423 5505",
    "sg:postcode":"52135",
    "sg:province":"IA",
    "sg:tags":[
        "oil"
    ],
    "wof:name":"Conoco Amart",
    "wof:placetype":"venue"
},
  "geometry": {"coordinates":[-91.658327,42.997612],"type":"Point"}
}