{
  "type": "Feature",
  "properties": {
    "iso:country":"US",
    "sg:address":"2791 State Hwy 60",
    "sg:city":"Sheldon",
    "sg:classifiers":[
        {
            "category":"Wholesale",
            "subcategory":"Farm Supplies",
            "type":"Manufacturing & Wholesale Goods"
        }
    ],
    "sg:phone":"+1 712 324 5197",
    "sg:postcode":"51201",
    "sg:province":"IA",
    "sg:tags":[
        "feed"
    ],
    "wof:name":"Farmers Co-Op Society",
    "wof:placetype":"venue"
},
  "geometry": {"coordinates":[-95.86147,43.166646],"type":"Point"}
}