{
  "type": "Feature",
  "properties": {
    "addr:full":"3822 6th Ave Sioux City SD 51106",
    "addr:housenumber":"3822",
    "addr:postcode":"51106",
    "addr:street":"6Th Ave",
    "iso:country":"US",
    "sg:address":"3822 6th Ave",
    "sg:city":"Sioux City",
    "sg:classifiers":[
        {
            "category":"Building & Trades",
            "subcategory":"Cleaning & Sanitation",
            "type":"Services"
        }
    ],
    "sg:phone":"+1 712 274 9409",
    "sg:postcode":"51106",
    "sg:province":"SD",
    "sg:tags":[
        "janitor"
    ],
    "wof:name":"Jarvis Janitorial Svc",
    "wof:placetype":"venue"
},
  "geometry": {"coordinates":[-96.35692299999999,42.467128],"type":"Point"}
}