{
  "type": "Feature",
  "properties": {
    "iso:country":"US",
    "sg:address":"1309 S Kentucky Ave",
    "sg:city":"Mason City",
    "sg:classifiers":[
        {
            "category":"Organizations",
            "subcategory":"Religious Organization",
            "type":"Services"
        }
    ],
    "sg:phone":"+1 641 424 4211",
    "sg:postcode":"50401",
    "sg:province":"IA",
    "sg:tags":[
        "church"
    ],
    "wof:name":"Church Of Jesus Christ Of Lds",
    "wof:placetype":"venue"
},
  "geometry": {"coordinates":[-93.181123,43.139202],"type":"Point"}
}