{
  "type": "Feature",
  "properties": {
    "iso:country":"US",
    "sg:address":"1212 3rd Ave",
    "sg:city":"Alton",
    "sg:classifiers":[
        {
            "category":"Food & Beverages",
            "subcategory":"Groceries & Convenience Stores",
            "type":"Retail Goods"
        }
    ],
    "sg:phone":"+1 712 756 4315",
    "sg:postcode":"51003",
    "sg:province":"IA",
    "wof:name":"Midwest Farmers Coop",
    "wof:placetype":"venue"
},
  "geometry": {"coordinates":[-96.008779,42.990061],"type":"Point"}
}