{
  "type": "Feature",
  "properties": {
    "iso:country":"US",
    "sg:address":"107 S Locust St",
    "sg:city":"Glenwood",
    "sg:classifiers":[
        {
            "category":"Government",
            "subcategory":"Office",
            "type":"Public Place"
        }
    ],
    "sg:phone":"+1 712 527 4868",
    "sg:postcode":"51534",
    "sg:province":"IA",
    "sg:tags":[
        "village"
    ],
    "wof:name":"Glenwood Secretary-Water Board",
    "wof:placetype":"venue"
},
  "geometry": {"coordinates":[-95.744657,41.046169],"type":"Point"}
}