{
  "type": "Feature",
  "properties": {
    "iso:country":"US",
    "sg:address":"4004 Vegas Ct",
    "sg:city":"Sioux City",
    "sg:classifiers":[
        {
            "category":"Professional",
            "subcategory":"Computer Services",
            "type":"Services"
        }
    ],
    "sg:phone":"+1 712 266 9597",
    "sg:postcode":"51106",
    "sg:province":"SD",
    "wof:name":"Computers & More",
    "wof:placetype":"venue"
},
  "geometry": {"coordinates":[-96.359142,42.452869],"type":"Point"}
}