{
  "type": "Feature",
  "properties": {
    "iso:country":"US",
    "sg:address":"134 W Jefferson St",
    "sg:city":"Osceola",
    "sg:classifiers":[
        {
            "category":"Government",
            "subcategory":"Office",
            "type":"Public Place"
        }
    ],
    "sg:phone":"+1 641 342 3724",
    "sg:postcode":"50213",
    "sg:province":"IA",
    "sg:tags":[
        "county",
        "program",
        "health"
    ],
    "wof:name":"Clarke County Public Health",
    "wof:placetype":"venue"
},
  "geometry": {"coordinates":[-93.766103,41.033402],"type":"Point"}
}