{
  "type": "Feature",
  "properties": {
    "iso:country":"US",
    "sg:address":"607 S 5th St",
    "sg:city":"Bellevue",
    "sg:classifiers":[
        {
            "category":"Travel",
            "subcategory":"Hotels & Motels",
            "type":"Entertainment"
        },
        {
            "category":"Personal",
            "type":"Services"
        }
    ],
    "sg:phone":"+1 563 872 3158",
    "sg:postcode":"52031",
    "sg:province":"IA",
    "sg:tags":[
        "concierge",
        "assistant"
    ],
    "wof:name":"Ralph E Kraai",
    "wof:placetype":"venue"
},
  "geometry": {"coordinates":[-90.42593599999999,42.253382],"type":"Point"}
}