{
  "type": "Feature",
  "properties": {
    "iso:country":"US",
    "sg:address":"100 E Union St",
    "sg:city":"Unionville",
    "sg:classifiers":[
        {
            "category":"Organizations",
            "subcategory":"Religious Organization",
            "type":"Services"
        }
    ],
    "sg:phone":"+1 641 452 6442",
    "sg:postcode":"52594",
    "sg:province":"IA",
    "sg:tags":[
        "church"
    ],
    "wof:name":"Unionville Baptist Church",
    "wof:placetype":"venue"
},
  "geometry": {"coordinates":[-92.69590100000001,40.819441],"type":"Point"}
}