{
  "type": "Feature",
  "properties": {
    "iso:country":"US",
    "sg:address":"913 Chatburn Ave",
    "sg:city":"Harlan",
    "sg:classifiers":[
        {
            "category":"Health Services",
            "subcategory":"Doctor",
            "type":"Services"
        }
    ],
    "sg:phone":"+1 712 755 2854",
    "sg:postcode":"51537",
    "sg:province":"IA",
    "sg:tags":[
        "dentist"
    ],
    "wof:name":"Southwest Orthodontic Assoc",
    "wof:placetype":"venue"
},
  "geometry": {"coordinates":[-95.32126599999999,41.645282],"type":"Point"}
}