{
  "type": "Feature",
  "properties": {
    "iso:country":"US",
    "sg:address":"617 2nd St",
    "sg:city":"Webster City",
    "sg:classifiers":[
        {
            "category":"Shopping",
            "type":"Retail Goods"
        }
    ],
    "sg:phone":"+1 515 832 2391",
    "sg:postcode":"50595",
    "sg:province":"IA",
    "sg:tags":[
        "hearing",
        "equipment",
        "supply",
        "impaired"
    ],
    "wof:name":"Hearing Unlimited",
    "wof:placetype":"venue"
},
  "geometry": {"coordinates":[-93.82121600000001,42.469519],"type":"Point"}
}