{
  "type": "Feature",
  "properties": {
    "iso:country":"US",
    "sg:address":"1045 140th St",
    "sg:city":"Danbury",
    "sg:phone":"+1 712 365 4627",
    "sg:postcode":"51019",
    "sg:province":"IA",
    "sg:tags":[
        "beef",
        "farm",
        "corn",
        "soybean",
        "cattle",
        "feedlot"
    ],
    "wof:name":"Schultz De Wayne",
    "wof:placetype":"venue"
},
  "geometry": {"coordinates":[-95.59439999999999,42.204242],"type":"Point"}
}