{
  "type": "Feature",
  "properties": {
    "iso:country":"US",
    "sg:address":"520 E Ave NW",
    "sg:city":"Cedar Rapids",
    "sg:classifiers":[
        {
            "category":"Manufacturing",
            "subcategory":"Metals",
            "type":"Manufacturing & Wholesale Goods"
        }
    ],
    "sg:phone":"+1 319 365 5267",
    "sg:postcode":"52405",
    "sg:province":"IA",
    "sg:tags":[
        "equipment",
        "heating"
    ],
    "sg:website":"www.johnsongas.com",
    "wof:name":"Johnson Gas Appliance Co",
    "wof:placetype":"venue"
},
  "geometry": {"coordinates":[-91.68196500000001,41.97806],"type":"Point"}
}