{
  "type": "Feature",
  "properties": {
    "iso:country":"US",
    "sg:address":"736 1400th St",
    "sg:city":"Harlan",
    "sg:classifiers":[
        {
            "category":"Insurance",
            "subcategory":"Insurance Agent",
            "type":"Services"
        }
    ],
    "sg:phone":"+1 712 627 4632",
    "sg:postcode":"51537",
    "sg:province":"IA",
    "wof:name":"Mary L Stephany Insurance",
    "wof:placetype":"venue"
},
  "geometry": {"coordinates":[-95.430328,41.703748],"type":"Point"}
}