{
  "type": "Feature",
  "properties": {
    "iso:country":"US",
    "sg:address":"1937 Elmwood Ave",
    "sg:city":"Alvord",
    "sg:phone":"+1 712 473 2453",
    "sg:postcode":"51230",
    "sg:province":"IA",
    "sg:tags":[
        "farm",
        "corn"
    ],
    "wof:name":"David Childress",
    "wof:placetype":"venue"
},
  "geometry": {"coordinates":[-96.29388,43.366918],"type":"Point"}
}