{
  "type": "Feature",
  "properties": {
    "iso:country":"US",
    "sg:address":"2417 255th St",
    "sg:city":"De Witt",
    "sg:classifiers":[
        {
            "category":"Building & Trades",
            "subcategory":"Plumbing",
            "type":"Services"
        }
    ],
    "sg:phone":"+1 563 847 5221",
    "sg:postcode":"52742",
    "sg:province":"IA",
    "sg:tags":[
        "conditioning",
        "air",
        "system",
        "contractor"
    ],
    "wof:name":"Dick's Heating & Air Cond",
    "wof:placetype":"venue"
},
  "geometry": {"coordinates":[-90.61508499999999,41.807423],"type":"Point"}
}