{
  "type": "Feature",
  "properties": {
    "iso:country":"US",
    "sg:address":"335 River Dr",
    "sg:city":"Princeton",
    "sg:classifiers":[
        {
            "category":"Banks & Credit Unions",
            "subcategory":"Financial Services",
            "type":"Services"
        }
    ],
    "sg:phone":"+1 563 289 5311",
    "sg:postcode":"52768",
    "sg:province":"IA",
    "sg:tags":[
        "company",
        "holding"
    ],
    "sg:website":"www.greatriverbank.com",
    "wof:name":"Princeton Le Claire Agency Inc",
    "wof:placetype":"venue"
},
  "geometry": {"coordinates":[-90.339637,41.677393],"type":"Point"}
}