{
  "type": "Feature",
  "properties": {
    "iso:country":"US",
    "sg:address":"1409 S Main St",
    "sg:city":"Centerville",
    "sg:classifiers":[
        {
            "category":"Social Services",
            "subcategory":"Child Care",
            "type":"Services"
        }
    ],
    "sg:phone":"+1 641 437 4437",
    "sg:postcode":"52544",
    "sg:province":"IA",
    "sg:tags":[
        "kindergarten",
        "academic",
        "school"
    ],
    "wof:name":"Learning Tree Preschool",
    "wof:placetype":"venue"
},
  "geometry": {"coordinates":[-92.874105,40.721645],"type":"Point"}
}