{
  "type": "Feature",
  "properties": {
    "iso:country":"US",
    "sg:address":"406 E 7th St",
    "sg:city":"Dubuque",
    "sg:classifiers":[
        {
            "category":"Wholesale",
            "subcategory":"Machinery & Supplies",
            "type":"Manufacturing & Wholesale Goods"
        }
    ],
    "sg:phone":"+1 563 690 0505",
    "sg:postcode":"52001",
    "sg:province":"IA",
    "sg:tags":[
        "equipment",
        "paint"
    ],
    "wof:name":"Dubuque Paint Equipment Svc",
    "wof:placetype":"venue"
},
  "geometry": {"coordinates":[-90.66016999999999,42.501854],"type":"Point"}
}