{
  "type": "Feature",
  "properties": {
    "addr:full":"641 Edgewood Rd NW Cedar Rapids IA 52405",
    "addr:housenumber":"641",
    "addr:postcode":"52405",
    "addr:street":"Edgewood Rd Nw",
    "iso:country":"US",
    "sg:address":"641 Edgewood Rd NW",
    "sg:city":"Cedar Rapids",
    "sg:classifiers":[
        {
            "category":"Food & Beverages",
            "subcategory":"Groceries & Convenience Stores",
            "type":"Retail Goods"
        }
    ],
    "sg:phone":"+1 319 396 7680",
    "sg:postcode":"52405",
    "sg:province":"IA",
    "sg:website":"www.caseys.com",
    "wof:name":"Casey's General Store",
    "wof:placetype":"venue"
},
  "geometry": {"coordinates":[-91.71571400000001,41.978608],"type":"Point"}
}