{
  "type": "Feature",
  "properties": {
    "addr:full":"1924 14th St Rock Valley IA 51247",
    "addr:housenumber":"1924",
    "addr:postcode":"51247",
    "addr:street":"14Th St",
    "iso:country":"US",
    "sg:address":"1924 14th St",
    "sg:city":"Rock Valley",
    "sg:classifiers":[
        {
            "category":"Farming",
            "subcategory":"Farm",
            "type":"Manufacturing & Wholesale Goods"
        }
    ],
    "sg:phone":"+1 712 476 2368",
    "sg:postcode":"51247",
    "sg:province":"IA",
    "sg:tags":[
        "crop",
        "general"
    ],
    "wof:name":"Vanbeek Wilmer",
    "wof:placetype":"venue"
},
  "geometry": {"coordinates":[-96.28956700000001,43.204094],"type":"Point"}
}