{
  "type": "Feature",
  "properties": {
    "iso:country":"US",
    "sg:address":"1524 Hawthorne Ln",
    "sg:city":"Jefferson",
    "sg:classifiers":[
        {
            "category":"Building & Trades",
            "subcategory":"Construction",
            "type":"Services"
        }
    ],
    "sg:phone":"+1 515 386 3589",
    "sg:postcode":"50129",
    "sg:province":"IA",
    "sg:tags":[
        "contractor"
    ],
    "wof:name":"Mark Bauer Development Co",
    "wof:placetype":"venue"
},
  "geometry": {"coordinates":[-94.396201,42.01012],"type":"Point"}
}