{
  "type": "Feature",
  "properties": {
    "iso:country":"US",
    "sg:address":"122 E Washington St",
    "sg:city":"Brighton",
    "sg:classifiers":[
        {
            "category":"Banks & Credit Unions",
            "subcategory":"Bank",
            "type":"Services"
        }
    ],
    "sg:phone":"+1 319 694 2821",
    "sg:postcode":"52540",
    "sg:province":"IA",
    "wof:name":"Federation Bank",
    "wof:placetype":"venue"
},
  "geometry": {"coordinates":[-91.820075,41.174882],"type":"Point"}
}