{
  "type": "Feature",
  "properties": {
    "iso:country":"US",
    "sg:address":"601 S Franklin St",
    "sg:city":"Corydon",
    "sg:classifiers":[
        {
            "category":"Local Transit",
            "type":"Transportation"
        }
    ],
    "sg:phone":"+1 641 872 2517",
    "sg:postcode":"50060",
    "sg:province":"IA",
    "wof:name":"Bott Enterprises Inc",
    "wof:placetype":"venue"
},
  "geometry": {"coordinates":[-93.31894200000001,40.751892],"type":"Point"}
}