{
  "type": "Feature",
  "properties": {
    "addr:full":"209 E 9th St Coralville IA 52241",
    "addr:housenumber":"209",
    "addr:postcode":"52241",
    "addr:street":"E 9Th St",
    "iso:country":"US",
    "sg:address":"209 E 9th St",
    "sg:city":"Coralville",
    "sg:classifiers":[
        {
            "category":"Travel",
            "subcategory":"Hotels & Motels",
            "type":"Entertainment"
        }
    ],
    "sg:phone":"+1 319 351 8144",
    "sg:postcode":"52241",
    "sg:province":"IA",
    "sg:tags":[
        "operation"
    ],
    "wof:name":"Comfort Inn",
    "wof:placetype":"venue"
},
  "geometry": {"coordinates":[-91.560089,41.681483],"type":"Point"}
}