{
  "type": "Feature",
  "properties": {
    "iso:country":"US",
    "sg:address":"115 W Salem Ave",
    "sg:city":"Indianola",
    "sg:classifiers":[
        {
            "category":"Education",
            "subcategory":"School",
            "type":"Public Place"
        }
    ],
    "sg:phone":"+1 515 961 8191",
    "sg:postcode":"50125",
    "sg:province":"IA",
    "wof:name":"Heartland Area Education Agcy",
    "wof:placetype":"venue"
},
  "geometry": {"coordinates":[-93.56111,41.36023],"type":"Point"}
}