{
  "type": "Feature",
  "properties": {
    "iso:country":"US",
    "sg:address":"25 S Gilbert St",
    "sg:city":"Iowa City",
    "sg:classifiers":[
        {
            "category":"Manufacturing",
            "subcategory":"Retail Goods",
            "type":"Manufacturing & Wholesale Goods"
        }
    ],
    "sg:phone":"+1 319 594 7158",
    "sg:postcode":"52240",
    "sg:province":"IA",
    "sg:tags":[
        "product",
        "mfg"
    ],
    "wof:name":"Kit Full",
    "wof:placetype":"venue"
},
  "geometry": {"coordinates":[-91.53025,41.660337],"type":"Point"}
}