{
  "type": "Feature",
  "properties": {
    "iso:country":"US",
    "sg:address":"3314 US Hwy 6",
    "sg:city":"Homestead",
    "sg:classifiers":[
        {
            "category":"Building & Trades",
            "subcategory":"Construction",
            "type":"Services"
        }
    ],
    "sg:phone":"+1 319 622 3049",
    "sg:postcode":"52236",
    "sg:province":"IA",
    "sg:tags":[
        "resurfacing",
        "laying",
        "refinishing",
        "floor"
    ],
    "wof:name":"SCS Flooring Co",
    "wof:placetype":"venue"
},
  "geometry": {"coordinates":[-91.84745100000001,41.759155],"type":"Point"}
}