{
  "type": "Feature",
  "properties": {
    "iso:country":"US",
    "sg:address":"1701 Oak St",
    "sg:city":"Sheldon",
    "sg:classifiers":[
        {
            "category":"Social Services",
            "type":"Services"
        }
    ],
    "sg:phone":"+1 712 324 4082",
    "sg:postcode":"51201",
    "sg:province":"IA",
    "sg:tags":[
        "organization",
        "welfare"
    ],
    "wof:name":"East Oak Apartments",
    "wof:placetype":"venue"
},
  "geometry": {"coordinates":[-95.837639,43.187804],"type":"Point"}
}