{
  "type": "Feature",
  "properties": {
    "iso:country":"US",
    "sg:address":"212 E Main St",
    "sg:city":"Ottumwa",
    "sg:classifiers":[
        {
            "category":"Personal",
            "subcategory":"Tattoo Parlor",
            "type":"Services"
        }
    ],
    "sg:phone":"+1 641 684 0055",
    "sg:postcode":"52501",
    "sg:province":"IA",
    "sg:tags":[
        "tattooing"
    ],
    "wof:name":"Savage Tattoo",
    "wof:placetype":"venue"
},
  "geometry": {"coordinates":[-92.411586,41.016959],"type":"Point"}
}