{
  "type": "Feature",
  "properties": {
    "iso:country":"US",
    "sg:address":"305 E Head St",
    "sg:city":"Jefferson",
    "sg:classifiers":[
        {
            "category":"Government",
            "subcategory":"Office",
            "type":"Public Place"
        }
    ],
    "sg:phone":"+1 515 386 8260",
    "sg:postcode":"50129",
    "sg:province":"IA",
    "sg:tags":[
        "city",
        "program"
    ],
    "wof:name":"Jefferson Sanitation Dept",
    "wof:placetype":"venue"
},
  "geometry": {"coordinates":[-94.372105,42.025231],"type":"Point"}
}