{
  "type": "Feature",
  "properties": {
    "iso:country":"US",
    "sg:address":"3070 State Hwy 25",
    "sg:city":"Orient",
    "sg:classifiers":[
        {
            "category":"Travel",
            "subcategory":"Hotels & Motels",
            "type":"Entertainment"
        }
    ],
    "sg:phone":"+1 641 345 2697",
    "sg:postcode":"50858",
    "sg:province":"IA",
    "sg:tags":[
        "breakfast",
        "operation",
        "bed",
        "accommodation"
    ],
    "wof:name":"Special Moments Bed Breakfast",
    "wof:placetype":"venue"
},
  "geometry": {"coordinates":[-94.43648899999999,41.201212],"type":"Point"}
}