{
  "type": "Feature",
  "properties": {
    "iso:country":"US",
    "sg:address":"230 E Leclaire Rd",
    "sg:city":"Eldridge",
    "sg:classifiers":[
        {
            "category":"Manufacturing",
            "subcategory":"Metals",
            "type":"Manufacturing & Wholesale Goods"
        }
    ],
    "sg:phone":"+1 563 285 9623",
    "sg:postcode":"52748",
    "sg:province":"IA",
    "sg:tags":[
        "steel"
    ],
    "wof:name":"Eldridge Welding & Ornamental",
    "wof:placetype":"venue"
},
  "geometry": {"coordinates":[-90.579776,41.654789],"type":"Point"}
}