{
  "type": "Feature",
  "properties": {
    "addr:full":"251 N Main Ave Sioux Center IA 51250",
    "addr:housenumber":"251",
    "addr:postcode":"51250",
    "addr:street":"N Main Ave",
    "iso:country":"US",
    "sg:address":"251 N Main Ave",
    "sg:city":"Sioux Center",
    "sg:classifiers":[
        {
            "category":"Restaurant",
            "type":"Food & Drink"
        }
    ],
    "sg:menulink":"http://www.allmenus.com/ia/west-branch/32115-pizza-ranch/menu/",
    "sg:phone":"+1 712 722 3988",
    "sg:postcode":"51250",
    "sg:province":"IA",
    "sg:tags":[
        "american",
        "pizza"
    ],
    "wof:name":"Pizza Ranch",
    "wof:placetype":"venue"
},
  "geometry": {"coordinates":[-96.17553100000001,43.079206],"type":"Point"}
}