{
  "type": "Feature",
  "properties": {
    "iso:country":"US",
    "sg:address":"506 NE Dodge St",
    "sg:city":"Greenfield",
    "sg:classifiers":[
        {
            "category":"Personal",
            "subcategory":"Beauty Salon",
            "type":"Services"
        }
    ],
    "sg:phone":"+1 641 743 6110",
    "sg:postcode":"50849",
    "sg:province":"IA",
    "sg:tags":[
        "shop"
    ],
    "wof:name":"Georgia's Beauty Shop",
    "wof:placetype":"venue"
},
  "geometry": {"coordinates":[-94.454425,41.309809],"type":"Point"}
}