{
  "type": "Feature",
  "properties": {
    "iso:country":"US",
    "sg:address":"1919 260th St",
    "sg:city":"Inwood",
    "sg:phone":"+1 712 753 4964",
    "sg:postcode":"51240",
    "sg:province":"IA",
    "sg:tags":[
        "farm",
        "corn",
        "soybean"
    ],
    "wof:name":"Edwin Baatz Farm",
    "wof:placetype":"venue"
},
  "geometry": {"coordinates":[-96.409176,43.272849],"type":"Point"}
}