{
  "type": "Feature",
  "properties": {
    "addr:full":"104 3rd St Frederika IA 50631",
    "addr:housenumber":"104",
    "addr:postcode":"50631",
    "addr:street":"3Rd St",
    "iso:country":"US",
    "sg:address":"104 3rd St",
    "sg:city":"Frederika",
    "sg:classifiers":[
        {
            "category":"Government",
            "subcategory":"Post Office",
            "type":"Public Place"
        }
    ],
    "sg:phone":"+1 319 275 4754",
    "sg:postcode":"50631",
    "sg:province":"IA",
    "wof:name":"US Post Office",
    "wof:placetype":"venue"
},
  "geometry": {"coordinates":[-92.307945,42.881426],"type":"Point"}
}