{
  "type": "Feature",
  "properties": {
    "iso:country":"US",
    "sg:address":"114 S Grand St",
    "sg:city":"Chariton",
    "sg:classifiers":[
        {
            "category":"Building & Trades",
            "subcategory":"Plumbing",
            "type":"Services"
        }
    ],
    "sg:phone":"+1 641 774 8241",
    "sg:postcode":"50049",
    "sg:province":"IA",
    "sg:tags":[
        "mechanical",
        "contractor"
    ],
    "wof:name":"Travis Mechanical & Controls",
    "wof:placetype":"venue"
},
  "geometry": {"coordinates":[-93.306819,41.013474],"type":"Point"}
}