{
  "type": "Feature",
  "properties": {
    "iso:country":"US",
    "sg:address":"10503 Lake Eleanor Rd",
    "sg:city":"Dubuque",
    "sg:classifiers":[
        {
            "category":"Retail",
            "subcategory":"Auto Repair",
            "type":"Services"
        }
    ],
    "sg:phone":"+1 563 582 9677",
    "sg:postcode":"52003",
    "sg:province":"IA",
    "sg:tags":[
        "truck"
    ],
    "wof:name":"Northern Iowa Diesel LTD",
    "wof:placetype":"venue"
},
  "geometry": {"coordinates":[-90.67736499999999,42.447586],"type":"Point"}
}