{
  "type": "Feature",
  "properties": {
    "addr:full":"4207 Glass Rd NE Ste 2 Cedar Rapids IA 52402",
    "addr:housenumber":"4207",
    "addr:postcode":"52402",
    "addr:street":"Glass Rd Ne Ste 2",
    "iso:country":"US",
    "sg:address":"4207 Glass Rd NE Ste 2",
    "sg:city":"Cedar Rapids",
    "sg:classifiers":[
        {
            "category":"Health Services",
            "subcategory":"Dentist",
            "type":"Services"
        }
    ],
    "sg:phone":"+1 319 294 8181",
    "sg:postcode":"52402",
    "sg:province":"IA",
    "sg:tags":[
        "pediatric"
    ],
    "wof:name":"Balster Pediatric Dentistry",
    "wof:placetype":"venue"
},
  "geometry": {"coordinates":[-91.700294,42.016609],"type":"Point"}
}