{
  "type": "Feature",
  "properties": {
    "iso:country":"US",
    "sg:address":"719 38th St",
    "sg:city":"Sioux City",
    "sg:classifiers":[
        {
            "category":"Building & Trades",
            "subcategory":"Construction",
            "type":"Services"
        }
    ],
    "sg:phone":"+1 712 277 4178",
    "sg:postcode":"51104",
    "sg:province":"IA",
    "sg:tags":[
        "house"
    ],
    "wof:name":"Viking Construction Inc",
    "wof:placetype":"venue"
},
  "geometry": {"coordinates":[-96.40190699999999,42.53536],"type":"Point"}
}