{
  "type": "Feature",
  "properties": {
    "iso:country":"US",
    "sg:address":"1305 Hillcrest Dr",
    "sg:city":"Anita",
    "sg:classifiers":[
        {
            "category":"Farming",
            "subcategory":"Livestock Farm",
            "type":"Manufacturing & Wholesale Goods"
        }
    ],
    "sg:phone":"+1 712 762 3694",
    "sg:postcode":"50020",
    "sg:province":"IA",
    "sg:tags":[
        "beef",
        "corn",
        "field",
        "soybean",
        "cattle",
        "feedlot"
    ],
    "wof:name":"Kelloway Farms",
    "wof:placetype":"venue"
},
  "geometry": {"coordinates":[-94.772527,41.434772],"type":"Point"}
}