{
  "type": "Feature",
  "properties": {
    "iso:country":"US",
    "sg:address":"204 N Central Ave",
    "sg:city":"Allerton",
    "sg:classifiers":[
        {
            "category":"Wholesale",
            "subcategory":"Groceries",
            "type":"Manufacturing & Wholesale Goods"
        }
    ],
    "sg:phone":"+1 641 873 4119",
    "sg:postcode":"50008",
    "sg:province":"IA",
    "sg:tags":[
        "honey"
    ],
    "sg:website":"www.logchain.com",
    "wof:name":"Log Chain Apiary",
    "wof:placetype":"venue"
},
  "geometry": {"coordinates":[-93.365033,40.707631],"type":"Point"}
}