{
  "type": "Feature",
  "properties": {
    "iso:country":"US",
    "sg:address":"1726 Cerro Gordo Way",
    "sg:city":"Mason City",
    "sg:classifiers":[
        {
            "category":"Professional",
            "type":"Services"
        }
    ],
    "sg:phone":"+1 641 423 7770",
    "sg:postcode":"50401",
    "sg:province":"IA",
    "wof:name":"J S Services Inc",
    "wof:placetype":"venue"
},
  "geometry": {"coordinates":[-93.22877200000001,43.146832],"type":"Point"}
}