{
  "type": "Feature",
  "properties": {
    "addr:full":"2373 280th St Rippey IA 50235",
    "addr:housenumber":"2373",
    "addr:postcode":"50235",
    "addr:street":"280Th St",
    "iso:country":"US",
    "sg:address":"2373 280th St",
    "sg:city":"Rippey",
    "sg:classifiers":[
        {
            "category":"Freight",
            "type":"Transportation"
        }
    ],
    "sg:phone":"+1 515 436 8290",
    "sg:postcode":"50235",
    "sg:province":"IA",
    "sg:tags":[
        "trucking"
    ],
    "wof:name":"Randy Riley Trucking Inc",
    "wof:placetype":"venue"
},
  "geometry": {"coordinates":[-94.186454,41.950138],"type":"Point"}
}