{
  "type": "Feature",
  "properties": {
    "iso:country":"US",
    "sg:address":"4373 580th Ave",
    "sg:city":"West Bend",
    "sg:phone":"+1 515 887 4954",
    "sg:postcode":"50597",
    "sg:province":"IA",
    "sg:tags":[
        "farm",
        "corn"
    ],
    "wof:name":"Larry Fogarty",
    "wof:placetype":"venue"
},
  "geometry": {"coordinates":[-94.44270400000001,43.013166],"type":"Point"}
}