{
  "type": "Feature",
  "properties": {
    "iso:country":"US",
    "sg:address":"636 Avenue E",
    "sg:city":"Hawarden",
    "sg:classifiers":[
        {
            "category":"Building & Trades",
            "subcategory":"Construction",
            "type":"Services"
        }
    ],
    "sg:phone":"+1 712 551 1210",
    "sg:postcode":"51023",
    "sg:province":"SD",
    "sg:tags":[
        "concrete",
        "contractor"
    ],
    "wof:name":"Wahoo Concrete",
    "wof:placetype":"venue"
},
  "geometry": {"coordinates":[-96.488221,42.993553],"type":"Point"}
}