{
  "type": "Feature",
  "properties": {
    "iso:country":"US",
    "sg:address":"313 Grand Ave",
    "sg:city":"West Des Moines",
    "sg:classifiers":[
        {
            "category":"Restaurant",
            "type":"Food & Drink"
        }
    ],
    "sg:phone":"+1 515 222 5656",
    "sg:postcode":"50265",
    "sg:province":"IA",
    "sg:tags":[
        "pizza"
    ],
    "wof:name":"Pizza Palace Family Fun Ctr",
    "wof:placetype":"venue"
},
  "geometry": {"coordinates":[-93.704787,41.582768],"type":"Point"}
}