{
  "type": "Feature",
  "properties": {
    "addr:full":"806 S Main St Clarksville IA 50619",
    "addr:housenumber":"806",
    "addr:postcode":"50619",
    "addr:street":"S Main St",
    "iso:country":"US",
    "sg:address":"806 S Main St",
    "sg:city":"Clarksville",
    "sg:classifiers":[
        {
            "category":"Retail",
            "subcategory":"Veterinary Services",
            "type":"Services"
        }
    ],
    "sg:phone":"+1 319 278 1138",
    "sg:postcode":"50619",
    "sg:province":"IA",
    "sg:tags":[
        "veterinarian"
    ],
    "wof:name":"Clarksville Veterinary Svc",
    "wof:placetype":"venue"
},
  "geometry": {"coordinates":[-92.66779699999999,42.778284],"type":"Point"}
}