{
  "type": "Feature",
  "properties": {
    "iso:country":"US",
    "sg:address":"214 N 4th St",
    "sg:city":"Burlington",
    "sg:classifiers":[
        {
            "category":"Organizations",
            "subcategory":"Professional Association",
            "type":"Services"
        }
    ],
    "sg:phone":"+1 319 208 0271",
    "sg:postcode":"52601",
    "sg:province":"IA",
    "wof:name":"Alzheimers Association Inc",
    "wof:placetype":"venue"
},
  "geometry": {"coordinates":[-91.10378799999999,40.810038],"type":"Point"}
}