{
  "type": "Feature",
  "properties": {
    "addr:full":"1675 Lindle Ave Muscatine IA 52761",
    "addr:housenumber":"1675",
    "addr:postcode":"52761",
    "addr:street":"Lindle Ave",
    "iso:country":"US",
    "sg:address":"1675 Lindle Ave",
    "sg:city":"Muscatine",
    "sg:classifiers":[
        {
            "category":"Organizations",
            "subcategory":"Professional Association",
            "type":"Services"
        }
    ],
    "sg:phone":"+1 563 263 5530",
    "sg:postcode":"52761",
    "sg:province":"IA",
    "wof:name":"Girl Scout Mississippi Valley",
    "wof:placetype":"venue"
},
  "geometry": {"coordinates":[-91.136397,41.503071],"type":"Point"}
}