{
  "type": "Feature",
  "properties": {
    "iso:country":"US",
    "sg:address":"485 O'Neill St",
    "sg:city":"Dubuque",
    "sg:classifiers":[
        {
            "category":"Building & Trades",
            "subcategory":"Plumbing",
            "type":"Services"
        }
    ],
    "sg:phone":"+1 563 583 5996",
    "sg:postcode":"52001",
    "sg:province":"IA",
    "sg:tags":[
        "plumbing",
        "contractor"
    ],
    "wof:name":"Reliable Plumbing Inc",
    "wof:placetype":"venue"
},
  "geometry": {"coordinates":[-90.591517,42.43945],"type":"Point"}
}