{
  "type": "Feature",
  "properties": {
    "addr:full":"801 Whitney St Atlantic IA 50022",
    "addr:housenumber":"801",
    "addr:postcode":"50022",
    "addr:street":"Whitney St",
    "iso:country":"US",
    "sg:address":"801 Whitney St",
    "sg:city":"Atlantic",
    "sg:classifiers":[
        {
            "category":"Education",
            "subcategory":"School",
            "type":"Public Place"
        }
    ],
    "sg:phone":"+1 712 243 1480",
    "sg:postcode":"50022",
    "sg:province":"IA",
    "wof:name":"Loess Hills Area Education",
    "wof:placetype":"venue"
},
  "geometry": {"coordinates":[-94.984194,41.402836],"type":"Point"}
}