{
  "type": "Feature",
  "properties": {
    "iso:country":"US",
    "sg:address":"1473 Iowa 9",
    "sg:city":"Larchwood",
    "sg:classifiers":[
        {
            "category":"Building & Trades",
            "subcategory":"Construction",
            "type":"Services"
        }
    ],
    "sg:phone":"+1 712 477 2848",
    "sg:postcode":"51241",
    "sg:province":"IA",
    "sg:tags":[
        "system",
        "specialty",
        "heating",
        "contractor",
        "air conditioning"
    ],
    "wof:name":"Reinke Htg & Air Cond Inc",
    "wof:placetype":"venue"
},
  "geometry": {"coordinates":[-96.429092,43.436089],"type":"Point"}
}