{
  "type": "Feature",
  "properties": {
    "addr:full":"2125 300th St Forest City IA 50436",
    "addr:housenumber":"2125",
    "addr:postcode":"50436",
    "addr:street":"300Th St",
    "iso:country":"US",
    "sg:address":"2125 300th St",
    "sg:city":"Forest City",
    "sg:classifiers":[
        {
            "category":"Retail",
            "subcategory":"Auto Repair",
            "type":"Services"
        }
    ],
    "sg:phone":"+1 641 927 4680",
    "sg:postcode":"50436",
    "sg:province":"IA",
    "sg:tags":[
        "body",
        "automobile",
        "painting",
        "general"
    ],
    "wof:name":"B K Auto Body",
    "wof:placetype":"venue"
},
  "geometry": {"coordinates":[-93.58572100000001,43.198754],"type":"Point"}
}