{
  "type": "Feature",
  "properties": {
    "iso:country":"US",
    "sg:address":"3178 Quebec Ave",
    "sg:city":"Orient",
    "sg:phone":"+1 641 337 5704",
    "sg:postcode":"50858",
    "sg:province":"IA",
    "sg:tags":[
        "farm",
        "corn"
    ],
    "wof:name":"Vandewater Eldon Farm",
    "wof:placetype":"venue"
},
  "geometry": {"coordinates":[-94.39537900000001,41.18937],"type":"Point"}
}