{
  "type": "Feature",
  "properties": {
    "iso:country":"US",
    "sg:address":"2415 Ingersoll Ave",
    "sg:city":"Des Moines",
    "sg:classifiers":[
        {
            "category":"Travel",
            "subcategory":"Travel Agent",
            "type":"Entertainment"
        }
    ],
    "sg:phone":"+1 515 282 4026",
    "sg:postcode":"50312",
    "sg:province":"IA",
    "sg:tags":[
        "tours",
        "promoter"
    ],
    "sg:website":"www.journertours.com",
    "wof:name":"Journer Tours",
    "wof:placetype":"venue"
},
  "geometry": {"coordinates":[-93.651949,41.585776],"type":"Point"}
}