{
  "type": "Feature",
  "properties": {
    "iso:country":"US",
    "sg:address":"1433 W Front St",
    "sg:city":"Buffalo",
    "sg:classifiers":[
        {
            "category":"Recreation",
            "type":"Entertainment"
        }
    ],
    "sg:phone":"+1 563 328 3281",
    "sg:postcode":"52728",
    "sg:province":"IA",
    "sg:tags":[
        "parks"
    ],
    "wof:name":"Buffalo Shores",
    "wof:placetype":"venue"
},
  "geometry": {"coordinates":[-90.74137399999999,41.454196],"type":"Point"}
}