{
  "type": "Feature",
  "properties": {
    "iso:country":"US",
    "sg:address":"20661 178th St",
    "sg:city":"Farmersburg",
    "sg:phone":"+1 563 536 2383",
    "sg:postcode":"52047",
    "sg:province":"IA",
    "sg:tags":[
        "farm",
        "corn"
    ],
    "wof:name":"Larry Friedlein",
    "wof:placetype":"venue"
},
  "geometry": {"coordinates":[-91.39690299999999,42.968517],"type":"Point"}
}