{
  "type": "Feature",
  "properties": {
    "iso:country":"US",
    "sg:address":"3201 E Granger Ave",
    "sg:city":"Des Moines",
    "sg:classifiers":[
        {
            "category":"Freight",
            "type":"Transportation"
        }
    ],
    "sg:phone":"+1 515 256 9777",
    "sg:postcode":"50317",
    "sg:province":"IA",
    "sg:tags":[
        "trucking"
    ],
    "wof:name":"Little Dutch Lines",
    "wof:placetype":"venue"
},
  "geometry": {"coordinates":[-93.54732799999999,41.572787],"type":"Point"}
}