{
  "type": "Feature",
  "properties": {
    "addr:full":"7025 30th Ave Atkins IA 52206",
    "addr:housenumber":"7025",
    "addr:postcode":"52206",
    "addr:street":"30Th Ave",
    "iso:country":"US",
    "sg:address":"7025 30th Ave",
    "sg:city":"Atkins",
    "sg:phone":"+1 319 446 7558",
    "sg:postcode":"52206",
    "sg:province":"IA",
    "sg:tags":[
        "farm",
        "corn",
        "soybean"
    ],
    "wof:name":"Danny Kaestner",
    "wof:placetype":"venue"
},
  "geometry": {"coordinates":[-91.912347,42.003306],"type":"Point"}
}