{
  "type": "Feature",
  "properties": {
    "iso:country":"US",
    "sg:address":"6022 120th St",
    "sg:city":"Ocheyedan",
    "sg:phone":"+1 712 758 3175",
    "sg:postcode":"51354",
    "sg:province":"IA",
    "sg:tags":[
        "farm",
        "corn",
        "soybean"
    ],
    "wof:name":"Van Gelder Charlene",
    "wof:placetype":"venue"
},
  "geometry": {"coordinates":[-95.599932,43.475977],"type":"Point"}
}