{
  "type": "Feature",
  "properties": {
    "iso:country":"US",
    "sg:address":"1302 US Hwy 71",
    "sg:city":"Carroll",
    "sg:classifiers":[
        {
            "category":"Restaurant",
            "type":"Food & Drink"
        }
    ],
    "sg:phone":"+1 712 792 9673",
    "sg:postcode":"51401",
    "sg:province":"IA",
    "wof:name":"A & W Family Restaurant",
    "wof:placetype":"venue"
},
  "geometry": {"coordinates":[-94.878615,42.074341],"type":"Point"}
}