{
  "type": "Feature",
  "properties": {
    "iso:country":"US",
    "sg:address":"4338 Hickory Ave",
    "sg:city":"Orange City",
    "sg:classifiers":[
        {
            "category":"Home & Garden",
            "subcategory":"Building Materials",
            "type":"Retail Goods"
        }
    ],
    "sg:phone":"+1 712 722 3063",
    "sg:postcode":"51041",
    "sg:province":"IA",
    "sg:tags":[
        "door"
    ],
    "wof:name":"Solid Rock Construction",
    "wof:placetype":"venue"
},
  "geometry": {"coordinates":[-96.135727,43.020725],"type":"Point"}
}