{
  "type": "Feature",
  "properties": {
    "iso:country":"US",
    "sg:address":"11111 NW 16th St",
    "sg:city":"Ankeny",
    "sg:classifiers":[
        {
            "category":"Building & Trades",
            "subcategory":"Construction",
            "type":"Services"
        }
    ],
    "sg:phone":"+1 515 964 3067",
    "sg:postcode":"50023",
    "sg:province":"IA",
    "sg:tags":[
        "waterproofing",
        "contractor"
    ],
    "wof:name":"Bob Bauer Basement Waterprfng",
    "wof:placetype":"venue"
},
  "geometry": {"coordinates":[-93.639184,41.769471],"type":"Point"}
}