{
  "type": "Feature",
  "properties": {
    "addr:full":"5625 Hickman Rd Des Moines IA 50310",
    "addr:housenumber":"5625",
    "addr:postcode":"50310",
    "addr:street":"Hickman Rd Des",
    "iso:country":"US",
    "sg:address":"5625 Hickman Rd",
    "sg:city":"Des Moines",
    "sg:classifiers":[
        {
            "category":"Shopping",
            "type":"Retail Goods"
        }
    ],
    "sg:phone":"+1 515 255 5230",
    "sg:postcode":"50310",
    "sg:province":"IA",
    "sg:tags":[
        "religious"
    ],
    "wof:name":"Divine Treasures Catholic",
    "wof:placetype":"venue"
},
  "geometry": {"coordinates":[-93.695723,41.614947],"type":"Point"}
}