{
  "type": "Feature",
  "properties": {
    "addr:full":"2790 290th St Rockwell City IA 50579",
    "addr:housenumber":"2790",
    "addr:postcode":"50579",
    "addr:street":"290Th St",
    "iso:country":"US",
    "sg:address":"2790 290th St",
    "sg:city":"Rockwell City",
    "sg:classifiers":[
        {
            "category":"Organizations",
            "subcategory":"Professional Association",
            "type":"Services"
        }
    ],
    "sg:phone":"+1 712 297 8874",
    "sg:postcode":"50579",
    "sg:province":"IA",
    "sg:tags":[
        "chambers",
        "commerce"
    ],
    "wof:name":"Chamber Of Commerce",
    "wof:placetype":"venue"
},
  "geometry": {"coordinates":[-94.580878,42.368593],"type":"Point"}
}