{
  "type": "Feature",
  "properties": {
    "addr:full":"1961 Indianola Ave Des Moines IA 50315",
    "addr:housenumber":"1961",
    "addr:postcode":"50315",
    "addr:street":"Indianola Ave",
    "iso:country":"US",
    "sg:address":"1961 Indianola Ave",
    "sg:city":"Des Moines",
    "sg:classifiers":[
        {
            "category":"Museum",
            "type":"Entertainment"
        }
    ],
    "sg:phone":"+1 515 280 3719",
    "sg:postcode":"50315",
    "sg:province":"IA",
    "wof:name":"Italian-American Cultural Ctr",
    "wof:placetype":"venue"
},
  "geometry": {"coordinates":[-93.61368899999999,41.569798],"type":"Point"}
}