{
  "type": "Feature",
  "properties": {
    "addr:city":"Des Moines",
    "addr:full":"1961 Indianola Ave Des Moines, Ia 50315-7134",
    "addr:house_number":"1961",
    "addr:housenumber":"1961",
    "addr:phone":"+1 515-280-3719",
    "addr:postcode":"50315-7134",
    "addr:road":"Indianola Ave",
    "addr:state":"IA",
    "addr:street":"Indianola Ave",
    "iso:country":"US",
    "sg:address":"1961 Indianola Ave",
    "sg:city":"Des Moines",
    "sg:classifiers":[
        {
            "category":"Museum",
            "type":"Entertainment"
        }
    ],
    "sg:phone":"+1 515 280 3719",
    "sg:postcode":"50315",
    "sg:province":"IA",
    "wof:airports":[
        102525803
    ],
    "wof:name":"Italian-American Cultural Center Of Iowa",
    "wof:placetype":"venue"
},
  "geometry": {"coordinates":[-93.61322,41.57037],"type":"Point"}
}