{
  "type": "Feature",
  "properties": {
    "addr:full":"404 W Water St Decorah IA 52101",
    "addr:housenumber":"404",
    "addr:postcode":"52101",
    "addr:street":"W Water St",
    "iso:country":"US",
    "sg:address":"404 W Water St",
    "sg:city":"Decorah",
    "sg:classifiers":[
        {
            "category":"Professional",
            "type":"Services"
        }
    ],
    "sg:phone":"+1 563 382 4400",
    "sg:postcode":"52101",
    "sg:province":"IA",
    "sg:tags":[
        "establishment"
    ],
    "wof:name":"Studio 404",
    "wof:placetype":"venue"
},
  "geometry": {"coordinates":[-91.790854,43.304226],"type":"Point"}
}