{
  "type": "Feature",
  "properties": {
    "addr:full":"1626 Yankee Ave New Liberty IA 52765",
    "addr:housenumber":"1626",
    "addr:postcode":"52765",
    "addr:street":"Yankee Ave",
    "iso:country":"US",
    "sg:address":"1626 Yankee Ave",
    "sg:city":"New Liberty",
    "sg:classifiers":[
        {
            "category":"Building & Trades",
            "subcategory":"Construction",
            "type":"Services"
        }
    ],
    "sg:phone":"+1 563 893 2328",
    "sg:postcode":"52765",
    "sg:province":"IA",
    "sg:tags":[
        "residential"
    ],
    "wof:name":"Gehrls RC Co",
    "wof:placetype":"venue"
},
  "geometry": {"coordinates":[-90.918127,41.709505],"type":"Point"}
}