{
  "type": "Feature",
  "properties": {
    "iso:country":"US",
    "sg:address":"1707 3rd Ave S",
    "sg:city":"Denison",
    "sg:classifiers":[
        {
            "category":"Wholesale",
            "subcategory":"Hardware",
            "type":"Manufacturing & Wholesale Goods"
        }
    ],
    "sg:phone":"+1 712 263 4330",
    "sg:postcode":"51442",
    "sg:province":"IA",
    "sg:tags":[
        "machinery"
    ],
    "wof:name":"Toms Shop Service",
    "wof:placetype":"venue"
},
  "geometry": {"coordinates":[-95.34760300000001,42.013321],"type":"Point"}
}