{
  "type": "Feature",
  "properties": {
    "iso:country":"US",
    "sg:address":"127 W 1st St",
    "sg:city":"Glidden",
    "sg:classifiers":[
        {
            "category":"Home & Garden",
            "subcategory":"Building Materials",
            "type":"Retail Goods"
        }
    ],
    "sg:phone":"+1 712 659 3795",
    "sg:postcode":"51443",
    "sg:province":"IA",
    "wof:name":"Schon Lumber",
    "wof:placetype":"venue"
},
  "geometry": {"coordinates":[-94.730362,42.055713],"type":"Point"}
}