{
  "type": "Feature",
  "properties": {
    "iso:country":"US",
    "sg:address":"1817 W Broadway",
    "sg:city":"Council Bluffs",
    "sg:classifiers":[
        {
            "category":"Professional",
            "type":"Services"
        },
        {
            "category":"Bakery",
            "type":"Food & Drink"
        },
        {
            "category":"Food & Beverages",
            "subcategory":"Groceries & Convenience Stores",
            "type":"Retail Goods"
        }
    ],
    "sg:phone":"+1 712 322 9491",
    "sg:postcode":"51501",
    "sg:province":"IA",
    "sg:tags":[
        "caterer"
    ],
    "wof:name":"No Frills Supermarket Council Bluffs",
    "wof:placetype":"venue"
},
  "geometry": {"coordinates":[-95.871201,41.261799],"type":"Point"}
}