{
  "type": "Feature",
  "properties": {
    "iso:country":"US",
    "sg:address":"209 3rd Ave",
    "sg:city":"Keystone",
    "sg:classifiers":[
        {
            "category":"Personal",
            "subcategory":"Beauty Salon",
            "type":"Services"
        }
    ],
    "sg:phone":"+1 319 442 3636",
    "sg:postcode":"52249",
    "sg:province":"IA",
    "sg:tags":[
        "shop"
    ],
    "wof:name":"Shear Design",
    "wof:placetype":"venue"
},
  "geometry": {"coordinates":[-92.19949699999999,42.001371],"type":"Point"}
}