{
  "type": "Feature",
  "properties": {
    "iso:country":"US",
    "sg:address":"308 Main St",
    "sg:city":"Coon Rapids",
    "sg:classifiers":[
        {
            "category":"Personal",
            "subcategory":"Beauty Salon",
            "type":"Services"
        }
    ],
    "sg:phone":"+1 712 999 2209",
    "sg:postcode":"50058",
    "sg:province":"IA",
    "sg:tags":[
        "shop"
    ],
    "wof:name":"Trendz Beauty Salon",
    "wof:placetype":"venue"
},
  "geometry": {"coordinates":[-94.676008,41.870803],"type":"Point"}
}