{
  "type": "Feature",
  "properties": {
    "iso:country":"US",
    "sg:address":"422 N Main St",
    "sg:city":"Allison",
    "sg:classifiers":[
        {
            "category":"Insurance",
            "subcategory":"Insurance Agent",
            "type":"Services"
        }
    ],
    "sg:phone":"+1 319 267 2247",
    "sg:postcode":"50602",
    "sg:province":"IA",
    "wof:name":"Butler County Farm Bureau",
    "wof:placetype":"venue"
},
  "geometry": {"coordinates":[-92.795045,42.754438],"type":"Point"}
}