{
  "type": "Feature",
  "properties": {
    "iso:country":"US",
    "sg:address":"21060 Holden Dr",
    "sg:city":"Davenport",
    "sg:classifiers":[
        {
            "category":"Wholesale",
            "subcategory":"Construction Materials",
            "type":"Manufacturing & Wholesale Goods"
        }
    ],
    "sg:phone":"+1 563 391 7025",
    "sg:postcode":"52804",
    "sg:province":"IA",
    "sg:tags":[
        "fence"
    ],
    "sg:website":"www.lovewellfence.com",
    "wof:name":"Lovewell Fencing Inc",
    "wof:placetype":"venue"
},
  "geometry": {"coordinates":[-90.570033,41.612073],"type":"Point"}
}