{
  "type": "Feature",
  "properties": {
    "iso:country":"US",
    "sg:address":"3939 Bowling St SW",
    "sg:city":"Cedar Rapids",
    "sg:classifiers":[
        {
            "category":"Building & Trades",
            "subcategory":"Cleaning & Sanitation",
            "type":"Services"
        }
    ],
    "sg:phone":"+1 319 981 3557",
    "sg:postcode":"52404",
    "sg:province":"IA",
    "sg:tags":[
        "home"
    ],
    "wof:name":"DO Service Better Inc",
    "wof:placetype":"venue"
},
  "geometry": {"coordinates":[-91.65687200000001,41.939186],"type":"Point"}
}