{
  "type": "Feature",
  "properties": {
    "addr:full":"4644 86th St Urbandale IA 50322",
    "addr:housenumber":"4644",
    "addr:postcode":"50322",
    "addr:street":"86Th St",
    "iso:country":"US",
    "sg:address":"4644 86th St",
    "sg:city":"Urbandale",
    "sg:classifiers":[
        {
            "category":"Shopping",
            "subcategory":"Clothing, Apparel, & Fashions",
            "type":"Retail Goods"
        }
    ],
    "sg:phone":"+1 515 244 6046",
    "sg:postcode":"50322",
    "sg:province":"IA",
    "sg:tags":[
        "wig",
        "toupee",
        "hairpiece"
    ],
    "wof:name":"USA Wigs",
    "wof:placetype":"venue"
},
  "geometry": {"coordinates":[-93.736549,41.644666],"type":"Point"}
}