{
  "type": "Feature",
  "properties": {
    "iso:country":"US",
    "sg:address":"106 E 1st St",
    "sg:city":"Ankeny",
    "sg:classifiers":[
        {
            "category":"Manufacturing",
            "subcategory":"Printing",
            "type":"Manufacturing & Wholesale Goods"
        }
    ],
    "sg:phone":"+1 515 964 0639",
    "sg:postcode":"50021",
    "sg:province":"IA",
    "sg:tags":[
        "newspaper"
    ],
    "wof:name":"Ankeny Press Citizen",
    "wof:placetype":"venue"
},
  "geometry": {"coordinates":[-93.598591,41.731923],"type":"Point"}
}