{
  "type": "Feature",
  "properties": {
    "iso:country":"US",
    "sg:address":"1833 140th Ave",
    "sg:city":"Donnellson",
    "sg:phone":"+1 319 836 2314",
    "sg:postcode":"52625",
    "sg:province":"IA",
    "sg:tags":[
        "food",
        "farm",
        "product",
        "corn",
        "soybean"
    ],
    "wof:name":"Ronald Hohl",
    "wof:placetype":"venue"
},
  "geometry": {"coordinates":[-91.641526,40.692458],"type":"Point"}
}