{
  "type": "Feature",
  "properties": {
    "addr:full":"321 E Main St Montezuma IA 50171",
    "addr:housenumber":"321",
    "addr:postcode":"50171",
    "addr:street":"E Main St",
    "iso:country":"US",
    "sg:address":"321 E Main St",
    "sg:city":"Montezuma",
    "sg:classifiers":[
        {
            "category":"Professional",
            "subcategory":"Lawyer & Legal Services",
            "type":"Services"
        }
    ],
    "sg:phone":"+1 641 623 4080",
    "sg:postcode":"50171",
    "sg:province":"IA",
    "sg:tags":[
        "attorney"
    ],
    "wof:name":"Mc Kelvie Law Office",
    "wof:placetype":"venue"
},
  "geometry": {"coordinates":[-92.52462800000001,41.585437],"type":"Point"}
}