{
  "type": "Feature",
  "properties": {
    "iso:country":"US",
    "sg:address":"109 Guthrie St",
    "sg:city":"De Soto",
    "sg:classifiers":[
        {
            "category":"Retail",
            "subcategory":"Veterinary Services",
            "type":"Services"
        }
    ],
    "sg:phone":"+1 515 834 2021",
    "sg:postcode":"50069",
    "sg:province":"IA",
    "sg:tags":[
        "veterinarian"
    ],
    "wof:name":"De Soto Veterinary Clinic",
    "wof:placetype":"venue"
},
  "geometry": {"coordinates":[-94.01250400000001,41.527447],"type":"Point"}
}