{
  "type": "Feature",
  "properties": {
    "iso:country":"US",
    "sg:address":"401 2nd St",
    "sg:city":"Gladbrook",
    "sg:classifiers":[
        {
            "category":"Banks & Credit Unions",
            "subcategory":"Bank",
            "type":"Services"
        }
    ],
    "sg:phone":"+1 641 473 2023",
    "sg:postcode":"50635",
    "sg:province":"IA",
    "wof:name":"F & M Bank",
    "wof:placetype":"venue"
},
  "geometry": {"coordinates":[-92.715221,42.187695],"type":"Point"}
}