{
  "type": "Feature",
  "properties": {
    "iso:country":"US",
    "sg:address":"2584 U Ave",
    "sg:city":"Waukee",
    "sg:classifiers":[
        {
            "category":"Building & Trades",
            "subcategory":"Plumbing",
            "type":"Services"
        }
    ],
    "sg:phone":"+1 515 987 4310",
    "sg:postcode":"50263",
    "sg:province":"IA",
    "sg:tags":[
        "heating",
        "contractor"
    ],
    "sg:website":"www.dorrianheating.us",
    "wof:name":"Dorrian Heating & Cooling Inc",
    "wof:placetype":"venue"
},
  "geometry": {"coordinates":[-93.89147,41.660477],"type":"Point"}
}