{
  "type": "Feature",
  "properties": {
    "iso:country":"US",
    "sg:address":"102 S Main St",
    "sg:city":"Gilman",
    "sg:classifiers":[
        {
            "category":"Freight",
            "type":"Transportation"
        }
    ],
    "sg:phone":"+1 641 498 2598",
    "sg:postcode":"50106",
    "sg:province":"IA",
    "sg:tags":[
        "grain",
        "elevator"
    ],
    "wof:name":"Central Counties Co-Op",
    "wof:placetype":"venue"
},
  "geometry": {"coordinates":[-92.78704999999999,41.879325],"type":"Point"}
}