{
  "type": "Feature",
  "properties": {
    "iso:country":"US",
    "sg:address":"1513 Cantebury Cir",
    "sg:city":"Grundy Center",
    "sg:classifiers":[
        {
            "category":"Professional",
            "type":"Services"
        }
    ],
    "sg:phone":"+1 319 824 3770",
    "sg:postcode":"50638",
    "sg:province":"IA",
    "sg:tags":[
        "establishment"
    ],
    "wof:name":"Nights Sunday Holidays",
    "wof:placetype":"venue"
},
  "geometry": {"coordinates":[-92.784577,42.360297],"type":"Point"}
}