{
  "type": "Feature",
  "properties": {
    "addr:full":"17 2nd St NW Hampton IA 50441",
    "addr:housenumber":"17",
    "addr:postcode":"50441",
    "addr:street":"2Nd St Nw",
    "iso:country":"US",
    "sg:address":"17 2nd St NW",
    "sg:city":"Hampton",
    "sg:classifiers":[
        {
            "category":"Government",
            "subcategory":"Office",
            "type":"Public Place"
        }
    ],
    "sg:phone":"+1 641 456 4254",
    "sg:postcode":"50441",
    "sg:province":"IA",
    "sg:tags":[
        "county",
        "safety",
        "order"
    ],
    "wof:name":"Franklin Emergency Management",
    "wof:placetype":"venue"
},
  "geometry": {"coordinates":[-93.20984900000001,42.742569],"type":"Point"}
}