{
  "type": "Feature",
  "properties": {
    "iso:country":"US",
    "sg:address":"102 S Main St",
    "sg:city":"Roland",
    "sg:classifiers":[
        {
            "category":"Organizations",
            "subcategory":"Religious Organization",
            "type":"Services"
        }
    ],
    "sg:phone":"+1 515 388 4834",
    "sg:postcode":"50236",
    "sg:province":"IA",
    "sg:tags":[
        "church"
    ],
    "wof:name":"Salem Lutheran Church",
    "wof:placetype":"venue"
},
  "geometry": {"coordinates":[-93.500395,42.166364],"type":"Point"}
}