{
  "type": "Feature",
  "properties": {
    "iso:country":"US",
    "sg:address":"2021 E Main St",
    "sg:city":"Ottumwa",
    "sg:classifiers":[
        {
            "category":"Organizations",
            "subcategory":"Religious Organization",
            "type":"Services"
        }
    ],
    "sg:phone":"+1 641 684 4080",
    "sg:postcode":"52501",
    "sg:province":"IA",
    "wof:name":"First Foursquare Church",
    "wof:placetype":"venue"
},
  "geometry": {"coordinates":[-92.38835400000001,41.008424],"type":"Point"}
}