{
  "type": "Feature",
  "properties": {
    "iso:country":"US",
    "sg:address":"861 County Home Rd",
    "sg:city":"Springville",
    "sg:classifiers":[
        {
            "category":"Building & Trades",
            "subcategory":"Construction",
            "type":"Services"
        }
    ],
    "sg:phone":"+1 319 854 7351",
    "sg:postcode":"52336",
    "sg:province":"IA",
    "sg:tags":[
        "excavating",
        "contractor"
    ],
    "wof:name":"Weber Mid-State Construction",
    "wof:placetype":"venue"
},
  "geometry": {"coordinates":[-91.45368499999999,42.093013],"type":"Point"}
}