{
  "type": "Feature",
  "properties": {
    "addr:full":"425 2nd St SE Cedar Rapids IA 52401",
    "addr:housenumber":"425",
    "addr:postcode":"52401",
    "addr:street":"2Nd St Se",
    "iso:country":"US",
    "sg:address":"425 2nd St SE",
    "sg:city":"Cedar Rapids",
    "sg:classifiers":[
        {
            "category":"Professional",
            "subcategory":"Business Services",
            "type":"Services"
        }
    ],
    "sg:phone":"+1 319 896 6730",
    "sg:postcode":"52401",
    "sg:province":"IA",
    "sg:tags":[
        "telemarketing"
    ],
    "wof:name":"A Pac Job Hotline",
    "wof:placetype":"venue"
},
  "geometry": {"coordinates":[-91.666524,41.976667],"type":"Point"}
}