{
  "type": "Feature",
  "properties": {
    "iso:country":"US",
    "sg:address":"350 W 6th St",
    "sg:city":"Dubuque",
    "sg:classifiers":[
        {
            "category":"Government",
            "subcategory":"Post Office",
            "type":"Public Place"
        }
    ],
    "sg:phone":"+1 563 582 3674",
    "sg:postcode":"52001",
    "sg:province":"IA",
    "wof:name":"US Post Office",
    "wof:placetype":"venue"
},
  "geometry": {"coordinates":[-90.66800499999999,42.498621],"type":"Point"}
}