{
  "type": "Feature",
  "properties": {
    "iso:country":"US",
    "sg:address":"911 W 11th St",
    "sg:city":"Spencer",
    "sg:classifiers":[
        {
            "category":"Ice Cream",
            "type":"Food & Drink"
        }
    ],
    "sg:menulink":"http://www.allmenus.com/ia/spencer/172742-dairy-queen/menu/",
    "sg:phone":"+1 712 262 6686",
    "sg:postcode":"51301",
    "sg:province":"IA",
    "sg:tags":[
        "burger",
        "american"
    ],
    "wof:name":"Dairy Queen",
    "wof:placetype":"venue"
},
  "geometry": {"coordinates":[-95.158157,43.148662],"type":"Point"}
}