{
  "type": "Feature",
  "properties": {
    "iso:country":"US",
    "sg:address":"1915 E Kimberly Rd",
    "sg:city":"Davenport",
    "sg:classifiers":[
        {
            "category":"Restaurant",
            "type":"Food & Drink"
        }
    ],
    "sg:menulink":"http://www.allmenus.com/ia/davenport/96112-taco-johns/menu/",
    "sg:phone":"+1 563 355 2044",
    "sg:postcode":"52807",
    "sg:province":"IA",
    "sg:tags":[
        "american",
        "mexican"
    ],
    "wof:name":"Taco John's",
    "wof:placetype":"venue"
},
  "geometry": {"coordinates":[-90.54879099999999,41.556782],"type":"Point"}
}