{
  "type": "Feature",
  "properties": {
    "iso:country":"US",
    "sg:address":"240 State St",
    "sg:city":"Garner",
    "sg:classifiers":[
        {
            "category":"Home & Garden",
            "subcategory":"Carpets & Floor Coverings",
            "type":"Retail Goods"
        }
    ],
    "sg:phone":"+1 641 923 3462",
    "sg:postcode":"50438",
    "sg:province":"IA",
    "sg:tags":[
        "dealer",
        "rug"
    ],
    "wof:name":"All Iowa Sales Co",
    "wof:placetype":"venue"
},
  "geometry": {"coordinates":[-93.60220200000001,43.102943],"type":"Point"}
}