{
  "type": "Feature",
  "properties": {
    "iso:country":"US",
    "sg:address":"1505 Sunset Dr",
    "sg:city":"Belle Plaine",
    "sg:classifiers":[
        {
            "category":"Health Services",
            "subcategory":"Nursing And Care Facility",
            "type":"Services"
        }
    ],
    "sg:phone":"+1 319 444 2500",
    "sg:postcode":"52208",
    "sg:province":"IA",
    "sg:tags":[
        "home",
        "convalescent"
    ],
    "sg:website":"www.careinitiatives.org",
    "wof:name":"Belle Plaine Nursing & Rehab",
    "wof:placetype":"venue"
},
  "geometry": {"coordinates":[-92.26592599999999,41.89931],"type":"Point"}
}