{
  "type": "Feature",
  "properties": {
    "iso:country":"US",
    "sg:address":"1505 Mall Dr",
    "sg:city":"Iowa City",
    "sg:classifiers":[
        {
            "category":"Health Services",
            "subcategory":"Doctor",
            "type":"Services"
        }
    ],
    "sg:phone":"+1 319 337 2135",
    "sg:postcode":"52240",
    "sg:province":"IA",
    "sg:tags":[
        "clinic"
    ],
    "wof:name":"Associated Foot & Ankle Spec",
    "wof:placetype":"venue"
},
  "geometry": {"coordinates":[-91.50811299999999,41.643367],"type":"Point"}
}