{
  "type": "Feature",
  "properties": {
    "iso:country":"US",
    "sg:address":"5000 Tremont Ave",
    "sg:city":"Davenport",
    "sg:classifiers":[
        {
            "category":"Shopping",
            "type":"Retail Goods"
        }
    ],
    "sg:phone":"+1 563 391 6789",
    "sg:postcode":"52807",
    "sg:province":"IA",
    "sg:tags":[
        "orthopedic",
        "appliance"
    ],
    "wof:name":"Eastern Iowa Orthotics",
    "wof:placetype":"venue"
},
  "geometry": {"coordinates":[-90.56085400000001,41.572078],"type":"Point"}
}