{
  "type": "Feature",
  "properties": {
    "iso:country":"US",
    "sg:address":"207 W Center St",
    "sg:city":"Conrad",
    "sg:classifiers":[
        {
            "category":"Retail",
            "subcategory":"Auto Repair",
            "type":"Services"
        }
    ],
    "sg:phone":"+1 641 366 2567",
    "sg:postcode":"50621",
    "sg:province":"IA",
    "sg:tags":[
        "body"
    ],
    "wof:name":"Marv Moats Auto Body",
    "wof:placetype":"venue"
},
  "geometry": {"coordinates":[-92.877174,42.224425],"type":"Point"}
}