{
  "type": "Feature",
  "properties": {
    "iso:country":"US",
    "sg:address":"1500 N 2nd St",
    "sg:city":"Cherokee",
    "sg:classifiers":[
        {
            "category":"Restaurant",
            "type":"Food & Drink"
        }
    ],
    "sg:menulink":"http://www.allmenus.com/ia/cherokee/202652-mcdonalds/menu/",
    "sg:postcode":"51012",
    "sg:province":"IA",
    "sg:tags":[
        "burger",
        "american"
    ],
    "wof:name":"McDonald's",
    "wof:placetype":"venue"
},
  "geometry": {"coordinates":[-95.553151,42.767491],"type":"Point"}
}