{
  "type": "Feature",
  "properties": {
    "iso:country":"US",
    "sg:address":"421 S 6th St",
    "sg:city":"Burlington",
    "sg:classifiers":[
        {
            "category":"Building & Trades",
            "subcategory":"Construction",
            "type":"Services"
        }
    ],
    "sg:phone":"+1 319 753 2018",
    "sg:postcode":"52601",
    "sg:province":"IA",
    "sg:tags":[
        "contractor"
    ],
    "wof:name":"King Drywall & Plastering",
    "wof:placetype":"venue"
},
  "geometry": {"coordinates":[-91.107086,40.804698],"type":"Point"}
}