{
  "type": "Feature",
  "properties": {
    "iso:country":"US",
    "sg:address":"404 W Main St",
    "sg:city":"Washington",
    "sg:classifiers":[
        {
            "category":"Education",
            "subcategory":"School",
            "type":"Public Place"
        }
    ],
    "sg:phone":"+1 319 653 6543",
    "sg:postcode":"52353",
    "sg:province":"IA",
    "sg:website":"www.washington.k12.ia.us",
    "wof:name":"Washington Superintendent Ofc",
    "wof:placetype":"venue"
},
  "geometry": {"coordinates":[-91.69666100000001,41.29955],"type":"Point"}
}