{
  "type": "Feature",
  "properties": {
    "iso:country":"US",
    "sg:address":"2837 197th St",
    "sg:city":"Marshalltown",
    "sg:classifiers":[
        {
            "category":"Wholesale",
            "subcategory":"Durable Goods & Equipment",
            "type":"Manufacturing & Wholesale Goods"
        }
    ],
    "sg:phone":"+1 641 752 1312",
    "sg:postcode":"50158",
    "sg:province":"IA",
    "sg:tags":[
        "fire",
        "extinguisher"
    ],
    "wof:name":"Danner Fire Extinguisher Svc",
    "wof:placetype":"venue"
},
  "geometry": {"coordinates":[-92.86854200000001,42.06745],"type":"Point"}
}