{
  "type": "Feature",
  "properties": {
    "addr:full":"1611 220th St Manchester IA 52057",
    "addr:housenumber":"1611",
    "addr:postcode":"52057",
    "addr:street":"220Th St",
    "iso:country":"US",
    "sg:address":"1611 220th St",
    "sg:city":"Manchester",
    "sg:classifiers":[
        {
            "category":"Communications",
            "type":"Services"
        }
    ],
    "sg:phone":"+1 563 927 1486",
    "sg:postcode":"52057",
    "sg:province":"IA",
    "wof:name":"Pinnacle Towers Inc",
    "wof:placetype":"venue"
},
  "geometry": {"coordinates":[-91.488637,42.46923],"type":"Point"}
}