{
  "type": "Feature",
  "properties": {
    "iso:country":"US",
    "sg:address":"405 Jefferson St",
    "sg:city":"Bedford",
    "sg:classifiers":[
        {
            "category":"Government",
            "subcategory":"Office",
            "type":"Public Place"
        }
    ],
    "sg:phone":"+1 712 523 2124",
    "sg:postcode":"50833",
    "sg:province":"IA",
    "wof:name":"Taylor County Judicial Mgstrt",
    "wof:placetype":"venue"
},
  "geometry": {"coordinates":[-94.720135,40.668006],"type":"Point"}
}