{
  "type": "Feature",
  "properties": {
    "addr:full":"1322 Oasis Ave Winfield IA 52659",
    "addr:housenumber":"1322",
    "addr:postcode":"52659",
    "addr:street":"Oasis Ave",
    "iso:country":"US",
    "sg:address":"1322 Oasis Ave",
    "sg:city":"Winfield",
    "sg:phone":"+1 319 257 6653",
    "sg:postcode":"52659",
    "sg:province":"IA",
    "sg:tags":[
        "farm",
        "corn",
        "soybean"
    ],
    "wof:name":"Helphrey Kurtis",
    "wof:placetype":"venue"
},
  "geometry": {"coordinates":[-91.437843,41.114644],"type":"Point"}
}