{
  "type": "Feature",
  "properties": {
    "iso:country":"US",
    "sg:address":"217 East Porter Avenue",
    "sg:city":"Des Moines",
    "sg:classifiers":[
        {
            "category":"Professional",
            "subcategory":"Research",
            "type":"Services"
        }
    ],
    "sg:phone":"+1 515 270 7063",
    "sg:postcode":"50315",
    "sg:province":"IA",
    "sg:tags":[
        "dotnetnuke",
        "-net",
        "custom-applications",
        "development-consulting",
        "software-development",
        "c"
    ],
    "sg:website":"http://www.iowacomputergurus.com",
    "wof:name":"IowaComputerGurus",
    "wof:placetype":"venue"
},
  "geometry": {"coordinates":[-93.611597,41.533577],"type":"Point"}
}