{
  "type": "Feature",
  "properties": {
    "iso:country":"US",
    "sg:address":"514 Main St",
    "sg:city":"Osage",
    "sg:classifiers":[
        {
            "category":"Food & Beverages",
            "subcategory":"Meat & Fish",
            "type":"Retail Goods"
        }
    ],
    "sg:phone":"+1 641 732 4792",
    "sg:postcode":"50461",
    "sg:province":"IA",
    "wof:name":"S & S Locker",
    "wof:placetype":"venue"
},
  "geometry": {"coordinates":[-92.814442,43.284004],"type":"Point"}
}