{
  "type": "Feature",
  "properties": {
    "iso:country":"US",
    "sg:address":"565 Fenelon Pl",
    "sg:city":"Dubuque",
    "sg:classifiers":[
        {
            "category":"Building & Trades",
            "subcategory":"Construction",
            "type":"Services"
        }
    ],
    "sg:phone":"+1 563 556 7728",
    "sg:postcode":"52001",
    "sg:province":"IA",
    "sg:tags":[
        "house"
    ],
    "wof:name":"Richard Construction Co",
    "wof:placetype":"venue"
},
  "geometry": {"coordinates":[-90.671544,42.495747],"type":"Point"}
}