{
  "type": "Feature",
  "properties": {
    "addr:full":"3327 Singing Hills Blvd Sioux City IA 51106",
    "addr:housenumber":"3327",
    "addr:postcode":"51106",
    "addr:street":"Singing Hills Blvd",
    "iso:country":"US",
    "sg:address":"3327 Singing Hills Blvd",
    "sg:city":"Sioux City",
    "sg:classifiers":[
        {
            "category":"Restaurant",
            "type":"Food & Drink"
        }
    ],
    "sg:menulink":"http://www.allmenus.com/ia/sioux-city/67083-pizza-hut/menu/",
    "sg:phone":"+1 712 255 9100",
    "sg:postcode":"51106",
    "sg:province":"IA",
    "sg:tags":[
        "american",
        "pizza"
    ],
    "wof:name":"Pizza Hut",
    "wof:placetype":"venue"
},
  "geometry": {"coordinates":[-96.36533300000001,42.436065],"type":"Point"}
}