{
  "type": "Feature",
  "properties": {
    "iso:country":"US",
    "sg:address":"4215 Chamberlain Dr",
    "sg:city":"Des Moines",
    "sg:classifiers":[
        {
            "category":"Wholesale",
            "subcategory":"Electrical",
            "type":"Manufacturing & Wholesale Goods"
        }
    ],
    "sg:phone":"+1 515 255 9555",
    "sg:postcode":"50312",
    "sg:province":"IA",
    "sg:tags":[
        "sound",
        "equipment",
        "system"
    ],
    "wof:name":"Tri Point Audio Technologies",
    "wof:placetype":"venue"
},
  "geometry": {"coordinates":[-93.69964400000001,41.59368],"type":"Point"}
}