{
  "type": "Feature",
  "properties": {
    "iso:country":"US",
    "sg:address":"4707 Grayhawk Ridge Dr",
    "sg:city":"Sioux City",
    "sg:classifiers":[
        {
            "category":"Banks & Credit Unions",
            "subcategory":"Investment Brokerage",
            "type":"Services"
        }
    ],
    "sg:phone":"+1 712 258 7970",
    "sg:postcode":"51106",
    "sg:province":"SD",
    "sg:tags":[
        "funds",
        "mutual"
    ],
    "wof:name":"Siouxland Investments Svc Inc",
    "wof:placetype":"venue"
},
  "geometry": {"coordinates":[-96.348855,42.432417],"type":"Point"}
}