{
  "type": "Feature",
  "properties": {
    "iso:country":"US",
    "sg:address":"14241 Elmcrest Ct",
    "sg:city":"Clive",
    "sg:classifiers":[
        {
            "category":"Building & Trades",
            "subcategory":"Plumbing",
            "type":"Services"
        }
    ],
    "sg:phone":"+1 515 288 2332",
    "sg:postcode":"50325",
    "sg:province":"IA",
    "sg:tags":[
        "balancing",
        "air"
    ],
    "wof:name":"Precision Test & Balance",
    "wof:placetype":"venue"
},
  "geometry": {"coordinates":[-93.815817,41.602636],"type":"Point"}
}