{
  "type": "Feature",
  "properties": {
    "iso:country":"US",
    "sg:address":"102 W Main St",
    "sg:city":"West Branch",
    "sg:classifiers":[
        {
            "category":"Restaurant",
            "type":"Food & Drink"
        }
    ],
    "sg:phone":"+1 319 643 4050",
    "sg:postcode":"52358",
    "sg:province":"IA",
    "wof:name":"West Branch Bar & Grill",
    "wof:placetype":"venue"
},
  "geometry": {"coordinates":[-91.34743,41.671338],"type":"Point"}
}