{
  "type": "Feature",
  "properties": {
    "iso:country":"US",
    "sg:address":"515 Clark Ave",
    "sg:city":"Ames",
    "sg:classifiers":[
        {
            "category":"Government",
            "subcategory":"Office",
            "type":"Public Place"
        }
    ],
    "sg:phone":"+1 515 239 5120",
    "sg:postcode":"50010",
    "sg:province":"IA",
    "sg:tags":[
        "village"
    ],
    "sg:website":"www.amesutilities.com",
    "wof:name":"Ames Electric Dept",
    "wof:placetype":"venue"
},
  "geometry": {"coordinates":[-93.61698699999999,42.026729],"type":"Point"}
}