{
  "type": "Feature",
  "properties": {
    "iso:country":"US",
    "sg:address":"727 210th Ave",
    "sg:city":"Pella",
    "sg:classifiers":[
        {
            "category":"Building & Trades",
            "subcategory":"Construction",
            "type":"Services"
        }
    ],
    "sg:phone":"+1 641 627 5319",
    "sg:postcode":"50219",
    "sg:province":"IA",
    "sg:tags":[
        "general",
        "contractor"
    ],
    "sg:website":"www.koopman.biz",
    "wof:name":"Koopman Construction",
    "wof:placetype":"venue"
},
  "geometry": {"coordinates":[-92.94815699999999,41.417287],"type":"Point"}
}