{
  "type": "Feature",
  "properties": {
    "iso:country":"US",
    "sg:address":"70555 760th St",
    "sg:city":"Massena",
    "sg:classifiers":[
        {
            "category":"Shopping",
            "subcategory":"Gifts & Souvenirs",
            "type":"Retail Goods"
        }
    ],
    "sg:phone":"+1 712 779 3724",
    "sg:postcode":"50853",
    "sg:province":"IA",
    "wof:name":"Klassic Keepsakes",
    "wof:placetype":"venue"
},
  "geometry": {"coordinates":[-94.738795,41.215934],"type":"Point"}
}