{
  "type": "Feature",
  "properties": {
    "iso:country":"US",
    "sg:address":"1726 W 1st St",
    "sg:city":"Davenport",
    "sg:classifiers":[
        {
            "category":"Building & Trades",
            "subcategory":"Construction",
            "type":"Services"
        }
    ],
    "sg:phone":"+1 563 322 0771",
    "sg:postcode":"52802",
    "sg:province":"IA",
    "sg:tags":[
        "roofing",
        "industrial",
        "contractors-commercial",
        "contractor"
    ],
    "sg:website":"http://roofingtechnologyinc.com",
    "wof:name":"Roofing Technology Inc",
    "wof:placetype":"venue"
},
  "geometry": {"coordinates":[-90.60174600000001,41.520172],"type":"Point"}
}