{
  "type": "Feature",
  "properties": {
    "iso:country":"US",
    "sg:address":"1904 Quint Ave",
    "sg:city":"Carroll",
    "sg:classifiers":[
        {
            "category":"Building & Trades",
            "subcategory":"Construction",
            "type":"Services"
        }
    ],
    "sg:phone":"+1 712 792 3013",
    "sg:postcode":"51401",
    "sg:province":"IA",
    "sg:tags":[
        "general",
        "contractor"
    ],
    "wof:name":"Julich Construction",
    "wof:placetype":"venue"
},
  "geometry": {"coordinates":[-94.873869,42.080937],"type":"Point"}
}