{
  "type": "Feature",
  "properties": {
    "iso:country":"US",
    "sg:address":"2212 Okoboji Ave",
    "sg:city":"Milford",
    "sg:classifiers":[
        {
            "category":"Building & Trades",
            "subcategory":"Pest Control",
            "type":"Services"
        }
    ],
    "sg:phone":"+1 712 338 9022",
    "sg:postcode":"51351",
    "sg:province":"IA",
    "sg:website":"www.lakespestcontrol.com",
    "wof:name":"Lakes Pest Control",
    "wof:placetype":"venue"
},
  "geometry": {"coordinates":[-95.149879,43.336834],"type":"Point"}
}