{
  "type": "Feature",
  "properties": {
    "iso:country":"US",
    "sg:address":"210 6th Ave",
    "sg:city":"Lisbon",
    "sg:classifiers":[
        {
            "category":"Retail",
            "subcategory":"Auto Repair",
            "type":"Services"
        }
    ],
    "sg:phone":"+1 319 455 2352",
    "sg:postcode":"52233",
    "sg:province":"IA",
    "sg:tags":[
        "repairing",
        "automobile"
    ],
    "wof:name":"T & R Customs",
    "wof:placetype":"venue"
},
  "geometry": {"coordinates":[-91.677756,42.034865],"type":"Point"}
}