{
  "type": "Feature",
  "properties": {
    "iso:country":"US",
    "sg:address":"636 Kirkwood Blvd",
    "sg:city":"Davenport",
    "sg:classifiers":[
        {
            "category":"Organizations",
            "subcategory":"Religious Organization",
            "type":"Services"
        }
    ],
    "sg:phone":"+1 563 322 1575",
    "sg:postcode":"52803",
    "sg:province":"IA",
    "sg:tags":[
        "church"
    ],
    "wof:name":"Harvest Time Family Worship",
    "wof:placetype":"venue"
},
  "geometry": {"coordinates":[-90.56626300000001,41.536301],"type":"Point"}
}