{
  "type": "Feature",
  "properties": {
    "iso:country":"US",
    "sg:address":"36919 Saint Sebald Rd",
    "sg:city":"Strawberry Point",
    "sg:classifiers":[
        {
            "category":"Manufacturing",
            "subcategory":"Chemicals & Compounds",
            "type":"Manufacturing & Wholesale Goods"
        }
    ],
    "sg:phone":"+1 563 933 2293",
    "sg:postcode":"52076",
    "sg:province":"IA",
    "sg:tags":[
        "fertilizer",
        "mixing",
        "only"
    ],
    "wof:name":"Silveredge Cooperative",
    "wof:placetype":"venue"
},
  "geometry": {"coordinates":[-91.5681,42.689449],"type":"Point"}
}