{
  "type": "Feature",
  "properties": {
    "addr:full":"304 S Fremont St Shenandoah IA 51601",
    "addr:housenumber":"304",
    "addr:postcode":"51601",
    "addr:street":"S Fremont St",
    "iso:country":"US",
    "sg:address":"304 S Fremont St",
    "sg:city":"Shenandoah",
    "sg:classifiers":[
        {
            "category":"Autos & Motor Vehicles",
            "subcategory":"Auto Supplies",
            "type":"Retail Goods"
        }
    ],
    "sg:phone":"+1 712 246 3756",
    "sg:postcode":"51601",
    "sg:province":"IA",
    "sg:tags":[
        "tire"
    ],
    "wof:name":"Johnson Tire Co",
    "wof:placetype":"venue"
},
  "geometry": {"coordinates":[-95.385014,40.764029],"type":"Point"}
}