{
  "type": "Feature",
  "properties": {
    "addr:full":"2804 Eastern Ave Davenport IA 52803",
    "addr:housenumber":"2804",
    "addr:postcode":"52803",
    "addr:street":"Eastern Ave",
    "iso:country":"US",
    "sg:address":"2804 Eastern Ave",
    "sg:city":"Davenport",
    "sg:classifiers":[
        {
            "category":"Education",
            "subcategory":"Library",
            "type":"Public Place"
        }
    ],
    "sg:phone":"+1 563 326 7893",
    "sg:postcode":"52803",
    "sg:province":"IA",
    "wof:name":"Davenport Public Library",
    "wof:placetype":"venue"
},
  "geometry": {"coordinates":[-90.551528,41.547378],"type":"Point"}
}