{
  "type": "Feature",
  "properties": {
    "iso:country":"US",
    "sg:address":"203 NE 2nd St",
    "sg:city":"Leon",
    "sg:classifiers":[
        {
            "category":"Social Services",
            "subcategory":"Adult Care",
            "type":"Services"
        }
    ],
    "sg:phone":"+1 641 446 4433",
    "sg:postcode":"50144",
    "sg:province":"IA",
    "sg:tags":[
        "organization",
        "senior",
        "citizen"
    ],
    "wof:name":"Congregate Meal Site",
    "wof:placetype":"venue"
},
  "geometry": {"coordinates":[-93.745887,40.740224],"type":"Point"}
}