{
  "type": "Feature",
  "properties": {
    "iso:country":"US",
    "sg:address":"1417 Exchange St",
    "sg:city":"Keokuk",
    "sg:classifiers":[
        {
            "category":"Manufacturing",
            "subcategory":"Pet Food",
            "type":"Manufacturing & Wholesale Goods"
        }
    ],
    "sg:phone":"+1 319 524 5757",
    "sg:postcode":"52632",
    "sg:province":"IA",
    "sg:tags":[
        "corn",
        "milling",
        "wet"
    ],
    "wof:name":"Roquette America",
    "wof:placetype":"venue"
},
  "geometry": {"coordinates":[-91.393452,40.402294],"type":"Point"}
}