{
  "type": "Feature",
  "properties": {
    "addr:full":"400 Hwy 18 Spencer IA 51301",
    "addr:housenumber":"400",
    "addr:postcode":"51301",
    "addr:street":"Hwy 18",
    "iso:country":"US",
    "sg:address":"400 Hwy 18",
    "sg:city":"Spencer",
    "sg:classifiers":[
        {
            "category":"Freight",
            "type":"Transportation"
        }
    ],
    "sg:phone":"+1 712 262 5241",
    "sg:postcode":"51301",
    "sg:province":"IA",
    "sg:tags":[
        "warehouse",
        "self",
        "storage"
    ],
    "wof:name":"Warehouse",
    "wof:placetype":"venue"
},
  "geometry": {"coordinates":[-95.13873599999999,43.126245],"type":"Point"}
}