{
  "type": "Feature",
  "properties": {
    "addr:full":"24221 State Hwy 128 Elkader IA 52043",
    "addr:housenumber":"24221",
    "addr:postcode":"52043",
    "addr:street":"State Hwy 128",
    "iso:country":"US",
    "sg:address":"24221 State Hwy 128",
    "sg:city":"Elkader",
    "sg:classifiers":[
        {
            "category":"Organizations",
            "subcategory":"Religious Organization",
            "type":"Services"
        }
    ],
    "sg:phone":"+1 563 245 2437",
    "sg:postcode":"52043",
    "sg:province":"IA",
    "sg:tags":[
        "church"
    ],
    "wof:name":"Zion Lutheran Church",
    "wof:placetype":"venue"
},
  "geometry": {"coordinates":[-91.32549299999999,42.883589],"type":"Point"}
}