{
  "type": "Feature",
  "properties": {
    "iso:country":"US",
    "sg:address":"6268 Northwest Blvd",
    "sg:city":"Davenport",
    "sg:classifiers":[
        {
            "category":"Professional",
            "subcategory":"Management & Consulting",
            "type":"Services"
        }
    ],
    "sg:phone":"+1 563 391 4785",
    "sg:postcode":"52806",
    "sg:province":"IA",
    "sg:tags":[
        "steel",
        "erection"
    ],
    "wof:name":"Wilson Construction Lc",
    "wof:placetype":"venue"
},
  "geometry": {"coordinates":[-90.606793,41.586008],"type":"Point"}
}