{
  "type": "Feature",
  "properties": {
    "addr:full":"102 W 3rd St St Anthony IA 50239",
    "addr:housenumber":"102",
    "addr:postcode":"50239",
    "addr:street":"W 3Rd St",
    "iso:country":"US",
    "sg:address":"102 W 3rd St",
    "sg:city":"St Anthony",
    "sg:classifiers":[
        {
            "category":"Freight",
            "type":"Transportation"
        }
    ],
    "sg:phone":"+1 641 477 8244",
    "sg:postcode":"50239",
    "sg:province":"IA",
    "sg:tags":[
        "grain",
        "elevator"
    ],
    "wof:name":"Mackin Grain Co",
    "wof:placetype":"venue"
},
  "geometry": {"coordinates":[-93.197154,42.125206],"type":"Point"}
}