{
  "type": "Feature",
  "properties": {
    "addr:full":"2790 Ethel Ave Dubuque IA 52001",
    "addr:housenumber":"2790",
    "addr:postcode":"52001",
    "addr:street":"Ethel Ave",
    "iso:country":"US",
    "sg:address":"2790 Ethel Ave",
    "sg:city":"Dubuque",
    "sg:classifiers":[
        {
            "category":"Manufacturing",
            "subcategory":"Buildings",
            "type":"Manufacturing & Wholesale Goods"
        },
        {
            "category":"Real Estate",
            "subcategory":"Developer",
            "type":"Services"
        },
        {
            "category":"Building & Trades",
            "subcategory":"Construction",
            "type":"Services"
        }
    ],
    "sg:phone":"+1 563 556 2195",
    "sg:postcode":"52001",
    "sg:province":"IA",
    "sg:tags":[
        "home",
        "builder",
        "contractor"
    ],
    "sg:website":"http://www.habitat.org",
    "wof:name":"Habitat For Humanity International Inc",
    "wof:placetype":"venue"
},
  "geometry": {"coordinates":[-90.706067,42.494198],"type":"Point"}
}