{
  "type": "Feature",
  "properties": {
    "iso:country":"US",
    "sg:address":"308 Main St",
    "sg:city":"Nashua",
    "sg:classifiers":[
        {
            "category":"Real Estate",
            "subcategory":"Real Estate Agent",
            "type":"Services"
        }
    ],
    "sg:phone":"+1 641 435 2654",
    "sg:postcode":"50658",
    "sg:province":"IA",
    "wof:name":"New Age Realty LC",
    "wof:placetype":"venue"
},
  "geometry": {"coordinates":[-92.536334,42.952537],"type":"Point"}
}