{
  "type": "Feature",
  "properties": {
    "iso:country":"US",
    "sg:address":"2032 S Cypress St",
    "sg:city":"Sioux City",
    "sg:classifiers":[
        {
            "category":"Organizations",
            "subcategory":"Religious Organization",
            "type":"Services"
        }
    ],
    "sg:phone":"+1 712 276 2667",
    "sg:postcode":"51106",
    "sg:province":"SD",
    "sg:tags":[
        "church"
    ],
    "wof:name":"St James United Methodist Chr",
    "wof:placetype":"venue"
},
  "geometry": {"coordinates":[-96.340835,42.470079],"type":"Point"}
}