{
  "type": "Feature",
  "properties": {
    "iso:country":"US",
    "sg:address":"16739 Diplomat Rd",
    "sg:city":"Luana",
    "sg:classifiers":[
        {
            "category":"Recreation",
            "type":"Entertainment"
        }
    ],
    "sg:phone":"+1 563 539 4435",
    "sg:postcode":"52156",
    "sg:province":"IA",
    "sg:tags":[
        "course",
        "golf"
    ],
    "wof:name":"Tri City Club",
    "wof:placetype":"venue"
},
  "geometry": {"coordinates":[-91.474346,43.072284],"type":"Point"}
}