{
  "type": "Feature",
  "properties": {
    "addr:full":"715 N 4th St Oskaloosa IA 52577",
    "addr:housenumber":"715",
    "addr:postcode":"52577",
    "addr:street":"N 4Th St",
    "iso:country":"US",
    "sg:address":"715 N 4th St",
    "sg:city":"Oskaloosa",
    "sg:phone":"+1 641 673 9622",
    "sg:postcode":"52577",
    "sg:province":"IA",
    "sg:tags":[
        "farm",
        "corn"
    ],
    "wof:name":"Ralph Benzing",
    "wof:placetype":"venue"
},
  "geometry": {"coordinates":[-92.640415,41.302827],"type":"Point"}
}