{
  "type": "Feature",
  "properties": {
    "iso:country":"US",
    "sg:address":"1461 Coral Ridge Ave",
    "sg:city":"Coralville",
    "sg:classifiers":[
        {
            "category":"Shopping",
            "subcategory":"Bicycles & Sporting Goods",
            "type":"Retail Goods"
        }
    ],
    "sg:phone":"+1 319 625 9959",
    "sg:postcode":"52241",
    "sg:province":"IA",
    "wof:name":"Scheels All Sports",
    "wof:placetype":"venue"
},
  "geometry": {"coordinates":[-91.60832600000001,41.691776],"type":"Point"}
}