{
  "type": "Feature",
  "properties": {
    "addr:full":"723 W Thomas Ave Shenandoah IA 51601",
    "addr:housenumber":"723",
    "addr:postcode":"51601",
    "addr:street":"W Thomas Ave",
    "iso:country":"US",
    "sg:address":"723 W Thomas Ave",
    "sg:city":"Shenandoah",
    "sg:classifiers":[
        {
            "category":"Professional",
            "subcategory":"Lawyer & Legal Services",
            "type":"Services"
        }
    ],
    "sg:phone":"+1 712 246 4300",
    "sg:postcode":"51601",
    "sg:province":"IA",
    "sg:tags":[
        "attorney"
    ],
    "wof:name":"Rawson Stevens Law Firm",
    "wof:placetype":"venue"
},
  "geometry": {"coordinates":[-95.374905,40.765077],"type":"Point"}
}