{
  "type": "Feature",
  "properties": {
    "iso:country":"US",
    "sg:address":"11305 Aurora Ave",
    "sg:city":"Urbandale",
    "sg:classifiers":[
        {
            "category":"Professional",
            "subcategory":"Computer Services",
            "type":"Services"
        }
    ],
    "sg:phone":"+1 515 440 0848",
    "sg:postcode":"50322",
    "sg:province":"IA",
    "sg:tags":[
        "internet"
    ],
    "sg:website":"www.p-inet.com",
    "wof:name":"Prairie Inet",
    "wof:placetype":"venue"
},
  "geometry": {"coordinates":[-93.76918499999999,41.638482],"type":"Point"}
}