{
  "type": "Feature",
  "properties": {
    "iso:country":"US",
    "sg:address":"220 N Main St",
    "sg:city":"Davenport",
    "sg:classifiers":[
        {
            "category":"Real Estate",
            "subcategory":"Real Estate Agent",
            "type":"Services"
        }
    ],
    "sg:phone":"+1 563 322 9222",
    "sg:postcode":"52801",
    "sg:province":"IA",
    "sg:tags":[
        "management"
    ],
    "sg:website":"www.ryancompanies.com",
    "wof:name":"Ryan Properties Inc",
    "wof:placetype":"venue"
},
  "geometry": {"coordinates":[-90.575671,41.521629],"type":"Point"}
}