{
  "type": "Feature",
  "properties": {
    "addr:full":"3422 450th St Orange City IA 51041",
    "addr:housenumber":"3422",
    "addr:postcode":"51041",
    "addr:street":"450Th St",
    "iso:country":"US",
    "sg:address":"3422 450th St",
    "sg:city":"Orange City",
    "sg:classifiers":[
        {
            "category":"Retail",
            "subcategory":"Repair Shop",
            "type":"Services"
        }
    ],
    "sg:phone":"+1 712 737 2847",
    "sg:postcode":"51041",
    "sg:province":"IA",
    "sg:tags":[
        "ironwork"
    ],
    "wof:name":"Randy's Ironworks",
    "wof:placetype":"venue"
},
  "geometry": {"coordinates":[-96.10604499999999,42.997618],"type":"Point"}
}