{
  "type": "Feature",
  "properties": {
    "addr:full":"411 S Chestnut St Jefferson IA 50129",
    "addr:housenumber":"411",
    "addr:postcode":"50129",
    "addr:street":"S Chestnut St",
    "iso:country":"US",
    "sg:address":"411 S Chestnut St",
    "sg:city":"Jefferson",
    "sg:classifiers":[
        {
            "category":"Farming",
            "subcategory":"Farm",
            "type":"Manufacturing & Wholesale Goods"
        }
    ],
    "sg:phone":"+1 515 386 3092",
    "sg:postcode":"50129",
    "sg:province":"IA",
    "sg:tags":[
        "crop",
        "legal",
        "general"
    ],
    "wof:name":"John Beltz",
    "wof:placetype":"venue"
},
  "geometry": {"coordinates":[-94.373363,42.012193],"type":"Point"}
}