{
  "type": "Feature",
  "properties": {
    "iso:country":"US",
    "sg:address":"14777 US Hwy 65",
    "sg:city":"Zearing",
    "sg:classifiers":[
        {
            "category":"Organizations",
            "subcategory":"Religious Organization",
            "type":"Services"
        }
    ],
    "sg:phone":"+1 641 487 7855",
    "sg:postcode":"50278",
    "sg:province":"IA",
    "sg:tags":[
        "church"
    ],
    "sg:website":"www.forreallife.org",
    "wof:name":"Cornerstone Church Of Christ",
    "wof:placetype":"venue"
},
  "geometry": {"coordinates":[-93.309467,42.140421],"type":"Point"}
}