{
  "type": "Feature",
  "properties": {
    "addr:full":"11717 State Hwy 9 Thompson IA 50478",
    "addr:housenumber":"11717",
    "addr:postcode":"50478",
    "addr:street":"State Hwy 9",
    "iso:country":"US",
    "sg:address":"11717 State Hwy 9",
    "sg:city":"Thompson",
    "sg:classifiers":[
        {
            "category":"Food & Beverages",
            "subcategory":"Groceries & Convenience Stores",
            "type":"Retail Goods"
        }
    ],
    "sg:phone":"+1 641 584 2300",
    "sg:postcode":"50478",
    "sg:province":"IA",
    "sg:tags":[
        "grocer"
    ],
    "wof:name":"Hometown Market",
    "wof:placetype":"venue"
},
  "geometry": {"coordinates":[-93.75958,43.371239],"type":"Point"}
}