{
  "type": "Feature",
  "properties": {
    "iso:country":"US",
    "sg:address":"11222 Yankee Ave",
    "sg:city":"Cresco",
    "sg:classifiers":[
        {
            "category":"Building & Trades",
            "subcategory":"Construction",
            "type":"Services"
        }
    ],
    "sg:phone":"+1 563 547 2623",
    "sg:postcode":"52136",
    "sg:province":"IA",
    "sg:tags":[
        "house"
    ],
    "wof:name":"Ricks Construction",
    "wof:placetype":"venue"
},
  "geometry": {"coordinates":[-92.099878,43.350422],"type":"Point"}
}