{
  "type": "Feature",
  "properties": {
    "addr:full":"3701 Cheyenne Blvd Sioux City IA 51104",
    "addr:housenumber":"3701",
    "addr:postcode":"51104",
    "addr:street":"Cheyenne Blvd",
    "iso:country":"US",
    "sg:address":"3701 Cheyenne Blvd",
    "sg:city":"Sioux City",
    "sg:phone":"+1 712 277 3810",
    "sg:postcode":"51104",
    "sg:province":"IA",
    "sg:tags":[
        "farm",
        "corn",
        "soybean"
    ],
    "wof:name":"Kent Ivener",
    "wof:placetype":"venue"
},
  "geometry": {"coordinates":[-96.395293,42.535543],"type":"Point"}
}