{
  "type": "Feature",
  "properties": {
    "addr:full":"22428 US Hwy 6 Council Bluffs IA 51503",
    "addr:postcode":"22428;51503",
    "addr:street":"Us Hwy 6",
    "iso:country":"US",
    "sg:address":"22428 US Hwy 6",
    "sg:city":"Council Bluffs",
    "sg:classifiers":[
        {
            "category":"Building & Trades",
            "subcategory":"Construction",
            "type":"Services"
        }
    ],
    "sg:phone":"+1 712 323 3194",
    "sg:postcode":"51503",
    "sg:province":"IA",
    "sg:tags":[
        "house"
    ],
    "wof:name":"Krohn/Smith Const",
    "wof:placetype":"venue"
},
  "geometry": {"coordinates":[-95.76241899999999,41.280971],"type":"Point"}
}