{
  "type": "Feature",
  "properties": {
    "iso:country":"US",
    "sg:address":"1791 Page Ave",
    "sg:city":"Clarion",
    "sg:classifiers":[
        {
            "category":"Manufacturing",
            "subcategory":"Toys & Sporting Goods",
            "type":"Manufacturing & Wholesale Goods"
        }
    ],
    "sg:phone":"+1 515 532 2857",
    "sg:postcode":"50525",
    "sg:province":"IA",
    "sg:tags":[
        "equipment",
        "gymnasium",
        "supply"
    ],
    "sg:website":"www.sportsgraphicsinc.com",
    "wof:name":"Sportgraphics",
    "wof:placetype":"venue"
},
  "geometry": {"coordinates":[-93.682695,42.791054],"type":"Point"}
}