{
  "type": "Feature",
  "properties": {
    "iso:country":"US",
    "sg:address":"1232 140th St",
    "sg:city":"Essex",
    "sg:classifiers":[
        {
            "category":"Sports & Exercise",
            "subcategory":"Golf",
            "type":"Entertainment"
        }
    ],
    "sg:phone":"+1 712 379 3805",
    "sg:postcode":"51638",
    "sg:province":"IA",
    "sg:tags":[
        "course",
        "public"
    ],
    "wof:name":"Essex Golf & Recreation",
    "wof:placetype":"venue"
},
  "geometry": {"coordinates":[-95.33989099999999,40.84358],"type":"Point"}
}