{
  "type": "Feature",
  "properties": {
    "addr:full":"2414 Lucas Rd Muscatine IA 52761",
    "addr:housenumber":"2414",
    "addr:postcode":"52761",
    "addr:street":"Lucas Rd",
    "iso:country":"US",
    "sg:address":"2414 Lucas Rd",
    "sg:city":"Muscatine",
    "sg:classifiers":[
        {
            "category":"Building & Trades",
            "subcategory":"Construction",
            "type":"Services"
        }
    ],
    "sg:phone":"+1 563 263 4640",
    "sg:postcode":"52761",
    "sg:province":"IA",
    "sg:tags":[
        "hanging",
        "contractor"
    ],
    "wof:name":"Bromwell S Painting",
    "wof:placetype":"venue"
},
  "geometry": {"coordinates":[-91.072411,41.423252],"type":"Point"}
}