{
  "type": "Feature",
  "properties": {
    "addr:full":"113 W Main St Lake City IA 51449",
    "addr:housenumber":"113",
    "addr:postcode":"51449",
    "addr:street":"W Main St",
    "iso:country":"US",
    "sg:address":"113 W Main St",
    "sg:city":"Lake City",
    "sg:classifiers":[
        {
            "category":"Building & Trades",
            "subcategory":"Plumbing",
            "type":"Services"
        }
    ],
    "sg:phone":"+1 712 464 3230",
    "sg:postcode":"51449",
    "sg:province":"IA",
    "sg:tags":[
        "contractor"
    ],
    "wof:name":"Lake City Electric Company",
    "wof:placetype":"venue"
},
  "geometry": {"coordinates":[-94.734887,42.267285],"type":"Point"}
}