{
  "type": "Feature",
  "properties": {
    "addr:full":"525 Brandilynn Blvd Cedar Falls IA 50613",
    "addr:housenumber":"525",
    "addr:postcode":"50613",
    "addr:street":"Brandilynn Blvd",
    "iso:country":"US",
    "sg:address":"525 Brandilynn Blvd",
    "sg:city":"Cedar Falls",
    "sg:classifiers":[
        {
            "category":"Personal",
            "subcategory":"Beauty Salon",
            "type":"Services"
        }
    ],
    "sg:phone":"+1 319 277 7464",
    "sg:postcode":"50613",
    "sg:province":"IA",
    "wof:name":"Smart Style Family Hair Salon",
    "wof:placetype":"venue"
},
  "geometry": {"coordinates":[-92.438267,42.485036],"type":"Point"}
}