{
  "type": "Feature",
  "properties": {
    "iso:country":"US",
    "sg:address":"3044 Bethel St",
    "sg:city":"Waterloo",
    "sg:classifiers":[
        {
            "category":"Farming",
            "subcategory":"Farm",
            "type":"Manufacturing & Wholesale Goods"
        }
    ],
    "sg:phone":"+1 319 235 8964",
    "sg:postcode":"50702",
    "sg:province":"IA",
    "sg:tags":[
        "crop",
        "general"
    ],
    "wof:name":"Alan Flick",
    "wof:placetype":"venue"
},
  "geometry": {"coordinates":[-92.331317,42.468659],"type":"Point"}
}