{
  "type": "Feature",
  "properties": {
    "iso:country":"US",
    "sg:address":"2597 160th St",
    "sg:city":"Mount Union",
    "sg:phone":"+1 319 865 5307",
    "sg:postcode":"52644",
    "sg:province":"IA",
    "sg:tags":[
        "farm",
        "corn",
        "soybean"
    ],
    "wof:name":"Kevin Kongable",
    "wof:placetype":"venue"
},
  "geometry": {"coordinates":[-91.410347,41.074701],"type":"Point"}
}