{
  "type": "Feature",
  "properties": {
    "iso:country":"US",
    "sg:address":"1004 Iowa Ave",
    "sg:city":"Onawa",
    "sg:classifiers":[
        {
            "category":"Food & Beverages",
            "subcategory":"Groceries & Convenience Stores",
            "type":"Retail Goods"
        }
    ],
    "sg:phone":"+1 712 423 3265",
    "sg:postcode":"51040",
    "sg:province":"IA",
    "wof:name":"Sparky's One Stop",
    "wof:placetype":"venue"
},
  "geometry": {"coordinates":[-96.098637,42.026795],"type":"Point"}
}