{
  "type": "Feature",
  "properties": {
    "iso:country":"US",
    "sg:address":"1414 W Lombard St",
    "sg:city":"Davenport",
    "sg:classifiers":[
        {
            "category":"Shopping",
            "type":"Retail Goods"
        }
    ],
    "sg:phone":"+1 563 324 7707",
    "sg:postcode":"52804",
    "sg:province":"IA",
    "sg:tags":[
        "orthopedic",
        "appliance"
    ],
    "wof:name":"American Prosthetics-Orthtcs",
    "wof:placetype":"venue"
},
  "geometry": {"coordinates":[-90.594154,41.541959],"type":"Point"}
}