{
  "type": "Feature",
  "properties": {
    "addr:full":"209 N Broadway St Manly IA 50461",
    "addr:housenumber":"209",
    "addr:postcode":"50461",
    "addr:street":"N Broadway St",
    "iso:country":"US",
    "sg:address":"209 N Broadway St",
    "sg:city":"Manly",
    "sg:classifiers":[
        {
            "category":"Social Services",
            "subcategory":"Child Care",
            "type":"Services"
        }
    ],
    "sg:phone":"+1 641 454 2137",
    "sg:postcode":"50461",
    "sg:province":"IA",
    "wof:name":"Project Childcare",
    "wof:placetype":"venue"
},
  "geometry": {"coordinates":[-93.201071,43.288199],"type":"Point"}
}