{
  "type": "Feature",
  "properties": {
    "iso:country":"US",
    "sg:address":"5600 NW 78th Ave",
    "sg:city":"Johnston",
    "sg:classifiers":[
        {
            "category":"Travel",
            "subcategory":"Campground",
            "type":"Entertainment"
        }
    ],
    "sg:phone":"+1 515 276 0873",
    "sg:postcode":"50131",
    "sg:province":"IA",
    "wof:name":"Bob Shetler Campground",
    "wof:placetype":"venue"
},
  "geometry": {"coordinates":[-93.702119,41.70286],"type":"Point"}
}