{
  "type": "Feature",
  "properties": {
    "addr:full":"65868 248th St Nevada IA 50201",
    "addr:housenumber":"65868",
    "addr:postcode":"50201",
    "addr:street":"248Th St",
    "iso:country":"US",
    "sg:address":"65868 248th St",
    "sg:city":"Nevada",
    "sg:classifiers":[
        {
            "category":"Farming",
            "subcategory":"Farm",
            "type":"Manufacturing & Wholesale Goods"
        }
    ],
    "sg:phone":"+1 515 382 4855",
    "sg:postcode":"50201",
    "sg:province":"IA",
    "sg:tags":[
        "crop",
        "general"
    ],
    "wof:name":"Frank E McLain Jr",
    "wof:placetype":"venue"
},
  "geometry": {"coordinates":[-93.390218,42.007058],"type":"Point"}
}