{
  "type": "Feature",
  "properties": {
    "iso:country":"US",
    "sg:address":"212 W Bluff St",
    "sg:city":"Cherokee",
    "sg:classifiers":[
        {
            "category":"Health Services",
            "subcategory":"Doctor",
            "type":"Services"
        }
    ],
    "sg:phone":"+1 712 225 5128",
    "sg:postcode":"51012",
    "sg:province":"IA",
    "sg:tags":[
        "physician",
        "surgeon"
    ],
    "wof:name":"West Bluff Medical Assoc",
    "wof:placetype":"venue"
},
  "geometry": {"coordinates":[-95.55208399999999,42.75516],"type":"Point"}
}