{
  "type": "Feature",
  "properties": {
    "iso:country":"US",
    "sg:address":"101 W 3rd St",
    "sg:city":"Tipton",
    "sg:classifiers":[
        {
            "category":"Retail",
            "subcategory":"Auto Repair",
            "type":"Services"
        }
    ],
    "sg:phone":"+1 563 886 6184",
    "sg:postcode":"52772",
    "sg:province":"IA",
    "sg:tags":[
        "repairing",
        "automobile"
    ],
    "sg:website":"www.orourkemotorsonline.com",
    "wof:name":"O'Rourke Motors Inc",
    "wof:placetype":"venue"
},
  "geometry": {"coordinates":[-91.128411,41.767904],"type":"Point"}
}