{
  "type": "Feature",
  "properties": {
    "addr:full":"655 20th Ave SW Cedar Rapids IA 52404",
    "addr:housenumber":"655",
    "addr:postcode":"52404",
    "addr:street":"20Th Ave Sw",
    "iso:country":"US",
    "sg:address":"655 20th Ave SW",
    "sg:city":"Cedar Rapids",
    "sg:classifiers":[
        {
            "category":"Manufacturing",
            "subcategory":"Apparel",
            "type":"Manufacturing & Wholesale Goods"
        }
    ],
    "sg:phone":"+1 319 369 0044",
    "sg:postcode":"52404",
    "sg:province":"IA",
    "sg:tags":[
        "business"
    ],
    "wof:name":"Graphix Connection",
    "wof:placetype":"venue"
},
  "geometry": {"coordinates":[-91.67925099999999,41.958619],"type":"Point"}
}