{
  "type": "Feature",
  "properties": {
    "iso:country":"US",
    "sg:address":"507 Euclid Ave",
    "sg:city":"Des Moines",
    "sg:classifiers":[
        {
            "category":"Personal",
            "subcategory":"Beauty Salon",
            "type":"Services"
        }
    ],
    "sg:phone":"+1 515 244 7117",
    "sg:postcode":"50313",
    "sg:province":"IA",
    "wof:name":"Rose Ann's Beauty Salon",
    "wof:placetype":"venue"
},
  "geometry": {"coordinates":[-93.62473,41.627762],"type":"Point"}
}