{
  "type": "Feature",
  "properties": {
    "iso:country":"US",
    "sg:address":"1551 Clayton Ave",
    "sg:city":"Wayland",
    "sg:classifiers":[
        {
            "category":"Farming",
            "subcategory":"Livestock Farm",
            "type":"Manufacturing & Wholesale Goods"
        }
    ],
    "sg:phone":"+1 319 256 4842",
    "sg:postcode":"52654",
    "sg:province":"IA",
    "sg:tags":[
        "hog",
        "or",
        "feedlot"
    ],
    "wof:name":"Doyle Bachman",
    "wof:placetype":"venue"
},
  "geometry": {"coordinates":[-91.678487,41.083087],"type":"Point"}
}