{
  "type": "Feature",
  "properties": {
    "iso:country":"US",
    "sg:address":"1300 W Burlington Ave",
    "sg:city":"Fairfield",
    "sg:classifiers":[
        {
            "category":"Banks & Credit Unions",
            "subcategory":"Bank",
            "type":"Services"
        }
    ],
    "sg:phone":"+1 641 472 6525",
    "sg:postcode":"52556",
    "sg:province":"IA",
    "sg:tags":[
        "depository",
        "banking"
    ],
    "wof:name":"Western Union Fincl Svcs Inc",
    "wof:placetype":"venue"
},
  "geometry": {"coordinates":[-91.97989699999999,41.006368],"type":"Point"}
}