{
  "type": "Feature",
  "properties": {
    "addr:full":"989 Langworthy St Dubuque IA 52001",
    "addr:housenumber":"989",
    "addr:postcode":"52001",
    "addr:street":"Langworthy St",
    "iso:country":"US",
    "sg:address":"989 Langworthy St",
    "sg:city":"Dubuque",
    "sg:classifiers":[
        {
            "category":"Shopping",
            "type":"Retail Goods"
        }
    ],
    "sg:phone":"+1 563 556 0878",
    "sg:postcode":"52001",
    "sg:province":"IA",
    "sg:tags":[
        "hearing",
        "equipment",
        "supply",
        "impaired"
    ],
    "wof:name":"Beltone Hearing Aid Ctr",
    "wof:placetype":"venue"
},
  "geometry": {"coordinates":[-90.674335,42.493371],"type":"Point"}
}