{
  "type": "Feature",
  "properties": {
    "addr:full":"409 N Main St Centerville IA 52544",
    "addr:housenumber":"409",
    "addr:postcode":"52544",
    "addr:street":"N Main St",
    "iso:country":"US",
    "sg:address":"409 N Main St",
    "sg:city":"Centerville",
    "sg:classifiers":[
        {
            "category":"Manufacturing",
            "subcategory":"Printing",
            "type":"Manufacturing & Wholesale Goods"
        }
    ],
    "sg:phone":"+1 641 437 4567",
    "sg:postcode":"52544",
    "sg:province":"IA",
    "sg:tags":[
        "printer"
    ],
    "wof:name":"Star Printing Co",
    "wof:placetype":"venue"
},
  "geometry": {"coordinates":[-92.874123,40.735863],"type":"Point"}
}