{
  "type": "Feature",
  "properties": {
    "iso:country":"US",
    "sg:address":"15722 490th St",
    "sg:city":"Scarville",
    "sg:classifiers":[
        {
            "category":"Place Of Worship",
            "subcategory":"Church",
            "type":"Public Place"
        },
        {
            "category":"Place Of Worship",
            "type":"Public Place"
        }
    ],
    "sg:phone":"+1 641 568 3682",
    "sg:postcode":"50473",
    "sg:province":"IA",
    "sg:tags":[
        "lutheran",
        "america",
        "churches-lutheran",
        "churches-lutheran-evangelical"
    ],
    "wof:name":"Bethel Lutheran Church",
    "wof:placetype":"venue"
},
  "geometry": {"coordinates":[-93.681603,43.473186],"type":"Point"}
}