{
  "type": "Feature",
  "properties": {
    "addr:full":"404 4th St Sergeant Bluff IA 51054",
    "addr:housenumber":"404",
    "addr:postcode":"51054",
    "addr:street":"4Th St",
    "iso:country":"US",
    "sg:address":"404 4th St",
    "sg:city":"Sergeant Bluff",
    "sg:classifiers":[
        {
            "category":"Building & Trades",
            "subcategory":"Plumbing",
            "type":"Services"
        }
    ],
    "sg:phone":"+1 712 943 2410",
    "sg:postcode":"51054",
    "sg:province":"IA",
    "sg:tags":[
        "conditioning",
        "air",
        "system",
        "contractor"
    ],
    "wof:name":"Trucke Heating & Air Cond",
    "wof:placetype":"venue"
},
  "geometry": {"coordinates":[-96.359131,42.403779],"type":"Point"}
}