{
  "type": "Feature",
  "properties": {
    "iso:country":"US",
    "sg:address":"500 Sycamore St",
    "sg:city":"Waterloo",
    "sg:classifiers":[
        {
            "category":"Real Estate",
            "subcategory":"Real Estate Operator",
            "type":"Services"
        }
    ],
    "sg:phone":"+1 319 235 7754",
    "sg:postcode":"50703",
    "sg:province":"IA",
    "sg:tags":[
        "apartment"
    ],
    "wof:name":"Park Tower Apartments",
    "wof:placetype":"venue"
},
  "geometry": {"coordinates":[-92.335898,42.498253],"type":"Point"}
}