{
  "type": "Feature",
  "properties": {
    "iso:country":"US",
    "sg:address":"1905 Erie Ave",
    "sg:city":"Spirit Lake",
    "sg:classifiers":[
        {
            "category":"Manufacturing",
            "subcategory":"Chemicals & Compounds",
            "type":"Manufacturing & Wholesale Goods"
        }
    ],
    "sg:phone":"+1 712 336 2479",
    "sg:postcode":"51360",
    "sg:province":"IA",
    "sg:tags":[
        "agricultural",
        "mfg"
    ],
    "wof:name":"Lon Noble",
    "wof:placetype":"venue"
},
  "geometry": {"coordinates":[-95.097284,43.421681],"type":"Point"}
}