{
  "type": "Feature",
  "properties": {
    "iso:country":"US",
    "sg:address":"2322 Camden Dr",
    "sg:city":"Ames",
    "sg:classifiers":[
        {
            "category":"Banks & Credit Unions",
            "subcategory":"Investment Brokerage",
            "type":"Services"
        }
    ],
    "sg:phone":"+1 515 292 3174",
    "sg:postcode":"50010",
    "sg:province":"IA",
    "sg:tags":[
        "advisory"
    ],
    "wof:name":"Bakley Capital Management",
    "wof:placetype":"venue"
},
  "geometry": {"coordinates":[-93.638509,42.045898],"type":"Point"}
}