{
  "type": "Feature",
  "properties": {
    "iso:country":"US",
    "sg:address":"800 7th St SE",
    "sg:city":"Cedar Rapids",
    "sg:classifiers":[
        {
            "category":"Professional",
            "subcategory":"Employment Agencies",
            "type":"Services"
        }
    ],
    "sg:phone":"+1 319 366 0258",
    "sg:postcode":"52401",
    "sg:province":"IA",
    "wof:name":"Aarp Senior Employment",
    "wof:placetype":"venue"
},
  "geometry": {"coordinates":[-91.656972,41.976115],"type":"Point"}
}