{
  "type": "Feature",
  "properties": {
    "addr:full":"610 Salem Ave Orange City IA 51041",
    "addr:housenumber":"610",
    "addr:postcode":"51041",
    "addr:street":"Salem Ave",
    "iso:country":"US",
    "sg:address":"610 Salem Ave",
    "sg:city":"Orange City",
    "sg:classifiers":[
        {
            "category":"Manufacturing",
            "subcategory":"Glass & Minerals",
            "type":"Manufacturing & Wholesale Goods"
        }
    ],
    "sg:phone":"+1 712 737 4878",
    "sg:postcode":"51041",
    "sg:province":"IA",
    "sg:tags":[
        "concrete",
        "brick",
        "prod",
        "block"
    ],
    "wof:name":"Russell's Pre Cast",
    "wof:placetype":"venue"
},
  "geometry": {"coordinates":[-96.04042099999999,42.998798],"type":"Point"}
}