{
  "type": "Feature",
  "properties": {
    "addr:full":"104 N Otto St Maquoketa IA 52060",
    "addr:housenumber":"104",
    "addr:postcode":"52060",
    "addr:street":"N Otto St",
    "iso:country":"US",
    "sg:address":"104 N Otto St",
    "sg:city":"Maquoketa",
    "sg:classifiers":[
        {
            "category":"Building & Trades",
            "subcategory":"Construction",
            "type":"Services"
        }
    ],
    "sg:phone":"+1 563 652 2742",
    "sg:postcode":"52060",
    "sg:province":"IA",
    "sg:tags":[
        "general",
        "contractor"
    ],
    "wof:name":"G L Stockham & Son Inc",
    "wof:placetype":"venue"
},
  "geometry": {"coordinates":[-90.6619,42.070859],"type":"Point"}
}