{
  "type": "Feature",
  "properties": {
    "addr:full":"2885 John F Kennedy Rd Dubuque IA 52002",
    "addr:housenumber":"2885",
    "addr:postcode":"52002",
    "addr:street":"John F Kennedy Rd",
    "iso:country":"US",
    "sg:address":"2885 John F Kennedy Rd",
    "sg:city":"Dubuque",
    "sg:classifiers":[
        {
            "category":"Organizations",
            "subcategory":"Religious Organization",
            "type":"Services"
        }
    ],
    "sg:phone":"+1 563 582 5661",
    "sg:postcode":"52002",
    "sg:province":"IA",
    "sg:tags":[
        "church"
    ],
    "wof:name":"Summit Congregational Church",
    "wof:placetype":"venue"
},
  "geometry": {"coordinates":[-90.72120700000001,42.499773],"type":"Point"}
}