{
  "type": "Feature",
  "properties": {
    "iso:country":"US",
    "sg:address":"210 E 5th St",
    "sg:city":"Carroll",
    "sg:classifiers":[
        {
            "category":"Building & Trades",
            "subcategory":"Plumbing",
            "type":"Services"
        }
    ],
    "sg:phone":"+1 712 792 4779",
    "sg:postcode":"51401",
    "sg:province":"IA",
    "sg:tags":[
        "heating",
        "contractor"
    ],
    "wof:name":"Middendorf Sheet Metal Inc",
    "wof:placetype":"venue"
},
  "geometry": {"coordinates":[-94.86620600000001,42.064083],"type":"Point"}
}