{
  "type": "Feature",
  "properties": {
    "iso:country":"US",
    "sg:address":"1389 State Hwy 48",
    "sg:city":"Essex",
    "sg:classifiers":[
        {
            "category":"Farming",
            "subcategory":"Farm",
            "type":"Manufacturing & Wholesale Goods"
        }
    ],
    "sg:phone":"+1 712 379 3814",
    "sg:postcode":"51638",
    "sg:province":"IA",
    "sg:tags":[
        "crop",
        "general"
    ],
    "wof:name":"Dwight W & Judith K Lundgren",
    "wof:placetype":"venue"
},
  "geometry": {"coordinates":[-95.232848,40.845776],"type":"Point"}
}