{
  "type": "Feature",
  "properties": {
    "iso:country":"US",
    "sg:address":"722 Main St",
    "sg:city":"Osage",
    "sg:classifiers":[
        {
            "category":"Retail",
            "subcategory":"Repair Shop",
            "type":"Services"
        },
        {
            "category":"Shopping",
            "type":"Retail Goods"
        }
    ],
    "sg:phone":"+1 641 732 1336",
    "sg:postcode":"50461",
    "sg:province":"IA",
    "sg:tags":[
        "picture",
        "art",
        "gallery",
        "custom",
        "framing",
        "dealer"
    ],
    "wof:name":"Tomorrow's Treasures",
    "wof:placetype":"venue"
},
  "geometry": {"coordinates":[-92.810756,43.284018],"type":"Point"}
}