{
  "type": "Feature",
  "properties": {
    "iso:country":"US",
    "sg:address":"3381 S 42nd St",
    "sg:city":"Cumming",
    "sg:classifiers":[
        {
            "category":"Building & Trades",
            "subcategory":"Construction",
            "type":"Services"
        }
    ],
    "sg:phone":"+1 515 285 4649",
    "sg:postcode":"50061",
    "sg:province":"IA",
    "sg:tags":[
        "marking",
        "maintenance",
        "parking"
    ],
    "wof:name":"Speck Enterprises",
    "wof:placetype":"venue"
},
  "geometry": {"coordinates":[-93.76148000000001,41.522886],"type":"Point"}
}