{
  "type": "Feature",
  "properties": {
    "iso:country":"US",
    "sg:address":"852 Middle Rd",
    "sg:city":"Bettendorf",
    "sg:classifiers":[
        {
            "category":"Organizations",
            "subcategory":"Religious Organization",
            "type":"Services"
        }
    ],
    "sg:phone":"+1 563 441 9888",
    "sg:postcode":"52722",
    "sg:province":"IA",
    "sg:tags":[
        "church"
    ],
    "wof:name":"Rock Church Of The Quad Cities",
    "wof:placetype":"venue"
},
  "geometry": {"coordinates":[-90.520805,41.538747],"type":"Point"}
}