{
  "type": "Feature",
  "properties": {
    "addr:full":"1520 Jersey Ave Rudd IA 50471",
    "addr:housenumber":"1520",
    "addr:postcode":"50471",
    "addr:street":"Jersey Ave",
    "iso:country":"US",
    "sg:address":"1520 Jersey Ave",
    "sg:city":"Rudd",
    "sg:classifiers":[
        {
            "category":"Home & Garden",
            "subcategory":"Building Materials",
            "type":"Retail Goods"
        }
    ],
    "sg:phone":"+1 641 395 2681",
    "sg:postcode":"50471",
    "sg:province":"IA",
    "wof:name":"Clay Things",
    "wof:placetype":"venue"
},
  "geometry": {"coordinates":[-92.849547,43.129837],"type":"Point"}
}