{
  "type": "Feature",
  "properties": {
    "iso:country":"US",
    "sg:address":"1336 Meadowview Ln",
    "sg:city":"Davenport",
    "sg:classifiers":[
        {
            "category":"Professional",
            "subcategory":"Business Services",
            "type":"Services"
        }
    ],
    "sg:phone":"+1 563 386 8977",
    "sg:postcode":"52806",
    "sg:province":"IA",
    "wof:name":"Linberg Interiors",
    "wof:placetype":"venue"
},
  "geometry": {"coordinates":[-90.591154,41.583186],"type":"Point"}
}