{
  "type": "Feature",
  "properties": {
    "iso:country":"US",
    "sg:address":"1900 Ingersoll Ave",
    "sg:city":"Des Moines",
    "sg:classifiers":[
        {
            "category":"Shopping",
            "type":"Retail Goods"
        }
    ],
    "sg:phone":"+1 515 243 1443",
    "sg:postcode":"50309",
    "sg:province":"IA",
    "sg:tags":[
        "orthopedic",
        "appliance"
    ],
    "wof:name":"Spectrum Prosthetics",
    "wof:placetype":"venue"
},
  "geometry": {"coordinates":[-93.644797,41.585732],"type":"Point"}
}