{
  "type": "Feature",
  "properties": {
    "iso:country":"US",
    "sg:address":"212 Trilby St",
    "sg:city":"Olin",
    "sg:classifiers":[
        {
            "category":"Education",
            "subcategory":"School",
            "type":"Public Place"
        }
    ],
    "sg:phone":"+1 319 484 2155",
    "sg:postcode":"52320",
    "sg:province":"IA",
    "sg:website":"www.olin.k12.ia.us",
    "wof:name":"Olin School Superintendent",
    "wof:placetype":"venue"
},
  "geometry": {"coordinates":[-91.139934,41.99496],"type":"Point"}
}