{
  "type": "Feature",
  "properties": {
    "addr:full":"5929 Ashworth Rd West Des Moines IA 50266",
    "addr:housenumber":"5929",
    "addr:postcode":"50266",
    "addr:street":"Ashworth Rd",
    "iso:country":"US",
    "sg:address":"5929 Ashworth Rd",
    "sg:city":"West Des Moines",
    "sg:classifiers":[
        {
            "category":"Utilities",
            "subcategory":"Mobile Phone",
            "type":"Services"
        }
    ],
    "sg:phone":"+1 515 277 5550",
    "sg:postcode":"50266",
    "sg:province":"IA",
    "sg:tags":[
        "telephone",
        "cellular"
    ],
    "wof:name":"Xveon Wirless",
    "wof:placetype":"venue"
},
  "geometry": {"coordinates":[-93.78725799999999,41.584436],"type":"Point"}
}