{
  "type": "Feature",
  "properties": {
    "iso:country":"US",
    "sg:address":"408 4th St",
    "sg:city":"Sergeant Bluff",
    "sg:classifiers":[
        {
            "category":"Shopping",
            "subcategory":"Discount & Variety Stores",
            "type":"Retail Goods"
        }
    ],
    "sg:phone":"+1 712 943 5777",
    "sg:postcode":"51054",
    "sg:province":"IA",
    "wof:name":"Helle Hometown Variety Store",
    "wof:placetype":"venue"
},
  "geometry": {"coordinates":[-96.35917499999999,42.403778],"type":"Point"}
}