{
  "type": "Feature",
  "properties": {
    "iso:country":"US",
    "sg:address":"3206 Timber Valley Ct NE",
    "sg:city":"Cedar Rapids",
    "sg:classifiers":[
        {
            "category":"Real Estate",
            "subcategory":"Architect",
            "type":"Services"
        }
    ],
    "sg:phone":"+1 319 393 4755",
    "sg:postcode":"52402",
    "sg:province":"IA",
    "sg:tags":[
        "architectural"
    ],
    "wof:name":"Cottage Design",
    "wof:placetype":"venue"
},
  "geometry": {"coordinates":[-91.670789,42.013017],"type":"Point"}
}