{
  "type": "Feature",
  "properties": {
    "addr:full":"320 Laurie Cir Neola IA 51559",
    "addr:housenumber":"320",
    "addr:postcode":"51559",
    "addr:street":"Laurie Cir",
    "iso:country":"US",
    "sg:address":"320 Laurie Cir",
    "sg:city":"Neola",
    "sg:classifiers":[
        {
            "category":"Shopping",
            "type":"Retail Goods"
        }
    ],
    "sg:phone":"+1 712 485 2147",
    "sg:postcode":"51559",
    "sg:province":"IA",
    "sg:tags":[
        "cosmetic",
        "perfume"
    ],
    "wof:name":"Beauti Control",
    "wof:placetype":"venue"
},
  "geometry": {"coordinates":[-95.620171,41.456335],"type":"Point"}
}