{
  "type": "Feature",
  "properties": {
    "iso:country":"US",
    "sg:address":"204 S 2nd St",
    "sg:city":"Albia",
    "sg:classifiers":[
        {
            "category":"Organizations",
            "subcategory":"Religious Organization",
            "type":"Services"
        }
    ],
    "sg:phone":"+1 641 932 5516",
    "sg:postcode":"52531",
    "sg:province":"IA",
    "wof:name":"Albia Baptist Temple",
    "wof:placetype":"venue"
},
  "geometry": {"coordinates":[-92.80575,41.02519],"type":"Point"}
}