{
  "type": "Feature",
  "properties": {
    "iso:country":"US",
    "sg:address":"22955 Old Hwy 169",
    "sg:city":"Fort Dodge",
    "sg:classifiers":[
        {
            "category":"Retail",
            "subcategory":"Veterinary Services",
            "type":"Services"
        }
    ],
    "sg:phone":"+1 515 955 8591",
    "sg:postcode":"50501",
    "sg:province":"IA",
    "sg:tags":[
        "hospital",
        "animal"
    ],
    "wof:name":"Town & Country Veterinary Ctr",
    "wof:placetype":"venue"
},
  "geometry": {"coordinates":[-94.194091,42.456953],"type":"Point"}
}