{
  "type": "Feature",
  "properties": {
    "addr:full":"802 S Center St Marshalltown IA 50158",
    "addr:housenumber":"802",
    "addr:postcode":"50158",
    "addr:street":"S Center St",
    "iso:country":"US",
    "sg:address":"802 S Center St",
    "sg:city":"Marshalltown",
    "sg:classifiers":[
        {
            "category":"Banks & Credit Unions",
            "subcategory":"Bank",
            "type":"Services"
        }
    ],
    "sg:phone":"+1 641 752 4959",
    "sg:postcode":"50158",
    "sg:province":"IA",
    "wof:name":"Commercial Federal Bank",
    "wof:placetype":"venue"
},
  "geometry": {"coordinates":[-92.91270400000001,42.039224],"type":"Point"}
}