{
  "type": "Feature",
  "properties": {
    "addr:full":"1751 US Hwy 30 Carroll IA 51401",
    "addr:housenumber":"1751",
    "addr:postcode":"51401",
    "addr:street":"Us Hwy 30",
    "iso:country":"US",
    "sg:address":"1751 US Hwy 30",
    "sg:city":"Carroll",
    "sg:classifiers":[
        {
            "category":"Wholesale",
            "subcategory":"Groceries",
            "type":"Manufacturing & Wholesale Goods"
        }
    ],
    "sg:phone":"+1 712 792 3503",
    "sg:postcode":"51401",
    "sg:province":"IA",
    "sg:tags":[
        "food",
        "broker"
    ],
    "sg:website":"www.farner-bocken.com",
    "wof:name":"Farner-Bocken Co",
    "wof:placetype":"venue"
},
  "geometry": {"coordinates":[-94.946613,42.078733],"type":"Point"}
}