{
  "type": "Feature",
  "properties": {
    "iso:country":"US",
    "sg:address":"2530 Donna Reed Rd",
    "sg:city":"Denison",
    "sg:classifiers":[
        {
            "category":"Shopping",
            "type":"Retail Goods"
        }
    ],
    "sg:phone":"+1 712 263 5897",
    "sg:postcode":"51442",
    "sg:province":"IA",
    "sg:tags":[
        "livestock",
        "supply"
    ],
    "wof:name":"Livestock Supply",
    "wof:placetype":"venue"
},
  "geometry": {"coordinates":[-95.32297,41.9917],"type":"Point"}
}