{
  "type": "Feature",
  "properties": {
    "iso:country":"US",
    "sg:address":"110 N 1st Ave",
    "sg:city":"Winterset",
    "sg:classifiers":[
        {
            "category":"Professional",
            "subcategory":"Management & Consulting",
            "type":"Services"
        }
    ],
    "sg:phone":"+1 515 462 9165",
    "sg:postcode":"50273",
    "sg:province":"IA",
    "sg:tags":[
        "personnel",
        "consultant"
    ],
    "wof:name":"Professional Resources Inc",
    "wof:placetype":"venue"
},
  "geometry": {"coordinates":[-94.014616,41.334859],"type":"Point"}
}