{
  "type": "Feature",
  "properties": {
    "iso:country":"US",
    "sg:address":"2454 Cumming Rd",
    "sg:city":"Winterset",
    "sg:phone":"+1 515 462 4486",
    "sg:postcode":"50273",
    "sg:province":"IA",
    "sg:tags":[
        "farm",
        "corn",
        "soybean"
    ],
    "wof:name":"Gregory Bass Farm",
    "wof:placetype":"venue"
},
  "geometry": {"coordinates":[-93.957347,41.402019],"type":"Point"}
}