{
  "type": "Feature",
  "properties": {
    "addr:full":"2250 A St SW Cedar Rapids IA 52404",
    "addr:housenumber":"2250",
    "addr:postcode":"52404",
    "addr:street":"A St Sw",
    "iso:country":"US",
    "sg:address":"2250 A St SW",
    "sg:city":"Cedar Rapids",
    "sg:classifiers":[
        {
            "category":"Government",
            "subcategory":"Office",
            "type":"Public Place"
        }
    ],
    "sg:phone":"+1 319 398 5160",
    "sg:postcode":"52404",
    "sg:province":"IA",
    "sg:tags":[
        "city",
        "program"
    ],
    "wof:name":"Bluestem Solid Waste Agency",
    "wof:placetype":"venue"
},
  "geometry": {"coordinates":[-91.652816,41.963968],"type":"Point"}
}