{
  "type": "Feature",
  "properties": {
    "iso:country":"US",
    "sg:address":"8170 Hickman Rd",
    "sg:city":"Clive",
    "sg:classifiers":[
        {
            "category":"Professional",
            "subcategory":"Advertising",
            "type":"Services"
        }
    ],
    "sg:phone":"+1 515 727 8774",
    "sg:postcode":"50325",
    "sg:province":"IA",
    "sg:website":"www.primarysourcepromotion.com",
    "wof:name":"Primary Source LTD",
    "wof:placetype":"venue"
},
  "geometry": {"coordinates":[-93.729839,41.614687],"type":"Point"}
}