{
  "type": "Feature",
  "properties": {
    "iso:country":"US",
    "sg:address":"280 Ashworth Dr",
    "sg:city":"Waukee",
    "sg:classifiers":[
        {
            "category":"Health Services",
            "subcategory":"Chiropractor",
            "type":"Services"
        }
    ],
    "sg:phone":"+1 515 987 4541",
    "sg:postcode":"50263",
    "sg:province":"IA",
    "wof:name":"Brockman Chiropractic Office",
    "wof:placetype":"venue"
},
  "geometry": {"coordinates":[-93.88113,41.609906],"type":"Point"}
}