{
  "type": "Feature",
  "properties": {
    "iso:country":"US",
    "sg:address":"501 N Grand St",
    "sg:city":"Chariton",
    "sg:classifiers":[
        {
            "category":"Education",
            "subcategory":"School",
            "type":"Public Place"
        }
    ],
    "sg:phone":"+1 641 774 5066",
    "sg:postcode":"50049",
    "sg:province":"IA",
    "wof:name":"Chariton High School",
    "wof:placetype":"venue"
},
  "geometry": {"coordinates":[-93.306859,41.019369],"type":"Point"}
}