{
  "type": "Feature",
  "properties": {
    "iso:country":"US",
    "sg:address":"4521 F St",
    "sg:city":"Amana",
    "sg:classifiers":[
        {
            "category":"Retail",
            "subcategory":"Animal Services",
            "type":"Services"
        }
    ],
    "sg:phone":"+1 319 622 3087",
    "sg:postcode":"52203",
    "sg:province":"IA",
    "wof:name":"Blossom Hill Pet Suites",
    "wof:placetype":"venue"
},
  "geometry": {"coordinates":[-91.869995,41.801623],"type":"Point"}
}