{
  "type": "Feature",
  "properties": {
    "addr:full":"304 Sugar Creek Cir Perry IA 50220",
    "addr:housenumber":"304",
    "addr:postcode":"50220",
    "addr:street":"Sugar Creek Cir",
    "iso:country":"US",
    "sg:address":"304 Sugar Creek Cir",
    "sg:city":"Perry",
    "sg:classifiers":[
        {
            "category":"Real Estate",
            "subcategory":"Real Estate Operator",
            "type":"Services"
        }
    ],
    "sg:phone":"+1 515 465 2838",
    "sg:postcode":"50220",
    "sg:province":"IA",
    "sg:tags":[
        "property",
        "lessor"
    ],
    "wof:name":"Dean Blougher",
    "wof:placetype":"venue"
},
  "geometry": {"coordinates":[-94.095505,41.830631],"type":"Point"}
}