{
  "type": "Feature",
  "properties": {
    "iso:country":"US",
    "sg:address":"118 E 4th St",
    "sg:city":"Vinton",
    "sg:classifiers":[
        {
            "category":"Health Services",
            "subcategory":"Doctor",
            "type":"Services"
        }
    ],
    "sg:phone":"+1 319 472 5209",
    "sg:postcode":"52349",
    "sg:province":"IA",
    "sg:tags":[
        "dentist"
    ],
    "wof:name":"Family Dentistry",
    "wof:placetype":"venue"
},
  "geometry": {"coordinates":[-92.024102,42.167618],"type":"Point"}
}