{
  "type": "Feature",
  "properties": {
    "iso:country":"US",
    "sg:address":"307 N L St",
    "sg:city":"Oskaloosa",
    "sg:classifiers":[
        {
            "category":"Retail",
            "subcategory":"Auto Repair",
            "type":"Services"
        }
    ],
    "sg:phone":"+1 641 672 9104",
    "sg:postcode":"52577",
    "sg:province":"IA",
    "sg:tags":[
        "body",
        "automobile",
        "painting"
    ],
    "wof:name":"Darrell's Auto Ctr",
    "wof:placetype":"venue"
},
  "geometry": {"coordinates":[-92.659246,41.298399],"type":"Point"}
}