{
  "type": "Feature",
  "properties": {
    "addr:full":"24673 540th St Pocahontas IA 50574",
    "addr:housenumber":"24673",
    "addr:postcode":"50574",
    "addr:street":"540Th St",
    "iso:country":"US",
    "sg:address":"24673 540th St",
    "sg:city":"Pocahontas",
    "sg:classifiers":[
        {
            "category":"Farming",
            "subcategory":"Dairy Farm",
            "type":"Manufacturing & Wholesale Goods"
        }
    ],
    "sg:phone":"+1 712 335 3124",
    "sg:postcode":"50574",
    "sg:province":"IA",
    "sg:tags":[
        "corn",
        "soybean"
    ],
    "wof:name":"Steven Schott",
    "wof:placetype":"venue"
},
  "geometry": {"coordinates":[-94.636636,42.703099],"type":"Point"}
}