{
  "type": "Feature",
  "properties": {
    "iso:country":"US",
    "sg:address":"5265 State Hwy 9",
    "sg:city":"Sibley",
    "sg:phone":"+1 712 754 3117",
    "sg:postcode":"51249",
    "sg:province":"IA",
    "sg:tags":[
        "farm",
        "corn",
        "soybean"
    ],
    "wof:name":"Ernest Gradert",
    "wof:placetype":"venue"
},
  "geometry": {"coordinates":[-95.748645,43.432693],"type":"Point"}
}