{
  "type": "Feature",
  "properties": {
    "iso:country":"US",
    "sg:address":"22215 US Hwy 65",
    "sg:city":"Colo",
    "sg:classifiers":[
        {
            "category":"Manufacturing",
            "subcategory":"Tools & Machinery",
            "type":"Manufacturing & Wholesale Goods"
        }
    ],
    "sg:phone":"+1 641 377 2865",
    "sg:postcode":"50056",
    "sg:province":"IA",
    "sg:tags":[
        "machine",
        "shop"
    ],
    "wof:name":"Cady Machine Co",
    "wof:placetype":"venue"
},
  "geometry": {"coordinates":[-93.309544,42.031802],"type":"Point"}
}