{
  "type": "Feature",
  "properties": {
    "iso:country":"US",
    "sg:address":"611 N Main St",
    "sg:city":"Goldfield",
    "sg:classifiers":[
        {
            "category":"Shopping",
            "type":"Retail Goods"
        }
    ],
    "sg:phone":"+1 515 825 3400",
    "sg:postcode":"50542",
    "sg:province":"IA",
    "sg:tags":[
        "equipment",
        "telephone",
        "supply"
    ],
    "sg:website":"www.goldtelecom.com",
    "wof:name":"Goldfield Telecom LC",
    "wof:placetype":"venue"
},
  "geometry": {"coordinates":[-93.920452,42.737146],"type":"Point"}
}