{
  "type": "Feature",
  "properties": {
    "addr:full":"204 Jepsen Rd Cedar Falls IA 50613",
    "addr:housenumber":"204",
    "addr:postcode":"50613",
    "addr:street":"Jepsen Rd",
    "iso:country":"US",
    "sg:address":"204 Jepsen Rd",
    "sg:city":"Cedar Falls",
    "sg:classifiers":[
        {
            "category":"Farming",
            "subcategory":"Farm",
            "type":"Manufacturing & Wholesale Goods"
        }
    ],
    "sg:phone":"+1 319 266 7982",
    "sg:postcode":"50613",
    "sg:province":"IA",
    "sg:tags":[
        "corn",
        "soybean"
    ],
    "wof:name":"Isley Farms Inc",
    "wof:placetype":"venue"
},
  "geometry": {"coordinates":[-92.524423,42.514948],"type":"Point"}
}