{
  "type": "Feature",
  "properties": {
    "iso:country":"US",
    "sg:address":"407 Main St",
    "sg:city":"Sanborn",
    "sg:classifiers":[
        {
            "category":"Education",
            "subcategory":"Library",
            "type":"Public Place"
        }
    ],
    "sg:phone":"+1 712 930 3215",
    "sg:postcode":"51248",
    "sg:province":"IA",
    "wof:name":"Sanborn Public Library",
    "wof:placetype":"venue"
},
  "geometry": {"coordinates":[-95.65586999999999,43.184026],"type":"Point"}
}