{
  "type": "Feature",
  "properties": {
    "iso:country":"US",
    "sg:address":"3281 100th St",
    "sg:city":"Urbandale",
    "sg:classifiers":[
        {
            "category":"Restaurant",
            "type":"Food & Drink"
        }
    ],
    "sg:phone":"+1 515 727 4408",
    "sg:postcode":"50322",
    "sg:province":"IA",
    "sg:website":"www.stellasblueskydiner.com",
    "wof:name":"Stella's Blue Sky Diner",
    "wof:placetype":"venue"
},
  "geometry": {"coordinates":[-93.75577800000001,41.625545],"type":"Point"}
}