{
  "type": "Feature",
  "properties": {
    "iso:country":"US",
    "sg:address":"782 Old Stage Rd",
    "sg:city":"Postville",
    "sg:classifiers":[
        {
            "category":"Wholesale",
            "subcategory":"Machinery & Supplies",
            "type":"Manufacturing & Wholesale Goods"
        }
    ],
    "sg:phone":"+1 563 864 3962",
    "sg:postcode":"52162",
    "sg:province":"IA",
    "sg:tags":[
        "equipment",
        "dairy"
    ],
    "wof:name":"Lyle's Dairy Grooming",
    "wof:placetype":"venue"
},
  "geometry": {"coordinates":[-91.527985,43.176703],"type":"Point"}
}