{
  "type": "Feature",
  "properties": {
    "addr:full":"54047 115th St Story City IA 50248",
    "addr:housenumber":"54047",
    "addr:postcode":"50248",
    "addr:street":"115Th St",
    "iso:country":"US",
    "sg:address":"54047 115th St",
    "sg:city":"Story City",
    "sg:classifiers":[
        {
            "category":"Retail",
            "subcategory":"Repair Shop",
            "type":"Services"
        }
    ],
    "sg:phone":"+1 515 733 2701",
    "sg:postcode":"50248",
    "sg:province":"IA",
    "sg:tags":[
        "welding"
    ],
    "wof:name":"T N't Welding & Fabrication",
    "wof:placetype":"venue"
},
  "geometry": {"coordinates":[-93.61949300000001,42.187457],"type":"Point"}
}