{
  "type": "Feature",
  "properties": {
    "iso:country":"US",
    "sg:address":"32864 300th St",
    "sg:city":"Milton",
    "sg:classifiers":[
        {
            "category":"Food & Beverages",
            "subcategory":"Dairy",
            "type":"Retail Goods"
        }
    ],
    "sg:phone":"+1 641 656 4930",
    "sg:postcode":"52570",
    "sg:province":"IA",
    "sg:tags":[
        "product"
    ],
    "wof:name":"Moore Milk Inc",
    "wof:placetype":"venue"
},
  "geometry": {"coordinates":[-92.20321800000001,40.624589],"type":"Point"}
}