{
  "type": "Feature",
  "properties": {
    "iso:country":"US",
    "sg:address":"701 Steuben St",
    "sg:city":"Sioux City",
    "sg:classifiers":[
        {
            "category":"Social Services",
            "type":"Services"
        }
    ],
    "sg:phone":"+1 712 255 3551",
    "sg:postcode":"51101",
    "sg:province":"IA",
    "sg:tags":[
        "organization",
        "welfare"
    ],
    "sg:website":"www.unitedwaysiouxland.com",
    "wof:name":"United Way Of Siouxland",
    "wof:placetype":"venue"
},
  "geometry": {"coordinates":[-96.38885999999999,42.498498],"type":"Point"}
}