{
  "type": "Feature",
  "properties": {
    "addr:full":"4785 C Ave Marcus IA 51035",
    "addr:housenumber":"4785",
    "addr:postcode":"51035",
    "addr:street":"C Ave",
    "iso:country":"US",
    "sg:address":"4785 C Ave",
    "sg:city":"Marcus",
    "sg:classifiers":[
        {
            "category":"Retail",
            "subcategory":"Auto Repair",
            "type":"Services"
        }
    ],
    "sg:phone":"+1 712 376 2656",
    "sg:postcode":"51035",
    "sg:province":"IA",
    "sg:tags":[
        "repairing",
        "automobile"
    ],
    "wof:name":"Olson Garage",
    "wof:placetype":"venue"
},
  "geometry": {"coordinates":[-95.819137,42.824441],"type":"Point"}
}