{
  "type": "Feature",
  "properties": {
    "iso:country":"US",
    "sg:address":"514 S 13th St",
    "sg:city":"Fort Dodge",
    "sg:classifiers":[
        {
            "category":"Building & Trades",
            "subcategory":"Construction",
            "type":"Services"
        }
    ],
    "sg:phone":"+1 515 955 1493",
    "sg:postcode":"50501",
    "sg:province":"IA",
    "sg:tags":[
        "stone",
        "pointing"
    ],
    "wof:name":"Nikolangelo",
    "wof:placetype":"venue"
},
  "geometry": {"coordinates":[-94.181054,42.500241],"type":"Point"}
}