{
  "type": "Feature",
  "properties": {
    "addr:full":"1811 Vail Ave Muscatine IA 52761",
    "addr:housenumber":"1811",
    "addr:postcode":"52761",
    "addr:street":"Vail Ave",
    "iso:country":"US",
    "sg:address":"1811 Vail Ave",
    "sg:city":"Muscatine",
    "sg:classifiers":[
        {
            "category":"Professional",
            "subcategory":"Detective & Security Services",
            "type":"Services"
        }
    ],
    "sg:phone":"+1 563 262 3938",
    "sg:postcode":"52761",
    "sg:province":"IA",
    "sg:tags":[
        "investigator"
    ],
    "wof:name":"Loss Prevention & Invstgtv",
    "wof:placetype":"venue"
},
  "geometry": {"coordinates":[-90.90128799999999,41.478128],"type":"Point"}
}