{
  "type": "Feature",
  "properties": {
    "iso:country":"US",
    "sg:address":"505 Hilltop St",
    "sg:city":"Lynnville",
    "sg:classifiers":[
        {
            "category":"Wholesale",
            "subcategory":"Farm Supplies",
            "type":"Manufacturing & Wholesale Goods"
        }
    ],
    "sg:phone":"+1 641 527 2400",
    "sg:postcode":"50153",
    "sg:province":"IA",
    "sg:tags":[
        "feed"
    ],
    "wof:name":"Renaud Feed Ctr Inc",
    "wof:placetype":"venue"
},
  "geometry": {"coordinates":[-92.787978,41.576785],"type":"Point"}
}