{
  "type": "Feature",
  "properties": {
    "addr:full":"3010 S Center St Marshalltown IA 50158",
    "addr:housenumber":"3010",
    "addr:postcode":"50158",
    "addr:street":"S Center St",
    "iso:country":"US",
    "sg:address":"3010 S Center St",
    "sg:city":"Marshalltown",
    "sg:classifiers":[
        {
            "category":"Restaurant",
            "type":"Food & Drink"
        }
    ],
    "sg:menulink":"http://www.allmenus.com/ia/timber-creek/180895-wendys/menu/",
    "sg:phone":"+1 641 753 5333",
    "sg:postcode":"50158",
    "sg:province":"IA",
    "sg:tags":[
        "burger",
        "american",
        "soup"
    ],
    "wof:name":"Wendy's",
    "wof:placetype":"venue"
},
  "geometry": {"coordinates":[-92.912385,42.011413],"type":"Point"}
}