{
  "type": "Feature",
  "properties": {
    "iso:country":"US",
    "sg:address":"412 Willets Dr",
    "sg:city":"Knoxville",
    "sg:classifiers":[
        {
            "category":"Government",
            "subcategory":"Office",
            "type":"Public Place"
        }
    ],
    "sg:phone":"+1 641 828 2229",
    "sg:postcode":"50138",
    "sg:province":"IA",
    "wof:name":"County Shop",
    "wof:placetype":"venue"
},
  "geometry": {"coordinates":[-93.11913300000001,41.317437],"type":"Point"}
}