{
  "type": "Feature",
  "properties": {
    "addr:full":"103 Maple St Mondamin IA 51557",
    "addr:housenumber":"103",
    "addr:postcode":"51557",
    "addr:street":"Maple St",
    "iso:country":"US",
    "sg:address":"103 Maple St",
    "sg:city":"Mondamin",
    "sg:classifiers":[
        {
            "category":"Banks & Credit Unions",
            "subcategory":"Bank",
            "type":"Services"
        }
    ],
    "sg:phone":"+1 712 646 2421",
    "sg:postcode":"51557",
    "sg:province":"IA",
    "wof:name":"Midstates Bank",
    "wof:placetype":"venue"
},
  "geometry": {"coordinates":[-96.02338899999999,41.710439],"type":"Point"}
}