{
  "type": "Feature",
  "properties": {
    "iso:country":"US",
    "sg:address":"323 3rd St N",
    "sg:city":"Swea City",
    "sg:classifiers":[
        {
            "category":"Shopping",
            "subcategory":"Pharmacy",
            "type":"Retail Goods"
        }
    ],
    "sg:phone":"+1 515 272 4261",
    "sg:postcode":"50590",
    "sg:province":"IA",
    "wof:name":"Van Norman Pharmacy",
    "wof:placetype":"venue"
},
  "geometry": {"coordinates":[-94.309951,43.384778],"type":"Point"}
}