{
  "type": "Feature",
  "properties": {
    "iso:country":"US",
    "sg:address":"1400 Big Lake Rd",
    "sg:city":"Council Bluffs",
    "sg:classifiers":[
        {
            "category":"Banks & Credit Unions",
            "subcategory":"Bank",
            "type":"Services"
        }
    ],
    "sg:phone":"+1 712 242 0089",
    "sg:postcode":"51501",
    "sg:province":"IA",
    "wof:name":"Omaha Police Fed Credit Union",
    "wof:placetype":"venue"
},
  "geometry": {"coordinates":[-95.858884,41.289312],"type":"Point"}
}