{
  "type": "Feature",
  "properties": {
    "iso:country":"US",
    "sg:address":"14 W 21st St",
    "sg:city":"Spencer",
    "sg:classifiers":[
        {
            "category":"Insurance",
            "subcategory":"Insurance Agent",
            "type":"Services"
        }
    ],
    "sg:phone":"+1 712 262 3188",
    "sg:postcode":"51301",
    "sg:province":"IA",
    "sg:tags":[
        "adjuster"
    ],
    "wof:name":"North Central Adjustment Co",
    "wof:placetype":"venue"
},
  "geometry": {"coordinates":[-95.14588000000001,43.158879],"type":"Point"}
}