{
  "type": "Feature",
  "properties": {
    "iso:country":"US",
    "sg:address":"107 Indian Ave",
    "sg:city":"Forest City",
    "sg:classifiers":[
        {
            "category":"Social Services",
            "subcategory":"Child Care",
            "type":"Services"
        }
    ],
    "sg:phone":"+1 641 585 2239",
    "sg:postcode":"50436",
    "sg:province":"IA",
    "sg:tags":[
        "day"
    ],
    "wof:name":"Joanns Daycare",
    "wof:placetype":"venue"
},
  "geometry": {"coordinates":[-93.652745,43.256046],"type":"Point"}
}