{
  "type": "Feature",
  "properties": {
    "iso:country":"US",
    "sg:address":"1795 Loras Blvd",
    "sg:city":"Dubuque",
    "sg:classifiers":[
        {
            "category":"Recreation",
            "type":"Entertainment"
        }
    ],
    "sg:phone":"+1 563 583 4522",
    "sg:postcode":"52001",
    "sg:province":"IA",
    "sg:tags":[
        "tennis",
        "court"
    ],
    "wof:name":"Dubuque Tennis Assn",
    "wof:placetype":"venue"
},
  "geometry": {"coordinates":[-90.68977099999999,42.500135],"type":"Point"}
}