{
  "type": "Feature",
  "properties": {
    "iso:country":"US",
    "sg:address":"1565 330th St",
    "sg:city":"Ryan",
    "sg:phone":"+1 563 932 2278",
    "sg:postcode":"52330",
    "sg:province":"IA",
    "sg:tags":[
        "hog",
        "beef",
        "f",
        "farm",
        "corn",
        "soybean",
        "cattle",
        "feedlot"
    ],
    "wof:name":"Saathoff Farm",
    "wof:placetype":"venue"
},
  "geometry": {"coordinates":[-91.48223299999999,42.310838],"type":"Point"}
}