{
  "type": "Feature",
  "properties": {
    "iso:country":"US",
    "sg:address":"26917 216th St",
    "sg:city":"Bellevue",
    "sg:classifiers":[
        {
            "category":"Farming",
            "subcategory":"Livestock Farm",
            "type":"Manufacturing & Wholesale Goods"
        }
    ],
    "sg:phone":"+1 563 773 8156",
    "sg:postcode":"52031",
    "sg:province":"IA",
    "sg:tags":[
        "beef",
        "feedlot",
        "cattle"
    ],
    "wof:name":"Schwager Farm",
    "wof:placetype":"venue"
},
  "geometry": {"coordinates":[-90.58738,42.222055],"type":"Point"}
}