{
  "type": "Feature",
  "properties": {
    "iso:country":"US",
    "sg:address":"304 Broadway St",
    "sg:city":"Lost Nation",
    "sg:classifiers":[
        {
            "category":"Building & Trades",
            "subcategory":"Electrical",
            "type":"Services"
        }
    ],
    "sg:phone":"+1 563 678 2458",
    "sg:postcode":"52254",
    "sg:province":"IA",
    "sg:tags":[
        "electric",
        "contractor"
    ],
    "wof:name":"Martin Dosland",
    "wof:placetype":"venue"
},
  "geometry": {"coordinates":[-90.81693300000001,41.962879],"type":"Point"}
}