{
  "type": "Feature",
  "properties": {
    "iso:country":"US",
    "sg:address":"201 W Broadway St",
    "sg:city":"Eagle Grove",
    "sg:classifiers":[
        {
            "category":"Farming",
            "subcategory":"Farm & Veterinary Services",
            "type":"Manufacturing & Wholesale Goods"
        }
    ],
    "sg:phone":"+1 515 448 3502",
    "sg:postcode":"50533",
    "sg:province":"IA",
    "sg:tags":[
        "management"
    ],
    "wof:name":"John Govern",
    "wof:placetype":"venue"
},
  "geometry": {"coordinates":[-93.904488,42.66412],"type":"Point"}
}