{
  "type": "Feature",
  "properties": {
    "iso:country":"US",
    "sg:address":"4450 West St",
    "sg:city":"Sioux City",
    "sg:classifiers":[
        {
            "category":"Building & Trades",
            "subcategory":"Electrical",
            "type":"Services"
        }
    ],
    "sg:phone":"+1 712 252 0348",
    "sg:postcode":"51108",
    "sg:province":"IA",
    "sg:tags":[
        "electric",
        "contractor"
    ],
    "wof:name":"P J Electric & Equipment Co",
    "wof:placetype":"venue"
},
  "geometry": {"coordinates":[-96.43013999999999,42.547694],"type":"Point"}
}