{
  "type": "Feature",
  "properties": {
    "iso:country":"US",
    "sg:address":"401 4th Ave N",
    "sg:city":"Clinton",
    "sg:classifiers":[
        {
            "category":"Organizations",
            "subcategory":"Religious Organization",
            "type":"Services"
        }
    ],
    "sg:phone":"+1 563 242 4670",
    "sg:postcode":"52732",
    "sg:province":"IA",
    "sg:tags":[
        "church"
    ],
    "wof:name":"St Stephen's Lutheran Church",
    "wof:placetype":"venue"
},
  "geometry": {"coordinates":[-90.195567,41.849177],"type":"Point"}
}