{
  "type": "Feature",
  "properties": {
    "iso:country":"US",
    "sg:address":"3325 Ave I",
    "sg:city":"Council Bluffs",
    "sg:classifiers":[
        {
            "category":"Professional",
            "subcategory":"Business Services",
            "type":"Services"
        }
    ],
    "sg:phone":"+1 712 328 1498",
    "sg:postcode":"51501",
    "sg:province":"IA",
    "wof:name":"Hlb Enterprises",
    "wof:placetype":"venue"
},
  "geometry": {"coordinates":[-95.897825,41.26991],"type":"Point"}
}