{
  "type": "Feature",
  "properties": {
    "iso:country":"US",
    "sg:address":"121 E 4th St",
    "sg:city":"Spencer",
    "sg:classifiers":[
        {
            "category":"Social Services",
            "type":"Services"
        }
    ],
    "sg:phone":"+1 712 262 6548",
    "sg:postcode":"51301",
    "sg:province":"IA",
    "sg:tags":[
        "organization",
        "welfare"
    ],
    "wof:name":"Sunshine Services Inc",
    "wof:placetype":"venue"
},
  "geometry": {"coordinates":[-95.14208499999999,43.141509],"type":"Point"}
}