{
  "type": "Feature",
  "properties": {
    "iso:country":"US",
    "sg:address":"835 Church St",
    "sg:city":"Holy Cross",
    "sg:classifiers":[
        {
            "category":"Education",
            "subcategory":"School",
            "type":"Public Place"
        }
    ],
    "sg:phone":"+1 563 870 2405",
    "sg:postcode":"52053",
    "sg:province":"IA",
    "wof:name":"RHCL School",
    "wof:placetype":"venue"
},
  "geometry": {"coordinates":[-90.99711499999999,42.599773],"type":"Point"}
}