{
  "type": "Feature",
  "properties": {
    "iso:country":"US",
    "sg:address":"3830 450th St",
    "sg:city":"Orange City",
    "sg:phone":"+1 712 737 8114",
    "sg:postcode":"51003",
    "sg:province":"IA",
    "sg:tags":[
        "farm",
        "corn",
        "soybean"
    ],
    "wof:name":"Myron Vander Meulen",
    "wof:placetype":"venue"
},
  "geometry": {"coordinates":[-96.03605899999999,42.997472],"type":"Point"}
}