{
  "type": "Feature",
  "properties": {
    "addr:full":"25581 State Hwy 128 Garnavillo IA 52049",
    "addr:housenumber":"25581",
    "addr:postcode":"52049",
    "addr:street":"State Hwy 128",
    "iso:country":"US",
    "sg:address":"25581 State Hwy 128",
    "sg:city":"Garnavillo",
    "sg:classifiers":[
        {
            "category":"Farming",
            "subcategory":"Livestock Farm",
            "type":"Manufacturing & Wholesale Goods"
        }
    ],
    "sg:phone":"+1 563 245 2848",
    "sg:postcode":"52049",
    "sg:province":"IA",
    "sg:tags":[
        "hog",
        "or",
        "feedlot"
    ],
    "wof:name":"Cecil Dempster",
    "wof:placetype":"venue"
},
  "geometry": {"coordinates":[-91.2983,42.882864],"type":"Point"}
}