{
  "type": "Feature",
  "properties": {
    "addr:full":"121 E Main St Manchester IA 52057",
    "addr:housenumber":"121",
    "addr:postcode":"52057",
    "addr:street":"E Main St",
    "iso:country":"US",
    "sg:address":"121 E Main St",
    "sg:city":"Manchester",
    "sg:classifiers":[
        {
            "category":"Banks & Credit Unions",
            "subcategory":"Investment Brokerage",
            "type":"Services"
        }
    ],
    "sg:phone":"+1 563 927 2305",
    "sg:postcode":"52057",
    "sg:province":"IA",
    "sg:tags":[
        "stock",
        "bond"
    ],
    "wof:name":"Edward Jones Co",
    "wof:placetype":"venue"
},
  "geometry": {"coordinates":[-91.457655,42.483896],"type":"Point"}
}