{
  "type": "Feature",
  "properties": {
    "addr:full":"1361 Sycamore Ave Prescott IA 50859",
    "addr:housenumber":"1361",
    "addr:postcode":"50859",
    "addr:street":"Sycamore Ave",
    "iso:country":"US",
    "sg:address":"1361 Sycamore Ave",
    "sg:city":"Prescott",
    "sg:classifiers":[
        {
            "category":"Farming",
            "subcategory":"Livestock Farm",
            "type":"Manufacturing & Wholesale Goods"
        }
    ],
    "sg:phone":"+1 641 345 2635",
    "sg:postcode":"50859",
    "sg:province":"IA",
    "sg:tags":[
        "feedlot",
        "corn",
        "soybean",
        "beef",
        "cattle"
    ],
    "wof:name":"Mittag Show Cattle",
    "wof:placetype":"venue"
},
  "geometry": {"coordinates":[-94.56617900000001,41.103109],"type":"Point"}
}