{
  "type": "Feature",
  "properties": {
    "iso:country":"US",
    "sg:address":"4803 University Ave",
    "sg:city":"Des Moines",
    "sg:classifiers":[
        {
            "category":"Health Services",
            "subcategory":"Doctor",
            "type":"Services"
        }
    ],
    "sg:phone":"+1 515 279 3685",
    "sg:postcode":"50311",
    "sg:province":"IA",
    "sg:tags":[
        "dentist"
    ],
    "wof:name":"Blount Services Inc",
    "wof:placetype":"venue"
},
  "geometry": {"coordinates":[-93.684628,41.600451],"type":"Point"}
}