{
  "type": "Feature",
  "properties": {
    "iso:country":"US",
    "sg:address":"1148 Indian Ave",
    "sg:city":"Rock Rapids",
    "sg:phone":"+1 712 472 2296",
    "sg:postcode":"51246",
    "sg:province":"IA",
    "sg:tags":[
        "farm",
        "corn"
    ],
    "wof:name":"J Fastert",
    "wof:placetype":"venue"
},
  "geometry": {"coordinates":[-96.09607800000001,43.482973],"type":"Point"}
}