{
  "type": "Feature",
  "properties": {
    "addr:full":"220 40th St NE Cedar Rapids IA 52402",
    "addr:housenumber":"220",
    "addr:postcode":"52402",
    "addr:street":"40Th St Ne",
    "iso:country":"US",
    "sg:address":"220 40th St NE",
    "sg:city":"Cedar Rapids",
    "sg:classifiers":[
        {
            "category":"Organizations",
            "subcategory":"Religious Organization",
            "type":"Services"
        }
    ],
    "sg:phone":"+1 319 363 2029",
    "sg:postcode":"52402",
    "sg:province":"IA",
    "sg:tags":[
        "church"
    ],
    "sg:website":"www.christepiscopal.org",
    "wof:name":"Christ Episcopal Church",
    "wof:placetype":"venue"
},
  "geometry": {"coordinates":[-91.634418,42.019498],"type":"Point"}
}