{
  "type": "Feature",
  "properties": {
    "iso:country":"US",
    "sg:address":"2907 Greene Ave",
    "sg:city":"Eagle Grove",
    "sg:classifiers":[
        {
            "category":"Real Estate",
            "subcategory":"Real Estate Operator",
            "type":"Services"
        }
    ],
    "sg:phone":"+1 515 448 4935",
    "sg:postcode":"50533",
    "sg:province":"IA",
    "sg:tags":[
        "property",
        "lessor"
    ],
    "wof:name":"Fred Crovisier",
    "wof:placetype":"venue"
},
  "geometry": {"coordinates":[-93.853379,42.629179],"type":"Point"}
}