{
  "type": "Feature",
  "properties": {
    "iso:country":"US",
    "sg:address":"935 Lincoln Hwy",
    "sg:city":"Nevada",
    "sg:classifiers":[
        {
            "category":"Government",
            "subcategory":"Fire Station",
            "type":"Public Place"
        }
    ],
    "sg:phone":"+1 515 382 4420",
    "sg:postcode":"50201",
    "sg:province":"IA",
    "sg:tags":[
        "department"
    ],
    "wof:name":"Nevada Fire Station",
    "wof:placetype":"venue"
},
  "geometry": {"coordinates":[-93.44784,42.022792],"type":"Point"}
}