{
  "type": "Feature",
  "properties": {
    "iso:country":"US",
    "sg:address":"3810 66th St",
    "sg:city":"Urbandale",
    "sg:classifiers":[
        {
            "category":"Banks & Credit Unions",
            "subcategory":"Bank",
            "type":"Services"
        }
    ],
    "sg:phone":"+1 515 276 6083",
    "sg:postcode":"50322",
    "sg:province":"IA",
    "wof:name":"Polk County Sch Employees Cu",
    "wof:placetype":"venue"
},
  "geometry": {"coordinates":[-93.70745599999999,41.631012],"type":"Point"}
}