{
  "type": "Feature",
  "properties": {
    "iso:country":"US",
    "sg:address":"501 S Corkhill St",
    "sg:city":"Mt Pleasant",
    "sg:classifiers":[
        {
            "category":"Education",
            "subcategory":"School",
            "type":"Public Place"
        }
    ],
    "sg:phone":"+1 319 385 7765",
    "sg:postcode":"52641",
    "sg:province":"IA",
    "sg:website":"www.mtpleasantschools.com",
    "wof:name":"Lincoln Elementary School",
    "wof:placetype":"venue"
},
  "geometry": {"coordinates":[-91.54780599999999,40.961724],"type":"Point"}
}