{
  "type": "Feature",
  "properties": {
    "iso:country":"US",
    "sg:address":"101 W 8th St",
    "sg:city":"Sheldon",
    "sg:classifiers":[
        {
            "category":"Retail",
            "subcategory":"Auto Repair",
            "type":"Services"
        }
    ],
    "sg:phone":"+1 712 324 5085",
    "sg:postcode":"51201",
    "sg:province":"IA",
    "sg:tags":[
        "body",
        "shop"
    ],
    "wof:name":"Morgan Collision & Tire Center",
    "wof:placetype":"venue"
},
  "geometry": {"coordinates":[-95.85683299999999,43.182516],"type":"Point"}
}