{
  "type": "Feature",
  "properties": {
    "iso:country":"US",
    "sg:address":"1940 Ventura Ave",
    "sg:city":"Ottumwa",
    "sg:classifiers":[
        {
            "category":"Personal",
            "subcategory":"Beauty Salon",
            "type":"Services"
        }
    ],
    "sg:phone":"+1 641 684 4665",
    "sg:postcode":"52586",
    "sg:province":"IA",
    "wof:name":"Smart Style Family Hair Salon",
    "wof:placetype":"venue"
},
  "geometry": {"coordinates":[-92.46428,41.373962],"type":"Point"}
}