{
  "type": "Feature",
  "properties": {
    "iso:country":"US",
    "sg:address":"102 5th Ave SE",
    "sg:city":"Tripoli",
    "sg:classifiers":[
        {
            "category":"Recreation",
            "type":"Entertainment"
        }
    ],
    "sg:phone":"+1 319 882 3705",
    "sg:postcode":"50676",
    "sg:province":"IA",
    "sg:tags":[
        "center"
    ],
    "wof:name":"Action Rec Ctr",
    "wof:placetype":"venue"
},
  "geometry": {"coordinates":[-92.256861,42.804295],"type":"Point"}
}