{
  "type": "Feature",
  "properties": {
    "iso:country":"US",
    "sg:address":"2138 Lyon St",
    "sg:city":"Des Moines",
    "sg:classifiers":[
        {
            "category":"Building & Trades",
            "subcategory":"Electrical",
            "type":"Services"
        }
    ],
    "sg:phone":"+1 515 266 8396",
    "sg:postcode":"50317",
    "sg:province":"IA",
    "sg:tags":[
        "electric",
        "contractor"
    ],
    "wof:name":"Binder Electric",
    "wof:placetype":"venue"
},
  "geometry": {"coordinates":[-93.57805399999999,41.597297],"type":"Point"}
}