{
  "type": "Feature",
  "properties": {
    "iso:country":"US",
    "sg:address":"2055 N Towne Ln NE",
    "sg:city":"Cedar Rapids",
    "sg:classifiers":[
        {
            "category":"Wholesale",
            "subcategory":"Farm Supplies",
            "type":"Manufacturing & Wholesale Goods"
        }
    ],
    "sg:phone":"+1 319 294 8822",
    "sg:postcode":"52402",
    "sg:province":"IA",
    "sg:tags":[
        "feed",
        "concentrate",
        "supplement"
    ],
    "wof:name":"Nutra Blend",
    "wof:placetype":"venue"
},
  "geometry": {"coordinates":[-91.67221000000001,42.032885],"type":"Point"}
}