{
  "type": "Feature",
  "properties": {
    "iso:country":"US",
    "sg:address":"1319 N 16th St",
    "sg:city":"Council Bluffs",
    "sg:classifiers":[
        {
            "category":"Professional",
            "subcategory":"Credit Reporting & Collection",
            "type":"Services"
        }
    ],
    "sg:phone":"+1 712 328 1881",
    "sg:postcode":"51501",
    "sg:province":"IA",
    "sg:tags":[
        "agency"
    ],
    "wof:name":"Business & Professional Credit",
    "wof:placetype":"venue"
},
  "geometry": {"coordinates":[-95.867311,41.274177],"type":"Point"}
}