{
  "type": "Feature",
  "properties": {
    "iso:country":"US",
    "sg:address":"124 O Ave",
    "sg:city":"Paton",
    "sg:classifiers":[
        {
            "category":"Insurance",
            "subcategory":"Health Insurance",
            "type":"Services"
        }
    ],
    "sg:phone":"+1 515 544 3350",
    "sg:postcode":"50217",
    "sg:province":"IA",
    "sg:tags":[
        "plan"
    ],
    "wof:name":"Joanne Wilson",
    "wof:placetype":"venue"
},
  "geometry": {"coordinates":[-94.359188,42.205634],"type":"Point"}
}