{
  "type": "Feature",
  "properties": {
    "iso:country":"US",
    "sg:address":"23645 Oak Ave",
    "sg:city":"Turin",
    "sg:classifiers":[
        {
            "category":"Wholesale",
            "subcategory":"Machinery & Supplies",
            "type":"Manufacturing & Wholesale Goods"
        }
    ],
    "sg:phone":"+1 712 353 6743",
    "sg:postcode":"51040",
    "sg:province":"IA",
    "sg:tags":[
        "farm",
        "equipment"
    ],
    "wof:name":"C & F Equipment",
    "wof:placetype":"venue"
},
  "geometry": {"coordinates":[-95.943876,42.013493],"type":"Point"}
}