{
  "type": "Feature",
  "properties": {
    "iso:country":"US",
    "sg:address":"3521 Beaver Ave",
    "sg:city":"Des Moines",
    "sg:classifiers":[
        {
            "category":"Real Estate",
            "subcategory":"Real Estate Agent",
            "type":"Services"
        }
    ],
    "sg:phone":"+1 515 453 6423",
    "sg:postcode":"50310",
    "sg:province":"IA",
    "wof:name":"Roscoe Rlemenschneide",
    "wof:placetype":"venue"
},
  "geometry": {"coordinates":[-93.67737700000001,41.628389],"type":"Point"}
}