{
  "type": "Feature",
  "properties": {
    "addr:full":"3500 Kingman Blvd Des Moines IA 50311",
    "addr:housenumber":"3500",
    "addr:postcode":"50311",
    "addr:street":"Kingman Blvd",
    "iso:country":"US",
    "sg:address":"3500 Kingman Blvd",
    "sg:city":"Des Moines",
    "sg:classifiers":[
        {
            "category":"Real Estate",
            "subcategory":"Real Estate Operator",
            "type":"Services"
        }
    ],
    "sg:phone":"+1 515 279 7312",
    "sg:postcode":"50311",
    "sg:province":"IA",
    "sg:tags":[
        "building",
        "nonresidential"
    ],
    "wof:name":"Thoreau Center",
    "wof:placetype":"venue"
},
  "geometry": {"coordinates":[-93.66548299999999,41.596488],"type":"Point"}
}