{
  "type": "Feature",
  "properties": {
    "iso:country":"US",
    "sg:address":"2727 Hamilton Blvd",
    "sg:city":"Sioux City",
    "sg:classifiers":[
        {
            "category":"Banks & Credit Unions",
            "subcategory":"Bank",
            "type":"Services"
        }
    ],
    "sg:phone":"+1 712 277 0207",
    "sg:postcode":"51104",
    "sg:province":"IA",
    "wof:name":"First Federal Bank",
    "wof:placetype":"venue"
},
  "geometry": {"coordinates":[-96.41763,42.518406],"type":"Point"}
}