{
  "type": "Feature",
  "properties": {
    "addr:full":"200 W Lowe Ave Fairfield IA 52556",
    "addr:housenumber":"200",
    "addr:postcode":"52556",
    "addr:street":"W Lowe Ave",
    "iso:country":"US",
    "sg:address":"200 W Lowe Ave",
    "sg:city":"Fairfield",
    "sg:classifiers":[
        {
            "category":"Health Services",
            "subcategory":"Chiropractor",
            "type":"Services"
        }
    ],
    "sg:phone":"+1 641 469 6213",
    "sg:postcode":"52556",
    "sg:province":"IA",
    "wof:name":"Mediabrains Inc",
    "wof:placetype":"venue"
},
  "geometry": {"coordinates":[-91.966286,41.011973],"type":"Point"}
}