{
  "type": "Feature",
  "properties": {
    "iso:country":"US",
    "sg:address":"1446 295th Ave",
    "sg:city":"West Point",
    "sg:classifiers":[
        {
            "category":"Utilities",
            "type":"Services"
        }
    ],
    "sg:phone":"+1 319 528 4292",
    "sg:postcode":"52656",
    "sg:province":"IA",
    "sg:tags":[
        "sanitary"
    ],
    "wof:name":"Bergquist Snow Removal",
    "wof:placetype":"venue"
},
  "geometry": {"coordinates":[-91.34273899999999,40.747185],"type":"Point"}
}