{
  "type": "Feature",
  "properties": {
    "iso:country":"US",
    "sg:address":"11 E 4th St",
    "sg:city":"Atlantic",
    "sg:classifiers":[
        {
            "category":"Manufacturing",
            "subcategory":"Signs",
            "type":"Manufacturing & Wholesale Goods"
        }
    ],
    "sg:phone":"+1 712 243 4920",
    "sg:postcode":"50022",
    "sg:province":"IA",
    "wof:name":"Atlantic Signs",
    "wof:placetype":"venue"
},
  "geometry": {"coordinates":[-95.012885,41.406911],"type":"Point"}
}