{
  "type": "Feature",
  "properties": {
    "iso:country":"US",
    "sg:address":"10 Weimer St",
    "sg:city":"Ventura",
    "sg:classifiers":[
        {
            "category":"Organizations",
            "subcategory":"Religious Organization",
            "type":"Services"
        }
    ],
    "sg:phone":"+1 641 829 3600",
    "sg:postcode":"50482",
    "sg:province":"IA",
    "sg:tags":[
        "church"
    ],
    "wof:name":"United Methodist Church",
    "wof:placetype":"venue"
},
  "geometry": {"coordinates":[-93.47905900000001,43.127613],"type":"Point"}
}