{
  "type": "Feature",
  "properties": {
    "addr:full":"1510 NE Trilein Dr Ankeny IA 50021",
    "addr:housenumber":"1510",
    "addr:postcode":"50021",
    "addr:street":"Ne Trilein Dr",
    "iso:country":"US",
    "sg:address":"1510 NE Trilein Dr",
    "sg:city":"Ankeny",
    "sg:classifiers":[
        {
            "category":"Food & Beverages",
            "subcategory":"Liquor & Beverages",
            "type":"Retail Goods"
        }
    ],
    "sg:phone":"+1 515 964 5775",
    "sg:postcode":"50021",
    "sg:province":"IA",
    "sg:tags":[
        "wine"
    ],
    "wof:name":"World Of Wine",
    "wof:placetype":"venue"
},
  "geometry": {"coordinates":[-93.58984599999999,41.742831],"type":"Point"}
}