{
  "type": "Feature",
  "properties": {
    "addr:full":"1010 NW Prairie Ridge Dr Ankeny IA 50023",
    "addr:housenumber":"1010",
    "addr:postcode":"50023",
    "addr:street":"Nw Prairie Ridge Dr",
    "iso:country":"US",
    "sg:address":"1010 NW Prairie Ridge Dr",
    "sg:city":"Ankeny",
    "sg:classifiers":[
        {
            "category":"Education",
            "subcategory":"School",
            "type":"Public Place"
        }
    ],
    "sg:phone":"+1 515 965 9700",
    "sg:postcode":"50023",
    "sg:province":"IA",
    "sg:website":"www.ankeny.k12.ia.us",
    "wof:name":"Northview Middle School",
    "wof:placetype":"venue"
},
  "geometry": {"coordinates":[-93.620042,41.74169],"type":"Point"}
}