{
  "type": "Feature",
  "properties": {
    "iso:country":"US",
    "sg:address":"1806 4th Ave S",
    "sg:city":"Denison",
    "sg:classifiers":[
        {
            "category":"Professional",
            "subcategory":"Management & Consulting",
            "type":"Services"
        }
    ],
    "sg:phone":"+1 712 263 8380",
    "sg:postcode":"51442",
    "sg:province":"IA",
    "sg:tags":[
        "business"
    ],
    "wof:name":"Boyer Valley Communications",
    "wof:placetype":"venue"
},
  "geometry": {"coordinates":[-95.345331,42.012418],"type":"Point"}
}