{
  "type": "Feature",
  "properties": {
    "iso:country":"US",
    "sg:address":"3744 Hwy 61",
    "sg:city":"Burlington",
    "sg:classifiers":[
        {
            "category":"Building & Trades",
            "subcategory":"Construction",
            "type":"Services"
        }
    ],
    "sg:phone":"+1 319 752 5491",
    "sg:postcode":"52601",
    "sg:province":"IA",
    "sg:tags":[
        "concrete",
        "contractor"
    ],
    "wof:name":"Shipley Contracting Corp",
    "wof:placetype":"venue"
},
  "geometry": {"coordinates":[-91.164526,40.73696],"type":"Point"}
}