{
  "type": "Feature",
  "properties": {
    "addr:full":"303 Euclid Ave Des Moines IA 50313",
    "addr:housenumber":"303",
    "addr:postcode":"50313",
    "addr:street":"Euclid Ave",
    "iso:country":"US",
    "sg:address":"303 Euclid Ave",
    "sg:city":"Des Moines",
    "sg:classifiers":[
        {
            "category":"Banks & Credit Unions",
            "subcategory":"Bank",
            "type":"Services"
        }
    ],
    "sg:phone":"+1 515 282 7363",
    "sg:postcode":"50313",
    "sg:province":"IA",
    "wof:name":"Iowa Postal Credit Union",
    "wof:placetype":"venue"
},
  "geometry": {"coordinates":[-93.622271,41.627765],"type":"Point"}
}