{
  "type": "Feature",
  "properties": {
    "iso:country":"US",
    "sg:address":"1515 3rd Ave NW",
    "sg:city":"Fort Dodge",
    "sg:classifiers":[
        {
            "category":"Autos & Motor Vehicles",
            "subcategory":"Automobile Sales",
            "type":"Retail Goods"
        }
    ],
    "sg:phone":"+1 515 955 6400",
    "sg:postcode":"50501",
    "sg:province":"IA",
    "sg:tags":[
        "truck"
    ],
    "wof:name":"O'Halloran International",
    "wof:placetype":"venue"
},
  "geometry": {"coordinates":[-94.22202900000001,42.515576],"type":"Point"}
}