{
  "type": "Feature",
  "properties": {
    "iso:country":"US",
    "sg:address":"911 6th St",
    "sg:city":"Sioux City",
    "sg:classifiers":[
        {
            "category":"Real Estate",
            "subcategory":"Real Estate Agent",
            "type":"Services"
        }
    ],
    "sg:phone":"+1 712 277 8700",
    "sg:postcode":"51101",
    "sg:province":"IA",
    "sg:website":"www.siouxcityhomes.net",
    "wof:name":"Re/Max Of Siouxland",
    "wof:placetype":"venue"
},
  "geometry": {"coordinates":[-96.398742,42.496441],"type":"Point"}
}