{
  "type": "Feature",
  "properties": {
    "iso:country":"US",
    "sg:address":"224 N 2nd St",
    "sg:city":"Eldridge",
    "sg:classifiers":[
        {
            "category":"Health Services",
            "subcategory":"Chiropractor",
            "type":"Services"
        }
    ],
    "sg:phone":"+1 563 285 1414",
    "sg:postcode":"52748",
    "sg:province":"IA",
    "wof:name":"Back To Health",
    "wof:placetype":"venue"
},
  "geometry": {"coordinates":[-90.58449299999999,41.6567],"type":"Point"}
}