{
  "type": "Feature",
  "properties": {
    "iso:country":"US",
    "sg:address":"824 Volney Rd",
    "sg:city":"Monona",
    "sg:classifiers":[
        {
            "category":"Retail",
            "subcategory":"Repair Shop",
            "type":"Services"
        }
    ],
    "sg:phone":"+1 563 535 7194",
    "sg:postcode":"52172",
    "sg:province":"IA",
    "wof:name":"Colsch Cycle Repair",
    "wof:placetype":"venue"
},
  "geometry": {"coordinates":[-91.374476,43.178779],"type":"Point"}
}