{
  "type": "Feature",
  "properties": {
    "iso:country":"US",
    "sg:address":"3098 160th St",
    "sg:city":"Brooklyn",
    "sg:classifiers":[
        {
            "category":"Farming",
            "subcategory":"Farm",
            "type":"Manufacturing & Wholesale Goods"
        }
    ],
    "sg:phone":"+1 641 522 7590",
    "sg:postcode":"52211",
    "sg:province":"IA",
    "sg:tags":[
        "crop",
        "general"
    ],
    "wof:name":"Carl Anthony",
    "wof:placetype":"venue"
},
  "geometry": {"coordinates":[-92.47441000000001,41.847771],"type":"Point"}
}