{
  "type": "Feature",
  "properties": {
    "addr:full":"55547 265th St Ames IA 50010",
    "addr:housenumber":"55547",
    "addr:postcode":"50010",
    "addr:street":"265Th St",
    "iso:country":"US",
    "sg:address":"55547 265th St",
    "sg:city":"Ames",
    "sg:classifiers":[
        {
            "category":"Building & Trades",
            "subcategory":"Construction",
            "type":"Services"
        }
    ],
    "sg:phone":"+1 515 232 7160",
    "sg:postcode":"50010",
    "sg:province":"IA",
    "sg:tags":[
        "home",
        "builder"
    ],
    "wof:name":"Rollenhagen Construction Inc",
    "wof:placetype":"venue"
},
  "geometry": {"coordinates":[-93.59521599999999,41.972184],"type":"Point"}
}