{
  "type": "Feature",
  "properties": {
    "iso:country":"US",
    "sg:address":"35 W Main St",
    "sg:city":"Waukon",
    "sg:classifiers":[
        {
            "category":"Home & Garden",
            "subcategory":"Household Appliances",
            "type":"Retail Goods"
        }
    ],
    "sg:phone":"+1 563 568 2004",
    "sg:postcode":"52172",
    "sg:province":"IA",
    "sg:tags":[
        "cleaners",
        "vacuum"
    ],
    "wof:name":"Daves Vacs",
    "wof:placetype":"venue"
},
  "geometry": {"coordinates":[-91.475442,43.269359],"type":"Point"}
}