{
  "type": "Feature",
  "properties": {
    "iso:country":"US",
    "sg:address":"14872 232nd St",
    "sg:city":"Delta",
    "sg:phone":"+1 641 624 2237",
    "sg:postcode":"52550",
    "sg:province":"IA",
    "sg:tags":[
        "farm",
        "field",
        "corn",
        "soybean",
        "crop"
    ],
    "wof:name":"Don Workman Farms",
    "wof:placetype":"venue"
},
  "geometry": {"coordinates":[-92.320413,41.318861],"type":"Point"}
}