{
  "type": "Feature",
  "properties": {
    "iso:country":"US",
    "sg:address":"1308 2nd St",
    "sg:city":"Perry",
    "sg:classifiers":[
        {
            "category":"Insurance",
            "subcategory":"Insurance Agent",
            "type":"Services"
        }
    ],
    "sg:phone":"+1 515 465 5308",
    "sg:postcode":"50220",
    "sg:province":"IA",
    "wof:name":"Summerson Agency Inc",
    "wof:placetype":"venue"
},
  "geometry": {"coordinates":[-94.105091,41.841494],"type":"Point"}
}