{
  "type": "Feature",
  "properties": {
    "iso:country":"US",
    "sg:address":"2608 Madison Ave",
    "sg:city":"Burlington",
    "sg:classifiers":[
        {
            "category":"Restaurant",
            "type":"Food & Drink"
        },
        {
            "category":"Shopping",
            "subcategory":"Gifts & Souvenirs",
            "type":"Retail Goods"
        }
    ],
    "sg:phone":"+1 319 752 1894",
    "sg:postcode":"52601",
    "sg:province":"IA",
    "wof:name":"Big Momma's Gifts & Goodies",
    "wof:placetype":"venue"
},
  "geometry": {"coordinates":[-91.107803,40.779951],"type":"Point"}
}