{
  "type": "Feature",
  "properties": {
    "iso:country":"US",
    "sg:address":"11916 Hwy 99",
    "sg:city":"Burlington",
    "sg:classifiers":[
        {
            "category":"Autos & Motor Vehicles",
            "subcategory":"Automobile Sales",
            "type":"Retail Goods"
        }
    ],
    "sg:phone":"+1 319 752 0951",
    "sg:postcode":"52601",
    "sg:province":"IA",
    "sg:tags":[
        "car",
        "dealer"
    ],
    "wof:name":"Smith Motor Sales",
    "wof:placetype":"venue"
},
  "geometry": {"coordinates":[-91.109112,40.85424],"type":"Point"}
}