{
  "type": "Feature",
  "properties": {
    "iso:country":"US",
    "sg:address":"109 E Center St",
    "sg:city":"Conrad",
    "sg:classifiers":[
        {
            "category":"Restaurant",
            "type":"Food & Drink"
        }
    ],
    "sg:menulink":"http://www.allmenus.com/ia/clay/32065-pizza-ranch/menu/",
    "sg:phone":"+1 641 366 2600",
    "sg:postcode":"50621",
    "sg:province":"IA",
    "sg:tags":[
        "american",
        "pizza"
    ],
    "wof:name":"Pizza Ranch",
    "wof:placetype":"venue"
},
  "geometry": {"coordinates":[-92.874365,42.224546],"type":"Point"}
}