{
  "type": "Feature",
  "properties": {
    "iso:country":"US",
    "sg:address":"909 Red Bridge Rd",
    "sg:city":"Central City",
    "sg:classifiers":[
        {
            "category":"Insurance",
            "subcategory":"Insurance Agent",
            "type":"Services"
        }
    ],
    "sg:phone":"+1 319 437 2131",
    "sg:postcode":"52214",
    "sg:province":"IA",
    "wof:name":"Holub Insurance Agency",
    "wof:placetype":"venue"
},
  "geometry": {"coordinates":[-91.46594399999999,42.253099],"type":"Point"}
}