{
  "type": "Feature",
  "properties": {
    "iso:country":"US",
    "sg:address":"313 Kothe St",
    "sg:city":"Waterloo",
    "sg:classifiers":[
        {
            "category":"Manufacturing",
            "subcategory":"Food",
            "type":"Manufacturing & Wholesale Goods"
        }
    ],
    "sg:phone":"+1 319 232 1122",
    "sg:postcode":"50703",
    "sg:province":"IA",
    "sg:tags":[
        "extract",
        "syrup",
        "flavoring"
    ],
    "sg:website":"www.palmerhousefoods.com",
    "wof:name":"Palmer House Food Processing",
    "wof:placetype":"venue"
},
  "geometry": {"coordinates":[-92.351319,42.519159],"type":"Point"}
}