{
  "type": "Feature",
  "properties": {
    "addr:full":"604 Highway 57 Parkersburg IA 50665",
    "addr:housenumber":"604",
    "addr:postcode":"50665",
    "addr:street":"Highway 57",
    "iso:country":"US",
    "sg:address":"604 Highway 57",
    "sg:city":"Parkersburg",
    "sg:classifiers":[
        {
            "category":"Restaurant",
            "type":"Food & Drink"
        }
    ],
    "sg:menulink":"http://www.allmenus.com/ia/albion/32100-pizza-ranch/menu/",
    "sg:phone":"+1 319 346 1111",
    "sg:postcode":"50665",
    "sg:province":"IA",
    "sg:tags":[
        "american",
        "pizza"
    ],
    "wof:name":"Pizza Ranch",
    "wof:placetype":"venue"
},
  "geometry": {"coordinates":[-92.787035,42.570237],"type":"Point"}
}