{
  "type": "Feature",
  "properties": {
    "addr:full":"208 1st St SW Tripoli IA 50676",
    "addr:housenumber":"208",
    "addr:postcode":"50676",
    "addr:street":"1St St Sw",
    "iso:country":"US",
    "sg:address":"208 1st St SW",
    "sg:city":"Tripoli",
    "sg:classifiers":[
        {
            "category":"Organizations",
            "subcategory":"Religious Organization",
            "type":"Services"
        }
    ],
    "sg:phone":"+1 319 882 3579",
    "sg:postcode":"50676",
    "sg:province":"IA",
    "sg:tags":[
        "church"
    ],
    "wof:name":"Grace Lutheran Church",
    "wof:placetype":"venue"
},
  "geometry": {"coordinates":[-92.259508,42.808208],"type":"Point"}
}