{
  "type": "Feature",
  "properties": {
    "iso:country":"US",
    "sg:address":"2637 Fontanelle Rd",
    "sg:city":"Fontanelle",
    "sg:classifiers":[
        {
            "category":"Retail",
            "subcategory":"Auto Repair",
            "type":"Services"
        }
    ],
    "sg:phone":"+1 641 745 2083",
    "sg:postcode":"50846",
    "sg:province":"IA",
    "sg:tags":[
        "repairing",
        "automobile"
    ],
    "wof:name":"Mag One Automotive",
    "wof:placetype":"venue"
},
  "geometry": {"coordinates":[-94.56613900000001,41.267393],"type":"Point"}
}