{
  "type": "Feature",
  "properties": {
    "iso:country":"US",
    "sg:address":"275 Salina St",
    "sg:city":"Dubuque",
    "sg:classifiers":[
        {
            "category":"Retail",
            "subcategory":"Auto Repair",
            "type":"Services"
        }
    ],
    "sg:phone":"+1 563 556 6480",
    "sg:postcode":"52003",
    "sg:province":"IA",
    "sg:tags":[
        "wrecker"
    ],
    "wof:name":"Wenzel Towing Inc",
    "wof:placetype":"venue"
},
  "geometry": {"coordinates":[-90.663314,42.491575],"type":"Point"}
}