{
  "type": "Feature",
  "properties": {
    "iso:country":"US",
    "sg:address":"209 W 6th St",
    "sg:city":"West Liberty",
    "sg:classifiers":[
        {
            "category":"Professional",
            "subcategory":"Art Services",
            "type":"Services"
        }
    ],
    "sg:phone":"+1 319 627 6476",
    "sg:postcode":"52776",
    "sg:province":"IA",
    "sg:tags":[
        "graphic",
        "designer"
    ],
    "wof:name":"Showtime Graphics",
    "wof:placetype":"venue"
},
  "geometry": {"coordinates":[-91.267098,41.573406],"type":"Point"}
}