{
  "type": "Feature",
  "properties": {
    "addr:full":"1007 S Main St Clarion IA 50525",
    "addr:housenumber":"1007",
    "addr:postcode":"50525",
    "addr:street":"S Main St",
    "iso:country":"US",
    "sg:address":"1007 S Main St",
    "sg:city":"Clarion",
    "sg:classifiers":[
        {
            "category":"Freight",
            "type":"Transportation"
        }
    ],
    "sg:phone":"+1 515 532 6606",
    "sg:postcode":"50525",
    "sg:province":"IA",
    "sg:tags":[
        "operator",
        "local",
        "trucking"
    ],
    "wof:name":"Kreitlow Trucking",
    "wof:placetype":"venue"
},
  "geometry": {"coordinates":[-93.73262099999999,42.724163],"type":"Point"}
}