{
  "type": "Feature",
  "properties": {
    "iso:country":"US",
    "sg:address":"314 1st Ave W",
    "sg:city":"Dyersville",
    "sg:classifiers":[
        {
            "category":"Personal",
            "subcategory":"Beauty Salon",
            "type":"Services"
        }
    ],
    "sg:phone":"+1 563 875 2040",
    "sg:postcode":"52040",
    "sg:province":"IA",
    "sg:tags":[
        "shop"
    ],
    "wof:name":"Artistically Yours",
    "wof:placetype":"venue"
},
  "geometry": {"coordinates":[-91.128463,42.48461],"type":"Point"}
}