{
  "type": "Feature",
  "properties": {
    "addr:full":"120 E Washington St Iowa City IA 52240",
    "addr:housenumber":"120",
    "addr:postcode":"52240",
    "addr:street":"E Washington St",
    "iso:country":"US",
    "sg:address":"120 E Washington St",
    "sg:city":"Iowa City",
    "sg:classifiers":[
        {
            "category":"Shopping",
            "subcategory":"Clothing, Apparel, & Fashions",
            "type":"Retail Goods"
        }
    ],
    "sg:phone":"+1 319 338 1142",
    "sg:postcode":"52240",
    "sg:province":"IA",
    "sg:tags":[
        "furnishing"
    ],
    "wof:name":"Bremers Clothing & Tailors",
    "wof:placetype":"venue"
},
  "geometry": {"coordinates":[-91.533385,41.660144],"type":"Point"}
}