{
  "type": "Feature",
  "properties": {
    "iso:country":"US",
    "sg:address":"4151 Merle Hay Rd",
    "sg:city":"Des Moines",
    "sg:classifiers":[
        {
            "category":"Restaurant",
            "type":"Food & Drink"
        }
    ],
    "sg:menulink":"http://www.allmenus.com/ia/des-moines/225867-caseys-general-store/menu/",
    "sg:postcode":"50310",
    "sg:province":"IA",
    "sg:tags":[
        "american",
        "pizza"
    ],
    "wof:name":"Casey's General Store",
    "wof:placetype":"venue"
},
  "geometry": {"coordinates":[-93.69727,41.636259],"type":"Point"}
}