{
  "type": "Feature",
  "properties": {
    "iso:country":"US",
    "sg:address":"2015 Ridgeview Dr",
    "sg:city":"Davenport",
    "sg:classifiers":[
        {
            "category":"Building & Trades",
            "subcategory":"Construction",
            "type":"Services"
        }
    ],
    "sg:phone":"+1 563 391 4282",
    "sg:postcode":"52806",
    "sg:province":"IA",
    "sg:tags":[
        "foundation"
    ],
    "wof:name":"Wallace's Poured Foundations",
    "wof:placetype":"venue"
},
  "geometry": {"coordinates":[-90.606202,41.592183],"type":"Point"}
}