{
  "type": "Feature",
  "properties": {
    "iso:country":"US",
    "sg:address":"30690 247th Ave",
    "sg:city":"Exline",
    "sg:classifiers":[
        {
            "category":"Farming",
            "subcategory":"Livestock Farm",
            "type":"Manufacturing & Wholesale Goods"
        }
    ],
    "sg:phone":"+1 641 658 2667",
    "sg:postcode":"52555",
    "sg:province":"IA",
    "sg:tags":[
        "beef",
        "feedlot",
        "cattle"
    ],
    "wof:name":"Lawrence Richmond",
    "wof:placetype":"venue"
},
  "geometry": {"coordinates":[-92.814446,40.598968],"type":"Point"}
}