{
  "type": "Feature",
  "properties": {
    "addr:full":"2109 4th Ave S Clear Lake IA 50428",
    "addr:housenumber":"2109",
    "addr:postcode":"50428",
    "addr:street":"4Th Ave S Clear",
    "iso:country":"US",
    "sg:address":"2109 4th Ave S",
    "sg:city":"Clear Lake",
    "sg:classifiers":[
        {
            "category":"Manufacturing",
            "subcategory":"Metals",
            "type":"Manufacturing & Wholesale Goods"
        }
    ],
    "sg:phone":"+1 641 357 2100",
    "sg:postcode":"50428",
    "sg:province":"IA",
    "sg:tags":[
        "trim",
        "frame",
        "door",
        "sash"
    ],
    "wof:name":"Pella Corp",
    "wof:placetype":"venue"
},
  "geometry": {"coordinates":[-93.36317200000001,43.133669],"type":"Point"}
}