{
  "type": "Feature",
  "properties": {
    "addr:full":"109 S Putnam St Algona IA 50511",
    "addr:housenumber":"109",
    "addr:postcode":"50511",
    "addr:street":"S Putnam St",
    "iso:country":"US",
    "sg:address":"109 S Putnam St",
    "sg:city":"Algona",
    "sg:classifiers":[
        {
            "category":"Farming",
            "subcategory":"Farm",
            "type":"Manufacturing & Wholesale Goods"
        }
    ],
    "sg:phone":"+1 515 295 7299",
    "sg:postcode":"50511",
    "sg:province":"IA",
    "sg:tags":[
        "crop",
        "general"
    ],
    "wof:name":"James Lindhorst",
    "wof:placetype":"venue"
},
  "geometry": {"coordinates":[-94.215412,43.068863],"type":"Point"}
}