{
  "type": "Feature",
  "properties": {
    "iso:country":"US",
    "sg:address":"2436 Camanche Ave",
    "sg:city":"Clinton",
    "sg:classifiers":[
        {
            "category":"Retail",
            "subcategory":"Auto Repair",
            "type":"Services"
        }
    ],
    "sg:phone":"+1 563 244 7432",
    "sg:postcode":"52732",
    "sg:province":"IA",
    "sg:tags":[
        "body",
        "automobile",
        "painting",
        "repairing"
    ],
    "wof:name":"Authentic Auto Body",
    "wof:placetype":"venue"
},
  "geometry": {"coordinates":[-90.21355,41.821476],"type":"Point"}
}