{
  "type": "Feature",
  "properties": {
    "iso:country":"US",
    "sg:address":"611 S 6th St",
    "sg:city":"Clinton",
    "sg:classifiers":[
        {
            "category":"Home & Garden",
            "subcategory":"Building Materials",
            "type":"Retail Goods"
        }
    ],
    "sg:phone":"+1 563 241 1407",
    "sg:postcode":"52732",
    "sg:province":"IA",
    "sg:tags":[
        "windows"
    ],
    "wof:name":"R & S Window & Siding",
    "wof:placetype":"venue"
},
  "geometry": {"coordinates":[-90.198826,41.839893],"type":"Point"}
}