{
  "type": "Feature",
  "properties": {
    "addr:full":"1383 190th St Creston IA 50801",
    "addr:housenumber":"1383",
    "addr:postcode":"50801",
    "addr:street":"190Th St",
    "iso:country":"US",
    "sg:address":"1383 190th St",
    "sg:city":"Creston",
    "sg:classifiers":[
        {
            "category":"Professional",
            "subcategory":"Business Services",
            "type":"Services"
        }
    ],
    "sg:phone":"+1 641 782 2614",
    "sg:postcode":"50801",
    "sg:province":"IA",
    "wof:name":"Kinkade Sales LLC",
    "wof:placetype":"venue"
},
  "geometry": {"coordinates":[-94.39879999999999,41.028573],"type":"Point"}
}