{
  "type": "Feature",
  "properties": {
    "iso:country":"US",
    "sg:address":"2080 205th St",
    "sg:city":"Independence",
    "sg:classifiers":[
        {
            "category":"Farming",
            "subcategory":"Farm",
            "type":"Manufacturing & Wholesale Goods"
        }
    ],
    "sg:phone":"+1 319 334 3723",
    "sg:postcode":"50644",
    "sg:province":"IA",
    "sg:tags":[
        "crop",
        "general"
    ],
    "wof:name":"Chris Oloughlin",
    "wof:placetype":"venue"
},
  "geometry": {"coordinates":[-91.862565,42.489467],"type":"Point"}
}