{
  "type": "Feature",
  "properties": {
    "addr:full":"6101 SW 9th St Des Moines IA 50315",
    "addr:housenumber":"6101",
    "addr:postcode":"50315",
    "addr:street":"Sw 9Th St",
    "iso:country":"US",
    "sg:address":"6101 SW 9th St",
    "sg:city":"Des Moines",
    "sg:classifiers":[
        {
            "category":"Health Services",
            "subcategory":"Doctor",
            "type":"Services"
        }
    ],
    "sg:phone":"+1 515 285 6134",
    "sg:postcode":"50315",
    "sg:province":"IA",
    "sg:tags":[
        "dentist"
    ],
    "wof:name":"O Lee Willham DDS",
    "wof:placetype":"venue"
},
  "geometry": {"coordinates":[-93.625711,41.528316],"type":"Point"}
}