{
  "type": "Feature",
  "properties": {
    "iso:country":"US",
    "sg:address":"703 Main St",
    "sg:city":"Tabor",
    "sg:classifiers":[
        {
            "category":"Professional",
            "subcategory":"Business Services",
            "type":"Services"
        }
    ],
    "sg:phone":"+1 712 629 3195",
    "sg:postcode":"51653",
    "sg:province":"IA",
    "sg:tags":[
        "auctioneer"
    ],
    "wof:name":"Tabor Auction House",
    "wof:placetype":"venue"
},
  "geometry": {"coordinates":[-95.671471,40.899207],"type":"Point"}
}