{
  "type": "Feature",
  "properties": {
    "iso:country":"US",
    "sg:address":"1500 2nd Ave SE",
    "sg:city":"Cedar Rapids",
    "sg:classifiers":[
        {
            "category":"Real Estate",
            "subcategory":"Real Estate Agent",
            "type":"Services"
        }
    ],
    "sg:phone":"+1 319 378 6781",
    "sg:postcode":"52403",
    "sg:province":"IA",
    "sg:tags":[
        "appraiser"
    ],
    "wof:name":"Consolidated Property Conslnts",
    "wof:placetype":"venue"
},
  "geometry": {"coordinates":[-91.649773,41.988197],"type":"Point"}
}