{
  "type": "Feature",
  "properties": {
    "addr:full":"141 W Main St Fredericksburg IA 50630",
    "addr:housenumber":"141",
    "addr:postcode":"50630",
    "addr:street":"W Main St",
    "iso:country":"US",
    "sg:address":"141 W Main St",
    "sg:city":"Fredericksburg",
    "sg:classifiers":[
        {
            "category":"Restaurant",
            "type":"Food & Drink"
        }
    ],
    "sg:phone":"+1 563 237 6393",
    "sg:postcode":"50630",
    "sg:province":"IA",
    "wof:name":"Pizza Palace",
    "wof:placetype":"venue"
},
  "geometry": {"coordinates":[-92.19967,42.965219],"type":"Point"}
}