{
  "type": "Feature",
  "properties": {
    "iso:country":"US",
    "sg:address":"745 N 2nd St",
    "sg:city":"Cherokee",
    "sg:classifiers":[
        {
            "category":"Restaurant",
            "type":"Food & Drink"
        }
    ],
    "sg:phone":"+1 712 225 5924",
    "sg:postcode":"51012",
    "sg:province":"IA",
    "wof:name":"Family Table Restaurant",
    "wof:placetype":"venue"
},
  "geometry": {"coordinates":[-95.551618,42.756465],"type":"Point"}
}