{
  "type": "Feature",
  "properties": {
    "iso:country":"US",
    "sg:address":"109 N 4th St",
    "sg:city":"Mapleton",
    "sg:classifiers":[
        {
            "category":"Home & Garden",
            "subcategory":"Furniture",
            "type":"Retail Goods"
        }
    ],
    "sg:phone":"+1 712 882 2348",
    "sg:postcode":"51034",
    "sg:province":"IA",
    "wof:name":"Russ's Furniture",
    "wof:placetype":"venue"
},
  "geometry": {"coordinates":[-95.79334,42.167045],"type":"Point"}
}