{
  "type": "Feature",
  "properties": {
    "addr:full":"318 Leroy St Audubon IA 50025",
    "addr:housenumber":"318",
    "addr:postcode":"50025",
    "addr:street":"Leroy St",
    "iso:country":"US",
    "sg:address":"318 Leroy St",
    "sg:city":"Audubon",
    "sg:classifiers":[
        {
            "category":"Government",
            "subcategory":"Office",
            "type":"Public Place"
        }
    ],
    "sg:phone":"+1 712 563 2226",
    "sg:postcode":"50025",
    "sg:province":"IA",
    "sg:tags":[
        "county",
        "program",
        "health"
    ],
    "wof:name":"Audubon County Public Health",
    "wof:placetype":"venue"
},
  "geometry": {"coordinates":[-94.930142,41.721653],"type":"Point"}
}