{
  "type": "Feature",
  "properties": {
    "addr:full":"103 W Mission St Strawberry Point IA 52076",
    "addr:housenumber":"103",
    "addr:postcode":"52076",
    "addr:street":"W Mission St",
    "iso:country":"US",
    "sg:address":"103 W Mission St",
    "sg:city":"Strawberry Point",
    "sg:classifiers":[
        {
            "category":"Shopping",
            "type":"Retail Goods"
        }
    ],
    "sg:phone":"+1 563 933 6210",
    "sg:postcode":"52076",
    "sg:province":"IA",
    "sg:tags":[
        "telephone",
        "cellular"
    ],
    "wof:name":"Strawberry Computing",
    "wof:placetype":"venue"
},
  "geometry": {"coordinates":[-91.536491,42.68394],"type":"Point"}
}