{
  "type": "Feature",
  "properties": {
    "iso:country":"US",
    "sg:address":"317 S Cody Rd",
    "sg:city":"Le Claire",
    "sg:classifiers":[
        {
            "category":"Manufacturing",
            "subcategory":"Building Materials",
            "type":"Manufacturing & Wholesale Goods"
        }
    ],
    "sg:phone":"+1 563 289 3711",
    "sg:postcode":"52753",
    "sg:province":"IA",
    "wof:name":"Le Claire Millwork & Cabinetry",
    "wof:placetype":"venue"
},
  "geometry": {"coordinates":[-90.34432700000001,41.59469],"type":"Point"}
}