{
  "type": "Feature",
  "properties": {
    "iso:country":"US",
    "sg:address":"1583 State Hwy 5",
    "sg:city":"Knoxville",
    "sg:classifiers":[
        {
            "category":"Wholesale",
            "subcategory":"Farm Supplies",
            "type":"Manufacturing & Wholesale Goods"
        }
    ],
    "sg:phone":"+1 641 842 2851",
    "sg:postcode":"50138",
    "sg:province":"IA",
    "sg:tags":[
        "auction",
        "livestock",
        "market"
    ],
    "sg:website":"www.knoxreg.com",
    "wof:name":"Knoxville Regional Livestock",
    "wof:placetype":"venue"
},
  "geometry": {"coordinates":[-93.06788,41.292725],"type":"Point"}
}