{
  "type": "Feature",
  "properties": {
    "iso:country":"US",
    "sg:address":"3935 Merle Hay Rd",
    "sg:city":"Des Moines",
    "sg:classifiers":[
        {
            "category":"Retail",
            "subcategory":"Auto Repair",
            "type":"Services"
        }
    ],
    "sg:phone":"+1 515 276 3428",
    "sg:postcode":"50310",
    "sg:province":"IA",
    "sg:tags":[
        "repairing",
        "automobile"
    ],
    "wof:name":"Freedom Tire",
    "wof:placetype":"venue"
},
  "geometry": {"coordinates":[-93.697622,41.632458],"type":"Point"}
}