{
  "type": "Feature",
  "properties": {
    "addr:full":"151 Commercial St Central City IA 52214",
    "addr:housenumber":"151",
    "addr:postcode":"52214",
    "addr:street":"Commercial St",
    "iso:country":"US",
    "sg:address":"151 Commercial St",
    "sg:city":"Central City",
    "sg:classifiers":[
        {
            "category":"Utilities",
            "subcategory":"Refuse",
            "type":"Services"
        }
    ],
    "sg:phone":"+1 319 438 6563",
    "sg:postcode":"52214",
    "sg:province":"IA",
    "sg:tags":[
        "garbage",
        "collection"
    ],
    "wof:name":"Rudd Sanitation Inc",
    "wof:placetype":"venue"
},
  "geometry": {"coordinates":[-91.527463,42.205347],"type":"Point"}
}