{
  "type": "Feature",
  "properties": {
    "iso:country":"US",
    "sg:address":"513 Michigan St",
    "sg:city":"Storm Lake",
    "sg:classifiers":[
        {
            "category":"Personal",
            "subcategory":"Beauty Salon",
            "type":"Services"
        }
    ],
    "sg:phone":"+1 712 749 2912",
    "sg:postcode":"50588",
    "sg:province":"IA",
    "sg:tags":[
        "manicuring"
    ],
    "wof:name":"Tips To Toes Nail Salon",
    "wof:placetype":"venue"
},
  "geometry": {"coordinates":[-95.20197899999999,42.644347],"type":"Point"}
}