{
  "type": "Feature",
  "properties": {
    "iso:country":"US",
    "sg:address":"204 N Mill St",
    "sg:city":"Lake Mills",
    "sg:classifiers":[
        {
            "category":"Manufacturing",
            "subcategory":"Printing",
            "type":"Manufacturing & Wholesale Goods"
        }
    ],
    "sg:phone":"+1 641 592 4222",
    "sg:postcode":"50450",
    "sg:province":"IA",
    "sg:tags":[
        "newspaper"
    ],
    "wof:name":"Lake Mills Graphic",
    "wof:placetype":"venue"
},
  "geometry": {"coordinates":[-93.53479900000001,43.422478],"type":"Point"}
}