{
  "type": "Feature",
  "properties": {
    "iso:country":"US",
    "sg:address":"1505 Winfield Ave",
    "sg:city":"Mt Pleasant",
    "sg:classifiers":[
        {
            "category":"Home & Garden",
            "subcategory":"Garden Supply",
            "type":"Retail Goods"
        }
    ],
    "sg:phone":"+1 319 385 2888",
    "sg:postcode":"52641",
    "sg:province":"IA",
    "sg:tags":[
        "bulb",
        "seed"
    ],
    "wof:name":"Pioneer Seeds",
    "wof:placetype":"venue"
},
  "geometry": {"coordinates":[-91.531632,40.981444],"type":"Point"}
}