{
  "type": "Feature",
  "properties": {
    "iso:country":"US",
    "sg:address":"223 W Washington St",
    "sg:city":"Clarinda",
    "sg:classifiers":[
        {
            "category":"Social Services",
            "subcategory":"Child Care",
            "type":"Services"
        }
    ],
    "sg:phone":"+1 712 542 3652",
    "sg:postcode":"51632",
    "sg:province":"IA",
    "sg:tags":[
        "kindergarten",
        "academic",
        "school"
    ],
    "wof:name":"Clarinda Community Preschool",
    "wof:placetype":"venue"
},
  "geometry": {"coordinates":[-95.04028599999999,40.739377],"type":"Point"}
}