{
  "type": "Feature",
  "properties": {
    "iso:country":"US",
    "sg:address":"608 7th St",
    "sg:city":"Corning",
    "sg:classifiers":[
        {
            "category":"Government",
            "subcategory":"Post Office",
            "type":"Public Place"
        }
    ],
    "sg:phone":"+1 641 322 3646",
    "sg:postcode":"50841",
    "sg:province":"IA",
    "wof:name":"US Post Office",
    "wof:placetype":"venue"
},
  "geometry": {"coordinates":[-94.735764,40.989109],"type":"Point"}
}