{
  "type": "Feature",
  "properties": {
    "addr:full":"4988 20th Ave Aurelia IA 51005",
    "addr:housenumber":"4988",
    "addr:postcode":"51005",
    "addr:street":"20Th Ave Aurelia",
    "iso:country":"US",
    "sg:address":"4988 20th Ave",
    "sg:city":"Aurelia",
    "sg:classifiers":[
        {
            "category":"Farming",
            "subcategory":"Farm",
            "type":"Manufacturing & Wholesale Goods"
        }
    ],
    "sg:phone":"+1 712 434 2266",
    "sg:postcode":"51005",
    "sg:province":"IA",
    "wof:name":"Westphal Farms",
    "wof:placetype":"venue"
},
  "geometry": {"coordinates":[-95.367828,42.793538],"type":"Point"}
}