{
  "type": "Feature",
  "properties": {
    "iso:country":"US",
    "sg:address":"301 N 1st St",
    "sg:city":"Elkader",
    "sg:classifiers":[
        {
            "category":"Retail",
            "subcategory":"Auto Repair",
            "type":"Services"
        }
    ],
    "sg:phone":"+1 563 245 1698",
    "sg:postcode":"52043",
    "sg:province":"IA",
    "sg:tags":[
        "repairing",
        "automobile"
    ],
    "wof:name":"Erickson Pump Svc",
    "wof:placetype":"venue"
},
  "geometry": {"coordinates":[-91.407662,42.856118],"type":"Point"}
}