{
  "type": "Feature",
  "properties": {
    "addr:full":"1362 235th St Modale IA 51556",
    "addr:housenumber":"1362",
    "addr:postcode":"51556",
    "addr:street":"235Th St",
    "iso:country":"US",
    "sg:address":"1362 235th St",
    "sg:city":"Modale",
    "sg:phone":"+1 712 646 2416",
    "sg:postcode":"51556",
    "sg:province":"IA",
    "sg:tags":[
        "farm",
        "corn",
        "soybean"
    ],
    "wof:name":"Mike Johnston",
    "wof:placetype":"venue"
},
  "geometry": {"coordinates":[-96.04604500000001,41.668531],"type":"Point"}
}