{
  "type": "Feature",
  "properties": {
    "iso:country":"US",
    "sg:address":"2255 State Hwy 44",
    "sg:city":"Hamlin",
    "sg:classifiers":[
        {
            "category":"Farming",
            "subcategory":"Livestock Farm",
            "type":"Manufacturing & Wholesale Goods"
        }
    ],
    "sg:phone":"+1 712 563 2070",
    "sg:postcode":"50117",
    "sg:province":"IA",
    "sg:tags":[
        "beef",
        "feedlot",
        "cattle"
    ],
    "wof:name":"Dirk Rasmussen Farm",
    "wof:placetype":"venue"
},
  "geometry": {"coordinates":[-94.849144,41.674191],"type":"Point"}
}