{
  "type": "Feature",
  "properties": {
    "addr:full":"3102 355th St Oxford IA 52322",
    "addr:housenumber":"3102",
    "addr:postcode":"52322",
    "addr:street":"355Th St",
    "iso:country":"US",
    "sg:address":"3102 355th St",
    "sg:city":"Oxford",
    "sg:classifiers":[
        {
            "category":"Professional",
            "type":"Services"
        }
    ],
    "sg:phone":"+1 319 466 0568",
    "sg:postcode":"52322",
    "sg:province":"IA",
    "wof:name":"Lucidforms LLC",
    "wof:placetype":"venue"
},
  "geometry": {"coordinates":[-91.626426,41.675242],"type":"Point"}
}