{
  "type": "Feature",
  "properties": {
    "iso:country":"US",
    "sg:address":"2711 State Hwy 44",
    "sg:city":"Guthrie Center",
    "sg:classifiers":[
        {
            "category":"Travel",
            "subcategory":"Hotels & Motels",
            "type":"Entertainment"
        }
    ],
    "sg:phone":"+1 641 755 4356",
    "sg:postcode":"50115",
    "sg:province":"IA",
    "sg:tags":[
        "breakfast",
        "accommodation",
        "bed"
    ],
    "wof:name":"Prairie View Bed & Breakfast",
    "wof:placetype":"venue"
},
  "geometry": {"coordinates":[-94.402581,41.687895],"type":"Point"}
}