{
  "type": "Feature",
  "properties": {
    "iso:country":"US",
    "sg:address":"100 Kraiburg Blvd",
    "sg:city":"Lisbon",
    "sg:classifiers":[
        {
            "category":"Manufacturing",
            "subcategory":"Rubber & Plastics",
            "type":"Manufacturing & Wholesale Goods"
        }
    ],
    "sg:phone":"+1 319 455 2719",
    "sg:postcode":"52253",
    "sg:province":"IA",
    "sg:tags":[
        "supply"
    ],
    "sg:website":"www.hirail.com",
    "wof:name":"Hirail Corp",
    "wof:placetype":"venue"
},
  "geometry": {"coordinates":[-91.38666499999999,41.930039],"type":"Point"}
}