{
  "type": "Feature",
  "properties": {
    "iso:country":"US",
    "sg:address":"4700 S Lewis Blvd",
    "sg:city":"Sioux City",
    "sg:classifiers":[
        {
            "category":"Manufacturing",
            "subcategory":"Food",
            "type":"Manufacturing & Wholesale Goods"
        }
    ],
    "sg:phone":"+1 712 255 8814",
    "sg:postcode":"51106",
    "sg:province":"IA",
    "sg:tags":[
        "bottler"
    ],
    "wof:name":"Coca-Cola Bottling Co",
    "wof:placetype":"venue"
},
  "geometry": {"coordinates":[-96.366933,42.42577],"type":"Point"}
}