{
  "type": "Feature",
  "properties": {
    "addr:full":"124 S Clinton St Iowa City IA 52240",
    "addr:housenumber":"124",
    "addr:postcode":"52240",
    "addr:street":"S Clinton St",
    "iso:country":"US",
    "sg:address":"124 S Clinton St",
    "sg:city":"Iowa City",
    "sg:classifiers":[
        {
            "category":"Personal",
            "subcategory":"Barber",
            "type":"Services"
        }
    ],
    "sg:phone":"+1 319 354 1239",
    "sg:postcode":"52240",
    "sg:province":"IA",
    "wof:name":"Hawkeye Barber Shop",
    "wof:placetype":"venue"
},
  "geometry": {"coordinates":[-91.534553,41.659145],"type":"Point"}
}