{
  "type": "Feature",
  "properties": {
    "iso:country":"US",
    "sg:address":"2320 5th Ave NW",
    "sg:city":"Waverly",
    "sg:classifiers":[
        {
            "category":"Autos & Motor Vehicles",
            "subcategory":"Automobile Sales",
            "type":"Retail Goods"
        }
    ],
    "sg:phone":"+1 319 352 9000",
    "sg:postcode":"50677",
    "sg:province":"IA",
    "sg:tags":[
        "car",
        "dealer"
    ],
    "sg:website":"www.krueger-auto.com",
    "wof:name":"Krueger Auto & Truck Villa Inc",
    "wof:placetype":"venue"
},
  "geometry": {"coordinates":[-92.503277,42.730143],"type":"Point"}
}