{
  "type": "Feature",
  "properties": {
    "iso:country":"US",
    "sg:address":"1976 Lowe Dr",
    "sg:city":"Harvey",
    "sg:phone":"+1 641 628 2527",
    "sg:postcode":"50119",
    "sg:province":"IA",
    "sg:tags":[
        "farm",
        "corn"
    ],
    "wof:name":"Marion Verros",
    "wof:placetype":"venue"
},
  "geometry": {"coordinates":[-92.97244600000001,41.33213],"type":"Point"}
}