{
  "type": "Feature",
  "properties": {
    "iso:country":"US",
    "sg:address":"703 Dudley St",
    "sg:city":"Decorah",
    "sg:classifiers":[
        {
            "category":"Professional",
            "type":"Services"
        }
    ],
    "sg:phone":"+1 563 382 3639",
    "sg:postcode":"52101",
    "sg:province":"IA",
    "sg:tags":[
        "transportation"
    ],
    "sg:website":"http://www.hawkeyestages.com",
    "wof:name":"Hawkeye Stages Inc",
    "wof:placetype":"venue"
},
  "geometry": {"coordinates":[-91.79286399999999,43.292789],"type":"Point"}
}