{
  "type": "Feature",
  "properties": {
    "iso:country":"US",
    "sg:address":"701 E 18th St",
    "sg:city":"Spencer",
    "sg:classifiers":[
        {
            "category":"Organizations",
            "subcategory":"Religious Organization",
            "type":"Services"
        }
    ],
    "sg:phone":"+1 712 262 2945",
    "sg:postcode":"51301",
    "sg:province":"IA",
    "sg:tags":[
        "church"
    ],
    "wof:name":"First Christian Church",
    "wof:placetype":"venue"
},
  "geometry": {"coordinates":[-95.133511,43.156158],"type":"Point"}
}