{
  "type": "Feature",
  "properties": {
    "iso:country":"US",
    "sg:address":"1456 220th St",
    "sg:city":"Manchester",
    "sg:phone":"+1 563 927 3540",
    "sg:postcode":"52057",
    "sg:province":"IA",
    "sg:tags":[
        "farm",
        "corn",
        "soybean"
    ],
    "wof:name":"Dennis Gudenkauf",
    "wof:placetype":"venue"
},
  "geometry": {"coordinates":[-91.492677,42.46908],"type":"Point"}
}