{
  "type": "Feature",
  "properties": {
    "addr:full":"4500 W Central Park Ave Davenport IA 52801",
    "addr:housenumber":"4500",
    "addr:postcode":"52801",
    "addr:street":"W Central Park Ave",
    "iso:country":"US",
    "sg:address":"4500 W Central Park Ave",
    "sg:city":"Davenport",
    "sg:classifiers":[
        {
            "category":"Sports & Exercise",
            "subcategory":"Golf",
            "type":"Entertainment"
        },
        {
            "category":"Government",
            "subcategory":"Office",
            "type":"Public Place"
        }
    ],
    "sg:phone":"+1 563 326 7825",
    "sg:postcode":"52801",
    "sg:province":"IA",
    "sg:tags":[
        "course",
        "township",
        "government-city",
        "village"
    ],
    "sg:website":"http://www.cityofdavenportiowa.com/department/division.asp?fDD=41-367",
    "wof:name":"Emeis Golf Course",
    "wof:placetype":"venue"
},
  "geometry": {"coordinates":[-90.577499,41.523602],"type":"Point"}
}