{
  "type": "Feature",
  "properties": {
    "iso:country":"US",
    "sg:address":"2138 Stuart Rd",
    "sg:city":"Greenfield",
    "sg:classifiers":[
        {
            "category":"Farming",
            "subcategory":"Farm",
            "type":"Manufacturing & Wholesale Goods"
        }
    ],
    "sg:phone":"+1 641 743 8319",
    "sg:postcode":"50849",
    "sg:province":"IA",
    "sg:tags":[
        "crop",
        "general"
    ],
    "wof:name":"Stamper Car Farm",
    "wof:placetype":"venue"
},
  "geometry": {"coordinates":[-94.31791,41.339119],"type":"Point"}
}