{
  "type": "Feature",
  "properties": {
    "addr:full":"300 W Hutchings St Winterset IA 50273",
    "addr:housenumber":"300",
    "addr:postcode":"50273",
    "addr:street":"W Hutchings St",
    "iso:country":"US",
    "sg:address":"300 W Hutchings St",
    "sg:city":"Winterset",
    "sg:classifiers":[
        {
            "category":"Health Services",
            "subcategory":"Doctor",
            "type":"Services"
        }
    ],
    "sg:phone":"+1 515 462 2950",
    "sg:postcode":"50273",
    "sg:province":"IA",
    "sg:tags":[
        "physician",
        "surgeon"
    ],
    "wof:name":"Health Trust Physicians Clinic",
    "wof:placetype":"venue"
},
  "geometry": {"coordinates":[-94.01836900000001,41.32879],"type":"Point"}
}