{
  "type": "Feature",
  "properties": {
    "iso:country":"US",
    "sg:address":"2830 E 53rd St",
    "sg:city":"Davenport",
    "sg:classifiers":[
        {
            "category":"Home & Garden",
            "subcategory":"Building Materials",
            "type":"Retail Goods"
        }
    ],
    "sg:phone":"+1 563 441 1756",
    "sg:postcode":"52807",
    "sg:province":"IA",
    "sg:tags":[
        "windows"
    ],
    "wof:name":"Pella Window Store",
    "wof:placetype":"venue"
},
  "geometry": {"coordinates":[-90.53268,41.574931],"type":"Point"}
}