{
  "type": "Feature",
  "properties": {
    "addr:full":"3054 380th St Lohrville IA 51453",
    "addr:housenumber":"3054",
    "addr:postcode":"51453",
    "addr:street":"380Th St",
    "iso:country":"US",
    "sg:address":"3054 380th St",
    "sg:city":"Lohrville",
    "sg:phone":"+1 712 465 6805",
    "sg:postcode":"51453",
    "sg:province":"IA",
    "sg:tags":[
        "farm",
        "corn",
        "soybean"
    ],
    "wof:name":"Darrell Hawthorne",
    "wof:placetype":"venue"
},
  "geometry": {"coordinates":[-94.52197700000001,42.238134],"type":"Point"}
}