{
  "type": "Feature",
  "properties": {
    "addr:full":"2302 Spruce Hills Dr Bettendorf IA 52722",
    "addr:housenumber":"2302",
    "addr:postcode":"52722",
    "addr:street":"Spruce Hills Dr",
    "iso:country":"US",
    "sg:address":"2302 Spruce Hills Dr",
    "sg:city":"Bettendorf",
    "sg:classifiers":[
        {
            "category":"Shopping",
            "subcategory":"Department Store",
            "type":"Retail Goods"
        },
        {
            "category":"Shopping",
            "subcategory":"Discount & Variety Stores",
            "type":"Retail Goods"
        },
        {
            "category":"Shopping",
            "type":"Retail Goods"
        },
        {
            "category":"Food & Beverages",
            "subcategory":"Groceries & Convenience Stores",
            "type":"Retail Goods"
        }
    ],
    "sg:phone":"+1 563 344 0212",
    "sg:postcode":"52722",
    "sg:province":"IA",
    "sg:tags":[
        "merchandise"
    ],
    "sg:website":"http://www.dollargeneral.com",
    "wof:name":"Dollar General",
    "wof:placetype":"venue"
},
  "geometry": {"coordinates":[-90.500387,41.548883],"type":"Point"}
}