{
  "type": "Feature",
  "properties": {
    "iso:country":"US",
    "sg:address":"201 Banks St",
    "sg:city":"Randalia",
    "sg:classifiers":[
        {
            "category":"Manufacturing",
            "subcategory":"Rubber & Plastics",
            "type":"Manufacturing & Wholesale Goods"
        }
    ],
    "sg:phone":"+1 563 428 4649",
    "sg:postcode":"52164",
    "sg:province":"IA",
    "wof:name":"Custom Plastics Co",
    "wof:placetype":"venue"
},
  "geometry": {"coordinates":[-91.886713,42.861607],"type":"Point"}
}