{
  "type": "Feature",
  "properties": {
    "iso:country":"US",
    "sg:address":"2213 2nd Ave",
    "sg:city":"Muscatine",
    "sg:classifiers":[
        {
            "category":"Building & Trades",
            "subcategory":"Construction",
            "type":"Services"
        },
        {
            "category":"Manufacturing",
            "subcategory":"Building Materials",
            "type":"Manufacturing & Wholesale Goods"
        }
    ],
    "sg:phone":"+1 563 263 5550",
    "sg:postcode":"52761",
    "sg:province":"IA",
    "sg:tags":[
        "roofing",
        "sheet",
        "work",
        "metal",
        "contractor",
        "siding"
    ],
    "wof:name":"Metal Roofing Solutions",
    "wof:placetype":"venue"
},
  "geometry": {"coordinates":[-91.03556,41.448248],"type":"Point"}
}