{
  "type": "Feature",
  "properties": {
    "addr:full":"203 Norwood Dr Council Bluffs IA 51503",
    "addr:housenumber":"203",
    "addr:postcode":"51503",
    "addr:street":"Norwood Dr",
    "iso:country":"US",
    "sg:address":"203 Norwood Dr",
    "sg:city":"Council Bluffs",
    "sg:classifiers":[
        {
            "category":"Farming",
            "subcategory":"Farm",
            "type":"Manufacturing & Wholesale Goods"
        }
    ],
    "sg:phone":"+1 712 322 0850",
    "sg:postcode":"51503",
    "sg:province":"IA",
    "sg:tags":[
        "crop",
        "general"
    ],
    "wof:name":"Tritsch Farms Inc",
    "wof:placetype":"venue"
},
  "geometry": {"coordinates":[-95.795102,41.244002],"type":"Point"}
}