{
  "type": "Feature",
  "properties": {
    "iso:country":"US",
    "sg:address":"1210 S F St",
    "sg:city":"Oskaloosa",
    "sg:classifiers":[
        {
            "category":"Real Estate",
            "subcategory":"Real Estate Operator",
            "type":"Services"
        }
    ],
    "sg:phone":"+1 641 673 0364",
    "sg:postcode":"52577",
    "sg:province":"IA",
    "sg:tags":[
        "apartment"
    ],
    "wof:name":"Oskaloosa Park Apartments",
    "wof:placetype":"venue"
},
  "geometry": {"coordinates":[-92.652044,41.285215],"type":"Point"}
}