{
  "type": "Feature",
  "properties": {
    "addr:full":"308 4th St Rockwell City IA 50579",
    "addr:housenumber":"308",
    "addr:postcode":"50579",
    "addr:street":"4Th St",
    "iso:country":"US",
    "sg:address":"308 4th St",
    "sg:city":"Rockwell City",
    "sg:classifiers":[
        {
            "category":"Government",
            "subcategory":"Fire Station",
            "type":"Public Place"
        }
    ],
    "sg:phone":"+1 712 297 8530",
    "sg:postcode":"50579",
    "sg:province":"IA",
    "sg:tags":[
        "department"
    ],
    "wof:name":"Rockwell City Fire Dept",
    "wof:placetype":"venue"
},
  "geometry": {"coordinates":[-94.63357000000001,42.396798],"type":"Point"}
}