{
  "type": "Feature",
  "properties": {
    "addr:full":"706 5th St NE Independence IA 50644",
    "addr:housenumber":"706",
    "addr:postcode":"50644",
    "addr:street":"5Th St Ne",
    "iso:country":"US",
    "sg:address":"706 5th St NE",
    "sg:city":"Independence",
    "sg:classifiers":[
        {
            "category":"Home & Garden",
            "subcategory":"Garden Supply",
            "type":"Retail Goods"
        }
    ],
    "sg:phone":"+1 319 334 6621",
    "sg:postcode":"50644",
    "sg:province":"IA",
    "sg:tags":[
        "lawn",
        "mower"
    ],
    "wof:name":"Donald Becker",
    "wof:placetype":"venue"
},
  "geometry": {"coordinates":[-91.88634999999999,42.472562],"type":"Point"}
}