{
  "type": "Feature",
  "properties": {
    "iso:country":"US",
    "sg:address":"578 Graf Ct",
    "sg:city":"Durango",
    "sg:classifiers":[
        {
            "category":"Wholesale",
            "subcategory":"Durable Goods & Equipment",
            "type":"Manufacturing & Wholesale Goods"
        }
    ],
    "sg:phone":"+1 563 557 1935",
    "sg:postcode":"52039",
    "sg:province":"IA",
    "sg:tags":[
        "sawdust",
        "shaving"
    ],
    "wof:name":"KTM LTD-Graff Road",
    "wof:placetype":"venue"
},
  "geometry": {"coordinates":[-90.869685,42.494449],"type":"Point"}
}