{
  "type": "Feature",
  "properties": {
    "iso:country":"US",
    "sg:address":"4760 500th St",
    "sg:city":"Granville",
    "sg:classifiers":[
        {
            "category":"Farming",
            "subcategory":"Farm & Veterinary Services",
            "type":"Manufacturing & Wholesale Goods"
        }
    ],
    "sg:phone":"+1 712 727 3570",
    "sg:postcode":"51022",
    "sg:province":"IA",
    "sg:tags":[
        "livestock"
    ],
    "wof:name":"List Brothers",
    "wof:placetype":"venue"
},
  "geometry": {"coordinates":[-95.847692,42.923853],"type":"Point"}
}