{
  "type": "Feature",
  "properties": {
    "addr:full":"1405 W 9th St S Newton IA 50208",
    "addr:housenumber":"1405",
    "addr:postcode":"50208",
    "addr:street":"W 9Th St S",
    "iso:country":"US",
    "sg:address":"1405 W 9th St S",
    "sg:city":"Newton",
    "sg:classifiers":[
        {
            "category":"Restaurant",
            "type":"Food & Drink"
        }
    ],
    "sg:phone":"+1 641 792 7652",
    "sg:postcode":"50208",
    "sg:province":"IA",
    "wof:name":"V Palmas Steakhouse",
    "wof:placetype":"venue"
},
  "geometry": {"coordinates":[-93.06370800000001,41.68701],"type":"Point"}
}