{
  "type": "Feature",
  "properties": {
    "addr:full":"319 E Traer St Greene IA 50636",
    "addr:housenumber":"319",
    "addr:postcode":"50636",
    "addr:street":"E Traer St",
    "iso:country":"US",
    "sg:address":"319 E Traer St",
    "sg:city":"Greene",
    "sg:classifiers":[
        {
            "category":"Organizations",
            "subcategory":"Religious Organization",
            "type":"Services"
        }
    ],
    "sg:phone":"+1 641 816 4435",
    "sg:postcode":"50636",
    "sg:province":"IA",
    "sg:tags":[
        "church"
    ],
    "wof:name":"Presbyterian Church",
    "wof:placetype":"venue"
},
  "geometry": {"coordinates":[-92.799181,42.897584],"type":"Point"}
}