{
  "type": "Feature",
  "properties": {
    "iso:country":"US",
    "sg:address":"373 W 28th St S",
    "sg:city":"Newton",
    "sg:classifiers":[
        {
            "category":"Building & Trades",
            "subcategory":"Construction",
            "type":"Services"
        }
    ],
    "sg:phone":"+1 641 792 8807",
    "sg:postcode":"50208",
    "sg:province":"IA",
    "sg:tags":[
        "contractor"
    ],
    "wof:name":"Eds Contracting",
    "wof:placetype":"venue"
},
  "geometry": {"coordinates":[-93.08703800000001,41.696269],"type":"Point"}
}