{
  "type": "Feature",
  "properties": {
    "iso:country":"US",
    "sg:address":"2310 E 46th Pl",
    "sg:city":"Davenport",
    "sg:classifiers":[
        {
            "category":"Professional",
            "subcategory":"Management & Consulting",
            "type":"Services"
        }
    ],
    "sg:phone":"+1 563 359 7477",
    "sg:postcode":"52807",
    "sg:province":"IA",
    "wof:name":"Bevinco",
    "wof:placetype":"venue"
},
  "geometry": {"coordinates":[-90.543812,41.568713],"type":"Point"}
}