{
  "type": "Feature",
  "properties": {
    "addr:full":"20748 115th Ave Sperry IA 52650",
    "addr:housenumber":"20748",
    "addr:postcode":"52650",
    "addr:street":"115Th Ave",
    "iso:country":"US",
    "sg:address":"20748 115th Ave",
    "sg:city":"Sperry",
    "sg:classifiers":[
        {
            "category":"Retail",
            "subcategory":"Repair Shop",
            "type":"Services"
        }
    ],
    "sg:phone":"+1 319 985 2171",
    "sg:postcode":"52650",
    "sg:province":"IA",
    "wof:name":"Dons Service Center",
    "wof:placetype":"venue"
},
  "geometry": {"coordinates":[-91.15166600000001,40.975869],"type":"Point"}
}