{
  "type": "Feature",
  "properties": {
    "addr:full":"5504 Walford Rd SW Fairfax IA 52228",
    "addr:housenumber":"5504",
    "addr:postcode":"52228",
    "addr:street":"Walford Rd Sw",
    "iso:country":"US",
    "sg:address":"5504 Walford Rd SW",
    "sg:city":"Fairfax",
    "sg:classifiers":[
        {
            "category":"Building & Trades",
            "subcategory":"Construction",
            "type":"Services"
        }
    ],
    "sg:phone":"+1 319 846 2430",
    "sg:postcode":"52228",
    "sg:province":"IA",
    "sg:tags":[
        "house"
    ],
    "wof:name":"Van Weelden Construction",
    "wof:placetype":"venue"
},
  "geometry": {"coordinates":[-91.742267,41.876597],"type":"Point"}
}