{
  "type": "Feature",
  "properties": {
    "iso:country":"US",
    "sg:address":"4085 Valley Ave",
    "sg:city":"Riceville",
    "sg:classifiers":[
        {
            "category":"Wholesale",
            "subcategory":"Farm Supplies",
            "type":"Manufacturing & Wholesale Goods"
        }
    ],
    "sg:phone":"+1 641 985 2476",
    "sg:postcode":"50466",
    "sg:province":"IA",
    "sg:tags":[
        "feed"
    ],
    "wof:name":"Larry Fox Feed Lot",
    "wof:placetype":"venue"
},
  "geometry": {"coordinates":[-92.613877,43.353852],"type":"Point"}
}