{
  "type": "Feature",
  "properties": {
    "iso:country":"US",
    "sg:address":"108 S Franklin St",
    "sg:city":"Manchester",
    "sg:classifiers":[
        {
            "category":"Real Estate",
            "subcategory":"Real Estate Agent",
            "type":"Services"
        }
    ],
    "sg:phone":"+1 563 927 5600",
    "sg:postcode":"52057",
    "sg:province":"IA",
    "wof:name":"Iowa Realty Co",
    "wof:placetype":"venue"
},
  "geometry": {"coordinates":[-91.457829,42.483896],"type":"Point"}
}