{
  "type": "Feature",
  "properties": {
    "iso:country":"US",
    "sg:address":"4755 20th St",
    "sg:city":"Grinnell",
    "sg:classifiers":[
        {
            "category":"Farming",
            "subcategory":"Farm",
            "type":"Manufacturing & Wholesale Goods"
        }
    ],
    "sg:phone":"+1 641 593 6513",
    "sg:postcode":"50112",
    "sg:province":"IA",
    "wof:name":"KDD Inc",
    "wof:placetype":"venue"
},
  "geometry": {"coordinates":[-92.74641,41.607601],"type":"Point"}
}