{
  "type": "Feature",
  "properties": {
    "iso:country":"US",
    "sg:address":"519 W 4th St S",
    "sg:city":"Newton",
    "sg:classifiers":[
        {
            "category":"Building & Trades",
            "subcategory":"Construction",
            "type":"Services"
        }
    ],
    "sg:phone":"+1 641 792 6375",
    "sg:postcode":"50208",
    "sg:province":"IA",
    "sg:tags":[
        "contractor"
    ],
    "wof:name":"Lundin Le Roofing",
    "wof:placetype":"venue"
},
  "geometry": {"coordinates":[-93.058049,41.695418],"type":"Point"}
}