{
  "type": "Feature",
  "properties": {
    "addr:full":"1427 Army Post Rd Des Moines IA 50315",
    "addr:housenumber":"1427",
    "addr:postcode":"50315",
    "addr:street":"Army Post Rd Des",
    "iso:country":"US",
    "sg:address":"1427 Army Post Rd",
    "sg:city":"Des Moines",
    "sg:classifiers":[
        {
            "category":"Shopping",
            "type":"Retail Goods"
        }
    ],
    "sg:phone":"+1 515 256 9097",
    "sg:postcode":"50315",
    "sg:province":"IA",
    "sg:tags":[
        "art",
        "gallery",
        "dealer"
    ],
    "wof:name":"Studio Of Larry Anderson",
    "wof:placetype":"venue"
},
  "geometry": {"coordinates":[-93.63781,41.526618],"type":"Point"}
}