{
  "type": "Feature",
  "properties": {
    "iso:country":"US",
    "sg:address":"8737 Fir Ave",
    "sg:city":"Riceville",
    "sg:classifiers":[
        {
            "category":"Farming",
            "subcategory":"Livestock Farm",
            "type":"Manufacturing & Wholesale Goods"
        }
    ],
    "sg:phone":"+1 641 985 4014",
    "sg:postcode":"50466",
    "sg:province":"IA",
    "sg:tags":[
        "animal",
        "general"
    ],
    "wof:name":"Christopher Back",
    "wof:placetype":"venue"
},
  "geometry": {"coordinates":[-92.455674,43.389538],"type":"Point"}
}