{
  "type": "Feature",
  "properties": {
    "iso:country":"US",
    "sg:address":"523 N 7th Ave",
    "sg:city":"Washington",
    "sg:classifiers":[
        {
            "category":"Retail",
            "subcategory":"Auto Repair",
            "type":"Services"
        }
    ],
    "sg:phone":"+1 319 653 6113",
    "sg:postcode":"52353",
    "sg:province":"IA",
    "sg:tags":[
        "truck"
    ],
    "wof:name":"Hiway Service Ctr Inc",
    "wof:placetype":"venue"
},
  "geometry": {"coordinates":[-91.68465500000001,41.302032],"type":"Point"}
}