{
  "type": "Feature",
  "properties": {
    "addr:full":"2705 SW 9th St Des Moines IA 50315",
    "addr:housenumber":"2705",
    "addr:postcode":"50315",
    "addr:street":"Sw 9Th St",
    "iso:country":"US",
    "sg:address":"2705 SW 9th St",
    "sg:city":"Des Moines",
    "sg:classifiers":[
        {
            "category":"Banks & Credit Unions",
            "subcategory":"Bank",
            "type":"Services"
        }
    ],
    "sg:phone":"+1 515 243 6666",
    "sg:postcode":"50315",
    "sg:province":"IA",
    "sg:tags":[
        "cashing",
        "check"
    ],
    "wof:name":"Check 'n Go",
    "wof:placetype":"venue"
},
  "geometry": {"coordinates":[-93.625626,41.560301],"type":"Point"}
}