{
  "type": "Feature",
  "properties": {
    "addr:full":"421 N Main St Centerville IA 52544",
    "addr:housenumber":"421",
    "addr:postcode":"52544",
    "addr:street":"N Main St",
    "iso:country":"US",
    "sg:address":"421 N Main St",
    "sg:city":"Centerville",
    "sg:classifiers":[
        {
            "category":"Home & Garden",
            "subcategory":"Household Appliances",
            "type":"Retail Goods"
        }
    ],
    "sg:phone":"+1 641 437 4442",
    "sg:postcode":"52544",
    "sg:province":"IA",
    "sg:tags":[
        "cleaners",
        "vacuum"
    ],
    "wof:name":"Main Street Distributing",
    "wof:placetype":"venue"
},
  "geometry": {"coordinates":[-92.874122,40.735729],"type":"Point"}
}