{
  "type": "Feature",
  "properties": {
    "iso:country":"US",
    "sg:address":"4022 E 53rd St",
    "sg:city":"Davenport",
    "sg:classifiers":[
        {
            "category":"Home & Garden",
            "subcategory":"Home Furnishings",
            "type":"Retail Goods"
        }
    ],
    "sg:phone":"+1 563 344 0112",
    "sg:postcode":"52807",
    "sg:province":"IA",
    "sg:tags":[
        "linen"
    ],
    "sg:website":"www.bedbathandbeyond.com",
    "wof:name":"Bed Bath & Beyond",
    "wof:placetype":"venue"
},
  "geometry": {"coordinates":[-90.52112700000001,41.574718],"type":"Point"}
}