{
  "type": "Feature",
  "properties": {
    "addr:full":"203 N Main St Maquoketa IA 52060",
    "addr:housenumber":"203",
    "addr:postcode":"52060",
    "addr:street":"N Main St",
    "iso:country":"US",
    "sg:address":"203 N Main St",
    "sg:city":"Maquoketa",
    "sg:classifiers":[
        {
            "category":"Banks & Credit Unions",
            "subcategory":"Investment Brokerage",
            "type":"Services"
        }
    ],
    "sg:phone":"+1 563 652 6868",
    "sg:postcode":"52060",
    "sg:province":"IA",
    "sg:tags":[
        "security"
    ],
    "wof:name":"Linsco Private Ledger",
    "wof:placetype":"venue"
},
  "geometry": {"coordinates":[-90.66543299999999,42.070919],"type":"Point"}
}