{
  "type": "Feature",
  "properties": {
    "iso:country":"US",
    "sg:address":"4020 E 53rd St",
    "sg:city":"Davenport",
    "sg:classifiers":[
        {
            "category":"Restaurant",
            "type":"Food & Drink"
        }
    ],
    "sg:menulink":"http://www.allmenus.com/ia/davenport/110136-chilis/menu/",
    "sg:phone":"+1 563 359 1144",
    "sg:postcode":"52807",
    "sg:province":"IA",
    "sg:tags":[
        "burger",
        "american",
        "sandwich",
        "tex-mex",
        "soup"
    ],
    "wof:name":"Chili's",
    "wof:placetype":"venue"
},
  "geometry": {"coordinates":[-90.51553199999999,41.574959],"type":"Point"}
}