{
  "type": "Feature",
  "properties": {
    "iso:country":"US",
    "sg:address":"1216 2nd St",
    "sg:city":"Perry",
    "sg:classifiers":[
        {
            "category":"Home & Garden",
            "subcategory":"Home Furnishings",
            "type":"Retail Goods"
        }
    ],
    "sg:phone":"+1 515 465 4472",
    "sg:postcode":"50220",
    "sg:province":"IA",
    "sg:tags":[
        "curtain",
        "made",
        "drapery"
    ],
    "wof:name":"Perry Paint & Glass Co",
    "wof:placetype":"venue"
},
  "geometry": {"coordinates":[-94.10508900000001,41.840397],"type":"Point"}
}