{
  "type": "Feature",
  "properties": {
    "iso:country":"US",
    "sg:address":"1000 S West St",
    "sg:city":"Lake City",
    "sg:classifiers":[
        {
            "category":"Building & Trades",
            "subcategory":"Construction",
            "type":"Services"
        }
    ],
    "sg:phone":"+1 712 464 3398",
    "sg:postcode":"51449",
    "sg:province":"IA",
    "sg:tags":[
        "repairing",
        "remodeling",
        "contractor"
    ],
    "wof:name":"Redenius Construction",
    "wof:placetype":"venue"
},
  "geometry": {"coordinates":[-94.736237,42.259632],"type":"Point"}
}