{
  "type": "Feature",
  "properties": {
    "iso:country":"US",
    "sg:address":"3713 Green Ave",
    "sg:city":"Sioux City",
    "sg:classifiers":[
        {
            "category":"Organizations",
            "subcategory":"Religious Organization",
            "type":"Services"
        }
    ],
    "sg:phone":"+1 712 252 5212",
    "sg:postcode":"51106",
    "sg:province":"SD",
    "sg:tags":[
        "church"
    ],
    "wof:name":"Jehovah's Witnesses-Sioux City",
    "wof:placetype":"venue"
},
  "geometry": {"coordinates":[-96.361387,42.488385],"type":"Point"}
}