{
  "type": "Feature",
  "properties": {
    "iso:country":"US",
    "sg:address":"3716 1st Ave NE",
    "sg:city":"Cedar Rapids",
    "sg:classifiers":[
        {
            "category":"Professional",
            "subcategory":"Lawyer & Legal Services",
            "type":"Services"
        }
    ],
    "sg:phone":"+1 319 297 7222",
    "sg:postcode":"52402",
    "sg:province":"IA",
    "sg:tags":[
        "attorney"
    ],
    "wof:name":"Piersall Law Firm",
    "wof:placetype":"venue"
},
  "geometry": {"coordinates":[-91.634592,42.016899],"type":"Point"}
}