{
  "type": "Feature",
  "properties": {
    "iso:country":"US",
    "sg:address":"5321 Council St NE",
    "sg:city":"Cedar Rapids",
    "sg:classifiers":[
        {
            "category":"Banks & Credit Unions",
            "subcategory":"Bank",
            "type":"Services"
        }
    ],
    "sg:phone":"+1 319 378 3183",
    "sg:postcode":"52402",
    "sg:province":"IA",
    "wof:name":"U S Bank",
    "wof:placetype":"venue"
},
  "geometry": {"coordinates":[-91.65830200000001,42.032299],"type":"Point"}
}