{
  "type": "Feature",
  "properties": {
    "iso:country":"US",
    "sg:address":"5802 Hickman Rd",
    "sg:city":"Des Moines",
    "sg:classifiers":[
        {
            "category":"Retail",
            "subcategory":"Laundry & Dry Cleaning",
            "type":"Services"
        },
        {
            "category":"Shopping",
            "subcategory":"Clothing, Apparel, & Fashions",
            "type":"Retail Goods"
        }
    ],
    "sg:phone":"+1 515 306 4586",
    "sg:postcode":"50322",
    "sg:province":"IA",
    "sg:tags":[
        "tailor",
        "alteration",
        "clothes"
    ],
    "wof:name":"Hickman Tailors",
    "wof:placetype":"venue"
},
  "geometry": {"coordinates":[-93.69895699999999,41.614809],"type":"Point"}
}