{
  "type": "Feature",
  "properties": {
    "addr:full":"12 N Washington St Remsen IA 51050",
    "addr:housenumber":"12",
    "addr:postcode":"51050",
    "addr:street":"N Washington St",
    "iso:country":"US",
    "sg:address":"12 N Washington St",
    "sg:city":"Remsen",
    "sg:classifiers":[
        {
            "category":"Mining & Drilling",
            "type":"Manufacturing & Wholesale Goods"
        }
    ],
    "sg:phone":"+1 712 786 2238",
    "sg:postcode":"51050",
    "sg:province":"IA",
    "sg:tags":[
        "operator",
        "oil"
    ],
    "wof:name":"Amsoil Synthetic Oils",
    "wof:placetype":"venue"
},
  "geometry": {"coordinates":[-95.973331,42.818117],"type":"Point"}
}