{
  "type": "Feature",
  "properties": {
    "addr:full":"527 Lyons Ave Denison IA 51442",
    "addr:housenumber":"527",
    "addr:postcode":"51442",
    "addr:street":"Lyons Ave",
    "iso:country":"US",
    "sg:address":"527 Lyons Ave",
    "sg:city":"Denison",
    "sg:classifiers":[
        {
            "category":"Shopping",
            "subcategory":"Used Merchandise",
            "type":"Retail Goods"
        }
    ],
    "sg:phone":"+1 712 263 2026",
    "sg:postcode":"51442",
    "sg:province":"IA",
    "wof:name":"Allens Antiques",
    "wof:placetype":"venue"
},
  "geometry": {"coordinates":[-95.344718,42.023208],"type":"Point"}
}