{
  "type": "Feature",
  "properties": {
    "iso:country":"US",
    "sg:address":"406 Cass St",
    "sg:city":"Keosauqua",
    "sg:classifiers":[
        {
            "category":"Organizations",
            "subcategory":"Religious Organization",
            "type":"Services"
        }
    ],
    "sg:phone":"+1 319 293 3447",
    "sg:postcode":"52565",
    "sg:province":"IA",
    "sg:tags":[
        "church"
    ],
    "wof:name":"United Methodist Church",
    "wof:placetype":"venue"
},
  "geometry": {"coordinates":[-91.964536,40.732612],"type":"Point"}
}