{
  "type": "Feature",
  "properties": {
    "addr:full":"3134 1st Ave NE Cedar Rapids IA 52402",
    "addr:housenumber":"3134",
    "addr:postcode":"52402",
    "addr:street":"1St Ave Ne",
    "iso:country":"US",
    "sg:address":"3134 1st Ave NE",
    "sg:city":"Cedar Rapids",
    "sg:classifiers":[
        {
            "category":"Food & Beverages",
            "subcategory":"Groceries & Convenience Stores",
            "type":"Retail Goods"
        }
    ],
    "sg:phone":"+1 319 364 6839",
    "sg:postcode":"52402",
    "sg:province":"IA",
    "wof:name":"KWIK Shop",
    "wof:placetype":"venue"
},
  "geometry": {"coordinates":[-91.635006,42.0094],"type":"Point"}
}