{
  "type": "Feature",
  "properties": {
    "addr:full":"5615 SW 14th St Des Moines IA 50315",
    "addr:housenumber":"5615",
    "addr:postcode":"50315",
    "addr:street":"Sw 14Th St",
    "iso:country":"US",
    "sg:address":"5615 SW 14th St",
    "sg:city":"Des Moines",
    "sg:classifiers":[
        {
            "category":"Organizations",
            "subcategory":"Religious Organization",
            "type":"Services"
        }
    ],
    "sg:phone":"+1 515 285 3769",
    "sg:postcode":"50315",
    "sg:province":"IA",
    "sg:tags":[
        "church"
    ],
    "wof:name":"Peace Evangelical Lutheran Chr",
    "wof:placetype":"venue"
},
  "geometry": {"coordinates":[-93.63531399999999,41.532757],"type":"Point"}
}