{
  "type": "Feature",
  "properties": {
    "addr:full":"709 Furnas Dr Osceola IA 50213",
    "addr:housenumber":"709",
    "addr:postcode":"50213",
    "addr:street":"Furnas Dr",
    "iso:country":"US",
    "sg:address":"709 Furnas Dr",
    "sg:city":"Osceola",
    "sg:classifiers":[
        {
            "category":"Professional",
            "subcategory":"Management & Consulting",
            "type":"Services"
        }
    ],
    "sg:phone":"+1 641 342 2944",
    "sg:postcode":"50213",
    "sg:province":"IA",
    "sg:tags":[
        "development",
        "industrial"
    ],
    "wof:name":"Clarke County Development Corp",
    "wof:placetype":"venue"
},
  "geometry": {"coordinates":[-93.78309,41.028504],"type":"Point"}
}