{
  "type": "Feature",
  "properties": {
    "addr:full":"200 7th St Victor IA 52347",
    "addr:housenumber":"200",
    "addr:postcode":"ia 52347",
    "addr:street":"7Th St",
    "iso:country":"US",
    "sg:address":"200 7th St",
    "sg:city":"Victor",
    "sg:phone":"+1 319 647 3528",
    "sg:postcode":"52347",
    "sg:province":"IA",
    "sg:tags":[
        "gas"
    ],
    "wof:name":"Harden Brothers Propane Inc",
    "wof:placetype":"venue"
},
  "geometry": {"coordinates":[-92.29155799999999,41.727737],"type":"Point"}
}