{
  "type": "Feature",
  "properties": {
    "addr:full":"777 3rd St Des Moines IA 50309",
    "addr:housenumber":"777",
    "addr:postcode":"50309",
    "addr:street":"3Rd St",
    "iso:country":"US",
    "sg:address":"777 3rd St",
    "sg:city":"Des Moines",
    "sg:classifiers":[
        {
            "category":"Organizations",
            "subcategory":"Professional Association",
            "type":"Services"
        }
    ],
    "sg:phone":"+1 515 471 8050",
    "sg:postcode":"50309",
    "sg:province":"IA",
    "wof:name":"Polk Suburban Uni Serve Unit",
    "wof:placetype":"venue"
},
  "geometry": {"coordinates":[-93.621415,41.59073],"type":"Point"}
}