{
  "type": "Feature",
  "properties": {
    "addr:full":"702 Washington Ave Iowa Falls IA 50126",
    "addr:housenumber":"702",
    "addr:postcode":"50126",
    "addr:street":"Washington Ave",
    "iso:country":"US",
    "sg:address":"702 Washington Ave",
    "sg:city":"Iowa Falls",
    "sg:classifiers":[
        {
            "category":"Banks & Credit Unions",
            "subcategory":"Investment Brokerage",
            "type":"Services"
        }
    ],
    "sg:phone":"+1 641 648 4656",
    "sg:postcode":"50126",
    "sg:province":"IA",
    "sg:tags":[
        "stock",
        "bond"
    ],
    "wof:name":"Edward Jones Co",
    "wof:placetype":"venue"
},
  "geometry": {"coordinates":[-93.266655,42.519711],"type":"Point"}
}