{
  "type": "Feature",
  "properties": {
    "iso:country":"US",
    "sg:address":"3265 W 4th St",
    "sg:city":"Waterloo",
    "sg:classifiers":[
        {
            "category":"Professional",
            "subcategory":"Lawyer & Legal Services",
            "type":"Services"
        }
    ],
    "sg:phone":"+1 319 234 6843",
    "sg:postcode":"50701",
    "sg:province":"IA",
    "sg:tags":[
        "attorney"
    ],
    "wof:name":"Mason Law Office",
    "wof:placetype":"venue"
},
  "geometry": {"coordinates":[-92.37696699999999,42.472735],"type":"Point"}
}