{
  "type": "Feature",
  "properties": {
    "iso:country":"US",
    "sg:address":"22386 40th St",
    "sg:city":"Oelwein",
    "sg:phone":"+1 319 635 2998",
    "sg:postcode":"50662",
    "sg:province":"IA",
    "sg:tags":[
        "farm",
        "corn"
    ],
    "wof:name":"Jerry Bayness",
    "wof:placetype":"venue"
},
  "geometry": {"coordinates":[-92.028469,42.685866],"type":"Point"}
}