{
  "type": "Feature",
  "properties": {
    "iso:country":"US",
    "sg:address":"1700 N 15th St",
    "sg:city":"Fort Dodge",
    "sg:classifiers":[
        {
            "category":"Real Estate",
            "subcategory":"Developer",
            "type":"Services"
        }
    ],
    "sg:phone":"+1 515 576 2923",
    "sg:postcode":"50501",
    "sg:province":"IA",
    "sg:tags":[
        "cemetery"
    ],
    "wof:name":"Catholic Cemetery Improvement",
    "wof:placetype":"venue"
},
  "geometry": {"coordinates":[-94.17805300000001,42.521764],"type":"Point"}
}