{
  "type": "Feature",
  "properties": {
    "addr:full":"1021 N 18th St Centerville IA 52544",
    "addr:housenumber":"1021",
    "addr:postcode":"52544",
    "addr:street":"N 18Th St",
    "iso:country":"US",
    "sg:address":"1021 N 18th St",
    "sg:city":"Centerville",
    "sg:classifiers":[
        {
            "category":"Travel",
            "subcategory":"Hotels & Motels",
            "type":"Entertainment"
        }
    ],
    "sg:phone":"+1 641 856 8888",
    "sg:postcode":"52544",
    "sg:province":"IA",
    "sg:tags":[
        "lodging"
    ],
    "sg:website":"http://www.super8.com",
    "wof:name":"Super 8 Motel",
    "wof:placetype":"venue"
},
  "geometry": {"coordinates":[-92.864971,40.749041],"type":"Point"}
}