{
  "type": "Feature",
  "properties": {
    "addr:full":"825 Valley St Mediapolis IA 52637",
    "addr:housenumber":"825",
    "addr:postcode":"52637",
    "addr:street":"Valley St",
    "iso:country":"US",
    "sg:address":"825 Valley St",
    "sg:city":"Mediapolis",
    "sg:classifiers":[
        {
            "category":"Shopping",
            "subcategory":"Department Store",
            "type":"Retail Goods"
        }
    ],
    "sg:phone":"+1 319 394 9539",
    "sg:postcode":"52637",
    "sg:province":"IA",
    "wof:name":"LC's Discount Warehouse",
    "wof:placetype":"venue"
},
  "geometry": {"coordinates":[-91.16075600000001,41.011164],"type":"Point"}
}