{
  "type": "Feature",
  "properties": {
    "iso:country":"US",
    "sg:address":"106 Maquoketa St",
    "sg:city":"Anamosa",
    "sg:classifiers":[
        {
            "category":"Personal",
            "subcategory":"Beauty Salon",
            "type":"Services"
        }
    ],
    "sg:phone":"+1 319 462 3291",
    "sg:postcode":"52205",
    "sg:province":"IA",
    "wof:name":"Corner Cutters",
    "wof:placetype":"venue"
},
  "geometry": {"coordinates":[-91.276385,42.109315],"type":"Point"}
}