{
  "type": "Feature",
  "properties": {
    "iso:country":"US",
    "sg:address":"833 4th Ave",
    "sg:city":"Grinnell",
    "sg:classifiers":[
        {
            "category":"Banks & Credit Unions",
            "subcategory":"Bank",
            "type":"Services"
        }
    ],
    "sg:phone":"+1 641 236 7575",
    "sg:postcode":"50112",
    "sg:province":"IA",
    "wof:name":"Wells Fargo Bank",
    "wof:placetype":"venue"
},
  "geometry": {"coordinates":[-92.725354,41.743306],"type":"Point"}
}