{
  "type": "Feature",
  "properties": {
    "iso:country":"US",
    "sg:address":"4655 121st St",
    "sg:city":"Urbandale",
    "sg:classifiers":[
        {
            "category":"Education",
            "subcategory":"College",
            "type":"Public Place"
        }
    ],
    "sg:phone":"+1 515 727 2100",
    "sg:postcode":"50323",
    "sg:province":"IA",
    "sg:tags":[
        "academic",
        "school"
    ],
    "wof:name":"Hamilton College",
    "wof:placetype":"venue"
},
  "geometry": {"coordinates":[-93.779731,41.648886],"type":"Point"}
}