{
  "type": "Feature",
  "properties": {
    "iso:country":"US",
    "sg:address":"208 E Army Post Rd",
    "sg:city":"Des Moines",
    "sg:classifiers":[
        {
            "category":"Shopping",
            "subcategory":"Used Merchandise",
            "type":"Retail Goods"
        }
    ],
    "sg:phone":"+1 515 285 5715",
    "sg:postcode":"50315",
    "sg:province":"IA",
    "sg:tags":[
        "pawnbroker"
    ],
    "wof:name":"Pawn Specialist Inc",
    "wof:placetype":"venue"
},
  "geometry": {"coordinates":[-93.61147,41.526469],"type":"Point"}
}