{
  "type": "Feature",
  "properties": {
    "iso:country":"US",
    "sg:address":"7373 NE Bluff Dr",
    "sg:city":"Bondurant",
    "sg:classifiers":[
        {
            "category":"Building & Trades",
            "subcategory":"Construction",
            "type":"Services"
        }
    ],
    "sg:phone":"+1 515 967 2843",
    "sg:postcode":"50035",
    "sg:province":"IA",
    "sg:tags":[
        "carpentry",
        "contractor"
    ],
    "wof:name":"Altman Trim Carpentry",
    "wof:placetype":"venue"
},
  "geometry": {"coordinates":[-93.460902,41.778626],"type":"Point"}
}