{
  "type": "Feature",
  "properties": {
    "iso:country":"US",
    "sg:address":"4212 Sue Linda Cir NE",
    "sg:city":"Iowa City",
    "sg:classifiers":[
        {
            "category":"Building & Trades",
            "subcategory":"Construction",
            "type":"Services"
        }
    ],
    "sg:phone":"+1 319 338 5720",
    "sg:postcode":"52240",
    "sg:province":"IA",
    "sg:tags":[
        "general",
        "contractor"
    ],
    "wof:name":"Boyd Crosby Construction",
    "wof:placetype":"venue"
},
  "geometry": {"coordinates":[-91.52151000000001,41.707377],"type":"Point"}
}