{
  "type": "Feature",
  "properties": {
    "iso:country":"US",
    "sg:address":"1701 Mount Pleasant St",
    "sg:city":"Burlington",
    "sg:classifiers":[
        {
            "category":"Travel",
            "subcategory":"Hotels & Motels",
            "type":"Entertainment"
        }
    ],
    "sg:phone":"+1 319 752 2748",
    "sg:postcode":"52601",
    "sg:province":"IA",
    "wof:name":"Lincolnville Motel",
    "wof:placetype":"venue"
},
  "geometry": {"coordinates":[-91.12230599999999,40.820004],"type":"Point"}
}