{
  "type": "Feature",
  "properties": {
    "iso:country":"US",
    "sg:address":"2220 140th St",
    "sg:city":"Essex",
    "sg:classifiers":[
        {
            "category":"Professional",
            "subcategory":"Management & Consulting",
            "type":"Services"
        }
    ],
    "sg:phone":"+1 712 586 4541",
    "sg:postcode":"51638",
    "sg:province":"IA",
    "sg:tags":[
        "business"
    ],
    "wof:name":"Image Professional Training",
    "wof:placetype":"venue"
},
  "geometry": {"coordinates":[-95.15248699999999,40.842993],"type":"Point"}
}