{
  "type": "Feature",
  "properties": {
    "addr:full":"2094 Morningview Rd Dubuque IA 52001",
    "addr:housenumber":"2094",
    "addr:postcode":"52001",
    "addr:street":"Morningview Rd",
    "iso:country":"US",
    "sg:address":"2094 Morningview Rd",
    "sg:city":"Dubuque",
    "sg:classifiers":[
        {
            "category":"Shopping",
            "type":"Retail Goods"
        }
    ],
    "sg:phone":"+1 563 583 8087",
    "sg:postcode":"52001",
    "sg:province":"IA",
    "sg:tags":[
        "merchandise"
    ],
    "wof:name":"Germain Fine Art & Associates",
    "wof:placetype":"venue"
},
  "geometry": {"coordinates":[-90.709222,42.505657],"type":"Point"}
}