{
  "type": "Feature",
  "properties": {
    "iso:country":"US",
    "sg:address":"2508 Lincoln Way",
    "sg:city":"Ames",
    "sg:classifiers":[
        {
            "category":"Restaurant",
            "type":"Food & Drink"
        }
    ],
    "sg:phone":"+1 515 268 1530",
    "sg:postcode":"50014",
    "sg:province":"IA",
    "wof:name":"Pita Pita",
    "wof:placetype":"venue"
},
  "geometry": {"coordinates":[-93.650071,42.022804],"type":"Point"}
}