{
  "type": "Feature",
  "properties": {
    "iso:country":"US",
    "sg:address":"4134 250th St",
    "sg:city":"George",
    "sg:phone":"+1 712 475 3528",
    "sg:postcode":"51237",
    "sg:province":"IA",
    "sg:tags":[
        "farm",
        "corn"
    ],
    "wof:name":"David Daniels",
    "wof:placetype":"venue"
},
  "geometry": {"coordinates":[-95.97411700000001,43.286873],"type":"Point"}
}