{
  "type": "Feature",
  "properties": {
    "iso:country":"US",
    "sg:address":"4425 Singing Hills Blvd",
    "sg:city":"Sioux City",
    "sg:classifiers":[
        {
            "category":"Professional",
            "subcategory":"Engineering",
            "type":"Services"
        }
    ],
    "sg:phone":"+1 712 266 1554",
    "sg:postcode":"51106",
    "sg:province":"SD",
    "sg:tags":[
        "engineer"
    ],
    "sg:website":"www.dgrnet.com",
    "wof:name":"Dewild Grant Reckert & Assoc",
    "wof:placetype":"venue"
},
  "geometry": {"coordinates":[-96.346729,42.437406],"type":"Point"}
}