{
  "type": "Feature",
  "properties": {
    "addr:full":"14184 130th St Bristow IA 50611",
    "addr:housenumber":"14184",
    "addr:postcode":"50611",
    "addr:street":"130Th St",
    "iso:country":"US",
    "sg:address":"14184 130th St",
    "sg:city":"Bristow",
    "sg:classifiers":[
        {
            "category":"Wholesale",
            "subcategory":"Construction Materials",
            "type":"Manufacturing & Wholesale Goods"
        }
    ],
    "sg:phone":"+1 641 894 3368",
    "sg:postcode":"50611",
    "sg:province":"IA",
    "sg:tags":[
        "sand",
        "gravel"
    ],
    "wof:name":"Ayers Lime & Rock",
    "wof:placetype":"venue"
},
  "geometry": {"coordinates":[-92.942803,42.862155],"type":"Point"}
}