{
  "type": "Feature",
  "properties": {
    "addr:full":"211 N Franklin St Manchester IA 52057",
    "addr:housenumber":"211",
    "addr:postcode":"52057",
    "addr:street":"N Franklin St",
    "iso:country":"US",
    "sg:address":"211 N Franklin St",
    "sg:city":"Manchester",
    "sg:classifiers":[
        {
            "category":"Restaurant",
            "type":"Food & Drink"
        }
    ],
    "sg:phone":"+1 563 927 2058",
    "sg:postcode":"52057",
    "sg:province":"IA",
    "wof:name":"Jude's Cafe",
    "wof:placetype":"venue"
},
  "geometry": {"coordinates":[-91.45786200000001,42.485683],"type":"Point"}
}