{
  "type": "Feature",
  "properties": {
    "addr:full":"5208 Boulder Dr West Des Moines IA 50265",
    "addr:housenumber":"5208",
    "addr:postcode":"50265",
    "addr:street":"Boulder Dr",
    "iso:country":"US",
    "sg:address":"5208 Boulder Dr",
    "sg:city":"West Des Moines",
    "sg:classifiers":[
        {
            "category":"Insurance",
            "subcategory":"Insurance Agent",
            "type":"Services"
        }
    ],
    "sg:phone":"+1 515 225 9663",
    "sg:postcode":"50265",
    "sg:province":"IA",
    "wof:name":"State Farm Insurance",
    "wof:placetype":"venue"
},
  "geometry": {"coordinates":[-93.773751,41.577856],"type":"Point"}
}