{
  "type": "Feature",
  "properties": {
    "iso:country":"US",
    "sg:address":"15212 Newcomer Ave",
    "sg:city":"Grinnell",
    "sg:classifiers":[
        {
            "category":"Organizations",
            "subcategory":"Religious Organization",
            "type":"Services"
        }
    ],
    "sg:phone":"+1 641 498 7897",
    "sg:postcode":"50112",
    "sg:province":"IA",
    "sg:tags":[
        "church"
    ],
    "wof:name":"Newburg-Chester United Church",
    "wof:placetype":"venue"
},
  "geometry": {"coordinates":[-92.77562,41.818784],"type":"Point"}
}