{
  "type": "Feature",
  "properties": {
    "iso:country":"US",
    "sg:address":"2018 SE 6th St",
    "sg:city":"Des Moines",
    "sg:classifiers":[
        {
            "category":"Personal",
            "subcategory":"Barber",
            "type":"Services"
        }
    ],
    "sg:phone":"+1 515 282 6065",
    "sg:postcode":"50315",
    "sg:province":"IA",
    "sg:tags":[
        "shop"
    ],
    "wof:name":"Gomez Hair Styling Shop",
    "wof:placetype":"venue"
},
  "geometry": {"coordinates":[-93.605375,41.56647],"type":"Point"}
}