{
  "type": "Feature",
  "properties": {
    "addr:full":"1825 Industrial Cir West Des Moines IA 50265",
    "addr:housenumber":"1825",
    "addr:postcode":"50265",
    "addr:street":"Industrial Cir",
    "iso:country":"US",
    "sg:address":"1825 Industrial Cir",
    "sg:city":"West Des Moines",
    "sg:classifiers":[
        {
            "category":"Building & Trades",
            "subcategory":"Construction",
            "type":"Services"
        }
    ],
    "sg:phone":"+1 515 222 0684",
    "sg:postcode":"50265",
    "sg:province":"IA",
    "sg:tags":[
        "home",
        "builder"
    ],
    "sg:website":"www.millardhomes.com",
    "wof:name":"Millard Construction Inc",
    "wof:placetype":"venue"
},
  "geometry": {"coordinates":[-93.731844,41.558144],"type":"Point"}
}