{
  "type": "Feature",
  "properties": {
    "addr:full":"406 Mechanic St Wapello IA 52653",
    "addr:housenumber":"406",
    "addr:postcode":"52653",
    "addr:street":"Mechanic St",
    "iso:country":"US",
    "sg:address":"406 Mechanic St",
    "sg:city":"Wapello",
    "sg:classifiers":[
        {
            "category":"Health Services",
            "subcategory":"Doctor",
            "type":"Services"
        }
    ],
    "sg:phone":"+1 319 527 4211",
    "sg:postcode":"52653",
    "sg:province":"IA",
    "sg:tags":[
        "clinic"
    ],
    "wof:name":"Planned Parenthood",
    "wof:placetype":"venue"
},
  "geometry": {"coordinates":[-91.188098,41.182424],"type":"Point"}
}