{
  "type": "Feature",
  "properties": {
    "iso:country":"US",
    "sg:address":"3516 Ellwinn Ln SE",
    "sg:city":"Cedar Rapids",
    "sg:classifiers":[
        {
            "category":"Wholesale",
            "subcategory":"Non-durable Goods",
            "type":"Manufacturing & Wholesale Goods"
        }
    ],
    "sg:phone":"+1 319 363 6465",
    "sg:postcode":"52403",
    "sg:province":"IA",
    "wof:name":"Greg Best",
    "wof:placetype":"venue"
},
  "geometry": {"coordinates":[-91.617791,41.992581],"type":"Point"}
}