{
  "type": "Feature",
  "properties": {
    "iso:country":"US",
    "sg:address":"301 East St",
    "sg:city":"Shelby",
    "sg:classifiers":[
        {
            "category":"Health Services",
            "subcategory":"Doctor",
            "type":"Services"
        }
    ],
    "sg:phone":"+1 712 544 2511",
    "sg:postcode":"51570",
    "sg:province":"IA",
    "sg:tags":[
        "clinic"
    ],
    "wof:name":"Shelby Medical Clinic",
    "wof:placetype":"venue"
},
  "geometry": {"coordinates":[-95.450953,41.513946],"type":"Point"}
}