{
  "type": "Feature",
  "properties": {
    "iso:country":"US",
    "sg:address":"645 26th St SE",
    "sg:city":"Cedar Rapids",
    "sg:classifiers":[
        {
            "category":"Education",
            "subcategory":"School",
            "type":"Public Place"
        }
    ],
    "sg:phone":"+1 319 558 2467",
    "sg:postcode":"52403",
    "sg:province":"IA",
    "sg:tags":[
        "high",
        "middle",
        "elementary"
    ],
    "wof:name":"Grant Wood Elementary School",
    "wof:placetype":"venue"
},
  "geometry": {"coordinates":[-91.63069900000001,41.979],"type":"Point"}
}