{
  "type": "Feature",
  "properties": {
    "addr:full":"320 N Main St Allison IA 50602",
    "addr:housenumber":"320",
    "addr:postcode":"50602",
    "addr:street":"N Main St",
    "iso:country":"US",
    "sg:address":"320 N Main St",
    "sg:city":"Allison",
    "sg:classifiers":[
        {
            "category":"Government",
            "subcategory":"Office",
            "type":"Public Place"
        }
    ],
    "sg:phone":"+1 319 267 2707",
    "sg:postcode":"50602",
    "sg:province":"IA",
    "wof:name":"Butter County Extension Svc",
    "wof:placetype":"venue"
},
  "geometry": {"coordinates":[-92.795197,42.752864],"type":"Point"}
}