{
  "type": "Feature",
  "properties": {
    "addr:full":"840 S 18th St Fort Dodge IA 50501",
    "addr:housenumber":"840",
    "addr:postcode":"50501",
    "addr:street":"S 18Th St",
    "iso:country":"US",
    "sg:address":"840 S 18th St",
    "sg:city":"Fort Dodge",
    "sg:classifiers":[
        {
            "category":"Building & Trades",
            "subcategory":"Construction",
            "type":"Services"
        }
    ],
    "sg:phone":"+1 515 955 4291",
    "sg:postcode":"50501",
    "sg:province":"IA",
    "sg:tags":[
        "general",
        "contractor"
    ],
    "wof:name":"Keith L Anderson Builder",
    "wof:placetype":"venue"
},
  "geometry": {"coordinates":[-94.17347100000001,42.496758],"type":"Point"}
}