{
  "type": "Feature",
  "properties": {
    "iso:country":"US",
    "sg:address":"902 10th St",
    "sg:city":"Onawa",
    "sg:classifiers":[
        {
            "category":"Banks & Credit Unions",
            "subcategory":"Bank",
            "type":"Services"
        }
    ],
    "sg:phone":"+1 712 423 1060",
    "sg:postcode":"51040",
    "sg:province":"IA",
    "wof:name":"Iowa State Bank",
    "wof:placetype":"venue"
},
  "geometry": {"coordinates":[-96.09734,42.028079],"type":"Point"}
}