{
  "type": "Feature",
  "properties": {
    "iso:country":"US",
    "sg:address":"1625 Zenith Dr",
    "sg:city":"Sioux City",
    "sg:classifiers":[
        {
            "category":"Autos & Motor Vehicles",
            "subcategory":"Auto Supplies",
            "type":"Retail Goods"
        }
    ],
    "sg:phone":"+1 712 277 0039",
    "sg:postcode":"51103",
    "sg:province":"IA",
    "sg:tags":[
        "tire"
    ],
    "wof:name":"Tire Associates Warehouse",
    "wof:placetype":"venue"
},
  "geometry": {"coordinates":[-96.428561,42.492337],"type":"Point"}
}