{
  "type": "Feature",
  "properties": {
    "iso:country":"US",
    "sg:address":"124 Beed Ave NE",
    "sg:city":"Titonka",
    "sg:classifiers":[
        {
            "category":"Retail",
            "subcategory":"Veterinary Services",
            "type":"Services"
        }
    ],
    "sg:phone":"+1 515 928 2642",
    "sg:postcode":"50480",
    "sg:province":"IA",
    "sg:tags":[
        "veterinarian"
    ],
    "wof:name":"Titonka Veterinary Clnc",
    "wof:placetype":"venue"
},
  "geometry": {"coordinates":[-94.03874,43.236697],"type":"Point"}
}