{
  "type": "Feature",
  "properties": {
    "addr:full":"3149 W Broadway Council Bluffs IA 51501",
    "addr:housenumber":"3149",
    "addr:postcode":"51501",
    "addr:street":"W Broadway",
    "iso:country":"US",
    "sg:address":"3149 W Broadway",
    "sg:city":"Council Bluffs",
    "sg:classifiers":[
        {
            "category":"Shopping",
            "subcategory":"Used Merchandise",
            "type":"Retail Goods"
        }
    ],
    "sg:phone":"+1 712 325 1808",
    "sg:postcode":"51501",
    "sg:province":"IA",
    "sg:tags":[
        "instrument",
        "pawnbroker",
        "teacher",
        "musical"
    ],
    "wof:name":"Mister Money USA",
    "wof:placetype":"venue"
},
  "geometry": {"coordinates":[-95.895798,41.261799],"type":"Point"}
}