{
  "type": "Feature",
  "properties": {
    "addr:full":"5226 University Ave Cedar Falls IA 50613",
    "addr:housenumber":"5226",
    "addr:postcode":"50613",
    "addr:street":"University Ave",
    "iso:country":"US",
    "sg:address":"5226 University Ave",
    "sg:city":"Cedar Falls",
    "sg:classifiers":[
        {
            "category":"Restaurant",
            "type":"Food & Drink"
        }
    ],
    "sg:menulink":"http://www.allmenus.com/ia/cedar-falls/225797-caseys-general-store/menu/",
    "sg:phone":"+1 319 266 2574",
    "sg:postcode":"50613",
    "sg:province":"IA",
    "sg:tags":[
        "american",
        "pizza"
    ],
    "wof:name":"Casey's General Store",
    "wof:placetype":"venue"
},
  "geometry": {"coordinates":[-92.42010000000001,42.509473],"type":"Point"}
}