{
  "type": "Feature",
  "properties": {
    "addr:full":"2209 10th St Emmetsburg IA 50536",
    "addr:housenumber":"2209",
    "addr:postcode":"50536",
    "addr:street":"10Th St",
    "iso:country":"US",
    "sg:address":"2209 10th St",
    "sg:city":"Emmetsburg",
    "sg:classifiers":[
        {
            "category":"Autos & Motor Vehicles",
            "subcategory":"Auto Supplies",
            "type":"Retail Goods"
        }
    ],
    "sg:phone":"+1 712 852 4142",
    "sg:postcode":"50536",
    "sg:province":"IA",
    "sg:tags":[
        "automobile",
        "parts"
    ],
    "wof:name":"NAPA Auto Parts",
    "wof:placetype":"venue"
},
  "geometry": {"coordinates":[-94.678904,43.111099],"type":"Point"}
}