{
  "type": "Feature",
  "properties": {
    "iso:country":"US",
    "sg:address":"30747 Forest Rd",
    "sg:city":"Hinton",
    "sg:classifiers":[
        {
            "category":"Farming",
            "subcategory":"Farm",
            "type":"Manufacturing & Wholesale Goods"
        }
    ],
    "sg:phone":"+1 712 239 1013",
    "sg:postcode":"51024",
    "sg:province":"IA",
    "sg:tags":[
        "crop",
        "general"
    ],
    "wof:name":"Joe Vondrak",
    "wof:placetype":"venue"
},
  "geometry": {"coordinates":[-96.40492,42.607277],"type":"Point"}
}