{
  "type": "Feature",
  "properties": {
    "iso:country":"US",
    "sg:address":"2142 480th Ave",
    "sg:city":"Deep River",
    "sg:classifiers":[
        {
            "category":"Home & Garden",
            "subcategory":"Garden Supply",
            "type":"Retail Goods"
        }
    ],
    "sg:phone":"+1 641 595 6853",
    "sg:postcode":"52222",
    "sg:province":"IA",
    "sg:tags":[
        "lawn",
        "mower"
    ],
    "wof:name":"Carl's Small Engine Repairs",
    "wof:placetype":"venue"
},
  "geometry": {"coordinates":[-92.373295,41.601573],"type":"Point"}
}