{
  "type": "Feature",
  "properties": {
    "iso:country":"US",
    "sg:address":"221 W Main St",
    "sg:city":"Lake Mills",
    "sg:classifiers":[
        {
            "category":"Shopping",
            "subcategory":"Gifts & Souvenirs",
            "type":"Retail Goods"
        }
    ],
    "sg:phone":"+1 641 592 1995",
    "sg:postcode":"50450",
    "sg:province":"IA",
    "sg:tags":[
        "shop"
    ],
    "wof:name":"Main Attractions",
    "wof:placetype":"venue"
},
  "geometry": {"coordinates":[-93.53476000000001,43.419291],"type":"Point"}
}