{
  "type": "Feature",
  "properties": {
    "iso:country":"US",
    "sg:address":"3 Hillcrest St",
    "sg:city":"Cherokee",
    "sg:classifiers":[
        {
            "category":"Building & Trades",
            "subcategory":"Construction",
            "type":"Services"
        }
    ],
    "sg:phone":"+1 712 225 5681",
    "sg:postcode":"51012",
    "sg:province":"IA",
    "wof:name":"Anderson Enterprises",
    "wof:placetype":"venue"
},
  "geometry": {"coordinates":[-95.553049,42.75925],"type":"Point"}
}