{
  "type": "Feature",
  "properties": {
    "iso:country":"US",
    "sg:address":"2118 5th Ave S",
    "sg:city":"Fort Dodge",
    "sg:classifiers":[
        {
            "category":"Wholesale",
            "subcategory":"Machinery & Supplies",
            "type":"Manufacturing & Wholesale Goods"
        }
    ],
    "sg:phone":"+1 515 955 7202",
    "sg:postcode":"50501",
    "sg:province":"IA",
    "sg:tags":[
        "bearing"
    ],
    "wof:name":"Bearing Service Co",
    "wof:placetype":"venue"
},
  "geometry": {"coordinates":[-94.16915899999999,42.501242],"type":"Point"}
}