{
  "type": "Feature",
  "properties": {
    "addr:full":"135 Marion Blvd Marion IA 52302",
    "addr:housenumber":"135",
    "addr:postcode":"52302",
    "addr:street":"Marion Blvd",
    "iso:country":"US",
    "sg:address":"135 Marion Blvd",
    "sg:city":"Marion",
    "sg:classifiers":[
        {
            "category":"Professional",
            "subcategory":"Accounting & Tax Preparation",
            "type":"Services"
        }
    ],
    "sg:phone":"+1 319 373 7700",
    "sg:postcode":"52302",
    "sg:province":"IA",
    "sg:tags":[
        "return",
        "filing"
    ],
    "wof:name":"Liberty Tax Svc",
    "wof:placetype":"venue"
},
  "geometry": {"coordinates":[-91.611637,42.03123],"type":"Point"}
}