{
  "type": "Feature",
  "properties": {
    "iso:country":"US",
    "sg:address":"205 N Clark St",
    "sg:city":"Forest City",
    "sg:classifiers":[
        {
            "category":"Home & Garden",
            "subcategory":"Hardware",
            "type":"Retail Goods"
        }
    ],
    "sg:phone":"+1 641 585 2505",
    "sg:postcode":"50436",
    "sg:province":"IA",
    "wof:name":"Hansen Hardware Hank II",
    "wof:placetype":"venue"
},
  "geometry": {"coordinates":[-93.638085,43.26545],"type":"Point"}
}