{
  "type": "Feature",
  "properties": {
    "addr:full":"1771 Guthrie Ave Des Moines IA 50316",
    "addr:housenumber":"1771",
    "addr:postcode":"50316",
    "addr:street":"Guthrie Ave",
    "iso:country":"US",
    "sg:address":"1771 Guthrie Ave",
    "sg:city":"Des Moines",
    "sg:classifiers":[
        {
            "category":"Wholesale",
            "subcategory":"Machinery & Supplies",
            "type":"Manufacturing & Wholesale Goods"
        }
    ],
    "sg:phone":"+1 515 289 2874",
    "sg:postcode":"50316",
    "sg:province":"IA",
    "sg:tags":[
        "hoist"
    ],
    "wof:name":"Material Handling Innovations",
    "wof:placetype":"venue"
},
  "geometry": {"coordinates":[-93.587127,41.614934],"type":"Point"}
}