{
  "type": "Feature",
  "properties": {
    "addr:full":"1507 Ohio St Des Moines IA 50314",
    "addr:housenumber":"1507",
    "addr:postcode":"50314",
    "addr:street":"Ohio St",
    "iso:country":"US",
    "sg:address":"1507 Ohio St",
    "sg:city":"Des Moines",
    "sg:classifiers":[
        {
            "category":"Wholesale",
            "subcategory":"Construction Materials",
            "type":"Manufacturing & Wholesale Goods"
        }
    ],
    "sg:phone":"+1 515 244 8327",
    "sg:postcode":"50314",
    "sg:province":"IA",
    "sg:tags":[
        "marble"
    ],
    "wof:name":"Des Moines Marble & Mantel Co",
    "wof:placetype":"venue"
},
  "geometry": {"coordinates":[-93.617242,41.607539],"type":"Point"}
}