{
  "type": "Feature",
  "properties": {
    "iso:country":"US",
    "sg:address":"1801 S Main Ave",
    "sg:city":"Sioux Center",
    "sg:classifiers":[
        {
            "category":"Autos & Motor Vehicles",
            "subcategory":"Fuel & Gas Station",
            "type":"Retail Goods"
        }
    ],
    "sg:phone":"+1 712 722 3900",
    "sg:postcode":"51250",
    "sg:province":"IA",
    "sg:tags":[
        "oil"
    ],
    "wof:name":"M J's 66",
    "wof:placetype":"venue"
},
  "geometry": {"coordinates":[-96.175391,43.05832],"type":"Point"}
}