{
  "type": "Feature",
  "properties": {
    "addr:full":"3301 Pennsylvania Ave Dubuque IA 52001",
    "addr:housenumber":"3301",
    "addr:postcode":"52001",
    "addr:street":"Pennsylvania Ave",
    "iso:country":"US",
    "sg:address":"3301 Pennsylvania Ave",
    "sg:city":"Dubuque",
    "sg:classifiers":[
        {
            "category":"Utilities",
            "subcategory":"Mobile Phone",
            "type":"Services"
        }
    ],
    "sg:phone":"+1 563 583 0777",
    "sg:postcode":"52001",
    "sg:province":"IA",
    "sg:tags":[
        "telephone",
        "cellular"
    ],
    "wof:name":"In Touch",
    "wof:placetype":"venue"
},
  "geometry": {"coordinates":[-90.72125200000001,42.500468],"type":"Point"}
}