{
  "type": "Feature",
  "properties": {
    "iso:country":"US",
    "sg:address":"417 S 3rd Ave",
    "sg:city":"Villisca",
    "sg:classifiers":[
        {
            "category":"Manufacturing",
            "subcategory":"Printing",
            "type":"Manufacturing & Wholesale Goods"
        }
    ],
    "sg:phone":"+1 712 826 2142",
    "sg:postcode":"50864",
    "sg:province":"IA",
    "sg:tags":[
        "newspaper"
    ],
    "wof:name":"Villisca Review & Stanton",
    "wof:placetype":"venue"
},
  "geometry": {"coordinates":[-94.97712,40.928503],"type":"Point"}
}