{
  "type": "Feature",
  "properties": {
    "iso:country":"US",
    "sg:address":"1611 Oriole Ave",
    "sg:city":"Waterloo",
    "sg:classifiers":[
        {
            "category":"Professional",
            "type":"Services"
        }
    ],
    "sg:phone":"+1 319 287 5920",
    "sg:postcode":"50701",
    "sg:province":"IA",
    "sg:tags":[
        "establishment"
    ],
    "wof:name":"Xmlam & Kelling",
    "wof:placetype":"venue"
},
  "geometry": {"coordinates":[-92.38485799999999,42.48879],"type":"Point"}
}