{
  "type": "Feature",
  "properties": {
    "addr:full":"415 Oak Dr Postville IA 52162",
    "addr:housenumber":"415",
    "addr:postcode":"52162",
    "addr:street":"Oak Dr Postville",
    "iso:country":"US",
    "sg:address":"415 Oak Dr",
    "sg:city":"Postville",
    "sg:classifiers":[
        {
            "category":"Government",
            "subcategory":"Office",
            "type":"Public Place"
        }
    ],
    "sg:phone":"+1 563 864 7454",
    "sg:postcode":"52162",
    "sg:province":"IA",
    "sg:tags":[
        "village"
    ],
    "wof:name":"Postville Clerk",
    "wof:placetype":"venue"
},
  "geometry": {"coordinates":[-91.56146099999999,43.082486],"type":"Point"}
}