{
  "type": "Feature",
  "properties": {
    "iso:country":"US",
    "sg:address":"197 510th St",
    "sg:city":"Marcus",
    "sg:classifiers":[
        {
            "category":"Professional",
            "subcategory":"Business Services",
            "type":"Services"
        }
    ],
    "sg:phone":"+1 712 376 4494",
    "sg:postcode":"51035",
    "sg:province":"IA",
    "sg:tags":[
        "embroidery"
    ],
    "wof:name":"Country Creations",
    "wof:placetype":"venue"
},
  "geometry": {"coordinates":[-95.841331,42.778975],"type":"Point"}
}