{
  "type": "Feature",
  "properties": {
    "iso:country":"US",
    "sg:address":"326 SW Maple St",
    "sg:city":"Ankeny",
    "sg:classifiers":[
        {
            "category":"Personal",
            "subcategory":"Shoe Repair & Shine",
            "type":"Services"
        }
    ],
    "sg:phone":"+1 515 964 4545",
    "sg:postcode":"50023",
    "sg:province":"IA",
    "sg:tags":[
        "parlor"
    ],
    "wof:name":"Kluesners Shoe Repair Shop",
    "wof:placetype":"venue"
},
  "geometry": {"coordinates":[-93.608633,41.728807],"type":"Point"}
}