{
  "type": "Feature",
  "properties": {
    "iso:country":"US",
    "sg:address":"600 Lake Ave",
    "sg:city":"Storm Lake",
    "sg:classifiers":[
        {
            "category":"Insurance",
            "subcategory":"Insurance Agent",
            "type":"Services"
        }
    ],
    "sg:phone":"+1 712 732 7030",
    "sg:postcode":"50588",
    "sg:province":"IA",
    "wof:name":"Central Insurance",
    "wof:placetype":"venue"
},
  "geometry": {"coordinates":[-95.20084199999999,42.645476],"type":"Point"}
}