{
  "type": "Feature",
  "properties": {
    "iso:country":"US",
    "sg:address":"1743 137th St",
    "sg:city":"Earlham",
    "sg:phone":"+1 515 758 2439",
    "sg:postcode":"50072",
    "sg:province":"IA",
    "sg:tags":[
        "beef",
        "farm",
        "corn",
        "cash",
        "grain",
        "cattle",
        "feedlot"
    ],
    "wof:name":"Jeffrey K Howell",
    "wof:placetype":"venue"
},
  "geometry": {"coordinates":[-94.080033,41.452981],"type":"Point"}
}