{
  "type": "Feature",
  "properties": {
    "iso:country":"US",
    "sg:address":"1228 E Rusholme St",
    "sg:city":"Davenport",
    "sg:classifiers":[
        {
            "category":"Health Services",
            "subcategory":"Doctor",
            "type":"Services"
        }
    ],
    "sg:phone":"+1 563 324 3818",
    "sg:postcode":"52803",
    "sg:province":"IA",
    "sg:tags":[
        "physician",
        "surgeon"
    ],
    "wof:name":"Chest & Vascular Surgery",
    "wof:placetype":"venue"
},
  "geometry": {"coordinates":[-90.556732,41.542923],"type":"Point"}
}