{
  "type": "Feature",
  "properties": {
    "addr:full":"415 S Johnson St Corydon IA 50060",
    "addr:housenumber":"415",
    "addr:postcode":"50060",
    "addr:street":"S Johnson St",
    "iso:country":"US",
    "sg:address":"415 S Johnson St",
    "sg:city":"Corydon",
    "sg:classifiers":[
        {
            "category":"Building & Trades",
            "subcategory":"Pest Control",
            "type":"Services"
        }
    ],
    "sg:phone":"+1 641 872 1891",
    "sg:postcode":"50060",
    "sg:province":"IA",
    "wof:name":"Curry Pest Control",
    "wof:placetype":"venue"
},
  "geometry": {"coordinates":[-93.31568300000001,40.753712],"type":"Point"}
}