{
  "type": "Feature",
  "properties": {
    "iso:country":"US",
    "sg:address":"1220 S Elk Run Rd",
    "sg:city":"Waterloo",
    "sg:classifiers":[
        {
            "category":"Manufacturing",
            "subcategory":"Printing",
            "type":"Manufacturing & Wholesale Goods"
        }
    ],
    "sg:phone":"+1 319 287 6888",
    "sg:postcode":"50703",
    "sg:province":"IA",
    "sg:tags":[
        "engraver",
        "wood"
    ],
    "wof:name":"Tags N More",
    "wof:placetype":"venue"
},
  "geometry": {"coordinates":[-92.258505,42.476385],"type":"Point"}
}