{
  "type": "Feature",
  "properties": {
    "iso:country":"US",
    "sg:address":"417 Cedar St",
    "sg:city":"Tipton",
    "sg:classifiers":[
        {
            "category":"Personal",
            "subcategory":"Barber",
            "type":"Services"
        }
    ],
    "sg:phone":"+1 563 886 2627",
    "sg:postcode":"52772",
    "sg:province":"IA",
    "sg:tags":[
        "shop"
    ],
    "wof:name":"Cedar Street Barber Shop",
    "wof:placetype":"venue"
},
  "geometry": {"coordinates":[-91.128483,41.769826],"type":"Point"}
}