{
  "type": "Feature",
  "properties": {
    "addr:full":"1220 S 22nd St Fort Dodge IA 50501",
    "addr:housenumber":"1220",
    "addr:postcode":"50501",
    "addr:street":"S 22Nd St",
    "iso:country":"US",
    "sg:address":"1220 S 22nd St",
    "sg:city":"Fort Dodge",
    "sg:classifiers":[
        {
            "category":"Wholesale",
            "subcategory":"Hardware",
            "type":"Manufacturing & Wholesale Goods"
        }
    ],
    "sg:phone":"+1 515 972 4680",
    "sg:postcode":"50501",
    "sg:province":"IA",
    "sg:tags":[
        "furnace"
    ],
    "wof:name":"MEC Heating & Cooling Inc",
    "wof:placetype":"venue"
},
  "geometry": {"coordinates":[-94.167911,42.491383],"type":"Point"}
}