{
  "type": "Feature",
  "properties": {
    "addr:full":"2400 Kerper Blvd Dubuque IA 52001",
    "addr:housenumber":"2400",
    "addr:postcode":"52001",
    "addr:street":"Kerper Blvd",
    "iso:country":"US",
    "sg:address":"2400 Kerper Blvd",
    "sg:city":"Dubuque",
    "sg:classifiers":[
        {
            "category":"Manufacturing",
            "subcategory":"Tools & Machinery",
            "type":"Manufacturing & Wholesale Goods"
        }
    ],
    "sg:phone":"+1 563 588 2855",
    "sg:postcode":"52001",
    "sg:province":"IA",
    "sg:tags":[
        "machine",
        "shop"
    ],
    "wof:name":"Hermsen Machine",
    "wof:placetype":"venue"
},
  "geometry": {"coordinates":[-90.64993699999999,42.526644],"type":"Point"}
}