{
  "type": "Feature",
  "properties": {
    "addr:full":"1091 University Ave Dubuque IA 52001",
    "addr:housenumber":"1091",
    "addr:postcode":"52001",
    "addr:street":"University Ave",
    "iso:country":"US",
    "sg:address":"1091 University Ave",
    "sg:city":"Dubuque",
    "sg:classifiers":[
        {
            "category":"Restaurant",
            "type":"Food & Drink"
        }
    ],
    "sg:menulink":"http://www.allmenus.com/ia/dubuque/247472-athenian-grill/menu/",
    "sg:phone":"+1 563 556 9046",
    "sg:postcode":"52001",
    "sg:province":"IA",
    "sg:tags":[
        "greek"
    ],
    "wof:name":"Athenian Grill",
    "wof:placetype":"venue"
},
  "geometry": {"coordinates":[-90.68147999999999,42.499082],"type":"Point"}
}