{
  "type": "Feature",
  "properties": {
    "addr:full":"315 S 2nd Ave W Newton IA 50208",
    "addr:housenumber":"315",
    "addr:postcode":"50208",
    "addr:street":"S 2Nd Ave W",
    "iso:country":"US",
    "sg:address":"315 S 2nd Ave W",
    "sg:city":"Newton",
    "sg:classifiers":[
        {
            "category":"Insurance",
            "subcategory":"Insurance Agent",
            "type":"Services"
        }
    ],
    "sg:phone":"+1 641 792 4267",
    "sg:postcode":"50208",
    "sg:province":"IA",
    "wof:name":"Hawkeye Mutual Insurance Assoc",
    "wof:placetype":"venue"
},
  "geometry": {"coordinates":[-93.05726199999999,41.69847],"type":"Point"}
}