{
  "type": "Feature",
  "properties": {
    "addr:full":"3179 Big Bend Rd Ely IA 52227",
    "addr:housenumber":"3179",
    "addr:postcode":"52227",
    "addr:street":"Big Bend Rd",
    "iso:country":"US",
    "sg:address":"3179 Big Bend Rd",
    "sg:city":"Ely",
    "sg:classifiers":[
        {
            "category":"Utilities",
            "subcategory":"Refuse",
            "type":"Services"
        }
    ],
    "sg:phone":"+1 641 772 4550",
    "sg:postcode":"52227",
    "sg:province":"IA",
    "sg:tags":[
        "garbage",
        "collection"
    ],
    "wof:name":"Sun Valley Sanitary District",
    "wof:placetype":"venue"
},
  "geometry": {"coordinates":[-91.589879,41.943813],"type":"Point"}
}