{
  "type": "Feature",
  "properties": {
    "iso:country":"US",
    "sg:address":"330 N 16th Ave",
    "sg:city":"Eldridge",
    "sg:classifiers":[
        {
            "category":"Professional",
            "subcategory":"Management & Consulting",
            "type":"Services"
        }
    ],
    "sg:phone":"+1 563 285 5712",
    "sg:postcode":"52748",
    "sg:province":"IA",
    "sg:tags":[
        "consultant",
        "energy",
        "conservation"
    ],
    "wof:name":"American Finishing Resources",
    "wof:placetype":"venue"
},
  "geometry": {"coordinates":[-90.564395,41.657233],"type":"Point"}
}