{
  "type": "Feature",
  "properties": {
    "addr:full":"22702 136th St Ottumwa IA 52501",
    "addr:housenumber":"22702",
    "addr:postcode":"52501",
    "addr:street":"136Th St",
    "iso:country":"US",
    "sg:address":"22702 136th St",
    "sg:city":"Ottumwa",
    "sg:classifiers":[
        {
            "category":"Farming",
            "subcategory":"Livestock Farm",
            "type":"Manufacturing & Wholesale Goods"
        }
    ],
    "sg:phone":"+1 641 938 2495",
    "sg:postcode":"52501",
    "sg:province":"IA",
    "wof:name":"David E Brinegar",
    "wof:placetype":"venue"
},
  "geometry": {"coordinates":[-92.592181,41.086151],"type":"Point"}
}