{
  "type": "Feature",
  "properties": {
    "addr:full":"102 S Elmwood Ave Davenport IA 52802",
    "addr:housenumber":"102",
    "addr:postcode":"52802",
    "addr:street":"S Elmwood Ave",
    "iso:country":"US",
    "sg:address":"102 S Elmwood Ave",
    "sg:city":"Davenport",
    "sg:classifiers":[
        {
            "category":"Home & Garden",
            "subcategory":"Building Materials",
            "type":"Retail Goods"
        },
        {
            "category":"Building & Trades",
            "subcategory":"Construction",
            "type":"Services"
        }
    ],
    "sg:phone":"+1 563 324 0940",
    "sg:postcode":"52802",
    "sg:province":"IA",
    "sg:tags":[
        "industrial",
        "chimneys-prefabricated",
        "mason",
        "contractors-commercial",
        "masonry",
        "contractor",
        "chimney"
    ],
    "wof:name":"Ron Fuller Masonry Inc",
    "wof:placetype":"venue"
},
  "geometry": {"coordinates":[-90.615219,41.520018],"type":"Point"}
}