{
  "type": "Feature",
  "properties": {
    "iso:country":"US",
    "sg:address":"300 3rd Ave SW",
    "sg:city":"Pocahontas",
    "sg:phone":"+1 712 335 3769",
    "sg:postcode":"50574",
    "sg:province":"IA",
    "sg:tags":[
        "farm",
        "corn",
        "soybean"
    ],
    "wof:name":"Bruce Bauer",
    "wof:placetype":"venue"
},
  "geometry": {"coordinates":[-94.67498399999999,42.729625],"type":"Point"}
}