{
  "type": "Feature",
  "properties": {
    "iso:country":"US",
    "sg:address":"12121 Wright Rd",
    "sg:city":"La Porte City",
    "sg:classifiers":[
        {
            "category":"Professional",
            "subcategory":"Business Services",
            "type":"Services"
        }
    ],
    "sg:phone":"+1 319 342 2960",
    "sg:postcode":"50651",
    "sg:province":"IA",
    "wof:name":"G3 Technologies",
    "wof:placetype":"venue"
},
  "geometry": {"coordinates":[-92.099374,42.329991],"type":"Point"}
}