{
  "type": "Feature",
  "properties": {
    "addr:full":"917 11th St Boone IA 50036",
    "addr:housenumber":"917",
    "addr:postcode":"50036",
    "addr:street":"11Th St",
    "iso:country":"US",
    "sg:address":"917 11th St",
    "sg:city":"Boone",
    "sg:classifiers":[
        {
            "category":"Personal",
            "subcategory":"Beauty Salon",
            "type":"Services"
        }
    ],
    "sg:phone":"+1 515 432 4113",
    "sg:postcode":"50036",
    "sg:province":"IA",
    "wof:name":"Mirror Image",
    "wof:placetype":"venue"
},
  "geometry": {"coordinates":[-93.87984299999999,42.066995],"type":"Point"}
}