{
  "type": "Feature",
  "properties": {
    "iso:country":"US",
    "sg:address":"2711 E Kanesville Blvd",
    "sg:city":"Council Bluffs",
    "sg:classifiers":[
        {
            "category":"Personal",
            "subcategory":"Tanning Parlor",
            "type":"Services"
        }
    ],
    "sg:phone":"+1 712 322 9000",
    "sg:postcode":"51503",
    "sg:province":"IA",
    "sg:tags":[
        "salon"
    ],
    "wof:name":"Sundazzled Salon & Day Spa",
    "wof:placetype":"venue"
},
  "geometry": {"coordinates":[-95.81119700000001,41.279357],"type":"Point"}
}