{
  "type": "Feature",
  "properties": {
    "iso:country":"US",
    "sg:address":"1840 120th St",
    "sg:city":"Bode",
    "sg:phone":"+1 515 379 1421",
    "sg:postcode":"50519",
    "sg:province":"IA",
    "sg:tags":[
        "farm",
        "corn"
    ],
    "wof:name":"Clifford Helland",
    "wof:placetype":"venue"
},
  "geometry": {"coordinates":[-94.277479,42.877436],"type":"Point"}
}