{
  "type": "Feature",
  "properties": {
    "iso:country":"US",
    "sg:address":"1413 2nd Ave",
    "sg:city":"Vinton",
    "sg:classifiers":[
        {
            "category":"Social Services",
            "subcategory":"Adult Care",
            "type":"Services"
        }
    ],
    "sg:phone":"+1 319 472 2092",
    "sg:postcode":"52349",
    "sg:province":"IA",
    "sg:tags":[
        "home",
        "residential"
    ],
    "wof:name":"Lutheran Home Apartments",
    "wof:placetype":"venue"
},
  "geometry": {"coordinates":[-92.0231,42.158356],"type":"Point"}
}