{
  "type": "Feature",
  "properties": {
    "iso:country":"US",
    "sg:address":"317 Broadway St",
    "sg:city":"Audubon",
    "sg:classifiers":[
        {
            "category":"Shopping",
            "subcategory":"Gifts & Souvenirs",
            "type":"Retail Goods"
        }
    ],
    "sg:phone":"+1 712 563 4576",
    "sg:postcode":"50025",
    "sg:province":"IA",
    "sg:tags":[
        "shop"
    ],
    "wof:name":"Present Co",
    "wof:placetype":"venue"
},
  "geometry": {"coordinates":[-94.933246,41.720348],"type":"Point"}
}