{
  "type": "Feature",
  "properties": {
    "iso:country":"US",
    "sg:address":"41046 220th Ave",
    "sg:city":"Havelock",
    "sg:phone":"+1 712 776 2336",
    "sg:postcode":"50546",
    "sg:province":"IA",
    "sg:tags":[
        "farm",
        "corn",
        "soybean"
    ],
    "wof:name":"Harvey Cornwell",
    "wof:placetype":"venue"
},
  "geometry": {"coordinates":[-94.678794,42.888439],"type":"Point"}
}