{
  "type": "Feature",
  "properties": {
    "addr:full":"826 Ave G Fort Madison IA 52627",
    "addr:housenumber":"826",
    "addr:postcode":"52627",
    "addr:street":"Ave G",
    "iso:country":"US",
    "sg:address":"826 Ave G",
    "sg:city":"Fort Madison",
    "sg:classifiers":[
        {
            "category":"Retail",
            "subcategory":"Portrait Studio",
            "type":"Services"
        }
    ],
    "sg:phone":"+1 319 372 1362",
    "sg:postcode":"52627",
    "sg:province":"IA",
    "sg:tags":[
        "photographer"
    ],
    "wof:name":"John Gorham Photography",
    "wof:placetype":"venue"
},
  "geometry": {"coordinates":[-91.312985,40.630868],"type":"Point"}
}