{
  "type": "Feature",
  "properties": {
    "iso:country":"US",
    "sg:address":"513 N Main St",
    "sg:city":"Burlington",
    "sg:classifiers":[
        {
            "category":"Government",
            "subcategory":"Jail",
            "type":"Public Place"
        }
    ],
    "sg:phone":"+1 319 753 8281",
    "sg:postcode":"52601",
    "sg:province":"IA",
    "sg:tags":[
        "govt",
        "state",
        "institution"
    ],
    "wof:name":"Juvenile Probation Ofc",
    "wof:placetype":"venue"
},
  "geometry": {"coordinates":[-91.100759,40.812195],"type":"Point"}
}