{
  "type": "Feature",
  "properties": {
    "addr:full":"117 S 2nd St Maquoketa IA 52060",
    "addr:housenumber":"117",
    "addr:postcode":"52060",
    "addr:street":"S 2Nd St",
    "iso:country":"US",
    "sg:address":"117 S 2nd St",
    "sg:city":"Maquoketa",
    "sg:classifiers":[
        {
            "category":"Home & Garden",
            "subcategory":"Household Appliances",
            "type":"Retail Goods"
        }
    ],
    "sg:phone":"+1 563 652 6577",
    "sg:postcode":"52060",
    "sg:province":"IA",
    "wof:name":"Mayberry Maytag Home Appliance",
    "wof:placetype":"venue"
},
  "geometry": {"coordinates":[-90.66680100000001,42.068989],"type":"Point"}
}