{
  "type": "Feature",
  "properties": {
    "iso:country":"US",
    "sg:address":"4316 Union St",
    "sg:city":"Elk Horn",
    "sg:classifiers":[
        {
            "category":"Building & Trades",
            "subcategory":"Construction",
            "type":"Services"
        }
    ],
    "sg:phone":"+1 712 764 7007",
    "sg:postcode":"51531",
    "sg:province":"IA",
    "sg:tags":[
        "layer",
        "carpet"
    ],
    "wof:name":"General Floor Svc",
    "wof:placetype":"venue"
},
  "geometry": {"coordinates":[-95.06098299999999,41.593806],"type":"Point"}
}