{
  "type": "Feature",
  "properties": {
    "addr:full":"1604 Mount Pleasant St Burlington IA 52601",
    "addr:housenumber":"1604",
    "addr:postcode":"52601",
    "addr:street":"Mount Pleasant St",
    "iso:country":"US",
    "sg:address":"1604 Mount Pleasant St",
    "sg:city":"Burlington",
    "sg:classifiers":[
        {
            "category":"Retail",
            "subcategory":"Repair Shop",
            "type":"Services"
        }
    ],
    "sg:phone":"+1 319 752 5060",
    "sg:postcode":"52601",
    "sg:province":"IA",
    "sg:tags":[
        "taxidermist"
    ],
    "wof:name":"Messer's Artistic Taxidermy",
    "wof:placetype":"venue"
},
  "geometry": {"coordinates":[-91.12161500000001,40.819828],"type":"Point"}
}