{
  "type": "Feature",
  "properties": {
    "iso:country":"US",
    "sg:address":"315 1st St",
    "sg:city":"Lyle",
    "sg:classifiers":[
        {
            "category":"Organizations",
            "subcategory":"Religious Organization",
            "type":"Services"
        }
    ],
    "sg:phone":"+1 507 325 2321",
    "sg:postcode":"55953",
    "sg:province":"IA",
    "wof:name":"Helen Velonis Ministries Inc",
    "wof:placetype":"venue"
},
  "geometry": {"coordinates":[-92.944496,43.503816],"type":"Point"}
}