{
  "type": "Feature",
  "properties": {
    "addr:full":"2577 NW 158th St Clive IA 50325",
    "addr:housenumber":"2577",
    "addr:postcode":"50325",
    "addr:street":"Nw 158Th St",
    "iso:country":"US",
    "sg:address":"2577 NW 158th St",
    "sg:city":"Clive",
    "sg:classifiers":[
        {
            "category":"Professional",
            "subcategory":"Computer Services",
            "type":"Services"
        }
    ],
    "sg:phone":"+1 515 988 7799",
    "sg:postcode":"50325",
    "sg:province":"IA",
    "sg:tags":[
        "datum"
    ],
    "wof:name":"Universalink",
    "wof:placetype":"venue"
},
  "geometry": {"coordinates":[-93.835596,41.618911],"type":"Point"}
}