{
  "type": "Feature",
  "properties": {
    "iso:country":"US",
    "sg:address":"20 US Hwy 6",
    "sg:city":"Waukee",
    "sg:classifiers":[
        {
            "category":"Restaurant",
            "type":"Food & Drink"
        }
    ],
    "sg:phone":"+1 515 987 6753",
    "sg:postcode":"50263",
    "sg:province":"IA",
    "sg:tags":[
        "pizza"
    ],
    "wof:name":"Casey's Carry Out Pizza",
    "wof:placetype":"venue"
},
  "geometry": {"coordinates":[-93.879766,41.614883],"type":"Point"}
}