{
  "type": "Feature",
  "properties": {
    "iso:country":"US",
    "sg:address":"1916 W Main St",
    "sg:city":"Sac City",
    "sg:classifiers":[
        {
            "category":"Restaurant",
            "type":"Food & Drink"
        }
    ],
    "sg:menulink":"http://www.allmenus.com/ia/jackson/120812-subway/menu/",
    "sg:postcode":"50583",
    "sg:province":"IA",
    "sg:tags":[
        "american",
        "sandwich"
    ],
    "wof:name":"Subway",
    "wof:placetype":"venue"
},
  "geometry": {"coordinates":[-95.007448,42.422533],"type":"Point"}
}