{
  "type": "Feature",
  "properties": {
    "iso:country":"US",
    "sg:address":"14035 State Hwy 14",
    "sg:city":"Greene",
    "sg:classifiers":[
        {
            "category":"Farming",
            "subcategory":"Livestock Farm",
            "type":"Manufacturing & Wholesale Goods"
        }
    ],
    "sg:phone":"+1 641 823 5839",
    "sg:postcode":"50636",
    "sg:province":"IA",
    "sg:tags":[
        "hog",
        "beef",
        "corn",
        "cash",
        "grain",
        "cattle",
        "feedlot"
    ],
    "wof:name":"Byron Schipper",
    "wof:placetype":"venue"
},
  "geometry": {"coordinates":[-92.810226,42.846811],"type":"Point"}
}