{
  "type": "Feature",
  "properties": {
    "iso:country":"US",
    "sg:address":"2508 4th St SW",
    "sg:city":"Mason City",
    "sg:classifiers":[
        {
            "category":"Utilities",
            "subcategory":"Mobile Phone",
            "type":"Services"
        }
    ],
    "sg:phone":"+1 641 424 0221",
    "sg:postcode":"50401",
    "sg:province":"IA",
    "sg:tags":[
        "telephone",
        "cellular"
    ],
    "wof:name":"Radio Shack",
    "wof:placetype":"venue"
},
  "geometry": {"coordinates":[-93.23568899999999,43.148526],"type":"Point"}
}