{
  "type": "Feature",
  "properties": {
    "addr:full":"2585 175th St Calmar IA 52132",
    "addr:housenumber":"2585",
    "addr:postcode":"52132",
    "addr:street":"175Th St",
    "iso:country":"US",
    "sg:address":"2585 175th St",
    "sg:city":"Calmar",
    "sg:classifiers":[
        {
            "category":"Organizations",
            "subcategory":"Community Association",
            "type":"Services"
        }
    ],
    "sg:phone":"+1 563 562 3191",
    "sg:postcode":"52132",
    "sg:province":"IA",
    "sg:tags":[
        "club"
    ],
    "wof:name":"South Winn Golf & Country Club",
    "wof:placetype":"venue"
},
  "geometry": {"coordinates":[-91.889523,43.191358],"type":"Point"}
}