{
  "type": "Feature",
  "properties": {
    "addr:full":"616 6th Ave W Cresco IA 52136",
    "addr:housenumber":"616",
    "addr:postcode":"52136",
    "addr:street":"6Th Ave W Cresco",
    "iso:country":"US",
    "sg:address":"616 6th Ave W",
    "sg:city":"Cresco",
    "sg:classifiers":[
        {
            "category":"Manufacturing",
            "subcategory":"Pet Food",
            "type":"Manufacturing & Wholesale Goods"
        }
    ],
    "sg:phone":"+1 563 547 5827",
    "sg:postcode":"52136",
    "sg:province":"IA",
    "sg:tags":[
        "milling",
        "restaurant"
    ],
    "sg:website":"www.sunrich.com",
    "wof:name":"Integrity Mills",
    "wof:placetype":"venue"
},
  "geometry": {"coordinates":[-92.12932600000001,43.378372],"type":"Point"}
}