{
  "type": "Feature",
  "properties": {
    "iso:country":"US",
    "sg:address":"2707 N Liberty Rd NE",
    "sg:city":"North Liberty",
    "sg:classifiers":[
        {
            "category":"Organizations",
            "subcategory":"Religious Organization",
            "type":"Services"
        }
    ],
    "sg:phone":"+1 319 626 2040",
    "sg:postcode":"52317",
    "sg:province":"IA",
    "sg:tags":[
        "church"
    ],
    "wof:name":"Grace Community Church",
    "wof:placetype":"venue"
},
  "geometry": {"coordinates":[-91.575811,41.734305],"type":"Point"}
}