{
  "type": "Feature",
  "properties": {
    "addr:full":"1210 Keokuk Ave Spirit Lake IA 51360",
    "addr:housenumber":"1210",
    "addr:postcode":"51360",
    "addr:street":"Keokuk Ave",
    "iso:country":"US",
    "sg:address":"1210 Keokuk Ave",
    "sg:city":"Spirit Lake",
    "sg:classifiers":[
        {
            "category":"Shopping",
            "subcategory":"Used Merchandise",
            "type":"Retail Goods"
        }
    ],
    "sg:phone":"+1 712 336 4894",
    "sg:postcode":"51360",
    "sg:province":"IA",
    "wof:name":"D&D Antiques",
    "wof:placetype":"venue"
},
  "geometry": {"coordinates":[-95.106769,43.428263],"type":"Point"}
}