{
  "type": "Feature",
  "properties": {
    "iso:country":"US",
    "sg:address":"103 E Main St",
    "sg:city":"Cherokee",
    "sg:classifiers":[
        {
            "category":"Home & Garden",
            "subcategory":"Furniture",
            "type":"Retail Goods"
        }
    ],
    "sg:phone":"+1 712 225 6013",
    "sg:postcode":"51012",
    "sg:province":"IA",
    "wof:name":"Melander's TV & Appliance",
    "wof:placetype":"venue"
},
  "geometry": {"coordinates":[-95.551227,42.749601],"type":"Point"}
}