{
  "type": "Feature",
  "properties": {
    "addr:full":"109 N Main St Conrad IA 50621",
    "addr:housenumber":"109",
    "addr:postcode":"50621",
    "addr:street":"N Main St",
    "iso:country":"US",
    "sg:address":"109 N Main St",
    "sg:city":"Conrad",
    "sg:classifiers":[
        {
            "category":"Bars & Pubs",
            "type":"Food & Drink"
        }
    ],
    "sg:phone":"+1 641 366 2687",
    "sg:postcode":"50621",
    "sg:province":"IA",
    "sg:tags":[
        "lounge",
        "cocktail"
    ],
    "wof:name":"Rondell Lounge",
    "wof:placetype":"venue"
},
  "geometry": {"coordinates":[-92.87466499999999,42.225315],"type":"Point"}
}