{
  "type": "Feature",
  "properties": {
    "addr:full":"302 W Summit St Winterset IA 50273",
    "addr:housenumber":"302",
    "addr:postcode":"50273",
    "addr:street":"W Summit St",
    "iso:country":"US",
    "sg:address":"302 W Summit St",
    "sg:city":"Winterset",
    "sg:classifiers":[
        {
            "category":"Personal",
            "subcategory":"Beauty Salon",
            "type":"Services"
        }
    ],
    "sg:phone":"+1 515 462 2364",
    "sg:postcode":"50273",
    "sg:province":"IA",
    "wof:name":"Betty's Shear Design",
    "wof:placetype":"venue"
},
  "geometry": {"coordinates":[-94.018142,41.330147],"type":"Point"}
}