{
  "type": "Feature",
  "properties": {
    "addr:full":"523 4th St Story City IA 50248",
    "addr:housenumber":"523",
    "addr:postcode":"50248",
    "addr:street":"4Th St",
    "iso:country":"US",
    "sg:address":"523 4th St",
    "sg:city":"Story City",
    "sg:classifiers":[
        {
            "category":"Personal",
            "subcategory":"Beauty Salon",
            "type":"Services"
        }
    ],
    "sg:phone":"+1 515 733 4621",
    "sg:postcode":"50248",
    "sg:province":"IA",
    "wof:name":"Beauty Nook",
    "wof:placetype":"venue"
},
  "geometry": {"coordinates":[-93.597236,42.184828],"type":"Point"}
}