{
  "type": "Feature",
  "properties": {
    "iso:country":"US",
    "sg:address":"3137 Talbot Rd",
    "sg:city":"Sioux City",
    "sg:classifiers":[
        {
            "category":"Retail",
            "subcategory":"Animal Services",
            "type":"Services"
        }
    ],
    "sg:phone":"+1 712 258 4055",
    "sg:postcode":"51103",
    "sg:province":"IA",
    "wof:name":"Bay Kennels",
    "wof:placetype":"venue"
},
  "geometry": {"coordinates":[-96.43984500000001,42.524561],"type":"Point"}
}