{
  "type": "Feature",
  "properties": {
    "addr:full":"1724 W Locust St Davenport IA 52804",
    "addr:housenumber":"1724",
    "addr:postcode":"52804",
    "addr:street":"W Locust St",
    "iso:country":"US",
    "sg:address":"1724 W Locust St",
    "sg:city":"Davenport",
    "sg:classifiers":[
        {
            "category":"Banks & Credit Unions",
            "subcategory":"Bank",
            "type":"Services"
        }
    ],
    "sg:phone":"+1 563 322 3140",
    "sg:postcode":"52804",
    "sg:province":"IA",
    "sg:tags":[
        "cashing",
        "check"
    ],
    "wof:name":"Check Into Cash",
    "wof:placetype":"venue"
},
  "geometry": {"coordinates":[-90.602064,41.53825],"type":"Point"}
}