{
  "type": "Feature",
  "properties": {
    "iso:country":"US",
    "sg:address":"1101 N 2nd St",
    "sg:city":"Clinton",
    "sg:classifiers":[
        {
            "category":"Personal",
            "subcategory":"Beauty Salon",
            "type":"Services"
        }
    ],
    "sg:phone":"+1 563 243 6460",
    "sg:postcode":"52732",
    "sg:province":"IA",
    "wof:name":"Clinton Family Hair Care Ctr",
    "wof:placetype":"venue"
},
  "geometry": {"coordinates":[-90.185318,41.857298],"type":"Point"}
}