{
  "type": "Feature",
  "properties": {
    "addr:full":"201 Washington St Clearfield IA 50840",
    "addr:housenumber":"201",
    "addr:postcode":"50840",
    "addr:street":"Washington St",
    "iso:country":"US",
    "sg:address":"201 Washington St",
    "sg:city":"Clearfield",
    "sg:classifiers":[
        {
            "category":"Personal",
            "subcategory":"Beauty Salon",
            "type":"Services"
        }
    ],
    "sg:phone":"+1 641 336 2811",
    "sg:postcode":"50840",
    "sg:province":"IA",
    "wof:name":"New You",
    "wof:placetype":"venue"
},
  "geometry": {"coordinates":[-94.473191,40.801775],"type":"Point"}
}