{
  "type": "Feature",
  "properties": {
    "addr:full":"3918 Walnut Grove Ct Cedar Rapids IA 52402",
    "addr:housenumber":"3918",
    "addr:postcode":"52402",
    "addr:street":"Walnut Grove Ct",
    "iso:country":"US",
    "sg:address":"3918 Walnut Grove Ct",
    "sg:city":"Cedar Rapids",
    "sg:classifiers":[
        {
            "category":"Professional",
            "subcategory":"Business Services",
            "type":"Services"
        }
    ],
    "sg:phone":"+1 319 378 4903",
    "sg:postcode":"52402",
    "sg:province":"IA",
    "wof:name":"Central Planes Aviation Lc",
    "wof:placetype":"venue"
},
  "geometry": {"coordinates":[-91.73030199999999,42.019624],"type":"Point"}
}