{
  "type": "Feature",
  "properties": {
    "iso:country":"US",
    "sg:address":"5655 State Hwy 175",
    "sg:city":"Ida Grove",
    "sg:classifiers":[
        {
            "category":"Building & Trades",
            "subcategory":"Pest Control",
            "type":"Services"
        }
    ],
    "sg:phone":"+1 712 364 2330",
    "sg:postcode":"51445",
    "sg:province":"IA",
    "sg:tags":[
        "insect",
        "devices"
    ],
    "wof:name":"Cropmate Co",
    "wof:placetype":"venue"
},
  "geometry": {"coordinates":[-95.51446,42.343734],"type":"Point"}
}