{
  "type": "Feature",
  "properties": {
    "iso:country":"US",
    "sg:address":"4895 8th Ave",
    "sg:city":"Marion",
    "sg:classifiers":[
        {
            "category":"Manufacturing",
            "subcategory":"Tools & Machinery",
            "type":"Manufacturing & Wholesale Goods"
        }
    ],
    "sg:phone":"+1 319 377 6339",
    "sg:postcode":"52302",
    "sg:province":"IA",
    "sg:tags":[
        "pump"
    ],
    "wof:name":"Northway Well & Pump Co",
    "wof:placetype":"venue"
},
  "geometry": {"coordinates":[-91.56288499999999,42.03402],"type":"Point"}
}