{
  "type": "Feature",
  "properties": {
    "addr:full":"104 Center St Wiota IA 50274",
    "addr:housenumber":"104",
    "addr:postcode":"50274",
    "addr:street":"Center St",
    "iso:country":"US",
    "sg:address":"104 Center St",
    "sg:city":"Wiota",
    "sg:classifiers":[
        {
            "category":"Organizations",
            "subcategory":"Religious Organization",
            "type":"Services"
        }
    ],
    "sg:phone":"+1 712 783 4431",
    "sg:postcode":"50274",
    "sg:province":"IA",
    "sg:tags":[
        "church"
    ],
    "wof:name":"United Methodist Church",
    "wof:placetype":"venue"
},
  "geometry": {"coordinates":[-94.88947400000001,41.403555],"type":"Point"}
}