{
  "type": "Feature",
  "properties": {
    "addr:full":"720 1st Ave Perry IA 50220",
    "addr:housenumber":"720",
    "addr:postcode":"50220",
    "addr:street":"1St Ave",
    "iso:country":"US",
    "sg:address":"720 1st Ave",
    "sg:city":"Perry",
    "sg:classifiers":[
        {
            "category":"Banks & Credit Unions",
            "subcategory":"Bank",
            "type":"Services"
        }
    ],
    "sg:phone":"+1 515 465 5180",
    "sg:postcode":"50220",
    "sg:province":"IA",
    "wof:name":"Family Credit Union",
    "wof:placetype":"venue"
},
  "geometry": {"coordinates":[-94.106494,41.835132],"type":"Point"}
}