{
  "type": "Feature",
  "properties": {
    "addr:full":"1103 Broad St Grinnell IA 50112",
    "addr:housenumber":"1103",
    "addr:postcode":"50112",
    "addr:street":"Broad St",
    "iso:country":"US",
    "sg:address":"1103 Broad St",
    "sg:city":"Grinnell",
    "sg:classifiers":[
        {
            "category":"Retail",
            "subcategory":"Funeral Services",
            "type":"Services"
        }
    ],
    "sg:phone":"+1 641 236 3134",
    "sg:postcode":"50112",
    "sg:province":"IA",
    "sg:tags":[
        "director"
    ],
    "wof:name":"Smith Funeral Home",
    "wof:placetype":"venue"
},
  "geometry": {"coordinates":[-92.7242,41.747573],"type":"Point"}
}