{
  "type": "Feature",
  "properties": {
    "addr:full":"1501 E 10th St Atlantic IA 50022",
    "addr:housenumber":"1501",
    "addr:postcode":"50022",
    "addr:street":"E 10Th St",
    "iso:country":"US",
    "sg:address":"1501 E 10th St",
    "sg:city":"Atlantic",
    "sg:classifiers":[
        {
            "category":"Health Services",
            "subcategory":"Doctor",
            "type":"Services"
        }
    ],
    "sg:phone":"+1 712 243 7590",
    "sg:postcode":"50022",
    "sg:province":"IA",
    "sg:tags":[
        "physician",
        "surgeon"
    ],
    "wof:name":"Bluffs Urological Assoc",
    "wof:placetype":"venue"
},
  "geometry": {"coordinates":[-94.993274,41.400966],"type":"Point"}
}