{
  "type": "Feature",
  "properties": {
    "iso:country":"US",
    "sg:address":"301 Main Ave",
    "sg:city":"Clear Lake",
    "sg:classifiers":[
        {
            "category":"Shopping",
            "subcategory":"Florist",
            "type":"Retail Goods"
        }
    ],
    "sg:phone":"+1 641 357 1505",
    "sg:postcode":"50428",
    "sg:province":"IA",
    "wof:name":"Red Geranium",
    "wof:placetype":"venue"
},
  "geometry": {"coordinates":[-93.381011,43.136516],"type":"Point"}
}