{
  "type": "Feature",
  "properties": {
    "addr:full":"207 S 1st St Guttenberg IA 52052",
    "addr:housenumber":"207",
    "addr:postcode":"52052",
    "addr:street":"S 1St St",
    "iso:country":"US",
    "sg:address":"207 S 1st St",
    "sg:city":"Guttenberg",
    "sg:classifiers":[
        {
            "category":"Retail",
            "subcategory":"Funeral Services",
            "type":"Services"
        }
    ],
    "sg:phone":"+1 563 252 1842",
    "sg:postcode":"52052",
    "sg:province":"IA",
    "sg:tags":[
        "director",
        "home"
    ],
    "wof:name":"Tuecke-Allyn Funeral Home Inc",
    "wof:placetype":"venue"
},
  "geometry": {"coordinates":[-91.09773,42.784702],"type":"Point"}
}