{
  "type": "Feature",
  "properties": {
    "iso:country":"US",
    "sg:address":"35 W State St",
    "sg:city":"Marshalltown",
    "sg:classifiers":[
        {
            "category":"Sports & Exercise",
            "subcategory":"Gym",
            "type":"Entertainment"
        }
    ],
    "sg:phone":"+1 641 754 1754",
    "sg:postcode":"50158",
    "sg:province":"IA",
    "sg:tags":[
        "fitness",
        "physical",
        "facility"
    ],
    "wof:name":"Curves For Women",
    "wof:placetype":"venue"
},
  "geometry": {"coordinates":[-92.914102,42.050468],"type":"Point"}
}