{
  "type": "Feature",
  "properties": {
    "iso:country":"US",
    "sg:address":"608 Market St",
    "sg:city":"Audubon",
    "sg:classifiers":[
        {
            "category":"Government",
            "subcategory":"Office",
            "type":"Public Place"
        }
    ],
    "sg:phone":"+1 712 563 4239",
    "sg:postcode":"50025",
    "sg:province":"IA",
    "wof:name":"Audubon County Extension Svc",
    "wof:placetype":"venue"
},
  "geometry": {"coordinates":[-94.93238100000001,41.71783],"type":"Point"}
}