{
  "type": "Feature",
  "properties": {
    "iso:country":"US",
    "sg:address":"109 W Van Buren St",
    "sg:city":"Centerville",
    "sg:classifiers":[
        {
            "category":"Insurance",
            "subcategory":"Insurance Agent",
            "type":"Services"
        }
    ],
    "sg:phone":"+1 641 856 3333",
    "sg:postcode":"52544",
    "sg:province":"IA",
    "wof:name":"North Side Of The Square Inc",
    "wof:placetype":"venue"
},
  "geometry": {"coordinates":[-92.87423699999999,40.734933],"type":"Point"}
}