{
  "type": "Feature",
  "properties": {
    "iso:country":"US",
    "sg:address":"11131 Red Bridge St",
    "sg:city":"Monroe",
    "sg:classifiers":[
        {
            "category":"Farming",
            "subcategory":"Livestock Farm",
            "type":"Manufacturing & Wholesale Goods"
        }
    ],
    "sg:phone":"+1 641 793 2937",
    "sg:postcode":"50170",
    "sg:province":"IA",
    "sg:tags":[
        "field",
        "corn",
        "soybean",
        "general"
    ],
    "wof:name":"Dop Family Farm",
    "wof:placetype":"venue"
},
  "geometry": {"coordinates":[-93.024519,41.540473],"type":"Point"}
}