{
  "type": "Feature",
  "properties": {
    "addr:full":"1855 160th St Creston IA 50801",
    "addr:housenumber":"1855",
    "addr:postcode":"50801",
    "addr:street":"160Th St",
    "iso:country":"US",
    "sg:address":"1855 160th St",
    "sg:city":"Creston",
    "sg:classifiers":[
        {
            "category":"Real Estate",
            "subcategory":"Real Estate Operator",
            "type":"Services"
        }
    ],
    "sg:phone":"+1 641 782 4229",
    "sg:postcode":"50801",
    "sg:province":"IA",
    "sg:tags":[
        "property",
        "lessor"
    ],
    "wof:name":"Dale Mc Ginnis",
    "wof:placetype":"venue"
},
  "geometry": {"coordinates":[-94.30755600000001,41.071003],"type":"Point"}
}