{
  "type": "Feature",
  "properties": {
    "iso:country":"US",
    "sg:address":"157 Norton Ave",
    "sg:city":"Council Bluffs",
    "sg:classifiers":[
        {
            "category":"Retail",
            "subcategory":"Portrait Studio",
            "type":"Services"
        }
    ],
    "sg:phone":"+1 712 322 6827",
    "sg:postcode":"51503",
    "sg:province":"IA",
    "sg:tags":[
        "photo"
    ],
    "wof:name":"Mike Whye Photographer",
    "wof:placetype":"venue"
},
  "geometry": {"coordinates":[-95.84039799999999,41.274705],"type":"Point"}
}