{
  "type": "Feature",
  "properties": {
    "iso:country":"US",
    "sg:address":"2455 Williams Blvd SW",
    "sg:city":"Cedar Rapids",
    "sg:classifiers":[
        {
            "category":"Retail",
            "subcategory":"Auto Repair",
            "type":"Services"
        }
    ],
    "sg:phone":"+1 319 365 0022",
    "sg:postcode":"52404",
    "sg:province":"IA",
    "wof:name":"Boulevard Automotive",
    "wof:placetype":"venue"
},
  "geometry": {"coordinates":[-91.705213,41.965552],"type":"Point"}
}