{
  "type": "Feature",
  "properties": {
    "addr:full":"10 35th St Des Moines IA 50312",
    "addr:housenumber":"10",
    "addr:postcode":"50312",
    "addr:street":"35Th St",
    "iso:country":"US",
    "sg:address":"10 35th St",
    "sg:city":"Des Moines",
    "sg:classifiers":[
        {
            "category":"Professional",
            "subcategory":"Advertising",
            "type":"Services"
        }
    ],
    "sg:phone":"+1 515 223 6490",
    "sg:postcode":"50312",
    "sg:province":"IA",
    "wof:name":"Accent Ads Inc",
    "wof:placetype":"venue"
},
  "geometry": {"coordinates":[-93.664264,41.578141],"type":"Point"}
}