{
  "type": "Feature",
  "properties": {
    "iso:country":"US",
    "sg:address":"1021 Seneca St",
    "sg:city":"Storm Lake",
    "sg:phone":"+1 712 732 2596",
    "sg:postcode":"50588",
    "sg:province":"IA",
    "sg:tags":[
        "farm",
        "corn",
        "soybean"
    ],
    "wof:name":"Skibsted Orlean",
    "wof:placetype":"venue"
},
  "geometry": {"coordinates":[-95.196741,42.649893],"type":"Point"}
}