{
  "type": "Feature",
  "properties": {
    "iso:country":"US",
    "sg:address":"3561 Turnberry Dr",
    "sg:city":"West Des Moines",
    "sg:classifiers":[
        {
            "category":"Building & Trades",
            "subcategory":"Electrical",
            "type":"Services"
        }
    ],
    "sg:phone":"+1 515 440 3428",
    "sg:postcode":"50265",
    "sg:province":"IA",
    "sg:tags":[
        "equipment",
        "industrial",
        "electrical",
        "contractor"
    ],
    "wof:name":"Pro Service Electric",
    "wof:placetype":"venue"
},
  "geometry": {"coordinates":[-93.75249599999999,41.553684],"type":"Point"}
}