{
  "type": "Feature",
  "properties": {
    "iso:country":"US",
    "sg:address":"2024 NW 92nd Ct",
    "sg:city":"Clive",
    "sg:classifiers":[
        {
            "category":"Professional",
            "subcategory":"Lawyer & Legal Services",
            "type":"Services"
        }
    ],
    "sg:phone":"+1 515 223 0574",
    "sg:postcode":"50325",
    "sg:province":"IA",
    "sg:tags":[
        "attorney"
    ],
    "wof:name":"Gene Maddox",
    "wof:placetype":"venue"
},
  "geometry": {"coordinates":[-93.743284,41.609582],"type":"Point"}
}