{
  "type": "Feature",
  "properties": {
    "iso:country":"US",
    "sg:address":"1305 Country Club Ln",
    "sg:city":"Spencer",
    "sg:phone":"+1 712 262 1131",
    "sg:postcode":"51301",
    "sg:province":"IA",
    "sg:tags":[
        "farm",
        "corn",
        "soybean"
    ],
    "wof:name":"Jim K Barglof",
    "wof:placetype":"venue"
},
  "geometry": {"coordinates":[-95.181749,43.151044],"type":"Point"}
}