{
  "type": "Feature",
  "properties": {
    "iso:country":"US",
    "sg:address":"1441 29th St",
    "sg:city":"West Des Moines",
    "sg:classifiers":[
        {
            "category":"Professional",
            "subcategory":"Accounting & Tax Preparation",
            "type":"Services"
        }
    ],
    "sg:phone":"+1 515 223 7300",
    "sg:postcode":"50266",
    "sg:province":"IA",
    "sg:tags":[
        "accountant"
    ],
    "sg:website":"www.brookslodden.com",
    "wof:name":"Brooks Lodden",
    "wof:placetype":"venue"
},
  "geometry": {"coordinates":[-93.74373,41.595118],"type":"Point"}
}