{
  "type": "Feature",
  "properties": {
    "iso:country":"US",
    "sg:address":"2538 York Ave",
    "sg:city":"Winthrop",
    "sg:classifiers":[
        {
            "category":"Manufacturing",
            "subcategory":"Tools & Machinery",
            "type":"Manufacturing & Wholesale Goods"
        }
    ],
    "sg:phone":"+1 563 927 6624",
    "sg:postcode":"50682",
    "sg:province":"IA",
    "wof:name":"Sutton Welding & Fabrication",
    "wof:placetype":"venue"
},
  "geometry": {"coordinates":[-91.61738,42.421575],"type":"Point"}
}