{
  "type": "Feature",
  "properties": {
    "iso:country":"US",
    "sg:address":"20 N Frederick Ave",
    "sg:city":"Oelwein",
    "sg:classifiers":[
        {
            "category":"Home & Garden",
            "subcategory":"Hardware",
            "type":"Retail Goods"
        }
    ],
    "sg:phone":"+1 319 283 3826",
    "sg:postcode":"50662",
    "sg:province":"IA",
    "wof:name":"Ace Hardware",
    "wof:placetype":"venue"
},
  "geometry": {"coordinates":[-91.913431,42.679018],"type":"Point"}
}