{
  "type": "Feature",
  "properties": {
    "iso:country":"US",
    "sg:address":"3982 Aurora St",
    "sg:city":"Dubuque",
    "sg:classifiers":[
        {
            "category":"Professional",
            "subcategory":"Business Services",
            "type":"Services"
        }
    ],
    "sg:phone":"+1 563 557 2082",
    "sg:postcode":"52002",
    "sg:province":"IA",
    "wof:name":"Koester Wise Enterprises LLP",
    "wof:placetype":"venue"
},
  "geometry": {"coordinates":[-90.73726499999999,42.50593],"type":"Point"}
}