{
  "type": "Feature",
  "properties": {
    "iso:country":"US",
    "sg:address":"2458 170th St",
    "sg:city":"Greeley",
    "sg:classifiers":[
        {
            "category":"Farming",
            "subcategory":"Farm",
            "type":"Manufacturing & Wholesale Goods"
        }
    ],
    "sg:phone":"+1 563 925 2215",
    "sg:postcode":"52050",
    "sg:province":"IA",
    "sg:tags":[
        "crop",
        "general"
    ],
    "wof:name":"Dan Krogmann",
    "wof:placetype":"venue"
},
  "geometry": {"coordinates":[-91.313976,42.543142],"type":"Point"}
}