{
  "type": "Feature",
  "properties": {
    "addr:full":"428 Western Ave Davenport IA 52801",
    "addr:housenumber":"428",
    "addr:postcode":"52801",
    "addr:street":"Western Ave",
    "iso:country":"US",
    "sg:address":"428 Western Ave",
    "sg:city":"Davenport",
    "sg:classifiers":[
        {
            "category":"Government",
            "subcategory":"Office",
            "type":"Public Place"
        }
    ],
    "sg:phone":"+1 563 326 8635",
    "sg:postcode":"52801",
    "sg:province":"IA",
    "sg:tags":[
        "county",
        "taxation"
    ],
    "sg:website":"www.scottcountyiowa.com",
    "wof:name":"Scott County Assessor Office",
    "wof:placetype":"venue"
},
  "geometry": {"coordinates":[-90.581521,41.523753],"type":"Point"}
}