{
  "type": "Feature",
  "properties": {
    "addr:full":"1214 Agency St Burlington IA 52601",
    "addr:housenumber":"1214",
    "addr:postcode":"52601",
    "addr:street":"Agency St",
    "iso:country":"US",
    "sg:address":"1214 Agency St",
    "sg:city":"Burlington",
    "sg:classifiers":[
        {
            "category":"Building & Trades",
            "subcategory":"Construction",
            "type":"Services"
        }
    ],
    "sg:phone":"+1 319 754 5764",
    "sg:postcode":"52601",
    "sg:province":"IA",
    "sg:tags":[
        "elevator"
    ],
    "wof:name":"KONE Inc",
    "wof:placetype":"venue"
},
  "geometry": {"coordinates":[-91.115611,40.814037],"type":"Point"}
}