{
  "type": "Feature",
  "properties": {
    "addr:full":"1827 1st St W Independence IA 50644",
    "addr:housenumber":"1827",
    "addr:postcode":"50644",
    "addr:street":"1St St W",
    "iso:country":"US",
    "sg:address":"1827 1st St W",
    "sg:city":"Independence",
    "sg:classifiers":[
        {
            "category":"Retail",
            "subcategory":"Funeral Services",
            "type":"Services"
        }
    ],
    "sg:phone":"+1 319 334 2501",
    "sg:postcode":"50644",
    "sg:province":"IA",
    "sg:tags":[
        "director"
    ],
    "wof:name":"Reiff Funeral Homes",
    "wof:placetype":"venue"
},
  "geometry": {"coordinates":[-91.916978,42.468337],"type":"Point"}
}