{
  "type": "Feature",
  "properties": {
    "addr:full":"500 High Ave W Oskaloosa IA 52577",
    "addr:housenumber":"500",
    "addr:postcode":"52577",
    "addr:street":"High Ave W Oskaloosa",
    "iso:country":"US",
    "sg:address":"500 High Ave W",
    "sg:city":"Oskaloosa",
    "sg:classifiers":[
        {
            "category":"Social Services",
            "type":"Services"
        }
    ],
    "sg:phone":"+1 641 673 4306",
    "sg:postcode":"52577",
    "sg:province":"IA",
    "sg:tags":[
        "organization",
        "welfare"
    ],
    "wof:name":"Red Cross Of Mahaska County",
    "wof:placetype":"venue"
},
  "geometry": {"coordinates":[-92.65083199999999,41.295324],"type":"Point"}
}