{
  "type": "Feature",
  "properties": {
    "addr:full":"2807 260th St Kamrar IA 50132",
    "addr:housenumber":"2807",
    "addr:postcode":"50132",
    "addr:street":"260Th St",
    "iso:country":"US",
    "sg:address":"2807 260th St",
    "sg:city":"Kamrar",
    "sg:phone":"+1 515 325 6336",
    "sg:postcode":"50132",
    "sg:province":"IA",
    "sg:tags":[
        "farm",
        "corn"
    ],
    "wof:name":"Lester Denekas",
    "wof:placetype":"venue"
},
  "geometry": {"coordinates":[-93.619176,42.412715],"type":"Point"}
}