{
  "type": "Feature",
  "properties": {
    "iso:country":"US",
    "sg:address":"700 6th Ave",
    "sg:city":"De Witt",
    "sg:classifiers":[
        {
            "category":"Real Estate",
            "subcategory":"Real Estate Agent",
            "type":"Services"
        }
    ],
    "sg:phone":"+1 563 659 8185",
    "sg:postcode":"52742",
    "sg:province":"IA",
    "wof:name":"Total Realty",
    "wof:placetype":"venue"
},
  "geometry": {"coordinates":[-90.538963,41.823268],"type":"Point"}
}