{
  "type": "Feature",
  "properties": {
    "iso:country":"US",
    "sg:address":"2709 Jordan Grove",
    "sg:city":"West Des Moines",
    "sg:classifiers":[
        {
            "category":"Professional",
            "subcategory":"Management & Consulting",
            "type":"Services"
        }
    ],
    "sg:phone":"+1 515 225 1075",
    "sg:postcode":"50265",
    "sg:province":"IA",
    "wof:name":"Ely Bennett",
    "wof:placetype":"venue"
},
  "geometry": {"coordinates":[-93.741564,41.567738],"type":"Point"}
}