{
  "type": "Feature",
  "properties": {
    "addr:full":"6388 State Hwy 14 S Newton IA 50208",
    "addr:housenumber":"6388",
    "addr:postcode":"50208",
    "addr:street":"State Hwy 14 S",
    "iso:country":"US",
    "sg:address":"6388 State Hwy 14 S",
    "sg:city":"Newton",
    "sg:classifiers":[
        {
            "category":"Retail",
            "subcategory":"Repair Shop",
            "type":"Services"
        }
    ],
    "sg:phone":"+1 641 791 7384",
    "sg:postcode":"50208",
    "sg:province":"IA",
    "sg:tags":[
        "scooter",
        "motorcycle",
        "motor"
    ],
    "wof:name":"Mid Iowa Motor Sports",
    "wof:placetype":"venue"
},
  "geometry": {"coordinates":[-93.091229,41.623124],"type":"Point"}
}