{
  "type": "Feature",
  "properties": {
    "iso:country":"US",
    "sg:address":"816 5th Ave",
    "sg:city":"Grinnell",
    "sg:classifiers":[
        {
            "category":"Restaurant",
            "type":"Food & Drink"
        }
    ],
    "sg:phone":"+1 641 236 5331",
    "sg:postcode":"50112",
    "sg:province":"IA",
    "wof:name":"Pagliai's Pizza",
    "wof:placetype":"venue"
},
  "geometry": {"coordinates":[-92.725553,41.744621],"type":"Point"}
}