{
  "type": "Feature",
  "properties": {
    "iso:country":"US",
    "sg:address":"24757 200th St",
    "sg:city":"Calmar",
    "sg:classifiers":[
        {
            "category":"Utilities",
            "subcategory":"Cable",
            "type":"Services"
        }
    ],
    "sg:phone":"+1 563 737 2296",
    "sg:postcode":"52132",
    "sg:province":"IA",
    "sg:tags":[
        "television"
    ],
    "wof:name":"Ridgeway Cablevision",
    "wof:placetype":"venue"
},
  "geometry": {"coordinates":[-92.087405,43.227645],"type":"Point"}
}