{
  "type": "Feature",
  "properties": {
    "addr:full":"1581 Grundy Ave Moville IA 51039",
    "addr:housenumber":"1581",
    "addr:postcode":"51039",
    "addr:street":"Grundy Ave",
    "iso:country":"US",
    "sg:address":"1581 Grundy Ave",
    "sg:city":"Moville",
    "sg:classifiers":[
        {
            "category":"Farming",
            "subcategory":"Farm",
            "type":"Manufacturing & Wholesale Goods"
        }
    ],
    "sg:phone":"+1 712 873 3740",
    "sg:postcode":"51039",
    "sg:province":"IA",
    "sg:tags":[
        "crop",
        "general"
    ],
    "wof:name":"Ted Peters Farms",
    "wof:placetype":"venue"
},
  "geometry": {"coordinates":[-96.09581300000001,42.477757],"type":"Point"}
}