{
  "type": "Feature",
  "properties": {
    "iso:country":"US",
    "sg:address":"2240 7th Ave",
    "sg:city":"Marion",
    "sg:classifiers":[
        {
            "category":"Restaurant",
            "type":"Food & Drink"
        }
    ],
    "sg:phone":"+1 319 377 1699",
    "sg:postcode":"52302",
    "sg:province":"IA",
    "wof:name":"Subway Sandwiches & Salads",
    "wof:placetype":"venue"
},
  "geometry": {"coordinates":[-91.586146,42.033344],"type":"Point"}
}