{
  "type": "Feature",
  "properties": {
    "iso:country":"US",
    "sg:address":"5058 Grand Ave",
    "sg:city":"West Des Moines",
    "sg:classifiers":[
        {
            "category":"Professional",
            "type":"Services"
        }
    ],
    "sg:phone":"+1 515 267 9097",
    "sg:postcode":"50265",
    "sg:province":"IA",
    "sg:tags":[
        "scientist"
    ],
    "sg:website":"www.garinc.com",
    "wof:name":"Global Tech Svc",
    "wof:placetype":"venue"
},
  "geometry": {"coordinates":[-93.770702,41.541334],"type":"Point"}
}