{
  "type": "Feature",
  "properties": {
    "iso:country":"US",
    "sg:address":"211 W 53rd St",
    "sg:city":"Davenport",
    "sg:classifiers":[
        {
            "category":"Food & Beverages",
            "subcategory":"Liquor & Beverages",
            "type":"Retail Goods"
        }
    ],
    "sg:phone":"+1 563 386 8651",
    "sg:postcode":"52806",
    "sg:province":"IA",
    "wof:name":"Liquor Store",
    "wof:placetype":"venue"
},
  "geometry": {"coordinates":[-90.57457700000001,41.574454],"type":"Point"}
}