{
  "type": "Feature",
  "properties": {
    "addr:full":"25 1st St SE Oelwein IA 50662",
    "addr:housenumber":"25",
    "addr:postcode":"50662",
    "addr:street":"1St St Se",
    "iso:country":"US",
    "sg:address":"25 1st St SE",
    "sg:city":"Oelwein",
    "sg:classifiers":[
        {
            "category":"Manufacturing",
            "subcategory":"Printing",
            "type":"Manufacturing & Wholesale Goods"
        }
    ],
    "sg:phone":"+1 319 283 2144",
    "sg:postcode":"50662",
    "sg:province":"IA",
    "sg:tags":[
        "newspaper"
    ],
    "sg:website":"www.oelweindailyregister.com",
    "wof:name":"Oelwein Publishing Co",
    "wof:placetype":"venue"
},
  "geometry": {"coordinates":[-91.91311,42.677135],"type":"Point"}
}