{
  "type": "Feature",
  "properties": {
    "addr:full":"917 S Kennedy Ave Madrid IA 50156",
    "addr:housenumber":"917",
    "addr:postcode":"50156",
    "addr:street":"S Kennedy Ave",
    "iso:country":"US",
    "sg:address":"917 S Kennedy Ave",
    "sg:city":"Madrid",
    "sg:classifiers":[
        {
            "category":"Real Estate",
            "subcategory":"Developer",
            "type":"Services"
        }
    ],
    "sg:phone":"+1 515 795 2120",
    "sg:postcode":"50156",
    "sg:province":"IA",
    "sg:tags":[
        "mobile",
        "home"
    ],
    "wof:name":"Meadow Estates",
    "wof:placetype":"venue"
},
  "geometry": {"coordinates":[-93.81561499999999,41.868162],"type":"Point"}
}