{
  "type": "Feature",
  "properties": {
    "addr:full":"708 E 6th St Vinton IA 52349",
    "addr:housenumber":"708",
    "addr:postcode":"52349",
    "addr:street":"E 6Th St",
    "iso:country":"US",
    "sg:address":"708 E 6th St",
    "sg:city":"Vinton",
    "sg:classifiers":[
        {
            "category":"Building & Trades",
            "subcategory":"Cleaning & Sanitation",
            "type":"Services"
        }
    ],
    "sg:phone":"+1 319 472 2310",
    "sg:postcode":"52349",
    "sg:province":"IA",
    "sg:tags":[
        "window"
    ],
    "wof:name":"C & J Cleaning & Window Wash",
    "wof:placetype":"venue"
},
  "geometry": {"coordinates":[-92.01611200000001,42.165662],"type":"Point"}
}