{
  "type": "Feature",
  "properties": {
    "iso:country":"US",
    "sg:address":"229 S Main St",
    "sg:city":"Maquoketa",
    "sg:classifiers":[
        {
            "category":"Health Services",
            "subcategory":"Optometrist",
            "type":"Services"
        }
    ],
    "sg:phone":"+1 563 652 2795",
    "sg:postcode":"52060",
    "sg:province":"IA",
    "wof:name":"Sybesma Eye & Vision Ctr",
    "wof:placetype":"venue"
},
  "geometry": {"coordinates":[-90.665424,42.067294],"type":"Point"}
}