{
  "type": "Feature",
  "properties": {
    "addr:full":"800 S Center St Shenandoah IA 51601",
    "addr:housenumber":"800",
    "addr:postcode":"51601",
    "addr:street":"S Center St",
    "iso:country":"US",
    "sg:address":"800 S Center St",
    "sg:city":"Shenandoah",
    "sg:classifiers":[
        {
            "category":"Wholesale",
            "subcategory":"Non-durable Goods",
            "type":"Manufacturing & Wholesale Goods"
        }
    ],
    "sg:phone":"+1 712 246 3305",
    "sg:postcode":"51601",
    "sg:province":"IA",
    "wof:name":"Omni Trade Linx",
    "wof:placetype":"venue"
},
  "geometry": {"coordinates":[-95.366079,40.759122],"type":"Point"}
}