{
  "type": "Feature",
  "properties": {
    "iso:country":"US",
    "sg:address":"112 Center St",
    "sg:city":"Elgin",
    "sg:classifiers":[
        {
            "category":"Autos & Motor Vehicles",
            "subcategory":"Fuel & Gas Station",
            "type":"Retail Goods"
        }
    ],
    "sg:phone":"+1 563 426 5496",
    "sg:postcode":"52141",
    "sg:province":"IA",
    "sg:tags":[
        "oil"
    ],
    "wof:name":"Don's Phillips 66",
    "wof:placetype":"venue"
},
  "geometry": {"coordinates":[-91.627807,42.957404],"type":"Point"}
}