{
  "type": "Feature",
  "properties": {
    "addr:full":"28637 620th Ave Nevada IA 50201",
    "addr:housenumber":"28637",
    "addr:postcode":"50201",
    "addr:street":"620Th Ave",
    "iso:country":"US",
    "sg:address":"28637 620th Ave",
    "sg:city":"Nevada",
    "sg:classifiers":[
        {
            "category":"Professional",
            "type":"Services"
        }
    ],
    "sg:phone":"+1 515 382 4144",
    "sg:postcode":"50201",
    "sg:province":"IA",
    "wof:name":"Barkers Creek and Company Inc",
    "wof:placetype":"venue"
},
  "geometry": {"coordinates":[-93.46343899999999,41.930776],"type":"Point"}
}