{
  "type": "Feature",
  "properties": {
    "addr:full":"102 1st Ave SW Waucoma IA 52171",
    "addr:housenumber":"102",
    "addr:postcode":"52171",
    "addr:street":"1St Ave Sw",
    "iso:country":"US",
    "sg:address":"102 1st Ave SW",
    "sg:city":"Waucoma",
    "sg:classifiers":[
        {
            "category":"Banks & Credit Unions",
            "subcategory":"Bank",
            "type":"Services"
        }
    ],
    "sg:phone":"+1 563 776 6414",
    "sg:postcode":"52171",
    "sg:province":"IA",
    "wof:name":"State Bank Of Lawler",
    "wof:placetype":"venue"
},
  "geometry": {"coordinates":[-92.034751,43.055997],"type":"Point"}
}