{
  "type": "Feature",
  "properties": {
    "addr:full":"15 X Ave Story City IA 50248",
    "addr:housenumber":"15",
    "addr:postcode":"50248",
    "addr:street":"X Ave",
    "iso:country":"US",
    "sg:address":"15 X Ave",
    "sg:city":"Story City",
    "sg:classifiers":[
        {
            "category":"Home & Garden",
            "subcategory":"Garden Supply",
            "type":"Retail Goods"
        }
    ],
    "sg:phone":"+1 515 733 2101",
    "sg:postcode":"50248",
    "sg:province":"IA",
    "sg:tags":[
        "bulb",
        "seed"
    ],
    "sg:website":"www.prairiebrandseed.com",
    "wof:name":"Sansgaard Seed Farm Inc",
    "wof:placetype":"venue"
},
  "geometry": {"coordinates":[-93.71793099999999,42.205776],"type":"Point"}
}