{
  "type": "Feature",
  "properties": {
    "addr:full":"26 S Main St Denison IA 51442",
    "addr:housenumber":"26",
    "addr:postcode":"51442",
    "addr:street":"S Main St",
    "iso:country":"US",
    "sg:address":"26 S Main St",
    "sg:city":"Denison",
    "sg:classifiers":[
        {
            "category":"Personal",
            "subcategory":"Beauty Salon",
            "type":"Services"
        }
    ],
    "sg:phone":"+1 712 263 5347",
    "sg:postcode":"51442",
    "sg:province":"IA",
    "wof:name":"Touch Of Class",
    "wof:placetype":"venue"
},
  "geometry": {"coordinates":[-95.355221,42.016453],"type":"Point"}
}