{
  "type": "Feature",
  "properties": {
    "iso:country":"US",
    "sg:address":"4327 N 13th St",
    "sg:city":"Carter Lake",
    "sg:classifiers":[
        {
            "category":"Retail",
            "subcategory":"Repair Shop",
            "type":"Services"
        }
    ],
    "sg:phone":"+1 712 347 5531",
    "sg:postcode":"51510",
    "sg:province":"IA",
    "sg:tags":[
        "taxidermist"
    ],
    "wof:name":"Dutson's Taxidermy",
    "wof:placetype":"venue"
},
  "geometry": {"coordinates":[-95.913195,41.297163],"type":"Point"}
}