{
  "type": "Feature",
  "properties": {
    "addr:full":"1089 Jackson Ave Tipton IA 52772",
    "addr:housenumber":"1089",
    "addr:postcode":"52772",
    "addr:street":"Jackson Ave",
    "iso:country":"US",
    "sg:address":"1089 Jackson Ave",
    "sg:city":"Tipton",
    "sg:classifiers":[
        {
            "category":"Wholesale",
            "subcategory":"Machinery & Supplies",
            "type":"Manufacturing & Wholesale Goods"
        }
    ],
    "sg:phone":"+1 563 886 6855",
    "sg:postcode":"52772",
    "sg:province":"IA",
    "sg:tags":[
        "equipment",
        "industrial"
    ],
    "wof:name":"Lawson Products Incorporated",
    "wof:placetype":"venue"
},
  "geometry": {"coordinates":[-91.19100400000001,41.788081],"type":"Point"}
}