{
  "type": "Feature",
  "properties": {
    "iso:country":"US",
    "sg:address":"609 2nd St",
    "sg:city":"Ida Grove",
    "sg:classifiers":[
        {
            "category":"Autos & Motor Vehicles",
            "subcategory":"Auto Supplies",
            "type":"Retail Goods"
        }
    ],
    "sg:phone":"+1 712 364 3625",
    "sg:postcode":"51445",
    "sg:province":"IA",
    "sg:tags":[
        "automobile",
        "parts"
    ],
    "wof:name":"Hanson Auto Supply",
    "wof:placetype":"venue"
},
  "geometry": {"coordinates":[-95.474028,42.345006],"type":"Point"}
}