{
  "type": "Feature",
  "properties": {
    "iso:country":"US",
    "sg:address":"19073 90th St",
    "sg:city":"Maynard",
    "sg:classifiers":[
        {
            "category":"Retail",
            "subcategory":"Animal Services",
            "type":"Services"
        }
    ],
    "sg:phone":"+1 563 637 2296",
    "sg:postcode":"50655",
    "sg:province":"IA",
    "wof:name":"Frederika Kennels LLC",
    "wof:placetype":"venue"
},
  "geometry": {"coordinates":[-91.963683,42.758631],"type":"Point"}
}