{
  "type": "Feature",
  "properties": {
    "iso:country":"US",
    "sg:address":"518 N 2nd St",
    "sg:city":"Cherokee",
    "sg:classifiers":[
        {
            "category":"Retail",
            "subcategory":"Portrait Studio",
            "type":"Services"
        }
    ],
    "sg:phone":"+1 712 225 2453",
    "sg:postcode":"51012",
    "sg:province":"IA",
    "sg:tags":[
        "photographer"
    ],
    "wof:name":"Pierson Photography",
    "wof:placetype":"venue"
},
  "geometry": {"coordinates":[-95.551345,42.754994],"type":"Point"}
}