{
  "type": "Feature",
  "properties": {
    "iso:country":"US",
    "sg:address":"3002 Newport Rd NE",
    "sg:city":"Iowa City",
    "sg:classifiers":[
        {
            "category":"Shopping",
            "type":"Retail Goods"
        }
    ],
    "sg:phone":"+1 319 338 7889",
    "sg:postcode":"52240",
    "sg:province":"IA",
    "sg:tags":[
        "wedding",
        "supply"
    ],
    "wof:name":"Gazebo On The Green",
    "wof:placetype":"venue"
},
  "geometry": {"coordinates":[-91.507324,41.71022],"type":"Point"}
}