{
  "type": "Feature",
  "properties": {
    "addr:full":"406 E Pine St Winfield IA 52659",
    "addr:housenumber":"406",
    "addr:postcode":"52659",
    "addr:street":"E Pine St",
    "iso:country":"US",
    "sg:address":"406 E Pine St",
    "sg:city":"Winfield",
    "sg:classifiers":[
        {
            "category":"Freight",
            "type":"Transportation"
        }
    ],
    "sg:phone":"+1 319 257 3263",
    "sg:postcode":"52659",
    "sg:province":"IA",
    "sg:tags":[
        "operator",
        "trucking"
    ],
    "wof:name":"Dmf Trucking",
    "wof:placetype":"venue"
},
  "geometry": {"coordinates":[-91.43244799999999,41.127605],"type":"Point"}
}