{
  "type": "Feature",
  "properties": {
    "addr:full":"300 13th St NW Cedar Rapids IA 52405",
    "addr:housenumber":"300",
    "addr:postcode":"52405",
    "addr:street":"13Th St Nw",
    "iso:country":"US",
    "sg:address":"300 13th St NW",
    "sg:city":"Cedar Rapids",
    "sg:classifiers":[
        {
            "category":"Education",
            "subcategory":"School",
            "type":"Public Place"
        }
    ],
    "sg:phone":"+1 319 558 2153",
    "sg:postcode":"52405",
    "sg:province":"IA",
    "sg:tags":[
        "high",
        "middle",
        "elementary"
    ],
    "wof:name":"Cedar Rapids Community School District",
    "wof:placetype":"venue"
},
  "geometry": {"coordinates":[-91.68940000000001,41.9753],"type":"Point"}
}