{
  "type": "Feature",
  "properties": {
    "addr:full":"3781 470th St Orange City IA 51041",
    "addr:housenumber":"3781",
    "addr:postcode":"51041",
    "addr:street":"470Th St",
    "iso:country":"US",
    "sg:address":"3781 470th St",
    "sg:city":"Orange City",
    "sg:classifiers":[
        {
            "category":"Professional",
            "type":"Services"
        }
    ],
    "sg:phone":"+1 712 737 3684",
    "sg:postcode":"51041",
    "sg:province":"IA",
    "sg:tags":[
        "establishment"
    ],
    "wof:name":"Bonnema & Bonnema",
    "wof:placetype":"venue"
},
  "geometry": {"coordinates":[-96.040847,42.967362],"type":"Point"}
}