{
  "type": "Feature",
  "properties": {
    "iso:country":"US",
    "sg:address":"535 NE 48th Pl",
    "sg:city":"Des Moines",
    "sg:classifiers":[
        {
            "category":"Building & Trades",
            "subcategory":"Plumbing",
            "type":"Services"
        }
    ],
    "sg:phone":"+1 515 244 4411",
    "sg:postcode":"50313",
    "sg:province":"IA",
    "sg:tags":[
        "septic"
    ],
    "wof:name":"B & B Sanitation & Septic Svc",
    "wof:placetype":"venue"
},
  "geometry": {"coordinates":[-93.613041,41.64851],"type":"Point"}
}