{
  "type": "Feature",
  "properties": {
    "iso:country":"US",
    "sg:address":"101 S Main St",
    "sg:city":"Charles City",
    "sg:classifiers":[
        {
            "category":"Government",
            "subcategory":"Office",
            "type":"Public Place"
        }
    ],
    "sg:phone":"+1 641 257 6118",
    "sg:postcode":"50616",
    "sg:province":"IA",
    "sg:tags":[
        "county",
        "taxation"
    ],
    "wof:name":"Floyd County Treasurer-Tax",
    "wof:placetype":"venue"
},
  "geometry": {"coordinates":[-92.68150900000001,43.064417],"type":"Point"}
}