{
  "type": "Feature",
  "properties": {
    "iso:country":"US",
    "sg:address":"2044 Logan Ave",
    "sg:city":"Waterloo",
    "sg:classifiers":[
        {
            "category":"Restaurant",
            "type":"Food & Drink"
        }
    ],
    "sg:phone":"+1 319 226 3338",
    "sg:postcode":"50703",
    "sg:province":"IA",
    "wof:name":"East Of China",
    "wof:placetype":"venue"
},
  "geometry": {"coordinates":[-92.337639,42.529932],"type":"Point"}
}