{
  "type": "Feature",
  "properties": {
    "iso:country":"US",
    "sg:address":"1704 15th St",
    "sg:city":"Rock Valley",
    "sg:classifiers":[
        {
            "category":"Retail",
            "subcategory":"Funeral Services",
            "type":"Services"
        }
    ],
    "sg:phone":"+1 712 476 2106",
    "sg:postcode":"51247",
    "sg:province":"IA",
    "sg:tags":[
        "director"
    ],
    "wof:name":"Porter Funeral Home",
    "wof:placetype":"venue"
},
  "geometry": {"coordinates":[-96.29169,43.205151],"type":"Point"}
}