{
  "type": "Feature",
  "properties": {
    "iso:country":"US",
    "sg:address":"101 Main St",
    "sg:city":"Argyle",
    "sg:classifiers":[
        {
            "category":"Organizations",
            "subcategory":"Religious Organization",
            "type":"Services"
        }
    ],
    "sg:phone":"+1 319 838 2702",
    "sg:postcode":"52639",
    "sg:province":"IA",
    "sg:tags":[
        "church"
    ],
    "wof:name":"Argyle Presbyterian Church",
    "wof:placetype":"venue"
},
  "geometry": {"coordinates":[-91.414745,40.532392],"type":"Point"}
}