{
  "type": "Feature",
  "properties": {
    "iso:country":"US",
    "sg:address":"928 Blondeau St",
    "sg:city":"Keokuk",
    "sg:classifiers":[
        {
            "category":"Organizations",
            "subcategory":"Religious Organization",
            "type":"Services"
        }
    ],
    "sg:phone":"+1 319 524 5266",
    "sg:postcode":"52632",
    "sg:province":"IA",
    "sg:tags":[
        "church"
    ],
    "wof:name":"First Christian Church",
    "wof:placetype":"venue"
},
  "geometry": {"coordinates":[-91.38616399999999,40.400085],"type":"Point"}
}