{
  "type": "Feature",
  "properties": {
    "iso:country":"US",
    "sg:address":"4860 Asbury Rd",
    "sg:city":"Dubuque",
    "sg:classifiers":[
        {
            "category":"Restaurant",
            "type":"Food & Drink"
        }
    ],
    "sg:menulink":"http://www.allmenus.com/ia/dubuque/154501-hardees/menu/",
    "sg:phone":"+1 563 584 0180",
    "sg:postcode":"52002",
    "sg:province":"IA",
    "sg:tags":[
        "burger",
        "american"
    ],
    "wof:name":"Hardee's",
    "wof:placetype":"venue"
},
  "geometry": {"coordinates":[-90.749387,42.514686],"type":"Point"}
}