{
  "type": "Feature",
  "properties": {
    "iso:country":"US",
    "sg:address":"424 Primrose Dr",
    "sg:city":"Hudson",
    "sg:classifiers":[
        {
            "category":"Building & Trades",
            "subcategory":"Construction",
            "type":"Services"
        }
    ],
    "sg:phone":"+1 319 988 3515",
    "sg:postcode":"50643",
    "sg:province":"IA",
    "sg:tags":[
        "concrete",
        "contractor"
    ],
    "wof:name":"T C Construction Co",
    "wof:placetype":"venue"
},
  "geometry": {"coordinates":[-92.461147,42.396359],"type":"Point"}
}