{
  "type": "Feature",
  "properties": {
    "addr:full":"502 W Walnut St Ogden IA 50212",
    "addr:housenumber":"502",
    "addr:postcode":"50212",
    "addr:street":"W Walnut St",
    "iso:country":"US",
    "sg:address":"502 W Walnut St",
    "sg:city":"Ogden",
    "sg:classifiers":[
        {
            "category":"Organizations",
            "subcategory":"Religious Organization",
            "type":"Services"
        }
    ],
    "sg:phone":"+1 515 275 3151",
    "sg:postcode":"50212",
    "sg:province":"IA",
    "sg:tags":[
        "church"
    ],
    "wof:name":"Church Of Christ",
    "wof:placetype":"venue"
},
  "geometry": {"coordinates":[-94.033331,42.038958],"type":"Point"}
}