{
  "type": "Feature",
  "properties": {
    "iso:country":"US",
    "sg:address":"118 N Clark St",
    "sg:city":"Forest City",
    "sg:classifiers":[
        {
            "category":"Professional",
            "subcategory":"Accounting & Tax Preparation",
            "type":"Services"
        }
    ],
    "sg:phone":"+1 641 582 3337",
    "sg:postcode":"50436",
    "sg:province":"IA",
    "sg:tags":[
        "return",
        "filing"
    ],
    "wof:name":"Rogness-1040 Etc",
    "wof:placetype":"venue"
},
  "geometry": {"coordinates":[-93.638375,43.263818],"type":"Point"}
}