{
  "type": "Feature",
  "properties": {
    "iso:country":"US",
    "sg:address":"3110 SE Grant St",
    "sg:city":"Ankeny",
    "sg:classifiers":[
        {
            "category":"Professional",
            "subcategory":"Computer Services",
            "type":"Services"
        }
    ],
    "sg:phone":"+1 515 964 4040",
    "sg:postcode":"50021",
    "sg:province":"IA",
    "sg:tags":[
        "related"
    ],
    "wof:name":"Frank De Lathouder",
    "wof:placetype":"venue"
},
  "geometry": {"coordinates":[-93.597465,41.699121],"type":"Point"}
}