{
  "type": "Feature",
  "properties": {
    "addr:full":"401 Main St Iowa Falls IA 50126",
    "addr:housenumber":"401",
    "addr:postcode":"50126",
    "addr:street":"Main St",
    "iso:country":"US",
    "sg:address":"401 Main St",
    "sg:city":"Iowa Falls",
    "sg:classifiers":[
        {
            "category":"Government",
            "subcategory":"Post Office",
            "type":"Public Place"
        }
    ],
    "sg:phone":"+1 641 648 9492",
    "sg:postcode":"50126",
    "sg:province":"IA",
    "sg:website":"www.usps.gov",
    "wof:name":"US Post Office",
    "wof:placetype":"venue"
},
  "geometry": {"coordinates":[-93.265424,42.521451],"type":"Point"}
}