{
  "type": "Feature",
  "properties": {
    "iso:country":"US",
    "sg:address":"9403 Hammontree Dr",
    "sg:city":"Urbandale",
    "sg:classifiers":[
        {
            "category":"Building & Trades",
            "subcategory":"Construction",
            "type":"Services"
        }
    ],
    "sg:phone":"+1 515 270 6745",
    "sg:postcode":"50322",
    "sg:province":"IA",
    "sg:tags":[
        "contractor"
    ],
    "wof:name":"Worldwide Refinishing Systems",
    "wof:placetype":"venue"
},
  "geometry": {"coordinates":[-93.749009,41.6408],"type":"Point"}
}