{
  "type": "Feature",
  "properties": {
    "iso:country":"US",
    "sg:address":"1712 S Paxton St",
    "sg:city":"Sioux City",
    "sg:classifiers":[
        {
            "category":"Building & Trades",
            "subcategory":"Construction",
            "type":"Services"
        }
    ],
    "sg:phone":"+1 712 898 2377",
    "sg:postcode":"51106",
    "sg:province":"IA",
    "sg:tags":[
        "general",
        "contractor"
    ],
    "wof:name":"A Plus Builders",
    "wof:placetype":"venue"
},
  "geometry": {"coordinates":[-96.36524799999999,42.473227],"type":"Point"}
}