{
  "type": "Feature",
  "properties": {
    "addr:full":"628 16th Ave Council Bluffs IA 51501",
    "addr:housenumber":"628",
    "addr:postcode":"51501",
    "addr:street":"16Th Ave",
    "iso:country":"US",
    "sg:address":"628 16th Ave",
    "sg:city":"Council Bluffs",
    "sg:classifiers":[
        {
            "category":"Bars & Pubs",
            "subcategory":"Nightclub",
            "type":"Food & Drink"
        }
    ],
    "sg:phone":"+1 712 322 6086",
    "sg:postcode":"51501",
    "sg:province":"IA",
    "sg:tags":[
        "nightlife"
    ],
    "wof:name":"Hard Luck Saloon",
    "wof:placetype":"venue"
},
  "geometry": {"coordinates":[-95.85425499999999,41.246757],"type":"Point"}
}