{
  "type": "Feature",
  "properties": {
    "iso:country":"US",
    "sg:address":"3507 Keystone Dr",
    "sg:city":"Dubuque",
    "sg:classifiers":[
        {
            "category":"Social Services",
            "subcategory":"Child Care",
            "type":"Services"
        }
    ],
    "sg:phone":"+1 563 583 8275",
    "sg:postcode":"52002",
    "sg:province":"IA",
    "wof:name":"Pooh's Corner Children Ctr",
    "wof:placetype":"venue"
},
  "geometry": {"coordinates":[-90.72677,42.505034],"type":"Point"}
}