{
  "type": "Feature",
  "properties": {
    "iso:country":"US",
    "sg:address":"102 Garfield St SW",
    "sg:city":"Bondurant",
    "sg:classifiers":[
        {
            "category":"Government",
            "subcategory":"Office",
            "type":"Public Place"
        }
    ],
    "sg:phone":"+1 515 957 8076",
    "sg:postcode":"50035",
    "sg:province":"IA",
    "sg:tags":[
        "village"
    ],
    "wof:name":"Bondurant City Office",
    "wof:placetype":"venue"
},
  "geometry": {"coordinates":[-93.46460500000001,41.700496],"type":"Point"}
}