{
  "type": "Feature",
  "properties": {
    "addr:full":"5708 Gateway Dr Grimes IA 50111",
    "addr:housenumber":"5708",
    "addr:postcode":"50111",
    "addr:street":"Gateway Dr",
    "iso:country":"US",
    "sg:address":"5708 Gateway Dr",
    "sg:city":"Grimes",
    "sg:classifiers":[
        {
            "category":"Home & Garden",
            "subcategory":"Garden Supply",
            "type":"Retail Goods"
        }
    ],
    "sg:phone":"+1 515 986 5558",
    "sg:postcode":"50111",
    "sg:province":"IA",
    "sg:tags":[
        "sprinkler"
    ],
    "wof:name":"Rainpro",
    "wof:placetype":"venue"
},
  "geometry": {"coordinates":[-93.777969,41.661087],"type":"Point"}
}