{
  "type": "Feature",
  "properties": {
    "iso:country":"US",
    "sg:address":"9 W Maple St",
    "sg:city":"Ringsted",
    "sg:classifiers":[
        {
            "category":"Building & Trades",
            "subcategory":"Landscaping Services",
            "type":"Services"
        }
    ],
    "sg:phone":"+1 712 866 0251",
    "sg:postcode":"50578",
    "sg:province":"IA",
    "sg:tags":[
        "lawn",
        "maintenance"
    ],
    "wof:name":"Culbertson's Spraying",
    "wof:placetype":"venue"
},
  "geometry": {"coordinates":[-94.51110300000001,43.294612],"type":"Point"}
}