{
  "type": "Feature",
  "properties": {
    "iso:country":"US",
    "sg:address":"3924 79th St",
    "sg:city":"Urbandale",
    "sg:classifiers":[
        {
            "category":"Professional",
            "subcategory":"Computer Services",
            "type":"Services"
        }
    ],
    "sg:phone":"+1 515 278 8441",
    "sg:postcode":"50322",
    "sg:province":"IA",
    "sg:tags":[
        "datum"
    ],
    "wof:name":"Iowa Web",
    "wof:placetype":"venue"
},
  "geometry": {"coordinates":[-93.726865,41.632633],"type":"Point"}
}