{
  "type": "Feature",
  "properties": {
    "iso:country":"US",
    "sg:address":"1710 Exeter Ave",
    "sg:city":"Ionia",
    "sg:phone":"+1 641 394 3613",
    "sg:postcode":"50645",
    "sg:province":"IA",
    "sg:tags":[
        "farm",
        "corn",
        "soybean"
    ],
    "wof:name":"Gary Reis",
    "wof:placetype":"venue"
},
  "geometry": {"coordinates":[-92.45571700000001,43.110889],"type":"Point"}
}