{
  "type": "Feature",
  "properties": {
    "iso:country":"US",
    "sg:address":"35245 340th St",
    "sg:city":"Kingsley",
    "sg:classifiers":[
        {
            "category":"Farming",
            "subcategory":"Livestock Farm",
            "type":"Manufacturing & Wholesale Goods"
        }
    ],
    "sg:phone":"+1 712 944 5119",
    "sg:postcode":"51028",
    "sg:province":"IA",
    "sg:tags":[
        "feedlot",
        "corn",
        "soybean",
        "beef",
        "cattle"
    ],
    "wof:name":"Vos Livestock",
    "wof:placetype":"venue"
},
  "geometry": {"coordinates":[-96.130521,42.561419],"type":"Point"}
}