{
  "type": "Feature",
  "properties": {
    "addr:full":"804 N 2nd St Bellevue IA 52031",
    "addr:housenumber":"804",
    "addr:postcode":"52031",
    "addr:street":"N 2Nd St",
    "iso:country":"US",
    "sg:address":"804 N 2nd St",
    "sg:city":"Bellevue",
    "sg:classifiers":[
        {
            "category":"Wholesale",
            "subcategory":"Hardware",
            "type":"Manufacturing & Wholesale Goods"
        }
    ],
    "sg:phone":"+1 563 872 4740",
    "sg:postcode":"52031",
    "sg:province":"IA",
    "wof:name":"Alpine Living Air Product",
    "wof:placetype":"venue"
},
  "geometry": {"coordinates":[-90.427314,42.265492],"type":"Point"}
}