{
  "type": "Feature",
  "properties": {
    "iso:country":"US",
    "sg:address":"625 Parker St",
    "sg:city":"Stanhope",
    "sg:classifiers":[
        {
            "category":"Health Services",
            "subcategory":"Doctor",
            "type":"Services"
        }
    ],
    "sg:phone":"+1 515 826 3247",
    "sg:postcode":"50246",
    "sg:province":"IA",
    "sg:tags":[
        "dentist"
    ],
    "wof:name":"Jed Norris DDS",
    "wof:placetype":"venue"
},
  "geometry": {"coordinates":[-93.796008,42.29086],"type":"Point"}
}