{
  "type": "Feature",
  "properties": {
    "iso:country":"US",
    "sg:address":"1800 State St",
    "sg:city":"Granger",
    "sg:classifiers":[
        {
            "category":"Shopping",
            "subcategory":"Bicycles & Sporting Goods",
            "type":"Retail Goods"
        }
    ],
    "sg:phone":"+1 515 999 2279",
    "sg:postcode":"50109",
    "sg:province":"IA",
    "wof:name":"Des Moines Disc Golf Club",
    "wof:placetype":"venue"
},
  "geometry": {"coordinates":[-93.82808199999999,41.761064],"type":"Point"}
}