{
  "type": "Feature",
  "properties": {
    "iso:country":"US",
    "sg:address":"3011 N Harrison St",
    "sg:city":"Davenport",
    "sg:classifiers":[
        {
            "category":"Professional",
            "subcategory":"Accounting & Tax Preparation",
            "type":"Services"
        }
    ],
    "sg:phone":"+1 563 322 4372",
    "sg:postcode":"52803",
    "sg:province":"IA",
    "sg:tags":[
        "accountant"
    ],
    "wof:name":"Dorothy L Votroubek PC",
    "wof:placetype":"venue"
},
  "geometry": {"coordinates":[-90.576553,41.551154],"type":"Point"}
}