{
  "type": "Feature",
  "properties": {
    "addr:full":"3120 Manawa Centre Dr Ste 400 Council Bluffs IA 51501",
    "addr:housenumber":"3120",
    "addr:postcode":"51501",
    "addr:street":"Manawa Centre Dr Ste 400",
    "iso:country":"US",
    "sg:address":"3120 Manawa Centre Dr Ste 400",
    "sg:city":"Council Bluffs",
    "sg:classifiers":[
        {
            "category":"Restaurant",
            "type":"Food & Drink"
        }
    ],
    "sg:phone":"+1 712 366 4700",
    "sg:postcode":"51501",
    "sg:province":"IA",
    "sg:tags":[
        "pizza",
        "italian"
    ],
    "sg:website":"www.oldriverpizzacompany.com",
    "wof:name":"Old River Pizza Company",
    "wof:placetype":"venue"
},
  "geometry": {"coordinates":[-95.847701,41.229856],"type":"Point"}
}