{
  "type": "Feature",
  "properties": {
    "iso:country":"US",
    "sg:address":"6406 160th St",
    "sg:city":"Ocheyedan",
    "sg:classifiers":[
        {
            "category":"Farming",
            "subcategory":"Livestock Farm",
            "type":"Manufacturing & Wholesale Goods"
        }
    ],
    "sg:phone":"+1 712 758 3267",
    "sg:postcode":"51354",
    "sg:province":"IA",
    "sg:tags":[
        "beef",
        "feedlot",
        "cattle"
    ],
    "wof:name":"Douglas Block",
    "wof:placetype":"venue"
},
  "geometry": {"coordinates":[-95.52341199999999,43.41573],"type":"Point"}
}