{
  "type": "Feature",
  "properties": {
    "addr:full":"20 N 7th St Estherville IA 51334",
    "addr:housenumber":"20",
    "addr:postcode":"51334",
    "addr:street":"N 7Th St",
    "iso:country":"US",
    "sg:address":"20 N 7th St",
    "sg:city":"Estherville",
    "sg:classifiers":[
        {
            "category":"Professional",
            "subcategory":"Business Services",
            "type":"Services"
        }
    ],
    "sg:phone":"+1 712 362 8759",
    "sg:postcode":"51334",
    "sg:province":"IA",
    "wof:name":"Real Life Solutions",
    "wof:placetype":"venue"
},
  "geometry": {"coordinates":[-94.83532200000001,43.402781],"type":"Point"}
}