{
  "type": "Feature",
  "properties": {
    "iso:country":"US",
    "sg:address":"306 N 9th St",
    "sg:city":"Oskaloosa",
    "sg:classifiers":[
        {
            "category":"Professional",
            "subcategory":"Business Services",
            "type":"Services"
        }
    ],
    "sg:phone":"+1 641 673 4780",
    "sg:postcode":"52577",
    "sg:province":"IA",
    "sg:tags":[
        "embroidery"
    ],
    "wof:name":"Delightful Embroidery",
    "wof:placetype":"venue"
},
  "geometry": {"coordinates":[-92.63436900000001,41.298467],"type":"Point"}
}