{
  "type": "Feature",
  "properties": {
    "addr:full":"118 1st St NW Cedar Rapids IA 52405",
    "addr:housenumber":"118",
    "addr:postcode":"52405",
    "addr:street":"1St St Nw",
    "iso:country":"US",
    "sg:address":"118 1st St NW",
    "sg:city":"Cedar Rapids",
    "sg:classifiers":[
        {
            "category":"Home & Garden",
            "subcategory":"Building Materials",
            "type":"Retail Goods"
        }
    ],
    "sg:phone":"+1 319 364 5036",
    "sg:postcode":"52405",
    "sg:province":"IA",
    "sg:tags":[
        "paint"
    ],
    "wof:name":"Mautz Paint Factory Store",
    "wof:placetype":"venue"
},
  "geometry": {"coordinates":[-91.673748,41.977374],"type":"Point"}
}