{
  "type": "Feature",
  "properties": {
    "iso:country":"US",
    "sg:address":"309 S Gear Ave",
    "sg:city":"West Burlington",
    "sg:classifiers":[
        {
            "category":"Autos & Motor Vehicles",
            "subcategory":"Automobile Sales",
            "type":"Retail Goods"
        }
    ],
    "sg:phone":"+1 319 758 5910",
    "sg:postcode":"52655",
    "sg:province":"IA",
    "sg:tags":[
        "car",
        "dealer"
    ],
    "wof:name":"Shottenkirk Jeep-W Burlington",
    "wof:placetype":"venue"
},
  "geometry": {"coordinates":[-91.16992399999999,40.823356],"type":"Point"}
}