{
  "type": "Feature",
  "properties": {
    "iso:country":"US",
    "sg:address":"2005 E Washington St",
    "sg:city":"Mt Pleasant",
    "sg:classifiers":[
        {
            "category":"Local Transit",
            "type":"Transportation"
        }
    ],
    "sg:phone":"+1 319 385 2103",
    "sg:postcode":"52641",
    "sg:province":"IA",
    "sg:tags":[
        "bus",
        "line"
    ],
    "wof:name":"Trailways Bus System",
    "wof:placetype":"venue"
},
  "geometry": {"coordinates":[-91.522747,40.960479],"type":"Point"}
}