{
  "type": "Feature",
  "properties": {
    "iso:country":"US",
    "sg:address":"1607 S 18th St",
    "sg:city":"Centerville",
    "sg:classifiers":[
        {
            "category":"Organizations",
            "subcategory":"Non-profit Organization",
            "type":"Services"
        }
    ],
    "sg:phone":"+1 641 856 2908",
    "sg:postcode":"52544",
    "sg:province":"IA",
    "sg:tags":[
        "information",
        "alcoholism",
        "treatment"
    ],
    "wof:name":"SIEDA Neighborhood Ctr",
    "wof:placetype":"venue"
},
  "geometry": {"coordinates":[-92.867831,40.719066],"type":"Point"}
}