{
  "type": "Feature",
  "properties": {
    "iso:country":"US",
    "sg:address":"1003 W State St",
    "sg:city":"Marshalltown",
    "sg:classifiers":[
        {
            "category":"Building & Trades",
            "subcategory":"Electrical",
            "type":"Services"
        }
    ],
    "sg:phone":"+1 641 752 2855",
    "sg:postcode":"50158",
    "sg:province":"IA",
    "sg:tags":[
        "electric",
        "contractor"
    ],
    "wof:name":"Flathers & Co Electric",
    "wof:placetype":"venue"
},
  "geometry": {"coordinates":[-92.929056,42.050435],"type":"Point"}
}