{
  "type": "Feature",
  "properties": {
    "iso:country":"US",
    "sg:address":"1921 Hamilton Blvd",
    "sg:city":"Sioux City",
    "sg:classifiers":[
        {
            "category":"Restaurant",
            "type":"Food & Drink"
        },
        {
            "category":"Ice Cream",
            "type":"Food & Drink"
        }
    ],
    "sg:menulink":"http://www.allmenus.com/ia/sioux-city/184724-cold-stone-creamery/menu/",
    "sg:phone":"+1 712 276 1572",
    "sg:postcode":"51104",
    "sg:province":"IA",
    "sg:tags":[
        "smoothy",
        "juice",
        "american",
        "ice",
        "cream"
    ],
    "wof:name":"Cold Stone Creamery",
    "wof:placetype":"venue"
},
  "geometry": {"coordinates":[-96.416849,42.510816],"type":"Point"}
}