{
  "type": "Feature",
  "properties": {
    "addr:full":"2816 Lancelot Ln NW Cedar Rapids IA 52405",
    "addr:housenumber":"2816",
    "addr:postcode":"52405",
    "addr:street":"Lancelot Ln Nw",
    "iso:country":"US",
    "sg:address":"2816 Lancelot Ln NW",
    "sg:city":"Cedar Rapids",
    "sg:classifiers":[
        {
            "category":"Wholesale",
            "subcategory":"Home Furnishings",
            "type":"Manufacturing & Wholesale Goods"
        }
    ],
    "sg:phone":"+1 319 362 7344",
    "sg:postcode":"52405",
    "sg:province":"IA",
    "sg:tags":[
        "closet",
        "accessory"
    ],
    "wof:name":"Space Options",
    "wof:placetype":"venue"
},
  "geometry": {"coordinates":[-91.70840099999999,41.981443],"type":"Point"}
}