{
  "type": "Feature",
  "properties": {
    "iso:country":"US",
    "sg:address":"1212 Washington St",
    "sg:city":"Muscatine",
    "sg:classifiers":[
        {
            "category":"Retail",
            "subcategory":"Repair Shop",
            "type":"Services"
        }
    ],
    "sg:phone":"+1 563 263 9957",
    "sg:postcode":"52761",
    "sg:province":"IA",
    "sg:tags":[
        "plumbing",
        "drain",
        "cleaning",
        "sewer"
    ],
    "wof:name":"Drain King",
    "wof:placetype":"venue"
},
  "geometry": {"coordinates":[-91.036704,41.434288],"type":"Point"}
}