{
  "type": "Feature",
  "properties": {
    "iso:country":"US",
    "sg:address":"6224 Ave O",
    "sg:city":"Fort Madison",
    "sg:classifiers":[
        {
            "category":"Retail",
            "subcategory":"Repair Shop",
            "type":"Services"
        }
    ],
    "sg:phone":"+1 319 372 7232",
    "sg:postcode":"52627",
    "sg:province":"IA",
    "sg:tags":[
        "welding"
    ],
    "sg:website":"www.huffmanwelding.com",
    "wof:name":"Huffman Welding & Machine Inc",
    "wof:placetype":"venue"
},
  "geometry": {"coordinates":[-91.382711,40.624182],"type":"Point"}
}