{
  "type": "Feature",
  "properties": {
    "addr:full":"1124 Germanville Rd Brighton IA 52540",
    "addr:housenumber":"1124",
    "addr:postcode":"52540",
    "addr:street":"Germanville Rd",
    "iso:country":"US",
    "sg:address":"1124 Germanville Rd",
    "sg:city":"Brighton",
    "sg:classifiers":[
        {
            "category":"Real Estate",
            "subcategory":"Real Estate Operator",
            "type":"Services"
        }
    ],
    "sg:phone":"+1 319 694 3892",
    "sg:postcode":"52540",
    "sg:province":"IA",
    "sg:tags":[
        "property",
        "lessor"
    ],
    "wof:name":"Gary Fritz",
    "wof:placetype":"venue"
},
  "geometry": {"coordinates":[-91.802081,41.14261],"type":"Point"}
}