{
  "type": "Feature",
  "properties": {
    "iso:country":"US",
    "sg:address":"303 E South St",
    "sg:city":"Marengo",
    "sg:classifiers":[
        {
            "category":"Building & Trades",
            "subcategory":"Construction",
            "type":"Services"
        }
    ],
    "sg:phone":"+1 319 642 2004",
    "sg:postcode":"52301",
    "sg:province":"IA",
    "sg:tags":[
        "house"
    ],
    "wof:name":"Dains Construction",
    "wof:placetype":"venue"
},
  "geometry": {"coordinates":[-92.066079,41.796957],"type":"Point"}
}