{
  "type": "Feature",
  "properties": {
    "iso:country":"US",
    "sg:address":"109 N Downey St",
    "sg:city":"West Branch",
    "sg:classifiers":[
        {
            "category":"Personal",
            "subcategory":"Beauty Salon",
            "type":"Services"
        }
    ],
    "sg:phone":"+1 319 643 5648",
    "sg:postcode":"52358",
    "sg:province":"IA",
    "wof:name":"County Line Salon",
    "wof:placetype":"venue"
},
  "geometry": {"coordinates":[-91.346541,41.672431],"type":"Point"}
}