{
  "type": "Feature",
  "properties": {
    "iso:country":"US",
    "sg:address":"225 S 6th Ave",
    "sg:city":"De Witt",
    "sg:classifiers":[
        {
            "category":"Manufacturing",
            "subcategory":"Tools & Machinery",
            "type":"Manufacturing & Wholesale Goods"
        }
    ],
    "sg:phone":"+1 563 659 5051",
    "sg:postcode":"52742",
    "sg:province":"IA",
    "sg:tags":[
        "machine",
        "shop"
    ],
    "wof:name":"FDC Inc",
    "wof:placetype":"venue"
},
  "geometry": {"coordinates":[-90.539008,41.814137],"type":"Point"}
}