{
  "type": "Feature",
  "properties": {
    "addr:full":"3312 71st Cir Urbandale IA 50322",
    "addr:housenumber":"3312",
    "addr:postcode":"50322",
    "addr:street":"71St Cir",
    "iso:country":"US",
    "sg:address":"3312 71st Cir",
    "sg:city":"Urbandale",
    "sg:classifiers":[
        {
            "category":"Real Estate",
            "subcategory":"Real Estate Operator",
            "type":"Services"
        }
    ],
    "sg:phone":"+1 515 278 0045",
    "sg:postcode":"50322",
    "sg:province":"IA",
    "sg:tags":[
        "residential",
        "agent"
    ],
    "wof:name":"Wise Realty",
    "wof:placetype":"venue"
},
  "geometry": {"coordinates":[-93.716459,41.624739],"type":"Point"}
}