{
  "type": "Feature",
  "properties": {
    "addr:full":"514 Lombard St Clarence IA 52216",
    "addr:housenumber":"514",
    "addr:postcode":"52216",
    "addr:street":"Lombard St",
    "iso:country":"US",
    "sg:address":"514 Lombard St",
    "sg:city":"Clarence",
    "sg:classifiers":[
        {
            "category":"Personal",
            "subcategory":"Beauty Salon",
            "type":"Services"
        }
    ],
    "sg:phone":"+1 563 452 3904",
    "sg:postcode":"52216",
    "sg:province":"IA",
    "wof:name":"Fashion Flair Beauty Salon",
    "wof:placetype":"venue"
},
  "geometry": {"coordinates":[-91.055538,41.888671],"type":"Point"}
}