{
  "type": "Feature",
  "properties": {
    "addr:full":"1027 6th St SW Hampton IA 50441",
    "addr:housenumber":"1027",
    "addr:postcode":"50441",
    "addr:street":"6Th St Sw",
    "iso:country":"US",
    "sg:address":"1027 6th St SW",
    "sg:city":"Hampton",
    "sg:classifiers":[
        {
            "category":"Retail",
            "subcategory":"Repair Shop",
            "type":"Services"
        }
    ],
    "sg:phone":"+1 641 456 3671",
    "sg:postcode":"50441",
    "sg:province":"IA",
    "sg:tags":[
        "farm",
        "equipment",
        "parts"
    ],
    "wof:name":"Miller's Tractor Svc",
    "wof:placetype":"venue"
},
  "geometry": {"coordinates":[-93.214732,42.732243],"type":"Point"}
}