{
  "type": "Feature",
  "properties": {
    "iso:country":"US",
    "sg:address":"625 Warren St",
    "sg:city":"Duncombe",
    "sg:classifiers":[
        {
            "category":"Organizations",
            "subcategory":"Religious Organization",
            "type":"Services"
        }
    ],
    "sg:phone":"+1 515 543 8145",
    "sg:postcode":"50532",
    "sg:province":"IA",
    "wof:name":"United Methodist Church",
    "wof:placetype":"venue"
},
  "geometry": {"coordinates":[-93.994282,42.469094],"type":"Point"}
}