{
  "type": "Feature",
  "properties": {
    "iso:country":"US",
    "sg:address":"101 Market St",
    "sg:city":"Audubon",
    "sg:classifiers":[
        {
            "category":"Manufacturing",
            "subcategory":"Motor Vehicles & Parts",
            "type":"Manufacturing & Wholesale Goods"
        }
    ],
    "sg:phone":"+1 712 563 0808",
    "sg:postcode":"50025",
    "sg:province":"IA",
    "sg:tags":[
        "trailer"
    ],
    "wof:name":"Country Side Industries",
    "wof:placetype":"venue"
},
  "geometry": {"coordinates":[-94.936955,41.724159],"type":"Point"}
}