{
  "type": "Feature",
  "properties": {
    "iso:country":"US",
    "sg:address":"811 S Mill St",
    "sg:city":"Decorah",
    "sg:classifiers":[
        {
            "category":"Farming",
            "subcategory":"Farm",
            "type":"Manufacturing & Wholesale Goods"
        }
    ],
    "sg:phone":"+1 563 382 2871",
    "sg:postcode":"52101",
    "sg:province":"IA",
    "sg:tags":[
        "crop",
        "general"
    ],
    "wof:name":"Lowell Vsetecka",
    "wof:placetype":"venue"
},
  "geometry": {"coordinates":[-91.792233,43.296722],"type":"Point"}
}