{
  "type": "Feature",
  "properties": {
    "iso:country":"US",
    "sg:address":"660 9th St",
    "sg:city":"Marion",
    "sg:classifiers":[
        {
            "category":"Retail",
            "subcategory":"Repair Shop",
            "type":"Services"
        }
    ],
    "sg:phone":"+1 319 377 8352",
    "sg:postcode":"52302",
    "sg:province":"IA",
    "sg:tags":[
        "taxidermist"
    ],
    "wof:name":"All Seasons Wildlife Art",
    "wof:placetype":"venue"
},
  "geometry": {"coordinates":[-91.60057999999999,42.032781],"type":"Point"}
}