{
  "type": "Feature",
  "properties": {
    "addr:full":"48161 280th St Canton IA 57013",
    "addr:housenumber":"48161",
    "addr:postcode":"57013",
    "addr:street":"280Th St",
    "iso:country":"US",
    "sg:address":"48161 280th St",
    "sg:city":"Canton",
    "sg:phone":"+1 605 987 5175",
    "sg:postcode":"57013",
    "sg:province":"IA",
    "sg:tags":[
        "farm",
        "corn",
        "soybean"
    ],
    "wof:name":"Charles Kuehl",
    "wof:placetype":"venue"
},
  "geometry": {"coordinates":[-96.57705799999999,43.329918],"type":"Point"}
}