{
  "type": "Feature",
  "properties": {
    "iso:country":"US",
    "sg:address":"4347 1st Ave SE Apt 126",
    "sg:city":"Cedar Rapids",
    "sg:classifiers":[
        {
            "category":"Real Estate",
            "subcategory":"Real Estate Operator",
            "type":"Services"
        }
    ],
    "sg:phone":"+1 319 366 6624",
    "sg:postcode":"52402",
    "sg:province":"IA",
    "sg:tags":[
        "apartment"
    ],
    "wof:name":"Glenbrook Centre Apartments the",
    "wof:placetype":"venue"
},
  "geometry": {"coordinates":[-91.629997,42.027802],"type":"Point"}
}