{
  "type": "Feature",
  "properties": {
    "iso:country":"US",
    "sg:address":"4000 University Ave",
    "sg:city":"Waterloo",
    "sg:classifiers":[
        {
            "category":"Banks & Credit Unions",
            "subcategory":"Bank",
            "type":"Services"
        }
    ],
    "sg:phone":"+1 319 234 1007",
    "sg:postcode":"50701",
    "sg:province":"IA",
    "sg:tags":[
        "state"
    ],
    "wof:name":"Deere John Community Credit Un",
    "wof:placetype":"venue"
},
  "geometry": {"coordinates":[-92.406229,42.505652],"type":"Point"}
}