{
  "type": "Feature",
  "properties": {
    "iso:country":"US",
    "sg:address":"110 N Ankeny Blvd",
    "sg:city":"Ankeny",
    "sg:classifiers":[
        {
            "category":"Recreation",
            "type":"Entertainment"
        }
    ],
    "sg:phone":"+1 515 963 1700",
    "sg:postcode":"50023",
    "sg:province":"IA",
    "sg:tags":[
        "martial",
        "arts",
        "instruction"
    ],
    "wof:name":"Rients Black Belt Academy",
    "wof:placetype":"venue"
},
  "geometry": {"coordinates":[-93.600346,41.735417],"type":"Point"}
}