{
  "type": "Feature",
  "properties": {
    "iso:country":"US",
    "sg:address":"304 W Broadway St",
    "sg:city":"Eagle Grove",
    "sg:classifiers":[
        {
            "category":"Real Estate",
            "subcategory":"Real Estate Agent",
            "type":"Services"
        }
    ],
    "sg:phone":"+1 515 448 3232",
    "sg:postcode":"50533",
    "sg:province":"IA",
    "wof:name":"C J Coopers Real Estate",
    "wof:placetype":"venue"
},
  "geometry": {"coordinates":[-93.90589,42.664035],"type":"Point"}
}