{
  "type": "Feature",
  "properties": {
    "iso:country":"US",
    "sg:address":"408 Edgewood Rd NW",
    "sg:city":"Cedar Rapids",
    "sg:classifiers":[
        {
            "category":"Building & Trades",
            "subcategory":"Electrical",
            "type":"Services"
        }
    ],
    "sg:phone":"+1 319 396 1308",
    "sg:postcode":"52405",
    "sg:province":"IA",
    "sg:tags":[
        "electric",
        "contractor"
    ],
    "wof:name":"MMC Industrial Prod Us Elect",
    "wof:placetype":"venue"
},
  "geometry": {"coordinates":[-91.716052,41.977312],"type":"Point"}
}