{
  "type": "Feature",
  "properties": {
    "iso:country":"US",
    "sg:address":"116 S 2nd St",
    "sg:city":"Maquoketa",
    "sg:classifiers":[
        {
            "category":"Professional",
            "subcategory":"Lawyer & Legal Services",
            "type":"Services"
        }
    ],
    "sg:phone":"+1 563 652 6831",
    "sg:postcode":"52060",
    "sg:province":"IA",
    "sg:tags":[
        "attorney"
    ],
    "wof:name":"Wright Law Office",
    "wof:placetype":"venue"
},
  "geometry": {"coordinates":[-90.666951,42.068988],"type":"Point"}
}