{
  "type": "Feature",
  "properties": {
    "addr:full":"502 N Jackson St Charles City IA 50616",
    "addr:housenumber":"502",
    "addr:postcode":"50616",
    "addr:street":"N Jackson St",
    "iso:country":"US",
    "sg:address":"502 N Jackson St",
    "sg:city":"Charles City",
    "sg:classifiers":[
        {
            "category":"Organizations",
            "subcategory":"Religious Organization",
            "type":"Services"
        }
    ],
    "sg:phone":"+1 641 228 5310",
    "sg:postcode":"50616",
    "sg:province":"IA",
    "wof:name":"Congregational Church",
    "wof:placetype":"venue"
},
  "geometry": {"coordinates":[-92.677035,43.070855],"type":"Point"}
}