{
  "type": "Feature",
  "properties": {
    "iso:country":"US",
    "sg:address":"460 Wales St",
    "sg:city":"Iowa City",
    "sg:classifiers":[
        {
            "category":"Building & Trades",
            "subcategory":"Construction",
            "type":"Services"
        }
    ],
    "sg:phone":"+1 319 358 7387",
    "sg:postcode":"52245",
    "sg:province":"IA",
    "sg:tags":[
        "house"
    ],
    "wof:name":"Top Shelf Construction",
    "wof:placetype":"venue"
},
  "geometry": {"coordinates":[-91.51105099999999,41.656127],"type":"Point"}
}