{
  "type": "Feature",
  "properties": {
    "iso:country":"US",
    "sg:address":"528 Main St",
    "sg:city":"Osage",
    "sg:classifiers":[
        {
            "category":"Real Estate",
            "subcategory":"Real Estate Agent",
            "type":"Services"
        }
    ],
    "sg:phone":"+1 641 732 5803",
    "sg:postcode":"50461",
    "sg:province":"IA",
    "wof:name":"Joe Spartz Real Estate",
    "wof:placetype":"venue"
},
  "geometry": {"coordinates":[-92.81416400000001,43.284004],"type":"Point"}
}