{
  "type": "Feature",
  "properties": {
    "addr:full":"248 3rd St NW Sioux Center IA 51250",
    "addr:housenumber":"248",
    "addr:postcode":"51250",
    "addr:street":"3Rd St Nw",
    "iso:country":"US",
    "sg:address":"248 3rd St NW",
    "sg:city":"Sioux Center",
    "sg:classifiers":[
        {
            "category":"Parking",
            "type":"Transportation"
        }
    ],
    "sg:phone":"+1 712 722 1923",
    "sg:postcode":"51250",
    "sg:province":"IA",
    "sg:tags":[
        "garage"
    ],
    "wof:name":"Ambulance Garage",
    "wof:placetype":"venue"
},
  "geometry": {"coordinates":[-96.178579,43.079785],"type":"Point"}
}