{
  "type": "Feature",
  "properties": {
    "iso:country":"US",
    "sg:address":"29877 323rd Ave",
    "sg:city":"Richland",
    "sg:classifiers":[
        {
            "category":"Farming",
            "subcategory":"Livestock Farm",
            "type":"Manufacturing & Wholesale Goods"
        }
    ],
    "sg:phone":"+1 319 456 3729",
    "sg:postcode":"52585",
    "sg:province":"IA",
    "sg:tags":[
        "beef",
        "corn",
        "crop",
        "field",
        "so",
        "cattle",
        "feedlot"
    ],
    "wof:name":"Richard Bond",
    "wof:placetype":"venue"
},
  "geometry": {"coordinates":[-91.978334,41.222081],"type":"Point"}
}