{
  "type": "Feature",
  "properties": {
    "iso:country":"US",
    "sg:address":"43992 235th Ave",
    "sg:city":"Lake Mills",
    "sg:classifiers":[
        {
            "category":"Government",
            "subcategory":"Office",
            "type":"Public Place"
        }
    ],
    "sg:phone":"+1 641 592 9632",
    "sg:postcode":"50450",
    "sg:province":"IA",
    "wof:name":"Game Management Unit",
    "wof:placetype":"venue"
},
  "geometry": {"coordinates":[-93.50547,43.379729],"type":"Point"}
}