{
  "type": "Feature",
  "properties": {
    "addr:full":"2000 University Ave Dubuque IA 52001",
    "addr:housenumber":"2000",
    "addr:postcode":"52001",
    "addr:street":"University Ave",
    "iso:country":"US",
    "sg:address":"2000 University Ave",
    "sg:city":"Dubuque",
    "sg:classifiers":[
        {
            "category":"Shopping",
            "subcategory":"Books",
            "type":"Retail Goods"
        }
    ],
    "sg:phone":"+1 563 589 3131",
    "sg:postcode":"52001",
    "sg:province":"IA",
    "sg:tags":[
        "dealer"
    ],
    "sg:website":"www.dbq.bkstr.com",
    "wof:name":"Babka Book Store",
    "wof:placetype":"venue"
},
  "geometry": {"coordinates":[-90.693197,42.499055],"type":"Point"}
}