{
  "type": "Feature",
  "properties": {
    "addr:full":"108 Emmons St Hiawatha IA 52233",
    "addr:housenumber":"108",
    "addr:postcode":"52233",
    "addr:street":"Emmons St",
    "iso:country":"US",
    "sg:address":"108 Emmons St",
    "sg:city":"Hiawatha",
    "sg:classifiers":[
        {
            "category":"Social Services",
            "subcategory":"Child Care",
            "type":"Services"
        }
    ],
    "sg:phone":"+1 319 378 3100",
    "sg:postcode":"52233",
    "sg:province":"IA",
    "sg:tags":[
        "kindergarten",
        "academic",
        "school"
    ],
    "wof:name":"Essential Montessori",
    "wof:placetype":"venue"
},
  "geometry": {"coordinates":[-91.676163,42.03882],"type":"Point"}
}