{
  "type": "Feature",
  "properties": {
    "iso:country":"US",
    "sg:address":"205 S 7th Ave W",
    "sg:city":"Lake Mills",
    "sg:classifiers":[
        {
            "category":"Organizations",
            "subcategory":"Religious Organization",
            "type":"Services"
        }
    ],
    "sg:phone":"+1 641 592 8892",
    "sg:postcode":"50450",
    "sg:province":"IA",
    "sg:tags":[
        "church"
    ],
    "wof:name":"North Prairie Lutheran Chr",
    "wof:placetype":"venue"
},
  "geometry": {"coordinates":[-93.535572,43.412766],"type":"Point"}
}