{
  "type": "Feature",
  "properties": {
    "addr:full":"1107 S Clark St Pella IA 50219",
    "addr:housenumber":"1107",
    "addr:postcode":"50219",
    "addr:street":"S Clark St",
    "iso:country":"US",
    "sg:address":"1107 S Clark St",
    "sg:city":"Pella",
    "sg:classifiers":[
        {
            "category":"Freight",
            "type":"Transportation"
        }
    ],
    "sg:phone":"+1 641 628 2693",
    "sg:postcode":"50219",
    "sg:province":"IA",
    "sg:tags":[
        "operator",
        "local",
        "trucking"
    ],
    "wof:name":"Leeman Trucking Inc",
    "wof:placetype":"venue"
},
  "geometry": {"coordinates":[-92.91448,41.382004],"type":"Point"}
}