{
  "type": "Feature",
  "properties": {
    "iso:country":"US",
    "sg:address":"7039 Caves Rd",
    "sg:city":"Maquoketa",
    "sg:classifiers":[
        {
            "category":"Retail",
            "subcategory":"Auto Repair",
            "type":"Services"
        }
    ],
    "sg:phone":"+1 563 652 2613",
    "sg:postcode":"52060",
    "sg:province":"IA",
    "sg:tags":[
        "automotive"
    ],
    "wof:name":"James E Bickford",
    "wof:placetype":"venue"
},
  "geometry": {"coordinates":[-90.729502,42.094781],"type":"Point"}
}