{
  "type": "Feature",
  "properties": {
    "addr:full":"421 S Illinois Ave Mason City IA 50401",
    "addr:housenumber":"421",
    "addr:postcode":"50401",
    "addr:street":"S Illinois Ave",
    "iso:country":"US",
    "sg:address":"421 S Illinois Ave",
    "sg:city":"Mason City",
    "sg:classifiers":[
        {
            "category":"Restaurant",
            "type":"Food & Drink"
        },
        {
            "category":"Ice Cream",
            "type":"Food & Drink"
        }
    ],
    "sg:menulink":"http://www.allmenus.com/ia/mason-city/172737-dairy-queen/menu/",
    "sg:phone":"+1 641 380 0234",
    "sg:postcode":"50401",
    "sg:province":"IA",
    "sg:tags":[
        "burger",
        "american",
        "ice",
        "cream"
    ],
    "wof:name":"Dairy Queen",
    "wof:placetype":"venue"
},
  "geometry": {"coordinates":[-93.170937,43.14781],"type":"Point"}
}