{
  "type": "Feature",
  "properties": {
    "addr:full":"419 W 6th St Sioux City IA 51103",
    "addr:housenumber":"419",
    "addr:postcode":"51103",
    "addr:street":"W 6Th St",
    "iso:country":"US",
    "sg:address":"419 W 6th St",
    "sg:city":"Sioux City",
    "sg:classifiers":[
        {
            "category":"Professional",
            "subcategory":"Engineering",
            "type":"Services"
        }
    ],
    "sg:phone":"+1 712 252 5132",
    "sg:postcode":"51103",
    "sg:province":"IA",
    "sg:tags":[
        "engineer"
    ],
    "wof:name":"Certified Testing Svc Inc",
    "wof:placetype":"venue"
},
  "geometry": {"coordinates":[-96.413836,42.499754],"type":"Point"}
}