{
  "type": "Feature",
  "properties": {
    "addr:full":"123 E 1st St Monticello IA 52310",
    "addr:housenumber":"123",
    "addr:postcode":"52310",
    "addr:street":"E 1St St",
    "iso:country":"US",
    "sg:address":"123 E 1st St",
    "sg:city":"Monticello",
    "sg:classifiers":[
        {
            "category":"Professional",
            "subcategory":"Lawyer & Legal Services",
            "type":"Services"
        }
    ],
    "sg:phone":"+1 319 465 3531",
    "sg:postcode":"52310",
    "sg:province":"IA",
    "sg:tags":[
        "attorney"
    ],
    "wof:name":"Strittmatter Law Firm",
    "wof:placetype":"venue"
},
  "geometry": {"coordinates":[-91.189268,42.238209],"type":"Point"}
}