{
  "type": "Feature",
  "properties": {
    "iso:country":"US",
    "sg:address":"1725 N Roosevelt Ave",
    "sg:city":"Burlington",
    "sg:classifiers":[
        {
            "category":"Restaurant",
            "type":"Food & Drink"
        }
    ],
    "sg:menulink":"http://www.allmenus.com/ia/burlington/202638-mcdonalds/menu/",
    "sg:postcode":"52601",
    "sg:province":"IA",
    "sg:tags":[
        "burger",
        "american"
    ],
    "wof:name":"McDonald's",
    "wof:placetype":"venue"
},
  "geometry": {"coordinates":[-91.141524,40.826866],"type":"Point"}
}