{
  "type": "Feature",
  "properties": {
    "addr:full":"2419 Fern Ave Cedar Falls IA 50613",
    "addr:housenumber":"2419",
    "addr:postcode":"50613",
    "addr:street":"Fern Ave",
    "iso:country":"US",
    "sg:address":"2419 Fern Ave",
    "sg:city":"Cedar Falls",
    "sg:classifiers":[
        {
            "category":"Education",
            "subcategory":"School",
            "type":"Public Place"
        }
    ],
    "sg:phone":"+1 319 266 2614",
    "sg:postcode":"50613",
    "sg:province":"IA",
    "wof:name":"North Cedar Elementary School",
    "wof:placetype":"venue"
},
  "geometry": {"coordinates":[-92.45407,42.558592],"type":"Point"}
}