{
  "type": "Feature",
  "properties": {
    "iso:country":"US",
    "sg:address":"417 3rd St SE",
    "sg:city":"Cedar Rapids",
    "sg:classifiers":[
        {
            "category":"Recreation",
            "type":"Entertainment"
        }
    ],
    "sg:phone":"+1 319 362 6330",
    "sg:postcode":"52401",
    "sg:province":"IA",
    "sg:tags":[
        "martial art"
    ],
    "sg:website":"www.cedar-river-aikikai.org",
    "wof:name":"Cedar River Aikikai",
    "wof:placetype":"venue"
},
  "geometry": {"coordinates":[-91.664497,41.976501],"type":"Point"}
}