{
  "type": "Feature",
  "properties": {
    "addr:full":"11201 Douglas Ave Urbandale IA 50322",
    "addr:housenumber":"11201",
    "addr:postcode":"50322",
    "addr:street":"Douglas Ave",
    "iso:country":"US",
    "sg:address":"11201 Douglas Ave",
    "sg:city":"Urbandale",
    "sg:classifiers":[
        {
            "category":"Insurance",
            "subcategory":"Hazard Insurance",
            "type":"Services"
        }
    ],
    "sg:phone":"+1 515 278 3000",
    "sg:postcode":"50322",
    "sg:province":"IA",
    "sg:tags":[
        "fidelity",
        "bond"
    ],
    "sg:website":"www.cwgins.com",
    "wof:name":"Continental Western Group",
    "wof:placetype":"venue"
},
  "geometry": {"coordinates":[-93.771621,41.629614],"type":"Point"}
}