{
  "type": "Feature",
  "properties": {
    "iso:country":"US",
    "sg:address":"712 Sylvan Ave",
    "sg:city":"Davenport",
    "sg:classifiers":[
        {
            "category":"Personal",
            "subcategory":"Barber",
            "type":"Services"
        }
    ],
    "sg:phone":"+1 563 324 9810",
    "sg:postcode":"52803",
    "sg:province":"IA",
    "sg:tags":[
        "shop"
    ],
    "wof:name":"Chesney's",
    "wof:placetype":"venue"
},
  "geometry": {"coordinates":[-90.562765,41.527679],"type":"Point"}
}