{
  "type": "Feature",
  "properties": {
    "addr:full":"3325 Center Point Rd NE Cedar Rapids IA 52402",
    "addr:housenumber":"3325",
    "addr:postcode":"52402",
    "addr:street":"Center Point Rd Ne",
    "iso:country":"US",
    "sg:address":"3325 Center Point Rd NE",
    "sg:city":"Cedar Rapids",
    "sg:classifiers":[
        {
            "category":"Bars & Pubs",
            "type":"Food & Drink"
        },
        {
            "category":"Restaurant",
            "type":"Food & Drink"
        }
    ],
    "sg:phone":"+1 319 261 3131",
    "sg:postcode":"52402",
    "sg:province":"IA",
    "sg:tags":[
        "british"
    ],
    "sg:website":"www.thelondonercr.com",
    "wof:name":"The Londoner",
    "wof:placetype":"venue"
},
  "geometry": {"coordinates":[-91.664045,42.012165],"type":"Point"}
}