{
  "type": "Feature",
  "properties": {
    "iso:country":"US",
    "sg:address":"18072 State Hwy 64",
    "sg:city":"Maquoketa",
    "sg:classifiers":[
        {
            "category":"Banks & Credit Unions",
            "subcategory":"Bank",
            "type":"Services"
        }
    ],
    "sg:phone":"+1 563 652 4400",
    "sg:postcode":"52060",
    "sg:province":"IA",
    "wof:name":"Dutrac Community Credit Union",
    "wof:placetype":"venue"
},
  "geometry": {"coordinates":[-90.68908999999999,42.066467],"type":"Point"}
}