{
  "type": "Feature",
  "properties": {
    "iso:country":"US",
    "sg:address":"206 Main St S",
    "sg:city":"Hazleton",
    "sg:classifiers":[
        {
            "category":"Home & Garden",
            "subcategory":"Furniture",
            "type":"Retail Goods"
        }
    ],
    "sg:phone":"+1 319 636 9152",
    "sg:postcode":"50641",
    "sg:province":"IA",
    "wof:name":"Comfort Zone",
    "wof:placetype":"venue"
},
  "geometry": {"coordinates":[-91.90559399999999,42.615509],"type":"Point"}
}