{
  "type": "Feature",
  "properties": {
    "iso:country":"US",
    "sg:address":"6028 Kimball Ave",
    "sg:city":"Waterloo",
    "sg:classifiers":[
        {
            "category":"Education",
            "subcategory":"School",
            "type":"Public Place"
        }
    ],
    "sg:phone":"+1 319 433 2880",
    "sg:postcode":"50701",
    "sg:province":"IA",
    "wof:name":"Orange Elementary School",
    "wof:placetype":"venue"
},
  "geometry": {"coordinates":[-92.356988,42.42766],"type":"Point"}
}