{
  "type": "Feature",
  "properties": {
    "iso:country":"US",
    "sg:address":"408 Orchard Dr",
    "sg:city":"Marshalltown",
    "sg:classifiers":[
        {
            "category":"Real Estate",
            "subcategory":"Real Estate Operator",
            "type":"Services"
        }
    ],
    "sg:phone":"+1 641 752 0584",
    "sg:postcode":"50158",
    "sg:province":"IA",
    "sg:tags":[
        "building",
        "apartment"
    ],
    "wof:name":"Wardon Inc",
    "wof:placetype":"venue"
},
  "geometry": {"coordinates":[-92.94185400000001,42.0432],"type":"Point"}
}