{
  "type": "Feature",
  "properties": {
    "addr:full":"2211 148th St Albion IA 50005",
    "addr:housenumber":"2211",
    "addr:postcode":"50005",
    "addr:street":"148Th St",
    "iso:country":"US",
    "sg:address":"2211 148th St",
    "sg:city":"Albion",
    "sg:phone":"+1 641 488 2260",
    "sg:postcode":"50005",
    "sg:province":"IA",
    "sg:tags":[
        "real",
        "lessor",
        "farm",
        "corn",
        "soybean",
        "property"
    ],
    "wof:name":"Van Mc Kibben Van",
    "wof:placetype":"venue"
},
  "geometry": {"coordinates":[-92.99921000000001,42.137135],"type":"Point"}
}