{
  "type": "Feature",
  "properties": {
    "addr:full":"807 N 4th St Central City IA 52214",
    "addr:housenumber":"807",
    "addr:postcode":"52214",
    "addr:street":"N 4Th St",
    "iso:country":"US",
    "sg:address":"807 N 4th St",
    "sg:city":"Central City",
    "sg:classifiers":[
        {
            "category":"Shopping",
            "subcategory":"Hobbies, Toys, & Games",
            "type":"Retail Goods"
        }
    ],
    "sg:phone":"+1 319 438 6653",
    "sg:postcode":"52214",
    "sg:province":"IA",
    "wof:name":"Janets Crafts",
    "wof:placetype":"venue"
},
  "geometry": {"coordinates":[-91.52387899999999,42.215337],"type":"Point"}
}