{
  "type": "Feature",
  "properties": {
    "addr:full":"1001 E Main St Ottumwa IA 52501",
    "addr:housenumber":"1001",
    "addr:postcode":"52501",
    "addr:street":"E Main St",
    "iso:country":"US",
    "sg:address":"1001 E Main St",
    "sg:city":"Ottumwa",
    "sg:classifiers":[
        {
            "category":"Restaurant",
            "type":"Food & Drink"
        },
        {
            "category":"Food & Beverages",
            "subcategory":"Groceries & Convenience Stores",
            "type":"Retail Goods"
        }
    ],
    "sg:menulink":"http://www.allmenus.com/ia/center/226044-caseys-general-store/menu/",
    "sg:phone":"+1 641 682 0930",
    "sg:postcode":"52501",
    "sg:province":"IA",
    "sg:tags":[
        "american",
        "pizza"
    ],
    "wof:name":"Casey's General Store",
    "wof:placetype":"venue"
},
  "geometry": {"coordinates":[-92.40168300000001,41.010678],"type":"Point"}
}