{
  "type": "Feature",
  "properties": {
    "iso:country":"US",
    "sg:address":"19 S 21st St",
    "sg:city":"Fort Dodge",
    "sg:classifiers":[
        {
            "category":"Wholesale",
            "subcategory":"Machinery & Supplies",
            "type":"Manufacturing & Wholesale Goods"
        }
    ],
    "sg:phone":"+1 515 955 2344",
    "sg:postcode":"50501",
    "sg:province":"IA",
    "sg:tags":[
        "janitor"
    ],
    "wof:name":"Central Iowa Distributing Inc",
    "wof:placetype":"venue"
},
  "geometry": {"coordinates":[-94.169382,42.506061],"type":"Point"}
}