{
  "type": "Feature",
  "properties": {
    "iso:country":"US",
    "sg:address":"906 Sunset Dr",
    "sg:city":"Fairfield",
    "sg:classifiers":[
        {
            "category":"Shopping",
            "subcategory":"Clothing, Apparel, & Fashions",
            "type":"Retail Goods"
        }
    ],
    "sg:phone":"+1 641 472 8281",
    "sg:postcode":"52556",
    "sg:province":"IA",
    "sg:tags":[
        "item",
        "boutique"
    ],
    "wof:name":"Celestial Silks",
    "wof:placetype":"venue"
},
  "geometry": {"coordinates":[-91.97442700000001,40.995336],"type":"Point"}
}