{
  "type": "Feature",
  "properties": {
    "iso:country":"US",
    "sg:address":"1607 Summit-View Dr",
    "sg:city":"Creston",
    "sg:phone":"+1 641 782 4717",
    "sg:postcode":"50801",
    "sg:province":"IA",
    "sg:tags":[
        "farm"
    ],
    "wof:name":"Christophers Garden",
    "wof:placetype":"venue"
},
  "geometry": {"coordinates":[-94.389253,41.070102],"type":"Point"}
}