{
  "type": "Feature",
  "properties": {
    "iso:country":"US",
    "sg:address":"211 N Maple St",
    "sg:city":"Monticello",
    "sg:classifiers":[
        {
            "category":"Farming",
            "subcategory":"Farm",
            "type":"Manufacturing & Wholesale Goods"
        }
    ],
    "sg:phone":"+1 319 465 3051",
    "sg:postcode":"52310",
    "sg:province":"IA",
    "sg:tags":[
        "crop",
        "general"
    ],
    "wof:name":"Manternach Farm Inc",
    "wof:placetype":"venue"
},
  "geometry": {"coordinates":[-91.18789599999999,42.240627],"type":"Point"}
}