{
  "type": "Feature",
  "properties": {
    "iso:country":"US",
    "sg:address":"2320 Iowa Ave",
    "sg:city":"Independence",
    "sg:classifiers":[
        {
            "category":"Health Services",
            "subcategory":"Health Practitioner",
            "type":"Services"
        }
    ],
    "sg:phone":"+1 319 334 5155",
    "sg:postcode":"50644",
    "sg:province":"IA",
    "sg:tags":[
        "therapist",
        "physical"
    ],
    "wof:name":"Millennium Therapy",
    "wof:placetype":"venue"
},
  "geometry": {"coordinates":[-91.91952499999999,42.456199],"type":"Point"}
}