{
  "type": "Feature",
  "properties": {
    "iso:country":"US",
    "sg:address":"1541 Newby Ave",
    "sg:city":"Albion",
    "sg:classifiers":[
        {
            "category":"Real Estate",
            "subcategory":"Real Estate Operator",
            "type":"Services"
        }
    ],
    "sg:phone":"+1 641 488 2490",
    "sg:postcode":"50005",
    "sg:province":"IA",
    "sg:tags":[
        "property",
        "lessor"
    ],
    "wof:name":"W Wayne Wiley",
    "wof:placetype":"venue"
},
  "geometry": {"coordinates":[-92.98188399999999,42.129985],"type":"Point"}
}