{
  "type": "Feature",
  "properties": {
    "addr:full":"3395 275th St Parnell IA 52325",
    "addr:housenumber":"3395",
    "addr:postcode":"52325",
    "addr:street":"275Th St",
    "iso:country":"US",
    "sg:address":"3395 275th St",
    "sg:city":"Parnell",
    "sg:classifiers":[
        {
            "category":"Farming",
            "subcategory":"Livestock Farm",
            "type":"Manufacturing & Wholesale Goods"
        }
    ],
    "sg:phone":"+1 319 628 4131",
    "sg:postcode":"52325",
    "sg:province":"IA",
    "sg:tags":[
        "beef",
        "feedlot",
        "cattle"
    ],
    "wof:name":"Anna Marie Sleeth",
    "wof:placetype":"venue"
},
  "geometry": {"coordinates":[-91.83614,41.607827],"type":"Point"}
}