{
  "type": "Feature",
  "properties": {
    "iso:country":"US",
    "sg:address":"1665 US Hwy 6",
    "sg:city":"West Liberty",
    "sg:phone":"+1 319 627 2377",
    "sg:postcode":"52776",
    "sg:province":"IA",
    "sg:tags":[
        "farm",
        "corn",
        "soybean"
    ],
    "wof:name":"Priscilla Haessig",
    "wof:placetype":"venue"
},
  "geometry": {"coordinates":[-91.245515,41.568188],"type":"Point"}
}