{
  "type": "Feature",
  "properties": {
    "addr:full":"6175 Merle Hay Rd Johnston IA 50131",
    "addr:housenumber":"6175",
    "addr:postcode":"50131",
    "addr:street":"Merle Hay Rd",
    "iso:country":"US",
    "sg:address":"6175 Merle Hay Rd",
    "sg:city":"Johnston",
    "sg:classifiers":[
        {
            "category":"Insurance",
            "subcategory":"Insurance Agent",
            "type":"Services"
        }
    ],
    "sg:phone":"+1 515 270 8487",
    "sg:postcode":"50131",
    "sg:province":"IA",
    "sg:website":"www.insurancecenter.com",
    "wof:name":"Insurance Center",
    "wof:placetype":"venue"
},
  "geometry": {"coordinates":[-93.697596,41.671507],"type":"Point"}
}