{
  "type": "Feature",
  "properties": {
    "iso:country":"US",
    "sg:address":"6916 Lafayette Rd",
    "sg:city":"Raymond",
    "sg:classifiers":[
        {
            "category":"Education",
            "subcategory":"School",
            "type":"Public Place"
        }
    ],
    "sg:phone":"+1 319 233 5980",
    "sg:postcode":"50667",
    "sg:province":"IA",
    "wof:name":"St Joseph's School",
    "wof:placetype":"venue"
},
  "geometry": {"coordinates":[-92.214159,42.468096],"type":"Point"}
}