{
  "type": "Feature",
  "properties": {
    "addr:full":"935 S Ohio Ave Davenport IA 52802",
    "addr:housenumber":"935",
    "addr:postcode":"52802",
    "addr:street":"S Ohio Ave",
    "iso:country":"US",
    "sg:address":"935 S Ohio Ave",
    "sg:city":"Davenport",
    "sg:classifiers":[
        {
            "category":"Building & Trades",
            "subcategory":"Cleaning & Sanitation",
            "type":"Services"
        }
    ],
    "sg:phone":"+1 563 323 5235",
    "sg:postcode":"52802",
    "sg:province":"IA",
    "sg:tags":[
        "maintenance"
    ],
    "wof:name":"Reynolds Window Cleaning Svc",
    "wof:placetype":"venue"
},
  "geometry": {"coordinates":[-90.625424,41.509017],"type":"Point"}
}