{
  "type": "Feature",
  "properties": {
    "addr:full":"508 N Elm St Jefferson IA 50129",
    "addr:housenumber":"508",
    "addr:postcode":"50129",
    "addr:street":"N Elm St",
    "iso:country":"US",
    "sg:address":"508 N Elm St",
    "sg:city":"Jefferson",
    "sg:classifiers":[
        {
            "category":"Restaurant",
            "type":"Food & Drink"
        }
    ],
    "sg:menulink":"http://www.allmenus.com/ia/jefferson/225955-caseys-general-store/menu/",
    "sg:phone":"+1 515 386 4463",
    "sg:postcode":"50129",
    "sg:province":"IA",
    "sg:tags":[
        "american",
        "pizza"
    ],
    "wof:name":"Casey's General Store",
    "wof:placetype":"venue"
},
  "geometry": {"coordinates":[-94.377419,42.019436],"type":"Point"}
}