{
  "type": "Feature",
  "properties": {
    "iso:country":"US",
    "sg:address":"910 10th St",
    "sg:city":"Nevada",
    "sg:classifiers":[
        {
            "category":"Education",
            "subcategory":"School",
            "type":"Public Place"
        }
    ],
    "sg:phone":"+1 515 382 2383",
    "sg:postcode":"50201",
    "sg:province":"IA",
    "wof:name":"Central Elementary School",
    "wof:placetype":"venue"
},
  "geometry": {"coordinates":[-93.44690900000001,42.02058],"type":"Point"}
}