{
  "type": "Feature",
  "properties": {
    "iso:country":"US",
    "sg:address":"315 S Main St",
    "sg:city":"Donnellson",
    "sg:classifiers":[
        {
            "category":"Local Transit",
            "type":"Transportation"
        }
    ],
    "sg:phone":"+1 319 835 5226",
    "sg:postcode":"52625",
    "sg:province":"IA",
    "wof:name":"Medical Transport Inc",
    "wof:placetype":"venue"
},
  "geometry": {"coordinates":[-91.56438,40.638],"type":"Point"}
}