{
  "type": "Feature",
  "properties": {
    "iso:country":"US",
    "sg:address":"369 332nd Pl",
    "sg:city":"Perry",
    "sg:classifiers":[
        {
            "category":"Freight",
            "type":"Transportation"
        }
    ],
    "sg:phone":"+1 515 465 2415",
    "sg:postcode":"50220",
    "sg:province":"IA",
    "sg:tags":[
        "trucking"
    ],
    "wof:name":"Luett Farms Trucking Inc",
    "wof:placetype":"venue"
},
  "geometry": {"coordinates":[-94.09557,41.871593],"type":"Point"}
}