{
  "type": "Feature",
  "properties": {
    "iso:country":"US",
    "sg:address":"414 E Congress St",
    "sg:city":"Nora Springs",
    "sg:classifiers":[
        {
            "category":"Food & Beverages",
            "subcategory":"Groceries & Convenience Stores",
            "type":"Retail Goods"
        }
    ],
    "sg:phone":"+1 641 749 2503",
    "sg:postcode":"50458",
    "sg:province":"IA",
    "wof:name":"Kum & Go",
    "wof:placetype":"venue"
},
  "geometry": {"coordinates":[-93.000488,43.142812],"type":"Point"}
}