{
  "type": "Feature",
  "properties": {
    "iso:country":"US",
    "sg:address":"830 L Ave",
    "sg:city":"Nevada",
    "sg:classifiers":[
        {
            "category":"Personal",
            "subcategory":"Barber",
            "type":"Services"
        }
    ],
    "sg:phone":"+1 515 382 3550",
    "sg:postcode":"50201",
    "sg:province":"IA",
    "wof:name":"Rusty Razor",
    "wof:placetype":"venue"
},
  "geometry": {"coordinates":[-93.44924899999999,42.022639],"type":"Point"}
}