{
  "type": "Feature",
  "properties": {
    "iso:country":"US",
    "sg:address":"104 3rd St SW",
    "sg:city":"Altoona",
    "sg:classifiers":[
        {
            "category":"Personal",
            "subcategory":"Beauty Salon",
            "type":"Services"
        }
    ],
    "sg:phone":"+1 515 967 2700",
    "sg:postcode":"50009",
    "sg:province":"IA",
    "sg:tags":[
        "shop"
    ],
    "wof:name":"Family Hair Care",
    "wof:placetype":"venue"
},
  "geometry": {"coordinates":[-93.464626,41.649351],"type":"Point"}
}