{
  "type": "Feature",
  "properties": {
    "addr:full":"2482 197th Ave Manchester IA 52057",
    "addr:housenumber":"2482",
    "addr:postcode":"52057",
    "addr:street":"197Th Ave",
    "iso:country":"US",
    "sg:address":"2482 197th Ave",
    "sg:city":"Manchester",
    "sg:classifiers":[
        {
            "category":"Freight",
            "type":"Transportation"
        }
    ],
    "sg:phone":"+1 563 927 4254",
    "sg:postcode":"52057",
    "sg:province":"IA",
    "sg:tags":[
        "commercial",
        "storage"
    ],
    "wof:name":"A-1 Container Trailer & Office",
    "wof:placetype":"venue"
},
  "geometry": {"coordinates":[-91.407854,42.423207],"type":"Point"}
}