{
  "type": "Feature",
  "properties": {
    "iso:country":"US",
    "sg:address":"1709 Dupont Way NW",
    "sg:city":"Swisher",
    "sg:phone":"+1 319 846 2931",
    "sg:postcode":"52338",
    "sg:province":"IA",
    "sg:tags":[
        "farm",
        "field",
        "corn",
        "crop"
    ],
    "wof:name":"Ernest Mouchka",
    "wof:placetype":"venue"
},
  "geometry": {"coordinates":[-91.747232,41.80602],"type":"Point"}
}