{
  "type": "Feature",
  "properties": {
    "addr:full":"2323 290th St Kelley IA 50134",
    "addr:housenumber":"2323",
    "addr:postcode":"50134",
    "addr:street":"290Th St",
    "iso:country":"US",
    "sg:address":"2323 290th St",
    "sg:city":"Kelley",
    "sg:phone":"+1 515 769 2458",
    "sg:postcode":"50134",
    "sg:province":"IA",
    "sg:tags":[
        "farm",
        "corn"
    ],
    "wof:name":"Phillip Ringgenberg",
    "wof:placetype":"venue"
},
  "geometry": {"coordinates":[-93.71437400000001,41.936171],"type":"Point"}
}