{
  "type": "Feature",
  "properties": {
    "iso:country":"US",
    "sg:address":"2271 270th St",
    "sg:city":"Ames",
    "sg:phone":"+1 515 292 2888",
    "sg:postcode":"50014",
    "sg:province":"IA",
    "sg:tags":[
        "farm",
        "corn",
        "soybean"
    ],
    "wof:name":"Robert Tripp",
    "wof:placetype":"venue"
},
  "geometry": {"coordinates":[-93.721087,41.965124],"type":"Point"}
}