{
  "type": "Feature",
  "properties": {
    "addr:full":"14093 Derby Grange Rd Dubuque IA 52002",
    "addr:housenumber":"14093",
    "addr:postcode":"52002",
    "addr:street":"Derby Grange Rd",
    "iso:country":"US",
    "sg:address":"14093 Derby Grange Rd",
    "sg:city":"Dubuque",
    "sg:classifiers":[
        {
            "category":"Building & Trades",
            "subcategory":"Electrical",
            "type":"Services"
        }
    ],
    "sg:phone":"+1 563 583 3252",
    "sg:postcode":"52002",
    "sg:province":"IA",
    "sg:tags":[
        "electrical",
        "contractor"
    ],
    "wof:name":"Kenneth Keller Electric",
    "wof:placetype":"venue"
},
  "geometry": {"coordinates":[-90.767698,42.530113],"type":"Point"}
}