{
  "type": "Feature",
  "properties": {
    "iso:country":"US",
    "sg:address":"1119 362nd Ave",
    "sg:city":"Preston",
    "sg:classifiers":[
        {
            "category":"Real Estate",
            "subcategory":"Real Estate Operator",
            "type":"Services"
        }
    ],
    "sg:phone":"+1 563 689 6220",
    "sg:postcode":"52069",
    "sg:province":"IA",
    "sg:tags":[
        "property",
        "lessor"
    ],
    "wof:name":"Allen Kloft",
    "wof:placetype":"venue"
},
  "geometry": {"coordinates":[-90.397344,42.015988],"type":"Point"}
}