{
  "type": "Feature",
  "properties": {
    "iso:country":"US",
    "sg:address":"1012 W Kimberly Rd",
    "sg:city":"Davenport",
    "sg:classifiers":[
        {
            "category":"Restaurant",
            "type":"Food & Drink"
        }
    ],
    "sg:menulink":"http://www.allmenus.com/ia/davenport/198332-kfc---kentucky-fried-chicken/menu/",
    "sg:phone":"+1 563 386 6695",
    "sg:postcode":"52806",
    "sg:province":"IA",
    "sg:tags":[
        "american",
        "chicken"
    ],
    "wof:name":"KFC - Kentucky Fried Chicken",
    "wof:placetype":"venue"
},
  "geometry": {"coordinates":[-90.58701499999999,41.560156],"type":"Point"}
}