{
  "type": "Feature",
  "properties": {
    "iso:country":"US",
    "sg:address":"19651 620th St",
    "sg:city":"Pomeroy",
    "sg:phone":"+1 712 468 2323",
    "sg:postcode":"50575",
    "sg:province":"IA",
    "sg:tags":[
        "farm",
        "corn",
        "soybean"
    ],
    "wof:name":"Charles Passow",
    "wof:placetype":"venue"
},
  "geometry": {"coordinates":[-94.724217,42.588382],"type":"Point"}
}