{
  "type": "Feature",
  "properties": {
    "addr:full":"5417 N Gaines St Davenport IA 52806",
    "addr:housenumber":"5417",
    "addr:postcode":"52806",
    "addr:street":"N Gaines St",
    "iso:country":"US",
    "sg:address":"5417 N Gaines St",
    "sg:city":"Davenport",
    "sg:classifiers":[
        {
            "category":"Real Estate",
            "subcategory":"Real Estate Operator",
            "type":"Services"
        }
    ],
    "sg:phone":"+1 563 391 4470",
    "sg:postcode":"52806",
    "sg:province":"IA",
    "sg:tags":[
        "building",
        "apartment"
    ],
    "wof:name":"Candlelight Village",
    "wof:placetype":"venue"
},
  "geometry": {"coordinates":[-90.58161,41.575641],"type":"Point"}
}