{
  "type": "Feature",
  "properties": {
    "iso:country":"US",
    "sg:address":"1040 73rd St",
    "sg:city":"Windsor Heights",
    "sg:classifiers":[
        {
            "category":"Personal",
            "subcategory":"Beauty Salon",
            "type":"Services"
        }
    ],
    "sg:phone":"+1 515 224 4685",
    "sg:postcode":"50311",
    "sg:province":"IA",
    "wof:name":"Talking Heads Salon",
    "wof:placetype":"venue"
},
  "geometry": {"coordinates":[-93.718481,41.597193],"type":"Point"}
}