{
  "type": "Feature",
  "properties": {
    "addr:full":"1500 3rd Ave SE Le Mars IA 51031",
    "addr:housenumber":"1500",
    "addr:postcode":"51031",
    "addr:street":"3Rd Ave Se",
    "iso:country":"US",
    "sg:address":"1500 3rd Ave SE",
    "sg:city":"Le Mars",
    "sg:classifiers":[
        {
            "category":"Personal",
            "subcategory":"Beauty Salon",
            "type":"Services"
        }
    ],
    "sg:phone":"+1 712 546 4001",
    "sg:postcode":"51031",
    "sg:province":"IA",
    "wof:name":"Mary's Beauty Salon",
    "wof:placetype":"venue"
},
  "geometry": {"coordinates":[-96.162572,42.773315],"type":"Point"}
}