{
  "type": "Feature",
  "properties": {
    "addr:full":"605 US Hwy 20 Parkersburg IA 50665",
    "addr:housenumber":"605",
    "addr:postcode":"50665",
    "addr:street":"Us Hwy 20",
    "iso:country":"US",
    "sg:address":"605 US Hwy 20",
    "sg:city":"Parkersburg",
    "sg:classifiers":[
        {
            "category":"Food & Beverages",
            "subcategory":"Groceries & Convenience Stores",
            "type":"Retail Goods"
        }
    ],
    "sg:phone":"+1 319 346 2468",
    "sg:postcode":"50665",
    "sg:province":"IA",
    "wof:name":"KWIK Star",
    "wof:placetype":"venue"
},
  "geometry": {"coordinates":[-92.787177,42.570446],"type":"Point"}
}