{
  "type": "Feature",
  "properties": {
    "addr:full":"3108 S Center St Marshalltown IA 50158",
    "addr:housenumber":"3108",
    "addr:postcode":"50158",
    "addr:street":"S Center St",
    "iso:country":"US",
    "sg:address":"3108 S Center St",
    "sg:city":"Marshalltown",
    "sg:classifiers":[
        {
            "category":"Travel",
            "subcategory":"Hotels & Motels",
            "type":"Entertainment"
        }
    ],
    "sg:phone":"+1 641 752 5485",
    "sg:postcode":"50158",
    "sg:province":"IA",
    "sg:tags":[
        "operation"
    ],
    "wof:name":"Economy Inn",
    "wof:placetype":"venue"
},
  "geometry": {"coordinates":[-92.91231000000001,42.011066],"type":"Point"}
}