{
  "type": "Feature",
  "properties": {
    "iso:country":"US",
    "sg:address":"202 S Ankeny Blvd",
    "sg:city":"Ankeny",
    "sg:classifiers":[
        {
            "category":"Restaurant",
            "type":"Food & Drink"
        }
    ],
    "sg:phone":"+1 515 964 9696",
    "sg:postcode":"50023",
    "sg:province":"IA",
    "wof:name":"Original Joe's",
    "wof:placetype":"venue"
},
  "geometry": {"coordinates":[-93.60037199999999,41.72962],"type":"Point"}
}