{
  "type": "Feature",
  "properties": {
    "iso:country":"US",
    "sg:address":"5153 320th St",
    "sg:city":"Cylinder",
    "sg:classifiers":[
        {
            "category":"Farming",
            "subcategory":"Farm",
            "type":"Manufacturing & Wholesale Goods"
        }
    ],
    "sg:phone":"+1 712 424 3217",
    "sg:postcode":"50528",
    "sg:province":"IA",
    "wof:name":"Hutch Mill Farms",
    "wof:placetype":"venue"
},
  "geometry": {"coordinates":[-94.569951,43.183713],"type":"Point"}
}