{
  "type": "Feature",
  "properties": {
    "iso:country":"US",
    "sg:address":"1900 1st St W",
    "sg:city":"Independence",
    "sg:classifiers":[
        {
            "category":"Restaurant",
            "type":"Food & Drink"
        }
    ],
    "sg:menulink":"http://www.allmenus.com/ia/washington/32080-pizza-ranch/menu/",
    "sg:phone":"+1 319 334 9000",
    "sg:postcode":"50644",
    "sg:province":"IA",
    "sg:tags":[
        "american",
        "pizza"
    ],
    "wof:name":"Pizza Ranch",
    "wof:placetype":"venue"
},
  "geometry": {"coordinates":[-91.91885499999999,42.468405],"type":"Point"}
}