{
  "type": "Feature",
  "properties": {
    "iso:country":"US",
    "sg:address":"103 E State St",
    "sg:city":"Mason City",
    "sg:classifiers":[
        {
            "category":"Real Estate",
            "subcategory":"Real Estate Agent",
            "type":"Services"
        }
    ],
    "sg:phone":"+1 641 422 1018",
    "sg:postcode":"50401",
    "sg:province":"IA",
    "sg:tags":[
        "appraiser"
    ],
    "wof:name":"Kelly Appraisal Svc",
    "wof:placetype":"venue"
},
  "geometry": {"coordinates":[-93.19940200000001,43.151735],"type":"Point"}
}