{
  "type": "Feature",
  "properties": {
    "iso:country":"US",
    "sg:address":"185 NW 66th Ave",
    "sg:city":"Des Moines",
    "sg:classifiers":[
        {
            "category":"Building & Trades",
            "subcategory":"Cleaning & Sanitation",
            "type":"Services"
        }
    ],
    "sg:phone":"+1 515 270 1511",
    "sg:postcode":"50313",
    "sg:province":"IA",
    "sg:tags":[
        "janitor"
    ],
    "wof:name":"Diamond Carpet & Cleaning Svc",
    "wof:placetype":"venue"
},
  "geometry": {"coordinates":[-93.619079,41.680429],"type":"Point"}
}