{
  "type": "Feature",
  "properties": {
    "addr:full":"2259 110th St Fort Atkinson IA 52144",
    "addr:housenumber":"2259",
    "addr:postcode":"52144",
    "addr:street":"110Th St",
    "iso:country":"US",
    "sg:address":"2259 110th St",
    "sg:city":"Fort Atkinson",
    "sg:classifiers":[
        {
            "category":"Real Estate",
            "subcategory":"Real Estate Operator",
            "type":"Services"
        }
    ],
    "sg:phone":"+1 563 534 7146",
    "sg:postcode":"52144",
    "sg:province":"IA",
    "sg:tags":[
        "property",
        "lessor"
    ],
    "wof:name":"Steven Lechtenberg",
    "wof:placetype":"venue"
},
  "geometry": {"coordinates":[-91.84627399999999,43.096551],"type":"Point"}
}