{
  "type": "Feature",
  "properties": {
    "iso:country":"US",
    "sg:address":"2506 4th Ave S",
    "sg:city":"Denison",
    "sg:classifiers":[
        {
            "category":"Restaurant",
            "type":"Food & Drink"
        }
    ],
    "sg:phone":"+1 712 263 9313",
    "sg:postcode":"51442",
    "sg:province":"IA",
    "sg:tags":[
        "pizza"
    ],
    "sg:website":"www.godfathers.com",
    "wof:name":"Godfather's Pizza",
    "wof:placetype":"venue"
},
  "geometry": {"coordinates":[-95.335954,42.01301],"type":"Point"}
}