{
  "type": "Feature",
  "properties": {
    "addr:full":"1574 March Ave Floyd IA 50435",
    "addr:housenumber":"1574",
    "addr:postcode":"50435",
    "addr:street":"March Ave",
    "iso:country":"US",
    "sg:address":"1574 March Ave",
    "sg:city":"Floyd",
    "sg:classifiers":[
        {
            "category":"Farming",
            "subcategory":"Farm",
            "type":"Manufacturing & Wholesale Goods"
        }
    ],
    "sg:phone":"+1 641 398 2251",
    "sg:postcode":"50435",
    "sg:province":"IA",
    "sg:tags":[
        "crop",
        "general"
    ],
    "wof:name":"Emmett Nauman",
    "wof:placetype":"venue"
},
  "geometry": {"coordinates":[-92.790294,43.130633],"type":"Point"}
}