{
  "type": "Feature",
  "properties": {
    "addr:full":"2338 Valleyview Ave St Charles IA 50240",
    "addr:housenumber":"2338",
    "addr:postcode":"50240",
    "addr:street":"Valleyview Ave",
    "iso:country":"US",
    "sg:address":"2338 Valleyview Ave",
    "sg:city":"St Charles",
    "sg:classifiers":[
        {
            "category":"Building & Trades",
            "subcategory":"Construction",
            "type":"Services"
        }
    ],
    "sg:phone":"+1 515 462 9288",
    "sg:postcode":"50240",
    "sg:province":"IA",
    "sg:tags":[
        "house",
        "general",
        "contractor"
    ],
    "wof:name":"Valley View Construction Inc",
    "wof:placetype":"venue"
},
  "geometry": {"coordinates":[-93.84673600000001,41.313886],"type":"Point"}
}