{
  "type": "Feature",
  "properties": {
    "addr:full":"3721 N Fairmount St Davenport IA 52806",
    "addr:housenumber":"3721",
    "addr:postcode":"52806",
    "addr:street":"N Fairmount St",
    "iso:country":"US",
    "sg:address":"3721 N Fairmount St",
    "sg:city":"Davenport",
    "sg:classifiers":[
        {
            "category":"Real Estate",
            "subcategory":"Developer",
            "type":"Services"
        }
    ],
    "sg:phone":"+1 563 391 3249",
    "sg:postcode":"52806",
    "sg:province":"IA",
    "sg:tags":[
        "mobile",
        "home"
    ],
    "wof:name":"Hickory Grove Mobile Home Park",
    "wof:placetype":"venue"
},
  "geometry": {"coordinates":[-90.62946100000001,41.557654],"type":"Point"}
}