{
  "type": "Feature",
  "properties": {
    "iso:country":"US",
    "sg:address":"2600 Edgewood Rd SW Ofc",
    "sg:city":"Cedar Rapids",
    "sg:classifiers":[
        {
            "category":"Shopping",
            "subcategory":"Mobile Phones",
            "type":"Retail Goods"
        }
    ],
    "sg:phone":"+1 319 390 1051",
    "sg:postcode":"52404",
    "sg:province":"IA",
    "wof:name":"U S Cellular Westdale Mall",
    "wof:placetype":"venue"
},
  "geometry": {"coordinates":[-91.716103,41.953899],"type":"Point"}
}