{
  "type": "Feature",
  "properties": {
    "iso:country":"US",
    "sg:address":"3607 Ingersoll Ave",
    "sg:city":"Des Moines",
    "sg:classifiers":[
        {
            "category":"Real Estate",
            "subcategory":"Real Estate Operator",
            "type":"Services"
        }
    ],
    "sg:phone":"+1 515 255 8495",
    "sg:postcode":"50312",
    "sg:province":"IA",
    "sg:tags":[
        "apartment"
    ],
    "wof:name":"Risser Investments",
    "wof:placetype":"venue"
},
  "geometry": {"coordinates":[-93.666714,41.5864],"type":"Point"}
}