{
  "type": "Feature",
  "properties": {
    "iso:country":"US",
    "sg:address":"2201 W Broadway",
    "sg:city":"Council Bluffs",
    "sg:classifiers":[
        {
            "category":"Bakery",
            "type":"Food & Drink"
        }
    ],
    "sg:phone":"+1 712 328 3532",
    "sg:postcode":"51501",
    "sg:province":"IA",
    "wof:name":"Old Home Bread",
    "wof:placetype":"venue"
},
  "geometry": {"coordinates":[-95.876999,41.261902],"type":"Point"}
}