{
  "type": "Feature",
  "properties": {
    "iso:country":"US",
    "sg:address":"3100 Westwood Dr NW",
    "sg:city":"Cedar Rapids",
    "sg:classifiers":[
        {
            "category":"Wholesale",
            "subcategory":"Non-durable Goods",
            "type":"Manufacturing & Wholesale Goods"
        }
    ],
    "sg:phone":"+1 319 396 5189",
    "sg:postcode":"52405",
    "sg:province":"IA",
    "wof:name":"R J S Independent",
    "wof:placetype":"venue"
},
  "geometry": {"coordinates":[-91.71208900000001,41.984913],"type":"Point"}
}