{
  "type": "Feature",
  "properties": {
    "iso:country":"US",
    "sg:address":"119 1st St W",
    "sg:city":"Mt Vernon",
    "sg:classifiers":[
        {
            "category":"Restaurant",
            "type":"Food & Drink"
        }
    ],
    "sg:phone":"+1 319 895 8654",
    "sg:postcode":"52314",
    "sg:province":"IA",
    "wof:name":"Chameleon's Pub & Grub",
    "wof:placetype":"venue"
},
  "geometry": {"coordinates":[-91.417858,41.922768],"type":"Point"}
}