{
  "type": "Feature",
  "properties": {
    "iso:country":"US",
    "sg:address":"25 S 15th St",
    "sg:city":"Council Bluffs",
    "sg:classifiers":[
        {
            "category":"Building & Trades",
            "subcategory":"Construction",
            "type":"Services"
        }
    ],
    "sg:phone":"+1 712 325 0474",
    "sg:postcode":"51501",
    "sg:province":"IA",
    "sg:tags":[
        "excavating"
    ],
    "wof:name":"Kc Excavating Inc",
    "wof:placetype":"venue"
},
  "geometry": {"coordinates":[-95.865917,41.260873],"type":"Point"}
}