{
  "type": "Feature",
  "properties": {
    "iso:country":"US",
    "sg:address":"30441 Prier Rd",
    "sg:city":"Dyersville",
    "sg:classifiers":[
        {
            "category":"Building & Trades",
            "subcategory":"Plumbing",
            "type":"Services"
        }
    ],
    "sg:phone":"+1 563 875 2626",
    "sg:postcode":"52040",
    "sg:province":"IA",
    "sg:tags":[
        "plumbing",
        "contractor"
    ],
    "wof:name":"Prier Brothers Inc",
    "wof:placetype":"venue"
},
  "geometry": {"coordinates":[-91.082538,42.474109],"type":"Point"}
}