{
  "type": "Feature",
  "properties": {
    "iso:country":"US",
    "sg:address":"717 8th St SE",
    "sg:city":"Orange City",
    "sg:classifiers":[
        {
            "category":"Cinema",
            "subcategory":"Movie Theater",
            "type":"Entertainment"
        }
    ],
    "sg:phone":"+1 712 737 8866",
    "sg:postcode":"51041",
    "sg:province":"IA",
    "wof:name":"Holland Plaza 4 Theatre",
    "wof:placetype":"venue"
},
  "geometry": {"coordinates":[-96.048552,42.997574],"type":"Point"}
}