{
  "type": "Feature",
  "properties": {
    "iso:country":"US",
    "sg:address":"6004 Dagle Dr",
    "sg:city":"Des Moines",
    "sg:classifiers":[
        {
            "category":"Social Services",
            "subcategory":"Child Care",
            "type":"Services"
        }
    ],
    "sg:phone":"+1 515 274 2277",
    "sg:postcode":"50311",
    "sg:province":"IA",
    "sg:tags":[
        "day"
    ],
    "wof:name":"Chrch of Jesus Christ Ltr Day",
    "wof:placetype":"venue"
},
  "geometry": {"coordinates":[-93.701583,41.598801],"type":"Point"}
}