{
  "type": "Feature",
  "properties": {
    "addr:full":"411 Viking Rd Cedar Falls IA 50613",
    "addr:housenumber":"411",
    "addr:postcode":"50613",
    "addr:street":"Viking Rd",
    "iso:country":"US",
    "sg:address":"411 Viking Rd",
    "sg:city":"Cedar Falls",
    "sg:classifiers":[
        {
            "category":"Shopping",
            "subcategory":"Catalog Store",
            "type":"Retail Goods"
        }
    ],
    "sg:phone":"+1 319 268 0104",
    "sg:postcode":"50613",
    "sg:province":"IA",
    "sg:tags":[
        "mail",
        "order"
    ],
    "sg:website":"www.porters.com",
    "wof:name":"Porter's Camera Store Inc",
    "wof:placetype":"venue"
},
  "geometry": {"coordinates":[-92.450363,42.484126],"type":"Point"}
}