{
  "type": "Feature",
  "properties": {
    "addr:full":"1837 Newton Ave Tipton IA 52772",
    "addr:housenumber":"1837",
    "addr:postcode":"52772",
    "addr:street":"Newton Ave",
    "iso:country":"US",
    "sg:address":"1837 Newton Ave",
    "sg:city":"Tipton",
    "sg:phone":"+1 563 886 3335",
    "sg:postcode":"52772",
    "sg:province":"IA",
    "sg:tags":[
        "farm",
        "corn"
    ],
    "wof:name":"Rodney Schwitzer",
    "wof:placetype":"venue"
},
  "geometry": {"coordinates":[-91.102446,41.679468],"type":"Point"}
}