{
  "type": "Feature",
  "properties": {
    "iso:country":"US",
    "sg:address":"1018 W 7th St",
    "sg:city":"Sioux City",
    "sg:classifiers":[
        {
            "category":"Building & Trades",
            "subcategory":"Plumbing",
            "type":"Services"
        }
    ],
    "sg:phone":"+1 712 252 3535",
    "sg:postcode":"51103",
    "sg:province":"IA",
    "sg:tags":[
        "plumbing",
        "contractor"
    ],
    "wof:name":"Quality Plumbing Co",
    "wof:placetype":"venue"
},
  "geometry": {"coordinates":[-96.42083700000001,42.504073],"type":"Point"}
}