{
  "type": "Feature",
  "properties": {
    "iso:country":"US",
    "sg:address":"3125 Taylor Ave",
    "sg:city":"Walker",
    "sg:phone":"+1 319 224 3436",
    "sg:postcode":"52352",
    "sg:province":"IA",
    "sg:tags":[
        "farm",
        "corn"
    ],
    "wof:name":"Dean & Daphne Hoover",
    "wof:placetype":"venue"
},
  "geometry": {"coordinates":[-91.70593,42.336428],"type":"Point"}
}