{
  "type": "Feature",
  "properties": {
    "addr:full":"210 5th St Durant IA 52747",
    "addr:housenumber":"210",
    "addr:postcode":"52747",
    "addr:street":"5Th St",
    "iso:country":"US",
    "sg:address":"210 5th St",
    "sg:city":"Durant",
    "sg:classifiers":[
        {
            "category":"Shopping",
            "subcategory":"Florist",
            "type":"Retail Goods"
        }
    ],
    "sg:phone":"+1 563 785 4513",
    "sg:postcode":"52747",
    "sg:province":"IA",
    "wof:name":"Blooming Ideas",
    "wof:placetype":"venue"
},
  "geometry": {"coordinates":[-90.918892,41.602064],"type":"Point"}
}