{
  "type": "Feature",
  "properties": {
    "addr:full":"3500 S Lakeport St Sioux City SD 51106",
    "addr:housenumber":"3500",
    "addr:postcode":"51106",
    "addr:street":"S Lakeport St",
    "iso:country":"US",
    "sg:address":"3500 S Lakeport St",
    "sg:city":"Sioux City",
    "sg:classifiers":[
        {
            "category":"Banks & Credit Unions",
            "subcategory":"Bank",
            "type":"Services"
        }
    ],
    "sg:phone":"+1 712 274 4650",
    "sg:postcode":"51106",
    "sg:province":"SD",
    "sg:tags":[
        "loan",
        "real estate"
    ],
    "wof:name":"Carteret Mortgage",
    "wof:placetype":"venue"
},
  "geometry": {"coordinates":[-96.34562,42.448473],"type":"Point"}
}