{
  "type": "Feature",
  "properties": {
    "addr:full":"1621 Wink Ave Yale IA 50277",
    "addr:postcode":"1621;50277",
    "addr:street":"Wink Ave",
    "iso:country":"US",
    "sg:address":"1621 Wink Ave",
    "sg:city":"Yale",
    "sg:classifiers":[
        {
            "category":"Retail",
            "subcategory":"Auto Repair",
            "type":"Services"
        }
    ],
    "sg:phone":"+1 641 439 6657",
    "sg:postcode":"50277",
    "sg:province":"IA",
    "sg:tags":[
        "general"
    ],
    "wof:name":"Three D Truck Repair",
    "wof:placetype":"venue"
},
  "geometry": {"coordinates":[-94.30971099999999,41.773205],"type":"Point"}
}