{
  "type": "Feature",
  "properties": {
    "iso:country":"US",
    "sg:address":"2114 Spicer Ave",
    "sg:city":"Wilton",
    "sg:phone":"+1 563 732 2969",
    "sg:postcode":"52778",
    "sg:province":"IA",
    "sg:tags":[
        "farm",
        "corn"
    ],
    "wof:name":"Phil Urmie",
    "wof:placetype":"venue"
},
  "geometry": {"coordinates":[-91.016201,41.638887],"type":"Point"}
}