{
  "type": "Feature",
  "properties": {
    "iso:country":"US",
    "sg:address":"391 Heritage Dr",
    "sg:city":"Waukon",
    "sg:classifiers":[
        {
            "category":"Education",
            "subcategory":"Vocational School",
            "type":"Public Place"
        }
    ],
    "sg:phone":"+1 563 568 2614",
    "sg:postcode":"52172",
    "sg:province":"IA",
    "sg:tags":[
        "training",
        "computer"
    ],
    "wof:name":"Bank Training",
    "wof:placetype":"venue"
},
  "geometry": {"coordinates":[-91.55057499999999,43.265819],"type":"Point"}
}