{
  "type": "Feature",
  "properties": {
    "iso:country":"US",
    "sg:address":"10574 80th St",
    "sg:city":"Wyoming",
    "sg:classifiers":[
        {
            "category":"Professional",
            "subcategory":"Business Services",
            "type":"Services"
        }
    ],
    "sg:phone":"+1 563 488 2532",
    "sg:postcode":"52362",
    "sg:province":"IA",
    "wof:name":"Rj Iron Design",
    "wof:placetype":"venue"
},
  "geometry": {"coordinates":[-91.07454300000001,42.047753],"type":"Point"}
}