{
  "type": "Feature",
  "properties": {
    "addr:full":"210 1st Ave E Dyersville IA 52040",
    "addr:housenumber":"210",
    "addr:postcode":"52040",
    "addr:street":"1St Ave E Dyersville",
    "iso:country":"US",
    "sg:address":"210 1st Ave E",
    "sg:city":"Dyersville",
    "sg:classifiers":[
        {
            "category":"Bars & Pubs",
            "type":"Food & Drink"
        }
    ],
    "sg:phone":"+1 563 875 8832",
    "sg:postcode":"52040",
    "sg:province":"IA",
    "wof:name":"English Pub",
    "wof:placetype":"venue"
},
  "geometry": {"coordinates":[-91.122696,42.484692],"type":"Point"}
}