{
  "type": "Feature",
  "properties": {
    "iso:country":"US",
    "sg:address":"1527 Albia Rd",
    "sg:city":"Ottumwa",
    "sg:classifiers":[
        {
            "category":"Sports & Exercise",
            "subcategory":"Bowling",
            "type":"Entertainment"
        }
    ],
    "sg:phone":"+1 641 684 9250",
    "sg:postcode":"52501",
    "sg:province":"IA",
    "sg:tags":[
        "center"
    ],
    "wof:name":"Strike Zone",
    "wof:placetype":"venue"
},
  "geometry": {"coordinates":[-92.44232100000001,41.009288],"type":"Point"}
}