{
  "type": "Feature",
  "properties": {
    "iso:country":"US",
    "sg:address":"16989 V Ave",
    "sg:city":"Steamboat Rock",
    "sg:classifiers":[
        {
            "category":"Manufacturing",
            "subcategory":"Lumber",
            "type":"Manufacturing & Wholesale Goods"
        }
    ],
    "sg:phone":"+1 641 868 2324",
    "sg:postcode":"50672",
    "sg:province":"IA",
    "wof:name":"Leverton Sawmill",
    "wof:placetype":"venue"
},
  "geometry": {"coordinates":[-93.07168900000001,42.455708],"type":"Point"}
}