{
  "type": "Feature",
  "properties": {
    "iso:country":"US",
    "sg:address":"313 Story St Ste 1",
    "sg:city":"Council Bluffs",
    "sg:classifiers":[
        {
            "category":"Education",
            "subcategory":"Preschool",
            "type":"Public Place"
        },
        {
            "category":"Education",
            "subcategory":"School",
            "type":"Public Place"
        }
    ],
    "sg:phone":"+1 712 322 6655",
    "sg:postcode":"51503",
    "sg:province":"IA",
    "sg:tags":[
        "elementary"
    ],
    "sg:website":"www.oursaviorscb.org",
    "wof:name":"Our Savior's Lutheran Church Elca",
    "wof:placetype":"venue"
},
  "geometry": {"coordinates":[-95.84849,41.255394],"type":"Point"}
}