{
  "type": "Feature",
  "properties": {
    "iso:country":"US",
    "sg:address":"3800 Douglas Ave",
    "sg:city":"Des Moines",
    "sg:classifiers":[
        {
            "category":"Professional",
            "subcategory":"Computer Services",
            "type":"Services"
        }
    ],
    "sg:phone":"+1 515 255 8199",
    "sg:postcode":"50310",
    "sg:province":"IA",
    "sg:tags":[
        "website",
        "design"
    ],
    "sg:website":"www.dmwebcenter.com",
    "wof:name":"Interweb",
    "wof:placetype":"venue"
},
  "geometry": {"coordinates":[-93.66961499999999,41.62952],"type":"Point"}
}