{
  "type": "Feature",
  "properties": {
    "iso:country":"US",
    "sg:address":"110 W Main St",
    "sg:city":"St Charles",
    "sg:classifiers":[
        {
            "category":"Personal",
            "subcategory":"Beauty Salon",
            "type":"Services"
        }
    ],
    "sg:phone":"+1 641 396 2339",
    "sg:postcode":"50240",
    "sg:province":"IA",
    "wof:name":"Classic Cuts By Darcy",
    "wof:placetype":"venue"
},
  "geometry": {"coordinates":[-93.80591699999999,41.288372],"type":"Point"}
}