{
  "type": "Feature",
  "properties": {
    "iso:country":"US",
    "sg:address":"201 W 53rd St",
    "sg:city":"Davenport",
    "sg:classifiers":[
        {
            "category":"Food & Beverages",
            "subcategory":"Groceries & Convenience Stores",
            "type":"Retail Goods"
        }
    ],
    "sg:phone":"+1 563 391 5212",
    "sg:postcode":"52806",
    "sg:province":"IA",
    "wof:name":"Kwik Shop 586",
    "wof:placetype":"venue"
},
  "geometry": {"coordinates":[-90.574752,41.574454],"type":"Point"}
}