{
  "type": "Feature",
  "properties": {
    "iso:country":"US",
    "sg:address":"1801 Highway Blvd",
    "sg:city":"Spencer",
    "sg:classifiers":[
        {
            "category":"Real Estate",
            "subcategory":"Real Estate Agent",
            "type":"Services"
        }
    ],
    "sg:phone":"+1 712 262 1066",
    "sg:postcode":"51301",
    "sg:province":"IA",
    "sg:website":"www.spencer-realty.com",
    "wof:name":"Spencer Realty",
    "wof:placetype":"venue"
},
  "geometry": {"coordinates":[-95.147865,43.158874],"type":"Point"}
}