{
  "type": "Feature",
  "properties": {
    "iso:country":"US",
    "sg:address":"4220 E Ave",
    "sg:city":"Paullina",
    "sg:phone":"+1 712 376 4859",
    "sg:postcode":"51035",
    "sg:province":"IA",
    "sg:tags":[
        "farm",
        "corn",
        "beef",
        "feedlot",
        "cattle"
    ],
    "wof:name":"Mike Meyer",
    "wof:placetype":"venue"
},
  "geometry": {"coordinates":[-95.78066,42.906516],"type":"Point"}
}