{
  "type": "Feature",
  "properties": {
    "iso:country":"US",
    "sg:address":"24825 10th Ave",
    "sg:city":"Stockton",
    "sg:classifiers":[
        {
            "category":"Building & Trades",
            "subcategory":"Construction",
            "type":"Services"
        }
    ],
    "sg:phone":"+1 563 785 6221",
    "sg:postcode":"52769",
    "sg:province":"IA",
    "sg:tags":[
        "fence",
        "contractor"
    ],
    "wof:name":"D & D Fencing",
    "wof:placetype":"venue"
},
  "geometry": {"coordinates":[-90.879564,41.666091],"type":"Point"}
}