{
  "type": "Feature",
  "properties": {
    "addr:full":"201 S Cody Rd Le Claire IA 52753",
    "addr:housenumber":"201",
    "addr:postcode":"52753",
    "addr:street":"S Cody Rd",
    "iso:country":"US",
    "sg:address":"201 S Cody Rd",
    "sg:city":"Le Claire",
    "sg:classifiers":[
        {
            "category":"Restaurant",
            "type":"Food & Drink"
        }
    ],
    "sg:phone":"+1 563 289 2733",
    "sg:postcode":"52753",
    "sg:province":"IA",
    "wof:name":"Lydia's Bakery Cafe",
    "wof:placetype":"venue"
},
  "geometry": {"coordinates":[-90.343733,41.595561],"type":"Point"}
}