{
  "type": "Feature",
  "properties": {
    "addr:full":"1305 Madison Ave Council Bluffs IA 51503",
    "addr:housenumber":"1305",
    "addr:postcode":"51503",
    "addr:street":"Madison Ave",
    "iso:country":"US",
    "sg:address":"1305 Madison Ave",
    "sg:city":"Council Bluffs",
    "sg:classifiers":[
        {
            "category":"Professional",
            "subcategory":"Accounting & Tax Preparation",
            "type":"Services"
        }
    ],
    "sg:phone":"+1 712 323 5365",
    "sg:postcode":"51503",
    "sg:province":"IA",
    "sg:tags":[
        "bookkeeping",
        "general"
    ],
    "wof:name":"Bob's Bookkeeping Svc",
    "wof:placetype":"venue"
},
  "geometry": {"coordinates":[-95.832218,41.25137],"type":"Point"}
}