{
  "type": "Feature",
  "properties": {
    "iso:country":"US",
    "sg:address":"12294 Esgate Rd",
    "sg:city":"Maquoketa",
    "sg:classifiers":[
        {
            "category":"Farming",
            "subcategory":"Livestock Farm",
            "type":"Manufacturing & Wholesale Goods"
        }
    ],
    "sg:phone":"+1 563 652 4534",
    "sg:postcode":"52060",
    "sg:province":"IA",
    "sg:tags":[
        "feedlot",
        "grain",
        "cash",
        "beef",
        "cattle"
    ],
    "wof:name":"Larry Hayward",
    "wof:placetype":"venue"
},
  "geometry": {"coordinates":[-90.714725,42.140898],"type":"Point"}
}