{
  "type": "Feature",
  "properties": {
    "iso:country":"US",
    "sg:address":"1725 O Ave NW",
    "sg:city":"Cedar Rapids",
    "sg:classifiers":[
        {
            "category":"Social Services",
            "type":"Services"
        }
    ],
    "sg:phone":"+1 319 398 3647",
    "sg:postcode":"52405",
    "sg:province":"IA",
    "sg:tags":[
        "care",
        "center",
        "day"
    ],
    "wof:name":"Milestone Adult Day Health Ctr",
    "wof:placetype":"venue"
},
  "geometry": {"coordinates":[-91.695948,41.98898],"type":"Point"}
}