{
  "type": "Feature",
  "properties": {
    "addr:full":"301 S Iowa Ave Washington IA 52353",
    "addr:housenumber":"301",
    "addr:postcode":"52353",
    "addr:street":"S Iowa Ave",
    "iso:country":"US",
    "sg:address":"301 S Iowa Ave",
    "sg:city":"Washington",
    "sg:classifiers":[
        {
            "category":"Insurance",
            "subcategory":"Insurance Agent",
            "type":"Services"
        }
    ],
    "sg:phone":"+1 319 653 5172",
    "sg:postcode":"52353",
    "sg:province":"IA",
    "wof:name":"Sellers Insurance Inc",
    "wof:placetype":"venue"
},
  "geometry": {"coordinates":[-91.691704,41.297399],"type":"Point"}
}