{
  "type": "Feature",
  "properties": {
    "addr:full":"3130 Sandy Beach Rd NE Solon IA 52333",
    "addr:housenumber":"3130",
    "addr:postcode":"52333",
    "addr:street":"Sandy Beach Rd Ne",
    "iso:country":"US",
    "sg:address":"3130 Sandy Beach Rd NE",
    "sg:city":"Solon",
    "sg:classifiers":[
        {
            "category":"Professional",
            "subcategory":"Management & Consulting",
            "type":"Services"
        }
    ],
    "sg:phone":"+1 319 848 9015",
    "sg:postcode":"52333",
    "sg:province":"IA",
    "sg:tags":[
        "business"
    ],
    "wof:name":"Kay Hofland Wound Consulting I",
    "wof:placetype":"venue"
},
  "geometry": {"coordinates":[-91.624864,41.827911],"type":"Point"}
}