{
  "type": "Feature",
  "properties": {
    "iso:country":"US",
    "sg:address":"123 N Main St",
    "sg:city":"Protivin",
    "sg:classifiers":[
        {
            "category":"Retail",
            "subcategory":"Funeral Services",
            "type":"Services"
        }
    ],
    "sg:phone":"+1 563 569 8363",
    "sg:postcode":"52163",
    "sg:province":"IA",
    "sg:tags":[
        "director"
    ],
    "wof:name":"Conway Funeral Home",
    "wof:placetype":"venue"
},
  "geometry": {"coordinates":[-92.09085,43.218161],"type":"Point"}
}