{
  "type": "Feature",
  "properties": {
    "iso:country":"US",
    "sg:address":"408 Maxwell St",
    "sg:city":"Maxwell",
    "sg:classifiers":[
        {
            "category":"Education",
            "subcategory":"School",
            "type":"Public Place"
        }
    ],
    "sg:phone":"+1 515 387 8842",
    "sg:postcode":"50161",
    "sg:province":"IA",
    "wof:name":"Collins-Maxwell Superintendent",
    "wof:placetype":"venue"
},
  "geometry": {"coordinates":[-93.398342,41.891223],"type":"Point"}
}