{
  "type": "Feature",
  "properties": {
    "iso:country":"US",
    "sg:address":"805 7th St",
    "sg:city":"Harlan",
    "sg:classifiers":[
        {
            "category":"Restaurant",
            "type":"Food & Drink"
        }
    ],
    "sg:phone":"+1 712 755 3309",
    "sg:postcode":"51537",
    "sg:province":"IA",
    "wof:name":"Subs & Suds",
    "wof:placetype":"venue"
},
  "geometry": {"coordinates":[-95.31904900000001,41.659929],"type":"Point"}
}