{
  "type": "Feature",
  "properties": {
    "iso:country":"US",
    "sg:address":"408 N Page St",
    "sg:city":"Monona",
    "sg:classifiers":[
        {
            "category":"Building & Trades",
            "subcategory":"Landscaping Services",
            "type":"Services"
        }
    ],
    "sg:phone":"+1 563 539 2770",
    "sg:postcode":"52159",
    "sg:province":"IA",
    "sg:tags":[
        "lawn",
        "maintenance",
        "grounds"
    ],
    "wof:name":"Schlein's Lawn Care",
    "wof:placetype":"venue"
},
  "geometry": {"coordinates":[-91.391057,43.055733],"type":"Point"}
}