{
  "type": "Feature",
  "properties": {
    "iso:country":"US",
    "sg:address":"2270 180th Ave",
    "sg:city":"Milford",
    "sg:phone":"+1 712 338 4912",
    "sg:postcode":"51351",
    "sg:province":"IA",
    "sg:tags":[
        "farm",
        "corn"
    ],
    "wof:name":"Tim Hemphill",
    "wof:placetype":"venue"
},
  "geometry": {"coordinates":[-95.229012,43.317626],"type":"Point"}
}