{
  "type": "Feature",
  "properties": {
    "iso:country":"US",
    "sg:address":"626 Prospect",
    "sg:city":"Lehigh",
    "sg:classifiers":[
        {
            "category":"Retail",
            "subcategory":"Auto Repair",
            "type":"Services"
        }
    ],
    "sg:phone":"+1 515 359 2321",
    "sg:postcode":"50557",
    "sg:province":"IA",
    "sg:tags":[
        "truck"
    ],
    "wof:name":"Wayne Goodrich",
    "wof:placetype":"venue"
},
  "geometry": {"coordinates":[-94.04850999999999,42.364329],"type":"Point"}
}