{
  "type": "Feature",
  "properties": {
    "addr:full":"1446 E Fleming Ave Des Moines IA 50313",
    "addr:housenumber":"1446",
    "addr:postcode":"50313",
    "addr:street":"E Fleming Ave",
    "iso:country":"US",
    "sg:address":"1446 E Fleming Ave",
    "sg:city":"Des Moines",
    "sg:classifiers":[
        {
            "category":"Building & Trades",
            "subcategory":"Landscaping Services",
            "type":"Services"
        }
    ],
    "sg:phone":"+1 515 669 9500",
    "sg:postcode":"50313",
    "sg:province":"IA",
    "sg:tags":[
        "lawn",
        "maintenance",
        "grounds"
    ],
    "wof:name":"Grass Masters Lawn Care Inc",
    "wof:placetype":"venue"
},
  "geometry": {"coordinates":[-93.59686499999999,41.632339],"type":"Point"}
}