{
  "type": "Feature",
  "properties": {
    "addr:full":"209 W Pleasant St Knoxville IA 50138",
    "addr:housenumber":"209",
    "addr:postcode":"50138",
    "addr:street":"W Pleasant St",
    "iso:country":"US",
    "sg:address":"209 W Pleasant St",
    "sg:city":"Knoxville",
    "sg:classifiers":[
        {
            "category":"Autos & Motor Vehicles",
            "subcategory":"Motorcycle Sales",
            "type":"Retail Goods"
        }
    ],
    "sg:phone":"+1 641 842 6686",
    "sg:postcode":"50138",
    "sg:province":"IA",
    "sg:tags":[
        "scooter"
    ],
    "wof:name":"Moto-Source",
    "wof:placetype":"venue"
},
  "geometry": {"coordinates":[-93.09993900000001,41.320683],"type":"Point"}
}