{
  "type": "Feature",
  "properties": {
    "iso:country":"US",
    "sg:address":"1315 Main St",
    "sg:city":"Pilot Grove",
    "sg:classifiers":[
        {
            "category":"Professional",
            "type":"Services"
        }
    ],
    "sg:phone":"+1 641 469 3496",
    "sg:postcode":"52657",
    "sg:province":"IA",
    "sg:tags":[
        "establishment"
    ],
    "wof:name":"Pauls Processing",
    "wof:placetype":"venue"
},
  "geometry": {"coordinates":[-91.51640399999999,40.767848],"type":"Point"}
}