{
  "type": "Feature",
  "properties": {
    "addr:full":"725 N Center Point Rd Hiawatha IA 52233",
    "addr:housenumber":"725",
    "addr:postcode":"52233",
    "addr:street":"N Center Point Rd",
    "iso:country":"US",
    "sg:address":"725 N Center Point Rd",
    "sg:city":"Hiawatha",
    "sg:classifiers":[
        {
            "category":"Home & Garden",
            "subcategory":"Carpets & Floor Coverings",
            "type":"Retail Goods"
        }
    ],
    "sg:phone":"+1 319 393 1199",
    "sg:postcode":"52233",
    "sg:province":"IA",
    "sg:tags":[
        "dealer",
        "rug"
    ],
    "wof:name":"Flooring Xpress",
    "wof:placetype":"venue"
},
  "geometry": {"coordinates":[-91.681375,42.04558],"type":"Point"}
}