{
  "type": "Feature",
  "properties": {
    "addr:full":"427 E Pleasant View Dr Des Moines IA 50315",
    "addr:housenumber":"427",
    "addr:postcode":"50315",
    "addr:street":"E Pleasant View Dr",
    "iso:country":"US",
    "sg:address":"427 E Pleasant View Dr",
    "sg:city":"Des Moines",
    "sg:classifiers":[
        {
            "category":"Building & Trades",
            "subcategory":"Construction",
            "type":"Services"
        }
    ],
    "sg:phone":"+1 515 280 7494",
    "sg:postcode":"50315",
    "sg:province":"IA",
    "sg:tags":[
        "house"
    ],
    "wof:name":"Pack Remodeling",
    "wof:placetype":"venue"
},
  "geometry": {"coordinates":[-93.612667,41.557193],"type":"Point"}
}