{
  "type": "Feature",
  "properties": {
    "addr:full":"700 Technology Pl Waverly IA 50677",
    "addr:housenumber":"700",
    "addr:postcode":"50677",
    "addr:street":"Technology Pl",
    "iso:country":"US",
    "sg:address":"700 Technology Pl",
    "sg:city":"Waverly",
    "sg:classifiers":[
        {
            "category":"Wholesale",
            "subcategory":"Hardware",
            "type":"Manufacturing & Wholesale Goods"
        }
    ],
    "sg:phone":"+1 319 352 4312",
    "sg:postcode":"50677",
    "sg:province":"IA",
    "sg:tags":[
        "fastener"
    ],
    "wof:name":"Fastenal Co",
    "wof:placetype":"venue"
},
  "geometry": {"coordinates":[-92.47782599999999,42.707201],"type":"Point"}
}