{
  "type": "Feature",
  "properties": {
    "addr:full":"210 Lakeview Dr Clermont IA 52135",
    "addr:housenumber":"210",
    "addr:postcode":"52135",
    "addr:street":"Lakeview Dr",
    "iso:country":"US",
    "sg:address":"210 Lakeview Dr",
    "sg:city":"Clermont",
    "sg:classifiers":[
        {
            "category":"Building & Trades",
            "subcategory":"Cleaning & Sanitation",
            "type":"Services"
        }
    ],
    "sg:phone":"+1 563 423 5000",
    "sg:postcode":"52135",
    "sg:province":"IA",
    "wof:name":"Complete Cleaning",
    "wof:placetype":"venue"
},
  "geometry": {"coordinates":[-91.662938,42.995245],"type":"Point"}
}