{
  "type": "Feature",
  "properties": {
    "addr:full":"106 Cedar St Elkader IA 52043",
    "addr:housenumber":"106",
    "addr:postcode":"52043",
    "addr:street":"Cedar St",
    "iso:country":"US",
    "sg:address":"106 Cedar St",
    "sg:city":"Elkader",
    "sg:classifiers":[
        {
            "category":"Manufacturing",
            "subcategory":"Printing",
            "type":"Manufacturing & Wholesale Goods"
        }
    ],
    "sg:phone":"+1 563 245 1311",
    "sg:postcode":"52043",
    "sg:province":"IA",
    "sg:tags":[
        "newspaper"
    ],
    "sg:website":"www.claytoncountyregister.com",
    "wof:name":"Clayton County Register",
    "wof:placetype":"venue"
},
  "geometry": {"coordinates":[-91.405306,42.855297],"type":"Point"}
}