{
  "type": "Feature",
  "properties": {
    "iso:country":"US",
    "sg:address":"607 S East St",
    "sg:city":"Bloomfield",
    "sg:classifiers":[
        {
            "category":"Wholesale",
            "subcategory":"Scrap",
            "type":"Manufacturing & Wholesale Goods"
        }
    ],
    "sg:phone":"+1 641 664 1820",
    "sg:postcode":"52537",
    "sg:province":"IA",
    "sg:tags":[
        "salvage"
    ],
    "sg:website":"www.pipermotors.com",
    "wof:name":"Piper's Auto Salvage",
    "wof:placetype":"venue"
},
  "geometry": {"coordinates":[-92.40959599999999,40.74656],"type":"Point"}
}