{
  "type": "Feature",
  "properties": {
    "addr:full":"4291 NE 6th St Des Moines IA 50313",
    "addr:housenumber":"4291",
    "addr:postcode":"50313",
    "addr:street":"Ne 6Th St",
    "iso:country":"US",
    "sg:address":"4291 NE 6th St",
    "sg:city":"Des Moines",
    "sg:classifiers":[
        {
            "category":"Organizations",
            "subcategory":"Religious Organization",
            "type":"Services"
        }
    ],
    "sg:phone":"+1 515 284 7401",
    "sg:postcode":"50313",
    "sg:province":"IA",
    "sg:tags":[
        "church"
    ],
    "wof:name":"Vietnamese Evangelical Church",
    "wof:placetype":"venue"
},
  "geometry": {"coordinates":[-93.611396,41.636909],"type":"Point"}
}