{
  "type": "Feature",
  "properties": {
    "addr:full":"911 S 5th Ave Marshalltown IA 50158",
    "addr:housenumber":"911",
    "addr:postcode":"50158",
    "addr:street":"S 5Th Ave",
    "iso:country":"US",
    "sg:address":"911 S 5th Ave",
    "sg:city":"Marshalltown",
    "sg:classifiers":[
        {
            "category":"Restaurant",
            "type":"Food & Drink"
        }
    ],
    "sg:phone":"+1 641 752 8385",
    "sg:postcode":"50158",
    "sg:province":"IA",
    "sg:tags":[
        "eating"
    ],
    "wof:name":"Dog House Quilting",
    "wof:placetype":"venue"
},
  "geometry": {"coordinates":[-92.904832,42.037986],"type":"Point"}
}