{
  "type": "Feature",
  "properties": {
    "iso:country":"US",
    "sg:address":"205 E Gilman St",
    "sg:city":"Sheffield",
    "sg:classifiers":[
        {
            "category":"Freight",
            "type":"Transportation"
        }
    ],
    "sg:phone":"+1 641 892 4229",
    "sg:postcode":"50475",
    "sg:province":"IA",
    "sg:tags":[
        "grain",
        "elevator"
    ],
    "sg:website":"www.agvantage.com",
    "wof:name":"Agvantage Fs Inc",
    "wof:placetype":"venue"
},
  "geometry": {"coordinates":[-93.210047,42.893183],"type":"Point"}
}