{
  "type": "Feature",
  "properties": {
    "addr:full":"525 S Portland St Bancroft IA 50517",
    "addr:housenumber":"525",
    "addr:postcode":"50517",
    "addr:street":"S Portland St",
    "iso:country":"US",
    "sg:address":"525 S Portland St",
    "sg:city":"Bancroft",
    "sg:classifiers":[
        {
            "category":"Health Services",
            "subcategory":"Doctor",
            "type":"Services"
        }
    ],
    "sg:phone":"+1 515 885 0009",
    "sg:postcode":"50517",
    "sg:province":"IA",
    "sg:tags":[
        "physician",
        "surgeon"
    ],
    "wof:name":"Tigges Merle Dr & Ke",
    "wof:placetype":"venue"
},
  "geometry": {"coordinates":[-94.218002,43.287157],"type":"Point"}
}