{
  "type": "Feature",
  "properties": {
    "iso:country":"US",
    "sg:address":"615 S Main St",
    "sg:city":"Monticello",
    "sg:classifiers":[
        {
            "category":"Shopping",
            "subcategory":"Used Merchandise",
            "type":"Retail Goods"
        }
    ],
    "sg:phone":"+1 319 465 3609",
    "sg:postcode":"52310",
    "sg:province":"IA",
    "sg:tags":[
        "antique"
    ],
    "wof:name":"Box-N-Bucket",
    "wof:placetype":"venue"
},
  "geometry": {"coordinates":[-91.185805,42.233081],"type":"Point"}
}