{
  "type": "Feature",
  "properties": {
    "iso:country":"US",
    "sg:address":"107 Main St",
    "sg:city":"Fort Atkinson",
    "sg:classifiers":[
        {
            "category":"Government",
            "subcategory":"Post Office",
            "type":"Public Place"
        }
    ],
    "sg:phone":"+1 563 534 7246",
    "sg:postcode":"52132",
    "sg:province":"IA",
    "wof:name":"US Post Office",
    "wof:placetype":"venue"
},
  "geometry": {"coordinates":[-91.932722,43.143472],"type":"Point"}
}