{
  "type": "Feature",
  "properties": {
    "addr:full":"1621 N Elm St Ottumwa IA 52501",
    "addr:housenumber":"1621",
    "addr:postcode":"52501",
    "addr:street":"N Elm St",
    "iso:country":"US",
    "sg:address":"1621 N Elm St",
    "sg:city":"Ottumwa",
    "sg:classifiers":[
        {
            "category":"Building & Trades",
            "subcategory":"Construction",
            "type":"Services"
        }
    ],
    "sg:phone":"+1 641 684 7886",
    "sg:postcode":"52501",
    "sg:province":"IA",
    "sg:tags":[
        "contractor"
    ],
    "wof:name":"Process Contracting Inc",
    "wof:placetype":"venue"
},
  "geometry": {"coordinates":[-92.39729800000001,41.035483],"type":"Point"}
}