{
  "type": "Feature",
  "properties": {
    "addr:full":"5831 Grundy Rd Hudson IA 50643",
    "addr:housenumber":"5831",
    "addr:postcode":"50643",
    "addr:street":"Grundy Rd",
    "iso:country":"US",
    "sg:address":"5831 Grundy Rd",
    "sg:city":"Hudson",
    "sg:classifiers":[
        {
            "category":"Organizations",
            "subcategory":"Religious Organization",
            "type":"Services"
        }
    ],
    "sg:phone":"+1 319 988 3967",
    "sg:postcode":"50643",
    "sg:province":"IA",
    "sg:tags":[
        "church"
    ],
    "wof:name":"Zion Lutheran Church",
    "wof:placetype":"venue"
},
  "geometry": {"coordinates":[-92.533897,42.429163],"type":"Point"}
}