{
  "type": "Feature",
  "properties": {
    "iso:country":"US",
    "sg:address":"113 N Federal Ave",
    "sg:city":"Mason City",
    "sg:classifiers":[
        {
            "category":"Insurance",
            "subcategory":"Insurance Agent",
            "type":"Services"
        }
    ],
    "sg:phone":"+1 641 424 2424",
    "sg:postcode":"50401",
    "sg:province":"IA",
    "wof:name":"Commercial Federal Ins Corp",
    "wof:placetype":"venue"
},
  "geometry": {"coordinates":[-93.200973,43.153512],"type":"Point"}
}