{
  "type": "Feature",
  "properties": {
    "addr:full":"401 5th St Parkersburg IA 50665",
    "addr:housenumber":"401",
    "addr:postcode":"50665",
    "addr:street":"5Th St",
    "iso:country":"US",
    "sg:address":"401 5th St",
    "sg:city":"Parkersburg",
    "sg:classifiers":[
        {
            "category":"Recreation",
            "type":"Entertainment"
        }
    ],
    "sg:phone":"+1 319 346 1461",
    "sg:postcode":"50665",
    "sg:province":"IA",
    "sg:tags":[
        "attraction",
        "tourist"
    ],
    "wof:name":"Parkersburg Historical Home",
    "wof:placetype":"venue"
},
  "geometry": {"coordinates":[-92.78972899999999,42.576409],"type":"Point"}
}