{
  "type": "Feature",
  "properties": {
    "iso:country":"US",
    "sg:address":"819 3rd Ave",
    "sg:city":"Sheldon",
    "sg:classifiers":[
        {
            "category":"Insurance",
            "subcategory":"Insurance Agent",
            "type":"Services"
        }
    ],
    "sg:phone":"+1 712 324 4049",
    "sg:postcode":"51201",
    "sg:province":"IA",
    "wof:name":"AFLAC",
    "wof:placetype":"venue"
},
  "geometry": {"coordinates":[-95.85440699999999,43.181745],"type":"Point"}
}