{
  "type": "Feature",
  "properties": {
    "iso:country":"US",
    "sg:address":"704 W Jefferson St",
    "sg:city":"Bloomfield",
    "sg:classifiers":[
        {
            "category":"Retail",
            "subcategory":"Car Wash",
            "type":"Services"
        }
    ],
    "sg:phone":"+1 641 664 9500",
    "sg:postcode":"52537",
    "sg:province":"IA",
    "sg:tags":[
        "carwash"
    ],
    "wof:name":"West Side Car Wash",
    "wof:placetype":"venue"
},
  "geometry": {"coordinates":[-92.42388200000001,40.751338],"type":"Point"}
}