{
  "type": "Feature",
  "properties": {
    "iso:country":"US",
    "sg:address":"2109 S Glass St",
    "sg:city":"Sioux City",
    "sg:classifiers":[
        {
            "category":"Professional",
            "subcategory":"Business Services",
            "type":"Services"
        }
    ],
    "sg:phone":"+1 712 276 3350",
    "sg:postcode":"51106",
    "sg:province":"IA",
    "wof:name":"Walker Kathy",
    "wof:placetype":"venue"
},
  "geometry": {"coordinates":[-96.362375,42.468561],"type":"Point"}
}