{
  "type": "Feature",
  "properties": {
    "iso:country":"US",
    "sg:address":"1735 11th St NW",
    "sg:city":"Cedar Rapids",
    "sg:classifiers":[
        {
            "category":"Organizations",
            "subcategory":"Community Association",
            "type":"Services"
        }
    ],
    "sg:phone":"+1 319 363 5215",
    "sg:postcode":"52405",
    "sg:province":"IA",
    "sg:tags":[
        "fraternal"
    ],
    "wof:name":"Fraternal Order Of Eagles",
    "wof:placetype":"venue"
},
  "geometry": {"coordinates":[-91.687051,41.991661],"type":"Point"}
}