{
  "type": "Feature",
  "properties": {
    "iso:country":"US",
    "sg:address":"3001 Raven St",
    "sg:city":"Iowa City",
    "sg:classifiers":[
        {
            "category":"Building & Trades",
            "subcategory":"Construction",
            "type":"Services"
        }
    ],
    "sg:phone":"+1 319 337 3972",
    "sg:postcode":"52245",
    "sg:province":"IA",
    "sg:tags":[
        "hanging",
        "contractor"
    ],
    "wof:name":"Carter Painting Inc",
    "wof:placetype":"venue"
},
  "geometry": {"coordinates":[-91.486474,41.656021],"type":"Point"}
}