{
  "type": "Feature",
  "properties": {
    "iso:country":"US",
    "sg:address":"409 W Sheridan Ave",
    "sg:city":"Shenandoah",
    "sg:classifiers":[
        {
            "category":"Shopping",
            "type":"Retail Goods"
        }
    ],
    "sg:phone":"+1 712 246 1623",
    "sg:postcode":"51601",
    "sg:province":"IA",
    "sg:tags":[
        "merchandise",
        "monument"
    ],
    "wof:name":"Clinton L Allen Monuments Inc",
    "wof:placetype":"venue"
},
  "geometry": {"coordinates":[-95.371143,40.766022],"type":"Point"}
}