{
  "type": "Feature",
  "properties": {
    "iso:country":"US",
    "sg:address":"2112 15th St",
    "sg:city":"Spirit Lake",
    "sg:classifiers":[
        {
            "category":"Wholesale",
            "subcategory":"Machinery & Supplies",
            "type":"Manufacturing & Wholesale Goods"
        }
    ],
    "sg:phone":"+1 712 332 2893",
    "sg:postcode":"51360",
    "sg:province":"IA",
    "sg:tags":[
        "hoist"
    ],
    "wof:name":"Luhrs Lake Svc",
    "wof:placetype":"venue"
},
  "geometry": {"coordinates":[-95.12317299999999,43.425705],"type":"Point"}
}