{
  "type": "Feature",
  "properties": {
    "iso:country":"US",
    "sg:address":"518 W Locust St",
    "sg:city":"Davenport",
    "sg:classifiers":[
        {
            "category":"Education",
            "subcategory":"Library",
            "type":"Public Place"
        }
    ],
    "sg:phone":"+1 563 333 6245",
    "sg:postcode":"52803",
    "sg:province":"IA",
    "wof:name":"O'Keefe Library",
    "wof:placetype":"venue"
},
  "geometry": {"coordinates":[-90.58260900000001,41.538354],"type":"Point"}
}