{
  "type": "Feature",
  "properties": {
    "addr:full":"139 NE Broadway Ave Des Moines IA 50313",
    "addr:housenumber":"139",
    "addr:postcode":"50313",
    "addr:street":"Ne Broadway Ave",
    "iso:country":"US",
    "sg:address":"139 NE Broadway Ave",
    "sg:city":"Des Moines",
    "sg:classifiers":[
        {
            "category":"Building & Trades",
            "subcategory":"Plumbing",
            "type":"Services"
        }
    ],
    "sg:phone":"+1 515 334 0909",
    "sg:postcode":"50313",
    "sg:province":"IA",
    "sg:tags":[
        "septic"
    ],
    "wof:name":"Capital City Septic",
    "wof:placetype":"venue"
},
  "geometry": {"coordinates":[-93.61748799999999,41.644108],"type":"Point"}
}