{
  "type": "Feature",
  "properties": {
    "iso:country":"US",
    "sg:address":"23860 Territorial Rd",
    "sg:city":"Le Claire",
    "sg:classifiers":[
        {
            "category":"Wholesale",
            "subcategory":"Hardware",
            "type":"Manufacturing & Wholesale Goods"
        }
    ],
    "sg:phone":"+1 563 289 3830",
    "sg:postcode":"52804",
    "sg:province":"IA",
    "wof:name":"Lawson Products Inc",
    "wof:placetype":"venue"
},
  "geometry": {"coordinates":[-90.435056,41.626337],"type":"Point"}
}