{
  "type": "Feature",
  "properties": {
    "addr:full":"402 N 3rd St Polk City IA 50226",
    "addr:housenumber":"402",
    "addr:postcode":"50226",
    "addr:street":"N 3Rd St",
    "iso:country":"US",
    "sg:address":"402 N 3rd St",
    "sg:city":"Polk City",
    "sg:classifiers":[
        {
            "category":"Government",
            "subcategory":"Office",
            "type":"Public Place"
        }
    ],
    "sg:phone":"+1 515 984 6035",
    "sg:postcode":"50226",
    "sg:province":"IA",
    "sg:tags":[
        "executive"
    ],
    "wof:name":"Water Plant",
    "wof:placetype":"venue"
},
  "geometry": {"coordinates":[-93.710595,41.775184],"type":"Point"}
}