{
  "type": "Feature",
  "properties": {
    "iso:country":"US",
    "sg:address":"131 Welch Ave",
    "sg:city":"Ames",
    "sg:classifiers":[
        {
            "category":"Restaurant",
            "type":"Food & Drink"
        }
    ],
    "sg:phone":"+1 515 292 2244",
    "sg:postcode":"50014",
    "sg:province":"IA",
    "wof:name":"Mr Goodcents Subs & Pastas",
    "wof:placetype":"venue"
},
  "geometry": {"coordinates":[-93.650165,42.021875],"type":"Point"}
}