{
  "type": "Feature",
  "properties": {
    "iso:country":"US",
    "sg:address":"724 N Dubuque St",
    "sg:city":"Iowa City",
    "sg:classifiers":[
        {
            "category":"Organizations",
            "subcategory":"Community Association",
            "type":"Services"
        }
    ],
    "sg:phone":"+1 319 351 5639",
    "sg:postcode":"52245",
    "sg:province":"IA",
    "sg:tags":[
        "sorority",
        "fraternity"
    ],
    "wof:name":"Alpha Tau Omega",
    "wof:placetype":"venue"
},
  "geometry": {"coordinates":[-91.532938,41.669132],"type":"Point"}
}