{
  "type": "Feature",
  "properties": {
    "iso:country":"US",
    "sg:address":"1200 Pleasant St",
    "sg:city":"Des Moines",
    "sg:classifiers":[
        {
            "category":"Health Services",
            "subcategory":"Health Practitioner",
            "type":"Services"
        }
    ],
    "sg:phone":"+1 515 241 6700",
    "sg:postcode":"50309",
    "sg:province":"IA",
    "sg:tags":[
        "psychologist"
    ],
    "wof:name":"Dereke Campbell PHD",
    "wof:placetype":"venue"
},
  "geometry": {"coordinates":[-93.63658599999999,41.58986],"type":"Point"}
}