{
  "type": "Feature",
  "properties": {
    "addr:full":"605 2nd St Oakville IA 52646",
    "addr:housenumber":"605",
    "addr:postcode":"52646",
    "addr:street":"2Nd St",
    "iso:country":"US",
    "sg:address":"605 2nd St",
    "sg:city":"Oakville",
    "sg:classifiers":[
        {
            "category":"Government",
            "subcategory":"Fire Station",
            "type":"Public Place"
        }
    ],
    "sg:phone":"+1 319 766 2688",
    "sg:postcode":"52646",
    "sg:province":"IA",
    "sg:tags":[
        "department"
    ],
    "wof:name":"Oakville Fire Department",
    "wof:placetype":"venue"
},
  "geometry": {"coordinates":[-91.043128,41.100074],"type":"Point"}
}