{
  "type": "Feature",
  "properties": {
    "addr:full":"169 Main St Dubuque IA 52001",
    "addr:housenumber":"169",
    "addr:postcode":"52001",
    "addr:street":"Main St",
    "iso:country":"US",
    "sg:address":"169 Main St",
    "sg:city":"Dubuque",
    "sg:classifiers":[
        {
            "category":"Personal",
            "subcategory":"Tattoo Parlor",
            "type":"Services"
        },
        {
            "category":"Personal",
            "subcategory":"Piercing",
            "type":"Services"
        }
    ],
    "sg:phone":"+1 563 589 0169",
    "sg:postcode":"52001",
    "sg:province":"IA",
    "sg:tags":[
        "body"
    ],
    "sg:website":"http://www.mystictattooink.com",
    "wof:name":"Mystic Tattoo",
    "wof:placetype":"venue"
},
  "geometry": {"coordinates":[-90.66431900000001,42.495622],"type":"Point"}
}