{
  "type": "Feature",
  "properties": {
    "addr:full":"3121 Grand Ave Ames IA 50010",
    "addr:housenumber":"3121",
    "addr:postcode":"50010",
    "addr:street":"Grand Ave",
    "iso:country":"US",
    "sg:address":"3121 Grand Ave",
    "sg:city":"Ames",
    "sg:classifiers":[
        {
            "category":"Food & Beverages",
            "subcategory":"Groceries & Convenience Stores",
            "type":"Retail Goods"
        }
    ],
    "sg:phone":"+1 515 232 1226",
    "sg:postcode":"50010",
    "sg:province":"IA",
    "sg:tags":[
        "grocer"
    ],
    "wof:name":"Cub Foods",
    "wof:placetype":"venue"
},
  "geometry": {"coordinates":[-93.620769,42.052868],"type":"Point"}
}