{
  "type": "Feature",
  "properties": {
    "iso:country":"US",
    "sg:address":"1007 S Prospect Dr",
    "sg:city":"Toledo",
    "sg:classifiers":[
        {
            "category":"Recreation",
            "type":"Entertainment"
        }
    ],
    "sg:phone":"+1 641 484 5803",
    "sg:postcode":"52342",
    "sg:province":"IA",
    "sg:tags":[
        "hall",
        "auditorium"
    ],
    "wof:name":"Reinig Community Ctr",
    "wof:placetype":"venue"
},
  "geometry": {"coordinates":[-92.588183,41.988757],"type":"Point"}
}