{
  "type": "Feature",
  "properties": {
    "iso:country":"US",
    "sg:address":"650 Main St",
    "sg:city":"Mediapolis",
    "sg:classifiers":[
        {
            "category":"Insurance",
            "subcategory":"Insurance Agent",
            "type":"Services"
        }
    ],
    "sg:phone":"+1 319 394 3323",
    "sg:postcode":"52637",
    "sg:province":"IA",
    "wof:name":"Breuer Agency Inc",
    "wof:placetype":"venue"
},
  "geometry": {"coordinates":[-91.16357000000001,41.007823],"type":"Point"}
}