{
  "type": "Feature",
  "properties": {
    "addr:full":"1006 Park Ln Ida Grove IA 51445",
    "addr:housenumber":"1006",
    "addr:postcode":"51445",
    "addr:street":"Park Ln",
    "iso:country":"US",
    "sg:address":"1006 Park Ln",
    "sg:city":"Ida Grove",
    "sg:classifiers":[
        {
            "category":"Organizations",
            "subcategory":"Religious Organization",
            "type":"Services"
        }
    ],
    "sg:phone":"+1 712 364 3301",
    "sg:postcode":"51445",
    "sg:province":"IA",
    "sg:tags":[
        "church"
    ],
    "wof:name":"United Methodist Church",
    "wof:placetype":"venue"
},
  "geometry": {"coordinates":[-95.470122,42.335542],"type":"Point"}
}