{
  "type": "Feature",
  "properties": {
    "addr:full":"103 N Main St Conrad IA 50621",
    "addr:housenumber":"103",
    "addr:postcode":"50621",
    "addr:street":"N Main St",
    "iso:country":"US",
    "sg:address":"103 N Main St",
    "sg:city":"Conrad",
    "sg:classifiers":[
        {
            "category":"Home & Garden",
            "subcategory":"Hardware",
            "type":"Retail Goods"
        }
    ],
    "sg:phone":"+1 641 366 2305",
    "sg:postcode":"50621",
    "sg:province":"IA",
    "wof:name":"Kibby's Hardware",
    "wof:placetype":"venue"
},
  "geometry": {"coordinates":[-92.874663,42.225587],"type":"Point"}
}