{
  "type": "Feature",
  "properties": {
    "iso:country":"US",
    "sg:address":"4683 Starling Ave",
    "sg:city":"Paullina",
    "sg:phone":"+1 712 446 2394",
    "sg:postcode":"51046",
    "sg:province":"IA",
    "sg:tags":[
        "farm",
        "corn"
    ],
    "wof:name":"Orville Tewes",
    "wof:placetype":"venue"
},
  "geometry": {"coordinates":[-95.58397100000001,42.970732],"type":"Point"}
}