{
  "type": "Feature",
  "properties": {
    "iso:country":"US",
    "sg:address":"1022 W 5th St",
    "sg:city":"Waterloo",
    "sg:classifiers":[
        {
            "category":"Health Services",
            "subcategory":"Doctor",
            "type":"Services"
        }
    ],
    "sg:phone":"+1 319 226 4104",
    "sg:postcode":"50702",
    "sg:province":"IA",
    "sg:tags":[
        "dentist"
    ],
    "wof:name":"Comfort Dental",
    "wof:placetype":"venue"
},
  "geometry": {"coordinates":[-92.347809,42.487845],"type":"Point"}
}