{
  "type": "Feature",
  "properties": {
    "iso:country":"US",
    "sg:address":"1032 Denmark Hilltop",
    "sg:city":"Fort Madison",
    "sg:classifiers":[
        {
            "category":"Professional",
            "subcategory":"Research",
            "type":"Services"
        }
    ],
    "sg:phone":"+1 319 372 6294",
    "sg:postcode":"52627",
    "sg:province":"IA",
    "sg:tags":[
        "commercial",
        "physical"
    ],
    "wof:name":"Sahdwell Enviromental Prdts",
    "wof:placetype":"venue"
},
  "geometry": {"coordinates":[-91.31505199999999,40.637024],"type":"Point"}
}