{
  "type": "Feature",
  "properties": {
    "addr:full":"1027 5th St NE Sibley IA 51249",
    "addr:housenumber":"1027",
    "addr:postcode":"51249",
    "addr:street":"5Th St Ne",
    "iso:country":"US",
    "sg:address":"1027 5th St NE",
    "sg:city":"Sibley",
    "sg:classifiers":[
        {
            "category":"Farming",
            "subcategory":"Fish & Marine Products",
            "type":"Manufacturing & Wholesale Goods"
        }
    ],
    "sg:phone":"+1 712 754 2655",
    "sg:postcode":"51249",
    "sg:province":"IA",
    "sg:tags":[
        "management"
    ],
    "wof:name":"Dick Strouth Taxidermy",
    "wof:placetype":"venue"
},
  "geometry": {"coordinates":[-95.73880800000001,43.40911],"type":"Point"}
}