{
  "type": "Feature",
  "properties": {
    "iso:country":"US",
    "sg:address":"819 Broad St",
    "sg:city":"Grinnell",
    "sg:classifiers":[
        {
            "category":"Banks & Credit Unions",
            "subcategory":"Bank",
            "type":"Services"
        }
    ],
    "sg:phone":"+1 641 236 8822",
    "sg:postcode":"50112",
    "sg:province":"IA",
    "sg:tags":[
        "state"
    ],
    "wof:name":"University Iowa Cmnty Cr Unio",
    "wof:placetype":"venue"
},
  "geometry": {"coordinates":[-92.724194,41.743163],"type":"Point"}
}