{
  "type": "Feature",
  "properties": {
    "iso:country":"US",
    "sg:address":"700 College Dr",
    "sg:city":"Decorah",
    "sg:classifiers":[
        {
            "category":"Education",
            "subcategory":"College",
            "type":"Public Place"
        }
    ],
    "sg:phone":"+1 563 387 2000",
    "sg:postcode":"52101",
    "sg:province":"IA",
    "sg:tags":[
        "academic",
        "school"
    ],
    "sg:website":"www.luther.edu",
    "wof:name":"LUTHER College",
    "wof:placetype":"venue"
},
  "geometry": {"coordinates":[-91.798996,43.312545],"type":"Point"}
}