{
  "type": "Feature",
  "properties": {
    "iso:country":"US",
    "sg:address":"124 3rd St SW",
    "sg:city":"Orange City",
    "sg:classifiers":[
        {
            "category":"Personal",
            "subcategory":"Barber",
            "type":"Services"
        }
    ],
    "sg:phone":"+1 712 737 6433",
    "sg:postcode":"51041",
    "sg:province":"IA",
    "wof:name":"Barbershop",
    "wof:placetype":"venue"
},
  "geometry": {"coordinates":[-96.059392,43.003936],"type":"Point"}
}