{
  "type": "Feature",
  "properties": {
    "iso:country":"US",
    "sg:address":"3925 340th St",
    "sg:city":"Boyden",
    "sg:phone":"+1 712 725 2400",
    "sg:postcode":"51234",
    "sg:province":"IA",
    "sg:tags":[
        "farm",
        "corn"
    ],
    "wof:name":"Creswell Ceil",
    "wof:placetype":"venue"
},
  "geometry": {"coordinates":[-96.014826,43.156829],"type":"Point"}
}