{
  "type": "Feature",
  "properties": {
    "iso:country":"US",
    "sg:address":"315 7th Ave",
    "sg:city":"Wellman",
    "sg:classifiers":[
        {
            "category":"Retail",
            "subcategory":"Repair Shop",
            "type":"Services"
        }
    ],
    "sg:phone":"+1 319 646 2813",
    "sg:postcode":"52356",
    "sg:province":"IA",
    "sg:tags":[
        "repairing",
        "piano",
        "refinishing"
    ],
    "wof:name":"Mc Clellen Piano Tuning",
    "wof:placetype":"venue"
},
  "geometry": {"coordinates":[-91.83672799999999,41.465841],"type":"Point"}
}