{
  "type": "Feature",
  "properties": {
    "iso:country":"US",
    "sg:address":"2303 E 53rd St",
    "sg:city":"Davenport",
    "sg:classifiers":[
        {
            "category":"Retail",
            "subcategory":"Laundry & Dry Cleaning",
            "type":"Services"
        }
    ],
    "sg:phone":"+1 563 344 4220",
    "sg:postcode":"52807",
    "sg:province":"IA",
    "sg:tags":[
        "cleaners"
    ],
    "wof:name":"Burke Cleaners-Home Of Mr Neat",
    "wof:placetype":"venue"
},
  "geometry": {"coordinates":[-90.544191,41.574682],"type":"Point"}
}