{
  "type": "Feature",
  "properties": {
    "iso:country":"US",
    "sg:address":"1647 Michigan Ave",
    "sg:city":"Livermore",
    "sg:phone":"+1 515 332 2719",
    "sg:postcode":"50558",
    "sg:province":"IA",
    "sg:tags":[
        "farm",
        "soybean"
    ],
    "wof:name":"Ron Thompson",
    "wof:placetype":"venue"
},
  "geometry": {"coordinates":[-94.19827100000001,42.815955],"type":"Point"}
}