{
  "type": "Feature",
  "properties": {
    "iso:country":"US",
    "sg:address":"21987 250th St",
    "sg:city":"Elkader",
    "sg:classifiers":[
        {
            "category":"Farming",
            "subcategory":"Livestock Farm",
            "type":"Manufacturing & Wholesale Goods"
        }
    ],
    "sg:phone":"+1 563 245 1341",
    "sg:postcode":"52043",
    "sg:province":"IA",
    "sg:tags":[
        "beef",
        "feedlot",
        "cattle"
    ],
    "wof:name":"Dwane Hoth",
    "wof:placetype":"venue"
},
  "geometry": {"coordinates":[-91.370355,42.866548],"type":"Point"}
}