{
  "type": "Feature",
  "properties": {
    "iso:country":"US",
    "sg:address":"105 W 76th St",
    "sg:city":"Davenport",
    "sg:classifiers":[
        {
            "category":"Banks & Credit Unions",
            "subcategory":"Investment Brokerage",
            "type":"Services"
        }
    ],
    "sg:phone":"+1 563 322 4429",
    "sg:postcode":"52806",
    "sg:province":"IA",
    "sg:tags":[
        "consultant",
        "planning",
        "financial"
    ],
    "wof:name":"Sellers & Associates",
    "wof:placetype":"venue"
},
  "geometry": {"coordinates":[-90.57519000000001,41.593854],"type":"Point"}
}