{
  "type": "Feature",
  "properties": {
    "addr:full":"1309 57th St Des Moines IA 50311",
    "addr:housenumber":"1309",
    "addr:postcode":"50311",
    "addr:street":"57Th St",
    "iso:country":"US",
    "sg:address":"1309 57th St",
    "sg:city":"Des Moines",
    "sg:classifiers":[
        {
            "category":"Shopping",
            "subcategory":"Bicycles & Sporting Goods",
            "type":"Retail Goods"
        }
    ],
    "sg:phone":"+1 515 255 0283",
    "sg:postcode":"50311",
    "sg:province":"IA",
    "sg:tags":[
        "tackle",
        "fishing"
    ],
    "wof:name":"Bite's Rod & Reel Repair",
    "wof:placetype":"venue"
},
  "geometry": {"coordinates":[-93.69532100000001,41.602091],"type":"Point"}
}