{
  "type": "Feature",
  "properties": {
    "iso:country":"US",
    "sg:address":"3917 Greenview Dr",
    "sg:city":"Urbandale",
    "sg:classifiers":[
        {
            "category":"Real Estate",
            "subcategory":"Developer",
            "type":"Services"
        }
    ],
    "sg:phone":"+1 515 238 3692",
    "sg:postcode":"50322",
    "sg:province":"IA",
    "sg:tags":[
        "consultant"
    ],
    "wof:name":"Cody Road Development LLC",
    "wof:placetype":"venue"
},
  "geometry": {"coordinates":[-93.746757,41.635314],"type":"Point"}
}