{
  "type": "Feature",
  "properties": {
    "addr:full":"800 N Main St Donnellson IA 52625",
    "addr:housenumber":"800",
    "addr:postcode":"52625",
    "addr:street":"N Main St",
    "iso:country":"US",
    "sg:address":"800 N Main St",
    "sg:city":"Donnellson",
    "sg:classifiers":[
        {
            "category":"Real Estate",
            "subcategory":"Real Estate Operator",
            "type":"Services"
        }
    ],
    "sg:phone":"+1 319 627 2626",
    "sg:postcode":"52625",
    "sg:province":"IA",
    "sg:tags":[
        "apartment"
    ],
    "wof:name":"Senior Donnellson Housing Inc",
    "wof:placetype":"venue"
},
  "geometry": {"coordinates":[-91.564453,40.646282],"type":"Point"}
}