{
  "type": "Feature",
  "properties": {
    "iso:country":"US",
    "sg:address":"102 S Main St",
    "sg:city":"Elkader",
    "sg:classifiers":[
        {
            "category":"Shopping",
            "type":"Retail Goods"
        }
    ],
    "sg:phone":"+1 563 245 3500",
    "sg:postcode":"52043",
    "sg:province":"IA",
    "sg:tags":[
        "art",
        "gallery",
        "dealer"
    ],
    "wof:name":"Witts Custom Framing",
    "wof:placetype":"venue"
},
  "geometry": {"coordinates":[-91.404489,42.854484],"type":"Point"}
}