{
  "type": "Feature",
  "properties": {
    "iso:country":"US",
    "sg:address":"12 N 21st St",
    "sg:city":"Fort Dodge",
    "sg:classifiers":[
        {
            "category":"Wholesale",
            "subcategory":"Machinery & Supplies",
            "type":"Manufacturing & Wholesale Goods"
        }
    ],
    "sg:phone":"+1 515 576 7161",
    "sg:postcode":"50501",
    "sg:province":"IA",
    "sg:tags":[
        "farm",
        "equipment"
    ],
    "wof:name":"Brokaw Supply Co",
    "wof:placetype":"venue"
},
  "geometry": {"coordinates":[-94.16953100000001,42.507269],"type":"Point"}
}