{
  "type": "Feature",
  "properties": {
    "iso:country":"US",
    "sg:address":"206 Main St",
    "sg:city":"Van Horne",
    "sg:classifiers":[
        {
            "category":"Professional",
            "subcategory":"Business Services",
            "type":"Services"
        }
    ],
    "sg:phone":"+1 319 228 8855",
    "sg:postcode":"52346",
    "sg:province":"IA",
    "sg:tags":[
        "telemarketing"
    ],
    "wof:name":"Ikan Marketing",
    "wof:placetype":"venue"
},
  "geometry": {"coordinates":[-92.091194,42.008654],"type":"Point"}
}