{
  "type": "Feature",
  "properties": {
    "iso:country":"US",
    "sg:address":"6788 Wapello Ave SE",
    "sg:city":"Nichols",
    "sg:classifiers":[
        {
            "category":"Farming",
            "subcategory":"Farm & Veterinary Services",
            "type":"Manufacturing & Wholesale Goods"
        }
    ],
    "sg:phone":"+1 319 629 4242",
    "sg:postcode":"52766",
    "sg:province":"IA",
    "wof:name":"Railridge Inc",
    "wof:placetype":"venue"
},
  "geometry": {"coordinates":[-91.387788,41.438557],"type":"Point"}
}