{
  "type": "Feature",
  "properties": {
    "iso:country":"US",
    "sg:address":"2720 1st Ave NE",
    "sg:city":"Cedar Rapids",
    "sg:classifiers":[
        {
            "category":"Professional",
            "subcategory":"Management & Consulting",
            "type":"Services"
        }
    ],
    "sg:phone":"+1 319 369 0517",
    "sg:postcode":"52402",
    "sg:province":"IA",
    "sg:tags":[
        "consultant",
        "industrial"
    ],
    "wof:name":"Industrial Support Svc",
    "wof:placetype":"venue"
},
  "geometry": {"coordinates":[-91.634863,42.004772],"type":"Point"}
}