{
  "type": "Feature",
  "properties": {
    "iso:country":"US",
    "sg:address":"808 Elm St",
    "sg:city":"Atlantic",
    "sg:classifiers":[
        {
            "category":"Freight",
            "type":"Transportation"
        }
    ],
    "sg:phone":"+1 712 243 6768",
    "sg:postcode":"50022",
    "sg:province":"IA",
    "sg:tags":[
        "operator",
        "trucking"
    ],
    "wof:name":"Larry Sellers",
    "wof:placetype":"venue"
},
  "geometry": {"coordinates":[-95.01022500000001,41.402903],"type":"Point"}
}