{
  "type": "Feature",
  "properties": {
    "addr:full":"104 W Jayne St Lone Tree IA 52755",
    "addr:housenumber":"104",
    "addr:postcode":"52755",
    "addr:street":"W Jayne St",
    "iso:country":"US",
    "sg:address":"104 W Jayne St",
    "sg:city":"Lone Tree",
    "sg:classifiers":[
        {
            "category":"Insurance",
            "subcategory":"Insurance Agent",
            "type":"Services"
        }
    ],
    "sg:phone":"+1 319 629 4922",
    "sg:postcode":"52755",
    "sg:province":"IA",
    "wof:name":"Young Insurance",
    "wof:placetype":"venue"
},
  "geometry": {"coordinates":[-91.42762999999999,41.487306],"type":"Point"}
}