{
  "type": "Feature",
  "properties": {
    "addr:full":"101 S Dubuque St Iowa City IA 52240",
    "addr:housenumber":"101",
    "addr:postcode":"52240",
    "addr:street":"S Dubuque St",
    "iso:country":"US",
    "sg:address":"101 S Dubuque St",
    "sg:city":"Iowa City",
    "sg:classifiers":[
        {
            "category":"Shopping",
            "subcategory":"Jewelry",
            "type":"Retail Goods"
        }
    ],
    "sg:phone":"+1 319 338 4212",
    "sg:postcode":"52240",
    "sg:province":"IA",
    "sg:tags":[
        "jeweler"
    ],
    "sg:website":"www.herteenandstockerjewelers.com",
    "wof:name":"Herteen & Stocker Jewelers",
    "wof:placetype":"venue"
},
  "geometry": {"coordinates":[-91.533147,41.657865],"type":"Point"}
}