{
  "type": "Feature",
  "properties": {
    "iso:country":"US",
    "sg:address":"108 W 6th St",
    "sg:city":"Carroll",
    "sg:classifiers":[
        {
            "category":"Real Estate",
            "subcategory":"Real Estate Agent",
            "type":"Services"
        }
    ],
    "sg:phone":"+1 712 792 5560",
    "sg:postcode":"51401",
    "sg:province":"IA",
    "sg:tags":[
        "authorities",
        "housing"
    ],
    "wof:name":"Regional Housing Authority",
    "wof:placetype":"venue"
},
  "geometry": {"coordinates":[-94.868594,42.066036],"type":"Point"}
}