{
  "type": "Feature",
  "properties": {
    "iso:country":"US",
    "sg:address":"4411 F St",
    "sg:city":"Amana",
    "sg:classifiers":[
        {
            "category":"Building & Trades",
            "subcategory":"Construction",
            "type":"Services"
        }
    ],
    "sg:phone":"+1 319 981 3845",
    "sg:postcode":"52203",
    "sg:province":"IA",
    "sg:tags":[
        "general",
        "contractor"
    ],
    "wof:name":"Village Construction",
    "wof:placetype":"venue"
},
  "geometry": {"coordinates":[-91.87159699999999,41.801818],"type":"Point"}
}