{
  "type": "Feature",
  "properties": {
    "iso:country":"US",
    "sg:address":"420 North St",
    "sg:city":"Tipton",
    "sg:classifiers":[
        {
            "category":"Freight",
            "type":"Transportation"
        }
    ],
    "sg:phone":"+1 563 886 2739",
    "sg:postcode":"52772",
    "sg:province":"IA",
    "sg:tags":[
        "operator",
        "trucking"
    ],
    "wof:name":"Lukemyres Trucking",
    "wof:placetype":"venue"
},
  "geometry": {"coordinates":[-91.12320699999999,41.77918],"type":"Point"}
}