{
  "type": "Feature",
  "properties": {
    "iso:country":"US",
    "sg:address":"402 4th St",
    "sg:city":"Ireton",
    "sg:classifiers":[
        {
            "category":"Government",
            "subcategory":"Office",
            "type":"Public Place"
        }
    ],
    "sg:phone":"+1 712 278 2054",
    "sg:postcode":"51027",
    "sg:province":"IA",
    "sg:tags":[
        "village"
    ],
    "wof:name":"Ireton Community Ctr",
    "wof:placetype":"venue"
},
  "geometry": {"coordinates":[-96.318247,42.974913],"type":"Point"}
}