{
  "type": "Feature",
  "properties": {
    "iso:country":"US",
    "sg:address":"109 Pine St",
    "sg:city":"Muscatine",
    "sg:classifiers":[
        {
            "category":"Manufacturing",
            "subcategory":"Tools & Machinery",
            "type":"Manufacturing & Wholesale Goods"
        }
    ],
    "sg:phone":"+1 563 263 5221",
    "sg:postcode":"52761",
    "sg:province":"IA",
    "sg:tags":[
        "machine",
        "shop"
    ],
    "wof:name":"Schmarje Machine Co",
    "wof:placetype":"venue"
},
  "geometry": {"coordinates":[-91.047752,41.420078],"type":"Point"}
}