{
  "type": "Feature",
  "properties": {
    "iso:country":"US",
    "sg:address":"3917 E 14th St",
    "sg:city":"Des Moines",
    "sg:classifiers":[
        {
            "category":"Restaurant",
            "type":"Food & Drink"
        }
    ],
    "sg:menulink":"http://www.allmenus.com/ia/lee/158450-arbys/menu/",
    "sg:phone":"+1 515 266 8853",
    "sg:postcode":"50313",
    "sg:province":"IA",
    "sg:tags":[
        "burger",
        "american"
    ],
    "wof:name":"Arby's",
    "wof:placetype":"venue"
},
  "geometry": {"coordinates":[-93.600447,41.631751],"type":"Point"}
}