{
  "type": "Feature",
  "properties": {
    "addr:full":"3470 350th St Auburn IA 51433",
    "addr:housenumber":"3470",
    "addr:postcode":"51433",
    "addr:street":"350Th St",
    "iso:country":"US",
    "sg:address":"3470 350th St",
    "sg:city":"Auburn",
    "sg:classifiers":[
        {
            "category":"Farming",
            "subcategory":"Livestock Farm",
            "type":"Manufacturing & Wholesale Goods"
        }
    ],
    "sg:phone":"+1 712 688 7771",
    "sg:postcode":"51433",
    "sg:province":"IA",
    "sg:tags":[
        "hog",
        "corn",
        "or",
        "feedlot"
    ],
    "wof:name":"Doug Sturm",
    "wof:placetype":"venue"
},
  "geometry": {"coordinates":[-94.900678,42.281878],"type":"Point"}
}