{
  "type": "Feature",
  "properties": {
    "iso:country":"US",
    "sg:address":"4813 Crestmoor Dr",
    "sg:city":"Des Moines",
    "sg:classifiers":[
        {
            "category":"Shopping",
            "subcategory":"Computers & Home Electronics",
            "type":"Retail Goods"
        }
    ],
    "sg:phone":"+1 515 727 4009",
    "sg:postcode":"50310",
    "sg:province":"IA",
    "sg:tags":[
        "software"
    ],
    "wof:name":"Tucker Ware",
    "wof:placetype":"venue"
},
  "geometry": {"coordinates":[-93.680834,41.641747],"type":"Point"}
}