{
  "type": "Feature",
  "properties": {
    "addr:full":"238 Center St Elgin IA 52141",
    "addr:housenumber":"238",
    "addr:postcode":"52141",
    "addr:street":"Center St",
    "iso:country":"US",
    "sg:address":"238 Center St",
    "sg:city":"Elgin",
    "sg:classifiers":[
        {
            "category":"Government",
            "subcategory":"Post Office",
            "type":"Public Place"
        }
    ],
    "sg:phone":"+1 563 426 5626",
    "sg:postcode":"52141",
    "sg:province":"IA",
    "wof:name":"US Post Office",
    "wof:placetype":"venue"
},
  "geometry": {"coordinates":[-91.628051,42.957405],"type":"Point"}
}