{
  "type": "Feature",
  "properties": {
    "iso:country":"US",
    "sg:address":"101 E Jackson St",
    "sg:city":"Corydon",
    "sg:classifiers":[
        {
            "category":"Retail",
            "subcategory":"Auto Repair",
            "type":"Services"
        }
    ],
    "sg:phone":"+1 641 872 2338",
    "sg:postcode":"50060",
    "sg:province":"IA",
    "sg:tags":[
        "repairing",
        "automobile"
    ],
    "wof:name":"Rod's Auto Svc",
    "wof:placetype":"venue"
},
  "geometry": {"coordinates":[-93.31723700000001,40.758441],"type":"Point"}
}