{
  "type": "Feature",
  "properties": {
    "addr:full":"213 N Andrew St Mediapolis IA 52637",
    "addr:housenumber":"213",
    "addr:postcode":"52637",
    "addr:street":"N Andrew St",
    "iso:country":"US",
    "sg:address":"213 N Andrew St",
    "sg:city":"Mediapolis",
    "sg:classifiers":[
        {
            "category":"Wholesale",
            "subcategory":"Hardware",
            "type":"Manufacturing & Wholesale Goods"
        }
    ],
    "sg:phone":"+1 319 394 3615",
    "sg:postcode":"52637",
    "sg:province":"IA",
    "sg:tags":[
        "purifying",
        "cleaning",
        "air"
    ],
    "wof:name":"Cling's & Assoc",
    "wof:placetype":"venue"
},
  "geometry": {"coordinates":[-91.166546,41.00938],"type":"Point"}
}