{
  "type": "Feature",
  "properties": {
    "addr:full":"1434 Gabriel Ave Mount Pleasant IA 52641",
    "addr:housenumber":"1434",
    "addr:postcode":"52641",
    "addr:street":"Gabriel Ave",
    "iso:country":"US",
    "sg:address":"1434 Gabriel Ave",
    "sg:city":"Mount Pleasant",
    "sg:classifiers":[
        {
            "category":"Farming",
            "subcategory":"Farm",
            "type":"Manufacturing & Wholesale Goods"
        }
    ],
    "sg:phone":"+1 319 256 4661",
    "sg:postcode":"52641",
    "sg:province":"IA",
    "sg:tags":[
        "operator",
        "general",
        "commercial",
        "crop",
        "trucking"
    ],
    "wof:name":"Gillespie Farm",
    "wof:placetype":"venue"
},
  "geometry": {"coordinates":[-91.620586,41.098732],"type":"Point"}
}