{
  "type": "Feature",
  "properties": {
    "addr:full":"18297 Lincoln Rd Fayette IA 52142",
    "addr:housenumber":"18297",
    "addr:postcode":"52142",
    "addr:street":"Lincoln Rd",
    "iso:country":"US",
    "sg:address":"18297 Lincoln Rd",
    "sg:city":"Fayette",
    "sg:classifiers":[
        {
            "category":"Freight",
            "type":"Transportation"
        }
    ],
    "sg:phone":"+1 563 425 3219",
    "sg:postcode":"52142",
    "sg:province":"IA",
    "sg:tags":[
        "operator",
        "trucking"
    ],
    "wof:name":"Doug Kiel Trucking",
    "wof:placetype":"venue"
},
  "geometry": {"coordinates":[-91.810194,42.897908],"type":"Point"}
}