{
  "type": "Feature",
  "properties": {
    "addr:full":"527 S Riverside Dr Iowa City IA 52246",
    "addr:housenumber":"527",
    "addr:postcode":"52246",
    "addr:street":"S Riverside Dr",
    "iso:country":"US",
    "sg:address":"527 S Riverside Dr",
    "sg:city":"Iowa City",
    "sg:classifiers":[
        {
            "category":"Shopping",
            "type":"Retail Goods"
        }
    ],
    "sg:phone":"+1 319 356 0959",
    "sg:postcode":"52246",
    "sg:province":"IA",
    "sg:tags":[
        "picture",
        "frame"
    ],
    "wof:name":"Claim To Frame Art Gallery",
    "wof:placetype":"venue"
},
  "geometry": {"coordinates":[-91.54044399999999,41.653665],"type":"Point"}
}