{
  "type": "Feature",
  "properties": {
    "addr:full":"410 Main St Ames IA 50010",
    "addr:housenumber":"410",
    "addr:postcode":"50010",
    "addr:street":"Main St",
    "iso:country":"US",
    "sg:address":"410 Main St",
    "sg:city":"Ames",
    "sg:classifiers":[
        {
            "category":"Shopping",
            "subcategory":"Computers & Home Electronics",
            "type":"Retail Goods"
        }
    ],
    "sg:phone":"+1 515 232 3040",
    "sg:postcode":"50010",
    "sg:province":"IA",
    "sg:tags":[
        "equipment",
        "dealer"
    ],
    "wof:name":"Vanguard Computer Systems",
    "wof:placetype":"venue"
},
  "geometry": {"coordinates":[-93.61676,42.024982],"type":"Point"}
}