{
  "type": "Feature",
  "properties": {
    "iso:country":"US",
    "sg:address":"205 6th St NE",
    "sg:city":"Primghar",
    "sg:phone":"+1 712 957 0965",
    "sg:postcode":"51245",
    "sg:province":"IA",
    "sg:tags":[
        "farm",
        "corn"
    ],
    "wof:name":"Dennis Magnussen",
    "wof:placetype":"venue"
},
  "geometry": {"coordinates":[-95.62544,43.091707],"type":"Point"}
}