{
  "type": "Feature",
  "properties": {
    "iso:country":"US",
    "sg:address":"506 W Lowell Ave",
    "sg:city":"Shenandoah",
    "sg:classifiers":[
        {
            "category":"Manufacturing",
            "subcategory":"Printing",
            "type":"Manufacturing & Wholesale Goods"
        }
    ],
    "sg:phone":"+1 712 246 3451",
    "sg:postcode":"51601",
    "sg:province":"IA",
    "sg:tags":[
        "commercial"
    ],
    "wof:name":"World Printing Co",
    "wof:placetype":"venue"
},
  "geometry": {"coordinates":[-95.371286,40.766789],"type":"Point"}
}