{
  "type": "Feature",
  "properties": {
    "addr:full":"712 Jefferson St Burlington IA 52601",
    "addr:housenumber":"712",
    "addr:postcode":"52601",
    "addr:street":"Jefferson St",
    "iso:country":"US",
    "sg:address":"712 Jefferson St",
    "sg:city":"Burlington",
    "sg:classifiers":[
        {
            "category":"Wholesale",
            "subcategory":"Machinery & Supplies",
            "type":"Manufacturing & Wholesale Goods"
        }
    ],
    "sg:phone":"+1 319 752 2788",
    "sg:postcode":"52601",
    "sg:province":"IA",
    "sg:tags":[
        "janitor"
    ],
    "wof:name":"Five Flags Co",
    "wof:placetype":"venue"
},
  "geometry": {"coordinates":[-91.108304,40.811116],"type":"Point"}
}