{
  "type": "Feature",
  "properties": {
    "addr:full":"16465 585th Ave Story City IA 50248",
    "addr:housenumber":"16465",
    "addr:postcode":"50248",
    "addr:street":"585Th Ave",
    "iso:country":"US",
    "sg:address":"16465 585th Ave",
    "sg:city":"Story City",
    "sg:phone":"+1 515 388 4528",
    "sg:postcode":"50248",
    "sg:province":"IA",
    "sg:tags":[
        "farm",
        "corn",
        "soybean"
    ],
    "wof:name":"Robert Jacobson",
    "wof:placetype":"venue"
},
  "geometry": {"coordinates":[-93.53118499999999,42.112363],"type":"Point"}
}