{
  "type": "Feature",
  "properties": {
    "iso:country":"US",
    "sg:address":"1351 Spruce Ave",
    "sg:city":"Riverside",
    "sg:classifiers":[
        {
            "category":"Home & Garden",
            "subcategory":"Hardware",
            "type":"Retail Goods"
        },
        {
            "category":"Retail",
            "subcategory":"Repair Shop",
            "type":"Services"
        }
    ],
    "sg:phone":"+1 319 648 3958",
    "sg:postcode":"52327",
    "sg:province":"IA",
    "sg:tags":[
        "saw"
    ],
    "wof:name":"Jim's Small Engine Repair",
    "wof:placetype":"venue"
},
  "geometry": {"coordinates":[-91.59891399999999,41.460341],"type":"Point"}
}