{
  "type": "Feature",
  "properties": {
    "addr:full":"926 71st St NE Cedar Rapids IA 52402",
    "addr:housenumber":"926",
    "addr:postcode":"52402",
    "addr:street":"71St St Ne",
    "iso:country":"US",
    "sg:address":"926 71st St NE",
    "sg:city":"Cedar Rapids",
    "sg:classifiers":[
        {
            "category":"Retail",
            "subcategory":"Repair Shop",
            "type":"Services"
        }
    ],
    "sg:phone":"+1 319 393 8882",
    "sg:postcode":"52402",
    "sg:province":"IA",
    "sg:tags":[
        "equipment",
        "establishment"
    ],
    "wof:name":"Carls Spot Free Mobile Wash",
    "wof:placetype":"venue"
},
  "geometry": {"coordinates":[-91.643792,42.049605],"type":"Point"}
}