{
  "type": "Feature",
  "properties": {
    "iso:country":"US",
    "sg:address":"1829 U Ave",
    "sg:city":"Grand Junction",
    "sg:classifiers":[
        {
            "category":"Real Estate",
            "subcategory":"Real Estate Operator",
            "type":"Services"
        }
    ],
    "sg:phone":"+1 515 436 8239",
    "sg:postcode":"50107",
    "sg:province":"IA",
    "sg:tags":[
        "property",
        "lessor"
    ],
    "wof:name":"Mike Scharingson Farm",
    "wof:placetype":"venue"
},
  "geometry": {"coordinates":[-94.241743,41.96977],"type":"Point"}
}