{
  "type": "Feature",
  "properties": {
    "addr:full":"14 Allamakee St NW Waukon IA 52172",
    "addr:housenumber":"14",
    "addr:postcode":"52172",
    "addr:street":"Allamakee St Nw",
    "iso:country":"US",
    "sg:address":"14 Allamakee St NW",
    "sg:city":"Waukon",
    "sg:classifiers":[
        {
            "category":"Insurance",
            "subcategory":"Hazard Insurance",
            "type":"Services"
        }
    ],
    "sg:phone":"+1 563 568 4789",
    "sg:postcode":"52172",
    "sg:province":"IA",
    "sg:tags":[
        "bond"
    ],
    "wof:name":"Jail & Bail",
    "wof:placetype":"venue"
},
  "geometry": {"coordinates":[-91.475627,43.270039],"type":"Point"}
}