{
  "type": "Feature",
  "properties": {
    "iso:country":"US",
    "sg:address":"15564 300th St",
    "sg:city":"Mason City",
    "sg:classifiers":[
        {
            "category":"Professional",
            "subcategory":"Business Services",
            "type":"Services"
        }
    ],
    "sg:phone":"+1 641 424 1116",
    "sg:postcode":"50401",
    "sg:province":"IA",
    "sg:tags":[
        "auctioneer"
    ],
    "wof:name":"Seeck Antique Auction Ctr",
    "wof:placetype":"venue"
},
  "geometry": {"coordinates":[-93.20925800000001,43.197466],"type":"Point"}
}