{
  "type": "Feature",
  "properties": {
    "iso:country":"US",
    "sg:address":"17542 Pleasant Grove Rd",
    "sg:city":"Yarmouth",
    "sg:classifiers":[
        {
            "category":"Mining & Drilling",
            "type":"Manufacturing & Wholesale Goods"
        }
    ],
    "sg:phone":"+1 319 394 3400",
    "sg:postcode":"52660",
    "sg:province":"IA",
    "sg:tags":[
        "stone"
    ],
    "wof:name":"L & W Quarries",
    "wof:placetype":"venue"
},
  "geometry": {"coordinates":[-91.27624299999999,40.973034],"type":"Point"}
}