{
  "type": "Feature",
  "properties": {
    "iso:country":"US",
    "sg:address":"1319 Jackson St",
    "sg:city":"Sioux City",
    "sg:classifiers":[
        {
            "category":"Home & Garden",
            "subcategory":"Carpets & Floor Coverings",
            "type":"Retail Goods"
        }
    ],
    "sg:phone":"+1 712 277 3339",
    "sg:postcode":"51105",
    "sg:province":"IA",
    "sg:tags":[
        "material"
    ],
    "wof:name":"Mikes Sioux City Carpets",
    "wof:placetype":"venue"
},
  "geometry": {"coordinates":[-96.402169,42.504839],"type":"Point"}
}