{
  "type": "Feature",
  "properties": {
    "addr:full":"5028 Rolling Acres Rd Walker IA 52352",
    "addr:housenumber":"5028",
    "addr:postcode":"52352",
    "addr:street":"Rolling Acres Rd",
    "iso:country":"US",
    "sg:address":"5028 Rolling Acres Rd",
    "sg:city":"Walker",
    "sg:classifiers":[
        {
            "category":"Retail",
            "subcategory":"Animal Services",
            "type":"Services"
        }
    ],
    "sg:phone":"+1 319 849 2271",
    "sg:postcode":"52352",
    "sg:province":"IA",
    "wof:name":"Sunset Kennels",
    "wof:placetype":"venue"
},
  "geometry": {"coordinates":[-91.807779,42.230732],"type":"Point"}
}