{
  "type": "Feature",
  "properties": {
    "addr:full":"3833 N Division St Davenport IA 52806",
    "addr:housenumber":"3833",
    "addr:postcode":"52806",
    "addr:street":"N Division St",
    "iso:country":"US",
    "sg:address":"3833 N Division St",
    "sg:city":"Davenport",
    "sg:classifiers":[
        {
            "category":"Cinema",
            "subcategory":"Movie Rental",
            "type":"Entertainment"
        }
    ],
    "sg:phone":"+1 563 388 7700",
    "sg:postcode":"52806",
    "sg:province":"IA",
    "sg:tags":[
        "leasing",
        "video",
        "disc",
        "tape"
    ],
    "wof:name":"Family Video",
    "wof:placetype":"venue"
},
  "geometry": {"coordinates":[-90.600601,41.558974],"type":"Point"}
}