{
  "type": "Feature",
  "properties": {
    "iso:country":"US",
    "sg:address":"1908 S Stark St",
    "sg:city":"Davenport",
    "sg:classifiers":[
        {
            "category":"Professional",
            "subcategory":"Business Services",
            "type":"Services"
        }
    ],
    "sg:phone":"+1 563 322 7149",
    "sg:postcode":"52802",
    "sg:province":"IA",
    "wof:name":"Eastern Iowa Grain Inspection",
    "wof:placetype":"venue"
},
  "geometry": {"coordinates":[-90.639712,41.499043],"type":"Point"}
}