{
  "type": "Feature",
  "properties": {
    "iso:country":"US",
    "sg:address":"2304 University Ave",
    "sg:city":"Des Moines",
    "sg:classifiers":[
        {
            "category":"Shopping",
            "subcategory":"Clothing, Apparel, & Fashions",
            "type":"Retail Goods"
        }
    ],
    "sg:phone":"+1 515 996 2694",
    "sg:postcode":"50311",
    "sg:province":"IA",
    "wof:name":"Day Dreams Inc",
    "wof:placetype":"venue"
},
  "geometry": {"coordinates":[-93.649663,41.600323],"type":"Point"}
}