{
  "type": "Feature",
  "properties": {
    "iso:country":"US",
    "sg:address":"1667 Baxter Ave",
    "sg:city":"Jesup",
    "sg:classifiers":[
        {
            "category":"Retail",
            "subcategory":"Repair Shop",
            "type":"Services"
        }
    ],
    "sg:phone":"+1 319 827 2813",
    "sg:postcode":"50648",
    "sg:province":"IA",
    "wof:name":"T JS Repair",
    "wof:placetype":"venue"
},
  "geometry": {"coordinates":[-92.062511,42.544846],"type":"Point"}
}