{
  "type": "Feature",
  "properties": {
    "addr:full":"14610 Yak Blvd Selma IA 52588",
    "addr:postcode":"14610;52588",
    "addr:street":"Yak Blvd",
    "iso:country":"US",
    "sg:address":"14610 Yak Blvd",
    "sg:city":"Selma",
    "sg:classifiers":[
        {
            "category":"Real Estate",
            "subcategory":"Real Estate Operator",
            "type":"Services"
        }
    ],
    "sg:phone":"+1 641 936 4397",
    "sg:postcode":"52588",
    "sg:province":"IA",
    "sg:tags":[
        "property",
        "lessor"
    ],
    "wof:name":"Goodell Farms",
    "wof:placetype":"venue"
},
  "geometry": {"coordinates":[-92.197665,40.828096],"type":"Point"}
}