{
  "type": "Feature",
  "properties": {
    "addr:full":"315 Main St Cedar Falls IA 50613",
    "addr:housenumber":"315",
    "addr:postcode":"50613",
    "addr:street":"Main St",
    "iso:country":"US",
    "sg:address":"315 Main St",
    "sg:city":"Cedar Falls",
    "sg:classifiers":[
        {
            "category":"Shopping",
            "subcategory":"Gifts & Souvenirs",
            "type":"Retail Goods"
        }
    ],
    "sg:phone":"+1 319 266 8171",
    "sg:postcode":"50613",
    "sg:province":"IA",
    "sg:tags":[
        "shop"
    ],
    "wof:name":"Cathy's Hallmark",
    "wof:placetype":"venue"
},
  "geometry": {"coordinates":[-92.445555,42.535175],"type":"Point"}
}