{
  "type": "Feature",
  "properties": {
    "iso:country":"US",
    "sg:address":"1511 US Hwy 71",
    "sg:city":"Carroll",
    "sg:classifiers":[
        {
            "category":"Food & Beverages",
            "subcategory":"Groceries & Convenience Stores",
            "type":"Retail Goods"
        }
    ],
    "sg:phone":"+1 712 792 9183",
    "sg:postcode":"51401",
    "sg:province":"IA",
    "wof:name":"Carroll Country Store",
    "wof:placetype":"venue"
},
  "geometry": {"coordinates":[-94.878668,42.076089],"type":"Point"}
}