{
  "type": "Feature",
  "properties": {
    "addr:full":"910 E South St Marshalltown IA 50158",
    "addr:housenumber":"910 e",
    "addr:postcode":"50158",
    "addr:street":"South St",
    "iso:country":"US",
    "sg:address":"910 E South St",
    "sg:city":"Marshalltown",
    "sg:classifiers":[
        {
            "category":"Shopping",
            "subcategory":"Used Merchandise",
            "type":"Retail Goods"
        }
    ],
    "sg:phone":"+1 641 752 5946",
    "sg:postcode":"50158",
    "sg:province":"IA",
    "wof:name":"Kevin S Antiques",
    "wof:placetype":"venue"
},
  "geometry": {"coordinates":[-92.898228,42.034844],"type":"Point"}
}