{
  "type": "Feature",
  "properties": {
    "iso:country":"US",
    "sg:address":"23202 Pleasant Ridge Rd",
    "sg:city":"Monona",
    "sg:classifiers":[
        {
            "category":"Wholesale",
            "subcategory":"Machinery & Supplies",
            "type":"Manufacturing & Wholesale Goods"
        }
    ],
    "sg:phone":"+1 563 539 2027",
    "sg:postcode":"52159",
    "sg:province":"IA",
    "wof:name":"J & B Distributing",
    "wof:placetype":"venue"
},
  "geometry": {"coordinates":[-91.34321300000001,43.068048],"type":"Point"}
}