{
  "type": "Feature",
  "properties": {
    "addr:full":"4106 Morningside Ave Sioux City IA 51106",
    "addr:housenumber":"4106",
    "addr:postcode":"51106",
    "addr:street":"Morningside Ave",
    "iso:country":"US",
    "sg:address":"4106 Morningside Ave",
    "sg:city":"Sioux City",
    "sg:classifiers":[
        {
            "category":"Professional",
            "type":"Services"
        }
    ],
    "sg:phone":"+1 712 274 8843",
    "sg:postcode":"51106",
    "sg:province":"IA",
    "sg:tags":[
        "establishment"
    ],
    "wof:name":"Board Room",
    "wof:placetype":"venue"
},
  "geometry": {"coordinates":[-96.353714,42.470568],"type":"Point"}
}