{
  "type": "Feature",
  "properties": {
    "iso:country":"US",
    "sg:address":"1700 W Bremer Ave",
    "sg:city":"Waverly",
    "sg:classifiers":[
        {
            "category":"Professional",
            "subcategory":"Lawyer & Legal Services",
            "type":"Services"
        }
    ],
    "sg:phone":"+1 319 352 4425",
    "sg:postcode":"50677",
    "sg:province":"IA",
    "sg:tags":[
        "planning",
        "estate"
    ],
    "wof:name":"Eagle Financial Group",
    "wof:placetype":"venue"
},
  "geometry": {"coordinates":[-92.491737,42.725701],"type":"Point"}
}