{
  "type": "Feature",
  "properties": {
    "addr:full":"1409 Wisconsin St Muscatine IA 52761",
    "addr:housenumber":"1409",
    "addr:postcode":"52761",
    "addr:street":"Wisconsin St",
    "iso:country":"US",
    "sg:address":"1409 Wisconsin St",
    "sg:city":"Muscatine",
    "sg:classifiers":[
        {
            "category":"Education",
            "subcategory":"School",
            "type":"Public Place"
        }
    ],
    "sg:phone":"+1 563 263 6079",
    "sg:postcode":"52761",
    "sg:province":"IA",
    "wof:name":"Garfield Elementary School",
    "wof:placetype":"venue"
},
  "geometry": {"coordinates":[-91.067294,41.401757],"type":"Point"}
}