{
  "type": "Feature",
  "properties": {
    "iso:country":"US",
    "sg:address":"7 1st Ave NE",
    "sg:city":"Oelwein",
    "sg:classifiers":[
        {
            "category":"Professional",
            "type":"Services"
        }
    ],
    "sg:phone":"+1 319 283 9359",
    "sg:postcode":"50662",
    "sg:province":"IA",
    "sg:tags":[
        "establishment"
    ],
    "wof:name":"Wilbert Burial Vault",
    "wof:placetype":"venue"
},
  "geometry": {"coordinates":[-91.91187600000001,42.678898],"type":"Point"}
}