{
  "type": "Feature",
  "properties": {
    "iso:country":"US",
    "sg:address":"3111 Ave K",
    "sg:city":"Fort Madison",
    "sg:classifiers":[
        {
            "category":"Personal",
            "subcategory":"Beauty Salon",
            "type":"Services"
        }
    ],
    "sg:phone":"+1 319 372 1450",
    "sg:postcode":"52627",
    "sg:province":"IA",
    "sg:tags":[
        "shop"
    ],
    "wof:name":"Ritas Beauty Salon",
    "wof:placetype":"venue"
},
  "geometry": {"coordinates":[-91.35177299999999,40.627943],"type":"Point"}
}