{
  "type": "Feature",
  "properties": {
    "iso:country":"US",
    "sg:address":"703 5th St",
    "sg:city":"Kalona",
    "sg:classifiers":[
        {
            "category":"Building & Trades",
            "subcategory":"Construction",
            "type":"Services"
        }
    ],
    "sg:phone":"+1 319 656 5462",
    "sg:postcode":"52247",
    "sg:province":"IA",
    "sg:tags":[
        "hanging",
        "contractor"
    ],
    "wof:name":"Creative Color Painting Dctn",
    "wof:placetype":"venue"
},
  "geometry": {"coordinates":[-91.706001,41.489375],"type":"Point"}
}