{
  "type": "Feature",
  "properties": {
    "addr:full":"113 E 5th St West Liberty IA 52776",
    "addr:housenumber":"113",
    "addr:postcode":"52776",
    "addr:street":"E 5Th St",
    "iso:country":"US",
    "sg:address":"113 E 5th St",
    "sg:city":"West Liberty",
    "sg:classifiers":[
        {
            "category":"Organizations",
            "subcategory":"Religious Organization",
            "type":"Services"
        }
    ],
    "sg:phone":"+1 319 627 2780",
    "sg:postcode":"52776",
    "sg:province":"IA",
    "sg:tags":[
        "church"
    ],
    "wof:name":"West Liberty United Meth Chr",
    "wof:placetype":"venue"
},
  "geometry": {"coordinates":[-91.263251,41.572266],"type":"Point"}
}