{
  "type": "Feature",
  "properties": {
    "iso:country":"US",
    "sg:address":"7318 Oliver Smith Dr",
    "sg:city":"Urbandale",
    "sg:classifiers":[
        {
            "category":"Food & Beverages",
            "subcategory":"Candy",
            "type":"Retail Goods"
        }
    ],
    "sg:phone":"+1 515 278 7075",
    "sg:postcode":"50322",
    "sg:province":"IA",
    "sg:tags":[
        "nut"
    ],
    "wof:name":"Mountain Man Distributors",
    "wof:placetype":"venue"
},
  "geometry": {"coordinates":[-93.72016600000001,41.626362],"type":"Point"}
}