{
  "type": "Feature",
  "properties": {
    "addr:full":"107 Maple Rd Avoca IA 51521",
    "addr:housenumber":"107",
    "addr:postcode":"51521",
    "addr:street":"Maple Rd",
    "iso:country":"US",
    "sg:address":"107 Maple Rd",
    "sg:city":"Avoca",
    "sg:classifiers":[
        {
            "category":"Food & Beverages",
            "subcategory":"Bakery",
            "type":"Retail Goods"
        }
    ],
    "sg:phone":"+1 712 343 6361",
    "sg:postcode":"51521",
    "sg:province":"IA",
    "sg:tags":[
        "baker"
    ],
    "wof:name":"Cakery",
    "wof:placetype":"venue"
},
  "geometry": {"coordinates":[-95.33018199999999,41.512996],"type":"Point"}
}