{
  "type": "Feature",
  "properties": {
    "iso:country":"US",
    "sg:address":"907 Rainbow Dr",
    "sg:city":"Cedar Falls",
    "sg:classifiers":[
        {
            "category":"Health Services",
            "subcategory":"Doctor",
            "type":"Services"
        }
    ],
    "sg:phone":"+1 319 277 7441",
    "sg:postcode":"50613",
    "sg:province":"IA",
    "sg:tags":[
        "dentist"
    ],
    "wof:name":"Pedar B Didriksen DDS",
    "wof:placetype":"venue"
},
  "geometry": {"coordinates":[-92.435329,42.521269],"type":"Point"}
}