{
  "type": "Feature",
  "properties": {
    "addr:full":"1301 36th St SE Cedar Rapids IA 52403",
    "addr:housenumber":"1301",
    "addr:postcode":"52403",
    "addr:street":"36Th St Se",
    "iso:country":"US",
    "sg:address":"1301 36th St SE",
    "sg:city":"Cedar Rapids",
    "sg:classifiers":[
        {
            "category":"Building & Trades",
            "subcategory":"Electrical",
            "type":"Services"
        }
    ],
    "sg:phone":"+1 319 366 6145",
    "sg:postcode":"52403",
    "sg:province":"IA",
    "sg:tags":[
        "electric",
        "contractor"
    ],
    "wof:name":"All American Electric Of Ia",
    "wof:placetype":"venue"
},
  "geometry": {"coordinates":[-91.61587900000001,41.970341],"type":"Point"}
}