{
  "type": "Feature",
  "properties": {
    "iso:country":"US",
    "sg:address":"206 S Main St",
    "sg:city":"Grimes",
    "sg:classifiers":[
        {
            "category":"Health Services",
            "subcategory":"Chiropractor",
            "type":"Services"
        }
    ],
    "sg:phone":"+1 515 986 9189",
    "sg:postcode":"50111",
    "sg:province":"IA",
    "wof:name":"Williamson Family Chiropractic",
    "wof:placetype":"venue"
},
  "geometry": {"coordinates":[-93.791133,41.686539],"type":"Point"}
}