{
  "type": "Feature",
  "properties": {
    "addr:full":"500 E Columbus St Mt Ayr IA 50854",
    "addr:housenumber":"500",
    "addr:postcode":"50854",
    "addr:street":"E Columbus St",
    "iso:country":"US",
    "sg:address":"500 E Columbus St",
    "sg:city":"Mt Ayr",
    "sg:classifiers":[
        {
            "category":"Health Services",
            "subcategory":"Nursing And Care Facility",
            "type":"Services"
        }
    ],
    "sg:phone":"+1 641 464 0651",
    "sg:postcode":"50854",
    "sg:province":"IA",
    "sg:tags":[
        "adult"
    ],
    "wof:name":"Clearview Estates",
    "wof:placetype":"venue"
},
  "geometry": {"coordinates":[-94.23201400000001,40.718274],"type":"Point"}
}