{
  "type": "Feature",
  "properties": {
    "addr:full":"5240 Edgewood Rd NE Cedar Rapids IA 52410",
    "addr:housenumber":"5240",
    "addr:postcode":"52410",
    "addr:street":"Edgewood Rd Ne",
    "iso:country":"US",
    "sg:address":"5240 Edgewood Rd NE",
    "sg:city":"Cedar Rapids",
    "sg:classifiers":[
        {
            "category":"Restaurant",
            "type":"Food & Drink"
        }
    ],
    "sg:phone":"+1 319 294 4992",
    "sg:postcode":"52410",
    "sg:province":"IA",
    "sg:tags":[
        "traditional",
        "american"
    ],
    "sg:website":"www.beefobradys.com",
    "wof:name":"Beef O'Brady's",
    "wof:placetype":"venue"
},
  "geometry": {"coordinates":[-91.70134,42.032492],"type":"Point"}
}