{
  "type": "Feature",
  "properties": {
    "iso:country":"US",
    "sg:address":"1050 Moscow Rd",
    "sg:city":"Moscow",
    "sg:phone":"+1 563 724 3482",
    "sg:postcode":"52760",
    "sg:province":"IA",
    "sg:tags":[
        "farm",
        "corn"
    ],
    "wof:name":"Dierdorff Dene",
    "wof:placetype":"venue"
},
  "geometry": {"coordinates":[-91.089281,41.591378],"type":"Point"}
}