{
  "type": "Feature",
  "properties": {
    "iso:country":"US",
    "sg:address":"414 W 7th St",
    "sg:city":"Carroll",
    "sg:classifiers":[
        {
            "category":"Banks & Credit Unions",
            "subcategory":"Bank",
            "type":"Services"
        }
    ],
    "sg:phone":"+1 712 792 4939",
    "sg:postcode":"51401",
    "sg:province":"IA",
    "sg:tags":[
        "loan",
        "real estate"
    ],
    "wof:name":"Iowa Mortgage",
    "wof:placetype":"venue"
},
  "geometry": {"coordinates":[-94.872304,42.068204],"type":"Point"}
}