{
  "type": "Feature",
  "properties": {
    "addr:full":"2712 Court St Sioux City IA 51104",
    "addr:housenumber":"2712",
    "addr:postcode":"51104",
    "addr:street":"Court St",
    "iso:country":"US",
    "sg:address":"2712 Court St",
    "sg:city":"Sioux City",
    "sg:classifiers":[
        {
            "category":"Organizations",
            "subcategory":"Religious Organization",
            "type":"Services"
        }
    ],
    "sg:phone":"+1 712 258 4197",
    "sg:postcode":"51104",
    "sg:province":"IA",
    "sg:tags":[
        "church"
    ],
    "wof:name":"Siouxland First Wiccan Congr",
    "wof:placetype":"venue"
},
  "geometry": {"coordinates":[-96.39595199999999,42.518349],"type":"Point"}
}