{
  "type": "Feature",
  "properties": {
    "addr:full":"201 5th St Kalona IA 52247",
    "addr:housenumber":"201",
    "addr:postcode":"52247",
    "addr:street":"5Th St",
    "iso:country":"US",
    "sg:address":"201 5th St",
    "sg:city":"Kalona",
    "sg:classifiers":[
        {
            "category":"Professional",
            "subcategory":"Lawyer & Legal Services",
            "type":"Services"
        }
    ],
    "sg:phone":"+1 319 656 2227",
    "sg:postcode":"52247",
    "sg:province":"IA",
    "sg:tags":[
        "attorney"
    ],
    "wof:name":"Anderson Law Office",
    "wof:placetype":"venue"
},
  "geometry": {"coordinates":[-91.706068,41.483974],"type":"Point"}
}