{
  "type": "Feature",
  "properties": {
    "addr:full":"103 1st Ave Persia IA 51563",
    "addr:housenumber":"103",
    "addr:postcode":"51563",
    "addr:street":"1St Ave",
    "iso:country":"US",
    "sg:address":"103 1st Ave",
    "sg:city":"Persia",
    "sg:classifiers":[
        {
            "category":"Building & Trades",
            "subcategory":"Electrical",
            "type":"Services"
        }
    ],
    "sg:phone":"+1 712 488 3651",
    "sg:postcode":"51563",
    "sg:province":"IA",
    "sg:tags":[
        "electric",
        "contractor"
    ],
    "wof:name":"Carrigan Electric",
    "wof:placetype":"venue"
},
  "geometry": {"coordinates":[-95.56955000000001,41.58173],"type":"Point"}
}