{
  "type": "Feature",
  "properties": {
    "iso:country":"US",
    "sg:address":"1400 W Elm Ave",
    "sg:city":"Pocahontas",
    "sg:classifiers":[
        {
            "category":"Wholesale",
            "subcategory":"Machinery & Supplies",
            "type":"Manufacturing & Wholesale Goods"
        }
    ],
    "sg:phone":"+1 712 335 4522",
    "sg:postcode":"50574",
    "sg:province":"IA",
    "sg:tags":[
        "farm",
        "equipment"
    ],
    "wof:name":"Pocahontas Equipment",
    "wof:placetype":"venue"
},
  "geometry": {"coordinates":[-94.68628200000001,42.7326],"type":"Point"}
}