{
  "type": "Feature",
  "properties": {
    "addr:full":"142 Valley View Dr Council Bluffs IA 51503",
    "addr:housenumber":"142",
    "addr:postcode":"51503",
    "addr:street":"Valley View Dr",
    "iso:country":"US",
    "sg:address":"142 Valley View Dr",
    "sg:city":"Council Bluffs",
    "sg:classifiers":[
        {
            "category":"Organizations",
            "subcategory":"Religious Organization",
            "type":"Services"
        }
    ],
    "sg:phone":"+1 712 323 4251",
    "sg:postcode":"51503",
    "sg:province":"IA",
    "sg:tags":[
        "church"
    ],
    "wof:name":"Seventh-Day Adventist Church",
    "wof:placetype":"venue"
},
  "geometry": {"coordinates":[-95.810604,41.25364],"type":"Point"}
}