{
  "type": "Feature",
  "properties": {
    "addr:full":"517 Main St Griswold IA 51535",
    "addr:housenumber":"517",
    "addr:postcode":"51535",
    "addr:street":"Main St",
    "iso:country":"US",
    "sg:address":"517 Main St",
    "sg:city":"Griswold",
    "sg:classifiers":[
        {
            "category":"Professional",
            "subcategory":"Management & Consulting",
            "type":"Services"
        }
    ],
    "sg:phone":"+1 712 778 2335",
    "sg:postcode":"51535",
    "sg:province":"IA",
    "sg:tags":[
        "consultant",
        "business"
    ],
    "wof:name":"White Commercial Corp",
    "wof:placetype":"venue"
},
  "geometry": {"coordinates":[-95.14260299999999,41.234796],"type":"Point"}
}