{
  "type": "Feature",
  "properties": {
    "addr:full":"2020 N Harrison St Davenport IA 52803",
    "addr:housenumber":"2020",
    "addr:postcode":"52803",
    "addr:street":"N Harrison St",
    "iso:country":"US",
    "sg:address":"2020 N Harrison St",
    "sg:city":"Davenport",
    "sg:classifiers":[
        {
            "category":"Organizations",
            "subcategory":"Non-profit Organization",
            "type":"Services"
        }
    ],
    "sg:phone":"+1 563 324 5261",
    "sg:postcode":"52803",
    "sg:province":"IA",
    "sg:tags":[
        "alternative",
        "abortion"
    ],
    "wof:name":"Birth Right",
    "wof:placetype":"venue"
},
  "geometry": {"coordinates":[-90.577353,41.540419],"type":"Point"}
}