{
  "type": "Feature",
  "properties": {
    "iso:country":"US",
    "sg:address":"520 17th St",
    "sg:city":"Marion",
    "sg:classifiers":[
        {
            "category":"Retail",
            "subcategory":"Auto Repair",
            "type":"Services"
        }
    ],
    "sg:phone":"+1 319 447 0605",
    "sg:postcode":"52302",
    "sg:province":"IA",
    "sg:tags":[
        "body",
        "automobile",
        "painting"
    ],
    "wof:name":"Discount Auto Body",
    "wof:placetype":"venue"
},
  "geometry": {"coordinates":[-91.591988,42.032173],"type":"Point"}
}