{
  "type": "Feature",
  "properties": {
    "addr:full":"323 Fairview Ave Iowa City IA 52245",
    "addr:housenumber":"323",
    "addr:postcode":"52245",
    "addr:street":"Fairview Ave",
    "iso:country":"US",
    "sg:address":"323 Fairview Ave",
    "sg:city":"Iowa City",
    "sg:classifiers":[
        {
            "category":"Shopping",
            "subcategory":"Gifts & Souvenirs",
            "type":"Retail Goods"
        }
    ],
    "sg:phone":"+1 319 341 7990",
    "sg:postcode":"52245",
    "sg:province":"IA",
    "sg:tags":[
        "balloon",
        "artist"
    ],
    "wof:name":"Bear N Balloons",
    "wof:placetype":"venue"
},
  "geometry": {"coordinates":[-91.514394,41.658013],"type":"Point"}
}