{
  "type": "Feature",
  "properties": {
    "iso:country":"US",
    "sg:address":"24183 120th St",
    "sg:city":"South English",
    "sg:classifiers":[
        {
            "category":"Shopping",
            "subcategory":"Bicycles & Sporting Goods",
            "type":"Retail Goods"
        }
    ],
    "sg:phone":"+1 319 664 6118",
    "sg:postcode":"52335",
    "sg:province":"IA",
    "sg:tags":[
        "gun",
        "gunsmith"
    ],
    "wof:name":"Professional Gunsmithing Svc",
    "wof:placetype":"venue"
},
  "geometry": {"coordinates":[-92.128049,41.482148],"type":"Point"}
}