{
  "type": "Feature",
  "properties": {
    "iso:country":"US",
    "sg:address":"111 S 3rd Ave",
    "sg:city":"Marshalltown",
    "sg:classifiers":[
        {
            "category":"Food & Beverages",
            "subcategory":"Groceries & Convenience Stores",
            "type":"Retail Goods"
        }
    ],
    "sg:phone":"+1 641 752 2725",
    "sg:postcode":"50158",
    "sg:province":"IA",
    "wof:name":"Jiffy",
    "wof:placetype":"venue"
},
  "geometry": {"coordinates":[-92.908091,42.047795],"type":"Point"}
}