{
  "type": "Feature",
  "properties": {
    "iso:country":"US",
    "sg:address":"14115 290th St",
    "sg:city":"Donahue",
    "sg:classifiers":[
        {
            "category":"Building & Trades",
            "subcategory":"Construction",
            "type":"Services"
        }
    ],
    "sg:phone":"+1 563 285 5250",
    "sg:postcode":"52746",
    "sg:province":"IA",
    "sg:tags":[
        "dry wall",
        "contractor"
    ],
    "wof:name":"All Phases Construction Inc",
    "wof:placetype":"venue"
},
  "geometry": {"coordinates":[-90.624977,41.727674],"type":"Point"}
}