{
  "type": "Feature",
  "properties": {
    "iso:country":"US",
    "sg:address":"6901 Hickman Rd",
    "sg:city":"Urbandale",
    "sg:classifiers":[
        {
            "category":"Professional",
            "subcategory":"Business Services",
            "type":"Services"
        }
    ],
    "sg:phone":"+1 515 276 1990",
    "sg:postcode":"50322",
    "sg:province":"IA",
    "wof:name":"Crystal Sound Recording Studio",
    "wof:placetype":"venue"
},
  "geometry": {"coordinates":[-93.712845,41.614614],"type":"Point"}
}