{
  "type": "Feature",
  "properties": {
    "addr:full":"26654 Nature Ave Le Mars IA 51031",
    "addr:housenumber":"26654",
    "addr:postcode":"51031",
    "addr:street":"Nature Ave",
    "iso:country":"US",
    "sg:address":"26654 Nature Ave",
    "sg:city":"Le Mars",
    "sg:phone":"+1 712 546 4673",
    "sg:postcode":"51031",
    "sg:province":"IA",
    "sg:tags":[
        "farm",
        "corn",
        "soybean"
    ],
    "wof:name":"Susan Plendl",
    "wof:placetype":"venue"
},
  "geometry": {"coordinates":[-96.115438,42.66424],"type":"Point"}
}