{
  "type": "Feature",
  "properties": {
    "iso:country":"US",
    "sg:address":"206 8th St",
    "sg:city":"Des Moines",
    "sg:classifiers":[
        {
            "category":"Insurance",
            "subcategory":"Insurance Agent",
            "type":"Services"
        }
    ],
    "sg:phone":"+1 515 557 7307",
    "sg:postcode":"50309",
    "sg:province":"IA",
    "wof:name":"Centurion Casualty Co",
    "wof:placetype":"venue"
},
  "geometry": {"coordinates":[-93.62713100000001,41.585313],"type":"Point"}
}