{
  "type": "Feature",
  "properties": {
    "addr:full":"2227 140th St Floyd IA 50435",
    "addr:housenumber":"2227",
    "addr:postcode":"50435",
    "addr:street":"140Th St",
    "iso:country":"US",
    "sg:address":"2227 140th St",
    "sg:city":"Floyd",
    "sg:classifiers":[
        {
            "category":"Farming",
            "subcategory":"Dairy Farm",
            "type":"Manufacturing & Wholesale Goods"
        }
    ],
    "sg:phone":"+1 641 398 2343",
    "sg:postcode":"50435",
    "sg:province":"IA",
    "wof:name":"Jim Janssen",
    "wof:placetype":"venue"
},
  "geometry": {"coordinates":[-92.786203,43.156262],"type":"Point"}
}