{
  "type": "Feature",
  "properties": {
    "iso:country":"US",
    "sg:address":"667 7th St NW",
    "sg:city":"Sioux Center",
    "sg:classifiers":[
        {
            "category":"Building & Trades",
            "subcategory":"Landscaping Services",
            "type":"Services"
        }
    ],
    "sg:phone":"+1 712 722 2963",
    "sg:postcode":"51250",
    "sg:province":"IA",
    "sg:tags":[
        "lawn",
        "maintenance",
        "grounds"
    ],
    "wof:name":"J J's Lawn Care",
    "wof:placetype":"venue"
},
  "geometry": {"coordinates":[-96.186086,43.084199],"type":"Point"}
}