{
  "type": "Feature",
  "properties": {
    "iso:country":"US",
    "sg:address":"1934 Paulson Dr",
    "sg:city":"Ames",
    "sg:classifiers":[
        {
            "category":"Home & Garden",
            "subcategory":"Garden Supply",
            "type":"Retail Goods"
        }
    ],
    "sg:phone":"+1 515 232 8768",
    "sg:postcode":"50010",
    "sg:province":"IA",
    "sg:tags":[
        "bulb",
        "seed"
    ],
    "wof:name":"Ames Best Hybrids",
    "wof:placetype":"venue"
},
  "geometry": {"coordinates":[-93.608209,42.041523],"type":"Point"}
}