{
  "type": "Feature",
  "properties": {
    "iso:country":"US",
    "sg:address":"208 Broadway St",
    "sg:city":"Clearfield",
    "sg:classifiers":[
        {
            "category":"Shopping",
            "type":"Retail Goods"
        }
    ],
    "sg:phone":"+1 641 336 2311",
    "sg:postcode":"50840",
    "sg:province":"IA",
    "sg:tags":[
        "chemical"
    ],
    "wof:name":"Taygold Cooperative",
    "wof:placetype":"venue"
},
  "geometry": {"coordinates":[-94.475539,40.803451],"type":"Point"}
}