{
  "type": "Feature",
  "properties": {
    "iso:country":"US",
    "sg:address":"2934 Devils Glen Rd",
    "sg:city":"Bettendorf",
    "sg:phone":"+1 563 381 4443",
    "sg:postcode":"52722",
    "sg:province":"IA",
    "sg:tags":[
        "equipment",
        "supply"
    ],
    "wof:name":"Goodwin Tucker Group",
    "wof:placetype":"venue"
},
  "geometry": {"coordinates":[-90.483769,41.552237],"type":"Point"}
}