{
  "type": "Feature",
  "properties": {
    "iso:country":"US",
    "sg:address":"402 S Main St",
    "sg:city":"Inwood",
    "sg:classifiers":[
        {
            "category":"Real Estate",
            "subcategory":"Real Estate Agent",
            "type":"Services"
        }
    ],
    "sg:phone":"+1 712 753 4390",
    "sg:postcode":"51240",
    "sg:province":"IA",
    "wof:name":"Bruggeman Realty & Tax Svc",
    "wof:placetype":"venue"
},
  "geometry": {"coordinates":[-96.431956,43.306268],"type":"Point"}
}