{
  "type": "Feature",
  "properties": {
    "iso:country":"US",
    "sg:address":"700 W Water St",
    "sg:city":"Shell Rock",
    "sg:classifiers":[
        {
            "category":"Personal",
            "subcategory":"Beauty Salon",
            "type":"Services"
        }
    ],
    "sg:phone":"+1 319 885 6540",
    "sg:postcode":"50670",
    "sg:province":"IA",
    "wof:name":"Cut Hut",
    "wof:placetype":"venue"
},
  "geometry": {"coordinates":[-92.584039,42.714857],"type":"Point"}
}