{
  "type": "Feature",
  "properties": {
    "iso:country":"US",
    "sg:address":"1101 S 20th St",
    "sg:city":"Council Bluffs",
    "sg:classifiers":[
        {
            "category":"Wholesale",
            "subcategory":"Scrap",
            "type":"Manufacturing & Wholesale Goods"
        }
    ],
    "sg:phone":"+1 712 325 1115",
    "sg:postcode":"51501",
    "sg:province":"IA",
    "sg:tags":[
        "cloth",
        "wiping"
    ],
    "sg:website":"www.peerlesswipingcloth.com",
    "wof:name":"Peerless Wiping Cloth Co",
    "wof:placetype":"venue"
},
  "geometry": {"coordinates":[-95.873159,41.251097],"type":"Point"}
}