{
  "type": "Feature",
  "properties": {
    "addr:full":"1510 W 1st St Cedar Falls IA 50613",
    "addr:housenumber":"1510",
    "addr:postcode":"50613",
    "addr:street":"W 1St St",
    "iso:country":"US",
    "sg:address":"1510 W 1st St",
    "sg:city":"Cedar Falls",
    "sg:classifiers":[
        {
            "category":"Government",
            "subcategory":"Fire Station",
            "type":"Public Place"
        }
    ],
    "sg:phone":"+1 319 266 4892",
    "sg:postcode":"50613",
    "sg:province":"IA",
    "sg:tags":[
        "state",
        "protection"
    ],
    "wof:name":"Fire Marshall",
    "wof:placetype":"venue"
},
  "geometry": {"coordinates":[-92.464291,42.537776],"type":"Point"}
}