{
  "type": "Feature",
  "properties": {
    "iso:country":"US",
    "sg:address":"431 W Main St",
    "sg:city":"Solon",
    "sg:classifiers":[
        {
            "category":"Retail",
            "subcategory":"Auto Repair",
            "type":"Services"
        }
    ],
    "sg:phone":"+1 319 624 2517",
    "sg:postcode":"52333",
    "sg:province":"IA",
    "sg:tags":[
        "general",
        "supply"
    ],
    "wof:name":"Kens Auto Clinic Inc",
    "wof:placetype":"venue"
},
  "geometry": {"coordinates":[-91.499433,41.807158],"type":"Point"}
}