{
  "type": "Feature",
  "properties": {
    "iso:country":"US",
    "sg:address":"2244 Mckinley Ave",
    "sg:city":"Keokuk",
    "sg:classifiers":[
        {
            "category":"Place Of Worship",
            "subcategory":"Church",
            "type":"Public Place"
        },
        {
            "category":"Place Of Worship",
            "type":"Public Place"
        }
    ],
    "sg:phone":"+1 319 524 8713",
    "sg:postcode":"52632",
    "sg:province":"IA",
    "sg:tags":[
        "churches-pentecostal-independent",
        "churches-pentecostal"
    ],
    "wof:name":"Church Of New Beginnings Of Keokuk",
    "wof:placetype":"venue"
},
  "geometry": {"coordinates":[-91.40311199999999,40.405998],"type":"Point"}
}