{
  "type": "Feature",
  "properties": {
    "iso:country":"US",
    "sg:address":"3336 Prairie Dr NE",
    "sg:city":"Cedar Rapids",
    "sg:classifiers":[
        {
            "category":"Organizations",
            "subcategory":"Religious Organization",
            "type":"Services"
        }
    ],
    "sg:phone":"+1 319 363 7571",
    "sg:postcode":"52402",
    "sg:province":"IA",
    "sg:tags":[
        "church"
    ],
    "wof:name":"Prairie Drive Full Gospel Chr",
    "wof:placetype":"venue"
},
  "geometry": {"coordinates":[-91.652366,42.012823],"type":"Point"}
}