{
  "type": "Feature",
  "properties": {
    "addr:full":"12327 Stratford Dr Clive IA 50325",
    "addr:housenumber":"12327",
    "addr:postcode":"50325",
    "addr:street":"Stratford Dr",
    "iso:country":"US",
    "sg:address":"12327 Stratford Dr",
    "sg:city":"Clive",
    "sg:classifiers":[
        {
            "category":"Professional",
            "type":"Services"
        }
    ],
    "sg:phone":"+1 515 440 1998",
    "sg:postcode":"50325",
    "sg:province":"IA",
    "sg:tags":[
        "establishment"
    ],
    "wof:name":"Rochon Corp",
    "wof:placetype":"venue"
},
  "geometry": {"coordinates":[-93.78833400000001,41.602321],"type":"Point"}
}