{
  "type": "Feature",
  "properties": {
    "iso:country":"US",
    "sg:address":"1406 Market St",
    "sg:city":"Burlington",
    "sg:classifiers":[
        {
            "category":"Shopping",
            "subcategory":"Gifts & Souvenirs",
            "type":"Retail Goods"
        }
    ],
    "sg:phone":"+1 319 758 6176",
    "sg:postcode":"52601",
    "sg:province":"IA",
    "wof:name":"Jjs Gifts & Things",
    "wof:placetype":"venue"
},
  "geometry": {"coordinates":[-91.116502,40.809908],"type":"Point"}
}