{
  "type": "Feature",
  "properties": {
    "addr:full":"706 Allen St Boone IA 50036",
    "addr:housenumber":"706",
    "addr:postcode":"50036",
    "addr:street":"Allen St",
    "iso:country":"US",
    "sg:address":"706 Allen St",
    "sg:city":"Boone",
    "sg:classifiers":[
        {
            "category":"Building & Trades",
            "subcategory":"Plumbing",
            "type":"Services"
        }
    ],
    "sg:phone":"+1 515 432 6762",
    "sg:postcode":"50036",
    "sg:province":"IA",
    "sg:tags":[
        "heating",
        "contractor"
    ],
    "wof:name":"Duncan Heating & Plumbing",
    "wof:placetype":"venue"
},
  "geometry": {"coordinates":[-93.878789,42.063756],"type":"Point"}
}