{
  "type": "Feature",
  "properties": {
    "iso:country":"US",
    "sg:address":"1260 3rd Ave SE",
    "sg:city":"Cedar Rapids",
    "sg:classifiers":[
        {
            "category":"Health Services",
            "subcategory":"Doctor",
            "type":"Services"
        }
    ],
    "sg:phone":"+1 319 363 2682",
    "sg:postcode":"52403",
    "sg:province":"IA",
    "sg:tags":[
        "obstetrician",
        "gynecologist"
    ],
    "wof:name":"Linn County OB-Gyn PC",
    "wof:placetype":"venue"
},
  "geometry": {"coordinates":[-91.65419799999999,41.9842],"type":"Point"}
}