{
  "type": "Feature",
  "properties": {
    "iso:country":"US",
    "sg:address":"1350 Boyson Rd",
    "sg:city":"Hiawatha",
    "sg:classifiers":[
        {
            "category":"Health Services",
            "subcategory":"Doctor",
            "type":"Services"
        }
    ],
    "sg:phone":"+1 319 395 0159",
    "sg:postcode":"52233",
    "sg:province":"IA",
    "sg:tags":[
        "dentist"
    ],
    "wof:name":"Family Dentistry",
    "wof:placetype":"venue"
},
  "geometry": {"coordinates":[-91.690066,42.044294],"type":"Point"}
}