{
  "type": "Feature",
  "properties": {
    "iso:country":"US",
    "sg:address":"3849 N Brady St",
    "sg:city":"Davenport",
    "sg:classifiers":[
        {
            "category":"Shopping",
            "subcategory":"Musical Instruments",
            "type":"Retail Goods"
        }
    ],
    "sg:phone":"+1 563 391 9000",
    "sg:postcode":"52806",
    "sg:province":"IA",
    "sg:website":"www.griggsmusic.com",
    "wof:name":"Griggs Music",
    "wof:placetype":"venue"
},
  "geometry": {"coordinates":[-90.568231,41.560178],"type":"Point"}
}