{
  "type": "Feature",
  "properties": {
    "addr:full":"221 Rose Ave Swisher IA 52338",
    "addr:housenumber":"221",
    "addr:postcode":"52338",
    "addr:street":"Rose Ave",
    "iso:country":"US",
    "sg:address":"221 Rose Ave",
    "sg:city":"Swisher",
    "sg:classifiers":[
        {
            "category":"Shopping",
            "subcategory":"Hobbies, Toys, & Games",
            "type":"Retail Goods"
        }
    ],
    "sg:phone":"+1 319 857 5006",
    "sg:postcode":"52338",
    "sg:province":"IA",
    "sg:tags":[
        "product",
        "ceramic"
    ],
    "wof:name":"E & R Creations Ceramic & Gift",
    "wof:placetype":"venue"
},
  "geometry": {"coordinates":[-91.69439800000001,41.845338],"type":"Point"}
}