{
  "type": "Feature",
  "properties": {
    "addr:full":"2415 McKinley Ave Des Moines IA 50321",
    "addr:housenumber":"2415",
    "addr:postcode":"50321",
    "addr:street":"Mckinley Ave",
    "iso:country":"US",
    "sg:address":"2415 McKinley Ave",
    "sg:city":"Des Moines",
    "sg:classifiers":[
        {
            "category":"Shopping",
            "type":"Retail Goods"
        }
    ],
    "sg:phone":"+1 515 285 6759",
    "sg:postcode":"50321",
    "sg:province":"IA",
    "sg:tags":[
        "wedding",
        "supply"
    ],
    "wof:name":"Tommy's Dove Release",
    "wof:placetype":"venue"
},
  "geometry": {"coordinates":[-93.645094,41.540983],"type":"Point"}
}