{
  "type": "Feature",
  "properties": {
    "iso:country":"US",
    "sg:address":"2724 360th St",
    "sg:city":"Buffalo Center",
    "sg:classifiers":[
        {
            "category":"Sports & Exercise",
            "subcategory":"Golf",
            "type":"Entertainment"
        }
    ],
    "sg:phone":"+1 641 926 5393",
    "sg:postcode":"50424",
    "sg:province":"IA",
    "sg:tags":[
        "course"
    ],
    "wof:name":"Gruis",
    "wof:placetype":"venue"
},
  "geometry": {"coordinates":[-93.934262,43.284168],"type":"Point"}
}