{
  "type": "Feature",
  "properties": {
    "iso:country":"US",
    "sg:address":"812 E Ohio St",
    "sg:city":"Lenox",
    "sg:classifiers":[
        {
            "category":"Freight",
            "type":"Transportation"
        }
    ],
    "sg:phone":"+1 641 333 2760",
    "sg:postcode":"50851",
    "sg:province":"IA",
    "sg:tags":[
        "local",
        "storage",
        "trucking"
    ],
    "wof:name":"Rl Dougherty Inc",
    "wof:placetype":"venue"
},
  "geometry": {"coordinates":[-94.54795,40.882508],"type":"Point"}
}