{
  "type": "Feature",
  "properties": {
    "iso:country":"US",
    "sg:address":"2011 7th Ave",
    "sg:city":"Camanche",
    "sg:classifiers":[
        {
            "category":"Manufacturing",
            "subcategory":"Metals",
            "type":"Manufacturing & Wholesale Goods"
        }
    ],
    "sg:phone":"+1 563 242 0000",
    "sg:postcode":"52730",
    "sg:province":"IA",
    "sg:tags":[
        "steel",
        "mills"
    ],
    "wof:name":"Ipsco Tubulars Inc",
    "wof:placetype":"venue"
},
  "geometry": {"coordinates":[-90.25778099999999,41.79894],"type":"Point"}
}