{
  "type": "Feature",
  "properties": {
    "addr:full":"20717 State Hwy 1 Keosauqua IA 52565",
    "addr:housenumber":"20717",
    "addr:postcode":"52565",
    "addr:street":"State Hwy 1",
    "iso:country":"US",
    "sg:address":"20717 State Hwy 1",
    "sg:city":"Keosauqua",
    "sg:classifiers":[
        {
            "category":"Recreation",
            "type":"Entertainment"
        }
    ],
    "sg:phone":"+1 319 293 3897",
    "sg:postcode":"52565",
    "sg:province":"IA",
    "sg:tags":[
        "charter",
        "canoe"
    ],
    "wof:name":"Hawkeye Canoe Rental",
    "wof:placetype":"venue"
},
  "geometry": {"coordinates":[-91.95802999999999,40.743746],"type":"Point"}
}