{
  "type": "Feature",
  "properties": {
    "iso:country":"US",
    "sg:address":"2600 Myrtle St",
    "sg:city":"Sioux City",
    "sg:classifiers":[
        {
            "category":"Social Services",
            "subcategory":"Child Care",
            "type":"Services"
        }
    ],
    "sg:phone":"+1 712 252 2878",
    "sg:postcode":"51103",
    "sg:province":"IA",
    "wof:name":"Busy Bees Daycare Ctr",
    "wof:placetype":"venue"
},
  "geometry": {"coordinates":[-96.422713,42.517761],"type":"Point"}
}