{
  "type": "Feature",
  "properties": {
    "addr:full":"710 Maple St Shenandoah IA 51601",
    "addr:housenumber":"710",
    "addr:postcode":"51601",
    "addr:street":"Maple St",
    "iso:country":"US",
    "sg:address":"710 Maple St",
    "sg:city":"Shenandoah",
    "sg:classifiers":[
        {
            "category":"Shopping",
            "subcategory":"Gifts & Souvenirs",
            "type":"Retail Goods"
        }
    ],
    "sg:phone":"+1 712 246 3408",
    "sg:postcode":"51601",
    "sg:province":"IA",
    "sg:tags":[
        "shop"
    ],
    "wof:name":"Gift Shop",
    "wof:placetype":"venue"
},
  "geometry": {"coordinates":[-95.375167,40.760205],"type":"Point"}
}