{
  "type": "Feature",
  "properties": {
    "addr:full":"205 Water St Cambridge IA 50046",
    "addr:housenumber":"205",
    "addr:postcode":"50046",
    "addr:street":"Water St",
    "iso:country":"US",
    "sg:address":"205 Water St",
    "sg:city":"Cambridge",
    "sg:classifiers":[
        {
            "category":"Banks & Credit Unions",
            "subcategory":"Bank",
            "type":"Services"
        }
    ],
    "sg:phone":"+1 515 597 2500",
    "sg:postcode":"50046",
    "sg:province":"IA",
    "wof:name":"Fidelity Bank",
    "wof:placetype":"venue"
},
  "geometry": {"coordinates":[-93.52926100000001,41.899222],"type":"Point"}
}