{
  "type": "Feature",
  "properties": {
    "iso:country":"US",
    "sg:address":"1611 1st Ave N",
    "sg:city":"Fort Dodge",
    "sg:classifiers":[
        {
            "category":"Health Services",
            "subcategory":"Doctor",
            "type":"Services"
        }
    ],
    "sg:phone":"+1 515 576 5646",
    "sg:postcode":"50501",
    "sg:province":"IA",
    "sg:tags":[
        "dentist"
    ],
    "wof:name":"Lance Crawford DDS",
    "wof:placetype":"venue"
},
  "geometry": {"coordinates":[-94.175821,42.507236],"type":"Point"}
}