{
  "type": "Feature",
  "properties": {
    "iso:country":"US",
    "sg:address":"917 Central Ave",
    "sg:city":"Fort Dodge",
    "sg:classifiers":[
        {
            "category":"Professional",
            "subcategory":"Computer Services",
            "type":"Services"
        }
    ],
    "sg:phone":"+1 515 955 1005",
    "sg:postcode":"50501",
    "sg:province":"IA",
    "sg:tags":[
        "information",
        "technology"
    ],
    "sg:website":"www.utai.com",
    "wof:name":"Universal Technologies Assoc",
    "wof:placetype":"venue"
},
  "geometry": {"coordinates":[-94.185689,42.505233],"type":"Point"}
}