{
  "type": "Feature",
  "properties": {
    "iso:country":"US",
    "sg:address":"206 W State St",
    "sg:city":"Williamsburg",
    "sg:classifiers":[
        {
            "category":"Professional",
            "subcategory":"Accounting & Tax Preparation",
            "type":"Services"
        }
    ],
    "sg:phone":"+1 319 668 1560",
    "sg:postcode":"52361",
    "sg:province":"IA",
    "sg:tags":[
        "accountant"
    ],
    "wof:name":"Rose & Weinbrenner",
    "wof:placetype":"venue"
},
  "geometry": {"coordinates":[-92.010049,41.661848],"type":"Point"}
}