{
  "type": "Feature",
  "properties": {
    "iso:country":"US",
    "sg:address":"1900 Ingersoll Ave",
    "sg:city":"Des Moines",
    "sg:classifiers":[
        {
            "category":"Insurance",
            "subcategory":"Insurance Agent",
            "type":"Services"
        }
    ],
    "sg:phone":"+1 515 244 4172",
    "sg:postcode":"50309",
    "sg:province":"IA",
    "wof:name":"Steadman & Blackburn Insurance",
    "wof:placetype":"venue"
},
  "geometry": {"coordinates":[-93.644797,41.585732],"type":"Point"}
}