{
  "type": "Feature",
  "properties": {
    "addr:full":"209 150th St West Bend IA 50597",
    "addr:housenumber":"209",
    "addr:postcode":"50597",
    "addr:street":"150Th St",
    "iso:country":"US",
    "sg:address":"209 150th St",
    "sg:city":"West Bend",
    "sg:classifiers":[
        {
            "category":"Freight",
            "type":"Transportation"
        }
    ],
    "sg:phone":"+1 515 887 5346",
    "sg:postcode":"50597",
    "sg:province":"IA",
    "sg:tags":[
        "operator",
        "trucking"
    ],
    "wof:name":"R&R & Sons",
    "wof:placetype":"venue"
},
  "geometry": {"coordinates":[-94.39701599999999,42.980359],"type":"Point"}
}