{
  "type": "Feature",
  "properties": {
    "iso:country":"US",
    "sg:address":"515 N Adams St",
    "sg:city":"Carroll",
    "sg:classifiers":[
        {
            "category":"Government",
            "subcategory":"Office",
            "type":"Public Place"
        }
    ],
    "sg:phone":"+1 712 792 5269",
    "sg:postcode":"51401",
    "sg:province":"IA",
    "sg:tags":[
        "state",
        "program"
    ],
    "wof:name":"Transportation-Drivers License",
    "wof:placetype":"venue"
},
  "geometry": {"coordinates":[-94.86883,42.065872],"type":"Point"}
}