{
  "type": "Feature",
  "properties": {
    "iso:country":"US",
    "sg:address":"309 Montgomery St",
    "sg:city":"Decorah",
    "sg:classifiers":[
        {
            "category":"Retail",
            "subcategory":"Repair Shop",
            "type":"Services"
        }
    ],
    "sg:phone":"+1 563 382 3374",
    "sg:postcode":"52101",
    "sg:province":"IA",
    "sg:tags":[
        "lock",
        "locksmith"
    ],
    "wof:name":"Roger's Lock & Key",
    "wof:placetype":"venue"
},
  "geometry": {"coordinates":[-91.77659199999999,43.302116],"type":"Point"}
}