{
  "type": "Feature",
  "properties": {
    "iso:country":"US",
    "sg:address":"1440 Locust St",
    "sg:city":"Des Moines",
    "sg:classifiers":[
        {
            "category":"Professional",
            "subcategory":"Lawyer & Legal Services",
            "type":"Services"
        }
    ],
    "sg:phone":"+1 515 287 0402",
    "sg:postcode":"50309",
    "sg:province":"IA",
    "sg:tags":[
        "attorney"
    ],
    "wof:name":"Lora M Jorgensen",
    "wof:placetype":"venue"
},
  "geometry": {"coordinates":[-93.63616399999999,41.584407],"type":"Point"}
}