{
  "type": "Feature",
  "properties": {
    "addr:full":"3902 1st Ave NE Cedar Rapids IA 52402",
    "addr:housenumber":"3902",
    "addr:postcode":"52402",
    "addr:street":"1St Ave Ne",
    "iso:country":"US",
    "sg:address":"3902 1st Ave NE",
    "sg:city":"Cedar Rapids",
    "sg:classifiers":[
        {
            "category":"Health Services",
            "subcategory":"Clinic",
            "type":"Services"
        }
    ],
    "sg:phone":"+1 319 369 6911",
    "sg:postcode":"52402",
    "sg:province":"IA",
    "sg:tags":[
        "examination",
        "insurance"
    ],
    "wof:name":"APPS",
    "wof:placetype":"venue"
},
  "geometry": {"coordinates":[-91.632532,42.019426],"type":"Point"}
}