{
  "type": "Feature",
  "properties": {
    "iso:country":"US",
    "sg:address":"905 25th St SW",
    "sg:city":"Spencer",
    "sg:classifiers":[
        {
            "category":"Health Services",
            "subcategory":"Medical Lab",
            "type":"Services"
        }
    ],
    "sg:phone":"+1 712 262 7162",
    "sg:postcode":"51301",
    "sg:province":"IA",
    "sg:tags":[
        "laboratory",
        "dental"
    ],
    "wof:name":"Spencer Dental Arts",
    "wof:placetype":"venue"
},
  "geometry": {"coordinates":[-95.157456,43.112313],"type":"Point"}
}