{
  "type": "Feature",
  "properties": {
    "iso:country":"US",
    "sg:address":"902 W Madison St",
    "sg:city":"Knoxville",
    "sg:classifiers":[
        {
            "category":"Personal",
            "subcategory":"Hair Removal",
            "type":"Services"
        }
    ],
    "sg:phone":"+1 641 780 4717",
    "sg:postcode":"50138",
    "sg:province":"IA",
    "wof:name":"RAC Credit Reparation",
    "wof:placetype":"venue"
},
  "geometry": {"coordinates":[-93.107179,41.313426],"type":"Point"}
}