{
  "type": "Feature",
  "properties": {
    "iso:country":"US",
    "sg:address":"301 W Webster St",
    "sg:city":"Wyoming",
    "sg:classifiers":[
        {
            "category":"Manufacturing",
            "subcategory":"Printing",
            "type":"Manufacturing & Wholesale Goods"
        }
    ],
    "sg:phone":"+1 563 488 2281",
    "sg:postcode":"52362",
    "sg:province":"IA",
    "sg:tags":[
        "newspaper"
    ],
    "wof:name":"Midland Times",
    "wof:placetype":"venue"
},
  "geometry": {"coordinates":[-91.01136,42.059773],"type":"Point"}
}