{
  "type": "Feature",
  "properties": {
    "addr:full":"20421 210th St Hawkeye IA 52147",
    "addr:housenumber":"20421",
    "addr:postcode":"52147",
    "addr:street":"210Th St",
    "iso:country":"US",
    "sg:address":"20421 210th St",
    "sg:city":"Hawkeye",
    "sg:phone":"+1 563 427 3769",
    "sg:postcode":"52147",
    "sg:province":"IA",
    "sg:tags":[
        "farm",
        "corn",
        "soybean"
    ],
    "wof:name":"James Hyman",
    "wof:placetype":"venue"
},
  "geometry": {"coordinates":[-91.983048,42.935762],"type":"Point"}
}