{
  "type": "Feature",
  "properties": {
    "addr:full":"105 Douglas St Merrill IA 51038",
    "addr:housenumber":"105",
    "addr:postcode":"51038",
    "addr:street":"Douglas St",
    "iso:country":"US",
    "sg:address":"105 Douglas St",
    "sg:city":"Merrill",
    "sg:classifiers":[
        {
            "category":"Manufacturing",
            "subcategory":"Tools & Machinery",
            "type":"Manufacturing & Wholesale Goods"
        }
    ],
    "sg:phone":"+1 712 938 3119",
    "sg:postcode":"51038",
    "sg:province":"IA",
    "sg:tags":[
        "machine",
        "shop"
    ],
    "wof:name":"Custom Crankshaft",
    "wof:placetype":"venue"
},
  "geometry": {"coordinates":[-96.247236,42.718946],"type":"Point"}
}