{
  "type": "Feature",
  "properties": {
    "addr:full":"20554 R Ave Hawkeye IA 52147",
    "addr:housenumber":"20554",
    "addr:postcode":"52147",
    "addr:street":"R Ave",
    "iso:country":"US",
    "sg:address":"20554 R Ave",
    "sg:city":"Hawkeye",
    "sg:classifiers":[
        {
            "category":"Organizations",
            "subcategory":"Religious Organization",
            "type":"Services"
        }
    ],
    "sg:phone":"+1 563 427 3476",
    "sg:postcode":"52147",
    "sg:province":"IA",
    "wof:name":"His Hands Evangelistic Assn",
    "wof:placetype":"venue"
},
  "geometry": {"coordinates":[-91.94338,42.926092],"type":"Point"}
}