{
  "type": "Feature",
  "properties": {
    "iso:country":"US",
    "sg:address":"1050 Dale Dr",
    "sg:city":"Hudson",
    "sg:classifiers":[
        {
            "category":"Manufacturing",
            "subcategory":"Printing",
            "type":"Manufacturing & Wholesale Goods"
        }
    ],
    "sg:phone":"+1 319 988 3306",
    "sg:postcode":"50643",
    "sg:province":"IA",
    "sg:tags":[
        "printer"
    ],
    "sg:website":"www.autobodyonline.com",
    "wof:name":"Pagetek Printing & Design",
    "wof:placetype":"venue"
},
  "geometry": {"coordinates":[-92.448549,42.414874],"type":"Point"}
}