{
  "type": "Feature",
  "properties": {
    "addr:full":"1650 State Hwy 92 Fontanelle IA 50846",
    "addr:housenumber":"1650",
    "addr:postcode":"50846",
    "addr:street":"State Hwy 92",
    "iso:country":"US",
    "sg:address":"1650 State Hwy 92",
    "sg:city":"Fontanelle",
    "sg:classifiers":[
        {
            "category":"Building & Trades",
            "subcategory":"Construction",
            "type":"Services"
        }
    ],
    "sg:phone":"+1 641 745 4181",
    "sg:postcode":"50846",
    "sg:province":"IA",
    "sg:tags":[
        "drainage",
        "contractor"
    ],
    "wof:name":"Cummins Construction Co",
    "wof:placetype":"venue"
},
  "geometry": {"coordinates":[-94.580912,41.287462],"type":"Point"}
}