{
  "type": "Feature",
  "properties": {
    "iso:country":"US",
    "sg:address":"1028 N 18th St",
    "sg:city":"Centerville",
    "sg:classifiers":[
        {
            "category":"Restaurant",
            "type":"Food & Drink"
        }
    ],
    "sg:phone":"+1 641 437 4488",
    "sg:postcode":"52544",
    "sg:province":"IA",
    "sg:website":"www.subway.com",
    "wof:name":"Subway Sandwiches & Salads",
    "wof:placetype":"venue"
},
  "geometry": {"coordinates":[-92.868117,40.742554],"type":"Point"}
}