{
  "type": "Feature",
  "properties": {
    "addr:full":"60451 110th Ave Fonda IA 50540",
    "addr:housenumber":"60451",
    "addr:postcode":"50540",
    "addr:street":"110Th Ave",
    "iso:country":"US",
    "sg:address":"60451 110th Ave",
    "sg:city":"Fonda",
    "sg:phone":"+1 712 288 6520",
    "sg:postcode":"50540",
    "sg:province":"IA",
    "sg:tags":[
        "farm",
        "corn",
        "soybean"
    ],
    "wof:name":"James Wernimont",
    "wof:placetype":"venue"
},
  "geometry": {"coordinates":[-94.89469800000001,42.61167],"type":"Point"}
}