{
  "type": "Feature",
  "properties": {
    "addr:full":"4712 Mount Vernon Rd SE Cedar Rapids IA 52403",
    "addr:housenumber":"4712",
    "addr:postcode":"52403",
    "addr:street":"Mount Vernon Rd Se",
    "iso:country":"US",
    "sg:address":"4712 Mount Vernon Rd SE",
    "sg:city":"Cedar Rapids",
    "sg:classifiers":[
        {
            "category":"Autos & Motor Vehicles",
            "subcategory":"Automobile Sales",
            "type":"Retail Goods"
        }
    ],
    "sg:phone":"+1 319 362 1990",
    "sg:postcode":"52403",
    "sg:province":"IA",
    "sg:tags":[
        "used"
    ],
    "wof:name":"Below Book Autos",
    "wof:placetype":"venue"
},
  "geometry": {"coordinates":[-91.59615700000001,41.976903],"type":"Point"}
}