{
  "type": "Feature",
  "properties": {
    "iso:country":"US",
    "sg:address":"124 W Ashland Ave",
    "sg:city":"Indianola",
    "sg:classifiers":[
        {
            "category":"Shopping",
            "subcategory":"Books",
            "type":"Retail Goods"
        }
    ],
    "sg:phone":"+1 515 961 2886",
    "sg:postcode":"50125",
    "sg:province":"IA",
    "sg:tags":[
        "dealer"
    ],
    "wof:name":"ARK",
    "wof:placetype":"venue"
},
  "geometry": {"coordinates":[-93.56118600000001,41.361417],"type":"Point"}
}