{
  "type": "Feature",
  "properties": {
    "iso:country":"US",
    "sg:address":"17405 246th Ave",
    "sg:city":"Pleasant Valley",
    "sg:classifiers":[
        {
            "category":"Professional",
            "subcategory":"Research",
            "type":"Services"
        }
    ],
    "sg:phone":"+1 563 332 6870",
    "sg:postcode":"52767",
    "sg:province":"IA",
    "sg:tags":[
        "environmental",
        "ecological"
    ],
    "wof:name":"Environmental Planning Strgs",
    "wof:placetype":"venue"
},
  "geometry": {"coordinates":[-90.425301,41.559968],"type":"Point"}
}