{
  "type": "Feature",
  "properties": {
    "addr:full":"1231 Broadway Denison IA 51442",
    "addr:housenumber":"1231",
    "addr:postcode":"51442",
    "addr:street":"Broadway",
    "iso:country":"US",
    "sg:address":"1231 Broadway",
    "sg:city":"Denison",
    "sg:classifiers":[
        {
            "category":"Personal",
            "subcategory":"Shoe Repair & Shine",
            "type":"Services"
        }
    ],
    "sg:phone":"+1 712 263 2665",
    "sg:postcode":"51442",
    "sg:province":"IA",
    "sg:tags":[
        "repairing",
        "boot"
    ],
    "wof:name":"Ed's Shoe Svc",
    "wof:placetype":"venue"
},
  "geometry": {"coordinates":[-95.35603500000001,42.01667],"type":"Point"}
}