{
  "type": "Feature",
  "properties": {
    "addr:full":"440 Iowa Ave Martensdale IA 50160",
    "addr:housenumber":"440",
    "addr:postcode":"50160",
    "addr:street":"Iowa Ave",
    "iso:country":"US",
    "sg:address":"440 Iowa Ave",
    "sg:city":"Martensdale",
    "sg:classifiers":[
        {
            "category":"Retail",
            "subcategory":"Auto Repair",
            "type":"Services"
        }
    ],
    "sg:phone":"+1 641 764 2343",
    "sg:postcode":"50160",
    "sg:province":"IA",
    "sg:tags":[
        "body",
        "automobile",
        "painting"
    ],
    "wof:name":"O'Mara Auto Body",
    "wof:placetype":"venue"
},
  "geometry": {"coordinates":[-93.74009100000001,41.373693],"type":"Point"}
}