{
  "type": "Feature",
  "properties": {
    "addr:full":"2001 W 10th St Spencer IA 51301",
    "addr:housenumber":"2001",
    "addr:postcode":"51301",
    "addr:street":"W 10Th St",
    "iso:country":"US",
    "sg:address":"2001 W 10th St",
    "sg:city":"Spencer",
    "sg:classifiers":[
        {
            "category":"Personal",
            "type":"Services"
        }
    ],
    "sg:phone":"+1 712 262 3272",
    "sg:postcode":"51301",
    "sg:province":"IA",
    "wof:name":"Lil Miss Fancy Pants",
    "wof:placetype":"venue"
},
  "geometry": {"coordinates":[-95.17289700000001,43.147363],"type":"Point"}
}