{
  "type": "Feature",
  "properties": {
    "addr:full":"501 Court St Williamsburg IA 52361",
    "addr:housenumber":"501",
    "addr:postcode":"52361",
    "addr:street":"Court St",
    "iso:country":"US",
    "sg:address":"501 Court St",
    "sg:city":"Williamsburg",
    "sg:classifiers":[
        {
            "category":"Restaurant",
            "type":"Food & Drink"
        }
    ],
    "sg:phone":"+1 319 668 1694",
    "sg:postcode":"52361",
    "sg:province":"IA",
    "wof:name":"Dinner Bell Cafe & Lounge",
    "wof:placetype":"venue"
},
  "geometry": {"coordinates":[-92.00883399999999,41.661759],"type":"Point"}
}