{
  "type": "Feature",
  "properties": {
    "iso:country":"US",
    "sg:address":"151 4th St",
    "sg:city":"Des Moines",
    "sg:classifiers":[
        {
            "category":"Parking",
            "type":"Transportation"
        }
    ],
    "sg:phone":"+1 515 242 0022",
    "sg:postcode":"50309",
    "sg:province":"IA",
    "sg:tags":[
        "garage"
    ],
    "wof:name":"Parking Inc",
    "wof:placetype":"venue"
},
  "geometry": {"coordinates":[-93.62140599999999,41.584445],"type":"Point"}
}