{
  "type": "Feature",
  "properties": {
    "iso:country":"US",
    "sg:address":"216 W 4th St",
    "sg:city":"Vinton",
    "sg:classifiers":[
        {
            "category":"Organizations",
            "subcategory":"Non-profit Organization",
            "type":"Services"
        }
    ],
    "sg:phone":"+1 319 472 2443",
    "sg:postcode":"52349",
    "sg:province":"IA",
    "sg:tags":[
        "information",
        "alcoholism",
        "treatment"
    ],
    "wof:name":"Area Substance Abuse Council",
    "wof:placetype":"venue"
},
  "geometry": {"coordinates":[-92.026646,42.16763],"type":"Point"}
}