{
  "type": "Feature",
  "properties": {
    "iso:country":"US",
    "sg:address":"220 S Riverside Dr",
    "sg:city":"Ames",
    "sg:classifiers":[
        {
            "category":"Professional",
            "subcategory":"Business Services",
            "type":"Services"
        }
    ],
    "sg:phone":"+1 515 233 4695",
    "sg:postcode":"50010",
    "sg:province":"IA",
    "wof:name":"Buena Vista Partners LLC",
    "wof:placetype":"venue"
},
  "geometry": {"coordinates":[-93.62949500000001,42.020462],"type":"Point"}
}