{
  "type": "Feature",
  "properties": {
    "addr:full":"2510 26th Street Dr SE Cedar Rapids IA 52403",
    "addr:housenumber":"2510",
    "addr:postcode":"52403",
    "addr:street":"26Th Street Dr Se",
    "iso:country":"US",
    "sg:address":"2510 26th Street Dr SE",
    "sg:city":"Cedar Rapids",
    "sg:classifiers":[
        {
            "category":"Professional",
            "type":"Services"
        }
    ],
    "sg:phone":"+1 319 363 9088",
    "sg:postcode":"52403",
    "sg:province":"IA",
    "wof:name":"Writers Ink",
    "wof:placetype":"venue"
},
  "geometry": {"coordinates":[-91.631709,42.001412],"type":"Point"}
}