{
  "type": "Feature",
  "properties": {
    "iso:country":"US",
    "sg:address":"335 1st St N",
    "sg:city":"Winthrop",
    "sg:classifiers":[
        {
            "category":"Shopping",
            "type":"Retail Goods"
        }
    ],
    "sg:phone":"+1 319 935 3564",
    "sg:postcode":"50682",
    "sg:province":"IA",
    "sg:tags":[
        "trophy",
        "medal",
        "award"
    ],
    "wof:name":"Trott Trophies",
    "wof:placetype":"venue"
},
  "geometry": {"coordinates":[-91.73178900000001,42.475424],"type":"Point"}
}