{
  "type": "Feature",
  "properties": {
    "addr:full":"1725 Rockingham Rd Davenport IA 52802",
    "addr:housenumber":"1725",
    "addr:postcode":"52802",
    "addr:street":"Rockingham Rd",
    "iso:country":"US",
    "sg:address":"1725 Rockingham Rd",
    "sg:city":"Davenport",
    "sg:classifiers":[
        {
            "category":"Manufacturing",
            "subcategory":"Chemicals & Compounds",
            "type":"Manufacturing & Wholesale Goods"
        }
    ],
    "sg:phone":"+1 563 324 5317",
    "sg:postcode":"52802",
    "sg:province":"IA",
    "sg:tags":[
        "gas"
    ],
    "wof:name":"BOC Gases",
    "wof:placetype":"venue"
},
  "geometry": {"coordinates":[-90.601163,41.519495],"type":"Point"}
}