{
  "type": "Feature",
  "properties": {
    "addr:full":"400 Washington St Burlington IA 52601",
    "addr:housenumber":"400",
    "addr:postcode":"52601",
    "addr:street":"Washington St",
    "iso:country":"US",
    "sg:address":"400 Washington St",
    "sg:city":"Burlington",
    "sg:classifiers":[
        {
            "category":"Government",
            "subcategory":"Office",
            "type":"Public Place"
        }
    ],
    "sg:phone":"+1 319 753 8123",
    "sg:postcode":"52601",
    "sg:province":"IA",
    "sg:tags":[
        "city",
        "taxation"
    ],
    "wof:name":"Burlington Finance Dept",
    "wof:placetype":"venue"
},
  "geometry": {"coordinates":[-91.104744,40.811243],"type":"Point"}
}