{
  "type": "Feature",
  "properties": {
    "iso:country":"US",
    "sg:address":"1325 Reed Ave",
    "sg:city":"Sumner",
    "sg:classifiers":[
        {
            "category":"Professional",
            "subcategory":"Business Services",
            "type":"Services"
        }
    ],
    "sg:phone":"+1 319 882 4474",
    "sg:postcode":"50674",
    "sg:province":"IA",
    "wof:name":"Roger Quigley Col/Auctioneer",
    "wof:placetype":"venue"
},
  "geometry": {"coordinates":[-92.218892,42.85804],"type":"Point"}
}