{
  "type": "Feature",
  "properties": {
    "iso:country":"US",
    "sg:address":"1659 334th Rd",
    "sg:city":"Madrid",
    "sg:classifiers":[
        {
            "category":"Shopping",
            "subcategory":"Luggage & Leather Goods",
            "type":"Retail Goods"
        },
        {
            "category":"Wholesale",
            "subcategory":"Non-durable Goods",
            "type":"Manufacturing & Wholesale Goods"
        }
    ],
    "sg:phone":"+1 515 795 2115",
    "sg:postcode":"50156",
    "sg:province":"IA",
    "sg:tags":[
        "work",
        "custom"
    ],
    "wof:name":"Straps Leather and Tack",
    "wof:placetype":"venue"
},
  "geometry": {"coordinates":[-93.838047,41.877987],"type":"Point"}
}