{
  "type": "Feature",
  "properties": {
    "iso:country":"US",
    "sg:address":"429 Arizona Ave SW",
    "sg:city":"Orange City",
    "sg:classifiers":[
        {
            "category":"Wholesale",
            "subcategory":"Toys & Hobbies",
            "type":"Manufacturing & Wholesale Goods"
        }
    ],
    "sg:phone":"+1 712 737 2946",
    "sg:postcode":"51041",
    "sg:province":"IA",
    "wof:name":"Delicate Dolls",
    "wof:placetype":"venue"
},
  "geometry": {"coordinates":[-96.05967200000001,43.002326],"type":"Point"}
}