{
  "type": "Feature",
  "properties": {
    "addr:full":"4475 121st St Urbandale IA 50323",
    "addr:housenumber":"4475",
    "addr:postcode":"50323",
    "addr:street":"121St St",
    "iso:country":"US",
    "sg:address":"4475 121st St",
    "sg:city":"Urbandale",
    "sg:classifiers":[
        {
            "category":"Manufacturing",
            "subcategory":"Motor Vehicles & Parts",
            "type":"Manufacturing & Wholesale Goods"
        }
    ],
    "sg:phone":"+1 515 276 1066",
    "sg:postcode":"50323",
    "sg:province":"IA",
    "sg:tags":[
        "automobile",
        "supply"
    ],
    "sg:website":"www.bellautomotive.com",
    "wof:name":"Bell Automotive Products",
    "wof:placetype":"venue"
},
  "geometry": {"coordinates":[-93.781446,41.641348],"type":"Point"}
}