{
  "type": "Feature",
  "properties": {
    "iso:country":"US",
    "sg:address":"980 73rd St",
    "sg:city":"Windsor Heights",
    "sg:classifiers":[
        {
            "category":"Shopping",
            "subcategory":"Used Merchandise",
            "type":"Retail Goods"
        }
    ],
    "sg:phone":"+1 515 223 5104",
    "sg:postcode":"50312",
    "sg:province":"IA",
    "sg:tags":[
        "antique"
    ],
    "wof:name":"Time Passages LTD",
    "wof:placetype":"venue"
},
  "geometry": {"coordinates":[-93.71760999999999,41.595174],"type":"Point"}
}