{
  "type": "Feature",
  "properties": {
    "iso:country":"US",
    "sg:address":"40135 State Hwy 37",
    "sg:city":"Soldier",
    "sg:phone":"+1 712 884 2583",
    "sg:postcode":"51572",
    "sg:province":"IA",
    "sg:tags":[
        "farm",
        "corn"
    ],
    "wof:name":"Gordon Foss Farm",
    "wof:placetype":"venue"
},
  "geometry": {"coordinates":[-95.76988799999999,41.977555],"type":"Point"}
}