{
  "type": "Feature",
  "properties": {
    "iso:country":"US",
    "sg:address":"534 2100th St",
    "sg:city":"Earling",
    "sg:phone":"+1 712 747 3291",
    "sg:postcode":"51530",
    "sg:province":"IA",
    "sg:tags":[
        "farm",
        "corn",
        "soybean"
    ],
    "wof:name":"Lawrence Schaben",
    "wof:placetype":"venue"
},
  "geometry": {"coordinates":[-95.472565,41.805337],"type":"Point"}
}