{
  "type": "Feature",
  "properties": {
    "iso:country":"US",
    "sg:address":"205 4th St",
    "sg:city":"Akron",
    "sg:classifiers":[
        {
            "category":"Health Services",
            "subcategory":"Health Practitioner",
            "type":"Services"
        }
    ],
    "sg:phone":"+1 712 568 3700",
    "sg:postcode":"51001",
    "sg:province":"IA",
    "sg:tags":[
        "paramedic"
    ],
    "wof:name":"Siouxland Paramedics",
    "wof:placetype":"venue"
},
  "geometry": {"coordinates":[-96.557101,42.827694],"type":"Point"}
}