{
  "type": "Feature",
  "properties": {
    "iso:country":"US",
    "sg:address":"105 E Broadway St",
    "sg:city":"Paullina",
    "sg:classifiers":[
        {
            "category":"Restaurant",
            "type":"Food & Drink"
        }
    ],
    "sg:phone":"+1 712 448 2428",
    "sg:postcode":"51046",
    "sg:province":"IA",
    "wof:name":"Monte's Steak House",
    "wof:placetype":"venue"
},
  "geometry": {"coordinates":[-95.687049,42.979272],"type":"Point"}
}