{
  "type": "Feature",
  "properties": {
    "addr:full":"1519 6th St SW Cedar Rapids IA 52404",
    "addr:housenumber":"1519",
    "addr:postcode":"52404",
    "addr:street":"6Th St Sw",
    "iso:country":"US",
    "sg:address":"1519 6th St SW",
    "sg:city":"Cedar Rapids",
    "sg:classifiers":[
        {
            "category":"Restaurant",
            "type":"Food & Drink"
        }
    ],
    "sg:menulink":"http://www.allmenus.com/ia/cedar-rapids/154480-hardees/menu/",
    "sg:phone":"+1 319 363 7710",
    "sg:postcode":"52404",
    "sg:province":"IA",
    "sg:tags":[
        "burger",
        "american"
    ],
    "wof:name":"Hardee's",
    "wof:placetype":"venue"
},
  "geometry": {"coordinates":[-91.677053,41.962626],"type":"Point"}
}