{
  "type": "Feature",
  "properties": {
    "iso:country":"US",
    "sg:address":"919 S Market St",
    "sg:city":"Oskaloosa",
    "sg:classifiers":[
        {
            "category":"Home & Garden",
            "subcategory":"Building Materials",
            "type":"Retail Goods"
        }
    ],
    "sg:phone":"+1 641 673 8666",
    "sg:postcode":"52577",
    "sg:province":"IA",
    "sg:tags":[
        "glass",
        "window",
        "plate"
    ],
    "wof:name":"Oskaloosa Glass & Millworks",
    "wof:placetype":"venue"
},
  "geometry": {"coordinates":[-92.64513599999999,41.287464],"type":"Point"}
}