{
  "type": "Feature",
  "properties": {
    "addr:full":"1601 McPherson Ave Council Bluffs IA 51503",
    "addr:housenumber":"1601",
    "addr:postcode":"51503",
    "addr:street":"Mcpherson Ave",
    "iso:country":"US",
    "sg:address":"1601 McPherson Ave",
    "sg:city":"Council Bluffs",
    "sg:classifiers":[
        {
            "category":"Professional",
            "subcategory":"Accounting & Tax Preparation",
            "type":"Services"
        }
    ],
    "sg:phone":"+1 712 256 7271",
    "sg:postcode":"51503",
    "sg:province":"IA",
    "sg:tags":[
        "accountant"
    ],
    "wof:name":"Emmet Tinley CPA",
    "wof:placetype":"venue"
},
  "geometry": {"coordinates":[-95.822689,41.267006],"type":"Point"}
}