{
  "type": "Feature",
  "properties": {
    "iso:country":"US",
    "sg:address":"100 Interpower Ave",
    "sg:city":"Oskaloosa",
    "sg:classifiers":[
        {
            "category":"Manufacturing",
            "subcategory":"Tools & Machinery",
            "type":"Manufacturing & Wholesale Goods"
        }
    ],
    "sg:phone":"+1 641 673 5000",
    "sg:postcode":"52577",
    "sg:province":"IA",
    "sg:tags":[
        "physician",
        "surgeon"
    ],
    "sg:website":"www.interpower.com",
    "wof:name":"Panel Components Corp",
    "wof:placetype":"venue"
},
  "geometry": {"coordinates":[-92.648185,41.318645],"type":"Point"}
}