{
  "type": "Feature",
  "properties": {
    "addr:full":"1619 335th St Brighton IA 52540",
    "addr:housenumber":"1619",
    "addr:postcode":"52540",
    "addr:street":"335Th St",
    "iso:country":"US",
    "sg:address":"1619 335th St",
    "sg:city":"Brighton",
    "sg:classifiers":[
        {
            "category":"Farming",
            "subcategory":"Livestock Farm",
            "type":"Manufacturing & Wholesale Goods"
        }
    ],
    "sg:phone":"+1 319 694 2745",
    "sg:postcode":"52540",
    "sg:province":"IA",
    "sg:tags":[
        "beef",
        "feedlot",
        "cattle"
    ],
    "wof:name":"Leroy Mineart",
    "wof:placetype":"venue"
},
  "geometry": {"coordinates":[-91.82868999999999,41.166848],"type":"Point"}
}