{
  "type": "Feature",
  "properties": {
    "addr:full":"11051 NE University Ave Mitchellville IA 50169",
    "addr:housenumber":"11051",
    "addr:postcode":"50169",
    "addr:street":"Ne University Ave",
    "iso:country":"US",
    "sg:address":"11051 NE University Ave",
    "sg:city":"Mitchellville",
    "sg:classifiers":[
        {
            "category":"Retail",
            "subcategory":"Funeral Services",
            "type":"Services"
        }
    ],
    "sg:phone":"+1 515 967 0778",
    "sg:postcode":"50169",
    "sg:province":"IA",
    "sg:tags":[
        "director"
    ],
    "wof:name":"Mitchellville Funeral Home",
    "wof:placetype":"venue"
},
  "geometry": {"coordinates":[-93.40421499999999,41.600698],"type":"Point"}
}