{
  "type": "Feature",
  "properties": {
    "iso:country":"US",
    "sg:address":"401 2nd St NW",
    "sg:city":"Altoona",
    "sg:classifiers":[
        {
            "category":"Freight",
            "type":"Transportation"
        }
    ],
    "sg:phone":"+1 515 957 9798",
    "sg:postcode":"50009",
    "sg:province":"IA",
    "sg:tags":[
        "trucking"
    ],
    "wof:name":"Anderson Trucking Svc Inc",
    "wof:placetype":"venue"
},
  "geometry": {"coordinates":[-93.46665,41.653188],"type":"Point"}
}