{
  "type": "Feature",
  "properties": {
    "iso:country":"US",
    "sg:address":"2010 SE Delaware Ave",
    "sg:city":"Ankeny",
    "sg:classifiers":[
        {
            "category":"Utilities",
            "subcategory":"Mobile Phone",
            "type":"Services"
        }
    ],
    "sg:phone":"+1 515 965 8934",
    "sg:postcode":"50021",
    "sg:province":"IA",
    "sg:tags":[
        "telephone",
        "cellular"
    ],
    "wof:name":"Nextel Retail",
    "wof:placetype":"venue"
},
  "geometry": {"coordinates":[-93.58128600000001,41.7089],"type":"Point"}
}