{
  "type": "Feature",
  "properties": {
    "iso:country":"US",
    "sg:address":"1620 Country Club Ln",
    "sg:city":"Hampton",
    "sg:classifiers":[
        {
            "category":"Recreation",
            "type":"Entertainment"
        }
    ],
    "sg:phone":"+1 641 456 3256",
    "sg:postcode":"50441",
    "sg:province":"IA",
    "sg:tags":[
        "course",
        "golf"
    ],
    "wof:name":"Hampton Country Club",
    "wof:placetype":"venue"
},
  "geometry": {"coordinates":[-93.19982400000001,42.77436],"type":"Point"}
}