{
  "type": "Feature",
  "properties": {
    "addr:full":"118 Hayward Ave Ames IA 50014",
    "addr:housenumber":"118",
    "addr:postcode":"50014",
    "addr:street":"Hayward Ave",
    "iso:country":"US",
    "sg:address":"118 Hayward Ave",
    "sg:city":"Ames",
    "sg:classifiers":[
        {
            "category":"Food & Beverages",
            "subcategory":"Groceries & Convenience Stores",
            "type":"Retail Goods"
        }
    ],
    "sg:phone":"+1 515 292 2170",
    "sg:postcode":"50014",
    "sg:province":"IA",
    "sg:tags":[
        "grocer"
    ],
    "wof:name":"Morales Tienda Latina",
    "wof:placetype":"venue"
},
  "geometry": {"coordinates":[-93.651624,42.02231],"type":"Point"}
}