{
  "type": "Feature",
  "properties": {
    "addr:full":"208 W 2nd St Muscatine IA 52761",
    "addr:housenumber":"208",
    "addr:postcode":"52761",
    "addr:street":"W 2Nd St",
    "iso:country":"US",
    "sg:address":"208 W 2nd St",
    "sg:city":"Muscatine",
    "sg:classifiers":[
        {
            "category":"Professional",
            "subcategory":"Lawyer & Legal Services",
            "type":"Services"
        },
        {
            "category":"Real Estate",
            "subcategory":"Real Estate Operator",
            "type":"Services"
        }
    ],
    "sg:phone":"+1 563 263 6900",
    "sg:postcode":"52761",
    "sg:province":"IA",
    "sg:tags":[
        "building",
        "attorney",
        "nonresidential"
    ],
    "wof:name":"John Eichelberger PC",
    "wof:placetype":"venue"
},
  "geometry": {"coordinates":[-91.046823,41.420589],"type":"Point"}
}