{
  "type": "Feature",
  "properties": {
    "iso:country":"US",
    "sg:address":"1614 Fuller Rd",
    "sg:city":"West Des Moines",
    "sg:classifiers":[
        {
            "category":"Manufacturing",
            "subcategory":"Metals",
            "type":"Manufacturing & Wholesale Goods"
        }
    ],
    "sg:phone":"+1 515 225 6523",
    "sg:postcode":"50265",
    "sg:province":"IA",
    "sg:tags":[
        "harness",
        "wire"
    ],
    "wof:name":"Thorson Manufacturing Co",
    "wof:placetype":"venue"
},
  "geometry": {"coordinates":[-93.728775,41.564142],"type":"Point"}
}