{
  "type": "Feature",
  "properties": {
    "iso:country":"US",
    "sg:address":"613 Water St",
    "sg:city":"Sioux City",
    "sg:classifiers":[
        {
            "category":"Shopping",
            "subcategory":"Computers & Home Electronics",
            "type":"Retail Goods"
        }
    ],
    "sg:phone":"+1 712 252 9740",
    "sg:postcode":"51103",
    "sg:province":"IA",
    "sg:tags":[
        "audio"
    ],
    "wof:name":"Doug Johnson Audio & Video",
    "wof:placetype":"venue"
},
  "geometry": {"coordinates":[-96.409457,42.497171],"type":"Point"}
}