{
  "type": "Feature",
  "properties": {
    "iso:country":"US",
    "sg:address":"263 Manor Dr",
    "sg:city":"Osceola",
    "sg:classifiers":[
        {
            "category":"Real Estate",
            "subcategory":"Real Estate Operator",
            "type":"Services"
        }
    ],
    "sg:phone":"+1 641 342 1557",
    "sg:postcode":"50213",
    "sg:province":"IA",
    "sg:tags":[
        "apartment"
    ],
    "sg:website":"www.cohenesrey.com",
    "wof:name":"Country Club Apartments",
    "wof:placetype":"venue"
},
  "geometry": {"coordinates":[-93.758486,41.020542],"type":"Point"}
}