{
  "type": "Feature",
  "properties": {
    "iso:country":"US",
    "sg:address":"4818 Idaho Cir",
    "sg:city":"Ames",
    "sg:classifiers":[
        {
            "category":"Real Estate",
            "subcategory":"Real Estate Operator",
            "type":"Services"
        }
    ],
    "sg:phone":"+1 515 292 6676",
    "sg:postcode":"50014",
    "sg:province":"IA",
    "sg:tags":[
        "property",
        "lessor"
    ],
    "wof:name":"Maier Farm Property",
    "wof:placetype":"venue"
},
  "geometry": {"coordinates":[-93.684003,42.032382],"type":"Point"}
}