{
  "type": "Feature",
  "properties": {
    "addr:full":"118 N Oak Park Ave Colfax IA 50054",
    "addr:housenumber":"118",
    "addr:postcode":"50054",
    "addr:street":"N Oak Park Ave",
    "iso:country":"US",
    "sg:address":"118 N Oak Park Ave",
    "sg:city":"Colfax",
    "sg:classifiers":[
        {
            "category":"Government",
            "subcategory":"Office",
            "type":"Public Place"
        }
    ],
    "sg:phone":"+1 515 674 3053",
    "sg:postcode":"50054",
    "sg:province":"IA",
    "sg:tags":[
        "village"
    ],
    "wof:name":"Colfax City Office",
    "wof:placetype":"venue"
},
  "geometry": {"coordinates":[-93.23836300000001,41.677528],"type":"Point"}
}