{
  "type": "Feature",
  "properties": {
    "iso:country":"US",
    "sg:address":"62988 Upland Rd",
    "sg:city":"Griswold",
    "sg:classifiers":[
        {
            "category":"Organizations",
            "subcategory":"Religious Organization",
            "type":"Services"
        }
    ],
    "sg:phone":"+1 712 778 4485",
    "sg:postcode":"50843",
    "sg:province":"IA",
    "sg:tags":[
        "church"
    ],
    "wof:name":"St John's United Church-Christ",
    "wof:placetype":"venue"
},
  "geometry": {"coordinates":[-94.98483299999999,41.216487],"type":"Point"}
}