{
  "type": "Feature",
  "properties": {
    "iso:country":"US",
    "sg:address":"300 Potter Dr",
    "sg:city":"Bellevue",
    "sg:classifiers":[
        {
            "category":"Restaurant",
            "type":"Food & Drink"
        }
    ],
    "sg:menulink":"http://www.allmenus.com/ia/bellevue/246189-potters-mill/menu/",
    "sg:phone":"+1 563 872 3838",
    "sg:postcode":"52031",
    "sg:province":"IA",
    "sg:tags":[
        "american"
    ],
    "wof:name":"Potter's Mill",
    "wof:placetype":"venue"
},
  "geometry": {"coordinates":[-90.42036899999999,42.252104],"type":"Point"}
}