{
  "type": "Feature",
  "properties": {
    "iso:country":"US",
    "sg:address":"1434 W 6th St",
    "sg:city":"Nevada",
    "sg:classifiers":[
        {
            "category":"Building & Trades",
            "subcategory":"Construction",
            "type":"Services"
        }
    ],
    "sg:phone":"+1 515 382 3103",
    "sg:postcode":"50201",
    "sg:province":"IA",
    "sg:tags":[
        "general",
        "contractor"
    ],
    "wof:name":"Lightning Construction",
    "wof:placetype":"venue"
},
  "geometry": {"coordinates":[-93.46582100000001,42.024874],"type":"Point"}
}