{
  "type": "Feature",
  "properties": {
    "iso:country":"US",
    "sg:address":"208 Center Ave S",
    "sg:city":"Epworth",
    "sg:classifiers":[
        {
            "category":"Health Services",
            "subcategory":"Doctor",
            "type":"Services"
        }
    ],
    "sg:phone":"+1 563 876 3396",
    "sg:postcode":"52045",
    "sg:province":"IA",
    "sg:tags":[
        "dentist"
    ],
    "wof:name":"Epworth Family Dentistry",
    "wof:placetype":"venue"
},
  "geometry": {"coordinates":[-90.93194800000001,42.443954],"type":"Point"}
}