{
  "type": "Feature",
  "properties": {
    "iso:country":"US",
    "sg:address":"118 N Ida St",
    "sg:city":"Battle Creek",
    "sg:classifiers":[
        {
            "category":"Real Estate",
            "subcategory":"Real Estate Operator",
            "type":"Services"
        }
    ],
    "sg:phone":"+1 712 365 4338",
    "sg:postcode":"51006",
    "sg:province":"IA",
    "sg:tags":[
        "apartment"
    ],
    "wof:name":"Willow Dale Wellness Vlg Apts",
    "wof:placetype":"venue"
},
  "geometry": {"coordinates":[-95.59811500000001,42.316711],"type":"Point"}
}