{
  "type": "Feature",
  "properties": {
    "iso:country":"US",
    "sg:address":"812 13th St",
    "sg:city":"Kalona",
    "sg:classifiers":[
        {
            "category":"Retail",
            "subcategory":"Repair Shop",
            "type":"Services"
        }
    ],
    "sg:phone":"+1 319 656 5284",
    "sg:postcode":"52247",
    "sg:province":"IA",
    "sg:tags":[
        "taxidermist"
    ],
    "wof:name":"Whitetail Taxidermy",
    "wof:placetype":"venue"
},
  "geometry": {"coordinates":[-91.696506,41.489563],"type":"Point"}
}