{
  "type": "Feature",
  "properties": {
    "addr:full":"1348 290th St Redding IA 50837",
    "addr:housenumber":"1348",
    "addr:postcode":"50837",
    "addr:street":"290Th St",
    "iso:country":"US",
    "sg:address":"1348 290th St",
    "sg:city":"Redding",
    "sg:classifiers":[
        {
            "category":"Farming",
            "subcategory":"Farm",
            "type":"Manufacturing & Wholesale Goods"
        }
    ],
    "sg:phone":"+1 641 767 5201",
    "sg:postcode":"50837",
    "sg:province":"IA",
    "wof:name":"Elliott Swine Enterprise",
    "wof:placetype":"venue"
},
  "geometry": {"coordinates":[-94.634168,41.230085],"type":"Point"}
}