{
  "type": "Feature",
  "properties": {
    "iso:country":"US",
    "sg:address":"52113 230th St",
    "sg:city":"Glenwood",
    "sg:classifiers":[
        {
            "category":"Arts & Performance",
            "subcategory":"Theater",
            "type":"Entertainment"
        }
    ],
    "sg:phone":"+1 712 526 2198",
    "sg:postcode":"51534",
    "sg:province":"IA",
    "sg:tags":[
        "live",
        "music"
    ],
    "wof:name":"Hop-N-Tunes",
    "wof:placetype":"venue"
},
  "geometry": {"coordinates":[-95.742267,41.128457],"type":"Point"}
}