{
  "type": "Feature",
  "properties": {
    "iso:country":"US",
    "sg:address":"316 Front St",
    "sg:city":"Neola",
    "sg:classifiers":[
        {
            "category":"Shopping",
            "subcategory":"Gifts & Souvenirs",
            "type":"Retail Goods"
        }
    ],
    "sg:phone":"+1 712 485 2511",
    "sg:postcode":"51559",
    "sg:province":"IA",
    "sg:tags":[
        "shop"
    ],
    "wof:name":"Country Mall",
    "wof:placetype":"venue"
},
  "geometry": {"coordinates":[-95.62039799999999,41.44689],"type":"Point"}
}