{
  "type": "Feature",
  "properties": {
    "iso:country":"US",
    "sg:address":"400 S 1st St",
    "sg:city":"Indianola",
    "sg:classifiers":[
        {
            "category":"Building & Trades",
            "subcategory":"Construction",
            "type":"Services"
        }
    ],
    "sg:phone":"+1 515 961 0991",
    "sg:postcode":"50125",
    "sg:province":"IA",
    "sg:tags":[
        "hanging",
        "contractor"
    ],
    "wof:name":"Perfection Painting",
    "wof:placetype":"venue"
},
  "geometry": {"coordinates":[-93.55958099999999,41.356241],"type":"Point"}
}