{
  "type": "Feature",
  "properties": {
    "addr:full":"711 N 18th St Centerville IA 52544",
    "addr:housenumber":"711",
    "addr:postcode":"52544",
    "addr:street":"N 18Th St",
    "iso:country":"US",
    "sg:address":"711 N 18th St",
    "sg:city":"Centerville",
    "sg:classifiers":[
        {
            "category":"Personal",
            "subcategory":"Beauty Salon",
            "type":"Services"
        }
    ],
    "sg:phone":"+1 641 437 7302",
    "sg:postcode":"52544",
    "sg:province":"IA",
    "wof:name":"Elite Salon",
    "wof:placetype":"venue"
},
  "geometry": {"coordinates":[-92.86791599999999,40.728274],"type":"Point"}
}