{
  "type": "Feature",
  "properties": {
    "iso:country":"US",
    "sg:address":"5920 Tremont Ave",
    "sg:city":"Davenport",
    "sg:classifiers":[
        {
            "category":"Wholesale",
            "subcategory":"Machinery & Supplies",
            "type":"Manufacturing & Wholesale Goods"
        }
    ],
    "sg:phone":"+1 563 386 7496",
    "sg:postcode":"52807",
    "sg:province":"IA",
    "sg:tags":[
        "equipment",
        "layer",
        "carpet"
    ],
    "wof:name":"E J Welch Co",
    "wof:placetype":"venue"
},
  "geometry": {"coordinates":[-90.560757,41.580215],"type":"Point"}
}