{
  "type": "Feature",
  "properties": {
    "iso:country":"US",
    "sg:address":"212 E 3rd St",
    "sg:city":"Carroll",
    "sg:classifiers":[
        {
            "category":"Retail",
            "subcategory":"Auto Repair",
            "type":"Services"
        }
    ],
    "sg:phone":"+1 712 792 3379",
    "sg:postcode":"51401",
    "sg:province":"IA",
    "sg:tags":[
        "body",
        "automobile",
        "painting"
    ],
    "wof:name":"Simons Body Shop",
    "wof:placetype":"venue"
},
  "geometry": {"coordinates":[-94.86704,42.062165],"type":"Point"}
}