{
  "type": "Feature",
  "properties": {
    "addr:full":"101 N Page St Monona IA 52159",
    "addr:housenumber":"101",
    "addr:postcode":"52159",
    "addr:street":"N Page St",
    "iso:country":"US",
    "sg:address":"101 N Page St",
    "sg:city":"Monona",
    "sg:classifiers":[
        {
            "category":"Professional",
            "type":"Services"
        }
    ],
    "sg:phone":"+1 563 539 8024",
    "sg:postcode":"52159",
    "sg:province":"IA",
    "sg:tags":[
        "establishment"
    ],
    "wof:name":"T F Enterprises",
    "wof:placetype":"venue"
},
  "geometry": {"coordinates":[-91.39109999999999,43.054003],"type":"Point"}
}