{
  "type": "Feature",
  "properties": {
    "iso:country":"US",
    "sg:address":"149 W Broadway",
    "sg:city":"Council Bluffs",
    "sg:classifiers":[
        {
            "category":"Shopping",
            "subcategory":"Used Merchandise",
            "type":"Retail Goods"
        }
    ],
    "sg:phone":"+1 712 322 4036",
    "sg:postcode":"51503",
    "sg:province":"IA",
    "sg:tags":[
        "shop",
        "thrift"
    ],
    "wof:name":"Mohm Thrift Store",
    "wof:placetype":"venue"
},
  "geometry": {"coordinates":[-95.845996,41.262141],"type":"Point"}
}