{
  "type": "Feature",
  "properties": {
    "iso:country":"US",
    "sg:address":"1373 220th St",
    "sg:city":"Manchester",
    "sg:classifiers":[
        {
            "category":"Retail",
            "subcategory":"Auto Repair",
            "type":"Services"
        }
    ],
    "sg:phone":"+1 563 927 4231",
    "sg:postcode":"52057",
    "sg:province":"IA",
    "sg:tags":[
        "general"
    ],
    "wof:name":"Dureys Auto",
    "wof:placetype":"venue"
},
  "geometry": {"coordinates":[-91.532127,42.469201],"type":"Point"}
}