{
  "type": "Feature",
  "properties": {
    "addr:full":"203 5th St West Des Moines IA 50265",
    "addr:housenumber":"203",
    "addr:postcode":"50265",
    "addr:street":"5Th St",
    "iso:country":"US",
    "sg:address":"203 5th St",
    "sg:city":"West Des Moines",
    "sg:classifiers":[
        {
            "category":"Shopping",
            "type":"Retail Goods"
        }
    ],
    "sg:phone":"+1 515 277 6734",
    "sg:postcode":"50265",
    "sg:province":"IA",
    "sg:tags":[
        "art",
        "gallery",
        "dealer"
    ],
    "wof:name":"Olson-Larsen Galleries",
    "wof:placetype":"venue"
},
  "geometry": {"coordinates":[-93.708814,41.572476],"type":"Point"}
}