{
  "type": "Feature",
  "properties": {
    "addr:full":"307 Lincoln St Strawberry Point IA 52076",
    "addr:housenumber":"307",
    "addr:postcode":"52076",
    "addr:street":"Lincoln St",
    "iso:country":"US",
    "sg:address":"307 Lincoln St",
    "sg:city":"Strawberry Point",
    "sg:classifiers":[
        {
            "category":"Organizations",
            "subcategory":"Religious Organization",
            "type":"Services"
        }
    ],
    "sg:phone":"+1 563 933 2043",
    "sg:postcode":"52076",
    "sg:province":"IA",
    "sg:tags":[
        "church"
    ],
    "wof:name":"Community Bible Church",
    "wof:placetype":"venue"
},
  "geometry": {"coordinates":[-91.541443,42.677129],"type":"Point"}
}