{
  "type": "Feature",
  "properties": {
    "iso:country":"US",
    "sg:address":"2100 S 35th St",
    "sg:city":"Council Bluffs",
    "sg:classifiers":[
        {
            "category":"Manufacturing",
            "subcategory":"Rubber & Plastics",
            "type":"Manufacturing & Wholesale Goods"
        }
    ],
    "sg:phone":"+1 712 322 2294",
    "sg:postcode":"51501",
    "sg:province":"IA",
    "sg:tags":[
        "pipe"
    ],
    "sg:website":"www.cresline.com",
    "wof:name":"Cresline Plastic Pipe Plant",
    "wof:placetype":"venue"
},
  "geometry": {"coordinates":[-95.899495,41.242869],"type":"Point"}
}