{
  "type": "Feature",
  "properties": {
    "iso:country":"US",
    "sg:address":"319 S 7th St",
    "sg:city":"Chariton",
    "sg:classifiers":[
        {
            "category":"Professional",
            "subcategory":"Management & Consulting",
            "type":"Services"
        }
    ],
    "sg:phone":"+1 641 774 8824",
    "sg:postcode":"50049",
    "sg:province":"IA",
    "sg:tags":[
        "marketing",
        "program"
    ],
    "sg:website":"www.mckinleyinc.net",
    "wof:name":"Mc Kinley Inc",
    "wof:placetype":"venue"
},
  "geometry": {"coordinates":[-93.303552,41.011156],"type":"Point"}
}