{
  "type": "Feature",
  "properties": {
    "iso:country":"US",
    "sg:address":"2846 State Hwy 183",
    "sg:city":"Missouri Valley",
    "sg:phone":"+1 712 642 3946",
    "sg:postcode":"51555",
    "sg:province":"IA",
    "sg:tags":[
        "farm",
        "corn"
    ],
    "wof:name":"Mc Intosh Kathryn",
    "wof:placetype":"venue"
},
  "geometry": {"coordinates":[-95.894706,41.608122],"type":"Point"}
}