{
  "type": "Feature",
  "properties": {
    "iso:country":"US",
    "sg:address":"2375 State Hwy 38",
    "sg:city":"Wilton",
    "sg:classifiers":[
        {
            "category":"Freight",
            "type":"Transportation"
        }
    ],
    "sg:phone":"+1 563 732 2137",
    "sg:postcode":"52778",
    "sg:province":"IA",
    "sg:tags":[
        "trucking"
    ],
    "wof:name":"Jenkins Trucking",
    "wof:placetype":"venue"
},
  "geometry": {"coordinates":[-91.03617,41.602468],"type":"Point"}
}