{
  "type": "Feature",
  "properties": {
    "addr:full":"12654 U Ave Dike IA 50624",
    "addr:housenumber":"12654",
    "addr:postcode":"50624",
    "addr:street":"U Ave",
    "iso:country":"US",
    "sg:address":"12654 U Ave",
    "sg:city":"Dike",
    "sg:phone":"+1 319 989 2525",
    "sg:postcode":"50624",
    "sg:province":"IA",
    "sg:tags":[
        "farm",
        "corn",
        "soybean"
    ],
    "wof:name":"Meyer Mervan",
    "wof:placetype":"venue"
},
  "geometry": {"coordinates":[-92.633066,42.518335],"type":"Point"}
}