{
  "type": "Feature",
  "properties": {
    "addr:full":"1807 27th St Sioux City IA 51104",
    "addr:housenumber":"1807",
    "addr:postcode":"51104",
    "addr:street":"27Th St",
    "iso:country":"US",
    "sg:address":"1807 27th St",
    "sg:city":"Sioux City",
    "sg:classifiers":[
        {
            "category":"Education",
            "subcategory":"School",
            "type":"Public Place"
        }
    ],
    "sg:phone":"+1 712 279 6838",
    "sg:postcode":"51104",
    "sg:province":"IA",
    "wof:name":"Lowell Elementary School",
    "wof:placetype":"venue"
},
  "geometry": {"coordinates":[-96.386882,42.517594],"type":"Point"}
}