{
  "type": "Feature",
  "properties": {
    "addr:full":"5012 Alburnett Rd Marion IA 52302",
    "addr:housenumber":"5012",
    "addr:postcode":"52302",
    "addr:street":"Alburnett Rd",
    "iso:country":"US",
    "sg:address":"5012 Alburnett Rd",
    "sg:city":"Marion",
    "sg:classifiers":[
        {
            "category":"Autos & Motor Vehicles",
            "subcategory":"Automobile Sales",
            "type":"Retail Goods"
        }
    ],
    "sg:phone":"+1 319 377 3577",
    "sg:postcode":"52302",
    "sg:province":"IA",
    "sg:tags":[
        "snowmobile"
    ],
    "wof:name":"Outdoor Equipment Inc",
    "wof:placetype":"venue"
},
  "geometry": {"coordinates":[-91.619072,42.065669],"type":"Point"}
}