{
  "type": "Feature",
  "properties": {
    "iso:country":"US",
    "sg:address":"721 N Main St",
    "sg:city":"Carroll",
    "sg:classifiers":[
        {
            "category":"Professional",
            "subcategory":"Lawyer & Legal Services",
            "type":"Services"
        }
    ],
    "sg:phone":"+1 712 792 3508",
    "sg:postcode":"51401",
    "sg:province":"IA",
    "sg:tags":[
        "attorney"
    ],
    "wof:name":"Neu Minnich Comito & Neu",
    "wof:placetype":"venue"
},
  "geometry": {"coordinates":[-94.86632400000001,42.06754],"type":"Point"}
}