{
  "type": "Feature",
  "properties": {
    "iso:country":"US",
    "sg:address":"409 Clark St",
    "sg:city":"Reinbeck",
    "sg:classifiers":[
        {
            "category":"Retail",
            "subcategory":"Funeral Services",
            "type":"Services"
        }
    ],
    "sg:phone":"+1 319 345 2622",
    "sg:postcode":"50669",
    "sg:province":"IA",
    "sg:tags":[
        "director"
    ],
    "wof:name":"French-Hand Funeral Home",
    "wof:placetype":"venue"
},
  "geometry": {"coordinates":[-92.599131,42.323774],"type":"Point"}
}