{
  "type": "Feature",
  "properties": {
    "iso:country":"US",
    "sg:address":"62633 Levi Rd",
    "sg:city":"Glenwood",
    "sg:phone":"+1 712 527 3271",
    "sg:postcode":"51534",
    "sg:province":"IA",
    "sg:tags":[
        "farm",
        "corn",
        "soybean"
    ],
    "wof:name":"R L D Land and Cattle Inc",
    "wof:placetype":"venue"
},
  "geometry": {"coordinates":[-95.73743,40.977125],"type":"Point"}
}