{
  "type": "Feature",
  "properties": {
    "iso:country":"US",
    "sg:address":"230 Nebraska St",
    "sg:city":"Sioux City",
    "sg:classifiers":[
        {
            "category":"Health Services",
            "subcategory":"Doctor",
            "type":"Services"
        }
    ],
    "sg:phone":"+1 712 252 0088",
    "sg:postcode":"51101",
    "sg:province":"IA",
    "sg:tags":[
        "medical"
    ],
    "wof:name":"Siouxland Hemtlgy Onclgy Asct",
    "wof:placetype":"venue"
},
  "geometry": {"coordinates":[-96.403373,42.492338],"type":"Point"}
}