{
  "type": "Feature",
  "properties": {
    "addr:full":"1510 NW 86th St Clive IA 50325",
    "addr:housenumber":"1510",
    "addr:postcode":"50325",
    "addr:street":"Nw 86Th St",
    "iso:country":"US",
    "sg:address":"1510 NW 86th St",
    "sg:city":"Clive",
    "sg:classifiers":[
        {
            "category":"Professional",
            "subcategory":"Business Services",
            "type":"Services"
        }
    ],
    "sg:phone":"+1 515 457 1199",
    "sg:postcode":"50325",
    "sg:province":"IA",
    "wof:name":"Muzak Business Music Svc",
    "wof:placetype":"venue"
},
  "geometry": {"coordinates":[-93.736307,41.603518],"type":"Point"}
}