{
  "type": "Feature",
  "properties": {
    "iso:country":"US",
    "sg:address":"1700 W Townline St",
    "sg:city":"Creston",
    "sg:classifiers":[
        {
            "category":"Health Services",
            "subcategory":"Doctor",
            "type":"Services"
        }
    ],
    "sg:phone":"+1 641 782 3841",
    "sg:postcode":"50801",
    "sg:province":"IA",
    "sg:tags":[
        "medical"
    ],
    "wof:name":"Union County Family Support",
    "wof:placetype":"venue"
},
  "geometry": {"coordinates":[-94.384433,41.071101],"type":"Point"}
}