{
  "type": "Feature",
  "properties": {
    "iso:country":"US",
    "sg:address":"1390 N 14th St",
    "sg:city":"Fort Dodge",
    "sg:classifiers":[
        {
            "category":"Professional",
            "subcategory":"Business Services",
            "type":"Services"
        }
    ],
    "sg:phone":"+1 515 576 7081",
    "sg:postcode":"50501",
    "sg:province":"IA",
    "wof:name":"Willow Lane Enterprises Inc",
    "wof:placetype":"venue"
},
  "geometry": {"coordinates":[-94.18364099999999,42.520009],"type":"Point"}
}