{
  "type": "Feature",
  "properties": {
    "addr:full":"2703 E Kanesville Blvd Council Bluffs IA 51503",
    "addr:housenumber":"2703",
    "addr:postcode":"51503",
    "addr:street":"E Kanesville Blvd",
    "iso:country":"US",
    "sg:address":"2703 E Kanesville Blvd",
    "sg:city":"Council Bluffs",
    "sg:classifiers":[
        {
            "category":"Wholesale",
            "subcategory":"Farm Supplies",
            "type":"Manufacturing & Wholesale Goods"
        }
    ],
    "sg:phone":"+1 712 328 2898",
    "sg:postcode":"51503",
    "sg:province":"IA",
    "wof:name":"Bomgaars",
    "wof:placetype":"venue"
},
  "geometry": {"coordinates":[-95.81119700000001,41.279357],"type":"Point"}
}