{
  "type": "Feature",
  "properties": {
    "addr:full":"19118 Kittyhawk Ave Carroll IA 51401",
    "addr:postcode":"19118;51401",
    "addr:street":"Kittyhawk Ave",
    "iso:country":"US",
    "sg:address":"19118 Kittyhawk Ave",
    "sg:city":"Carroll",
    "sg:classifiers":[
        {
            "category":"Wholesale",
            "subcategory":"Farm Supplies",
            "type":"Manufacturing & Wholesale Goods"
        }
    ],
    "sg:phone":"+1 712 792 9705",
    "sg:postcode":"51401",
    "sg:province":"IA",
    "wof:name":"Farmers Co-Op Carroll",
    "wof:placetype":"venue"
},
  "geometry": {"coordinates":[-94.897898,42.075213],"type":"Point"}
}