{
  "type": "Feature",
  "properties": {
    "iso:country":"US",
    "sg:address":"1056 Central Ave",
    "sg:city":"Dubuque",
    "sg:classifiers":[
        {
            "category":"Autos & Motor Vehicles",
            "subcategory":"Motorcycle Sales",
            "type":"Retail Goods"
        }
    ],
    "sg:phone":"+1 563 583 6175",
    "sg:postcode":"52001",
    "sg:province":"IA",
    "sg:tags":[
        "scooter"
    ],
    "wof:name":"Smith Cycle Inc",
    "wof:placetype":"venue"
},
  "geometry": {"coordinates":[-90.666132,42.503463],"type":"Point"}
}