{
  "type": "Feature",
  "properties": {
    "iso:country":"US",
    "sg:address":"3040 Asbury Rd",
    "sg:city":"Dubuque",
    "sg:classifiers":[
        {
            "category":"Restaurant",
            "type":"Food & Drink"
        }
    ],
    "sg:phone":"+1 563 583 3896",
    "sg:postcode":"52001",
    "sg:province":"IA",
    "sg:tags":[
        "eating"
    ],
    "wof:name":"John W Grill",
    "wof:placetype":"venue"
},
  "geometry": {"coordinates":[-90.713087,42.509351],"type":"Point"}
}