{
  "type": "Feature",
  "properties": {
    "addr:full":"1887 Hidden Valley Ln Fort Dodge IA 50501",
    "addr:housenumber":"1887",
    "addr:postcode":"50501",
    "addr:street":"Hidden Valley Ln",
    "iso:country":"US",
    "sg:address":"1887 Hidden Valley Ln",
    "sg:city":"Fort Dodge",
    "sg:classifiers":[
        {
            "category":"Home & Garden",
            "subcategory":"Furniture",
            "type":"Retail Goods"
        }
    ],
    "sg:phone":"+1 515 576 1226",
    "sg:postcode":"50501",
    "sg:province":"IA",
    "wof:name":"Schneppys Cabinet Shop",
    "wof:placetype":"venue"
},
  "geometry": {"coordinates":[-94.269412,42.520724],"type":"Point"}
}