{
  "type": "Feature",
  "properties": {
    "addr:full":"9953 140th Ave Anamosa IA 52205",
    "addr:housenumber":"9953",
    "addr:postcode":"52205",
    "addr:street":"140Th Ave",
    "iso:country":"US",
    "sg:address":"9953 140th Ave",
    "sg:city":"Anamosa",
    "sg:classifiers":[
        {
            "category":"Manufacturing",
            "subcategory":"Tools & Machinery",
            "type":"Manufacturing & Wholesale Goods"
        }
    ],
    "sg:phone":"+1 319 484 2307",
    "sg:postcode":"52205",
    "sg:province":"IA",
    "sg:tags":[
        "industrial",
        "mfg"
    ],
    "wof:name":"C & L Performance",
    "wof:placetype":"venue"
},
  "geometry": {"coordinates":[-91.151263,42.077348],"type":"Point"}
}