{
  "type": "Feature",
  "properties": {
    "iso:country":"US",
    "sg:address":"1271 Buchanan Ave",
    "sg:city":"Sioux City",
    "sg:classifiers":[
        {
            "category":"Building & Trades",
            "subcategory":"Construction",
            "type":"Services"
        }
    ],
    "sg:phone":"+1 712 255 9366",
    "sg:postcode":"51108",
    "sg:province":"IA",
    "sg:tags":[
        "general",
        "contractor"
    ],
    "wof:name":"Miller Homes",
    "wof:placetype":"venue"
},
  "geometry": {"coordinates":[-96.302693,42.525052],"type":"Point"}
}