{
  "type": "Feature",
  "properties": {
    "addr:full":"2901 SW 18th St Des Moines IA 50315",
    "addr:housenumber":"2901",
    "addr:postcode":"50315",
    "addr:street":"Sw 18Th St",
    "iso:country":"US",
    "sg:address":"2901 SW 18th St",
    "sg:city":"Des Moines",
    "sg:classifiers":[
        {
            "category":"Professional",
            "type":"Services"
        }
    ],
    "sg:phone":"+1 515 237 8255",
    "sg:postcode":"50315",
    "sg:province":"IA",
    "wof:name":"Cay Services Ltd",
    "wof:placetype":"venue"
},
  "geometry": {"coordinates":[-93.64013300000001,41.557746],"type":"Point"}
}