{
  "type": "Feature",
  "properties": {
    "iso:country":"US",
    "sg:address":"20461 Dogwood Ave",
    "sg:city":"Akron",
    "sg:classifiers":[
        {
            "category":"Real Estate",
            "subcategory":"Real Estate Operator",
            "type":"Services"
        }
    ],
    "sg:phone":"+1 712 568 2023",
    "sg:postcode":"51001",
    "sg:province":"IA",
    "sg:tags":[
        "property",
        "lessor"
    ],
    "wof:name":"Dwain J Willer Farms Inc",
    "wof:placetype":"venue"
},
  "geometry": {"coordinates":[-96.487875,42.75801],"type":"Point"}
}