{
  "type": "Feature",
  "properties": {
    "addr:full":"956 240th Pl Pella IA 50219",
    "addr:housenumber":"956",
    "addr:postcode":"50219",
    "addr:street":"240Th Pl",
    "iso:country":"US",
    "sg:address":"956 240th Pl",
    "sg:city":"Pella",
    "sg:phone":"+1 641 628 2003",
    "sg:postcode":"50219",
    "sg:province":"IA",
    "sg:tags":[
        "farm",
        "corn"
    ],
    "wof:name":"Dop Donald",
    "wof:placetype":"venue"
},
  "geometry": {"coordinates":[-92.890326,41.386778],"type":"Point"}
}