{
  "type": "Feature",
  "properties": {
    "iso:country":"US",
    "sg:address":"8802 267th St",
    "sg:city":"Bernard",
    "sg:classifiers":[
        {
            "category":"Farming",
            "subcategory":"Dairy Farm",
            "type":"Manufacturing & Wholesale Goods"
        }
    ],
    "sg:phone":"+1 563 879 3273",
    "sg:postcode":"52032",
    "sg:province":"IA",
    "wof:name":"Sunrise Dairy Farm",
    "wof:placetype":"venue"
},
  "geometry": {"coordinates":[-90.792658,42.265969],"type":"Point"}
}