{
  "type": "Feature",
  "properties": {
    "addr:full":"700 E Bridge St Elkader IA 52043",
    "addr:housenumber":"700",
    "addr:postcode":"52043",
    "addr:street":"E Bridge St",
    "iso:country":"US",
    "sg:address":"700 E Bridge St",
    "sg:city":"Elkader",
    "sg:classifiers":[
        {
            "category":"Farming",
            "subcategory":"Nursery",
            "type":"Manufacturing & Wholesale Goods"
        }
    ],
    "sg:phone":"+1 563 245 2247",
    "sg:postcode":"52043",
    "sg:province":"IA",
    "sg:tags":[
        "greenhouse"
    ],
    "wof:name":"Elkader Greenhouse & Lndscpng",
    "wof:placetype":"venue"
},
  "geometry": {"coordinates":[-91.39665599999999,42.85695],"type":"Point"}
}