{
  "type": "Feature",
  "properties": {
    "iso:country":"US",
    "sg:address":"1927 Keokuk St",
    "sg:city":"Iowa City",
    "sg:classifiers":[
        {
            "category":"Real Estate",
            "subcategory":"Real Estate Agent",
            "type":"Services"
        }
    ],
    "sg:phone":"+1 319 358 1515",
    "sg:postcode":"52240",
    "sg:province":"IA",
    "sg:tags":[
        "management"
    ],
    "wof:name":"Nebury Management Co",
    "wof:placetype":"venue"
},
  "geometry": {"coordinates":[-91.524992,41.640826],"type":"Point"}
}