{
  "type": "Feature",
  "properties": {
    "addr:full":"1207 Broadway St West Burlington IA 52655",
    "addr:housenumber":"1207",
    "addr:postcode":"52655",
    "addr:street":"Broadway St West",
    "iso:country":"US",
    "sg:address":"1207 Broadway St",
    "sg:city":"West Burlington",
    "sg:classifiers":[
        {
            "category":"Retail",
            "subcategory":"Auto Repair",
            "type":"Services"
        }
    ],
    "sg:phone":"+1 319 753 2895",
    "sg:postcode":"52655",
    "sg:province":"IA",
    "sg:tags":[
        "repairing",
        "tire"
    ],
    "wof:name":"Bauer Built Tire & Svc Ctr",
    "wof:placetype":"venue"
},
  "geometry": {"coordinates":[-91.156893,40.812326],"type":"Point"}
}