{
  "type": "Feature",
  "properties": {
    "iso:country":"US",
    "sg:address":"2190 270th St",
    "sg:city":"Milford",
    "sg:classifiers":[
        {
            "category":"Retail",
            "subcategory":"Auto Repair",
            "type":"Services"
        }
    ],
    "sg:phone":"+1 712 262 2365",
    "sg:postcode":"51351",
    "sg:province":"IA",
    "sg:tags":[
        "body",
        "automobile",
        "painting"
    ],
    "wof:name":"J T Restoration & Collision",
    "wof:placetype":"venue"
},
  "geometry": {"coordinates":[-95.167344,43.255557],"type":"Point"}
}