{
  "type": "Feature",
  "properties": {
    "iso:country":"US",
    "sg:address":"3009 Kirkwood St",
    "sg:city":"Burlington",
    "sg:classifiers":[
        {
            "category":"Organizations",
            "subcategory":"Labor Organization",
            "type":"Services"
        }
    ],
    "sg:phone":"+1 319 754 4014",
    "sg:postcode":"52601",
    "sg:province":"IA",
    "wof:name":"United Auto Workers",
    "wof:placetype":"venue"
},
  "geometry": {"coordinates":[-91.13963800000001,40.819701],"type":"Point"}
}