{
  "type": "Feature",
  "properties": {
    "iso:country":"US",
    "sg:address":"14521 State Hwy 136",
    "sg:city":"Dyersville",
    "sg:classifiers":[
        {
            "category":"Farming",
            "subcategory":"Farm",
            "type":"Manufacturing & Wholesale Goods"
        }
    ],
    "sg:phone":"+1 563 875 7686",
    "sg:postcode":"52040",
    "sg:province":"IA",
    "sg:tags":[
        "crop",
        "general"
    ],
    "wof:name":"Hoeger Jerome",
    "wof:placetype":"venue"
},
  "geometry": {"coordinates":[-91.109587,42.503068],"type":"Point"}
}