{
  "type": "Feature",
  "properties": {
    "addr:full":"329 E State St Mason City IA 50401",
    "addr:housenumber":"329",
    "addr:postcode":"50401",
    "addr:street":"E State St",
    "iso:country":"US",
    "sg:address":"329 E State St",
    "sg:city":"Mason City",
    "sg:classifiers":[
        {
            "category":"Organizations",
            "subcategory":"Religious Organization",
            "type":"Services"
        }
    ],
    "sg:phone":"+1 641 423 7749",
    "sg:postcode":"50401",
    "sg:province":"IA",
    "sg:tags":[
        "church"
    ],
    "wof:name":"St Paul Lutheran Church",
    "wof:placetype":"venue"
},
  "geometry": {"coordinates":[-93.19580000000001,43.151744],"type":"Point"}
}