{
  "type": "Feature",
  "properties": {
    "addr:full":"749 Mormon Trek Blvd Iowa City IA 52246",
    "addr:housenumber":"749",
    "addr:postcode":"52246",
    "addr:street":"Mormon Trek Blvd",
    "iso:country":"US",
    "sg:address":"749 Mormon Trek Blvd",
    "sg:city":"Iowa City",
    "sg:classifiers":[
        {
            "category":"Restaurant",
            "type":"Food & Drink"
        }
    ],
    "sg:phone":"+1 319 338 7400",
    "sg:postcode":"52246",
    "sg:province":"IA",
    "sg:tags":[
        "eating"
    ],
    "wof:name":"Bobs Your Uncle",
    "wof:placetype":"venue"
},
  "geometry": {"coordinates":[-91.57406400000001,41.650833],"type":"Point"}
}