{
  "type": "Feature",
  "properties": {
    "iso:country":"US",
    "sg:address":"1107 Scott St",
    "sg:city":"Ruthven",
    "sg:classifiers":[
        {
            "category":"Insurance",
            "subcategory":"Insurance Agent",
            "type":"Services"
        }
    ],
    "sg:phone":"+1 712 837 5741",
    "sg:postcode":"51358",
    "sg:province":"IA",
    "wof:name":"Packers Livestock Insurance",
    "wof:placetype":"venue"
},
  "geometry": {"coordinates":[-94.897879,43.128293],"type":"Point"}
}