{
  "type": "Feature",
  "properties": {
    "addr:full":"18579 Cedar Ridge Rd Durango IA 52039",
    "addr:housenumber":"18579",
    "addr:postcode":"52039",
    "addr:street":"Cedar Ridge Rd",
    "iso:country":"US",
    "sg:address":"18579 Cedar Ridge Rd",
    "sg:city":"Durango",
    "sg:phone":"+1 563 552 1149",
    "sg:postcode":"52039",
    "sg:province":"IA",
    "sg:tags":[
        "farm",
        "hog",
        "corn",
        "or",
        "feedlot"
    ],
    "wof:name":"Troy Brehm",
    "wof:placetype":"venue"
},
  "geometry": {"coordinates":[-90.84970199999999,42.547791],"type":"Point"}
}