{
  "type": "Feature",
  "properties": {
    "iso:country":"US",
    "sg:address":"305 6th Ave SE",
    "sg:city":"Hampton",
    "sg:classifiers":[
        {
            "category":"Autos & Motor Vehicles",
            "subcategory":"Automobile Sales",
            "type":"Retail Goods"
        }
    ],
    "sg:phone":"+1 641 456 4860",
    "sg:postcode":"50441",
    "sg:province":"IA",
    "sg:tags":[
        "car",
        "dealer"
    ],
    "wof:name":"Hampton Auto Sales & Svc",
    "wof:placetype":"venue"
},
  "geometry": {"coordinates":[-93.20365,42.736316],"type":"Point"}
}