{
  "type": "Feature",
  "properties": {
    "iso:country":"US",
    "sg:address":"615 E Lane St",
    "sg:city":"Winterset",
    "sg:classifiers":[
        {
            "category":"Retail",
            "subcategory":"Repair Shop",
            "type":"Services"
        }
    ],
    "sg:phone":"+1 515 462 1942",
    "sg:postcode":"50273",
    "sg:province":"IA",
    "sg:tags":[
        "welding"
    ],
    "wof:name":"Simon Welding",
    "wof:placetype":"venue"
},
  "geometry": {"coordinates":[-94.00664399999999,41.341041],"type":"Point"}
}