{
  "type": "Feature",
  "properties": {
    "addr:full":"915 Turner St Marshalltown IA 50158",
    "addr:housenumber":"915",
    "addr:postcode":"50158",
    "addr:street":"Turner St",
    "iso:country":"US",
    "sg:address":"915 Turner St",
    "sg:city":"Marshalltown",
    "sg:classifiers":[
        {
            "category":"Bars & Pubs",
            "type":"Food & Drink"
        }
    ],
    "sg:phone":"+1 641 754 9898",
    "sg:postcode":"50158",
    "sg:province":"IA",
    "wof:name":"J B Bar",
    "wof:placetype":"venue"
},
  "geometry": {"coordinates":[-92.89620499999999,42.041162],"type":"Point"}
}