{
  "type": "Feature",
  "properties": {
    "addr:full":"200 E Grand Ave Des Moines IA 50309",
    "addr:housenumber":"200",
    "addr:postcode":"50309",
    "addr:street":"E Grand Ave",
    "iso:country":"US",
    "sg:address":"200 E Grand Ave",
    "sg:city":"Des Moines",
    "sg:classifiers":[
        {
            "category":"Social Services",
            "subcategory":"Job Training",
            "type":"Services"
        }
    ],
    "sg:phone":"+1 515 242 4867",
    "sg:postcode":"50309",
    "sg:province":"IA",
    "sg:tags":[
        "rehab",
        "government"
    ],
    "wof:name":"Workforce Div",
    "wof:placetype":"venue"
},
  "geometry": {"coordinates":[-93.61301899999999,41.590342],"type":"Point"}
}