{
  "type": "Feature",
  "properties": {
    "iso:country":"US",
    "sg:address":"1145 Douglas Ave",
    "sg:city":"Des Moines",
    "sg:classifiers":[
        {
            "category":"Retail",
            "subcategory":"Auto Repair",
            "type":"Services"
        }
    ],
    "sg:phone":"+1 515 243 9122",
    "sg:postcode":"50313",
    "sg:province":"IA",
    "sg:tags":[
        "repairing",
        "automobile"
    ],
    "wof:name":"Wyatt's Auto Repair",
    "wof:placetype":"venue"
},
  "geometry": {"coordinates":[-93.633622,41.629566],"type":"Point"}
}