{
  "type": "Feature",
  "properties": {
    "addr:full":"716 S 4th St Council Bluffs IA 51503",
    "addr:housenumber":"716",
    "addr:postcode":"51503",
    "addr:street":"S 4Th St",
    "iso:country":"US",
    "sg:address":"716 S 4th St",
    "sg:city":"Council Bluffs",
    "sg:classifiers":[
        {
            "category":"Recreation",
            "type":"Entertainment"
        }
    ],
    "sg:phone":"+1 712 325 4874",
    "sg:postcode":"51503",
    "sg:province":"IA",
    "sg:tags":[
        "amusement"
    ],
    "wof:name":"American Legion",
    "wof:placetype":"venue"
},
  "geometry": {"coordinates":[-95.850702,41.253536],"type":"Point"}
}