{
  "type": "Feature",
  "properties": {
    "addr:full":"650 Ashworth Dr Waukee IA 50263",
    "addr:housenumber":"650",
    "addr:postcode":"50263",
    "addr:street":"Ashworth Dr",
    "iso:country":"US",
    "sg:address":"650 Ashworth Dr",
    "sg:city":"Waukee",
    "sg:classifiers":[
        {
            "category":"Organizations",
            "subcategory":"Religious Organization",
            "type":"Services"
        }
    ],
    "sg:phone":"+1 515 987 4531",
    "sg:postcode":"50263",
    "sg:province":"IA",
    "sg:tags":[
        "church"
    ],
    "sg:website":"www.waukeechurch.org",
    "wof:name":"Waukee United Methodist Church",
    "wof:placetype":"venue"
},
  "geometry": {"coordinates":[-93.886049,41.612056],"type":"Point"}
}