{
  "type": "Feature",
  "properties": {
    "addr:full":"17656 Ivy Ave Carroll IA 51401",
    "addr:housenumber":"17656",
    "addr:postcode":"51401",
    "addr:street":"Ivy Ave",
    "iso:country":"US",
    "sg:address":"17656 Ivy Ave",
    "sg:city":"Carroll",
    "sg:classifiers":[
        {
            "category":"Shopping",
            "subcategory":"Discount & Variety Stores",
            "type":"Retail Goods"
        }
    ],
    "sg:phone":"+1 712 792 0395",
    "sg:postcode":"51401",
    "sg:province":"IA",
    "sg:tags":[
        "merchandise",
        "general"
    ],
    "wof:name":"Tukan Trike Store Inc",
    "wof:placetype":"venue"
},
  "geometry": {"coordinates":[-94.93651699999999,42.097995],"type":"Point"}
}