{
  "type": "Feature",
  "properties": {
    "iso:country":"US",
    "sg:address":"150 1st Ave NE",
    "sg:city":"Cedar Rapids",
    "sg:classifiers":[
        {
            "category":"Banks & Credit Unions",
            "subcategory":"Investment Brokerage",
            "type":"Services"
        }
    ],
    "sg:phone":"+1 319 362 2325",
    "sg:postcode":"52401",
    "sg:province":"IA",
    "sg:tags":[
        "commodity"
    ],
    "wof:name":"Bump Investor Svc",
    "wof:placetype":"venue"
},
  "geometry": {"coordinates":[-91.66919,41.978451],"type":"Point"}
}