{
  "type": "Feature",
  "properties": {
    "addr:full":"21117 283rd Ave Moulton IA 52572",
    "addr:housenumber":"21117",
    "addr:postcode":"52572",
    "addr:street":"283Rd Ave",
    "iso:country":"US",
    "sg:address":"21117 283rd Ave",
    "sg:city":"Moulton",
    "sg:classifiers":[
        {
            "category":"Personal",
            "subcategory":"Beauty Salon",
            "type":"Services"
        }
    ],
    "sg:phone":"+1 641 437 4767",
    "sg:postcode":"52572",
    "sg:province":"IA",
    "sg:tags":[
        "care",
        "skin"
    ],
    "wof:name":"Country Lane Cut & Style",
    "wof:placetype":"venue"
},
  "geometry": {"coordinates":[-92.747996,40.739573],"type":"Point"}
}