{
  "type": "Feature",
  "properties": {
    "iso:country":"US",
    "sg:address":"5825 Merle Hay Rd",
    "sg:city":"Johnston",
    "sg:classifiers":[
        {
            "category":"Restaurant",
            "type":"Food & Drink"
        }
    ],
    "sg:phone":"+1 515 276 3887",
    "sg:postcode":"50131",
    "sg:province":"IA",
    "sg:tags":[
        "eating"
    ],
    "wof:name":"El Mariachi",
    "wof:placetype":"venue"
},
  "geometry": {"coordinates":[-93.69758899999999,41.667243],"type":"Point"}
}