{
  "type": "Feature",
  "properties": {
    "iso:country":"US",
    "sg:address":"1501 Jackson St",
    "sg:city":"Dubuque",
    "sg:classifiers":[
        {
            "category":"Professional",
            "subcategory":"Business Services",
            "type":"Services"
        }
    ],
    "sg:phone":"+1 563 556 5372",
    "sg:postcode":"52001",
    "sg:province":"IA",
    "sg:tags":[
        "translator",
        "interpreter"
    ],
    "wof:name":"Immigration Outreach Office",
    "wof:placetype":"venue"
},
  "geometry": {"coordinates":[-90.666651,42.508568],"type":"Point"}
}