{
  "type": "Feature",
  "properties": {
    "addr:full":"3112 3rd St Des Moines IA 50313",
    "addr:housenumber":"3112",
    "addr:postcode":"50313",
    "addr:street":"3Rd St",
    "iso:country":"US",
    "sg:address":"3112 3rd St",
    "sg:city":"Des Moines",
    "sg:classifiers":[
        {
            "category":"Government",
            "subcategory":"Office",
            "type":"Public Place"
        }
    ],
    "sg:phone":"+1 515 280 8706",
    "sg:postcode":"50313",
    "sg:province":"IA",
    "sg:tags":[
        "safety",
        "order"
    ],
    "wof:name":"Iowa Wing C A P",
    "wof:placetype":"venue"
},
  "geometry": {"coordinates":[-93.621194,41.625825],"type":"Point"}
}