{
  "type": "Feature",
  "properties": {
    "addr:full":"3915 NW 98th Ave Polk City IA 50226",
    "addr:housenumber":"3915",
    "addr:postcode":"50226",
    "addr:street":"Nw 98Th Ave",
    "iso:country":"US",
    "sg:address":"3915 NW 98th Ave",
    "sg:city":"Polk City",
    "sg:classifiers":[
        {
            "category":"Wholesale",
            "subcategory":"Durable Goods & Equipment",
            "type":"Manufacturing & Wholesale Goods"
        }
    ],
    "sg:phone":"+1 515 984 6484",
    "sg:postcode":"50226",
    "sg:province":"IA",
    "sg:tags":[
        "professional"
    ],
    "wof:name":"Riverton Financial Services",
    "wof:placetype":"venue"
},
  "geometry": {"coordinates":[-93.672918,41.739398],"type":"Point"}
}