{
  "type": "Feature",
  "properties": {
    "addr:full":"1918 SE 14th St Des Moines IA 50320",
    "addr:housenumber":"1918",
    "addr:postcode":"50320",
    "addr:street":"Se 14Th St",
    "iso:country":"US",
    "sg:address":"1918 SE 14th St",
    "sg:city":"Des Moines",
    "sg:classifiers":[
        {
            "category":"Shopping",
            "subcategory":"Tobacco",
            "type":"Retail Goods"
        }
    ],
    "sg:phone":"+1 515 283 1288",
    "sg:postcode":"50320",
    "sg:province":"IA",
    "sg:tags":[
        "cigarette",
        "cigar",
        "dealer"
    ],
    "wof:name":"Smoke Shop",
    "wof:placetype":"venue"
},
  "geometry": {"coordinates":[-93.59699999999999,41.569206],"type":"Point"}
}