{
  "type": "Feature",
  "properties": {
    "iso:country":"US",
    "sg:address":"8000 Douglas Ave",
    "sg:city":"Urbandale",
    "sg:classifiers":[
        {
            "category":"Real Estate",
            "subcategory":"Real Estate Agent",
            "type":"Services"
        }
    ],
    "sg:phone":"+1 515 453 6500",
    "sg:postcode":"50322",
    "sg:province":"IA",
    "wof:name":"Iowa Realty Co",
    "wof:placetype":"venue"
},
  "geometry": {"coordinates":[-93.731984,41.629077],"type":"Point"}
}