{
  "type": "Feature",
  "properties": {
    "iso:country":"US",
    "sg:address":"3339 Sheridan Ave",
    "sg:city":"Des Moines",
    "sg:classifiers":[
        {
            "category":"Shopping",
            "subcategory":"Gifts & Souvenirs",
            "type":"Retail Goods"
        }
    ],
    "sg:phone":"+1 515 279 5825",
    "sg:postcode":"50310",
    "sg:province":"IA",
    "wof:name":"Kim Card",
    "wof:placetype":"venue"
},
  "geometry": {"coordinates":[-93.66292799999999,41.618684],"type":"Point"}
}