{
  "type": "Feature",
  "properties": {
    "addr:full":"507 Madison St Pella IA 50219",
    "addr:housenumber":"507",
    "addr:postcode":"50219",
    "addr:street":"Madison St",
    "iso:country":"US",
    "sg:address":"507 Madison St",
    "sg:city":"Pella",
    "sg:classifiers":[
        {
            "category":"Professional",
            "subcategory":"Art Services",
            "type":"Services"
        }
    ],
    "sg:phone":"+1 641 628 4855",
    "sg:postcode":"50219",
    "sg:province":"IA",
    "sg:tags":[
        "commercial",
        "graphic",
        "design"
    ],
    "wof:name":"Defotograaf",
    "wof:placetype":"venue"
},
  "geometry": {"coordinates":[-92.913894,41.415431],"type":"Point"}
}