{
  "type": "Feature",
  "properties": {
    "addr:full":"1849 Forest Ave Des Moines IA 50314",
    "addr:housenumber":"1849",
    "addr:postcode":"50314",
    "addr:street":"Forest Ave",
    "iso:country":"US",
    "sg:address":"1849 Forest Ave",
    "sg:city":"Des Moines",
    "sg:classifiers":[
        {
            "category":"Social Services",
            "subcategory":"Child Care",
            "type":"Services"
        }
    ],
    "sg:phone":"+1 515 243 7678",
    "sg:postcode":"50314",
    "sg:province":"IA",
    "sg:tags":[
        "day"
    ],
    "wof:name":"Drake University Head Start",
    "wof:placetype":"venue"
},
  "geometry": {"coordinates":[-93.64220899999999,41.604148],"type":"Point"}
}