{
  "type": "Feature",
  "properties": {
    "addr:full":"5402 Morningside Ave Sioux City SD 51106",
    "addr:housenumber":"5402",
    "addr:postcode":"51106",
    "addr:street":"Morningside Ave",
    "iso:country":"US",
    "sg:address":"5402 Morningside Ave",
    "sg:city":"Sioux City",
    "sg:classifiers":[
        {
            "category":"Health Services",
            "subcategory":"Doctor",
            "type":"Services"
        }
    ],
    "sg:phone":"+1 712 276 8432",
    "sg:postcode":"51106",
    "sg:province":"SD",
    "sg:tags":[
        "dentist"
    ],
    "wof:name":"Burnight & Petzoldt",
    "wof:placetype":"venue"
},
  "geometry": {"coordinates":[-96.337377,42.469974],"type":"Point"}
}