{
  "type": "Feature",
  "properties": {
    "iso:country":"US",
    "sg:address":"307 E Call St",
    "sg:city":"Algona",
    "sg:classifiers":[
        {
            "category":"Professional",
            "subcategory":"Accounting & Tax Preparation",
            "type":"Services"
        }
    ],
    "sg:phone":"+1 515 295 7275",
    "sg:postcode":"50511",
    "sg:province":"IA",
    "sg:tags":[
        "accountant"
    ],
    "wof:name":"Erpelding Voight & Co",
    "wof:placetype":"venue"
},
  "geometry": {"coordinates":[-94.23303799999999,43.069951],"type":"Point"}
}