{
  "type": "Feature",
  "properties": {
    "iso:country":"US",
    "sg:address":"215 Main St",
    "sg:city":"Little Rock",
    "sg:classifiers":[
        {
            "category":"Manufacturing",
            "subcategory":"Retail Goods",
            "type":"Manufacturing & Wholesale Goods"
        }
    ],
    "sg:phone":"+1 712 479 2869",
    "sg:postcode":"51243",
    "sg:province":"IA",
    "sg:tags":[
        "product",
        "mfg"
    ],
    "wof:name":"Raco Industries",
    "wof:placetype":"venue"
},
  "geometry": {"coordinates":[-95.88329,43.442951],"type":"Point"}
}