{
  "type": "Feature",
  "properties": {
    "addr:full":"118 N Main St Conrad IA 50621",
    "addr:housenumber":"118",
    "addr:postcode":"50621",
    "addr:street":"N Main St",
    "iso:country":"US",
    "sg:address":"118 N Main St",
    "sg:city":"Conrad",
    "sg:classifiers":[
        {
            "category":"Personal",
            "subcategory":"Beauty Salon",
            "type":"Services"
        }
    ],
    "sg:phone":"+1 641 366 3077",
    "sg:postcode":"50621",
    "sg:province":"IA",
    "sg:tags":[
        "shop"
    ],
    "wof:name":"Classic Cuts",
    "wof:placetype":"venue"
},
  "geometry": {"coordinates":[-92.874667,42.224908],"type":"Point"}
}