{
  "type": "Feature",
  "properties": {
    "iso:country":"US",
    "sg:address":"2820 S Martha St",
    "sg:city":"Sioux City",
    "sg:classifiers":[
        {
            "category":"Organizations",
            "subcategory":"Religious Organization",
            "type":"Services"
        }
    ],
    "sg:phone":"+1 712 276 5026",
    "sg:postcode":"51106",
    "sg:province":"IA",
    "wof:name":"Saints Wrestling Club Inc",
    "wof:placetype":"venue"
},
  "geometry": {"coordinates":[-96.36081900000001,42.458664],"type":"Point"}
}