{
  "type": "Feature",
  "properties": {
    "addr:full":"1922 McMurray Ave Webster City IA 50595",
    "addr:housenumber":"1922",
    "addr:postcode":"50595",
    "addr:street":"Mcmurray Ave",
    "iso:country":"US",
    "sg:address":"1922 McMurray Ave",
    "sg:city":"Webster City",
    "sg:classifiers":[
        {
            "category":"Real Estate",
            "subcategory":"Real Estate Agent",
            "type":"Services"
        }
    ],
    "sg:phone":"+1 515 832 5667",
    "sg:postcode":"50595",
    "sg:province":"IA",
    "wof:name":"Farmers National Co",
    "wof:placetype":"venue"
},
  "geometry": {"coordinates":[-93.73511499999999,42.507383],"type":"Point"}
}