{
  "type": "Feature",
  "properties": {
    "iso:country":"US",
    "sg:address":"1303 Tomahawk Dr",
    "sg:city":"Dubuque",
    "sg:classifiers":[
        {
            "category":"Building & Trades",
            "subcategory":"Construction",
            "type":"Services"
        }
    ],
    "sg:phone":"+1 563 556 5297",
    "sg:postcode":"52003",
    "sg:province":"IA",
    "sg:tags":[
        "hanging",
        "contractor"
    ],
    "wof:name":"Bettcher Painting",
    "wof:placetype":"venue"
},
  "geometry": {"coordinates":[-90.670112,42.474799],"type":"Point"}
}