{
  "type": "Feature",
  "properties": {
    "addr:full":"4165 120th St Urbandale IA 50323",
    "addr:housenumber":"4165",
    "addr:postcode":"50323",
    "addr:street":"120Th St",
    "iso:country":"US",
    "sg:address":"4165 120th St",
    "sg:city":"Urbandale",
    "sg:classifiers":[
        {
            "category":"Professional",
            "subcategory":"Management & Consulting",
            "type":"Services"
        }
    ],
    "sg:phone":"+1 515 278 1931",
    "sg:postcode":"50323",
    "sg:province":"IA",
    "sg:tags":[
        "consultant",
        "resource",
        "human"
    ],
    "sg:website":"www.meritresources.com",
    "wof:name":"Merit Resources Inc",
    "wof:placetype":"venue"
},
  "geometry": {"coordinates":[-93.77962100000001,41.633332],"type":"Point"}
}