{
  "type": "Feature",
  "properties": {
    "addr:full":"107 Main St Van Horne IA 52346",
    "addr:housenumber":"107",
    "addr:postcode":"52346",
    "addr:street":"Main St Van",
    "iso:country":"US",
    "sg:address":"107 Main St",
    "sg:city":"Van Horne",
    "sg:classifiers":[
        {
            "category":"Bars & Pubs",
            "type":"Food & Drink"
        }
    ],
    "sg:phone":"+1 319 228 8439",
    "sg:postcode":"52346",
    "sg:province":"IA",
    "sg:tags":[
        "lounge",
        "cocktail"
    ],
    "wof:name":"Main Street Station",
    "wof:placetype":"venue"
},
  "geometry": {"coordinates":[-92.091047,42.008508],"type":"Point"}
}