{
  "type": "Feature",
  "properties": {
    "addr:full":"108 1st St E Mt Vernon IA 52314",
    "addr:housenumber":"108",
    "addr:postcode":"52314",
    "addr:street":"1St St",
    "iso:country":"US",
    "sg:address":"108 1st St E",
    "sg:city":"Mt Vernon",
    "sg:classifiers":[
        {
            "category":"Health Services",
            "subcategory":"Health Practitioner",
            "type":"Services"
        }
    ],
    "sg:phone":"+1 319 895 8684",
    "sg:postcode":"52314",
    "sg:province":"IA",
    "sg:tags":[
        "therapist",
        "physical"
    ],
    "wof:name":"Physiotherapy Associates Inc",
    "wof:placetype":"venue"
},
  "geometry": {"coordinates":[-91.417025,41.922151],"type":"Point"}
}