{
  "type": "Feature",
  "properties": {
    "iso:country":"US",
    "sg:address":"1203 3rd Ave",
    "sg:city":"Sheldon",
    "sg:classifiers":[
        {
            "category":"Manufacturing",
            "subcategory":"Signs",
            "type":"Manufacturing & Wholesale Goods"
        }
    ],
    "sg:phone":"+1 712 324 5118",
    "sg:postcode":"51201",
    "sg:province":"IA",
    "wof:name":"Sign Graphics",
    "wof:placetype":"venue"
},
  "geometry": {"coordinates":[-95.85620400000001,43.177496],"type":"Point"}
}