{
  "type": "Feature",
  "properties": {
    "iso:country":"US",
    "sg:address":"8431 Hickman Rd",
    "sg:city":"Urbandale",
    "sg:classifiers":[
        {
            "category":"Real Estate",
            "subcategory":"Real Estate Agent",
            "type":"Services"
        }
    ],
    "sg:phone":"+1 515 453 7590",
    "sg:postcode":"50322",
    "sg:province":"IA",
    "wof:name":"Kathryn Neuwerth",
    "wof:placetype":"venue"
},
  "geometry": {"coordinates":[-93.733135,41.615002],"type":"Point"}
}