{
  "type": "Feature",
  "properties": {
    "iso:country":"US",
    "sg:address":"612 10th St",
    "sg:city":"Perry",
    "sg:classifiers":[
        {
            "category":"Health Services",
            "subcategory":"Podiatrist",
            "type":"Services"
        }
    ],
    "sg:phone":"+1 515 465 5688",
    "sg:postcode":"50220",
    "sg:province":"IA",
    "wof:name":"Todd R Miller DPM",
    "wof:placetype":"venue"
},
  "geometry": {"coordinates":[-94.094388,41.833774],"type":"Point"}
}