{
  "type": "Feature",
  "properties": {
    "addr:full":"1918 Greene St Adel IA 50003",
    "addr:housenumber":"1918",
    "addr:postcode":"50003",
    "addr:street":"Greene St",
    "iso:country":"US",
    "sg:address":"1918 Greene St",
    "sg:city":"Adel",
    "sg:classifiers":[
        {
            "category":"Government",
            "subcategory":"Office",
            "type":"Public Place"
        }
    ],
    "sg:phone":"+1 515 993 3413",
    "sg:postcode":"50003",
    "sg:province":"IA",
    "sg:tags":[
        "federal"
    ],
    "wof:name":"Natural Resources Conservation",
    "wof:placetype":"venue"
},
  "geometry": {"coordinates":[-94.031482,41.613865],"type":"Point"}
}