{
  "type": "Feature",
  "properties": {
    "iso:country":"US",
    "sg:address":"4318 Union St",
    "sg:city":"Elk Horn",
    "sg:classifiers":[
        {
            "category":"Shopping",
            "subcategory":"Gifts & Souvenirs",
            "type":"Retail Goods"
        }
    ],
    "sg:phone":"+1 712 764 7632",
    "sg:postcode":"51531",
    "sg:province":"IA",
    "sg:tags":[
        "shop"
    ],
    "wof:name":"Bev's Butik",
    "wof:placetype":"venue"
},
  "geometry": {"coordinates":[-95.06098299999999,41.593806],"type":"Point"}
}