{
  "type": "Feature",
  "properties": {
    "iso:country":"US",
    "sg:address":"1714 River St",
    "sg:city":"Waterloo",
    "sg:classifiers":[
        {
            "category":"Building & Trades",
            "subcategory":"Construction",
            "type":"Services"
        }
    ],
    "sg:phone":"+1 319 232 4741",
    "sg:postcode":"50702",
    "sg:province":"IA",
    "sg:tags":[
        "fabricator",
        "metal"
    ],
    "wof:name":"C & C Welding & Sandblasting",
    "wof:placetype":"venue"
},
  "geometry": {"coordinates":[-92.325442,42.488315],"type":"Point"}
}