{
  "type": "Feature",
  "properties": {
    "iso:country":"US",
    "sg:address":"3056 318th St",
    "sg:city":"Hull",
    "sg:classifiers":[
        {
            "category":"Real Estate",
            "subcategory":"Real Estate Operator",
            "type":"Services"
        }
    ],
    "sg:phone":"+1 712 439 2080",
    "sg:postcode":"51239",
    "sg:province":"IA",
    "sg:tags":[
        "building",
        "parks"
    ],
    "wof:name":"Northwest Builders",
    "wof:placetype":"venue"
},
  "geometry": {"coordinates":[-96.18572399999999,43.188036],"type":"Point"}
}