{
  "type": "Feature",
  "properties": {
    "iso:country":"US",
    "sg:address":"19 2nd Ave NW",
    "sg:city":"Le Mars",
    "sg:classifiers":[
        {
            "category":"Government",
            "subcategory":"Office",
            "type":"Public Place"
        }
    ],
    "sg:phone":"+1 712 546 8877",
    "sg:postcode":"51031",
    "sg:province":"IA",
    "sg:tags":[
        "state",
        "resource"
    ],
    "wof:name":"Human Services Dept",
    "wof:placetype":"venue"
},
  "geometry": {"coordinates":[-96.16935700000001,42.794053],"type":"Point"}
}