{
  "type": "Feature",
  "properties": {
    "iso:country":"US",
    "sg:address":"63079 US Hwy 275",
    "sg:city":"Glenwood",
    "sg:phone":"+1 712 527 3368",
    "sg:postcode":"51534",
    "sg:province":"IA",
    "sg:tags":[
        "farm",
        "field",
        "corn",
        "crop",
        "soybean"
    ],
    "wof:name":"Alan Agnew",
    "wof:placetype":"venue"
},
  "geometry": {"coordinates":[-95.671134,40.972757],"type":"Point"}
}