{
  "type": "Feature",
  "properties": {
    "iso:country":"US",
    "sg:address":"2420 Lincoln Way",
    "sg:city":"Ames",
    "sg:classifiers":[
        {
            "category":"Arts & Performance",
            "subcategory":"Theater",
            "type":"Entertainment"
        }
    ],
    "sg:phone":"+1 515 292 5483",
    "sg:postcode":"50014",
    "sg:province":"IA",
    "sg:tags":[
        "bureau"
    ],
    "wof:name":"People's Productions",
    "wof:placetype":"venue"
},
  "geometry": {"coordinates":[-93.649833,42.022728],"type":"Point"}
}