{
  "type": "Feature",
  "properties": {
    "addr:full":"811 N 56th St Clear Lake IA 50428",
    "addr:housenumber":"811",
    "addr:postcode":"50428",
    "addr:street":"N 56Th St",
    "iso:country":"US",
    "sg:address":"811 N 56th St",
    "sg:city":"Clear Lake",
    "sg:classifiers":[
        {
            "category":"Food & Beverages",
            "subcategory":"Fruits & Vegetables",
            "type":"Retail Goods"
        }
    ],
    "sg:phone":"+1 641 357 4097",
    "sg:postcode":"50428",
    "sg:province":"IA",
    "sg:tags":[
        "produce"
    ],
    "wof:name":"Furleigh Fruit & Veg Farm",
    "wof:placetype":"venue"
},
  "geometry": {"coordinates":[-93.320188,43.145394],"type":"Point"}
}