{
  "type": "Feature",
  "properties": {
    "iso:country":"US",
    "sg:address":"1406 SW 7th St",
    "sg:city":"Atlantic",
    "sg:classifiers":[
        {
            "category":"Social Services",
            "subcategory":"Job Training",
            "type":"Services"
        }
    ],
    "sg:phone":"+1 712 243 2668",
    "sg:postcode":"50022",
    "sg:province":"IA",
    "sg:tags":[
        "rehabilitation"
    ],
    "sg:website":"www.cassinc.org",
    "wof:name":"Cass Inc",
    "wof:placetype":"venue"
},
  "geometry": {"coordinates":[-95.033215,41.39644],"type":"Point"}
}