{
  "type": "Feature",
  "properties": {
    "iso:country":"US",
    "sg:address":"114 E Broadway St",
    "sg:city":"Eagle Grove",
    "sg:classifiers":[
        {
            "category":"Real Estate",
            "subcategory":"Real Estate Agent",
            "type":"Services"
        }
    ],
    "sg:phone":"+1 515 448 5017",
    "sg:postcode":"50533",
    "sg:province":"IA",
    "sg:tags":[
        "cooperative"
    ],
    "wof:name":"W & H Co-Op Oil Co",
    "wof:placetype":"venue"
},
  "geometry": {"coordinates":[-93.901073,42.664053],"type":"Point"}
}