{
  "type": "Feature",
  "properties": {
    "iso:country":"US",
    "sg:address":"2430 450th Ave",
    "sg:city":"Wallingford",
    "sg:classifiers":[
        {
            "category":"Real Estate",
            "subcategory":"Real Estate Operator",
            "type":"Services"
        }
    ],
    "sg:phone":"+1 712 867 4575",
    "sg:postcode":"51365",
    "sg:province":"IA",
    "sg:tags":[
        "property",
        "lessor"
    ],
    "wof:name":"Nitchals John",
    "wof:placetype":"venue"
},
  "geometry": {"coordinates":[-94.698076,43.29703],"type":"Point"}
}