{
  "type": "Feature",
  "properties": {
    "iso:country":"US",
    "sg:address":"2501 Grand Ave",
    "sg:city":"Ames",
    "sg:classifiers":[
        {
            "category":"Shopping",
            "subcategory":"Pharmacy",
            "type":"Retail Goods"
        }
    ],
    "sg:phone":"+1 515 232 8276",
    "sg:postcode":"50010",
    "sg:province":"IA",
    "sg:website":"www.walgreens.com",
    "wof:name":"Walgreens",
    "wof:placetype":"venue"
},
  "geometry": {"coordinates":[-93.620717,42.048477],"type":"Point"}
}