{
  "type": "Feature",
  "properties": {
    "iso:country":"US",
    "sg:address":"2981 Plank Rd",
    "sg:city":"Keokuk",
    "sg:classifiers":[
        {
            "category":"Education",
            "subcategory":"School",
            "type":"Public Place"
        }
    ],
    "sg:phone":"+1 319 524 5450",
    "sg:postcode":"52632",
    "sg:province":"IA",
    "wof:name":"Cardinal Stritch High School",
    "wof:placetype":"venue"
},
  "geometry": {"coordinates":[-91.39664,40.416217],"type":"Point"}
}