{
  "type": "Feature",
  "properties": {
    "addr:full":"15255 65th Ave Blue Grass IA 52726",
    "addr:housenumber":"15255",
    "addr:postcode":"52726",
    "addr:street":"65Th Ave",
    "iso:country":"US",
    "sg:address":"15255 65th Ave",
    "sg:city":"Blue Grass",
    "sg:classifiers":[
        {
            "category":"Professional",
            "type":"Services"
        }
    ],
    "sg:phone":"+1 563 381 1428",
    "sg:postcode":"52726",
    "sg:province":"IA",
    "wof:name":"Alvin Ehlers",
    "wof:placetype":"venue"
},
  "geometry": {"coordinates":[-90.775131,41.527807],"type":"Point"}
}