{
  "type": "Feature",
  "properties": {
    "addr:full":"902 W Kimberly Rd Davenport IA 52806",
    "addr:housenumber":"902",
    "addr:postcode":"52806",
    "addr:street":"W Kimberly Rd",
    "iso:country":"US",
    "sg:address":"902 W Kimberly Rd",
    "sg:city":"Davenport",
    "sg:classifiers":[
        {
            "category":"Shopping",
            "subcategory":"Clothing, Apparel, & Fashions",
            "type":"Retail Goods"
        }
    ],
    "sg:phone":"+1 563 388 1596",
    "sg:postcode":"52806",
    "sg:province":"IA",
    "sg:website":"www.fashionbug.com",
    "wof:name":"Fashion Bug",
    "wof:placetype":"venue"
},
  "geometry": {"coordinates":[-90.588611,41.560233],"type":"Point"}
}