{
  "type": "Feature",
  "properties": {
    "addr:full":"10681 500th St Thompson IA 50465",
    "addr:housenumber":"10681",
    "addr:postcode":"50465",
    "addr:street":"500Th St",
    "iso:country":"US",
    "sg:address":"10681 500th St",
    "sg:city":"Thompson",
    "sg:classifiers":[
        {
            "category":"Organizations",
            "subcategory":"Religious Organization",
            "type":"Services"
        }
    ],
    "sg:phone":"+1 641 584 2743",
    "sg:postcode":"50465",
    "sg:province":"IA",
    "sg:tags":[
        "church"
    ],
    "wof:name":"Trinity Lutheran Church",
    "wof:placetype":"venue"
},
  "geometry": {"coordinates":[-93.780108,43.487498],"type":"Point"}
}