{
  "type": "Feature",
  "properties": {
    "iso:country":"US",
    "sg:address":"201 N Cherry St",
    "sg:city":"Creston",
    "sg:classifiers":[
        {
            "category":"Wholesale",
            "subcategory":"Farm Supplies",
            "type":"Manufacturing & Wholesale Goods"
        }
    ],
    "sg:phone":"+1 641 782 7025",
    "sg:postcode":"50801",
    "sg:province":"IA",
    "sg:tags":[
        "auction",
        "livestock",
        "market"
    ],
    "wof:name":"Creston Livestock Auction",
    "wof:placetype":"venue"
},
  "geometry": {"coordinates":[-94.35673199999999,41.059698],"type":"Point"}
}