{
  "type": "Feature",
  "properties": {
    "iso:country":"US",
    "sg:address":"101 S 1st St",
    "sg:city":"Marquette",
    "sg:classifiers":[
        {
            "category":"Travel",
            "subcategory":"Hotels & Motels",
            "type":"Entertainment"
        }
    ],
    "sg:phone":"+1 563 873 3497",
    "sg:postcode":"52164",
    "sg:province":"IA",
    "wof:name":"Frontier Motel",
    "wof:placetype":"venue"
},
  "geometry": {"coordinates":[-91.88457699999999,42.861632],"type":"Point"}
}