{
  "type": "Feature",
  "properties": {
    "iso:country":"US",
    "sg:address":"1319 Union Ave",
    "sg:city":"Cushing",
    "sg:phone":"+1 712 384 2431",
    "sg:postcode":"51018",
    "sg:province":"IA",
    "sg:tags":[
        "farm",
        "grain",
        "cash"
    ],
    "wof:name":"Huth Farms",
    "wof:placetype":"venue"
},
  "geometry": {"coordinates":[-95.68198099999999,42.513165],"type":"Point"}
}