{
  "type": "Feature",
  "properties": {
    "iso:country":"US",
    "sg:address":"13333 University Ave",
    "sg:city":"Clive",
    "sg:classifiers":[
        {
            "category":"Professional",
            "type":"Services"
        }
    ],
    "sg:phone":"+1 515 224 6492",
    "sg:postcode":"50325",
    "sg:province":"IA",
    "sg:tags":[
        "establishment"
    ],
    "wof:name":"Manning Family LTD Partnership",
    "wof:placetype":"venue"
},
  "geometry": {"coordinates":[-93.804627,41.600448],"type":"Point"}
}