{
  "type": "Feature",
  "properties": {
    "iso:country":"US",
    "sg:address":"15 S Dubuque St",
    "sg:city":"Iowa City",
    "sg:classifiers":[
        {
            "category":"Shopping",
            "subcategory":"Books",
            "type":"Retail Goods"
        }
    ],
    "sg:phone":"+1 319 337 2681",
    "sg:postcode":"52240",
    "sg:province":"IA",
    "sg:tags":[
        "dealer"
    ],
    "sg:website":"www.prairielights.com",
    "wof:name":"Prairie Lights Books",
    "wof:placetype":"venue"
},
  "geometry": {"coordinates":[-91.533185,41.660286],"type":"Point"}
}