{
  "type": "Feature",
  "properties": {
    "addr:full":"2701 SE Convenience Blvd Ankeny IA 50021",
    "addr:housenumber":"2701",
    "addr:postcode":"50021",
    "addr:street":"Se Convenience Blvd",
    "iso:country":"US",
    "sg:address":"2701 SE Convenience Blvd",
    "sg:city":"Ankeny",
    "sg:classifiers":[
        {
            "category":"Professional",
            "subcategory":"Computer Services",
            "type":"Services"
        }
    ],
    "sg:phone":"+1 515 964 9599",
    "sg:postcode":"50021",
    "sg:province":"IA",
    "sg:tags":[
        "consultant",
        "designer"
    ],
    "wof:name":"G P Solutions",
    "wof:placetype":"venue"
},
  "geometry": {"coordinates":[-93.572862,41.698249],"type":"Point"}
}