{
  "type": "Feature",
  "properties": {
    "iso:country":"US",
    "sg:address":"822 Douglas St",
    "sg:city":"Sioux City",
    "sg:classifiers":[
        {
            "category":"Government",
            "subcategory":"Office",
            "type":"Public Place"
        }
    ],
    "sg:phone":"+1 712 279 6500",
    "sg:postcode":"51101",
    "sg:province":"IA",
    "wof:name":"Woodbury County Motor Vehicle",
    "wof:placetype":"venue"
},
  "geometry": {"coordinates":[-96.40639899999999,42.498785],"type":"Point"}
}