{
  "type": "Feature",
  "properties": {
    "iso:country":"US",
    "sg:address":"22560 Raleigh Rd",
    "sg:city":"Pacific Junction",
    "sg:classifiers":[
        {
            "category":"Retail",
            "subcategory":"Laundry & Dry Cleaning",
            "type":"Services"
        }
    ],
    "sg:phone":"+1 712 323 2325",
    "sg:postcode":"51561",
    "sg:province":"IA",
    "sg:tags":[
        "cleaners",
        "rug",
        "carpet"
    ],
    "wof:name":"Natural Carpet Cleaners",
    "wof:placetype":"venue"
},
  "geometry": {"coordinates":[-95.759328,40.904498],"type":"Point"}
}