{
  "type": "Feature",
  "properties": {
    "addr:full":"6909 Hickman Rd Des Moines IA 50322",
    "addr:housenumber":"6909",
    "addr:postcode":"50322",
    "addr:street":"Hickman Rd Des",
    "iso:country":"US",
    "sg:address":"6909 Hickman Rd",
    "sg:city":"Des Moines",
    "sg:classifiers":[
        {
            "category":"Shopping",
            "type":"Retail Goods"
        }
    ],
    "sg:phone":"+1 515 278 1321",
    "sg:postcode":"50322",
    "sg:province":"IA",
    "sg:tags":[
        "hearing",
        "equipment",
        "supply",
        "impaired"
    ],
    "wof:name":"Professional Hearing Aid Ctr",
    "wof:placetype":"venue"
},
  "geometry": {"coordinates":[-93.712749,41.614616],"type":"Point"}
}