{
  "type": "Feature",
  "properties": {
    "addr:full":"105 S Main St George IA 51237",
    "addr:housenumber":"105",
    "addr:postcode":"51237",
    "addr:street":"S Main",
    "iso:country":"US",
    "sg:address":"105 S Main St",
    "sg:city":"George",
    "sg:classifiers":[
        {
            "category":"Personal",
            "subcategory":"Beauty Salon",
            "type":"Services"
        }
    ],
    "sg:phone":"+1 712 475 3375",
    "sg:postcode":"51237",
    "sg:province":"IA",
    "sg:tags":[
        "hair",
        "stylist"
    ],
    "wof:name":"Hair Hut",
    "wof:placetype":"venue"
},
  "geometry": {"coordinates":[-96.002342,43.343561],"type":"Point"}
}