{
  "type": "Feature",
  "properties": {
    "iso:country":"US",
    "sg:address":"306 Union St",
    "sg:city":"West Union",
    "sg:classifiers":[
        {
            "category":"Real Estate",
            "subcategory":"Real Estate Agent",
            "type":"Services"
        }
    ],
    "sg:phone":"+1 563 422 3277",
    "sg:postcode":"52175",
    "sg:province":"IA",
    "wof:name":"Iowa Realty Co",
    "wof:placetype":"venue"
},
  "geometry": {"coordinates":[-91.810536,42.958696],"type":"Point"}
}