{
  "type": "Feature",
  "properties": {
    "addr:full":"1166 65th St West Des Moines IA 50266",
    "addr:housenumber":"1166",
    "addr:postcode":"50266",
    "addr:street":"65Th St",
    "iso:country":"US",
    "sg:address":"1166 65th St",
    "sg:city":"West Des Moines",
    "sg:classifiers":[
        {
            "category":"Real Estate",
            "subcategory":"Real Estate Operator",
            "type":"Services"
        }
    ],
    "sg:phone":"+1 515 225 6889",
    "sg:postcode":"50266",
    "sg:province":"IA",
    "sg:tags":[
        "property",
        "lessor"
    ],
    "wof:name":"Johnne D Syverson",
    "wof:placetype":"venue"
},
  "geometry": {"coordinates":[-93.79679,41.584413],"type":"Point"}
}