{
  "type": "Feature",
  "properties": {
    "iso:country":"US",
    "sg:address":"2906 NE Huntington Ln",
    "sg:city":"Ankeny",
    "sg:classifiers":[
        {
            "category":"Professional",
            "subcategory":"Management & Consulting",
            "type":"Services"
        }
    ],
    "sg:phone":"+1 515 770 4343",
    "sg:postcode":"50021",
    "sg:province":"IA",
    "wof:name":"Susan L Nelson Inc",
    "wof:placetype":"venue"
},
  "geometry": {"coordinates":[-93.58283299999999,41.754861],"type":"Point"}
}