{
  "type": "Feature",
  "properties": {
    "iso:country":"US",
    "sg:address":"715 10th Ave S",
    "sg:city":"Mt Vernon",
    "sg:classifiers":[
        {
            "category":"Retail",
            "subcategory":"Funeral Services",
            "type":"Services"
        }
    ],
    "sg:phone":"+1 319 895 8425",
    "sg:postcode":"52314",
    "sg:province":"IA",
    "sg:tags":[
        "director"
    ],
    "wof:name":"Morgan Funeral Homes",
    "wof:placetype":"venue"
},
  "geometry": {"coordinates":[-91.429209,41.924483],"type":"Point"}
}