{
  "type": "Feature",
  "properties": {
    "iso:country":"US",
    "sg:address":"2111 Harrison Dr",
    "sg:city":"Clinton",
    "sg:classifiers":[
        {
            "category":"Building & Trades",
            "subcategory":"Construction",
            "type":"Services"
        },
        {
            "category":"Manufacturing",
            "subcategory":"Building Materials",
            "type":"Manufacturing & Wholesale Goods"
        }
    ],
    "sg:phone":"+1 563 242 6036",
    "sg:postcode":"52732",
    "sg:province":"IA",
    "sg:tags":[
        "roofing",
        "industrial",
        "sheet",
        "work",
        "metal",
        "contractor",
        "siding",
        "contractors-commercial"
    ],
    "wof:name":"Jeff King's Snowplowing",
    "wof:placetype":"venue"
},
  "geometry": {"coordinates":[-90.23437,41.818588],"type":"Point"}
}