{
  "type": "Feature",
  "properties": {
    "addr:full":"3243 University Ave Waterloo IA 50701",
    "addr:housenumber":"3243",
    "addr:postcode":"50701",
    "addr:street":"University Ave",
    "iso:country":"US",
    "sg:address":"3243 University Ave",
    "sg:city":"Waterloo",
    "sg:classifiers":[
        {
            "category":"Social Services",
            "subcategory":"Child Care",
            "type":"Services"
        }
    ],
    "sg:phone":"+1 319 234 1066",
    "sg:postcode":"50701",
    "sg:province":"IA",
    "sg:website":"www.kindercare.com",
    "wof:name":"Kinder Care Learning Ctr",
    "wof:placetype":"venue"
},
  "geometry": {"coordinates":[-92.389453,42.50115],"type":"Point"}
}