{
  "type": "Feature",
  "properties": {
    "addr:full":"367 Cedar Cross Rd Dubuque IA 52003",
    "addr:housenumber":"367",
    "addr:postcode":"52003",
    "addr:street":"Cedar Cross Rd",
    "iso:country":"US",
    "sg:address":"367 Cedar Cross Rd",
    "sg:city":"Dubuque",
    "sg:classifiers":[
        {
            "category":"Organizations",
            "subcategory":"Professional Association",
            "type":"Services"
        }
    ],
    "sg:phone":"+1 563 583 8249",
    "sg:postcode":"52003",
    "sg:province":"IA",
    "wof:name":"American Cancer Society",
    "wof:placetype":"venue"
},
  "geometry": {"coordinates":[-90.717428,42.486179],"type":"Point"}
}