{
  "type": "Feature",
  "properties": {
    "iso:country":"US",
    "sg:address":"302 SE Kent St",
    "sg:city":"Greenfield",
    "sg:classifiers":[
        {
            "category":"Restaurant",
            "type":"Food & Drink"
        }
    ],
    "sg:menulink":"http://www.allmenus.com/ia/greenfield/67013-pizza-hut/menu/",
    "sg:phone":"+1 641 343 7163",
    "sg:postcode":"50849",
    "sg:province":"IA",
    "sg:tags":[
        "american",
        "pizza"
    ],
    "wof:name":"Pizza Hut",
    "wof:placetype":"venue"
},
  "geometry": {"coordinates":[-94.45781599999999,41.303178],"type":"Point"}
}