{
  "type": "Feature",
  "properties": {
    "iso:country":"US",
    "sg:address":"11 9th Ave",
    "sg:city":"Livermore",
    "sg:classifiers":[
        {
            "category":"Professional",
            "type":"Services"
        }
    ],
    "sg:phone":"+1 515 379 1269",
    "sg:postcode":"50558",
    "sg:province":"IA",
    "sg:tags":[
        "establishment"
    ],
    "wof:name":"Crahan Electric",
    "wof:placetype":"venue"
},
  "geometry": {"coordinates":[-94.179126,42.864081],"type":"Point"}
}