{
  "type": "Feature",
  "properties": {
    "addr:full":"114 N Market St Ottumwa IA 52501",
    "addr:housenumber":"114",
    "addr:postcode":"52501",
    "addr:street":"N Market St",
    "iso:country":"US",
    "sg:address":"114 N Market St",
    "sg:city":"Ottumwa",
    "sg:classifiers":[
        {
            "category":"Professional",
            "subcategory":"Lawyer & Legal Services",
            "type":"Services"
        }
    ],
    "sg:phone":"+1 641 684 9068",
    "sg:postcode":"52501",
    "sg:province":"IA",
    "sg:tags":[
        "attorney"
    ],
    "wof:name":"William H Appel Jr",
    "wof:placetype":"venue"
},
  "geometry": {"coordinates":[-92.410186,41.018169],"type":"Point"}
}