{
  "type": "Feature",
  "properties": {
    "iso:country":"US",
    "sg:address":"6425 180th St",
    "sg:city":"Schaller",
    "sg:phone":"+1 712 275 4462",
    "sg:postcode":"51053",
    "sg:province":"IA",
    "sg:tags":[
        "farm",
        "corn",
        "soybean"
    ],
    "wof:name":"Kyle Bennett",
    "wof:placetype":"venue"
},
  "geometry": {"coordinates":[-95.350447,42.4435],"type":"Point"}
}