{
  "type": "Feature",
  "properties": {
    "iso:country":"US",
    "sg:address":"1345 440th St",
    "sg:city":"Cherokee",
    "sg:phone":"+1 712 437 2257",
    "sg:postcode":"51012",
    "sg:province":"IA",
    "sg:tags":[
        "farm",
        "corn",
        "soybean"
    ],
    "wof:name":"Anderson Gust",
    "wof:placetype":"venue"
},
  "geometry": {"coordinates":[-95.614358,42.881092],"type":"Point"}
}