{
  "type": "Feature",
  "properties": {
    "iso:country":"US",
    "sg:address":"6875 State St",
    "sg:city":"Bettendorf",
    "sg:classifiers":[
        {
            "category":"Freight",
            "type":"Transportation"
        }
    ],
    "sg:phone":"+1 563 332 4300",
    "sg:postcode":"52722",
    "sg:province":"IA",
    "sg:tags":[
        "warehouse",
        "storage"
    ],
    "wof:name":"Ameri Cold Logistics",
    "wof:placetype":"venue"
},
  "geometry": {"coordinates":[-90.437551,41.55916],"type":"Point"}
}