{
  "type": "Feature",
  "properties": {
    "iso:country":"US",
    "sg:address":"123 1st St SW",
    "sg:city":"Waverly",
    "sg:classifiers":[
        {
            "category":"Government",
            "subcategory":"Fire Station",
            "type":"Public Place"
        }
    ],
    "sg:phone":"+1 319 352 5521",
    "sg:postcode":"50677",
    "sg:province":"IA",
    "sg:tags":[
        "department"
    ],
    "wof:name":"Waverly Fire Dept",
    "wof:placetype":"venue"
},
  "geometry": {"coordinates":[-92.47190399999999,42.72554],"type":"Point"}
}