{
  "type": "Feature",
  "properties": {
    "iso:country":"US",
    "sg:address":"1014 Parrott St",
    "sg:city":"Aplington",
    "sg:classifiers":[
        {
            "category":"Wholesale",
            "subcategory":"Auto Parts",
            "type":"Manufacturing & Wholesale Goods"
        }
    ],
    "sg:phone":"+1 319 347 2491",
    "sg:postcode":"50604",
    "sg:province":"IA",
    "sg:tags":[
        "repair",
        "used",
        "general"
    ],
    "wof:name":"Repair & Conversion",
    "wof:placetype":"venue"
},
  "geometry": {"coordinates":[-92.88600099999999,42.584055],"type":"Point"}
}