{
  "type": "Feature",
  "properties": {
    "addr:full":"301 2nd St Gladbrook IA 50635",
    "addr:housenumber":"301",
    "addr:postcode":"50635",
    "addr:street":"2Nd St",
    "iso:country":"US",
    "sg:address":"301 2nd St",
    "sg:city":"Gladbrook",
    "sg:classifiers":[
        {
            "category":"Education",
            "subcategory":"Library",
            "type":"Public Place"
        }
    ],
    "sg:phone":"+1 641 473 3236",
    "sg:postcode":"50635",
    "sg:province":"IA",
    "wof:name":"Gladbrook Public Library",
    "wof:placetype":"venue"
},
  "geometry": {"coordinates":[-92.716864,42.187689],"type":"Point"}
}