{
  "type": "Feature",
  "properties": {
    "addr:full":"1673 210th St New Market IA 51646",
    "addr:housenumber":"1673",
    "addr:postcode":"51646",
    "addr:street":"210Th St",
    "iso:country":"US",
    "sg:address":"1673 210th St",
    "sg:city":"New Market",
    "sg:classifiers":[
        {
            "category":"Farming",
            "subcategory":"Farm",
            "type":"Manufacturing & Wholesale Goods"
        }
    ],
    "sg:phone":"+1 712 585 3459",
    "sg:postcode":"51646",
    "sg:province":"IA",
    "wof:name":"Ladoga Hills Farm",
    "wof:placetype":"venue"
},
  "geometry": {"coordinates":[-94.80043000000001,40.741506],"type":"Point"}
}