{
  "type": "Feature",
  "properties": {
    "addr:full":"302 N Cherry St St Charles IA 50240",
    "addr:housenumber":"302",
    "addr:postcode":"50240",
    "addr:street":"N Cherry St",
    "iso:country":"US",
    "sg:address":"302 N Cherry St",
    "sg:city":"St Charles",
    "sg:classifiers":[
        {
            "category":"Organizations",
            "subcategory":"Religious Organization",
            "type":"Services"
        }
    ],
    "sg:phone":"+1 641 396 2943",
    "sg:postcode":"50240",
    "sg:province":"IA",
    "wof:name":"Freefire Ministries",
    "wof:placetype":"venue"
},
  "geometry": {"coordinates":[-93.812372,41.290305],"type":"Point"}
}