{
  "type": "Feature",
  "properties": {
    "iso:country":"US",
    "sg:address":"2000 Westfield Ave",
    "sg:city":"Waterloo",
    "sg:classifiers":[
        {
            "category":"Manufacturing",
            "subcategory":"Tools & Machinery",
            "type":"Manufacturing & Wholesale Goods"
        }
    ],
    "sg:phone":"+1 319 292 4311",
    "sg:postcode":"50701",
    "sg:province":"IA",
    "sg:tags":[
        "casting",
        "mfg"
    ],
    "wof:name":"John Deere Foundry",
    "wof:placetype":"venue"
},
  "geometry": {"coordinates":[-92.36957700000001,42.507489],"type":"Point"}
}