{
  "type": "Feature",
  "properties": {
    "iso:country":"US",
    "sg:address":"2601 Wright Brothers Blvd E SW",
    "sg:city":"Cedar Rapids",
    "sg:classifiers":[
        {
            "category":"Airport",
            "type":"Transportation"
        }
    ],
    "sg:phone":"+1 319 366 1925",
    "sg:postcode":"52404",
    "sg:province":"IA",
    "sg:tags":[
        "aircraft",
        "maintenance"
    ],
    "wof:name":"Piedmont Hawthorne Aviation",
    "wof:placetype":"venue"
},
  "geometry": {"coordinates":[-91.625406,41.890026],"type":"Point"}
}