{
  "type": "Feature",
  "properties": {
    "addr:full":"514 1st St Glenwood IA 51534",
    "addr:housenumber":"514",
    "addr:postcode":"51534",
    "addr:street":"1St St",
    "iso:country":"US",
    "sg:address":"514 1st St",
    "sg:city":"Glenwood",
    "sg:classifiers":[
        {
            "category":"Health Services",
            "subcategory":"Doctor",
            "type":"Services"
        }
    ],
    "sg:phone":"+1 712 527 3144",
    "sg:postcode":"51534",
    "sg:province":"IA",
    "sg:tags":[
        "dentist"
    ],
    "wof:name":"Glenwood Family Dentistry",
    "wof:placetype":"venue"
},
  "geometry": {"coordinates":[-95.743854,41.047426],"type":"Point"}
}