{
  "type": "Feature",
  "properties": {
    "iso:country":"US",
    "sg:address":"112 E Main St",
    "sg:city":"Clarinda",
    "sg:classifiers":[
        {
            "category":"Government",
            "subcategory":"Office",
            "type":"Public Place"
        }
    ],
    "sg:phone":"+1 712 542 3214",
    "sg:postcode":"51632",
    "sg:province":"IA",
    "sg:tags":[
        "county"
    ],
    "wof:name":"Page County Clerk",
    "wof:placetype":"venue"
},
  "geometry": {"coordinates":[-95.03772600000001,40.738335],"type":"Point"}
}