{
  "type": "Feature",
  "properties": {
    "addr:full":"1603 Rolling St Ruthven IA 51358",
    "addr:housenumber":"1603",
    "addr:postcode":"51358",
    "addr:street":"Rolling St",
    "iso:country":"US",
    "sg:address":"1603 Rolling St",
    "sg:city":"Ruthven",
    "sg:phone":"+1 712 837 5513",
    "sg:postcode":"51358",
    "sg:province":"IA",
    "sg:tags":[
        "gas"
    ],
    "wof:name":"Ruthven Co-Op Oil Co",
    "wof:placetype":"venue"
},
  "geometry": {"coordinates":[-94.899027,43.129361],"type":"Point"}
}