{
  "type": "Feature",
  "properties": {
    "iso:country":"US",
    "sg:address":"200 N Adams Ave",
    "sg:city":"Mason City",
    "sg:classifiers":[
        {
            "category":"Professional",
            "subcategory":"Accounting & Tax Preparation",
            "type":"Services"
        }
    ],
    "sg:phone":"+1 641 423 0574",
    "sg:postcode":"50401",
    "sg:province":"IA",
    "sg:tags":[
        "accountant"
    ],
    "wof:name":"Hogan-Hansen",
    "wof:placetype":"venue"
},
  "geometry": {"coordinates":[-93.204286,43.154517],"type":"Point"}
}