{
  "type": "Feature",
  "properties": {
    "iso:country":"US",
    "sg:address":"400 Collins Rd NE",
    "sg:city":"Cedar Rapids",
    "sg:classifiers":[
        {
            "category":"Government",
            "subcategory":"Office",
            "type":"Public Place"
        }
    ],
    "sg:phone":"+1 319 295 3170",
    "sg:postcode":"52402",
    "sg:province":"IA",
    "sg:tags":[
        "federal",
        "security"
    ],
    "wof:name":"US Defense Dept",
    "wof:placetype":"venue"
},
  "geometry": {"coordinates":[-91.64014899999999,42.028212],"type":"Point"}
}