{
  "type": "Feature",
  "properties": {
    "iso:country":"US",
    "sg:address":"223 Herman St",
    "sg:city":"Woolstock",
    "sg:classifiers":[
        {
            "category":"Wholesale",
            "subcategory":"Machinery & Supplies",
            "type":"Manufacturing & Wholesale Goods"
        }
    ],
    "sg:phone":"+1 515 839 5530",
    "sg:postcode":"50599",
    "sg:province":"IA",
    "sg:tags":[
        "farm",
        "equipment"
    ],
    "wof:name":"Broshar Implement Inc",
    "wof:placetype":"venue"
},
  "geometry": {"coordinates":[-93.844261,42.566369],"type":"Point"}
}