{
  "type": "Feature",
  "properties": {
    "addr:full":"905 Main St Boyden IA 51234",
    "addr:housenumber":"905",
    "addr:postcode":"51234",
    "addr:street":"Main St",
    "iso:country":"US",
    "sg:address":"905 Main St",
    "sg:city":"Boyden",
    "sg:classifiers":[
        {
            "category":"Education",
            "subcategory":"Library",
            "type":"Public Place"
        }
    ],
    "sg:phone":"+1 712 725 2281",
    "sg:postcode":"51234",
    "sg:province":"IA",
    "wof:name":"Boyden Public Library",
    "wof:placetype":"venue"
},
  "geometry": {"coordinates":[-96.00600900000001,43.191871],"type":"Point"}
}