{
  "type": "Feature",
  "properties": {
    "iso:country":"US",
    "sg:address":"315 Flindt Dr",
    "sg:city":"Storm Lake",
    "sg:classifiers":[
        {
            "category":"Manufacturing",
            "subcategory":"Metals",
            "type":"Manufacturing & Wholesale Goods"
        }
    ],
    "sg:phone":"+1 712 732 2760",
    "sg:postcode":"50588",
    "sg:province":"IA",
    "sg:tags":[
        "industrial",
        "valve"
    ],
    "sg:website":"www.merrillmfg.com",
    "wof:name":"Merrill Manufacturing Co",
    "wof:placetype":"venue"
},
  "geometry": {"coordinates":[-95.186234,42.637743],"type":"Point"}
}