{
  "type": "Feature",
  "properties": {
    "addr:full":"503 W Milwaukee St New Hampton IA 50659",
    "addr:housenumber":"503",
    "addr:postcode":"50659",
    "addr:street":"W Milwaukee St",
    "iso:country":"US",
    "sg:address":"503 W Milwaukee St",
    "sg:city":"New Hampton",
    "sg:classifiers":[
        {
            "category":"Restaurant",
            "type":"Food & Drink"
        }
    ],
    "sg:phone":"+1 641 394 5730",
    "sg:postcode":"50659",
    "sg:province":"IA",
    "wof:name":"Kolby's Dine & Stein",
    "wof:placetype":"venue"
},
  "geometry": {"coordinates":[-92.32221800000001,43.06679],"type":"Point"}
}