{
  "type": "Feature",
  "properties": {
    "iso:country":"US",
    "sg:address":"313 Myles Ln",
    "sg:city":"Kingsley",
    "sg:classifiers":[
        {
            "category":"Freight",
            "type":"Transportation"
        }
    ],
    "sg:phone":"+1 712 378 3674",
    "sg:postcode":"51028",
    "sg:province":"IA",
    "sg:tags":[
        "commercial",
        "storage"
    ],
    "wof:name":"Kingsley Public Storage",
    "wof:placetype":"venue"
},
  "geometry": {"coordinates":[-95.961437,42.589219],"type":"Point"}
}