{
  "type": "Feature",
  "properties": {
    "iso:country":"US",
    "sg:address":"427 2nd Ave SW",
    "sg:city":"Cresco",
    "sg:classifiers":[
        {
            "category":"Manufacturing",
            "subcategory":"Tools & Machinery",
            "type":"Manufacturing & Wholesale Goods"
        }
    ],
    "sg:phone":"+1 563 547 5873",
    "sg:postcode":"52136",
    "sg:province":"IA",
    "sg:tags":[
        "equipment",
        "household",
        "cooking"
    ],
    "sg:website":"www.bethanyhousewares.com",
    "wof:name":"Bethany Housewares Inc",
    "wof:placetype":"venue"
},
  "geometry": {"coordinates":[-92.12224399999999,43.371055],"type":"Point"}
}