{
  "type": "Feature",
  "properties": {
    "addr:full":"1310 6th Ave Des Moines IA 50314",
    "addr:housenumber":"1310",
    "addr:postcode":"50314",
    "addr:street":"6Th Ave",
    "iso:country":"US",
    "sg:address":"1310 6th Ave",
    "sg:city":"Des Moines",
    "sg:classifiers":[
        {
            "category":"Shopping",
            "subcategory":"Clothing, Apparel, & Fashions",
            "type":"Retail Goods"
        }
    ],
    "sg:phone":"+1 515 245 9782",
    "sg:postcode":"50314",
    "sg:province":"IA",
    "wof:name":"Hope Ministries",
    "wof:placetype":"venue"
},
  "geometry": {"coordinates":[-93.625851,41.603776],"type":"Point"}
}