{
  "type": "Feature",
  "properties": {
    "addr:full":"2136 13th St Coralville IA 52241",
    "addr:housenumber":"2136",
    "addr:postcode":"52241",
    "addr:street":"13Th St",
    "iso:country":"US",
    "sg:address":"2136 13th St",
    "sg:city":"Coralville",
    "sg:classifiers":[
        {
            "category":"Retail",
            "subcategory":"Repair Shop",
            "type":"Services"
        }
    ],
    "sg:phone":"+1 319 338 8735",
    "sg:postcode":"52241",
    "sg:province":"IA",
    "sg:tags":[
        "lock",
        "locksmith"
    ],
    "wof:name":"Russell's Locksmith",
    "wof:placetype":"venue"
},
  "geometry": {"coordinates":[-91.589786,41.689527],"type":"Point"}
}