{
  "type": "Feature",
  "properties": {
    "iso:country":"US",
    "sg:address":"28534 160th St",
    "sg:city":"Iowa Falls",
    "sg:classifiers":[
        {
            "category":"Shopping",
            "subcategory":"Computers & Home Electronics",
            "type":"Retail Goods"
        }
    ],
    "sg:phone":"+1 641 648 5410",
    "sg:postcode":"50126",
    "sg:province":"IA",
    "wof:name":"Green Belt Satellites",
    "wof:placetype":"venue"
},
  "geometry": {"coordinates":[-93.14926699999999,42.470999],"type":"Point"}
}