{
  "type": "Feature",
  "properties": {
    "iso:country":"US",
    "sg:address":"322 N Harrison St",
    "sg:city":"Fremont",
    "sg:classifiers":[
        {
            "category":"Retail",
            "subcategory":"Laundry & Dry Cleaning",
            "type":"Services"
        }
    ],
    "sg:phone":"+1 641 933 4774",
    "sg:postcode":"52561",
    "sg:province":"IA",
    "sg:tags":[
        "cleaners",
        "rug",
        "carpet"
    ],
    "wof:name":"Alpha Omega Carpet Cleaning",
    "wof:placetype":"venue"
},
  "geometry": {"coordinates":[-92.42957800000001,41.219408],"type":"Point"}
}