{
  "type": "Feature",
  "properties": {
    "addr:full":"2172 M Ave Williamsburg IA 52361",
    "addr:housenumber":"2172",
    "addr:postcode":"52361",
    "addr:street":"M Ave",
    "iso:country":"US",
    "sg:address":"2172 M Ave",
    "sg:city":"Williamsburg",
    "sg:classifiers":[
        {
            "category":"Manufacturing",
            "subcategory":"Tools & Machinery",
            "type":"Manufacturing & Wholesale Goods"
        }
    ],
    "sg:phone":"+1 319 668 1300",
    "sg:postcode":"52361",
    "sg:province":"IA",
    "sg:tags":[
        "farm",
        "equipment"
    ],
    "sg:website":"www.kinzemfg.com",
    "wof:name":"Kinze Manufacturing Inc",
    "wof:placetype":"venue"
},
  "geometry": {"coordinates":[-92.066031,41.693309],"type":"Point"}
}