{
  "type": "Feature",
  "properties": {
    "addr:full":"3600 Lafayette Rd Evansdale IA 50707",
    "addr:housenumber":"3600",
    "addr:postcode":"50707",
    "addr:street":"Rd",
    "iso:country":"US",
    "sg:address":"3600 Lafayette Rd",
    "sg:city":"Evansdale",
    "sg:classifiers":[
        {
            "category":"Banks & Credit Unions",
            "subcategory":"Financial Services",
            "type":"Services"
        }
    ],
    "sg:phone":"+1 319 236 2265",
    "sg:postcode":"50707",
    "sg:province":"IA",
    "sg:tags":[
        "company",
        "holding"
    ],
    "sg:website":"www.fssbonline.com",
    "wof:name":"Evans Bancshares Inc",
    "wof:placetype":"venue"
},
  "geometry": {"coordinates":[-92.286422,42.476763],"type":"Point"}
}