{
  "type": "Feature",
  "properties": {
    "addr:full":"210 11th St Wellman IA 52356",
    "addr:housenumber":"210",
    "addr:postcode":"52356",
    "addr:street":"11Th St",
    "iso:country":"US",
    "sg:address":"210 11th St",
    "sg:city":"Wellman",
    "sg:classifiers":[
        {
            "category":"Organizations",
            "subcategory":"Religious Organization",
            "type":"Services"
        }
    ],
    "sg:phone":"+1 319 646 2244",
    "sg:postcode":"52356",
    "sg:province":"IA",
    "sg:tags":[
        "church"
    ],
    "wof:name":"St Joseph's Church",
    "wof:placetype":"venue"
},
  "geometry": {"coordinates":[-91.830091,41.472177],"type":"Point"}
}