{
  "type": "Feature",
  "properties": {
    "addr:full":"1120 W 5th St Wilton IA 52778",
    "addr:housenumber":"1120",
    "addr:postcode":"52778",
    "addr:street":"W 5Th St",
    "iso:country":"US",
    "sg:address":"1120 W 5th St",
    "sg:city":"Wilton",
    "sg:classifiers":[
        {
            "category":"Building & Trades",
            "subcategory":"Construction",
            "type":"Services"
        }
    ],
    "sg:phone":"+1 563 732 5242",
    "sg:postcode":"52778",
    "sg:province":"IA",
    "sg:tags":[
        "excavating",
        "contractor"
    ],
    "wof:name":"C Kleppe Excavating & Trucking",
    "wof:placetype":"venue"
},
  "geometry": {"coordinates":[-91.03456199999999,41.590275],"type":"Point"}
}