{
  "type": "Feature",
  "properties": {
    "addr:full":"203 Main St Archer IA 51231",
    "addr:housenumber":"203",
    "addr:postcode":"51231",
    "addr:street":"Main St",
    "iso:country":"US",
    "sg:address":"203 Main St",
    "sg:city":"Archer",
    "sg:classifiers":[
        {
            "category":"Government",
            "subcategory":"Post Office",
            "type":"Public Place"
        }
    ],
    "sg:phone":"+1 712 723 5213",
    "sg:postcode":"51231",
    "sg:province":"IA",
    "wof:name":"US Post Office",
    "wof:placetype":"venue"
},
  "geometry": {"coordinates":[-95.74583800000001,43.114952],"type":"Point"}
}