{
  "type": "Feature",
  "properties": {
    "iso:country":"US",
    "sg:address":"57744 Lewis Rd",
    "sg:city":"Lewis",
    "sg:classifiers":[
        {
            "category":"Government",
            "subcategory":"Office",
            "type":"Public Place"
        }
    ],
    "sg:phone":"+1 712 769 2587",
    "sg:postcode":"51544",
    "sg:province":"IA",
    "sg:tags":[
        "state"
    ],
    "wof:name":"Natural Resources Dept",
    "wof:placetype":"venue"
},
  "geometry": {"coordinates":[-95.08408,41.293847],"type":"Point"}
}