{
  "type": "Feature",
  "properties": {
    "addr:full":"104 N 3rd St Montezuma IA 50171",
    "addr:housenumber":"104",
    "addr:postcode":"50171",
    "addr:street":"N 3Rd St",
    "iso:country":"US",
    "sg:address":"104 N 3rd St",
    "sg:city":"Montezuma",
    "sg:classifiers":[
        {
            "category":"Shopping",
            "subcategory":"Florist",
            "type":"Retail Goods"
        }
    ],
    "sg:phone":"+1 641 623 5412",
    "sg:postcode":"50171",
    "sg:province":"IA",
    "wof:name":"Bryan Candle & Flower Corner",
    "wof:placetype":"venue"
},
  "geometry": {"coordinates":[-92.524888,41.586287],"type":"Point"}
}