{
  "type": "Feature",
  "properties": {
    "addr:full":"306 E 1st St Monticello IA 52310",
    "addr:housenumber":"306",
    "addr:postcode":"52310",
    "addr:street":"E 1St St",
    "iso:country":"US",
    "sg:address":"306 E 1st St",
    "sg:city":"Monticello",
    "sg:classifiers":[
        {
            "category":"Organizations",
            "subcategory":"Professional Association",
            "type":"Services"
        }
    ],
    "sg:phone":"+1 319 465 5626",
    "sg:postcode":"52310",
    "sg:province":"IA",
    "sg:tags":[
        "business"
    ],
    "wof:name":"Monticello Chamber Of Commerce",
    "wof:placetype":"venue"
},
  "geometry": {"coordinates":[-91.185816,42.238048],"type":"Point"}
}