{
  "type": "Feature",
  "properties": {
    "iso:country":"US",
    "sg:address":"7404 Hampshire Dr NE",
    "sg:city":"Cedar Rapids",
    "sg:classifiers":[
        {
            "category":"Wholesale",
            "subcategory":"Machinery & Supplies",
            "type":"Manufacturing & Wholesale Goods"
        }
    ],
    "sg:phone":"+1 319 377 1226",
    "sg:postcode":"52402",
    "sg:province":"IA",
    "sg:tags":[
        "equipment",
        "industrial"
    ],
    "wof:name":"Harry Ferris Co",
    "wof:placetype":"venue"
},
  "geometry": {"coordinates":[-91.634603,42.052826],"type":"Point"}
}