{
  "type": "Feature",
  "properties": {
    "iso:country":"US",
    "sg:address":"2952 270 St",
    "sg:city":"Villisca",
    "sg:phone":"+1 712 826 5432",
    "sg:postcode":"50864",
    "sg:province":"IA",
    "sg:tags":[
        "farm",
        "corn",
        "beef",
        "feedlot",
        "cattle"
    ],
    "wof:name":"Raymond Eitzen",
    "wof:placetype":"venue"
},
  "geometry": {"coordinates":[-95.073909,40.91535],"type":"Point"}
}