{
  "type": "Feature",
  "properties": {
    "iso:country":"US",
    "sg:address":"419 2nd Ave SE",
    "sg:city":"Cedar Rapids",
    "sg:classifiers":[
        {
            "category":"Shopping",
            "subcategory":"Bicycles & Sporting Goods",
            "type":"Retail Goods"
        }
    ],
    "sg:phone":"+1 319 362 1052",
    "sg:postcode":"52401",
    "sg:province":"IA",
    "sg:tags":[
        "bike"
    ],
    "sg:website":"www.hallbicycle.com",
    "wof:name":"Hall Bicycle Company",
    "wof:placetype":"venue"
},
  "geometry": {"coordinates":[-91.66529800000001,41.979401],"type":"Point"}
}