{
  "type": "Feature",
  "properties": {
    "iso:country":"US",
    "sg:address":"2501 Maury St",
    "sg:city":"Des Moines",
    "sg:classifiers":[
        {
            "category":"Government",
            "subcategory":"Office",
            "type":"Public Place"
        }
    ],
    "sg:phone":"+1 515 248 6214",
    "sg:postcode":"50317",
    "sg:province":"IA",
    "sg:tags":[
        "village"
    ],
    "wof:name":"Southeast Neighborhood Site",
    "wof:placetype":"venue"
},
  "geometry": {"coordinates":[-93.56905999999999,41.580428],"type":"Point"}
}