{
  "type": "Feature",
  "properties": {
    "addr:full":"410 State Hwy 78 Wayland IA 52654",
    "addr:housenumber":"410",
    "addr:postcode":"52654",
    "addr:street":"State Hwy 78",
    "iso:country":"US",
    "sg:address":"410 State Hwy 78",
    "sg:city":"Wayland",
    "sg:classifiers":[
        {
            "category":"Retail",
            "subcategory":"Auto Repair",
            "type":"Services"
        }
    ],
    "sg:phone":"+1 319 256 7000",
    "sg:postcode":"52654",
    "sg:province":"IA",
    "sg:tags":[
        "wrecker"
    ],
    "wof:name":"Richard Oil Co",
    "wof:placetype":"venue"
},
  "geometry": {"coordinates":[-91.652705,41.149746],"type":"Point"}
}