{
  "type": "Feature",
  "properties": {
    "iso:country":"US",
    "sg:address":"606 Court St",
    "sg:city":"Bellevue",
    "sg:classifiers":[
        {
            "category":"Building & Trades",
            "subcategory":"Construction",
            "type":"Services"
        }
    ],
    "sg:phone":"+1 563 872 4908",
    "sg:postcode":"52031",
    "sg:province":"IA",
    "sg:tags":[
        "pumping",
        "contractor"
    ],
    "wof:name":"Putman Tankerman Svc",
    "wof:placetype":"venue"
},
  "geometry": {"coordinates":[-90.429146,42.256279],"type":"Point"}
}