{
  "type": "Feature",
  "properties": {
    "addr:full":"736 Old Lincoln Hwy Crescent IA 51526",
    "addr:housenumber":"736",
    "addr:postcode":"51526",
    "addr:street":"Old Lincoln Hwy Crescent",
    "iso:country":"US",
    "sg:address":"736 Old Lincoln Hwy",
    "sg:city":"Crescent",
    "sg:classifiers":[
        {
            "category":"Manufacturing",
            "subcategory":"Signs",
            "type":"Manufacturing & Wholesale Goods"
        }
    ],
    "sg:phone":"+1 712 545 3375",
    "sg:postcode":"51526",
    "sg:province":"IA",
    "wof:name":"Allen Sign Co",
    "wof:placetype":"venue"
},
  "geometry": {"coordinates":[-95.858395,41.363719],"type":"Point"}
}