{
  "type": "Feature",
  "properties": {
    "iso:country":"US",
    "sg:address":"104 W Main St",
    "sg:city":"Agency",
    "sg:classifiers":[
        {
            "category":"Education",
            "subcategory":"Library",
            "type":"Public Place"
        }
    ],
    "sg:phone":"+1 641 937 6002",
    "sg:postcode":"52530",
    "sg:province":"IA",
    "wof:name":"Agency Public Library",
    "wof:placetype":"venue"
},
  "geometry": {"coordinates":[-92.308352,40.994842],"type":"Point"}
}