{
  "type": "Feature",
  "properties": {
    "addr:full":"414 E 3rd St Muscatine IA 52761",
    "addr:housenumber":"414",
    "addr:postcode":"52761",
    "addr:street":"E 3Rd St",
    "iso:country":"US",
    "sg:address":"414 E 3rd St",
    "sg:city":"Muscatine",
    "sg:classifiers":[
        {
            "category":"Wholesale",
            "subcategory":"Furniture",
            "type":"Manufacturing & Wholesale Goods"
        }
    ],
    "sg:phone":"+1 563 264 7400",
    "sg:postcode":"52761",
    "sg:province":"IA",
    "sg:website":"www.honi.com",
    "wof:name":"HNI Corp",
    "wof:placetype":"venue"
},
  "geometry": {"coordinates":[-91.042304,41.42433],"type":"Point"}
}