{
  "type": "Feature",
  "properties": {
    "addr:full":"2230 Independence Ave Waterloo IA 50707",
    "addr:housenumber":"2230",
    "addr:postcode":"50707",
    "addr:street":"Independence Ave",
    "iso:country":"US",
    "sg:address":"2230 Independence Ave",
    "sg:city":"Waterloo",
    "sg:classifiers":[
        {
            "category":"Retail",
            "subcategory":"Auto Repair",
            "type":"Services"
        }
    ],
    "sg:phone":"+1 319 236 7788",
    "sg:postcode":"50707",
    "sg:province":"IA",
    "sg:tags":[
        "general"
    ],
    "wof:name":"Basic Auto & Repair",
    "wof:placetype":"venue"
},
  "geometry": {"coordinates":[-92.28957699999999,42.498321],"type":"Point"}
}