{
  "type": "Feature",
  "properties": {
    "addr:full":"535 W Broadway Council Bluffs IA 51501",
    "addr:housenumber":"535",
    "addr:postcode":"51501",
    "addr:street":"W Broadway",
    "iso:country":"US",
    "sg:address":"535 W Broadway",
    "sg:city":"Council Bluffs",
    "sg:classifiers":[
        {
            "category":"Real Estate",
            "subcategory":"Real Estate Agent",
            "type":"Services"
        }
    ],
    "sg:phone":"+1 712 325 0445",
    "sg:postcode":"51501",
    "sg:province":"IA",
    "sg:website":"www.heartlandproperties.com",
    "wof:name":"Heartland Properties Inc",
    "wof:placetype":"venue"
},
  "geometry": {"coordinates":[-95.85064800000001,41.260937],"type":"Point"}
}