{
  "type": "Feature",
  "properties": {
    "iso:country":"US",
    "sg:address":"421 Birch Ave",
    "sg:city":"Eldora",
    "sg:classifiers":[
        {
            "category":"Retail",
            "subcategory":"Repair Shop",
            "type":"Services"
        }
    ],
    "sg:phone":"+1 641 858 3025",
    "sg:postcode":"50627",
    "sg:province":"IA",
    "wof:name":"Bills Shop",
    "wof:placetype":"venue"
},
  "geometry": {"coordinates":[-93.08909800000001,42.366197],"type":"Point"}
}