{
  "type": "Feature",
  "properties": {
    "addr:full":"72 N Yorktown Pike Mason City IA 50401",
    "addr:housenumber":"72",
    "addr:postcode":"50401",
    "addr:street":"N Yorktown Pike",
    "iso:country":"US",
    "sg:address":"72 N Yorktown Pike",
    "sg:city":"Mason City",
    "sg:classifiers":[
        {
            "category":"Food & Beverages",
            "subcategory":"Liquor & Beverages",
            "type":"Retail Goods"
        }
    ],
    "sg:phone":"+1 641 423 2857",
    "sg:postcode":"50401",
    "sg:province":"IA",
    "sg:tags":[
        "alcoholic"
    ],
    "wof:name":"Christmas Spirits",
    "wof:placetype":"venue"
},
  "geometry": {"coordinates":[-93.14371800000001,43.15182],"type":"Point"}
}