{
  "type": "Feature",
  "properties": {
    "iso:country":"US",
    "sg:address":"3 Beck Ct",
    "sg:city":"Grinnell",
    "sg:classifiers":[
        {
            "category":"Manufacturing",
            "subcategory":"Toys & Sporting Goods",
            "type":"Manufacturing & Wholesale Goods"
        }
    ],
    "sg:phone":"+1 641 236 5205",
    "sg:postcode":"50112",
    "sg:province":"IA",
    "sg:tags":[
        "mfg"
    ],
    "wof:name":"Yos Creations",
    "wof:placetype":"venue"
},
  "geometry": {"coordinates":[-92.709337,41.74232],"type":"Point"}
}