{
  "type": "Feature",
  "properties": {
    "iso:country":"US",
    "sg:address":"599 N Kennedy Ave",
    "sg:city":"Madrid",
    "sg:classifiers":[
        {
            "category":"Education",
            "subcategory":"School",
            "type":"Public Place"
        }
    ],
    "sg:phone":"+1 515 795 3240",
    "sg:postcode":"50156",
    "sg:province":"IA",
    "wof:name":"Madrid Junior & High School",
    "wof:placetype":"venue"
},
  "geometry": {"coordinates":[-93.81568799999999,41.881021],"type":"Point"}
}