{
  "type": "Feature",
  "properties": {
    "iso:country":"US",
    "sg:address":"305 Alice St",
    "sg:city":"Woolstock",
    "sg:classifiers":[
        {
            "category":"Retail",
            "subcategory":"Repair Shop",
            "type":"Services"
        }
    ],
    "sg:phone":"+1 515 839 5744",
    "sg:postcode":"50599",
    "sg:province":"IA",
    "sg:tags":[
        "related"
    ],
    "wof:name":"J R's Repair",
    "wof:placetype":"venue"
},
  "geometry": {"coordinates":[-93.845536,42.566659],"type":"Point"}
}