{
  "type": "Feature",
  "properties": {
    "iso:country":"US",
    "sg:address":"1495 390th St",
    "sg:city":"Stratford",
    "sg:classifiers":[
        {
            "category":"Farming",
            "subcategory":"Farm",
            "type":"Manufacturing & Wholesale Goods"
        }
    ],
    "sg:phone":"+1 515 838 2613",
    "sg:postcode":"50249",
    "sg:province":"IA",
    "sg:tags":[
        "crop",
        "general"
    ],
    "wof:name":"Steven Carlson",
    "wof:placetype":"venue"
},
  "geometry": {"coordinates":[-93.874916,42.224362],"type":"Point"}
}