{
  "type": "Feature",
  "properties": {
    "addr:full":"2711 W 63rd St Davenport IA 52806",
    "addr:housenumber":"2711",
    "addr:postcode":"52806",
    "addr:street":"W 63Rd St",
    "iso:country":"US",
    "sg:address":"2711 W 63rd St",
    "sg:city":"Davenport",
    "sg:classifiers":[
        {
            "category":"Health Services",
            "subcategory":"Chiropractor",
            "type":"Services"
        }
    ],
    "sg:phone":"+1 563 386 7037",
    "sg:postcode":"52806",
    "sg:province":"IA",
    "wof:name":"Hess Dr Jerry",
    "wof:placetype":"venue"
},
  "geometry": {"coordinates":[-90.613523,41.585857],"type":"Point"}
}