{
  "type": "Feature",
  "properties": {
    "iso:country":"US",
    "sg:address":"502 Main St",
    "sg:city":"Lowden",
    "sg:classifiers":[
        {
            "category":"Home & Garden",
            "subcategory":"Household Appliances",
            "type":"Retail Goods"
        }
    ],
    "sg:phone":"+1 563 941 5800",
    "sg:postcode":"52255",
    "sg:province":"IA",
    "wof:name":"Olsen's Appliance & Sentry",
    "wof:placetype":"venue"
},
  "geometry": {"coordinates":[-90.927436,41.857706],"type":"Point"}
}