{
  "type": "Feature",
  "properties": {
    "iso:country":"US",
    "sg:address":"111 N Elm St",
    "sg:city":"Cresco",
    "sg:classifiers":[
        {
            "category":"Banks & Credit Unions",
            "subcategory":"Investment Brokerage",
            "type":"Services"
        }
    ],
    "sg:phone":"+1 563 547 5340",
    "sg:postcode":"52136",
    "sg:province":"IA",
    "sg:tags":[
        "consultant",
        "planning",
        "financial"
    ],
    "wof:name":"American Express Financial Adv",
    "wof:placetype":"venue"
},
  "geometry": {"coordinates":[-92.11636300000001,43.373211],"type":"Point"}
}