{
  "type": "Feature",
  "properties": {
    "iso:country":"US",
    "sg:address":"309 2nd St NW",
    "sg:city":"Bondurant",
    "sg:classifiers":[
        {
            "category":"Personal",
            "subcategory":"Beauty Salon",
            "type":"Services"
        }
    ],
    "sg:phone":"+1 515 967 3144",
    "sg:postcode":"50035",
    "sg:province":"IA",
    "sg:tags":[
        "shop"
    ],
    "wof:name":"Styling Headquarters Beauty",
    "wof:placetype":"venue"
},
  "geometry": {"coordinates":[-93.467157,41.702867],"type":"Point"}
}