{
  "type": "Feature",
  "properties": {
    "iso:country":"US",
    "sg:address":"2235 9th St",
    "sg:city":"Aurelia",
    "sg:classifiers":[
        {
            "category":"Shopping",
            "subcategory":"Used Merchandise",
            "type":"Retail Goods"
        }
    ],
    "sg:phone":"+1 712 434 2244",
    "sg:postcode":"51005",
    "sg:province":"IA",
    "sg:tags":[
        "antique"
    ],
    "wof:name":"Cedars Antiques",
    "wof:placetype":"venue"
},
  "geometry": {"coordinates":[-95.444058,42.720423],"type":"Point"}
}