{
  "type": "Feature",
  "properties": {
    "addr:full":"1802 5th Ave NW Waverly IA 50677",
    "addr:housenumber":"1802",
    "addr:postcode":"50677",
    "addr:street":"5Th Ave Nw",
    "iso:country":"US",
    "sg:address":"1802 5th Ave NW",
    "sg:city":"Waverly",
    "sg:classifiers":[
        {
            "category":"Social Services",
            "subcategory":"Adult Care",
            "type":"Services"
        }
    ],
    "sg:phone":"+1 319 352 8851",
    "sg:postcode":"50677",
    "sg:province":"IA",
    "sg:tags":[
        "home",
        "residential"
    ],
    "wof:name":"Bartels Assisted Living Apts",
    "wof:placetype":"venue"
},
  "geometry": {"coordinates":[-92.49321999999999,42.730165],"type":"Point"}
}