{
  "type": "Feature",
  "properties": {
    "iso:country":"US",
    "sg:address":"6631 SE Bloomfield Rd",
    "sg:city":"Des Moines",
    "sg:classifiers":[
        {
            "category":"Home & Garden",
            "subcategory":"Furniture",
            "type":"Retail Goods"
        }
    ],
    "sg:phone":"+1 515 285 5151",
    "sg:postcode":"50320",
    "sg:province":"IA",
    "wof:name":"Southtown Furniture Warehouse",
    "wof:placetype":"venue"
},
  "geometry": {"coordinates":[-93.59669,41.524644],"type":"Point"}
}