{
  "type": "Feature",
  "properties": {
    "iso:country":"US",
    "sg:address":"8710 SE 6th Ave",
    "sg:city":"Runnells",
    "sg:phone":"+1 515 967 7555",
    "sg:postcode":"50237",
    "sg:province":"IA",
    "sg:tags":[
        "farm",
        "field",
        "corn",
        "soybean",
        "crop"
    ],
    "wof:name":"Tim Fritz",
    "wof:placetype":"venue"
},
  "geometry": {"coordinates":[-93.42446,41.579881],"type":"Point"}
}