{
  "type": "Feature",
  "properties": {
    "iso:country":"US",
    "sg:address":"2136 Zeller Ave",
    "sg:city":"Marshalltown",
    "sg:classifiers":[
        {
            "category":"Real Estate",
            "subcategory":"Real Estate Operator",
            "type":"Services"
        }
    ],
    "sg:phone":"+1 641 752 6130",
    "sg:postcode":"50158",
    "sg:province":"IA",
    "sg:tags":[
        "building",
        "apartment"
    ],
    "wof:name":"NM Le Grand Village Apts",
    "wof:placetype":"venue"
},
  "geometry": {"coordinates":[-92.785556,42.036433],"type":"Point"}
}