{
  "type": "Feature",
  "properties": {
    "iso:country":"US",
    "sg:address":"2796 130th St",
    "sg:city":"Belmond",
    "sg:classifiers":[
        {
            "category":"Organizations",
            "subcategory":"Religious Organization",
            "type":"Services"
        }
    ],
    "sg:phone":"+1 641 444 3204",
    "sg:postcode":"50421",
    "sg:province":"IA",
    "sg:tags":[
        "church"
    ],
    "wof:name":"Evangelical Free Church",
    "wof:placetype":"venue"
},
  "geometry": {"coordinates":[-93.61717899999999,42.860288],"type":"Point"}
}