{
  "type": "Feature",
  "properties": {
    "addr:full":"3411 150th St Brooklyn IA 52211",
    "addr:housenumber":"3411",
    "addr:postcode":"52211",
    "addr:street":"150Th St",
    "iso:country":"US",
    "sg:address":"3411 150th St",
    "sg:city":"Brooklyn",
    "sg:classifiers":[
        {
            "category":"Farming",
            "subcategory":"Livestock Farm",
            "type":"Manufacturing & Wholesale Goods"
        }
    ],
    "sg:phone":"+1 641 522 5556",
    "sg:postcode":"52211",
    "sg:province":"IA",
    "sg:tags":[
        "beef",
        "feedlot",
        "cattle"
    ],
    "wof:name":"Marvin Keller",
    "wof:placetype":"venue"
},
  "geometry": {"coordinates":[-92.49403100000001,41.803132],"type":"Point"}
}