{
  "type": "Feature",
  "properties": {
    "addr:full":"221 1st St E Independence IA 50644",
    "addr:housenumber":"221",
    "addr:postcode":"50644",
    "addr:street":"1St St E",
    "iso:country":"US",
    "sg:address":"221 1st St E",
    "sg:city":"Independence",
    "sg:classifiers":[
        {
            "category":"Shopping",
            "subcategory":"Gifts & Souvenirs",
            "type":"Retail Goods"
        }
    ],
    "sg:phone":"+1 319 334 9355",
    "sg:postcode":"50644",
    "sg:province":"IA",
    "sg:tags":[
        "collectible"
    ],
    "wof:name":"S & K Collectibles",
    "wof:placetype":"venue"
},
  "geometry": {"coordinates":[-91.893027,42.468646],"type":"Point"}
}