{
  "type": "Feature",
  "properties": {
    "addr:full":"1321 Jewell Ave Kingsley IA 51028",
    "addr:housenumber":"1321",
    "addr:postcode":"51028",
    "addr:street":"Jewell Ave",
    "iso:country":"US",
    "sg:address":"1321 Jewell Ave",
    "sg:city":"Kingsley",
    "sg:phone":"+1 712 378 2384",
    "sg:postcode":"51028",
    "sg:province":"IA",
    "sg:tags":[
        "farm",
        "corn",
        "soybean"
    ],
    "wof:name":"Leo Keck",
    "wof:placetype":"venue"
},
  "geometry": {"coordinates":[-95.978207,42.516066],"type":"Point"}
}