{
  "type": "Feature",
  "properties": {
    "addr:full":"2174 Coolidge St Pella IA 50219",
    "addr:housenumber":"2174",
    "addr:postcode":"50219",
    "addr:street":"Coolidge St",
    "iso:country":"US",
    "sg:address":"2174 Coolidge St",
    "sg:city":"Pella",
    "sg:classifiers":[
        {
            "category":"Building & Trades",
            "subcategory":"Construction",
            "type":"Services"
        }
    ],
    "sg:phone":"+1 641 628 8223",
    "sg:postcode":"50219",
    "sg:province":"IA",
    "sg:tags":[
        "concrete",
        "contractor"
    ],
    "wof:name":"G & B CONCRETE Inc",
    "wof:placetype":"venue"
},
  "geometry": {"coordinates":[-92.933753,41.465339],"type":"Point"}
}