{
  "type": "Feature",
  "properties": {
    "iso:country":"US",
    "sg:address":"207 S B St",
    "sg:city":"Fairfield",
    "sg:classifiers":[
        {
            "category":"Building & Trades",
            "subcategory":"Construction",
            "type":"Services"
        }
    ],
    "sg:phone":"+1 641 472 4534",
    "sg:postcode":"52556",
    "sg:province":"IA",
    "sg:tags":[
        "carpentry",
        "contractor"
    ],
    "wof:name":"Charles E Crawford II",
    "wof:placetype":"venue"
},
  "geometry": {"coordinates":[-91.96110400000001,41.005586],"type":"Point"}
}