{
  "type": "Feature",
  "properties": {
    "iso:country":"US",
    "sg:address":"349 W Main St",
    "sg:city":"Marengo",
    "sg:classifiers":[
        {
            "category":"Farming",
            "subcategory":"Farm",
            "type":"Manufacturing & Wholesale Goods"
        }
    ],
    "sg:phone":"+1 319 642 3065",
    "sg:postcode":"52301",
    "sg:province":"IA",
    "sg:tags":[
        "crop",
        "general"
    ],
    "wof:name":"Bill McKusker",
    "wof:placetype":"venue"
},
  "geometry": {"coordinates":[-92.07327600000001,41.800684],"type":"Point"}
}