{
  "type": "Feature",
  "properties": {
    "addr:full":"1318 W 6th St Cedar Falls IA 50613",
    "addr:housenumber":"1318",
    "addr:postcode":"50613",
    "addr:street":"W 6Th St",
    "iso:country":"US",
    "sg:address":"1318 W 6th St",
    "sg:city":"Cedar Falls",
    "sg:classifiers":[
        {
            "category":"Retail",
            "subcategory":"Portrait Studio",
            "type":"Services"
        }
    ],
    "sg:phone":"+1 319 277 5002",
    "sg:postcode":"50613",
    "sg:province":"IA",
    "sg:tags":[
        "photographer",
        "photo"
    ],
    "wof:name":"Memory Makers Photographers",
    "wof:placetype":"venue"
},
  "geometry": {"coordinates":[-92.464541,42.533215],"type":"Point"}
}