{
  "type": "Feature",
  "properties": {
    "iso:country":"US",
    "sg:address":"1 N Main St",
    "sg:city":"Albia",
    "sg:classifiers":[
        {
            "category":"Banks & Credit Unions",
            "subcategory":"Investment Brokerage",
            "type":"Services"
        }
    ],
    "sg:phone":"+1 641 932 7130",
    "sg:postcode":"52531",
    "sg:province":"IA",
    "wof:name":"Midwest Investment Group",
    "wof:placetype":"venue"
},
  "geometry": {"coordinates":[-92.80712800000001,41.028097],"type":"Point"}
}