{
  "type": "Feature",
  "properties": {
    "addr:full":"106 E State St Jefferson IA 50129",
    "addr:housenumber":"106",
    "addr:postcode":"50129",
    "addr:street":"E State St",
    "iso:country":"US",
    "sg:address":"106 E State St",
    "sg:city":"Jefferson",
    "sg:classifiers":[
        {
            "category":"Shopping",
            "subcategory":"Used Merchandise",
            "type":"Retail Goods"
        }
    ],
    "sg:phone":"+1 515 386 3107",
    "sg:postcode":"50129",
    "sg:province":"IA",
    "sg:tags":[
        "antique"
    ],
    "wof:name":"Antiques & More Consignment",
    "wof:placetype":"venue"
},
  "geometry": {"coordinates":[-94.37468200000001,42.016339],"type":"Point"}
}