{
  "type": "Feature",
  "properties": {
    "iso:country":"US",
    "sg:address":"1000 Lake Shore Dr",
    "sg:city":"Okoboji",
    "sg:classifiers":[
        {
            "category":"Autos & Motor Vehicles",
            "subcategory":"Recreational Vehicle Sales",
            "type":"Retail Goods"
        }
    ],
    "sg:phone":"+1 712 332 7323",
    "sg:postcode":"51355",
    "sg:province":"IA",
    "sg:website":"www.smithsrv.com",
    "wof:name":"Smith's Recreational Vehicles",
    "wof:placetype":"venue"
},
  "geometry": {"coordinates":[-95.128411,43.37806],"type":"Point"}
}