{
  "type": "Feature",
  "properties": {
    "iso:country":"US",
    "sg:address":"2717 Murray St",
    "sg:city":"Sioux City",
    "sg:classifiers":[
        {
            "category":"Manufacturing",
            "subcategory":"Tools & Machinery",
            "type":"Manufacturing & Wholesale Goods"
        }
    ],
    "sg:phone":"+1 712 277 3937",
    "sg:postcode":"51111",
    "sg:province":"IA",
    "sg:tags":[
        "optical"
    ],
    "wof:name":"Pech Optical Corp",
    "wof:placetype":"venue"
},
  "geometry": {"coordinates":[-96.373706,42.427028],"type":"Point"}
}