{
  "type": "Feature",
  "properties": {
    "iso:country":"US",
    "sg:address":"11643 Howard Ave",
    "sg:city":"Elma",
    "sg:phone":"+1 641 393 2512",
    "sg:postcode":"50628",
    "sg:province":"IA",
    "sg:tags":[
        "farm",
        "corn"
    ],
    "wof:name":"Roger Gesell",
    "wof:placetype":"venue"
},
  "geometry": {"coordinates":[-92.40633200000001,43.347384],"type":"Point"}
}