{
  "type": "Feature",
  "properties": {
    "addr:full":"5107 Ave O Fort Madison IA 52627",
    "addr:postcode":"52627",
    "addr:street":"5107 Ave O",
    "iso:country":"US",
    "sg:address":"5107 Ave O",
    "sg:city":"Fort Madison",
    "sg:classifiers":[
        {
            "category":"Travel",
            "subcategory":"Hotels & Motels",
            "type":"Entertainment"
        }
    ],
    "sg:phone":"+1 319 372 8500",
    "sg:postcode":"52627",
    "sg:province":"IA",
    "sg:website":"www.super8.com",
    "wof:name":"Super 8 Motel",
    "wof:placetype":"venue"
},
  "geometry": {"coordinates":[-91.380715,40.62421],"type":"Point"}
}