{
  "type": "Feature",
  "properties": {
    "iso:country":"US",
    "sg:address":"4651 1st Ave SE Ste 2",
    "sg:city":"Cedar Rapids",
    "sg:classifiers":[
        {
            "category":"Education",
            "subcategory":"Music School",
            "type":"Public Place"
        }
    ],
    "sg:phone":"+1 319 378 1720",
    "sg:postcode":"52402",
    "sg:province":"IA",
    "sg:tags":[
        "instrument",
        "teacher",
        "musical"
    ],
    "wof:name":"Guitar Center Inc",
    "wof:placetype":"venue"
},
  "geometry": {"coordinates":[-91.624067,42.023966],"type":"Point"}
}