{
  "type": "Feature",
  "properties": {
    "iso:country":"US",
    "sg:address":"815 1st St",
    "sg:city":"De Witt",
    "sg:classifiers":[
        {
            "category":"Social Services",
            "subcategory":"Child Care",
            "type":"Services"
        }
    ],
    "sg:phone":"+1 563 659 8222",
    "sg:postcode":"52742",
    "sg:province":"IA",
    "sg:tags":[
        "day"
    ],
    "wof:name":"Moores Kid Kare",
    "wof:placetype":"venue"
},
  "geometry": {"coordinates":[-90.54198,41.815874],"type":"Point"}
}