{
  "type": "Feature",
  "properties": {
    "iso:country":"US",
    "sg:address":"122 5th St",
    "sg:city":"West Des Moines",
    "sg:classifiers":[
        {
            "category":"Restaurant",
            "type":"Food & Drink"
        }
    ],
    "sg:phone":"+1 515 255 4100",
    "sg:postcode":"50265",
    "sg:province":"IA",
    "wof:name":"Junction 122",
    "wof:placetype":"venue"
},
  "geometry": {"coordinates":[-93.70896500000001,41.569675],"type":"Point"}
}