{
  "type": "Feature",
  "properties": {
    "iso:country":"US",
    "sg:address":"1948 Boxelder Ave",
    "sg:city":"Emerson",
    "sg:classifiers":[
        {
            "category":"Professional",
            "subcategory":"Business Services",
            "type":"Services"
        }
    ],
    "sg:phone":"+1 712 623 2811",
    "sg:postcode":"51533",
    "sg:province":"IA",
    "wof:name":"D&K Express",
    "wof:placetype":"venue"
},
  "geometry": {"coordinates":[-95.33721799999999,41.023827],"type":"Point"}
}