{
  "type": "Feature",
  "properties": {
    "addr:full":"1600 4th Ave SW Le Mars IA 51031",
    "addr:housenumber":"1600",
    "addr:postcode":"51031",
    "addr:street":"4Th Ave Sw",
    "iso:country":"US",
    "sg:address":"1600 4th Ave SW",
    "sg:city":"Le Mars",
    "sg:classifiers":[
        {
            "category":"Health Services",
            "subcategory":"Nursing And Care Facility",
            "type":"Services"
        }
    ],
    "sg:phone":"+1 712 548 4330",
    "sg:postcode":"51031",
    "sg:province":"IA",
    "wof:name":"Laura Donohue",
    "wof:placetype":"venue"
},
  "geometry": {"coordinates":[-96.170467,42.772776],"type":"Point"}
}