{
  "type": "Feature",
  "properties": {
    "iso:country":"US",
    "sg:address":"2345 11th St",
    "sg:city":"Nevada",
    "sg:classifiers":[
        {
            "category":"Building & Trades",
            "subcategory":"Plumbing",
            "type":"Services"
        }
    ],
    "sg:phone":"+1 515 382 6373",
    "sg:postcode":"50201",
    "sg:province":"IA",
    "sg:tags":[
        "plumbing",
        "contractor"
    ],
    "wof:name":"Vansickel's Plumbing",
    "wof:placetype":"venue"
},
  "geometry": {"coordinates":[-93.444582,42.034627],"type":"Point"}
}