{
  "type": "Feature",
  "properties": {
    "addr:full":"4555 Q Ave Larrabee IA 51029",
    "addr:housenumber":"4555",
    "addr:postcode":"51029",
    "addr:street":"Q Ave",
    "iso:country":"US",
    "sg:address":"4555 Q Ave",
    "sg:city":"Larrabee",
    "sg:classifiers":[
        {
            "category":"Freight",
            "type":"Transportation"
        }
    ],
    "sg:phone":"+1 712 437 2492",
    "sg:postcode":"51029",
    "sg:province":"IA",
    "sg:tags":[
        "operator",
        "local",
        "trucking"
    ],
    "wof:name":"Ricks Tank Wagon Service",
    "wof:placetype":"venue"
},
  "geometry": {"coordinates":[-95.544338,42.85431],"type":"Point"}
}