{
  "type": "Feature",
  "properties": {
    "iso:country":"US",
    "sg:address":"3434 N Fillmore St",
    "sg:city":"Davenport",
    "sg:classifiers":[
        {
            "category":"Building & Trades",
            "subcategory":"Landscaping Services",
            "type":"Services"
        }
    ],
    "sg:phone":"+1 563 370 0102",
    "sg:postcode":"52806",
    "sg:province":"IA",
    "sg:tags":[
        "tree"
    ],
    "wof:name":"Frank's Tree Svc",
    "wof:placetype":"venue"
},
  "geometry": {"coordinates":[-90.593799,41.555165],"type":"Point"}
}