{
  "type": "Feature",
  "properties": {
    "iso:country":"US",
    "sg:address":"131 N 13th St",
    "sg:city":"Centerville",
    "sg:classifiers":[
        {
            "category":"Shopping",
            "type":"Retail Goods"
        }
    ],
    "sg:phone":"+1 641 856 2014",
    "sg:postcode":"52544",
    "sg:province":"IA",
    "sg:tags":[
        "pet",
        "shop"
    ],
    "wof:name":"Pet Paradise",
    "wof:placetype":"venue"
},
  "geometry": {"coordinates":[-92.87325800000001,40.732523],"type":"Point"}
}