{
  "type": "Feature",
  "properties": {
    "iso:country":"US",
    "sg:address":"100 N Grand St",
    "sg:city":"Chariton",
    "sg:classifiers":[
        {
            "category":"Shopping",
            "subcategory":"Hobbies, Toys, & Games",
            "type":"Retail Goods"
        }
    ],
    "sg:phone":"+1 641 774 8021",
    "sg:postcode":"50049",
    "sg:province":"IA",
    "wof:name":"Ingrams Wooden Wonders",
    "wof:placetype":"venue"
},
  "geometry": {"coordinates":[-93.30689700000001,41.014455],"type":"Point"}
}