{
  "type": "Feature",
  "properties": {
    "iso:country":"US",
    "sg:address":"20006 Osage Ave",
    "sg:city":"Keosauqua",
    "sg:phone":"+1 319 293 3586",
    "sg:postcode":"52565",
    "sg:province":"IA",
    "sg:tags":[
        "farm",
        "corn"
    ],
    "wof:name":"Rex Mote",
    "wof:placetype":"venue"
},
  "geometry": {"coordinates":[-91.910404,40.754113],"type":"Point"}
}