{
  "type": "Feature",
  "properties": {
    "iso:country":"US",
    "sg:address":"3115 Hickory Grove Rd",
    "sg:city":"Davenport",
    "sg:classifiers":[
        {
            "category":"Retail",
            "subcategory":"Auto Repair",
            "type":"Services"
        }
    ],
    "sg:phone":"+1 563 579 7668",
    "sg:postcode":"52806",
    "sg:province":"IA",
    "sg:tags":[
        "body",
        "automobile",
        "painting",
        "repairing"
    ],
    "wof:name":"Creative Customs & Collision",
    "wof:placetype":"venue"
},
  "geometry": {"coordinates":[-90.61785500000001,41.550473],"type":"Point"}
}