{
  "type": "Feature",
  "properties": {
    "iso:country":"US",
    "sg:address":"131 E Main St",
    "sg:city":"Ottumwa",
    "sg:classifiers":[
        {
            "category":"Insurance",
            "subcategory":"Hazard Insurance",
            "type":"Services"
        }
    ],
    "sg:phone":"+1 641 683 1970",
    "sg:postcode":"52501",
    "sg:province":"IA",
    "sg:tags":[
        "bond"
    ],
    "wof:name":"A Hawkeye Bail Bonds",
    "wof:placetype":"venue"
},
  "geometry": {"coordinates":[-92.41250599999999,41.017751],"type":"Point"}
}