{
  "type": "Feature",
  "properties": {
    "addr:full":"2411 Sisley Grove Rd SW Cedar Rapids IA 52404",
    "addr:postcode":"2411;52404",
    "addr:street":"Sisley Grove Rd Sw",
    "iso:country":"US",
    "sg:address":"2411 Sisley Grove Rd SW",
    "sg:city":"Cedar Rapids",
    "sg:classifiers":[
        {
            "category":"Retail",
            "subcategory":"Animal Services",
            "type":"Services"
        }
    ],
    "sg:phone":"+1 319 446 7557",
    "sg:postcode":"52404",
    "sg:province":"IA",
    "sg:tags":[
        "pet",
        "boarding",
        "sitting"
    ],
    "wof:name":"Brook Sunny Kennels",
    "wof:placetype":"venue"
},
  "geometry": {"coordinates":[-91.81361800000001,41.954003],"type":"Point"}
}