{
  "type": "Feature",
  "properties": {
    "iso:country":"US",
    "sg:address":"590 Samuel St",
    "sg:city":"Dubuque",
    "sg:classifiers":[
        {
            "category":"Real Estate",
            "subcategory":"Developer",
            "type":"Services"
        }
    ],
    "sg:phone":"+1 563 582 0027",
    "sg:postcode":"52003",
    "sg:province":"IA",
    "wof:name":"Dubuque Southgate Development Inc",
    "wof:placetype":"venue"
},
  "geometry": {"coordinates":[-90.67026799999999,42.483391],"type":"Point"}
}