{
  "type": "Feature",
  "properties": {
    "addr:full":"1802 SE Delaware Ave Ankeny IA 50021",
    "addr:housenumber":"1802",
    "addr:postcode":"50021",
    "addr:street":"Se Delaware Ave",
    "iso:country":"US",
    "sg:address":"1802 SE Delaware Ave",
    "sg:city":"Ankeny",
    "sg:classifiers":[
        {
            "category":"Food & Beverages",
            "subcategory":"Specialty",
            "type":"Retail Goods"
        }
    ],
    "sg:phone":"+1 515 965 3398",
    "sg:postcode":"50021",
    "sg:province":"IA",
    "sg:tags":[
        "tea",
        "coffee"
    ],
    "wof:name":"Coffee Point",
    "wof:placetype":"venue"
},
  "geometry": {"coordinates":[-93.581266,41.712981],"type":"Point"}
}