{
  "type": "Feature",
  "properties": {
    "addr:full":"207 Iowa Ave Nora Springs IA 50458",
    "addr:housenumber":"207",
    "addr:postcode":"50458",
    "addr:street":"Iowa Ave Nora",
    "iso:country":"US",
    "sg:address":"207 Iowa Ave",
    "sg:city":"Nora Springs",
    "sg:classifiers":[
        {
            "category":"Professional",
            "subcategory":"Business Services",
            "type":"Services"
        }
    ],
    "sg:phone":"+1 641 749 2678",
    "sg:postcode":"50458",
    "sg:province":"IA",
    "sg:tags":[
        "embroidery"
    ],
    "wof:name":"See-N-Sew",
    "wof:placetype":"venue"
},
  "geometry": {"coordinates":[-93.004369,43.145438],"type":"Point"}
}