{
  "type": "Feature",
  "properties": {
    "iso:country":"US",
    "sg:address":"1035 Warren Ave",
    "sg:city":"Osceola",
    "sg:classifiers":[
        {
            "category":"Wholesale",
            "subcategory":"Dairy",
            "type":"Manufacturing & Wholesale Goods"
        },
        {
            "category":"Social Services",
            "type":"Services"
        }
    ],
    "sg:phone":"+1 641 342 6700",
    "sg:postcode":"50213",
    "sg:province":"IA",
    "sg:tags":[
        "information",
        "product",
        "meat",
        "center",
        "general",
        "diabetes"
    ],
    "wof:name":"Power Logistics Inc",
    "wof:placetype":"venue"
},
  "geometry": {"coordinates":[-93.788701,41.022827],"type":"Point"}
}