{
  "type": "Feature",
  "properties": {
    "addr:full":"503 N Broadway St Red Oak IA 51566",
    "addr:housenumber":"503",
    "addr:postcode":"51566",
    "addr:street":"N Broadway St",
    "iso:country":"US",
    "sg:address":"503 N Broadway St",
    "sg:city":"Red Oak",
    "sg:classifiers":[
        {
            "category":"Autos & Motor Vehicles",
            "subcategory":"Automobile Sales",
            "type":"Retail Goods"
        }
    ],
    "sg:phone":"+1 712 623 9140",
    "sg:postcode":"51566",
    "sg:province":"IA",
    "sg:tags":[
        "car",
        "dealer"
    ],
    "wof:name":"Broadway Motors",
    "wof:placetype":"venue"
},
  "geometry": {"coordinates":[-95.232803,41.009365],"type":"Point"}
}