{
  "type": "Feature",
  "properties": {
    "iso:country":"US",
    "sg:address":"313 Barre St",
    "sg:city":"Kingsley",
    "sg:classifiers":[
        {
            "category":"Retail",
            "subcategory":"Funeral Services",
            "type":"Services"
        }
    ],
    "sg:phone":"+1 712 378 3031",
    "sg:postcode":"51028",
    "sg:province":"IA",
    "sg:tags":[
        "director"
    ],
    "wof:name":"Rohde Earnest Funeral Home",
    "wof:placetype":"venue"
},
  "geometry": {"coordinates":[-95.968688,42.591223],"type":"Point"}
}