{
  "type": "Feature",
  "properties": {
    "iso:country":"US",
    "sg:address":"1503 252nd St",
    "sg:city":"Jefferson",
    "sg:classifiers":[
        {
            "category":"Building & Trades",
            "subcategory":"Construction",
            "type":"Services"
        }
    ],
    "sg:phone":"+1 515 386 4226",
    "sg:postcode":"50129",
    "sg:province":"IA",
    "sg:tags":[
        "excavating",
        "contractor"
    ],
    "wof:name":"Murphy Excavating",
    "wof:placetype":"venue"
},
  "geometry": {"coordinates":[-94.35183499999999,41.989988],"type":"Point"}
}