{
  "type": "Feature",
  "properties": {
    "addr:full":"915 13th St SW Spencer IA 51301",
    "addr:housenumber":"915",
    "addr:postcode":"51301",
    "addr:street":"13Th St Sw",
    "iso:country":"US",
    "sg:address":"915 13th St SW",
    "sg:city":"Spencer",
    "sg:classifiers":[
        {
            "category":"Shopping",
            "subcategory":"Department Store",
            "type":"Retail Goods"
        }
    ],
    "sg:phone":"+1 712 264 1111",
    "sg:postcode":"51301",
    "sg:province":"IA",
    "wof:name":"Sears Roebuck & Co",
    "wof:placetype":"venue"
},
  "geometry": {"coordinates":[-95.157426,43.12455],"type":"Point"}
}