{
  "type": "Feature",
  "properties": {
    "addr:full":"410 NW Ash Dr Ankeny IA 50021",
    "addr:housenumber":"410",
    "addr:postcode":"50021",
    "addr:street":"Nw Ash Dr",
    "iso:country":"US",
    "sg:address":"410 NW Ash Dr",
    "sg:city":"Ankeny",
    "sg:classifiers":[
        {
            "category":"Health Services",
            "subcategory":"Nursing And Care Facility",
            "type":"Services"
        }
    ],
    "sg:phone":"+1 515 964 1101",
    "sg:postcode":"50021",
    "sg:province":"IA",
    "sg:tags":[
        "home",
        "convalescent"
    ],
    "wof:name":"Sunnyview Care Ctr",
    "wof:placetype":"venue"
},
  "geometry": {"coordinates":[-93.609861,41.733842],"type":"Point"}
}