{
  "type": "Feature",
  "properties": {
    "addr:full":"1429 Deer Woods Dr NE Swisher IA 52338",
    "addr:housenumber":"1429",
    "addr:postcode":"52338",
    "addr:street":"Deer Woods Dr Ne",
    "iso:country":"US",
    "sg:address":"1429 Deer Woods Dr NE",
    "sg:city":"Swisher",
    "sg:classifiers":[
        {
            "category":"Building & Trades",
            "subcategory":"Construction",
            "type":"Services"
        }
    ],
    "sg:phone":"+1 319 848 7463",
    "sg:postcode":"52338",
    "sg:province":"IA",
    "sg:tags":[
        "home",
        "builder"
    ],
    "wof:name":"Hansen Construction",
    "wof:placetype":"venue"
},
  "geometry": {"coordinates":[-91.648703,41.832982],"type":"Point"}
}