{
  "type": "Feature",
  "properties": {
    "addr:full":"2955 Summer St Burlington IA 52601",
    "addr:housenumber":"2955",
    "addr:postcode":"52601",
    "addr:street":"Summer St",
    "iso:country":"US",
    "sg:address":"2955 Summer St",
    "sg:city":"Burlington",
    "sg:classifiers":[
        {
            "category":"Government",
            "subcategory":"Office",
            "type":"Public Place"
        }
    ],
    "sg:phone":"+1 319 753 8146",
    "sg:postcode":"52601",
    "sg:province":"IA",
    "sg:tags":[
        "village"
    ],
    "wof:name":"Burlington Property Mntnc",
    "wof:placetype":"venue"
},
  "geometry": {"coordinates":[-91.117699,40.779311],"type":"Point"}
}