{
  "type": "Feature",
  "properties": {
    "iso:country":"US",
    "sg:address":"2523 Franklin Ave NE",
    "sg:city":"Cedar Rapids",
    "sg:classifiers":[
        {
            "category":"Building & Trades",
            "subcategory":"Construction",
            "type":"Services"
        }
    ],
    "sg:phone":"+1 319 362 3865",
    "sg:postcode":"52402",
    "sg:province":"IA",
    "sg:tags":[
        "downspouts",
        "gutter"
    ],
    "wof:name":"Chuck Kamberling Contracting",
    "wof:placetype":"venue"
},
  "geometry": {"coordinates":[-91.641555,42.004415],"type":"Point"}
}