{
  "type": "Feature",
  "properties": {
    "iso:country":"US",
    "sg:address":"1408 9th Ave N",
    "sg:city":"Humboldt",
    "sg:classifiers":[
        {
            "category":"Education",
            "subcategory":"School",
            "type":"Public Place"
        }
    ],
    "sg:phone":"+1 515 332 1330",
    "sg:postcode":"50548",
    "sg:province":"IA",
    "wof:name":"Humboldt Community School Dist",
    "wof:placetype":"venue"
},
  "geometry": {"coordinates":[-94.228669,42.730963],"type":"Point"}
}