{
  "type": "Feature",
  "properties": {
    "addr:full":"216 Edgar St Marquette IA 52158",
    "addr:housenumber":"216",
    "addr:postcode":"52158",
    "addr:street":"Edgar St",
    "iso:country":"US",
    "sg:address":"216 Edgar St",
    "sg:city":"Marquette",
    "sg:classifiers":[
        {
            "category":"Travel",
            "subcategory":"Travel Agent",
            "type":"Entertainment"
        }
    ],
    "sg:phone":"+1 563 873 1200",
    "sg:postcode":"52158",
    "sg:province":"IA",
    "sg:tags":[
        "information",
        "tourist"
    ],
    "wof:name":"City Of Marquette Tourist Info",
    "wof:placetype":"venue"
},
  "geometry": {"coordinates":[-91.181037,43.044527],"type":"Point"}
}