{
  "type": "Feature",
  "properties": {
    "iso:country":"US",
    "sg:address":"407 1st St",
    "sg:city":"Little Sioux",
    "sg:classifiers":[
        {
            "category":"Government",
            "subcategory":"Office",
            "type":"Public Place"
        }
    ],
    "sg:phone":"+1 712 649 2211",
    "sg:postcode":"51545",
    "sg:province":"IA",
    "sg:tags":[
        "city"
    ],
    "wof:name":"Little Sioux City Clerk",
    "wof:placetype":"venue"
},
  "geometry": {"coordinates":[-96.025424,41.809559],"type":"Point"}
}