{
  "type": "Feature",
  "properties": {
    "iso:country":"US",
    "sg:address":"116 S Main St",
    "sg:city":"Alta",
    "sg:classifiers":[
        {
            "category":"Shopping",
            "subcategory":"Jewelry",
            "type":"Retail Goods"
        }
    ],
    "sg:phone":"+1 712 200 2255",
    "sg:postcode":"51002",
    "sg:province":"IA",
    "sg:tags":[
        "jeweler"
    ],
    "wof:name":"Peterson Jewelry",
    "wof:placetype":"venue"
},
  "geometry": {"coordinates":[-95.30419999999999,42.674426],"type":"Point"}
}