{
  "type": "Feature",
  "properties": {
    "addr:full":"4689 40th Ave Alta IA 51002",
    "addr:housenumber":"4689",
    "addr:postcode":"51002",
    "addr:street":"40Th Ave",
    "iso:country":"US",
    "sg:address":"4689 40th Ave",
    "sg:city":"Alta",
    "sg:classifiers":[
        {
            "category":"Real Estate",
            "subcategory":"Real Estate Operator",
            "type":"Services"
        }
    ],
    "sg:phone":"+1 712 296 3744",
    "sg:postcode":"51002",
    "sg:province":"IA",
    "sg:tags":[
        "property",
        "lessor"
    ],
    "wof:name":"Plagman Farms Inc",
    "wof:placetype":"venue"
},
  "geometry": {"coordinates":[-95.329055,42.838272],"type":"Point"}
}