{
  "type": "Feature",
  "properties": {
    "iso:country":"US",
    "sg:address":"2102 Kimball Ave",
    "sg:city":"Waterloo",
    "sg:classifiers":[
        {
            "category":"Health Services",
            "subcategory":"Doctor",
            "type":"Services"
        }
    ],
    "sg:phone":"+1 319 233 3506",
    "sg:postcode":"50702",
    "sg:province":"IA",
    "sg:tags":[
        "dentist"
    ],
    "wof:name":"Waterloo Dental Assoc",
    "wof:placetype":"venue"
},
  "geometry": {"coordinates":[-92.356976,42.469903],"type":"Point"}
}