{
  "type": "Feature",
  "properties": {
    "addr:full":"2390 Cumberland Square Dr Bettendorf IA 52722",
    "addr:housenumber":"2390",
    "addr:postcode":"52722",
    "addr:street":"Cumberland Square Dr",
    "iso:country":"US",
    "sg:address":"2390 Cumberland Square Dr",
    "sg:city":"Bettendorf",
    "sg:classifiers":[
        {
            "category":"Wholesale",
            "subcategory":"Stationery",
            "type":"Manufacturing & Wholesale Goods"
        },
        {
            "category":"Shopping",
            "type":"Retail Goods"
        }
    ],
    "sg:phone":"+1 563 359 3487",
    "sg:postcode":"52722",
    "sg:province":"IA",
    "sg:tags":[
        "equipment",
        "supply",
        "art",
        "dealer",
        "gallery"
    ],
    "wof:name":"Evergreen Art Works",
    "wof:placetype":"venue"
},
  "geometry": {"coordinates":[-90.499274,41.549324],"type":"Point"}
}