{
  "type": "Feature",
  "properties": {
    "addr:full":"804 SE 30th St Des Moines IA 50317",
    "addr:housenumber":"804",
    "addr:postcode":"50317",
    "addr:street":"Se 30Th St",
    "iso:country":"US",
    "sg:address":"804 SE 30th St",
    "sg:city":"Des Moines",
    "sg:classifiers":[
        {
            "category":"Autos & Motor Vehicles",
            "subcategory":"Automobile Sales",
            "type":"Retail Goods"
        }
    ],
    "sg:phone":"+1 515 266 3940",
    "sg:postcode":"50317",
    "sg:province":"IA",
    "sg:tags":[
        "wrecker"
    ],
    "sg:website":"www.donsautotruck.com",
    "wof:name":"Don's Rebuilders",
    "wof:placetype":"venue"
},
  "geometry": {"coordinates":[-93.558393,41.580131],"type":"Point"}
}