{
  "type": "Feature",
  "properties": {
    "addr:full":"709 Meadow Lane Ct Mt Vernon IA 52314",
    "addr:housenumber":"709",
    "addr:postcode":"52314",
    "addr:street":"Meadow Lane Ct",
    "iso:country":"US",
    "sg:address":"709 Meadow Lane Ct",
    "sg:city":"Mt Vernon",
    "sg:classifiers":[
        {
            "category":"Real Estate",
            "subcategory":"Real Estate Operator",
            "type":"Services"
        }
    ],
    "sg:phone":"+1 319 895 6358",
    "sg:postcode":"52314",
    "sg:province":"IA",
    "sg:tags":[
        "building",
        "apartment"
    ],
    "wof:name":"Kintzle's Imperial Apartments",
    "wof:placetype":"venue"
},
  "geometry": {"coordinates":[-91.41196100000001,41.918457],"type":"Point"}
}