{
  "type": "Feature",
  "properties": {
    "addr:full":"1106 Prairie du Chien Rd Iowa City IA 52245",
    "addr:housenumber":"1106",
    "addr:postcode":"52245",
    "addr:street":"Prairie Du Chien Rd",
    "iso:country":"US",
    "sg:address":"1106 Prairie du Chien Rd",
    "sg:city":"Iowa City",
    "sg:classifiers":[
        {
            "category":"Wholesale",
            "subcategory":"Dairy",
            "type":"Manufacturing & Wholesale Goods"
        }
    ],
    "sg:phone":"+1 319 338 4932",
    "sg:postcode":"52245",
    "sg:province":"IA",
    "sg:tags":[
        "product"
    ],
    "wof:name":"Dairy Farmers of America Inc",
    "wof:placetype":"venue"
},
  "geometry": {"coordinates":[-91.521136,41.676349],"type":"Point"}
}