{
  "type": "Feature",
  "properties": {
    "addr:full":"1736 Mamie Eisenhower Ave Boone IA 50036",
    "addr:housenumber":"1736",
    "addr:postcode":"50036",
    "addr:street":"Mamie Eisenhower Ave",
    "iso:country":"US",
    "sg:address":"1736 Mamie Eisenhower Ave",
    "sg:city":"Boone",
    "sg:classifiers":[
        {
            "category":"Retail",
            "subcategory":"Car Wash",
            "type":"Services"
        }
    ],
    "sg:phone":"+1 515 432 5506",
    "sg:postcode":"50036",
    "sg:province":"IA",
    "sg:tags":[
        "automobile",
        "detail",
        "clean"
    ],
    "wof:name":"Perfect Image",
    "wof:placetype":"venue"
},
  "geometry": {"coordinates":[-93.86392600000001,42.059564],"type":"Point"}
}