{
  "type": "Feature",
  "properties": {
    "addr:full":"611 Main St Osage IA 50461",
    "addr:housenumber":"611",
    "addr:postcode":"50461",
    "addr:street":"Main St",
    "iso:country":"US",
    "sg:address":"611 Main St",
    "sg:city":"Osage",
    "sg:classifiers":[
        {
            "category":"Professional",
            "subcategory":"Accounting & Tax Preparation",
            "type":"Services"
        }
    ],
    "sg:phone":"+1 641 732 3445",
    "sg:postcode":"50461",
    "sg:province":"IA",
    "sg:tags":[
        "return",
        "filing"
    ],
    "wof:name":"Bisbee Income Tax & Accounting",
    "wof:placetype":"venue"
},
  "geometry": {"coordinates":[-92.81273899999999,43.28416],"type":"Point"}
}