{
  "type": "Feature",
  "properties": {
    "addr:full":"19 1st Ave SE Britt IA 50423",
    "addr:housenumber":"19",
    "addr:postcode":"50423",
    "addr:street":"1St Ave Se",
    "iso:country":"US",
    "sg:address":"19 1st Ave SE",
    "sg:city":"Britt",
    "sg:classifiers":[
        {
            "category":"Shopping",
            "type":"Retail Goods"
        }
    ],
    "sg:phone":"+1 641 843 4443",
    "sg:postcode":"50423",
    "sg:province":"IA",
    "sg:tags":[
        "church",
        "supply"
    ],
    "wof:name":"Helen Smidt Gift Nook & Bible",
    "wof:placetype":"venue"
},
  "geometry": {"coordinates":[-93.800551,43.096763],"type":"Point"}
}