{
  "type": "Feature",
  "properties": {
    "iso:country":"US",
    "sg:address":"407 7th Ave",
    "sg:city":"Sully",
    "sg:classifiers":[
        {
            "category":"Wholesale",
            "subcategory":"Meat",
            "type":"Manufacturing & Wholesale Goods"
        }
    ],
    "sg:phone":"+1 641 594 4240",
    "sg:postcode":"50251",
    "sg:province":"IA",
    "sg:tags":[
        "product"
    ],
    "wof:name":"Community Lockers",
    "wof:placetype":"venue"
},
  "geometry": {"coordinates":[-92.845986,41.578172],"type":"Point"}
}