{
  "type": "Feature",
  "properties": {
    "iso:country":"US",
    "sg:address":"2904 SE 14th St",
    "sg:city":"Des Moines",
    "sg:classifiers":[
        {
            "category":"Local Transit",
            "type":"Transportation"
        }
    ],
    "sg:phone":"+1 515 285 6346",
    "sg:postcode":"50320",
    "sg:province":"IA",
    "sg:tags":[
        "limousine"
    ],
    "sg:website":"www.smithsonlimousines.com",
    "wof:name":"Smithson Limousine Svc",
    "wof:placetype":"venue"
},
  "geometry": {"coordinates":[-93.597032,41.558721],"type":"Point"}
}