{
  "type": "Feature",
  "properties": {
    "iso:country":"US",
    "sg:address":"2030 Plank Rd",
    "sg:city":"Keokuk",
    "sg:classifiers":[
        {
            "category":"Organizations",
            "subcategory":"Religious Organization",
            "type":"Services"
        }
    ],
    "sg:phone":"+1 319 524 1191",
    "sg:postcode":"52632",
    "sg:province":"IA",
    "sg:tags":[
        "church"
    ],
    "wof:name":"St Paul United Church",
    "wof:placetype":"venue"
},
  "geometry": {"coordinates":[-91.392983,40.410692],"type":"Point"}
}