{
  "type": "Feature",
  "properties": {
    "iso:country":"US",
    "sg:address":"2723 Grand Ave",
    "sg:city":"Des Moines",
    "sg:classifiers":[
        {
            "category":"Autos & Motor Vehicles",
            "subcategory":"Fuel & Gas Station",
            "type":"Retail Goods"
        }
    ],
    "sg:phone":"+1 515 288 1800",
    "sg:postcode":"50312",
    "sg:province":"IA",
    "sg:tags":[
        "oil"
    ],
    "wof:name":"Schaller & Son Phillips 66",
    "wof:placetype":"venue"
},
  "geometry": {"coordinates":[-93.65416,41.584464],"type":"Point"}
}