{
  "type": "Feature",
  "properties": {
    "iso:country":"US",
    "sg:address":"709 S Garnavillo St",
    "sg:city":"Anamosa",
    "sg:classifiers":[
        {
            "category":"Building & Trades",
            "subcategory":"Construction",
            "type":"Services"
        }
    ],
    "sg:phone":"+1 319 462 4764",
    "sg:postcode":"52205",
    "sg:province":"IA",
    "sg:tags":[
        "contractor"
    ],
    "wof:name":"Spray Rite",
    "wof:placetype":"venue"
},
  "geometry": {"coordinates":[-91.28593600000001,42.100234],"type":"Point"}
}