{
  "type": "Feature",
  "properties": {
    "iso:country":"US",
    "sg:address":"1417 Main Ave",
    "sg:city":"Clear Lake",
    "sg:classifiers":[
        {
            "category":"Shopping",
            "subcategory":"Used Merchandise",
            "type":"Retail Goods"
        }
    ],
    "sg:phone":"+1 641 357 4352",
    "sg:postcode":"50428",
    "sg:province":"IA",
    "sg:tags":[
        "antique"
    ],
    "wof:name":"Yesteryear House Of Antiques",
    "wof:placetype":"venue"
},
  "geometry": {"coordinates":[-93.371208,43.137278],"type":"Point"}
}