{
  "type": "Feature",
  "properties": {
    "iso:country":"US",
    "sg:address":"135 E Main St",
    "sg:city":"Marshalltown",
    "sg:classifiers":[
        {
            "category":"Personal",
            "subcategory":"Tanning Parlor",
            "type":"Services"
        }
    ],
    "sg:phone":"+1 641 754 0156",
    "sg:postcode":"50158",
    "sg:province":"IA",
    "sg:tags":[
        "salon"
    ],
    "wof:name":"Apparel Outlet",
    "wof:placetype":"venue"
},
  "geometry": {"coordinates":[-92.91081,42.049086],"type":"Point"}
}