{
  "type": "Feature",
  "properties": {
    "addr:full":"201 E 2nd St Davenport IA 52801",
    "addr:housenumber":"201",
    "addr:postcode":"52801",
    "addr:street":"E 2Nd St",
    "iso:country":"US",
    "sg:address":"201 E 2nd St",
    "sg:city":"Davenport",
    "sg:classifiers":[
        {
            "category":"Banks & Credit Unions",
            "subcategory":"Bank",
            "type":"Services"
        }
    ],
    "sg:phone":"+1 563 328 3100",
    "sg:postcode":"52801",
    "sg:province":"IA",
    "sg:tags":[
        "national",
        "commercial"
    ],
    "wof:name":"US Bank",
    "wof:placetype":"venue"
},
  "geometry": {"coordinates":[-90.571175,41.52131],"type":"Point"}
}