{
  "type": "Feature",
  "properties": {
    "addr:full":"131 5th Ave S Clinton IA 52732",
    "addr:housenumber":"131",
    "addr:postcode":"52732",
    "addr:street":"5Th Ave S",
    "iso:country":"US",
    "sg:address":"131 5th Ave S",
    "sg:city":"Clinton",
    "sg:classifiers":[
        {
            "category":"Shopping",
            "subcategory":"Bicycles & Sporting Goods",
            "type":"Retail Goods"
        }
    ],
    "sg:phone":"+1 563 243 8000",
    "sg:postcode":"52732",
    "sg:province":"IA",
    "wof:name":"River City Bike Shop",
    "wof:placetype":"venue"
},
  "geometry": {"coordinates":[-90.18748100000001,41.841133],"type":"Point"}
}