{
  "type": "Feature",
  "properties": {
    "addr:full":"125 S 3rd St Ames IA 50010",
    "addr:housenumber":"125",
    "addr:postcode":"50010",
    "addr:street":"S 3Rd St",
    "iso:country":"US",
    "sg:address":"125 S 3rd St",
    "sg:city":"Ames",
    "sg:classifiers":[
        {
            "category":"Health Services",
            "subcategory":"Hospital",
            "type":"Services"
        }
    ],
    "sg:phone":"+1 515 232 5811",
    "sg:postcode":"50010",
    "sg:province":"IA",
    "sg:tags":[
        "mental"
    ],
    "sg:website":"www.richmondcenter.net",
    "wof:name":"Richmond Center",
    "wof:placetype":"venue"
},
  "geometry": {"coordinates":[-93.610906,42.020227],"type":"Point"}
}