{
  "type": "Feature",
  "properties": {
    "iso:country":"US",
    "sg:address":"3410 76th Ave",
    "sg:city":"Bettendorf",
    "sg:phone":"+1 563 332 5064",
    "sg:postcode":"52722",
    "sg:province":"IA",
    "sg:tags":[
        "beef",
        "farm",
        "corn",
        "soybean",
        "cattle",
        "feedlot"
    ],
    "wof:name":"Glen Seligman",
    "wof:placetype":"venue"
},
  "geometry": {"coordinates":[-90.485658,41.597146],"type":"Point"}
}