{
  "type": "Feature",
  "properties": {
    "iso:country":"US",
    "sg:address":"3 N Walnut Ave",
    "sg:city":"New Hampton",
    "sg:classifiers":[
        {
            "category":"Professional",
            "type":"Services"
        }
    ],
    "sg:phone":"+1 641 394 2767",
    "sg:postcode":"50659",
    "sg:province":"IA",
    "wof:name":"Adwork Incorporated",
    "wof:placetype":"venue"
},
  "geometry": {"coordinates":[-92.31650500000001,43.059724],"type":"Point"}
}