{
  "type": "Feature",
  "properties": {
    "iso:country":"US",
    "sg:address":"115 E College St",
    "sg:city":"Iowa City",
    "sg:classifiers":[
        {
            "category":"Restaurant",
            "type":"Food & Drink"
        }
    ],
    "sg:phone":"+1 319 688 0002",
    "sg:postcode":"52240",
    "sg:province":"IA",
    "wof:name":"Venuto's World Bistro",
    "wof:placetype":"venue"
},
  "geometry": {"coordinates":[-91.533236,41.658744],"type":"Point"}
}