{
  "type": "Feature",
  "properties": {
    "iso:country":"US",
    "sg:address":"720 Edgewood Rd NW",
    "sg:city":"Cedar Rapids",
    "sg:classifiers":[
        {
            "category":"Organizations",
            "subcategory":"Religious Organization",
            "type":"Services"
        }
    ],
    "sg:phone":"+1 319 396 8547",
    "sg:postcode":"52405",
    "sg:province":"IA",
    "sg:tags":[
        "church"
    ],
    "sg:website":"www.holyredeemerlutheran-cr-ia.org",
    "wof:name":"Holy Redeemer Lutheran",
    "wof:placetype":"venue"
},
  "geometry": {"coordinates":[-91.716033,41.979901],"type":"Point"}
}