{
  "type": "Feature",
  "properties": {
    "addr:full":"1524 10th Ave N Humboldt IA 50548",
    "addr:housenumber":"1524",
    "addr:postcode":"50548",
    "addr:street":"10Th Ave N",
    "iso:country":"US",
    "sg:address":"1524 10th Ave N",
    "sg:city":"Humboldt",
    "sg:classifiers":[
        {
            "category":"Insurance",
            "subcategory":"Insurance Agent",
            "type":"Services"
        }
    ],
    "sg:phone":"+1 515 332 2210",
    "sg:postcode":"50548",
    "sg:province":"IA",
    "wof:name":"State Farm Insurance",
    "wof:placetype":"venue"
},
  "geometry": {"coordinates":[-94.23166399999999,42.731776],"type":"Point"}
}