{
  "type": "Feature",
  "properties": {
    "addr:full":"630 N Dubuque St Iowa City IA 52245",
    "addr:housenumber":"630",
    "addr:postcode":"52245",
    "addr:street":"N Dubuque St",
    "iso:country":"US",
    "sg:address":"630 N Dubuque St",
    "sg:city":"Iowa City",
    "sg:classifiers":[
        {
            "category":"Organizations",
            "subcategory":"Community Association",
            "type":"Services"
        }
    ],
    "sg:phone":"+1 319 337 4140",
    "sg:postcode":"52245",
    "sg:province":"IA",
    "sg:tags":[
        "fraternal"
    ],
    "wof:name":"Sigma Nu Fraternity",
    "wof:placetype":"venue"
},
  "geometry": {"coordinates":[-91.532878,41.668779],"type":"Point"}
}