{
  "type": "Feature",
  "properties": {
    "addr:full":"6101 49th St S Muscatine IA 52761",
    "addr:housenumber":"6101",
    "addr:postcode":"52761",
    "addr:street":"49Th St S",
    "iso:country":"US",
    "sg:address":"6101 49th St S",
    "sg:city":"Muscatine",
    "sg:classifiers":[
        {
            "category":"Manufacturing",
            "subcategory":"Rubber & Plastics",
            "type":"Manufacturing & Wholesale Goods"
        }
    ],
    "sg:phone":"+1 563 263 6642",
    "sg:postcode":"52761",
    "sg:province":"IA",
    "sg:tags":[
        "product"
    ],
    "wof:name":"Wiedemann Church Products",
    "wof:placetype":"venue"
},
  "geometry": {"coordinates":[-91.12383699999999,41.370895],"type":"Point"}
}