{
  "type": "Feature",
  "properties": {
    "addr:full":"217 W 4th St Vinton IA 52349",
    "addr:housenumber":"217",
    "addr:postcode":"52349",
    "addr:street":"W 4Th St",
    "iso:country":"US",
    "sg:address":"217 W 4th St",
    "sg:city":"Vinton",
    "sg:classifiers":[
        {
            "category":"Manufacturing",
            "subcategory":"Printing",
            "type":"Manufacturing & Wholesale Goods"
        }
    ],
    "sg:phone":"+1 319 472 2080",
    "sg:postcode":"52349",
    "sg:province":"IA",
    "sg:tags":[
        "printer"
    ],
    "sg:website":"www.nobarriers.com",
    "wof:name":"Cedar River Ink",
    "wof:placetype":"venue"
},
  "geometry": {"coordinates":[-92.026646,42.16778],"type":"Point"}
}