{
  "type": "Feature",
  "properties": {
    "iso:country":"US",
    "sg:address":"145 1st St S",
    "sg:city":"Maynard",
    "sg:classifiers":[
        {
            "category":"Retail",
            "subcategory":"Auto Repair",
            "type":"Services"
        }
    ],
    "sg:phone":"+1 563 637 2363",
    "sg:postcode":"50655",
    "sg:province":"IA",
    "sg:tags":[
        "repairing",
        "automobile"
    ],
    "wof:name":"Lon's Auto Repair",
    "wof:placetype":"venue"
},
  "geometry": {"coordinates":[-91.87741200000001,42.773371],"type":"Point"}
}