{
  "type": "Feature",
  "properties": {
    "iso:country":"US",
    "sg:address":"15479 Liberty Ave",
    "sg:city":"Bloomfield",
    "sg:classifiers":[
        {
            "category":"Retail",
            "subcategory":"Repair Shop",
            "type":"Services"
        }
    ],
    "sg:phone":"+1 641 722 3388",
    "sg:postcode":"52537",
    "sg:province":"IA",
    "sg:tags":[
        "scooter",
        "motorcycle",
        "motor"
    ],
    "wof:name":"T T's Cycle Parts",
    "wof:placetype":"venue"
},
  "geometry": {"coordinates":[-92.426411,40.820779],"type":"Point"}
}