{
  "type": "Feature",
  "properties": {
    "addr:full":"115 Main St Gilbert IA 50105",
    "addr:housenumber":"115",
    "addr:postcode":"50105",
    "addr:street":"Main St",
    "iso:country":"US",
    "sg:address":"115 Main St",
    "sg:city":"Gilbert",
    "sg:classifiers":[
        {
            "category":"Retail",
            "subcategory":"Veterinary Services",
            "type":"Services"
        }
    ],
    "sg:phone":"+1 515 233 6689",
    "sg:postcode":"50105",
    "sg:province":"IA",
    "sg:tags":[
        "veterinarian"
    ],
    "wof:name":"Companion Animal Clinic",
    "wof:placetype":"venue"
},
  "geometry": {"coordinates":[-93.649547,42.107723],"type":"Point"}
}