{
  "type": "Feature",
  "properties": {
    "iso:country":"US",
    "sg:address":"1253 State Hwy 14",
    "sg:city":"Knoxville",
    "sg:classifiers":[
        {
            "category":"Shopping",
            "subcategory":"Used Merchandise",
            "type":"Retail Goods"
        }
    ],
    "sg:phone":"+1 641 842 4644",
    "sg:postcode":"50138",
    "sg:province":"IA",
    "wof:name":"Antiques Orr Others",
    "wof:placetype":"venue"
},
  "geometry": {"coordinates":[-93.109644,41.339519],"type":"Point"}
}