{
  "type": "Feature",
  "properties": {
    "addr:full":"524 Euclid Ave Des Moines IA 50313",
    "addr:housenumber":"524",
    "addr:postcode":"50313",
    "addr:street":"Euclid Ave",
    "iso:country":"US",
    "sg:address":"524 Euclid Ave",
    "sg:city":"Des Moines",
    "sg:classifiers":[
        {
            "category":"Personal",
            "subcategory":"Barber",
            "type":"Services"
        }
    ],
    "sg:phone":"+1 515 244 1535",
    "sg:postcode":"50313",
    "sg:province":"IA",
    "wof:name":"Steve's Barber Shop",
    "wof:placetype":"venue"
},
  "geometry": {"coordinates":[-93.624557,41.627612],"type":"Point"}
}