{
  "type": "Feature",
  "properties": {
    "iso:country":"US",
    "sg:address":"506 Mulberry Ave",
    "sg:city":"Muscatine",
    "sg:classifiers":[
        {
            "category":"Retail",
            "subcategory":"Auto Repair",
            "type":"Services"
        }
    ],
    "sg:phone":"+1 563 264 1722",
    "sg:postcode":"52761",
    "sg:province":"IA",
    "sg:tags":[
        "repairing",
        "automobile"
    ],
    "wof:name":"Leo's Auto Sale & Repair",
    "wof:placetype":"venue"
},
  "geometry": {"coordinates":[-91.044138,41.426286],"type":"Point"}
}