{
  "type": "Feature",
  "properties": {
    "iso:country":"US",
    "sg:address":"226 Dillaway St",
    "sg:city":"Muscatine",
    "sg:classifiers":[
        {
            "category":"Manufacturing",
            "subcategory":"Signs",
            "type":"Manufacturing & Wholesale Goods"
        }
    ],
    "sg:phone":"+1 563 263 1093",
    "sg:postcode":"52761",
    "sg:province":"IA",
    "wof:name":"Artistic Signs",
    "wof:placetype":"venue"
},
  "geometry": {"coordinates":[-91.064108,41.429405],"type":"Point"}
}