{
  "type": "Feature",
  "properties": {
    "iso:country":"US",
    "sg:address":"301 3rd Ave",
    "sg:city":"Charles City",
    "sg:classifiers":[
        {
            "category":"Manufacturing",
            "subcategory":"Printing",
            "type":"Manufacturing & Wholesale Goods"
        }
    ],
    "sg:phone":"+1 641 330 4137",
    "sg:postcode":"50616",
    "sg:province":"IA",
    "sg:tags":[
        "commercial"
    ],
    "wof:name":"Simply Inviting",
    "wof:placetype":"venue"
},
  "geometry": {"coordinates":[-92.66983399999999,43.065495],"type":"Point"}
}