{
  "type": "Feature",
  "properties": {
    "iso:country":"US",
    "sg:address":"689 P Ave",
    "sg:city":"Boone",
    "sg:classifiers":[
        {
            "category":"Farming",
            "subcategory":"Livestock Farm",
            "type":"Manufacturing & Wholesale Goods"
        }
    ],
    "sg:phone":"+1 515 432 2170",
    "sg:postcode":"50036",
    "sg:province":"IA",
    "sg:tags":[
        "animal",
        "general"
    ],
    "wof:name":"Triangle B Farms Inc",
    "wof:placetype":"venue"
},
  "geometry": {"coordinates":[-93.87402,42.108689],"type":"Point"}
}