{
  "type": "Feature",
  "properties": {
    "addr:full":"107 N Washington St Edgewood IA 52042",
    "addr:housenumber":"107",
    "addr:postcode":"52042",
    "addr:street":"N Washington St",
    "iso:country":"US",
    "sg:address":"107 N Washington St",
    "sg:city":"Edgewood",
    "sg:classifiers":[
        {
            "category":"Health Services",
            "subcategory":"Chiropractor",
            "type":"Services"
        }
    ],
    "sg:phone":"+1 563 928 7116",
    "sg:postcode":"52042",
    "sg:province":"IA",
    "wof:name":"Edgewood Chiropractic Svc",
    "wof:placetype":"venue"
},
  "geometry": {"coordinates":[-91.401123,42.645291],"type":"Point"}
}