{
  "type": "Feature",
  "properties": {
    "addr:full":"2839 Burton Ave Waterloo IA 50703",
    "addr:housenumber":"2839",
    "addr:postcode":"50703",
    "addr:street":"Burton Ave",
    "iso:country":"US",
    "sg:address":"2839 Burton Ave",
    "sg:city":"Waterloo",
    "sg:classifiers":[
        {
            "category":"Manufacturing",
            "subcategory":"Metals",
            "type":"Manufacturing & Wholesale Goods"
        }
    ],
    "sg:phone":"+1 319 232 0745",
    "sg:postcode":"50703",
    "sg:province":"IA",
    "sg:tags":[
        "treating",
        "heat"
    ],
    "wof:name":"Advanced Heat Treat Corp",
    "wof:placetype":"venue"
},
  "geometry": {"coordinates":[-92.357388,42.540711],"type":"Point"}
}