{
  "type": "Feature",
  "properties": {
    "iso:country":"US",
    "sg:address":"521 W Garfield St",
    "sg:city":"Davenport",
    "sg:classifiers":[
        {
            "category":"Professional",
            "subcategory":"Management & Consulting",
            "type":"Services"
        }
    ],
    "sg:phone":"+1 563 326 5535",
    "sg:postcode":"52803",
    "sg:province":"IA",
    "sg:tags":[
        "business"
    ],
    "wof:name":"Managed Systems & Consulting",
    "wof:placetype":"venue"
},
  "geometry": {"coordinates":[-90.581253,41.54859],"type":"Point"}
}