{
  "type": "Feature",
  "properties": {
    "iso:country":"US",
    "sg:address":"4650 86th St",
    "sg:city":"Urbandale",
    "sg:classifiers":[
        {
            "category":"Food & Beverages",
            "subcategory":"Liquor & Beverages",
            "type":"Retail Goods"
        }
    ],
    "sg:phone":"+1 515 270 8609",
    "sg:postcode":"50322",
    "sg:province":"IA",
    "wof:name":"Wine & Spirit Gallery",
    "wof:placetype":"venue"
},
  "geometry": {"coordinates":[-93.736549,41.644549],"type":"Point"}
}