{
  "type": "Feature",
  "properties": {
    "iso:country":"US",
    "sg:address":"2307 692 Ave",
    "sg:city":"Albia",
    "sg:classifiers":[
        {
            "category":"Recreation",
            "type":"Entertainment"
        }
    ],
    "sg:phone":"+1 641 932 5493",
    "sg:postcode":"52531",
    "sg:province":"IA",
    "sg:tags":[
        "stable"
    ],
    "wof:name":"Robinson Arena Inc",
    "wof:placetype":"venue"
},
  "geometry": {"coordinates":[-92.73115799999999,40.976774],"type":"Point"}
}