{
  "type": "Feature",
  "properties": {
    "iso:country":"US",
    "sg:address":"915 N 13th St",
    "sg:city":"Clear Lake",
    "sg:classifiers":[
        {
            "category":"Retail",
            "subcategory":"Repair Shop",
            "type":"Services"
        }
    ],
    "sg:phone":"+1 641 357 5326",
    "sg:postcode":"50428",
    "sg:province":"IA",
    "sg:tags":[
        "refinishing",
        "furniture"
    ],
    "wof:name":"Bix Furniture Restoration",
    "wof:placetype":"venue"
},
  "geometry": {"coordinates":[-93.372587,43.143465],"type":"Point"}
}