{
  "type": "Feature",
  "properties": {
    "iso:country":"US",
    "sg:address":"1817 385th Ave",
    "sg:city":"Brooklyn",
    "sg:classifiers":[
        {
            "category":"Freight",
            "type":"Transportation"
        }
    ],
    "sg:phone":"+1 641 522 5614",
    "sg:postcode":"52211",
    "sg:province":"IA",
    "sg:tags":[
        "trucking"
    ],
    "wof:name":"Mid Iowa Transport",
    "wof:placetype":"venue"
},
  "geometry": {"coordinates":[-92.42890199999999,41.73787],"type":"Point"}
}