{
  "type": "Feature",
  "properties": {
    "iso:country":"US",
    "sg:address":"2281 State Hwy 2",
    "sg:city":"Sidney",
    "sg:classifiers":[
        {
            "category":"Sports & Exercise",
            "subcategory":"Golf",
            "type":"Entertainment"
        }
    ],
    "sg:phone":"+1 712 374 2347",
    "sg:postcode":"51652",
    "sg:province":"IA",
    "sg:tags":[
        "course"
    ],
    "wof:name":"Fremont County Golf Course",
    "wof:placetype":"venue"
},
  "geometry": {"coordinates":[-95.62908400000001,40.748245],"type":"Point"}
}