{
  "type": "Feature",
  "properties": {
    "iso:country":"US",
    "sg:address":"1711 Osceola Ave",
    "sg:city":"Chariton",
    "sg:classifiers":[
        {
            "category":"Social Services",
            "subcategory":"Child Care",
            "type":"Services"
        }
    ],
    "sg:phone":"+1 641 774 3215",
    "sg:postcode":"50049",
    "sg:province":"IA",
    "wof:name":"Discovery PRESCHOOL-Lchc",
    "wof:placetype":"venue"
},
  "geometry": {"coordinates":[-93.319248,41.02117],"type":"Point"}
}