{
  "type": "Feature",
  "properties": {
    "iso:country":"US",
    "sg:address":"2807 Lincoln Way",
    "sg:city":"Sioux City",
    "sg:classifiers":[
        {
            "category":"Real Estate",
            "subcategory":"Real Estate Operator",
            "type":"Services"
        }
    ],
    "sg:phone":"+1 712 274 7750",
    "sg:postcode":"51106",
    "sg:province":"IA",
    "sg:tags":[
        "apartment"
    ],
    "wof:name":"Landmark Apartments",
    "wof:placetype":"venue"
},
  "geometry": {"coordinates":[-96.371262,42.458835],"type":"Point"}
}