{
  "type": "Feature",
  "properties": {
    "addr:full":"105 E Broadway St Paullina IA 51046",
    "addr:housenumber":"105",
    "addr:postcode":"51046",
    "addr:street":"E Broadway St",
    "iso:country":"US",
    "sg:address":"105 E Broadway St",
    "sg:city":"Paullina",
    "sg:classifiers":[
        {
            "category":"Bars & Pubs",
            "type":"Food & Drink"
        }
    ],
    "sg:phone":"+1 712 448 2479",
    "sg:postcode":"51046",
    "sg:province":"IA",
    "wof:name":"Lightning Lounge",
    "wof:placetype":"venue"
},
  "geometry": {"coordinates":[-95.687049,42.979272],"type":"Point"}
}