{
  "type": "Feature",
  "properties": {
    "addr:full":"521 Central Ave Fort Dodge IA 50501",
    "addr:housenumber":"521",
    "addr:postcode":"50501",
    "addr:street":"Central Ave",
    "iso:country":"US",
    "sg:address":"521 Central Ave",
    "sg:city":"Fort Dodge",
    "sg:classifiers":[
        {
            "category":"Manufacturing",
            "subcategory":"Apparel",
            "type":"Manufacturing & Wholesale Goods"
        }
    ],
    "sg:phone":"+1 515 955 4480",
    "sg:postcode":"50501",
    "sg:province":"IA",
    "sg:tags":[
        "glove"
    ],
    "wof:name":"Fort Dodge Sewing",
    "wof:placetype":"venue"
},
  "geometry": {"coordinates":[-94.19014,42.504635],"type":"Point"}
}