{
  "type": "Feature",
  "properties": {
    "iso:country":"US",
    "sg:address":"9998 Swanson Blvd",
    "sg:city":"Clive",
    "sg:classifiers":[
        {
            "category":"Shopping",
            "subcategory":"Optical Goods",
            "type":"Retail Goods"
        }
    ],
    "sg:phone":"+1 515 226 0140",
    "sg:postcode":"50325",
    "sg:province":"IA",
    "wof:name":"Optica",
    "wof:placetype":"venue"
},
  "geometry": {"coordinates":[-93.75515,41.611579],"type":"Point"}
}