{
  "type": "Feature",
  "properties": {
    "iso:country":"US",
    "sg:address":"214 E 4th St S",
    "sg:city":"Newton",
    "sg:classifiers":[
        {
            "category":"Building & Trades",
            "subcategory":"Construction",
            "type":"Services"
        }
    ],
    "sg:phone":"+1 641 792 6239",
    "sg:postcode":"50208",
    "sg:province":"IA",
    "sg:tags":[
        "general",
        "contractor"
    ],
    "wof:name":"Cabinets By Design",
    "wof:placetype":"venue"
},
  "geometry": {"coordinates":[-93.049689,41.69847],"type":"Point"}
}