{
  "type": "Feature",
  "properties": {
    "iso:country":"US",
    "sg:address":"21265 430th St",
    "sg:city":"Lake Mills",
    "sg:classifiers":[
        {
            "category":"Utilities",
            "subcategory":"Refuse",
            "type":"Services"
        }
    ],
    "sg:phone":"+1 641 592 9182",
    "sg:postcode":"50450",
    "sg:province":"IA",
    "sg:tags":[
        "landfill"
    ],
    "sg:website":"www.wm.com",
    "wof:name":"Central Disposal Systems Inc",
    "wof:placetype":"venue"
},
  "geometry": {"coordinates":[-93.562299,43.386261],"type":"Point"}
}