{
  "type": "Feature",
  "properties": {
    "iso:country":"US",
    "sg:address":"450 Thelma St",
    "sg:city":"Hudson",
    "sg:classifiers":[
        {
            "category":"Organizations",
            "subcategory":"Religious Organization",
            "type":"Services"
        }
    ],
    "sg:phone":"+1 319 988 3053",
    "sg:postcode":"50643",
    "sg:province":"IA",
    "sg:tags":[
        "church"
    ],
    "wof:name":"Faith Baptist Church",
    "wof:placetype":"venue"
},
  "geometry": {"coordinates":[-92.44647399999999,42.403217],"type":"Point"}
}