{
  "type": "Feature",
  "properties": {
    "iso:country":"US",
    "sg:address":"120 S Cardinal Dr",
    "sg:city":"Clarinda",
    "sg:classifiers":[
        {
            "category":"Farming",
            "subcategory":"Livestock Farm",
            "type":"Manufacturing & Wholesale Goods"
        }
    ],
    "sg:phone":"+1 712 542 4228",
    "sg:postcode":"51632",
    "sg:province":"IA",
    "sg:tags":[
        "animal",
        "general"
    ],
    "wof:name":"Tritsch Farms Inc",
    "wof:placetype":"venue"
},
  "geometry": {"coordinates":[-95.04819500000001,40.738013],"type":"Point"}
}