{
  "type": "Feature",
  "properties": {
    "iso:country":"US",
    "sg:address":"2754 Redwing Ave",
    "sg:city":"Sanborn",
    "sg:classifiers":[
        {
            "category":"Farming",
            "subcategory":"Farm",
            "type":"Manufacturing & Wholesale Goods"
        }
    ],
    "sg:phone":"+1 712 729 5410",
    "sg:postcode":"51248",
    "sg:province":"IA",
    "sg:tags":[
        "crop",
        "general"
    ],
    "wof:name":"Fulk Dale",
    "wof:placetype":"venue"
},
  "geometry": {"coordinates":[-95.683745,43.250475],"type":"Point"}
}