{
  "type": "Feature",
  "properties": {
    "addr:full":"610 W Jasper St Pleasantville IA 50225",
    "addr:housenumber":"610",
    "addr:postcode":"50225",
    "addr:street":"W Jasper St",
    "iso:country":"US",
    "sg:address":"610 W Jasper St",
    "sg:city":"Pleasantville",
    "sg:classifiers":[
        {
            "category":"Professional",
            "subcategory":"Computer Services",
            "type":"Services"
        }
    ],
    "sg:phone":"+1 515 848 3299",
    "sg:postcode":"50225",
    "sg:province":"IA",
    "wof:name":"Hampstead Computer Repair",
    "wof:placetype":"venue"
},
  "geometry": {"coordinates":[-93.274728,41.385546],"type":"Point"}
}