{
  "type": "Feature",
  "properties": {
    "addr:full":"2827 8th Ave S Fort Dodge IA 50501",
    "addr:housenumber":"2827",
    "addr:postcode":"50501",
    "addr:street":"8Th Ave S",
    "iso:country":"US",
    "sg:address":"2827 8th Ave S",
    "sg:city":"Fort Dodge",
    "sg:classifiers":[
        {
            "category":"Manufacturing",
            "subcategory":"Pet Food",
            "type":"Manufacturing & Wholesale Goods"
        }
    ],
    "sg:phone":"+1 515 576 7311",
    "sg:postcode":"50501",
    "sg:province":"IA",
    "sg:tags":[
        "feed"
    ],
    "sg:website":"www.landolakesinc.com",
    "wof:name":"Land O'Lakes",
    "wof:placetype":"venue"
},
  "geometry": {"coordinates":[-94.15846000000001,42.497523],"type":"Point"}
}