{
  "type": "Feature",
  "properties": {
    "addr:full":"929 Grandview Blvd Sioux City IA 51103",
    "addr:housenumber":"929",
    "addr:postcode":"51103",
    "addr:street":"Grandview Blvd",
    "iso:country":"US",
    "sg:address":"929 Grandview Blvd",
    "sg:city":"Sioux City",
    "sg:classifiers":[
        {
            "category":"Building & Trades",
            "subcategory":"Construction",
            "type":"Services"
        }
    ],
    "sg:phone":"+1 712 252 2165",
    "sg:postcode":"51103",
    "sg:province":"IA",
    "sg:tags":[
        "contractor"
    ],
    "wof:name":"Western Contracting",
    "wof:placetype":"venue"
},
  "geometry": {"coordinates":[-96.408012,42.499853],"type":"Point"}
}