{
  "type": "Feature",
  "properties": {
    "iso:country":"US",
    "sg:address":"112 Central Ave E",
    "sg:city":"Clarion",
    "sg:classifiers":[
        {
            "category":"Real Estate",
            "subcategory":"Real Estate Agent",
            "type":"Services"
        }
    ],
    "sg:phone":"+1 515 532 3917",
    "sg:postcode":"50525",
    "sg:province":"IA",
    "sg:website":"www.northiarealestate.com",
    "wof:name":"North Iowa Real Estate Co",
    "wof:placetype":"venue"
},
  "geometry": {"coordinates":[-93.732741,42.731604],"type":"Point"}
}