{
  "type": "Feature",
  "properties": {
    "iso:country":"US",
    "sg:address":"3001 Main St",
    "sg:city":"Keokuk",
    "sg:classifiers":[
        {
            "category":"Banks & Credit Unions",
            "subcategory":"Bank",
            "type":"Services"
        }
    ],
    "sg:phone":"+1 319 526 5409",
    "sg:postcode":"52632",
    "sg:province":"IA",
    "wof:name":"Keokuk Savings Bank",
    "wof:placetype":"venue"
},
  "geometry": {"coordinates":[-91.40196899999999,40.413761],"type":"Point"}
}