{
  "type": "Feature",
  "properties": {
    "addr:full":"125 S Main St Kingsley IA 51028",
    "addr:housenumber":"125",
    "addr:postcode":"51028",
    "addr:street":"S Main St",
    "iso:country":"US",
    "sg:address":"125 S Main St",
    "sg:city":"Kingsley",
    "sg:classifiers":[
        {
            "category":"Health Services",
            "subcategory":"Optometrist",
            "type":"Services"
        }
    ],
    "sg:phone":"+1 712 378 2640",
    "sg:postcode":"51028",
    "sg:province":"IA",
    "wof:name":"Kingsley Vision Ctr",
    "wof:placetype":"venue"
},
  "geometry": {"coordinates":[-95.96725600000001,42.584271],"type":"Point"}
}