{
  "type": "Feature",
  "properties": {
    "iso:country":"US",
    "sg:address":"17935 Crystal Ave",
    "sg:city":"Arcadia",
    "sg:classifiers":[
        {
            "category":"Farming",
            "subcategory":"Livestock Farm",
            "type":"Manufacturing & Wholesale Goods"
        }
    ],
    "sg:phone":"+1 712 689 2214",
    "sg:postcode":"51430",
    "sg:province":"IA",
    "sg:tags":[
        "animal",
        "general"
    ],
    "wof:name":"Lady K Enterprises Inc",
    "wof:placetype":"venue"
},
  "geometry": {"coordinates":[-95.043221,42.094227],"type":"Point"}
}