{
  "type": "Feature",
  "properties": {
    "iso:country":"US",
    "sg:address":"402 1st Ave S",
    "sg:city":"Mt Vernon",
    "sg:classifiers":[
        {
            "category":"Shopping",
            "type":"Retail Goods"
        }
    ],
    "sg:phone":"+1 319 895 2100",
    "sg:postcode":"52314",
    "sg:province":"IA",
    "sg:tags":[
        "art",
        "gallery",
        "dealer"
    ],
    "wof:name":"A R Tworks Gallery",
    "wof:placetype":"venue"
},
  "geometry": {"coordinates":[-91.41914,41.919897],"type":"Point"}
}