{
  "type": "Feature",
  "properties": {
    "addr:full":"3114 Merle Hay Rd Des Moines IA 50310",
    "addr:housenumber":"3114",
    "addr:postcode":"50310",
    "addr:street":"Merle Hay Rd Des",
    "iso:country":"US",
    "sg:address":"3114 Merle Hay Rd",
    "sg:city":"Des Moines",
    "sg:classifiers":[
        {
            "category":"Wholesale",
            "subcategory":"Machinery & Supplies",
            "type":"Manufacturing & Wholesale Goods"
        }
    ],
    "sg:phone":"+1 515 278 1100",
    "sg:postcode":"50310",
    "sg:province":"IA",
    "sg:tags":[
        "salon",
        "beauty"
    ],
    "wof:name":"Aeriel Beauty Supply",
    "wof:placetype":"venue"
},
  "geometry": {"coordinates":[-93.697811,41.624813],"type":"Point"}
}