{
  "type": "Feature",
  "properties": {
    "iso:country":"US",
    "sg:address":"1102 N Lincoln St",
    "sg:city":"Knoxville",
    "sg:classifiers":[
        {
            "category":"Restaurant",
            "type":"Food & Drink"
        }
    ],
    "sg:phone":"+1 641 842 2333",
    "sg:postcode":"50138",
    "sg:province":"IA",
    "sg:website":"www.subway.com",
    "wof:name":"Subway Sandwiches & Salads",
    "wof:placetype":"venue"
},
  "geometry": {"coordinates":[-93.10957399999999,41.327612],"type":"Point"}
}