{
  "type": "Feature",
  "properties": {
    "iso:country":"US",
    "sg:address":"127 Marion Blvd",
    "sg:city":"Marion",
    "sg:classifiers":[
        {
            "category":"Health Services",
            "subcategory":"Chiropractor",
            "type":"Services"
        }
    ],
    "sg:phone":"+1 319 447 1317",
    "sg:postcode":"52302",
    "sg:province":"IA",
    "wof:name":"Bradley Dennis Dr",
    "wof:placetype":"venue"
},
  "geometry": {"coordinates":[-91.611287,42.031326],"type":"Point"}
}