{
  "type": "Feature",
  "properties": {
    "addr:full":"2919 Elm St Dubuque IA 52001",
    "addr:housenumber":"2919",
    "addr:postcode":"52001",
    "addr:street":"Elm St",
    "iso:country":"US",
    "sg:address":"2919 Elm St",
    "sg:city":"Dubuque",
    "sg:classifiers":[
        {
            "category":"Retail",
            "subcategory":"Portrait Studio",
            "type":"Services"
        }
    ],
    "sg:phone":"+1 563 556 1154",
    "sg:postcode":"52001",
    "sg:province":"IA",
    "sg:tags":[
        "photographer"
    ],
    "wof:name":"Photography By Dan White",
    "wof:placetype":"venue"
},
  "geometry": {"coordinates":[-90.677836,42.526752],"type":"Point"}
}