{
  "type": "Feature",
  "properties": {
    "iso:country":"US",
    "sg:address":"2725 Johnson Ave NW",
    "sg:city":"Cedar Rapids",
    "sg:classifiers":[
        {
            "category":"Retail",
            "subcategory":"Auto Repair",
            "type":"Services"
        }
    ],
    "sg:phone":"+1 319 261 0536",
    "sg:postcode":"52405",
    "sg:province":"IA",
    "sg:tags":[
        "repairing",
        "automobile",
        "towing"
    ],
    "wof:name":"Jones Automotive",
    "wof:placetype":"venue"
},
  "geometry": {"coordinates":[-91.70880099999999,41.9744],"type":"Point"}
}