{
  "type": "Feature",
  "properties": {
    "iso:country":"US",
    "sg:address":"510 2nd Ave",
    "sg:city":"Vinton",
    "sg:classifiers":[
        {
            "category":"Education",
            "subcategory":"Library",
            "type":"Public Place"
        }
    ],
    "sg:phone":"+1 319 472 4208",
    "sg:postcode":"52349",
    "sg:province":"IA",
    "wof:name":"Vinton Public Library",
    "wof:placetype":"venue"
},
  "geometry": {"coordinates":[-92.022881,42.166582],"type":"Point"}
}