{
  "type": "Feature",
  "properties": {
    "iso:country":"US",
    "sg:address":"114 N Mississippi St",
    "sg:city":"Blue Grass",
    "sg:classifiers":[
        {
            "category":"Education",
            "subcategory":"Library",
            "type":"Public Place"
        }
    ],
    "sg:phone":"+1 563 381 2868",
    "sg:postcode":"52726",
    "sg:province":"IA",
    "wof:name":"Scott County of",
    "wof:placetype":"venue"
},
  "geometry": {"coordinates":[-90.765602,41.509399],"type":"Point"}
}