{
  "type": "Feature",
  "properties": {
    "addr:full":"2342 63rd St Vinton IA 52349",
    "addr:housenumber":"2342",
    "addr:postcode":"52349",
    "addr:street":"63Rd St",
    "iso:country":"US",
    "sg:address":"2342 63rd St",
    "sg:city":"Vinton",
    "sg:classifiers":[
        {
            "category":"Farming",
            "subcategory":"Livestock Farm",
            "type":"Manufacturing & Wholesale Goods"
        }
    ],
    "sg:phone":"+1 319 472 3635",
    "sg:postcode":"52349",
    "sg:province":"IA",
    "sg:tags":[
        "general"
    ],
    "wof:name":"Olson & Sons",
    "wof:placetype":"venue"
},
  "geometry": {"coordinates":[-92.04011199999999,42.108739],"type":"Point"}
}