{
  "type": "Feature",
  "properties": {
    "iso:country":"US",
    "sg:address":"304 Main St",
    "sg:city":"Curlew",
    "sg:classifiers":[
        {
            "category":"Government",
            "subcategory":"Office",
            "type":"Public Place"
        }
    ],
    "sg:phone":"+1 712 855 2361",
    "sg:postcode":"50551",
    "sg:province":"IA",
    "wof:name":"County Maintenance Building",
    "wof:placetype":"venue"
},
  "geometry": {"coordinates":[-94.720502,42.478827],"type":"Point"}
}