{
  "type": "Feature",
  "properties": {
    "iso:country":"US",
    "sg:address":"1005 N Lincoln St",
    "sg:city":"Knoxville",
    "sg:classifiers":[
        {
            "category":"Organizations",
            "subcategory":"Religious Organization",
            "type":"Services"
        }
    ],
    "sg:phone":"+1 641 828 7603",
    "sg:postcode":"50138",
    "sg:province":"IA",
    "sg:tags":[
        "church"
    ],
    "sg:website":"www.celebratechurch.com",
    "wof:name":"Celebrate Community Church",
    "wof:placetype":"venue"
},
  "geometry": {"coordinates":[-93.109419,41.326757],"type":"Point"}
}