{
  "type": "Feature",
  "properties": {
    "iso:country":"US",
    "sg:address":"1309 Industrial Blvd",
    "sg:city":"Marshalltown",
    "sg:classifiers":[
        {
            "category":"Wholesale",
            "subcategory":"Hardware",
            "type":"Manufacturing & Wholesale Goods"
        }
    ],
    "sg:phone":"+1 641 752 9674",
    "sg:postcode":"50158",
    "sg:province":"IA",
    "sg:tags":[
        "fastener"
    ],
    "wof:name":"Fastenal Co",
    "wof:placetype":"venue"
},
  "geometry": {"coordinates":[-92.89081299999999,42.035522],"type":"Point"}
}