{
  "type": "Feature",
  "properties": {
    "addr:full":"3417 260th St Hull IA 51239",
    "addr:housenumber":"3417",
    "addr:postcode":"51239",
    "addr:street":"260Th St",
    "iso:country":"US",
    "sg:address":"3417 260th St",
    "sg:city":"Hull",
    "sg:classifiers":[
        {
            "category":"Farming",
            "subcategory":"Livestock Farm",
            "type":"Manufacturing & Wholesale Goods"
        }
    ],
    "sg:phone":"+1 712 439 2805",
    "sg:postcode":"51239",
    "sg:province":"IA",
    "sg:tags":[
        "beef",
        "feedlot",
        "cattle"
    ],
    "wof:name":"Kevin Roozing",
    "wof:placetype":"venue"
},
  "geometry": {"coordinates":[-96.115668,43.271747],"type":"Point"}
}