{
  "type": "Feature",
  "properties": {
    "addr:full":"1520 Whitters Way NW Cedar Rapids IA 52405",
    "addr:housenumber":"1520",
    "addr:postcode":"52405",
    "addr:street":"Whitters Way Nw",
    "iso:country":"US",
    "sg:address":"1520 Whitters Way NW",
    "sg:city":"Cedar Rapids",
    "sg:classifiers":[
        {
            "category":"Building & Trades",
            "subcategory":"Construction",
            "type":"Services"
        }
    ],
    "sg:phone":"+1 319 363 2750",
    "sg:postcode":"52405",
    "sg:province":"IA",
    "sg:tags":[
        "house"
    ],
    "wof:name":"Whitters Home Builders Inc",
    "wof:placetype":"venue"
},
  "geometry": {"coordinates":[-91.696192,41.994259],"type":"Point"}
}