{
  "type": "Feature",
  "properties": {
    "iso:country":"US",
    "sg:address":"4110 Hickory Ave",
    "sg:city":"Sioux Center",
    "sg:classifiers":[
        {
            "category":"Manufacturing",
            "subcategory":"Building Materials",
            "type":"Manufacturing & Wholesale Goods"
        },
        {
            "category":"Building & Trades",
            "subcategory":"Construction",
            "type":"Services"
        }
    ],
    "sg:phone":"+1 712 722 1775",
    "sg:postcode":"51250",
    "sg:province":"IA",
    "sg:tags":[
        "carpentry",
        "contractor",
        "cabinet"
    ],
    "wof:name":"Ron's Cabinet Shop",
    "wof:placetype":"venue"
},
  "geometry": {"coordinates":[-96.135633,43.05381],"type":"Point"}
}