{
  "type": "Feature",
  "properties": {
    "iso:country":"US",
    "sg:address":"2314 SE 78th St",
    "sg:city":"Runnells",
    "sg:classifiers":[
        {
            "category":"Shopping",
            "subcategory":"Crafts & Fabrics",
            "type":"Retail Goods"
        }
    ],
    "sg:phone":"+1 515 265 8031",
    "sg:postcode":"50237",
    "sg:province":"IA",
    "sg:tags":[
        "sewing"
    ],
    "wof:name":"Sew The Word",
    "wof:placetype":"venue"
},
  "geometry": {"coordinates":[-93.44799500000001,41.562996],"type":"Point"}
}