{
  "type": "Feature",
  "properties": {
    "iso:country":"US",
    "sg:address":"905 E Laurel St",
    "sg:city":"Davenport",
    "sg:classifiers":[
        {
            "category":"Building & Trades",
            "subcategory":"Cleaning & Sanitation",
            "type":"Services"
        }
    ],
    "sg:phone":"+1 563 324 4718",
    "sg:postcode":"52803",
    "sg:province":"IA",
    "sg:tags":[
        "house"
    ],
    "wof:name":"Good Help",
    "wof:placetype":"venue"
},
  "geometry": {"coordinates":[-90.56162399999999,41.53999],"type":"Point"}
}