{
  "type": "Feature",
  "properties": {
    "addr:full":"2186 Illinois Dr Pella IA 50219",
    "addr:housenumber":"2186",
    "addr:postcode":"50219",
    "addr:street":"Illinois Dr",
    "iso:country":"US",
    "sg:address":"2186 Illinois Dr",
    "sg:city":"Pella",
    "sg:classifiers":[
        {
            "category":"Wholesale",
            "subcategory":"Auto Parts",
            "type":"Manufacturing & Wholesale Goods"
        }
    ],
    "sg:phone":"+1 641 628 3651",
    "sg:postcode":"50219",
    "sg:province":"IA",
    "sg:tags":[
        "tire"
    ],
    "wof:name":"K & B Tire LTD",
    "wof:placetype":"venue"
},
  "geometry": {"coordinates":[-92.92414100000001,41.378096],"type":"Point"}
}