{
  "type": "Feature",
  "properties": {
    "iso:country":"US",
    "sg:address":"419 N Main St",
    "sg:city":"Dundee",
    "sg:classifiers":[
        {
            "category":"Retail",
            "subcategory":"Auto Repair",
            "type":"Services"
        }
    ],
    "sg:phone":"+1 563 924 2188",
    "sg:postcode":"52038",
    "sg:province":"IA",
    "sg:tags":[
        "body",
        "automobile",
        "painting"
    ],
    "wof:name":"Conrad's Auto",
    "wof:placetype":"venue"
},
  "geometry": {"coordinates":[-91.54568999999999,42.581805],"type":"Point"}
}