{
  "type": "Feature",
  "properties": {
    "addr:full":"2508 Union Rd Cedar Falls IA 50613",
    "addr:housenumber":"2508",
    "addr:postcode":"50613",
    "addr:street":"Union Rd",
    "iso:country":"US",
    "sg:address":"2508 Union Rd",
    "sg:city":"Cedar Falls",
    "sg:classifiers":[
        {
            "category":"Real Estate",
            "subcategory":"Developer",
            "type":"Services"
        }
    ],
    "sg:phone":"+1 319 266 6093",
    "sg:postcode":"50613",
    "sg:province":"IA",
    "sg:tags":[
        "mobile",
        "home"
    ],
    "wof:name":"Cedar Falls Mobile Home Vlg",
    "wof:placetype":"venue"
},
  "geometry": {"coordinates":[-92.494962,42.516952],"type":"Point"}
}