{
  "type": "Feature",
  "properties": {
    "addr:full":"115 2nd St Lake View IA 51450",
    "addr:housenumber":"115",
    "addr:postcode":"51450",
    "addr:street":"2Nd St",
    "iso:country":"US",
    "sg:address":"115 2nd St",
    "sg:city":"Lake View",
    "sg:classifiers":[
        {
            "category":"Organizations",
            "subcategory":"Religious Organization",
            "type":"Services"
        }
    ],
    "sg:phone":"+1 712 657 3324",
    "sg:postcode":"51450",
    "sg:province":"IA",
    "sg:tags":[
        "church"
    ],
    "wof:name":"Lutheran Church",
    "wof:placetype":"venue"
},
  "geometry": {"coordinates":[-95.02151000000001,42.253195],"type":"Point"}
}