{
  "type": "Feature",
  "properties": {
    "addr:full":"810 31st Ave SW Cedar Rapids IA 52404",
    "addr:housenumber":"810",
    "addr:postcode":"52404",
    "addr:street":"31St Ave Sw",
    "iso:country":"US",
    "sg:address":"810 31st Ave SW",
    "sg:city":"Cedar Rapids",
    "sg:classifiers":[
        {
            "category":"Wholesale",
            "subcategory":"Auto Parts",
            "type":"Manufacturing & Wholesale Goods"
        }
    ],
    "sg:phone":"+1 319 366 8705",
    "sg:postcode":"52404",
    "sg:province":"IA",
    "sg:tags":[
        "body",
        "automobile",
        "shop"
    ],
    "wof:name":"Car Colors Inc",
    "wof:placetype":"venue"
},
  "geometry": {"coordinates":[-91.678918,41.947125],"type":"Point"}
}