{
  "type": "Feature",
  "properties": {
    "addr:full":"600 Walnut St Atlantic IA 50022",
    "addr:housenumber":"600",
    "addr:postcode":"50022",
    "addr:street":"Walnut St",
    "iso:country":"US",
    "sg:address":"600 Walnut St",
    "sg:city":"Atlantic",
    "sg:classifiers":[
        {
            "category":"Insurance",
            "subcategory":"Insurance Agent",
            "type":"Services"
        }
    ],
    "sg:phone":"+1 712 243 4392",
    "sg:postcode":"50022",
    "sg:province":"IA",
    "sg:website":"www.partnersins.com",
    "wof:name":"Partners Insurance Inc",
    "wof:placetype":"venue"
},
  "geometry": {"coordinates":[-95.011602,41.404983],"type":"Point"}
}