{
  "type": "Feature",
  "properties": {
    "iso:country":"US",
    "sg:address":"1701 Summit St",
    "sg:city":"Sioux City",
    "sg:classifiers":[
        {
            "category":"Organizations",
            "subcategory":"Religious Organization",
            "type":"Services"
        }
    ],
    "sg:phone":"+1 712 258 6446",
    "sg:postcode":"51105",
    "sg:province":"IA",
    "sg:tags":[
        "monastery",
        "convent"
    ],
    "wof:name":"Sisters Of St Francis",
    "wof:placetype":"venue"
},
  "geometry": {"coordinates":[-96.409533,42.509166],"type":"Point"}
}