{
  "type": "Feature",
  "properties": {
    "addr:full":"706 Garden Rd Ames IA 50010",
    "addr:housenumber":"706",
    "addr:postcode":"50010",
    "addr:street":"Garden Rd",
    "iso:country":"US",
    "sg:address":"706 Garden Rd",
    "sg:city":"Ames",
    "sg:classifiers":[
        {
            "category":"Retail",
            "subcategory":"Auto Repair",
            "type":"Services"
        }
    ],
    "sg:phone":"+1 515 233 4641",
    "sg:postcode":"50010",
    "sg:province":"IA",
    "sg:tags":[
        "general"
    ],
    "wof:name":"Greenawalt Enterprises",
    "wof:placetype":"venue"
},
  "geometry": {"coordinates":[-93.60279,41.988196],"type":"Point"}
}