{
  "type": "Feature",
  "properties": {
    "addr:full":"2172 280th St Early IA 50535",
    "addr:housenumber":"2172",
    "addr:postcode":"50535",
    "addr:street":"280Th St",
    "iso:country":"US",
    "sg:address":"2172 280th St",
    "sg:city":"Early",
    "sg:phone":"+1 712 273 5137",
    "sg:postcode":"50535",
    "sg:province":"IA",
    "sg:tags":[
        "farm",
        "corn",
        "soybean"
    ],
    "wof:name":"Mark Weber",
    "wof:placetype":"venue"
},
  "geometry": {"coordinates":[-95.153761,42.385774],"type":"Point"}
}