{
  "type": "Feature",
  "properties": {
    "iso:country":"US",
    "sg:address":"2001 Fairview Dr",
    "sg:city":"Cedar Falls",
    "sg:classifiers":[
        {
            "category":"Freight",
            "type":"Transportation"
        }
    ],
    "sg:phone":"+1 319 266 8767",
    "sg:postcode":"50613",
    "sg:province":"IA",
    "sg:tags":[
        "warehouse"
    ],
    "wof:name":"Cedar Falls Schools Warehouse",
    "wof:placetype":"venue"
},
  "geometry": {"coordinates":[-92.438158,42.517745],"type":"Point"}
}