{
  "type": "Feature",
  "properties": {
    "addr:full":"3030 100th St Urbandale IA 50322",
    "addr:housenumber":"3030",
    "addr:postcode":"50322",
    "addr:street":"100Th St",
    "iso:country":"US",
    "sg:address":"3030 100th St",
    "sg:city":"Urbandale",
    "sg:classifiers":[
        {
            "category":"Home & Garden",
            "subcategory":"Furniture",
            "type":"Retail Goods"
        }
    ],
    "sg:phone":"+1 515 270 1133",
    "sg:postcode":"50322",
    "sg:province":"IA",
    "wof:name":"Amish Haus At Wagschal",
    "wof:placetype":"venue"
},
  "geometry": {"coordinates":[-93.75589600000001,41.623295],"type":"Point"}
}