{
  "type": "Feature",
  "properties": {
    "addr:full":"101 14th St SE Orange City IA 51041",
    "addr:housenumber":"101",
    "addr:postcode":"51041",
    "addr:street":"14Th St Se",
    "iso:country":"US",
    "sg:address":"101 14th St SE",
    "sg:city":"Orange City",
    "sg:classifiers":[
        {
            "category":"Personal",
            "type":"Services"
        },
        {
            "category":"Wholesale",
            "subcategory":"Meat",
            "type":"Manufacturing & Wholesale Goods"
        }
    ],
    "sg:phone":"+1 712 737 4829",
    "sg:postcode":"51041",
    "sg:province":"IA",
    "sg:tags":[
        "poultry",
        "packer",
        "processing"
    ],
    "wof:name":"Advance Brands LLC",
    "wof:placetype":"venue"
},
  "geometry": {"coordinates":[-96.059556,42.989975],"type":"Point"}
}