{
  "type": "Feature",
  "properties": {
    "iso:country":"US",
    "sg:address":"1010 Oregon St",
    "sg:city":"Muscatine",
    "sg:classifiers":[
        {
            "category":"Freight",
            "type":"Transportation"
        }
    ],
    "sg:phone":"+1 563 262 5484",
    "sg:postcode":"52761",
    "sg:province":"IA",
    "sg:tags":[
        "operator",
        "local",
        "trucking"
    ],
    "wof:name":"Lane Trucking",
    "wof:placetype":"venue"
},
  "geometry": {"coordinates":[-91.063153,41.405665],"type":"Point"}
}