{
  "type": "Feature",
  "properties": {
    "iso:country":"US",
    "sg:address":"1631 Lincoln Way",
    "sg:city":"Clinton",
    "sg:classifiers":[
        {
            "category":"Health Services",
            "subcategory":"Chiropractor",
            "type":"Services"
        }
    ],
    "sg:phone":"+1 563 242 8090",
    "sg:postcode":"52732",
    "sg:province":"IA",
    "wof:name":"Riverbend Chiropractic & Rehab",
    "wof:placetype":"venue"
},
  "geometry": {"coordinates":[-90.22445399999999,41.816491],"type":"Point"}
}