{
  "type": "Feature",
  "properties": {
    "addr:full":"717 E Broadway Council Bluffs IA 51503",
    "addr:housenumber":"717",
    "addr:postcode":"51503",
    "addr:street":"E Broadway",
    "iso:country":"US",
    "sg:address":"717 E Broadway",
    "sg:city":"Council Bluffs",
    "sg:classifiers":[
        {
            "category":"Autos & Motor Vehicles",
            "subcategory":"Automobile Sales",
            "type":"Retail Goods"
        }
    ],
    "sg:phone":"+1 712 256 4504",
    "sg:postcode":"51503",
    "sg:province":"IA",
    "sg:tags":[
        "car",
        "dealer"
    ],
    "wof:name":"Hand Pick Auto",
    "wof:placetype":"venue"
},
  "geometry": {"coordinates":[-95.83817500000001,41.267422],"type":"Point"}
}