{
  "type": "Feature",
  "properties": {
    "iso:country":"US",
    "sg:address":"810 Juhl Ave",
    "sg:city":"Waverly",
    "sg:classifiers":[
        {
            "category":"Retail",
            "subcategory":"Repair Shop",
            "type":"Services"
        }
    ],
    "sg:phone":"+1 319 352 6500",
    "sg:postcode":"50677",
    "sg:province":"IA",
    "wof:name":"Gilbert Creations",
    "wof:placetype":"venue"
},
  "geometry": {"coordinates":[-92.481731,42.735634],"type":"Point"}
}