{
  "type": "Feature",
  "properties": {
    "iso:country":"US",
    "sg:address":"4607 580th Ave",
    "sg:city":"West Bend",
    "sg:phone":"+1 515 887 2555",
    "sg:postcode":"50597",
    "sg:province":"IA",
    "sg:tags":[
        "farm",
        "corn",
        "soybean"
    ],
    "wof:name":"Myra Kuntz",
    "wof:placetype":"venue"
},
  "geometry": {"coordinates":[-94.44287799999999,42.979586],"type":"Point"}
}