{
  "type": "Feature",
  "properties": {
    "addr:full":"61 S Front St Lansing IA 52151",
    "addr:housenumber":"61",
    "addr:postcode":"52151",
    "addr:street":"S Front St",
    "iso:country":"US",
    "sg:address":"61 S Front St",
    "sg:city":"Lansing",
    "sg:classifiers":[
        {
            "category":"Museum",
            "type":"Entertainment"
        }
    ],
    "sg:phone":"+1 563 538 4641",
    "sg:postcode":"52151",
    "sg:province":"IA",
    "sg:website":"www.lansingiowa.org",
    "wof:name":"Museum Of River History",
    "wof:placetype":"venue"
},
  "geometry": {"coordinates":[-91.214141,43.361389],"type":"Point"}
}