{
  "type": "Feature",
  "properties": {
    "iso:country":"US",
    "sg:address":"22638 Old Hwy 169",
    "sg:city":"Fort Dodge",
    "sg:classifiers":[
        {
            "category":"Building & Trades",
            "subcategory":"Construction",
            "type":"Services"
        }
    ],
    "sg:phone":"+1 515 955 8727",
    "sg:postcode":"50501",
    "sg:province":"IA",
    "sg:tags":[
        "general",
        "contractor"
    ],
    "wof:name":"Double C Builders",
    "wof:placetype":"venue"
},
  "geometry": {"coordinates":[-94.205461,42.466681],"type":"Point"}
}