{
  "type": "Feature",
  "properties": {
    "iso:country":"US",
    "sg:address":"9200 Hickman Rd",
    "sg:city":"Clive",
    "sg:classifiers":[
        {
            "category":"Building & Trades",
            "subcategory":"Landscaping Services",
            "type":"Services"
        }
    ],
    "sg:phone":"+1 515 270 0558",
    "sg:postcode":"50325",
    "sg:province":"IA",
    "sg:tags":[
        "lawn",
        "apartment",
        "management",
        "cleaning",
        "maintenance",
        "care"
    ],
    "wof:name":"Gentry Management Services",
    "wof:placetype":"venue"
},
  "geometry": {"coordinates":[-93.74196499999999,41.614794],"type":"Point"}
}