{
  "type": "Feature",
  "properties": {
    "iso:country":"US",
    "sg:address":"2508 W Broadway",
    "sg:city":"Council Bluffs",
    "sg:classifiers":[
        {
            "category":"Shopping",
            "subcategory":"Pharmacy",
            "type":"Retail Goods"
        }
    ],
    "sg:phone":"+1 712 328 2266",
    "sg:postcode":"51501",
    "sg:province":"IA",
    "sg:tags":[
        "drugstore"
    ],
    "sg:website":"www.walgreens.com",
    "wof:name":"Walgreen Drug Stores",
    "wof:placetype":"venue"
},
  "geometry": {"coordinates":[-95.882401,41.2621],"type":"Point"}
}