{
  "type": "Feature",
  "properties": {
    "iso:country":"US",
    "sg:address":"5745 NE 17th St",
    "sg:city":"Des Moines",
    "sg:classifiers":[
        {
            "category":"Wholesale",
            "subcategory":"Scrap",
            "type":"Manufacturing & Wholesale Goods"
        }
    ],
    "sg:phone":"+1 515 263 3707",
    "sg:postcode":"50313",
    "sg:province":"IA",
    "sg:tags":[
        "recycling",
        "center"
    ],
    "wof:name":"A-Tec Recycling Inc",
    "wof:placetype":"venue"
},
  "geometry": {"coordinates":[-93.59263900000001,41.665855],"type":"Point"}
}