{
  "type": "Feature",
  "properties": {
    "iso:country":"US",
    "sg:address":"504 1st Ave S",
    "sg:city":"Altoona",
    "sg:classifiers":[
        {
            "category":"Shopping",
            "subcategory":"Computers & Home Electronics",
            "type":"Retail Goods"
        }
    ],
    "sg:phone":"+1 515 957 9067",
    "sg:postcode":"50009",
    "sg:province":"IA",
    "sg:tags":[
        "software"
    ],
    "sg:website":"www.hvacestimator.com",
    "wof:name":"HVACESTIMATOR.COM",
    "wof:placetype":"venue"
},
  "geometry": {"coordinates":[-93.464528,41.647497],"type":"Point"}
}