{
  "type": "Feature",
  "properties": {
    "iso:country":"US",
    "sg:address":"17557 Lourdes Rd",
    "sg:city":"Elma",
    "sg:classifiers":[
        {
            "category":"Retail",
            "subcategory":"Auto Repair",
            "type":"Services"
        }
    ],
    "sg:phone":"+1 641 393 2263",
    "sg:postcode":"50628",
    "sg:province":"IA",
    "sg:tags":[
        "repairing",
        "automobile"
    ],
    "wof:name":"Lourdes Service Station",
    "wof:placetype":"venue"
},
  "geometry": {"coordinates":[-92.298863,43.261615],"type":"Point"}
}