{
  "type": "Feature",
  "properties": {
    "addr:full":"18 E Army Post Rd Des Moines IA 50315",
    "addr:housenumber":"18",
    "addr:postcode":"50315",
    "addr:street":"E Army Post Rd Des",
    "iso:country":"US",
    "sg:address":"18 E Army Post Rd",
    "sg:city":"Des Moines",
    "sg:classifiers":[
        {
            "category":"Personal",
            "type":"Services"
        }
    ],
    "sg:phone":"+1 515 953 5949",
    "sg:postcode":"50315",
    "sg:province":"IA",
    "sg:tags":[
        "therapist",
        "massage"
    ],
    "wof:name":"Overton Therapeutic Massage",
    "wof:placetype":"venue"
},
  "geometry": {"coordinates":[-93.613778,41.526487],"type":"Point"}
}