{
  "type": "Feature",
  "properties": {
    "iso:country":"US",
    "sg:address":"100 1st St SE",
    "sg:city":"Oelwein",
    "sg:classifiers":[
        {
            "category":"Home & Garden",
            "subcategory":"Hardware",
            "type":"Retail Goods"
        }
    ],
    "sg:phone":"+1 319 283 5361",
    "sg:postcode":"50662",
    "sg:province":"IA",
    "wof:name":"Meyer & Lincoln True Value",
    "wof:placetype":"venue"
},
  "geometry": {"coordinates":[-91.91197099999999,42.67705],"type":"Point"}
}