{
  "type": "Feature",
  "properties": {
    "iso:country":"US",
    "sg:address":"913 Park St",
    "sg:city":"Sheldon",
    "sg:classifiers":[
        {
            "category":"Shopping",
            "type":"Retail Goods"
        }
    ],
    "sg:phone":"+1 712 324 4575",
    "sg:postcode":"51201",
    "sg:province":"IA",
    "sg:tags":[
        "equipment",
        "care",
        "health",
        "home"
    ],
    "sg:website":"www.wheelchairdynamics.com",
    "wof:name":"Wheelchair Dynamics Inc",
    "wof:placetype":"venue"
},
  "geometry": {"coordinates":[-95.843149,43.186092],"type":"Point"}
}