{
  "type": "Feature",
  "properties": {
    "iso:country":"US",
    "sg:address":"109 Elm Ave",
    "sg:city":"New Hampton",
    "sg:classifiers":[
        {
            "category":"Retail",
            "subcategory":"Repair Shop",
            "type":"Services"
        }
    ],
    "sg:phone":"+1 641 330 4980",
    "sg:postcode":"50659",
    "sg:province":"IA",
    "wof:name":"Daves Locksmith Service",
    "wof:placetype":"venue"
},
  "geometry": {"coordinates":[-92.321572,43.061009],"type":"Point"}
}