{
  "type": "Feature",
  "properties": {
    "addr:full":"111 S 1st Ave Marshalltown IA 50158",
    "addr:housenumber":"111",
    "addr:postcode":"50158",
    "addr:street":"S 1St Ave",
    "iso:country":"US",
    "sg:address":"111 S 1st Ave",
    "sg:city":"Marshalltown",
    "sg:classifiers":[
        {
            "category":"Building & Trades",
            "subcategory":"Electrical",
            "type":"Services"
        }
    ],
    "sg:phone":"+1 641 753 0832",
    "sg:postcode":"50158",
    "sg:province":"IA",
    "sg:tags":[
        "electric",
        "contractor"
    ],
    "wof:name":"M & N Construction & Electric",
    "wof:placetype":"venue"
},
  "geometry": {"coordinates":[-92.911378,42.04779],"type":"Point"}
}