{
  "type": "Feature",
  "properties": {
    "iso:country":"US",
    "sg:address":"228 N Pine St",
    "sg:city":"Creston",
    "sg:classifiers":[
        {
            "category":"Professional",
            "subcategory":"Business Services",
            "type":"Services"
        }
    ],
    "sg:phone":"+1 641 782 7329",
    "sg:postcode":"50801",
    "sg:province":"IA",
    "sg:tags":[
        "arbitration"
    ],
    "wof:name":"Iowa Mediation Svc",
    "wof:placetype":"venue"
},
  "geometry": {"coordinates":[-94.36156,41.059362],"type":"Point"}
}