{
  "type": "Feature",
  "properties": {
    "iso:country":"US",
    "sg:address":"301 Parkway St",
    "sg:city":"Olin",
    "sg:classifiers":[
        {
            "category":"Education",
            "subcategory":"Library",
            "type":"Public Place"
        }
    ],
    "sg:phone":"+1 319 484 2944",
    "sg:postcode":"52320",
    "sg:province":"IA",
    "wof:name":"Olin Public Library",
    "wof:placetype":"venue"
},
  "geometry": {"coordinates":[-91.137705,41.993719],"type":"Point"}
}