{
  "type": "Feature",
  "properties": {
    "iso:country":"US",
    "sg:address":"102 W Skillet Ave",
    "sg:city":"Dayton",
    "sg:classifiers":[
        {
            "category":"Professional",
            "subcategory":"Lawyer & Legal Services",
            "type":"Services"
        }
    ],
    "sg:phone":"+1 515 547 2273",
    "sg:postcode":"50530",
    "sg:province":"IA",
    "sg:tags":[
        "attorney"
    ],
    "wof:name":"Leonard R Holland Law Office",
    "wof:placetype":"venue"
},
  "geometry": {"coordinates":[-94.07101900000001,42.261611],"type":"Point"}
}