{
  "type": "Feature",
  "properties": {
    "iso:country":"US",
    "sg:address":"3930 Langley Ave",
    "sg:city":"Lake City",
    "sg:phone":"+1 712 464 8044",
    "sg:postcode":"51449",
    "sg:province":"IA",
    "sg:tags":[
        "farm",
        "corn",
        "crop"
    ],
    "wof:name":"Iler Spraying",
    "wof:placetype":"venue"
},
  "geometry": {"coordinates":[-94.68714199999999,42.219508],"type":"Point"}
}