{
  "type": "Feature",
  "properties": {
    "addr:full":"1717 Kentucky Ave Rutland IA 50548",
    "addr:housenumber":"1717",
    "addr:postcode":"50548",
    "addr:street":"Kentucky Ave",
    "iso:country":"US",
    "sg:address":"1717 Kentucky Ave",
    "sg:city":"Rutland",
    "sg:phone":"+1 515 332 3389",
    "sg:postcode":"50548",
    "sg:province":"IA",
    "sg:tags":[
        "farm",
        "grain",
        "cash"
    ],
    "wof:name":"Clifford Erickson",
    "wof:placetype":"venue"
},
  "geometry": {"coordinates":[-94.247294,42.801624],"type":"Point"}
}