{
  "type": "Feature",
  "properties": {
    "iso:country":"US",
    "sg:address":"105 Main St N",
    "sg:city":"Marble Rock",
    "sg:classifiers":[
        {
            "category":"Education",
            "subcategory":"Library",
            "type":"Public Place"
        }
    ],
    "sg:phone":"+1 641 315 4480",
    "sg:postcode":"50653",
    "sg:province":"IA",
    "wof:name":"Marble Rock Public Library",
    "wof:placetype":"venue"
},
  "geometry": {"coordinates":[-92.868424,42.96594],"type":"Point"}
}