{
  "type": "Feature",
  "properties": {
    "iso:country":"US",
    "sg:address":"16587 Hwy 60",
    "sg:city":"Le Mars",
    "sg:classifiers":[
        {
            "category":"Autos & Motor Vehicles",
            "subcategory":"Automobile Sales",
            "type":"Retail Goods"
        }
    ],
    "sg:phone":"+1 712 546 8403",
    "sg:postcode":"51031",
    "sg:province":"IA",
    "sg:tags":[
        "performance",
        "race",
        "dealer"
    ],
    "wof:name":"Plain Vanilla Racing Inc",
    "wof:placetype":"venue"
},
  "geometry": {"coordinates":[-96.174273,42.809213],"type":"Point"}
}