{
  "type": "Feature",
  "properties": {
    "iso:country":"US",
    "sg:address":"812 Iowa Ave",
    "sg:city":"Onawa",
    "sg:classifiers":[
        {
            "category":"Home & Garden",
            "subcategory":"Furniture",
            "type":"Retail Goods"
        }
    ],
    "sg:phone":"+1 712 423 2821",
    "sg:postcode":"51040",
    "sg:province":"IA",
    "wof:name":"Virg's Furniture",
    "wof:placetype":"venue"
},
  "geometry": {"coordinates":[-96.095771,42.026775],"type":"Point"}
}