{
  "type": "Feature",
  "properties": {
    "iso:country":"US",
    "sg:address":"105 W 1st St",
    "sg:city":"Sumner",
    "sg:classifiers":[
        {
            "category":"Shopping",
            "subcategory":"Clothing, Apparel, & Fashions",
            "type":"Retail Goods"
        }
    ],
    "sg:phone":"+1 563 578 3235",
    "sg:postcode":"50674",
    "sg:province":"IA",
    "sg:tags":[
        "infant",
        "wear"
    ],
    "wof:name":"Kid's N Kompany",
    "wof:placetype":"venue"
},
  "geometry": {"coordinates":[-92.098983,42.847379],"type":"Point"}
}