{
  "type": "Feature",
  "properties": {
    "addr:full":"118 S Clinton St Iowa City IA 52240",
    "addr:housenumber":"118",
    "addr:postcode":"52240",
    "addr:street":"S Clinton St",
    "iso:country":"US",
    "sg:address":"118 S Clinton St",
    "sg:city":"Iowa City",
    "sg:classifiers":[
        {
            "category":"Professional",
            "subcategory":"Accounting & Tax Preparation",
            "type":"Services"
        }
    ],
    "sg:phone":"+1 319 354 3000",
    "sg:postcode":"52240",
    "sg:province":"IA",
    "sg:tags":[
        "accountant"
    ],
    "sg:website":"www.cliftoncpa.com",
    "wof:name":"Clifton Gunderson & Co",
    "wof:placetype":"venue"
},
  "geometry": {"coordinates":[-91.534554,41.659069],"type":"Point"}
}