{
  "type": "Feature",
  "properties": {
    "iso:country":"US",
    "sg:address":"702 S 2nd St",
    "sg:city":"Clinton",
    "sg:classifiers":[
        {
            "category":"Bars & Pubs",
            "type":"Food & Drink"
        }
    ],
    "sg:phone":"+1 563 242 0779",
    "sg:postcode":"52732",
    "sg:province":"IA",
    "wof:name":"Mac's Pub",
    "wof:placetype":"venue"
},
  "geometry": {"coordinates":[-90.18830199999999,41.838952],"type":"Point"}
}