{
  "type": "Feature",
  "properties": {
    "addr:full":"211 3rd Ave NE Titonka IA 50480",
    "addr:housenumber":"211",
    "addr:postcode":"50480",
    "addr:street":"3Rd Ave Ne",
    "iso:country":"US",
    "sg:address":"211 3rd Ave NE",
    "sg:city":"Titonka",
    "sg:classifiers":[
        {
            "category":"Recreation",
            "type":"Entertainment"
        }
    ],
    "sg:phone":"+1 515 928 2025",
    "sg:postcode":"50480",
    "sg:province":"IA",
    "sg:tags":[
        "pool",
        "swimming"
    ],
    "wof:name":"Titonka Swimming Pool",
    "wof:placetype":"venue"
},
  "geometry": {"coordinates":[-94.03899199999999,43.237837],"type":"Point"}
}