{
  "type": "Feature",
  "properties": {
    "addr:full":"84 W 11th St Waterloo IA 50702",
    "addr:housenumber":"84",
    "addr:postcode":"50702",
    "addr:street":"W 11Th St",
    "iso:country":"US",
    "sg:address":"84 W 11th St",
    "sg:city":"Waterloo",
    "sg:classifiers":[
        {
            "category":"Manufacturing",
            "subcategory":"Tools & Machinery",
            "type":"Manufacturing & Wholesale Goods"
        }
    ],
    "sg:phone":"+1 319 232 7993",
    "sg:postcode":"50702",
    "sg:province":"IA",
    "sg:tags":[
        "pattern",
        "model",
        "maker"
    ],
    "sg:website":"www.midwestpatternco.com",
    "wof:name":"Mid-West Pattern Co",
    "wof:placetype":"venue"
},
  "geometry": {"coordinates":[-92.331057,42.491484],"type":"Point"}
}