{
  "type": "Feature",
  "properties": {
    "iso:country":"US",
    "sg:address":"1535 SE Delaware Ave",
    "sg:city":"Ankeny",
    "sg:classifiers":[
        {
            "category":"Education",
            "subcategory":"College",
            "type":"Public Place"
        }
    ],
    "sg:phone":"+1 515 965 6050",
    "sg:postcode":"50021",
    "sg:province":"IA",
    "sg:tags":[
        "academic",
        "school"
    ],
    "wof:name":"Upper Iowa University",
    "wof:placetype":"venue"
},
  "geometry": {"coordinates":[-93.581091,41.71588],"type":"Point"}
}