{
  "type": "Feature",
  "properties": {
    "iso:country":"US",
    "sg:address":"101 W 76th St",
    "sg:city":"Davenport",
    "sg:classifiers":[
        {
            "category":"Wholesale",
            "subcategory":"Medical Equipment & Supplies",
            "type":"Manufacturing & Wholesale Goods"
        }
    ],
    "sg:phone":"+1 563 391 7200",
    "sg:postcode":"52806",
    "sg:province":"IA",
    "sg:tags":[
        "dental"
    ],
    "wof:name":"Patterson Dental Co",
    "wof:placetype":"venue"
},
  "geometry": {"coordinates":[-90.575334,41.593998],"type":"Point"}
}