{
  "type": "Feature",
  "properties": {
    "iso:country":"US",
    "sg:address":"5440 Corporate Park Dr",
    "sg:city":"Davenport",
    "sg:classifiers":[
        {
            "category":"Manufacturing",
            "subcategory":"Printing",
            "type":"Manufacturing & Wholesale Goods"
        }
    ],
    "sg:phone":"+1 563 359 3696",
    "sg:postcode":"52807",
    "sg:province":"IA",
    "sg:tags":[
        "printer"
    ],
    "sg:website":"www.midlandcorp.com",
    "wof:name":"Midland Information Resources",
    "wof:placetype":"venue"
},
  "geometry": {"coordinates":[-90.518461,41.575427],"type":"Point"}
}