{
  "type": "Feature",
  "properties": {
    "addr:full":"103 North Ave Council Bluffs IA 51503",
    "addr:housenumber":"103",
    "addr:postcode":"51503",
    "addr:street":"North Ave",
    "iso:country":"US",
    "sg:address":"103 North Ave",
    "sg:city":"Council Bluffs",
    "sg:classifiers":[
        {
            "category":"Insurance",
            "subcategory":"Insurance Agent",
            "type":"Services"
        }
    ],
    "sg:phone":"+1 712 328 3975",
    "sg:postcode":"51503",
    "sg:province":"IA",
    "wof:name":"Campbell Insurance Inc",
    "wof:placetype":"venue"
},
  "geometry": {"coordinates":[-95.831052,41.271644],"type":"Point"}
}