{
  "type": "Feature",
  "properties": {
    "addr:full":"613 1st St Grimes IA 50111",
    "addr:housenumber":"613",
    "addr:postcode":"50111",
    "addr:street":"1St St",
    "iso:country":"US",
    "sg:address":"613 1st St",
    "sg:city":"Grimes",
    "sg:classifiers":[
        {
            "category":"Social Services",
            "subcategory":"Child Care",
            "type":"Services"
        }
    ],
    "sg:phone":"+1 515 986 4449",
    "sg:postcode":"50111",
    "sg:province":"IA",
    "sg:tags":[
        "day"
    ],
    "wof:name":"Julie Willemsen",
    "wof:placetype":"venue"
},
  "geometry": {"coordinates":[-93.788374,41.688461],"type":"Point"}
}