{
  "type": "Feature",
  "properties": {
    "addr:full":"2798 360th St Rock Valley IA 51247",
    "addr:housenumber":"2798",
    "addr:postcode":"51247",
    "addr:street":"360Th St",
    "iso:country":"US",
    "sg:address":"2798 360th St",
    "sg:city":"Rock Valley",
    "sg:classifiers":[
        {
            "category":"Building & Trades",
            "subcategory":"Plumbing",
            "type":"Services"
        }
    ],
    "sg:phone":"+1 712 722 2092",
    "sg:postcode":"51247",
    "sg:province":"IA",
    "sg:tags":[
        "plumbing",
        "contractor"
    ],
    "wof:name":"Paul's Plumbing & Heating",
    "wof:placetype":"venue"
},
  "geometry": {"coordinates":[-96.238953,43.12763],"type":"Point"}
}