{
  "type": "Feature",
  "properties": {
    "addr:full":"2911 Kingman Blvd Des Moines IA 50311",
    "addr:housenumber":"2911",
    "addr:postcode":"50311",
    "addr:street":"Kingman Blvd",
    "iso:country":"US",
    "sg:address":"2911 Kingman Blvd",
    "sg:city":"Des Moines",
    "sg:classifiers":[
        {
            "category":"Building & Trades",
            "subcategory":"Construction",
            "type":"Services"
        }
    ],
    "sg:phone":"+1 515 237 8100",
    "sg:postcode":"50311",
    "sg:province":"IA",
    "sg:tags":[
        "house"
    ],
    "wof:name":"Scisco Const",
    "wof:placetype":"venue"
},
  "geometry": {"coordinates":[-93.65925300000001,41.596662],"type":"Point"}
}