{
  "type": "Feature",
  "properties": {
    "iso:country":"US",
    "sg:address":"3030 Corral Ct",
    "sg:city":"Bettendorf",
    "sg:classifiers":[
        {
            "category":"Building & Trades",
            "subcategory":"Construction",
            "type":"Services"
        }
    ],
    "sg:phone":"+1 563 332 2783",
    "sg:postcode":"52722",
    "sg:province":"IA",
    "sg:tags":[
        "masonry",
        "contractor"
    ],
    "wof:name":"Bi State Masonry",
    "wof:placetype":"venue"
},
  "geometry": {"coordinates":[-90.468324,41.553667],"type":"Point"}
}