{
  "type": "Feature",
  "properties": {
    "iso:country":"US",
    "sg:address":"12990 Jewel Ave",
    "sg:city":"Carroll",
    "sg:phone":"+1 712 673 2730",
    "sg:postcode":"51401",
    "sg:province":"IA",
    "sg:tags":[
        "farm",
        "corn"
    ],
    "wof:name":"Robert Wittrock",
    "wof:placetype":"venue"
},
  "geometry": {"coordinates":[-94.907426,42.166013],"type":"Point"}
}