{
  "type": "Feature",
  "properties": {
    "iso:country":"US",
    "sg:address":"1036 Industrial Park Rd",
    "sg:city":"Iowa Falls",
    "sg:classifiers":[
        {
            "category":"Manufacturing",
            "subcategory":"Printing",
            "type":"Manufacturing & Wholesale Goods"
        }
    ],
    "sg:phone":"+1 641 648 5047",
    "sg:postcode":"50126",
    "sg:province":"IA",
    "sg:tags":[
        "printer"
    ],
    "wof:name":"Berry Iowa Corp",
    "wof:placetype":"venue"
},
  "geometry": {"coordinates":[-93.27042899999999,42.51219],"type":"Point"}
}