{
  "type": "Feature",
  "properties": {
    "iso:country":"US",
    "sg:address":"PO Box 1342",
    "sg:city":"Bettendorf",
    "sg:classifiers":[
        {
            "category":"Professional",
            "subcategory":"Employment Agencies",
            "type":"Services"
        }
    ],
    "sg:phone":"+1 563 332 8724",
    "sg:postcode":"52722",
    "sg:province":"IA",
    "wof:name":"K Di",
    "wof:placetype":"venue"
},
  "geometry": {"coordinates":[-90.49099699999999,41.551201],"type":"Point"}
}