{
  "type": "Feature",
  "properties": {
    "addr:full":"50 W 13th St Dubuque IA 52001",
    "addr:housenumber":"50",
    "addr:postcode":"52001",
    "addr:street":"W 13Th St",
    "iso:country":"US",
    "sg:address":"50 W 13th St",
    "sg:city":"Dubuque",
    "sg:classifiers":[
        {
            "category":"Government",
            "subcategory":"Office",
            "type":"Public Place"
        }
    ],
    "sg:phone":"+1 563 589 4150",
    "sg:postcode":"52001",
    "sg:province":"IA",
    "sg:tags":[
        "village"
    ],
    "wof:name":"Dubuque Electrical Permits",
    "wof:placetype":"venue"
},
  "geometry": {"coordinates":[-90.667845,42.505319],"type":"Point"}
}