{
  "type": "Feature",
  "properties": {
    "addr:full":"309 1st St E Independence IA 50644",
    "addr:housenumber":"309",
    "addr:postcode":"50644",
    "addr:street":"1St St E",
    "iso:country":"US",
    "sg:address":"309 1st St E",
    "sg:city":"Independence",
    "sg:classifiers":[
        {
            "category":"Social Services",
            "type":"Services"
        }
    ],
    "sg:phone":"+1 319 334 7146",
    "sg:postcode":"50644",
    "sg:province":"IA",
    "sg:tags":[
        "organization",
        "welfare"
    ],
    "wof:name":"Crisis Child Care Svc",
    "wof:placetype":"venue"
},
  "geometry": {"coordinates":[-91.891671,42.468643],"type":"Point"}
}