{
  "type": "Feature",
  "properties": {
    "addr:full":"3886 US Hwy 61 Blue Grass IA 52726",
    "addr:housenumber":"3886",
    "addr:postcode":"52726",
    "addr:street":"Us Hwy 61",
    "iso:country":"US",
    "sg:address":"3886 US Hwy 61",
    "sg:city":"Blue Grass",
    "sg:classifiers":[
        {
            "category":"Professional",
            "subcategory":"Business Services",
            "type":"Services"
        }
    ],
    "sg:phone":"+1 563 381 2645",
    "sg:postcode":"52726",
    "sg:province":"IA",
    "sg:tags":[
        "auctioneer"
    ],
    "wof:name":"Woods Auction Svc",
    "wof:placetype":"venue"
},
  "geometry": {"coordinates":[-90.80719999999999,41.513103],"type":"Point"}
}