{
  "type": "Feature",
  "properties": {
    "iso:country":"US",
    "sg:address":"9150 NE 94th Ave",
    "sg:city":"Bondurant",
    "sg:classifiers":[
        {
            "category":"Building & Trades",
            "subcategory":"Electrical",
            "type":"Services"
        }
    ],
    "sg:phone":"+1 515 967 8877",
    "sg:postcode":"50035",
    "sg:province":"IA",
    "sg:tags":[
        "electrician"
    ],
    "sg:website":"http://www.zipweb.com/?businessName=StewartElectricIncorporated/",
    "wof:name":"Stewart Electric Inc",
    "wof:placetype":"venue"
},
  "geometry": {"coordinates":[-93.417306,41.731839],"type":"Point"}
}