{
  "type": "Feature",
  "properties": {
    "addr:full":"211 Commercial St Ottumwa IA 52586",
    "addr:housenumber":"211",
    "addr:postcode":"52586",
    "addr:street":"Commercial St",
    "iso:country":"US",
    "sg:address":"211 Commercial St",
    "sg:city":"Ottumwa",
    "sg:classifiers":[
        {
            "category":"Personal",
            "subcategory":"Beauty Salon",
            "type":"Services"
        }
    ],
    "sg:phone":"+1 641 682 3900",
    "sg:postcode":"52586",
    "sg:province":"IA",
    "sg:tags":[
        "shop",
        "barber"
    ],
    "wof:name":"Razors Edge",
    "wof:placetype":"venue"
},
  "geometry": {"coordinates":[-92.460309,41.321479],"type":"Point"}
}