{
  "type": "Feature",
  "properties": {
    "addr:full":"3228 W Broadway Council Bluffs IA 51501",
    "addr:housenumber":"3228",
    "addr:postcode":"51501",
    "addr:street":"W Broadway",
    "iso:country":"US",
    "sg:address":"3228 W Broadway",
    "sg:city":"Council Bluffs",
    "sg:classifiers":[
        {
            "category":"Building & Trades",
            "subcategory":"Equipment Rental",
            "type":"Services"
        }
    ],
    "sg:phone":"+1 712 322 5300",
    "sg:postcode":"51501",
    "sg:province":"IA",
    "sg:tags":[
        "leasing",
        "furniture"
    ],
    "wof:name":"Ace Rent-To-Own",
    "wof:placetype":"venue"
},
  "geometry": {"coordinates":[-95.89909900000001,41.262011],"type":"Point"}
}