{
  "type": "Feature",
  "properties": {
    "addr:full":"2220 E 17th St Des Moines IA 50316",
    "addr:housenumber":"2220",
    "addr:postcode":"50316",
    "addr:street":"E 17Th St",
    "iso:country":"US",
    "sg:address":"2220 E 17th St",
    "sg:city":"Des Moines",
    "sg:classifiers":[
        {
            "category":"Social Services",
            "type":"Services"
        }
    ],
    "sg:phone":"+1 515 564 0330",
    "sg:postcode":"50316",
    "sg:province":"IA",
    "sg:tags":[
        "organization",
        "welfare"
    ],
    "wof:name":"Food Bank Of Iowa",
    "wof:placetype":"venue"
},
  "geometry": {"coordinates":[-93.591126,41.611982],"type":"Point"}
}