{
  "type": "Feature",
  "properties": {
    "addr:full":"1441 Lincoln Ave Livermore IA 50558",
    "addr:housenumber":"1441",
    "addr:postcode":"50558",
    "addr:street":"Lincoln Ave",
    "iso:country":"US",
    "sg:address":"1441 Lincoln Ave",
    "sg:city":"Livermore",
    "sg:phone":"+1 515 379 1283",
    "sg:postcode":"50558",
    "sg:province":"IA",
    "sg:tags":[
        "farm",
        "corn",
        "soybean"
    ],
    "wof:name":"Don Farmer Rutz",
    "wof:placetype":"venue"
},
  "geometry": {"coordinates":[-94.227282,42.842682],"type":"Point"}
}