{
  "type": "Feature",
  "properties": {
    "iso:country":"US",
    "sg:address":"708 N Church St",
    "sg:city":"Algona",
    "sg:classifiers":[
        {
            "category":"Organizations",
            "subcategory":"Community Association",
            "type":"Services"
        }
    ],
    "sg:phone":"+1 515 295 2830",
    "sg:postcode":"50511",
    "sg:province":"IA",
    "wof:name":"Algona Bulldog Booster Club",
    "wof:placetype":"venue"
},
  "geometry": {"coordinates":[-94.22785,43.075585],"type":"Point"}
}