{
  "type": "Feature",
  "properties": {
    "addr:full":"205 Kaufmann Ave Dubuque IA 52001",
    "addr:housenumber":"205",
    "addr:postcode":"52001",
    "addr:street":"Kaufmann Ave",
    "iso:country":"US",
    "sg:address":"205 Kaufmann Ave",
    "sg:city":"Dubuque",
    "sg:classifiers":[
        {
            "category":"Professional",
            "subcategory":"Business Services",
            "type":"Services"
        }
    ],
    "sg:phone":"+1 563 583 7292",
    "sg:postcode":"52001",
    "sg:province":"IA",
    "sg:tags":[
        "embroidery"
    ],
    "wof:name":"Dpm Hobbies",
    "wof:placetype":"venue"
},
  "geometry": {"coordinates":[-90.674414,42.512901],"type":"Point"}
}