{
  "type": "Feature",
  "properties": {
    "addr:full":"1607 10th St Manson IA 50563",
    "addr:housenumber":"1607",
    "addr:postcode":"50563",
    "addr:street":"10Th St",
    "iso:country":"US",
    "sg:address":"1607 10th St",
    "sg:city":"Manson",
    "sg:classifiers":[
        {
            "category":"Freight",
            "type":"Transportation"
        }
    ],
    "sg:phone":"+1 712 469 2365",
    "sg:postcode":"50563",
    "sg:province":"IA",
    "sg:tags":[
        "trucking"
    ],
    "wof:name":"B & M Transportation",
    "wof:placetype":"venue"
},
  "geometry": {"coordinates":[-94.53667299999999,42.5354],"type":"Point"}
}