{
  "type": "Feature",
  "properties": {
    "addr:full":"120 10th St SW Waverly IA 50677",
    "addr:housenumber":"120",
    "addr:postcode":"50677",
    "addr:street":"10Th St Sw",
    "iso:country":"US",
    "sg:address":"120 10th St SW",
    "sg:city":"Waverly",
    "sg:classifiers":[
        {
            "category":"Retail",
            "subcategory":"Laundry & Dry Cleaning",
            "type":"Services"
        }
    ],
    "sg:phone":"+1 319 352 3847",
    "sg:postcode":"50677",
    "sg:province":"IA",
    "sg:tags":[
        "cleaners"
    ],
    "wof:name":"Press Rite Dry Cleaners",
    "wof:placetype":"venue"
},
  "geometry": {"coordinates":[-92.483104,42.725384],"type":"Point"}
}