{
  "type": "Feature",
  "properties": {
    "addr:full":"4658 86th St Urbandale IA 50322",
    "addr:housenumber":"4658",
    "addr:postcode":"50322",
    "addr:street":"86Th St",
    "iso:country":"US",
    "sg:address":"4658 86th St",
    "sg:city":"Urbandale",
    "sg:classifiers":[
        {
            "category":"Restaurant",
            "type":"Food & Drink"
        }
    ],
    "sg:menulink":"http://www.allmenus.com/ia/webster/69036-breadeaux-pizza/menu/",
    "sg:phone":"+1 515 276 4444",
    "sg:postcode":"50322",
    "sg:province":"IA",
    "sg:tags":[
        "american",
        "pizza"
    ],
    "wof:name":"Breadeaux Pizza",
    "wof:placetype":"venue"
},
  "geometry": {"coordinates":[-93.73655599999999,41.645257],"type":"Point"}
}