{
  "type": "Feature",
  "properties": {
    "iso:country":"US",
    "sg:address":"3523 Main St",
    "sg:city":"Keokuk",
    "sg:classifiers":[
        {
            "category":"Professional",
            "subcategory":"Engineering",
            "type":"Services"
        }
    ],
    "sg:phone":"+1 319 524 8730",
    "sg:postcode":"52632",
    "sg:province":"IA",
    "sg:tags":[
        "engineer"
    ],
    "wof:name":"Poepping Stone Bach & Assoc",
    "wof:placetype":"venue"
},
  "geometry": {"coordinates":[-91.411209,40.424404],"type":"Point"}
}