{
  "type": "Feature",
  "properties": {
    "iso:country":"US",
    "sg:address":"120 S Jordan Creek Pkwy",
    "sg:city":"West Des Moines",
    "sg:classifiers":[
        {
            "category":"Restaurant",
            "type":"Food & Drink"
        }
    ],
    "sg:menulink":"http://www.allmenus.com/ia/boone/10804-bravo!-cucina-italiana/menu/",
    "sg:phone":"+1 515 225 0660",
    "sg:postcode":"50266",
    "sg:province":"IA",
    "sg:tags":[
        "italian"
    ],
    "wof:name":"Bravo! Cucina Italiana",
    "wof:placetype":"venue"
},
  "geometry": {"coordinates":[-93.80929999999999,41.566507],"type":"Point"}
}