{
  "type": "Feature",
  "properties": {
    "addr:full":"2702 53rd St Des Moines IA 50310",
    "addr:housenumber":"2702",
    "addr:postcode":"50310",
    "addr:street":"53Rd St",
    "iso:country":"US",
    "sg:address":"2702 53rd St",
    "sg:city":"Des Moines",
    "sg:classifiers":[
        {
            "category":"Shopping",
            "subcategory":"Hobbies, Toys, & Games",
            "type":"Retail Goods"
        }
    ],
    "sg:phone":"+1 515 255 1994",
    "sg:postcode":"50310",
    "sg:province":"IA",
    "wof:name":"This N That Ceramics",
    "wof:placetype":"venue"
},
  "geometry": {"coordinates":[-93.691442,41.622105],"type":"Point"}
}