{
  "type": "Feature",
  "properties": {
    "addr:full":"1101 S E Ave Washington IA 52353",
    "addr:housenumber":"1101",
    "addr:postcode":"52353",
    "addr:street":"S E Ave",
    "iso:country":"US",
    "sg:address":"1101 S E Ave",
    "sg:city":"Washington",
    "sg:classifiers":[
        {
            "category":"Real Estate",
            "subcategory":"Developer",
            "type":"Services"
        }
    ],
    "sg:phone":"+1 319 653 3927",
    "sg:postcode":"52353",
    "sg:province":"IA",
    "sg:tags":[
        "cemetery"
    ],
    "wof:name":"Elm Grove Cemetery",
    "wof:placetype":"venue"
},
  "geometry": {"coordinates":[-91.69810099999999,41.289112],"type":"Point"}
}