{
  "type": "Feature",
  "properties": {
    "iso:country":"US",
    "sg:address":"501 Lake Ave",
    "sg:city":"Storm Lake",
    "sg:classifiers":[
        {
            "category":"Shopping",
            "subcategory":"Jewelry",
            "type":"Retail Goods"
        }
    ],
    "sg:phone":"+1 712 213 0130",
    "sg:postcode":"50588",
    "sg:province":"IA",
    "sg:tags":[
        "jeweler"
    ],
    "wof:name":"Daisy Jewelry",
    "wof:placetype":"venue"
},
  "geometry": {"coordinates":[-95.200875,42.644434],"type":"Point"}
}