{
  "type": "Feature",
  "properties": {
    "iso:country":"US",
    "sg:address":"6701 Douglas Ave",
    "sg:city":"Urbandale",
    "sg:classifiers":[
        {
            "category":"Health Services",
            "subcategory":"Doctor",
            "type":"Services"
        }
    ],
    "sg:phone":"+1 515 278 0404",
    "sg:postcode":"50322",
    "sg:province":"IA",
    "sg:tags":[
        "dentist"
    ],
    "wof:name":"Kroner Family Dentistry",
    "wof:placetype":"venue"
},
  "geometry": {"coordinates":[-93.70980900000001,41.629383],"type":"Point"}
}