{
  "type": "Feature",
  "properties": {
    "iso:country":"US",
    "sg:address":"20451 Jones-Delaware Rd",
    "sg:city":"Monticello",
    "sg:classifiers":[
        {
            "category":"Farming",
            "subcategory":"Farm",
            "type":"Manufacturing & Wholesale Goods"
        }
    ],
    "sg:phone":"+1 319 465 3993",
    "sg:postcode":"52310",
    "sg:province":"IA",
    "sg:tags":[
        "crop",
        "general"
    ],
    "wof:name":"Larry R Stahlberg",
    "wof:placetype":"venue"
},
  "geometry": {"coordinates":[-91.29297800000001,42.296283],"type":"Point"}
}