{
  "type": "Feature",
  "properties": {
    "iso:country":"US",
    "sg:address":"200 6th St",
    "sg:city":"Waukee",
    "sg:classifiers":[
        {
            "category":"Autos & Motor Vehicles",
            "subcategory":"Automobile Sales",
            "type":"Retail Goods"
        }
    ],
    "sg:phone":"+1 515 987 1751",
    "sg:postcode":"50263",
    "sg:province":"IA",
    "sg:tags":[
        "car",
        "dealer"
    ],
    "wof:name":"Interstate Automotive",
    "wof:placetype":"venue"
},
  "geometry": {"coordinates":[-93.885605,41.612764],"type":"Point"}
}