{
  "type": "Feature",
  "properties": {
    "iso:country":"US",
    "sg:address":"119 Main St",
    "sg:city":"Van Horne",
    "sg:classifiers":[
        {
            "category":"Organizations",
            "subcategory":"Community Association",
            "type":"Services"
        }
    ],
    "sg:phone":"+1 319 228 8726",
    "sg:postcode":"52346",
    "sg:province":"IA",
    "sg:tags":[
        "military"
    ],
    "wof:name":"American Legion",
    "wof:placetype":"venue"
},
  "geometry": {"coordinates":[-92.091049,42.008384],"type":"Point"}
}