{
  "type": "Feature",
  "properties": {
    "iso:country":"US",
    "sg:address":"1003 4th Ave",
    "sg:city":"Sheldon",
    "sg:classifiers":[
        {
            "category":"Professional",
            "type":"Services"
        }
    ],
    "sg:phone":"+1 712 324 3160",
    "sg:postcode":"51201",
    "sg:province":"IA",
    "sg:tags":[
        "establishment"
    ],
    "wof:name":"St Patrick's",
    "wof:placetype":"venue"
},
  "geometry": {"coordinates":[-95.85394100000001,43.179424],"type":"Point"}
}