{
  "type": "Feature",
  "properties": {
    "addr:full":"721 West St Whiting IA 51063",
    "addr:housenumber":"721",
    "addr:postcode":"51063",
    "addr:street":"West St",
    "iso:country":"US",
    "sg:address":"721 West St",
    "sg:city":"Whiting",
    "sg:classifiers":[
        {
            "category":"Organizations",
            "subcategory":"Religious Organization",
            "type":"Services"
        }
    ],
    "sg:phone":"+1 712 458 2411",
    "sg:postcode":"51063",
    "sg:province":"IA",
    "sg:tags":[
        "church"
    ],
    "wof:name":"Jehovah's Witnesses",
    "wof:placetype":"venue"
},
  "geometry": {"coordinates":[-96.15557,42.128465],"type":"Point"}
}