{
  "type": "Feature",
  "properties": {
    "addr:full":"103 1st St Bussey IA 50044",
    "addr:housenumber":"103",
    "addr:postcode":"50044",
    "addr:street":"1St St",
    "iso:country":"US",
    "sg:address":"103 1st St",
    "sg:city":"Bussey",
    "sg:classifiers":[
        {
            "category":"Personal",
            "subcategory":"Beauty Salon",
            "type":"Services"
        }
    ],
    "sg:phone":"+1 641 944 5844",
    "sg:postcode":"50044",
    "sg:province":"IA",
    "wof:name":"Janie's House Of Beauty",
    "wof:placetype":"venue"
},
  "geometry": {"coordinates":[-92.88905200000001,41.20819],"type":"Point"}
}