{
  "type": "Feature",
  "properties": {
    "addr:full":"903 4th St Gowrie IA 50543",
    "addr:housenumber":"903",
    "addr:postcode":"50543",
    "addr:street":"4Th St",
    "iso:country":"US",
    "sg:address":"903 4th St",
    "sg:city":"Gowrie",
    "sg:classifiers":[
        {
            "category":"Wholesale",
            "subcategory":"Farm Supplies",
            "type":"Manufacturing & Wholesale Goods"
        },
        {
            "category":"Home & Garden",
            "subcategory":"Garden Supply",
            "type":"Retail Goods"
        }
    ],
    "sg:phone":"+1 515 352 3663",
    "sg:postcode":"50543",
    "sg:province":"IA",
    "sg:tags":[
        "fertilizer"
    ],
    "wof:name":"Grower's Fertilizer Solutions",
    "wof:placetype":"venue"
},
  "geometry": {"coordinates":[-94.28097,42.277416],"type":"Point"}
}