{
  "type": "Feature",
  "properties": {
    "addr:full":"17 S 14th St Denison IA 51442",
    "addr:housenumber":"17",
    "addr:postcode":"51442",
    "addr:street":"S 14Th St",
    "iso:country":"US",
    "sg:address":"17 S 14th St",
    "sg:city":"Denison",
    "sg:classifiers":[
        {
            "category":"Health Services",
            "subcategory":"Chiropractor",
            "type":"Services"
        }
    ],
    "sg:phone":"+1 712 263 5608",
    "sg:postcode":"51442",
    "sg:province":"IA",
    "wof:name":"Denison Chiropractic Clinic",
    "wof:placetype":"venue"
},
  "geometry": {"coordinates":[-95.35390200000001,42.016548],"type":"Point"}
}