{
  "type": "Feature",
  "properties": {
    "iso:country":"US",
    "sg:address":"302 Read St",
    "sg:city":"Wesley",
    "sg:classifiers":[
        {
            "category":"Organizations",
            "subcategory":"Religious Organization",
            "type":"Services"
        }
    ],
    "sg:phone":"+1 515 679 4437",
    "sg:postcode":"50483",
    "sg:province":"IA",
    "sg:tags":[
        "church"
    ],
    "wof:name":"United Methodist Church",
    "wof:placetype":"venue"
},
  "geometry": {"coordinates":[-93.99364799999999,43.087111],"type":"Point"}
}