{
  "type": "Feature",
  "properties": {
    "addr:full":"5217 George Washington Carver Ave Ames IA 50010",
    "addr:housenumber":"5217",
    "addr:postcode":"50010",
    "addr:street":"George Washington Carver Ave",
    "iso:country":"US",
    "sg:address":"5217 George Washington Carver Ave",
    "sg:city":"Ames",
    "sg:classifiers":[
        {
            "category":"Home & Garden",
            "subcategory":"Garden Supply",
            "type":"Retail Goods"
        }
    ],
    "sg:phone":"+1 515 232 6856",
    "sg:postcode":"50010",
    "sg:province":"IA",
    "sg:tags":[
        "engine"
    ],
    "wof:name":"Hilker Small Engine",
    "wof:placetype":"venue"
},
  "geometry": {"coordinates":[-93.659423,42.067897],"type":"Point"}
}