{
  "type": "Feature",
  "properties": {
    "iso:country":"US",
    "sg:address":"217 Normandy St",
    "sg:city":"Waterloo",
    "sg:classifiers":[
        {
            "category":"Organizations",
            "subcategory":"Professional Association",
            "type":"Services"
        }
    ],
    "sg:phone":"+1 319 233 0421",
    "sg:postcode":"50703",
    "sg:province":"IA",
    "sg:tags":[
        "business"
    ],
    "wof:name":"Iowa Assoc For Education",
    "wof:placetype":"venue"
},
  "geometry": {"coordinates":[-92.365386,42.523687],"type":"Point"}
}