{
  "type": "Feature",
  "properties": {
    "iso:country":"US",
    "sg:address":"244 W 4th St",
    "sg:city":"St Ansgar",
    "sg:classifiers":[
        {
            "category":"Shopping",
            "subcategory":"Used Merchandise",
            "type":"Retail Goods"
        }
    ],
    "sg:phone":"+1 641 736 4438",
    "sg:postcode":"50472",
    "sg:province":"IA",
    "sg:tags":[
        "antique"
    ],
    "wof:name":"Picket Fence Antiques & Gifts",
    "wof:placetype":"venue"
},
  "geometry": {"coordinates":[-92.921159,43.378401],"type":"Point"}
}