{
  "type": "Feature",
  "properties": {
    "iso:country":"US",
    "sg:address":"3823 110th St",
    "sg:city":"Pierson",
    "sg:classifiers":[
        {
            "category":"Building & Trades",
            "subcategory":"Landscaping Services",
            "type":"Services"
        }
    ],
    "sg:phone":"+1 712 375 5494",
    "sg:postcode":"51048",
    "sg:province":"IA",
    "sg:tags":[
        "soil",
        "work",
        "erosion"
    ],
    "wof:name":"Byers Landscaping Co",
    "wof:placetype":"venue"
},
  "geometry": {"coordinates":[-95.855182,42.547474],"type":"Point"}
}