{
  "type": "Feature",
  "properties": {
    "addr:full":"1069 Nice Ave Bagley IA 50029",
    "addr:housenumber":"1069",
    "addr:postcode":"50029",
    "addr:street":"Nice Ave",
    "iso:country":"US",
    "sg:address":"1069 Nice Ave",
    "sg:city":"Bagley",
    "sg:classifiers":[
        {
            "category":"Professional",
            "subcategory":"Business Services",
            "type":"Services"
        }
    ],
    "sg:phone":"+1 641 427 5647",
    "sg:postcode":"50029",
    "sg:province":"IA",
    "wof:name":"Nrtc",
    "wof:placetype":"venue"
},
  "geometry": {"coordinates":[-94.492992,41.853541],"type":"Point"}
}