{
  "type": "Feature",
  "properties": {
    "iso:country":"US",
    "sg:address":"510 E 1st St",
    "sg:city":"Ankeny",
    "sg:classifiers":[
        {
            "category":"Organizations",
            "subcategory":"Religious Organization",
            "type":"Services"
        }
    ],
    "sg:phone":"+1 515 964 3038",
    "sg:postcode":"50021",
    "sg:province":"IA",
    "wof:name":"Our Lady Emclate Heart Church",
    "wof:placetype":"venue"
},
  "geometry": {"coordinates":[-93.5942,41.731931],"type":"Point"}
}