{
  "type": "Feature",
  "properties": {
    "iso:country":"US",
    "sg:address":"10884 225th St",
    "sg:city":"Moulton",
    "sg:classifiers":[
        {
            "category":"Farming",
            "subcategory":"Livestock Farm",
            "type":"Manufacturing & Wholesale Goods"
        }
    ],
    "sg:phone":"+1 641 642 3773",
    "sg:postcode":"52572",
    "sg:province":"IA",
    "sg:tags":[
        "beef",
        "feedlot",
        "cattle"
    ],
    "wof:name":"Powell Orris Farm",
    "wof:placetype":"venue"
},
  "geometry": {"coordinates":[-92.622084,40.732779],"type":"Point"}
}