{
  "type": "Feature",
  "properties": {
    "iso:country":"US",
    "sg:address":"307 4th St NE",
    "sg:city":"Waukon",
    "sg:classifiers":[
        {
            "category":"Retail",
            "subcategory":"Auto Repair",
            "type":"Services"
        }
    ],
    "sg:phone":"+1 563 568 3373",
    "sg:postcode":"52172",
    "sg:province":"IA",
    "sg:tags":[
        "automotive"
    ],
    "wof:name":"Hennessy Towing",
    "wof:placetype":"venue"
},
  "geometry": {"coordinates":[-91.469584,43.272751],"type":"Point"}
}