{
  "type": "Feature",
  "properties": {
    "iso:country":"US",
    "sg:address":"1909 Clarke-Lucas Ave",
    "sg:city":"Lucas",
    "sg:classifiers":[
        {
            "category":"Real Estate",
            "subcategory":"Real Estate Operator",
            "type":"Services"
        }
    ],
    "sg:phone":"+1 641 342 7147",
    "sg:postcode":"50151",
    "sg:province":"IA",
    "sg:tags":[
        "property",
        "lessor"
    ],
    "wof:name":"Mary Irving",
    "wof:placetype":"venue"
},
  "geometry": {"coordinates":[-93.556854,41.028901],"type":"Point"}
}