{
  "type": "Feature",
  "properties": {
    "iso:country":"US",
    "sg:address":"420 Main St",
    "sg:city":"Little Rock",
    "sg:classifiers":[
        {
            "category":"Home & Garden",
            "subcategory":"Building Materials",
            "type":"Retail Goods"
        }
    ],
    "sg:phone":"+1 712 479 2234",
    "sg:postcode":"51243",
    "sg:province":"IA",
    "wof:name":"Farm & Home Inc",
    "wof:placetype":"venue"
},
  "geometry": {"coordinates":[-95.883127,43.444916],"type":"Point"}
}