{
  "type": "Feature",
  "properties": {
    "addr:full":"126 Franklin Ave Des Moines IA 50314",
    "addr:housenumber":"126",
    "addr:postcode":"50314",
    "addr:street":"Franklin Ave",
    "iso:country":"US",
    "sg:address":"126 Franklin Ave",
    "sg:city":"Des Moines",
    "sg:classifiers":[
        {
            "category":"Manufacturing",
            "subcategory":"Electronics",
            "type":"Manufacturing & Wholesale Goods"
        }
    ],
    "sg:phone":"+1 515 244 3723",
    "sg:postcode":"50314",
    "sg:province":"IA",
    "sg:tags":[
        "equipment",
        "electronic",
        "supply"
    ],
    "wof:name":"Selindh Machine Co",
    "wof:placetype":"venue"
},
  "geometry": {"coordinates":[-93.61933999999999,41.610937],"type":"Point"}
}