{
  "type": "Feature",
  "properties": {
    "iso:country":"US",
    "sg:address":"734 Street F58",
    "sg:city":"Shelby",
    "sg:classifiers":[
        {
            "category":"Personal",
            "subcategory":"Beauty Salon",
            "type":"Services"
        }
    ],
    "sg:phone":"+1 712 744 3629",
    "sg:postcode":"51570",
    "sg:province":"IA",
    "sg:tags":[
        "shop"
    ],
    "wof:name":"Country Hair",
    "wof:placetype":"venue"
},
  "geometry": {"coordinates":[-95.431071,41.585745],"type":"Point"}
}