{
  "type": "Feature",
  "properties": {
    "iso:country":"US",
    "sg:address":"300 N State St",
    "sg:city":"Denver",
    "sg:classifiers":[
        {
            "category":"Real Estate",
            "subcategory":"Real Estate Agent",
            "type":"Services"
        }
    ],
    "sg:phone":"+1 319 984 5600",
    "sg:postcode":"50622",
    "sg:province":"IA",
    "wof:name":"Re/Max Alliance",
    "wof:placetype":"venue"
},
  "geometry": {"coordinates":[-92.33732000000001,42.673733],"type":"Point"}
}