{
  "type": "Feature",
  "properties": {
    "addr:full":"209 Lincoln Way Ames IA 50010",
    "addr:housenumber":"209",
    "addr:postcode":"50010",
    "addr:street":"Lincoln Way",
    "iso:country":"US",
    "sg:address":"209 Lincoln Way",
    "sg:city":"Ames",
    "sg:classifiers":[
        {
            "category":"Restaurant",
            "type":"Food & Drink"
        }
    ],
    "sg:menulink":"http://www.allmenus.com/ia/ames/160770-burger-king/menu/",
    "sg:phone":"+1 515 232 6550",
    "sg:postcode":"50010",
    "sg:province":"IA",
    "sg:tags":[
        "burger",
        "american"
    ],
    "wof:name":"Burger King",
    "wof:placetype":"venue"
},
  "geometry": {"coordinates":[-93.612196,42.022896],"type":"Point"}
}