{
  "type": "Feature",
  "properties": {
    "iso:country":"US",
    "sg:address":"145 S 4th St",
    "sg:city":"Forest City",
    "sg:classifiers":[
        {
            "category":"Insurance",
            "subcategory":"Insurance Agent",
            "type":"Services"
        }
    ],
    "sg:phone":"+1 641 585 2925",
    "sg:postcode":"50436",
    "sg:province":"IA",
    "sg:website":"www.farmcityinsurance.com",
    "wof:name":"Farm & City Insurance Svc",
    "wof:placetype":"venue"
},
  "geometry": {"coordinates":[-93.63704300000001,43.263],"type":"Point"}
}