{
  "type": "Feature",
  "properties": {
    "iso:country":"US",
    "sg:address":"124 N Main St",
    "sg:city":"Lenox",
    "sg:classifiers":[
        {
            "category":"Real Estate",
            "subcategory":"Real Estate Agent",
            "type":"Services"
        }
    ],
    "sg:phone":"+1 641 333 4656",
    "sg:postcode":"50851",
    "sg:province":"IA",
    "sg:website":"www.agconnect.org",
    "wof:name":"Ag Connect",
    "wof:placetype":"venue"
},
  "geometry": {"coordinates":[-94.55893399999999,40.882373],"type":"Point"}
}