{
  "type": "Feature",
  "properties": {
    "iso:country":"US",
    "sg:address":"409 Maple St",
    "sg:city":"West Des Moines",
    "sg:classifiers":[
        {
            "category":"Food & Beverages",
            "subcategory":"Meat & Fish",
            "type":"Retail Goods"
        }
    ],
    "sg:phone":"+1 515 279 2404",
    "sg:postcode":"50265",
    "sg:province":"IA",
    "wof:name":"Honey Sweet Gourmet Foods",
    "wof:placetype":"venue"
},
  "geometry": {"coordinates":[-93.708804,41.571161],"type":"Point"}
}