{
  "type": "Feature",
  "properties": {
    "iso:country":"US",
    "sg:address":"1015 Duff Ave",
    "sg:city":"Ames",
    "sg:classifiers":[
        {
            "category":"Health Services",
            "subcategory":"Doctor",
            "type":"Services"
        }
    ],
    "sg:phone":"+1 515 239 6770",
    "sg:postcode":"50010",
    "sg:province":"IA",
    "sg:tags":[
        "physician",
        "surgeon"
    ],
    "sg:website":"www.mgmc.org",
    "wof:name":"Mary Greeley Rahab & Wellness",
    "wof:placetype":"venue"
},
  "geometry": {"coordinates":[-93.61066700000001,42.031925],"type":"Point"}
}