{
  "type": "Feature",
  "properties": {
    "iso:country":"US",
    "sg:address":"1500 W 3rd St",
    "sg:city":"Wilton",
    "sg:classifiers":[
        {
            "category":"Building & Trades",
            "subcategory":"Cleaning & Sanitation",
            "type":"Services"
        }
    ],
    "sg:phone":"+1 563 732 4351",
    "sg:postcode":"52778",
    "sg:province":"IA",
    "sg:tags":[
        "janitor"
    ],
    "wof:name":"FBG Svc Corp",
    "wof:placetype":"venue"
},
  "geometry": {"coordinates":[-91.03822599999999,41.588564],"type":"Point"}
}