{
  "type": "Feature",
  "properties": {
    "iso:country":"US",
    "sg:address":"2201 4th St SW",
    "sg:city":"Mason City",
    "sg:classifiers":[
        {
            "category":"Bakery",
            "type":"Food & Drink"
        }
    ],
    "sg:menulink":"http://www.allmenus.com/ia/mason-city/102033-perkins-restaurant--bakery/menu/",
    "sg:phone":"+1 641 423 2360",
    "sg:postcode":"50401",
    "sg:province":"IA",
    "sg:tags":[
        "sandwich",
        "salad",
        "soup",
        "american",
        "pastry",
        "wrap"
    ],
    "wof:name":"Perkins Restaurant & Bakery",
    "wof:placetype":"venue"
},
  "geometry": {"coordinates":[-93.23378,43.148311],"type":"Point"}
}