{
  "type": "Feature",
  "properties": {
    "iso:country":"US",
    "sg:address":"3835 W 9th St",
    "sg:city":"Waterloo",
    "sg:classifiers":[
        {
            "category":"Shopping",
            "type":"Retail Goods"
        }
    ],
    "sg:phone":"+1 319 232 6010",
    "sg:postcode":"50702",
    "sg:province":"IA",
    "sg:tags":[
        "orthopedic",
        "appliance"
    ],
    "wof:name":"Great Plains Orthotics-Prsthtc",
    "wof:placetype":"venue"
},
  "geometry": {"coordinates":[-92.34861600000001,42.458094],"type":"Point"}
}