{
  "type": "Feature",
  "properties": {
    "iso:country":"US",
    "sg:address":"365 Beaver Kreek Ctr",
    "sg:city":"North Liberty",
    "sg:classifiers":[
        {
            "category":"Ice Cream",
            "type":"Food & Drink"
        }
    ],
    "sg:menulink":"http://www.allmenus.com/ia/penn/172749-dairy-queen/menu/",
    "sg:phone":"+1 319 626 2011",
    "sg:postcode":"52317",
    "sg:province":"IA",
    "sg:tags":[
        "burger",
        "american"
    ],
    "wof:name":"Dairy Queen",
    "wof:placetype":"venue"
},
  "geometry": {"coordinates":[-91.59197500000001,41.743136],"type":"Point"}
}