{
  "type": "Feature",
  "properties": {
    "iso:country":"US",
    "sg:address":"400 4th Ave",
    "sg:city":"Armstrong",
    "sg:classifiers":[
        {
            "category":"Education",
            "subcategory":"School",
            "type":"Public Place"
        }
    ],
    "sg:phone":"+1 712 868 3550",
    "sg:postcode":"50514",
    "sg:province":"IA",
    "sg:website":"http://www.armstrong.k12.ia.us",
    "wof:name":"Armstrng-Rngsted Elmntary Schl",
    "wof:placetype":"venue"
},
  "geometry": {"coordinates":[-94.483017,43.398312],"type":"Point"}
}