{
  "type": "Feature",
  "properties": {
    "iso:country":"US",
    "sg:address":"402 Main St",
    "sg:city":"Little Rock",
    "sg:classifiers":[
        {
            "category":"Education",
            "subcategory":"Library",
            "type":"Public Place"
        }
    ],
    "sg:phone":"+1 712 479 2298",
    "sg:postcode":"51243",
    "sg:province":"IA",
    "wof:name":"Little Rock Library",
    "wof:placetype":"venue"
},
  "geometry": {"coordinates":[-95.883126,43.445114],"type":"Point"}
}