{
  "type": "Feature",
  "properties": {
    "iso:country":"US",
    "sg:address":"1918 E Ave",
    "sg:city":"Dawson",
    "sg:phone":"+1 515 428 8210",
    "sg:postcode":"50066",
    "sg:province":"IA",
    "sg:tags":[
        "farm",
        "corn",
        "soybean"
    ],
    "wof:name":"Charles Heinz",
    "wof:placetype":"venue"
},
  "geometry": {"coordinates":[-94.202724,41.757924],"type":"Point"}
}