{
  "type": "Feature",
  "properties": {
    "iso:country":"US",
    "sg:address":"616 7th Ave",
    "sg:city":"Coralville",
    "sg:classifiers":[
        {
            "category":"Building & Trades",
            "subcategory":"Construction",
            "type":"Services"
        }
    ],
    "sg:phone":"+1 319 351 1435",
    "sg:postcode":"52241",
    "sg:province":"IA",
    "sg:tags":[
        "hanging",
        "contractor"
    ],
    "wof:name":"Five Star Painting",
    "wof:placetype":"venue"
},
  "geometry": {"coordinates":[-91.574817,41.677793],"type":"Point"}
}