{
  "type": "Feature",
  "properties": {
    "iso:country":"US",
    "sg:address":"306 Hwy 37",
    "sg:city":"Dunlap",
    "sg:classifiers":[
        {
            "category":"Home & Garden",
            "subcategory":"Garden Supply",
            "type":"Retail Goods"
        }
    ],
    "sg:phone":"+1 712 643 5822",
    "sg:postcode":"51529",
    "sg:province":"IA",
    "sg:tags":[
        "fertilizer"
    ],
    "wof:name":"Dunlap Fertilizer Co",
    "wof:placetype":"venue"
},
  "geometry": {"coordinates":[-95.601884,41.856494],"type":"Point"}
}