{
  "type": "Feature",
  "properties": {
    "addr:full":"124 S Main St Kingsley IA 51028",
    "addr:housenumber":"124",
    "addr:postcode":"51028",
    "addr:street":"S Main St",
    "iso:country":"US",
    "sg:address":"124 S Main St",
    "sg:city":"Kingsley",
    "sg:classifiers":[
        {
            "category":"Retail",
            "subcategory":"Auto Repair",
            "type":"Services"
        }
    ],
    "sg:phone":"+1 712 378 3016",
    "sg:postcode":"51028",
    "sg:province":"IA",
    "sg:tags":[
        "automobile",
        "co",
        "drive",
        "transporter"
    ],
    "wof:name":"Plendl Brothers Trucking Shop",
    "wof:placetype":"venue"
},
  "geometry": {"coordinates":[-95.967406,42.584271],"type":"Point"}
}