{
  "type": "Feature",
  "properties": {
    "iso:country":"US",
    "sg:address":"503 Washington Ave",
    "sg:city":"Iowa Falls",
    "sg:classifiers":[
        {
            "category":"Real Estate",
            "subcategory":"Real Estate Agent",
            "type":"Services"
        }
    ],
    "sg:phone":"+1 641 648 4246",
    "sg:postcode":"50126",
    "sg:province":"IA",
    "sg:website":"www.jenningsre.com",
    "wof:name":"Jennings Real Estate & Ins",
    "wof:placetype":"venue"
},
  "geometry": {"coordinates":[-93.264151,42.519561],"type":"Point"}
}