{
  "type": "Feature",
  "properties": {
    "iso:country":"US",
    "sg:address":"24551 Eagle Dr",
    "sg:city":"Bonaparte",
    "sg:classifiers":[
        {
            "category":"Shopping",
            "subcategory":"Clothing, Apparel, & Fashions",
            "type":"Retail Goods"
        }
    ],
    "sg:phone":"+1 319 592 3790",
    "sg:postcode":"52620",
    "sg:province":"IA",
    "sg:tags":[
        "salvage",
        "surplus",
        "merchandise"
    ],
    "wof:name":"Ben Hendricks Enteprises Inc",
    "wof:placetype":"venue"
},
  "geometry": {"coordinates":[-91.78117,40.692775],"type":"Point"}
}