{
  "type": "Feature",
  "properties": {
    "iso:country":"US",
    "sg:address":"1883 300th St",
    "sg:city":"Toledo",
    "sg:phone":"+1 641 484 3149",
    "sg:postcode":"52342",
    "sg:province":"IA",
    "sg:tags":[
        "farm",
        "soybean"
    ],
    "wof:name":"Harold Wilkerson",
    "wof:placetype":"venue"
},
  "geometry": {"coordinates":[-92.59616699999999,42.007086],"type":"Point"}
}