{
  "type": "Feature",
  "properties": {
    "iso:country":"US",
    "sg:address":"205 S Marion Ave",
    "sg:city":"Washington",
    "sg:classifiers":[
        {
            "category":"Health Services",
            "subcategory":"Doctor",
            "type":"Services"
        }
    ],
    "sg:phone":"+1 319 653 3412",
    "sg:postcode":"52353",
    "sg:province":"IA",
    "sg:tags":[
        "dentist"
    ],
    "wof:name":"John Helscher DDS",
    "wof:placetype":"venue"
},
  "geometry": {"coordinates":[-91.693085,41.298344],"type":"Point"}
}