{
  "type": "Feature",
  "properties": {
    "iso:country":"US",
    "sg:address":"2165 NW 108th St",
    "sg:city":"Clive",
    "sg:classifiers":[
        {
            "category":"Shopping",
            "subcategory":"Stationery & Office Supplies",
            "type":"Retail Goods"
        }
    ],
    "sg:phone":"+1 515 727 7934",
    "sg:postcode":"50325",
    "sg:province":"IA",
    "wof:name":"Lilly Office Supply LLC",
    "wof:placetype":"venue"
},
  "geometry": {"coordinates":[-93.76549900000001,41.613606],"type":"Point"}
}