{
  "type": "Feature",
  "properties": {
    "iso:country":"US",
    "sg:address":"4522 N Thornwood Ave",
    "sg:city":"Davenport",
    "sg:classifiers":[
        {
            "category":"Building & Trades",
            "subcategory":"Construction",
            "type":"Services"
        }
    ],
    "sg:phone":"+1 563 285 2973",
    "sg:postcode":"52806",
    "sg:province":"IA",
    "sg:tags":[
        "system",
        "specialty",
        "heating",
        "contractor",
        "air conditioning"
    ],
    "wof:name":"J B Heating And Air",
    "wof:placetype":"venue"
},
  "geometry": {"coordinates":[-90.61645900000001,41.566509],"type":"Point"}
}