{
  "type": "Feature",
  "properties": {
    "iso:country":"US",
    "sg:address":"12998 English Mill Rd",
    "sg:city":"Dubuque",
    "sg:classifiers":[
        {
            "category":"Freight",
            "type":"Transportation"
        }
    ],
    "sg:phone":"+1 563 583 8333",
    "sg:postcode":"52003",
    "sg:province":"IA",
    "sg:tags":[
        "trucking"
    ],
    "wof:name":"Lamco Limited",
    "wof:placetype":"venue"
},
  "geometry": {"coordinates":[-90.728371,42.486253],"type":"Point"}
}