{
  "type": "Feature",
  "properties": {
    "addr:full":"103 Franklin St Cedar Falls IA 50613",
    "addr:housenumber":"103",
    "addr:postcode":"50613",
    "addr:street":"Franklin St",
    "iso:country":"US",
    "sg:address":"103 Franklin St",
    "sg:city":"Cedar Falls",
    "sg:classifiers":[
        {
            "category":"Autos & Motor Vehicles",
            "subcategory":"Fuel & Gas Station",
            "type":"Retail Goods"
        }
    ],
    "sg:phone":"+1 319 266 5857",
    "sg:postcode":"50613",
    "sg:province":"IA",
    "sg:tags":[
        "oil"
    ],
    "wof:name":"Metro 66",
    "wof:placetype":"venue"
},
  "geometry": {"coordinates":[-92.44952499999999,42.536907],"type":"Point"}
}