{
  "type": "Feature",
  "properties": {
    "iso:country":"US",
    "sg:address":"1605 N Ankeny Blvd",
    "sg:city":"Ankeny",
    "sg:classifiers":[
        {
            "category":"Organizations",
            "subcategory":"Professional Association",
            "type":"Services"
        }
    ],
    "sg:phone":"+1 515 965 9237",
    "sg:postcode":"50023",
    "sg:province":"IA",
    "wof:name":"Iowa Veterinary Medical Assn",
    "wof:placetype":"venue"
},
  "geometry": {"coordinates":[-93.600336,41.746342],"type":"Point"}
}