{
  "type": "Feature",
  "properties": {
    "iso:country":"US",
    "sg:address":"1110 42nd St",
    "sg:city":"West Des Moines",
    "sg:classifiers":[
        {
            "category":"Professional",
            "subcategory":"Management & Consulting",
            "type":"Services"
        }
    ],
    "sg:phone":"+1 515 224 6494",
    "sg:postcode":"50266",
    "sg:province":"IA",
    "sg:tags":[
        "consultant"
    ],
    "wof:name":"Poertner Consulting Group",
    "wof:placetype":"venue"
},
  "geometry": {"coordinates":[-93.761449,41.586306],"type":"Point"}
}