{
  "type": "Feature",
  "properties": {
    "addr:full":"215 W 39th Street Ct Sioux City IA 51104",
    "addr:housenumber":"215",
    "addr:postcode":"51104",
    "addr:street":"W 39Th Street",
    "iso:country":"US",
    "sg:address":"215 W 39th Street Ct",
    "sg:city":"Sioux City",
    "sg:classifiers":[
        {
            "category":"Building & Trades",
            "subcategory":"Construction",
            "type":"Services"
        }
    ],
    "sg:phone":"+1 712 574 0072",
    "sg:postcode":"51104",
    "sg:province":"IA",
    "sg:tags":[
        "contractor"
    ],
    "wof:name":"Tee Jay Builders Inc",
    "wof:placetype":"venue"
},
  "geometry": {"coordinates":[-96.415404,42.537137],"type":"Point"}
}