{
  "type": "Feature",
  "properties": {
    "iso:country":"US",
    "sg:address":"105 9th Ave",
    "sg:city":"Belle Plaine",
    "sg:classifiers":[
        {
            "category":"Health Services",
            "subcategory":"Doctor",
            "type":"Services"
        }
    ],
    "sg:phone":"+1 319 444 3210",
    "sg:postcode":"52208",
    "sg:province":"IA",
    "sg:tags":[
        "physician",
        "surgeon"
    ],
    "wof:name":"U I Family Care Ctr",
    "wof:placetype":"venue"
},
  "geometry": {"coordinates":[-92.275431,41.886155],"type":"Point"}
}