{
  "type": "Feature",
  "properties": {
    "addr:full":"2520 Gordon Dr Sioux City SD 51106",
    "addr:housenumber":"2520",
    "addr:postcode":"51106",
    "addr:street":"Gordon Dr",
    "iso:country":"US",
    "sg:address":"2520 Gordon Dr",
    "sg:city":"Sioux City",
    "sg:classifiers":[
        {
            "category":"Shopping",
            "subcategory":"Bicycles & Sporting Goods",
            "type":"Retail Goods"
        }
    ],
    "sg:phone":"+1 712 233 0919",
    "sg:postcode":"51106",
    "sg:province":"SD",
    "sg:tags":[
        "tackle",
        "fishing"
    ],
    "wof:name":"Anglers Pit Stop",
    "wof:placetype":"venue"
},
  "geometry": {"coordinates":[-96.376119,42.489743],"type":"Point"}
}