{
  "type": "Feature",
  "properties": {
    "addr:full":"2702 B Ave Guernsey IA 52221",
    "addr:housenumber":"2702",
    "addr:postcode":"52221",
    "addr:street":"B Ave",
    "iso:country":"US",
    "sg:address":"2702 B Ave",
    "sg:city":"Guernsey",
    "sg:classifiers":[
        {
            "category":"Building & Trades",
            "subcategory":"Construction",
            "type":"Services"
        }
    ],
    "sg:phone":"+1 319 685 4270",
    "sg:postcode":"52221",
    "sg:province":"IA",
    "sg:tags":[
        "installs",
        "wooden",
        "mfg",
        "cabinet"
    ],
    "wof:name":"English River Woodworking",
    "wof:placetype":"venue"
},
  "geometry": {"coordinates":[-92.279363,41.620182],"type":"Point"}
}