{
  "type": "Feature",
  "properties": {
    "iso:country":"US",
    "sg:address":"701 US Hwy 218",
    "sg:city":"Vinton",
    "sg:classifiers":[
        {
            "category":"Wholesale",
            "subcategory":"Farm Supplies",
            "type":"Manufacturing & Wholesale Goods"
        }
    ],
    "sg:phone":"+1 319 472 5261",
    "sg:postcode":"52349",
    "sg:province":"IA",
    "sg:tags":[
        "bulb",
        "seed"
    ],
    "wof:name":"Remington Hybrid Seed Co",
    "wof:placetype":"venue"
},
  "geometry": {"coordinates":[-92.037604,42.173898],"type":"Point"}
}