{
  "type": "Feature",
  "properties": {
    "addr:full":"507 SW 2nd St Gilmore City IA 50541",
    "addr:housenumber":"507",
    "addr:postcode":"50541",
    "addr:street":"Sw 2Nd St",
    "iso:country":"US",
    "sg:address":"507 SW 2nd St",
    "sg:city":"Gilmore City",
    "sg:phone":"+1 515 373 6266",
    "sg:postcode":"50541",
    "sg:province":"IA",
    "sg:tags":[
        "farm",
        "grain",
        "cash"
    ],
    "wof:name":"Frederick Hodgell",
    "wof:placetype":"venue"
},
  "geometry": {"coordinates":[-94.445695,42.72773],"type":"Point"}
}