{
  "type": "Feature",
  "properties": {
    "addr:full":"10 10th Ave NW Oelwein IA 50662",
    "addr:housenumber":"10",
    "addr:postcode":"50662",
    "addr:street":"10Th Ave Nw",
    "iso:country":"US",
    "sg:address":"10 10th Ave NW",
    "sg:city":"Oelwein",
    "sg:classifiers":[
        {
            "category":"Organizations",
            "subcategory":"Religious Organization",
            "type":"Services"
        }
    ],
    "sg:phone":"+1 319 283 1955",
    "sg:postcode":"50662",
    "sg:province":"IA",
    "wof:name":"Church of Christ West Side",
    "wof:placetype":"venue"
},
  "geometry": {"coordinates":[-91.92879000000001,42.679184],"type":"Point"}
}