{
  "type": "Feature",
  "properties": {
    "iso:country":"US",
    "sg:address":"2488 Oriole Ave",
    "sg:city":"Afton",
    "sg:phone":"+1 641 346 2550",
    "sg:postcode":"50830",
    "sg:province":"IA",
    "sg:tags":[
        "hog",
        "beef",
        "farm",
        "corn",
        "cash",
        "grain",
        "cattle",
        "feedlot"
    ],
    "wof:name":"Mark E Hudson",
    "wof:placetype":"venue"
},
  "geometry": {"coordinates":[-94.204955,40.936836],"type":"Point"}
}