{
  "type": "Feature",
  "properties": {
    "iso:country":"US",
    "sg:address":"3311 140th St",
    "sg:city":"Cumming",
    "sg:classifiers":[
        {
            "category":"Building & Trades",
            "subcategory":"Construction",
            "type":"Services"
        }
    ],
    "sg:phone":"+1 515 981 9465",
    "sg:postcode":"50061",
    "sg:province":"IA",
    "sg:tags":[
        "excavating",
        "contractor"
    ],
    "wof:name":"Harkin Construction",
    "wof:placetype":"venue"
},
  "geometry": {"coordinates":[-93.814278,41.452113],"type":"Point"}
}