{
  "type": "Feature",
  "properties": {
    "addr:full":"5665 Greendale Rd Johnston IA 50131",
    "addr:housenumber":"5665",
    "addr:postcode":"50131",
    "addr:street":"Greendale Rd",
    "iso:country":"US",
    "sg:address":"5665 Greendale Rd",
    "sg:city":"Johnston",
    "sg:classifiers":[
        {
            "category":"Building & Trades",
            "subcategory":"Construction",
            "type":"Services"
        }
    ],
    "sg:phone":"+1 515 270 1117",
    "sg:postcode":"50131",
    "sg:province":"IA",
    "sg:tags":[
        "general",
        "contractor"
    ],
    "sg:website":"www.hansencompany.com",
    "wof:name":"Hansen Co Inc",
    "wof:placetype":"venue"
},
  "geometry": {"coordinates":[-93.700249,41.667981],"type":"Point"}
}