{
  "type": "Feature",
  "properties": {
    "iso:country":"US",
    "sg:address":"4206 R Ave",
    "sg:city":"Larrabee",
    "sg:classifiers":[
        {
            "category":"Farming",
            "subcategory":"Farm",
            "type":"Manufacturing & Wholesale Goods"
        }
    ],
    "sg:phone":"+1 712 446 3884",
    "sg:postcode":"51029",
    "sg:province":"IA",
    "sg:tags":[
        "crop",
        "general"
    ],
    "wof:name":"Bierman Farms Inc",
    "wof:placetype":"venue"
},
  "geometry": {"coordinates":[-95.52452,42.90893],"type":"Point"}
}