{
  "type": "Feature",
  "properties": {
    "addr:full":"1043 J Ave Ute IA 51060",
    "addr:housenumber":"1043",
    "addr:postcode":"51060",
    "addr:street":"J Ave",
    "iso:country":"US",
    "sg:address":"1043 J Ave",
    "sg:city":"Ute",
    "sg:classifiers":[
        {
            "category":"Farming",
            "subcategory":"Farm",
            "type":"Manufacturing & Wholesale Goods"
        }
    ],
    "sg:phone":"+1 712 885 2616",
    "sg:postcode":"51060",
    "sg:province":"IA",
    "sg:tags":[
        "crop",
        "general"
    ],
    "wof:name":"Joel Kuhlmann",
    "wof:placetype":"venue"
},
  "geometry": {"coordinates":[-95.661332,42.08086],"type":"Point"}
}