{
  "type": "Feature",
  "properties": {
    "iso:country":"US",
    "sg:address":"1730 1st Ave NE",
    "sg:city":"Cedar Rapids",
    "sg:classifiers":[
        {
            "category":"Health Services",
            "subcategory":"Doctor",
            "type":"Services"
        }
    ],
    "sg:phone":"+1 319 365 3993",
    "sg:postcode":"52402",
    "sg:province":"IA",
    "sg:tags":[
        "psychiatrist"
    ],
    "wof:name":"Whitters Alan C MD",
    "wof:placetype":"venue"
},
  "geometry": {"coordinates":[-91.64792199999999,41.990752],"type":"Point"}
}