{
  "type": "Feature",
  "properties": {
    "iso:country":"US",
    "sg:address":"207 2nd Ave SE",
    "sg:city":"Cedar Rapids",
    "sg:classifiers":[
        {
            "category":"Shopping",
            "subcategory":"Pharmacy",
            "type":"Retail Goods"
        }
    ],
    "sg:phone":"+1 319 366 6220",
    "sg:postcode":"52401",
    "sg:province":"IA",
    "sg:tags":[
        "drugstore"
    ],
    "sg:website":"www.savon.com",
    "wof:name":"Osco Drug",
    "wof:placetype":"venue"
},
  "geometry": {"coordinates":[-91.667503,41.978199],"type":"Point"}
}