{
  "type": "Feature",
  "properties": {
    "addr:full":"3940 Voss Ave Breda IA 51436",
    "addr:postcode":"3940;51436",
    "addr:street":"Voss Ave",
    "iso:country":"US",
    "sg:address":"3940 Voss Ave",
    "sg:city":"Breda",
    "sg:classifiers":[
        {
            "category":"Farming",
            "subcategory":"Poultry Farm",
            "type":"Manufacturing & Wholesale Goods"
        }
    ],
    "sg:phone":"+1 712 673 2681",
    "sg:postcode":"51436",
    "sg:province":"IA",
    "sg:tags":[
        "hatchery"
    ],
    "wof:name":"Tom's Toms",
    "wof:placetype":"venue"
},
  "geometry": {"coordinates":[-94.936103,42.223456],"type":"Point"}
}