{
  "type": "Feature",
  "properties": {
    "addr:full":"4207 Grandview Ave Des Moines IA 50317",
    "addr:housenumber":"4207",
    "addr:postcode":"50317",
    "addr:street":"Grandview Ave",
    "iso:country":"US",
    "sg:address":"4207 Grandview Ave",
    "sg:city":"Des Moines",
    "sg:classifiers":[
        {
            "category":"Building & Trades",
            "subcategory":"Pest Control",
            "type":"Services"
        }
    ],
    "sg:phone":"+1 515 265 3584",
    "sg:postcode":"50317",
    "sg:province":"IA",
    "wof:name":"Murphy Pest Control",
    "wof:placetype":"venue"
},
  "geometry": {"coordinates":[-93.52994099999999,41.621834],"type":"Point"}
}