{
  "type": "Feature",
  "properties": {
    "iso:country":"US",
    "sg:address":"4258 130th St",
    "sg:city":"Thornton",
    "sg:classifiers":[
        {
            "category":"Farming",
            "subcategory":"Livestock Farm",
            "type":"Manufacturing & Wholesale Goods"
        }
    ],
    "sg:phone":"+1 641 998 2108",
    "sg:postcode":"50479",
    "sg:province":"IA",
    "sg:tags":[
        "hog",
        "or",
        "feedlot"
    ],
    "wof:name":"Bruce Wonsmos",
    "wof:placetype":"venue"
},
  "geometry": {"coordinates":[-93.433762,42.951785],"type":"Point"}
}