{
  "type": "Feature",
  "properties": {
    "iso:country":"US",
    "sg:address":"103 E State St",
    "sg:city":"Mason City",
    "sg:classifiers":[
        {
            "category":"Social Services",
            "type":"Services"
        }
    ],
    "sg:phone":"+1 641 380 0443",
    "sg:postcode":"50401",
    "sg:province":"IA",
    "sg:tags":[
        "organization",
        "welfare"
    ],
    "wof:name":"Lutheran Services In Iowa",
    "wof:placetype":"venue"
},
  "geometry": {"coordinates":[-93.19940200000001,43.151735],"type":"Point"}
}