{
  "type": "Feature",
  "properties": {
    "iso:country":"US",
    "sg:address":"5072 Taft Ave SE",
    "sg:city":"Iowa City",
    "sg:phone":"+1 319 351 8596",
    "sg:postcode":"52240",
    "sg:province":"IA",
    "sg:tags":[
        "farm",
        "corn"
    ],
    "wof:name":"Ronald Waldschmidt",
    "wof:placetype":"venue"
},
  "geometry": {"coordinates":[-91.464259,41.56392],"type":"Point"}
}