{
  "type": "Feature",
  "properties": {
    "addr:full":"3024 Roblang Ct Des Moines IA 50317",
    "addr:housenumber":"3024",
    "addr:postcode":"50317",
    "addr:street":"Roblang Ct",
    "iso:country":"US",
    "sg:address":"3024 Roblang Ct",
    "sg:city":"Des Moines",
    "sg:classifiers":[
        {
            "category":"Arts & Performance",
            "subcategory":"Theater",
            "type":"Entertainment"
        }
    ],
    "sg:phone":"+1 515 299 5100",
    "sg:postcode":"50317",
    "sg:province":"IA",
    "sg:tags":[
        "entertainer",
        "business"
    ],
    "wof:name":"Raccoon Road Gang",
    "wof:placetype":"venue"
},
  "geometry": {"coordinates":[-93.559299,41.623888],"type":"Point"}
}