{
  "type": "Feature",
  "properties": {
    "iso:country":"US",
    "sg:address":"113 N Hall St",
    "sg:city":"Algona",
    "sg:classifiers":[
        {
            "category":"Real Estate",
            "subcategory":"Real Estate Services",
            "type":"Services"
        }
    ],
    "sg:phone":"+1 515 295 3745",
    "sg:postcode":"50511",
    "sg:province":"IA",
    "wof:name":"Kossuth Abstract & Title Co",
    "wof:placetype":"venue"
},
  "geometry": {"coordinates":[-94.23927,43.069723],"type":"Point"}
}