{
  "type": "Feature",
  "properties": {
    "iso:country":"US",
    "sg:address":"2100 Asbury Rd",
    "sg:city":"Dubuque",
    "sg:classifiers":[
        {
            "category":"Professional",
            "subcategory":"Lawyer & Legal Services",
            "type":"Services"
        }
    ],
    "sg:phone":"+1 563 582 7980",
    "sg:postcode":"52001",
    "sg:province":"IA",
    "sg:tags":[
        "attorney"
    ],
    "wof:name":"KANE Norby & Reddick",
    "wof:placetype":"venue"
},
  "geometry": {"coordinates":[-90.70059500000001,42.504325],"type":"Point"}
}