{
  "type": "Feature",
  "properties": {
    "iso:country":"US",
    "sg:address":"405 S Dubuque St",
    "sg:city":"Anamosa",
    "sg:classifiers":[
        {
            "category":"Social Services",
            "subcategory":"Child Care",
            "type":"Services"
        }
    ],
    "sg:phone":"+1 319 462 4802",
    "sg:postcode":"52205",
    "sg:province":"IA",
    "sg:tags":[
        "day"
    ],
    "wof:name":"Mel Kray Inc",
    "wof:placetype":"venue"
},
  "geometry": {"coordinates":[-91.274647,42.103986],"type":"Point"}
}