{
  "type": "Feature",
  "properties": {
    "iso:country":"US",
    "sg:address":"113 4th Ave S",
    "sg:city":"Clinton",
    "sg:classifiers":[
        {
            "category":"Personal",
            "type":"Services"
        }
    ],
    "sg:phone":"+1 563 242 7295",
    "sg:postcode":"52732",
    "sg:province":"IA",
    "sg:tags":[
        "therapist",
        "massage"
    ],
    "wof:name":"Van Kampen Therapeutic Massage",
    "wof:placetype":"venue"
},
  "geometry": {"coordinates":[-90.188023,41.84226],"type":"Point"}
}