{
  "type": "Feature",
  "properties": {
    "addr:full":"612 3rd St Underwood IA 51576",
    "addr:housenumber":"612",
    "addr:postcode":"51576",
    "addr:street":"3Rd St",
    "iso:country":"US",
    "sg:address":"612 3rd St",
    "sg:city":"Underwood",
    "sg:classifiers":[
        {
            "category":"Building & Trades",
            "subcategory":"Plumbing",
            "type":"Services"
        }
    ],
    "sg:phone":"+1 712 566 2087",
    "sg:postcode":"51576",
    "sg:province":"IA",
    "sg:tags":[
        "plumbing",
        "contractor"
    ],
    "wof:name":"KERR Plumbing & Heating",
    "wof:placetype":"venue"
},
  "geometry": {"coordinates":[-95.68512200000001,41.387041],"type":"Point"}
}