{
  "type": "Feature",
  "properties": {
    "iso:country":"US",
    "sg:address":"1454 30th St",
    "sg:city":"West Des Moines",
    "sg:classifiers":[
        {
            "category":"Professional",
            "subcategory":"Engineering",
            "type":"Services"
        }
    ],
    "sg:phone":"+1 515 224 6300",
    "sg:postcode":"50266",
    "sg:province":"IA",
    "sg:tags":[
        "engineer"
    ],
    "wof:name":"Krishna Engineering Consultant",
    "wof:placetype":"venue"
},
  "geometry": {"coordinates":[-93.74592199999999,41.595434],"type":"Point"}
}