{
  "type": "Feature",
  "properties": {
    "iso:country":"US",
    "sg:address":"110 Fox St SE",
    "sg:city":"Cascade",
    "sg:classifiers":[
        {
            "category":"Building & Trades",
            "subcategory":"Construction",
            "type":"Services"
        }
    ],
    "sg:phone":"+1 563 852 3048",
    "sg:postcode":"52033",
    "sg:province":"IA",
    "sg:tags":[
        "general",
        "contractor"
    ],
    "wof:name":"Beck Construction",
    "wof:placetype":"venue"
},
  "geometry": {"coordinates":[-90.995487,42.305703],"type":"Point"}
}