{
  "type": "Feature",
  "properties": {
    "iso:country":"US",
    "sg:address":"701 Highway St",
    "sg:city":"Underwood",
    "sg:classifiers":[
        {
            "category":"Wholesale",
            "subcategory":"Farm Supplies",
            "type":"Manufacturing & Wholesale Goods"
        }
    ],
    "sg:phone":"+1 712 566 2313",
    "sg:postcode":"51576",
    "sg:province":"IA",
    "sg:tags":[
        "fertilizer"
    ],
    "wof:name":"Agriland FS Inc",
    "wof:placetype":"venue"
},
  "geometry": {"coordinates":[-95.684674,41.378648],"type":"Point"}
}