{
  "type": "Feature",
  "properties": {
    "iso:country":"US",
    "sg:address":"12457 Y Camp Rd",
    "sg:city":"Burlington",
    "sg:classifiers":[
        {
            "category":"Wholesale",
            "subcategory":"Sporting Goods",
            "type":"Manufacturing & Wholesale Goods"
        }
    ],
    "sg:phone":"+1 319 753 5497",
    "sg:postcode":"52601",
    "sg:province":"IA",
    "sg:tags":[
        "paint",
        "game",
        "ball"
    ],
    "wof:name":"Jokers Wild Paintball Inc",
    "wof:placetype":"venue"
},
  "geometry": {"coordinates":[-91.114458,40.862811],"type":"Point"}
}