{
  "type": "Feature",
  "properties": {
    "iso:country":"US",
    "sg:address":"2410 Ave B",
    "sg:city":"Council Bluffs",
    "sg:classifiers":[
        {
            "category":"Building & Trades",
            "subcategory":"Construction",
            "type":"Services"
        }
    ],
    "sg:phone":"+1 712 328 7003",
    "sg:postcode":"51501",
    "sg:province":"IA",
    "sg:tags":[
        "insulation",
        "heat",
        "contractor"
    ],
    "wof:name":"A-1 Insulation",
    "wof:placetype":"venue"
},
  "geometry": {"coordinates":[-95.881669,41.263802],"type":"Point"}
}