{
  "type": "Feature",
  "properties": {
    "addr:full":"104 N Oak St Richland IA 52585",
    "addr:housenumber":"104",
    "addr:postcode":"52585",
    "addr:street":"N Oak St",
    "iso:country":"US",
    "sg:address":"104 N Oak St",
    "sg:city":"Richland",
    "sg:classifiers":[
        {
            "category":"Restaurant",
            "type":"Food & Drink"
        }
    ],
    "sg:phone":"+1 319 456 2008",
    "sg:postcode":"52585",
    "sg:province":"IA",
    "wof:name":"End Zone",
    "wof:placetype":"venue"
},
  "geometry": {"coordinates":[-91.993224,41.183968],"type":"Point"}
}