{
  "type": "Feature",
  "properties": {
    "iso:country":"US",
    "sg:address":"16 11th St SW",
    "sg:city":"Spencer",
    "sg:classifiers":[
        {
            "category":"Restaurant",
            "type":"Food & Drink"
        }
    ],
    "sg:phone":"+1 712 262 7540",
    "sg:postcode":"51301",
    "sg:province":"IA",
    "sg:tags":[
        "caterer"
    ],
    "wof:name":"Country Kitchen",
    "wof:placetype":"venue"
},
  "geometry": {"coordinates":[-95.14664500000001,43.126522],"type":"Point"}
}