{
  "type": "Feature",
  "properties": {
    "iso:country":"US",
    "sg:address":"113 Centennial Dr",
    "sg:city":"Mediapolis",
    "sg:classifiers":[
        {
            "category":"Farming",
            "subcategory":"Farm",
            "type":"Manufacturing & Wholesale Goods"
        }
    ],
    "sg:phone":"+1 319 394 3725",
    "sg:postcode":"52637",
    "sg:province":"IA",
    "sg:tags":[
        "crop",
        "general"
    ],
    "wof:name":"Mike Oberman",
    "wof:placetype":"venue"
},
  "geometry": {"coordinates":[-91.154634,41.006061],"type":"Point"}
}