{
  "type": "Feature",
  "properties": {
    "iso:country":"US",
    "sg:address":"418 1st St SW",
    "sg:city":"Cedar Rapids",
    "sg:classifiers":[
        {
            "category":"Home & Garden",
            "subcategory":"Household Appliances",
            "type":"Retail Goods"
        }
    ],
    "sg:phone":"+1 319 365 3075",
    "sg:postcode":"52404",
    "sg:province":"IA",
    "sg:tags":[
        "fabric",
        "sewing",
        "machine",
        "parts",
        "vacuum",
        "notion"
    ],
    "wof:name":"West Side Sewing & Fabric Ctr",
    "wof:placetype":"venue"
},
  "geometry": {"coordinates":[-91.67083,41.972906],"type":"Point"}
}