{
  "type": "Feature",
  "properties": {
    "iso:country":"US",
    "sg:address":"107 S Delaware Ave",
    "sg:city":"Mason City",
    "sg:classifiers":[
        {
            "category":"Banks & Credit Unions",
            "subcategory":"Bank",
            "type":"Services"
        }
    ],
    "sg:phone":"+1 641 424 2225",
    "sg:postcode":"50401",
    "sg:province":"IA",
    "sg:tags":[
        "escrow"
    ],
    "wof:name":"Escrow Plus Inc",
    "wof:placetype":"venue"
},
  "geometry": {"coordinates":[-93.199353,43.150827],"type":"Point"}
}