{
  "type": "Feature",
  "properties": {
    "addr:full":"7192 S 104th Ave E Reasnor IA 50232",
    "addr:housenumber":"7192",
    "addr:postcode":"50232",
    "addr:street":"S 104Th Ave E Reasnor",
    "iso:country":"US",
    "sg:address":"7192 S 104th Ave E",
    "sg:city":"Reasnor",
    "sg:classifiers":[
        {
            "category":"Farming",
            "subcategory":"Livestock Farm",
            "type":"Manufacturing & Wholesale Goods"
        }
    ],
    "sg:phone":"+1 641 793 2779",
    "sg:postcode":"50232",
    "sg:province":"IA",
    "sg:tags":[
        "corn",
        "soybean",
        "general"
    ],
    "wof:name":"Raymond Veenstra",
    "wof:placetype":"venue"
},
  "geometry": {"coordinates":[-92.96414,41.551879],"type":"Point"}
}