{
  "type": "Feature",
  "properties": {
    "addr:full":"2501 SE Creekview Dr Ankeny IA 50021",
    "addr:housenumber":"2501",
    "addr:postcode":"50021",
    "addr:street":"Se Creekview Dr",
    "iso:country":"US",
    "sg:address":"2501 SE Creekview Dr",
    "sg:city":"Ankeny",
    "sg:classifiers":[
        {
            "category":"Social Services",
            "subcategory":"Child Care",
            "type":"Services"
        }
    ],
    "sg:phone":"+1 515 964 3060",
    "sg:postcode":"50021",
    "sg:province":"IA",
    "wof:name":"Tender Years Day Care",
    "wof:placetype":"venue"
},
  "geometry": {"coordinates":[-93.571635,41.70297],"type":"Point"}
}