{
  "type": "Feature",
  "properties": {
    "iso:country":"US",
    "sg:address":"809 Clark St",
    "sg:city":"Charles City",
    "sg:classifiers":[
        {
            "category":"Banks & Credit Unions",
            "subcategory":"Bank",
            "type":"Services"
        }
    ],
    "sg:phone":"+1 641 257 1212",
    "sg:postcode":"50616",
    "sg:province":"IA",
    "sg:tags":[
        "loan"
    ],
    "wof:name":"First Security Investment Sec",
    "wof:placetype":"venue"
},
  "geometry": {"coordinates":[-92.677143,43.066636],"type":"Point"}
}