{
  "type": "Feature",
  "properties": {
    "iso:country":"US",
    "sg:address":"521 Main St",
    "sg:city":"Keokuk",
    "sg:classifiers":[
        {
            "category":"Shopping",
            "subcategory":"Bicycles & Sporting Goods",
            "type":"Retail Goods"
        }
    ],
    "sg:phone":"+1 319 524 9808",
    "sg:postcode":"52632",
    "sg:province":"IA",
    "wof:name":"Athletic Center",
    "wof:placetype":"venue"
},
  "geometry": {"coordinates":[-91.383883,40.396445],"type":"Point"}
}