{
  "type": "Feature",
  "properties": {
    "iso:country":"US",
    "sg:address":"114 Iowa Ave",
    "sg:city":"Dunlap",
    "sg:classifiers":[
        {
            "category":"Manufacturing",
            "subcategory":"Printing",
            "type":"Manufacturing & Wholesale Goods"
        }
    ],
    "sg:phone":"+1 712 643 5380",
    "sg:postcode":"51529",
    "sg:province":"IA",
    "sg:tags":[
        "newspaper"
    ],
    "sg:website":"www.dunlapiowa.com",
    "wof:name":"Dunlap Reporter",
    "wof:placetype":"venue"
},
  "geometry": {"coordinates":[-95.60212199999999,41.854273],"type":"Point"}
}