{
  "type": "Feature",
  "properties": {
    "iso:country":"US",
    "sg:address":"201 Reed St",
    "sg:city":"Akron",
    "sg:classifiers":[
        {
            "category":"Organizations",
            "subcategory":"Community Association",
            "type":"Services"
        }
    ],
    "sg:phone":"+1 712 568 3000",
    "sg:postcode":"51001",
    "sg:province":"IA",
    "sg:tags":[
        "military"
    ],
    "wof:name":"Legion Club",
    "wof:placetype":"venue"
},
  "geometry": {"coordinates":[-96.55828700000001,42.828737],"type":"Point"}
}