{
  "type": "Feature",
  "properties": {
    "iso:country":"US",
    "sg:address":"685 Marion Blvd",
    "sg:city":"Marion",
    "sg:classifiers":[
        {
            "category":"Restaurant",
            "type":"Food & Drink"
        }
    ],
    "sg:phone":"+1 319 447 1414",
    "sg:postcode":"52302",
    "sg:province":"IA",
    "sg:tags":[
        "italian"
    ],
    "sg:website":"www.cibofusion.com",
    "wof:name":"Cibo Fusion Restaurant & Lounge",
    "wof:placetype":"venue"
},
  "geometry": {"coordinates":[-91.617172,42.027853],"type":"Point"}
}