{
  "type": "Feature",
  "properties": {
    "iso:country":"US",
    "sg:address":"413 N Federal Ave",
    "sg:city":"Mason City",
    "sg:classifiers":[
        {
            "category":"Taxi",
            "type":"Transportation"
        }
    ],
    "sg:phone":"+1 641 423 4167",
    "sg:postcode":"50401",
    "sg:province":"IA",
    "sg:tags":[
        "taxicab"
    ],
    "wof:name":"K C Cab Co",
    "wof:placetype":"venue"
},
  "geometry": {"coordinates":[-93.200987,43.156217],"type":"Point"}
}