{
  "type": "Feature",
  "properties": {
    "iso:country":"US",
    "sg:address":"203 N Monroe St",
    "sg:city":"Monroe",
    "sg:classifiers":[
        {
            "category":"Autos & Motor Vehicles",
            "subcategory":"Automobile Sales",
            "type":"Retail Goods"
        }
    ],
    "sg:phone":"+1 641 259 2051",
    "sg:postcode":"50170",
    "sg:province":"IA",
    "sg:tags":[
        "car",
        "dealer"
    ],
    "wof:name":"Malone Motorsports",
    "wof:placetype":"venue"
},
  "geometry": {"coordinates":[-93.101715,41.523268],"type":"Point"}
}