{
  "type": "Feature",
  "properties": {
    "addr:full":"410 5th St SW Mason City IA 50401",
    "addr:housenumber":"410",
    "addr:postcode":"50401",
    "addr:street":"5Th St Sw",
    "iso:country":"US",
    "sg:address":"410 5th St SW",
    "sg:city":"Mason City",
    "sg:classifiers":[
        {
            "category":"Travel",
            "subcategory":"Hotels & Motels",
            "type":"Entertainment"
        }
    ],
    "sg:phone":"+1 641 423 4444",
    "sg:postcode":"50401",
    "sg:province":"IA",
    "wof:name":"Comfort Inn",
    "wof:placetype":"venue"
},
  "geometry": {"coordinates":[-93.20817099999999,43.147406],"type":"Point"}
}