{
  "type": "Feature",
  "properties": {
    "iso:country":"US",
    "sg:address":"4817 University Ave",
    "sg:city":"Des Moines",
    "sg:classifiers":[
        {
            "category":"Personal",
            "type":"Services"
        },
        {
            "category":"Personal",
            "subcategory":"Tattoo Parlor",
            "type":"Services"
        }
    ],
    "sg:phone":"+1 515 277 8288",
    "sg:postcode":"50311",
    "sg:province":"IA",
    "sg:tags":[
        "tattooing"
    ],
    "wof:name":"Creative Images",
    "wof:placetype":"venue"
},
  "geometry": {"coordinates":[-93.684467,41.60045],"type":"Point"}
}