{
  "type": "Feature",
  "properties": {
    "addr:full":"28374 210th St Harper IA 52231",
    "addr:housenumber":"28374",
    "addr:postcode":"52231",
    "addr:street":"210Th St",
    "iso:country":"US",
    "sg:address":"28374 210th St",
    "sg:city":"Harper",
    "sg:phone":"+1 641 635 2178",
    "sg:postcode":"52231",
    "sg:province":"IA",
    "sg:tags":[
        "hog",
        "beef",
        "farm",
        "corn",
        "soybean",
        "cattle",
        "or",
        "feedlot"
    ],
    "wof:name":"Elbern Inc",
    "wof:placetype":"venue"
},
  "geometry": {"coordinates":[-92.06063899999999,41.351613],"type":"Point"}
}