{
  "type": "Feature",
  "properties": {
    "addr:full":"340 SE Delaware Ave Ankeny IA 50021",
    "addr:housenumber":"340",
    "addr:postcode":"50021",
    "addr:street":"Se Delaware Ave",
    "iso:country":"US",
    "sg:address":"340 SE Delaware Ave",
    "sg:city":"Ankeny",
    "sg:classifiers":[
        {
            "category":"Health Services",
            "subcategory":"Doctor",
            "type":"Services"
        }
    ],
    "sg:phone":"+1 515 964 5482",
    "sg:postcode":"50021",
    "sg:province":"IA",
    "sg:tags":[
        "dentist"
    ],
    "wof:name":"Ankeny Family Dental Care",
    "wof:placetype":"venue"
},
  "geometry": {"coordinates":[-93.581197,41.729241],"type":"Point"}
}