{
  "type": "Feature",
  "properties": {
    "iso:country":"US",
    "sg:address":"1028 E 11th St",
    "sg:city":"Carroll",
    "sg:classifiers":[
        {
            "category":"Government",
            "subcategory":"Office",
            "type":"Public Place"
        }
    ],
    "sg:phone":"+1 712 792 3324",
    "sg:postcode":"51401",
    "sg:province":"IA",
    "sg:tags":[
        "village"
    ],
    "wof:name":"Park Maintenance Garage",
    "wof:placetype":"venue"
},
  "geometry": {"coordinates":[-94.851409,42.070493],"type":"Point"}
}