{
  "type": "Feature",
  "properties": {
    "iso:country":"US",
    "sg:address":"219 N Gilbert St",
    "sg:city":"Iowa City",
    "sg:classifiers":[
        {
            "category":"Shopping",
            "subcategory":"Used Merchandise",
            "type":"Retail Goods"
        }
    ],
    "sg:phone":"+1 319 338 3077",
    "sg:postcode":"52245",
    "sg:province":"IA",
    "sg:tags":[
        "book",
        "rare",
        "dealer"
    ],
    "wof:name":"Murphy-Brookfield Books",
    "wof:placetype":"venue"
},
  "geometry": {"coordinates":[-91.530198,41.664465],"type":"Point"}
}