{
  "type": "Feature",
  "properties": {
    "addr:full":"1501 NE Broadway Ave Des Moines IA 50313",
    "addr:housenumber":"1501",
    "addr:postcode":"50313",
    "addr:street":"Ne Broadway Ave",
    "iso:country":"US",
    "sg:address":"1501 NE Broadway Ave",
    "sg:city":"Des Moines",
    "sg:classifiers":[
        {
            "category":"Wholesale",
            "subcategory":"Machinery & Supplies",
            "type":"Manufacturing & Wholesale Goods"
        }
    ],
    "sg:phone":"+1 515 266 1111",
    "sg:postcode":"50313",
    "sg:province":"IA",
    "sg:tags":[
        "equipment",
        "welding"
    ],
    "wof:name":"Airgas",
    "wof:placetype":"venue"
},
  "geometry": {"coordinates":[-93.59941600000001,41.643978],"type":"Point"}
}