{
  "type": "Feature",
  "properties": {
    "iso:country":"US",
    "sg:address":"2394 113 St",
    "sg:city":"Tabor",
    "sg:classifiers":[
        {
            "category":"Farming",
            "subcategory":"Farm",
            "type":"Manufacturing & Wholesale Goods"
        }
    ],
    "sg:phone":"+1 712 629 1232",
    "sg:postcode":"51653",
    "sg:province":"IA",
    "sg:tags":[
        "crop",
        "general"
    ],
    "wof:name":"Plug A Long Farms Inc",
    "wof:placetype":"venue"
},
  "geometry": {"coordinates":[-95.72976300000001,40.883272],"type":"Point"}
}