{
  "type": "Feature",
  "properties": {
    "iso:country":"US",
    "sg:address":"6671 State Hwy 10",
    "sg:city":"Sutherland",
    "sg:classifiers":[
        {
            "category":"Farming",
            "subcategory":"Farm",
            "type":"Manufacturing & Wholesale Goods"
        }
    ],
    "sg:phone":"+1 712 446 3400",
    "sg:postcode":"51058",
    "sg:province":"IA",
    "sg:tags":[
        "crop",
        "general"
    ],
    "wof:name":"Mark Drefke",
    "wof:placetype":"venue"
},
  "geometry": {"coordinates":[-95.47320499999999,42.946166],"type":"Point"}
}