{
  "type": "Feature",
  "properties": {
    "addr:full":"125 US Hwy 30 Lisbon IA 52253",
    "addr:housenumber":"125",
    "addr:postcode":"52253",
    "addr:street":"Us Hwy 30",
    "iso:country":"US",
    "sg:address":"125 US Hwy 30",
    "sg:city":"Lisbon",
    "sg:classifiers":[
        {
            "category":"Bars & Pubs",
            "type":"Food & Drink"
        }
    ],
    "sg:phone":"+1 319 455 3187",
    "sg:postcode":"52253",
    "sg:province":"IA",
    "wof:name":"Abe's Pub & Grub",
    "wof:placetype":"venue"
},
  "geometry": {"coordinates":[-91.342167,41.918365],"type":"Point"}
}