{
  "type": "Feature",
  "properties": {
    "iso:country":"US",
    "sg:address":"300 N Pine St",
    "sg:city":"Creston",
    "sg:classifiers":[
        {
            "category":"Government",
            "subcategory":"Office",
            "type":"Public Place"
        }
    ],
    "sg:phone":"+1 641 782 1710",
    "sg:postcode":"50801",
    "sg:province":"IA",
    "sg:tags":[
        "county",
        "taxation"
    ],
    "wof:name":"Union County Treasurer",
    "wof:placetype":"venue"
},
  "geometry": {"coordinates":[-94.361492,41.060958],"type":"Point"}
}