{
  "type": "Feature",
  "properties": {
    "iso:country":"US",
    "sg:address":"2703 Indiana Ave",
    "sg:city":"Callender",
    "sg:classifiers":[
        {
            "category":"Building & Trades",
            "subcategory":"Equipment Rental",
            "type":"Services"
        }
    ],
    "sg:phone":"+1 515 571 9747",
    "sg:postcode":"50523",
    "sg:province":"IA",
    "sg:tags":[
        "toilet"
    ],
    "wof:name":"Jeff's Jons",
    "wof:placetype":"venue"
},
  "geometry": {"coordinates":[-94.24261199999999,42.397745],"type":"Point"}
}