{
  "type": "Feature",
  "properties": {
    "addr:full":"320 S 25th St Fort Dodge IA 50501",
    "addr:housenumber":"320",
    "addr:postcode":"50501",
    "addr:street":"S 25Th St",
    "iso:country":"US",
    "sg:address":"320 S 25th St",
    "sg:city":"Fort Dodge",
    "sg:classifiers":[
        {
            "category":"Shopping",
            "subcategory":"Bicycles & Sporting Goods",
            "type":"Retail Goods"
        }
    ],
    "sg:phone":"+1 515 573 3702",
    "sg:postcode":"50501",
    "sg:province":"IA",
    "sg:tags":[
        "equipment",
        "golf",
        "supply"
    ],
    "wof:name":"Stiles Golf Bowling & Trophies",
    "wof:placetype":"venue"
},
  "geometry": {"coordinates":[-94.163122,42.503034],"type":"Point"}
}