{
  "type": "Feature",
  "properties": {
    "addr:full":"2355 NW 126th Ave Polk City IA 50226",
    "addr:housenumber":"2355",
    "addr:postcode":"50226",
    "addr:street":"Nw 126Th Ave",
    "iso:country":"US",
    "sg:address":"2355 NW 126th Ave",
    "sg:city":"Polk City",
    "sg:phone":"+1 515 685 3395",
    "sg:postcode":"50226",
    "sg:province":"IA",
    "sg:tags":[
        "farm",
        "corn",
        "soybean"
    ],
    "wof:name":"Steve Kamps",
    "wof:placetype":"venue"
},
  "geometry": {"coordinates":[-93.649281,41.791457],"type":"Point"}
}