{
  "type": "Feature",
  "properties": {
    "iso:country":"US",
    "sg:address":"3428 Walden Ave",
    "sg:city":"Sioux City",
    "sg:classifiers":[
        {
            "category":"Freight",
            "type":"Transportation"
        }
    ],
    "sg:phone":"+1 712 276 3342",
    "sg:postcode":"51106",
    "sg:province":"IA",
    "sg:tags":[
        "trucking"
    ],
    "wof:name":"Christy Road Enterprises Inc",
    "wof:placetype":"venue"
},
  "geometry": {"coordinates":[-96.361789,42.452051],"type":"Point"}
}