{
  "type": "Feature",
  "properties": {
    "iso:country":"US",
    "sg:address":"1150 Polk Blvd",
    "sg:city":"Des Moines",
    "sg:classifiers":[
        {
            "category":"Restaurant",
            "type":"Food & Drink"
        }
    ],
    "sg:phone":"+1 515 277 1718",
    "sg:postcode":"50311",
    "sg:province":"IA",
    "sg:tags":[
        "delicatessen"
    ],
    "wof:name":"Maccabee's Glatt Kosher Deli",
    "wof:placetype":"venue"
},
  "geometry": {"coordinates":[-93.681809,41.598788],"type":"Point"}
}