{
  "type": "Feature",
  "properties": {
    "addr:full":"23708 300th St Parkersburg IA 50665",
    "addr:housenumber":"23708",
    "addr:postcode":"50665",
    "addr:street":"300Th St",
    "iso:country":"US",
    "sg:address":"23708 300th St",
    "sg:city":"Parkersburg",
    "sg:classifiers":[
        {
            "category":"Farming",
            "subcategory":"Farm",
            "type":"Manufacturing & Wholesale Goods"
        }
    ],
    "sg:phone":"+1 319 346 2293",
    "sg:postcode":"50665",
    "sg:province":"IA",
    "sg:tags":[
        "crop",
        "general"
    ],
    "wof:name":"Gerald Haan",
    "wof:placetype":"venue"
},
  "geometry": {"coordinates":[-92.76047699999999,42.613812],"type":"Point"}
}