{
  "type": "Feature",
  "properties": {
    "iso:country":"US",
    "sg:address":"505 5th Ave",
    "sg:city":"Des Moines",
    "sg:classifiers":[
        {
            "category":"Insurance",
            "subcategory":"Insurance Agent",
            "type":"Services"
        }
    ],
    "sg:phone":"+1 515 243 1146",
    "sg:postcode":"50309",
    "sg:province":"IA",
    "wof:name":"Peverill Capital Planning",
    "wof:placetype":"venue"
},
  "geometry": {"coordinates":[-93.624364,41.589547],"type":"Point"}
}