{
  "type": "Feature",
  "properties": {
    "iso:country":"US",
    "sg:address":"2302 SW 3rd St",
    "sg:city":"Ankeny",
    "sg:classifiers":[
        {
            "category":"Professional",
            "subcategory":"Research",
            "type":"Services"
        }
    ],
    "sg:phone":"+1 515 964 7378",
    "sg:postcode":"50021",
    "sg:province":"IA",
    "sg:tags":[
        "market",
        "analysis"
    ],
    "sg:website":"www.grapentine.com",
    "wof:name":"Grapentine Co",
    "wof:placetype":"venue"
},
  "geometry": {"coordinates":[-93.630326,41.729686],"type":"Point"}
}