{
  "type": "Feature",
  "properties": {
    "iso:country":"US",
    "sg:address":"4169 US 75 Ave",
    "sg:city":"Sioux Center",
    "sg:classifiers":[
        {
            "category":"Wholesale",
            "subcategory":"Machinery & Supplies",
            "type":"Manufacturing & Wholesale Goods"
        }
    ],
    "sg:phone":"+1 712 722 3770",
    "sg:postcode":"51250",
    "sg:province":"IA",
    "sg:tags":[
        "farm",
        "equipment"
    ],
    "wof:name":"Hog Slat Inc",
    "wof:placetype":"venue"
},
  "geometry": {"coordinates":[-96.175298,43.04394],"type":"Point"}
}