{
  "type": "Feature",
  "properties": {
    "iso:country":"US",
    "sg:address":"610 31st St SE",
    "sg:city":"Cedar Rapids",
    "sg:classifiers":[
        {
            "category":"Organizations",
            "subcategory":"Religious Organization",
            "type":"Services"
        }
    ],
    "sg:phone":"+1 319 364 2637",
    "sg:postcode":"52403",
    "sg:province":"IA",
    "wof:name":"St Stephen's Lutheran Church Elca",
    "wof:placetype":"venue"
},
  "geometry": {"coordinates":[-91.622902,41.980301],"type":"Point"}
}