{
  "type": "Feature",
  "properties": {
    "iso:country":"US",
    "sg:address":"445 State Hwy 92",
    "sg:city":"Prole",
    "sg:classifiers":[
        {
            "category":"Building & Trades",
            "subcategory":"Landscaping Services",
            "type":"Services"
        }
    ],
    "sg:phone":"+1 515 961 2535",
    "sg:postcode":"50229",
    "sg:province":"IA",
    "sg:tags":[
        "lawn",
        "maintenance",
        "grounds"
    ],
    "wof:name":"G & M Turf Svc",
    "wof:placetype":"venue"
},
  "geometry": {"coordinates":[-93.73145100000001,41.36637],"type":"Point"}
}