{
  "type": "Feature",
  "properties": {
    "iso:country":"US",
    "sg:address":"506 3rd St NW",
    "sg:city":"Fort Dodge",
    "sg:classifiers":[
        {
            "category":"Shopping",
            "subcategory":"Computers & Home Electronics",
            "type":"Retail Goods"
        }
    ],
    "sg:phone":"+1 515 576 3585",
    "sg:postcode":"50501",
    "sg:province":"IA",
    "wof:name":"Palmer Computer Sales & Svc",
    "wof:placetype":"venue"
},
  "geometry": {"coordinates":[-94.202977,42.519721],"type":"Point"}
}