{
  "type": "Feature",
  "properties": {
    "iso:country":"US",
    "sg:address":"1005 Fairchild St",
    "sg:city":"Iowa City",
    "sg:classifiers":[
        {
            "category":"Freight",
            "type":"Transportation"
        }
    ],
    "sg:phone":"+1 319 430 5605",
    "sg:postcode":"52245",
    "sg:province":"IA",
    "sg:tags":[
        "special"
    ],
    "wof:name":"Wades Storage Rentals",
    "wof:placetype":"venue"
},
  "geometry": {"coordinates":[-91.52111600000001,41.666727],"type":"Point"}
}