{
  "type": "Feature",
  "properties": {
    "iso:country":"US",
    "sg:address":"203 N 6th St",
    "sg:city":"Estherville",
    "sg:classifiers":[
        {
            "category":"Freight",
            "type":"Transportation"
        }
    ],
    "sg:phone":"+1 712 362 4689",
    "sg:postcode":"51334",
    "sg:province":"IA",
    "sg:tags":[
        "commercial",
        "storage"
    ],
    "wof:name":"ETM Storage",
    "wof:placetype":"venue"
},
  "geometry": {"coordinates":[-94.83682,43.404813],"type":"Point"}
}