{
  "type": "Feature",
  "properties": {
    "iso:country":"US",
    "sg:address":"945 US Hwy 30",
    "sg:city":"Lisbon",
    "sg:classifiers":[
        {
            "category":"Freight",
            "type":"Transportation"
        }
    ],
    "sg:phone":"+1 319 895 8899",
    "sg:postcode":"52253",
    "sg:province":"IA",
    "sg:tags":[
        "commercial",
        "storage"
    ],
    "wof:name":"Discount Storage",
    "wof:placetype":"venue"
},
  "geometry": {"coordinates":[-91.401617,41.917205],"type":"Point"}
}