{
  "type": "Feature",
  "properties": {
    "iso:country":"US",
    "sg:address":"118 S Chestnut St",
    "sg:city":"Jefferson",
    "sg:classifiers":[
        {
            "category":"Sports & Exercise",
            "subcategory":"Bowling",
            "type":"Entertainment"
        }
    ],
    "sg:phone":"+1 515 386 9119",
    "sg:postcode":"50129",
    "sg:province":"IA",
    "sg:tags":[
        "center"
    ],
    "wof:name":"Spare Time Lanes & Lounge",
    "wof:placetype":"venue"
},
  "geometry": {"coordinates":[-94.373498,42.015102],"type":"Point"}
}