{
  "type": "Feature",
  "properties": {
    "iso:country":"US",
    "sg:address":"1361 US Hwy 34",
    "sg:city":"Batavia",
    "sg:phone":"+1 641 662 2723",
    "sg:postcode":"52533",
    "sg:province":"IA",
    "sg:tags":[
        "farm",
        "corn",
        "soybean"
    ],
    "wof:name":"Dave Shipler",
    "wof:placetype":"venue"
},
  "geometry": {"coordinates":[-92.102034,41.009277],"type":"Point"}
}