{
  "type": "Feature",
  "properties": {
    "iso:country":"US",
    "sg:address":"305 Washington St",
    "sg:city":"La Porte City",
    "sg:classifiers":[
        {
            "category":"Professional",
            "type":"Services"
        }
    ],
    "sg:phone":"+1 319 342 3130",
    "sg:postcode":"50651",
    "sg:province":"IA",
    "sg:tags":[
        "establishment"
    ],
    "wof:name":"Anton Sales",
    "wof:placetype":"venue"
},
  "geometry": {"coordinates":[-92.19755499999999,42.317035],"type":"Point"}
}