{
  "type": "Feature",
  "properties": {
    "iso:country":"US",
    "sg:address":"2419 155th St",
    "sg:city":"Muscatine",
    "sg:classifiers":[
        {
            "category":"Farming",
            "subcategory":"Livestock Farm",
            "type":"Manufacturing & Wholesale Goods"
        }
    ],
    "sg:phone":"+1 563 264 2644",
    "sg:postcode":"52761",
    "sg:province":"IA",
    "sg:tags":[
        "beef",
        "feedlot",
        "cattle"
    ],
    "wof:name":"Frank Nelson",
    "wof:placetype":"venue"
},
  "geometry": {"coordinates":[-91.09617799999999,41.508603],"type":"Point"}
}