{
  "type": "Feature",
  "properties": {
    "iso:country":"US",
    "sg:address":"115 S Jefferson St",
    "sg:city":"Mt Pleasant",
    "sg:classifiers":[
        {
            "category":"Retail",
            "subcategory":"Portrait Studio",
            "type":"Services"
        }
    ],
    "sg:phone":"+1 319 986 5597",
    "sg:postcode":"52641",
    "sg:province":"IA",
    "sg:tags":[
        "photographer"
    ],
    "sg:website":"www.hendphoto.com",
    "wof:name":"Henderson Photography",
    "wof:placetype":"venue"
},
  "geometry": {"coordinates":[-91.55467,40.966543],"type":"Point"}
}