{
  "type": "Feature",
  "properties": {
    "iso:country":"US",
    "sg:address":"516 Maple Rd",
    "sg:city":"Harlan",
    "sg:classifiers":[
        {
            "category":"Government",
            "subcategory":"Office",
            "type":"Public Place"
        }
    ],
    "sg:phone":"+1 712 744 3403",
    "sg:postcode":"51537",
    "sg:province":"IA",
    "sg:tags":[
        "county"
    ],
    "wof:name":"Shelby County Conservation",
    "wof:placetype":"venue"
},
  "geometry": {"coordinates":[-95.322427,41.567715],"type":"Point"}
}