{
  "type": "Feature",
  "properties": {
    "iso:country":"US",
    "sg:address":"6300 Hickman Rd",
    "sg:city":"Windsor Heights",
    "sg:classifiers":[
        {
            "category":"Autos & Motor Vehicles",
            "subcategory":"Fuel & Gas Station",
            "type":"Retail Goods"
        }
    ],
    "sg:phone":"+1 515 278 0389",
    "sg:postcode":"50322",
    "sg:province":"IA",
    "sg:tags":[
        "oil"
    ],
    "wof:name":"Krueger's Amoco",
    "wof:placetype":"venue"
},
  "geometry": {"coordinates":[-93.70455,41.614885],"type":"Point"}
}