{
  "type": "Feature",
  "properties": {
    "iso:country":"US",
    "sg:address":"420 Iowa St",
    "sg:city":"Burlington",
    "sg:classifiers":[
        {
            "category":"Professional",
            "subcategory":"Employment Agencies",
            "type":"Services"
        }
    ],
    "sg:phone":"+1 319 753 3086",
    "sg:postcode":"52601",
    "sg:province":"IA",
    "sg:tags":[
        "consultant",
        "search",
        "executive"
    ],
    "wof:name":"Ploeger Recruiting",
    "wof:placetype":"venue"
},
  "geometry": {"coordinates":[-91.101555,40.818581],"type":"Point"}
}