{
  "type": "Feature",
  "properties": {
    "iso:country":"US",
    "sg:address":"3297 175th St",
    "sg:city":"Lawler",
    "sg:classifiers":[
        {
            "category":"Farming",
            "subcategory":"Livestock Farm",
            "type":"Manufacturing & Wholesale Goods"
        }
    ],
    "sg:phone":"+1 563 776 4071",
    "sg:postcode":"52171",
    "sg:province":"IA",
    "sg:tags":[
        "beef",
        "feedlot",
        "cattle"
    ],
    "wof:name":"Don Jirak Farm",
    "wof:placetype":"venue"
},
  "geometry": {"coordinates":[-92.101899,43.104633],"type":"Point"}
}