{
  "type": "Feature",
  "properties": {
    "addr:full":"726 1st Ave N Fort Dodge IA 50501",
    "addr:housenumber":"726",
    "addr:postcode":"50501",
    "addr:street":"1St Ave N",
    "iso:country":"US",
    "sg:address":"726 1st Ave N",
    "sg:city":"Fort Dodge",
    "sg:classifiers":[
        {
            "category":"Real Estate",
            "subcategory":"Real Estate Agent",
            "type":"Services"
        }
    ],
    "sg:phone":"+1 515 955 1070",
    "sg:postcode":"50501",
    "sg:province":"IA",
    "wof:name":"Daniels Realty & Assoc",
    "wof:placetype":"venue"
},
  "geometry": {"coordinates":[-94.187963,42.506128],"type":"Point"}
}