{
  "type": "Feature",
  "properties": {
    "addr:full":"9901 Douglas Ave Des Moines IA 50322",
    "addr:housenumber":"9901",
    "addr:postcode":"50322",
    "addr:street":"Douglas Ave",
    "iso:country":"US",
    "sg:address":"9901 Douglas Ave",
    "sg:city":"Des Moines",
    "sg:classifiers":[
        {
            "category":"Retail",
            "subcategory":"Auto Repair",
            "type":"Services"
        }
    ],
    "sg:phone":"+1 515 276 8632",
    "sg:postcode":"50322",
    "sg:province":"IA",
    "sg:tags":[
        "repairing",
        "automobile"
    ],
    "wof:name":"Iowa Auto Repair",
    "wof:placetype":"venue"
},
  "geometry": {"coordinates":[-93.754636,41.629497],"type":"Point"}
}