{
  "type": "Feature",
  "properties": {
    "addr:full":"101 W Main St Rembrandt IA 50576",
    "addr:housenumber":"101",
    "addr:postcode":"50576",
    "addr:street":"W Main St",
    "iso:country":"US",
    "sg:address":"101 W Main St",
    "sg:city":"Rembrandt",
    "sg:classifiers":[
        {
            "category":"Food & Beverages",
            "subcategory":"Groceries & Convenience Stores",
            "type":"Retail Goods"
        }
    ],
    "sg:phone":"+1 712 286 6661",
    "sg:postcode":"50576",
    "sg:province":"IA",
    "wof:name":"Town & Country Corner",
    "wof:placetype":"venue"
},
  "geometry": {"coordinates":[-95.16776900000001,42.825486],"type":"Point"}
}