{
  "type": "Feature",
  "properties": {
    "iso:country":"US",
    "sg:address":"19389 Durango Rd",
    "sg:city":"Sherrill",
    "sg:phone":"+1 563 552 1451",
    "sg:postcode":"52073",
    "sg:province":"IA",
    "sg:tags":[
        "farm",
        "corn"
    ],
    "wof:name":"Joseph Banwarth",
    "wof:placetype":"venue"
},
  "geometry": {"coordinates":[-90.756713,42.579931],"type":"Point"}
}