{
  "type": "Feature",
  "properties": {
    "iso:country":"US",
    "sg:address":"111 N Dubuque St",
    "sg:city":"Solon",
    "sg:classifiers":[
        {
            "category":"Retail",
            "subcategory":"Repair Shop",
            "type":"Services"
        }
    ],
    "sg:phone":"+1 319 624 2348",
    "sg:postcode":"52333",
    "sg:province":"IA",
    "sg:tags":[
        "equipment",
        "professional"
    ],
    "wof:name":"Wood Box",
    "wof:placetype":"venue"
},
  "geometry": {"coordinates":[-91.494207,41.807971],"type":"Point"}
}