{
  "type": "Feature",
  "properties": {
    "addr:full":"631 W Washington St Washington IA 52353",
    "addr:housenumber":"631",
    "addr:postcode":"52353",
    "addr:street":"W Washington St",
    "iso:country":"US",
    "sg:address":"631 W Washington St",
    "sg:city":"Washington",
    "sg:classifiers":[
        {
            "category":"Organizations",
            "subcategory":"Community Association",
            "type":"Services"
        }
    ],
    "sg:phone":"+1 319 653 4912",
    "sg:postcode":"52353",
    "sg:province":"IA",
    "wof:name":"Optimist Club of Washington",
    "wof:placetype":"venue"
},
  "geometry": {"coordinates":[-91.698126,41.298346],"type":"Point"}
}