{
  "type": "Feature",
  "properties": {
    "iso:country":"US",
    "sg:address":"503 E 19th St",
    "sg:city":"Spencer",
    "sg:classifiers":[
        {
            "category":"Real Estate",
            "subcategory":"Real Estate Operator",
            "type":"Services"
        }
    ],
    "sg:phone":"+1 712 262 3890",
    "sg:postcode":"51301",
    "sg:province":"IA",
    "sg:tags":[
        "apartment"
    ],
    "wof:name":"Spencer Manor Apartments",
    "wof:placetype":"venue"
},
  "geometry": {"coordinates":[-95.137322,43.157017],"type":"Point"}
}