{
  "type": "Feature",
  "properties": {
    "iso:country":"US",
    "sg:address":"1555 200th St",
    "sg:city":"West Chester",
    "sg:phone":"+1 319 698 4865",
    "sg:postcode":"52359",
    "sg:province":"IA",
    "sg:tags":[
        "farm",
        "corn",
        "soybean"
    ],
    "wof:name":"Roger Greiner Corp",
    "wof:placetype":"venue"
},
  "geometry": {"coordinates":[-91.838584,41.365572],"type":"Point"}
}