{
  "type": "Feature",
  "properties": {
    "addr:full":"520 Dover Ave NE Orange City IA 51041",
    "addr:housenumber":"520",
    "addr:postcode":"51041",
    "addr:street":"Dover Ave Ne",
    "iso:country":"US",
    "sg:address":"520 Dover Ave NE",
    "sg:city":"Orange City",
    "sg:classifiers":[
        {
            "category":"Professional",
            "subcategory":"Secretarial Services",
            "type":"Services"
        }
    ],
    "sg:phone":"+1 712 737 2353",
    "sg:postcode":"51041",
    "sg:province":"IA",
    "sg:tags":[
        "reporting"
    ],
    "wof:name":"Mary Wissink",
    "wof:placetype":"venue"
},
  "geometry": {"coordinates":[-96.052599,43.01134],"type":"Point"}
}