{
  "type": "Feature",
  "properties": {
    "iso:country":"US",
    "sg:address":"1850 Williams Blvd SW",
    "sg:city":"Cedar Rapids",
    "sg:classifiers":[
        {
            "category":"Building & Trades",
            "subcategory":"Construction",
            "type":"Services"
        }
    ],
    "sg:phone":"+1 319 363 5396",
    "sg:postcode":"52404",
    "sg:province":"IA",
    "sg:tags":[
        "house"
    ],
    "wof:name":"Bahndorf Construction",
    "wof:placetype":"venue"
},
  "geometry": {"coordinates":[-91.70022400000001,41.969495],"type":"Point"}
}