{
  "type": "Feature",
  "properties": {
    "iso:country":"US",
    "sg:address":"2701 6th Ave",
    "sg:city":"Des Moines",
    "sg:classifiers":[
        {
            "category":"Building & Trades",
            "subcategory":"Landscaping Services",
            "type":"Services"
        }
    ],
    "sg:phone":"+1 515 244 4564",
    "sg:postcode":"50313",
    "sg:province":"IA",
    "wof:name":"Glaser Lawn Care Inc",
    "wof:placetype":"venue"
},
  "geometry": {"coordinates":[-93.62470999999999,41.619559],"type":"Point"}
}