{
  "type": "Feature",
  "properties": {
    "addr:full":"2318 Whipporwill Hollow Dr Harpers Ferry IA 52146",
    "addr:housenumber":"2318",
    "addr:postcode":"52146",
    "addr:street":"Whipporwill Hollow Dr",
    "iso:country":"US",
    "sg:address":"2318 Whipporwill Hollow Dr",
    "sg:city":"Harpers Ferry",
    "sg:classifiers":[
        {
            "category":"Manufacturing",
            "subcategory":"Buildings",
            "type":"Manufacturing & Wholesale Goods"
        }
    ],
    "sg:phone":"+1 563 586 2774",
    "sg:postcode":"52146",
    "sg:province":"IA",
    "sg:tags":[
        "home",
        "log",
        "cabin"
    ],
    "wof:name":"Baughman Construction",
    "wof:placetype":"venue"
},
  "geometry": {"coordinates":[-91.170124,43.218628],"type":"Point"}
}