{
  "type": "Feature",
  "properties": {
    "iso:country":"US",
    "sg:address":"509 S 3rd Ave",
    "sg:city":"Rock Rapids",
    "sg:classifiers":[
        {
            "category":"Retail",
            "subcategory":"Laundry & Dry Cleaning",
            "type":"Services"
        }
    ],
    "sg:phone":"+1 712 472 3817",
    "sg:postcode":"51246",
    "sg:province":"IA",
    "sg:tags":[
        "cleaners",
        "rug",
        "carpet"
    ],
    "wof:name":"Koel's Carpet Cleaning Svc",
    "wof:placetype":"venue"
},
  "geometry": {"coordinates":[-96.172393,43.429846],"type":"Point"}
}