{
  "type": "Feature",
  "properties": {
    "addr:full":"2835 4th St SE Mason City IA 50401",
    "addr:housenumber":"2835",
    "addr:postcode":"50401",
    "addr:street":"4Th St Se",
    "iso:country":"US",
    "sg:address":"2835 4th St SE",
    "sg:city":"Mason City",
    "sg:classifiers":[
        {
            "category":"Freight",
            "type":"Transportation"
        }
    ],
    "sg:phone":"+1 641 421 4180",
    "sg:postcode":"50401",
    "sg:province":"IA",
    "sg:tags":[
        "commercial",
        "storage"
    ],
    "wof:name":"East Side Storage",
    "wof:placetype":"venue"
},
  "geometry": {"coordinates":[-93.17047599999999,43.147992],"type":"Point"}
}