{
  "type": "Feature",
  "properties": {
    "iso:country":"US",
    "sg:address":"1829 Industrial Cir",
    "sg:city":"West Des Moines",
    "sg:classifiers":[
        {
            "category":"Building & Trades",
            "subcategory":"Construction",
            "type":"Services"
        }
    ],
    "sg:phone":"+1 515 225 8240",
    "sg:postcode":"50265",
    "sg:province":"IA",
    "sg:tags":[
        "restoration",
        "preservation"
    ],
    "sg:website":"www.thewesterngroup.com",
    "wof:name":"Western Waterproofing",
    "wof:placetype":"venue"
},
  "geometry": {"coordinates":[-93.731754,41.558174],"type":"Point"}
}