{
  "type": "Feature",
  "properties": {
    "iso:country":"US",
    "sg:address":"1111 9th St",
    "sg:city":"Des Moines",
    "sg:classifiers":[
        {
            "category":"Social Services",
            "type":"Services"
        }
    ],
    "sg:phone":"+1 515 246 6572",
    "sg:postcode":"50314",
    "sg:province":"IA",
    "sg:tags":[
        "organization",
        "welfare"
    ],
    "wof:name":"Foster Grandparents Program",
    "wof:placetype":"venue"
},
  "geometry": {"coordinates":[-93.629306,41.600274],"type":"Point"}
}