{
  "type": "Feature",
  "properties": {
    "iso:country":"US",
    "sg:address":"207 E 2nd St",
    "sg:city":"Newell",
    "sg:classifiers":[
        {
            "category":"Government",
            "subcategory":"Office",
            "type":"Public Place"
        }
    ],
    "sg:phone":"+1 712 272 4410",
    "sg:postcode":"50568",
    "sg:province":"IA",
    "sg:tags":[
        "city"
    ],
    "wof:name":"Newell City Hall",
    "wof:placetype":"venue"
},
  "geometry": {"coordinates":[-95.001029,42.6054],"type":"Point"}
}