{
  "type": "Feature",
  "properties": {
    "addr:full":"701 N 3rd Ave Marshalltown IA 50158",
    "addr:housenumber":"701",
    "addr:postcode":"50158",
    "addr:street":"N 3Rd Ave",
    "iso:country":"US",
    "sg:address":"701 N 3rd Ave",
    "sg:city":"Marshalltown",
    "sg:classifiers":[
        {
            "category":"Autos & Motor Vehicles",
            "subcategory":"Auto Supplies",
            "type":"Retail Goods"
        }
    ],
    "sg:phone":"+1 641 752 1974",
    "sg:postcode":"50158",
    "sg:province":"IA",
    "sg:tags":[
        "tire"
    ],
    "wof:name":"Used Tire Outlet Ctr",
    "wof:placetype":"venue"
},
  "geometry": {"coordinates":[-92.90805899999999,42.059286],"type":"Point"}
}