{
  "type": "Feature",
  "properties": {
    "addr:full":"2104 Hanford St Sioux City IA 51109",
    "addr:housenumber":"2104",
    "addr:postcode":"51109",
    "addr:street":"Hanford St",
    "iso:country":"US",
    "sg:address":"2104 Hanford St",
    "sg:city":"Sioux City",
    "sg:classifiers":[
        {
            "category":"Retail",
            "subcategory":"Repair Shop",
            "type":"Services"
        }
    ],
    "sg:phone":"+1 712 255 6087",
    "sg:postcode":"51109",
    "sg:province":"IA",
    "wof:name":"B & D Pop-A-Lock",
    "wof:placetype":"venue"
},
  "geometry": {"coordinates":[-96.485921,42.516054],"type":"Point"}
}