{
  "type": "Feature",
  "properties": {
    "addr:full":"506 5th St Sully IA 50251",
    "addr:housenumber":"506",
    "addr:postcode":"50251",
    "addr:street":"5Th St",
    "iso:country":"US",
    "sg:address":"506 5th St",
    "sg:city":"Sully",
    "sg:classifiers":[
        {
            "category":"Building & Trades",
            "subcategory":"Electrical",
            "type":"Services"
        }
    ],
    "sg:phone":"+1 641 594 4222",
    "sg:postcode":"50251",
    "sg:province":"IA",
    "sg:tags":[
        "electric",
        "contractor"
    ],
    "wof:name":"Van Maanen Electric Inc",
    "wof:placetype":"venue"
},
  "geometry": {"coordinates":[-92.848731,41.577318],"type":"Point"}
}