{
  "type": "Feature",
  "properties": {
    "addr:full":"2201 V Ave Villisca IA 50864",
    "addr:housenumber":"2201",
    "addr:postcode":"50864",
    "addr:street":"V Ave",
    "iso:country":"US",
    "sg:address":"2201 V Ave",
    "sg:city":"Villisca",
    "sg:classifiers":[
        {
            "category":"Utilities",
            "subcategory":"Cable",
            "type":"Services"
        }
    ],
    "sg:phone":"+1 712 826 4022",
    "sg:postcode":"50864",
    "sg:province":"IA",
    "sg:tags":[
        "television"
    ],
    "wof:name":"Johnston Communications",
    "wof:placetype":"venue"
},
  "geometry": {"coordinates":[-94.966278,40.98461],"type":"Point"}
}