{
  "type": "Feature",
  "properties": {
    "iso:country":"US",
    "sg:address":"100 E Taylor St",
    "sg:city":"Creston",
    "sg:classifiers":[
        {
            "category":"Shopping",
            "subcategory":"Department Store",
            "type":"Retail Goods"
        }
    ],
    "sg:phone":"+1 641 782 3791",
    "sg:postcode":"50801",
    "sg:province":"IA",
    "sg:tags":[
        "shop"
    ],
    "wof:name":"Essential Journey",
    "wof:placetype":"venue"
},
  "geometry": {"coordinates":[-94.36145999999999,41.049192],"type":"Point"}
}