{
  "type": "Feature",
  "properties": {
    "addr:full":"2600 Aldrich Dr Webster City IA 50595",
    "addr:housenumber":"2600",
    "addr:postcode":"50595",
    "addr:street":"Aldrich Dr",
    "iso:country":"US",
    "sg:address":"2600 Aldrich Dr",
    "sg:city":"Webster City",
    "sg:classifiers":[
        {
            "category":"Organizations",
            "subcategory":"Religious Organization",
            "type":"Services"
        }
    ],
    "sg:phone":"+1 515 832 5624",
    "sg:postcode":"50595",
    "sg:province":"IA",
    "sg:tags":[
        "church"
    ],
    "wof:name":"Kingdom Hall-Jehovah's Witness",
    "wof:placetype":"venue"
},
  "geometry": {"coordinates":[-93.82072599999999,42.44545],"type":"Point"}
}