{
  "type": "Feature",
  "properties": {
    "addr:full":"1112 8th St Sioux City IA 51105",
    "addr:housenumber":"1112",
    "addr:postcode":"51105",
    "addr:street":"8Th St",
    "iso:country":"US",
    "sg:address":"1112 8th St",
    "sg:city":"Sioux City",
    "sg:classifiers":[
        {
            "category":"Organizations",
            "subcategory":"Religious Organization",
            "type":"Services"
        }
    ],
    "sg:phone":"+1 712 258 3813",
    "sg:postcode":"51105",
    "sg:province":"IA",
    "sg:tags":[
        "church"
    ],
    "wof:name":"St Josephs Church",
    "wof:placetype":"venue"
},
  "geometry": {"coordinates":[-96.395843,42.498521],"type":"Point"}
}