{
  "type": "Feature",
  "properties": {
    "addr:full":"3216 Division St Burlington IA 52601",
    "addr:housenumber":"3216",
    "addr:postcode":"52601",
    "addr:street":"Division St",
    "iso:country":"US",
    "sg:address":"3216 Division St",
    "sg:city":"Burlington",
    "sg:classifiers":[
        {
            "category":"Banks & Credit Unions",
            "subcategory":"Bank",
            "type":"Services"
        }
    ],
    "sg:phone":"+1 319 754 7536",
    "sg:postcode":"52601",
    "sg:province":"IA",
    "sg:tags":[
        "loan",
        "real estate"
    ],
    "wof:name":"Citi Financial",
    "wof:placetype":"venue"
},
  "geometry": {"coordinates":[-91.14290200000001,40.807715],"type":"Point"}
}