{
  "type": "Feature",
  "properties": {
    "addr:full":"124 Main St Aurelia IA 51005",
    "addr:housenumber":"124",
    "addr:postcode":"51005",
    "addr:street":"Main St",
    "iso:country":"US",
    "sg:address":"124 Main St",
    "sg:city":"Aurelia",
    "sg:classifiers":[
        {
            "category":"Personal",
            "subcategory":"Beauty Salon",
            "type":"Services"
        }
    ],
    "sg:phone":"+1 712 434 5470",
    "sg:postcode":"51005",
    "sg:province":"IA",
    "wof:name":"Hair By Us",
    "wof:placetype":"venue"
},
  "geometry": {"coordinates":[-95.436463,42.712249],"type":"Point"}
}