{
  "type": "Feature",
  "properties": {
    "addr:full":"25857 Timber Ave Glidden IA 51443",
    "addr:housenumber":"25857",
    "addr:postcode":"51443",
    "addr:street":"Timber Ave",
    "iso:country":"US",
    "sg:address":"25857 Timber Ave",
    "sg:city":"Glidden",
    "sg:classifiers":[
        {
            "category":"Retail",
            "subcategory":"Auto Repair",
            "type":"Services"
        }
    ],
    "sg:phone":"+1 712 659 3076",
    "sg:postcode":"51443",
    "sg:province":"IA",
    "sg:tags":[
        "repairing",
        "automobile"
    ],
    "wof:name":"Turner Painting & Repair",
    "wof:placetype":"venue"
},
  "geometry": {"coordinates":[-94.72593999999999,41.992688],"type":"Point"}
}