{
  "type": "Feature",
  "properties": {
    "iso:country":"US",
    "sg:address":"115 N Madison Ave",
    "sg:city":"Ottumwa",
    "sg:classifiers":[
        {
            "category":"Retail",
            "subcategory":"Auto Repair",
            "type":"Services"
        }
    ],
    "sg:phone":"+1 641 684 6867",
    "sg:postcode":"52501",
    "sg:province":"IA",
    "sg:tags":[
        "automobile",
        "top",
        "upholstery"
    ],
    "wof:name":"Ottumwa Seat & Top",
    "wof:placetype":"venue"
},
  "geometry": {"coordinates":[-92.413597,41.00326],"type":"Point"}
}