{
  "type": "Feature",
  "properties": {
    "iso:country":"US",
    "sg:address":"2073 235th St",
    "sg:city":"Hamlin",
    "sg:classifiers":[
        {
            "category":"Farming",
            "subcategory":"Livestock Farm",
            "type":"Manufacturing & Wholesale Goods"
        }
    ],
    "sg:phone":"+1 712 563 3955",
    "sg:postcode":"50117",
    "sg:province":"IA",
    "sg:tags":[
        "hog",
        "or",
        "feedlot"
    ],
    "wof:name":"Dan Wittrock",
    "wof:placetype":"venue"
},
  "geometry": {"coordinates":[-94.885988,41.666896],"type":"Point"}
}