{
  "type": "Feature",
  "properties": {
    "addr:full":"1107 Sycamore St Dallas Center IA 50063",
    "addr:housenumber":"1107",
    "addr:postcode":"50063",
    "addr:street":"Sycamore St",
    "iso:country":"US",
    "sg:address":"1107 Sycamore St",
    "sg:city":"Dallas Center",
    "sg:classifiers":[
        {
            "category":"Freight",
            "type":"Transportation"
        }
    ],
    "sg:phone":"+1 515 992 3767",
    "sg:postcode":"50063",
    "sg:province":"IA",
    "sg:tags":[
        "grain",
        "elevator"
    ],
    "wof:name":"Heartland Co-Op",
    "wof:placetype":"venue"
},
  "geometry": {"coordinates":[-93.958546,41.683388],"type":"Point"}
}