{
  "type": "Feature",
  "properties": {
    "iso:country":"US",
    "sg:address":"1525 E San Marnan Dr",
    "sg:city":"Waterloo",
    "sg:classifiers":[
        {
            "category":"Shopping",
            "subcategory":"Optical Goods",
            "type":"Retail Goods"
        }
    ],
    "sg:phone":"+1 319 232 9600",
    "sg:postcode":"50702",
    "sg:province":"IA",
    "wof:name":"Eye Mart Optical",
    "wof:placetype":"venue"
},
  "geometry": {"coordinates":[-92.323854,42.46544],"type":"Point"}
}