{
  "type": "Feature",
  "properties": {
    "iso:country":"US",
    "sg:address":"612 S Vermont St",
    "sg:city":"Maquoketa",
    "sg:classifiers":[
        {
            "category":"Education",
            "subcategory":"School",
            "type":"Public Place"
        }
    ],
    "sg:phone":"+1 563 652 4984",
    "sg:postcode":"52060",
    "sg:province":"IA",
    "wof:name":"Maquoketa Community Schl Dist",
    "wof:placetype":"venue"
},
  "geometry": {"coordinates":[-90.673239,42.060841],"type":"Point"}
}