{
  "type": "Feature",
  "properties": {
    "iso:country":"US",
    "sg:address":"915 13th Ave N",
    "sg:city":"Clinton",
    "sg:classifiers":[
        {
            "category":"Health Services",
            "subcategory":"Doctor",
            "type":"Services"
        }
    ],
    "sg:phone":"+1 563 243 2511",
    "sg:postcode":"52732",
    "sg:province":"IA",
    "sg:tags":[
        "physician",
        "family",
        "practice",
        "surgeons",
        "medicine"
    ],
    "wof:name":"Morrison Family Health Clinic",
    "wof:placetype":"venue"
},
  "geometry": {"coordinates":[-90.201706,41.859348],"type":"Point"}
}