{
  "type": "Feature",
  "properties": {
    "iso:country":"US",
    "sg:address":"200 E Char-Mac Dr",
    "sg:city":"Lawton",
    "sg:classifiers":[
        {
            "category":"Health Services",
            "subcategory":"Nursing And Care Facility",
            "type":"Services"
        }
    ],
    "sg:phone":"+1 712 944 4893",
    "sg:postcode":"51030",
    "sg:province":"IA",
    "sg:tags":[
        "home",
        "convalescent"
    ],
    "wof:name":"Char-Mac Assisted Living",
    "wof:placetype":"venue"
},
  "geometry": {"coordinates":[-96.18270699999999,42.474971],"type":"Point"}
}