{
  "type": "Feature",
  "properties": {
    "addr:full":"18557 State Hwy 21 What Cheer IA 50268",
    "addr:housenumber":"18557",
    "addr:postcode":"50268",
    "addr:street":"State Hwy 21",
    "iso:country":"US",
    "sg:address":"18557 State Hwy 21",
    "sg:city":"What Cheer",
    "sg:classifiers":[
        {
            "category":"Real Estate",
            "subcategory":"Real Estate Operator",
            "type":"Services"
        }
    ],
    "sg:phone":"+1 641 634 2219",
    "sg:postcode":"50268",
    "sg:province":"IA",
    "sg:tags":[
        "property",
        "lessor"
    ],
    "wof:name":"Striegel Virginia",
    "wof:placetype":"venue"
},
  "geometry": {"coordinates":[-92.354788,41.390698],"type":"Point"}
}