{
  "type": "Feature",
  "properties": {
    "iso:country":"US",
    "sg:address":"903 S Lake St",
    "sg:city":"Lake Mills",
    "sg:classifiers":[
        {
            "category":"Personal",
            "subcategory":"Beauty Salon",
            "type":"Services"
        }
    ],
    "sg:phone":"+1 641 592 4700",
    "sg:postcode":"50450",
    "sg:province":"IA",
    "sg:tags":[
        "shop"
    ],
    "wof:name":"Hair Inc",
    "wof:placetype":"venue"
},
  "geometry": {"coordinates":[-93.532526,43.411079],"type":"Point"}
}