{
  "type": "Feature",
  "properties": {
    "iso:country":"US",
    "sg:address":"1210 W Sheridan Ave",
    "sg:city":"Shenandoah",
    "sg:classifiers":[
        {
            "category":"Building & Trades",
            "subcategory":"Plumbing",
            "type":"Services"
        }
    ],
    "sg:phone":"+1 712 246 1803",
    "sg:postcode":"51601",
    "sg:province":"IA",
    "sg:tags":[
        "plumbing",
        "contractor"
    ],
    "wof:name":"John Gowing Plumbing & Heating",
    "wof:placetype":"venue"
},
  "geometry": {"coordinates":[-95.383455,40.765808],"type":"Point"}
}