{
  "type": "Feature",
  "properties": {
    "iso:country":"US",
    "sg:address":"31173 283rd Ave",
    "sg:city":"Hopkinton",
    "sg:classifiers":[
        {
            "category":"Wholesale",
            "subcategory":"Scrap",
            "type":"Manufacturing & Wholesale Goods"
        }
    ],
    "sg:phone":"+1 563 926 2442",
    "sg:postcode":"52237",
    "sg:province":"IA",
    "sg:tags":[
        "recycling",
        "center"
    ],
    "wof:name":"Bacon Recycling",
    "wof:placetype":"venue"
},
  "geometry": {"coordinates":[-91.24084999999999,42.337526],"type":"Point"}
}