{
  "type": "Feature",
  "properties": {
    "iso:country":"US",
    "sg:address":"1509 Choctaw Ct",
    "sg:city":"Sioux City",
    "sg:classifiers":[
        {
            "category":"Banks & Credit Unions",
            "subcategory":"Investment Brokerage",
            "type":"Services"
        }
    ],
    "sg:phone":"+1 712 239 9254",
    "sg:postcode":"51104",
    "sg:province":"IA",
    "wof:name":"T J Investments",
    "wof:placetype":"venue"
},
  "geometry": {"coordinates":[-96.389679,42.539684],"type":"Point"}
}