{
  "type": "Feature",
  "properties": {
    "addr:full":"1202 Central Ave W Clarion IA 50525",
    "addr:housenumber":"1202",
    "addr:postcode":"50525",
    "addr:street":"Central Ave W Clarion",
    "iso:country":"US",
    "sg:address":"1202 Central Ave W",
    "sg:city":"Clarion",
    "sg:classifiers":[
        {
            "category":"Building & Trades",
            "subcategory":"Construction",
            "type":"Services"
        }
    ],
    "sg:phone":"+1 515 532 2509",
    "sg:postcode":"50525",
    "sg:province":"IA",
    "sg:tags":[
        "drainage",
        "contractor"
    ],
    "wof:name":"Hilpipre Tiling",
    "wof:placetype":"venue"
},
  "geometry": {"coordinates":[-93.751017,42.73159],"type":"Point"}
}