{
  "type": "Feature",
  "properties": {
    "addr:full":"585 Huff St Dubuque IA 52003",
    "addr:housenumber":"585",
    "addr:postcode":"52003",
    "addr:street":"Huff St",
    "iso:country":"US",
    "sg:address":"585 Huff St",
    "sg:city":"Dubuque",
    "sg:classifiers":[
        {
            "category":"Building & Trades",
            "subcategory":"Cleaning & Sanitation",
            "type":"Services"
        }
    ],
    "sg:phone":"+1 563 557 7787",
    "sg:postcode":"52003",
    "sg:province":"IA",
    "sg:tags":[
        "janitor"
    ],
    "wof:name":"FBG Svc Corp",
    "wof:placetype":"venue"
},
  "geometry": {"coordinates":[-90.661558,42.486218],"type":"Point"}
}