{
  "type": "Feature",
  "properties": {
    "iso:country":"US",
    "sg:address":"3610 Williams Blvd SW",
    "sg:city":"Cedar Rapids",
    "sg:classifiers":[
        {
            "category":"Banks & Credit Unions",
            "subcategory":"Bank",
            "type":"Services"
        }
    ],
    "sg:phone":"+1 319 654 9595",
    "sg:postcode":"52404",
    "sg:province":"IA",
    "sg:website":"www.hillsbank.com",
    "wof:name":"Hills Bank and Trust Company",
    "wof:placetype":"venue"
},
  "geometry": {"coordinates":[-91.71639999999999,41.958],"type":"Point"}
}