{
  "type": "Feature",
  "properties": {
    "iso:country":"US",
    "sg:address":"1622 W 1st St",
    "sg:city":"Ankeny",
    "sg:classifiers":[
        {
            "category":"Restaurant",
            "type":"Food & Drink"
        }
    ],
    "sg:phone":"+1 515 963 9000",
    "sg:postcode":"50023",
    "sg:province":"IA",
    "wof:name":"Breadeaux Pizza",
    "wof:placetype":"venue"
},
  "geometry": {"coordinates":[-93.623458,41.731929],"type":"Point"}
}