{
  "type": "Feature",
  "properties": {
    "addr:full":"200 High Ave W Oskaloosa IA 52577",
    "addr:housenumber":"200",
    "addr:postcode":"52577",
    "addr:street":"High Ave W Oskaloosa",
    "iso:country":"US",
    "sg:address":"200 High Ave W",
    "sg:city":"Oskaloosa",
    "sg:classifiers":[
        {
            "category":"Personal",
            "subcategory":"Beauty Salon",
            "type":"Services"
        }
    ],
    "sg:phone":"+1 641 672 8788",
    "sg:postcode":"52577",
    "sg:province":"IA",
    "sg:tags":[
        "manicuring"
    ],
    "wof:name":"Glory Nails",
    "wof:placetype":"venue"
},
  "geometry": {"coordinates":[-92.646912,41.295335],"type":"Point"}
}