{
  "type": "Feature",
  "properties": {
    "addr:full":"3156 220th St Terril IA 51364",
    "addr:housenumber":"3156",
    "addr:postcode":"51364",
    "addr:street":"220Th St",
    "iso:country":"US",
    "sg:address":"3156 220th St",
    "sg:city":"Terril",
    "sg:classifiers":[
        {
            "category":"Farming",
            "subcategory":"Farm & Veterinary Services",
            "type":"Manufacturing & Wholesale Goods"
        }
    ],
    "sg:phone":"+1 712 853 6413",
    "sg:postcode":"51364",
    "sg:province":"IA",
    "sg:tags":[
        "aerial",
        "applicator"
    ],
    "wof:name":"Guy's Air Spraying",
    "wof:placetype":"venue"
},
  "geometry": {"coordinates":[-94.96256200000001,43.327648],"type":"Point"}
}