{
  "type": "Feature",
  "properties": {
    "iso:country":"US",
    "sg:address":"1311 Herold Ave",
    "sg:city":"Des Moines",
    "sg:classifiers":[
        {
            "category":"Building & Trades",
            "subcategory":"Construction",
            "type":"Services"
        }
    ],
    "sg:phone":"+1 515 285 5641",
    "sg:postcode":"50315",
    "sg:province":"IA",
    "sg:tags":[
        "foundation",
        "contractor"
    ],
    "wof:name":"Painovich Brothers Corp",
    "wof:placetype":"venue"
},
  "geometry": {"coordinates":[-93.62947200000001,41.542133],"type":"Point"}
}