{
  "type": "Feature",
  "properties": {
    "iso:country":"US",
    "sg:address":"105 3rd St NW",
    "sg:city":"Fort Atkinson",
    "sg:classifiers":[
        {
            "category":"Professional",
            "subcategory":"Accounting & Tax Preparation",
            "type":"Services"
        }
    ],
    "sg:phone":"+1 563 534 5555",
    "sg:postcode":"52144",
    "sg:province":"IA",
    "sg:tags":[
        "return",
        "filing"
    ],
    "wof:name":"Refund Recovery Svc",
    "wof:placetype":"venue"
},
  "geometry": {"coordinates":[-91.933097,43.14377],"type":"Point"}
}