{
  "type": "Feature",
  "properties": {
    "iso:country":"US",
    "sg:address":"879 Jefferson St",
    "sg:city":"Burlington",
    "sg:classifiers":[
        {
            "category":"Retail",
            "subcategory":"Animal Services",
            "type":"Services"
        }
    ],
    "sg:phone":"+1 319 754 4230",
    "sg:postcode":"52601",
    "sg:province":"IA",
    "sg:tags":[
        "pet",
        "grooming",
        "washing"
    ],
    "wof:name":"Pride & Groom",
    "wof:placetype":"venue"
},
  "geometry": {"coordinates":[-91.110613,40.81141],"type":"Point"}
}