{
  "type": "Feature",
  "properties": {
    "iso:country":"US",
    "sg:address":"501 W State St",
    "sg:city":"Jefferson",
    "sg:classifiers":[
        {
            "category":"Travel",
            "subcategory":"Travel Agent",
            "type":"Entertainment"
        }
    ],
    "sg:phone":"+1 515 386 8317",
    "sg:postcode":"50129",
    "sg:province":"IA",
    "sg:tags":[
        "agency"
    ],
    "wof:name":"Town & Country Travel Ltd",
    "wof:placetype":"venue"
},
  "geometry": {"coordinates":[-94.38140199999999,42.016258],"type":"Point"}
}