{
  "type": "Feature",
  "properties": {
    "iso:country":"US",
    "sg:address":"1137 Grant St",
    "sg:city":"Bettendorf",
    "sg:classifiers":[
        {
            "category":"Food & Beverages",
            "subcategory":"Candy",
            "type":"Retail Goods"
        }
    ],
    "sg:phone":"+1 563 359 1505",
    "sg:postcode":"52722",
    "sg:province":"IA",
    "sg:tags":[
        "confectionery"
    ],
    "wof:name":"Flaherty Happy Tyme Co",
    "wof:placetype":"venue"
},
  "geometry": {"coordinates":[-90.516488,41.526149],"type":"Point"}
}