{
  "type": "Feature",
  "properties": {
    "addr:full":"606 Walnut St Des Moines IA 50309",
    "addr:housenumber":"606",
    "addr:postcode":"50309",
    "addr:street":"Walnut St",
    "iso:country":"US",
    "sg:address":"606 Walnut St",
    "sg:city":"Des Moines",
    "sg:classifiers":[
        {
            "category":"Shopping",
            "subcategory":"Pharmacy",
            "type":"Retail Goods"
        }
    ],
    "sg:phone":"+1 515 283 1793",
    "sg:postcode":"50309",
    "sg:province":"IA",
    "wof:name":"Walgreens",
    "wof:placetype":"venue"
},
  "geometry": {"coordinates":[-93.62576799999999,41.585593],"type":"Point"}
}