{
  "type": "Feature",
  "properties": {
    "iso:country":"US",
    "sg:address":"915 Robins Rd",
    "sg:city":"Hiawatha",
    "sg:classifiers":[
        {
            "category":"Building & Trades",
            "subcategory":"Electrical",
            "type":"Services"
        }
    ],
    "sg:phone":"+1 319 373 7777",
    "sg:postcode":"52233",
    "sg:province":"IA",
    "sg:tags":[
        "electric",
        "contractor"
    ],
    "sg:website":"www.gleasonelectric.com",
    "wof:name":"Gleason Electric",
    "wof:placetype":"venue"
},
  "geometry": {"coordinates":[-91.672843,42.047569],"type":"Point"}
}