{
  "type": "Feature",
  "properties": {
    "iso:country":"US",
    "sg:address":"105 N Martha St",
    "sg:city":"Roland",
    "sg:classifiers":[
        {
            "category":"Building & Trades",
            "subcategory":"Plumbing",
            "type":"Services"
        }
    ],
    "sg:phone":"+1 515 388 4188",
    "sg:postcode":"50236",
    "sg:province":"IA",
    "sg:tags":[
        "plumbing",
        "contractor"
    ],
    "wof:name":"Hometown Plumbing",
    "wof:placetype":"venue"
},
  "geometry": {"coordinates":[-93.495104,42.167732],"type":"Point"}
}