{
  "type": "Feature",
  "properties": {
    "iso:country":"US",
    "sg:address":"1740 Falls Ave",
    "sg:city":"Waterloo",
    "sg:classifiers":[
        {
            "category":"Restaurant",
            "type":"Food & Drink"
        }
    ],
    "sg:phone":"+1 319 232 0344",
    "sg:postcode":"50701",
    "sg:province":"IA",
    "sg:website":"www.steamboatgardens.com",
    "wof:name":"Steamboat Garden",
    "wof:placetype":"venue"
},
  "geometry": {"coordinates":[-92.368284,42.498869],"type":"Point"}
}