{
  "type": "Feature",
  "properties": {
    "addr:full":"520 E Jefferson St Corydon IA 50060",
    "addr:housenumber":"520",
    "addr:postcode":"50060",
    "addr:street":"E Jefferson St",
    "iso:country":"US",
    "sg:address":"520 E Jefferson St",
    "sg:city":"Corydon",
    "sg:classifiers":[
        {
            "category":"Shopping",
            "subcategory":"Bicycles & Sporting Goods",
            "type":"Retail Goods"
        }
    ],
    "sg:phone":"+1 641 872 1501",
    "sg:postcode":"50060",
    "sg:province":"IA",
    "sg:tags":[
        "gun",
        "gunsmith"
    ],
    "wof:name":"Mike's Guns",
    "wof:placetype":"venue"
},
  "geometry": {"coordinates":[-93.312056,40.757094],"type":"Point"}
}