{
  "type": "Feature",
  "properties": {
    "iso:country":"US",
    "sg:address":"2507 University Ave",
    "sg:city":"Des Moines",
    "sg:classifiers":[
        {
            "category":"Museum",
            "type":"Entertainment"
        }
    ],
    "sg:phone":"+1 515 271 3841",
    "sg:postcode":"50311",
    "sg:province":"IA",
    "sg:tags":[
        "gallery"
    ],
    "wof:name":"Harmon Fine Arts Center",
    "wof:placetype":"venue"
},
  "geometry": {"coordinates":[-93.652128,41.600462],"type":"Point"}
}