{
  "type": "Feature",
  "properties": {
    "iso:country":"US",
    "sg:address":"1231 4th St SW",
    "sg:city":"Waverly",
    "sg:classifiers":[
        {
            "category":"Food & Beverages",
            "subcategory":"Specialty",
            "type":"Retail Goods"
        }
    ],
    "sg:phone":"+1 319 352 2292",
    "sg:postcode":"50677",
    "sg:province":"IA",
    "sg:tags":[
        "vitamin"
    ],
    "wof:name":"General Nutrition Ctr",
    "wof:placetype":"venue"
},
  "geometry": {"coordinates":[-92.47537199999999,42.713716],"type":"Point"}
}