{
  "type": "Feature",
  "properties": {
    "iso:country":"US",
    "sg:address":"6824 Panorama Dr",
    "sg:city":"Panora",
    "sg:classifiers":[
        {
            "category":"Professional",
            "subcategory":"Management & Consulting",
            "type":"Services"
        }
    ],
    "sg:phone":"+1 641 755 3433",
    "sg:postcode":"50216",
    "sg:province":"IA",
    "sg:tags":[
        "consultant"
    ],
    "wof:name":"Capitol Consultants",
    "wof:placetype":"venue"
},
  "geometry": {"coordinates":[-94.40388799999999,41.705414],"type":"Point"}
}