{
  "type": "Feature",
  "properties": {
    "iso:country":"US",
    "sg:address":"130 N Park Pl",
    "sg:city":"Cresco",
    "sg:classifiers":[
        {
            "category":"Banks & Credit Unions",
            "subcategory":"Bank",
            "type":"Services"
        }
    ],
    "sg:phone":"+1 563 547 2244",
    "sg:postcode":"52136",
    "sg:province":"IA",
    "sg:website":"www.fortressbanks.com",
    "wof:name":"Fortress Bank Of Cresco",
    "wof:placetype":"venue"
},
  "geometry": {"coordinates":[-92.115864,43.373906],"type":"Point"}
}