{
  "type": "Feature",
  "properties": {
    "iso:country":"US",
    "sg:address":"1073 Rockford Rd SW",
    "sg:city":"Cedar Rapids",
    "sg:classifiers":[
        {
            "category":"Professional",
            "subcategory":"Lawyer & Legal Services",
            "type":"Services"
        }
    ],
    "sg:phone":"+1 319 362 2474",
    "sg:postcode":"52404",
    "sg:province":"IA",
    "wof:name":"Richards Allan M",
    "wof:placetype":"venue"
},
  "geometry": {"coordinates":[-91.686302,41.966499],"type":"Point"}
}