{
  "type": "Feature",
  "properties": {
    "addr:full":"3201 Manawa Dr Council Bluffs IA 51501",
    "addr:housenumber":"3201",
    "addr:postcode":"51501",
    "addr:street":"Manawa Dr",
    "iso:country":"US",
    "sg:address":"3201 Manawa Dr",
    "sg:city":"Council Bluffs",
    "sg:classifiers":[
        {
            "category":"Shopping",
            "subcategory":"Department Store",
            "type":"Retail Goods"
        },
        {
            "category":"Shopping",
            "subcategory":"Mobile Phones",
            "type":"Retail Goods"
        },
        {
            "category":"Food & Beverages",
            "subcategory":"Groceries & Convenience Stores",
            "type":"Retail Goods"
        }
    ],
    "sg:phone":"+1 712 366 3326",
    "sg:postcode":"51501",
    "sg:province":"IA",
    "sg:website":"www.walmart.com",
    "wof:name":"Walmart",
    "wof:placetype":"venue"
},
  "geometry": {"coordinates":[-95.84412399999999,41.226874],"type":"Point"}
}