{
  "type": "Feature",
  "properties": {
    "addr:full":"708 Court St Harlan IA 51537",
    "addr:housenumber":"708",
    "addr:postcode":"51537",
    "addr:street":"Court St",
    "iso:country":"US",
    "sg:address":"708 Court St",
    "sg:city":"Harlan",
    "sg:classifiers":[
        {
            "category":"Insurance",
            "subcategory":"Insurance Agent",
            "type":"Services"
        }
    ],
    "sg:phone":"+1 712 755 3270",
    "sg:postcode":"51537",
    "sg:province":"IA",
    "wof:name":"New York Life Insurance Co",
    "wof:placetype":"venue"
},
  "geometry": {"coordinates":[-95.318997,41.657771],"type":"Point"}
}