{
  "type": "Feature",
  "properties": {
    "addr:full":"3606 Metro Dr Ste 300 Council Bluffs IA 51501",
    "addr:postcode":"3606;51501",
    "addr:street":"Metro Dr Ste 300",
    "iso:country":"US",
    "sg:address":"3606 Metro Dr Ste 300",
    "sg:city":"Council Bluffs",
    "sg:classifiers":[
        {
            "category":"Shopping",
            "subcategory":"Shoes",
            "type":"Retail Goods"
        }
    ],
    "sg:phone":"+1 712 366 0555",
    "sg:postcode":"51501",
    "sg:province":"IA",
    "sg:tags":[
        "store"
    ],
    "sg:website":"www.famousfootwear.com",
    "wof:name":"Famous Footwear",
    "wof:placetype":"venue"
},
  "geometry": {"coordinates":[-95.838244,41.223125],"type":"Point"}
}