{
  "type": "Feature",
  "properties": {
    "iso:country":"US",
    "sg:address":"1414 E Commercial St",
    "sg:city":"Algona",
    "sg:classifiers":[
        {
            "category":"Retail",
            "subcategory":"Auto Repair",
            "type":"Services"
        }
    ],
    "sg:phone":"+1 515 295 5030",
    "sg:postcode":"50511",
    "sg:province":"IA",
    "sg:tags":[
        "body",
        "automobile",
        "painting"
    ],
    "wof:name":"G & C Autobody",
    "wof:placetype":"venue"
},
  "geometry": {"coordinates":[-94.218085,43.075577],"type":"Point"}
}