{
  "type": "Feature",
  "properties": {
    "addr:full":"2519 E 53rd St Davenport IA 52807",
    "addr:housenumber":"2519",
    "addr:postcode":"52807",
    "addr:street":"E 53Rd St",
    "iso:country":"US",
    "sg:address":"2519 E 53rd St",
    "sg:city":"Davenport",
    "sg:classifiers":[
        {
            "category":"Fast Food",
            "type":"Food & Drink"
        },
        {
            "category":"Restaurant",
            "type":"Food & Drink"
        }
    ],
    "sg:phone":"+1 563 355 7722",
    "sg:postcode":"52807",
    "sg:province":"IA",
    "sg:tags":[
        "style",
        "hamburger",
        "family",
        "dog",
        "hot",
        "american"
    ],
    "sg:website":"http://www.checkers.com",
    "wof:name":"Checkers Drive In",
    "wof:placetype":"venue"
},
  "geometry": {"coordinates":[-90.540195,41.574772],"type":"Point"}
}