{
  "type": "Feature",
  "properties": {
    "iso:country":"US",
    "sg:address":"116 Mulberry Ave",
    "sg:city":"Muscatine",
    "sg:classifiers":[
        {
            "category":"Communications",
            "subcategory":"Film & Video Production",
            "type":"Services"
        }
    ],
    "sg:phone":"+1 563 262 8589",
    "sg:postcode":"52761",
    "sg:province":"IA",
    "sg:tags":[
        "motion"
    ],
    "wof:name":"Pieper Video Productions",
    "wof:placetype":"venue"
},
  "geometry": {"coordinates":[-91.040817,41.422926],"type":"Point"}
}