{
  "type": "Feature",
  "properties": {
    "iso:country":"US",
    "sg:address":"29470 Coldwater Ave",
    "sg:city":"Honey Creek",
    "sg:classifiers":[
        {
            "category":"Building & Trades",
            "subcategory":"Pest Control",
            "type":"Services"
        }
    ],
    "sg:phone":"+1 712 545 3383",
    "sg:postcode":"51542",
    "sg:province":"IA",
    "wof:name":"National Exterminators",
    "wof:placetype":"venue"
},
  "geometry": {"coordinates":[-95.810895,41.443966],"type":"Point"}
}