{
  "type": "Feature",
  "properties": {
    "iso:country":"US",
    "sg:address":"462 7th Ave",
    "sg:city":"Marion",
    "sg:classifiers":[
        {
            "category":"Personal",
            "subcategory":"Barber",
            "type":"Services"
        }
    ],
    "sg:phone":"+1 319 377 0505",
    "sg:postcode":"52302",
    "sg:province":"IA",
    "wof:name":"Seventh Avenue Barbershop & Salon",
    "wof:placetype":"venue"
},
  "geometry": {"coordinates":[-91.605659,42.033441],"type":"Point"}
}