{
  "type": "Feature",
  "properties": {
    "addr:full":"1042 73rd St Windsor Heights IA 50311",
    "addr:housenumber":"1042",
    "addr:postcode":"50311",
    "addr:street":"73Rd St",
    "iso:country":"US",
    "sg:address":"1042 73rd St",
    "sg:city":"Windsor Heights",
    "sg:classifiers":[
        {
            "category":"Professional",
            "subcategory":"Accounting & Tax Preparation",
            "type":"Services"
        }
    ],
    "sg:phone":"+1 515 224 1829",
    "sg:postcode":"50311",
    "sg:province":"IA",
    "sg:tags":[
        "return",
        "filing"
    ],
    "wof:name":"Liberty Tax Svc",
    "wof:placetype":"venue"
},
  "geometry": {"coordinates":[-93.718484,41.597167],"type":"Point"}
}