{
  "type": "Feature",
  "properties": {
    "addr:full":"206 N Evans Rd Evansdale IA 50707",
    "addr:housenumber":"206",
    "addr:postcode":"50707",
    "addr:street":"N Evans Rd",
    "iso:country":"US",
    "sg:address":"206 N Evans Rd",
    "sg:city":"Evansdale",
    "sg:classifiers":[
        {
            "category":"Personal",
            "subcategory":"Beauty Salon",
            "type":"Services"
        }
    ],
    "sg:phone":"+1 319 232 5875",
    "sg:postcode":"50707",
    "sg:province":"IA",
    "wof:name":"Karen's Kuts & Kurls",
    "wof:placetype":"venue"
},
  "geometry": {"coordinates":[-92.288026,42.480104],"type":"Point"}
}