{
  "type": "Feature",
  "properties": {
    "addr:full":"860 White St Dubuque IA 52001",
    "addr:housenumber":"860",
    "addr:postcode":"52001",
    "addr:street":"White St",
    "iso:country":"US",
    "sg:address":"860 White St",
    "sg:city":"Dubuque",
    "sg:classifiers":[
        {
            "category":"Health Services",
            "subcategory":"Clinic",
            "type":"Services"
        }
    ],
    "sg:phone":"+1 563 585 1409",
    "sg:postcode":"52001",
    "sg:province":"IA",
    "sg:tags":[
        "home"
    ],
    "sg:website":"www.homeinstead.com",
    "wof:name":"Home Instead Senior Care",
    "wof:placetype":"venue"
},
  "geometry": {"coordinates":[-90.66427,42.502082],"type":"Point"}
}