{
  "type": "Feature",
  "properties": {
    "iso:country":"US",
    "sg:address":"800 Cedar Cross Rd",
    "sg:city":"Dubuque",
    "sg:classifiers":[
        {
            "category":"Retail",
            "subcategory":"Auto Repair",
            "type":"Services"
        }
    ],
    "sg:phone":"+1 563 556 8323",
    "sg:postcode":"52003",
    "sg:province":"IA",
    "sg:tags":[
        "body",
        "automobile",
        "painting",
        "repairing"
    ],
    "wof:name":"Hart Auto Body & Paint Company",
    "wof:placetype":"venue"
},
  "geometry": {"coordinates":[-90.71209,42.481201],"type":"Point"}
}