{
  "type": "Feature",
  "properties": {
    "iso:country":"US",
    "sg:address":"2159 195th St",
    "sg:city":"Afton",
    "sg:classifiers":[
        {
            "category":"Retail",
            "subcategory":"Auto Repair",
            "type":"Services"
        }
    ],
    "sg:phone":"+1 641 347 8787",
    "sg:postcode":"50830",
    "sg:province":"IA",
    "sg:tags":[
        "general"
    ],
    "wof:name":"Gary Nissen Auto",
    "wof:placetype":"venue"
},
  "geometry": {"coordinates":[-94.261152,41.02061],"type":"Point"}
}