{
  "type": "Feature",
  "properties": {
    "iso:country":"US",
    "sg:address":"11176 J Ave",
    "sg:city":"Wapello",
    "sg:classifiers":[
        {
            "category":"Farming",
            "subcategory":"Farm",
            "type":"Manufacturing & Wholesale Goods"
        }
    ],
    "sg:phone":"+1 319 523 5857",
    "sg:postcode":"52653",
    "sg:province":"IA",
    "sg:tags":[
        "feedlot",
        "cattle",
        "crop",
        "beef",
        "general"
    ],
    "wof:name":"Keltic Corp",
    "wof:placetype":"venue"
},
  "geometry": {"coordinates":[-91.191903,41.218879],"type":"Point"}
}