{
  "type": "Feature",
  "properties": {
    "addr:full":"2704 360th St Lohrville IA 51453",
    "addr:housenumber":"2704",
    "addr:postcode":"51453",
    "addr:street":"360Th St",
    "iso:country":"US",
    "sg:address":"2704 360th St",
    "sg:city":"Lohrville",
    "sg:classifiers":[
        {
            "category":"Building & Trades",
            "subcategory":"Construction",
            "type":"Services"
        }
    ],
    "sg:phone":"+1 712 465 4905",
    "sg:postcode":"51453",
    "sg:province":"IA",
    "sg:tags":[
        "excavating",
        "contractor"
    ],
    "wof:name":"Gemberling Excavation",
    "wof:placetype":"venue"
},
  "geometry": {"coordinates":[-94.59020099999999,42.267088],"type":"Point"}
}