{
  "type": "Feature",
  "properties": {
    "addr:full":"10214 Oakwood Dr Urbandale IA 50322",
    "addr:housenumber":"10214",
    "addr:postcode":"50322",
    "addr:street":"Oakwood Dr",
    "iso:country":"US",
    "sg:address":"10214 Oakwood Dr",
    "sg:city":"Urbandale",
    "sg:classifiers":[
        {
            "category":"Professional",
            "subcategory":"Computer Services",
            "type":"Services"
        }
    ],
    "sg:phone":"+1 515 334 5525",
    "sg:postcode":"50322",
    "sg:province":"IA",
    "sg:tags":[
        "communications",
        "datum",
        "telephone"
    ],
    "wof:name":"Daniel J Webster",
    "wof:placetype":"venue"
},
  "geometry": {"coordinates":[-93.75909900000001,41.644509],"type":"Point"}
}