{
  "type": "Feature",
  "properties": {
    "addr:full":"14602 35th St Oelwein IA 50662",
    "addr:housenumber":"14602",
    "addr:postcode":"50662",
    "addr:street":"35Th St",
    "iso:country":"US",
    "sg:address":"14602 35th St",
    "sg:city":"Oelwein",
    "sg:classifiers":[
        {
            "category":"Restaurant",
            "type":"Food & Drink"
        }
    ],
    "sg:phone":"+1 319 283 2307",
    "sg:postcode":"50662",
    "sg:province":"IA",
    "sg:tags":[
        "eating"
    ],
    "wof:name":"Jennys Country Parlor",
    "wof:placetype":"venue"
},
  "geometry": {"coordinates":[-91.872854,42.679638],"type":"Point"}
}