{
  "type": "Feature",
  "properties": {
    "iso:country":"US",
    "sg:address":"1404 16th St",
    "sg:city":"Harlan",
    "sg:classifiers":[
        {
            "category":"Freight",
            "type":"Transportation"
        }
    ],
    "sg:phone":"+1 712 755 7792",
    "sg:postcode":"51537",
    "sg:province":"IA",
    "sg:tags":[
        "operator",
        "local",
        "trucking"
    ],
    "wof:name":"Akorn Trucking LLC",
    "wof:placetype":"venue"
},
  "geometry": {"coordinates":[-95.33224800000001,41.65412],"type":"Point"}
}