{
  "type": "Feature",
  "properties": {
    "addr:full":"801 N Broadway St Red Oak IA 51566",
    "addr:housenumber":"801",
    "addr:postcode":"51566",
    "addr:street":"N Broadway St",
    "iso:country":"US",
    "sg:address":"801 N Broadway St",
    "sg:city":"Red Oak",
    "sg:classifiers":[
        {
            "category":"Shopping",
            "subcategory":"Department Store",
            "type":"Retail Goods"
        }
    ],
    "sg:phone":"+1 712 623 4818",
    "sg:postcode":"51566",
    "sg:province":"IA",
    "sg:tags":[
        "shop"
    ],
    "wof:name":"Pamida",
    "wof:placetype":"venue"
},
  "geometry": {"coordinates":[-95.23271,41.011793],"type":"Point"}
}