{
  "type": "Feature",
  "properties": {
    "iso:country":"US",
    "sg:address":"109 8th St NW",
    "sg:city":"Hampton",
    "sg:classifiers":[
        {
            "category":"Professional",
            "type":"Services"
        }
    ],
    "sg:phone":"+1 641 456 3769",
    "sg:postcode":"50441",
    "sg:province":"IA",
    "wof:name":"You Call We Haul",
    "wof:placetype":"venue"
},
  "geometry": {"coordinates":[-93.217107,42.743505],"type":"Point"}
}