{
  "type": "Feature",
  "properties": {
    "iso:country":"US",
    "sg:address":"3557 5th Ave S",
    "sg:city":"Fort Dodge",
    "sg:classifiers":[
        {
            "category":"Home & Garden",
            "subcategory":"Carpets & Floor Coverings",
            "type":"Retail Goods"
        }
    ],
    "sg:phone":"+1 515 955 2207",
    "sg:postcode":"50501",
    "sg:province":"IA",
    "sg:tags":[
        "dealer",
        "rug"
    ],
    "sg:website":"www.jimscarpetone.com",
    "wof:name":"Jim's Carpet One",
    "wof:placetype":"venue"
},
  "geometry": {"coordinates":[-94.14595,42.501187],"type":"Point"}
}