{
  "type": "Feature",
  "properties": {
    "iso:country":"US",
    "sg:address":"231 2nd Ave NE",
    "sg:city":"Le Mars",
    "sg:classifiers":[
        {
            "category":"Government",
            "subcategory":"Office",
            "type":"Public Place"
        }
    ],
    "sg:phone":"+1 712 546 8101",
    "sg:postcode":"51031",
    "sg:province":"IA",
    "sg:tags":[
        "civil",
        "defense",
        "agency"
    ],
    "wof:name":"Civil Defense",
    "wof:placetype":"venue"
},
  "geometry": {"coordinates":[-96.163707,42.796335],"type":"Point"}
}