{
  "type": "Feature",
  "properties": {
    "iso:country":"US",
    "sg:address":"12150 Addison Ave",
    "sg:city":"Riceville",
    "sg:classifiers":[
        {
            "category":"Manufacturing",
            "subcategory":"Motor Vehicles & Parts",
            "type":"Manufacturing & Wholesale Goods"
        }
    ],
    "sg:phone":"+1 641 985 2900",
    "sg:postcode":"50466",
    "sg:province":"IA",
    "sg:tags":[
        "equipment",
        "truck"
    ],
    "wof:name":"Iowa Contract Fabricators Inc",
    "wof:placetype":"venue"
},
  "geometry": {"coordinates":[-92.554215,43.34005],"type":"Point"}
}