{
  "type": "Feature",
  "properties": {
    "addr:full":"1803 Washington St Hamburg IA 51640",
    "addr:housenumber":"1803",
    "addr:postcode":"51640",
    "addr:street":"Washington St",
    "iso:country":"US",
    "sg:address":"1803 Washington St",
    "sg:city":"Hamburg",
    "sg:classifiers":[
        {
            "category":"Autos & Motor Vehicles",
            "subcategory":"Fuel & Gas Station",
            "type":"Retail Goods"
        }
    ],
    "sg:phone":"+1 712 382 1421",
    "sg:postcode":"51640",
    "sg:province":"IA",
    "sg:tags":[
        "oil"
    ],
    "wof:name":"Holt Gas Co",
    "wof:placetype":"venue"
},
  "geometry": {"coordinates":[-95.652777,40.61089],"type":"Point"}
}