{
  "type": "Feature",
  "properties": {
    "iso:country":"US",
    "sg:address":"402 Linden St",
    "sg:city":"Oakland",
    "sg:classifiers":[
        {
            "category":"Home & Garden",
            "subcategory":"Building Materials",
            "type":"Retail Goods"
        }
    ],
    "sg:phone":"+1 712 482 3118",
    "sg:postcode":"51560",
    "sg:province":"IA",
    "wof:name":"Fullerton Building Ctr",
    "wof:placetype":"venue"
},
  "geometry": {"coordinates":[-95.396017,41.310776],"type":"Point"}
}