{
  "type": "Feature",
  "properties": {
    "iso:country":"US",
    "sg:address":"3800 Country Club Blvd",
    "sg:city":"Sioux City",
    "sg:classifiers":[
        {
            "category":"Professional",
            "subcategory":"Business Services",
            "type":"Services"
        }
    ],
    "sg:phone":"+1 712 234 1463",
    "sg:postcode":"51104",
    "sg:province":"IA",
    "wof:name":"Jnb Venture LLC",
    "wof:placetype":"venue"
},
  "geometry": {"coordinates":[-96.41302899999999,42.536166],"type":"Point"}
}