{
  "type": "Feature",
  "properties": {
    "iso:country":"US",
    "sg:address":"615 8th St",
    "sg:city":"De Witt",
    "sg:classifiers":[
        {
            "category":"Social Services",
            "type":"Services"
        }
    ],
    "sg:phone":"+1 563 659 9612",
    "sg:postcode":"52742",
    "sg:province":"IA",
    "sg:tags":[
        "organization",
        "welfare"
    ],
    "wof:name":"Referral & Svc Ctr",
    "wof:placetype":"venue"
},
  "geometry": {"coordinates":[-90.53912,41.823187],"type":"Point"}
}