{
  "type": "Feature",
  "properties": {
    "iso:country":"US",
    "sg:address":"201 Main St",
    "sg:city":"Ida Grove",
    "sg:classifiers":[
        {
            "category":"Insurance",
            "subcategory":"Insurance Agent",
            "type":"Services"
        }
    ],
    "sg:phone":"+1 712 364 2774",
    "sg:postcode":"51445",
    "sg:province":"IA",
    "wof:name":"Hoffman Insurance",
    "wof:placetype":"venue"
},
  "geometry": {"coordinates":[-95.47129,42.345079],"type":"Point"}
}