{
  "type": "Feature",
  "properties": {
    "iso:country":"US",
    "sg:address":"1696 State Hwy 14",
    "sg:city":"Knoxville",
    "sg:classifiers":[
        {
            "category":"Retail",
            "subcategory":"Auto Repair",
            "type":"Services"
        }
    ],
    "sg:phone":"+1 641 842 7478",
    "sg:postcode":"50138",
    "sg:province":"IA",
    "sg:tags":[
        "body",
        "automobile",
        "painting"
    ],
    "wof:name":"Chuck's Auto",
    "wof:placetype":"venue"
},
  "geometry": {"coordinates":[-93.108318,41.272242],"type":"Point"}
}