{
  "type": "Feature",
  "properties": {
    "addr:full":"501 Sycamore St Waterloo IA 50703",
    "addr:housenumber":"501",
    "addr:postcode":"50703",
    "addr:street":"Sycamore St",
    "iso:country":"US",
    "sg:address":"501 Sycamore St",
    "sg:city":"Waterloo",
    "sg:classifiers":[
        {
            "category":"Organizations",
            "subcategory":"Non-profit Organization",
            "type":"Services"
        }
    ],
    "sg:phone":"+1 319 433 0395",
    "sg:postcode":"50703",
    "sg:province":"IA",
    "sg:tags":[
        "human"
    ],
    "wof:name":"Families First",
    "wof:placetype":"venue"
},
  "geometry": {"coordinates":[-92.335898,42.498253],"type":"Point"}
}