{
  "type": "Feature",
  "properties": {
    "iso:country":"US",
    "sg:address":"1404 190th St",
    "sg:city":"Winterset",
    "sg:phone":"+1 515 462 3739",
    "sg:postcode":"50273",
    "sg:province":"IA",
    "sg:tags":[
        "farm",
        "corn",
        "soybean"
    ],
    "wof:name":"Dennis Bautch",
    "wof:placetype":"venue"
},
  "geometry": {"coordinates":[-94.138964,41.373609],"type":"Point"}
}