{
  "type": "Feature",
  "properties": {
    "iso:country":"US",
    "sg:address":"702 S Phillips St",
    "sg:city":"Algona",
    "sg:classifiers":[
        {
            "category":"Food & Beverages",
            "subcategory":"Specialty",
            "type":"Retail Goods"
        }
    ],
    "sg:phone":"+1 515 295 7014",
    "sg:postcode":"50511",
    "sg:province":"IA",
    "sg:tags":[
        "tea",
        "coffee"
    ],
    "wof:name":"Daily Grind",
    "wof:placetype":"venue"
},
  "geometry": {"coordinates":[-94.22701600000001,43.063301],"type":"Point"}
}