{
  "type": "Feature",
  "properties": {
    "iso:country":"US",
    "sg:address":"802 12th St",
    "sg:city":"Hawarden",
    "sg:classifiers":[
        {
            "category":"Organizations",
            "subcategory":"Religious Organization",
            "type":"Services"
        }
    ],
    "sg:phone":"+1 712 551 4294",
    "sg:postcode":"51023",
    "sg:province":"IA",
    "sg:tags":[
        "church"
    ],
    "wof:name":"Friendship Assembly Of God",
    "wof:placetype":"venue"
},
  "geometry": {"coordinates":[-96.483942,42.999547],"type":"Point"}
}