{
  "type": "Feature",
  "properties": {
    "iso:country":"US",
    "sg:address":"600 E Main St",
    "sg:city":"Anamosa",
    "sg:classifiers":[
        {
            "category":"Recreation",
            "type":"Entertainment"
        }
    ],
    "sg:phone":"+1 319 462 6181",
    "sg:postcode":"52205",
    "sg:province":"IA",
    "sg:tags":[
        "hall",
        "auditorium"
    ],
    "wof:name":"Lawrence Community Ctr",
    "wof:placetype":"venue"
},
  "geometry": {"coordinates":[-91.278526,42.108332],"type":"Point"}
}