{
  "type": "Feature",
  "properties": {
    "iso:country":"US",
    "sg:address":"1201 6th St SW",
    "sg:city":"Cedar Rapids",
    "sg:classifiers":[
        {
            "category":"Government",
            "subcategory":"Office",
            "type":"Public Place"
        }
    ],
    "sg:phone":"+1 319 286 5802",
    "sg:postcode":"52404",
    "sg:province":"IA",
    "sg:tags":[
        "village"
    ],
    "wof:name":"Cedar Rapids Engineering Dept",
    "wof:placetype":"venue"
},
  "geometry": {"coordinates":[-91.677138,41.966466],"type":"Point"}
}