{
  "type": "Feature",
  "properties": {
    "iso:country":"US",
    "sg:address":"5000 Westown Pkwy",
    "sg:city":"West Des Moines",
    "sg:classifiers":[
        {
            "category":"Insurance",
            "subcategory":"Insurance Agent",
            "type":"Services"
        }
    ],
    "sg:phone":"+1 515 273 3530",
    "sg:postcode":"50265",
    "sg:province":"IA",
    "wof:name":"Insurance Strategies Consltng",
    "wof:placetype":"venue"
},
  "geometry": {"coordinates":[-93.77457200000001,41.59542],"type":"Point"}
}