{
  "type": "Feature",
  "properties": {
    "iso:country":"US",
    "sg:address":"125 Kitty Hawk Dr",
    "sg:city":"Ames",
    "sg:classifiers":[
        {
            "category":"Food & Beverages",
            "subcategory":"Bakery",
            "type":"Retail Goods"
        }
    ],
    "sg:phone":"+1 515 233 9352",
    "sg:postcode":"50010",
    "sg:province":"IA",
    "sg:tags":[
        "baker"
    ],
    "wof:name":"Old Home Bread",
    "wof:placetype":"venue"
},
  "geometry": {"coordinates":[-93.61152,41.996443],"type":"Point"}
}