{
  "type": "Feature",
  "properties": {
    "iso:country":"US",
    "sg:address":"2500 Quincy Ave",
    "sg:city":"Bedford",
    "sg:classifiers":[
        {
            "category":"Farming",
            "subcategory":"Farm",
            "type":"Manufacturing & Wholesale Goods"
        }
    ],
    "sg:phone":"+1 712 523 3268",
    "sg:postcode":"50833",
    "sg:province":"IA",
    "sg:tags":[
        "crop",
        "general"
    ],
    "wof:name":"Murphy Farm",
    "wof:placetype":"venue"
},
  "geometry": {"coordinates":[-94.613983,40.684043],"type":"Point"}
}