{
  "type": "Feature",
  "properties": {
    "addr:full":"205 E 2nd St Muscatine IA 52761",
    "addr:housenumber":"205",
    "addr:postcode":"52761",
    "addr:street":"E 2Nd St",
    "iso:country":"US",
    "sg:address":"205 E 2nd St",
    "sg:city":"Muscatine",
    "sg:classifiers":[
        {
            "category":"Place Of Worship",
            "type":"Public Place"
        }
    ],
    "sg:phone":"+1 563 264 0331",
    "sg:postcode":"52761",
    "sg:province":"IA",
    "sg:tags":[
        "church"
    ],
    "wof:name":"Iglesia El Shofar",
    "wof:placetype":"venue"
},
  "geometry": {"coordinates":[-91.04462700000001,41.421976],"type":"Point"}
}