{
  "type": "Feature",
  "properties": {
    "addr:full":"600 Raccoon St Des Moines IA 50309",
    "addr:housenumber":"600",
    "addr:postcode":"50309",
    "addr:street":"Raccoon St",
    "iso:country":"US",
    "sg:address":"600 Raccoon St",
    "sg:city":"Des Moines",
    "sg:phone":"+1 515 244 4271",
    "sg:postcode":"50309",
    "sg:province":"IA",
    "sg:tags":[
        "oil"
    ],
    "sg:website":"www.lubricants-oil.com",
    "wof:name":"Diamond Oil Co",
    "wof:placetype":"venue"
},
  "geometry": {"coordinates":[-93.60607,41.583771],"type":"Point"}
}