{
  "type": "Feature",
  "properties": {
    "addr:full":"22287 Oakes Rd Glenwood IA 51534",
    "addr:postcode":"22287;51534",
    "addr:street":"Oakes Rd",
    "iso:country":"US",
    "sg:address":"22287 Oakes Rd",
    "sg:city":"Glenwood",
    "sg:classifiers":[
        {
            "category":"Manufacturing",
            "subcategory":"Textiles",
            "type":"Manufacturing & Wholesale Goods"
        }
    ],
    "sg:phone":"+1 712 527 3361",
    "sg:postcode":"51534",
    "sg:province":"IA",
    "sg:tags":[
        "finishing",
        "plant",
        "cotton"
    ],
    "wof:name":"Anns Decorating",
    "wof:placetype":"venue"
},
  "geometry": {"coordinates":[-95.764573,40.94761],"type":"Point"}
}