{
  "type": "Feature",
  "properties": {
    "iso:country":"US",
    "sg:address":"1118 25th St SE",
    "sg:city":"Cedar Rapids",
    "sg:classifiers":[
        {
            "category":"Professional",
            "subcategory":"Computer Services",
            "type":"Services"
        }
    ],
    "sg:phone":"+1 319 366 5598",
    "sg:postcode":"52403",
    "sg:province":"IA",
    "sg:tags":[
        "related"
    ],
    "wof:name":"Jesse Peterson",
    "wof:placetype":"venue"
},
  "geometry": {"coordinates":[-91.63167,41.974801],"type":"Point"}
}