{
  "type": "Feature",
  "properties": {
    "addr:full":"926 Concert St Keokuk IA 52632",
    "addr:housenumber":"926",
    "addr:postcode":"52632",
    "addr:street":"Concert St",
    "iso:country":"US",
    "sg:address":"926 Concert St",
    "sg:city":"Keokuk",
    "sg:classifiers":[
        {
            "category":"Manufacturing",
            "subcategory":"Printing",
            "type":"Manufacturing & Wholesale Goods"
        }
    ],
    "sg:phone":"+1 319 524 1000",
    "sg:postcode":"52632",
    "sg:province":"IA",
    "sg:tags":[
        "screen"
    ],
    "wof:name":"Dragon Studio",
    "wof:placetype":"venue"
},
  "geometry": {"coordinates":[-91.38514600000001,40.400732],"type":"Point"}
}