{
  "type": "Feature",
  "properties": {
    "iso:country":"US",
    "sg:address":"29818 270th St",
    "sg:city":"Shell Rock",
    "sg:phone":"+1 319 885 6654",
    "sg:postcode":"50670",
    "sg:province":"IA",
    "sg:tags":[
        "farm",
        "corn",
        "soybean"
    ],
    "wof:name":"Lynn Rodenbeck",
    "wof:placetype":"venue"
},
  "geometry": {"coordinates":[-92.63728,42.656771],"type":"Point"}
}