{
  "type": "Feature",
  "properties": {
    "iso:country":"US",
    "sg:address":"4303 Stone Ave",
    "sg:city":"Sioux City",
    "sg:classifiers":[
        {
            "category":"Organizations",
            "subcategory":"Non-profit Organization",
            "type":"Services"
        }
    ],
    "sg:phone":"+1 712 274 2252",
    "sg:postcode":"51106",
    "sg:province":"IA",
    "sg:website":"www.midstepservices.com",
    "wof:name":"Mid Step Svc",
    "wof:placetype":"venue"
},
  "geometry": {"coordinates":[-96.351556,42.479202],"type":"Point"}
}