{
  "type": "Feature",
  "properties": {
    "addr:full":"2540 E 53rd St Davenport IA 52807",
    "addr:housenumber":"2540",
    "addr:postcode":"52807",
    "addr:street":"E 53Rd St",
    "iso:country":"US",
    "sg:address":"2540 E 53rd St",
    "sg:city":"Davenport",
    "sg:classifiers":[
        {
            "category":"Home & Garden",
            "subcategory":"Carpets & Floor Coverings",
            "type":"Retail Goods"
        }
    ],
    "sg:phone":"+1 563 344 3399",
    "sg:postcode":"52807",
    "sg:province":"IA",
    "sg:tags":[
        "dealer",
        "rug"
    ],
    "sg:website":"www.flooringxpress.com",
    "wof:name":"FLOORING Xpress",
    "wof:placetype":"venue"
},
  "geometry": {"coordinates":[-90.53926300000001,41.574862],"type":"Point"}
}