{
  "type": "Feature",
  "properties": {
    "addr:full":"3275 X Ave Manilla IA 51454",
    "addr:housenumber":"3275",
    "addr:postcode":"51454",
    "addr:street":"X Ave",
    "iso:country":"US",
    "sg:address":"3275 X Ave",
    "sg:city":"Manilla",
    "sg:phone":"+1 712 654 2160",
    "sg:postcode":"51454",
    "sg:province":"IA",
    "sg:tags":[
        "farm",
        "corn",
        "soybean"
    ],
    "wof:name":"Gary Muhlbauer",
    "wof:placetype":"venue"
},
  "geometry": {"coordinates":[-95.232564,41.878204],"type":"Point"}
}