{
  "type": "Feature",
  "properties": {
    "iso:country":"US",
    "sg:address":"3701 Southgate Dr",
    "sg:city":"Sioux City",
    "sg:classifiers":[
        {
            "category":"Freight",
            "type":"Transportation"
        }
    ],
    "sg:phone":"+1 712 258 7568",
    "sg:postcode":"51106",
    "sg:province":"IA",
    "sg:tags":[
        "mover"
    ],
    "wof:name":"I-Go Van & Storage Co",
    "wof:placetype":"venue"
},
  "geometry": {"coordinates":[-96.36964999999999,42.442026],"type":"Point"}
}