{
  "type": "Feature",
  "properties": {
    "iso:country":"US",
    "sg:address":"390 25th St SE",
    "sg:city":"Cedar Rapids",
    "sg:classifiers":[
        {
            "category":"Building & Trades",
            "subcategory":"Plumbing",
            "type":"Services"
        }
    ],
    "sg:phone":"+1 319 364 5044",
    "sg:postcode":"52403",
    "sg:province":"IA",
    "sg:tags":[
        "plumbing",
        "contractor"
    ],
    "wof:name":"Langan Plumbing & Heating Inc",
    "wof:placetype":"venue"
},
  "geometry": {"coordinates":[-91.631569,41.98367],"type":"Point"}
}