{
  "type": "Feature",
  "properties": {
    "addr:full":"118 20th St NE Cedar Rapids IA 52402",
    "addr:housenumber":"118",
    "addr:postcode":"52402",
    "addr:street":"20Th St Ne",
    "iso:country":"US",
    "sg:address":"118 20th St NE",
    "sg:city":"Cedar Rapids",
    "sg:classifiers":[
        {
            "category":"Building & Trades",
            "subcategory":"Construction",
            "type":"Services"
        }
    ],
    "sg:phone":"+1 319 366 2123",
    "sg:postcode":"52402",
    "sg:province":"IA",
    "sg:tags":[
        "contractor",
        "doctor",
        "hanging"
    ],
    "wof:name":"B & B Precision Painting",
    "wof:placetype":"venue"
},
  "geometry": {"coordinates":[-91.64070100000001,41.995098],"type":"Point"}
}