{
  "type": "Feature",
  "properties": {
    "addr:full":"3101 Ingersoll Ave Des Moines IA 50312",
    "addr:housenumber":"3101",
    "addr:postcode":"50312",
    "addr:street":"Ingersoll Ave",
    "iso:country":"US",
    "sg:address":"3101 Ingersoll Ave",
    "sg:city":"Des Moines",
    "sg:classifiers":[
        {
            "category":"Banks & Credit Unions",
            "subcategory":"Bank",
            "type":"Services"
        }
    ],
    "sg:phone":"+1 515 255 0515",
    "sg:postcode":"50312",
    "sg:province":"IA",
    "sg:tags":[
        "loan",
        "real estate"
    ],
    "wof:name":"Probity National Mortgage",
    "wof:placetype":"venue"
},
  "geometry": {"coordinates":[-93.661126,41.586282],"type":"Point"}
}