{
  "type": "Feature",
  "properties": {
    "iso:country":"US",
    "sg:address":"4091 Jackson Ave",
    "sg:city":"Orange City",
    "sg:phone":"+1 712 737 3192",
    "sg:postcode":"51041",
    "sg:province":"IA",
    "sg:tags":[
        "farm",
        "corn"
    ],
    "wof:name":"Mike Kleinhesselink",
    "wof:placetype":"venue"
},
  "geometry": {"coordinates":[-96.057006,43.056916],"type":"Point"}
}