{
  "type": "Feature",
  "properties": {
    "iso:country":"US",
    "sg:address":"205 Winfield Ave",
    "sg:city":"Mt Pleasant",
    "sg:classifiers":[
        {
            "category":"Wholesale",
            "subcategory":"Farm Supplies",
            "type":"Manufacturing & Wholesale Goods"
        }
    ],
    "sg:phone":"+1 319 385 2548",
    "sg:postcode":"52641",
    "sg:province":"IA",
    "sg:tags":[
        "feed"
    ],
    "wof:name":"Agri-Center-Henry County Inc",
    "wof:placetype":"venue"
},
  "geometry": {"coordinates":[-91.549809,40.981475],"type":"Point"}
}