{
  "type": "Feature",
  "properties": {
    "addr:full":"903 13th St Belle Plaine IA 52208",
    "addr:housenumber":"903",
    "addr:postcode":"52208",
    "addr:street":"13Th St",
    "iso:country":"US",
    "sg:address":"903 13th St",
    "sg:city":"Belle Plaine",
    "sg:classifiers":[
        {
            "category":"Personal",
            "subcategory":"Beauty Salon",
            "type":"Services"
        }
    ],
    "sg:phone":"+1 319 444 3898",
    "sg:postcode":"52208",
    "sg:province":"IA",
    "wof:name":"Hair Hut",
    "wof:placetype":"venue"
},
  "geometry": {"coordinates":[-92.274924,41.897024],"type":"Point"}
}