{
  "type": "Feature",
  "properties": {
    "iso:country":"US",
    "sg:address":"111 E Franklin St",
    "sg:city":"Bloomfield",
    "sg:classifiers":[
        {
            "category":"Wholesale",
            "subcategory":"Scrap",
            "type":"Manufacturing & Wholesale Goods"
        }
    ],
    "sg:phone":"+1 641 664 1324",
    "sg:postcode":"52537",
    "sg:province":"IA",
    "sg:tags":[
        "recycling",
        "center"
    ],
    "wof:name":"Bloomfield Redemption Ctr",
    "wof:placetype":"venue"
},
  "geometry": {"coordinates":[-92.41493699999999,40.750604],"type":"Point"}
}