{
  "type": "Feature",
  "properties": {
    "addr:full":"1712 S 42nd St West Des Moines IA 50265",
    "addr:housenumber":"1712",
    "addr:postcode":"50265",
    "addr:street":"S 42Nd St",
    "iso:country":"US",
    "sg:address":"1712 S 42nd St",
    "sg:city":"West Des Moines",
    "sg:classifiers":[
        {
            "category":"Building & Trades",
            "subcategory":"Construction",
            "type":"Services"
        }
    ],
    "sg:phone":"+1 515 223 4211",
    "sg:postcode":"50265",
    "sg:province":"IA",
    "sg:tags":[
        "general",
        "contractor"
    ],
    "wof:name":"Acheson Construction Inc",
    "wof:placetype":"venue"
},
  "geometry": {"coordinates":[-93.760155,41.544529],"type":"Point"}
}