{
  "type": "Feature",
  "properties": {
    "addr:full":"9178 145th St Davenport IA 52804",
    "addr:housenumber":"9178",
    "addr:postcode":"52804",
    "addr:street":"145Th St",
    "iso:country":"US",
    "sg:address":"9178 145th St",
    "sg:city":"Davenport",
    "sg:classifiers":[
        {
            "category":"Utilities",
            "subcategory":"Water",
            "type":"Services"
        },
        {
            "category":"Building & Trades",
            "subcategory":"Plumbing",
            "type":"Services"
        },
        {
            "category":"Home & Garden",
            "subcategory":"Hardware",
            "type":"Retail Goods"
        }
    ],
    "sg:phone":"+1 563 381 4278",
    "sg:postcode":"52804",
    "sg:province":"IA",
    "sg:tags":[
        "filtration",
        "softening",
        "supply",
        "work",
        "purification",
        "equipment",
        "conditioning"
    ],
    "wof:name":"Burdick's Water Services",
    "wof:placetype":"venue"
},
  "geometry": {"coordinates":[-90.72163,41.51618],"type":"Point"}
}