{
  "type": "Feature",
  "properties": {
    "addr:full":"550 1st Ave Coralville IA 52241",
    "addr:housenumber":"550",
    "addr:postcode":"52241",
    "addr:street":"1St Ave",
    "iso:country":"US",
    "sg:address":"550 1st Ave",
    "sg:city":"Coralville",
    "sg:classifiers":[
        {
            "category":"Restaurant",
            "type":"Food & Drink"
        }
    ],
    "sg:menulink":"http://www.allmenus.com/ia/west-lucas/160827-burger-king/menu/",
    "sg:phone":"+1 319 341 9408",
    "sg:postcode":"52241",
    "sg:province":"IA",
    "sg:tags":[
        "burger",
        "american"
    ],
    "wof:name":"Burger King",
    "wof:placetype":"venue"
},
  "geometry": {"coordinates":[-91.566216,41.675258],"type":"Point"}
}