{
  "type": "Feature",
  "properties": {
    "iso:country":"US",
    "sg:address":"3325 Utica Ridge Rd",
    "sg:city":"Bettendorf",
    "sg:classifiers":[
        {
            "category":"Banks & Credit Unions",
            "subcategory":"Bank",
            "type":"Services"
        }
    ],
    "sg:phone":"+1 563 332 5300",
    "sg:postcode":"52722",
    "sg:province":"IA",
    "sg:tags":[
        "loan",
        "real estate"
    ],
    "wof:name":"Symmetry Mortgage Corp",
    "wof:placetype":"venue"
},
  "geometry": {"coordinates":[-90.516902,41.556913],"type":"Point"}
}