{
  "type": "Feature",
  "properties": {
    "iso:country":"US",
    "sg:address":"819 Longview St",
    "sg:city":"Cedar Falls",
    "sg:classifiers":[
        {
            "category":"Personal",
            "subcategory":"Beauty Salon",
            "type":"Services"
        }
    ],
    "sg:phone":"+1 319 277 0644",
    "sg:postcode":"50613",
    "sg:province":"IA",
    "sg:tags":[
        "shop"
    ],
    "wof:name":"Hair Connection",
    "wof:placetype":"venue"
},
  "geometry": {"coordinates":[-92.455412,42.554638],"type":"Point"}
}