{
  "type": "Feature",
  "properties": {
    "iso:country":"US",
    "sg:address":"1010 E Army Post Rd",
    "sg:city":"Des Moines",
    "sg:classifiers":[
        {
            "category":"Home & Garden",
            "subcategory":"Hardware",
            "type":"Retail Goods"
        }
    ],
    "sg:phone":"+1 515 953 5833",
    "sg:postcode":"50315",
    "sg:province":"IA",
    "sg:tags":[
        "tool",
        "used"
    ],
    "wof:name":"Harbor Freight Tools USA Inc",
    "wof:placetype":"venue"
},
  "geometry": {"coordinates":[-93.602514,41.526428],"type":"Point"}
}