{
  "type": "Feature",
  "properties": {
    "addr:full":"401 West St Bonaparte IA 52620",
    "addr:housenumber":"401",
    "addr:postcode":"52620",
    "addr:street":"West St",
    "iso:country":"US",
    "sg:address":"401 West St",
    "sg:city":"Bonaparte",
    "sg:classifiers":[
        {
            "category":"Retail",
            "subcategory":"Auto Repair",
            "type":"Services"
        }
    ],
    "sg:phone":"+1 319 592 3105",
    "sg:postcode":"52620",
    "sg:province":"IA",
    "sg:tags":[
        "wrecker"
    ],
    "wof:name":"Hainline Wholesale Tire Svc",
    "wof:placetype":"venue"
},
  "geometry": {"coordinates":[-91.803754,40.701775],"type":"Point"}
}