{
  "type": "Feature",
  "properties": {
    "iso:country":"US",
    "sg:address":"4672 Sutliff Rd NE",
    "sg:city":"Solon",
    "sg:classifiers":[
        {
            "category":"Farming",
            "subcategory":"Farm",
            "type":"Manufacturing & Wholesale Goods"
        }
    ],
    "sg:phone":"+1 319 624 2911",
    "sg:postcode":"52333",
    "sg:province":"IA",
    "wof:name":"Iowa Farm Dealers",
    "wof:placetype":"venue"
},
  "geometry": {"coordinates":[-91.468867,41.816513],"type":"Point"}
}