{
  "type": "Feature",
  "properties": {
    "iso:country":"US",
    "sg:address":"52783 Cherrywood Ave",
    "sg:city":"Griswold",
    "sg:classifiers":[
        {
            "category":"Farming",
            "subcategory":"Livestock Farm",
            "type":"Manufacturing & Wholesale Goods"
        }
    ],
    "sg:phone":"+1 712 778 2397",
    "sg:postcode":"51535",
    "sg:province":"IA",
    "sg:tags":[
        "beef",
        "feedlot",
        "cattle"
    ],
    "wof:name":"Mike Scoles",
    "wof:placetype":"venue"
},
  "geometry": {"coordinates":[-95.181758,41.235217],"type":"Point"}
}