{
  "type": "Feature",
  "properties": {
    "iso:country":"US",
    "sg:address":"6119 28th Avenue Dr",
    "sg:city":"Vinton",
    "sg:classifiers":[
        {
            "category":"Manufacturing",
            "subcategory":"Printing",
            "type":"Manufacturing & Wholesale Goods"
        }
    ],
    "sg:phone":"+1 319 472 3322",
    "sg:postcode":"52349",
    "sg:province":"IA",
    "sg:tags":[
        "commercial"
    ],
    "sg:website":"www.greentreegraphics.com",
    "wof:name":"Greentree Graphics",
    "wof:placetype":"venue"
},
  "geometry": {"coordinates":[-91.941264,42.133767],"type":"Point"}
}