{
  "type": "Feature",
  "properties": {
    "iso:country":"US",
    "sg:address":"614 S Vermont St",
    "sg:city":"Maquoketa",
    "sg:classifiers":[
        {
            "category":"Personal",
            "subcategory":"Beauty Salon",
            "type":"Services"
        }
    ],
    "sg:phone":"+1 563 652 5394",
    "sg:postcode":"52060",
    "sg:province":"IA",
    "wof:name":"Fringe Benefits Salon",
    "wof:placetype":"venue"
},
  "geometry": {"coordinates":[-90.673238,42.060683],"type":"Point"}
}