{
  "type": "Feature",
  "properties": {
    "iso:country":"US",
    "sg:address":"523 Euclid Ave",
    "sg:city":"Des Moines",
    "sg:classifiers":[
        {
            "category":"Restaurant",
            "type":"Food & Drink"
        }
    ],
    "sg:phone":"+1 515 243 3085",
    "sg:postcode":"50313",
    "sg:province":"IA",
    "wof:name":"Chicago Dog Deli & Pizza",
    "wof:placetype":"venue"
},
  "geometry": {"coordinates":[-93.624577,41.627762],"type":"Point"}
}