{
  "type": "Feature",
  "properties": {
    "iso:country":"US",
    "sg:address":"2105 Lincoln Way",
    "sg:city":"Clinton",
    "sg:classifiers":[
        {
            "category":"Building & Trades",
            "subcategory":"Construction",
            "type":"Services"
        }
    ],
    "sg:phone":"+1 563 242 2740",
    "sg:postcode":"52732",
    "sg:province":"IA",
    "sg:tags":[
        "excavating",
        "contractor"
    ],
    "wof:name":"Foley Construction Co",
    "wof:placetype":"venue"
},
  "geometry": {"coordinates":[-90.235647,41.81569],"type":"Point"}
}