{
  "type": "Feature",
  "properties": {
    "iso:country":"US",
    "sg:address":"5608 SW 9th St",
    "sg:city":"Des Moines",
    "sg:classifiers":[
        {
            "category":"Health Services",
            "subcategory":"Nursing And Care Facility",
            "type":"Services"
        }
    ],
    "sg:phone":"+1 515 285 3070",
    "sg:postcode":"50315",
    "sg:province":"IA",
    "sg:tags":[
        "home",
        "convalescent"
    ],
    "wof:name":"Genesis Senior Living Ctr",
    "wof:placetype":"venue"
},
  "geometry": {"coordinates":[-93.625812,41.531996],"type":"Point"}
}