{
  "type": "Feature",
  "properties": {
    "iso:country":"US",
    "sg:address":"28172 Beechnut Rd",
    "sg:city":"Clermont",
    "sg:classifiers":[
        {
            "category":"Local Transit",
            "type":"Transportation"
        }
    ],
    "sg:phone":"+1 563 423 7226",
    "sg:postcode":"52135",
    "sg:province":"IA",
    "sg:tags":[
        "passenger"
    ],
    "wof:name":"Magic Moments Limousine",
    "wof:placetype":"venue"
},
  "geometry": {"coordinates":[-91.633962,43.043627],"type":"Point"}
}