{
  "type": "Feature",
  "properties": {
    "addr:full":"1508 1st Ave NE Cedar Rapids IA 52402",
    "addr:housenumber":"1508",
    "addr:postcode":"52402",
    "addr:street":"1St Ave Ne",
    "iso:country":"US",
    "sg:address":"1508 1st Ave NE",
    "sg:city":"Cedar Rapids",
    "sg:classifiers":[
        {
            "category":"Banks & Credit Unions",
            "subcategory":"Investment Brokerage",
            "type":"Services"
        }
    ],
    "sg:phone":"+1 319 362 3225",
    "sg:postcode":"52402",
    "sg:province":"IA",
    "sg:tags":[
        "advisory",
        "financial"
    ],
    "wof:name":"PPS Financial Svc Inc",
    "wof:placetype":"venue"
},
  "geometry": {"coordinates":[-91.65081000000001,41.989032],"type":"Point"}
}