{
  "type": "Feature",
  "properties": {
    "addr:full":"542 5th St West Des Moines IA 50265",
    "addr:housenumber":"542",
    "addr:postcode":"50265",
    "addr:street":"5Th St",
    "iso:country":"US",
    "sg:address":"542 5th St",
    "sg:city":"West Des Moines",
    "sg:classifiers":[
        {
            "category":"Food & Beverages",
            "subcategory":"Groceries & Convenience Stores",
            "type":"Retail Goods"
        }
    ],
    "sg:phone":"+1 515 279 4466",
    "sg:postcode":"50265",
    "sg:province":"IA",
    "wof:name":"Scott's Shoppe",
    "wof:placetype":"venue"
},
  "geometry": {"coordinates":[-93.70896500000001,41.576513],"type":"Point"}
}