{
  "type": "Feature",
  "properties": {
    "iso:country":"US",
    "sg:address":"962 Maplewood Dr NE",
    "sg:city":"Cedar Rapids",
    "sg:classifiers":[
        {
            "category":"Manufacturing",
            "subcategory":"Chemicals & Compounds",
            "type":"Manufacturing & Wholesale Goods"
        }
    ],
    "sg:phone":"+1 319 364 7875",
    "sg:postcode":"52402",
    "sg:province":"IA",
    "sg:tags":[
        "mfg"
    ],
    "wof:name":"Cassies Cleaning With Class",
    "wof:placetype":"venue"
},
  "geometry": {"coordinates":[-91.657079,41.996073],"type":"Point"}
}