{
  "type": "Feature",
  "properties": {
    "iso:country":"US",
    "sg:address":"1403 NW Church St",
    "sg:city":"Leon",
    "sg:classifiers":[
        {
            "category":"Government",
            "subcategory":"Office",
            "type":"Public Place"
        }
    ],
    "sg:phone":"+1 641 446 4855",
    "sg:postcode":"50144",
    "sg:province":"IA",
    "wof:name":"South Central Comnty Program",
    "wof:placetype":"venue"
},
  "geometry": {"coordinates":[-93.747714,40.750352],"type":"Point"}
}