{
  "type": "Feature",
  "properties": {
    "iso:country":"US",
    "sg:address":"3940 E 29th St",
    "sg:city":"Des Moines",
    "sg:classifiers":[
        {
            "category":"Professional",
            "subcategory":"Management & Consulting",
            "type":"Services"
        }
    ],
    "sg:phone":"+1 515 262 2220",
    "sg:postcode":"50317",
    "sg:province":"IA",
    "sg:tags":[
        "business"
    ],
    "wof:name":"Exact Software Erp-Na Inc",
    "wof:placetype":"venue"
},
  "geometry": {"coordinates":[-93.56125,41.630578],"type":"Point"}
}