{
  "type": "Feature",
  "properties": {
    "iso:country":"US",
    "sg:address":"8651 Douglas Ave",
    "sg:city":"Urbandale",
    "sg:classifiers":[
        {
            "category":"Shopping",
            "subcategory":"Clothing, Apparel, & Fashions",
            "type":"Retail Goods"
        }
    ],
    "sg:phone":"+1 515 278 2553",
    "sg:postcode":"50322",
    "sg:province":"IA",
    "wof:name":"Lb Standard Clothiers",
    "wof:placetype":"venue"
},
  "geometry": {"coordinates":[-93.738501,41.629404],"type":"Point"}
}