{
  "type": "Feature",
  "properties": {
    "iso:country":"US",
    "sg:address":"115 Iowa Ave",
    "sg:city":"Dunlap",
    "sg:classifiers":[
        {
            "category":"Professional",
            "subcategory":"Lawyer & Legal Services",
            "type":"Services"
        }
    ],
    "sg:phone":"+1 712 643 1304",
    "sg:postcode":"51529",
    "sg:province":"IA",
    "sg:tags":[
        "attorney"
    ],
    "wof:name":"Bush Law Office",
    "wof:placetype":"venue"
},
  "geometry": {"coordinates":[-95.60205000000001,41.854404],"type":"Point"}
}