{
  "type": "Feature",
  "properties": {
    "iso:country":"US",
    "sg:address":"1165 Casper Ave",
    "sg:city":"Plainfield",
    "sg:phone":"+1 319 276 3537",
    "sg:postcode":"50666",
    "sg:province":"IA",
    "sg:tags":[
        "farm",
        "corn"
    ],
    "wof:name":"Brian Bahlmann",
    "wof:placetype":"venue"
},
  "geometry": {"coordinates":[-92.51124,42.881929],"type":"Point"}
}