{
  "type": "Feature",
  "properties": {
    "addr:full":"3371 Needham Ave Wall Lake IA 51466",
    "addr:housenumber":"3371",
    "addr:postcode":"51466",
    "addr:street":"Needham Ave Wall",
    "iso:country":"US",
    "sg:address":"3371 Needham Ave",
    "sg:city":"Wall Lake",
    "sg:classifiers":[
        {
            "category":"Professional",
            "subcategory":"Business Services",
            "type":"Services"
        }
    ],
    "sg:phone":"+1 712 664 2777",
    "sg:postcode":"51466",
    "sg:province":"IA",
    "sg:tags":[
        "retail",
        "miscellaneous",
        "merchandise"
    ],
    "wof:name":"Haley Implement Co New Holland",
    "wof:placetype":"venue"
},
  "geometry": {"coordinates":[-95.09030199999999,42.301206],"type":"Point"}
}