{
  "type": "Feature",
  "properties": {
    "addr:full":"2142 220th St Independence IA 50644",
    "addr:housenumber":"2142",
    "addr:postcode":"50644",
    "addr:street":"220Th St",
    "iso:country":"US",
    "sg:address":"2142 220th St",
    "sg:city":"Independence",
    "sg:classifiers":[
        {
            "category":"Building & Trades",
            "subcategory":"Construction",
            "type":"Services"
        }
    ],
    "sg:phone":"+1 319 934 3540",
    "sg:postcode":"50644",
    "sg:province":"IA",
    "sg:tags":[
        "carpenter"
    ],
    "wof:name":"Steve's Custom Carpentry",
    "wof:placetype":"venue"
},
  "geometry": {"coordinates":[-91.85310699999999,42.468636],"type":"Point"}
}