{
  "type": "Feature",
  "properties": {
    "addr:full":"423 George St Sioux City IA 51103",
    "addr:housenumber":"423",
    "addr:postcode":"51103",
    "addr:street":"George St",
    "iso:country":"US",
    "sg:address":"423 George St",
    "sg:city":"Sioux City",
    "sg:classifiers":[
        {
            "category":"Organizations",
            "subcategory":"Religious Organization",
            "type":"Services"
        }
    ],
    "sg:phone":"+1 712 258 4938",
    "sg:postcode":"51103",
    "sg:province":"IA",
    "sg:tags":[
        "church"
    ],
    "wof:name":"New Creation Ministries",
    "wof:placetype":"venue"
},
  "geometry": {"coordinates":[-96.426999,42.501392],"type":"Point"}
}