{
  "type": "Feature",
  "properties": {
    "iso:country":"US",
    "sg:address":"2819 22nd Ave NW",
    "sg:city":"Waverly",
    "sg:classifiers":[
        {
            "category":"Retail",
            "subcategory":"Auto Repair",
            "type":"Services"
        }
    ],
    "sg:phone":"+1 319 352 3670",
    "sg:postcode":"50677",
    "sg:province":"IA",
    "sg:tags":[
        "general"
    ],
    "wof:name":"Smittys Repair",
    "wof:placetype":"venue"
},
  "geometry": {"coordinates":[-92.50540599999999,42.74448],"type":"Point"}
}