{
  "type": "Feature",
  "properties": {
    "addr:full":"2841 Littlefield Dr Exira IA 50076",
    "addr:housenumber":"2841",
    "addr:postcode":"50076",
    "addr:street":"Littlefield Dr Exira",
    "iso:country":"US",
    "sg:address":"2841 Littlefield Dr",
    "sg:city":"Exira",
    "sg:phone":"+1 712 268 2739",
    "sg:postcode":"50076",
    "sg:province":"IA",
    "sg:tags":[
        "farm",
        "corn"
    ],
    "wof:name":"Lawrence Clausen",
    "wof:placetype":"venue"
},
  "geometry": {"coordinates":[-94.75811400000001,41.536902],"type":"Point"}
}