{
  "type": "Feature",
  "properties": {
    "iso:country":"US",
    "sg:address":"2609 Rainbow Dr",
    "sg:city":"Cedar Falls",
    "sg:classifiers":[
        {
            "category":"Retail",
            "subcategory":"Portrait Studio",
            "type":"Services"
        }
    ],
    "sg:phone":"+1 319 277 7141",
    "sg:postcode":"50613",
    "sg:province":"IA",
    "sg:tags":[
        "photographer"
    ],
    "wof:name":"Vorland Photography",
    "wof:placetype":"venue"
},
  "geometry": {"coordinates":[-92.41368300000001,42.516983],"type":"Point"}
}