{
  "type": "Feature",
  "properties": {
    "iso:country":"US",
    "sg:address":"110 E Leclaire Rd",
    "sg:city":"Eldridge",
    "sg:classifiers":[
        {
            "category":"Insurance",
            "subcategory":"Insurance Agent",
            "type":"Services"
        }
    ],
    "sg:phone":"+1 563 285 4321",
    "sg:postcode":"52748",
    "sg:province":"IA",
    "wof:name":"Porter Insurance",
    "wof:placetype":"venue"
},
  "geometry": {"coordinates":[-90.58282699999999,41.654771],"type":"Point"}
}