{
  "type": "Feature",
  "properties": {
    "iso:country":"US",
    "sg:address":"2746 Cedar Terrace Dr",
    "sg:city":"Waterloo",
    "sg:classifiers":[
        {
            "category":"Freight",
            "type":"Transportation"
        }
    ],
    "sg:phone":"+1 319 296 2797",
    "sg:postcode":"50702",
    "sg:province":"IA",
    "sg:tags":[
        "delivery"
    ],
    "wof:name":"D & R Delivery",
    "wof:placetype":"venue"
},
  "geometry": {"coordinates":[-92.292457,42.446827],"type":"Point"}
}