{
  "type": "Feature",
  "properties": {
    "iso:country":"US",
    "sg:address":"701 S Federal Ave",
    "sg:city":"Mason City",
    "sg:classifiers":[
        {
            "category":"Professional",
            "type":"Services"
        }
    ],
    "sg:phone":"+1 641 423 0391",
    "sg:postcode":"50401",
    "sg:province":"IA",
    "sg:tags":[
        "establishment"
    ],
    "wof:name":"Castle Co",
    "wof:placetype":"venue"
},
  "geometry": {"coordinates":[-93.201088,43.144679],"type":"Point"}
}