{
  "type": "Feature",
  "properties": {
    "iso:country":"US",
    "sg:address":"103 Winding Ridge Rd",
    "sg:city":"Denver",
    "sg:classifiers":[
        {
            "category":"Professional",
            "type":"Services"
        }
    ],
    "sg:phone":"+1 319 984 5726",
    "sg:postcode":"50622",
    "sg:province":"IA",
    "wof:name":"James M Lown",
    "wof:placetype":"venue"
},
  "geometry": {"coordinates":[-92.372196,42.68508],"type":"Point"}
}