{
  "type": "Feature",
  "properties": {
    "addr:full":"122 1st St N Newton IA 50208",
    "addr:housenumber":"122",
    "addr:postcode":"50208",
    "addr:street":"1St St N",
    "iso:country":"US",
    "sg:address":"122 1st St N",
    "sg:city":"Newton",
    "sg:classifiers":[
        {
            "category":"Real Estate",
            "subcategory":"Real Estate Operator",
            "type":"Services"
        }
    ],
    "sg:phone":"+1 641 792 3443",
    "sg:postcode":"50208",
    "sg:province":"IA",
    "sg:tags":[
        "apartment"
    ],
    "wof:name":"Easy Keep Management Inc",
    "wof:placetype":"venue"
},
  "geometry": {"coordinates":[-93.05359199999999,41.700263],"type":"Point"}
}