{
  "type": "Feature",
  "properties": {
    "iso:country":"US",
    "sg:address":"3302 49th St",
    "sg:city":"Des Moines",
    "sg:classifiers":[
        {
            "category":"Local Transit",
            "type":"Transportation"
        }
    ],
    "sg:phone":"+1 515 249 1127",
    "sg:postcode":"50310",
    "sg:province":"IA",
    "sg:tags":[
        "airport"
    ],
    "wof:name":"Genes Transportation",
    "wof:placetype":"venue"
},
  "geometry": {"coordinates":[-93.685363,41.62674],"type":"Point"}
}