{
  "type": "Feature",
  "properties": {
    "addr:full":"1508 Hill Ave Spirit Lake IA 51360",
    "addr:housenumber":"1508",
    "addr:postcode":"51360",
    "addr:street":"Hill Ave",
    "iso:country":"US",
    "sg:address":"1508 Hill Ave",
    "sg:city":"Spirit Lake",
    "sg:classifiers":[
        {
            "category":"Professional",
            "subcategory":"Business Services",
            "type":"Services"
        }
    ],
    "sg:phone":"+1 712 336 3385",
    "sg:postcode":"51360",
    "sg:province":"IA",
    "sg:tags":[
        "interior",
        "design"
    ],
    "wof:name":"Designing Windows",
    "wof:placetype":"venue"
},
  "geometry": {"coordinates":[-95.10236399999999,43.425471],"type":"Point"}
}