{
  "type": "Feature",
  "properties": {
    "addr:full":"119 2nd St SE State Center IA 50247",
    "addr:housenumber":"119",
    "addr:postcode":"50247",
    "addr:street":"2Nd St Se",
    "iso:country":"US",
    "sg:address":"119 2nd St SE",
    "sg:city":"State Center",
    "sg:classifiers":[
        {
            "category":"Manufacturing",
            "subcategory":"Printing",
            "type":"Manufacturing & Wholesale Goods"
        }
    ],
    "sg:phone":"+1 641 483 2946",
    "sg:postcode":"50247",
    "sg:province":"IA",
    "sg:tags":[
        "commercial"
    ],
    "wof:name":"Eagle Printing",
    "wof:placetype":"venue"
},
  "geometry": {"coordinates":[-93.162087,42.016119],"type":"Point"}
}