{
  "type": "Feature",
  "properties": {
    "iso:country":"US",
    "sg:address":"1306 S 12th Ave E",
    "sg:city":"Newton",
    "sg:classifiers":[
        {
            "category":"Autos & Motor Vehicles",
            "subcategory":"Fuel & Gas Station",
            "type":"Retail Goods"
        }
    ],
    "sg:phone":"+1 641 792 2450",
    "sg:postcode":"50208",
    "sg:province":"IA",
    "sg:tags":[
        "station",
        "gasoline"
    ],
    "wof:name":"Newton Auto Service & Repair",
    "wof:placetype":"venue"
},
  "geometry": {"coordinates":[-93.036412,41.689293],"type":"Point"}
}