{
  "type": "Feature",
  "properties": {
    "addr:full":"612 Colleen Ave Waterloo IA 50707",
    "addr:housenumber":"612",
    "addr:postcode":"50707",
    "addr:street":"Colleen Ave",
    "iso:country":"US",
    "sg:address":"612 Colleen Ave",
    "sg:city":"Waterloo",
    "sg:classifiers":[
        {
            "category":"Organizations",
            "subcategory":"Community Association",
            "type":"Services"
        }
    ],
    "sg:phone":"+1 319 233 5569",
    "sg:postcode":"50707",
    "sg:province":"IA",
    "wof:name":"Order of White Shrine",
    "wof:placetype":"venue"
},
  "geometry": {"coordinates":[-92.292776,42.47025],"type":"Point"}
}