{
  "type": "Feature",
  "properties": {
    "iso:country":"US",
    "sg:address":"218 2nd St",
    "sg:city":"Hull",
    "sg:classifiers":[
        {
            "category":"Education",
            "subcategory":"School",
            "type":"Public Place"
        }
    ],
    "sg:phone":"+1 712 439 2490",
    "sg:postcode":"51239",
    "sg:province":"IA",
    "wof:name":"Hull Prot Ref Christian School",
    "wof:placetype":"venue"
},
  "geometry": {"coordinates":[-96.147243,43.189319],"type":"Point"}
}