{
  "type": "Feature",
  "properties": {
    "addr:full":"116 27th St NE Cedar Rapids IA 52402",
    "addr:housenumber":"116",
    "addr:postcode":"52402",
    "addr:street":"27Th St Ne",
    "iso:country":"US",
    "sg:address":"116 27th St NE",
    "sg:city":"Cedar Rapids",
    "sg:classifiers":[
        {
            "category":"Professional",
            "subcategory":"Computer Services",
            "type":"Services"
        }
    ],
    "sg:phone":"+1 319 366 0622",
    "sg:postcode":"52402",
    "sg:province":"IA",
    "sg:tags":[
        "repair"
    ],
    "wof:name":"Barb's Computer Sales & Service",
    "wof:placetype":"venue"
},
  "geometry": {"coordinates":[-91.635498,42.003502],"type":"Point"}
}