{
  "type": "Feature",
  "properties": {
    "iso:country":"US",
    "sg:address":"615 Maben Ave",
    "sg:city":"Garner",
    "sg:classifiers":[
        {
            "category":"Building & Trades",
            "subcategory":"Landscaping Services",
            "type":"Services"
        }
    ],
    "sg:phone":"+1 641 923 2957",
    "sg:postcode":"50438",
    "sg:province":"IA",
    "sg:tags":[
        "landscape"
    ],
    "wof:name":"Marks Outdoor Service",
    "wof:placetype":"venue"
},
  "geometry": {"coordinates":[-93.600692,43.099486],"type":"Point"}
}