{
  "type": "Feature",
  "properties": {
    "iso:country":"US",
    "sg:address":"20 Orchard St",
    "sg:city":"Le Mars",
    "sg:classifiers":[
        {
            "category":"Building & Trades",
            "subcategory":"Landscaping Services",
            "type":"Services"
        }
    ],
    "sg:phone":"+1 712 546 8130",
    "sg:postcode":"51031",
    "sg:province":"IA",
    "wof:name":"Larrys Stump Grinding Service",
    "wof:placetype":"venue"
},
  "geometry": {"coordinates":[-96.181269,42.78652],"type":"Point"}
}