{
  "type": "Feature",
  "properties": {
    "iso:country":"US",
    "sg:address":"928 6th Ave",
    "sg:city":"Des Moines",
    "sg:classifiers":[
        {
            "category":"Education",
            "subcategory":"College",
            "type":"Public Place"
        }
    ],
    "sg:phone":"+1 515 643 3180",
    "sg:postcode":"50309",
    "sg:province":"IA",
    "sg:tags":[
        "academic",
        "school"
    ],
    "wof:name":"Mercy College Health Sciences",
    "wof:placetype":"venue"
},
  "geometry": {"coordinates":[-93.62572299999999,41.594692],"type":"Point"}
}