{
  "type": "Feature",
  "properties": {
    "addr:full":"211 E Bremer Ave Waverly IA 50677",
    "addr:housenumber":"211",
    "addr:postcode":"50677",
    "addr:street":"E Bremer Ave",
    "iso:country":"US",
    "sg:address":"211 E Bremer Ave",
    "sg:city":"Waverly",
    "sg:classifiers":[
        {
            "category":"Shopping",
            "subcategory":"Clothing, Apparel, & Fashions",
            "type":"Retail Goods"
        }
    ],
    "sg:phone":"+1 319 352 1868",
    "sg:postcode":"50677",
    "sg:province":"IA",
    "wof:name":"Elegant Woman",
    "wof:placetype":"venue"
},
  "geometry": {"coordinates":[-92.468009,42.725874],"type":"Point"}
}