{
  "type": "Feature",
  "properties": {
    "addr:full":"108 W 3rd St Massena IA 50853",
    "addr:housenumber":"108",
    "addr:postcode":"50853",
    "addr:street":"W 3Rd St",
    "iso:country":"US",
    "sg:address":"108 W 3rd St",
    "sg:city":"Massena",
    "sg:classifiers":[
        {
            "category":"Organizations",
            "subcategory":"Religious Organization",
            "type":"Services"
        }
    ],
    "sg:phone":"+1 712 779 2270",
    "sg:postcode":"50853",
    "sg:province":"IA",
    "sg:tags":[
        "church"
    ],
    "wof:name":"United Methodist Church",
    "wof:placetype":"venue"
},
  "geometry": {"coordinates":[-94.769036,41.253879],"type":"Point"}
}