{
  "type": "Feature",
  "properties": {
    "addr:full":"2311 S 8th St Marshalltown IA 50158",
    "addr:housenumber":"2311",
    "addr:postcode":"50158",
    "addr:street":"S 8Th St",
    "iso:country":"US",
    "sg:address":"2311 S 8th St",
    "sg:city":"Marshalltown",
    "sg:classifiers":[
        {
            "category":"Manufacturing",
            "subcategory":"Printing",
            "type":"Manufacturing & Wholesale Goods"
        }
    ],
    "sg:phone":"+1 641 752 6089",
    "sg:postcode":"50158",
    "sg:province":"IA",
    "sg:tags":[
        "commercial"
    ],
    "wof:name":"Colorful Promotions",
    "wof:placetype":"venue"
},
  "geometry": {"coordinates":[-92.92491,42.018678],"type":"Point"}
}