{
  "type": "Feature",
  "properties": {
    "addr:full":"2230 120th St Bayard IA 50029",
    "addr:housenumber":"2230",
    "addr:postcode":"50029",
    "addr:street":"120Th St",
    "iso:country":"US",
    "sg:address":"2230 120th St",
    "sg:city":"Bayard",
    "sg:phone":"+1 641 427 5624",
    "sg:postcode":"50029",
    "sg:province":"IA",
    "sg:tags":[
        "farm",
        "grain",
        "cash"
    ],
    "wof:name":"Hay Nyle",
    "wof:placetype":"venue"
},
  "geometry": {"coordinates":[-94.507784,41.834379],"type":"Point"}
}