{
  "type": "Feature",
  "properties": {
    "addr:full":"1255 S Jordan Creek Pkwy West Des Moines IA 50266",
    "addr:housenumber":"1255",
    "addr:postcode":"50266",
    "addr:street":"S Jordan Creek Pkwy",
    "iso:country":"US",
    "sg:address":"1255 S Jordan Creek Pkwy",
    "sg:city":"West Des Moines",
    "sg:classifiers":[
        {
            "category":"Banks & Credit Unions",
            "subcategory":"Bank",
            "type":"Services"
        }
    ],
    "sg:phone":"+1 515 223 1113",
    "sg:postcode":"50266",
    "sg:province":"IA",
    "sg:website":"www.freedomfinancialbank.com",
    "wof:name":"Freedom Financial Bank",
    "wof:placetype":"venue"
},
  "geometry": {"coordinates":[-93.809321,41.566041],"type":"Point"}
}