{
  "type": "Feature",
  "properties": {
    "iso:country":"US",
    "sg:address":"400 Harrison St",
    "sg:city":"Dubuque",
    "sg:classifiers":[
        {
            "category":"Building & Trades",
            "subcategory":"Construction",
            "type":"Services"
        }
    ],
    "sg:phone":"+1 563 557 7213",
    "sg:postcode":"52003",
    "sg:province":"IA",
    "sg:tags":[
        "tile",
        "dealer"
    ],
    "wof:name":"Carpet One Carpet Shack",
    "wof:placetype":"venue"
},
  "geometry": {"coordinates":[-90.66316,42.488525],"type":"Point"}
}