{
  "type": "Feature",
  "properties": {
    "iso:country":"US",
    "sg:address":"8550 Hickman Rd",
    "sg:city":"Clive",
    "sg:classifiers":[
        {
            "category":"Wholesale",
            "subcategory":"Auto Parts",
            "type":"Manufacturing & Wholesale Goods"
        }
    ],
    "sg:phone":"+1 515 251 8699",
    "sg:postcode":"50325",
    "sg:province":"IA",
    "sg:tags":[
        "body",
        "automobile",
        "shop"
    ],
    "wof:name":"Automotive Finishes",
    "wof:placetype":"venue"
},
  "geometry": {"coordinates":[-93.735409,41.614761],"type":"Point"}
}