{
  "type": "Feature",
  "properties": {
    "iso:country":"US",
    "sg:address":"51576 Green Island Rd",
    "sg:city":"Miles",
    "sg:classifiers":[
        {
            "category":"Government",
            "subcategory":"Office",
            "type":"Public Place"
        }
    ],
    "sg:phone":"+1 563 682 7392",
    "sg:postcode":"52064",
    "sg:province":"IA",
    "sg:tags":[
        "state"
    ],
    "wof:name":"Conservation Commission",
    "wof:placetype":"venue"
},
  "geometry": {"coordinates":[-90.276725,42.137578],"type":"Point"}
}