{
  "type": "Feature",
  "properties": {
    "iso:country":"US",
    "sg:address":"1214 Middle St",
    "sg:city":"Mediapolis",
    "sg:classifiers":[
        {
            "category":"Organizations",
            "subcategory":"Community Association",
            "type":"Services"
        }
    ],
    "sg:phone":"+1 319 394 3827",
    "sg:postcode":"52637",
    "sg:province":"IA",
    "wof:name":"Sasaya Inc",
    "wof:placetype":"venue"
},
  "geometry": {"coordinates":[-91.156297,41.00854],"type":"Point"}
}