{
  "type": "Feature",
  "properties": {
    "iso:country":"US",
    "sg:address":"4301 Dakota Dr",
    "sg:city":"West Des Moines",
    "sg:classifiers":[
        {
            "category":"Professional",
            "subcategory":"Computer Services",
            "type":"Services"
        }
    ],
    "sg:phone":"+1 515 222 1403",
    "sg:postcode":"50265",
    "sg:province":"IA",
    "wof:name":"Universal Solutions Inc",
    "wof:placetype":"venue"
},
  "geometry": {"coordinates":[-93.764206,41.580205],"type":"Point"}
}