{
  "type": "Feature",
  "properties": {
    "addr:full":"2034 E Ridgeway Ave Waterloo IA 50702",
    "addr:housenumber":"2034",
    "addr:postcode":"50702",
    "addr:street":"E Ridgeway Ave",
    "iso:country":"US",
    "sg:address":"2034 E Ridgeway Ave",
    "sg:city":"Waterloo",
    "sg:classifiers":[
        {
            "category":"Shopping",
            "subcategory":"Books",
            "type":"Retail Goods"
        }
    ],
    "sg:phone":"+1 319 235 2105",
    "sg:postcode":"50702",
    "sg:province":"IA",
    "sg:tags":[
        "dealer"
    ],
    "wof:name":"Family Christian Book Store",
    "wof:placetype":"venue"
},
  "geometry": {"coordinates":[-92.322605,42.467581],"type":"Point"}
}