{
  "type": "Feature",
  "properties": {
    "iso:country":"US",
    "sg:address":"207 7th Ave",
    "sg:city":"Wellman",
    "sg:classifiers":[
        {
            "category":"Autos & Motor Vehicles",
            "subcategory":"Automobile Sales",
            "type":"Retail Goods"
        }
    ],
    "sg:phone":"+1 319 646 6695",
    "sg:postcode":"52356",
    "sg:province":"IA",
    "sg:tags":[
        "car",
        "dealer"
    ],
    "wof:name":"Buckwalter Motors LTD",
    "wof:placetype":"venue"
},
  "geometry": {"coordinates":[-91.83710499999999,41.463772],"type":"Point"}
}