{
  "type": "Feature",
  "properties": {
    "iso:country":"US",
    "sg:address":"1355 260th St",
    "sg:city":"Schaller",
    "sg:classifiers":[
        {
            "category":"Farming",
            "subcategory":"Farm",
            "type":"Manufacturing & Wholesale Goods"
        }
    ],
    "sg:phone":"+1 712 275 4420",
    "sg:postcode":"51053",
    "sg:province":"IA",
    "sg:tags":[
        "crop",
        "general"
    ],
    "wof:name":"Dan Roeder",
    "wof:placetype":"venue"
},
  "geometry": {"coordinates":[-95.303517,42.414685],"type":"Point"}
}