{
  "type": "Feature",
  "properties": {
    "addr:full":"180 Harrison St Dubuque IA 52003",
    "addr:housenumber":"180",
    "addr:postcode":"52003",
    "addr:street":"Harrison St",
    "iso:country":"US",
    "sg:address":"180 Harrison St",
    "sg:city":"Dubuque",
    "sg:classifiers":[
        {
            "category":"Manufacturing",
            "subcategory":"Metals",
            "type":"Manufacturing & Wholesale Goods"
        }
    ],
    "sg:phone":"+1 563 583 1731",
    "sg:postcode":"52003",
    "sg:province":"IA",
    "sg:tags":[
        "secondary",
        "refining",
        "smelting"
    ],
    "sg:website":"www.altertrading.com",
    "wof:name":"Alter Scrap Processing",
    "wof:placetype":"venue"
},
  "geometry": {"coordinates":[-90.66304700000001,42.485357],"type":"Point"}
}