{
  "type": "Feature",
  "properties": {
    "iso:country":"US",
    "sg:address":"2201 Ave H",
    "sg:city":"Fort Madison",
    "sg:classifiers":[
        {
            "category":"Health Services",
            "subcategory":"Doctor",
            "type":"Services"
        }
    ],
    "sg:phone":"+1 319 372 3442",
    "sg:postcode":"52627",
    "sg:province":"IA",
    "sg:tags":[
        "physician",
        "surgeon"
    ],
    "wof:name":"Edeliro A Escobar MD",
    "wof:placetype":"venue"
},
  "geometry": {"coordinates":[-91.33815199999999,40.630312],"type":"Point"}
}