{
  "type": "Feature",
  "properties": {
    "iso:country":"US",
    "sg:address":"316 S Duff Ave",
    "sg:city":"Ames",
    "sg:classifiers":[
        {
            "category":"Professional",
            "subcategory":"Accounting & Tax Preparation",
            "type":"Services"
        }
    ],
    "sg:phone":"+1 515 233 4060",
    "sg:postcode":"50010",
    "sg:province":"IA",
    "sg:tags":[
        "accountant"
    ],
    "wof:name":"Cline Devries & Allen",
    "wof:placetype":"venue"
},
  "geometry": {"coordinates":[-93.61029499999999,42.019393],"type":"Point"}
}