{
  "type": "Feature",
  "properties": {
    "addr:full":"138 15th St NW Mason City IA 50401",
    "addr:housenumber":"138",
    "addr:postcode":"50401",
    "addr:street":"15Th St Nw",
    "iso:country":"US",
    "sg:address":"138 15th St NW",
    "sg:city":"Mason City",
    "sg:classifiers":[
        {
            "category":"Arena",
            "subcategory":"Sports Club",
            "type":"Entertainment"
        }
    ],
    "sg:phone":"+1 641 423 1210",
    "sg:postcode":"50401",
    "sg:province":"IA",
    "wof:name":"Lunker Club Inc",
    "wof:placetype":"venue"
},
  "geometry": {"coordinates":[-93.205049,43.166368],"type":"Point"}
}