{
  "type": "Feature",
  "properties": {
    "addr:full":"224 4th St Sioux City IA 51101",
    "addr:housenumber":"224",
    "addr:postcode":"51101",
    "addr:street":"4Th St",
    "iso:country":"US",
    "sg:address":"224 4th St",
    "sg:city":"Sioux City",
    "sg:classifiers":[
        {
            "category":"Health Services",
            "subcategory":"Nursing And Care Facility",
            "type":"Services"
        }
    ],
    "sg:phone":"+1 712 233 1298",
    "sg:postcode":"51101",
    "sg:province":"IA",
    "sg:tags":[
        "home"
    ],
    "sg:website":"www.hospiceofsiouxland.org",
    "wof:name":"Hospice Of Siouxland",
    "wof:placetype":"venue"
},
  "geometry": {"coordinates":[-96.408238,42.494041],"type":"Point"}
}