{
  "type": "Feature",
  "properties": {
    "iso:country":"US",
    "sg:address":"6724 State Hwy 38",
    "sg:city":"Olin",
    "sg:classifiers":[
        {
            "category":"Building & Trades",
            "subcategory":"Construction",
            "type":"Services"
        }
    ],
    "sg:phone":"+1 319 484 2270",
    "sg:postcode":"52320",
    "sg:province":"IA",
    "sg:tags":[
        "millwright"
    ],
    "wof:name":"Tri-States",
    "wof:placetype":"venue"
},
  "geometry": {"coordinates":[-91.13659800000001,42.027839],"type":"Point"}
}