{
  "type": "Feature",
  "properties": {
    "iso:country":"US",
    "sg:address":"5731 Urbandale Ave",
    "sg:city":"Des Moines",
    "sg:classifiers":[
        {
            "category":"Professional",
            "subcategory":"Accounting & Tax Preparation",
            "type":"Services"
        }
    ],
    "sg:phone":"+1 515 278 4247",
    "sg:postcode":"50310",
    "sg:province":"IA",
    "sg:tags":[
        "return"
    ],
    "wof:name":"Evan M Gotsdiner CPA",
    "wof:placetype":"venue"
},
  "geometry": {"coordinates":[-93.697315,41.62227],"type":"Point"}
}