{
  "type": "Feature",
  "properties": {
    "iso:country":"US",
    "sg:address":"107 N Main St",
    "sg:city":"Conrad",
    "sg:classifiers":[
        {
            "category":"Shopping",
            "subcategory":"Florist",
            "type":"Retail Goods"
        }
    ],
    "sg:phone":"+1 641 366 2113",
    "sg:postcode":"50621",
    "sg:province":"IA",
    "wof:name":"Country Cobbler",
    "wof:placetype":"venue"
},
  "geometry": {"coordinates":[-92.874664,42.225406],"type":"Point"}
}