{
  "type": "Feature",
  "properties": {
    "addr:full":"1186 Old Portland Rd Van Meter IA 50261",
    "addr:housenumber":"1186",
    "addr:postcode":"50261",
    "addr:street":"Old Portland Rd",
    "iso:country":"US",
    "sg:address":"1186 Old Portland Rd",
    "sg:city":"Van Meter",
    "sg:phone":"+1 515 996 2021",
    "sg:postcode":"50261",
    "sg:province":"IA",
    "sg:tags":[
        "beef",
        "farm",
        "corn",
        "soybean",
        "cattle",
        "feedlot"
    ],
    "wof:name":"Bill Radke",
    "wof:placetype":"venue"
},
  "geometry": {"coordinates":[-93.973901,41.495067],"type":"Point"}
}