{
  "type": "Feature",
  "properties": {
    "iso:country":"US",
    "sg:address":"788 8th Ave SE",
    "sg:city":"Cedar Rapids",
    "sg:classifiers":[
        {
            "category":"Health Services",
            "subcategory":"Health Practitioner",
            "type":"Services"
        }
    ],
    "sg:phone":"+1 319 369 0722",
    "sg:postcode":"52401",
    "sg:province":"IA",
    "sg:tags":[
        "physician",
        "assistant"
    ],
    "wof:name":"Nancy Morris",
    "wof:placetype":"venue"
},
  "geometry": {"coordinates":[-91.65679,41.976153],"type":"Point"}
}