{
  "type": "Feature",
  "properties": {
    "addr:full":"630 Patterson Dr Carlisle IA 50047",
    "addr:housenumber":"630",
    "addr:postcode":"50047",
    "addr:street":"Patterson Dr",
    "iso:country":"US",
    "sg:address":"630 Patterson Dr",
    "sg:city":"Carlisle",
    "sg:classifiers":[
        {
            "category":"Health Services",
            "subcategory":"Clinic",
            "type":"Services"
        }
    ],
    "sg:phone":"+1 515 989 9000",
    "sg:postcode":"50047",
    "sg:province":"IA",
    "sg:tags":[
        "home"
    ],
    "sg:website":"www.comfortkeepers.com",
    "wof:name":"Comfort Keepers",
    "wof:placetype":"venue"
},
  "geometry": {"coordinates":[-93.493027,41.485521],"type":"Point"}
}