{
  "type": "Feature",
  "properties": {
    "addr:full":"538 2nd St Traer IA 50675",
    "addr:housenumber":"538",
    "addr:postcode":"50675",
    "addr:street":"2Nd St",
    "iso:country":"US",
    "sg:address":"538 2nd St",
    "sg:city":"Traer",
    "sg:classifiers":[
        {
            "category":"Bars & Pubs",
            "type":"Food & Drink"
        }
    ],
    "sg:phone":"+1 319 478 9941",
    "sg:postcode":"50675",
    "sg:province":"IA",
    "wof:name":"Sunnyside Tavern",
    "wof:placetype":"venue"
},
  "geometry": {"coordinates":[-92.466964,42.193458],"type":"Point"}
}