{
  "type": "Feature",
  "properties": {
    "iso:country":"US",
    "sg:address":"901 Bank Ct",
    "sg:city":"Center Point",
    "sg:classifiers":[
        {
            "category":"Banks & Credit Unions",
            "subcategory":"Bank",
            "type":"Services"
        }
    ],
    "sg:phone":"+1 319 849 1838",
    "sg:postcode":"52213",
    "sg:province":"IA",
    "wof:name":"Center Point Bank & Trust Co",
    "wof:placetype":"venue"
},
  "geometry": {"coordinates":[-91.773596,42.179792],"type":"Point"}
}