{
  "type": "Feature",
  "properties": {
    "iso:country":"US",
    "sg:address":"900 Garfield Ave",
    "sg:city":"Tipton",
    "sg:classifiers":[
        {
            "category":"Professional",
            "subcategory":"Computer Services",
            "type":"Services"
        }
    ],
    "sg:phone":"+1 563 432 7703",
    "sg:postcode":"52772",
    "sg:province":"IA",
    "sg:tags":[
        "datum"
    ],
    "wof:name":"D M S Technical Consulting",
    "wof:placetype":"venue"
},
  "geometry": {"coordinates":[-91.249287,41.816314],"type":"Point"}
}