{
  "type": "Feature",
  "properties": {
    "iso:country":"US",
    "sg:address":"221 W 2nd St",
    "sg:city":"Washington",
    "sg:classifiers":[
        {
            "category":"Government",
            "subcategory":"Jail",
            "type":"Public Place"
        }
    ],
    "sg:phone":"+1 319 653 5902",
    "sg:postcode":"52353",
    "sg:province":"IA",
    "sg:tags":[
        "county",
        "govt",
        "institution"
    ],
    "wof:name":"Washington County Jail",
    "wof:placetype":"venue"
},
  "geometry": {"coordinates":[-91.69547,41.300464],"type":"Point"}
}