{
  "type": "Feature",
  "properties": {
    "iso:country":"US",
    "sg:address":"1172 Main St",
    "sg:city":"Dubuque",
    "sg:classifiers":[
        {
            "category":"Shopping",
            "type":"Retail Goods"
        }
    ],
    "sg:phone":"+1 563 582 1561",
    "sg:postcode":"52001",
    "sg:province":"IA",
    "sg:tags":[
        "art",
        "gallery",
        "dealer"
    ],
    "wof:name":"Brownstone Gallery & Frame Shp",
    "wof:placetype":"venue"
},
  "geometry": {"coordinates":[-90.668644,42.503538],"type":"Point"}
}