{
  "type": "Feature",
  "properties": {
    "addr:full":"2667 N Ave Adel IA 50003",
    "addr:housenumber":"2667",
    "addr:postcode":"50003",
    "addr:street":"N Ave",
    "iso:country":"US",
    "sg:address":"2667 N Ave",
    "sg:city":"Adel",
    "sg:classifiers":[
        {
            "category":"Professional",
            "type":"Services"
        }
    ],
    "sg:phone":"+1 515 993 4374",
    "sg:postcode":"50003",
    "sg:province":"IA",
    "wof:name":"Stanley Olson",
    "wof:placetype":"venue"
},
  "geometry": {"coordinates":[-94.023067,41.644363],"type":"Point"}
}