{
  "type": "Feature",
  "properties": {
    "iso:country":"US",
    "sg:address":"210 S Franklin St",
    "sg:city":"Manchester",
    "sg:classifiers":[
        {
            "category":"Restaurant",
            "type":"Food & Drink"
        }
    ],
    "sg:phone":"+1 563 927 3354",
    "sg:postcode":"52057",
    "sg:province":"IA",
    "wof:name":"Deli One",
    "wof:placetype":"venue"
},
  "geometry": {"coordinates":[-91.45780000000001,42.482738],"type":"Point"}
}