{
  "type": "Feature",
  "properties": {
    "addr:full":"280 4th Ave Keystone IA 52249",
    "addr:housenumber":"280",
    "addr:postcode":"52249",
    "addr:street":"4Th Ave",
    "iso:country":"US",
    "sg:address":"280 4th Ave",
    "sg:city":"Keystone",
    "sg:classifiers":[
        {
            "category":"Education",
            "subcategory":"School",
            "type":"Public Place"
        }
    ],
    "sg:phone":"+1 319 442 3221",
    "sg:postcode":"52249",
    "sg:province":"IA",
    "wof:name":"Keystone Elementary School",
    "wof:placetype":"venue"
},
  "geometry": {"coordinates":[-92.200669,42.000694],"type":"Point"}
}