{
  "type": "Feature",
  "properties": {
    "iso:country":"US",
    "sg:address":"2939 200th St",
    "sg:city":"Winthrop",
    "sg:phone":"+1 319 935 3477",
    "sg:postcode":"50682",
    "sg:province":"IA",
    "sg:tags":[
        "farm",
        "corn"
    ],
    "wof:name":"Troy Tempus",
    "wof:placetype":"venue"
},
  "geometry": {"coordinates":[-91.70705700000001,42.497591],"type":"Point"}
}