{
  "type": "Feature",
  "properties": {
    "addr:full":"1409 Clark St Des Moines IA 50314",
    "addr:housenumber":"1409",
    "addr:postcode":"50314",
    "addr:street":"Clark St",
    "iso:country":"US",
    "sg:address":"1409 Clark St",
    "sg:city":"Des Moines",
    "sg:classifiers":[
        {
            "category":"Professional",
            "type":"Services"
        }
    ],
    "sg:phone":"+1 515 243 3712",
    "sg:postcode":"50314",
    "sg:province":"IA",
    "sg:tags":[
        "establishment"
    ],
    "wof:name":"Minority Community Liaison",
    "wof:placetype":"venue"
},
  "geometry": {"coordinates":[-93.63895599999999,41.605956],"type":"Point"}
}