{
  "type": "Feature",
  "properties": {
    "iso:country":"US",
    "sg:address":"725 E Forest Dr",
    "sg:city":"Forest City",
    "sg:phone":"+1 641 582 4906",
    "sg:postcode":"50436",
    "sg:province":"IA",
    "sg:tags":[
        "farm",
        "corn",
        "soybean"
    ],
    "wof:name":"Bill Goetz",
    "wof:placetype":"venue"
},
  "geometry": {"coordinates":[-93.637384,43.256959],"type":"Point"}
}