{
  "type": "Feature",
  "properties": {
    "addr:full":"708 1st Ave Coralville IA 52241",
    "addr:housenumber":"708",
    "addr:postcode":"52241",
    "addr:street":"1St Ave",
    "iso:country":"US",
    "sg:address":"708 1st Ave",
    "sg:city":"Coralville",
    "sg:classifiers":[
        {
            "category":"Restaurant",
            "type":"Food & Drink"
        }
    ],
    "sg:phone":"+1 319 339 8500",
    "sg:postcode":"52241",
    "sg:province":"IA",
    "wof:name":"Cancun",
    "wof:placetype":"venue"
},
  "geometry": {"coordinates":[-91.565809,41.681572],"type":"Point"}
}