{
  "type": "Feature",
  "properties": {
    "iso:country":"US",
    "sg:address":"1005 Black Hawk Rd",
    "sg:city":"Waterloo",
    "sg:classifiers":[
        {
            "category":"Recreation",
            "type":"Entertainment"
        }
    ],
    "sg:phone":"+1 319 232 7512",
    "sg:postcode":"50701",
    "sg:province":"IA",
    "sg:tags":[
        "tennis",
        "court"
    ],
    "wof:name":"Black Hawk Tennis Club",
    "wof:placetype":"venue"
},
  "geometry": {"coordinates":[-92.371638,42.49301],"type":"Point"}
}