{
  "type": "Feature",
  "properties": {
    "iso:country":"US",
    "sg:address":"3080 Donna Reed Rd",
    "sg:city":"Manilla",
    "sg:classifiers":[
        {
            "category":"Wholesale",
            "subcategory":"Machinery & Supplies",
            "type":"Manufacturing & Wholesale Goods"
        }
    ],
    "sg:phone":"+1 712 654 3635",
    "sg:postcode":"51454",
    "sg:province":"IA",
    "sg:tags":[
        "farm",
        "equipment"
    ],
    "wof:name":"Thomson-Stracke Implement",
    "wof:placetype":"venue"
},
  "geometry": {"coordinates":[-95.305446,41.910736],"type":"Point"}
}