{
  "type": "Feature",
  "properties": {
    "iso:country":"US",
    "sg:address":"723 2nd St",
    "sg:city":"Webster City",
    "sg:classifiers":[
        {
            "category":"Bars & Pubs",
            "type":"Food & Drink"
        }
    ],
    "sg:phone":"+1 515 832 4225",
    "sg:postcode":"50595",
    "sg:province":"IA",
    "wof:name":"Wild Side Sports Tap",
    "wof:placetype":"venue"
},
  "geometry": {"coordinates":[-93.82321,42.469532],"type":"Point"}
}