{
  "type": "Feature",
  "properties": {
    "addr:full":"1809 Agency St Burlington IA 52601",
    "addr:housenumber":"1809",
    "addr:postcode":"52601",
    "addr:street":"Agency St",
    "iso:country":"US",
    "sg:address":"1809 Agency St",
    "sg:city":"Burlington",
    "sg:classifiers":[
        {
            "category":"Social Services",
            "subcategory":"Child Care",
            "type":"Services"
        }
    ],
    "sg:phone":"+1 319 754 4248",
    "sg:postcode":"52601",
    "sg:province":"IA",
    "sg:tags":[
        "kindergarten",
        "academic",
        "school"
    ],
    "wof:name":"Naoh's Ark Pre School",
    "wof:placetype":"venue"
},
  "geometry": {"coordinates":[-91.12496,40.815106],"type":"Point"}
}