{
  "type": "Feature",
  "properties": {
    "addr:full":"5656 Morningside Dr Johnston IA 50131",
    "addr:housenumber":"5656",
    "addr:postcode":"50131",
    "addr:street":"Morningside Dr",
    "iso:country":"US",
    "sg:address":"5656 Morningside Dr",
    "sg:city":"Johnston",
    "sg:classifiers":[
        {
            "category":"Home & Garden",
            "subcategory":"Home Furnishings",
            "type":"Retail Goods"
        }
    ],
    "sg:phone":"+1 515 254 0520",
    "sg:postcode":"50131",
    "sg:province":"IA",
    "wof:name":"Blinds and Decor Galore",
    "wof:placetype":"venue"
},
  "geometry": {"coordinates":[-93.695657,41.685257],"type":"Point"}
}