{
  "type": "Feature",
  "properties": {
    "addr:full":"603 Greenwood Dr Iowa City IA 52246",
    "addr:housenumber":"603",
    "addr:postcode":"52246",
    "addr:street":"Greenwood Dr",
    "iso:country":"US",
    "sg:address":"603 Greenwood Dr",
    "sg:city":"Iowa City",
    "sg:classifiers":[
        {
            "category":"Organizations",
            "subcategory":"Non-profit Organization",
            "type":"Services"
        }
    ],
    "sg:phone":"+1 319 338 0763",
    "sg:postcode":"52246",
    "sg:province":"IA",
    "wof:name":"Good Shepherd Child Care Ctr",
    "wof:placetype":"venue"
},
  "geometry": {"coordinates":[-91.54851499999999,41.65216],"type":"Point"}
}