{
  "type": "Feature",
  "properties": {
    "addr:full":"1230 Collins Road Cedar Rapids IA 52402",
    "addr:housenumber":"1230",
    "addr:postcode":"52402",
    "addr:street":"Collins Road",
    "iso:country":"US",
    "sg:address":"1230 Collins Road",
    "sg:city":"Cedar Rapids",
    "sg:classifiers":[
        {
            "category":"Travel",
            "subcategory":"Hotels & Motels",
            "type":"Entertainment"
        },
        {
            "category":"Retail",
            "subcategory":"Event Space",
            "type":"Services"
        }
    ],
    "sg:phone":"+1 319 294 9407",
    "sg:postcode":"52402",
    "sg:province":"IA",
    "sg:tags":[
        "venue"
    ],
    "sg:website":"www.holidayinnexpress.com",
    "wof:name":"Holiday Inn Express Hotel Cedar Rapids - Collins Rd",
    "wof:placetype":"venue"
},
  "geometry": {"coordinates":[-91.655098,42.029031],"type":"Point"}
}