{
  "type": "Feature",
  "properties": {
    "addr:full":"1213 N Lincoln St Knoxville IA 50138",
    "addr:housenumber":"1213",
    "addr:postcode":"50138",
    "addr:street":"N Lincoln St",
    "iso:country":"US",
    "sg:address":"1213 N Lincoln St",
    "sg:city":"Knoxville",
    "sg:classifiers":[
        {
            "category":"Professional",
            "subcategory":"Business Services",
            "type":"Services"
        }
    ],
    "sg:phone":"+1 641 842 3532",
    "sg:postcode":"50138",
    "sg:province":"IA",
    "sg:tags":[
        "interior",
        "designer"
    ],
    "wof:name":"Cathie Carter Interior Design",
    "wof:placetype":"venue"
},
  "geometry": {"coordinates":[-93.109427,41.328549],"type":"Point"}
}