{
  "type": "Feature",
  "properties": {
    "addr:full":"1023 US Hwy 169 Bode IA 50519",
    "addr:housenumber":"1023",
    "addr:postcode":"50519",
    "addr:street":"Us Hwy 169 Bode",
    "iso:country":"US",
    "sg:address":"1023 US Hwy 169",
    "sg:city":"Bode",
    "sg:classifiers":[
        {
            "category":"Organizations",
            "subcategory":"Religious Organization",
            "type":"Services"
        }
    ],
    "sg:phone":"+1 515 379 1470",
    "sg:postcode":"50519",
    "sg:province":"IA",
    "sg:tags":[
        "church"
    ],
    "wof:name":"St Joseph Catholic Church",
    "wof:placetype":"venue"
},
  "geometry": {"coordinates":[-94.22722,42.902712],"type":"Point"}
}