{
  "type": "Feature",
  "properties": {
    "addr:full":"218 S Main St Stockport IA 52651",
    "addr:housenumber":"218",
    "addr:postcode":"52651",
    "addr:street":"S Main St",
    "iso:country":"US",
    "sg:address":"218 S Main St",
    "sg:city":"Stockport",
    "sg:classifiers":[
        {
            "category":"Personal",
            "subcategory":"Beauty Salon",
            "type":"Services"
        }
    ],
    "sg:phone":"+1 319 796 2209",
    "sg:postcode":"52651",
    "sg:province":"IA",
    "wof:name":"Martha's Hair Care",
    "wof:placetype":"venue"
},
  "geometry": {"coordinates":[-91.833568,40.856556],"type":"Point"}
}