{
  "type": "Feature",
  "properties": {
    "iso:country":"US",
    "sg:address":"3031 N Ave",
    "sg:city":"Denison",
    "sg:classifiers":[
        {
            "category":"Farming",
            "subcategory":"Livestock Farm",
            "type":"Manufacturing & Wholesale Goods"
        }
    ],
    "sg:phone":"+1 712 263 6338",
    "sg:postcode":"51442",
    "sg:province":"IA",
    "sg:tags":[
        "beef",
        "feedlot",
        "cattle"
    ],
    "wof:name":"McMinimee Farms",
    "wof:placetype":"venue"
},
  "geometry": {"coordinates":[-95.2799,42.016549],"type":"Point"}
}