{
  "type": "Feature",
  "properties": {
    "iso:country":"US",
    "sg:address":"22849 State Hwy 1",
    "sg:city":"Keosauqua",
    "sg:classifiers":[
        {
            "category":"Utilities",
            "subcategory":"Cable",
            "type":"Services"
        }
    ],
    "sg:phone":"+1 319 293 6336",
    "sg:postcode":"52565",
    "sg:province":"IA",
    "sg:tags":[
        "television"
    ],
    "wof:name":"Starwest Cable TV Inc",
    "wof:placetype":"venue"
},
  "geometry": {"coordinates":[-91.948916,40.714246],"type":"Point"}
}