{
  "type": "Feature",
  "properties": {
    "addr:full":"1016 2nd Ave Sheldon IA 51201",
    "addr:housenumber":"1016",
    "addr:postcode":"51201",
    "addr:street":"2Nd Ave",
    "iso:country":"US",
    "sg:address":"1016 2nd Ave",
    "sg:city":"Sheldon",
    "sg:classifiers":[
        {
            "category":"Wholesale",
            "subcategory":"Farm Supplies",
            "type":"Manufacturing & Wholesale Goods"
        }
    ],
    "sg:phone":"+1 712 324 2548",
    "sg:postcode":"51201",
    "sg:province":"IA",
    "sg:tags":[
        "feed"
    ],
    "sg:website":"www.midwestcoop.com",
    "wof:name":"Midwest Farmers Co-Op",
    "wof:placetype":"venue"
},
  "geometry": {"coordinates":[-95.856782,43.179908],"type":"Point"}
}