{
  "type": "Feature",
  "properties": {
    "addr:full":"1421 Ingersoll Ave Des Moines IA 50312",
    "addr:housenumber":"1421",
    "addr:postcode":"50312",
    "addr:street":"Ingersoll Ave",
    "iso:country":"US",
    "sg:address":"1421 Ingersoll Ave",
    "sg:city":"Des Moines",
    "sg:classifiers":[
        {
            "category":"Food & Beverages",
            "subcategory":"Groceries & Convenience Stores",
            "type":"Retail Goods"
        }
    ],
    "sg:phone":"+1 515 243 2357",
    "sg:postcode":"50312",
    "sg:province":"IA",
    "wof:name":"Quik Trip",
    "wof:placetype":"venue"
},
  "geometry": {"coordinates":[-93.636985,41.586421],"type":"Point"}
}