{
  "type": "Feature",
  "properties": {
    "iso:country":"US",
    "sg:address":"19481 140th St",
    "sg:city":"Carroll",
    "sg:classifiers":[
        {
            "category":"Organizations",
            "subcategory":"Religious Organization",
            "type":"Services"
        }
    ],
    "sg:phone":"+1 712 792 3934",
    "sg:postcode":"51401",
    "sg:province":"IA",
    "sg:tags":[
        "church"
    ],
    "wof:name":"Our Lady Of Mount Carmel",
    "wof:placetype":"venue"
},
  "geometry": {"coordinates":[-94.90788000000001,42.152484],"type":"Point"}
}