{
  "type": "Feature",
  "properties": {
    "iso:country":"US",
    "sg:address":"801 S 3rd St",
    "sg:city":"Clinton",
    "sg:classifiers":[
        {
            "category":"Manufacturing",
            "subcategory":"Printing",
            "type":"Manufacturing & Wholesale Goods"
        }
    ],
    "sg:phone":"+1 563 243 1304",
    "sg:postcode":"52732",
    "sg:province":"IA",
    "sg:tags":[
        "screen"
    ],
    "sg:website":"www.adcraftprintwear.com",
    "wof:name":"Adcraft Printwear Co",
    "wof:placetype":"venue"
},
  "geometry": {"coordinates":[-90.19072199999999,41.83781],"type":"Point"}
}