{
  "type": "Feature",
  "properties": {
    "addr:full":"212 Main St Gravity IA 50848",
    "addr:housenumber":"212",
    "addr:postcode":"50848",
    "addr:street":"Main St",
    "iso:country":"US",
    "sg:address":"212 Main St",
    "sg:city":"Gravity",
    "sg:classifiers":[
        {
            "category":"Government",
            "subcategory":"Post Office",
            "type":"Public Place"
        }
    ],
    "sg:phone":"+1 712 537 2780",
    "sg:postcode":"50848",
    "sg:province":"IA",
    "wof:name":"US Post Office",
    "wof:placetype":"venue"
},
  "geometry": {"coordinates":[-94.744889,40.75605],"type":"Point"}
}