{
  "type": "Feature",
  "properties": {
    "iso:country":"US",
    "sg:address":"1861 Liberty Ave",
    "sg:city":"Waterloo",
    "sg:classifiers":[
        {
            "category":"Freight",
            "type":"Transportation"
        }
    ],
    "sg:phone":"+1 319 233 0538",
    "sg:postcode":"50702",
    "sg:province":"IA",
    "sg:tags":[
        "operator",
        "trucking"
    ],
    "wof:name":"Tim Zarifis",
    "wof:placetype":"venue"
},
  "geometry": {"coordinates":[-92.326633,42.478506],"type":"Point"}
}