{
  "type": "Feature",
  "properties": {
    "addr:full":"1206 Davis Ave Corning IA 50841",
    "addr:housenumber":"1206",
    "addr:postcode":"50841",
    "addr:street":"Davis Ave",
    "iso:country":"US",
    "sg:address":"1206 Davis Ave",
    "sg:city":"Corning",
    "sg:classifiers":[
        {
            "category":"Professional",
            "type":"Services"
        }
    ],
    "sg:phone":"+1 641 322 4515",
    "sg:postcode":"50841",
    "sg:province":"IA",
    "wof:name":"Southwest Iowa Mill Wright Ser",
    "wof:placetype":"venue"
},
  "geometry": {"coordinates":[-94.734229,40.994502],"type":"Point"}
}