{
  "type": "Feature",
  "properties": {
    "addr:full":"6425 W Kimberly Rd Davenport IA 52806",
    "addr:housenumber":"6425",
    "addr:postcode":"52806",
    "addr:street":"W Kimberly Rd",
    "iso:country":"US",
    "sg:address":"6425 W Kimberly Rd",
    "sg:city":"Davenport",
    "sg:classifiers":[
        {
            "category":"Retail",
            "subcategory":"Auto Repair",
            "type":"Services"
        }
    ],
    "sg:phone":"+1 563 445 0667",
    "sg:postcode":"52806",
    "sg:province":"IA",
    "sg:tags":[
        "automobile",
        "co",
        "drive",
        "transporter"
    ],
    "wof:name":"Kimberly Auto Mart",
    "wof:placetype":"venue"
},
  "geometry": {"coordinates":[-90.675588,41.591332],"type":"Point"}
}