{
  "type": "Feature",
  "properties": {
    "iso:country":"US",
    "sg:address":"423 6th St",
    "sg:city":"Sioux City",
    "sg:classifiers":[
        {
            "category":"Professional",
            "subcategory":"Lawyer & Legal Services",
            "type":"Services"
        }
    ],
    "sg:phone":"+1 712 277 1261",
    "sg:postcode":"51101",
    "sg:province":"IA",
    "sg:tags":[
        "attorney"
    ],
    "wof:name":"Corbett Anderson Corbett Law",
    "wof:placetype":"venue"
},
  "geometry": {"coordinates":[-96.40593200000001,42.496409],"type":"Point"}
}