{
  "type": "Feature",
  "properties": {
    "addr:full":"801 W Wall St Centerville IA 52544",
    "addr:housenumber":"801",
    "addr:postcode":"52544",
    "addr:street":"W Wall St",
    "iso:country":"US",
    "sg:address":"801 W Wall St",
    "sg:city":"Centerville",
    "sg:classifiers":[
        {
            "category":"Professional",
            "subcategory":"Business Services",
            "type":"Services"
        }
    ],
    "sg:phone":"+1 641 856 6503",
    "sg:postcode":"52544",
    "sg:province":"IA",
    "wof:name":"Element of Design",
    "wof:placetype":"venue"
},
  "geometry": {"coordinates":[-92.880673,40.727882],"type":"Point"}
}