{
  "type": "Feature",
  "properties": {
    "iso:country":"US",
    "sg:address":"26920 Leuchs Rd",
    "sg:city":"Farley",
    "sg:classifiers":[
        {
            "category":"Real Estate",
            "subcategory":"Real Estate Operator",
            "type":"Services"
        }
    ],
    "sg:phone":"+1 563 744 3917",
    "sg:postcode":"52046",
    "sg:province":"IA",
    "sg:tags":[
        "property",
        "lessor"
    ],
    "wof:name":"Gerald Rowles",
    "wof:placetype":"venue"
},
  "geometry": {"coordinates":[-91.01618999999999,42.426065],"type":"Point"}
}