{
  "type": "Feature",
  "properties": {
    "addr:full":"2860 280th St Dickens IA 51333",
    "addr:housenumber":"2860",
    "addr:postcode":"51333",
    "addr:street":"280Th St",
    "iso:country":"US",
    "sg:address":"2860 280th St",
    "sg:city":"Dickens",
    "sg:phone":"+1 712 853 6340",
    "sg:postcode":"51333",
    "sg:province":"IA",
    "sg:tags":[
        "farm",
        "corn",
        "soybean"
    ],
    "wof:name":"Darrell Beving",
    "wof:placetype":"venue"
},
  "geometry": {"coordinates":[-95.02225,43.243467],"type":"Point"}
}