{
  "type": "Feature",
  "properties": {
    "iso:country":"US",
    "sg:address":"2111 US Hwy 169",
    "sg:city":"Algona",
    "sg:classifiers":[
        {
            "category":"Education",
            "subcategory":"School",
            "type":"Public Place"
        }
    ],
    "sg:phone":"+1 515 295 6098",
    "sg:postcode":"50511",
    "sg:province":"IA",
    "wof:name":"Algona Alternative High School",
    "wof:placetype":"venue"
},
  "geometry": {"coordinates":[-94.23632000000001,43.084452],"type":"Point"}
}