{
  "type": "Feature",
  "properties": {
    "addr:full":"273 N 3rd St Laurens IA 50554",
    "addr:housenumber":"273",
    "addr:postcode":"50554",
    "addr:street":"N 3Rd St",
    "iso:country":"US",
    "sg:address":"273 N 3rd St",
    "sg:city":"Laurens",
    "sg:classifiers":[
        {
            "category":"Education",
            "subcategory":"Library",
            "type":"Public Place"
        }
    ],
    "sg:phone":"+1 712 841 4612",
    "sg:postcode":"50554",
    "sg:province":"IA",
    "wof:name":"Laurens Public Library",
    "wof:placetype":"venue"
},
  "geometry": {"coordinates":[-94.85142500000001,42.849318],"type":"Point"}
}