{
  "type": "Feature",
  "properties": {
    "iso:country":"US",
    "sg:address":"1208 13th St N",
    "sg:city":"Humboldt",
    "sg:classifiers":[
        {
            "category":"Professional",
            "type":"Services"
        },
        {
            "category":"Banks & Credit Unions",
            "subcategory":"Bank",
            "type":"Services"
        }
    ],
    "sg:phone":"+1 515 332 4096",
    "sg:postcode":"50548",
    "sg:province":"IA",
    "sg:tags":[
        "state",
        "establishment"
    ],
    "wof:name":"Power Co-Op Employees Credit",
    "wof:placetype":"venue"
},
  "geometry": {"coordinates":[-94.227225,42.735136],"type":"Point"}
}