{
  "type": "Feature",
  "properties": {
    "iso:country":"US",
    "sg:address":"721 S Main St",
    "sg:city":"Maquoketa",
    "sg:classifiers":[
        {
            "category":"Health Services",
            "subcategory":"Chiropractor",
            "type":"Services"
        }
    ],
    "sg:phone":"+1 563 652 6446",
    "sg:postcode":"52060",
    "sg:province":"IA",
    "wof:name":"Aise Chiropractic Ctr",
    "wof:placetype":"venue"
},
  "geometry": {"coordinates":[-90.665381,42.05999],"type":"Point"}
}