{
  "type": "Feature",
  "properties": {
    "iso:country":"US",
    "sg:address":"16609 State Hwy 13",
    "sg:city":"Farmersburg",
    "sg:classifiers":[
        {
            "category":"Farming",
            "subcategory":"Livestock Farm",
            "type":"Manufacturing & Wholesale Goods"
        }
    ],
    "sg:phone":"+1 563 536 2314",
    "sg:postcode":"52047",
    "sg:province":"IA",
    "sg:tags":[
        "beef",
        "feedlot",
        "cattle"
    ],
    "wof:name":"Home Farm Organics",
    "wof:placetype":"venue"
},
  "geometry": {"coordinates":[-91.309563,42.988936],"type":"Point"}
}