{
  "type": "Feature",
  "properties": {
    "iso:country":"US",
    "sg:address":"2775 86th St",
    "sg:city":"Urbandale",
    "sg:classifiers":[
        {
            "category":"Real Estate",
            "subcategory":"Real Estate Agent",
            "type":"Services"
        }
    ],
    "sg:phone":"+1 515 224 8726",
    "sg:postcode":"50322",
    "sg:province":"IA",
    "wof:name":"Jonesie Viggers",
    "wof:placetype":"venue"
},
  "geometry": {"coordinates":[-93.736437,41.61933],"type":"Point"}
}