{
  "type": "Feature",
  "properties": {
    "addr:full":"2918 Zinnia Rd Elk Horn IA 51531",
    "addr:housenumber":"2918",
    "addr:postcode":"51531",
    "addr:street":"Zinnia Rd",
    "iso:country":"US",
    "sg:address":"2918 Zinnia Rd",
    "sg:city":"Elk Horn",
    "sg:classifiers":[
        {
            "category":"Wholesale",
            "subcategory":"Farm Supplies",
            "type":"Manufacturing & Wholesale Goods"
        },
        {
            "category":"Shopping",
            "type":"Retail Goods"
        }
    ],
    "sg:phone":"+1 712 764 5581",
    "sg:postcode":"51531",
    "sg:province":"IA",
    "sg:tags":[
        "bulb",
        "seed",
        "merchandise"
    ],
    "wof:name":"Steen Feed Inc",
    "wof:placetype":"venue"
},
  "geometry": {"coordinates":[-95.040818,41.588936],"type":"Point"}
}