{
  "type": "Feature",
  "properties": {
    "iso:country":"US",
    "sg:address":"117 S Main Ave",
    "sg:city":"Alburnett",
    "sg:classifiers":[
        {
            "category":"Banks & Credit Unions",
            "subcategory":"Bank",
            "type":"Services"
        }
    ],
    "sg:phone":"+1 319 842 2211",
    "sg:postcode":"52202",
    "sg:province":"IA",
    "wof:name":"Farmers State Bank",
    "wof:placetype":"venue"
},
  "geometry": {"coordinates":[-91.618482,42.148096],"type":"Point"}
}