{
  "type": "Feature",
  "properties": {
    "iso:country":"US",
    "sg:address":"1327 Broadway",
    "sg:city":"Denison",
    "sg:classifiers":[
        {
            "category":"Professional",
            "subcategory":"Business Services",
            "type":"Services"
        }
    ],
    "sg:phone":"+1 712 263 8950",
    "sg:postcode":"51442",
    "sg:province":"IA",
    "sg:tags":[
        "interior",
        "consultant",
        "design",
        "decorator"
    ],
    "wof:name":"Amiee 'n Me Gift & Flower Shop",
    "wof:placetype":"venue"
},
  "geometry": {"coordinates":[-95.355007,42.016664],"type":"Point"}
}