{
  "type": "Feature",
  "properties": {
    "iso:country":"US",
    "sg:address":"505 East St",
    "sg:city":"Lynnville",
    "sg:classifiers":[
        {
            "category":"Organizations",
            "subcategory":"Religious Organization",
            "type":"Services"
        }
    ],
    "sg:phone":"+1 641 527 3374",
    "sg:postcode":"50153",
    "sg:province":"IA",
    "sg:tags":[
        "church"
    ],
    "wof:name":"Lynnville Friends Church",
    "wof:placetype":"venue"
},
  "geometry": {"coordinates":[-92.782669,41.577464],"type":"Point"}
}