{
  "type": "Feature",
  "properties": {
    "iso:country":"US",
    "sg:address":"1206 S Main St",
    "sg:city":"Charles City",
    "sg:classifiers":[
        {
            "category":"Government",
            "subcategory":"Office",
            "type":"Public Place"
        }
    ],
    "sg:phone":"+1 641 228 5713",
    "sg:postcode":"50616",
    "sg:province":"IA",
    "sg:tags":[
        "county",
        "resource"
    ],
    "wof:name":"Floyd County Human Svc",
    "wof:placetype":"venue"
},
  "geometry": {"coordinates":[-92.682429,43.055557],"type":"Point"}
}