{
  "type": "Feature",
  "properties": {
    "addr:full":"108 E Jefferson St Osceola IA 50213",
    "addr:housenumber":"108",
    "addr:postcode":"50213",
    "addr:street":"E Jefferson St",
    "iso:country":"US",
    "sg:address":"108 E Jefferson St",
    "sg:city":"Osceola",
    "sg:classifiers":[
        {
            "category":"Bars & Pubs",
            "type":"Food & Drink"
        }
    ],
    "sg:phone":"+1 641 342 2069",
    "sg:postcode":"50213",
    "sg:province":"IA",
    "wof:name":"Plain Jane's Lounge",
    "wof:placetype":"venue"
},
  "geometry": {"coordinates":[-93.76483399999999,41.033404],"type":"Point"}
}