{
  "type": "Feature",
  "properties": {
    "iso:country":"US",
    "sg:address":"1621 Maine St",
    "sg:city":"Des Moines",
    "sg:classifiers":[
        {
            "category":"Building & Trades",
            "subcategory":"Construction",
            "type":"Services"
        }
    ],
    "sg:phone":"+1 515 243 5424",
    "sg:postcode":"50314",
    "sg:province":"IA",
    "sg:tags":[
        "resurfacing",
        "laying",
        "refinishing",
        "floor"
    ],
    "wof:name":"Pro Floor",
    "wof:placetype":"venue"
},
  "geometry": {"coordinates":[-93.618431,41.608234],"type":"Point"}
}