{
  "type": "Feature",
  "properties": {
    "addr:full":"1607 E Grand Ave Des Moines IA 50316",
    "addr:housenumber":"1607",
    "addr:postcode":"50316",
    "addr:street":"E Grand Ave",
    "iso:country":"US",
    "sg:address":"1607 E Grand Ave",
    "sg:city":"Des Moines",
    "sg:classifiers":[
        {
            "category":"Shopping",
            "subcategory":"Clothing, Apparel, & Fashions",
            "type":"Retail Goods"
        }
    ],
    "sg:phone":"+1 515 266 6767",
    "sg:postcode":"50316",
    "sg:province":"IA",
    "sg:tags":[
        "western"
    ],
    "wof:name":"Steves Jewelry",
    "wof:placetype":"venue"
},
  "geometry": {"coordinates":[-93.590034,41.594912],"type":"Point"}
}