{
  "type": "Feature",
  "properties": {
    "iso:country":"US",
    "sg:address":"3429 Spring St",
    "sg:city":"Davenport",
    "sg:classifiers":[
        {
            "category":"Health Services",
            "subcategory":"Doctor",
            "type":"Services"
        }
    ],
    "sg:phone":"+1 563 355 3600",
    "sg:postcode":"52807",
    "sg:province":"IA",
    "sg:tags":[
        "dentist"
    ],
    "wof:name":"Williams & Iglehart",
    "wof:placetype":"venue"
},
  "geometry": {"coordinates":[-90.547657,41.554838],"type":"Point"}
}