{
  "type": "Feature",
  "properties": {
    "addr:full":"630 Pennsylvania Ave Story City IA 50248",
    "addr:housenumber":"630",
    "addr:postcode":"50248",
    "addr:street":"Pennsylvania Ave",
    "iso:country":"US",
    "sg:address":"630 Pennsylvania Ave",
    "sg:city":"Story City",
    "sg:classifiers":[
        {
            "category":"Autos & Motor Vehicles",
            "subcategory":"Auto Supplies",
            "type":"Retail Goods"
        }
    ],
    "sg:phone":"+1 515 733 4388",
    "sg:postcode":"50248",
    "sg:province":"IA",
    "sg:tags":[
        "automobile",
        "parts"
    ],
    "wof:name":"Wheeler Auto Supply",
    "wof:placetype":"venue"
},
  "geometry": {"coordinates":[-93.59589,42.187258],"type":"Point"}
}