{
  "type": "Feature",
  "properties": {
    "iso:country":"US",
    "sg:address":"2904 Hwy 38",
    "sg:city":"Hopkinton",
    "sg:classifiers":[
        {
            "category":"Professional",
            "subcategory":"Business Services",
            "type":"Services"
        }
    ],
    "sg:phone":"+1 563 926 2827",
    "sg:postcode":"52237",
    "sg:province":"IA",
    "wof:name":"Fund Raisers 4 You Inc",
    "wof:placetype":"venue"
},
  "geometry": {"coordinates":[-91.228995,42.332504],"type":"Point"}
}