{
  "type": "Feature",
  "properties": {
    "iso:country":"US",
    "sg:address":"2714 Beaver Ave",
    "sg:city":"Des Moines",
    "sg:classifiers":[
        {
            "category":"Shopping",
            "subcategory":"Musical Instruments",
            "type":"Retail Goods"
        }
    ],
    "sg:phone":"+1 515 277 0145",
    "sg:postcode":"50310",
    "sg:province":"IA",
    "wof:name":"Uptempo Music",
    "wof:placetype":"venue"
},
  "geometry": {"coordinates":[-93.67316599999999,41.620031],"type":"Point"}
}