{
  "type": "Feature",
  "properties": {
    "iso:country":"US",
    "sg:address":"604 Central Ave W",
    "sg:city":"Hampton",
    "sg:classifiers":[
        {
            "category":"Retail",
            "subcategory":"Car Wash",
            "type":"Services"
        }
    ],
    "sg:phone":"+1 641 456 2882",
    "sg:postcode":"50441",
    "sg:province":"IA",
    "sg:tags":[
        "polishing",
        "washing"
    ],
    "wof:name":"Pralle's Wash City",
    "wof:placetype":"venue"
},
  "geometry": {"coordinates":[-93.214782,42.741689],"type":"Point"}
}