{
  "type": "Feature",
  "properties": {
    "iso:country":"US",
    "sg:address":"15658 Kittyhawk Ave",
    "sg:city":"Carroll",
    "sg:phone":"+1 712 792 5917",
    "sg:postcode":"51401",
    "sg:province":"IA",
    "sg:tags":[
        "farm",
        "corn",
        "grain",
        "cash",
        "soybean"
    ],
    "wof:name":"Pat Wiederin",
    "wof:placetype":"venue"
},
  "geometry": {"coordinates":[-94.89781000000001,42.12846],"type":"Point"}
}