{
  "type": "Feature",
  "properties": {
    "iso:country":"US",
    "sg:address":"211 E Boston Ave",
    "sg:city":"Indianola",
    "sg:classifiers":[
        {
            "category":"Banks & Credit Unions",
            "subcategory":"Bank",
            "type":"Services"
        }
    ],
    "sg:phone":"+1 515 961 7411",
    "sg:postcode":"50125",
    "sg:province":"IA",
    "sg:website":"www.comfedbank.com",
    "wof:name":"Commercial Federal",
    "wof:placetype":"venue"
},
  "geometry": {"coordinates":[-93.55842199999999,41.362256],"type":"Point"}
}