{
  "type": "Feature",
  "properties": {
    "iso:country":"US",
    "sg:address":"1214 E 8th St N",
    "sg:city":"Newton",
    "sg:classifiers":[
        {
            "category":"Building & Trades",
            "subcategory":"Landscaping Services",
            "type":"Services"
        }
    ],
    "sg:phone":"+1 641 787 9663",
    "sg:postcode":"50208",
    "sg:province":"IA",
    "sg:tags":[
        "landscape",
        "contractor"
    ],
    "wof:name":"Realm",
    "wof:placetype":"venue"
},
  "geometry": {"coordinates":[-93.044061,41.711425],"type":"Point"}
}