{
  "type": "Feature",
  "properties": {
    "iso:country":"US",
    "sg:address":"720 S Monroe Ave",
    "sg:city":"Mason City",
    "sg:classifiers":[
        {
            "category":"Wholesale",
            "subcategory":"Machinery & Supplies",
            "type":"Manufacturing & Wholesale Goods"
        }
    ],
    "sg:phone":"+1 641 424 4775",
    "sg:postcode":"50401",
    "sg:province":"IA",
    "sg:tags":[
        "equipment",
        "welding"
    ],
    "sg:website":"www.airgas.com",
    "wof:name":"Airgas",
    "wof:placetype":"venue"
},
  "geometry": {"coordinates":[-93.20909399999999,43.144406],"type":"Point"}
}