{
  "type": "Feature",
  "properties": {
    "iso:country":"US",
    "sg:address":"910 E Maple Leaf Dr",
    "sg:city":"Mt Pleasant",
    "sg:classifiers":[
        {
            "category":"Organizations",
            "subcategory":"Religious Organization",
            "type":"Services"
        }
    ],
    "sg:phone":"+1 319 385 2651",
    "sg:postcode":"52641",
    "sg:province":"IA",
    "sg:tags":[
        "church"
    ],
    "wof:name":"Faith Lutheran Pastor's Study",
    "wof:placetype":"venue"
},
  "geometry": {"coordinates":[-91.68113700000001,40.982511],"type":"Point"}
}