{
  "type": "Feature",
  "properties": {
    "addr:full":"823 Wheeler St Ames IA 50010",
    "addr:housenumber":"823",
    "addr:postcode":"50010",
    "addr:street":"Wheeler St",
    "iso:country":"US",
    "sg:address":"823 Wheeler St",
    "sg:city":"Ames",
    "sg:classifiers":[
        {
            "category":"Personal",
            "subcategory":"Beauty Salon",
            "type":"Services"
        }
    ],
    "sg:phone":"+1 515 663 9767",
    "sg:postcode":"50010",
    "sg:province":"IA",
    "sg:tags":[
        "manicuring"
    ],
    "wof:name":"Nikki & Nails",
    "wof:placetype":"venue"
},
  "geometry": {"coordinates":[-93.62272,42.054044],"type":"Point"}
}