{
  "type": "Feature",
  "properties": {
    "iso:country":"US",
    "sg:address":"1207 S Main St",
    "sg:city":"Fairfield",
    "sg:classifiers":[
        {
            "category":"Personal",
            "type":"Services"
        }
    ],
    "sg:phone":"+1 641 472 7936",
    "sg:postcode":"52556",
    "sg:province":"IA",
    "wof:name":"Cynthia Cole Intuitive",
    "wof:placetype":"venue"
},
  "geometry": {"coordinates":[-91.96314099999999,40.996096],"type":"Point"}
}