{
  "type": "Feature",
  "properties": {
    "addr:full":"107 E State St Mason City IA 50401",
    "addr:housenumber":"107",
    "addr:postcode":"50401",
    "addr:street":"E State St",
    "iso:country":"US",
    "sg:address":"107 E State St",
    "sg:city":"Mason City",
    "sg:classifiers":[
        {
            "category":"Shopping",
            "subcategory":"Jewelry",
            "type":"Retail Goods"
        }
    ],
    "sg:phone":"+1 641 423 3566",
    "sg:postcode":"50401",
    "sg:province":"IA",
    "sg:tags":[
        "diamond"
    ],
    "sg:website":"www.rossidiamonds.com",
    "wof:name":"Ross Caniglia Diamonds",
    "wof:placetype":"venue"
},
  "geometry": {"coordinates":[-93.199354,43.151736],"type":"Point"}
}