{
  "type": "Feature",
  "properties": {
    "addr:full":"311 2nd St Coralville IA 52241",
    "addr:housenumber":"311",
    "addr:postcode":"52241",
    "addr:street":"2Nd St",
    "iso:country":"US",
    "sg:address":"311 2nd St",
    "sg:city":"Coralville",
    "sg:classifiers":[
        {
            "category":"Retail",
            "subcategory":"Veterinary Services",
            "type":"Services"
        }
    ],
    "sg:phone":"+1 319 341 0386",
    "sg:postcode":"52241",
    "sg:province":"IA",
    "sg:tags":[
        "veterinarian"
    ],
    "wof:name":"Tender Care Animal Hospital",
    "wof:placetype":"venue"
},
  "geometry": {"coordinates":[-91.568026,41.6698],"type":"Point"}
}