{
  "type": "Feature",
  "properties": {
    "iso:country":"US",
    "sg:address":"200 Main St",
    "sg:city":"Akron",
    "sg:classifiers":[
        {
            "category":"Retail",
            "subcategory":"Funeral Services",
            "type":"Services"
        }
    ],
    "sg:phone":"+1 712 568 2721",
    "sg:postcode":"51001",
    "sg:province":"IA",
    "sg:tags":[
        "director"
    ],
    "wof:name":"Schroeder Funeral Home",
    "wof:placetype":"venue"
},
  "geometry": {"coordinates":[-96.559601,42.82672],"type":"Point"}
}