{
  "type": "Feature",
  "properties": {
    "iso:country":"US",
    "sg:address":"4302 University Ave",
    "sg:city":"Cedar Falls",
    "sg:classifiers":[
        {
            "category":"Shopping",
            "subcategory":"Bicycles & Sporting Goods",
            "type":"Retail Goods"
        }
    ],
    "sg:phone":"+1 319 277 0734",
    "sg:postcode":"50613",
    "sg:province":"IA",
    "sg:website":"www.europacycle.com",
    "wof:name":"Europa Cycle & Ski",
    "wof:placetype":"venue"
},
  "geometry": {"coordinates":[-92.410205,42.506526],"type":"Point"}
}