{
  "type": "Feature",
  "properties": {
    "iso:country":"US",
    "sg:address":"22 1st Ave NW",
    "sg:city":"Le Mars",
    "sg:classifiers":[
        {
            "category":"Utilities",
            "subcategory":"Mobile Phone",
            "type":"Services"
        }
    ],
    "sg:phone":"+1 712 546 6110",
    "sg:postcode":"51031",
    "sg:province":"IA",
    "sg:tags":[
        "telephone",
        "cellular"
    ],
    "wof:name":"U S Cellular",
    "wof:placetype":"venue"
},
  "geometry": {"coordinates":[-96.167737,42.794025],"type":"Point"}
}