{
  "type": "Feature",
  "properties": {
    "addr:full":"2804 Sherry Ln Urbandale IA 50322",
    "addr:housenumber":"2804",
    "addr:postcode":"50322",
    "addr:street":"Sherry Ln",
    "iso:country":"US",
    "sg:address":"2804 Sherry Ln",
    "sg:city":"Urbandale",
    "sg:classifiers":[
        {
            "category":"Professional",
            "subcategory":"Business Services",
            "type":"Services"
        }
    ],
    "sg:phone":"+1 515 727 5272",
    "sg:postcode":"50322",
    "sg:province":"IA",
    "wof:name":"Heer Enterprises LLC",
    "wof:placetype":"venue"
},
  "geometry": {"coordinates":[-93.748892,41.621088],"type":"Point"}
}