{
  "type": "Feature",
  "properties": {
    "iso:country":"US",
    "sg:address":"108 N Main St",
    "sg:city":"Osceola",
    "sg:classifiers":[
        {
            "category":"Professional",
            "subcategory":"Business Services",
            "type":"Services"
        }
    ],
    "sg:phone":"+1 641 342 2171",
    "sg:postcode":"50213",
    "sg:province":"IA",
    "sg:tags":[
        "embroidery"
    ],
    "wof:name":"P J's Ooo-Lala",
    "wof:placetype":"venue"
},
  "geometry": {"coordinates":[-93.76574599999999,41.035021],"type":"Point"}
}