{
  "type": "Feature",
  "properties": {
    "iso:country":"US",
    "sg:address":"2920 E 53rd St",
    "sg:city":"Davenport",
    "sg:classifiers":[
        {
            "category":"Personal",
            "subcategory":"Tanning Parlor",
            "type":"Services"
        }
    ],
    "sg:phone":"+1 563 359 8909",
    "sg:postcode":"52807",
    "sg:province":"IA",
    "sg:tags":[
        "salon"
    ],
    "wof:name":"Rio Tan Inc",
    "wof:placetype":"venue"
},
  "geometry": {"coordinates":[-90.53203000000001,41.574939],"type":"Point"}
}