{
  "type": "Feature",
  "properties": {
    "iso:country":"US",
    "sg:address":"2605 Floyd Blvd",
    "sg:city":"Sioux City",
    "sg:classifiers":[
        {
            "category":"Wholesale",
            "subcategory":"Electrical",
            "type":"Manufacturing & Wholesale Goods"
        }
    ],
    "sg:phone":"+1 712 255 1675",
    "sg:postcode":"51104",
    "sg:province":"IA",
    "sg:tags":[
        "alarm",
        "burglar",
        "system"
    ],
    "wof:name":"Traum Security Systems",
    "wof:placetype":"venue"
},
  "geometry": {"coordinates":[-96.383779,42.517064],"type":"Point"}
}