{
  "type": "Feature",
  "properties": {
    "addr:full":"804 Olive St Cedar Falls IA 50613",
    "addr:housenumber":"804",
    "addr:postcode":"50613",
    "addr:street":"Olive St",
    "iso:country":"US",
    "sg:address":"804 Olive St",
    "sg:city":"Cedar Falls",
    "sg:classifiers":[
        {
            "category":"Retail",
            "subcategory":"Animal Services",
            "type":"Services"
        }
    ],
    "sg:phone":"+1 319 268 1220",
    "sg:postcode":"50613",
    "sg:province":"IA",
    "sg:tags":[
        "pet",
        "boarding",
        "sitting"
    ],
    "wof:name":"J & B Dog Grooming & Boarding",
    "wof:placetype":"venue"
},
  "geometry": {"coordinates":[-92.45457500000001,42.530539],"type":"Point"}
}