{
  "type": "Feature",
  "properties": {
    "iso:country":"US",
    "sg:address":"411 Luther St",
    "sg:city":"Luther",
    "sg:classifiers":[
        {
            "category":"Freight",
            "type":"Transportation"
        }
    ],
    "sg:phone":"+1 515 795 2386",
    "sg:postcode":"50152",
    "sg:province":"IA",
    "sg:tags":[
        "grain",
        "elevator"
    ],
    "wof:name":"Heartland Co-Op",
    "wof:placetype":"venue"
},
  "geometry": {"coordinates":[-93.82189099999999,41.96741],"type":"Point"}
}