{
  "type": "Feature",
  "properties": {
    "iso:country":"US",
    "sg:address":"410 Hanna Blvd",
    "sg:city":"Waterloo",
    "sg:classifiers":[
        {
            "category":"Professional",
            "subcategory":"Business Services",
            "type":"Services"
        }
    ],
    "sg:phone":"+1 319 235 8918",
    "sg:postcode":"50701",
    "sg:province":"IA",
    "wof:name":"Phillips Enterprises",
    "wof:placetype":"venue"
},
  "geometry": {"coordinates":[-92.383537,42.505828],"type":"Point"}
}