{
  "type": "Feature",
  "properties": {
    "addr:full":"160 W Main St Wyoming IA 52362",
    "addr:housenumber":"160",
    "addr:postcode":"52362",
    "addr:street":"W Main St",
    "iso:country":"US",
    "sg:address":"160 W Main St",
    "sg:city":"Wyoming",
    "sg:classifiers":[
        {
            "category":"Food & Beverages",
            "subcategory":"Groceries & Convenience Stores",
            "type":"Retail Goods"
        }
    ],
    "sg:phone":"+1 563 488 2220",
    "sg:postcode":"52362",
    "sg:province":"IA",
    "sg:tags":[
        "grocer"
    ],
    "wof:name":"Holly's Town Super Market",
    "wof:placetype":"venue"
},
  "geometry": {"coordinates":[-91.00716,42.058957],"type":"Point"}
}