{
  "type": "Feature",
  "properties": {
    "iso:country":"US",
    "sg:address":"501 S White St",
    "sg:city":"Mt Pleasant",
    "sg:classifiers":[
        {
            "category":"Health Services",
            "subcategory":"Doctor",
            "type":"Services"
        }
    ],
    "sg:phone":"+1 319 385 6775",
    "sg:postcode":"52641",
    "sg:province":"IA",
    "sg:tags":[
        "physician",
        "surgeon"
    ],
    "wof:name":"Bouchey Eye Surgery",
    "wof:placetype":"venue"
},
  "geometry": {"coordinates":[-91.558058,40.962719],"type":"Point"}
}