{
  "type": "Feature",
  "properties": {
    "iso:country":"US",
    "sg:address":"4820 SW 9th St",
    "sg:city":"Des Moines",
    "sg:classifiers":[
        {
            "category":"Retail",
            "subcategory":"Car Wash",
            "type":"Services"
        }
    ],
    "sg:phone":"+1 515 287 1003",
    "sg:postcode":"50315",
    "sg:province":"IA",
    "sg:tags":[
        "polishing",
        "washing"
    ],
    "wof:name":"Ash",
    "wof:placetype":"venue"
},
  "geometry": {"coordinates":[-93.625826,41.539329],"type":"Point"}
}