{
  "type": "Feature",
  "properties": {
    "iso:country":"US",
    "sg:address":"3035 170th St",
    "sg:city":"Homestead",
    "sg:classifiers":[
        {
            "category":"Farming",
            "subcategory":"Poultry Farm",
            "type":"Manufacturing & Wholesale Goods"
        }
    ],
    "sg:phone":"+1 319 662 4051",
    "sg:postcode":"52236",
    "sg:province":"IA",
    "sg:tags":[
        "chicken",
        "egg"
    ],
    "wof:name":"Matthew Kahler",
    "wof:placetype":"venue"
},
  "geometry": {"coordinates":[-91.902311,41.759459],"type":"Point"}
}