{
  "type": "Feature",
  "properties": {
    "iso:country":"US",
    "sg:address":"202 E Washington St",
    "sg:city":"Clarinda",
    "sg:classifiers":[
        {
            "category":"Organizations",
            "subcategory":"Non-profit Organization",
            "type":"Services"
        }
    ],
    "sg:phone":"+1 712 542 3643",
    "sg:postcode":"51632",
    "sg:province":"IA",
    "wof:name":"Clarinda Hospitality Group",
    "wof:placetype":"venue"
},
  "geometry": {"coordinates":[-95.035184,40.739337],"type":"Point"}
}