{
  "type": "Feature",
  "properties": {
    "iso:country":"US",
    "sg:address":"1212 13th Ave S",
    "sg:city":"Rock Valley",
    "sg:classifiers":[
        {
            "category":"Farming",
            "subcategory":"Farm",
            "type":"Manufacturing & Wholesale Goods"
        }
    ],
    "sg:phone":"+1 712 476 2582",
    "sg:postcode":"51247",
    "sg:province":"IA",
    "sg:tags":[
        "crop",
        "general"
    ],
    "wof:name":"Wilbur Rook",
    "wof:placetype":"venue"
},
  "geometry": {"coordinates":[-96.299154,43.198184],"type":"Point"}
}