{
  "type": "Feature",
  "properties": {
    "iso:country":"US",
    "sg:address":"3254 Mississippi River Rd",
    "sg:city":"Keokuk",
    "sg:classifiers":[
        {
            "category":"Freight",
            "type":"Transportation"
        }
    ],
    "sg:phone":"+1 319 524 6841",
    "sg:postcode":"52632",
    "sg:province":"IA",
    "sg:tags":[
        "terminal",
        "marine"
    ],
    "wof:name":"Orba-Johnson Transshipment Co",
    "wof:placetype":"venue"
},
  "geometry": {"coordinates":[-91.37651,40.485617],"type":"Point"}
}