{
  "type": "Feature",
  "properties": {
    "iso:country":"US",
    "sg:address":"22 S 14th St",
    "sg:city":"Denison",
    "sg:classifiers":[
        {
            "category":"Bars & Pubs",
            "type":"Food & Drink"
        }
    ],
    "sg:phone":"+1 712 263 2083",
    "sg:postcode":"51442",
    "sg:province":"IA",
    "sg:tags":[
        "club",
        "night"
    ],
    "wof:name":"Latino Night Club",
    "wof:placetype":"venue"
},
  "geometry": {"coordinates":[-95.353752,42.016494],"type":"Point"}
}