{
  "type": "Feature",
  "properties": {
    "iso:country":"US",
    "sg:address":"110 W 7th St",
    "sg:city":"Boone",
    "sg:classifiers":[
        {
            "category":"Health Services",
            "subcategory":"Clinic",
            "type":"Services"
        }
    ],
    "sg:phone":"+1 515 432 8936",
    "sg:postcode":"50036",
    "sg:province":"IA",
    "wof:name":"Hall Transcription Enterprises",
    "wof:placetype":"venue"
},
  "geometry": {"coordinates":[-93.895611,42.062647],"type":"Point"}
}