{
  "type": "Feature",
  "properties": {
    "iso:country":"US",
    "sg:address":"206 Maple St",
    "sg:city":"Olin",
    "sg:classifiers":[
        {
            "category":"Social Services",
            "subcategory":"Child Care",
            "type":"Services"
        }
    ],
    "sg:phone":"+1 319 484 4466",
    "sg:postcode":"52320",
    "sg:province":"IA",
    "wof:name":"Little Lion Learning Ctr",
    "wof:placetype":"venue"
},
  "geometry": {"coordinates":[-91.14078499999999,41.995157],"type":"Point"}
}