{
  "type": "Feature",
  "properties": {
    "addr:full":"2241 Lincoln Ave Dubuque IA 52001",
    "addr:housenumber":"2241",
    "addr:postcode":"52001",
    "addr:street":"Lincoln Ave",
    "iso:country":"US",
    "sg:address":"2241 Lincoln Ave",
    "sg:city":"Dubuque",
    "sg:classifiers":[
        {
            "category":"Museum",
            "type":"Entertainment"
        }
    ],
    "sg:phone":"+1 563 557 9545",
    "sg:postcode":"52001",
    "sg:province":"IA",
    "wof:name":"Mathias Ham House Historic",
    "wof:placetype":"venue"
},
  "geometry": {"coordinates":[-90.649827,42.531237],"type":"Point"}
}