{
  "type": "Feature",
  "properties": {
    "addr:full":"2550 SE 43rd St Pleasant Hill IA 50327",
    "addr:housenumber":"2550",
    "addr:postcode":"50327",
    "addr:street":"Se 43Rd St",
    "iso:country":"US",
    "sg:address":"2550 SE 43rd St",
    "sg:city":"Pleasant Hill",
    "sg:classifiers":[
        {
            "category":"Manufacturing",
            "subcategory":"Glass & Minerals",
            "type":"Manufacturing & Wholesale Goods"
        }
    ],
    "sg:phone":"+1 515 265 2224",
    "sg:postcode":"50327",
    "sg:province":"IA",
    "sg:tags":[
        "cement"
    ],
    "wof:name":"Holcim Us Inc",
    "wof:placetype":"venue"
},
  "geometry": {"coordinates":[-93.52955799999999,41.562903],"type":"Point"}
}