{
  "type": "Feature",
  "properties": {
    "addr:full":"49767 180th Ave Scarville IA 50473",
    "addr:housenumber":"49767",
    "addr:postcode":"50473",
    "addr:street":"180Th Ave",
    "iso:country":"US",
    "sg:address":"49767 180th Ave",
    "sg:city":"Scarville",
    "sg:phone":"+1 641 568 3537",
    "sg:postcode":"50473",
    "sg:province":"IA",
    "sg:tags":[
        "farm",
        "corn",
        "soybean"
    ],
    "wof:name":"Homer Peterson",
    "wof:placetype":"venue"
},
  "geometry": {"coordinates":[-93.616939,43.482141],"type":"Point"}
}