{
  "type": "Feature",
  "properties": {
    "iso:country":"US",
    "sg:address":"1504 Laurel Dr",
    "sg:city":"Decorah",
    "sg:classifiers":[
        {
            "category":"Shopping",
            "subcategory":"Gifts & Souvenirs",
            "type":"Retail Goods"
        }
    ],
    "sg:phone":"+1 563 382 1382",
    "sg:postcode":"52101",
    "sg:province":"IA",
    "sg:tags":[
        "basket",
        "parcel"
    ],
    "wof:name":"Total Basket Cases",
    "wof:placetype":"venue"
},
  "geometry": {"coordinates":[-91.78609299999999,43.327835],"type":"Point"}
}