{
  "type": "Feature",
  "properties": {
    "addr:full":"5658 Westminster Dr Cedar Falls IA 50613",
    "addr:housenumber":"5658",
    "addr:postcode":"50613",
    "addr:street":"Westminster Dr",
    "iso:country":"US",
    "sg:address":"5658 Westminster Dr",
    "sg:city":"Cedar Falls",
    "sg:classifiers":[
        {
            "category":"Autos & Motor Vehicles",
            "subcategory":"Auto Supplies",
            "type":"Retail Goods"
        }
    ],
    "sg:phone":"+1 319 277 7005",
    "sg:postcode":"50613",
    "sg:province":"IA",
    "sg:tags":[
        "automobile",
        "parts"
    ],
    "wof:name":"Keystone Automotive",
    "wof:placetype":"venue"
},
  "geometry": {"coordinates":[-92.456985,42.487105],"type":"Point"}
}