{
  "type": "Feature",
  "properties": {
    "iso:country":"US",
    "sg:address":"908 W Cedar St",
    "sg:city":"Cherokee",
    "sg:classifiers":[
        {
            "category":"Social Services",
            "subcategory":"Child Care",
            "type":"Services"
        }
    ],
    "sg:phone":"+1 712 225 5455",
    "sg:postcode":"51012",
    "sg:province":"IA",
    "sg:tags":[
        "day"
    ],
    "wof:name":"Dees Daycare Center",
    "wof:placetype":"venue"
},
  "geometry": {"coordinates":[-95.56413999999999,42.751915],"type":"Point"}
}