{
  "type": "Feature",
  "properties": {
    "iso:country":"US",
    "sg:address":"1303 Broadway St",
    "sg:city":"Pella",
    "sg:classifiers":[
        {
            "category":"Social Services",
            "subcategory":"Job Training",
            "type":"Services"
        }
    ],
    "sg:phone":"+1 641 628 9196",
    "sg:postcode":"50219",
    "sg:province":"IA",
    "sg:tags":[
        "rehabilitation"
    ],
    "wof:name":"Christian Opportunity Ctr",
    "wof:placetype":"venue"
},
  "geometry": {"coordinates":[-92.918387,41.416504],"type":"Point"}
}