{
  "type": "Feature",
  "properties": {
    "iso:country":"US",
    "sg:address":"2991 260th St",
    "sg:city":"Charles City",
    "sg:classifiers":[
        {
            "category":"Farming",
            "subcategory":"Farm",
            "type":"Manufacturing & Wholesale Goods"
        }
    ],
    "sg:phone":"+1 641 228 2660",
    "sg:postcode":"50616",
    "sg:province":"IA",
    "sg:tags":[
        "crop",
        "general"
    ],
    "wof:name":"William Ritzman",
    "wof:placetype":"venue"
},
  "geometry": {"coordinates":[-92.634642,42.980046],"type":"Point"}
}