{
  "type": "Feature",
  "properties": {
    "addr:full":"1264 Quail Ave Badger IA 50516",
    "addr:housenumber":"1264",
    "addr:postcode":"50516",
    "addr:street":"Quail Ave",
    "iso:country":"US",
    "sg:address":"1264 Quail Ave",
    "sg:city":"Badger",
    "sg:classifiers":[
        {
            "category":"Professional",
            "subcategory":"Business Services",
            "type":"Services"
        }
    ],
    "sg:phone":"+1 515 545 4416",
    "sg:postcode":"50516",
    "sg:province":"IA",
    "wof:name":"Benjamin Trophy Company",
    "wof:placetype":"venue"
},
  "geometry": {"coordinates":[-94.129188,42.606207],"type":"Point"}
}