{
  "type": "Feature",
  "properties": {
    "addr:full":"813 4th St Manning IA 51455",
    "addr:housenumber":"813",
    "addr:postcode":"51455",
    "addr:street":"4Th St",
    "iso:country":"US",
    "sg:address":"813 4th St",
    "sg:city":"Manning",
    "sg:classifiers":[
        {
            "category":"Shopping",
            "subcategory":"Used Merchandise",
            "type":"Retail Goods"
        }
    ],
    "sg:phone":"+1 712 655 2929",
    "sg:postcode":"51455",
    "sg:province":"IA",
    "sg:tags":[
        "second",
        "store",
        "hand"
    ],
    "wof:name":"Village Bargain Shoppe",
    "wof:placetype":"venue"
},
  "geometry": {"coordinates":[-95.065258,41.908163],"type":"Point"}
}