{
  "type": "Feature",
  "properties": {
    "iso:country":"US",
    "sg:address":"24419 Violet Ave",
    "sg:city":"Plymouth",
    "sg:classifiers":[
        {
            "category":"Real Estate",
            "subcategory":"Real Estate Operator",
            "type":"Services"
        }
    ],
    "sg:phone":"+1 641 696 5762",
    "sg:postcode":"50464",
    "sg:province":"IA",
    "sg:tags":[
        "property",
        "lessor"
    ],
    "wof:name":"Rufus Glassel",
    "wof:placetype":"venue"
},
  "geometry": {"coordinates":[-93.073683,43.24835],"type":"Point"}
}