{
  "type": "Feature",
  "properties": {
    "iso:country":"US",
    "sg:address":"424 E Locust St",
    "sg:city":"Des Moines",
    "sg:classifiers":[
        {
            "category":"Shopping",
            "subcategory":"Music",
            "type":"Retail Goods"
        }
    ],
    "sg:phone":"+1 515 284 1401",
    "sg:postcode":"50309",
    "sg:province":"IA",
    "sg:tags":[
        "compact",
        "record",
        "disc",
        "tape"
    ],
    "wof:name":"ZZZ Records",
    "wof:placetype":"venue"
},
  "geometry": {"coordinates":[-93.611512,41.589674],"type":"Point"}
}