{
  "type": "Feature",
  "properties": {
    "iso:country":"US",
    "sg:address":"3195 Cumming Rd",
    "sg:city":"Cumming",
    "sg:classifiers":[
        {
            "category":"Building & Trades",
            "subcategory":"Construction",
            "type":"Services"
        }
    ],
    "sg:phone":"+1 515 277 5115",
    "sg:postcode":"50061",
    "sg:province":"IA",
    "sg:tags":[
        "general",
        "contractor"
    ],
    "wof:name":"Archer Construction Inc",
    "wof:placetype":"venue"
},
  "geometry": {"coordinates":[-93.814587,41.481118],"type":"Point"}
}