{
  "type": "Feature",
  "properties": {
    "iso:country":"US",
    "sg:address":"15564 180th St",
    "sg:city":"Alden",
    "sg:phone":"+1 515 855 4261",
    "sg:postcode":"50006",
    "sg:province":"IA",
    "sg:tags":[
        "farm"
    ],
    "wof:name":"Van Langen Norman",
    "wof:placetype":"venue"
},
  "geometry": {"coordinates":[-93.39399899999999,42.441123],"type":"Point"}
}