{
  "type": "Feature",
  "properties": {
    "addr:full":"555 John F Kennedy Rd Ste 476 Dubuque IA 52002",
    "addr:housenumber":"555",
    "addr:postcode":"52002",
    "addr:street":"John F Kennedy Rd Ste 476",
    "iso:country":"US",
    "sg:address":"555 John F Kennedy Rd Ste 476",
    "sg:city":"Dubuque",
    "sg:classifiers":[
        {
            "category":"Personal",
            "subcategory":"Beauty Salon",
            "type":"Services"
        }
    ],
    "sg:phone":"+1 563 583 1633",
    "sg:postcode":"52002",
    "sg:province":"IA",
    "sg:tags":[
        "hair",
        "stylist"
    ],
    "sg:website":"http://www.costcutters.com",
    "wof:name":"Cost Cutters",
    "wof:placetype":"venue"
},
  "geometry": {"coordinates":[-90.716087,42.493692],"type":"Point"}
}