{
  "type": "Feature",
  "properties": {
    "addr:full":"300 4th St Sioux Rapids IA 50585",
    "addr:housenumber":"300",
    "addr:postcode":"50585",
    "addr:street":"4Th St",
    "iso:country":"US",
    "sg:address":"300 4th St",
    "sg:city":"Sioux Rapids",
    "sg:classifiers":[
        {
            "category":"Organizations",
            "subcategory":"Religious Organization",
            "type":"Services"
        }
    ],
    "sg:phone":"+1 712 283 2771",
    "sg:postcode":"50585",
    "sg:province":"IA",
    "sg:tags":[
        "church"
    ],
    "wof:name":"Sioux Rapids Baptist Church",
    "wof:placetype":"venue"
},
  "geometry": {"coordinates":[-95.14778699999999,42.892278],"type":"Point"}
}