{
  "type": "Feature",
  "properties": {
    "addr:full":"708 Commerce Dr Decorah IA 52101",
    "addr:housenumber":"708",
    "addr:postcode":"52101",
    "addr:street":"Commerce Dr",
    "iso:country":"US",
    "sg:address":"708 Commerce Dr",
    "sg:city":"Decorah",
    "sg:classifiers":[
        {
            "category":"Professional",
            "subcategory":"Engineering",
            "type":"Services"
        }
    ],
    "sg:phone":"+1 563 382 4194",
    "sg:postcode":"52101",
    "sg:province":"IA",
    "sg:tags":[
        "engineer"
    ],
    "wof:name":"Erdman Engineering",
    "wof:placetype":"venue"
},
  "geometry": {"coordinates":[-91.77027099999999,43.293175],"type":"Point"}
}