{
  "type": "Feature",
  "properties": {
    "iso:country":"US",
    "sg:address":"5804 Franklin Ave",
    "sg:city":"Des Moines",
    "sg:classifiers":[
        {
            "category":"Retail",
            "subcategory":"Laundry & Dry Cleaning",
            "type":"Services"
        }
    ],
    "sg:phone":"+1 515 277 0262",
    "sg:postcode":"50322",
    "sg:province":"IA",
    "sg:tags":[
        "cleaners"
    ],
    "wof:name":"Franklin Park Cleaners",
    "wof:placetype":"venue"
},
  "geometry": {"coordinates":[-93.698808,41.611192],"type":"Point"}
}