{
  "type": "Feature",
  "properties": {
    "iso:country":"US",
    "sg:address":"915 N Main St",
    "sg:city":"Carroll",
    "sg:classifiers":[
        {
            "category":"Farming",
            "subcategory":"Farm",
            "type":"Manufacturing & Wholesale Goods"
        }
    ],
    "sg:phone":"+1 712 792 6348",
    "sg:postcode":"51401",
    "sg:province":"IA",
    "sg:tags":[
        "crop",
        "general"
    ],
    "wof:name":"Scott Bauck",
    "wof:placetype":"venue"
},
  "geometry": {"coordinates":[-94.865314,42.069746],"type":"Point"}
}