{
  "type": "Feature",
  "properties": {
    "iso:country":"US",
    "sg:address":"2420 Agency St",
    "sg:city":"Burlington",
    "sg:classifiers":[
        {
            "category":"Organizations",
            "subcategory":"Religious Organization",
            "type":"Services"
        }
    ],
    "sg:phone":"+1 319 752 7224",
    "sg:postcode":"52601",
    "sg:province":"IA",
    "sg:tags":[
        "lutheran",
        "church"
    ],
    "wof:name":"Our Svior Lutheran Church Wels",
    "wof:placetype":"venue"
},
  "geometry": {"coordinates":[-91.133594,40.81463],"type":"Point"}
}