{
  "type": "Feature",
  "properties": {
    "iso:country":"US",
    "sg:address":"1020 S 4th St",
    "sg:city":"Ames",
    "sg:classifiers":[
        {
            "category":"Government",
            "subcategory":"Office",
            "type":"Public Place"
        }
    ],
    "sg:phone":"+1 515 239 1635",
    "sg:postcode":"50010",
    "sg:province":"IA",
    "sg:website":"www.dot.gov",
    "wof:name":"Department Of Transportation",
    "wof:placetype":"venue"
},
  "geometry": {"coordinates":[-93.625001,42.019159],"type":"Point"}
}