{
  "type": "Feature",
  "properties": {
    "iso:country":"US",
    "sg:address":"116 E Main St",
    "sg:city":"Ossian",
    "sg:classifiers":[
        {
            "category":"Shopping",
            "subcategory":"Florist",
            "type":"Retail Goods"
        }
    ],
    "sg:phone":"+1 563 532 9535",
    "sg:postcode":"52161",
    "sg:province":"IA",
    "wof:name":"Blooms On Main",
    "wof:placetype":"venue"
},
  "geometry": {"coordinates":[-91.76470399999999,43.145528],"type":"Point"}
}