{
  "type": "Feature",
  "properties": {
    "iso:country":"US",
    "sg:address":"247 S 9th St",
    "sg:city":"Sac City",
    "sg:classifiers":[
        {
            "category":"Building & Trades",
            "subcategory":"Construction",
            "type":"Services"
        }
    ],
    "sg:phone":"+1 712 662 4817",
    "sg:postcode":"50583",
    "sg:province":"IA",
    "sg:tags":[
        "house",
        "carpentry",
        "contractor"
    ],
    "wof:name":"Pullen Remodeling",
    "wof:placetype":"venue"
},
  "geometry": {"coordinates":[-94.994371,42.418946],"type":"Point"}
}