{
  "type": "Feature",
  "properties": {
    "addr:full":"1001 73rd St Windsor Heights IA 50311",
    "addr:housenumber":"1001",
    "addr:postcode":"50311",
    "addr:street":"73Rd St",
    "iso:country":"US",
    "sg:address":"1001 73rd St",
    "sg:city":"Windsor Heights",
    "sg:classifiers":[
        {
            "category":"Personal",
            "subcategory":"Beauty Salon",
            "type":"Services"
        }
    ],
    "sg:phone":"+1 515 279 2990",
    "sg:postcode":"50311",
    "sg:province":"IA",
    "wof:name":"Smart Style Family Hair Salon",
    "wof:placetype":"venue"
},
  "geometry": {"coordinates":[-93.71858899999999,41.596458],"type":"Point"}
}