{
  "type": "Feature",
  "properties": {
    "addr:full":"108 N Main St Elkader IA 52043",
    "addr:housenumber":"108",
    "addr:postcode":"52043",
    "addr:street":"N Main St",
    "iso:country":"US",
    "sg:address":"108 N Main St",
    "sg:city":"Elkader",
    "sg:classifiers":[
        {
            "category":"Cinema",
            "subcategory":"Movie Theater",
            "type":"Entertainment"
        }
    ],
    "sg:phone":"+1 563 245 2036",
    "sg:postcode":"52043",
    "sg:province":"IA",
    "wof:name":"Elkader Cinema",
    "wof:placetype":"venue"
},
  "geometry": {"coordinates":[-91.405109,42.855263],"type":"Point"}
}