{
  "type": "Feature",
  "properties": {
    "addr:full":"631 E Ayers St Osceola IA 50213",
    "addr:housenumber":"631",
    "addr:postcode":"50213",
    "addr:street":"E Ayers St",
    "iso:country":"US",
    "sg:address":"631 E Ayers St",
    "sg:city":"Osceola",
    "sg:classifiers":[
        {
            "category":"Real Estate",
            "subcategory":"Real Estate Operator",
            "type":"Services"
        }
    ],
    "sg:phone":"+1 641 342 2015",
    "sg:postcode":"50213",
    "sg:province":"IA",
    "sg:tags":[
        "building",
        "apartment"
    ],
    "wof:name":"Osceola Estates",
    "wof:placetype":"venue"
},
  "geometry": {"coordinates":[-93.755222,41.038891],"type":"Point"}
}