{
  "type": "Feature",
  "properties": {
    "iso:country":"US",
    "sg:address":"1295 280th St",
    "sg:city":"Oskaloosa",
    "sg:phone":"+1 641 672 2269",
    "sg:postcode":"52577",
    "sg:province":"IA",
    "sg:tags":[
        "farm",
        "corn"
    ],
    "wof:name":"Randy A Denburger",
    "wof:placetype":"venue"
},
  "geometry": {"coordinates":[-92.809917,41.24871],"type":"Point"}
}