{
  "type": "Feature",
  "properties": {
    "addr:full":"10249 Grand Ave Greene IA 50636",
    "addr:housenumber":"10249",
    "addr:postcode":"50636",
    "addr:street":"Grand Ave",
    "iso:country":"US",
    "sg:address":"10249 Grand Ave",
    "sg:city":"Greene",
    "sg:classifiers":[
        {
            "category":"Farming",
            "subcategory":"Farm",
            "type":"Manufacturing & Wholesale Goods"
        }
    ],
    "sg:phone":"+1 641 823 4509",
    "sg:postcode":"50636",
    "sg:province":"IA",
    "sg:tags":[
        "crop",
        "general"
    ],
    "wof:name":"DC Farms Inc",
    "wof:placetype":"venue"
},
  "geometry": {"coordinates":[-92.906893,42.900012],"type":"Point"}
}