{
  "type": "Feature",
  "properties": {
    "iso:country":"US",
    "sg:address":"158 S Elm St",
    "sg:city":"Avoca",
    "sg:classifiers":[
        {
            "category":"Food & Beverages",
            "subcategory":"Liquor & Beverages",
            "type":"Retail Goods"
        }
    ],
    "sg:phone":"+1 712 343 6994",
    "sg:postcode":"51521",
    "sg:province":"IA",
    "wof:name":"Avoca Liquor",
    "wof:placetype":"venue"
},
  "geometry": {"coordinates":[-95.33951500000001,41.475699],"type":"Point"}
}