{
  "type": "Feature",
  "properties": {
    "iso:country":"US",
    "sg:address":"4501 Southern Hills Dr",
    "sg:city":"Sioux City",
    "sg:classifiers":[
        {
            "category":"Real Estate",
            "subcategory":"Real Estate Agent",
            "type":"Services"
        }
    ],
    "sg:phone":"+1 712 276 5210",
    "sg:postcode":"51106",
    "sg:province":"IA",
    "wof:name":"Arjenator Inc",
    "wof:placetype":"venue"
},
  "geometry": {"coordinates":[-96.347702,42.44045],"type":"Point"}
}