{
  "type": "Feature",
  "properties": {
    "iso:country":"US",
    "sg:address":"17 N Vine St",
    "sg:city":"Glenwood",
    "sg:classifiers":[
        {
            "category":"Autos & Motor Vehicles",
            "subcategory":"Auto Supplies",
            "type":"Retail Goods"
        }
    ],
    "sg:phone":"+1 712 527 4819",
    "sg:postcode":"51534",
    "sg:province":"IA",
    "sg:tags":[
        "automobile",
        "parts"
    ],
    "wof:name":"Anderson Auto Parts Carquest",
    "wof:placetype":"venue"
},
  "geometry": {"coordinates":[-95.74173999999999,41.046564],"type":"Point"}
}