{
  "type": "Feature",
  "properties": {
    "iso:country":"US",
    "sg:address":"3605 40th Ave",
    "sg:city":"Fenton",
    "sg:classifiers":[
        {
            "category":"Farming",
            "subcategory":"Fish & Marine Products",
            "type":"Manufacturing & Wholesale Goods"
        }
    ],
    "sg:phone":"+1 515 925 3364",
    "sg:postcode":"50539",
    "sg:province":"IA",
    "sg:tags":[
        "catching"
    ],
    "wof:name":"Allan Bernhard",
    "wof:placetype":"venue"
},
  "geometry": {"coordinates":[-94.383983,43.287357],"type":"Point"}
}