{
  "type": "Feature",
  "properties": {
    "iso:country":"US",
    "sg:address":"2114 270th Ave",
    "sg:city":"De Witt",
    "sg:classifiers":[
        {
            "category":"Wholesale",
            "subcategory":"Machinery & Supplies",
            "type":"Manufacturing & Wholesale Goods"
        }
    ],
    "sg:phone":"+1 563 659 2866",
    "sg:postcode":"52742",
    "sg:province":"IA",
    "sg:tags":[
        "farm",
        "equipment"
    ],
    "sg:website":"www.kunauimplement.com",
    "wof:name":"Kunau Implement",
    "wof:placetype":"venue"
},
  "geometry": {"coordinates":[-90.56794600000001,41.869713],"type":"Point"}
}