{
  "type": "Feature",
  "properties": {
    "iso:country":"US",
    "sg:address":"850 22nd Ave",
    "sg:city":"Coralville",
    "sg:classifiers":[
        {
            "category":"Health Services",
            "subcategory":"Health Practitioner",
            "type":"Services"
        }
    ],
    "sg:phone":"+1 319 354 3131",
    "sg:postcode":"52241",
    "sg:province":"IA",
    "sg:tags":[
        "operates",
        "therapist",
        "speech",
        "therapy",
        "occupational",
        "physical"
    ],
    "wof:name":"Premier Health Associates Inc",
    "wof:placetype":"venue"
},
  "geometry": {"coordinates":[-91.595308,41.682732],"type":"Point"}
}