{
  "type": "Feature",
  "properties": {
    "iso:country":"US",
    "sg:address":"1231 Broadway",
    "sg:city":"Denison",
    "sg:classifiers":[
        {
            "category":"Retail",
            "subcategory":"Portrait Studio",
            "type":"Services"
        }
    ],
    "sg:phone":"+1 712 263 8882",
    "sg:postcode":"51442",
    "sg:province":"IA",
    "sg:tags":[
        "photo",
        "repair"
    ],
    "wof:name":"Portraits By Hope",
    "wof:placetype":"venue"
},
  "geometry": {"coordinates":[-95.35603500000001,42.01667],"type":"Point"}
}