{
  "type": "Feature",
  "properties": {
    "iso:country":"US",
    "sg:address":"113 Gilbert Dr",
    "sg:city":"Evansdale",
    "sg:classifiers":[
        {
            "category":"Retail",
            "subcategory":"Auto Repair",
            "type":"Services"
        }
    ],
    "sg:phone":"+1 319 232 7658",
    "sg:postcode":"50707",
    "sg:province":"IA",
    "sg:tags":[
        "repairing",
        "automobile"
    ],
    "wof:name":"Advanced Auto Svc",
    "wof:placetype":"venue"
},
  "geometry": {"coordinates":[-92.29528999999999,42.462658],"type":"Point"}
}