{
  "type": "Feature",
  "properties": {
    "iso:country":"US",
    "sg:address":"1409 4th Ave S",
    "sg:city":"Denison",
    "sg:classifiers":[
        {
            "category":"Shopping",
            "subcategory":"Florist",
            "type":"Retail Goods"
        }
    ],
    "sg:phone":"+1 712 263 3220",
    "sg:postcode":"51442",
    "sg:province":"IA",
    "wof:name":"Country Rose",
    "wof:placetype":"venue"
},
  "geometry": {"coordinates":[-95.351996,42.012285],"type":"Point"}
}