{
  "type": "Feature",
  "properties": {
    "iso:country":"US",
    "sg:address":"618 Lombard St",
    "sg:city":"Clarence",
    "sg:classifiers":[
        {
            "category":"Food & Beverages",
            "subcategory":"Groceries & Convenience Stores",
            "type":"Retail Goods"
        }
    ],
    "sg:phone":"+1 563 452 3311",
    "sg:postcode":"52216",
    "sg:province":"IA",
    "sg:tags":[
        "grocer"
    ],
    "wof:name":"Lange's Grocery",
    "wof:placetype":"venue"
},
  "geometry": {"coordinates":[-91.054954,41.888674],"type":"Point"}
}