{
  "type": "Feature",
  "properties": {
    "iso:country":"US",
    "sg:address":"2901 Hamilton Blvd",
    "sg:city":"Sioux City",
    "sg:classifiers":[
        {
            "category":"Real Estate",
            "subcategory":"Real Estate Operator",
            "type":"Services"
        }
    ],
    "sg:phone":"+1 712 239 6565",
    "sg:postcode":"51104",
    "sg:province":"IA",
    "sg:tags":[
        "mall",
        "shopping",
        "center"
    ],
    "wof:name":"Market Place Shopping Ctr",
    "wof:placetype":"venue"
},
  "geometry": {"coordinates":[-96.41787100000001,42.520026],"type":"Point"}
}