{
  "type": "Feature",
  "properties": {
    "iso:country":"US",
    "sg:address":"304 1st St",
    "sg:city":"Corwith",
    "sg:classifiers":[
        {
            "category":"Organizations",
            "subcategory":"Community Association",
            "type":"Services"
        }
    ],
    "sg:phone":"+1 515 583 2632",
    "sg:postcode":"50430",
    "sg:province":"IA",
    "sg:tags":[
        "military"
    ],
    "wof:name":"American Legion",
    "wof:placetype":"venue"
},
  "geometry": {"coordinates":[-93.95649400000001,42.993358],"type":"Point"}
}