{
  "type": "Feature",
  "properties": {
    "addr:full":"2082 280th Ave De Witt IA 52742",
    "addr:housenumber":"2082",
    "addr:postcode":"52742",
    "addr:street":"280Th Ave De",
    "iso:country":"US",
    "sg:address":"2082 280th Ave",
    "sg:city":"De Witt",
    "sg:phone":"+1 563 659 8626",
    "sg:postcode":"52742",
    "sg:province":"IA",
    "sg:tags":[
        "farm",
        "corn"
    ],
    "wof:name":"Keith Green",
    "wof:placetype":"venue"
},
  "geometry": {"coordinates":[-90.548588,41.875557],"type":"Point"}
}