{
  "type": "Feature",
  "properties": {
    "iso:country":"US",
    "sg:address":"1203 Jersey Ridge Rd",
    "sg:city":"Davenport",
    "sg:classifiers":[
        {
            "category":"Professional",
            "subcategory":"Lawyer & Legal Services",
            "type":"Services"
        }
    ],
    "sg:phone":"+1 563 322 1020",
    "sg:postcode":"52803",
    "sg:province":"IA",
    "wof:name":"Kroeger Neill",
    "wof:placetype":"venue"
},
  "geometry": {"coordinates":[-90.543317,41.532464],"type":"Point"}
}