{
  "type": "Feature",
  "properties": {
    "iso:country":"US",
    "sg:address":"1948 111th St",
    "sg:city":"Atalissa",
    "sg:phone":"+1 563 649 2594",
    "sg:postcode":"52720",
    "sg:province":"IA",
    "sg:tags":[
        "farm",
        "corn"
    ],
    "wof:name":"Herbert Johnson",
    "wof:placetype":"venue"
},
  "geometry": {"coordinates":[-91.185875,41.578675],"type":"Point"}
}