{
  "type": "Feature",
  "properties": {
    "addr:full":"27387 130th Ave Donahue IA 52746",
    "addr:housenumber":"27387",
    "addr:postcode":"52746",
    "addr:street":"130Th Ave",
    "iso:country":"US",
    "sg:address":"27387 130th Ave",
    "sg:city":"Donahue",
    "sg:classifiers":[
        {
            "category":"Shopping",
            "subcategory":"Florist",
            "type":"Retail Goods"
        }
    ],
    "sg:phone":"+1 563 282 4338",
    "sg:postcode":"52746",
    "sg:province":"IA",
    "wof:name":"Miss Effies Country Flowers",
    "wof:placetype":"venue"
},
  "geometry": {"coordinates":[-90.646022,41.704162],"type":"Point"}
}