{
  "type": "Feature",
  "properties": {
    "iso:country":"US",
    "sg:address":"360 Main St W",
    "sg:city":"Maynard",
    "sg:classifiers":[
        {
            "category":"Bars & Pubs",
            "type":"Food & Drink"
        }
    ],
    "sg:phone":"+1 563 637 2872",
    "sg:postcode":"50655",
    "sg:province":"IA",
    "sg:tags":[
        "lounge",
        "cocktail"
    ],
    "wof:name":"Centerfield Lounge",
    "wof:placetype":"venue"
},
  "geometry": {"coordinates":[-91.88078400000001,42.773897],"type":"Point"}
}