{
  "type": "Feature",
  "properties": {
    "iso:country":"US",
    "sg:address":"315 Main St E",
    "sg:city":"Rockwell",
    "sg:classifiers":[
        {
            "category":"Personal",
            "subcategory":"Beauty Salon",
            "type":"Services"
        }
    ],
    "sg:phone":"+1 641 822 3464",
    "sg:postcode":"50469",
    "sg:province":"IA",
    "wof:name":"Styles Plus",
    "wof:placetype":"venue"
},
  "geometry": {"coordinates":[-93.18931600000001,42.985315],"type":"Point"}
}