{
  "type": "Feature",
  "properties": {
    "iso:country":"US",
    "sg:address":"726 S 17th St",
    "sg:city":"Fort Dodge",
    "sg:classifiers":[
        {
            "category":"Organizations",
            "subcategory":"Non-profit Organization",
            "type":"Services"
        }
    ],
    "sg:phone":"+1 515 576 7261",
    "sg:postcode":"50501",
    "sg:province":"IA",
    "sg:tags":[
        "info",
        "addiction",
        "abuse",
        "treatment",
        "drug"
    ],
    "sg:website":"www.communityandfamilyresources.org",
    "wof:name":"Community & Family Resource",
    "wof:placetype":"venue"
},
  "geometry": {"coordinates":[-94.174887,42.498436],"type":"Point"}
}