{
  "type": "Feature",
  "properties": {
    "iso:country":"US",
    "sg:address":"1627 Grand Ave",
    "sg:city":"West Des Moines",
    "sg:classifiers":[
        {
            "category":"Organizations",
            "subcategory":"Religious Organization",
            "type":"Services"
        }
    ],
    "sg:phone":"+1 515 225 6414",
    "sg:postcode":"50265",
    "sg:province":"IA",
    "sg:tags":[
        "church"
    ],
    "sg:website":"www.sacredheartwdm.org",
    "wof:name":"Sacred Heart Church",
    "wof:placetype":"venue"
},
  "geometry": {"coordinates":[-93.72718500000001,41.57792],"type":"Point"}
}