{
  "type": "Feature",
  "properties": {
    "iso:country":"US",
    "sg:address":"1921 51st St NE",
    "sg:city":"Cedar Rapids",
    "sg:classifiers":[
        {
            "category":"Professional",
            "subcategory":"Management & Consulting",
            "type":"Services"
        }
    ],
    "sg:phone":"+1 319 373 5281",
    "sg:postcode":"52402",
    "sg:province":"IA",
    "sg:tags":[
        "consultant"
    ],
    "wof:name":"Hoffman Design Consultants",
    "wof:placetype":"venue"
},
  "geometry": {"coordinates":[-91.66800499999999,42.029859],"type":"Point"}
}