{
  "type": "Feature",
  "properties": {
    "iso:country":"US",
    "sg:address":"300 W 1st St",
    "sg:city":"Leon",
    "sg:classifiers":[
        {
            "category":"Professional",
            "subcategory":"Business Services",
            "type":"Services"
        }
    ],
    "sg:phone":"+1 641 446 4114",
    "sg:postcode":"50144",
    "sg:province":"IA",
    "sg:tags":[
        "merchandising"
    ],
    "wof:name":"Finders Keepers",
    "wof:placetype":"venue"
},
  "geometry": {"coordinates":[-93.74921500000001,40.739515],"type":"Point"}
}