{
  "type": "Feature",
  "properties": {
    "addr:full":"1819 Falls Ave Waterloo IA 50701",
    "addr:housenumber":"1819",
    "addr:postcode":"50701",
    "addr:street":"Falls Ave",
    "iso:country":"US",
    "sg:address":"1819 Falls Ave",
    "sg:city":"Waterloo",
    "sg:classifiers":[
        {
            "category":"Wholesale",
            "subcategory":"Electrical",
            "type":"Manufacturing & Wholesale Goods"
        }
    ],
    "sg:phone":"+1 319 232 0662",
    "sg:postcode":"50701",
    "sg:province":"IA",
    "sg:tags":[
        "electric",
        "motor"
    ],
    "wof:name":"Motor Winding Inc",
    "wof:placetype":"venue"
},
  "geometry": {"coordinates":[-92.36989699999999,42.499196],"type":"Point"}
}