{
  "type": "Feature",
  "properties": {
    "addr:full":"1120 Windsor Ave Waucoma IA 52171",
    "addr:housenumber":"1120",
    "addr:postcode":"52171",
    "addr:street":"Windsor Ave",
    "iso:country":"US",
    "sg:address":"1120 Windsor Ave",
    "sg:city":"Waucoma",
    "sg:classifiers":[
        {
            "category":"Farming",
            "subcategory":"Dairy Farm",
            "type":"Manufacturing & Wholesale Goods"
        }
    ],
    "sg:phone":"+1 563 569 8753",
    "sg:postcode":"52171",
    "sg:province":"IA",
    "wof:name":"Victor Lukes",
    "wof:placetype":"venue"
},
  "geometry": {"coordinates":[-92.101237,43.19549],"type":"Point"}
}