{
  "type": "Feature",
  "properties": {
    "iso:country":"US",
    "sg:address":"3542 168th St",
    "sg:city":"Wever",
    "sg:classifiers":[
        {
            "category":"Banks & Credit Unions",
            "subcategory":"Bank",
            "type":"Services"
        }
    ],
    "sg:phone":"+1 319 372 5141",
    "sg:postcode":"52658",
    "sg:province":"IA",
    "sg:tags":[
        "saving",
        "commercial"
    ],
    "sg:website":"http://www.fsbwever.com",
    "wof:name":"Farmers Savings Bank",
    "wof:placetype":"venue"
},
  "geometry": {"coordinates":[-91.23604400000001,40.717456],"type":"Point"}
}