{
  "type": "Feature",
  "properties": {
    "iso:country":"US",
    "sg:address":"2600 Ave A",
    "sg:city":"Fort Madison",
    "sg:classifiers":[
        {
            "category":"Education",
            "subcategory":"School",
            "type":"Public Place"
        }
    ],
    "sg:phone":"+1 319 372 2486",
    "sg:postcode":"52627",
    "sg:province":"IA",
    "sg:website":"www.aquinas.pvt.k12.ia.us",
    "wof:name":"Aquinas High School",
    "wof:placetype":"venue"
},
  "geometry": {"coordinates":[-91.345027,40.637524],"type":"Point"}
}