{
  "type": "Feature",
  "properties": {
    "iso:country":"US",
    "sg:address":"3965 290th Ave",
    "sg:city":"Dickens",
    "sg:classifiers":[
        {
            "category":"Farming",
            "subcategory":"Farm",
            "type":"Manufacturing & Wholesale Goods"
        }
    ],
    "sg:phone":"+1 712 836 2535",
    "sg:postcode":"51333",
    "sg:province":"IA",
    "wof:name":"Shady Blue Farms Inc",
    "wof:placetype":"venue"
},
  "geometry": {"coordinates":[-95.012413,43.073083],"type":"Point"}
}