{
  "type": "Feature",
  "properties": {
    "iso:country":"US",
    "sg:address":"201 Main St",
    "sg:city":"Keosauqua",
    "sg:classifiers":[
        {
            "category":"Education",
            "subcategory":"College",
            "type":"Public Place"
        }
    ],
    "sg:phone":"+1 319 293 7115",
    "sg:postcode":"52565",
    "sg:province":"IA",
    "sg:tags":[
        "academic",
        "school"
    ],
    "wof:name":"Indian Hills Community College",
    "wof:placetype":"venue"
},
  "geometry": {"coordinates":[-91.963871,40.730246],"type":"Point"}
}