{
  "type": "Feature",
  "properties": {
    "iso:country":"US",
    "sg:address":"517 4th St",
    "sg:city":"Sibley",
    "sg:classifiers":[
        {
            "category":"Insurance",
            "subcategory":"Insurance Agent",
            "type":"Services"
        }
    ],
    "sg:phone":"+1 712 754 3944",
    "sg:postcode":"51249",
    "sg:province":"IA",
    "wof:name":"Creative Assests Consultants",
    "wof:placetype":"venue"
},
  "geometry": {"coordinates":[-95.74680499999999,43.405086],"type":"Point"}
}