{
  "type": "Feature",
  "properties": {
    "addr:full":"1010 SE National Dr Ankeny IA 50021",
    "addr:housenumber":"1010",
    "addr:postcode":"50021",
    "addr:street":"Se National Dr",
    "iso:country":"US",
    "sg:address":"1010 SE National Dr",
    "sg:city":"Ankeny",
    "sg:classifiers":[
        {
            "category":"Food & Beverages",
            "subcategory":"Groceries & Convenience Stores",
            "type":"Retail Goods"
        }
    ],
    "sg:phone":"+1 515 963 1985",
    "sg:postcode":"50021",
    "sg:province":"IA",
    "sg:website":"www.shortstop.com",
    "wof:name":"Short Stop",
    "wof:placetype":"venue"
},
  "geometry": {"coordinates":[-93.58245599999999,41.704929],"type":"Point"}
}