{
  "type": "Feature",
  "properties": {
    "iso:country":"US",
    "sg:address":"933 E Pierce St",
    "sg:city":"Council Bluffs",
    "sg:classifiers":[
        {
            "category":"Professional",
            "subcategory":"Research",
            "type":"Services"
        }
    ],
    "sg:phone":"+1 712 396 4422",
    "sg:postcode":"51503",
    "sg:province":"IA",
    "sg:tags":[
        "laboratory"
    ],
    "wof:name":"Path Lab Inc",
    "wof:placetype":"venue"
},
  "geometry": {"coordinates":[-95.83526000000001,41.268994],"type":"Point"}
}