{
  "type": "Feature",
  "properties": {
    "iso:country":"US",
    "sg:address":"2635 Adventureland Dr",
    "sg:city":"Altoona",
    "sg:classifiers":[
        {
            "category":"Autos & Motor Vehicles",
            "subcategory":"Fuel & Gas Station",
            "type":"Retail Goods"
        }
    ],
    "sg:phone":"+1 515 967 1700",
    "sg:postcode":"50009",
    "sg:province":"IA",
    "sg:tags":[
        "oil"
    ],
    "wof:name":"BP",
    "wof:placetype":"venue"
},
  "geometry": {"coordinates":[-93.493225,41.658594],"type":"Point"}
}