{
  "type": "Feature",
  "properties": {
    "iso:country":"US",
    "sg:address":"1213 S Main Ave",
    "sg:city":"Sioux Center",
    "sg:classifiers":[
        {
            "category":"Insurance",
            "subcategory":"Insurance Agent",
            "type":"Services"
        }
    ],
    "sg:phone":"+1 712 722 2243",
    "sg:postcode":"51250",
    "sg:province":"IA",
    "sg:website":"www.vansinsurance.com",
    "wof:name":"Van's Insurance Inc",
    "wof:placetype":"venue"
},
  "geometry": {"coordinates":[-96.175462,43.066298],"type":"Point"}
}