{
  "type": "Feature",
  "properties": {
    "addr:full":"3660 River Rd Osage IA 50461",
    "addr:housenumber":"3660",
    "addr:postcode":"50461",
    "addr:street":"River Rd",
    "iso:country":"US",
    "sg:address":"3660 River Rd",
    "sg:city":"Osage",
    "sg:classifiers":[
        {
            "category":"Professional",
            "subcategory":"Business Services",
            "type":"Services"
        }
    ],
    "sg:phone":"+1 641 732 3679",
    "sg:postcode":"50461",
    "sg:province":"IA",
    "wof:name":"Red Cedar Enterprises Inc",
    "wof:placetype":"venue"
},
  "geometry": {"coordinates":[-92.865442,43.295222],"type":"Point"}
}