{
  "type": "Feature",
  "properties": {
    "addr:full":"307 College Ct Iowa City IA 52245",
    "addr:housenumber":"307",
    "addr:postcode":"52245",
    "addr:street":"College Ct",
    "iso:country":"US",
    "sg:address":"307 College Ct",
    "sg:city":"Iowa City",
    "sg:classifiers":[
        {
            "category":"Building & Trades",
            "subcategory":"Equipment Rental",
            "type":"Services"
        }
    ],
    "sg:phone":"+1 319 688 2578",
    "sg:postcode":"52245",
    "sg:province":"IA",
    "wof:name":"Storks Nest",
    "wof:placetype":"venue"
},
  "geometry": {"coordinates":[-91.51312900000001,41.656822],"type":"Point"}
}