{
  "type": "Feature",
  "properties": {
    "addr:full":"1046 120th St Renwick IA 50447",
    "addr:housenumber":"1046",
    "addr:postcode":"50447",
    "addr:street":"120Th St",
    "iso:country":"US",
    "sg:address":"1046 120th St",
    "sg:city":"Renwick",
    "sg:classifiers":[
        {
            "category":"Farming",
            "subcategory":"Farm",
            "type":"Manufacturing & Wholesale Goods"
        }
    ],
    "sg:phone":"+1 515 824 3029",
    "sg:postcode":"50447",
    "sg:province":"IA",
    "wof:name":"Prestage Farms Of Iowa",
    "wof:placetype":"venue"
},
  "geometry": {"coordinates":[-93.97071800000001,42.877307],"type":"Point"}
}