{
  "type": "Feature",
  "properties": {
    "iso:country":"US",
    "sg:address":"2618 Bever Ave SE",
    "sg:city":"Cedar Rapids",
    "sg:classifiers":[
        {
            "category":"Professional",
            "subcategory":"Advertising",
            "type":"Services"
        }
    ],
    "sg:phone":"+1 319 362 6272",
    "sg:postcode":"52403",
    "sg:province":"IA",
    "sg:tags":[
        "public",
        "relations"
    ],
    "wof:name":"Mc Puffery Ltd",
    "wof:placetype":"venue"
},
  "geometry": {"coordinates":[-91.62905600000001,41.984307],"type":"Point"}
}