{
  "type": "Feature",
  "properties": {
    "iso:country":"US",
    "sg:address":"1515 W Pleasant St",
    "sg:city":"Knoxville",
    "sg:classifiers":[
        {
            "category":"Health Services",
            "subcategory":"Hospital",
            "type":"Services"
        }
    ],
    "sg:phone":"+1 641 828 5039",
    "sg:postcode":"50138",
    "sg:province":"IA",
    "sg:tags":[
        "specialty"
    ],
    "wof:name":"Acquisition and Materiel Mgt",
    "wof:placetype":"venue"
},
  "geometry": {"coordinates":[-93.11339599999999,41.320817],"type":"Point"}
}