{
  "type": "Feature",
  "properties": {
    "iso:country":"US",
    "sg:address":"1735 Hull Ave",
    "sg:city":"Des Moines",
    "sg:classifiers":[
        {
            "category":"Food & Beverages",
            "subcategory":"Fruits & Vegetables",
            "type":"Retail Goods"
        }
    ],
    "sg:phone":"+1 515 265 9700",
    "sg:postcode":"50313",
    "sg:province":"IA",
    "sg:tags":[
        "produce"
    ],
    "wof:name":"Big M Produce",
    "wof:placetype":"venue"
},
  "geometry": {"coordinates":[-93.586906,41.62221],"type":"Point"}
}