{
  "type": "Feature",
  "properties": {
    "iso:country":"US",
    "sg:address":"404 SW Logan St",
    "sg:city":"Ankeny",
    "sg:classifiers":[
        {
            "category":"Manufacturing",
            "subcategory":"Printing",
            "type":"Manufacturing & Wholesale Goods"
        }
    ],
    "sg:phone":"+1 515 964 0919",
    "sg:postcode":"50023",
    "sg:province":"IA",
    "sg:tags":[
        "commercial"
    ],
    "wof:name":"Buck Printing & Signs",
    "wof:placetype":"venue"
},
  "geometry": {"coordinates":[-93.60260100000001,41.727726],"type":"Point"}
}