{
  "type": "Feature",
  "properties": {
    "addr:full":"5800 SE 56th St Carlisle IA 50047",
    "addr:housenumber":"5800",
    "addr:postcode":"50047",
    "addr:street":"Se 56Th St",
    "iso:country":"US",
    "sg:address":"5800 SE 56th St",
    "sg:city":"Carlisle",
    "sg:classifiers":[
        {
            "category":"Freight",
            "type":"Transportation"
        }
    ],
    "sg:phone":"+1 515 240 0450",
    "sg:postcode":"50047",
    "sg:province":"IA",
    "sg:tags":[
        "trucking"
    ],
    "wof:name":"Rusty Parkins Trucking",
    "wof:placetype":"venue"
},
  "geometry": {"coordinates":[-93.500794,41.52963],"type":"Point"}
}