{
  "type": "Feature",
  "properties": {
    "iso:country":"US",
    "sg:address":"1152 C Ave",
    "sg:city":"Danbury",
    "sg:phone":"+1 712 679 2481",
    "sg:postcode":"51439",
    "sg:province":"IA",
    "sg:tags":[
        "beef",
        "farm",
        "corn",
        "cash",
        "grain",
        "cattle",
        "feedlot"
    ],
    "wof:name":"Gary Teut",
    "wof:placetype":"venue"
},
  "geometry": {"coordinates":[-95.633505,42.182324],"type":"Point"}
}