{
  "type": "Feature",
  "properties": {
    "iso:country":"US",
    "sg:address":"4540 F Ave NW",
    "sg:city":"Cedar Rapids",
    "sg:classifiers":[
        {
            "category":"Professional",
            "subcategory":"Management & Consulting",
            "type":"Services"
        }
    ],
    "sg:phone":"+1 319 396 4772",
    "sg:postcode":"52405",
    "sg:province":"IA",
    "wof:name":"Maintenance Management Svcs",
    "wof:placetype":"venue"
},
  "geometry": {"coordinates":[-91.729927,41.981893],"type":"Point"}
}