{
  "type": "Feature",
  "properties": {
    "iso:country":"US",
    "sg:address":"1430 Locust St",
    "sg:city":"Des Moines",
    "sg:classifiers":[
        {
            "category":"Professional",
            "subcategory":"Advertising",
            "type":"Services"
        }
    ],
    "sg:phone":"+1 515 251 8400",
    "sg:postcode":"50309",
    "sg:province":"IA",
    "sg:tags":[
        "counselor"
    ],
    "sg:website":"www.inthebag-lunches.com",
    "wof:name":"Mc Lellan Marketing Group",
    "wof:placetype":"venue"
},
  "geometry": {"coordinates":[-93.636292,41.58437],"type":"Point"}
}