{
  "type": "Feature",
  "properties": {
    "iso:country":"US",
    "sg:address":"46 1st St SW",
    "sg:city":"Badger",
    "sg:classifiers":[
        {
            "category":"Wholesale",
            "subcategory":"Electrical",
            "type":"Manufacturing & Wholesale Goods"
        }
    ],
    "sg:phone":"+1 515 545 4801",
    "sg:postcode":"50516",
    "sg:province":"IA",
    "sg:tags":[
        "control",
        "security",
        "system"
    ],
    "wof:name":"Uneek Security & Fire Solution",
    "wof:placetype":"venue"
},
  "geometry": {"coordinates":[-94.148303,42.615373],"type":"Point"}
}