{
  "type": "Feature",
  "properties": {
    "addr:full":"318 2nd Ave SW Sioux Center IA 51250",
    "addr:housenumber":"318",
    "addr:postcode":"51250",
    "addr:street":"2Nd Ave Sw",
    "iso:country":"US",
    "sg:address":"318 2nd Ave SW",
    "sg:city":"Sioux Center",
    "sg:classifiers":[
        {
            "category":"Building & Trades",
            "subcategory":"Construction",
            "type":"Services"
        }
    ],
    "sg:phone":"+1 712 722 2016",
    "sg:postcode":"51250",
    "sg:province":"IA",
    "sg:tags":[
        "general",
        "contractor"
    ],
    "wof:name":"Four Seasons Builders",
    "wof:placetype":"venue"
},
  "geometry": {"coordinates":[-96.178179,43.075059],"type":"Point"}
}