{
  "type": "Feature",
  "properties": {
    "iso:country":"US",
    "sg:address":"111 Anna Ct",
    "sg:city":"Preston",
    "sg:classifiers":[
        {
            "category":"Retail",
            "subcategory":"Repair Shop",
            "type":"Services"
        }
    ],
    "sg:phone":"+1 563 689 3813",
    "sg:postcode":"52069",
    "sg:province":"IA",
    "sg:tags":[
        "television",
        "radio-service"
    ],
    "wof:name":"Dbs Tv",
    "wof:placetype":"venue"
},
  "geometry": {"coordinates":[-90.39527099999999,42.05554],"type":"Point"}
}