{
  "type": "Feature",
  "properties": {
    "iso:country":"US",
    "sg:address":"406 S Grant St",
    "sg:city":"Lake Mills",
    "sg:classifiers":[
        {
            "category":"Organizations",
            "subcategory":"Religious Organization",
            "type":"Services"
        }
    ],
    "sg:phone":"+1 641 592 0022",
    "sg:postcode":"50450",
    "sg:province":"IA",
    "sg:tags":[
        "church"
    ],
    "wof:name":"St Patrick's Catholic Church",
    "wof:placetype":"venue"
},
  "geometry": {"coordinates":[-93.53131500000001,43.415669],"type":"Point"}
}