{
  "type": "Feature",
  "properties": {
    "iso:country":"US",
    "sg:address":"4439 Indigo Ave",
    "sg:city":"St Ansgar",
    "sg:classifiers":[
        {
            "category":"Wholesale",
            "subcategory":"Construction Materials",
            "type":"Manufacturing & Wholesale Goods"
        }
    ],
    "sg:phone":"+1 641 713 4514",
    "sg:postcode":"50472",
    "sg:province":"IA",
    "sg:tags":[
        "sand",
        "gravel"
    ],
    "wof:name":"L R Falk Construction Co",
    "wof:placetype":"venue"
},
  "geometry": {"coordinates":[-92.870558,43.423524],"type":"Point"}
}