{
  "type": "Feature",
  "properties": {
    "iso:country":"US",
    "sg:address":"245 W 1st St",
    "sg:city":"Dubuque",
    "sg:classifiers":[
        {
            "category":"Shopping",
            "subcategory":"Jewelry",
            "type":"Retail Goods"
        }
    ],
    "sg:phone":"+1 563 583 5249",
    "sg:postcode":"52001",
    "sg:province":"IA",
    "sg:tags":[
        "jeweler"
    ],
    "wof:name":"Jewelry Box",
    "wof:placetype":"venue"
},
  "geometry": {"coordinates":[-90.664767,42.49494],"type":"Point"}
}