{
  "type": "Feature",
  "properties": {
    "iso:country":"US",
    "sg:address":"227 Leclaire St",
    "sg:city":"Davenport",
    "sg:classifiers":[
        {
            "category":"Restaurant",
            "type":"Food & Drink"
        }
    ],
    "sg:phone":"+1 563 322 8339",
    "sg:postcode":"52803",
    "sg:province":"IA",
    "wof:name":"India Palace",
    "wof:placetype":"venue"
},
  "geometry": {"coordinates":[-90.568214,41.522411],"type":"Point"}
}