{
  "type": "Feature",
  "properties": {
    "addr:full":"2510 Central Ave Estherville IA 51334",
    "addr:housenumber":"2510",
    "addr:postcode":"51334",
    "addr:street":"Central Ave",
    "iso:country":"US",
    "sg:address":"2510 Central Ave",
    "sg:city":"Estherville",
    "sg:classifiers":[
        {
            "category":"Restaurant",
            "type":"Food & Drink"
        }
    ],
    "sg:menulink":"http://www.allmenus.com/ia/estherville/202694-mcdonalds/menu/",
    "sg:postcode":"51334",
    "sg:province":"IA",
    "sg:tags":[
        "burger",
        "american"
    ],
    "wof:name":"McDonald's",
    "wof:placetype":"venue"
},
  "geometry": {"coordinates":[-94.810311,43.399327],"type":"Point"}
}