{
  "type": "Feature",
  "properties": {
    "iso:country":"US",
    "sg:address":"601 High St",
    "sg:city":"Keokuk",
    "sg:classifiers":[
        {
            "category":"Building & Trades",
            "subcategory":"Construction",
            "type":"Services"
        }
    ],
    "sg:phone":"+1 319 524 2093",
    "sg:postcode":"52632",
    "sg:province":"IA",
    "sg:tags":[
        "maintenance",
        "contractor"
    ],
    "wof:name":"Midwest Maintenance Svc",
    "wof:placetype":"venue"
},
  "geometry": {"coordinates":[-91.38181299999999,40.399262],"type":"Point"}
}