{
  "type": "Feature",
  "properties": {
    "addr:full":"603 B St Corning IA 50839",
    "addr:housenumber":"603",
    "addr:postcode":"50839",
    "addr:street":"B St",
    "iso:country":"US",
    "sg:address":"603 B St",
    "sg:city":"Corning",
    "sg:classifiers":[
        {
            "category":"Farming",
            "subcategory":"Livestock Farm",
            "type":"Manufacturing & Wholesale Goods"
        },
        {
            "category":"Retail",
            "subcategory":"Animal Services",
            "type":"Services"
        }
    ],
    "sg:phone":"+1 641 322 4802",
    "sg:postcode":"50839",
    "sg:province":"IA",
    "sg:tags":[
        "ranch"
    ],
    "wof:name":"One Sky Ranch",
    "wof:placetype":"venue"
},
  "geometry": {"coordinates":[-94.821158,41.049877],"type":"Point"}
}