{
  "type": "Feature",
  "properties": {
    "iso:country":"US",
    "sg:address":"5615 E Dunkerton Rd",
    "sg:city":"Waterloo",
    "sg:classifiers":[
        {
            "category":"Freight",
            "type":"Transportation"
        }
    ],
    "sg:phone":"+1 319 822 4647",
    "sg:postcode":"50703",
    "sg:province":"IA",
    "sg:tags":[
        "operator",
        "local",
        "trucking"
    ],
    "wof:name":"Salisburys Trucking",
    "wof:placetype":"venue"
},
  "geometry": {"coordinates":[-92.22653800000001,42.570453],"type":"Point"}
}