{
  "type": "Feature",
  "properties": {
    "addr:full":"4444 1st Ave NE Cedar Rapids IA 52402",
    "addr:housenumber":"4444",
    "addr:postcode":"52402",
    "addr:street":"1St Ave Ne",
    "iso:country":"US",
    "sg:address":"4444 1st Ave NE",
    "sg:city":"Cedar Rapids",
    "sg:classifiers":[
        {
            "category":"Shopping",
            "subcategory":"Clothing, Apparel, & Fashions",
            "type":"Retail Goods"
        }
    ],
    "sg:phone":"+1 319 393 0170",
    "sg:postcode":"52402",
    "sg:province":"IA",
    "sg:tags":[
        "sport",
        "wear",
        "sportswear"
    ],
    "wof:name":"Sportswear Retail",
    "wof:placetype":"venue"
},
  "geometry": {"coordinates":[-91.627116,42.023241],"type":"Point"}
}