{
  "type": "Feature",
  "properties": {
    "addr:full":"1448 190th St Shenandoah IA 51601",
    "addr:housenumber":"1448",
    "addr:postcode":"51601",
    "addr:street":"190Th St",
    "iso:country":"US",
    "sg:address":"1448 190th St",
    "sg:city":"Shenandoah",
    "sg:classifiers":[
        {
            "category":"Farming",
            "subcategory":"Livestock Farm",
            "type":"Manufacturing & Wholesale Goods"
        }
    ],
    "sg:phone":"+1 712 246 3537",
    "sg:postcode":"51601",
    "sg:province":"IA",
    "sg:tags":[
        "hog",
        "or",
        "feedlot"
    ],
    "wof:name":"Fischer Farms",
    "wof:placetype":"venue"
},
  "geometry": {"coordinates":[-95.299297,40.7715],"type":"Point"}
}