{
  "type": "Feature",
  "properties": {
    "addr:full":"617 Pennsylvania Ave Story City IA 50248",
    "addr:housenumber":"617",
    "addr:postcode":"50248",
    "addr:street":"Pennsylvania Ave",
    "iso:country":"US",
    "sg:address":"617 Pennsylvania Ave",
    "sg:city":"Story City",
    "sg:classifiers":[
        {
            "category":"Organizations",
            "subcategory":"Non-profit Organization",
            "type":"Services"
        }
    ],
    "sg:phone":"+1 515 733 4917",
    "sg:postcode":"50248",
    "sg:province":"IA",
    "wof:name":"Story City Senior Citizens Ctr",
    "wof:placetype":"venue"
},
  "geometry": {"coordinates":[-93.596037,42.187442],"type":"Point"}
}