{
  "type": "Feature",
  "properties": {
    "iso:country":"US",
    "sg:address":"1001 25th Ave",
    "sg:city":"Coralville",
    "sg:classifiers":[
        {
            "category":"Real Estate",
            "subcategory":"Real Estate Operator",
            "type":"Services"
        }
    ],
    "sg:phone":"+1 319 351 2505",
    "sg:postcode":"52241",
    "sg:province":"IA",
    "sg:tags":[
        "apartment"
    ],
    "wof:name":"Gregory Apartments",
    "wof:placetype":"venue"
},
  "geometry": {"coordinates":[-91.603443,41.6887],"type":"Point"}
}