{
  "type": "Feature",
  "properties": {
    "addr:full":"610 W 4th St Storm Lake IA 50588",
    "addr:housenumber":"610",
    "addr:postcode":"50588",
    "addr:street":"W 4Th St",
    "iso:country":"US",
    "sg:address":"610 W 4th St",
    "sg:city":"Storm Lake",
    "sg:classifiers":[
        {
            "category":"Professional",
            "subcategory":"Management & Consulting",
            "type":"Services"
        }
    ],
    "sg:phone":"+1 712 749 2416",
    "sg:postcode":"50588",
    "sg:province":"IA",
    "wof:name":"Camburn Artegal",
    "wof:placetype":"venue"
},
  "geometry": {"coordinates":[-95.207864,42.642453],"type":"Point"}
}