{
  "type": "Feature",
  "properties": {
    "iso:country":"US",
    "sg:address":"77 16th Ave SW",
    "sg:city":"Cedar Rapids",
    "sg:classifiers":[
        {
            "category":"Real Estate",
            "subcategory":"Real Estate Agent",
            "type":"Services"
        }
    ],
    "sg:phone":"+1 319 365 4144",
    "sg:postcode":"52404",
    "sg:province":"IA",
    "wof:name":"Krouse Real Estate",
    "wof:placetype":"venue"
},
  "geometry": {"coordinates":[-91.660646,41.965184],"type":"Point"}
}