{
  "type": "Feature",
  "properties": {
    "iso:country":"US",
    "sg:address":"1655 230th St",
    "sg:city":"Tipton",
    "sg:phone":"+1 563 886 2041",
    "sg:postcode":"52772",
    "sg:province":"IA",
    "sg:tags":[
        "farm",
        "corn",
        "soybean"
    ],
    "wof:name":"Bruce Kroeger",
    "wof:placetype":"venue"
},
  "geometry": {"coordinates":[-91.041543,41.757334],"type":"Point"}
}