{
  "type": "Feature",
  "properties": {
    "iso:country":"US",
    "sg:address":"210 N Maple St",
    "sg:city":"Creston",
    "sg:classifiers":[
        {
            "category":"Shopping",
            "subcategory":"Books",
            "type":"Retail Goods"
        }
    ],
    "sg:phone":"+1 641 782 8822",
    "sg:postcode":"50801",
    "sg:province":"IA",
    "sg:tags":[
        "new",
        "used"
    ],
    "wof:name":"Bookstore",
    "wof:placetype":"venue"
},
  "geometry": {"coordinates":[-94.36277200000001,41.059589],"type":"Point"}
}