{
  "type": "Feature",
  "properties": {
    "addr:full":"605 E 13th St Spencer IA 51301",
    "addr:housenumber":"605",
    "addr:postcode":"51301",
    "addr:street":"E 13Th St",
    "iso:country":"US",
    "sg:address":"605 E 13th St",
    "sg:city":"Spencer",
    "sg:classifiers":[
        {
            "category":"Farming",
            "subcategory":"Farm",
            "type":"Manufacturing & Wholesale Goods"
        }
    ],
    "sg:phone":"+1 712 262 7822",
    "sg:postcode":"51301",
    "sg:province":"IA",
    "sg:tags":[
        "crop",
        "general"
    ],
    "wof:name":"Terraapro Consulting",
    "wof:placetype":"venue"
},
  "geometry": {"coordinates":[-95.13678299999999,43.151182],"type":"Point"}
}