{
  "type": "Feature",
  "properties": {
    "addr:full":"134 Main St Merrill IA 51038",
    "addr:housenumber":"134",
    "addr:postcode":"51038",
    "addr:street":"Main St",
    "iso:country":"US",
    "sg:address":"134 Main St",
    "sg:city":"Merrill",
    "sg:classifiers":[
        {
            "category":"Government",
            "subcategory":"Post Office",
            "type":"Public Place"
        }
    ],
    "sg:phone":"+1 712 938 2325",
    "sg:postcode":"51038",
    "sg:province":"IA",
    "wof:name":"US Post Office",
    "wof:placetype":"venue"
},
  "geometry": {"coordinates":[-96.247749,42.719936],"type":"Point"}
}