{
  "type": "Feature",
  "properties": {
    "iso:country":"US",
    "sg:address":"125 W Salem Ave",
    "sg:city":"Indianola",
    "sg:classifiers":[
        {
            "category":"Shopping",
            "subcategory":"Clothing, Apparel, & Fashions",
            "type":"Retail Goods"
        }
    ],
    "sg:phone":"+1 515 961 2105",
    "sg:postcode":"50125",
    "sg:province":"IA",
    "sg:tags":[
        "shop",
        "bridal"
    ],
    "sg:website":"www.partypalisades.com",
    "wof:name":"Party Palisades",
    "wof:placetype":"venue"
},
  "geometry": {"coordinates":[-93.561212,41.360233],"type":"Point"}
}