{
  "type": "Feature",
  "properties": {
    "addr:full":"24852 305th St Burnside IA 50521",
    "addr:housenumber":"24852",
    "addr:postcode":"50521",
    "addr:street":"305Th St",
    "iso:country":"US",
    "sg:address":"24852 305th St",
    "sg:city":"Burnside",
    "sg:classifiers":[
        {
            "category":"Building & Trades",
            "subcategory":"Plumbing",
            "type":"Services"
        }
    ],
    "sg:phone":"+1 515 359 2903",
    "sg:postcode":"50521",
    "sg:province":"IA",
    "sg:tags":[
        "tank",
        "septic"
    ],
    "wof:name":"Kahl Construction Co",
    "wof:placetype":"venue"
},
  "geometry": {"coordinates":[-94.108394,42.346953],"type":"Point"}
}