{
  "type": "Feature",
  "properties": {
    "iso:country":"US",
    "sg:address":"128 E 2nd St",
    "sg:city":"Muscatine",
    "sg:classifiers":[
        {
            "category":"Social Services",
            "type":"Services"
        }
    ],
    "sg:phone":"+1 563 264 0880",
    "sg:postcode":"52761",
    "sg:province":"IA",
    "sg:tags":[
        "organization",
        "welfare"
    ],
    "wof:name":"Proteus Inc",
    "wof:placetype":"venue"
},
  "geometry": {"coordinates":[-91.044803,41.42168],"type":"Point"}
}