{
  "type": "Feature",
  "properties": {
    "iso:country":"US",
    "sg:address":"425 S 2nd St",
    "sg:city":"Ames",
    "sg:classifiers":[
        {
            "category":"Insurance",
            "subcategory":"Insurance Agent",
            "type":"Services"
        }
    ],
    "sg:phone":"+1 515 232 3715",
    "sg:postcode":"50010",
    "sg:province":"IA",
    "wof:name":"Massachusetts Mutual-Blue Chip",
    "wof:placetype":"venue"
},
  "geometry": {"coordinates":[-93.615865,42.021707],"type":"Point"}
}