{
  "type": "Feature",
  "properties": {
    "iso:country":"US",
    "sg:address":"56279 Oak Ridge Rd",
    "sg:city":"Story City",
    "sg:phone":"+1 515 733 2682",
    "sg:postcode":"50248",
    "sg:province":"IA",
    "sg:tags":[
        "farm",
        "corn",
        "soybean"
    ],
    "wof:name":"Larry Fuhrman",
    "wof:placetype":"venue"
},
  "geometry": {"coordinates":[-93.57511700000001,42.20134],"type":"Point"}
}