{
  "type": "Feature",
  "properties": {
    "addr:full":"4911 Ironwood Ave Orange City IA 51041",
    "addr:housenumber":"4911",
    "addr:postcode":"51041",
    "addr:street":"Ironwood Ave",
    "iso:country":"US",
    "sg:address":"4911 Ironwood Ave",
    "sg:city":"Orange City",
    "sg:classifiers":[
        {
            "category":"Farming",
            "subcategory":"Dairy Farm",
            "type":"Manufacturing & Wholesale Goods"
        }
    ],
    "sg:phone":"+1 712 737 4120",
    "sg:postcode":"51041",
    "sg:province":"IA",
    "wof:name":"William Aberson",
    "wof:placetype":"venue"
},
  "geometry": {"coordinates":[-96.076185,42.937594],"type":"Point"}
}