{
  "type": "Feature",
  "properties": {
    "iso:country":"US",
    "sg:address":"8 E Main St",
    "sg:city":"Marshalltown",
    "sg:classifiers":[
        {
            "category":"Restaurant",
            "type":"Food & Drink"
        }
    ],
    "sg:phone":"+1 641 752 1375",
    "sg:postcode":"50158",
    "sg:province":"IA",
    "sg:tags":[
        "eating"
    ],
    "wof:name":"Angstman Inc",
    "wof:placetype":"venue"
},
  "geometry": {"coordinates":[-92.912874,42.049236],"type":"Point"}
}