{
  "type": "Feature",
  "properties": {
    "addr:full":"22974 Quail Ave Clarksville IA 50619",
    "addr:housenumber":"22974",
    "addr:postcode":"50619",
    "addr:street":"Quail Ave",
    "iso:country":"US",
    "sg:address":"22974 Quail Ave",
    "sg:city":"Clarksville",
    "sg:phone":"+1 319 278 1004",
    "sg:postcode":"50619",
    "sg:province":"IA",
    "sg:tags":[
        "hog",
        "f",
        "farm",
        "corn",
        "crop",
        "field",
        "soybean",
        "or",
        "feedlot"
    ],
    "wof:name":"Johnson Randal",
    "wof:placetype":"venue"
},
  "geometry": {"coordinates":[-92.71221199999999,42.716293],"type":"Point"}
}