{
  "type": "Feature",
  "properties": {
    "iso:country":"US",
    "sg:address":"1813 Briarwood Ln",
    "sg:city":"Muscatine",
    "sg:classifiers":[
        {
            "category":"Manufacturing",
            "subcategory":"Signs",
            "type":"Manufacturing & Wholesale Goods"
        }
    ],
    "sg:phone":"+1 563 263 1093",
    "sg:postcode":"52761",
    "sg:province":"IA",
    "sg:tags":[
        "specialty",
        "mfg"
    ],
    "wof:name":"Artistic Signs",
    "wof:placetype":"venue"
},
  "geometry": {"coordinates":[-91.056577,41.435638],"type":"Point"}
}