{
  "type": "Feature",
  "properties": {
    "iso:country":"US",
    "sg:address":"20934 92nd St",
    "sg:city":"Maquoketa",
    "sg:classifiers":[
        {
            "category":"Home & Garden",
            "subcategory":"Home Furnishings",
            "type":"Retail Goods"
        }
    ],
    "sg:phone":"+1 563 652 3031",
    "sg:postcode":"52060",
    "sg:province":"IA",
    "sg:tags":[
        "fireplace"
    ],
    "wof:name":"Great River Stove Co",
    "wof:placetype":"venue"
},
  "geometry": {"coordinates":[-90.658101,42.113032],"type":"Point"}
}