{
  "type": "Feature",
  "properties": {
    "addr:full":"1761 290 Ave Sidney IA 51652",
    "addr:housenumber":"1761",
    "addr:postcode":"51652",
    "addr:street":"290 Ave",
    "iso:country":"US",
    "sg:address":"1761 290 Ave",
    "sg:city":"Sidney",
    "sg:phone":"+1 712 374 2397",
    "sg:postcode":"51652",
    "sg:province":"IA",
    "sg:tags":[
        "farm",
        "corn",
        "soybean"
    ],
    "wof:name":"Helen Maher",
    "wof:placetype":"venue"
},
  "geometry": {"coordinates":[-95.63313599999999,40.867886],"type":"Point"}
}