{
  "type": "Feature",
  "properties": {
    "addr:full":"1609 3rd Ave S Denison IA 51442",
    "addr:housenumber":"1609",
    "addr:postcode":"51442",
    "addr:street":"3Rd Ave S",
    "iso:country":"US",
    "sg:address":"1609 3rd Ave S",
    "sg:city":"Denison",
    "sg:classifiers":[
        {
            "category":"Organizations",
            "subcategory":"Religious Organization",
            "type":"Services"
        }
    ],
    "sg:phone":"+1 712 263 3457",
    "sg:postcode":"51442",
    "sg:province":"IA",
    "wof:name":"Church of Christ",
    "wof:placetype":"venue"
},
  "geometry": {"coordinates":[-95.349116,42.013323],"type":"Point"}
}