{
  "type": "Feature",
  "properties": {
    "addr:full":"984 510th Ave Montezuma IA 50171",
    "addr:housenumber":"984",
    "addr:postcode":"50171",
    "addr:street":"510Th Ave",
    "iso:country":"US",
    "sg:address":"984 510th Ave",
    "sg:city":"Montezuma",
    "sg:classifiers":[
        {
            "category":"Manufacturing",
            "subcategory":"Lumber",
            "type":"Manufacturing & Wholesale Goods"
        }
    ],
    "sg:phone":"+1 641 623 5323",
    "sg:postcode":"50171",
    "sg:province":"IA",
    "sg:tags":[
        "mill",
        "sawmill"
    ],
    "wof:name":"Gabel's Sawmill",
    "wof:placetype":"venue"
},
  "geometry": {"coordinates":[-92.58876600000001,41.552426],"type":"Point"}
}