{
  "type": "Feature",
  "properties": {
    "addr:full":"29058 510th Ave Kelley IA 50134",
    "addr:housenumber":"29058",
    "addr:postcode":"50134",
    "addr:street":"510Th Ave",
    "iso:country":"US",
    "sg:address":"29058 510th Ave",
    "sg:city":"Kelley",
    "sg:classifiers":[
        {
            "category":"Manufacturing",
            "subcategory":"Tools & Machinery",
            "type":"Manufacturing & Wholesale Goods"
        }
    ],
    "sg:phone":"+1 515 203 6943",
    "sg:postcode":"50134",
    "sg:province":"IA",
    "sg:tags":[
        "industrial",
        "mfg"
    ],
    "wof:name":"Hurst & Associates Inc",
    "wof:placetype":"venue"
},
  "geometry": {"coordinates":[-93.678755,41.935295],"type":"Point"}
}