{
  "type": "Feature",
  "properties": {
    "iso:country":"US",
    "sg:address":"403 S State St",
    "sg:city":"Hubbard",
    "sg:classifiers":[
        {
            "category":"Health Services",
            "subcategory":"Doctor",
            "type":"Services"
        }
    ],
    "sg:phone":"+1 641 864 3264",
    "sg:postcode":"50122",
    "sg:province":"IA",
    "sg:tags":[
        "physician",
        "surgeon"
    ],
    "wof:name":"Hubbard Care Ctr",
    "wof:placetype":"venue"
},
  "geometry": {"coordinates":[-93.29033200000001,42.300807],"type":"Point"}
}