{
  "type": "Feature",
  "properties": {
    "iso:country":"US",
    "sg:address":"1901 Morningside Ave",
    "sg:city":"Sioux City",
    "sg:classifiers":[
        {
            "category":"Banks & Credit Unions",
            "subcategory":"Bank",
            "type":"Services"
        }
    ],
    "sg:phone":"+1 712 276 5333",
    "sg:postcode":"51106",
    "sg:province":"IA",
    "sg:website":"www.morningsidebank.com",
    "wof:name":"Morningside Bank & Trust",
    "wof:placetype":"venue"
},
  "geometry": {"coordinates":[-96.35600599999999,42.470774],"type":"Point"}
}