{
  "type": "Feature",
  "properties": {
    "iso:country":"US",
    "sg:address":"1916 S 12th St",
    "sg:city":"Council Bluffs",
    "sg:classifiers":[
        {
            "category":"Freight",
            "type":"Transportation"
        }
    ],
    "sg:phone":"+1 712 322 0600",
    "sg:postcode":"51501",
    "sg:province":"IA",
    "sg:tags":[
        "operator",
        "local",
        "trucking"
    ],
    "wof:name":"Ron Amaral Trucking",
    "wof:placetype":"venue"
},
  "geometry": {"coordinates":[-95.861994,41.242845],"type":"Point"}
}