{
  "type": "Feature",
  "properties": {
    "iso:country":"US",
    "sg:address":"1355 H Ave",
    "sg:city":"Ogden",
    "sg:classifiers":[
        {
            "category":"Professional",
            "type":"Services"
        }
    ],
    "sg:phone":"+1 515 275 2411",
    "sg:postcode":"50212",
    "sg:province":"IA",
    "wof:name":"Roma Land Inc",
    "wof:placetype":"venue"
},
  "geometry": {"coordinates":[-94.02796499999999,42.014787],"type":"Point"}
}