{
  "type": "Feature",
  "properties": {
    "iso:country":"US",
    "sg:address":"1717 8th Ave N",
    "sg:city":"Humboldt",
    "sg:classifiers":[
        {
            "category":"Retail",
            "subcategory":"Funeral Services",
            "type":"Services"
        }
    ],
    "sg:phone":"+1 515 332 4695",
    "sg:postcode":"50548",
    "sg:province":"IA",
    "wof:name":"Sievers Laufersweiler Fnrl HM",
    "wof:placetype":"venue"
},
  "geometry": {"coordinates":[-94.233298,42.730626],"type":"Point"}
}