{
  "type": "Feature",
  "properties": {
    "iso:country":"US",
    "sg:address":"2800 US Hwy 6",
    "sg:city":"Iowa City",
    "sg:classifiers":[
        {
            "category":"Manufacturing",
            "subcategory":"Printing",
            "type":"Manufacturing & Wholesale Goods"
        }
    ],
    "sg:phone":"+1 319 337 9623",
    "sg:postcode":"52240",
    "sg:province":"IA",
    "sg:tags":[
        "printer"
    ],
    "sg:website":"www.bankersadvertising.com",
    "wof:name":"Economy Advertising Co",
    "wof:placetype":"venue"
},
  "geometry": {"coordinates":[-91.493945,41.633353],"type":"Point"}
}