{
  "type": "Feature",
  "properties": {
    "iso:country":"US",
    "sg:address":"7625 Office Plaza Dr N",
    "sg:city":"West Des Moines",
    "sg:classifiers":[
        {
            "category":"Travel",
            "subcategory":"Hotels & Motels",
            "type":"Entertainment"
        }
    ],
    "sg:phone":"+1 515 221 0001",
    "sg:postcode":"50266",
    "sg:province":"IA",
    "sg:website":"www.candlewoodsuites.com",
    "wof:name":"Candlewood Suites",
    "wof:placetype":"venue"
},
  "geometry": {"coordinates":[-93.809867,41.58658],"type":"Point"}
}