{
  "type": "Feature",
  "properties": {
    "addr:full":"709 Grandview Ave Muscatine IA 52761",
    "addr:housenumber":"709",
    "addr:postcode":"52761",
    "addr:street":"Grandview Ave",
    "iso:country":"US",
    "sg:address":"709 Grandview Ave",
    "sg:city":"Muscatine",
    "sg:classifiers":[
        {
            "category":"Food & Beverages",
            "subcategory":"Groceries & Convenience Stores",
            "type":"Retail Goods"
        }
    ],
    "sg:phone":"+1 563 263 4956",
    "sg:postcode":"52761",
    "sg:province":"IA",
    "wof:name":"Kum & Go",
    "wof:placetype":"venue"
},
  "geometry": {"coordinates":[-91.062938,41.409462],"type":"Point"}
}