{
  "type": "Feature",
  "properties": {
    "iso:country":"US",
    "sg:address":"1425 Morgan St",
    "sg:city":"Keokuk",
    "sg:classifiers":[
        {
            "category":"Building & Trades",
            "subcategory":"Equipment Rental",
            "type":"Services"
        }
    ],
    "sg:phone":"+1 319 526 6365",
    "sg:postcode":"52632",
    "sg:province":"IA",
    "sg:tags":[
        "medical"
    ],
    "wof:name":"Keokuk Area Medical Eqp & Sup",
    "wof:placetype":"venue"
},
  "geometry": {"coordinates":[-91.38709900000001,40.406044],"type":"Point"}
}