{
  "type": "Feature",
  "properties": {
    "addr:full":"2318 Johnson St Keokuk IA 52632",
    "addr:housenumber":"2318",
    "addr:postcode":"52632",
    "addr:street":"Johnson St",
    "iso:country":"US",
    "sg:address":"2318 Johnson St",
    "sg:city":"Keokuk",
    "sg:classifiers":[
        {
            "category":"Building & Trades",
            "subcategory":"Construction",
            "type":"Services"
        }
    ],
    "sg:phone":"+1 319 524 7755",
    "sg:postcode":"52632",
    "sg:province":"IA",
    "sg:tags":[
        "painter"
    ],
    "wof:name":"Hall Painting & Decorating",
    "wof:placetype":"venue"
},
  "geometry": {"coordinates":[-91.39908200000001,40.409087],"type":"Point"}
}