{
  "type": "Feature",
  "properties": {
    "iso:country":"US",
    "sg:address":"404 8th St SW",
    "sg:city":"Altoona",
    "sg:classifiers":[
        {
            "category":"Retail",
            "subcategory":"Car Wash",
            "type":"Services"
        }
    ],
    "sg:phone":"+1 515 967 0923",
    "sg:postcode":"50009",
    "sg:province":"IA",
    "sg:tags":[
        "polishing",
        "washing"
    ],
    "wof:name":"Super Wash",
    "wof:placetype":"venue"
},
  "geometry": {"coordinates":[-93.467923,41.644013],"type":"Point"}
}