{
  "type": "Feature",
  "properties": {
    "addr:full":"1521 18th St Spirit Lake IA 51360",
    "addr:housenumber":"1521",
    "addr:postcode":"51360",
    "addr:street":"18Th St",
    "iso:country":"US",
    "sg:address":"1521 18th St",
    "sg:city":"Spirit Lake",
    "sg:classifiers":[
        {
            "category":"Home & Garden",
            "subcategory":"Furniture",
            "type":"Retail Goods"
        }
    ],
    "sg:phone":"+1 712 336 1000",
    "sg:postcode":"51360",
    "sg:province":"IA",
    "wof:name":"A Thousand Baskets",
    "wof:placetype":"venue"
},
  "geometry": {"coordinates":[-95.11081299999999,43.422516],"type":"Point"}
}