{
  "type": "Feature",
  "properties": {
    "iso:country":"US",
    "sg:address":"2023 NW 92nd Ct",
    "sg:city":"Clive",
    "sg:classifiers":[
        {
            "category":"Wholesale",
            "subcategory":"Medical Equipment & Supplies",
            "type":"Manufacturing & Wholesale Goods"
        }
    ],
    "sg:phone":"+1 515 223 4138",
    "sg:postcode":"50325",
    "sg:province":"IA",
    "sg:tags":[
        "hospital"
    ],
    "wof:name":"Kinetic Concepts Inc",
    "wof:placetype":"venue"
},
  "geometry": {"coordinates":[-93.743145,41.609643],"type":"Point"}
}