{
  "type": "Feature",
  "properties": {
    "iso:country":"US",
    "sg:address":"111 W White St",
    "sg:city":"Preston",
    "sg:classifiers":[
        {
            "category":"Professional",
            "subcategory":"Advertising",
            "type":"Services"
        }
    ],
    "sg:phone":"+1 563 689 6851",
    "sg:postcode":"52069",
    "sg:province":"IA",
    "sg:tags":[
        "agency",
        "specialty"
    ],
    "wof:name":"Dean Budde",
    "wof:placetype":"venue"
},
  "geometry": {"coordinates":[-90.39462899999999,42.05253],"type":"Point"}
}