{
  "type": "Feature",
  "properties": {
    "addr:full":"4994 Barnes City Rd Montezuma IA 50171",
    "addr:housenumber":"4994",
    "addr:postcode":"50171",
    "addr:street":"Barnes City Rd",
    "iso:country":"US",
    "sg:address":"4994 Barnes City Rd",
    "sg:city":"Montezuma",
    "sg:classifiers":[
        {
            "category":"Real Estate",
            "subcategory":"Real Estate Operator",
            "type":"Services"
        }
    ],
    "sg:phone":"+1 641 623 3658",
    "sg:postcode":"50171",
    "sg:province":"IA",
    "sg:tags":[
        "property",
        "lessor"
    ],
    "wof:name":"Larry Huff",
    "wof:placetype":"venue"
},
  "geometry": {"coordinates":[-92.48942099999999,41.567511],"type":"Point"}
}