{
  "type": "Feature",
  "properties": {
    "iso:country":"US",
    "sg:address":"909 W Main St",
    "sg:city":"Manchester",
    "sg:classifiers":[
        {
            "category":"Banks & Credit Unions",
            "subcategory":"Bank",
            "type":"Services"
        }
    ],
    "sg:phone":"+1 563 927 3159",
    "sg:postcode":"52057",
    "sg:province":"IA",
    "sg:tags":[
        "loan"
    ],
    "wof:name":"Farm Credit Svc Of America",
    "wof:placetype":"venue"
},
  "geometry": {"coordinates":[-91.46957999999999,42.483918],"type":"Point"}
}