{
  "type": "Feature",
  "properties": {
    "iso:country":"US",
    "sg:address":"131 Roosevelt St",
    "sg:city":"Alburnett",
    "sg:classifiers":[
        {
            "category":"Education",
            "subcategory":"School",
            "type":"Public Place"
        }
    ],
    "sg:phone":"+1 319 842 2261",
    "sg:postcode":"52202",
    "sg:province":"IA",
    "wof:name":"Alburnett High School",
    "wof:placetype":"venue"
},
  "geometry": {"coordinates":[-91.620386,42.149538],"type":"Point"}
}