{
  "type": "Feature",
  "properties": {
    "addr:full":"108 W Broadway Ave Fairfield IA 52556",
    "addr:housenumber":"108",
    "addr:postcode":"52556",
    "addr:street":"W Broadway Ave",
    "iso:country":"US",
    "sg:address":"108 W Broadway Ave",
    "sg:city":"Fairfield",
    "sg:classifiers":[
        {
            "category":"Professional",
            "subcategory":"Advertising",
            "type":"Services"
        }
    ],
    "sg:phone":"+1 641 472 4852",
    "sg:postcode":"52556",
    "sg:province":"IA",
    "wof:name":"Iowa Source",
    "wof:placetype":"venue"
},
  "geometry": {"coordinates":[-91.964491,41.007544],"type":"Point"}
}