{
  "type": "Feature",
  "properties": {
    "iso:country":"US",
    "sg:address":"1011 E Platt St",
    "sg:city":"Maquoketa",
    "sg:classifiers":[
        {
            "category":"Retail",
            "subcategory":"Auto Repair",
            "type":"Services"
        }
    ],
    "sg:phone":"+1 563 652 5913",
    "sg:postcode":"52060",
    "sg:province":"IA",
    "sg:tags":[
        "repairing",
        "automobile"
    ],
    "wof:name":"C & R Tires",
    "wof:placetype":"venue"
},
  "geometry": {"coordinates":[-90.654568,42.069101],"type":"Point"}
}