{
  "type": "Feature",
  "properties": {
    "iso:country":"US",
    "sg:address":"604 Mulberry St",
    "sg:city":"Waterloo",
    "sg:classifiers":[
        {
            "category":"Communications",
            "type":"Services"
        }
    ],
    "sg:phone":"+1 319 433 0271",
    "sg:postcode":"50703",
    "sg:province":"IA",
    "wof:name":"Total Choice Comm Inc",
    "wof:placetype":"venue"
},
  "geometry": {"coordinates":[-92.333065,42.4991],"type":"Point"}
}