{
  "type": "Feature",
  "properties": {
    "iso:country":"US",
    "sg:address":"2112 NE 105th Pl",
    "sg:city":"Ankeny",
    "sg:classifiers":[
        {
            "category":"Manufacturing",
            "subcategory":"Pottery",
            "type":"Manufacturing & Wholesale Goods"
        }
    ],
    "sg:phone":"+1 515 964 0827",
    "sg:postcode":"50021",
    "sg:province":"IA",
    "sg:tags":[
        "product",
        "mfg"
    ],
    "wof:name":"Morgan Creek Pottery",
    "wof:placetype":"venue"
},
  "geometry": {"coordinates":[-93.58120099999999,41.752787],"type":"Point"}
}