{
  "type": "Feature",
  "properties": {
    "iso:country":"US",
    "sg:address":"2591 Heartland Pl",
    "sg:city":"Coralville",
    "sg:classifiers":[
        {
            "category":"Ice Cream",
            "type":"Food & Drink"
        }
    ],
    "sg:menulink":"http://www.allmenus.com/ia/clear-creek/182778-culvers/menu/",
    "sg:phone":"+1 319 545 8255",
    "sg:postcode":"52241",
    "sg:province":"IA",
    "sg:tags":[
        "burger",
        "american"
    ],
    "wof:name":"Culver's",
    "wof:placetype":"venue"
},
  "geometry": {"coordinates":[-91.61005299999999,41.700317],"type":"Point"}
}