{
  "type": "Feature",
  "properties": {
    "iso:country":"US",
    "sg:address":"408 Church St",
    "sg:city":"Royal",
    "sg:classifiers":[
        {
            "category":"Organizations",
            "subcategory":"Religious Organization",
            "type":"Services"
        }
    ],
    "sg:phone":"+1 712 933 2489",
    "sg:postcode":"51357",
    "sg:province":"IA",
    "sg:tags":[
        "church"
    ],
    "wof:name":"United Methodist Church",
    "wof:placetype":"venue"
},
  "geometry": {"coordinates":[-95.28683599999999,43.062584],"type":"Point"}
}