{
  "type": "Feature",
  "properties": {
    "iso:country":"US",
    "sg:address":"413 E Walnut St",
    "sg:city":"Ogden",
    "sg:classifiers":[
        {
            "category":"Professional",
            "subcategory":"Business Services",
            "type":"Services"
        }
    ],
    "sg:phone":"+1 515 275 3030",
    "sg:postcode":"50212",
    "sg:province":"IA",
    "sg:tags":[
        "auctioneer"
    ],
    "wof:name":"Herman Auction Ctr",
    "wof:placetype":"venue"
},
  "geometry": {"coordinates":[-94.02274800000001,42.039132],"type":"Point"}
}