{
  "type": "Feature",
  "properties": {
    "iso:country":"US",
    "sg:address":"325 Chestnut St",
    "sg:city":"Atlantic",
    "sg:classifiers":[
        {
            "category":"Home & Garden",
            "subcategory":"Hardware",
            "type":"Retail Goods"
        }
    ],
    "sg:phone":"+1 712 243 4667",
    "sg:postcode":"50022",
    "sg:province":"IA",
    "wof:name":"Robinson True Value Hardware",
    "wof:placetype":"venue"
},
  "geometry": {"coordinates":[-95.01306599999999,41.407744],"type":"Point"}
}