{
  "type": "Feature",
  "properties": {
    "iso:country":"US",
    "sg:address":"201 Main St",
    "sg:city":"Oxford Junction",
    "sg:classifiers":[
        {
            "category":"Government",
            "subcategory":"Fire Station",
            "type":"Public Place"
        }
    ],
    "sg:phone":"+1 563 826 2879",
    "sg:postcode":"52323",
    "sg:province":"IA",
    "sg:tags":[
        "department"
    ],
    "wof:name":"Oxford Junction Volunteer Fire",
    "wof:placetype":"venue"
},
  "geometry": {"coordinates":[-90.955139,41.98281],"type":"Point"}
}