{
  "type": "Feature",
  "properties": {
    "addr:full":"1100 Nebraska St Sioux City IA 51105",
    "addr:housenumber":"1100",
    "addr:postcode":"51105",
    "addr:street":"Nebraska St",
    "iso:country":"US",
    "sg:address":"1100 Nebraska St",
    "sg:city":"Sioux City",
    "sg:classifiers":[
        {
            "category":"Ice Cream",
            "type":"Food & Drink"
        }
    ],
    "sg:menulink":"http://www.allmenus.com/ia/sioux-city/172766-dairy-queen/menu/",
    "sg:phone":"+1 712 255 9626",
    "sg:postcode":"51105",
    "sg:province":"IA",
    "sg:tags":[
        "burger",
        "american"
    ],
    "wof:name":"Dairy Queen",
    "wof:placetype":"venue"
},
  "geometry": {"coordinates":[-96.403493,42.501827],"type":"Point"}
}