{
  "type": "Feature",
  "properties": {
    "addr:full":"20549 45th St Cresco IA 52136",
    "addr:housenumber":"20549",
    "addr:postcode":"52136",
    "addr:street":"45Th St",
    "iso:country":"US",
    "sg:address":"20549 45th St",
    "sg:city":"Cresco",
    "sg:phone":"+1 563 547 2454",
    "sg:postcode":"52136",
    "sg:province":"IA",
    "sg:tags":[
        "farm",
        "corn",
        "beef",
        "feedlot",
        "cattle"
    ],
    "wof:name":"Lawrence Goetsch",
    "wof:placetype":"venue"
},
  "geometry": {"coordinates":[-92.159965,43.450603],"type":"Point"}
}