{
  "type": "Feature",
  "properties": {
    "iso:country":"US",
    "sg:address":"4005 Merle Hay Rd",
    "sg:city":"Des Moines",
    "sg:classifiers":[
        {
            "category":"Restaurant",
            "type":"Food & Drink"
        }
    ],
    "sg:menulink":"http://www.allmenus.com/ia/des-moines/198288-kfc---kentucky-fried-chicken/menu/",
    "sg:phone":"+1 515 276 7498",
    "sg:postcode":"50310",
    "sg:province":"IA",
    "sg:tags":[
        "american",
        "chicken"
    ],
    "wof:name":"KFC - Kentucky Fried Chicken",
    "wof:placetype":"venue"
},
  "geometry": {"coordinates":[-93.697327,41.633411],"type":"Point"}
}