{
  "type": "Feature",
  "properties": {
    "addr:full":"880 Locust St Dubuque IA 52001",
    "addr:housenumber":"880",
    "addr:postcode":"52001",
    "addr:street":"Locust St",
    "iso:country":"US",
    "sg:address":"880 Locust St",
    "sg:city":"Dubuque",
    "sg:classifiers":[
        {
            "category":"Sports & Exercise",
            "subcategory":"Bowling",
            "type":"Entertainment"
        }
    ],
    "sg:phone":"+1 563 588 2695",
    "sg:postcode":"52001",
    "sg:province":"IA",
    "sg:tags":[
        "center"
    ],
    "wof:name":"Fischer Bowling Lanes",
    "wof:placetype":"venue"
},
  "geometry": {"coordinates":[-90.668341,42.500717],"type":"Point"}
}