{
  "type": "Feature",
  "properties": {
    "iso:country":"US",
    "sg:address":"17104 Gardners Ln",
    "sg:city":"Dubuque",
    "sg:classifiers":[
        {
            "category":"Organizations",
            "subcategory":"Labor Organization",
            "type":"Services"
        }
    ],
    "sg:phone":"+1 563 556 5758",
    "sg:postcode":"52001",
    "sg:province":"IA",
    "wof:name":"H&M Realty Lc",
    "wof:placetype":"venue"
},
  "geometry": {"coordinates":[-90.691756,42.544647],"type":"Point"}
}