{
  "type": "Feature",
  "properties": {
    "iso:country":"US",
    "sg:address":"30386 260th St",
    "sg:city":"Merrill",
    "sg:phone":"+1 712 938 2418",
    "sg:postcode":"51038",
    "sg:province":"IA",
    "sg:tags":[
        "hog",
        "beef",
        "farm",
        "corn",
        "soybean",
        "cattle",
        "or",
        "feedlot"
    ],
    "wof:name":"Jay Dunn",
    "wof:placetype":"venue"
},
  "geometry": {"coordinates":[-96.232174,42.677871],"type":"Point"}
}