{
  "type": "Feature",
  "properties": {
    "iso:country":"US",
    "sg:address":"22 1st St NE",
    "sg:city":"Le Mars",
    "sg:classifiers":[
        {
            "category":"Organizations",
            "subcategory":"Non-profit Organization",
            "type":"Services"
        }
    ],
    "sg:phone":"+1 712 546 7868",
    "sg:postcode":"51031",
    "sg:province":"IA",
    "sg:tags":[
        "information",
        "alcoholism",
        "treatment"
    ],
    "wof:name":"Jackson Recovery Ctr",
    "wof:placetype":"venue"
},
  "geometry": {"coordinates":[-96.16618800000001,42.794203],"type":"Point"}
}