{
  "type": "Feature",
  "properties": {
    "iso:country":"US",
    "sg:address":"2601 120th St NW",
    "sg:city":"Swisher",
    "sg:classifiers":[
        {
            "category":"Food & Beverages",
            "subcategory":"Groceries & Convenience Stores",
            "type":"Retail Goods"
        }
    ],
    "sg:phone":"+1 319 857 4845",
    "sg:postcode":"52338",
    "sg:province":"IA",
    "wof:name":"Swisher Gas-N-Go",
    "wof:placetype":"venue"
},
  "geometry": {"coordinates":[-91.670514,41.847877],"type":"Point"}
}