{
  "type": "Feature",
  "properties": {
    "iso:country":"US",
    "sg:address":"220 N Main St",
    "sg:city":"Davenport",
    "sg:classifiers":[
        {
            "category":"Social Services",
            "type":"Services"
        }
    ],
    "sg:phone":"+1 563 322 4660",
    "sg:postcode":"52801",
    "sg:province":"IA",
    "sg:tags":[
        "organization",
        "welfare"
    ],
    "wof:name":"Variety The Childrens Charity",
    "wof:placetype":"venue"
},
  "geometry": {"coordinates":[-90.575671,41.521629],"type":"Point"}
}