{
  "type": "Feature",
  "properties": {
    "iso:country":"US",
    "sg:address":"2136 Green Bay Rd",
    "sg:city":"Wever",
    "sg:classifiers":[
        {
            "category":"Freight",
            "type":"Transportation"
        }
    ],
    "sg:phone":"+1 319 372 7852",
    "sg:postcode":"52658",
    "sg:province":"IA",
    "sg:tags":[
        "grain",
        "elevator"
    ],
    "sg:website":"www.colusaelevator.com",
    "wof:name":"Colusa Elevator",
    "wof:placetype":"venue"
},
  "geometry": {"coordinates":[-91.190961,40.644329],"type":"Point"}
}