{
  "type": "Feature",
  "properties": {
    "iso:country":"US",
    "sg:address":"104 1st St NW",
    "sg:city":"Farley",
    "sg:classifiers":[
        {
            "category":"Professional",
            "subcategory":"Lawyer & Legal Services",
            "type":"Services"
        }
    ],
    "sg:phone":"+1 563 744 3720",
    "sg:postcode":"52045",
    "sg:province":"IA",
    "sg:tags":[
        "attorney"
    ],
    "wof:name":"Gary Ankeny Law Office",
    "wof:placetype":"venue"
},
  "geometry": {"coordinates":[-90.933447,42.44648],"type":"Point"}
}