{
  "type": "Feature",
  "properties": {
    "iso:country":"US",
    "sg:address":"1215 Melrose Ave",
    "sg:city":"Iowa City",
    "sg:classifiers":[
        {
            "category":"Shopping",
            "subcategory":"Stationery & Office Supplies",
            "type":"Retail Goods"
        }
    ],
    "sg:phone":"+1 319 354 2176",
    "sg:postcode":"52246",
    "sg:province":"IA",
    "wof:name":"Cirrus Imaging Supply",
    "wof:placetype":"venue"
},
  "geometry": {"coordinates":[-91.559281,41.655771],"type":"Point"}
}