{
  "type": "Feature",
  "properties": {
    "addr:full":"809 4th St Sibley IA 51249",
    "addr:housenumber":"809",
    "addr:postcode":"51249",
    "addr:street":"4Th St",
    "iso:country":"US",
    "sg:address":"809 4th St",
    "sg:city":"Sibley",
    "sg:phone":"+1 712 754 2642",
    "sg:postcode":"51249",
    "sg:province":"IA",
    "sg:tags":[
        "farm",
        "soybean"
    ],
    "wof:name":"Curtis Marco",
    "wof:placetype":"venue"
},
  "geometry": {"coordinates":[-95.742446,43.405129],"type":"Point"}
}