{
  "type": "Feature",
  "properties": {
    "addr:full":"614 E Jackson St Shell Rock IA 50670",
    "addr:housenumber":"614",
    "addr:postcode":"50670",
    "addr:street":"E Jackson St",
    "iso:country":"US",
    "sg:address":"614 E Jackson St",
    "sg:city":"Shell Rock",
    "sg:classifiers":[
        {
            "category":"Recreation",
            "type":"Entertainment"
        }
    ],
    "sg:phone":"+1 319 885 6400",
    "sg:postcode":"50670",
    "sg:province":"IA",
    "sg:tags":[
        "pool",
        "swimming"
    ],
    "wof:name":"Shell Rock Swimming Pool",
    "wof:placetype":"venue"
},
  "geometry": {"coordinates":[-92.58372,42.705914],"type":"Point"}
}