{
  "type": "Feature",
  "properties": {
    "iso:country":"US",
    "sg:address":"7012 Madison Ave",
    "sg:city":"Urbandale",
    "sg:classifiers":[
        {
            "category":"Professional",
            "subcategory":"Credit Reporting & Collection",
            "type":"Services"
        }
    ],
    "sg:phone":"+1 515 251 3788",
    "sg:postcode":"50322",
    "sg:province":"IA",
    "sg:tags":[
        "agency"
    ],
    "wof:name":"TDL Svc Inc",
    "wof:placetype":"venue"
},
  "geometry": {"coordinates":[-93.71441900000001,41.6311],"type":"Point"}
}