{
  "type": "Feature",
  "properties": {
    "iso:country":"US",
    "sg:address":"5329 Colt Dr",
    "sg:city":"West Des Moines",
    "sg:classifiers":[
        {
            "category":"Autos & Motor Vehicles",
            "subcategory":"Fuel & Gas Station",
            "type":"Retail Goods"
        }
    ],
    "sg:phone":"+1 515 440 6823",
    "sg:postcode":"50266",
    "sg:province":"IA",
    "sg:tags":[
        "station",
        "gasoline"
    ],
    "wof:name":"Phillips 66 Co",
    "wof:placetype":"venue"
},
  "geometry": {"coordinates":[-93.77913100000001,41.582223],"type":"Point"}
}