{
  "type": "Feature",
  "properties": {
    "iso:country":"US",
    "sg:address":"411 W Clarinda Ave",
    "sg:city":"Shenandoah",
    "sg:classifiers":[
        {
            "category":"Organizations",
            "subcategory":"Non-profit Organization",
            "type":"Services"
        }
    ],
    "sg:phone":"+1 712 246 4832",
    "sg:postcode":"51601",
    "sg:province":"IA",
    "sg:tags":[
        "information",
        "alcoholism",
        "treatment"
    ],
    "wof:name":"Zion Recovery Svc Inc",
    "wof:placetype":"venue"
},
  "geometry": {"coordinates":[-95.370085,40.764266],"type":"Point"}
}