{
  "type": "Feature",
  "properties": {
    "addr:full":"620 Main St Mineola IA 51554",
    "addr:housenumber":"620",
    "addr:postcode":"51554",
    "addr:street":"Main St",
    "iso:country":"US",
    "sg:address":"620 Main St",
    "sg:city":"Mineola",
    "sg:classifiers":[
        {
            "category":"Organizations",
            "subcategory":"Religious Organization",
            "type":"Services"
        }
    ],
    "sg:phone":"+1 712 526 2268",
    "sg:postcode":"51554",
    "sg:province":"IA",
    "sg:tags":[
        "church"
    ],
    "wof:name":"St John Lutheran ELCA",
    "wof:placetype":"venue"
},
  "geometry": {"coordinates":[-95.691996,41.143092],"type":"Point"}
}