{
  "type": "Feature",
  "properties": {
    "addr:full":"529 Church St Ottumwa IA 52501",
    "addr:housenumber":"529",
    "addr:postcode":"52501",
    "addr:street":"Church St",
    "iso:country":"US",
    "sg:address":"529 Church St",
    "sg:city":"Ottumwa",
    "sg:classifiers":[
        {
            "category":"Personal",
            "subcategory":"Beauty Salon",
            "type":"Services"
        }
    ],
    "sg:phone":"+1 641 683 7655",
    "sg:postcode":"52501",
    "sg:province":"IA",
    "wof:name":"Anjila's Mane Design",
    "wof:placetype":"venue"
},
  "geometry": {"coordinates":[-92.418459,41.009572],"type":"Point"}
}