{
  "type": "Feature",
  "properties": {
    "addr:full":"1003 Main St Keokuk IA 52632",
    "addr:housenumber":"1003",
    "addr:postcode":"52632",
    "addr:street":"Main St",
    "iso:country":"US",
    "sg:address":"1003 Main St",
    "sg:city":"Keokuk",
    "sg:classifiers":[
        {
            "category":"Autos & Motor Vehicles",
            "subcategory":"Auto Supplies",
            "type":"Retail Goods"
        }
    ],
    "sg:phone":"+1 319 524 5000",
    "sg:postcode":"52632",
    "sg:province":"IA",
    "sg:tags":[
        "tire"
    ],
    "wof:name":"Discont Tire & Svc",
    "wof:placetype":"venue"
},
  "geometry": {"coordinates":[-91.38816199999999,40.400524],"type":"Point"}
}