{
  "type": "Feature",
  "properties": {
    "iso:country":"US",
    "sg:address":"1441 29th St",
    "sg:city":"West Des Moines",
    "sg:classifiers":[
        {
            "category":"Health Services",
            "subcategory":"Chiropractor",
            "type":"Services"
        }
    ],
    "sg:phone":"+1 515 440 2242",
    "sg:postcode":"50266",
    "sg:province":"IA",
    "wof:name":"Gregory R Norton DC",
    "wof:placetype":"venue"
},
  "geometry": {"coordinates":[-93.74373,41.595118],"type":"Point"}
}