{
  "type": "Feature",
  "properties": {
    "iso:country":"US",
    "sg:address":"4000 114th St",
    "sg:city":"Urbandale",
    "sg:classifiers":[
        {
            "category":"Professional",
            "subcategory":"Advertising",
            "type":"Services"
        }
    ],
    "sg:phone":"+1 515 221 4900",
    "sg:postcode":"50322",
    "sg:province":"IA",
    "sg:tags":[
        "counselor"
    ],
    "sg:website":"www.trilixgroup.com",
    "wof:name":"Trilix Marketing Group",
    "wof:placetype":"venue"
},
  "geometry": {"coordinates":[-93.77142000000001,41.629845],"type":"Point"}
}