{
  "type": "Feature",
  "properties": {
    "iso:country":"US",
    "sg:address":"203 W Jackson St",
    "sg:city":"Corydon",
    "sg:classifiers":[
        {
            "category":"Insurance",
            "subcategory":"Insurance Agent",
            "type":"Services"
        }
    ],
    "sg:phone":"+1 641 872 2653",
    "sg:postcode":"50060",
    "sg:province":"IA",
    "wof:name":"New York Life Insurance Co",
    "wof:placetype":"venue"
},
  "geometry": {"coordinates":[-93.319607,40.758543],"type":"Point"}
}