{
  "type": "Feature",
  "properties": {
    "iso:country":"US",
    "sg:address":"715 Harmony St",
    "sg:city":"Council Bluffs",
    "sg:classifiers":[
        {
            "category":"Health Services",
            "subcategory":"Doctor",
            "type":"Services"
        }
    ],
    "sg:phone":"+1 712 328 5970",
    "sg:postcode":"51503",
    "sg:province":"IA",
    "sg:tags":[
        "physician",
        "surgeon"
    ],
    "wof:name":"Park Plaza Orthopedic Clinic",
    "wof:placetype":"venue"
},
  "geometry": {"coordinates":[-95.841003,41.269841],"type":"Point"}
}