{
  "type": "Feature",
  "properties": {
    "addr:full":"2921 Quincy Ave New London IA 52645",
    "addr:housenumber":"2921",
    "addr:postcode":"52645",
    "addr:street":"Quincy Ave",
    "iso:country":"US",
    "sg:address":"2921 Quincy Ave",
    "sg:city":"New London",
    "sg:classifiers":[
        {
            "category":"Organizations",
            "subcategory":"Religious Organization",
            "type":"Services"
        }
    ],
    "sg:phone":"+1 319 367 2295",
    "sg:postcode":"52645",
    "sg:province":"IA",
    "wof:name":"Palestine White Shrine",
    "wof:placetype":"venue"
},
  "geometry": {"coordinates":[-91.396016,40.878847],"type":"Point"}
}