{
  "type": "Feature",
  "properties": {
    "iso:country":"US",
    "sg:address":"1110 N 4th Ave",
    "sg:city":"Winterset",
    "sg:classifiers":[
        {
            "category":"Building & Trades",
            "subcategory":"Construction",
            "type":"Services"
        }
    ],
    "sg:phone":"+1 515 462 4273",
    "sg:postcode":"50273",
    "sg:province":"IA",
    "sg:tags":[
        "marking",
        "maintenance",
        "parking"
    ],
    "wof:name":"Winterset Street Dept",
    "wof:placetype":"venue"
},
  "geometry": {"coordinates":[-94.01835699999999,41.342806],"type":"Point"}
}