{
  "type": "Feature",
  "properties": {
    "addr:full":"415 E Bremer Ave Waverly IA 50677",
    "addr:housenumber":"415",
    "addr:postcode":"50677",
    "addr:street":"E Bremer Ave",
    "iso:country":"US",
    "sg:address":"415 E Bremer Ave",
    "sg:city":"Waverly",
    "sg:classifiers":[
        {
            "category":"Government",
            "subcategory":"Office",
            "type":"Public Place"
        }
    ],
    "sg:phone":"+1 319 352 1919",
    "sg:postcode":"50677",
    "sg:province":"IA",
    "sg:tags":[
        "county",
        "program",
        "health"
    ],
    "wof:name":"Bremer County Mental Health",
    "wof:placetype":"venue"
},
  "geometry": {"coordinates":[-92.465474,42.72589],"type":"Point"}
}