{
  "type": "Feature",
  "properties": {
    "addr:full":"1944 County Home Rd Marion IA 52302",
    "addr:housenumber":"1944",
    "addr:postcode":"52302",
    "addr:street":"County Home Rd",
    "iso:country":"US",
    "sg:address":"1944 County Home Rd",
    "sg:city":"Marion",
    "sg:classifiers":[
        {
            "category":"Government",
            "subcategory":"Office",
            "type":"Public Place"
        }
    ],
    "sg:phone":"+1 319 892 6400",
    "sg:postcode":"52302",
    "sg:province":"IA",
    "wof:name":"Linn County Engineer",
    "wof:placetype":"venue"
},
  "geometry": {"coordinates":[-91.55410000000001,42.093701],"type":"Point"}
}