{
  "type": "Feature",
  "properties": {
    "addr:full":"21982 Hawk Dr Keosauqua IA 52565",
    "addr:housenumber":"21982",
    "addr:postcode":"52565",
    "addr:street":"Hawk Dr",
    "iso:country":"US",
    "sg:address":"21982 Hawk Dr",
    "sg:city":"Keosauqua",
    "sg:classifiers":[
        {
            "category":"Travel",
            "subcategory":"Hotels & Motels",
            "type":"Entertainment"
        }
    ],
    "sg:phone":"+1 319 592 3133",
    "sg:postcode":"52565",
    "sg:province":"IA",
    "sg:tags":[
        "breakfast",
        "accommodation",
        "bed"
    ],
    "wof:name":"Mason House Inn",
    "wof:placetype":"venue"
},
  "geometry": {"coordinates":[-91.863311,40.727688],"type":"Point"}
}