{
  "type": "Feature",
  "properties": {
    "iso:country":"US",
    "sg:address":"1754 250th St",
    "sg:city":"Washington",
    "sg:classifiers":[
        {
            "category":"Farming",
            "subcategory":"Livestock Farm",
            "type":"Manufacturing & Wholesale Goods"
        }
    ],
    "sg:phone":"+1 319 653 5882",
    "sg:postcode":"52353",
    "sg:province":"IA",
    "sg:tags":[
        "hog",
        "or",
        "feedlot"
    ],
    "wof:name":"R B V Farming",
    "wof:placetype":"venue"
},
  "geometry": {"coordinates":[-91.80148699999999,41.292849],"type":"Point"}
}