{
  "type": "Feature",
  "properties": {
    "iso:country":"US",
    "sg:address":"607 Ave G",
    "sg:city":"Fort Madison",
    "sg:classifiers":[
        {
            "category":"Professional",
            "type":"Services"
        }
    ],
    "sg:phone":"+1 319 372 0139",
    "sg:postcode":"52627",
    "sg:province":"IA",
    "sg:tags":[
        "establishment"
    ],
    "wof:name":"Cowslick & Utter Things",
    "wof:placetype":"venue"
},
  "geometry": {"coordinates":[-91.30965399999999,40.630962],"type":"Point"}
}