{
  "type": "Feature",
  "properties": {
    "iso:country":"US",
    "sg:address":"1110 Buckeye Ave",
    "sg:city":"Ames",
    "sg:classifiers":[
        {
            "category":"Health Services",
            "subcategory":"Chiropractor",
            "type":"Services"
        }
    ],
    "sg:phone":"+1 515 233 9087",
    "sg:postcode":"50010",
    "sg:province":"IA",
    "wof:name":"Family Chiropractic Clinic",
    "wof:placetype":"venue"
},
  "geometry": {"coordinates":[-93.61113899999999,42.012973],"type":"Point"}
}