{
  "type": "Feature",
  "properties": {
    "iso:country":"US",
    "sg:address":"2071 280th St",
    "sg:city":"Clarion",
    "sg:phone":"+1 515 448 4943",
    "sg:postcode":"50525",
    "sg:province":"IA",
    "sg:tags":[
        "farm",
        "corn"
    ],
    "wof:name":"Leroy Schaumburg",
    "wof:placetype":"venue"
},
  "geometry": {"coordinates":[-93.760797,42.644747],"type":"Point"}
}