{
  "type": "Feature",
  "properties": {
    "addr:full":"213 Lincoln Hwy West Des Moines IA 50201",
    "addr:housenumber":"213",
    "addr:postcode":"50201",
    "addr:street":"Lincoln Hwy",
    "iso:country":"US",
    "sg:address":"213 Lincoln Hwy",
    "sg:city":"West Des Moines",
    "sg:classifiers":[
        {
            "category":"Shopping",
            "subcategory":"Computers & Home Electronics",
            "type":"Retail Goods"
        }
    ],
    "sg:phone":"+1 515 223 5010",
    "sg:postcode":"50201",
    "sg:province":"IA",
    "wof:name":"Top Notch",
    "wof:placetype":"venue"
},
  "geometry": {"coordinates":[-93.457617,42.022804],"type":"Point"}
}