{
  "type": "Feature",
  "properties": {
    "iso:country":"US",
    "sg:address":"2310 160th St",
    "sg:city":"Charter Oak",
    "sg:classifiers":[
        {
            "category":"Farming",
            "subcategory":"Farm",
            "type":"Manufacturing & Wholesale Goods"
        }
    ],
    "sg:phone":"+1 712 678 3612",
    "sg:postcode":"51439",
    "sg:province":"IA",
    "wof:name":"M J Neddermeyer Farms",
    "wof:placetype":"venue"
},
  "geometry": {"coordinates":[-95.556006,42.021253],"type":"Point"}
}