{
  "type": "Feature",
  "properties": {
    "iso:country":"US",
    "sg:address":"644 2100th St",
    "sg:city":"Earling",
    "sg:phone":"+1 712 747 9321",
    "sg:postcode":"51530",
    "sg:province":"IA",
    "sg:tags":[
        "farm",
        "corn",
        "soybean"
    ],
    "wof:name":"Clint Sonderman",
    "wof:placetype":"venue"
},
  "geometry": {"coordinates":[-95.42424699999999,41.805681],"type":"Point"}
}