{
  "type": "Feature",
  "properties": {
    "iso:country":"US",
    "sg:address":"2363 200th St",
    "sg:city":"Mount Pleasant",
    "sg:phone":"+1 319 385 4307",
    "sg:postcode":"52641",
    "sg:province":"IA",
    "sg:tags":[
        "farm",
        "soybean"
    ],
    "wof:name":"Warren Garrels",
    "wof:placetype":"venue"
},
  "geometry": {"coordinates":[-91.454984,41.016777],"type":"Point"}
}