{
  "type": "Feature",
  "properties": {
    "iso:country":"US",
    "sg:address":"116 S Division St",
    "sg:city":"Spragueville",
    "sg:classifiers":[
        {
            "category":"Organizations",
            "subcategory":"Religious Organization",
            "type":"Services"
        }
    ],
    "sg:phone":"+1 563 689 5229",
    "sg:postcode":"52074",
    "sg:province":"IA",
    "sg:tags":[
        "church"
    ],
    "wof:name":"Salem Lutheran Church Inc",
    "wof:placetype":"venue"
},
  "geometry": {"coordinates":[-90.432731,42.071515],"type":"Point"}
}