{
  "type": "Feature",
  "properties": {
    "iso:country":"US",
    "sg:address":"4216 Greenwood Dr",
    "sg:city":"Des Moines",
    "sg:classifiers":[
        {
            "category":"Professional",
            "subcategory":"Lawyer & Legal Services",
            "type":"Services"
        }
    ],
    "sg:phone":"+1 515 274 2935",
    "sg:postcode":"50312",
    "sg:province":"IA",
    "wof:name":"James R Austin",
    "wof:placetype":"venue"
},
  "geometry": {"coordinates":[-93.675431,41.58076],"type":"Point"}
}