{
  "type": "Feature",
  "properties": {
    "iso:country":"US",
    "sg:address":"7300 Beckett Dr NE",
    "sg:city":"Cedar Rapids",
    "sg:classifiers":[
        {
            "category":"Professional",
            "subcategory":"Management & Consulting",
            "type":"Services"
        }
    ],
    "sg:phone":"+1 319 447 9409",
    "sg:postcode":"52402",
    "sg:province":"IA",
    "sg:tags":[
        "business"
    ],
    "wof:name":"Interactive Solutions Inc",
    "wof:placetype":"venue"
},
  "geometry": {"coordinates":[-91.62938800000001,42.052209],"type":"Point"}
}