{
  "type": "Feature",
  "properties": {
    "addr:full":"2015 N 7th St Clinton IA 52732",
    "addr:housenumber":"2015",
    "addr:postcode":"52732",
    "addr:street":"N 7Th St",
    "iso:country":"US",
    "sg:address":"2015 N 7th St",
    "sg:city":"Clinton",
    "sg:classifiers":[
        {
            "category":"Building & Trades",
            "subcategory":"Construction",
            "type":"Services"
        }
    ],
    "sg:phone":"+1 563 243 7779",
    "sg:postcode":"52732",
    "sg:province":"IA",
    "sg:tags":[
        "repairing",
        "remodeling",
        "contractor"
    ],
    "wof:name":"Gutter Works",
    "wof:placetype":"venue"
},
  "geometry": {"coordinates":[-90.18856599999999,41.870055],"type":"Point"}
}