{
  "type": "Feature",
  "properties": {
    "iso:country":"US",
    "sg:address":"6031 Somerset Pl",
    "sg:city":"Johnston",
    "sg:classifiers":[
        {
            "category":"Freight",
            "type":"Transportation"
        }
    ],
    "sg:phone":"+1 515 229 5302",
    "sg:postcode":"50131",
    "sg:province":"IA",
    "sg:tags":[
        "delivery"
    ],
    "wof:name":"Preferred Home Delivery Svc",
    "wof:placetype":"venue"
},
  "geometry": {"coordinates":[-93.700515,41.664211],"type":"Point"}
}