{
  "type": "Feature",
  "properties": {
    "iso:country":"US",
    "sg:address":"222 E Robinson St",
    "sg:city":"Knoxville",
    "sg:classifiers":[
        {
            "category":"Banks & Credit Unions",
            "subcategory":"Bank",
            "type":"Services"
        }
    ],
    "sg:phone":"+1 641 828 8000",
    "sg:postcode":"50138",
    "sg:province":"IA",
    "wof:name":"Iowa State Savings Bank",
    "wof:placetype":"venue"
},
  "geometry": {"coordinates":[-93.09671,41.317943],"type":"Point"}
}