{
  "type": "Feature",
  "properties": {
    "iso:country":"US",
    "sg:address":"4693 50th Ave",
    "sg:city":"Alta",
    "sg:classifiers":[
        {
            "category":"Farming",
            "subcategory":"Livestock Farm",
            "type":"Manufacturing & Wholesale Goods"
        }
    ],
    "sg:phone":"+1 712 296 3757",
    "sg:postcode":"51002",
    "sg:province":"IA",
    "sg:tags":[
        "feedlot",
        "corn",
        "soybean",
        "beef",
        "cattle"
    ],
    "wof:name":"Bibler Farms",
    "wof:placetype":"venue"
},
  "geometry": {"coordinates":[-95.30931,42.837308],"type":"Point"}
}