{
  "type": "Feature",
  "properties": {
    "iso:country":"US",
    "sg:address":"700 Locust St",
    "sg:city":"Dubuque",
    "sg:classifiers":[
        {
            "category":"Professional",
            "subcategory":"Research",
            "type":"Services"
        }
    ],
    "sg:phone":"+1 563 588 2700",
    "sg:postcode":"52001",
    "sg:province":"IA",
    "sg:tags":[
        "foundation",
        "philanthropic"
    ],
    "wof:name":"Community Foundation-Greater",
    "wof:placetype":"venue"
},
  "geometry": {"coordinates":[-90.668328,42.500543],"type":"Point"}
}