{
  "type": "Feature",
  "properties": {
    "addr:full":"355 Wesley Pkwy Sioux City IA 51103",
    "addr:housenumber":"355",
    "addr:postcode":"51103",
    "addr:street":"Wesley Pkwy",
    "iso:country":"US",
    "sg:address":"355 Wesley Pkwy",
    "sg:city":"Sioux City",
    "sg:classifiers":[
        {
            "category":"Real Estate",
            "subcategory":"Real Estate Agent",
            "type":"Services"
        }
    ],
    "sg:phone":"+1 712 277 8140",
    "sg:postcode":"51103",
    "sg:province":"IA",
    "sg:website":"www.whyusajoslin.com",
    "wof:name":"Why USA Joslin Realty",
    "wof:placetype":"venue"
},
  "geometry": {"coordinates":[-96.410794,42.495045],"type":"Point"}
}