{
  "type": "Feature",
  "properties": {
    "addr:full":"1203 5th St NE Sioux Center IA 51250",
    "addr:housenumber":"1203",
    "addr:postcode":"51250",
    "addr:street":"5Th St Ne",
    "iso:country":"US",
    "sg:address":"1203 5th St NE",
    "sg:city":"Sioux Center",
    "sg:classifiers":[
        {
            "category":"Farming",
            "subcategory":"Farm",
            "type":"Manufacturing & Wholesale Goods"
        }
    ],
    "sg:phone":"+1 712 722 0195",
    "sg:postcode":"51250",
    "sg:province":"IA",
    "sg:tags":[
        "crop",
        "general"
    ],
    "wof:name":"Visser Family Farm LLC",
    "wof:placetype":"venue"
},
  "geometry": {"coordinates":[-96.15725500000001,43.082125],"type":"Point"}
}