{
  "type": "Feature",
  "properties": {
    "iso:country":"US",
    "sg:address":"211 S Oak St",
    "sg:city":"Sutherland",
    "sg:classifiers":[
        {
            "category":"Personal",
            "subcategory":"Beauty Salon",
            "type":"Services"
        }
    ],
    "sg:phone":"+1 712 446 3317",
    "sg:postcode":"51058",
    "sg:province":"IA",
    "wof:name":"Marlene's Beauty Salon",
    "wof:placetype":"venue"
},
  "geometry": {"coordinates":[-95.501091,42.973761],"type":"Point"}
}