{
  "type": "Feature",
  "properties": {
    "addr:full":"114 S Clinton St Iowa City IA 52240",
    "addr:housenumber":"114",
    "addr:postcode":"52240",
    "addr:street":"S Clinton St",
    "iso:country":"US",
    "sg:address":"114 S Clinton St",
    "sg:city":"Iowa City",
    "sg:classifiers":[
        {
            "category":"Shopping",
            "type":"Retail Goods"
        }
    ],
    "sg:phone":"+1 319 351 4453",
    "sg:postcode":"52240",
    "sg:province":"IA",
    "sg:tags":[
        "pet",
        "shop"
    ],
    "wof:name":"Pet Central Station",
    "wof:placetype":"venue"
},
  "geometry": {"coordinates":[-91.534555,41.659017],"type":"Point"}
}