{
  "type": "Feature",
  "properties": {
    "iso:country":"US",
    "sg:address":"179 Jacolyn Dr NW",
    "sg:city":"Cedar Rapids",
    "sg:classifiers":[
        {
            "category":"Personal",
            "subcategory":"Beauty Salon",
            "type":"Services"
        }
    ],
    "sg:phone":"+1 319 396 5510",
    "sg:postcode":"52405",
    "sg:province":"IA",
    "wof:name":"Lasting Impressions",
    "wof:placetype":"venue"
},
  "geometry": {"coordinates":[-91.73204699999999,41.969586],"type":"Point"}
}