{
  "type": "Feature",
  "properties": {
    "iso:country":"US",
    "sg:address":"13 N Vine St",
    "sg:city":"Glenwood",
    "sg:classifiers":[
        {
            "category":"Shopping",
            "type":"Retail Goods"
        }
    ],
    "sg:phone":"+1 712 527 2769",
    "sg:postcode":"51534",
    "sg:province":"IA",
    "sg:tags":[
        "picture",
        "frame"
    ],
    "wof:name":"Custom Creations Art & Framing",
    "wof:placetype":"venue"
},
  "geometry": {"coordinates":[-95.741742,41.04661],"type":"Point"}
}