{
  "type": "Feature",
  "properties": {
    "addr:full":"3380 Orchard Rd Osage IA 50461",
    "addr:housenumber":"3380",
    "addr:postcode":"50461",
    "addr:street":"Orchard Rd",
    "iso:country":"US",
    "sg:address":"3380 Orchard Rd",
    "sg:city":"Osage",
    "sg:phone":"+1 641 732 4128",
    "sg:postcode":"50461",
    "sg:province":"IA",
    "sg:tags":[
        "farm",
        "corn",
        "soybean"
    ],
    "wof:name":"Dean Wetherwell",
    "wof:placetype":"venue"
},
  "geometry": {"coordinates":[-92.777024,43.22893],"type":"Point"}
}