{
  "type": "Feature",
  "properties": {
    "iso:country":"US",
    "sg:address":"306 E Water St",
    "sg:city":"Decorah",
    "sg:classifiers":[
        {
            "category":"Retail",
            "subcategory":"Funeral Services",
            "type":"Services"
        }
    ],
    "sg:phone":"+1 563 382 5210",
    "sg:postcode":"52101",
    "sg:province":"IA",
    "sg:tags":[
        "director",
        "consultant",
        "management"
    ],
    "sg:website":"http://www.fjelstul.com",
    "wof:name":"Fjelstul Funeral Home",
    "wof:placetype":"venue"
},
  "geometry": {"coordinates":[-91.783332,43.304179],"type":"Point"}
}