{
  "type": "Feature",
  "properties": {
    "iso:country":"US",
    "sg:address":"4010 Alexandra Dr",
    "sg:city":"Waterloo",
    "sg:classifiers":[
        {
            "category":"Utilities",
            "subcategory":"Cable",
            "type":"Services"
        }
    ],
    "sg:phone":"+1 319 232 8800",
    "sg:postcode":"50702",
    "sg:province":"IA",
    "sg:tags":[
        "television"
    ],
    "wof:name":"Mediacom",
    "wof:placetype":"venue"
},
  "geometry": {"coordinates":[-92.332874,42.457683],"type":"Point"}
}