{
  "type": "Feature",
  "properties": {
    "iso:country":"US",
    "sg:address":"1625 8th Ave S",
    "sg:city":"Clinton",
    "sg:classifiers":[
        {
            "category":"Building & Trades",
            "subcategory":"Electrical",
            "type":"Services"
        }
    ],
    "sg:phone":"+1 563 242 8604",
    "sg:postcode":"52732",
    "sg:province":"IA",
    "sg:tags":[
        "electrical",
        "contractor"
    ],
    "wof:name":"Preferred Electric",
    "wof:placetype":"venue"
},
  "geometry": {"coordinates":[-90.226557,41.837223],"type":"Point"}
}