{
  "type": "Feature",
  "properties": {
    "iso:country":"US",
    "sg:address":"3170 1st St",
    "sg:city":"Marion",
    "sg:classifiers":[
        {
            "category":"Freight",
            "type":"Transportation"
        }
    ],
    "sg:phone":"+1 319 377 6635",
    "sg:postcode":"52302",
    "sg:province":"IA",
    "sg:tags":[
        "operator",
        "local",
        "trucking"
    ],
    "wof:name":"Brecht Trucking Inc",
    "wof:placetype":"venue"
},
  "geometry": {"coordinates":[-91.60884299999999,42.052009],"type":"Point"}
}