{
  "type": "Feature",
  "properties": {
    "iso:country":"US",
    "sg:address":"319 2nd St",
    "sg:city":"Gladbrook",
    "sg:classifiers":[
        {
            "category":"Cinema",
            "subcategory":"Movie Theater",
            "type":"Entertainment"
        }
    ],
    "sg:phone":"+1 641 473 2410",
    "sg:postcode":"50635",
    "sg:province":"IA",
    "wof:name":"Gladbrook Theater",
    "wof:placetype":"venue"
},
  "geometry": {"coordinates":[-92.716641,42.187767],"type":"Point"}
}