{
  "type": "Feature",
  "properties": {
    "addr:full":"1710 Lincoln Way Clinton IA 52732",
    "addr:housenumber":"1710",
    "addr:postcode":"52732",
    "addr:street":"Lincoln Way",
    "iso:country":"US",
    "sg:address":"1710 Lincoln Way",
    "sg:city":"Clinton",
    "sg:classifiers":[
        {
            "category":"Restaurant",
            "type":"Food & Drink"
        }
    ],
    "sg:menulink":"http://www.allmenus.com/ia/clinton/109337-village-inn/menu/",
    "sg:phone":"+1 563 242 7121",
    "sg:postcode":"52732",
    "sg:province":"IA",
    "sg:tags":[
        "new",
        "american"
    ],
    "wof:name":"Village Inn",
    "wof:placetype":"venue"
},
  "geometry": {"coordinates":[-90.227143,41.81613],"type":"Point"}
}