{
  "type": "Feature",
  "properties": {
    "addr:full":"2618 Oak Hill Ave Ashton IA 51232",
    "addr:housenumber":"2618",
    "addr:postcode":"51232",
    "addr:street":"Oak Hill Ave",
    "iso:country":"US",
    "sg:address":"2618 Oak Hill Ave",
    "sg:city":"Ashton",
    "sg:classifiers":[
        {
            "category":"Professional",
            "type":"Services"
        }
    ],
    "sg:phone":"+1 712 724 5064",
    "sg:postcode":"51232",
    "sg:province":"IA",
    "sg:tags":[
        "establishment"
    ],
    "wof:name":"Huss Brothers",
    "wof:placetype":"venue"
},
  "geometry": {"coordinates":[-95.78294699999999,43.269444],"type":"Point"}
}