{
  "type": "Feature",
  "properties": {
    "iso:country":"US",
    "sg:address":"30 W Main St",
    "sg:city":"Marshalltown",
    "sg:classifiers":[
        {
            "category":"Shopping",
            "type":"Retail Goods"
        }
    ],
    "sg:phone":"+1 641 752 5805",
    "sg:postcode":"50158",
    "sg:province":"IA",
    "sg:tags":[
        "hearing",
        "equipment",
        "supply",
        "impaired"
    ],
    "wof:name":"Marshalltown Hearing Aid Ctr",
    "wof:placetype":"venue"
},
  "geometry": {"coordinates":[-92.914164,42.049083],"type":"Point"}
}