{
  "type": "Feature",
  "properties": {
    "iso:country":"US",
    "sg:address":"16553 H Ave",
    "sg:city":"Wellsburg",
    "sg:classifiers":[
        {
            "category":"Organizations",
            "subcategory":"Religious Organization",
            "type":"Services"
        }
    ],
    "sg:phone":"+1 641 869 3992",
    "sg:postcode":"50680",
    "sg:province":"IA",
    "sg:tags":[
        "church"
    ],
    "wof:name":"Saint Pauls Lutheran Church",
    "wof:placetype":"venue"
},
  "geometry": {"coordinates":[-92.88657499999999,42.462385],"type":"Point"}
}