{
  "type": "Feature",
  "properties": {
    "iso:country":"US",
    "sg:address":"206 East St",
    "sg:city":"Brandon",
    "sg:classifiers":[
        {
            "category":"Retail",
            "subcategory":"Auto Repair",
            "type":"Services"
        }
    ],
    "sg:phone":"+1 319 474 2310",
    "sg:postcode":"52210",
    "sg:province":"IA",
    "sg:tags":[
        "general"
    ],
    "wof:name":"Kiler RPR/Diagnostic Cmpt Fuel",
    "wof:placetype":"venue"
},
  "geometry": {"coordinates":[-92.001932,42.314357],"type":"Point"}
}