{
  "type": "Feature",
  "properties": {
    "iso:country":"US",
    "sg:address":"702 E 4th St",
    "sg:city":"West Liberty",
    "sg:classifiers":[
        {
            "category":"Shopping",
            "subcategory":"Used Merchandise",
            "type":"Retail Goods"
        }
    ],
    "sg:phone":"+1 319 627 7438",
    "sg:postcode":"52776",
    "sg:province":"IA",
    "sg:tags":[
        "shop",
        "thrift"
    ],
    "wof:name":"West Liberty Clothing",
    "wof:placetype":"venue"
},
  "geometry": {"coordinates":[-91.25449999999999,41.570922],"type":"Point"}
}