{
  "type": "Feature",
  "properties": {
    "iso:country":"US",
    "sg:address":"509 E Grove St",
    "sg:city":"Maquoketa",
    "sg:classifiers":[
        {
            "category":"Government",
            "subcategory":"Office",
            "type":"Public Place"
        }
    ],
    "sg:phone":"+1 563 652 4318",
    "sg:postcode":"52060",
    "sg:province":"IA",
    "wof:name":"Jackson County Repair Shop",
    "wof:placetype":"venue"
},
  "geometry": {"coordinates":[-90.660701,42.073654],"type":"Point"}
}