{
  "type": "Feature",
  "properties": {
    "addr:full":"218 Main Ave Clinton IA 52732",
    "addr:housenumber":"218",
    "addr:postcode":"52732",
    "addr:street":"Main Ave",
    "iso:country":"US",
    "sg:address":"218 Main Ave",
    "sg:city":"Clinton",
    "sg:classifiers":[
        {
            "category":"Autos & Motor Vehicles",
            "subcategory":"Auto Supplies",
            "type":"Retail Goods"
        }
    ],
    "sg:phone":"+1 563 242 1712",
    "sg:postcode":"52732",
    "sg:province":"IA",
    "sg:tags":[
        "automotive",
        "lubrication",
        "tune",
        "accessory"
    ],
    "wof:name":"Jensen Oil",
    "wof:placetype":"venue"
},
  "geometry": {"coordinates":[-90.18079400000001,41.872866],"type":"Point"}
}