{
  "type": "Feature",
  "properties": {
    "addr:full":"950 31st St Des Moines IA 50312",
    "addr:housenumber":"950",
    "addr:postcode":"50312",
    "addr:street":"31St St",
    "iso:country":"US",
    "sg:address":"950 31st St",
    "sg:city":"Des Moines",
    "sg:classifiers":[
        {
            "category":"Building & Trades",
            "subcategory":"Construction",
            "type":"Services"
        }
    ],
    "sg:phone":"+1 515 277 4585",
    "sg:postcode":"50312",
    "sg:province":"IA",
    "sg:tags":[
        "general",
        "commercial",
        "family",
        "contractor"
    ],
    "wof:name":"Stackhouse & Co Inc",
    "wof:placetype":"venue"
},
  "geometry": {"coordinates":[-93.65934799999999,41.595431],"type":"Point"}
}