{
  "type": "Feature",
  "properties": {
    "addr:full":"207 Southview Dr Grundy Center IA 50638",
    "addr:housenumber":"207",
    "addr:postcode":"50638",
    "addr:street":"Southview Dr",
    "iso:country":"US",
    "sg:address":"207 Southview Dr",
    "sg:city":"Grundy Center",
    "sg:classifiers":[
        {
            "category":"Travel",
            "subcategory":"Travel Agent",
            "type":"Entertainment"
        }
    ],
    "sg:phone":"+1 319 825 6523",
    "sg:postcode":"50638",
    "sg:province":"IA",
    "sg:tags":[
        "agency"
    ],
    "wof:name":"Gold Star Cruise Agency",
    "wof:placetype":"venue"
},
  "geometry": {"coordinates":[-92.773776,42.355178],"type":"Point"}
}