{
  "type": "Feature",
  "properties": {
    "iso:country":"US",
    "sg:address":"114 N 3rd St",
    "sg:city":"Clear Lake",
    "sg:classifiers":[
        {
            "category":"Restaurant",
            "type":"Food & Drink"
        }
    ],
    "sg:phone":"+1 641 357 6400",
    "sg:postcode":"50428",
    "sg:province":"IA",
    "wof:name":"Rose Cottage Tea Room & Gifts",
    "wof:placetype":"venue"
},
  "geometry": {"coordinates":[-93.383486,43.137382],"type":"Point"}
}