{
  "type": "Feature",
  "properties": {
    "iso:country":"US",
    "sg:address":"6 Quincy Ter",
    "sg:city":"Mason City",
    "sg:classifiers":[
        {
            "category":"Retail",
            "subcategory":"Laundry & Dry Cleaning",
            "type":"Services"
        }
    ],
    "sg:phone":"+1 641 424 6977",
    "sg:postcode":"50401",
    "sg:province":"IA",
    "sg:tags":[
        "cleaners",
        "rug",
        "carpet"
    ],
    "wof:name":"Blue Diamond Carpet Care",
    "wof:placetype":"venue"
},
  "geometry": {"coordinates":[-93.211035,43.169449],"type":"Point"}
}