{
  "type": "Feature",
  "properties": {
    "iso:country":"US",
    "sg:address":"1402 Roosevelt St",
    "sg:city":"Clinton",
    "sg:classifiers":[
        {
            "category":"Manufacturing",
            "subcategory":"Printing",
            "type":"Manufacturing & Wholesale Goods"
        }
    ],
    "sg:phone":"+1 563 242 7895",
    "sg:postcode":"52732",
    "sg:province":"IA",
    "sg:tags":[
        "commercial"
    ],
    "sg:website":"www.clintonprinting.com",
    "wof:name":"Clinton Printing Co",
    "wof:placetype":"venue"
},
  "geometry": {"coordinates":[-90.183432,41.859655],"type":"Point"}
}