{
  "type": "Feature",
  "properties": {
    "iso:country":"US",
    "sg:address":"306 5th St",
    "sg:city":"Lake View",
    "sg:classifiers":[
        {
            "category":"Travel",
            "subcategory":"Hotels & Motels",
            "type":"Entertainment"
        }
    ],
    "sg:phone":"+1 712 657 2535",
    "sg:postcode":"51450",
    "sg:province":"IA",
    "sg:tags":[
        "breakfast",
        "accommodation",
        "bed"
    ],
    "wof:name":"Armstrong House B & B",
    "wof:placetype":"venue"
},
  "geometry": {"coordinates":[-95.05384100000001,42.307826],"type":"Point"}
}