{
  "type": "Feature",
  "properties": {
    "iso:country":"US",
    "sg:address":"6229 D Ave",
    "sg:city":"Washta",
    "sg:phone":"+1 712 375 5374",
    "sg:postcode":"51048",
    "sg:province":"IA",
    "sg:tags":[
        "farm",
        "field",
        "corn",
        "crop",
        "soybean"
    ],
    "wof:name":"Bill Socklowski",
    "wof:placetype":"venue"
},
  "geometry": {"coordinates":[-95.800152,42.614137],"type":"Point"}
}