{
  "type": "Feature",
  "properties": {
    "iso:country":"US",
    "sg:address":"3014 E Main St",
    "sg:city":"Knoxville",
    "sg:classifiers":[
        {
            "category":"Government",
            "subcategory":"Office",
            "type":"Public Place"
        }
    ],
    "sg:phone":"+1 641 842 5087",
    "sg:postcode":"50138",
    "sg:province":"IA",
    "sg:tags":[
        "county",
        "resource"
    ],
    "wof:name":"Marion County Human Svc",
    "wof:placetype":"venue"
},
  "geometry": {"coordinates":[-93.069447,41.314108],"type":"Point"}
}