{
  "type": "Feature",
  "properties": {
    "iso:country":"US",
    "sg:address":"6445 US Hwy 30",
    "sg:city":"Ely",
    "sg:classifiers":[
        {
            "category":"Farming",
            "subcategory":"Farm & Veterinary Services",
            "type":"Manufacturing & Wholesale Goods"
        }
    ],
    "sg:phone":"+1 319 848 4444",
    "sg:postcode":"52227",
    "sg:province":"IA",
    "sg:tags":[
        "management"
    ],
    "wof:name":"Breuer Farm Management Co",
    "wof:placetype":"venue"
},
  "geometry": {"coordinates":[-91.568361,41.925039],"type":"Point"}
}