{
  "type": "Feature",
  "properties": {
    "iso:country":"US",
    "sg:address":"1350 190th St",
    "sg:city":"Ionia",
    "sg:classifiers":[
        {
            "category":"Home & Garden",
            "subcategory":"Home Furnishings",
            "type":"Retail Goods"
        }
    ],
    "sg:phone":"+1 641 394 3984",
    "sg:postcode":"50645",
    "sg:province":"IA",
    "wof:name":"Rosalyn Custom Interiors",
    "wof:placetype":"venue"
},
  "geometry": {"coordinates":[-92.47585599999999,43.083008],"type":"Point"}
}