{
  "type": "Feature",
  "properties": {
    "iso:country":"US",
    "sg:address":"606 Colorado St",
    "sg:city":"Glidden",
    "sg:classifiers":[
        {
            "category":"Real Estate",
            "subcategory":"Real Estate Operator",
            "type":"Services"
        }
    ],
    "sg:phone":"+1 712 659 3732",
    "sg:postcode":"51443",
    "sg:province":"IA",
    "sg:tags":[
        "farm",
        "corn",
        "property",
        "soybean",
        "lessor"
    ],
    "wof:name":"William Schon",
    "wof:placetype":"venue"
},
  "geometry": {"coordinates":[-94.725962,42.061793],"type":"Point"}
}