{
  "type": "Feature",
  "properties": {
    "iso:country":"US",
    "sg:address":"100 8th St SE",
    "sg:city":"Altoona",
    "sg:classifiers":[
        {
            "category":"Banks & Credit Unions",
            "subcategory":"Bank",
            "type":"Services"
        }
    ],
    "sg:phone":"+1 515 967 0142",
    "sg:postcode":"50009",
    "sg:province":"IA",
    "sg:tags":[
        "state",
        "company",
        "holding"
    ],
    "wof:name":"Easter Enterprises Inc",
    "wof:placetype":"venue"
},
  "geometry": {"coordinates":[-93.46217799999999,41.644098],"type":"Point"}
}