{
  "type": "Feature",
  "properties": {
    "addr:full":"601 US Hwy 218 N La Porte City IA 50651",
    "addr:housenumber":"601",
    "addr:postcode":"50651",
    "addr:street":"Us Hwy 218 N La Porte",
    "iso:country":"US",
    "sg:address":"601 US Hwy 218 N",
    "sg:city":"La Porte City",
    "sg:classifiers":[
        {
            "category":"Shopping",
            "subcategory":"Pharmacy",
            "type":"Retail Goods"
        }
    ],
    "sg:phone":"+1 319 342 3620",
    "sg:postcode":"50651",
    "sg:province":"IA",
    "wof:name":"LA Porte City Pharmacy",
    "wof:placetype":"venue"
},
  "geometry": {"coordinates":[-92.19862000000001,42.320305],"type":"Point"}
}