{
  "type": "Feature",
  "properties": {
    "iso:country":"US",
    "sg:address":"1276 260th St",
    "sg:city":"Moorland",
    "sg:classifiers":[
        {
            "category":"Personal",
            "subcategory":"Beauty Salon",
            "type":"Services"
        }
    ],
    "sg:phone":"+1 515 573 2591",
    "sg:postcode":"50566",
    "sg:province":"IA",
    "wof:name":"Just Deb's",
    "wof:placetype":"venue"
},
  "geometry": {"coordinates":[-94.34624599999999,42.412547],"type":"Point"}
}