{
  "type": "Feature",
  "properties": {
    "addr:full":"24683 Dogwood Ave Fertile IA 50434",
    "addr:housenumber":"24683",
    "addr:postcode":"50434",
    "addr:street":"Dogwood Ave",
    "iso:country":"US",
    "sg:address":"24683 Dogwood Ave",
    "sg:city":"Fertile",
    "sg:phone":"+1 641 797 2750",
    "sg:postcode":"50434",
    "sg:province":"IA",
    "sg:tags":[
        "farm",
        "field",
        "corn",
        "crop"
    ],
    "wof:name":"Robert Kennedy",
    "wof:placetype":"venue"
},
  "geometry": {"coordinates":[-93.43794200000001,43.253551],"type":"Point"}
}