{
  "type": "Feature",
  "properties": {
    "iso:country":"US",
    "sg:address":"800 S Frederick Ave",
    "sg:city":"Oelwein",
    "sg:classifiers":[
        {
            "category":"Restaurant",
            "type":"Food & Drink"
        }
    ],
    "sg:phone":"+1 319 283 5070",
    "sg:postcode":"50662",
    "sg:province":"IA",
    "wof:name":"Eieios Restaurant & Drive Inn",
    "wof:placetype":"venue"
},
  "geometry": {"coordinates":[-91.913494,42.668223],"type":"Point"}
}