{
  "type": "Feature",
  "properties": {
    "addr:full":"330 Kimball Rd Iowa City IA 52245",
    "addr:housenumber":"330",
    "addr:postcode":"52245",
    "addr:street":"Kimball Rd",
    "iso:country":"US",
    "sg:address":"330 Kimball Rd",
    "sg:city":"Iowa City",
    "sg:classifiers":[
        {
            "category":"Real Estate",
            "subcategory":"Real Estate Agent",
            "type":"Services"
        }
    ],
    "sg:phone":"+1 319 351 2952",
    "sg:postcode":"52245",
    "sg:province":"IA",
    "wof:name":"Kic Ltd Co",
    "wof:placetype":"venue"
},
  "geometry": {"coordinates":[-91.527169,41.673032],"type":"Point"}
}