{
  "type": "Feature",
  "properties": {
    "addr:full":"4885 Orchard Dr Des Moines IA 50327",
    "addr:housenumber":"4885",
    "addr:postcode":"50327",
    "addr:street":"Orchard Dr",
    "iso:country":"US",
    "sg:address":"4885 Orchard Dr",
    "sg:city":"Des Moines",
    "sg:classifiers":[
        {
            "category":"Professional",
            "subcategory":"Business Services",
            "type":"Services"
        }
    ],
    "sg:phone":"+1 515 266 9684",
    "sg:postcode":"50327",
    "sg:province":"IA",
    "wof:name":"Fair Trade Inc",
    "wof:placetype":"venue"
},
  "geometry": {"coordinates":[-93.514004,41.589535],"type":"Point"}
}