{
  "type": "Feature",
  "properties": {
    "addr:full":"1680 175th St Webster City IA 50595",
    "addr:housenumber":"1680",
    "addr:postcode":"50595",
    "addr:street":"175Th St",
    "iso:country":"US",
    "sg:address":"1680 175th St",
    "sg:city":"Webster City",
    "sg:classifiers":[
        {
            "category":"Real Estate",
            "subcategory":"Real Estate Operator",
            "type":"Services"
        }
    ],
    "sg:phone":"+1 515 832 1117",
    "sg:postcode":"50595",
    "sg:province":"IA",
    "sg:tags":[
        "property",
        "lessor"
    ],
    "wof:name":"Arthur Labs",
    "wof:placetype":"venue"
},
  "geometry": {"coordinates":[-93.832167,42.536447],"type":"Point"}
}