{
  "type": "Feature",
  "properties": {
    "iso:country":"US",
    "sg:address":"33977 Grouse Ave",
    "sg:city":"Sioux City",
    "sg:classifiers":[
        {
            "category":"Shopping",
            "type":"Retail Goods"
        }
    ],
    "sg:phone":"+1 712 239 5531",
    "sg:postcode":"51108",
    "sg:province":"IA",
    "sg:tags":[
        "bird"
    ],
    "wof:name":"Zimmerman Pets",
    "wof:placetype":"venue"
},
  "geometry": {"coordinates":[-96.371095,42.562115],"type":"Point"}
}