{
  "type": "Feature",
  "properties": {
    "iso:country":"US",
    "sg:address":"3301 5th Ave",
    "sg:city":"Sioux City",
    "sg:classifiers":[
        {
            "category":"Retail",
            "subcategory":"Laundry & Dry Cleaning",
            "type":"Services"
        }
    ],
    "sg:phone":"+1 712 276 4657",
    "sg:postcode":"51106",
    "sg:province":"IA",
    "sg:tags":[
        "cleaners"
    ],
    "wof:name":"Gene Smith Cleaners",
    "wof:placetype":"venue"
},
  "geometry": {"coordinates":[-96.36415,42.468267],"type":"Point"}
}