{
  "type": "Feature",
  "properties": {
    "iso:country":"US",
    "sg:address":"28171 248th St",
    "sg:city":"Sigourney",
    "sg:phone":"+1 641 635 2676",
    "sg:postcode":"52591",
    "sg:province":"IA",
    "sg:tags":[
        "farm",
        "corn",
        "soybean"
    ],
    "wof:name":"Leland Sieren",
    "wof:placetype":"venue"
},
  "geometry": {"coordinates":[-92.04879,41.298185],"type":"Point"}
}