{
  "type": "Feature",
  "properties": {
    "iso:country":"US",
    "sg:address":"11375 190th St",
    "sg:city":"Davenport",
    "sg:classifiers":[
        {
            "category":"Freight",
            "type":"Transportation"
        }
    ],
    "sg:phone":"+1 563 243 2219",
    "sg:postcode":"52804",
    "sg:province":"IA",
    "sg:tags":[
        "mover"
    ],
    "sg:website":"www.hawkeyemover.com",
    "wof:name":"Hawkeye Movers Of Davenport",
    "wof:placetype":"venue"
},
  "geometry": {"coordinates":[-90.68254399999999,41.581838],"type":"Point"}
}