{
  "type": "Feature",
  "properties": {
    "iso:country":"US",
    "sg:address":"4780 Maple St",
    "sg:city":"Newton",
    "sg:classifiers":[
        {
            "category":"Wholesale",
            "subcategory":"Farm Supplies",
            "type":"Manufacturing & Wholesale Goods"
        }
    ],
    "sg:phone":"+1 641 792 5771",
    "sg:postcode":"50208",
    "sg:province":"IA",
    "wof:name":"Jass Ltd",
    "wof:placetype":"venue"
},
  "geometry": {"coordinates":[-93.10097399999999,41.652494],"type":"Point"}
}