{
  "type": "Feature",
  "properties": {
    "addr:full":"3574 Langley Ave Lake City IA 51449",
    "addr:housenumber":"3574",
    "addr:postcode":"51449",
    "addr:street":"Langley Ave",
    "iso:country":"US",
    "sg:address":"3574 Langley Ave",
    "sg:city":"Lake City",
    "sg:classifiers":[
        {
            "category":"Manufacturing",
            "subcategory":"Furniture",
            "type":"Manufacturing & Wholesale Goods"
        }
    ],
    "sg:phone":"+1 712 464 8140",
    "sg:postcode":"51449",
    "sg:province":"IA",
    "sg:tags":[
        "upholstered",
        "wood"
    ],
    "wof:name":"Kountry Krafts Hardwoods",
    "wof:placetype":"venue"
},
  "geometry": {"coordinates":[-94.68745800000001,42.270891],"type":"Point"}
}