{
  "type": "Feature",
  "properties": {
    "addr:full":"3625 Douglas Ave Des Moines IA 50310",
    "addr:housenumber":"3625",
    "addr:postcode":"50310",
    "addr:street":"Douglas Ave",
    "iso:country":"US",
    "sg:address":"3625 Douglas Ave",
    "sg:city":"Des Moines",
    "sg:classifiers":[
        {
            "category":"Shopping",
            "subcategory":"Computers & Home Electronics",
            "type":"Retail Goods"
        }
    ],
    "sg:phone":"+1 515 244 8271",
    "sg:postcode":"50310",
    "sg:province":"IA",
    "sg:tags":[
        "software"
    ],
    "wof:name":"Restexx Inc",
    "wof:placetype":"venue"
},
  "geometry": {"coordinates":[-93.667085,41.629608],"type":"Point"}
}