{
  "type": "Feature",
  "properties": {
    "iso:country":"US",
    "sg:address":"1745 200th St",
    "sg:city":"West Chester",
    "sg:classifiers":[
        {
            "category":"Farming",
            "subcategory":"Farm",
            "type":"Manufacturing & Wholesale Goods"
        }
    ],
    "sg:phone":"+1 319 698 7967",
    "sg:postcode":"52359",
    "sg:province":"IA",
    "wof:name":"BNW Inc",
    "wof:placetype":"venue"
},
  "geometry": {"coordinates":[-91.810435,41.363722],"type":"Point"}
}