{
  "type": "Feature",
  "properties": {
    "iso:country":"US",
    "sg:address":"223 Main St",
    "sg:city":"Goose Lake",
    "sg:classifiers":[
        {
            "category":"Banks & Credit Unions",
            "subcategory":"Bank",
            "type":"Services"
        }
    ],
    "sg:phone":"+1 563 677 2783",
    "sg:postcode":"52750",
    "sg:province":"IA",
    "wof:name":"Gateway State Bank",
    "wof:placetype":"venue"
},
  "geometry": {"coordinates":[-90.38327,41.968675],"type":"Point"}
}