{
  "type": "Feature",
  "properties": {
    "addr:full":"500 E Burlington Ave Fairfield IA 52556",
    "addr:housenumber":"500",
    "addr:postcode":"52556",
    "addr:street":"E Burlington Ave",
    "iso:country":"US",
    "sg:address":"500 E Burlington Ave",
    "sg:city":"Fairfield",
    "sg:classifiers":[
        {
            "category":"Wholesale",
            "subcategory":"Groceries",
            "type":"Manufacturing & Wholesale Goods"
        }
    ],
    "sg:phone":"+1 641 472 7441",
    "sg:postcode":"52556",
    "sg:province":"IA",
    "sg:tags":[
        "food",
        "product",
        "health"
    ],
    "wof:name":"K & E Ferguson & Sons",
    "wof:placetype":"venue"
},
  "geometry": {"coordinates":[-91.957398,41.006499],"type":"Point"}
}