{
  "type": "Feature",
  "properties": {
    "iso:country":"US",
    "sg:address":"718 Bridge Ave",
    "sg:city":"Davenport",
    "sg:classifiers":[
        {
            "category":"Real Estate",
            "subcategory":"Real Estate Agent",
            "type":"Services"
        }
    ],
    "sg:phone":"+1 563 383 0111",
    "sg:postcode":"52803",
    "sg:province":"IA",
    "wof:name":"Team Real Estate & Co",
    "wof:placetype":"venue"
},
  "geometry": {"coordinates":[-90.557914,41.527972],"type":"Point"}
}