{
  "type": "Feature",
  "properties": {
    "addr:full":"105 W Washington St Brighton IA 52540",
    "addr:housenumber":"105",
    "addr:postcode":"52540",
    "addr:street":"W Washington St",
    "iso:country":"US",
    "sg:address":"105 W Washington St",
    "sg:city":"Brighton",
    "sg:classifiers":[
        {
            "category":"Building & Trades",
            "subcategory":"Construction",
            "type":"Services"
        }
    ],
    "sg:phone":"+1 319 694 3140",
    "sg:postcode":"52540",
    "sg:province":"IA",
    "sg:tags":[
        "contractor"
    ],
    "wof:name":"Miller's General Contracting",
    "wof:placetype":"venue"
},
  "geometry": {"coordinates":[-91.822498,41.175011],"type":"Point"}
}