{
  "type": "Feature",
  "properties": {
    "iso:country":"US",
    "sg:address":"2442 225th St",
    "sg:city":"Oskaloosa",
    "sg:classifiers":[
        {
            "category":"Building & Trades",
            "subcategory":"Construction",
            "type":"Services"
        }
    ],
    "sg:phone":"+1 641 672 1537",
    "sg:postcode":"52577",
    "sg:province":"IA",
    "sg:tags":[
        "concrete",
        "contractor"
    ],
    "wof:name":"G & S Construction",
    "wof:placetype":"venue"
},
  "geometry": {"coordinates":[-92.589556,41.328861],"type":"Point"}
}