{
  "type": "Feature",
  "properties": {
    "iso:country":"US",
    "sg:address":"2325 Delta Ave",
    "sg:city":"Bridgewater",
    "sg:phone":"+1 641 745 4542",
    "sg:postcode":"50837",
    "sg:province":"IA",
    "sg:tags":[
        "farm",
        "soybean",
        "beef",
        "feedlot",
        "cattle"
    ],
    "wof:name":"Carrol Wood",
    "wof:placetype":"venue"
},
  "geometry": {"coordinates":[-94.64274,41.31428],"type":"Point"}
}