{
  "type": "Feature",
  "properties": {
    "addr:full":"4955 120th Ave Peterson IA 51047",
    "addr:housenumber":"4955",
    "addr:postcode":"51047",
    "addr:street":"120Th Ave",
    "iso:country":"US",
    "sg:address":"4955 120th Ave",
    "sg:city":"Peterson",
    "sg:phone":"+1 712 295 7361",
    "sg:postcode":"51047",
    "sg:province":"IA",
    "sg:tags":[
        "beef",
        "farm",
        "corn",
        "soybean",
        "cattle",
        "feedlot"
    ],
    "wof:name":"Ronald Krager",
    "wof:placetype":"venue"
},
  "geometry": {"coordinates":[-95.346219,42.929376],"type":"Point"}
}