{
  "type": "Feature",
  "properties": {
    "iso:country":"US",
    "sg:address":"2627 Ave L",
    "sg:city":"Fort Madison",
    "sg:classifiers":[
        {
            "category":"Personal",
            "subcategory":"Beauty Salon",
            "type":"Services"
        }
    ],
    "sg:phone":"+1 319 372 1112",
    "sg:postcode":"52627",
    "sg:province":"IA",
    "sg:tags":[
        "shop"
    ],
    "wof:name":"Prime Design",
    "wof:placetype":"venue"
},
  "geometry": {"coordinates":[-91.342761,40.627103],"type":"Point"}
}