{
  "type": "Feature",
  "properties": {
    "iso:country":"US",
    "sg:address":"103 E Main St",
    "sg:city":"Lake City",
    "sg:classifiers":[
        {
            "category":"Shopping",
            "subcategory":"Crafts & Fabrics",
            "type":"Retail Goods"
        }
    ],
    "sg:phone":"+1 712 464 7477",
    "sg:postcode":"51449",
    "sg:province":"IA",
    "sg:tags":[
        "material",
        "quilting",
        "supply"
    ],
    "wof:name":"Towne Square Quilt Shoppe",
    "wof:placetype":"venue"
},
  "geometry": {"coordinates":[-94.73379,42.267281],"type":"Point"}
}