{
  "type": "Feature",
  "properties": {
    "addr:full":"332 S Linn St Iowa City IA 52240",
    "addr:housenumber":"332",
    "addr:postcode":"52240",
    "addr:street":"S Linn St",
    "iso:country":"US",
    "sg:address":"332 S Linn St",
    "sg:city":"Iowa City",
    "sg:classifiers":[
        {
            "category":"Insurance",
            "subcategory":"Insurance Agent",
            "type":"Services"
        }
    ],
    "sg:phone":"+1 319 358 2522",
    "sg:postcode":"52240",
    "sg:province":"IA",
    "wof:name":"Western Fraternal",
    "wof:placetype":"venue"
},
  "geometry": {"coordinates":[-91.531588,41.656999],"type":"Point"}
}