{
  "type": "Feature",
  "properties": {
    "iso:country":"US",
    "sg:address":"220 N Douglas St",
    "sg:city":"Afton",
    "sg:classifiers":[
        {
            "category":"Professional",
            "subcategory":"Lawyer & Legal Services",
            "type":"Services"
        }
    ],
    "sg:phone":"+1 641 347 8723",
    "sg:postcode":"50830",
    "sg:province":"IA",
    "sg:tags":[
        "attorney"
    ],
    "wof:name":"Marion E James",
    "wof:placetype":"venue"
},
  "geometry": {"coordinates":[-94.197644,41.029122],"type":"Point"}
}