{
  "type": "Feature",
  "properties": {
    "addr:full":"103 Bel Aire Ct Tipton IA 52772",
    "addr:housenumber":"103",
    "addr:postcode":"52772",
    "addr:street":"Bel Aire Ct",
    "iso:country":"US",
    "sg:address":"103 Bel Aire Ct",
    "sg:city":"Tipton",
    "sg:classifiers":[
        {
            "category":"Farming",
            "subcategory":"Farm",
            "type":"Manufacturing & Wholesale Goods"
        }
    ],
    "sg:phone":"+1 563 886 2751",
    "sg:postcode":"52772",
    "sg:province":"IA",
    "sg:tags":[
        "crop",
        "general"
    ],
    "wof:name":"Clarence Schmidt",
    "wof:placetype":"venue"
},
  "geometry": {"coordinates":[-91.12491900000001,41.779868],"type":"Point"}
}