{
  "type": "Feature",
  "properties": {
    "iso:country":"US",
    "sg:address":"320 N 9th Ave",
    "sg:city":"Eldridge",
    "sg:classifiers":[
        {
            "category":"Home & Garden",
            "subcategory":"Building Materials",
            "type":"Retail Goods"
        }
    ],
    "sg:phone":"+1 563 285 9016",
    "sg:postcode":"52748",
    "sg:province":"IA",
    "sg:tags":[
        "roofing"
    ],
    "wof:name":"Whitco Wholesale",
    "wof:placetype":"venue"
},
  "geometry": {"coordinates":[-90.57202100000001,41.656723],"type":"Point"}
}