{
  "type": "Feature",
  "properties": {
    "iso:country":"US",
    "sg:address":"511 W 17th St",
    "sg:city":"Sioux City",
    "sg:classifiers":[
        {
            "category":"Organizations",
            "subcategory":"Religious Organization",
            "type":"Services"
        }
    ],
    "sg:phone":"+1 712 277 4432",
    "sg:postcode":"51103",
    "sg:province":"IA",
    "wof:name":"Pho Mon Buddhist Temple",
    "wof:placetype":"venue"
},
  "geometry": {"coordinates":[-96.42027299999999,42.508431],"type":"Point"}
}