{
  "type": "Feature",
  "properties": {
    "iso:country":"US",
    "sg:address":"39609 334th St",
    "sg:city":"Bellevue",
    "sg:classifiers":[
        {
            "category":"Building & Trades",
            "subcategory":"Construction",
            "type":"Services"
        }
    ],
    "sg:phone":"+1 563 872 5750",
    "sg:postcode":"52031",
    "sg:province":"IA",
    "sg:tags":[
        "general",
        "contractor"
    ],
    "wof:name":"Haxmeier Construction",
    "wof:placetype":"venue"
},
  "geometry": {"coordinates":[-90.43244300000001,42.321658],"type":"Point"}
}