{
  "type": "Feature",
  "properties": {
    "iso:country":"US",
    "sg:address":"722 Creston Ave",
    "sg:city":"Waterloo",
    "sg:classifiers":[
        {
            "category":"Wholesale",
            "subcategory":"Machinery & Supplies",
            "type":"Manufacturing & Wholesale Goods"
        },
        {
            "category":"Retail",
            "subcategory":"Repair Shop",
            "type":"Services"
        }
    ],
    "sg:phone":"+1 319 232 2055",
    "sg:postcode":"50707",
    "sg:province":"IA",
    "sg:tags":[
        "equipment",
        "establishment",
        "taxidermist"
    ],
    "wof:name":"Art Of The Wild Taxidermy",
    "wof:placetype":"venue"
},
  "geometry": {"coordinates":[-92.296859,42.490035],"type":"Point"}
}