{
  "type": "Feature",
  "properties": {
    "addr:full":"601 E Central St Jefferson IA 50129",
    "addr:housenumber":"601",
    "addr:postcode":"50129",
    "addr:street":"E Central St",
    "iso:country":"US",
    "sg:address":"601 E Central St",
    "sg:city":"Jefferson",
    "sg:classifiers":[
        {
            "category":"Manufacturing",
            "subcategory":"Tools & Machinery",
            "type":"Manufacturing & Wholesale Goods"
        }
    ],
    "sg:phone":"+1 515 386 2126",
    "sg:postcode":"50129",
    "sg:province":"IA",
    "sg:tags":[
        "electric"
    ],
    "wof:name":"Electrolux Home Products",
    "wof:placetype":"venue"
},
  "geometry": {"coordinates":[-94.35816800000001,42.026146],"type":"Point"}
}