{
  "type": "Feature",
  "properties": {
    "iso:country":"US",
    "sg:address":"319 E Washington St",
    "sg:city":"Iowa City",
    "sg:classifiers":[
        {
            "category":"Real Estate",
            "subcategory":"Architect",
            "type":"Services"
        }
    ],
    "sg:phone":"+1 319 338 7600",
    "sg:postcode":"52240",
    "sg:province":"IA",
    "wof:name":"Burns & Burns",
    "wof:placetype":"venue"
},
  "geometry": {"coordinates":[-91.530383,41.659971],"type":"Point"}
}