{
  "type": "Feature",
  "properties": {
    "iso:country":"US",
    "sg:address":"821 Willow St",
    "sg:city":"Dumont",
    "sg:classifiers":[
        {
            "category":"Building & Trades",
            "subcategory":"Construction",
            "type":"Services"
        }
    ],
    "sg:phone":"+1 641 857 3665",
    "sg:postcode":"50625",
    "sg:province":"IA",
    "sg:tags":[
        "general",
        "contractor"
    ],
    "wof:name":"Ulfers Construction",
    "wof:placetype":"venue"
},
  "geometry": {"coordinates":[-92.97431899999999,42.752885],"type":"Point"}
}