{
  "type": "Feature",
  "properties": {
    "addr:full":"2443 Garfield Ave Des Moines IA 50317",
    "addr:housenumber":"2443",
    "addr:postcode":"50317",
    "addr:street":"Garfield Ave",
    "iso:country":"US",
    "sg:address":"2443 Garfield Ave",
    "sg:city":"Des Moines",
    "sg:classifiers":[
        {
            "category":"Shopping",
            "subcategory":"Clothing, Apparel, & Fashions",
            "type":"Retail Goods"
        }
    ],
    "sg:phone":"+1 515 266 3873",
    "sg:postcode":"50317",
    "sg:province":"IA",
    "sg:tags":[
        "family"
    ],
    "wof:name":"Zumi Collections",
    "wof:placetype":"venue"
},
  "geometry": {"coordinates":[-93.57153099999999,41.602676],"type":"Point"}
}