{
  "type": "Feature",
  "properties": {
    "iso:country":"US",
    "sg:address":"1011 13th St N",
    "sg:city":"Humboldt",
    "sg:classifiers":[
        {
            "category":"Food & Beverages",
            "subcategory":"Liquor & Beverages",
            "type":"Retail Goods"
        }
    ],
    "sg:phone":"+1 515 332 4586",
    "sg:postcode":"50548",
    "sg:province":"IA",
    "wof:name":"Hyvee Wine & Spirits",
    "wof:placetype":"venue"
},
  "geometry": {"coordinates":[-94.227035,42.732597],"type":"Point"}
}