{
  "type": "Feature",
  "properties": {
    "iso:country":"US",
    "sg:address":"1117 E Madison Ave",
    "sg:city":"Fairfield",
    "sg:classifiers":[
        {
            "category":"Building & Trades",
            "subcategory":"Construction",
            "type":"Services"
        }
    ],
    "sg:phone":"+1 641 472 4363",
    "sg:postcode":"52556",
    "sg:province":"IA",
    "sg:tags":[
        "general",
        "contractor"
    ],
    "wof:name":"Pilcher Construction",
    "wof:placetype":"venue"
},
  "geometry": {"coordinates":[-91.946421,41.00302],"type":"Point"}
}