{
  "type": "Feature",
  "properties": {
    "iso:country":"US",
    "sg:address":"803 Ellis Dr",
    "sg:city":"Charles City",
    "sg:classifiers":[
        {
            "category":"Real Estate",
            "subcategory":"Real Estate Operator",
            "type":"Services"
        }
    ],
    "sg:phone":"+1 641 228 4975",
    "sg:postcode":"50616",
    "sg:province":"IA",
    "sg:tags":[
        "building",
        "apartment"
    ],
    "wof:name":"Myrtle Drive Apartments",
    "wof:placetype":"venue"
},
  "geometry": {"coordinates":[-92.658693,43.065847],"type":"Point"}
}