{
  "type": "Feature",
  "properties": {
    "iso:country":"US",
    "sg:address":"605 Main St",
    "sg:city":"Mediapolis",
    "sg:classifiers":[
        {
            "category":"Banks & Credit Unions",
            "subcategory":"Bank",
            "type":"Services"
        }
    ],
    "sg:phone":"+1 319 394 3191",
    "sg:postcode":"52637",
    "sg:province":"IA",
    "wof:name":"Mediapolis Savings Bank",
    "wof:placetype":"venue"
},
  "geometry": {"coordinates":[-91.164114,41.007979],"type":"Point"}
}