{
  "type": "Feature",
  "properties": {
    "iso:country":"US",
    "sg:address":"72551 130th St",
    "sg:city":"Le Roy",
    "sg:phone":"+1 507 324 5962",
    "sg:postcode":"55951",
    "sg:province":"IA",
    "sg:tags":[
        "hog",
        "farm",
        "corn",
        "soybean",
        "or",
        "feedlot"
    ],
    "wof:name":"Paul Yoch",
    "wof:placetype":"venue"
},
  "geometry": {"coordinates":[-92.58917099999999,43.543661],"type":"Point"}
}