{
  "type": "Feature",
  "properties": {
    "iso:country":"US",
    "sg:address":"2308 Heinz Rd",
    "sg:city":"Iowa City",
    "sg:classifiers":[
        {
            "category":"Professional",
            "subcategory":"Management & Consulting",
            "type":"Services"
        }
    ],
    "sg:phone":"+1 319 354 7600",
    "sg:postcode":"52240",
    "sg:province":"IA",
    "sg:tags":[
        "test",
        "preparation",
        "instruction"
    ],
    "sg:website":"www.buckledown.com",
    "wof:name":"Buckle Down Publishing Co",
    "wof:placetype":"venue"
},
  "geometry": {"coordinates":[-91.489474,41.634504],"type":"Point"}
}