{
  "type": "Feature",
  "properties": {
    "iso:country":"US",
    "sg:address":"323 Chickasaw St",
    "sg:city":"Nashua",
    "sg:phone":"+1 641 435 4964",
    "sg:postcode":"50658",
    "sg:province":"IA",
    "sg:tags":[
        "farm",
        "corn"
    ],
    "wof:name":"R L Muench",
    "wof:placetype":"venue"
},
  "geometry": {"coordinates":[-92.535265,42.96024],"type":"Point"}
}