{
  "type": "Feature",
  "properties": {
    "addr:full":"602 N Main Ave Huxley IA 50124",
    "addr:housenumber":"602",
    "addr:postcode":"50124",
    "addr:street":"N Main Ave",
    "iso:country":"US",
    "sg:address":"602 N Main Ave",
    "sg:city":"Huxley",
    "sg:classifiers":[
        {
            "category":"Health Services",
            "subcategory":"Doctor",
            "type":"Services"
        }
    ],
    "sg:phone":"+1 515 597 2800",
    "sg:postcode":"50124",
    "sg:province":"IA",
    "sg:tags":[
        "dentist"
    ],
    "wof:name":"Michael L Mc Gregor DDS",
    "wof:placetype":"venue"
},
  "geometry": {"coordinates":[-93.605543,41.899874],"type":"Point"}
}