{
  "type": "Feature",
  "properties": {
    "iso:country":"US",
    "sg:address":"1201 W Bremer Ave",
    "sg:city":"Waverly",
    "sg:classifiers":[
        {
            "category":"Personal",
            "type":"Services"
        }
    ],
    "sg:phone":"+1 319 352 9070",
    "sg:postcode":"50677",
    "sg:province":"IA",
    "sg:tags":[
        "program",
        "physical",
        "exercise",
        "fitness"
    ],
    "wof:name":"Curves For Women",
    "wof:placetype":"venue"
},
  "geometry": {"coordinates":[-92.48494599999999,42.72566],"type":"Point"}
}