{
  "type": "Feature",
  "properties": {
    "iso:country":"US",
    "sg:address":"111 Forbes St",
    "sg:city":"Essex",
    "sg:classifiers":[
        {
            "category":"Education",
            "subcategory":"School",
            "type":"Public Place"
        }
    ],
    "sg:phone":"+1 712 379 3114",
    "sg:postcode":"51638",
    "sg:province":"IA",
    "wof:name":"Essex Elementary School",
    "wof:placetype":"venue"
},
  "geometry": {"coordinates":[-95.30862500000001,40.828671],"type":"Point"}
}