{
  "type": "Feature",
  "properties": {
    "iso:country":"US",
    "sg:address":"2401 SE 14th St",
    "sg:city":"Des Moines",
    "sg:classifiers":[
        {
            "category":"Autos & Motor Vehicles",
            "subcategory":"Recreational Vehicle Sales",
            "type":"Retail Goods"
        }
    ],
    "sg:phone":"+1 515 280 1026",
    "sg:postcode":"50320",
    "sg:province":"IA",
    "wof:name":"Gary's Trailer Sales Inc",
    "wof:placetype":"venue"
},
  "geometry": {"coordinates":[-93.596953,41.562886],"type":"Point"}
}