{
  "type": "Feature",
  "properties": {
    "addr:full":"408 3rd St Menlo IA 50164",
    "addr:housenumber":"408",
    "addr:postcode":"50164",
    "addr:street":"3Rd St",
    "iso:country":"US",
    "sg:address":"408 3rd St",
    "sg:city":"Menlo",
    "sg:classifiers":[
        {
            "category":"Building & Trades",
            "subcategory":"Plumbing",
            "type":"Services"
        }
    ],
    "sg:phone":"+1 641 524 2161",
    "sg:postcode":"50164",
    "sg:province":"IA",
    "sg:tags":[
        "conditioning",
        "air",
        "system",
        "contractor"
    ],
    "wof:name":"Miller Plumbing Heating & Elec",
    "wof:placetype":"venue"
},
  "geometry": {"coordinates":[-94.406021,41.522692],"type":"Point"}
}