{
  "type": "Feature",
  "properties": {
    "addr:full":"323 14th St Ackley IA 50601",
    "addr:housenumber":"323",
    "addr:postcode":"50601",
    "addr:street":"14Th St",
    "iso:country":"US",
    "sg:address":"323 14th St",
    "sg:city":"Ackley",
    "sg:classifiers":[
        {
            "category":"Autos & Motor Vehicles",
            "subcategory":"Auto Supplies",
            "type":"Retail Goods"
        }
    ],
    "sg:phone":"+1 641 847 3561",
    "sg:postcode":"50601",
    "sg:province":"IA",
    "sg:tags":[
        "tire"
    ],
    "wof:name":"Randy's Tire Svc",
    "wof:placetype":"venue"
},
  "geometry": {"coordinates":[-93.06064000000001,42.553343],"type":"Point"}
}