{
  "type": "Feature",
  "properties": {
    "addr:full":"1530 W 53rd St Davenport IA 52806",
    "addr:housenumber":"1530",
    "addr:postcode":"52806",
    "addr:street":"W 53Rd St",
    "iso:country":"US",
    "sg:address":"1530 W 53rd St",
    "sg:city":"Davenport",
    "sg:classifiers":[
        {
            "category":"Banks & Credit Unions",
            "subcategory":"Bank",
            "type":"Services"
        }
    ],
    "sg:phone":"+1 563 388 8328",
    "sg:postcode":"52806",
    "sg:province":"IA",
    "wof:name":"Family Credit Union",
    "wof:placetype":"venue"
},
  "geometry": {"coordinates":[-90.59735999999999,41.574501],"type":"Point"}
}