{
  "type": "Feature",
  "properties": {
    "iso:country":"US",
    "sg:address":"103 4th St",
    "sg:city":"Lowden",
    "sg:classifiers":[
        {
            "category":"Building & Trades",
            "subcategory":"Plumbing",
            "type":"Services"
        }
    ],
    "sg:phone":"+1 563 944 7700",
    "sg:postcode":"52255",
    "sg:province":"IA",
    "sg:tags":[
        "conditioning",
        "air",
        "system",
        "contractor"
    ],
    "wof:name":"Kruckenberg Plumbing & Heating",
    "wof:placetype":"venue"
},
  "geometry": {"coordinates":[-90.922645,41.858262],"type":"Point"}
}