{
  "type": "Feature",
  "properties": {
    "iso:country":"US",
    "sg:address":"1305 W Milwaukee Ave",
    "sg:city":"Storm Lake",
    "sg:classifiers":[
        {
            "category":"Health Services",
            "subcategory":"Nursing And Care Facility",
            "type":"Services"
        }
    ],
    "sg:phone":"+1 712 749 2747",
    "sg:postcode":"50588",
    "sg:province":"IA",
    "sg:tags":[
        "hospice"
    ],
    "wof:name":"Buena Vista Regional Med Ctr",
    "wof:placetype":"venue"
},
  "geometry": {"coordinates":[-95.21852699999999,42.648281],"type":"Point"}
}