{
  "type": "Feature",
  "properties": {
    "iso:country":"US",
    "sg:address":"2170 NE Broadway Ave",
    "sg:city":"Des Moines",
    "sg:classifiers":[
        {
            "category":"Wholesale",
            "subcategory":"Hardware",
            "type":"Manufacturing & Wholesale Goods"
        }
    ],
    "sg:phone":"+1 515 261 3474",
    "sg:postcode":"50313",
    "sg:province":"IA",
    "sg:tags":[
        "plumbing",
        "fixture",
        "supply"
    ],
    "wof:name":"Mc Donald Supply",
    "wof:placetype":"venue"
},
  "geometry": {"coordinates":[-93.58286099999999,41.644221],"type":"Point"}
}