{
  "type": "Feature",
  "properties": {
    "iso:country":"US",
    "sg:address":"4504 Forest Ave",
    "sg:city":"Des Moines",
    "sg:classifiers":[
        {
            "category":"Building & Trades",
            "subcategory":"Construction",
            "type":"Services"
        }
    ],
    "sg:phone":"+1 515 274 1883",
    "sg:postcode":"50311",
    "sg:province":"IA",
    "sg:tags":[
        "painter"
    ],
    "wof:name":"Peterson Painting",
    "wof:placetype":"venue"
},
  "geometry": {"coordinates":[-93.680132,41.60392],"type":"Point"}
}