{
  "type": "Feature",
  "properties": {
    "iso:country":"US",
    "sg:address":"107 Cedar St SE",
    "sg:city":"Blairstown",
    "sg:classifiers":[
        {
            "category":"Education",
            "subcategory":"School",
            "type":"Public Place"
        }
    ],
    "sg:phone":"+1 319 454 6263",
    "sg:postcode":"52209",
    "sg:province":"IA",
    "wof:name":"Blairstown Schools",
    "wof:placetype":"venue"
},
  "geometry": {"coordinates":[-92.082717,41.906268],"type":"Point"}
}