{
  "type": "Feature",
  "properties": {
    "addr:full":"506 Main St Swaledale IA 50477",
    "addr:housenumber":"506",
    "addr:postcode":"50477",
    "addr:street":"Main St",
    "iso:country":"US",
    "sg:address":"506 Main St",
    "sg:city":"Swaledale",
    "sg:classifiers":[
        {
            "category":"Banks & Credit Unions",
            "subcategory":"Bank",
            "type":"Services"
        }
    ],
    "sg:phone":"+1 641 995 2312",
    "sg:postcode":"50477",
    "sg:province":"IA",
    "wof:name":"First State Bank",
    "wof:placetype":"venue"
},
  "geometry": {"coordinates":[-93.312989,42.978509],"type":"Point"}
}