{
  "type": "Feature",
  "properties": {
    "iso:country":"US",
    "sg:address":"214 E Main St",
    "sg:city":"Anamosa",
    "sg:classifiers":[
        {
            "category":"Personal",
            "subcategory":"Barber",
            "type":"Services"
        }
    ],
    "sg:phone":"+1 319 462 4662",
    "sg:postcode":"52205",
    "sg:province":"IA",
    "wof:name":"Razor's Edge",
    "wof:placetype":"venue"
},
  "geometry": {"coordinates":[-91.283996,42.10837],"type":"Point"}
}