{
  "type": "Feature",
  "properties": {
    "addr:full":"472 W 4th St Dubuque IA 52001",
    "addr:housenumber":"472",
    "addr:postcode":"52001",
    "addr:street":"W 4Th St",
    "iso:country":"US",
    "sg:address":"472 W 4th St",
    "sg:city":"Dubuque",
    "sg:classifiers":[
        {
            "category":"Home & Garden",
            "subcategory":"Furniture",
            "type":"Retail Goods"
        }
    ],
    "sg:phone":"+1 563 557 8159",
    "sg:postcode":"52001",
    "sg:province":"IA",
    "wof:name":"Tomorrows Treasures",
    "wof:placetype":"venue"
},
  "geometry": {"coordinates":[-90.66797,42.496784],"type":"Point"}
}