{
  "type": "Feature",
  "properties": {
    "addr:full":"11542 205th St Steamboat Rock IA 50672",
    "addr:housenumber":"11542",
    "addr:postcode":"50672",
    "addr:street":"205Th St",
    "iso:country":"US",
    "sg:address":"11542 205th St",
    "sg:city":"Steamboat Rock",
    "sg:classifiers":[
        {
            "category":"Farming",
            "subcategory":"Farm",
            "type":"Manufacturing & Wholesale Goods"
        }
    ],
    "sg:phone":"+1 641 869 3765",
    "sg:postcode":"50672",
    "sg:province":"IA",
    "sg:tags":[
        "crop",
        "general"
    ],
    "wof:name":"Richard Steppe Farms",
    "wof:placetype":"venue"
},
  "geometry": {"coordinates":[-92.98351099999999,42.405106],"type":"Point"}
}