{
  "type": "Feature",
  "properties": {
    "iso:country":"US",
    "sg:address":"1327 6th St SW",
    "sg:city":"Mason City",
    "sg:classifiers":[
        {
            "category":"Health Services",
            "subcategory":"Doctor",
            "type":"Services"
        }
    ],
    "sg:phone":"+1 641 423 0711",
    "sg:postcode":"50401",
    "sg:province":"IA",
    "sg:tags":[
        "physician",
        "surgeon"
    ],
    "wof:name":"Lindstrom Family Practice",
    "wof:placetype":"venue"
},
  "geometry": {"coordinates":[-93.223631,43.146397],"type":"Point"}
}