{
  "type": "Feature",
  "properties": {
    "iso:country":"US",
    "sg:address":"1251 University Ave",
    "sg:city":"Des Moines",
    "sg:classifiers":[
        {
            "category":"Government",
            "subcategory":"Office",
            "type":"Public Place"
        }
    ],
    "sg:phone":"+1 515 248 6213",
    "sg:postcode":"50314",
    "sg:province":"IA",
    "sg:tags":[
        "village"
    ],
    "wof:name":"Des Moines Model City",
    "wof:placetype":"venue"
},
  "geometry": {"coordinates":[-93.633737,41.600516],"type":"Point"}
}