{
  "type": "Feature",
  "properties": {
    "addr:full":"1751 Madison Ave Ste 326 Council Bluffs IA 51503",
    "addr:housenumber":"1751",
    "addr:postcode":"51503",
    "addr:street":"Madison Ave Ste 326",
    "iso:country":"US",
    "sg:address":"1751 Madison Ave Ste 326",
    "sg:city":"Council Bluffs",
    "sg:classifiers":[
        {
            "category":"Shopping",
            "subcategory":"Clothing, Apparel, & Fashions",
            "type":"Retail Goods"
        }
    ],
    "sg:phone":"+1 712 388 9037",
    "sg:postcode":"51503",
    "sg:province":"IA",
    "sg:tags":[
        "children's",
        "clothing"
    ],
    "sg:website":"www.childrensplace.com",
    "wof:name":"Children's Place",
    "wof:placetype":"venue"
},
  "geometry": {"coordinates":[-95.82710299999999,41.243999],"type":"Point"}
}