{
  "type": "Feature",
  "properties": {
    "addr:full":"1821 180th St Boone IA 50036",
    "addr:housenumber":"1821",
    "addr:postcode":"50036",
    "addr:street":"180Th St",
    "iso:country":"US",
    "sg:address":"1821 180th St",
    "sg:city":"Boone",
    "sg:phone":"+1 515 432 9933",
    "sg:postcode":"50036",
    "sg:province":"IA",
    "sg:tags":[
        "farm",
        "corn",
        "soybean"
    ],
    "wof:name":"CB Acres Inc",
    "wof:placetype":"venue"
},
  "geometry": {"coordinates":[-93.81020599999999,42.088992],"type":"Point"}
}