{
  "type": "Feature",
  "properties": {
    "iso:country":"US",
    "sg:address":"1429 400th St",
    "sg:city":"Avoca",
    "sg:phone":"+1 712 343 2490",
    "sg:postcode":"51521",
    "sg:province":"IA",
    "sg:tags":[
        "hog",
        "farm",
        "corn",
        "soybean",
        "or",
        "feedlot"
    ],
    "wof:name":"Ralph Klindt",
    "wof:placetype":"venue"
},
  "geometry": {"coordinates":[-95.29776699999999,41.548213],"type":"Point"}
}