{
  "type": "Feature",
  "properties": {
    "iso:country":"US",
    "sg:address":"2550 Camanche Ave",
    "sg:city":"Clinton",
    "sg:classifiers":[
        {
            "category":"Building & Trades",
            "subcategory":"Construction",
            "type":"Services"
        }
    ],
    "sg:phone":"+1 563 242 1111",
    "sg:postcode":"52732",
    "sg:province":"IA",
    "sg:tags":[
        "excavating",
        "contractor"
    ],
    "wof:name":"A-1 Budget Backhoe & Trucking",
    "wof:placetype":"venue"
},
  "geometry": {"coordinates":[-90.216114,41.819983],"type":"Point"}
}