{
  "type": "Feature",
  "properties": {
    "addr:full":"1755 Springview Dr Mason City IA 50401",
    "addr:housenumber":"1755",
    "addr:postcode":"50401",
    "addr:street":"Springview Dr",
    "iso:country":"US",
    "sg:address":"1755 Springview Dr",
    "sg:city":"Mason City",
    "sg:classifiers":[
        {
            "category":"Organizations",
            "subcategory":"Community Association",
            "type":"Services"
        }
    ],
    "sg:phone":"+1 641 424 6752",
    "sg:postcode":"50401",
    "sg:province":"IA",
    "wof:name":"Kiwanis International Inc",
    "wof:placetype":"venue"
},
  "geometry": {"coordinates":[-93.228869,43.143622],"type":"Point"}
}