{
  "type": "Feature",
  "properties": {
    "iso:country":"US",
    "sg:address":"524 3rd Ave S",
    "sg:city":"Clinton",
    "sg:classifiers":[
        {
            "category":"Building & Trades",
            "subcategory":"Plumbing",
            "type":"Services"
        }
    ],
    "sg:phone":"+1 563 242 4563",
    "sg:postcode":"52732",
    "sg:province":"IA",
    "sg:tags":[
        "heating",
        "contractor"
    ],
    "wof:name":"RHA Svc Inc",
    "wof:placetype":"venue"
},
  "geometry": {"coordinates":[-90.19649800000001,41.843466],"type":"Point"}
}