{
  "type": "Feature",
  "properties": {
    "iso:country":"US",
    "sg:address":"30401 400th Ave",
    "sg:city":"Bellevue",
    "sg:classifiers":[
        {
            "category":"Home & Garden",
            "subcategory":"Building Materials",
            "type":"Retail Goods"
        }
    ],
    "sg:phone":"+1 563 872 3127",
    "sg:postcode":"52031",
    "sg:province":"IA",
    "sg:tags":[
        "lumber"
    ],
    "wof:name":"Crown Hardwood Co Inc",
    "wof:placetype":"venue"
},
  "geometry": {"coordinates":[-90.43302799999999,42.300129],"type":"Point"}
}