{
  "type": "Feature",
  "properties": {
    "iso:country":"US",
    "sg:address":"5355 Eastern Ave",
    "sg:city":"Davenport",
    "sg:classifiers":[
        {
            "category":"Health Services",
            "subcategory":"Health Practitioner",
            "type":"Services"
        }
    ],
    "sg:phone":"+1 563 355 3867",
    "sg:postcode":"52807",
    "sg:province":"IA",
    "sg:tags":[
        "therapist",
        "physical"
    ],
    "wof:name":"Physical Therapy Ctr",
    "wof:placetype":"venue"
},
  "geometry": {"coordinates":[-90.55123399999999,41.574861],"type":"Point"}
}