{
  "type": "Feature",
  "properties": {
    "addr:full":"6632 Northwest Blvd Davenport IA 52806",
    "addr:housenumber":"6632",
    "addr:postcode":"52806",
    "addr:street":"Northwest Blvd",
    "iso:country":"US",
    "sg:address":"6632 Northwest Blvd",
    "sg:city":"Davenport",
    "sg:classifiers":[
        {
            "category":"Education",
            "subcategory":"Dance Studio",
            "type":"Public Place"
        }
    ],
    "sg:phone":"+1 563 386 7595",
    "sg:postcode":"52806",
    "sg:province":"IA",
    "sg:tags":[
        "instruction",
        "dancing"
    ],
    "wof:name":"Gruv Factory",
    "wof:placetype":"venue"
},
  "geometry": {"coordinates":[-90.609908,41.589304],"type":"Point"}
}