{
  "type": "Feature",
  "properties": {
    "iso:country":"US",
    "sg:address":"205 Olympic Ave",
    "sg:city":"Carroll",
    "sg:classifiers":[
        {
            "category":"Organizations",
            "subcategory":"Religious Organization",
            "type":"Services"
        }
    ],
    "sg:phone":"+1 712 792 4516",
    "sg:postcode":"51401",
    "sg:province":"IA",
    "sg:tags":[
        "church"
    ],
    "wof:name":"St Mary's",
    "wof:placetype":"venue"
},
  "geometry": {"coordinates":[-94.822478,41.980489],"type":"Point"}
}