{
  "type": "Feature",
  "properties": {
    "iso:country":"US",
    "sg:address":"112 Thomas Jefferson Dr",
    "sg:city":"Newton",
    "sg:classifiers":[
        {
            "category":"Social Services",
            "subcategory":"Child Care",
            "type":"Services"
        }
    ],
    "sg:phone":"+1 641 792 1394",
    "sg:postcode":"50208",
    "sg:province":"IA",
    "wof:name":"Head Start Newton Ctr",
    "wof:placetype":"venue"
},
  "geometry": {"coordinates":[-93.077263,41.699939],"type":"Point"}
}