{
  "type": "Feature",
  "properties": {
    "iso:country":"US",
    "sg:address":"311 E Broadway St",
    "sg:city":"Moulton",
    "sg:classifiers":[
        {
            "category":"Retail",
            "subcategory":"Funeral Services",
            "type":"Services"
        }
    ],
    "sg:phone":"+1 641 642 3221",
    "sg:postcode":"52572",
    "sg:province":"IA",
    "sg:tags":[
        "director"
    ],
    "wof:name":"Schmidt Family Funeral Home",
    "wof:placetype":"venue"
},
  "geometry": {"coordinates":[-92.67446099999999,40.687006],"type":"Point"}
}