{
  "type": "Feature",
  "properties": {
    "iso:country":"US",
    "sg:address":"3123 Troy Mills Blvd",
    "sg:city":"Walker",
    "sg:phone":"+1 319 224 3614",
    "sg:postcode":"50682",
    "sg:province":"IA",
    "sg:tags":[
        "farm",
        "corn",
        "soybean"
    ],
    "wof:name":"Rawson Derald",
    "wof:placetype":"venue"
},
  "geometry": {"coordinates":[-91.676481,42.33691],"type":"Point"}
}