{
  "type": "Feature",
  "properties": {
    "iso:country":"US",
    "sg:address":"3113 Pleasant St",
    "sg:city":"West Des Moines",
    "sg:classifiers":[
        {
            "category":"Professional",
            "subcategory":"Management & Consulting",
            "type":"Services"
        }
    ],
    "sg:phone":"+1 515 223 1366",
    "sg:postcode":"50266",
    "sg:province":"IA",
    "sg:tags":[
        "building",
        "nonresidential",
        "business",
        "op"
    ],
    "wof:name":"Energy Advisors Ltd",
    "wof:placetype":"venue"
},
  "geometry": {"coordinates":[-93.74741899999999,41.591573],"type":"Point"}
}