{
  "type": "Feature",
  "properties": {
    "addr:full":"602 Tilford St Dysart IA 52224",
    "addr:housenumber":"602",
    "addr:postcode":"52224",
    "addr:street":"Tilford St",
    "iso:country":"US",
    "sg:address":"602 Tilford St",
    "sg:city":"Dysart",
    "sg:classifiers":[
        {
            "category":"Organizations",
            "subcategory":"Religious Organization",
            "type":"Services"
        }
    ],
    "sg:phone":"+1 319 476 2750",
    "sg:postcode":"52224",
    "sg:province":"IA",
    "sg:tags":[
        "church"
    ],
    "wof:name":"United Methodist Church",
    "wof:placetype":"venue"
},
  "geometry": {"coordinates":[-92.309038,42.168384],"type":"Point"}
}