{
  "type": "Feature",
  "properties": {
    "iso:country":"US",
    "sg:address":"302 E 7th St",
    "sg:city":"Sanborn",
    "sg:classifiers":[
        {
            "category":"Insurance",
            "subcategory":"Insurance Agent",
            "type":"Services"
        }
    ],
    "sg:phone":"+1 712 729 5350",
    "sg:postcode":"51248",
    "sg:province":"IA",
    "wof:name":"Donkersloot Insurance",
    "wof:placetype":"venue"
},
  "geometry": {"coordinates":[-95.65302800000001,43.186104],"type":"Point"}
}