{
  "type": "Feature",
  "properties": {
    "addr:full":"218 1st Ave SE Hampton IA 50441",
    "addr:housenumber":"218",
    "addr:postcode":"50441",
    "addr:street":"1St Ave Se",
    "iso:country":"US",
    "sg:address":"218 1st Ave SE",
    "sg:city":"Hampton",
    "sg:classifiers":[
        {
            "category":"Retail",
            "subcategory":"Repair Shop",
            "type":"Services"
        }
    ],
    "sg:phone":"+1 641 456 3557",
    "sg:postcode":"50441",
    "sg:province":"IA",
    "wof:name":"Keiths Krafts & Fix It",
    "wof:placetype":"venue"
},
  "geometry": {"coordinates":[-93.20475500000001,42.740986],"type":"Point"}
}