{
  "type": "Feature",
  "properties": {
    "addr:full":"1762 Maura Knoll Dr Cedar Rapids IA 52403",
    "addr:housenumber":"1762",
    "addr:postcode":"52403",
    "addr:street":"Maura Knoll Dr",
    "iso:country":"US",
    "sg:address":"1762 Maura Knoll Dr",
    "sg:city":"Cedar Rapids",
    "sg:classifiers":[
        {
            "category":"Building & Trades",
            "subcategory":"Construction",
            "type":"Services"
        }
    ],
    "sg:phone":"+1 319 366 7858",
    "sg:postcode":"52403",
    "sg:province":"IA",
    "sg:tags":[
        "house"
    ],
    "wof:name":"Ferguson Const",
    "wof:placetype":"venue"
},
  "geometry": {"coordinates":[-91.538642,41.929088],"type":"Point"}
}