{
  "type": "Feature",
  "properties": {
    "iso:country":"US",
    "sg:address":"1874 695th Ave",
    "sg:city":"Albia",
    "sg:phone":"+1 641 932 2487",
    "sg:postcode":"52531",
    "sg:province":"IA",
    "sg:tags":[
        "farm",
        "corn"
    ],
    "wof:name":"Walter Templer",
    "wof:placetype":"venue"
},
  "geometry": {"coordinates":[-92.719274,41.037797],"type":"Point"}
}