{
  "type": "Feature",
  "properties": {
    "iso:country":"US",
    "sg:address":"13580 780th Ave",
    "sg:city":"Le Roy",
    "sg:phone":"+1 507 324 5254",
    "sg:postcode":"55951",
    "sg:province":"IA",
    "sg:tags":[
        "farm",
        "soybean"
    ],
    "wof:name":"Mark Withey",
    "wof:placetype":"venue"
},
  "geometry": {"coordinates":[-92.489171,43.545254],"type":"Point"}
}