{
  "type": "Feature",
  "properties": {
    "iso:country":"US",
    "sg:address":"101 N Main St",
    "sg:city":"Roland",
    "sg:classifiers":[
        {
            "category":"Retail",
            "subcategory":"Auto Repair",
            "type":"Services"
        }
    ],
    "sg:phone":"+1 515 388 4534",
    "sg:postcode":"50236",
    "sg:province":"IA",
    "sg:tags":[
        "repairing",
        "automobile"
    ],
    "wof:name":"Roland Service Ctr",
    "wof:placetype":"venue"
},
  "geometry": {"coordinates":[-93.50048,42.167708],"type":"Point"}
}