{
  "type": "Feature",
  "properties": {
    "iso:country":"US",
    "sg:address":"1306 180th St",
    "sg:city":"Clemons",
    "sg:classifiers":[
        {
            "category":"Building & Trades",
            "subcategory":"Landscaping Services",
            "type":"Services"
        }
    ],
    "sg:phone":"+1 641 477 8210",
    "sg:postcode":"50051",
    "sg:province":"IA",
    "sg:tags":[
        "lawn",
        "maintenance",
        "grounds"
    ],
    "wof:name":"Calkins Lawn Care",
    "wof:placetype":"venue"
},
  "geometry": {"coordinates":[-93.17321699999999,42.092054],"type":"Point"}
}