{
  "type": "Feature",
  "properties": {
    "iso:country":"US",
    "sg:address":"3917 530th Ave",
    "sg:city":"Ames",
    "sg:classifiers":[
        {
            "category":"Real Estate",
            "subcategory":"Real Estate Operator",
            "type":"Services"
        }
    ],
    "sg:phone":"+1 515 292 7377",
    "sg:postcode":"50010",
    "sg:province":"IA",
    "sg:tags":[
        "property",
        "lessor"
    ],
    "wof:name":"Kingsbury Weldon",
    "wof:placetype":"venue"
},
  "geometry": {"coordinates":[-93.639431,41.991486],"type":"Point"}
}