{
  "type": "Feature",
  "properties": {
    "addr:full":"111 Weimer St Ventura IA 50482",
    "addr:housenumber":"111",
    "addr:postcode":"50482",
    "addr:street":"Weimer St",
    "iso:country":"US",
    "sg:address":"111 Weimer St",
    "sg:city":"Ventura",
    "sg:classifiers":[
        {
            "category":"Wholesale",
            "subcategory":"Farm Supplies",
            "type":"Manufacturing & Wholesale Goods"
        }
    ],
    "sg:phone":"+1 641 829 3891",
    "sg:postcode":"50482",
    "sg:province":"IA",
    "sg:tags":[
        "grain"
    ],
    "wof:name":"Top Of Iowa",
    "wof:placetype":"venue"
},
  "geometry": {"coordinates":[-93.478899,43.128626],"type":"Point"}
}