{
  "type": "Feature",
  "properties": {
    "iso:country":"US",
    "sg:address":"109 S Walnut St",
    "sg:city":"Glenwood",
    "sg:classifiers":[
        {
            "category":"Shopping",
            "subcategory":"Department Store",
            "type":"Retail Goods"
        }
    ],
    "sg:phone":"+1 712 527 9108",
    "sg:postcode":"51534",
    "sg:province":"IA",
    "sg:tags":[
        "shop"
    ],
    "wof:name":"Family Dollar Store",
    "wof:placetype":"venue"
},
  "geometry": {"coordinates":[-95.74318599999999,41.046179],"type":"Point"}
}