{
  "type": "Feature",
  "properties": {
    "iso:country":"US",
    "sg:address":"4601 1st Ave SE Ste 1",
    "sg:city":"Cedar Rapids",
    "sg:classifiers":[
        {
            "category":"Shopping",
            "subcategory":"Department Store",
            "type":"Retail Goods"
        }
    ],
    "sg:phone":"+1 319 393 3809",
    "sg:postcode":"52402",
    "sg:province":"IA",
    "sg:website":"www.gordmans.com",
    "wof:name":"Gordmans",
    "wof:placetype":"venue"
},
  "geometry": {"coordinates":[-91.624414,42.023788],"type":"Point"}
}