{
  "type": "Feature",
  "properties": {
    "addr:full":"7143 W Bennington Rd Cedar Falls IA 50613",
    "addr:housenumber":"7143",
    "addr:postcode":"50613",
    "addr:street":"W Bennington Rd",
    "iso:country":"US",
    "sg:address":"7143 W Bennington Rd",
    "sg:city":"Cedar Falls",
    "sg:classifiers":[
        {
            "category":"Professional",
            "subcategory":"Art Services",
            "type":"Services"
        }
    ],
    "sg:phone":"+1 319 987 3329",
    "sg:postcode":"50613",
    "sg:province":"IA",
    "sg:tags":[
        "commercial",
        "design"
    ],
    "wof:name":"Dan Damjanovic",
    "wof:placetype":"venue"
},
  "geometry": {"coordinates":[-92.475713,42.599046],"type":"Point"}
}