{
  "type": "Feature",
  "properties": {
    "iso:country":"US",
    "sg:address":"1113 Essex St",
    "sg:city":"Iowa City",
    "sg:classifiers":[
        {
            "category":"Professional",
            "type":"Services"
        }
    ],
    "sg:phone":"+1 319 354 5265",
    "sg:postcode":"52240",
    "sg:province":"IA",
    "wof:name":"Pogie Inc",
    "wof:placetype":"venue"
},
  "geometry": {"coordinates":[-91.49302900000001,41.647629],"type":"Point"}
}