{
  "type": "Feature",
  "properties": {
    "iso:country":"US",
    "sg:address":"1030 S 2nd St",
    "sg:city":"Cherokee",
    "sg:classifiers":[
        {
            "category":"Banks & Credit Unions",
            "subcategory":"Bank",
            "type":"Services"
        }
    ],
    "sg:phone":"+1 712 225 5731",
    "sg:postcode":"51012",
    "sg:province":"IA",
    "sg:website":"www.nsccu.org",
    "wof:name":"North Star COMMUNITY Cu",
    "wof:placetype":"venue"
},
  "geometry": {"coordinates":[-95.551557,42.740913],"type":"Point"}
}