{
  "type": "Feature",
  "properties": {
    "iso:country":"US",
    "sg:address":"903 200th St",
    "sg:city":"Algona",
    "sg:classifiers":[
        {
            "category":"Farming",
            "subcategory":"Farm",
            "type":"Manufacturing & Wholesale Goods"
        }
    ],
    "sg:phone":"+1 515 295 2918",
    "sg:postcode":"50511",
    "sg:province":"IA",
    "sg:tags":[
        "crop",
        "general"
    ],
    "wof:name":"Jengar Inc",
    "wof:placetype":"venue"
},
  "geometry": {"coordinates":[-94.28587899999999,43.052806],"type":"Point"}
}