{
  "type": "Feature",
  "properties": {
    "iso:country":"US",
    "sg:address":"4333 University Ave",
    "sg:city":"Des Moines",
    "sg:classifiers":[
        {
            "category":"Building & Trades",
            "subcategory":"Cleaning & Sanitation",
            "type":"Services"
        }
    ],
    "sg:phone":"+1 515 255 8479",
    "sg:postcode":"50311",
    "sg:province":"IA",
    "sg:tags":[
        "house"
    ],
    "wof:name":"Melissa Nelson's Home Cleaning",
    "wof:placetype":"venue"
},
  "geometry": {"coordinates":[-93.67759700000001,41.600423],"type":"Point"}
}