{
  "type": "Feature",
  "properties": {
    "addr:full":"118 Main St Moville IA 51039",
    "addr:housenumber":"118",
    "addr:postcode":"51039",
    "addr:street":"Main St",
    "iso:country":"US",
    "sg:address":"118 Main St",
    "sg:city":"Moville",
    "sg:classifiers":[
        {
            "category":"Retail",
            "subcategory":"Auto Repair",
            "type":"Services"
        }
    ],
    "sg:phone":"+1 712 873 3400",
    "sg:postcode":"51039",
    "sg:province":"IA",
    "sg:tags":[
        "repairing",
        "automobile"
    ],
    "wof:name":"J & J Motor Co",
    "wof:placetype":"venue"
},
  "geometry": {"coordinates":[-96.073987,42.488728],"type":"Point"}
}