{
  "type": "Feature",
  "properties": {
    "addr:full":"507 Main St Coon Rapids IA 50058",
    "addr:housenumber":"507",
    "addr:postcode":"50058",
    "addr:street":"Main St",
    "iso:country":"US",
    "sg:address":"507 Main St",
    "sg:city":"Coon Rapids",
    "sg:classifiers":[
        {
            "category":"Government",
            "subcategory":"Post Office",
            "type":"Public Place"
        }
    ],
    "sg:phone":"+1 712 684 2224",
    "sg:postcode":"50058",
    "sg:province":"IA",
    "wof:name":"US Post Office",
    "wof:placetype":"venue"
},
  "geometry": {"coordinates":[-94.67879499999999,41.870861],"type":"Point"}
}