{
  "type": "Feature",
  "properties": {
    "iso:country":"US",
    "sg:address":"4333 Czech Ln NE",
    "sg:city":"Cedar Rapids",
    "sg:classifiers":[
        {
            "category":"Bagels",
            "subcategory":"None",
            "type":"Food & Drink"
        }
    ],
    "sg:phone":"+1 319 378 0033",
    "sg:postcode":"52402",
    "sg:province":"IA",
    "wof:name":"Bagelicious",
    "wof:placetype":"venue"
},
  "geometry": {"coordinates":[-91.666496,42.022701],"type":"Point"}
}