{
  "type": "Feature",
  "properties": {
    "addr:full":"130 W 6th St Kanawha IA 50447",
    "addr:housenumber":"130",
    "addr:postcode":"50447",
    "addr:street":"W 6Th St",
    "iso:country":"US",
    "sg:address":"130 W 6th St",
    "sg:city":"Kanawha",
    "sg:classifiers":[
        {
            "category":"Health Services",
            "subcategory":"Nursing And Care Facility",
            "type":"Services"
        }
    ],
    "sg:phone":"+1 641 762 3302",
    "sg:postcode":"50447",
    "sg:province":"IA",
    "sg:tags":[
        "home",
        "convalescent"
    ],
    "wof:name":"Kanawha Community Nursing Home",
    "wof:placetype":"venue"
},
  "geometry": {"coordinates":[-93.79573499999999,42.93877],"type":"Point"}
}