{
  "type": "Feature",
  "properties": {
    "addr:full":"52 3rd Avenue Brg Cedar Rapids IA 52401",
    "addr:housenumber":"52",
    "addr:postcode":"52401",
    "addr:street":"3Rd Avenue",
    "iso:country":"US",
    "sg:address":"52 3rd Avenue Brg",
    "sg:city":"Cedar Rapids",
    "sg:classifiers":[
        {
            "category":"Government",
            "subcategory":"Court House",
            "type":"Public Place"
        }
    ],
    "sg:phone":"+1 319 398 3411",
    "sg:postcode":"52401",
    "sg:province":"IA",
    "sg:tags":[
        "city"
    ],
    "wof:name":"District Court-Civil Div",
    "wof:placetype":"venue"
},
  "geometry": {"coordinates":[-91.67008300000001,41.97547],"type":"Point"}
}