{
  "type": "Feature",
  "properties": {
    "iso:country":"US",
    "sg:address":"2253 S Riverside Dr",
    "sg:city":"Iowa City",
    "sg:classifiers":[
        {
            "category":"Professional",
            "subcategory":"Accounting & Tax Preparation",
            "type":"Services"
        }
    ],
    "sg:phone":"+1 319 337 5528",
    "sg:postcode":"52246",
    "sg:province":"IA",
    "sg:tags":[
        "accountant"
    ],
    "wof:name":"Moeller Accounting Svc",
    "wof:placetype":"venue"
},
  "geometry": {"coordinates":[-91.538465,41.633955],"type":"Point"}
}