{
  "type": "Feature",
  "properties": {
    "addr:full":"208 1st Ave W Worthington IA 52078",
    "addr:housenumber":"208",
    "addr:postcode":"52078",
    "addr:street":"1St Ave W",
    "iso:country":"US",
    "sg:address":"208 1st Ave W",
    "sg:city":"Worthington",
    "sg:classifiers":[
        {
            "category":"Restaurant",
            "type":"Food & Drink"
        }
    ],
    "sg:phone":"+1 563 855 3225",
    "sg:postcode":"52078",
    "sg:province":"IA",
    "wof:name":"Last Straw",
    "wof:placetype":"venue"
},
  "geometry": {"coordinates":[-91.120279,42.397074],"type":"Point"}
}