{
  "type": "Feature",
  "properties": {
    "iso:country":"US",
    "sg:address":"2025 Grand Ave",
    "sg:city":"West Des Moines",
    "sg:classifiers":[
        {
            "category":"Restaurant",
            "type":"Food & Drink"
        }
    ],
    "sg:phone":"+1 515 222 9959",
    "sg:postcode":"50265",
    "sg:province":"IA",
    "wof:name":"Paradise Pizza Cafe",
    "wof:placetype":"venue"
},
  "geometry": {"coordinates":[-93.73278500000001,41.569036],"type":"Point"}
}