{
  "type": "Feature",
  "properties": {
    "iso:country":"US",
    "sg:address":"34898 150th St",
    "sg:city":"Le Mars",
    "sg:classifiers":[
        {
            "category":"Government",
            "subcategory":"Office",
            "type":"Public Place"
        }
    ],
    "sg:phone":"+1 712 546 6071",
    "sg:postcode":"51031",
    "sg:province":"IA",
    "wof:name":"Plymouth County Landfill",
    "wof:placetype":"venue"
},
  "geometry": {"coordinates":[-96.137168,42.836774],"type":"Point"}
}