{
  "type": "Feature",
  "properties": {
    "iso:country":"US",
    "sg:address":"2623 Kennedy Ave",
    "sg:city":"Cedar Falls",
    "sg:classifiers":[
        {
            "category":"Real Estate",
            "subcategory":"Real Estate Agent",
            "type":"Services"
        }
    ],
    "sg:phone":"+1 319 277 2329",
    "sg:postcode":"50613",
    "sg:province":"IA",
    "wof:name":"William C Morse",
    "wof:placetype":"venue"
},
  "geometry": {"coordinates":[-92.45766399999999,42.560284],"type":"Point"}
}