{
  "type": "Feature",
  "properties": {
    "iso:country":"US",
    "sg:address":"520 31st St",
    "sg:city":"Des Moines",
    "sg:classifiers":[
        {
            "category":"Real Estate",
            "subcategory":"Real Estate Operator",
            "type":"Services"
        }
    ],
    "sg:phone":"+1 515 244 5712",
    "sg:postcode":"50312",
    "sg:province":"IA",
    "sg:tags":[
        "apartment"
    ],
    "wof:name":"520 31st St",
    "wof:placetype":"venue"
},
  "geometry": {"coordinates":[-93.659397,41.585815],"type":"Point"}
}