{
  "type": "Feature",
  "properties": {
    "addr:full":"510 W 4th St St Ansgar IA 50472",
    "addr:housenumber":"510",
    "addr:postcode":"50472",
    "addr:street":"W 4Th St",
    "iso:country":"US",
    "sg:address":"510 W 4th St",
    "sg:city":"St Ansgar",
    "sg:classifiers":[
        {
            "category":"Organizations",
            "subcategory":"Religious Organization",
            "type":"Services"
        }
    ],
    "sg:phone":"+1 641 713 4300",
    "sg:postcode":"50472",
    "sg:province":"IA",
    "sg:tags":[
        "church"
    ],
    "wof:name":"United Methodist Church",
    "wof:placetype":"venue"
},
  "geometry": {"coordinates":[-92.92522599999999,43.378408],"type":"Point"}
}