{
  "type": "Feature",
  "properties": {
    "addr:full":"1230 N Market St Oskaloosa IA 52577",
    "addr:housenumber":"1230",
    "addr:postcode":"52577",
    "addr:street":"N Market St",
    "iso:country":"US",
    "sg:address":"1230 N Market St",
    "sg:city":"Oskaloosa",
    "sg:classifiers":[
        {
            "category":"Food & Beverages",
            "subcategory":"Specialty",
            "type":"Retail Goods"
        }
    ],
    "sg:phone":"+1 641 673 8567",
    "sg:postcode":"52577",
    "sg:province":"IA",
    "sg:tags":[
        "vitamin"
    ],
    "wof:name":"Mark L Richey",
    "wof:placetype":"venue"
},
  "geometry": {"coordinates":[-92.645245,41.305359],"type":"Point"}
}