{
  "type": "Feature",
  "properties": {
    "iso:country":"US",
    "sg:address":"503 Franklin St",
    "sg:city":"Wapello",
    "sg:classifiers":[
        {
            "category":"Government",
            "subcategory":"Police Station",
            "type":"Public Place"
        }
    ],
    "sg:phone":"+1 319 523 3511",
    "sg:postcode":"52653",
    "sg:province":"IA",
    "sg:tags":[
        "sheriff"
    ],
    "wof:name":"Louisa County Sheriff Jail",
    "wof:placetype":"venue"
},
  "geometry": {"coordinates":[-91.18708100000001,41.178916],"type":"Point"}
}