{
  "type": "Feature",
  "properties": {
    "addr:full":"805 Railroad St Perry IA 50220",
    "addr:housenumber":"805",
    "addr:postcode":"50220",
    "addr:street":"Railroad St",
    "iso:country":"US",
    "sg:address":"805 Railroad St",
    "sg:city":"Perry",
    "sg:classifiers":[
        {
            "category":"Utilities",
            "subcategory":"Fuel Oil & Lpg",
            "type":"Services"
        }
    ],
    "sg:phone":"+1 515 465 3013",
    "sg:postcode":"50220",
    "sg:province":"IA",
    "sg:tags":[
        "dealer"
    ],
    "wof:name":"Diamond Oil Co",
    "wof:placetype":"venue"
},
  "geometry": {"coordinates":[-94.104873,41.837321],"type":"Point"}
}