{
  "type": "Feature",
  "properties": {
    "addr:full":"4458 NW Urbandale Dr Urbandale IA 50322",
    "addr:housenumber":"4458",
    "addr:postcode":"50322",
    "addr:street":"Nw Urbandale Dr",
    "iso:country":"US",
    "sg:address":"4458 NW Urbandale Dr",
    "sg:city":"Urbandale",
    "sg:classifiers":[
        {
            "category":"Home & Garden",
            "subcategory":"Building Materials",
            "type":"Retail Goods"
        }
    ],
    "sg:phone":"+1 515 309 5350",
    "sg:postcode":"50322",
    "sg:province":"IA",
    "wof:name":"American Builders Supply",
    "wof:placetype":"venue"
},
  "geometry": {"coordinates":[-93.76582999999999,41.643042],"type":"Point"}
}