{
  "type": "Feature",
  "properties": {
    "iso:country":"US",
    "sg:address":"2845 Mount Pleasant St",
    "sg:city":"Burlington",
    "sg:classifiers":[
        {
            "category":"Wholesale",
            "subcategory":"Machinery & Supplies",
            "type":"Manufacturing & Wholesale Goods"
        }
    ],
    "sg:phone":"+1 319 752 7724",
    "sg:postcode":"52601",
    "sg:province":"IA",
    "sg:tags":[
        "burial",
        "vault"
    ],
    "wof:name":"Wilbert Burlington Vault Works",
    "wof:placetype":"venue"
},
  "geometry": {"coordinates":[-91.141108,40.825791],"type":"Point"}
}