{
  "type": "Feature",
  "properties": {
    "iso:country":"US",
    "sg:address":"2130 290th St",
    "sg:city":"Garner",
    "sg:classifiers":[
        {
            "category":"Wholesale",
            "subcategory":"Farm Supplies",
            "type":"Manufacturing & Wholesale Goods"
        }
    ],
    "sg:phone":"+1 641 927 4421",
    "sg:postcode":"50438",
    "sg:province":"IA",
    "sg:tags":[
        "grain"
    ],
    "wof:name":"Davison Grain & Livestock Inc",
    "wof:placetype":"venue"
},
  "geometry": {"coordinates":[-93.562826,43.18408],"type":"Point"}
}