{
  "type": "Feature",
  "properties": {
    "iso:country":"US",
    "sg:address":"721 2nd St",
    "sg:city":"Coralville",
    "sg:classifiers":[
        {
            "category":"Retail",
            "subcategory":"Auto Repair",
            "type":"Services"
        }
    ],
    "sg:phone":"+1 319 338 4462",
    "sg:postcode":"52241",
    "sg:province":"IA",
    "sg:tags":[
        "repairing",
        "automobile"
    ],
    "wof:name":"Dusty's Tire & Svc Inc",
    "wof:placetype":"venue"
},
  "geometry": {"coordinates":[-91.57663100000001,41.672355],"type":"Point"}
}