{
  "type": "Feature",
  "properties": {
    "addr:full":"3091 Settlers Trl Saint Charles IA 50240",
    "addr:housenumber":"3091",
    "addr:postcode":"50240",
    "addr:street":"Settlers Trl",
    "iso:country":"US",
    "sg:address":"3091 Settlers Trl",
    "sg:city":"Saint Charles",
    "sg:phone":"+1 641 765 4846",
    "sg:postcode":"50240",
    "sg:province":"IA",
    "sg:tags":[
        "farm",
        "grain",
        "cash"
    ],
    "wof:name":"Bill Husted",
    "wof:placetype":"venue"
},
  "geometry": {"coordinates":[-93.871064,41.237418],"type":"Point"}
}