{
  "type": "Feature",
  "properties": {
    "iso:country":"US",
    "sg:address":"2310 Independence Ave",
    "sg:city":"Letts",
    "sg:classifiers":[
        {
            "category":"Farming",
            "subcategory":"Livestock Farm",
            "type":"Manufacturing & Wholesale Goods"
        }
    ],
    "sg:phone":"+1 563 263 5907",
    "sg:postcode":"52754",
    "sg:province":"IA",
    "sg:tags":[
        "feedlot",
        "corn",
        "soybean",
        "beef",
        "cattle"
    ],
    "wof:name":"Garry Reid",
    "wof:placetype":"venue"
},
  "geometry": {"coordinates":[-91.214703,41.413483],"type":"Point"}
}