{
  "type": "Feature",
  "properties": {
    "addr:full":"19 Central Ave NW Le Mars IA 51031",
    "addr:housenumber":"19",
    "addr:postcode":"51031",
    "addr:street":"Central Ave Nw",
    "iso:country":"US",
    "sg:address":"19 Central Ave NW",
    "sg:city":"Le Mars",
    "sg:classifiers":[
        {
            "category":"Shopping",
            "subcategory":"Shoes",
            "type":"Retail Goods"
        }
    ],
    "sg:phone":"+1 712 546 4919",
    "sg:postcode":"51031",
    "sg:province":"IA",
    "sg:tags":[
        "boot"
    ],
    "wof:name":"Rust's Western Shed",
    "wof:placetype":"venue"
},
  "geometry": {"coordinates":[-96.166541,42.794055],"type":"Point"}
}