{
  "type": "Feature",
  "properties": {
    "iso:country":"US",
    "sg:address":"406 E State St",
    "sg:city":"Jefferson",
    "sg:classifiers":[
        {
            "category":"Shopping",
            "subcategory":"Bicycles & Sporting Goods",
            "type":"Retail Goods"
        }
    ],
    "sg:phone":"+1 515 386 3941",
    "sg:postcode":"50129",
    "sg:province":"IA",
    "sg:tags":[
        "bait",
        "fishing"
    ],
    "wof:name":"Cozad's Bait & Tackle",
    "wof:placetype":"venue"
},
  "geometry": {"coordinates":[-94.37072000000001,42.016357],"type":"Point"}
}