{
  "type": "Feature",
  "properties": {
    "iso:country":"US",
    "sg:address":"721 N 1st St",
    "sg:city":"Centerville",
    "sg:classifiers":[
        {
            "category":"Education",
            "subcategory":"Library",
            "type":"Public Place"
        }
    ],
    "sg:phone":"+1 641 856 2143",
    "sg:postcode":"52544",
    "sg:province":"IA",
    "wof:name":"Centerville Center Library",
    "wof:placetype":"venue"
},
  "geometry": {"coordinates":[-92.886887,40.739364],"type":"Point"}
}