{
  "type": "Feature",
  "properties": {
    "addr:full":"2800 University Ave West Des Moines IA 50266",
    "addr:housenumber":"2800",
    "addr:postcode":"50266",
    "addr:street":"University Ave",
    "iso:country":"US",
    "sg:address":"2800 University Ave",
    "sg:city":"West Des Moines",
    "sg:classifiers":[
        {
            "category":"Professional",
            "subcategory":"Advertising",
            "type":"Services"
        }
    ],
    "sg:phone":"+1 515 221 9744",
    "sg:postcode":"50266",
    "sg:province":"IA",
    "sg:tags":[
        "mailing",
        "shipping"
    ],
    "wof:name":"UPS Store",
    "wof:placetype":"venue"
},
  "geometry": {"coordinates":[-93.74531899999999,41.600383],"type":"Point"}
}