{
  "type": "Feature",
  "properties": {
    "iso:country":"US",
    "sg:address":"307 N Main St",
    "sg:city":"Chariton",
    "sg:classifiers":[
        {
            "category":"Health Services",
            "subcategory":"Optometrist",
            "type":"Services"
        }
    ],
    "sg:phone":"+1 641 774 5819",
    "sg:postcode":"50049",
    "sg:province":"IA",
    "wof:name":"Wolfe Clinic Eye Ctr",
    "wof:placetype":"venue"
},
  "geometry": {"coordinates":[-93.308474,41.016833],"type":"Point"}
}