{
  "type": "Feature",
  "properties": {
    "iso:country":"US",
    "sg:address":"1975 NW 92nd Ct",
    "sg:city":"Clive",
    "sg:classifiers":[
        {
            "category":"Building & Trades",
            "subcategory":"Cleaning & Sanitation",
            "type":"Services"
        }
    ],
    "sg:phone":"+1 515 401 6248",
    "sg:postcode":"50325",
    "sg:province":"IA",
    "sg:tags":[
        "polishing",
        "waxing",
        "floor"
    ],
    "wof:name":"All-Ways Best Cleaning Svc",
    "wof:placetype":"venue"
},
  "geometry": {"coordinates":[-93.74359699999999,41.610126],"type":"Point"}
}