{
  "type": "Feature",
  "properties": {
    "iso:country":"US",
    "sg:address":"3404 Elm Dr",
    "sg:city":"Urbandale",
    "sg:phone":"+1 515 252 0739",
    "sg:postcode":"50322",
    "sg:province":"IA",
    "sg:tags":[
        "farm",
        "corn"
    ],
    "wof:name":"Schultes John",
    "wof:placetype":"venue"
},
  "geometry": {"coordinates":[-93.72370600000001,41.626278],"type":"Point"}
}