{
  "type": "Feature",
  "properties": {
    "iso:country":"US",
    "sg:address":"1106 Mound St",
    "sg:city":"Davenport",
    "sg:classifiers":[
        {
            "category":"Professional",
            "subcategory":"Accounting & Tax Preparation",
            "type":"Services"
        }
    ],
    "sg:phone":"+1 563 326 5282",
    "sg:postcode":"52803",
    "sg:province":"IA",
    "sg:tags":[
        "return",
        "filing"
    ],
    "wof:name":"Johannsen & Beldin",
    "wof:placetype":"venue"
},
  "geometry": {"coordinates":[-90.54653399999999,41.531562],"type":"Point"}
}