{
  "type": "Feature",
  "properties": {
    "addr:full":"701 N Van Gordon Graettinger IA 51342",
    "addr:housenumber":"701",
    "addr:postcode":"51342",
    "addr:street":"N Van Gordon Graettinger",
    "iso:country":"US",
    "sg:address":"701 N Van Gordon",
    "sg:city":"Graettinger",
    "sg:classifiers":[
        {
            "category":"Home & Garden",
            "subcategory":"Furniture",
            "type":"Retail Goods"
        }
    ],
    "sg:phone":"+1 712 859 3367",
    "sg:postcode":"51342",
    "sg:province":"IA",
    "sg:tags":[
        "cabinet"
    ],
    "wof:name":"Kountry Woodhut",
    "wof:placetype":"venue"
},
  "geometry": {"coordinates":[-94.748198,43.245742],"type":"Point"}
}