{
  "type": "Feature",
  "properties": {
    "iso:country":"US",
    "sg:address":"655 4th St",
    "sg:city":"Waukee",
    "sg:classifiers":[
        {
            "category":"Building & Trades",
            "subcategory":"Construction",
            "type":"Services"
        }
    ],
    "sg:phone":"+1 515 987 4048",
    "sg:postcode":"50263",
    "sg:province":"IA",
    "sg:tags":[
        "downspouts",
        "gutter"
    ],
    "wof:name":"M & D Seamless Gutters",
    "wof:placetype":"venue"
},
  "geometry": {"coordinates":[-93.882436,41.609087],"type":"Point"}
}