{
  "type": "Feature",
  "properties": {
    "addr:full":"2201 E Ovid Ave Des Moines IA 50313",
    "addr:housenumber":"2201",
    "addr:postcode":"50313",
    "addr:street":"E Ovid Ave",
    "iso:country":"US",
    "sg:address":"2201 E Ovid Ave",
    "sg:city":"Des Moines",
    "sg:classifiers":[
        {
            "category":"Building & Trades",
            "subcategory":"Equipment Rental",
            "type":"Services"
        }
    ],
    "sg:phone":"+1 515 266 4246",
    "sg:postcode":"50313",
    "sg:province":"IA",
    "sg:tags":[
        "leasing"
    ],
    "wof:name":"Tramel Leasing",
    "wof:placetype":"venue"
},
  "geometry": {"coordinates":[-93.57809399999999,41.625877],"type":"Point"}
}