{
  "type": "Feature",
  "properties": {
    "iso:country":"US",
    "sg:address":"2907 270th St",
    "sg:city":"Winthrop",
    "sg:classifiers":[
        {
            "category":"Farming",
            "subcategory":"Livestock Farm",
            "type":"Manufacturing & Wholesale Goods"
        }
    ],
    "sg:phone":"+1 319 934 3755",
    "sg:postcode":"50682",
    "sg:province":"IA",
    "sg:tags":[
        "hog",
        "or",
        "feedlot"
    ],
    "wof:name":"Sloge Farm Inc",
    "wof:placetype":"venue"
},
  "geometry": {"coordinates":[-91.714021,42.398926],"type":"Point"}
}