{
  "type": "Feature",
  "properties": {
    "addr:full":"5510 170th St Sibley IA 51249",
    "addr:housenumber":"5510",
    "addr:postcode":"51249",
    "addr:street":"170Th St",
    "iso:country":"US",
    "sg:address":"5510 170th St",
    "sg:city":"Sibley",
    "sg:classifiers":[
        {
            "category":"Wholesale",
            "subcategory":"Chemicals & Plastics",
            "type":"Manufacturing & Wholesale Goods"
        }
    ],
    "sg:phone":"+1 712 754 3124",
    "sg:postcode":"51249",
    "sg:province":"IA",
    "wof:name":"Ike Adreon Distributing Co",
    "wof:placetype":"venue"
},
  "geometry": {"coordinates":[-95.70078100000001,43.404033],"type":"Point"}
}