{
  "type": "Feature",
  "properties": {
    "addr:full":"2212 Lyon St Des Moines IA 50317",
    "addr:housenumber":"2212",
    "addr:postcode":"50317",
    "addr:street":"Lyon St",
    "iso:country":"US",
    "sg:address":"2212 Lyon St",
    "sg:city":"Des Moines",
    "sg:classifiers":[
        {
            "category":"Manufacturing",
            "subcategory":"Metals",
            "type":"Manufacturing & Wholesale Goods"
        }
    ],
    "sg:phone":"+1 515 263 8902",
    "sg:postcode":"50317",
    "sg:province":"IA",
    "sg:tags":[
        "plumbing",
        "concrete",
        "lead"
    ],
    "wof:name":"Tc Construction",
    "wof:placetype":"venue"
},
  "geometry": {"coordinates":[-93.575362,41.597322],"type":"Point"}
}