{
  "type": "Feature",
  "properties": {
    "iso:country":"US",
    "sg:address":"2601 Dixon St",
    "sg:city":"Des Moines",
    "sg:classifiers":[
        {
            "category":"Professional",
            "subcategory":"Advertising",
            "type":"Services"
        }
    ],
    "sg:phone":"+1 515 265 9187",
    "sg:postcode":"50316",
    "sg:province":"IA",
    "wof:name":"Arrow Specialties Eagle",
    "wof:placetype":"venue"
},
  "geometry": {"coordinates":[-93.588814,41.620701],"type":"Point"}
}