{
  "type": "Feature",
  "properties": {
    "iso:country":"US",
    "sg:address":"703 S 1st St",
    "sg:city":"Chariton",
    "sg:classifiers":[
        {
            "category":"Organizations",
            "subcategory":"Religious Organization",
            "type":"Services"
        }
    ],
    "sg:phone":"+1 641 774 4756",
    "sg:postcode":"50049",
    "sg:province":"IA",
    "sg:tags":[
        "church"
    ],
    "wof:name":"Grace Baptist Church",
    "wof:placetype":"venue"
},
  "geometry": {"coordinates":[-93.29401300000001,41.005316],"type":"Point"}
}