{
  "type": "Feature",
  "properties": {
    "iso:country":"US",
    "sg:address":"829 1st Ave SE",
    "sg:city":"Oelwein",
    "sg:classifiers":[
        {
            "category":"Home & Garden",
            "subcategory":"Building Materials",
            "type":"Retail Goods"
        }
    ],
    "sg:phone":"+1 319 283 2122",
    "sg:postcode":"50662",
    "sg:province":"IA",
    "sg:tags":[
        "lumber"
    ],
    "wof:name":"Best Way Building Ctr Inc",
    "wof:placetype":"venue"
},
  "geometry": {"coordinates":[-91.9121,42.667737],"type":"Point"}
}