{
  "type": "Feature",
  "properties": {
    "iso:country":"US",
    "sg:address":"16 Susan Ln",
    "sg:city":"Council Bluffs",
    "sg:classifiers":[
        {
            "category":"Professional",
            "subcategory":"Computer Services",
            "type":"Services"
        }
    ],
    "sg:phone":"+1 712 322 7692",
    "sg:postcode":"51503",
    "sg:province":"IA",
    "sg:tags":[
        "related"
    ],
    "wof:name":"Dees Typing Service",
    "wof:placetype":"venue"
},
  "geometry": {"coordinates":[-95.827287,41.249097],"type":"Point"}
}