{
  "type": "Feature",
  "properties": {
    "addr:full":"3070 W Airline Hwy Waterloo IA 50703",
    "addr:housenumber":"3070",
    "addr:postcode":"50703",
    "addr:street":"W Airline Hwy",
    "iso:country":"US",
    "sg:address":"3070 W Airline Hwy",
    "sg:city":"Waterloo",
    "sg:classifiers":[
        {
            "category":"Manufacturing",
            "subcategory":"Printing",
            "type":"Manufacturing & Wholesale Goods"
        }
    ],
    "sg:phone":"+1 319 234 4651",
    "sg:postcode":"50703",
    "sg:province":"IA",
    "sg:tags":[
        "printer",
        "form"
    ],
    "sg:website":"www.controlofax.com",
    "wof:name":"Control-O-Fax Systems Inc",
    "wof:placetype":"venue"
},
  "geometry": {"coordinates":[-92.409205,42.542039],"type":"Point"}
}