{
  "type": "Feature",
  "properties": {
    "iso:country":"US",
    "sg:address":"4035 Primrose Ave",
    "sg:city":"Osage",
    "sg:phone":"+1 641 732 3919",
    "sg:postcode":"50461",
    "sg:province":"IA",
    "sg:tags":[
        "farm",
        "corn"
    ],
    "wof:name":"Ronald Valasek",
    "wof:placetype":"venue"
},
  "geometry": {"coordinates":[-92.73253699999999,43.3515],"type":"Point"}
}