{
  "type": "Feature",
  "properties": {
    "iso:country":"US",
    "sg:address":"200 N Jefferson Way",
    "sg:city":"Indianola",
    "sg:classifiers":[
        {
            "category":"Retail",
            "subcategory":"Auto Repair",
            "type":"Services"
        }
    ],
    "sg:phone":"+1 515 961 7848",
    "sg:postcode":"50125",
    "sg:province":"IA",
    "sg:tags":[
        "repairing",
        "automobile"
    ],
    "wof:name":"Heartland Tire & Auto",
    "wof:placetype":"venue"
},
  "geometry": {"coordinates":[-93.558313,41.361297],"type":"Point"}
}