{
  "type": "Feature",
  "properties": {
    "iso:country":"US",
    "sg:address":"405 E Margaret St",
    "sg:city":"Earlville",
    "sg:classifiers":[
        {
            "category":"Manufacturing",
            "subcategory":"Tools & Machinery",
            "type":"Manufacturing & Wholesale Goods"
        }
    ],
    "sg:phone":"+1 563 923 2003",
    "sg:postcode":"52041",
    "sg:province":"IA",
    "sg:tags":[
        "hog",
        "equipment"
    ],
    "wof:name":"S & R Mfg Inc",
    "wof:placetype":"venue"
},
  "geometry": {"coordinates":[-91.26616300000001,42.485457],"type":"Point"}
}