{
  "type": "Feature",
  "properties": {
    "iso:country":"US",
    "sg:address":"510 E Bloomington St",
    "sg:city":"Iowa City",
    "sg:classifiers":[
        {
            "category":"Health Services",
            "subcategory":"Doctor",
            "type":"Services"
        }
    ],
    "sg:phone":"+1 319 338 9247",
    "sg:postcode":"52245",
    "sg:province":"IA",
    "sg:tags":[
        "physician",
        "surgeon"
    ],
    "wof:name":"Surgical Services",
    "wof:placetype":"venue"
},
  "geometry": {"coordinates":[-91.527295,41.664719],"type":"Point"}
}