{
  "type": "Feature",
  "properties": {
    "iso:country":"US",
    "sg:address":"929 W Madison St",
    "sg:city":"Washington",
    "sg:classifiers":[
        {
            "category":"Personal",
            "subcategory":"Beauty Salon",
            "type":"Services"
        }
    ],
    "sg:phone":"+1 319 653 4247",
    "sg:postcode":"52353",
    "sg:province":"IA",
    "wof:name":"Hot Spot",
    "wof:placetype":"venue"
},
  "geometry": {"coordinates":[-91.70404600000001,41.296511],"type":"Point"}
}