{
  "type": "Feature",
  "properties": {
    "addr:full":"206 Monroe St N Hazleton IA 50641",
    "addr:housenumber":"206",
    "addr:postcode":"50641",
    "addr:street":"Monroe St N",
    "iso:country":"US",
    "sg:address":"206 Monroe St N",
    "sg:city":"Hazleton",
    "sg:classifiers":[
        {
            "category":"Insurance",
            "subcategory":"Hazard Insurance",
            "type":"Services"
        }
    ],
    "sg:phone":"+1 319 636 2031",
    "sg:postcode":"50641",
    "sg:province":"IA",
    "sg:tags":[
        "carrier"
    ],
    "wof:name":"Randy Quario",
    "wof:placetype":"venue"
},
  "geometry": {"coordinates":[-91.902044,42.620988],"type":"Point"}
}