{
  "type": "Feature",
  "properties": {
    "addr:full":"226 Brandilynn Blvd Cedar Falls IA 50613",
    "addr:housenumber":"226",
    "addr:postcode":"50613",
    "addr:street":"Brandilynn Blvd",
    "iso:country":"US",
    "sg:address":"226 Brandilynn Blvd",
    "sg:city":"Cedar Falls",
    "sg:classifiers":[
        {
            "category":"Restaurant",
            "type":"Food & Drink"
        }
    ],
    "sg:phone":"+1 319 266 6500",
    "sg:postcode":"50613",
    "sg:province":"IA",
    "sg:tags":[
        "eating"
    ],
    "wof:name":"Papa Ds Pizza",
    "wof:placetype":"venue"
},
  "geometry": {"coordinates":[-92.44382899999999,42.485167],"type":"Point"}
}