{
  "type": "Feature",
  "properties": {
    "iso:country":"US",
    "sg:address":"1227 475th Ave",
    "sg:city":"Sabula",
    "sg:classifiers":[
        {
            "category":"Building & Trades",
            "subcategory":"Construction",
            "type":"Services"
        }
    ],
    "sg:phone":"+1 563 687 2871",
    "sg:postcode":"52070",
    "sg:province":"IA",
    "sg:tags":[
        "house"
    ],
    "wof:name":"Owen Meyer Construction Inc",
    "wof:placetype":"venue"
},
  "geometry": {"coordinates":[-90.174182,41.999404],"type":"Point"}
}