{
  "type": "Feature",
  "properties": {
    "iso:country":"US",
    "sg:address":"236 S Cedar St",
    "sg:city":"Monticello",
    "sg:classifiers":[
        {
            "category":"Farming",
            "subcategory":"Farm",
            "type":"Manufacturing & Wholesale Goods"
        }
    ],
    "sg:phone":"+1 319 465 5836",
    "sg:postcode":"52310",
    "sg:province":"IA",
    "sg:tags":[
        "crop",
        "general"
    ],
    "wof:name":"David Hardersen",
    "wof:placetype":"venue"
},
  "geometry": {"coordinates":[-91.18972599999999,42.23627],"type":"Point"}
}