{
  "type": "Feature",
  "properties": {
    "addr:full":"201 S Clinton St Iowa City IA 52240",
    "addr:housenumber":"201",
    "addr:postcode":"52240",
    "addr:street":"S Clinton St",
    "iso:country":"US",
    "sg:address":"201 S Clinton St",
    "sg:city":"Iowa City",
    "sg:classifiers":[
        {
            "category":"Restaurant",
            "type":"Food & Drink"
        }
    ],
    "sg:phone":"+1 319 338 6395",
    "sg:postcode":"52240",
    "sg:province":"IA",
    "wof:name":"China Star",
    "wof:placetype":"venue"
},
  "geometry": {"coordinates":[-91.534639,41.657874],"type":"Point"}
}