{
  "type": "Feature",
  "properties": {
    "iso:country":"US",
    "sg:address":"3551 University Ave",
    "sg:city":"Waterloo",
    "sg:classifiers":[
        {
            "category":"Restaurant",
            "type":"Food & Drink"
        }
    ],
    "sg:phone":"+1 319 433 1291",
    "sg:postcode":"50701",
    "sg:province":"IA",
    "wof:name":"Crazy Buffett",
    "wof:placetype":"venue"
},
  "geometry": {"coordinates":[-92.39552399999999,42.503171],"type":"Point"}
}