{
  "type": "Feature",
  "properties": {
    "addr:full":"304 S 4th St Knoxville IA 50138",
    "addr:housenumber":"304",
    "addr:postcode":"50138",
    "addr:street":"S 4Th St",
    "iso:country":"US",
    "sg:address":"304 S 4th St",
    "sg:city":"Knoxville",
    "sg:classifiers":[
        {
            "category":"Organizations",
            "subcategory":"Professional Association",
            "type":"Services"
        },
        {
            "category":"Organizations",
            "subcategory":"Community Association",
            "type":"Services"
        }
    ],
    "sg:phone":"+1 641 842 5216",
    "sg:postcode":"50138",
    "sg:province":"IA",
    "sg:tags":[
        "business"
    ],
    "wof:name":"Masonic Lodge",
    "wof:placetype":"venue"
},
  "geometry": {"coordinates":[-93.095336,41.316211],"type":"Point"}
}