{
  "type": "Feature",
  "properties": {
    "addr:full":"4960 Sutliff Rd NE Solon IA 52333",
    "addr:housenumber":"4960",
    "addr:postcode":"52333",
    "addr:street":"Sutliff Rd Ne",
    "iso:country":"US",
    "sg:address":"4960 Sutliff Rd NE",
    "sg:city":"Solon",
    "sg:classifiers":[
        {
            "category":"Building & Trades",
            "subcategory":"Electrical",
            "type":"Services"
        }
    ],
    "sg:phone":"+1 319 624 2065",
    "sg:postcode":"52333",
    "sg:province":"IA",
    "sg:tags":[
        "electric",
        "contractor"
    ],
    "wof:name":"E & J Electric Inc",
    "wof:placetype":"venue"
},
  "geometry": {"coordinates":[-91.455044,41.816519],"type":"Point"}
}