{
  "type": "Feature",
  "properties": {
    "addr:full":"107 N Washington St Wyoming IA 52362",
    "addr:housenumber":"107",
    "addr:postcode":"52362",
    "addr:street":"N Washington St",
    "iso:country":"US",
    "sg:address":"107 N Washington St",
    "sg:city":"Wyoming",
    "sg:classifiers":[
        {
            "category":"Organizations",
            "subcategory":"Religious Organization",
            "type":"Services"
        }
    ],
    "sg:phone":"+1 563 488 3402",
    "sg:postcode":"52362",
    "sg:province":"IA",
    "sg:tags":[
        "church"
    ],
    "wof:name":"United Methodist Church",
    "wof:placetype":"venue"
},
  "geometry": {"coordinates":[-91.00570399999999,42.059308],"type":"Point"}
}