{
  "type": "Feature",
  "properties": {
    "addr:full":"4612 78th St Urbandale IA 50322",
    "addr:housenumber":"4612",
    "addr:postcode":"50322",
    "addr:street":"78Th St",
    "iso:country":"US",
    "sg:address":"4612 78th St",
    "sg:city":"Urbandale",
    "sg:classifiers":[
        {
            "category":"Professional",
            "subcategory":"Management & Consulting",
            "type":"Services"
        }
    ],
    "sg:phone":"+1 515 270 0645",
    "sg:postcode":"50322",
    "sg:province":"IA",
    "sg:tags":[
        "business"
    ],
    "wof:name":"Dasun Consulting LLC",
    "wof:placetype":"venue"
},
  "geometry": {"coordinates":[-93.725487,41.644908],"type":"Point"}
}