{
  "type": "Feature",
  "properties": {
    "iso:country":"US",
    "sg:address":"1031 Central Ave",
    "sg:city":"Fort Dodge",
    "sg:classifiers":[
        {
            "category":"Insurance",
            "subcategory":"Insurance Agent",
            "type":"Services"
        }
    ],
    "sg:phone":"+1 515 576 4341",
    "sg:postcode":"50501",
    "sg:province":"IA",
    "wof:name":"Allstate Insurance",
    "wof:placetype":"venue"
},
  "geometry": {"coordinates":[-94.18379299999999,42.50552],"type":"Point"}
}