{
  "type": "Feature",
  "properties": {
    "iso:country":"US",
    "sg:address":"1535 650th St",
    "sg:city":"Storm Lake",
    "sg:phone":"+1 712 732 5431",
    "sg:postcode":"50588",
    "sg:province":"IA",
    "sg:tags":[
        "farm",
        "corn"
    ],
    "wof:name":"Pat McKenna",
    "wof:placetype":"venue"
},
  "geometry": {"coordinates":[-95.107606,42.575705],"type":"Point"}
}