{
  "type": "Feature",
  "properties": {
    "iso:country":"US",
    "sg:address":"212 11th St NE",
    "sg:city":"Dyersville",
    "sg:classifiers":[
        {
            "category":"Organizations",
            "subcategory":"Religious Organization",
            "type":"Services"
        }
    ],
    "sg:phone":"+1 563 875 8619",
    "sg:postcode":"52040",
    "sg:province":"IA",
    "sg:tags":[
        "church"
    ],
    "wof:name":"Evangelical Free Church",
    "wof:placetype":"venue"
},
  "geometry": {"coordinates":[-91.110434,42.483082],"type":"Point"}
}