{
  "type": "Feature",
  "properties": {
    "addr:full":"16533 140th Ave What Cheer IA 50268",
    "addr:housenumber":"16533",
    "addr:postcode":"50268",
    "addr:street":"140Th Ave",
    "iso:country":"US",
    "sg:address":"16533 140th Ave",
    "sg:city":"What Cheer",
    "sg:phone":"+1 641 634 2234",
    "sg:postcode":"50268",
    "sg:province":"IA",
    "sg:tags":[
        "farm",
        "corn",
        "soybean"
    ],
    "wof:name":"Billy Dennis",
    "wof:placetype":"venue"
},
  "geometry": {"coordinates":[-92.335492,41.409038],"type":"Point"}
}