{
  "type": "Feature",
  "properties": {
    "addr:full":"216 Mechanic St Osage IA 50461",
    "addr:housenumber":"216",
    "addr:postcode":"50461",
    "addr:street":"Mechanic St",
    "iso:country":"US",
    "sg:address":"216 Mechanic St",
    "sg:city":"Osage",
    "sg:classifiers":[
        {
            "category":"Freight",
            "type":"Transportation"
        }
    ],
    "sg:phone":"+1 641 732 3768",
    "sg:postcode":"50461",
    "sg:province":"IA",
    "sg:tags":[
        "grain",
        "elevator"
    ],
    "wof:name":"Osage Co-Op Elevator",
    "wof:placetype":"venue"
},
  "geometry": {"coordinates":[-92.819699,43.285955],"type":"Point"}
}