{
  "type": "Feature",
  "properties": {
    "iso:country":"US",
    "sg:address":"1004 Carroll St",
    "sg:city":"Boone",
    "sg:classifiers":[
        {
            "category":"Professional",
            "subcategory":"Art Services",
            "type":"Services"
        }
    ],
    "sg:phone":"+1 515 432 2926",
    "sg:postcode":"50036",
    "sg:province":"IA",
    "sg:tags":[
        "commercial",
        "graphic",
        "design",
        "designer"
    ],
    "wof:name":"Scenic Valley Designs",
    "wof:placetype":"venue"
},
  "geometry": {"coordinates":[-93.885001,42.066331],"type":"Point"}
}