{
  "type": "Feature",
  "properties": {
    "addr:full":"706 Ansborough Ave Waterloo IA 50701",
    "addr:housenumber":"706",
    "addr:postcode":"50701",
    "addr:street":"Ansborough Ave",
    "iso:country":"US",
    "sg:address":"706 Ansborough Ave",
    "sg:city":"Waterloo",
    "sg:classifiers":[
        {
            "category":"Home & Garden",
            "subcategory":"Carpets & Floor Coverings",
            "type":"Retail Goods"
        }
    ],
    "sg:phone":"+1 319 232 9242",
    "sg:postcode":"50701",
    "sg:province":"IA",
    "sg:tags":[
        "material"
    ],
    "wof:name":"Floor Decor",
    "wof:placetype":"venue"
},
  "geometry": {"coordinates":[-92.376824,42.502718],"type":"Point"}
}