{
  "type": "Feature",
  "properties": {
    "iso:country":"US",
    "sg:address":"1000 7th Ave",
    "sg:city":"Marion",
    "sg:classifiers":[
        {
            "category":"Restaurant",
            "type":"Food & Drink"
        }
    ],
    "sg:phone":"+1 319 377 7757",
    "sg:postcode":"52302",
    "sg:province":"IA",
    "wof:name":"Marion Maid-Rite",
    "wof:placetype":"venue"
},
  "geometry": {"coordinates":[-91.59929700000001,42.033001],"type":"Point"}
}