{
  "type": "Feature",
  "properties": {
    "iso:country":"US",
    "sg:address":"815 Jackson Ave",
    "sg:city":"Mechanicsville",
    "sg:classifiers":[
        {
            "category":"Farming",
            "subcategory":"Farm",
            "type":"Manufacturing & Wholesale Goods"
        }
    ],
    "sg:phone":"+1 563 886 6337",
    "sg:postcode":"52306",
    "sg:province":"IA",
    "wof:name":"Clear Blue Sky LTD",
    "wof:placetype":"venue"
},
  "geometry": {"coordinates":[-91.191277,41.82826],"type":"Point"}
}