{
  "type": "Feature",
  "properties": {
    "iso:country":"US",
    "sg:address":"3939 1st Ave SE",
    "sg:city":"Cedar Rapids",
    "sg:classifiers":[
        {
            "category":"Restaurant",
            "type":"Food & Drink"
        }
    ],
    "sg:menulink":"http://www.allmenus.com/ia/cedar-rapids/98051-outback-steakhouse/menu/",
    "sg:phone":"+1 319 366 6683",
    "sg:postcode":"52402",
    "sg:province":"IA",
    "sg:tags":[
        "american",
        "steakhouse"
    ],
    "wof:name":"Outback Steakhouse",
    "wof:placetype":"venue"
},
  "geometry": {"coordinates":[-91.63304100000001,42.018696],"type":"Point"}
}