{
  "type": "Feature",
  "properties": {
    "addr:full":"1825 Kingbird Ave George IA 51237",
    "addr:housenumber":"1825",
    "addr:postcode":"51237",
    "addr:street":"Kingbird Ave",
    "iso:country":"US",
    "sg:address":"1825 Kingbird Ave",
    "sg:city":"George",
    "sg:classifiers":[
        {
            "category":"Real Estate",
            "subcategory":"Real Estate Operator",
            "type":"Services"
        }
    ],
    "sg:phone":"+1 712 475 3982",
    "sg:postcode":"51237",
    "sg:province":"IA",
    "sg:tags":[
        "property",
        "lessor"
    ],
    "wof:name":"Harold Kruse Inc",
    "wof:placetype":"venue"
},
  "geometry": {"coordinates":[-95.978505,43.385259],"type":"Point"}
}