{
  "type": "Feature",
  "properties": {
    "iso:country":"US",
    "sg:address":"707 Sharp St",
    "sg:city":"Glenwood",
    "sg:classifiers":[
        {
            "category":"Education",
            "subcategory":"School",
            "type":"Public Place"
        }
    ],
    "sg:phone":"+1 712 527 4886",
    "sg:postcode":"51534",
    "sg:province":"IA",
    "wof:name":"West Elementary School",
    "wof:placetype":"venue"
},
  "geometry": {"coordinates":[-95.746275,41.046128],"type":"Point"}
}