{
  "type": "Feature",
  "properties": {
    "iso:country":"US",
    "sg:address":"10995 115th Ave",
    "sg:city":"Burlington",
    "sg:classifiers":[
        {
            "category":"Organizations",
            "subcategory":"Religious Organization",
            "type":"Services"
        }
    ],
    "sg:phone":"+1 319 752 1592",
    "sg:postcode":"52601",
    "sg:province":"IA",
    "sg:tags":[
        "church"
    ],
    "wof:name":"Apostolic Christian Church",
    "wof:placetype":"venue"
},
  "geometry": {"coordinates":[-91.151197,40.838251],"type":"Point"}
}