{
  "type": "Feature",
  "properties": {
    "iso:country":"US",
    "sg:address":"110 W Gillet",
    "sg:city":"Preston",
    "sg:classifiers":[
        {
            "category":"Insurance",
            "subcategory":"Insurance Agent",
            "type":"Services"
        }
    ],
    "sg:phone":"+1 563 689 3290",
    "sg:postcode":"52069",
    "sg:province":"IA",
    "wof:name":"Farm Bureau Insurance",
    "wof:placetype":"venue"
},
  "geometry": {"coordinates":[-90.395287,42.050442],"type":"Point"}
}