{
  "type": "Feature",
  "properties": {
    "iso:country":"US",
    "sg:address":"1093 F Ave",
    "sg:city":"Ogden",
    "sg:phone":"+1 515 275 4495",
    "sg:postcode":"50212",
    "sg:province":"IA",
    "sg:tags":[
        "farm",
        "corn",
        "soybean"
    ],
    "wof:name":"Jeffrey Paulson",
    "wof:placetype":"venue"
},
  "geometry": {"coordinates":[-94.067128,42.050051],"type":"Point"}
}