{
  "type": "Feature",
  "properties": {
    "addr:full":"110 6th St Sioux Rapids IA 50585",
    "addr:housenumber":"110",
    "addr:postcode":"50585",
    "addr:street":"6Th St",
    "iso:country":"US",
    "sg:address":"110 6th St",
    "sg:city":"Sioux Rapids",
    "sg:classifiers":[
        {
            "category":"Personal",
            "subcategory":"Beauty Salon",
            "type":"Services"
        }
    ],
    "sg:phone":"+1 712 283 2309",
    "sg:postcode":"50585",
    "sg:province":"IA",
    "wof:name":"Hair Hut",
    "wof:placetype":"venue"
},
  "geometry": {"coordinates":[-95.145364,42.894179],"type":"Point"}
}