{
  "type": "Feature",
  "properties": {
    "addr:full":"1107 150th Ave Lu Verne IA 50560",
    "addr:housenumber":"1107",
    "addr:postcode":"50560",
    "addr:street":"150Th Ave",
    "iso:country":"US",
    "sg:address":"1107 150th Ave",
    "sg:city":"Lu Verne",
    "sg:phone":"+1 515 379 1007",
    "sg:postcode":"50560",
    "sg:province":"IA",
    "sg:tags":[
        "farm",
        "corn",
        "soybean"
    ],
    "wof:name":"Robert Altman",
    "wof:placetype":"venue"
},
  "geometry": {"coordinates":[-94.16835,42.930276],"type":"Point"}
}