{
  "type": "Feature",
  "properties": {
    "iso:country":"US",
    "sg:address":"618 Lafayette Ave",
    "sg:city":"Story City",
    "sg:classifiers":[
        {
            "category":"Retail",
            "subcategory":"Funeral Services",
            "type":"Services"
        }
    ],
    "sg:phone":"+1 515 733 4334",
    "sg:postcode":"50248",
    "sg:province":"IA",
    "sg:tags":[
        "director"
    ],
    "wof:name":"Soderstrum-Larson Funeral Home",
    "wof:placetype":"venue"
},
  "geometry": {"coordinates":[-93.592455,42.187431],"type":"Point"}
}