{
  "type": "Feature",
  "properties": {
    "iso:country":"US",
    "sg:address":"5411 Shriver Ave",
    "sg:city":"Des Moines",
    "sg:classifiers":[
        {
            "category":"Professional",
            "subcategory":"Art Services",
            "type":"Services"
        }
    ],
    "sg:phone":"+1 515 255 4504",
    "sg:postcode":"50312",
    "sg:province":"IA",
    "sg:tags":[
        "commercial",
        "design"
    ],
    "wof:name":"Hikchik Design",
    "wof:placetype":"venue"
},
  "geometry": {"coordinates":[-93.69277099999999,41.585202],"type":"Point"}
}