{
  "type": "Feature",
  "properties": {
    "addr:full":"4115 Hickory Hill Ln SE Cedar Rapids IA 52403",
    "addr:housenumber":"4115",
    "addr:postcode":"52403",
    "addr:street":"Hickory Hill Ln Se",
    "iso:country":"US",
    "sg:address":"4115 Hickory Hill Ln SE",
    "sg:city":"Cedar Rapids",
    "sg:classifiers":[
        {
            "category":"Wholesale",
            "subcategory":"Durable Goods & Equipment",
            "type":"Manufacturing & Wholesale Goods"
        }
    ],
    "sg:phone":"+1 319 364 0321",
    "sg:postcode":"52403",
    "sg:province":"IA",
    "sg:tags":[
        "representative",
        "manufacturer"
    ],
    "wof:name":"Pattison Sales",
    "wof:placetype":"venue"
},
  "geometry": {"coordinates":[-91.608777,41.965415],"type":"Point"}
}