{
  "type": "Feature",
  "properties": {
    "iso:country":"US",
    "sg:address":"815 Center St",
    "sg:city":"Cedar Falls",
    "sg:classifiers":[
        {
            "category":"Wholesale",
            "subcategory":"Construction Materials",
            "type":"Manufacturing & Wholesale Goods"
        }
    ],
    "sg:phone":"+1 319 266 2621",
    "sg:postcode":"50613",
    "sg:province":"IA",
    "sg:tags":[
        "sand",
        "gravel"
    ],
    "wof:name":"Benton's Sand & Gravel Inc",
    "wof:placetype":"venue"
},
  "geometry": {"coordinates":[-92.450717,42.543431],"type":"Point"}
}