{
  "type": "Feature",
  "properties": {
    "addr:full":"1241 6th Ave Des Moines IA 50314",
    "addr:housenumber":"1241",
    "addr:postcode":"50314",
    "addr:street":"6Th Ave",
    "iso:country":"US",
    "sg:address":"1241 6th Ave",
    "sg:city":"Des Moines",
    "sg:classifiers":[
        {
            "category":"Professional",
            "type":"Services"
        }
    ],
    "sg:phone":"+1 515 288 4211",
    "sg:postcode":"50314",
    "sg:province":"IA",
    "sg:tags":[
        "establishment"
    ],
    "wof:name":"SSMC Inc",
    "wof:placetype":"venue"
},
  "geometry": {"coordinates":[-93.625688,41.601705],"type":"Point"}
}