{
  "type": "Feature",
  "properties": {
    "addr:full":"122 Green Mountain Dr Iowa City IA 52245",
    "addr:housenumber":"122",
    "addr:postcode":"52245",
    "addr:street":"Green Mountain Dr",
    "iso:country":"US",
    "sg:address":"122 Green Mountain Dr",
    "sg:city":"Iowa City",
    "sg:classifiers":[
        {
            "category":"Home & Garden",
            "subcategory":"Home Furnishings",
            "type":"Retail Goods"
        }
    ],
    "sg:phone":"+1 319 354 4525",
    "sg:postcode":"52245",
    "sg:province":"IA",
    "wof:name":"Barry Clean Blinds",
    "wof:placetype":"venue"
},
  "geometry": {"coordinates":[-91.494389,41.662554],"type":"Point"}
}