{
  "type": "Feature",
  "properties": {
    "iso:country":"US",
    "sg:address":"2972 270th St",
    "sg:city":"Thor",
    "sg:phone":"+1 515 378 3295",
    "sg:postcode":"50591",
    "sg:province":"IA",
    "sg:tags":[
        "farm",
        "soybean"
    ],
    "wof:name":"Timothy Stensland",
    "wof:placetype":"venue"
},
  "geometry": {"coordinates":[-94.050991,42.659125],"type":"Point"}
}