{
  "type": "Feature",
  "properties": {
    "iso:country":"US",
    "sg:address":"2337 Blairs Ferry Rd NE",
    "sg:city":"Cedar Rapids",
    "sg:classifiers":[
        {
            "category":"Professional",
            "subcategory":"Employment Agencies",
            "type":"Services"
        }
    ],
    "sg:phone":"+1 319 378 4487",
    "sg:postcode":"52402",
    "sg:province":"IA",
    "wof:name":"Sedona Staffing Services Inc",
    "wof:placetype":"venue"
},
  "geometry": {"coordinates":[-91.678101,42.034698],"type":"Point"}
}