{
  "type": "Feature",
  "properties": {
    "iso:country":"US",
    "sg:address":"301 4th Ave NE",
    "sg:city":"Pocahontas",
    "sg:classifiers":[
        {
            "category":"Building & Trades",
            "subcategory":"Construction",
            "type":"Services"
        }
    ],
    "sg:phone":"+1 712 335 4061",
    "sg:postcode":"50574",
    "sg:province":"IA",
    "sg:tags":[
        "house"
    ],
    "wof:name":"Zdrazil Construction",
    "wof:placetype":"venue"
},
  "geometry": {"coordinates":[-94.66329399999999,42.737111],"type":"Point"}
}