{
  "type": "Feature",
  "properties": {
    "iso:country":"US",
    "sg:address":"10 Grand Ave",
    "sg:city":"Spencer",
    "sg:classifiers":[
        {
            "category":"Government",
            "subcategory":"Fire Station",
            "type":"Public Place"
        }
    ],
    "sg:phone":"+1 712 580 7240",
    "sg:postcode":"51301",
    "sg:province":"IA",
    "sg:tags":[
        "department"
    ],
    "sg:website":"www.spenceria.org",
    "wof:name":"Spencer Fire Dept",
    "wof:placetype":"venue"
},
  "geometry": {"coordinates":[-95.144417,43.138554],"type":"Point"}
}