{
  "type": "Feature",
  "properties": {
    "iso:country":"US",
    "sg:address":"302 S Cherry St",
    "sg:city":"Shell Rock",
    "sg:classifiers":[
        {
            "category":"Retail",
            "subcategory":"Animal Services",
            "type":"Services"
        }
    ],
    "sg:phone":"+1 319 885 6545",
    "sg:postcode":"50670",
    "sg:province":"IA",
    "sg:tags":[
        "pet",
        "grooming",
        "washing"
    ],
    "wof:name":"Creature Comforts",
    "wof:placetype":"venue"
},
  "geometry": {"coordinates":[-92.583167,42.71003],"type":"Point"}
}