{
  "type": "Feature",
  "properties": {
    "iso:country":"US",
    "sg:address":"422 N Main St",
    "sg:city":"Milton",
    "sg:classifiers":[
        {
            "category":"Education",
            "subcategory":"Library",
            "type":"Public Place"
        }
    ],
    "sg:phone":"+1 641 656 4611",
    "sg:postcode":"52570",
    "sg:province":"IA",
    "wof:name":"Milton Public Library",
    "wof:placetype":"venue"
},
  "geometry": {"coordinates":[-92.161939,40.674179],"type":"Point"}
}