{
  "type": "Feature",
  "properties": {
    "iso:country":"US",
    "sg:address":"4847 550th Ave",
    "sg:city":"Sabula",
    "sg:classifiers":[
        {
            "category":"Freight",
            "type":"Transportation"
        }
    ],
    "sg:phone":"+1 563 682 7454",
    "sg:postcode":"52070",
    "sg:province":"IA",
    "sg:tags":[
        "hauling",
        "trucking"
    ],
    "wof:name":"Meyer Custom Farming & Trckng",
    "wof:placetype":"venue"
},
  "geometry": {"coordinates":[-90.256871,42.071041],"type":"Point"}
}