{
  "type": "Feature",
  "properties": {
    "iso:country":"US",
    "sg:address":"115 E 3rd St",
    "sg:city":"Davenport",
    "sg:classifiers":[
        {
            "category":"Bars & Pubs",
            "type":"Food & Drink"
        },
        {
            "category":"Deli",
            "type":"Food & Drink"
        },
        {
            "category":"Restaurant",
            "type":"Food & Drink"
        }
    ],
    "sg:phone":"+1 563 322 3825",
    "sg:postcode":"52801",
    "sg:province":"IA",
    "sg:tags":[
        "tavern",
        "delicatessen",
        "french"
    ],
    "wof:name":"Duck City Bistro",
    "wof:placetype":"venue"
},
  "geometry": {"coordinates":[-90.573905,41.522431],"type":"Point"}
}