{
  "type": "Feature",
  "properties": {
    "iso:country":"US",
    "sg:address":"1725 High St",
    "sg:city":"Council Bluffs",
    "sg:classifiers":[
        {
            "category":"Retail",
            "subcategory":"Auto Repair",
            "type":"Services"
        }
    ],
    "sg:phone":"+1 712 322 9132",
    "sg:postcode":"51503",
    "sg:province":"IA",
    "wof:name":"Kim's Phillips 66 Service & Repair",
    "wof:placetype":"venue"
},
  "geometry": {"coordinates":[-95.846603,41.245499],"type":"Point"}
}