{
  "type": "Feature",
  "properties": {
    "iso:country":"US",
    "sg:address":"605 9th St",
    "sg:city":"Onawa",
    "sg:classifiers":[
        {
            "category":"Utilities",
            "subcategory":"Electric",
            "type":"Services"
        }
    ],
    "sg:phone":"+1 712 423 3778",
    "sg:postcode":"51040",
    "sg:province":"IA",
    "sg:tags":[
        "company"
    ],
    "wof:name":"Northwest Iowa Power Co-Op",
    "wof:placetype":"venue"
},
  "geometry": {"coordinates":[-96.095741,42.031972],"type":"Point"}
}