{
  "type": "Feature",
  "properties": {
    "iso:country":"US",
    "sg:address":"840 Old Marion Rd NE",
    "sg:city":"Cedar Rapids",
    "sg:classifiers":[
        {
            "category":"Shopping",
            "subcategory":"Gifts & Souvenirs",
            "type":"Retail Goods"
        }
    ],
    "sg:phone":"+1 319 393 8681",
    "sg:postcode":"52402",
    "sg:province":"IA",
    "wof:name":"Victorian Hope Chest Inc",
    "wof:placetype":"venue"
},
  "geometry": {"coordinates":[-91.64713999999999,42.022966],"type":"Point"}
}