{
  "type": "Feature",
  "properties": {
    "addr:full":"371 Horseshoe Rd Sherrill IA 52073",
    "addr:housenumber":"371",
    "addr:postcode":"52073",
    "addr:street":"Horseshoe Rd",
    "iso:country":"US",
    "sg:address":"371 Horseshoe Rd",
    "sg:city":"Sherrill",
    "sg:classifiers":[
        {
            "category":"Professional",
            "subcategory":"Business Services",
            "type":"Services"
        }
    ],
    "sg:phone":"+1 563 552 2837",
    "sg:postcode":"52073",
    "sg:province":"IA",
    "wof:name":"Gn Technologies Inc",
    "wof:placetype":"venue"
},
  "geometry": {"coordinates":[-90.870997,42.635369],"type":"Point"}
}