{
  "type": "Feature",
  "properties": {
    "iso:country":"US",
    "sg:address":"8679 Primrose Ln",
    "sg:city":"Clive",
    "sg:classifiers":[
        {
            "category":"Insurance",
            "subcategory":"Insurance Agent",
            "type":"Services"
        }
    ],
    "sg:phone":"+1 515 276 1452",
    "sg:postcode":"50325",
    "sg:province":"IA",
    "wof:name":"Popken Enterprises",
    "wof:placetype":"venue"
},
  "geometry": {"coordinates":[-93.739499,41.610824],"type":"Point"}
}