{
  "type": "Feature",
  "properties": {
    "iso:country":"US",
    "sg:address":"1615 E Linden St",
    "sg:city":"Algona",
    "sg:classifiers":[
        {
            "category":"Personal",
            "subcategory":"Beauty Salon",
            "type":"Services"
        }
    ],
    "sg:phone":"+1 515 295 2608",
    "sg:postcode":"50511",
    "sg:province":"IA",
    "sg:tags":[
        "shop"
    ],
    "wof:name":"Julies Clip & Curl",
    "wof:placetype":"venue"
},
  "geometry": {"coordinates":[-94.217834,43.072848],"type":"Point"}
}