{
  "type": "Feature",
  "properties": {
    "iso:country":"US",
    "sg:address":"5680 Barcelona St",
    "sg:city":"Bettendorf",
    "sg:classifiers":[
        {
            "category":"Professional",
            "subcategory":"Art Services",
            "type":"Services"
        }
    ],
    "sg:phone":"+1 563 785 4584",
    "sg:postcode":"52722",
    "sg:province":"IA",
    "sg:tags":[
        "photographer"
    ],
    "wof:name":"J L Nelson Photography",
    "wof:placetype":"venue"
},
  "geometry": {"coordinates":[-90.493272,41.577162],"type":"Point"}
}