{
  "type": "Feature",
  "properties": {
    "iso:country":"US",
    "sg:address":"4355 Dodge St",
    "sg:city":"Dubuque",
    "sg:classifiers":[
        {
            "category":"Autos & Motor Vehicles",
            "subcategory":"Automobile Sales",
            "type":"Retail Goods"
        }
    ],
    "sg:phone":"+1 563 583 8825",
    "sg:postcode":"52003",
    "sg:province":"IA",
    "sg:tags":[
        "car",
        "dealer"
    ],
    "wof:name":"Mike Finnin Motors Inc",
    "wof:placetype":"venue"
},
  "geometry": {"coordinates":[-90.733977,42.49001],"type":"Point"}
}