{
  "type": "Feature",
  "properties": {
    "addr:full":"2616 Gloria Dr Waterloo IA 50701",
    "addr:housenumber":"2616",
    "addr:postcode":"50701",
    "addr:street":"Gloria Dr",
    "iso:country":"US",
    "sg:address":"2616 Gloria Dr",
    "sg:city":"Waterloo",
    "sg:classifiers":[
        {
            "category":"Organizations",
            "subcategory":"Professional Association",
            "type":"Services"
        }
    ],
    "sg:phone":"+1 319 236 8059",
    "sg:postcode":"50701",
    "sg:province":"IA",
    "wof:name":"Iowa Association-Chiefs-Police",
    "wof:placetype":"venue"
},
  "geometry": {"coordinates":[-92.385942,42.473655],"type":"Point"}
}