{
  "type": "Feature",
  "properties": {
    "addr:full":"1745 Brookville Rd Fairfield IA 52556",
    "addr:housenumber":"1745",
    "addr:postcode":"52556",
    "addr:street":"Brookville Rd",
    "iso:country":"US",
    "sg:address":"1745 Brookville Rd",
    "sg:city":"Fairfield",
    "sg:classifiers":[
        {
            "category":"Farming",
            "subcategory":"Dairy Farm",
            "type":"Manufacturing & Wholesale Goods"
        }
    ],
    "sg:phone":"+1 641 472 8554",
    "sg:postcode":"52556",
    "sg:province":"IA",
    "wof:name":"Radiance Dairy",
    "wof:placetype":"venue"
},
  "geometry": {"coordinates":[-92.03592500000001,41.038785],"type":"Point"}
}