{
  "type": "Feature",
  "properties": {
    "addr:full":"510 E North St Lake City IA 51449",
    "addr:housenumber":"510",
    "addr:postcode":"51449",
    "addr:street":"E North St",
    "iso:country":"US",
    "sg:address":"510 E North St",
    "sg:city":"Lake City",
    "sg:classifiers":[
        {
            "category":"Education",
            "subcategory":"School",
            "type":"Public Place"
        }
    ],
    "sg:phone":"+1 712 464 7239",
    "sg:postcode":"51449",
    "sg:province":"IA",
    "wof:name":"Lincoln Elementary School",
    "wof:placetype":"venue"
},
  "geometry": {"coordinates":[-94.727706,42.271031],"type":"Point"}
}