{
  "type": "Feature",
  "properties": {
    "iso:country":"US",
    "sg:address":"1146 Blairs Ferry Rd NE",
    "sg:city":"Cedar Rapids",
    "sg:classifiers":[
        {
            "category":"Personal",
            "subcategory":"Beauty Salon",
            "type":"Services"
        }
    ],
    "sg:phone":"+1 319 743 0411",
    "sg:postcode":"52402",
    "sg:province":"IA",
    "wof:name":"Studio 1146 Salon & Spa",
    "wof:placetype":"venue"
},
  "geometry": {"coordinates":[-91.65401900000001,42.035304],"type":"Point"}
}