{
  "type": "Feature",
  "properties": {
    "iso:country":"US",
    "sg:address":"925 S 3rd St",
    "sg:city":"Clinton",
    "sg:classifiers":[
        {
            "category":"Government",
            "subcategory":"Office",
            "type":"Public Place"
        }
    ],
    "sg:phone":"+1 563 242 5756",
    "sg:postcode":"52732",
    "sg:province":"IA",
    "sg:tags":[
        "village"
    ],
    "wof:name":"Clinton Street Div",
    "wof:placetype":"venue"
},
  "geometry": {"coordinates":[-90.190641,41.836222],"type":"Point"}
}