{
  "type": "Feature",
  "properties": {
    "addr:full":"2382 317th St Bedford IA 50833",
    "addr:housenumber":"2382",
    "addr:postcode":"50833",
    "addr:street":"317Th St",
    "iso:country":"US",
    "sg:address":"2382 317th St",
    "sg:city":"Bedford",
    "sg:classifiers":[
        {
            "category":"Real Estate",
            "subcategory":"Real Estate Operator",
            "type":"Services"
        }
    ],
    "sg:phone":"+1 712 523 2123",
    "sg:postcode":"50833",
    "sg:province":"IA",
    "sg:tags":[
        "property",
        "lessor"
    ],
    "wof:name":"Jack Bowman",
    "wof:placetype":"venue"
},
  "geometry": {"coordinates":[-94.66325500000001,40.585859],"type":"Point"}
}