{
  "type": "Feature",
  "properties": {
    "iso:country":"US",
    "sg:address":"616 10th St",
    "sg:city":"Fort Madison",
    "sg:classifiers":[
        {
            "category":"Restaurant",
            "type":"Food & Drink"
        }
    ],
    "sg:phone":"+1 319 372 6985",
    "sg:postcode":"52627",
    "sg:province":"IA",
    "wof:name":"10th Street Station",
    "wof:placetype":"venue"
},
  "geometry": {"coordinates":[-91.315212,40.631864],"type":"Point"}
}