{
  "type": "Feature",
  "properties": {
    "addr:full":"5418 Blairs Forest Way NE Cedar Rapids IA 52402",
    "addr:housenumber":"5418",
    "addr:postcode":"52402",
    "addr:street":"Blairs Forest Way Ne",
    "iso:country":"US",
    "sg:address":"5418 Blairs Forest Way NE",
    "sg:city":"Cedar Rapids",
    "sg:classifiers":[
        {
            "category":"Insurance",
            "subcategory":"Health Insurance",
            "type":"Services"
        }
    ],
    "sg:phone":"+1 319 378 8917",
    "sg:postcode":"52402",
    "sg:province":"IA",
    "sg:tags":[
        "market"
    ],
    "sg:website":"www.gnc.com",
    "wof:name":"General Nutrition Center",
    "wof:placetype":"venue"
},
  "geometry": {"coordinates":[-91.6782,42.033798],"type":"Point"}
}