{
  "type": "Feature",
  "properties": {
    "iso:country":"US",
    "sg:address":"112 4th St SW",
    "sg:city":"State Center",
    "sg:classifiers":[
        {
            "category":"Retail",
            "subcategory":"Auto Repair",
            "type":"Services"
        }
    ],
    "sg:phone":"+1 641 483 2432",
    "sg:postcode":"50247",
    "sg:province":"IA",
    "sg:tags":[
        "body",
        "automobile",
        "painting",
        "general"
    ],
    "wof:name":"Terry's Auto Repair",
    "wof:placetype":"venue"
},
  "geometry": {"coordinates":[-93.16301300000001,42.013553],"type":"Point"}
}