{
  "type": "Feature",
  "properties": {
    "iso:country":"US",
    "sg:address":"2700 Ford St",
    "sg:city":"Ames",
    "sg:classifiers":[
        {
            "category":"Autos & Motor Vehicles",
            "subcategory":"Automobile Sales",
            "type":"Retail Goods"
        }
    ],
    "sg:phone":"+1 515 233 2700",
    "sg:postcode":"50010",
    "sg:province":"IA",
    "sg:tags":[
        "car",
        "dealer"
    ],
    "wof:name":"Badger Auto Sales Co",
    "wof:placetype":"venue"
},
  "geometry": {"coordinates":[-93.575896,42.026737],"type":"Point"}
}