{
  "type": "Feature",
  "properties": {
    "iso:country":"US",
    "sg:address":"632 S Main St",
    "sg:city":"Walcott",
    "sg:classifiers":[
        {
            "category":"Health Services",
            "subcategory":"Chiropractor",
            "type":"Services"
        }
    ],
    "sg:phone":"+1 563 284 6939",
    "sg:postcode":"52773",
    "sg:province":"IA",
    "wof:name":"Allmandinger Chiropractic Off",
    "wof:placetype":"venue"
},
  "geometry": {"coordinates":[-90.77477,41.580305],"type":"Point"}
}