{
  "type": "Feature",
  "properties": {
    "iso:country":"US",
    "sg:address":"1650 1st Ave NE",
    "sg:city":"Cedar Rapids",
    "sg:classifiers":[
        {
            "category":"Health Services",
            "subcategory":"Optometrist",
            "type":"Services"
        }
    ],
    "sg:phone":"+1 319 362 3937",
    "sg:postcode":"52402",
    "sg:province":"IA",
    "sg:tags":[
        "ophthalmologist"
    ],
    "wof:name":"Iowa Eye Center",
    "wof:placetype":"venue"
},
  "geometry": {"coordinates":[-91.6474,41.993801],"type":"Point"}
}