{
  "type": "Feature",
  "properties": {
    "iso:country":"US",
    "sg:address":"3124 Taylor Ave",
    "sg:city":"Persia",
    "sg:classifiers":[
        {
            "category":"Farming",
            "subcategory":"Farm",
            "type":"Manufacturing & Wholesale Goods"
        }
    ],
    "sg:phone":"+1 712 488 7268",
    "sg:postcode":"51563",
    "sg:province":"IA",
    "sg:tags":[
        "crop",
        "general"
    ],
    "wof:name":"Fred Divebless",
    "wof:placetype":"venue"
},
  "geometry": {"coordinates":[-95.631557,41.55945],"type":"Point"}
}