{
  "type": "Feature",
  "properties": {
    "addr:full":"3001 E 14th St Des Moines IA 50316",
    "addr:housenumber":"3001",
    "addr:postcode":"50316",
    "addr:street":"E 14Th St",
    "iso:country":"US",
    "sg:address":"3001 E 14th St",
    "sg:city":"Des Moines",
    "sg:classifiers":[
        {
            "category":"Home & Garden",
            "subcategory":"Hardware",
            "type":"Retail Goods"
        }
    ],
    "sg:phone":"+1 515 262 2162",
    "sg:postcode":"50316",
    "sg:province":"IA",
    "wof:name":"Thrasher's Hardware Inc",
    "wof:placetype":"venue"
},
  "geometry": {"coordinates":[-93.60053000000001,41.623189],"type":"Point"}
}