{
  "type": "Feature",
  "properties": {
    "addr:full":"615 58th Avenue Ct SW Cedar Rapids IA 52404",
    "addr:housenumber":"615",
    "addr:postcode":"52404",
    "addr:street":"58Th Avenue Ct Sw",
    "iso:country":"US",
    "sg:address":"615 58th Avenue Ct SW",
    "sg:city":"Cedar Rapids",
    "sg:classifiers":[
        {
            "category":"Wholesale",
            "subcategory":"Machinery & Supplies",
            "type":"Manufacturing & Wholesale Goods"
        }
    ],
    "sg:phone":"+1 319 363 2156",
    "sg:postcode":"52404",
    "sg:province":"IA",
    "sg:tags":[
        "equipment",
        "welding"
    ],
    "sg:website":"www.praxair.com",
    "wof:name":"Praxair Inc",
    "wof:placetype":"venue"
},
  "geometry": {"coordinates":[-91.67988099999999,41.921916],"type":"Point"}
}