{
  "type": "Feature",
  "properties": {
    "addr:full":"1100 NW Gabus Cir Grimes IA 50111",
    "addr:housenumber":"1100",
    "addr:postcode":"50111",
    "addr:street":"Nw Gabus Cir",
    "iso:country":"US",
    "sg:address":"1100 NW Gabus Cir",
    "sg:city":"Grimes",
    "sg:classifiers":[
        {
            "category":"Organizations",
            "subcategory":"Religious Organization",
            "type":"Services"
        }
    ],
    "sg:phone":"+1 515 986 5433",
    "sg:postcode":"50111",
    "sg:province":"IA",
    "sg:tags":[
        "church"
    ],
    "sg:website":"www.crossroads.lifewaylink.com",
    "wof:name":"Crossroads Community Church",
    "wof:placetype":"venue"
},
  "geometry": {"coordinates":[-93.79544300000001,41.698065],"type":"Point"}
}