{
  "type": "Feature",
  "properties": {
    "addr:full":"1229 25th St Des Moines IA 50311",
    "addr:housenumber":"1229",
    "addr:postcode":"50311",
    "addr:street":"25Th St",
    "iso:country":"US",
    "sg:address":"1229 25th St",
    "sg:city":"Des Moines",
    "sg:classifiers":[
        {
            "category":"Restaurant",
            "type":"Food & Drink"
        }
    ],
    "sg:phone":"+1 515 255 0535",
    "sg:postcode":"50311",
    "sg:province":"IA",
    "sg:website":"www.varsitycafe.com",
    "wof:name":"25th Street Cafe",
    "wof:placetype":"venue"
},
  "geometry": {"coordinates":[-93.650865,41.601352],"type":"Point"}
}