{
  "type": "Feature",
  "properties": {
    "iso:country":"US",
    "sg:address":"1000 Walton Rd",
    "sg:city":"Fairfield",
    "sg:classifiers":[
        {
            "category":"Professional",
            "subcategory":"Business Services",
            "type":"Services"
        }
    ],
    "sg:phone":"+1 641 472 4016",
    "sg:postcode":"52556",
    "sg:province":"IA",
    "wof:name":"Hirshberg & Assoc LLC",
    "wof:placetype":"venue"
},
  "geometry": {"coordinates":[-91.952533,41.01632],"type":"Point"}
}