{
  "type": "Feature",
  "properties": {
    "iso:country":"US",
    "sg:address":"109 E State St",
    "sg:city":"Algona",
    "sg:classifiers":[
        {
            "category":"Shopping",
            "subcategory":"Florist",
            "type":"Retail Goods"
        }
    ],
    "sg:phone":"+1 515 295 9483",
    "sg:postcode":"50511",
    "sg:province":"IA",
    "wof:name":"Buscher Florist Party Supplies",
    "wof:placetype":"venue"
},
  "geometry": {"coordinates":[-94.236637,43.068939],"type":"Point"}
}