{
  "type": "Feature",
  "properties": {
    "iso:country":"US",
    "sg:address":"1700 Dixon St",
    "sg:city":"Des Moines",
    "sg:classifiers":[
        {
            "category":"Shopping",
            "subcategory":"Computers & Home Electronics",
            "type":"Retail Goods"
        }
    ],
    "sg:phone":"+1 515 264 7956",
    "sg:postcode":"50316",
    "sg:province":"IA",
    "sg:tags":[
        "software"
    ],
    "wof:name":"MIDWEST Computer Ctr",
    "wof:placetype":"venue"
},
  "geometry": {"coordinates":[-93.58923,41.607986],"type":"Point"}
}