{
  "type": "Feature",
  "properties": {
    "addr:full":"1610 Country Club Rd Indianola IA 50125",
    "addr:housenumber":"1610",
    "addr:postcode":"50125",
    "addr:street":"Country Club Rd",
    "iso:country":"US",
    "sg:address":"1610 Country Club Rd",
    "sg:city":"Indianola",
    "sg:classifiers":[
        {
            "category":"Recreation",
            "type":"Entertainment"
        }
    ],
    "sg:phone":"+1 515 961 3303",
    "sg:postcode":"50125",
    "sg:province":"IA",
    "sg:tags":[
        "course",
        "golf"
    ],
    "sg:website":"www.indianolacountryclub.com",
    "wof:name":"Indianola Country Club",
    "wof:placetype":"venue"
},
  "geometry": {"coordinates":[-93.568003,41.381831],"type":"Point"}
}