{
  "type": "Feature",
  "properties": {
    "iso:country":"US",
    "sg:address":"1608 1st Ave S",
    "sg:city":"Fort Dodge",
    "sg:classifiers":[
        {
            "category":"Banks & Credit Unions",
            "subcategory":"Bank",
            "type":"Services"
        }
    ],
    "sg:phone":"+1 515 576 5111",
    "sg:postcode":"50501",
    "sg:province":"IA",
    "sg:tags":[
        "loan"
    ],
    "sg:website":"www.unitedbk.com",
    "wof:name":"United Bank Of Iowa",
    "wof:placetype":"venue"
},
  "geometry": {"coordinates":[-94.17501,42.505247],"type":"Point"}
}