{
  "type": "Feature",
  "properties": {
    "iso:country":"US",
    "sg:address":"59 5th St",
    "sg:city":"West Point",
    "sg:classifiers":[
        {
            "category":"Personal",
            "subcategory":"Beauty Salon",
            "type":"Services"
        }
    ],
    "sg:phone":"+1 319 837 6324",
    "sg:postcode":"52656",
    "sg:province":"IA",
    "wof:name":"Centre Of Attraction",
    "wof:placetype":"venue"
},
  "geometry": {"coordinates":[-91.452353,40.714836],"type":"Point"}
}