{
  "type": "Feature",
  "properties": {
    "iso:country":"US",
    "sg:address":"2912 W 13th St",
    "sg:city":"Davenport",
    "sg:classifiers":[
        {
            "category":"Personal",
            "type":"Services"
        }
    ],
    "sg:phone":"+1 563 323 5137",
    "sg:postcode":"52804",
    "sg:province":"IA",
    "wof:name":"Horizons Above Massage Center",
    "wof:placetype":"venue"
},
  "geometry": {"coordinates":[-90.618983,41.532867],"type":"Point"}
}