{
  "type": "Feature",
  "properties": {
    "iso:country":"US",
    "sg:address":"18 W Main St",
    "sg:city":"Treynor",
    "sg:classifiers":[
        {
            "category":"Restaurant",
            "type":"Food & Drink"
        }
    ],
    "sg:phone":"+1 712 487 3113",
    "sg:postcode":"51575",
    "sg:province":"IA",
    "wof:name":"Blimpie Subs & Salads",
    "wof:placetype":"venue"
},
  "geometry": {"coordinates":[-95.617053,41.232488],"type":"Point"}
}