{
  "type": "Feature",
  "properties": {
    "iso:country":"US",
    "sg:address":"19481 Highway 5",
    "sg:city":"Centerville",
    "sg:classifiers":[
        {
            "category":"Autos & Motor Vehicles",
            "subcategory":"Automobile Sales",
            "type":"Retail Goods"
        },
        {
            "category":"Retail",
            "subcategory":"Auto Repair",
            "type":"Services"
        }
    ],
    "sg:phone":"+1 641 437 4882",
    "sg:postcode":"52544",
    "sg:province":"IA",
    "sg:tags":[
        "body",
        "cars-wholesale",
        "used",
        "car",
        "dealers-used",
        "painting",
        "repairing"
    ],
    "wof:name":"Kirkland Auto Sales",
    "wof:placetype":"venue"
},
  "geometry": {"coordinates":[-92.858155,40.759209],"type":"Point"}
}