{
  "type": "Feature",
  "properties": {
    "iso:country":"US",
    "sg:address":"4502 Blairs Ferry Rd",
    "sg:city":"Cedar Rapids",
    "sg:classifiers":[
        {
            "category":"Organizations",
            "subcategory":"Religious Organization",
            "type":"Services"
        }
    ],
    "sg:phone":"+1 319 393 3900",
    "sg:postcode":"52411",
    "sg:province":"IA",
    "sg:website":"www.blairridge.org",
    "wof:name":"Blair Ridge Baptist Church",
    "wof:placetype":"venue"
},
  "geometry": {"coordinates":[-91.725037,42.040578],"type":"Point"}
}