{
  "type": "Feature",
  "properties": {
    "iso:country":"US",
    "sg:address":"427 Benton St",
    "sg:city":"Boone",
    "sg:classifiers":[
        {
            "category":"Professional",
            "subcategory":"Accounting & Tax Preparation",
            "type":"Services"
        }
    ],
    "sg:phone":"+1 515 432 2735",
    "sg:postcode":"50036",
    "sg:province":"IA",
    "sg:tags":[
        "accountant"
    ],
    "wof:name":"Moore Accounting & Tax Svc",
    "wof:placetype":"venue"
},
  "geometry": {"coordinates":[-93.87505899999999,42.060415],"type":"Point"}
}