{
  "type": "Feature",
  "properties": {
    "addr:full":"4915 Maple Dr Pleasant Hill IA 50327",
    "addr:housenumber":"4915",
    "addr:postcode":"50327",
    "addr:street":"Maple Dr",
    "iso:country":"US",
    "sg:address":"4915 Maple Dr",
    "sg:city":"Pleasant Hill",
    "sg:classifiers":[
        {
            "category":"Food & Beverages",
            "subcategory":"Groceries & Convenience Stores",
            "type":"Retail Goods"
        }
    ],
    "sg:phone":"+1 515 266 6080",
    "sg:postcode":"50327",
    "sg:province":"IA",
    "wof:name":"Kum & Go",
    "wof:placetype":"venue"
},
  "geometry": {"coordinates":[-93.51784000000001,41.597928],"type":"Point"}
}