{
  "type": "Feature",
  "properties": {
    "iso:country":"US",
    "sg:address":"9 N Elk Run Rd",
    "sg:city":"Waterloo",
    "sg:classifiers":[
        {
            "category":"Food & Beverages",
            "subcategory":"Groceries & Convenience Stores",
            "type":"Retail Goods"
        }
    ],
    "sg:phone":"+1 319 232 8954",
    "sg:postcode":"50703",
    "sg:province":"IA",
    "wof:name":"New Star",
    "wof:placetype":"venue"
},
  "geometry": {"coordinates":[-92.258752,42.498276],"type":"Point"}
}