{
  "type": "Feature",
  "properties": {
    "iso:country":"US",
    "sg:address":"4444 Czech Ln NE",
    "sg:city":"Cedar Rapids",
    "sg:classifiers":[
        {
            "category":"Travel",
            "subcategory":"Hotels & Motels",
            "type":"Entertainment"
        }
    ],
    "sg:phone":"+1 319 294 8211",
    "sg:postcode":"52402",
    "sg:province":"IA",
    "wof:name":"Leisure Hotels Llc",
    "wof:placetype":"venue"
},
  "geometry": {"coordinates":[-91.672997,42.0224],"type":"Point"}
}