{
  "type": "Feature",
  "properties": {
    "iso:country":"US",
    "sg:address":"23209 470th St",
    "sg:city":"Lake Mills",
    "sg:classifiers":[
        {
            "category":"Building & Trades",
            "subcategory":"Electrical",
            "type":"Services"
        }
    ],
    "sg:phone":"+1 641 592 8036",
    "sg:postcode":"50450",
    "sg:province":"IA",
    "sg:tags":[
        "electric",
        "contractor"
    ],
    "wof:name":"Rao Electric",
    "wof:placetype":"venue"
},
  "geometry": {"coordinates":[-93.533467,43.444705],"type":"Point"}
}