{
  "type": "Feature",
  "properties": {
    "addr:full":"810 5th St Durant IA 52747",
    "addr:housenumber":"810",
    "addr:postcode":"52747",
    "addr:street":"5Th St",
    "iso:country":"US",
    "sg:address":"810 5th St",
    "sg:city":"Durant",
    "sg:classifiers":[
        {
            "category":"Professional",
            "subcategory":"Accounting & Tax Preparation",
            "type":"Services"
        }
    ],
    "sg:phone":"+1 563 785 6996",
    "sg:postcode":"52747",
    "sg:province":"IA",
    "sg:tags":[
        "return",
        "filing"
    ],
    "wof:name":"Cynthia Puck Ap Tax Svc",
    "wof:placetype":"venue"
},
  "geometry": {"coordinates":[-90.908421,41.600371],"type":"Point"}
}