{
  "type": "Feature",
  "properties": {
    "iso:country":"US",
    "sg:address":"125 N 15th St",
    "sg:city":"Clarinda",
    "sg:classifiers":[
        {
            "category":"Home & Garden",
            "subcategory":"Garden Supply",
            "type":"Retail Goods"
        }
    ],
    "sg:phone":"+1 712 542 5649",
    "sg:postcode":"51632",
    "sg:province":"IA",
    "sg:tags":[
        "lawn",
        "mower"
    ],
    "wof:name":"Earl Schenck Corp",
    "wof:placetype":"venue"
},
  "geometry": {"coordinates":[-95.036432,40.738522],"type":"Point"}
}