{
  "type": "Feature",
  "properties": {
    "addr:full":"1665 Embassy West Dr Dubuque IA 52002",
    "addr:housenumber":"1665",
    "addr:postcode":"52002",
    "addr:street":"Embassy West Dr",
    "iso:country":"US",
    "sg:address":"1665 Embassy West Dr",
    "sg:city":"Dubuque",
    "sg:classifiers":[
        {
            "category":"Shopping",
            "type":"Retail Goods"
        }
    ],
    "sg:phone":"+1 563 556 0021",
    "sg:postcode":"52002",
    "sg:province":"IA",
    "sg:tags":[
        "orthopedic",
        "appliance"
    ],
    "wof:name":"Hanger Prosthetics & Orthotics",
    "wof:placetype":"venue"
},
  "geometry": {"coordinates":[-90.74380600000001,42.501413],"type":"Point"}
}