{
  "type": "Feature",
  "properties": {
    "addr:full":"1470 Deer Ave Corwith IA 50430",
    "addr:housenumber":"1470",
    "addr:postcode":"50430",
    "addr:street":"Deer Ave",
    "iso:country":"US",
    "sg:address":"1470 Deer Ave",
    "sg:city":"Corwith",
    "sg:phone":"+1 515 583 2630",
    "sg:postcode":"50430",
    "sg:province":"IA",
    "sg:tags":[
        "farm",
        "corn"
    ],
    "wof:name":"Paul Studer",
    "wof:placetype":"venue"
},
  "geometry": {"coordinates":[-93.91160600000001,42.977206],"type":"Point"}
}