{
  "type": "Feature",
  "properties": {
    "iso:country":"US",
    "sg:address":"1627 W Locust St",
    "sg:city":"Davenport",
    "sg:classifiers":[
        {
            "category":"Retail",
            "subcategory":"Animal Services",
            "type":"Services"
        }
    ],
    "sg:phone":"+1 563 323 5832",
    "sg:postcode":"52804",
    "sg:province":"IA",
    "sg:tags":[
        "boarding"
    ],
    "wof:name":"Kozy Kennels Korner",
    "wof:placetype":"venue"
},
  "geometry": {"coordinates":[-90.599672,41.538179],"type":"Point"}
}