{
  "type": "Feature",
  "properties": {
    "addr:full":"208 E Charles St Oelwein IA 50662",
    "addr:housenumber":"208",
    "addr:postcode":"50662",
    "addr:street":"E Charles St",
    "iso:country":"US",
    "sg:address":"208 E Charles St",
    "sg:city":"Oelwein",
    "sg:classifiers":[
        {
            "category":"Banks & Credit Unions",
            "subcategory":"Financial Services",
            "type":"Services"
        }
    ],
    "sg:phone":"+1 319 283 2541",
    "sg:postcode":"50662",
    "sg:province":"IA",
    "sg:tags":[
        "annuity",
        "insurance"
    ],
    "wof:name":"Modern Woodmen Of America",
    "wof:placetype":"venue"
},
  "geometry": {"coordinates":[-91.91036,42.678489],"type":"Point"}
}