{
  "type": "Feature",
  "properties": {
    "iso:country":"US",
    "sg:address":"212 N Iowa Ave",
    "sg:city":"Washington",
    "sg:classifiers":[
        {
            "category":"Professional",
            "subcategory":"Research",
            "type":"Services"
        }
    ],
    "sg:phone":"+1 319 653 3942",
    "sg:postcode":"52353",
    "sg:province":"IA",
    "sg:tags":[
        "organization",
        "noncommercial"
    ],
    "wof:name":"Washington Economic Dev Group",
    "wof:placetype":"venue"
},
  "geometry": {"coordinates":[-91.691512,41.301262],"type":"Point"}
}