{
  "type": "Feature",
  "properties": {
    "addr:full":"215 1st St NW Buffalo Center IA 50424",
    "addr:housenumber":"215",
    "addr:postcode":"50424",
    "addr:street":"1St St Nw",
    "iso:country":"US",
    "sg:address":"215 1st St NW",
    "sg:city":"Buffalo Center",
    "sg:classifiers":[
        {
            "category":"Organizations",
            "subcategory":"Religious Organization",
            "type":"Services"
        }
    ],
    "sg:phone":"+1 641 562 2251",
    "sg:postcode":"50424",
    "sg:province":"IA",
    "sg:tags":[
        "church"
    ],
    "wof:name":"United Methodist Church",
    "wof:placetype":"venue"
},
  "geometry": {"coordinates":[-93.94765,43.387888],"type":"Point"}
}