{
  "type": "Feature",
  "properties": {
    "addr:full":"14279 200th St Arcadia IA 51430",
    "addr:housenumber":"14279",
    "addr:postcode":"51430",
    "addr:street":"200Th St",
    "iso:country":"US",
    "sg:address":"14279 200th St",
    "sg:city":"Arcadia",
    "sg:classifiers":[
        {
            "category":"Real Estate",
            "subcategory":"Real Estate Operator",
            "type":"Services"
        }
    ],
    "sg:phone":"+1 712 689 2513",
    "sg:postcode":"51430",
    "sg:province":"IA",
    "sg:tags":[
        "property",
        "lessor"
    ],
    "wof:name":"Donald Badding",
    "wof:placetype":"venue"
},
  "geometry": {"coordinates":[-95.014115,42.064599],"type":"Point"}
}