{
  "type": "Feature",
  "properties": {
    "addr:full":"113 N Main St Paullina IA 51046",
    "addr:housenumber":"113",
    "addr:postcode":"51046",
    "addr:street":"N Main St",
    "iso:country":"US",
    "sg:address":"113 N Main St",
    "sg:city":"Paullina",
    "sg:classifiers":[
        {
            "category":"Shopping",
            "subcategory":"Used Merchandise",
            "type":"Retail Goods"
        }
    ],
    "sg:phone":"+1 712 949 4949",
    "sg:postcode":"51046",
    "sg:province":"IA",
    "sg:tags":[
        "antique"
    ],
    "wof:name":"Old Market Antique & Book",
    "wof:placetype":"venue"
},
  "geometry": {"coordinates":[-95.687926,42.982648],"type":"Point"}
}