{
  "type": "Feature",
  "properties": {
    "addr:full":"3778 450th Ave Emmetsburg IA 50536",
    "addr:housenumber":"3778",
    "addr:postcode":"50536",
    "addr:street":"450Th Ave",
    "iso:country":"US",
    "sg:address":"3778 450th Ave",
    "sg:city":"Emmetsburg",
    "sg:classifiers":[
        {
            "category":"Wholesale",
            "subcategory":"Auto Parts",
            "type":"Manufacturing & Wholesale Goods"
        }
    ],
    "sg:phone":"+1 712 852 2392",
    "sg:postcode":"50536",
    "sg:province":"IA",
    "sg:tags":[
        "automobile",
        "wrecking"
    ],
    "wof:name":"Wickman Auto Salvage",
    "wof:placetype":"venue"
},
  "geometry": {"coordinates":[-94.698683,43.10005],"type":"Point"}
}