{
  "type": "Feature",
  "properties": {
    "addr:full":"220 Highway 6 Waukee IA 50263",
    "addr:housenumber":"220",
    "addr:postcode":"50263",
    "addr:street":"Highway 6",
    "iso:country":"US",
    "sg:address":"220 Highway 6",
    "sg:city":"Waukee",
    "sg:classifiers":[
        {
            "category":"Ice Cream",
            "type":"Food & Drink"
        }
    ],
    "sg:menulink":"http://www.allmenus.com/ia/walnut/172700-dairy-queen/menu/",
    "sg:phone":"+1 515 987 7801",
    "sg:postcode":"50263",
    "sg:province":"IA",
    "sg:tags":[
        "burger",
        "american"
    ],
    "wof:name":"Dairy Queen",
    "wof:placetype":"venue"
},
  "geometry": {"coordinates":[-93.877799,41.61472],"type":"Point"}
}