{
  "type": "Feature",
  "properties": {
    "iso:country":"US",
    "sg:address":"110 E Center St",
    "sg:city":"Conrad",
    "sg:classifiers":[
        {
            "category":"Shopping",
            "subcategory":"Pharmacy",
            "type":"Retail Goods"
        }
    ],
    "sg:phone":"+1 641 366 2441",
    "sg:postcode":"50621",
    "sg:province":"IA",
    "wof:name":"Conrad Pharmacy",
    "wof:placetype":"venue"
},
  "geometry": {"coordinates":[-92.87447299999999,42.224576],"type":"Point"}
}