{
  "type": "Feature",
  "properties": {
    "addr:full":"200 N Wilson St Jefferson IA 50129",
    "addr:housenumber":"200",
    "addr:postcode":"50129",
    "addr:street":"N Wilson St",
    "iso:country":"US",
    "sg:address":"200 N Wilson St",
    "sg:city":"Jefferson",
    "sg:classifiers":[
        {
            "category":"Real Estate",
            "subcategory":"Real Estate Agent",
            "type":"Services"
        }
    ],
    "sg:phone":"+1 515 386 8156",
    "sg:postcode":"50129",
    "sg:province":"IA",
    "sg:website":"www.marsopeckumn.com",
    "wof:name":"Marso Peckumn Real Estate",
    "wof:placetype":"venue"
},
  "geometry": {"coordinates":[-94.374752,42.017251],"type":"Point"}
}