{
  "type": "Feature",
  "properties": {
    "addr:full":"100 N Oak St Anamosa IA 52205",
    "addr:housenumber":"100",
    "addr:postcode":"52205",
    "addr:street":"N Oak St",
    "iso:country":"US",
    "sg:address":"100 N Oak St",
    "sg:city":"Anamosa",
    "sg:classifiers":[
        {
            "category":"Freight",
            "type":"Transportation"
        }
    ],
    "sg:phone":"+1 319 462 3944",
    "sg:postcode":"52205",
    "sg:province":"IA",
    "sg:tags":[
        "livestock",
        "hauling"
    ],
    "wof:name":"Brickley Truck Line",
    "wof:placetype":"venue"
},
  "geometry": {"coordinates":[-91.27345699999999,42.108832],"type":"Point"}
}