{
  "type": "Feature",
  "properties": {
    "addr:full":"1109 Siemer Dr Denison IA 51442",
    "addr:housenumber":"1109",
    "addr:postcode":"51442",
    "addr:street":"Siemer Dr",
    "iso:country":"US",
    "sg:address":"1109 Siemer Dr",
    "sg:city":"Denison",
    "sg:classifiers":[
        {
            "category":"Farming",
            "subcategory":"Farm",
            "type":"Manufacturing & Wholesale Goods"
        }
    ],
    "sg:phone":"+1 712 263 3585",
    "sg:postcode":"51442",
    "sg:province":"IA",
    "sg:tags":[
        "real",
        "property",
        "crop",
        "lessor",
        "general"
    ],
    "wof:name":"Walter Brummer",
    "wof:placetype":"venue"
},
  "geometry": {"coordinates":[-95.33991,42.006197],"type":"Point"}
}