{
  "type": "Feature",
  "properties": {
    "addr:full":"408 Church St Exira IA 50076",
    "addr:housenumber":"408",
    "addr:postcode":"50076",
    "addr:street":"Church St",
    "iso:country":"US",
    "sg:address":"408 Church St",
    "sg:city":"Exira",
    "sg:classifiers":[
        {
            "category":"Freight",
            "type":"Transportation"
        }
    ],
    "sg:phone":"+1 712 268 2270",
    "sg:postcode":"50076",
    "sg:province":"IA",
    "sg:tags":[
        "livestock",
        "hauling"
    ],
    "wof:name":"Phippen Trucking",
    "wof:placetype":"venue"
},
  "geometry": {"coordinates":[-94.872933,41.59465],"type":"Point"}
}