{
  "type": "Feature",
  "properties": {
    "addr:full":"10101 University Ave Clive IA 50325",
    "addr:housenumber":"10101",
    "addr:postcode":"50325",
    "addr:street":"University Ave",
    "iso:country":"US",
    "sg:address":"10101 University Ave",
    "sg:city":"Clive",
    "sg:classifiers":[
        {
            "category":"Health Services",
            "subcategory":"Clinic",
            "type":"Services"
        }
    ],
    "sg:phone":"+1 515 224 6056",
    "sg:postcode":"50325",
    "sg:province":"IA",
    "sg:tags":[
        "home"
    ],
    "sg:website":"www.kellyhomecare.com",
    "wof:name":"Kelly Home Care Svc",
    "wof:placetype":"venue"
},
  "geometry": {"coordinates":[-93.76031500000001,41.600507],"type":"Point"}
}