{
  "type": "Feature",
  "properties": {
    "iso:country":"US",
    "sg:address":"4631 White Ave",
    "sg:city":"Sutherland",
    "sg:classifiers":[
        {
            "category":"Wholesale",
            "subcategory":"Scrap",
            "type":"Manufacturing & Wholesale Goods"
        }
    ],
    "sg:phone":"+1 712 446 3639",
    "sg:postcode":"51058",
    "sg:province":"IA",
    "sg:tags":[
        "recycling",
        "center"
    ],
    "wof:name":"Tri-State Antifreeze Recycling",
    "wof:placetype":"venue"
},
  "geometry": {"coordinates":[-95.447019,42.977833],"type":"Point"}
}