{
  "type": "Feature",
  "properties": {
    "addr:full":"320 N 4th St Clinton IA 52732",
    "addr:housenumber":"320",
    "addr:postcode":"52732",
    "addr:street":"N 4Th St",
    "iso:country":"US",
    "sg:address":"320 N 4th St",
    "sg:city":"Clinton",
    "sg:classifiers":[
        {
            "category":"Food & Beverages",
            "subcategory":"Bakery",
            "type":"Retail Goods"
        }
    ],
    "sg:phone":"+1 563 242 3541",
    "sg:postcode":"52732",
    "sg:province":"IA",
    "sg:tags":[
        "baker"
    ],
    "wof:name":"Wonder Hostess Outlet",
    "wof:placetype":"venue"
},
  "geometry": {"coordinates":[-90.193228,41.848637],"type":"Point"}
}