{
  "type": "Feature",
  "properties": {
    "iso:country":"US",
    "sg:address":"2444 E Kimberly Rd",
    "sg:city":"Davenport",
    "sg:classifiers":[
        {
            "category":"Professional",
            "subcategory":"Accounting & Tax Preparation",
            "type":"Services"
        }
    ],
    "sg:phone":"+1 563 359 4985",
    "sg:postcode":"52807",
    "sg:province":"IA",
    "sg:tags":[
        "accountant"
    ],
    "wof:name":"Horan Barker & Collins",
    "wof:placetype":"venue"
},
  "geometry": {"coordinates":[-90.540519,41.557034],"type":"Point"}
}