{
  "type": "Feature",
  "properties": {
    "iso:country":"US",
    "sg:address":"604 Hill Ave",
    "sg:city":"Spirit Lake",
    "sg:classifiers":[
        {
            "category":"Government",
            "subcategory":"Office",
            "type":"Public Place"
        }
    ],
    "sg:phone":"+1 712 336 2127",
    "sg:postcode":"51360",
    "sg:province":"IA",
    "sg:tags":[
        "govt",
        "city"
    ],
    "wof:name":"Spirit Lake Water Treatment",
    "wof:placetype":"venue"
},
  "geometry": {"coordinates":[-95.103432,43.435103],"type":"Point"}
}