{
  "type": "Feature",
  "properties": {
    "iso:country":"US",
    "sg:address":"130 E 11th St",
    "sg:city":"Monticello",
    "sg:classifiers":[
        {
            "category":"Manufacturing",
            "subcategory":"Pet Food",
            "type":"Manufacturing & Wholesale Goods"
        }
    ],
    "sg:phone":"+1 319 465 4220",
    "sg:postcode":"52310",
    "sg:province":"IA",
    "sg:tags":[
        "feed"
    ],
    "wof:name":"Frontier Feeds",
    "wof:placetype":"venue"
},
  "geometry": {"coordinates":[-91.19213000000001,42.252666],"type":"Point"}
}