{
  "type": "Feature",
  "properties": {
    "addr:full":"660 1st St Battle Creek IA 51006",
    "addr:housenumber":"660",
    "addr:postcode":"51006",
    "addr:street":"1St St",
    "iso:country":"US",
    "sg:address":"660 1st St",
    "sg:city":"Battle Creek",
    "sg:classifiers":[
        {
            "category":"Food & Beverages",
            "subcategory":"Groceries & Convenience Stores",
            "type":"Retail Goods"
        }
    ],
    "sg:phone":"+1 712 365 4675",
    "sg:postcode":"51006",
    "sg:province":"IA",
    "wof:name":"Sparkies One Stop",
    "wof:placetype":"venue"
},
  "geometry": {"coordinates":[-95.599053,42.315138],"type":"Point"}
}