{
  "type": "Feature",
  "properties": {
    "iso:country":"US",
    "sg:address":"822 Wren Ave",
    "sg:city":"Ackley",
    "sg:phone":"+1 641 847 3128",
    "sg:postcode":"50601",
    "sg:province":"IA",
    "sg:tags":[
        "farm",
        "corn",
        "soybean"
    ],
    "wof:name":"Farm",
    "wof:placetype":"venue"
},
  "geometry": {"coordinates":[-93.055915,42.65937],"type":"Point"}
}