{
  "type": "Feature",
  "properties": {
    "iso:country":"US",
    "sg:address":"305 Cedar St",
    "sg:city":"Garrison",
    "sg:classifiers":[
        {
            "category":"Retail",
            "subcategory":"Repair Shop",
            "type":"Services"
        }
    ],
    "sg:phone":"+1 319 477 3133",
    "sg:postcode":"52229",
    "sg:province":"IA",
    "sg:tags":[
        "welding"
    ],
    "wof:name":"Lint Repair & Welding",
    "wof:placetype":"venue"
},
  "geometry": {"coordinates":[-92.141114,42.141233],"type":"Point"}
}