{
  "type": "Feature",
  "properties": {
    "iso:country":"US",
    "sg:address":"5700 W Mustang Rd",
    "sg:city":"Cedar Rapids",
    "sg:classifiers":[
        {
            "category":"Shopping",
            "subcategory":"Crafts & Fabrics",
            "type":"Retail Goods"
        }
    ],
    "sg:phone":"+1 319 294 1054",
    "sg:postcode":"52411",
    "sg:province":"IA",
    "sg:tags":[
        "sewing"
    ],
    "wof:name":"Sew Whats New",
    "wof:placetype":"venue"
},
  "geometry": {"coordinates":[-91.718513,42.054381],"type":"Point"}
}