{
  "type": "Feature",
  "properties": {
    "iso:country":"US",
    "sg:address":"880 13th St",
    "sg:city":"Marion",
    "sg:classifiers":[
        {
            "category":"Health Services",
            "subcategory":"Dentist",
            "type":"Services"
        }
    ],
    "sg:phone":"+1 319 261 0716",
    "sg:postcode":"52302",
    "sg:province":"IA",
    "wof:name":"Convenient Affordable Denture Service",
    "wof:placetype":"venue"
},
  "geometry": {"coordinates":[-91.595913,42.03486],"type":"Point"}
}