{
  "type": "Feature",
  "properties": {
    "iso:country":"US",
    "sg:address":"948 7th Ave SE",
    "sg:city":"Sioux Center",
    "sg:classifiers":[
        {
            "category":"Manufacturing",
            "subcategory":"Motor Vehicles & Parts",
            "type":"Manufacturing & Wholesale Goods"
        }
    ],
    "sg:phone":"+1 712 722 1127",
    "sg:postcode":"51250",
    "sg:province":"IA",
    "sg:tags":[
        "equipment",
        "transportation",
        "mfg"
    ],
    "wof:name":"Walinga Inc",
    "wof:placetype":"venue"
},
  "geometry": {"coordinates":[-96.16602399999999,43.068231],"type":"Point"}
}