{
  "type": "Feature",
  "properties": {
    "iso:country":"US",
    "sg:address":"3116 Brockway Rd",
    "sg:city":"Waterloo",
    "sg:classifiers":[
        {
            "category":"Banks & Credit Unions",
            "subcategory":"Bank",
            "type":"Services"
        }
    ],
    "sg:phone":"+1 319 233 0273",
    "sg:postcode":"50701",
    "sg:province":"IA",
    "wof:name":"John Deere Comm Credit Union",
    "wof:placetype":"venue"
},
  "geometry": {"coordinates":[-92.35860700000001,42.467301],"type":"Point"}
}