{
  "type": "Feature",
  "properties": {
    "iso:country":"US",
    "sg:address":"240 Grand Blvd",
    "sg:city":"Waterloo",
    "sg:classifiers":[
        {
            "category":"Building & Trades",
            "subcategory":"Construction",
            "type":"Services"
        }
    ],
    "sg:phone":"+1 319 235 7212",
    "sg:postcode":"50707",
    "sg:province":"IA",
    "sg:tags":[
        "work",
        "carpentry"
    ],
    "wof:name":"Holtmeyers Remodeling & Wdwrk",
    "wof:placetype":"venue"
},
  "geometry": {"coordinates":[-92.281254,42.47352],"type":"Point"}
}