{
  "type": "Feature",
  "properties": {
    "addr:full":"3035 110th St Lenox IA 50851",
    "addr:housenumber":"3035",
    "addr:postcode":"50851",
    "addr:street":"110Th St",
    "iso:country":"US",
    "sg:address":"3035 110th St",
    "sg:city":"Lenox",
    "sg:classifiers":[
        {
            "category":"Shopping",
            "subcategory":"Gifts & Souvenirs",
            "type":"Retail Goods"
        }
    ],
    "sg:phone":"+1 641 333 2362",
    "sg:postcode":"50851",
    "sg:province":"IA",
    "sg:tags":[
        "shop"
    ],
    "wof:name":"Playne Jayne's Country Gifts",
    "wof:placetype":"venue"
},
  "geometry": {"coordinates":[-94.53992100000001,40.885165],"type":"Point"}
}