{
  "type": "Feature",
  "properties": {
    "iso:country":"US",
    "sg:address":"2043 Yankee Ave",
    "sg:city":"Durant",
    "sg:classifiers":[
        {
            "category":"Wholesale",
            "subcategory":"Farm Supplies",
            "type":"Manufacturing & Wholesale Goods"
        }
    ],
    "sg:phone":"+1 563 785 4648",
    "sg:postcode":"52747",
    "sg:province":"IA",
    "sg:tags":[
        "grain"
    ],
    "wof:name":"Harvest States Co-Op",
    "wof:placetype":"venue"
},
  "geometry": {"coordinates":[-90.91906899999999,41.649102],"type":"Point"}
}