{
  "type": "Feature",
  "properties": {
    "iso:country":"US",
    "sg:address":"48513 State Hwy 46",
    "sg:city":"Hudson",
    "sg:phone":"+1 605 984 2658",
    "sg:postcode":"57034",
    "sg:province":"IA",
    "sg:tags":[
        "farm",
        "corn",
        "soybean"
    ],
    "wof:name":"Dale Hennigs",
    "wof:placetype":"venue"
},
  "geometry": {"coordinates":[-96.507015,43.083762],"type":"Point"}
}