{
  "type": "Feature",
  "properties": {
    "addr:full":"22641 220th Ave Mt Union IA 52644",
    "addr:housenumber":"22641",
    "addr:postcode":"52644",
    "addr:street":"220Th Ave Mt",
    "iso:country":"US",
    "sg:address":"22641 220th Ave",
    "sg:city":"Mt Union",
    "sg:classifiers":[
        {
            "category":"Home & Garden",
            "subcategory":"Garden Supply",
            "type":"Retail Goods"
        }
    ],
    "sg:phone":"+1 319 865 1400",
    "sg:postcode":"52644",
    "sg:province":"IA",
    "sg:tags":[
        "fertilizer"
    ],
    "wof:name":"Golden Furrow Fertilizer",
    "wof:placetype":"venue"
},
  "geometry": {"coordinates":[-91.352552,41.015266],"type":"Point"}
}