{
  "type": "Feature",
  "properties": {
    "addr:full":"416 30th St SE Cedar Rapids IA 52403",
    "addr:housenumber":"416",
    "addr:postcode":"52403",
    "addr:street":"30Th St Se",
    "iso:country":"US",
    "sg:address":"416 30th St SE",
    "sg:city":"Cedar Rapids",
    "sg:classifiers":[
        {
            "category":"Building & Trades",
            "subcategory":"Electrical",
            "type":"Services"
        }
    ],
    "sg:phone":"+1 319 364 5400",
    "sg:postcode":"52403",
    "sg:province":"IA",
    "sg:tags":[
        "electric",
        "contractor"
    ],
    "wof:name":"Hart Electrical Svc Inc",
    "wof:placetype":"venue"
},
  "geometry": {"coordinates":[-91.62389,41.98226],"type":"Point"}
}