{
  "type": "Feature",
  "properties": {
    "iso:country":"US",
    "sg:address":"4244 Jay Ave",
    "sg:city":"Orange City",
    "sg:classifiers":[
        {
            "category":"Farming",
            "subcategory":"Dairy Farm",
            "type":"Manufacturing & Wholesale Goods"
        }
    ],
    "sg:phone":"+1 712 737 2237",
    "sg:postcode":"51041",
    "sg:province":"IA",
    "wof:name":"Hettinga Dairy",
    "wof:placetype":"venue"
},
  "geometry": {"coordinates":[-96.036894,43.034723],"type":"Point"}
}