{
  "type": "Feature",
  "properties": {
    "iso:country":"US",
    "sg:address":"400 Blairs Ferry Rd NE",
    "sg:city":"Cedar Rapids",
    "sg:classifiers":[
        {
            "category":"Banks & Credit Unions",
            "subcategory":"Bank",
            "type":"Services"
        }
    ],
    "sg:phone":"+1 319 221 1230",
    "sg:postcode":"52402",
    "sg:province":"IA",
    "sg:website":"www.bankerstrust.com",
    "wof:name":"Bankers Trust",
    "wof:placetype":"venue"
},
  "geometry": {"coordinates":[-91.636855,42.034825],"type":"Point"}
}