{
  "type": "Feature",
  "properties": {
    "iso:country":"US",
    "sg:address":"1035 3rd Ave SE",
    "sg:city":"Cedar Rapids",
    "sg:classifiers":[
        {
            "category":"Organizations",
            "subcategory":"Non-profit Organization",
            "type":"Services"
        }
    ],
    "sg:phone":"+1 319 362 3824",
    "sg:postcode":"52403",
    "sg:province":"IA",
    "sg:tags":[
        "charitable",
        "institution"
    ],
    "wof:name":"Generation Sans Frontiere",
    "wof:placetype":"venue"
},
  "geometry": {"coordinates":[-91.656318,41.982978],"type":"Point"}
}