{
  "type": "Feature",
  "properties": {
    "addr:full":"3400 Ziegler Ave Radcliffe IA 50230",
    "addr:postcode":"3400;50230",
    "addr:street":"Ziegler Ave",
    "iso:country":"US",
    "sg:address":"3400 Ziegler Ave",
    "sg:city":"Radcliffe",
    "sg:classifiers":[
        {
            "category":"Organizations",
            "subcategory":"Religious Organization",
            "type":"Services"
        }
    ],
    "sg:phone":"+1 515 899 2396",
    "sg:postcode":"50230",
    "sg:province":"IA",
    "sg:tags":[
        "church"
    ],
    "wof:name":"Salem Lutheran Church",
    "wof:placetype":"venue"
},
  "geometry": {"coordinates":[-93.48229000000001,42.296018],"type":"Point"}
}