{
  "type": "Feature",
  "properties": {
    "iso:country":"US",
    "sg:address":"1250 73rd St",
    "sg:city":"Windsor Heights",
    "sg:classifiers":[
        {
            "category":"Real Estate",
            "subcategory":"Real Estate Operator",
            "type":"Services"
        }
    ],
    "sg:phone":"+1 515 255 1716",
    "sg:postcode":"50311",
    "sg:province":"IA",
    "sg:tags":[
        "apartment"
    ],
    "wof:name":"Windsor Chateau Apartments",
    "wof:placetype":"venue"
},
  "geometry": {"coordinates":[-93.71799799999999,41.602738],"type":"Point"}
}