{
  "type": "Feature",
  "properties": {
    "iso:country":"US",
    "sg:address":"1854 Buckeye Ave",
    "sg:city":"Batavia",
    "sg:classifiers":[
        {
            "category":"Farming",
            "subcategory":"Farm",
            "type":"Manufacturing & Wholesale Goods"
        }
    ],
    "sg:phone":"+1 641 662 2936",
    "sg:postcode":"52533",
    "sg:province":"IA",
    "sg:tags":[
        "crop",
        "general"
    ],
    "wof:name":"Thomas Curray",
    "wof:placetype":"venue"
},
  "geometry": {"coordinates":[-92.14953,41.04479],"type":"Point"}
}