{
  "type": "Feature",
  "properties": {
    "iso:country":"US",
    "sg:address":"1909 390th St",
    "sg:city":"Lakota",
    "sg:classifiers":[
        {
            "category":"Building & Trades",
            "subcategory":"Construction",
            "type":"Services"
        }
    ],
    "sg:phone":"+1 515 886 2314",
    "sg:postcode":"50451",
    "sg:province":"IA",
    "sg:tags":[
        "home",
        "builder"
    ],
    "wof:name":"Janssen Construction",
    "wof:placetype":"venue"
},
  "geometry": {"coordinates":[-94.079824,43.327809],"type":"Point"}
}