{
  "type": "Feature",
  "properties": {
    "iso:country":"US",
    "sg:address":"24112 Mallard Ave",
    "sg:city":"Mason City",
    "sg:phone":"+1 641 454 2985",
    "sg:postcode":"50401",
    "sg:province":"IA",
    "sg:tags":[
        "farm",
        "corn",
        "soybean"
    ],
    "wof:name":"Jay Edgar",
    "wof:placetype":"venue"
},
  "geometry": {"coordinates":[-93.26043799999999,43.253711],"type":"Point"}
}