{
  "type": "Feature",
  "properties": {
    "iso:country":"US",
    "sg:address":"505 E Madison St",
    "sg:city":"Winterset",
    "sg:classifiers":[
        {
            "category":"Manufacturing",
            "subcategory":"Tools & Machinery",
            "type":"Manufacturing & Wholesale Goods"
        }
    ],
    "sg:phone":"+1 515 462 1773",
    "sg:postcode":"50273",
    "sg:province":"IA",
    "wof:name":"Parr Mfg",
    "wof:placetype":"venue"
},
  "geometry": {"coordinates":[-94.009592,41.347424],"type":"Point"}
}