{
  "type": "Feature",
  "properties": {
    "addr:full":"1807 17th Ave E Oskaloosa IA 52577",
    "addr:housenumber":"1807",
    "addr:postcode":"52577",
    "addr:street":"17Th Ave E Oskaloosa",
    "iso:country":"US",
    "sg:address":"1807 17th Ave E",
    "sg:city":"Oskaloosa",
    "sg:phone":"+1 641 673 3491",
    "sg:postcode":"52577",
    "sg:province":"IA",
    "sg:tags":[
        "gas"
    ],
    "wof:name":"Allied Gas & Chemical Co",
    "wof:placetype":"venue"
},
  "geometry": {"coordinates":[-92.623329,41.279569],"type":"Point"}
}