{
  "type": "Feature",
  "properties": {
    "iso:country":"US",
    "sg:address":"1287 E Maple St",
    "sg:city":"Maquoketa",
    "sg:classifiers":[
        {
            "category":"Manufacturing",
            "subcategory":"Printing",
            "type":"Manufacturing & Wholesale Goods"
        }
    ],
    "sg:phone":"+1 563 652 4971",
    "sg:postcode":"52060",
    "sg:province":"IA",
    "sg:tags":[
        "commercial"
    ],
    "sg:website":"www.maqweb.com",
    "wof:name":"Maquoketa Web Printing",
    "wof:placetype":"venue"
},
  "geometry": {"coordinates":[-90.649891,42.065401],"type":"Point"}
}