{
  "type": "Feature",
  "properties": {
    "iso:country":"US",
    "sg:address":"600 SE 18th St",
    "sg:city":"Des Moines",
    "sg:classifiers":[
        {
            "category":"Wholesale",
            "subcategory":"Construction Materials",
            "type":"Manufacturing & Wholesale Goods"
        }
    ],
    "sg:phone":"+1 515 262 8251",
    "sg:postcode":"50317",
    "sg:province":"IA",
    "sg:tags":[
        "building"
    ],
    "wof:name":"David Bear Inc",
    "wof:placetype":"venue"
},
  "geometry": {"coordinates":[-93.587153,41.582375],"type":"Point"}
}