{
  "type": "Feature",
  "properties": {
    "addr:full":"617 E 2nd St Des Moines IA 50309",
    "addr:housenumber":"617",
    "addr:postcode":"50309",
    "addr:street":"E 2Nd St",
    "iso:country":"US",
    "sg:address":"617 E 2nd St",
    "sg:city":"Des Moines",
    "sg:classifiers":[
        {
            "category":"Government",
            "subcategory":"Office",
            "type":"Public Place"
        }
    ],
    "sg:phone":"+1 515 281 9082",
    "sg:postcode":"50309",
    "sg:province":"IA",
    "sg:tags":[
        "state"
    ],
    "wof:name":"Governors Council-Dev Dsblts",
    "wof:placetype":"venue"
},
  "geometry": {"coordinates":[-93.615323,41.591425],"type":"Point"}
}