{
  "type": "Feature",
  "properties": {
    "iso:country":"US",
    "sg:address":"415 Main St",
    "sg:city":"Keokuk",
    "sg:classifiers":[
        {
            "category":"Shopping",
            "subcategory":"Used Merchandise",
            "type":"Retail Goods"
        }
    ],
    "sg:phone":"+1 319 524 4605",
    "sg:postcode":"52632",
    "sg:province":"IA",
    "sg:tags":[
        "antique"
    ],
    "wof:name":"Courtyard Books & Antiques",
    "wof:placetype":"venue"
},
  "geometry": {"coordinates":[-91.383149,40.395705],"type":"Point"}
}