{
  "type": "Feature",
  "properties": {
    "addr:full":"3906 77th St Urbandale IA 50322",
    "addr:housenumber":"3906",
    "addr:postcode":"50322",
    "addr:street":"77Th St",
    "iso:country":"US",
    "sg:address":"3906 77th St",
    "sg:city":"Urbandale",
    "sg:classifiers":[
        {
            "category":"Professional",
            "subcategory":"Management & Consulting",
            "type":"Services"
        }
    ],
    "sg:phone":"+1 515 253 9650",
    "sg:postcode":"50322",
    "sg:province":"IA",
    "wof:name":"Clegg Consultant Group",
    "wof:placetype":"venue"
},
  "geometry": {"coordinates":[-93.724885,41.631455],"type":"Point"}
}