{
  "type": "Feature",
  "properties": {
    "addr:full":"102 N Washington St Bloomfield IA 52537",
    "addr:housenumber":"102",
    "addr:postcode":"52537",
    "addr:street":"N Washington St",
    "iso:country":"US",
    "sg:address":"102 N Washington St",
    "sg:city":"Bloomfield",
    "sg:classifiers":[
        {
            "category":"Autos & Motor Vehicles",
            "subcategory":"Automobile Sales",
            "type":"Retail Goods"
        }
    ],
    "sg:phone":"+1 641 664 3164",
    "sg:postcode":"52537",
    "sg:province":"IA",
    "sg:tags":[
        "car",
        "dealer"
    ],
    "wof:name":"Jim's Auto Sales",
    "wof:placetype":"venue"
},
  "geometry": {"coordinates":[-92.413568,40.752674],"type":"Point"}
}