{
  "type": "Feature",
  "properties": {
    "iso:country":"US",
    "sg:address":"1936 Hancock Ave",
    "sg:city":"Moville",
    "sg:classifiers":[
        {
            "category":"Farming",
            "subcategory":"Livestock Farm",
            "type":"Manufacturing & Wholesale Goods"
        }
    ],
    "sg:phone":"+1 712 873 3808",
    "sg:postcode":"51039",
    "sg:province":"IA",
    "sg:tags":[
        "beef",
        "feedlot",
        "cattle"
    ],
    "wof:name":"Harry Jahn",
    "wof:placetype":"venue"
},
  "geometry": {"coordinates":[-96.03846,42.42205],"type":"Point"}
}