{
  "type": "Feature",
  "properties": {
    "iso:country":"US",
    "sg:address":"1775 300th St",
    "sg:city":"Ionia",
    "sg:phone":"+1 641 435 4878",
    "sg:postcode":"50645",
    "sg:province":"IA",
    "sg:tags":[
        "farm",
        "corn",
        "soybean"
    ],
    "wof:name":"Troy Miller",
    "wof:placetype":"venue"
},
  "geometry": {"coordinates":[-92.402337,42.921876],"type":"Point"}
}