{
  "type": "Feature",
  "properties": {
    "addr:full":"2727 Mount Pleasant St Burlington IA 52601",
    "addr:housenumber":"2727",
    "addr:postcode":"52601",
    "addr:street":"Mount Pleasant St",
    "iso:country":"US",
    "sg:address":"2727 Mount Pleasant St",
    "sg:city":"Burlington",
    "sg:classifiers":[
        {
            "category":"Organizations",
            "subcategory":"Community Association",
            "type":"Services"
        }
    ],
    "sg:phone":"+1 319 752 4781",
    "sg:postcode":"52601",
    "sg:province":"IA",
    "sg:tags":[
        "fraternal"
    ],
    "wof:name":"Fraternal Order Of Eagles",
    "wof:placetype":"venue"
},
  "geometry": {"coordinates":[-91.140304,40.825753],"type":"Point"}
}