{
  "type": "Feature",
  "properties": {
    "addr:full":"3725 Center Point Rd NE Cedar Rapids IA 52402",
    "addr:housenumber":"3725",
    "addr:postcode":"52402",
    "addr:street":"Center Point Rd Ne",
    "iso:country":"US",
    "sg:address":"3725 Center Point Rd NE",
    "sg:city":"Cedar Rapids",
    "sg:classifiers":[
        {
            "category":"Banks & Credit Unions",
            "subcategory":"Bank",
            "type":"Services"
        }
    ],
    "sg:phone":"+1 319 399 5026",
    "sg:postcode":"52402",
    "sg:province":"IA",
    "sg:tags":[
        "loan",
        "real estate"
    ],
    "wof:name":"Todd Financial Group",
    "wof:placetype":"venue"
},
  "geometry": {"coordinates":[-91.66432,42.017298],"type":"Point"}
}