{
  "type": "Feature",
  "properties": {
    "iso:country":"US",
    "sg:address":"1903 46th St",
    "sg:city":"Des Moines",
    "sg:classifiers":[
        {
            "category":"Banks & Credit Unions",
            "subcategory":"Investment Brokerage",
            "type":"Services"
        }
    ],
    "sg:phone":"+1 515 277 4778",
    "sg:postcode":"50310",
    "sg:province":"IA",
    "sg:tags":[
        "consultant",
        "planning",
        "financial"
    ],
    "wof:name":"Midwest Financial Consultants",
    "wof:placetype":"venue"
},
  "geometry": {"coordinates":[-93.680243,41.614865],"type":"Point"}
}