{
  "type": "Feature",
  "properties": {
    "iso:country":"US",
    "sg:address":"1524 76th St",
    "sg:city":"Luzerne",
    "sg:phone":"+1 319 444 2786",
    "sg:postcode":"52257",
    "sg:province":"IA",
    "sg:tags":[
        "farm",
        "corn",
        "soybean"
    ],
    "wof:name":"Three J Farms Inc",
    "wof:placetype":"venue"
},
  "geometry": {"coordinates":[-92.19616000000001,41.920645],"type":"Point"}
}