{
  "type": "Feature",
  "properties": {
    "addr:full":"222 Main St Iowa Falls IA 50126",
    "addr:housenumber":"222",
    "addr:postcode":"50126",
    "addr:street":"Main St",
    "iso:country":"US",
    "sg:address":"222 Main St",
    "sg:city":"Iowa Falls",
    "sg:classifiers":[
        {
            "category":"Professional",
            "subcategory":"Management & Consulting",
            "type":"Services"
        }
    ],
    "sg:phone":"+1 641 648 4230",
    "sg:postcode":"50126",
    "sg:province":"IA",
    "sg:tags":[
        "agricultural",
        "consultant"
    ],
    "wof:name":"Great Plains Protein",
    "wof:placetype":"venue"
},
  "geometry": {"coordinates":[-93.265345,42.519426],"type":"Point"}
}