{
  "type": "Feature",
  "properties": {
    "iso:country":"US",
    "sg:address":"550 39th St",
    "sg:city":"Des Moines",
    "sg:classifiers":[
        {
            "category":"Health Services",
            "subcategory":"Clinic",
            "type":"Services"
        }
    ],
    "sg:phone":"+1 515 226 0772",
    "sg:postcode":"50312",
    "sg:province":"IA",
    "sg:tags":[
        "holistic",
        "practitioner"
    ],
    "wof:name":"M Jane Bibber",
    "wof:placetype":"venue"
},
  "geometry": {"coordinates":[-93.669819,41.585405],"type":"Point"}
}