{
  "type": "Feature",
  "properties": {
    "iso:country":"US",
    "sg:address":"204 W Broadway Ave",
    "sg:city":"Fairfield",
    "sg:classifiers":[
        {
            "category":"Professional",
            "subcategory":"Management & Consulting",
            "type":"Services"
        }
    ],
    "sg:phone":"+1 641 472 3436",
    "sg:postcode":"52556",
    "sg:province":"IA",
    "sg:tags":[
        "consultant",
        "business"
    ],
    "wof:name":"Feda",
    "wof:placetype":"venue"
},
  "geometry": {"coordinates":[-91.965656,41.007555],"type":"Point"}
}