{
  "type": "Feature",
  "properties": {
    "iso:country":"US",
    "sg:address":"11016 Memorial Park Rd",
    "sg:city":"Burlington",
    "sg:classifiers":[
        {
            "category":"Manufacturing",
            "subcategory":"Tools & Machinery",
            "type":"Manufacturing & Wholesale Goods"
        }
    ],
    "sg:phone":"+1 319 752 8147",
    "sg:postcode":"52601",
    "sg:province":"IA",
    "sg:tags":[
        "equipment",
        "tree",
        "supply"
    ],
    "wof:name":"Boughton's Tree Svc",
    "wof:placetype":"venue"
},
  "geometry": {"coordinates":[-91.149911,40.841686],"type":"Point"}
}