{
  "type": "Feature",
  "properties": {
    "addr:full":"109 Richland St Richland IA 52585",
    "addr:housenumber":"109",
    "addr:postcode":"52585",
    "addr:street":"Richland St",
    "iso:country":"US",
    "sg:address":"109 Richland St",
    "sg:city":"Richland",
    "sg:classifiers":[
        {
            "category":"Government",
            "subcategory":"Office",
            "type":"Public Place"
        }
    ],
    "sg:phone":"+1 319 456 2511",
    "sg:postcode":"52585",
    "sg:province":"IA",
    "sg:tags":[
        "city"
    ],
    "wof:name":"Richland City Hall",
    "wof:placetype":"venue"
},
  "geometry": {"coordinates":[-91.99455399999999,41.184372],"type":"Point"}
}