{
  "type": "Feature",
  "properties": {
    "iso:country":"US",
    "sg:address":"111 2nd St SE",
    "sg:city":"Cresco",
    "sg:classifiers":[
        {
            "category":"Retail",
            "subcategory":"Car Wash",
            "type":"Services"
        }
    ],
    "sg:phone":"+1 563 547 4174",
    "sg:postcode":"52136",
    "sg:province":"IA",
    "sg:tags":[
        "polishing",
        "washing"
    ],
    "wof:name":"Cathy's Car Wash",
    "wof:placetype":"venue"
},
  "geometry": {"coordinates":[-92.114724,43.372352],"type":"Point"}
}