{
  "type": "Feature",
  "properties": {
    "addr:full":"240 Wiley Blvd SW Cedar Rapids IA 52404",
    "addr:housenumber":"240",
    "addr:postcode":"52404",
    "addr:street":"Wiley Blvd Sw",
    "iso:country":"US",
    "sg:address":"240 Wiley Blvd SW",
    "sg:city":"Cedar Rapids",
    "sg:classifiers":[
        {
            "category":"Professional",
            "subcategory":"Lawyer & Legal Services",
            "type":"Services"
        }
    ],
    "sg:phone":"+1 319 396 6577",
    "sg:postcode":"52404",
    "sg:province":"IA",
    "sg:tags":[
        "attorney"
    ],
    "wof:name":"Mollman Law Firm",
    "wof:placetype":"venue"
},
  "geometry": {"coordinates":[-91.72586800000001,41.965694],"type":"Point"}
}