{
  "type": "Feature",
  "properties": {
    "iso:country":"US",
    "sg:address":"1287 Madera St",
    "sg:city":"Dubuque",
    "sg:classifiers":[
        {
            "category":"Building & Trades",
            "subcategory":"Construction",
            "type":"Services"
        }
    ],
    "sg:phone":"+1 563 588 2608",
    "sg:postcode":"52001",
    "sg:province":"IA",
    "sg:tags":[
        "house"
    ],
    "wof:name":"Bisping Construction Company",
    "wof:placetype":"venue"
},
  "geometry": {"coordinates":[-90.698983,42.51983],"type":"Point"}
}