{
  "type": "Feature",
  "properties": {
    "iso:country":"US",
    "sg:address":"5201 NW Beaver Dr",
    "sg:city":"Johnston",
    "sg:classifiers":[
        {
            "category":"Wholesale",
            "subcategory":"Construction Materials",
            "type":"Manufacturing & Wholesale Goods"
        }
    ],
    "sg:phone":"+1 515 270 0343",
    "sg:postcode":"50131",
    "sg:province":"IA",
    "sg:tags":[
        "sand",
        "gravel"
    ],
    "wof:name":"Martin Marietta Aggregates",
    "wof:placetype":"venue"
},
  "geometry": {"coordinates":[-93.68406,41.656774],"type":"Point"}
}