{
  "type": "Feature",
  "properties": {
    "addr:full":"2060 Crossroads Blvd Waterloo IA 50702",
    "addr:housenumber":"2060",
    "addr:postcode":"50702",
    "addr:street":"Crossroads Blvd",
    "iso:country":"US",
    "sg:address":"2060 Crossroads Blvd",
    "sg:city":"Waterloo",
    "sg:classifiers":[
        {
            "category":"Food & Beverages",
            "subcategory":"Bakery",
            "type":"Retail Goods"
        }
    ],
    "sg:phone":"+1 319 291 6393",
    "sg:postcode":"50702",
    "sg:province":"IA",
    "sg:tags":[
        "cookie",
        "cracker"
    ],
    "wof:name":"Great American Cookie Co",
    "wof:placetype":"venue"
},
  "geometry": {"coordinates":[-92.319676,42.464013],"type":"Point"}
}