{
  "type": "Feature",
  "properties": {
    "iso:country":"US",
    "sg:address":"111 S 104th Ave E",
    "sg:city":"Monroe",
    "sg:classifiers":[
        {
            "category":"Farming",
            "subcategory":"Livestock Farm",
            "type":"Manufacturing & Wholesale Goods"
        }
    ],
    "sg:phone":"+1 641 793 2760",
    "sg:postcode":"50170",
    "sg:province":"IA",
    "sg:tags":[
        "beef",
        "feedlot",
        "cattle"
    ],
    "wof:name":"James Tool",
    "wof:placetype":"venue"
},
  "geometry": {"coordinates":[-93.051822,41.55173],"type":"Point"}
}