{
  "type": "Feature",
  "properties": {
    "addr:full":"2885 Oak Ave Garner IA 50438",
    "addr:housenumber":"2885",
    "addr:postcode":"50438",
    "addr:street":"Oak Ave",
    "iso:country":"US",
    "sg:address":"2885 Oak Ave",
    "sg:city":"Garner",
    "sg:classifiers":[
        {
            "category":"Insurance",
            "subcategory":"Insurance Agent",
            "type":"Services"
        }
    ],
    "sg:phone":"+1 641 923 3184",
    "sg:postcode":"50438",
    "sg:province":"IA",
    "wof:name":"Aflac Insurance",
    "wof:placetype":"venue"
},
  "geometry": {"coordinates":[-93.695283,43.180955],"type":"Point"}
}