{
  "type": "Feature",
  "properties": {
    "iso:country":"US",
    "sg:address":"316 E 6th St",
    "sg:city":"Storm Lake",
    "sg:classifiers":[
        {
            "category":"Professional",
            "subcategory":"Lawyer & Legal Services",
            "type":"Services"
        }
    ],
    "sg:phone":"+1 712 732 3538",
    "sg:postcode":"50588",
    "sg:province":"IA",
    "sg:tags":[
        "attorney"
    ],
    "wof:name":"Mack Hansen Gadd Armstrong",
    "wof:placetype":"venue"
},
  "geometry": {"coordinates":[-95.198177,42.645384],"type":"Point"}
}