{
  "type": "Feature",
  "properties": {
    "iso:country":"US",
    "sg:address":"2222 Philadelphia St",
    "sg:city":"Ames",
    "sg:classifiers":[
        {
            "category":"Health Services",
            "subcategory":"Podiatrist",
            "type":"Services"
        }
    ],
    "sg:phone":"+1 515 663 0900",
    "sg:postcode":"50010",
    "sg:province":"IA",
    "wof:name":"Ames Foot Clinic",
    "wof:placetype":"venue"
},
  "geometry": {"coordinates":[-93.58384599999999,42.035409],"type":"Point"}
}