{
  "type": "Feature",
  "properties": {
    "addr:full":"2200 W Kimberly Rd Davenport IA 52806",
    "addr:housenumber":"2200",
    "addr:postcode":"52806",
    "addr:street":"W Kimberly Rd",
    "iso:country":"US",
    "sg:address":"2200 W Kimberly Rd",
    "sg:city":"Davenport",
    "sg:classifiers":[
        {
            "category":"Banks & Credit Unions",
            "subcategory":"Bank",
            "type":"Services"
        }
    ],
    "sg:phone":"+1 563 388 6165",
    "sg:postcode":"52806",
    "sg:province":"IA",
    "wof:name":"Commercial Federal Bank",
    "wof:placetype":"venue"
},
  "geometry": {"coordinates":[-90.61021599999999,41.560238],"type":"Point"}
}