{
  "type": "Feature",
  "properties": {
    "addr:full":"2437 370th St Osage IA 50461",
    "addr:housenumber":"2437",
    "addr:postcode":"50461",
    "addr:street":"370Th St",
    "iso:country":"US",
    "sg:address":"2437 370th St",
    "sg:city":"Osage",
    "sg:phone":"+1 641 732 5768",
    "sg:postcode":"50461",
    "sg:province":"IA",
    "sg:tags":[
        "farm",
        "corn",
        "soybean"
    ],
    "wof:name":"Gary Kuper",
    "wof:placetype":"venue"
},
  "geometry": {"coordinates":[-92.744946,43.298885],"type":"Point"}
}