{
  "type": "Feature",
  "properties": {
    "addr:full":"3902 Ingersoll Ave Des Moines IA 50312",
    "addr:housenumber":"3902",
    "addr:postcode":"50312",
    "addr:street":"Ingersoll Ave",
    "iso:country":"US",
    "sg:address":"3902 Ingersoll Ave",
    "sg:city":"Des Moines",
    "sg:classifiers":[
        {
            "category":"Real Estate",
            "subcategory":"Real Estate Agent",
            "type":"Services"
        }
    ],
    "sg:phone":"+1 515 266 5352",
    "sg:postcode":"50312",
    "sg:province":"IA",
    "sg:website":"www.simplicityrealty.com",
    "wof:name":"SIMPLICITYREALTY.COM",
    "wof:placetype":"venue"
},
  "geometry": {"coordinates":[-93.671212,41.586282],"type":"Point"}
}