{
  "type": "Feature",
  "properties": {
    "iso:country":"US",
    "sg:address":"1436 175th Ave",
    "sg:city":"Donnellson",
    "sg:classifiers":[
        {
            "category":"Farming",
            "subcategory":"Farm",
            "type":"Manufacturing & Wholesale Goods"
        }
    ],
    "sg:phone":"+1 319 469 6091",
    "sg:postcode":"52631",
    "sg:province":"IA",
    "sg:tags":[
        "crop",
        "general"
    ],
    "wof:name":"Marvin Overton",
    "wof:placetype":"venue"
},
  "geometry": {"coordinates":[-91.577921,40.750036],"type":"Point"}
}