{
  "type": "Feature",
  "properties": {
    "iso:country":"US",
    "sg:address":"1921 Shoshoni Dr",
    "sg:city":"Council Bluffs",
    "sg:classifiers":[
        {
            "category":"Shopping",
            "subcategory":"Computers & Home Electronics",
            "type":"Retail Goods"
        }
    ],
    "sg:phone":"+1 712 366 0604",
    "sg:postcode":"51501",
    "sg:province":"IA",
    "sg:tags":[
        "equipment",
        "dealer"
    ],
    "wof:name":"Franks Computer",
    "wof:placetype":"venue"
},
  "geometry": {"coordinates":[-95.87209,41.22645],"type":"Point"}
}