{
  "type": "Feature",
  "properties": {
    "addr:full":"2134 US Hwy 6 Marengo IA 52301",
    "addr:housenumber":"2134",
    "addr:postcode":"52301",
    "addr:street":"Us Hwy 6",
    "iso:country":"US",
    "sg:address":"2134 US Hwy 6",
    "sg:city":"Marengo",
    "sg:classifiers":[
        {
            "category":"Farming",
            "subcategory":"Farm",
            "type":"Manufacturing & Wholesale Goods"
        }
    ],
    "sg:phone":"+1 319 642 7288",
    "sg:postcode":"52301",
    "sg:province":"IA",
    "sg:tags":[
        "crop",
        "general"
    ],
    "wof:name":"Brad Glandorf Farm",
    "wof:placetype":"venue"
},
  "geometry": {"coordinates":[-92.07562,41.789485],"type":"Point"}
}