{
  "type": "Feature",
  "properties": {
    "addr:full":"204 S Military St Martelle IA 52305",
    "addr:housenumber":"204",
    "addr:postcode":"52305",
    "addr:street":"S Military St",
    "iso:country":"US",
    "sg:address":"204 S Military St",
    "sg:city":"Martelle",
    "sg:classifiers":[
        {
            "category":"Government",
            "subcategory":"Post Office",
            "type":"Public Place"
        }
    ],
    "sg:phone":"+1 319 482 3181",
    "sg:postcode":"52305",
    "sg:province":"IA",
    "wof:name":"US Post Office",
    "wof:placetype":"venue"
},
  "geometry": {"coordinates":[-91.360563,42.020741],"type":"Point"}
}