{
  "type": "Feature",
  "properties": {
    "addr:full":"2905 D Ave NE Cedar Rapids IA 52402",
    "addr:housenumber":"2905",
    "addr:postcode":"52402",
    "addr:street":"D Ave Ne",
    "iso:country":"US",
    "sg:address":"2905 D Ave NE",
    "sg:city":"Cedar Rapids",
    "sg:classifiers":[
        {
            "category":"Organizations",
            "subcategory":"Religious Organization",
            "type":"Services"
        }
    ],
    "sg:phone":"+1 319 363 4983",
    "sg:postcode":"52402",
    "sg:province":"IA",
    "sg:tags":[
        "church"
    ],
    "wof:name":"Grace Brethren Church",
    "wof:placetype":"venue"
},
  "geometry": {"coordinates":[-91.64003099999999,42.007394],"type":"Point"}
}