{
  "type": "Feature",
  "properties": {
    "iso:country":"US",
    "sg:address":"3515 Spring St",
    "sg:city":"Davenport",
    "sg:classifiers":[
        {
            "category":"Health Services",
            "subcategory":"Chiropractor",
            "type":"Services"
        }
    ],
    "sg:phone":"+1 563 359 3543",
    "sg:postcode":"52807",
    "sg:province":"IA",
    "wof:name":"Don L Specht DC",
    "wof:placetype":"venue"
},
  "geometry": {"coordinates":[-90.54773299999999,41.555496],"type":"Point"}
}