{
  "type": "Feature",
  "properties": {
    "addr:full":"907 Hazel St Pella IA 50219",
    "addr:housenumber":"907",
    "addr:postcode":"50219",
    "addr:street":"Hazel St",
    "iso:country":"US",
    "sg:address":"907 Hazel St",
    "sg:city":"Pella",
    "sg:classifiers":[
        {
            "category":"Autos & Motor Vehicles",
            "subcategory":"Auto Supplies",
            "type":"Retail Goods"
        }
    ],
    "sg:phone":"+1 641 628 3706",
    "sg:postcode":"50219",
    "sg:province":"IA",
    "wof:name":"Vander Beek Running Board Sls",
    "wof:placetype":"venue"
},
  "geometry": {"coordinates":[-92.90968100000001,41.409301],"type":"Point"}
}