{
  "type": "Feature",
  "properties": {
    "addr:full":"7558 15th St Eldon IA 52554",
    "addr:housenumber":"7558",
    "addr:postcode":"52554",
    "addr:street":"15Th St",
    "iso:country":"US",
    "sg:address":"7558 15th St",
    "sg:city":"Eldon",
    "sg:phone":"+1 641 652 7887",
    "sg:postcode":"52554",
    "sg:province":"IA",
    "sg:tags":[
        "beef",
        "farm",
        "corn",
        "soybean",
        "cattle",
        "feedlot"
    ],
    "wof:name":"William Albert",
    "wof:placetype":"venue"
},
  "geometry": {"coordinates":[-92.29890399999999,40.899548],"type":"Point"}
}