{
  "type": "Feature",
  "properties": {
    "iso:country":"US",
    "sg:address":"354 Country Club Ct",
    "sg:city":"Eldridge",
    "sg:classifiers":[
        {
            "category":"Real Estate",
            "subcategory":"Real Estate Operator",
            "type":"Services"
        }
    ],
    "sg:phone":"+1 563 285 4787",
    "sg:postcode":"52748",
    "sg:province":"IA",
    "sg:tags":[
        "property",
        "lessor"
    ],
    "wof:name":"Claeys Farms",
    "wof:placetype":"venue"
},
  "geometry": {"coordinates":[-90.570268,41.652306],"type":"Point"}
}