{
  "type": "Feature",
  "properties": {
    "iso:country":"US",
    "sg:address":"1801 S Main St",
    "sg:city":"Burlington",
    "sg:classifiers":[
        {
            "category":"Building & Trades",
            "subcategory":"Construction",
            "type":"Services"
        }
    ],
    "sg:phone":"+1 319 752 4216",
    "sg:postcode":"52601",
    "sg:province":"IA",
    "sg:tags":[
        "general",
        "contractor"
    ],
    "wof:name":"A J Construction",
    "wof:placetype":"venue"
},
  "geometry": {"coordinates":[-91.098619,40.791798],"type":"Point"}
}