{
  "type": "Feature",
  "properties": {
    "addr:full":"1810 6th Ave Grinnell IA 50112",
    "addr:housenumber":"1810",
    "addr:postcode":"50112",
    "addr:street":"6Th Ave",
    "iso:country":"US",
    "sg:address":"1810 6th Ave",
    "sg:city":"Grinnell",
    "sg:classifiers":[
        {
            "category":"Restaurant",
            "type":"Food & Drink"
        }
    ],
    "sg:phone":"+1 641 236 7828",
    "sg:postcode":"50112",
    "sg:province":"IA",
    "sg:tags":[
        "parlor",
        "ice",
        "cream"
    ],
    "wof:name":"Dairy Barn",
    "wof:placetype":"venue"
},
  "geometry": {"coordinates":[-92.710414,41.746063],"type":"Point"}
}