{
  "type": "Feature",
  "properties": {
    "addr:full":"519 S 1st St Guttenberg IA 52052",
    "addr:housenumber":"519",
    "addr:postcode":"52052",
    "addr:street":"S 1St St",
    "iso:country":"US",
    "sg:address":"519 S 1st St",
    "sg:city":"Guttenberg",
    "sg:classifiers":[
        {
            "category":"Government",
            "subcategory":"Post Office",
            "type":"Public Place"
        }
    ],
    "sg:phone":"+1 563 252 1517",
    "sg:postcode":"52052",
    "sg:province":"IA",
    "wof:name":"US Post Office",
    "wof:placetype":"venue"
},
  "geometry": {"coordinates":[-91.096172,42.781429],"type":"Point"}
}