{
  "type": "Feature",
  "properties": {
    "addr:full":"1713 1800th St Irwin IA 51446",
    "addr:housenumber":"1713",
    "addr:postcode":"1800th;51446",
    "addr:street":"St",
    "iso:country":"US",
    "sg:address":"1713 1800th St",
    "sg:city":"Irwin",
    "sg:classifiers":[
        {
            "category":"Farming",
            "subcategory":"Farm",
            "type":"Manufacturing & Wholesale Goods"
        }
    ],
    "sg:phone":"+1 712 782 3236",
    "sg:postcode":"51446",
    "sg:province":"IA",
    "wof:name":"Young Brothers",
    "wof:placetype":"venue"
},
  "geometry": {"coordinates":[-95.24813399999999,41.760856],"type":"Point"}
}