{
  "type": "Feature",
  "properties": {
    "iso:country":"US",
    "sg:address":"506 E 18th St",
    "sg:city":"Carroll",
    "sg:classifiers":[
        {
            "category":"Real Estate",
            "subcategory":"Real Estate Operator",
            "type":"Services"
        }
    ],
    "sg:phone":"+1 712 792 5047",
    "sg:postcode":"51401",
    "sg:province":"IA",
    "sg:tags":[
        "apartment"
    ],
    "wof:name":"Fairview Village Apartments",
    "wof:placetype":"venue"
},
  "geometry": {"coordinates":[-94.85728400000001,42.078408],"type":"Point"}
}