{
  "type": "Feature",
  "properties": {
    "addr:full":"110 E Main St Lamoni IA 50140",
    "addr:housenumber":"110",
    "addr:postcode":"50140",
    "addr:street":"E Main St",
    "iso:country":"US",
    "sg:address":"110 E Main St",
    "sg:city":"Lamoni",
    "sg:classifiers":[
        {
            "category":"Shopping",
            "type":"Retail Goods"
        }
    ],
    "sg:phone":"+1 641 784 4033",
    "sg:postcode":"50140",
    "sg:province":"IA",
    "sg:tags":[
        "picture",
        "frame"
    ],
    "wof:name":"Gallery",
    "wof:placetype":"venue"
},
  "geometry": {"coordinates":[-93.93321299999999,40.623766],"type":"Point"}
}