{
  "type": "Feature",
  "properties": {
    "iso:country":"US",
    "sg:address":"2929 N 9th St",
    "sg:city":"Carter Lake",
    "sg:classifiers":[
        {
            "category":"Government",
            "subcategory":"Fire Station",
            "type":"Public Place"
        }
    ],
    "sg:phone":"+1 712 347 5900",
    "sg:postcode":"51510",
    "sg:province":"IA",
    "sg:tags":[
        "department"
    ],
    "wof:name":"Carter Lake Fire Adm",
    "wof:placetype":"venue"
},
  "geometry": {"coordinates":[-95.917946,41.285589],"type":"Point"}
}