{
  "type": "Feature",
  "properties": {
    "iso:country":"US",
    "sg:address":"26789 20th Ave",
    "sg:city":"Stockton",
    "sg:classifiers":[
        {
            "category":"Freight",
            "type":"Transportation"
        }
    ],
    "sg:phone":"+1 563 843 3108",
    "sg:postcode":"52769",
    "sg:province":"IA",
    "sg:tags":[
        "trucking"
    ],
    "wof:name":"Van Den Berghe Trucking",
    "wof:placetype":"venue"
},
  "geometry": {"coordinates":[-90.85994700000001,41.693062],"type":"Point"}
}