{
  "type": "Feature",
  "properties": {
    "addr:full":"100 North St Lincoln IA 50652",
    "addr:housenumber":"100",
    "addr:postcode":"50652",
    "addr:street":"North St",
    "iso:country":"US",
    "sg:address":"100 North St",
    "sg:city":"Lincoln",
    "sg:classifiers":[
        {
            "category":"Personal",
            "subcategory":"Beauty Salon",
            "type":"Services"
        }
    ],
    "sg:phone":"+1 641 473 3442",
    "sg:postcode":"50652",
    "sg:province":"IA",
    "wof:name":"Shelby's",
    "wof:placetype":"venue"
},
  "geometry": {"coordinates":[-92.6921,42.263922],"type":"Point"}
}