{
  "type": "Feature",
  "properties": {
    "addr:full":"119 4th Ave Coon Rapids IA 50058",
    "addr:housenumber":"119",
    "addr:postcode":"50058",
    "addr:street":"4Th Ave",
    "iso:country":"US",
    "sg:address":"119 4th Ave",
    "sg:city":"Coon Rapids",
    "sg:classifiers":[
        {
            "category":"Organizations",
            "subcategory":"Religious Organization",
            "type":"Services"
        }
    ],
    "sg:phone":"+1 712 999 5262",
    "sg:postcode":"50058",
    "sg:province":"IA",
    "sg:tags":[
        "church"
    ],
    "wof:name":"United Methodist Church",
    "wof:placetype":"venue"
},
  "geometry": {"coordinates":[-94.676064,41.871684],"type":"Point"}
}