{
  "type": "Feature",
  "properties": {
    "iso:country":"US",
    "sg:address":"415 E Bremer Ave",
    "sg:city":"Waverly",
    "sg:classifiers":[
        {
            "category":"Government",
            "subcategory":"Office",
            "type":"Public Place"
        }
    ],
    "sg:phone":"+1 319 352 5043",
    "sg:postcode":"50677",
    "sg:province":"IA",
    "wof:name":"Bremer County MIS Dept",
    "wof:placetype":"venue"
},
  "geometry": {"coordinates":[-92.465474,42.72589],"type":"Point"}
}