{
  "type": "Feature",
  "properties": {
    "iso:country":"US",
    "sg:address":"980 W Penn St",
    "sg:city":"North Liberty",
    "sg:classifiers":[
        {
            "category":"Freight",
            "type":"Transportation"
        }
    ],
    "sg:phone":"+1 319 626 7686",
    "sg:postcode":"52317",
    "sg:province":"IA",
    "sg:tags":[
        "commercial",
        "storage"
    ],
    "wof:name":"A L Storage",
    "wof:placetype":"venue"
},
  "geometry": {"coordinates":[-91.617262,41.75241],"type":"Point"}
}