{
  "type": "Feature",
  "properties": {
    "addr:full":"1860 State Hwy 92 West Chester IA 52359",
    "addr:housenumber":"1860",
    "addr:postcode":"52359",
    "addr:street":"State Hwy 92",
    "iso:country":"US",
    "sg:address":"1860 State Hwy 92",
    "sg:city":"West Chester",
    "sg:classifiers":[
        {
            "category":"Farming",
            "subcategory":"Farm",
            "type":"Manufacturing & Wholesale Goods"
        }
    ],
    "sg:phone":"+1 319 698 7177",
    "sg:postcode":"52359",
    "sg:province":"IA",
    "sg:tags":[
        "crop",
        "general"
    ],
    "wof:name":"Randy Bush",
    "wof:placetype":"venue"
},
  "geometry": {"coordinates":[-91.787386,41.33664],"type":"Point"}
}