{
  "type": "Feature",
  "properties": {
    "iso:country":"US",
    "sg:address":"2535 Viking Ave",
    "sg:city":"Fairbank",
    "sg:classifiers":[
        {
            "category":"Education",
            "subcategory":"School",
            "type":"Public Place"
        }
    ],
    "sg:phone":"+1 319 638 6711",
    "sg:postcode":"50629",
    "sg:province":"IA",
    "wof:name":"Wapsie Valley Comm Sch Dist",
    "wof:placetype":"venue"
},
  "geometry": {"coordinates":[-92.140618,42.67699],"type":"Point"}
}