{
  "type": "Feature",
  "properties": {
    "iso:country":"US",
    "sg:address":"610 3rd St SW",
    "sg:city":"State Center",
    "sg:classifiers":[
        {
            "category":"Organizations",
            "subcategory":"Religious Organization",
            "type":"Services"
        }
    ],
    "sg:phone":"+1 641 483 2460",
    "sg:postcode":"50247",
    "sg:province":"IA",
    "sg:tags":[
        "church"
    ],
    "wof:name":"Saint Joseph Catholic Church",
    "wof:placetype":"venue"
},
  "geometry": {"coordinates":[-93.17073000000001,42.013772],"type":"Point"}
}