{
  "type": "Feature",
  "properties": {
    "addr:full":"2929 Scott Blvd Winthrop IA 52326",
    "addr:housenumber":"2929",
    "addr:postcode":"52326",
    "addr:street":"Scott Blvd",
    "iso:country":"US",
    "sg:address":"2929 Scott Blvd",
    "sg:city":"Winthrop",
    "sg:classifiers":[
        {
            "category":"Shopping",
            "subcategory":"Used Merchandise",
            "type":"Retail Goods"
        }
    ],
    "sg:phone":"+1 319 934 3870",
    "sg:postcode":"52326",
    "sg:province":"IA",
    "wof:name":"Talking Guns Civil War Antique",
    "wof:placetype":"venue"
},
  "geometry": {"coordinates":[-91.72868200000001,42.36512],"type":"Point"}
}