{
  "type": "Feature",
  "properties": {
    "iso:country":"US",
    "sg:address":"1020 S Clinton St",
    "sg:city":"Albia",
    "sg:classifiers":[
        {
            "category":"Freight",
            "type":"Transportation"
        }
    ],
    "sg:phone":"+1 641 932 2580",
    "sg:postcode":"52531",
    "sg:province":"IA",
    "sg:tags":[
        "trucking"
    ],
    "wof:name":"WKM Trucking",
    "wof:placetype":"venue"
},
  "geometry": {"coordinates":[-92.80909200000001,41.017672],"type":"Point"}
}