{
  "type": "Feature",
  "properties": {
    "addr:full":"117 Iowa Ave Dunlap IA 51529",
    "addr:housenumber":"117",
    "addr:postcode":"51529",
    "addr:street":"Iowa Ave",
    "iso:country":"US",
    "sg:address":"117 Iowa Ave",
    "sg:city":"Dunlap",
    "sg:classifiers":[
        {
            "category":"Personal",
            "subcategory":"Beauty Salon",
            "type":"Services"
        }
    ],
    "sg:phone":"+1 712 643 5444",
    "sg:postcode":"51529",
    "sg:province":"IA",
    "sg:tags":[
        "shop"
    ],
    "wof:name":"Vickie's Headquarters",
    "wof:placetype":"venue"
},
  "geometry": {"coordinates":[-95.602068,41.854414],"type":"Point"}
}