{
  "type": "Feature",
  "properties": {
    "addr:full":"7810 SW 10th Pl Des Moines IA 50315",
    "addr:housenumber":"7810",
    "addr:postcode":"50315",
    "addr:street":"Sw 10Th Pl",
    "iso:country":"US",
    "sg:address":"7810 SW 10th Pl",
    "sg:city":"Des Moines",
    "sg:classifiers":[
        {
            "category":"Arts & Performance",
            "subcategory":"Theater",
            "type":"Entertainment"
        }
    ],
    "sg:phone":"+1 515 287 2303",
    "sg:postcode":"50315",
    "sg:province":"IA",
    "sg:tags":[
        "group"
    ],
    "wof:name":"Harmony Entertainment Inc",
    "wof:placetype":"venue"
},
  "geometry": {"coordinates":[-93.628896,41.512142],"type":"Point"}
}