{
  "type": "Feature",
  "properties": {
    "iso:country":"US",
    "sg:address":"3765 Hubbell Ave",
    "sg:city":"Des Moines",
    "sg:classifiers":[
        {
            "category":"Restaurant",
            "type":"Food & Drink"
        }
    ],
    "sg:phone":"+1 515 263 1555",
    "sg:postcode":"50317",
    "sg:province":"IA",
    "sg:tags":[
        "eating"
    ],
    "wof:name":"Enjoy Your Lunch",
    "wof:placetype":"venue"
},
  "geometry": {"coordinates":[-93.542519,41.630005],"type":"Point"}
}