{
  "type": "Feature",
  "properties": {
    "iso:country":"US",
    "sg:address":"6012 Gregory Ln",
    "sg:city":"Des Moines",
    "sg:classifiers":[
        {
            "category":"Wholesale",
            "subcategory":"Machinery & Supplies",
            "type":"Manufacturing & Wholesale Goods"
        }
    ],
    "sg:phone":"+1 515 202 6624",
    "sg:postcode":"50312",
    "sg:province":"IA",
    "sg:tags":[
        "contractor"
    ],
    "wof:name":"Ted's Mobile Repair",
    "wof:placetype":"venue"
},
  "geometry": {"coordinates":[-93.700827,41.575853],"type":"Point"}
}