{
  "type": "Feature",
  "properties": {
    "iso:country":"US",
    "sg:address":"123 S 4th St",
    "sg:city":"Council Bluffs",
    "sg:classifiers":[
        {
            "category":"Real Estate",
            "subcategory":"Real Estate Agent",
            "type":"Services"
        }
    ],
    "sg:phone":"+1 712 322 2504",
    "sg:postcode":"51503",
    "sg:province":"IA",
    "wof:name":"Harry C Crowl Co",
    "wof:placetype":"venue"
},
  "geometry": {"coordinates":[-95.84930199999999,41.258413],"type":"Point"}
}