{
  "type": "Feature",
  "properties": {
    "addr:full":"124 Main St Cedar Falls IA 50613",
    "addr:housenumber":"124",
    "addr:postcode":"50613",
    "addr:street":"Main St",
    "iso:country":"US",
    "sg:address":"124 Main St",
    "sg:city":"Cedar Falls",
    "sg:classifiers":[
        {
            "category":"Banks & Credit Unions",
            "subcategory":"Investment Brokerage",
            "type":"Services"
        }
    ],
    "sg:phone":"+1 319 277 6583",
    "sg:postcode":"50613",
    "sg:province":"IA",
    "sg:tags":[
        "security"
    ],
    "wof:name":"Edward Jones Co",
    "wof:placetype":"venue"
},
  "geometry": {"coordinates":[-92.44539399999999,42.537117],"type":"Point"}
}