{
  "type": "Feature",
  "properties": {
    "iso:country":"US",
    "sg:address":"1185 Maben Ave",
    "sg:city":"Garner",
    "sg:classifiers":[
        {
            "category":"Building & Trades",
            "subcategory":"Construction",
            "type":"Services"
        }
    ],
    "sg:phone":"+1 641 923 3363",
    "sg:postcode":"50438",
    "sg:province":"IA",
    "sg:tags":[
        "residential"
    ],
    "wof:name":"Reichardt Construction",
    "wof:placetype":"venue"
},
  "geometry": {"coordinates":[-93.600686,43.093986],"type":"Point"}
}