{
  "type": "Feature",
  "properties": {
    "addr:full":"531 Driftwood St Correctionville IA 51016",
    "addr:housenumber":"531",
    "addr:postcode":"51016",
    "addr:street":"Driftwood St",
    "iso:country":"US",
    "sg:address":"531 Driftwood St",
    "sg:city":"Correctionville",
    "sg:classifiers":[
        {
            "category":"Freight",
            "type":"Transportation"
        }
    ],
    "sg:phone":"+1 712 372 4433",
    "sg:postcode":"51016",
    "sg:province":"IA",
    "sg:tags":[
        "grain",
        "elevator"
    ],
    "wof:name":"Western Iowa Co-Op",
    "wof:placetype":"venue"
},
  "geometry": {"coordinates":[-95.785887,42.475917],"type":"Point"}
}