{
  "type": "Feature",
  "properties": {
    "iso:country":"US",
    "sg:address":"13225 Circle Dr",
    "sg:city":"Anamosa",
    "sg:classifiers":[
        {
            "category":"Professional",
            "subcategory":"Business Services",
            "type":"Services"
        }
    ],
    "sg:phone":"+1 319 462 6011",
    "sg:postcode":"52205",
    "sg:province":"IA",
    "sg:tags":[
        "fund",
        "promotion",
        "raising"
    ],
    "wof:name":"J & P Promotions",
    "wof:placetype":"venue"
},
  "geometry": {"coordinates":[-91.26219500000001,42.126988],"type":"Point"}
}