{
  "type": "Feature",
  "properties": {
    "addr:full":"122 E Robinson St Knoxville IA 50138",
    "addr:housenumber":"122",
    "addr:postcode":"50138",
    "addr:street":"E Robinson St",
    "iso:country":"US",
    "sg:address":"122 E Robinson St",
    "sg:city":"Knoxville",
    "sg:classifiers":[
        {
            "category":"Manufacturing",
            "subcategory":"Printing",
            "type":"Manufacturing & Wholesale Goods"
        }
    ],
    "sg:phone":"+1 641 842 2155",
    "sg:postcode":"50138",
    "sg:province":"IA",
    "sg:tags":[
        "newspaper"
    ],
    "sg:website":"www.journalexpress.net",
    "wof:name":"Knoxville Journal-Express Inc",
    "wof:placetype":"venue"
},
  "geometry": {"coordinates":[-93.09787799999999,41.317952],"type":"Point"}
}