{
  "type": "Feature",
  "properties": {
    "iso:country":"US",
    "sg:address":"1205 S 20th Ave W",
    "sg:city":"Newton",
    "sg:classifiers":[
        {
            "category":"Manufacturing",
            "subcategory":"Printing",
            "type":"Manufacturing & Wholesale Goods"
        }
    ],
    "sg:phone":"+1 641 792 6085",
    "sg:postcode":"50208",
    "sg:province":"IA",
    "sg:tags":[
        "screen"
    ],
    "wof:name":"D C Sports",
    "wof:placetype":"venue"
},
  "geometry": {"coordinates":[-93.067307,41.681263],"type":"Point"}
}