{
  "type": "Feature",
  "properties": {
    "iso:country":"US",
    "sg:address":"3800 Merle Hay Rd",
    "sg:city":"Des Moines",
    "sg:classifiers":[
        {
            "category":"Shopping",
            "subcategory":"Clothing, Apparel, & Fashions",
            "type":"Retail Goods"
        }
    ],
    "sg:phone":"+1 515 276 4613",
    "sg:postcode":"50310",
    "sg:province":"IA",
    "sg:tags":[
        "infant",
        "wear"
    ],
    "sg:website":"www.childrensplace.com",
    "wof:name":"Children's Place",
    "wof:placetype":"venue"
},
  "geometry": {"coordinates":[-93.697867,41.629403],"type":"Point"}
}