{
  "type": "Feature",
  "properties": {
    "iso:country":"US",
    "sg:address":"128 3rd St NW",
    "sg:city":"Sioux Center",
    "sg:classifiers":[
        {
            "category":"Banks & Credit Unions",
            "subcategory":"Bank",
            "type":"Services"
        }
    ],
    "sg:phone":"+1 712 722 1717",
    "sg:postcode":"51250",
    "sg:province":"IA",
    "wof:name":"Cooperative Credit Co",
    "wof:placetype":"venue"
},
  "geometry": {"coordinates":[-96.17730899999999,43.079804],"type":"Point"}
}