{
  "type": "Feature",
  "properties": {
    "iso:country":"US",
    "sg:address":"603 2nd St",
    "sg:city":"Victor",
    "sg:classifiers":[
        {
            "category":"Wholesale",
            "subcategory":"Farm Supplies",
            "type":"Manufacturing & Wholesale Goods"
        }
    ],
    "sg:phone":"+1 319 647 3774",
    "sg:postcode":"52347",
    "sg:province":"IA",
    "sg:tags":[
        "feed"
    ],
    "wof:name":"D & R Feed Inc",
    "wof:placetype":"venue"
},
  "geometry": {"coordinates":[-92.29687,41.731805],"type":"Point"}
}